Workbook

Sheet 00_Cover
A1: Apple Inc. (AAPL) — 9/10 Re-gated Institutional Model
A2: Owner-prepared submission; independent reviewer reproduction is required before certification
A4: Model snapshot
A5: Legal entity | B5: Apple Inc.
A6: Ticker | B6: AAPL
A7: Latest filing | B7: 2025-09-27 10-K filed 2025-10-31
A8: SEC accession | B8: 0000320193-25-000079
A9: Market price | B9: 327.5
A10: Market as-of | B10: 2026-07-15
A11: Active scenario | B11: =Assumptions!B4 -> Base
A12: DCF value / share | B12: =Valuation!G18 -> 136.40517
A13: Upside / (downside) | B13: =Valuation!G20 -> -0.58349567
A14: Gate decision | B14: =Gate_9of10!B17 -> OWNER READY — INDEPENDENT REVIEW REQUIRED
A16: What changed in the 9/10 re-gate
A17: 1 | B17: Replaced generic Sources sheet with target-cell provenance ledger
A18: 2 | B18: Replaced generic assumptions with company-specific operating drivers
A19: 3 | B19: Scenario selector now changes multiple operating outputs and the DCF
A20: 4 | B20: Debt, liquid assets and share-count valuation bridges are explicit
A21: 5 | B21: Checks are formula-driven; Gate_9of10 states owner evidence and review status
A22: 6 | B22: All original workbook files remain preserved; this is a new derivative output

Sheet Sources
A1: Apple Inc. — Source Provenance Ledger
A2: Every populated hardcoded historical or driver input is mapped to a target cell with period, value, unit, taxonomy/locator, accession and exact URL.
A4: Source ID | B4: Legal Entity | C4: Target Cell | D4: Metric | E4: Period / As-of | F4: Reported Value | G4: Units | H4: Currency | I4: Taxonomy / Locator | J4: Start | K4: End | L4: FY / FP | M4: Form | N4: Filed | O4: Accession | P4: Exact URL | Q4: Retrieved | R4: Source Class | S4: Transform / Mapping | T4: Verification | U4: Limitation / Disposition | V4: Complete?
A5: 1 | B5: Apple Inc. | C5: Historical!B5 | D5: Revenue | E5: 2021A | F5: 365817 | G5: USD millions | H5: USD | I5: us-gaap:RevenueFromContractWithCustomerExcludingAssessedTax | J5: 2020-09-27 | K5: 2021-09-25 | L5: 2023/FY | M5: 10-K | N5: 2023-11-03 | O5: 0000320193-23-000106 | P5: https://www.sec.gov/Archives/edgar/data/320193/000032019323000106/0000320193-23-000106-index.htm | Q5: 2026-07-16 | R5: Primary - SEC filing / Company Facts | S5: USD divided by 1,000,000; sign as presented | T5: Matched legal entity, period, form, filed date, accession and target | U5: None identified | V5: =IF(COUNTA(A5:U5)=21,"OK","MISSING") -> OK
A6: 2 | B6: Apple Inc. | C6: Historical!C5 | D6: Revenue | E6: 2022A | F6: 394328 | G6: USD millions | H6: USD | I6: us-gaap:RevenueFromContractWithCustomerExcludingAssessedTax | J6: 2021-09-26 | K6: 2022-09-24 | L6: 2024/FY | M6: 10-K | N6: 2024-11-01 | O6: 0000320193-24-000123 | P6: https://www.sec.gov/Archives/edgar/data/320193/000032019324000123/0000320193-24-000123-index.htm | Q6: 2026-07-16 | R6: Primary - SEC filing / Company Facts | S6: USD divided by 1,000,000; sign as presented | T6: Matched legal entity, period, form, filed date, accession and target | U6: None identified | V6: =IF(COUNTA(A6:U6)=21,"OK","MISSING") -> OK
A7: 3 | B7: Apple Inc. | C7: Historical!D5 | D7: Revenue | E7: 2023A | F7: 383285 | G7: USD millions | H7: USD | I7: us-gaap:RevenueFromContractWithCustomerExcludingAssessedTax | J7: 2022-09-25 | K7: 2023-09-30 | L7: 2025/FY | M7: 10-K | N7: 2025-10-31 | O7: 0000320193-25-000079 | P7: https://www.sec.gov/Archives/edgar/data/320193/000032019325000079/0000320193-25-000079-index.htm | Q7: 2026-07-16 | R7: Primary - SEC filing / Company Facts | S7: USD divided by 1,000,000; sign as presented | T7: Matched legal entity, period, form, filed date, accession and target | U7: None identified | V7: =IF(COUNTA(A7:U7)=21,"OK","MISSING") -> OK
A8: 4 | B8: Apple Inc. | C8: Historical!E5 | D8: Revenue | E8: 2024A | F8: 391035 | G8: USD millions | H8: USD | I8: us-gaap:RevenueFromContractWithCustomerExcludingAssessedTax | J8: 2023-10-01 | K8: 2024-09-28 | L8: 2025/FY | M8: 10-K | N8: 2025-10-31 | O8: 0000320193-25-000079 | P8: https://www.sec.gov/Archives/edgar/data/320193/000032019325000079/0000320193-25-000079-index.htm | Q8: 2026-07-16 | R8: Primary - SEC filing / Company Facts | S8: USD divided by 1,000,000; sign as presented | T8: Matched legal entity, period, form, filed date, accession and target | U8: None identified | V8: =IF(COUNTA(A8:U8)=21,"OK","MISSING") -> OK
A9: 5 | B9: Apple Inc. | C9: Historical!F5 | D9: Revenue | E9: 2025A | F9: 416161 | G9: USD millions | H9: USD | I9: us-gaap:RevenueFromContractWithCustomerExcludingAssessedTax | J9: 2024-09-29 | K9: 2025-09-27 | L9: 2025/FY | M9: 10-K | N9: 2025-10-31 | O9: 0000320193-25-000079 | P9: https://www.sec.gov/Archives/edgar/data/320193/000032019325000079/0000320193-25-000079-index.htm | Q9: 2026-07-16 | R9: Primary - SEC filing / Company Facts | S9: USD divided by 1,000,000; sign as presented | T9: Matched legal entity, period, form, filed date, accession and target | U9: None identified | V9: =IF(COUNTA(A9:U9)=21,"OK","MISSING") -> OK
A10: 6 | B10: Apple Inc. | C10: Historical!B6 | D10: Gross profit | E10: 2021A | F10: 152836 | G10: USD millions | H10: USD | I10: us-gaap:GrossProfit | J10: 2020-09-27 | K10: 2021-09-25 | L10: 2023/FY | M10: 10-K | N10: 2023-11-03 | O10: 0000320193-23-000106 | P10: https://www.sec.gov/Archives/edgar/data/320193/000032019323000106/0000320193-23-000106-index.htm | Q10: 2026-07-16 | R10: Primary - SEC filing / Company Facts | S10: USD divided by 1,000,000; sign as presented | T10: Matched legal entity, period, form, filed date, accession and target | U10: None identified | V10: =IF(COUNTA(A10:U10)=21,"OK","MISSING") -> OK
A11: 7 | B11: Apple Inc. | C11: Historical!C6 | D11: Gross profit | E11: 2022A | F11: 170782 | G11: USD millions | H11: USD | I11: us-gaap:GrossProfit | J11: 2021-09-26 | K11: 2022-09-24 | L11: 2024/FY | M11: 10-K | N11: 2024-11-01 | O11: 0000320193-24-000123 | P11: https://www.sec.gov/Archives/edgar/data/320193/000032019324000123/0000320193-24-000123-index.htm | Q11: 2026-07-16 | R11: Primary - SEC filing / Company Facts | S11: USD divided by 1,000,000; sign as presented | T11: Matched legal entity, period, form, filed date, accession and target | U11: None identified | V11: =IF(COUNTA(A11:U11)=21,"OK","MISSING") -> OK
A12: 8 | B12: Apple Inc. | C12: Historical!D6 | D12: Gross profit | E12: 2023A | F12: 169148 | G12: USD millions | H12: USD | I12: us-gaap:GrossProfit | J12: 2022-09-25 | K12: 2023-09-30 | L12: 2025/FY | M12: 10-K | N12: 2025-10-31 | O12: 0000320193-25-000079 | P12: https://www.sec.gov/Archives/edgar/data/320193/000032019325000079/0000320193-25-000079-index.htm | Q12: 2026-07-16 | R12: Primary - SEC filing / Company Facts | S12: USD divided by 1,000,000; sign as presented | T12: Matched legal entity, period, form, filed date, accession and target | U12: None identified | V12: =IF(COUNTA(A12:U12)=21,"OK","MISSING") -> OK
A13: 9 | B13: Apple Inc. | C13: Historical!E6 | D13: Gross profit | E13: 2024A | F13: 180683 | G13: USD millions | H13: USD | I13: us-gaap:GrossProfit | J13: 2023-10-01 | K13: 2024-09-28 | L13: 2025/FY | M13: 10-K | N13: 2025-10-31 | O13: 0000320193-25-000079 | P13: https://www.sec.gov/Archives/edgar/data/320193/000032019325000079/0000320193-25-000079-index.htm | Q13: 2026-07-16 | R13: Primary - SEC filing / Company Facts | S13: USD divided by 1,000,000; sign as presented | T13: Matched legal entity, period, form, filed date, accession and target | U13: None identified | V13: =IF(COUNTA(A13:U13)=21,"OK","MISSING") -> OK
A14: 10 | B14: Apple Inc. | C14: Historical!F6 | D14: Gross profit | E14: 2025A | F14: 195201 | G14: USD millions | H14: USD | I14: us-gaap:GrossProfit | J14: 2024-09-29 | K14: 2025-09-27 | L14: 2025/FY | M14: 10-K | N14: 2025-10-31 | O14: 0000320193-25-000079 | P14: https://www.sec.gov/Archives/edgar/data/320193/000032019325000079/0000320193-25-000079-index.htm | Q14: 2026-07-16 | R14: Primary - SEC filing / Company Facts | S14: USD divided by 1,000,000; sign as presented | T14: Matched legal entity, period, form, filed date, accession and target | U14: None identified | V14: =IF(COUNTA(A14:U14)=21,"OK","MISSING") -> OK
A15: 11 | B15: Apple Inc. | C15: Historical!B7 | D15: Operating income / EBIT | E15: 2021A | F15: 108949 | G15: USD millions | H15: USD | I15: us-gaap:OperatingIncomeLoss | J15: 2020-09-27 | K15: 2021-09-25 | L15: 2023/FY | M15: 10-K | N15: 2023-11-03 | O15: 0000320193-23-000106 | P15: https://www.sec.gov/Archives/edgar/data/320193/000032019323000106/0000320193-23-000106-index.htm | Q15: 2026-07-16 | R15: Primary - SEC filing / Company Facts | S15: USD divided by 1,000,000; sign as presented | T15: Matched legal entity, period, form, filed date, accession and target | U15: None identified | V15: =IF(COUNTA(A15:U15)=21,"OK","MISSING") -> OK
A16: 12 | B16: Apple Inc. | C16: Historical!C7 | D16: Operating income / EBIT | E16: 2022A | F16: 119437 | G16: USD millions | H16: USD | I16: us-gaap:OperatingIncomeLoss | J16: 2021-09-26 | K16: 2022-09-24 | L16: 2024/FY | M16: 10-K | N16: 2024-11-01 | O16: 0000320193-24-000123 | P16: https://www.sec.gov/Archives/edgar/data/320193/000032019324000123/0000320193-24-000123-index.htm | Q16: 2026-07-16 | R16: Primary - SEC filing / Company Facts | S16: USD divided by 1,000,000; sign as presented | T16: Matched legal entity, period, form, filed date, accession and target | U16: None identified | V16: =IF(COUNTA(A16:U16)=21,"OK","MISSING") -> OK
... A96: 92 | B96: Apple Inc. | C96: Valuation!G19 | D96: Market close | E96: 2026-07-15 | F96: 327.5 | G96: USD per share | H96: USD | I96: Issuer IR:Historical daily close | J96: N/A - instant | K96: 2026-07-15 | L96: N/A | M96: Market data | N96: 2026-07-15 | O96: N/A - market data | P96: https://investor.apple.com/investor-relations/stock-price/ | Q96: 2026-07-16 | R96: Primary - issuer investor-relations historical stock-price lookup | S96: Closing price as displayed; no FX | T96: Date and close matched on cited historical-price surface | U96: Issuer lookup is interactive; refresh the exact dated close before transaction use | V96: =IF(COUNTA(A96:U96)=21,"OK","MISSING") -> OK
A98: Ledger completeness | G98: =COUNTIF(V5:V96,"OK") -> 92 | H98: 92 | I98: =IF(G98=H98,"OK","REVIEW") -> OK

Sheet Historical
A1: Apple Inc. — Historical Financials
A2: SEC 10-K / Company Facts lineage; USD millions except per-share data and shares
A4: Metric | B4: 2021A | C4: 2022A | D4: 2023A | E4: 2024A | F4: 2025A
A5: Revenue | B5: 365817 | C5: 394328 | D5: 383285 | E5: 391035 | F5: 416161
A6: Gross profit | B6: 152836 | C6: 170782 | D6: 169148 | E6: 180683 | F6: 195201
A7: Operating income / EBIT | B7: 108949 | C7: 119437 | D7: 114301 | E7: 123216 | F7: 133050
A8: Net income | B8: 94680 | C8: 99803 | D8: 96995 | E8: 93736 | F8: 112010
A9: Cash from operations | B9: 104038 | C9: 122151 | D9: 110543 | E9: 118254 | F9: 111482
A10: Capital expenditures | B10: 11085 | C10: 10708 | D10: 10959 | E10: 9447 | F10: 12715
A11: Total assets | B11: 351002 | C11: 352755 | D11: 352583 | E11: 364980 | F11: 359241
A12: Shareholders' equity | B12: 63090 | C12: 50672 | D12: 62146 | E12: 56950 | F12: 73733
A13: Cash and equivalents | B13: 34940 | C13: 23646 | D13: 29965 | E13: 29943 | F13: 35934
A14: Total debt | C14: 110087 | D14: 105103 | E14: 96662 | F14: 90678
A15: Diluted weighted-average shares | B15: 16864.919 | C15: 16325.819 | D15: 15812.547 | E15: 15408.095 | F15: 15004.697
A17: Bridge policy | B17: Latest balance-sheet cash policy
A18: Liquid assets used in DCF | B18: =SUM(B23:B25) -> 132420 | F18: USD millions
A19: Debt used in DCF | B19: =F14 -> 90678 | F19: USD millions
A20: Share count used in DCF | B20: 14776.353 | F20: million shares
A22: Apple liquid-asset bridge | B22: 2025A | C22: Policy | D22: USD m | E22: Source | F22: Status
A23: Cash and equivalents | B23: =F13 -> 35934 | C23: Included | D23: USD m | E23: Historical latest balance | F23: Formula link
A24: Current marketable securities | B24: 18763 | C24: Included | D24: USD m | E24: us-gaap:MarketableSecuritiesCurrent | F24: OK
A25: Non-current marketable securities | B25: 77723 | C25: Included | D25: USD m | E25: us-gaap:MarketableSecuritiesNoncurrent | F25: OK

Sheet Assumptions
A1: Apple Inc. — Scenario Assumptions
A2: Selector drives operating revenues/margins and the DCF; blue/amber cells are editable inputs
A3: Scenario selector (1 Base / 2 Bull / 3 Bear) | B3: 1 | G3: Input
A4: Active scenario | B4: =CHOOSE(B3,"Base","Bull","Bear") -> Base | G4: Formula
A6: Assumption | B6: Units | C6: Base | D6: Bull | E6: Bear | F6: Active | G6: Rationale / evidence
A7: iPhone revenue growth | B7: % | C7: 0.03 | D7: 0.06 | E7: 0 | F7: =CHOOSE($B$3,C7,D7,E7) -> 0.03 | G7: 2025 iPhone revenue USD 209,586m; scenario growth driver
A8: Mac revenue growth | B8: % | C8: 0.04 | D8: 0.08 | E8: 0 | F8: =CHOOSE($B$3,C8,D8,E8) -> 0.04 | G8: 2025 Mac revenue USD 33,708m; scenario growth driver
A9: iPad revenue growth | B9: % | C9: 0.02 | D9: 0.06 | E9: -0.02 | F9: =CHOOSE($B$3,C9,D9,E9) -> 0.02 | G9: 2025 iPad revenue USD 28,023m; scenario growth driver
A10: Wearables revenue growth | B10: % | C10: 0.01 | D10: 0.05 | E10: -0.04 | F10: =CHOOSE($B$3,C10,D10,E10) -> 0.01 | G10: 2025 Wearables revenue USD 35,686m; scenario growth driver
A11: Services revenue growth | B11: % | C11: 0.11 | D11: 0.14 | E11: 0.07 | F11: =CHOOSE($B$3,C11,D11,E11) -> 0.11 | G11: 2025 Services revenue USD 109,158m; scenario growth driver
A12: Products gross margin | B12: % | C12: 0.368 | D12: 0.38 | E12: 0.355 | F12: =CHOOSE($B$3,C12,D12,E12) -> 0.368 | G12: 2025 reported products gross margin 36.8%
A13: Services gross margin | B13: % | C13: 0.754 | D13: 0.77 | E13: 0.72 | F13: =CHOOSE($B$3,C13,D13,E13) -> 0.754 | G13: 2025 reported services gross margin 75.4%
A14: R&D as % revenue | B14: % | C14: 0.083 | D14: 0.078 | E14: 0.09 | F14: =CHOOSE($B$3,C14,D14,E14) -> 0.083 | G14: 2025 R&D USD 34,550m / revenue
A15: SG&A as % revenue | B15: % | C15: 0.066 | D15: 0.062 | E15: 0.07 | F15: =CHOOSE($B$3,C15,D15,E15) -> 0.066 | G15: 2025 SG&A USD 27,601m / revenue
A16: Cash tax rate | B16: % | C16: 0.165 | D16: 0.15 | E16: 0.185 | F16: =CHOOSE($B$3,C16,D16,E16) -> 0.165 | G16: Normalized cash tax rate
A17: D&A as % revenue | B17: % | C17: 0.03 | D17: 0.032 | E17: 0.028 | F17: =CHOOSE($B$3,C17,D17,E17) -> 0.03 | G17: Normalized D&A intensity
A18: Capex as % revenue | B18: % | C18: 0.031 | D18: 0.028 | E18: 0.035 | F18: =CHOOSE($B$3,C18,D18,E18) -> 0.031 | G18: Normalized capex intensity
... A21: Terminal growth | B21: % | C21: 0.025 | D21: 0.03 | E21: 0.02 | F21: =CHOOSE($B$3,C21,D21,E21) -> 0.025 | G21: DCF perpetual-growth scenario

Sheet Forecast
A1: Apple Inc. — Operating Forecast
A2: Scenario-linked driver build; expense and capex anchors are negative model outflows; USD millions
A4: Metric | B4: 2025A | C4: 2026E | D4: 2027E | E4: 2028E | F4: 2029E | G4: 2030E
A5: iPhone revenue | B5: =Sector_KPIs!D5 -> 209586 | C5: =B5*(1+Assumptions!F7) -> 215873.58 | D5: =C5*(1+Assumptions!F7) -> 222349.79 | E5: =D5*(1+Assumptions!F7) -> 229020.28 | F5: =E5*(1+Assumptions!F7) -> 235890.89 | G5: =F5*(1+Assumptions!F7) -> 242967.62
A6: Mac revenue | B6: =Sector_KPIs!D6 -> 33708 | C6: =B6*(1+Assumptions!F8) -> 35056.32 | D6: =C6*(1+Assumptions!F8) -> 36458.573 | E6: =D6*(1+Assumptions!F8) -> 37916.916 | F6: =E6*(1+Assumptions!F8) -> 39433.592 | G6: =F6*(1+Assumptions!F8) -> 41010.936
A7: iPad revenue | B7: =Sector_KPIs!D7 -> 28023 | C7: =B7*(1+Assumptions!F9) -> 28583.46 | D7: =C7*(1+Assumptions!F9) -> 29155.129 | E7: =D7*(1+Assumptions!F9) -> 29738.232 | F7: =E7*(1+Assumptions!F9) -> 30332.996 | G7: =F7*(1+Assumptions!F9) -> 30939.656
A8: Wearables revenue | B8: =Sector_KPIs!D8 -> 35686 | C8: =B8*(1+Assumptions!F10) -> 36042.86 | D8: =C8*(1+Assumptions!F10) -> 36403.289 | E8: =D8*(1+Assumptions!F10) -> 36767.321 | F8: =E8*(1+Assumptions!F10) -> 37134.995 | G8: =F8*(1+Assumptions!F10) -> 37506.345
A9: Services revenue | B9: =Sector_KPIs!D9 -> 109158 | C9: =B9*(1+Assumptions!F11) -> 121165.38 | D9: =C9*(1+Assumptions!F11) -> 134493.57 | E9: =D9*(1+Assumptions!F11) -> 149287.86 | F9: =E9*(1+Assumptions!F11) -> 165709.53 | G9: =F9*(1+Assumptions!F11) -> 183937.58
A10: Total revenue | B10: =SUM(B5:B9) -> 416161 | C10: =SUM(C5:C9) -> 436721.6 | D10: =SUM(D5:D9) -> 458860.35 | E10: =SUM(E5:E9) -> 482730.61 | F10: =SUM(F5:F9) -> 508502 | G10: =SUM(G5:G9) -> 536362.13
A11: Products gross profit | B11: =Sector_KPIs!D11 -> 112887 | C11: =SUM(C5:C8)*Assumptions!F12 -> 116124.69 | D11: =SUM(D5:D8)*Assumptions!F12 -> 119366.97 | E11: =SUM(E5:E8)*Assumptions!F12 -> 122706.93 | F11: =SUM(F5:F8)*Assumptions!F12 -> 126147.63 | G11: =SUM(G5:G8)*Assumptions!F12 -> 129692.24
A12: Services gross profit | B12: =Sector_KPIs!D12 -> 82314 | C12: =C9*Assumptions!F13 -> 91358.697 | D12: =D9*Assumptions!F13 -> 101408.15 | E12: =E9*Assumptions!F13 -> 112563.05 | F12: =F9*Assumptions!F13 -> 124944.99 | G12: =G9*Assumptions!F13 -> 138688.93
A13: Total gross profit | B13: =SUM(B11:B12) -> 195201 | C13: =SUM(C11:C12) -> 207483.39 | D13: =SUM(D11:D12) -> 220775.13 | E13: =SUM(E11:E12) -> 235269.98 | F13: =SUM(F11:F12) -> 251092.62 | G13: =SUM(G11:G12) -> 268381.17
A14: R&D | B14: =-Sector_KPIs!D15 -> -34550 | C14: =-C10*Assumptions!F14 -> -36247.893 | D14: =-D10*Assumptions!F14 -> -38085.409 | E14: =-E10*Assumptions!F14 -> -40066.641 | F14: =-F10*Assumptions!F14 -> -42205.666 | G14: =-G10*Assumptions!F14 -> -44518.057
A15: SG&A | B15: =-Sector_KPIs!D16 -> -27601 | C15: =-C10*Assumptions!F15 -> -28823.626 | D15: =-D10*Assumptions!F15 -> -30284.783 | E15: =-E10*Assumptions!F15 -> -31860.221 | F15: =-F10*Assumptions!F15 -> -33561.132 | G15: =-G10*Assumptions!F15 -> -35399.901
A16: EBIT | B16: =SUM(B13:B15) -> 133050 | C16: =SUM(C13:C15) -> 142411.87 | D16: =SUM(D13:D15) -> 152404.94 | E16: =SUM(E13:E15) -> 163343.12 | F16: =SUM(F13:F15) -> 175325.82 | G16: =SUM(G13:G15) -> 188463.21
A17: Cash taxes | B17: =-B16*Assumptions!C16 -> -21953.25 | C17: =-C16*Assumptions!F16 -> -23497.958 | D17: =-D16*Assumptions!F16 -> -25146.814 | E17: =-E16*Assumptions!F16 -> -26951.615 | F17: =-F16*Assumptions!F16 -> -28928.76 | G17: =-G16*Assumptions!F16 -> -31096.43
A18: NOPAT | B18: =B16+B17 -> 111096.75 | C18: =SUM(C16:C17) -> 118913.91 | D18: =SUM(D16:D17) -> 127258.12 | E18: =SUM(E16:E17) -> 136391.51 | F18: =SUM(F16:F17) -> 146397.06 | G18: =SUM(G16:G17) -> 157366.78
A19: D&A | B19: =Sector_KPIs!D17 -> 11698 | C19: =C10*Assumptions!F17 -> 13101.648 | D19: =D10*Assumptions!F17 -> 13765.81 | E19: =E10*Assumptions!F17 -> 14481.918 | F19: =F10*Assumptions!F17 -> 15255.06 | G19: =G10*Assumptions!F17 -> 16090.864
A20: Capital expenditures | B20: =-Historical!F10 -> -12715 | C20: =-C10*Assumptions!F18 -> -13538.37 | D20: =-D10*Assumptions!F18 -> -14224.671 | E20: =-E10*Assumptions!F18 -> -14964.649 | F20: =-F10*Assumptions!F18 -> -15763.562 | G20: =-G10*Assumptions!F18 -> -16627.226
A21: Change in NWC | B21: =0 -> 0 | C21: =-(C10-B10)*Assumptions!F19 -> -205.606 | D21: =-(D10-C10)*Assumptions!F19 -> -221.3875 | E21: =-(E10-D10)*Assumptions!F19 -> -238.70265 | F21: =-(F10-E10)*Assumptions!F19 -> -257.71388 | G21: =-(G10-F10)*Assumptions!F19 -> -278.60129
A22: FCFF | B22: =SUM(B18:B21) -> 110079.75 | C22: =SUM(C18:C21) -> 118271.58 | D22: =SUM(D18:D21) -> 126577.87 | E22: =SUM(E18:E21) -> 135670.07 | F22: =SUM(F18:F21) -> 145630.84 | G22: =SUM(G18:G21) -> 156551.82

Sheet Valuation
A1: Apple Inc. — DCF Valuation
A2: Unlevered FCFF; liquid-asset and debt bridge policies are explicit
A4: DCF item | B4: Year 1 | C4: Year 2 | D4: Year 3 | E4: Year 4 | F4: Year 5 | G4: Bridge / output
A5: FCFF | B5: =Forecast!C22 -> 118271.58 | C5: =Forecast!D22 -> 126577.87 | D5: =Forecast!E22 -> 135670.07 | E5: =Forecast!F22 -> 145630.84 | F5: =Forecast!G22 -> 156551.82
A6: Discount period | B6: 1 | C6: 2 | D6: 3 | E6: 4 | F6: 5
A7: Discount factor | B7: =1/(1+Assumptions!F20)^B6 -> 0.91324201 | C7: =1/(1+Assumptions!F20)^C6 -> 0.83401097 | D7: =1/(1+Assumptions!F20)^D6 -> 0.76165385 | E7: =1/(1+Assumptions!F20)^E6 -> 0.69557429 | F7: =1/(1+Assumptions!F20)^F6 -> 0.63522767
A8: Present value of FCFF | B8: =B5*B7 -> 108010.58 | C8: =C5*C7 -> 105567.33 | D8: =D5*D7 -> 103333.63 | E8: =E5*E7 -> 101297.07 | F8: =F5*F7 -> 99446.046
A9: Terminal value | F9: =F5*(1+Assumptions!F21)/(Assumptions!F20-Assumptions!F21) -> 2292365.9
A10: PV of terminal value | F10: =F9*F7 -> 1456174.2
A11: Enterprise value | G11: =SUM(B8:F8)+F10 -> 1973828.9
A12: Liquid assets | G12: =Historical!B18 -> 132420
A13: Debt | G13: =Historical!B19 -> 90678
A14: Equity value | G14: =G11+G12-G13 -> 2015570.9
A15: Shares outstanding / diluted policy | G15: =Historical!B20 -> 14776.353
A17: Per-share outputs
A18: DCF value / share | G18: =G14/G15 -> 136.40517
A19: Market price | G19: 327.5
A20: Upside / (downside) | G20: =G18/G19-1 -> -0.58349567
A21: Market as-of | G21: 2026-07-15

Sheet Sensitivity
A1: Apple Inc. — DCF Sensitivity
A2: Implied value per share across WACC and terminal-growth assumptions
A4: WACC / TGR | B4: 0.015 | C4: 0.02 | D4: 0.025 | E4: 0.03 | F4: 0.035
A5: 0.08 | B5: =(SUM(Valuation!B8:F8)+Forecast!G22*(1+B$4)/($A5-B$4)*Valuation!F7+Valuation!G12-Valuation!G13)/Valuation!G15 -> 142.95036 | C5: =(SUM(Valuation!B8:F8)+Forecast!G22*(1+C$4)/($A5-C$4)*Valuation!F7+Valuation!G12-Valuation!G13)/Valuation!G15 -> 152.26893 | D5: =(SUM(Valuation!B8:F8)+Forecast!G22*(1+D$4)/($A5-D$4)*Valuation!F7+Valuation!G12-Valuation!G13)/Valuation!G15 -> 163.28179 | E5: =(SUM(Valuation!B8:F8)+Forecast!G22*(1+E$4)/($A5-E$4)*Valuation!F7+Valuation!G12-Valuation!G13)/Valuation!G15 -> 176.49722 | F5: =(SUM(Valuation!B8:F8)+Forecast!G22*(1+F$4)/($A5-F$4)*Valuation!F7+Valuation!G12-Valuation!G13)/Valuation!G15 -> 192.64941
A6: 0.0875 | B6: =(SUM(Valuation!B8:F8)+Forecast!G22*(1+B$4)/($A6-B$4)*Valuation!F7+Valuation!G12-Valuation!G13)/Valuation!G15 -> 132.07869 | C6: =(SUM(Valuation!B8:F8)+Forecast!G22*(1+C$4)/($A6-C$4)*Valuation!F7+Valuation!G12-Valuation!G13)/Valuation!G15 -> 139.55655 | D6: =(SUM(Valuation!B8:F8)+Forecast!G22*(1+D$4)/($A6-D$4)*Valuation!F7+Valuation!G12-Valuation!G13)/Valuation!G15 -> 148.23088 | E6: =(SUM(Valuation!B8:F8)+Forecast!G22*(1+E$4)/($A6-E$4)*Valuation!F7+Valuation!G12-Valuation!G13)/Valuation!G15 -> 158.41379 | F6: =(SUM(Valuation!B8:F8)+Forecast!G22*(1+F$4)/($A6-F$4)*Valuation!F7+Valuation!G12-Valuation!G13)/Valuation!G15 -> 170.53629
A7: 0.095 | B7: =(SUM(Valuation!B8:F8)+Forecast!G22*(1+B$4)/($A7-B$4)*Valuation!F7+Valuation!G12-Valuation!G13)/Valuation!G15 -> 123.24546 | C7: =(SUM(Valuation!B8:F8)+Forecast!G22*(1+C$4)/($A7-C$4)*Valuation!F7+Valuation!G12-Valuation!G13)/Valuation!G15 -> 129.38666 | D7: =(SUM(Valuation!B8:F8)+Forecast!G22*(1+D$4)/($A7-D$4)*Valuation!F7+Valuation!G12-Valuation!G13)/Valuation!G15 -> 136.40517 | E7: =(SUM(Valuation!B8:F8)+Forecast!G22*(1+E$4)/($A7-E$4)*Valuation!F7+Valuation!G12-Valuation!G13)/Valuation!G15 -> 144.50345 | F7: =(SUM(Valuation!B8:F8)+Forecast!G22*(1+F$4)/($A7-F$4)*Valuation!F7+Valuation!G12-Valuation!G13)/Valuation!G15 -> 153.95145
A8: 0.1025 | B8: =(SUM(Valuation!B8:F8)+Forecast!G22*(1+B$4)/($A8-B$4)*Valuation!F7+Valuation!G12-Valuation!G13)/Valuation!G15 -> 115.92649 | C8: =(SUM(Valuation!B8:F8)+Forecast!G22*(1+C$4)/($A8-C$4)*Valuation!F7+Valuation!G12-Valuation!G13)/Valuation!G15 -> 121.06583 | D8: =(SUM(Valuation!B8:F8)+Forecast!G22*(1+D$4)/($A8-D$4)*Valuation!F7+Valuation!G12-Valuation!G13)/Valuation!G15 -> 126.8683 | E8: =(SUM(Valuation!B8:F8)+Forecast!G22*(1+E$4)/($A8-E$4)*Valuation!F7+Valuation!G12-Valuation!G13)/Valuation!G15 -> 133.47112 | F8: =(SUM(Valuation!B8:F8)+Forecast!G22*(1+F$4)/($A8-F$4)*Valuation!F7+Valuation!G12-Valuation!G13)/Valuation!G15 -> 141.05213
A9: 0.11 | B9: =(SUM(Valuation!B8:F8)+Forecast!G22*(1+B$4)/($A9-B$4)*Valuation!F7+Valuation!G12-Valuation!G13)/Valuation!G15 -> 109.76316 | C9: =(SUM(Valuation!B8:F8)+Forecast!G22*(1+C$4)/($A9-C$4)*Valuation!F7+Valuation!G12-Valuation!G13)/Valuation!G15 -> 114.13181 | D9: =(SUM(Valuation!B8:F8)+Forecast!G22*(1+D$4)/($A9-D$4)*Valuation!F7+Valuation!G12-Valuation!G13)/Valuation!G15 -> 119.01441 | E9: =(SUM(Valuation!B8:F8)+Forecast!G22*(1+E$4)/($A9-E$4)*Valuation!F7+Valuation!G12-Valuation!G13)/Valuation!G15 -> 124.50735 | F9: =(SUM(Valuation!B8:F8)+Forecast!G22*(1+F$4)/($A9-F$4)*Valuation!F7+Valuation!G12-Valuation!G13)/Valuation!G15 -> 130.73267
B11: Central cross-check
B12: Active WACC | C12: =Assumptions!F20 -> 0.095
B13: Active TGR | C13: =Assumptions!F21 -> 0.025
B14: Active DCF value/share | C14: =Valuation!G18 -> 136.40517

Sheet Checks
A1: Apple Inc. — Model Checks
A2: Overall status is formula-driven from assertions; source completeness is linked to the provenance ledger
A4: Assertion | B4: Actual | C4: Expected | D4: Difference | E4: Tolerance | F4: Status | G4: Fix hint
A5: Source ledger complete | B5: =Sources!I98 -> OK | C5: OK | F5: =IF(B5=C5,"OK","REVIEW") -> OK | G5: Complete every mandatory provenance field
A6: Scenario selector valid | B6: =Assumptions!B3 -> 1 | C6: 1 | D6: =IF(AND(B6>=1,B6<=3),0,1) -> 0 | E6: 0 | F6: =IF(D6=E6,"OK","REVIEW") -> OK | G6: Set Assumptions!B3 to 1, 2 or 3
A7: Forecast revenue positive | B7: =Forecast!C10 -> 436721.6 | C7: 0 | D7: =IF(B7>0,0,1) -> 0 | E7: 0 | F7: =IF(D7=E7,"OK","REVIEW") -> OK | G7: Inspect revenue-driver formulas
A8: Five EBIT periods populated | B8: =COUNT(Forecast!C16:G16) -> 5 | C8: 5 | D8: =ABS(B8-C8) -> 0 | E8: 0 | F8: =IF(D8=E8,"OK","REVIEW") -> OK | G8: Inspect margin and opex build
A9: Five FCFF periods populated | B9: =COUNT(Forecast!C22:G22) -> 5 | C9: 5 | D9: =ABS(B9-C9) -> 0 | E9: 0 | F9: =IF(D9=E9,"OK","REVIEW") -> OK | G9: Inspect NOPAT, D&A, capex and NWC
A10: 2025A material forecast-anchor tie | B10: =SUM(ABS(Forecast!B5-Sector_KPIs!D5),ABS(Forecast!B6-Sector_KPIs!D6),ABS(Forecast!B7-Sector_KPIs!D7),ABS(Forecast!B8-Sector_KPIs!D8),ABS(Forecast!B9-Sector_KPIs!D9),ABS(Forecast!B11-Sector_KPIs!D11),ABS(Forecast!B12-Sector_KPIs!D12),ABS(ABS(Forecast!B14)-Sector_KPIs!D15),ABS(ABS(Forecast!B15)-Sector_KPIs!D16),ABS(Forecast!B19-Sector_KPIs!D17),ABS(ABS(Forecast!B20)-Historical!F10)) -> 0 | C10: 0 | D10: =ABS(B10-C10) -> 0 | E10: 0.1 | F10: =IF(D10<=E10,"OK","REVIEW") -> OK | G10: Historical inputs are positive as reported; forecast expense/capex anchors are negative model outflows
A11: DCF equity bridge | B11: =Valuation!G14 -> 2015570.9 | C11: =Valuation!G11+Valuation!G12-Valuation!G13 -> 2015570.9 | D11: =ABS(B11-C11) -> 0 | E11: 0.1 | F11: =IF(D11<=E11,"OK","REVIEW") -> OK | G11: Inspect EV, liquid assets and total debt
A12: DCF per-share identity | B12: =Valuation!G18 -> 136.40517 | C12: =Valuation!G14/Valuation!G15 -> 136.40517 | D12: =ABS(B12-C12) -> 0 | E12: 0.001 | F12: =IF(D12<=E12,"OK","REVIEW") -> OK | G12: Inspect shares bridge
A13: Market price positive and sourced | B13: =Valuation!G19 -> 327.5 | C13: 0 | D13: =IF(B13>0,0,1) -> 0 | E13: 0 | F13: =IF(D13=E13,"OK","REVIEW") -> OK | G13: Update the dated market source row in Sources
A14: Tie-outs históricos y de cobertura (Checks_TieOut) | B14: =COUNTIF(Checks_TieOut!H5:H61,"FAIL") -> 1 | C14: 0 | D14: =ABS(B14-C14) -> 1 | E14: 0 | F14: =IF(D14=E14,"OK","REVIEW") -> REVIEW | G14: Abrir Checks_TieOut y resolver toda fila en FAIL antes de volver a certificar el gate
A15: Overall status | F15: =IF(COUNTIF(F5:F14,"OK")=10,"OK","REVIEW") -> REVIEW

Sheet Sector_KPIs
A1: Apple Inc. — Company Operating Drivers
A2: Company-specific reported driver history; formulas reconcile the model totals to historical revenue where applicable
A4: Metric | B4: 2023A | C4: 2024A | D4: 2025A | E4: Units | F4: Source / locator | G4: Status
A5: iPhone revenue | B5: 200583 | C5: 201183 | D5: 209586 | E5: USD m | F5: 2025 Form 10-K, Net Sales by Reportable Segment and Product | G5: Reported
A6: Mac revenue | B6: 29357 | C6: 29984 | D6: 33708 | E6: USD m | F6: 2025 Form 10-K, product net sales | G6: Reported
A7: iPad revenue | B7: 28300 | C7: 26694 | D7: 28023 | E7: USD m | F7: 2025 Form 10-K, product net sales | G7: Reported
A8: Wearables, Home & Accessories revenue | B8: 39845 | C8: 37005 | D8: 35686 | E8: USD m | F8: 2025 Form 10-K, product net sales | G8: Reported
A9: Services revenue | B9: 85200 | C9: 96169 | D9: 109158 | E9: USD m | F9: 2025 Form 10-K, services net sales | G9: Reported
A10: Revenue total | B10: =SUM(B5:B9) -> 383285 | C10: =SUM(C5:C9) -> 391035 | D10: =SUM(D5:D9) -> 416161 | E10: USD m | F10: Sum of categories | G10: Formula
A11: Products gross profit | B11: 108803 | C11: 109633 | D11: 112887 | E11: USD m | F11: 2025 Form 10-K, products and services performance | G11: Reported
A12: Services gross profit | B12: 60345 | C12: 71050 | D12: 82314 | E12: USD m | F12: 2025 Form 10-K, products and services performance | G12: Reported
A13: Products gross margin | B13: 0.365 | C13: 0.372 | D13: 0.368 | E13: % | F13: 2025 Form 10-K, products and services performance | G13: Reported
A14: Services gross margin | B14: 0.708 | C14: 0.739 | D14: 0.754 | E14: % | F14: 2025 Form 10-K, products and services performance | G14: Reported
A15: R&D | B15: 29915 | C15: 31370 | D15: 34550 | E15: USD m | F15: 2025 Form 10-K, operating expenses | G15: Reported
A16: SG&A | B16: 24932 | C16: 26097 | D16: 27601 | E16: USD m | F16: 2025 Form 10-K, operating expenses | G16: Reported
A17: D&A | D17: 11698 | E17: USD m | F17: us-gaap:DepreciationDepletionAndAmortization | G17: Reported

Sheet Change_Log
A1: Apple Inc. — Change Log
A2: Re-gating work performed without overwriting the prior workbook
A4: Timestamp (UTC) | B4: Scope | C4: Change | D4: Evidence | E4: Prior hash | F4: Preparer | G4: Disposition
A5: Build 2026-07-17T02:33:12.208Z | B5: Source lineage | C5: Added line-item target-cell provenance ledger | D5: Sources + SEC Company Facts / 10-K | E5: 6560d19fbe4cd8919c00bc2f78dfe01eefa7ce0001ba10039ea4da797e7f837a | F5: Codex | G5: Ready for independent review
A6: Build 2026-07-17T02:33:12.208Z | B6: Operating model | C6: Added company-specific revenue and margin drivers | D6: Sector_KPIs, Assumptions, Forecast | E6: 6560d19fbe4cd8919c00bc2f78dfe01eefa7ce0001ba10039ea4da797e7f837a | F6: Codex | G6: Ready for independent review
A7: Build 2026-07-17T02:33:12.208Z | B7: Valuation | C7: Rebuilt FCFF DCF, bridge and sensitivity | D7: Valuation + Sensitivity | E7: 6560d19fbe4cd8919c00bc2f78dfe01eefa7ce0001ba10039ea4da797e7f837a | F7: Codex | G7: Ready for independent review
A8: Build 2026-07-17T02:33:12.208Z | B8: Governance | C8: Added formula-driven checks and Gate_9of10 | D8: Checks + Gate_9of10 | E8: 6560d19fbe4cd8919c00bc2f78dfe01eefa7ce0001ba10039ea4da797e7f837a | F8: Codex | G8: Owner submission only
A9: 46224 | B9: Ola 2 elevation to statement-grade IG: added audited FY2021A-FY2025A IS_Hist/CI_Hist/BS_Hist/CF_Hist/SCE_Hist, Segment_Products (Products/Services schedule), Checks_TieOut (33 tie-outs incl. cross-statement + cash/equity continuity), Sources_Audited, Source_Register. Native currency USD, no FX layer needed. FY2021 SCE roll-forward and FY2021 Products/Services split flagged as sourcing gaps (not in research package). Prior 9of10 sheets left unmodified; Gate_9of10 not re-certified. Root workbook untouched; built via Mog SDK only into the maintainer's archive. | C9: Claude (run 24e4a1f1)
A13: 46224 | B13: Added forecast layer: Fwd_Assumptions (Bear/Base/Bull driver switch, Fwd_Assumptions!B2), Fwd_IS (driver-built IS + simplified capex/D&A/SBC/WC/FCF/capital-return, FY2026E-FY2030E, anchored to FY2025A), Fwd_Summary. PARTIAL scope: no BS/CF forecast tabs, no debt-maturity schedule, no share-price-based buyback share-count solve — flagged in build report as an honest scope limitation, not fabricated detail. | C13: Claude (run 24e4a1f1)
A14: 46248 | B14: Capa de cobertura (2026-08-14): se agregaron Drivers_MDA (drivers de negocio del MD&A y los disclosures, FY2021A-FY2025A: ingresos por categoría de producto, por segmento geográfico, utilidad operativa por segmento con su reconciliación, economía Products vs Services, métricas operativas divulgadas, drivers FX, y declaración explícita de lo que Apple NO divulga) y Market_Package (precio, acciones, market cap, puente a EV, beta, Rf, ERP, costo de deuda, tasa de impuestos, WACC y múltiplos implícitos, cada input con fuente y FECHA). Se agregaron 18 tie-outs nuevos en Checks_TieOut (filas 40-57) y se amplió el rango del gate maestro de H5:H38 a H5:H57 (endurece, no debilita). Cerrada la brecha declarada en Sources_Audited!A11: el split Products/Services de FY2021 se obtuvo del 10-K FY2021. NINGUNA hoja histórica (IS/CI/BS/CF/SCE_Hist, Segment_Products) ni el DCF existente fueron modificados; los hallazgos sobre el puente de deuda y el precio en duro quedan declarados en Market_Package, no corregidos. | C14: Claude Opus 5 (capa de cobertura, piloto de flota)
A15: 46248 | B15: Checks_TieOut, Checks, Market_Package, Drivers_MDA y Change_Log | C15: Corrección de la revisión adversarial de la capa de cobertura. (1) Los checks 51 a 55 eran tautologías algebraicas —restaban cada celda contra su propia definición— y no podían ponerse rojos: se reconstruyeron contra fuente independiente, recomputando desde insumos primarios y desde los subtotales auditados de BS_Hist, más bandas de plausibilidad contra el precio fechado de Valuation!G19 y el conteo de acciones de BS_Hist!F40. (2) Checks_TieOut no gateaba nada: se agregó la fila Checks!A14:G14 (COUNTIF de FAIL sobre Checks_TieOut!H5:H61) y Checks!F15 pasa de 9 a 10 asserts, de modo que Gate_9of10!B18 cae en REVIEW si cae cualquier tie-out. (3) Kd refrescado de 5.27% fechado como texto a 5.20% con serial 2026-08-13, leído de la serie primaria de FRED BAMLC0A2CAAEY; el control de procedencia ahora exige fecha serial y castiga el desfase (Market_Package B90 reescrito y B92 nuevo). (4) Checks nuevos: 58 (Assumptions!C12 y C13 contra Drivers_MDA!F85 y F86), 59 (cruce geográfico por línea), 60 (márgenes brutos reportados contra calculados) y 61 (bandas de plausibilidad para las constantes sin tie). (5) Drivers_MDA!A145 corregido a "coincide en valor, no enlazado", A133 renombrada como ilustrativa de Americas, y bloque 9 nuevo (A150 a A155) declarando exactamente qué NO está mecanizado. (6) Change_Log: se vaciaron las filas 10 a 12 (duplicados idénticos de la 9); la corrección del conteo de tie-outs (34, no 33) vive hoy en la fila 16, en sus columnas correctas | D15: Informe de revisión adversarial 2026-08-14. Pruebas de instrumento con defectos plantados sobre copias en scratchpad: precio 1.00, Rf 99%, BS_Hist!F24 a 1000, BS_Hist!F7 corrupto, Drivers_MDA!F33 a 60000, F87 a 99%, F94 a 1, F96 a 999999, F119 a 999999, permutación de F31 con F32, y D34 devuelto a texto | E15: 11b1dbde2e38ed3654ee5ae5197b23d4c7269c59007f781943ecdc6d2d9ad75a | F15: Claude Opus 5 (corrección de auditoría) | G15: Instrumento probado: cada check tocado cae en FAIL ante su defecto y el gate se pone en REVIEW. El archivo activo queda sano
A16: 46248 | B16: Change_Log fila 9 | C16: CORRECCIÓN: la entrada de la fila 9 dice "33 tie-outs" y la cifra correcta es 34 — el rango original era H5:H38, 34 filas de status, las 34 en PASS. Las filas 10 a 12 eran duplicados idénticos de esa misma entrada y se vaciaron. Esta nota vivía en D9 (columna Evidence); se movió aquí, a la columna Change, según el encabezado A4:G4 | D16: Conteo de filas de status del rango original Checks_TieOut!H5:H38 | F16: Claude (ronda 3, segunda verificación) | G16: Nota de corrección; la fila 9 original se conserva intacta
A17: 46248 | B17: Checks_TieOut (51 a 56), Market_Package (bloque 8 de anclas, control de procedencia, notas), Drivers_MDA (A150:A155), Checks!A14, Gate_9of10!F17, Change_Log | C17: Ronda 3 — cierre de la segunda verificación. (1) Checks 51 a 53 re-anclados a un vintage DISTINTO: el 10-Q Q3 FY2026 (accn 0000320193-26-000020, radicado el 2026-07-31) trae el balance al 2026-06-27 y la columna comparativa al 2025-09-27; ambas vivas como constantes fechadas (B82/B83 y el bloque 8 nuevo, B104/B105). El 52 exige tie exacto de B17 contra B104 y banda de ±15% contra B82; el 53 conserva el puente del papel comercial (H1), exige tie exacto de B21 contra B105 y banda de ±25% contra B83 (la deriva real ya es +17.0%, una banda de ±10% caería en rojo con el libro sano); el 51 recomputa el EV con esas anclas. Se ELIMINARON los términos que la verificación probó redundantes (52 ≡ checks 14+15; 53 término 1 ≡ 17+18; 51 término 1 ≡ 0; 54 término 1 ≡ 0): lo que caza son las bandas y las anclas, no la "reconstrucción". (2) Bandas realistas: acciones de ±10% a ±3% (los buybacks retiran ~3%/año; 15,300 ahora cae en FAIL), precio de ±50% a ±25% (un error de precio dentro de banda es indetectable sin feed vivo — declarado). (3) Frescura ABSOLUTA: B92 suma un término contra HOY()−10; un paquete uniformemente obsoleto (las cuatro fechas en enero) ahora cae en FAIL. (4) El 54 conserva las bandas y gana la guardia del enlace vivo de la tasa efectiva (B37 tecleada en duro cae). (5) Notas de honestidad reescritas (Drivers_MDA A150:A155, checks 51 a 61): el mérito es de las bandas, las anclas de vintage distinto y los ties de suma; lo indetectable queda declarado, no tapado. (6) Tildes corregidas en las 26 celdas señaladas por la verificación. (7) Gate_9of10!F17: nota de que B16/B17 son decorativos (C5:C14 son constantes). Ninguna hoja histórica se tocó | D17: 10-Q Q3 FY2026, balance condensado R4 (EDGAR, accn 0000320193-26-000020); informe de la segunda verificación 2026-08-14; pruebas con defectos plantados sobre copia en scratchpad (tabla en el informe de la ronda 3) | E17: 6adb623eaa77a910e8ed018f057c338e01f2554721f777c5bc3fe3ce53763869 | F17: Claude (ronda 3, segunda verificación) | G17: Instrumento re-probado: los defectos originales siguen cayendo, acciones 15,300 y fechas de enero ahora caen, libro sano 100% PASS

Sheet Gate_9of10
A1: Apple Inc. — Gate 9/10 Owner Submission
A2: Independent review is a separate role; this sheet does not self-certify the workbook
A4: Gate | B4: Weight | C4: Owner status | D4: Blocker class | E4: Exact evidence range | F4: Native / visual evidence | G4: Independent action | H4: Notes
A5: H0 Controlled lineage / package | B5: 5 | C5: PASS | D5: None identified | E5: Change_Log!A4:G8; final .xlsx | F5: Prior hash preserved; OOXML integrity PASS 2026-07-17T02:36:50.230Z | G5: Reproduce lineage and package test | H5: Final JSON carries prior and final hashes
A6: H1 Source fidelity | B6: 20 | C6: PASS | D6: None identified | E6: Sources!A4:V500 | F6: SEC target-cell ledger + formula completeness | G6: Sample and reproduce ledger mappings | H6: Every populated hardcoded historical/driver cell mapped
A7: H2 Historical / formula / schedule mechanics | B7: 15 | C7: PASS | D7: None identified | E7: Historical!A4:F26; Forecast!A4:G30 | F7: Five-year historicals and formula-driven operating build | G7: Reperform historical and forecast ties | H7: Reported values preserved; forecast cells formula-driven
A8: H3 Scenario / sensitivity | B8: 10 | C8: PASS | D8: None identified | E8: Assumptions!A3:G30; Sensitivity!A4:G14 | F8: Base/Bull/Bear selector + dynamic DCF sensitivity | G8: Perturb selector 1/2/3 and reset to 1 | H8: Evidence JSON records exact outputs
A9: H4 Valuation fit / mechanics | B9: 15 | C9: PASS | D9: None identified | E9: Valuation!A4:G21; Historical!A17:F26 | F9: FCFF, bridge and per-share DCF | G9: Reperform DCF and balance-sheet bridge | H9: Debt/liquid asset/share policies explicit
A10: H5 Checks / error state | B10: 8 | C10: PASS | D10: None identified | E10: Checks!A4:G14 | F10: Formula-driven checks OK and zero formula-error matches 2026-07-17T02:33:53.917Z | G10: Reproduce checks and formula-error scan | H10: Final scan repeated after gate promotion
A11: H6 Native recalc / reproducibility | B11: 10 | C11: PASS | D11: None identified | E11: Checks!A4:G14 | F11: LibreOfficeDev 26.8.0.0.alpha0 2c87e51eeaa2b413ff4ae097b2705eea1995d8e5; save/reopen completed 2026-07-17T02:33:53.917Z | G11: Reopen and reproduce in native engine | H11: Final recalc repeated after gate promotion; evidence JSON carries hashes
A12: H7 Post-recalc all-sheet visual QA | B12: 7 | C12: PASS | D12: None identified | E12: internal QA evidence (not published) | F12: All 11 sheets rendered in preflight 2026-07-17T02:33:53.917Z; final render repeated after promotion | G12: Inspect preview manifest | H12: Final JSON carries per-sheet manifest
A13: H8 Material economic upgrade | B13: 5 | C13: PASS | D13: None identified | E13: Sector_KPIs!A4:G40; Assumptions!A6:G30; Forecast!A4:G30 | F13: Company-specific driver and margin build | G13: Challenge economic usefulness | H13: No relabel-only sector shell
A14: H9 Governance / limitations / handoff | B14: 5 | C14: PASS | D14: None identified | E14: Change_Log!A4:G8; Gate_9of10!A4:H26 | F14: Owner/reviewer separation and limitations explicit | G14: Assign independent reviewer | H14: No self-certification; evidence JSON is handoff surface
A16: Owner score | B16: =SUMIF(C5:C14,"PASS",B5:B14) -> 100
A17: Decision | B17: =IF(B16=100,"OWNER READY — INDEPENDENT REVIEW REQUIRED","PENDING OWNER QA") -> OWNER READY — INDEPENDENT REVIEW REQUIRED | F17: NOTA (2026-08-14, ronda 3): B16 y B17 son decorativos — C5:C14 son constantes "PASS" tecleadas, así que el puntaje del owner siempre da 100 y esta decisión nunca cambia sola; en 14 defectos plantados no se movió. La única señal viva de esta hoja es B18 (=Checks!F15). No citar B16/B17 como evidencia de salud. Preexistente: se declara y no se corrige para no tocar un output ya gateado
A18: Overall model status | B18: =Checks!F15 -> REVIEW
A20: Native recalculation / review metadata
A21: Build timestamp UTC | B21: Build 2026-07-17T02:33:12.208Z
A22: Required native engine | B22: LibreOfficeDev 26.8.0.0.alpha0 2c87e51eeaa2b413ff4ae097b2705eea1995d8e5
A23: Final native timestamp | B23: Native preflight 2026-07-17T02:33:53.917Z; final recalc after promotion 2026-07-17T02:36:51.597Z
A24: Visual manifest | B24: internal QA evidence (not published)
A25: Evidence manifest | B25: internal QA evidence (not published)
A26: Independent certification | B26: Not performed by owner-preparer

Sheet IS_Hist
A1: Apple Inc. — Consolidated Statements of Operations (audited, published constants)
A2: USD millions except per-share data and share counts (thousands). FY2021 per FY2021 10-K; FY2022-24 per FY2024 10-K; FY2025 per FY2025 10-K.
A4: Line item | B4: FY2021A | C4: FY2022A | D4: FY2023A | E4: FY2024A | F4: FY2025A | G4: Note ref
A5: Net sales — Products | C5: 316199 | D5: 298085 | E5: 294866 | F5: 307003 | G5: Segment; Rev
A6: Net sales — Services | C6: 78129 | D6: 85200 | E6: 96169 | F6: 109158 | G6: Segment; Rev
A7: Total net sales | B7: 365817 | C7: 394328 | D7: 383285 | E7: 391035 | F7: 416161 | G7: Rev
A8: Cost of sales — Products | C8: 201471 | D8: 189282 | E8: 185233 | F8: 194116 | G8: Segment; Rev
A9: Cost of sales — Services | C9: 22075 | D9: 24855 | E9: 25119 | F9: 26844 | G9: Segment; Rev
A10: Total cost of sales | B10: 212981 | C10: 223546 | D10: 214137 | E10: 210352 | F10: 220960 | G10: IS
A11: Gross margin | B11: 152836 | C11: 170782 | D11: 169148 | E11: 180683 | F11: 195201 | G11: IS
A12: Operating expenses
A13: Research and development | B13: 21914 | C13: 26251 | D13: 29915 | E13: 31370 | F13: 34550 | G13: IS
A14: Selling, general and administrative | B14: 21973 | C14: 25094 | D14: 24932 | E14: 26097 | F14: 27601 | G14: IS
A15: Total operating expenses | B15: 43887 | C15: 51345 | D15: 54847 | E15: 57467 | F15: 62151 | G15: IS
A16: Operating income | B16: 108949 | C16: 119437 | D16: 114301 | E16: 123216 | F16: 133050 | G16: IS
A17: Other income/(expense), net | B17: 258 | C17: -334 | D17: -565 | E17: 269 | F17: -321 | G17: IS
A18: Income before provision for income taxes | B18: 109207 | C18: 119103 | D18: 113736 | E18: 123485 | F18: 132729 | G18: IS
A19: Provision for income taxes | B19: 14527 | C19: 19300 | D19: 16741 | E19: 29749 | F19: 20719 | G19: IS
A20: Net income | B20: 94680 | C20: 99803 | D20: 96995 | E20: 93736 | F20: 112010 | G20: IS
A22: Basic EPS ($/sh) | B22: 5.67 | C22: 6.15 | D22: 6.16 | E22: 6.11 | F22: 7.49 | G22: IS
A23: Diluted EPS ($/sh) | B23: 5.61 | C23: 6.11 | D23: 6.13 | E23: 6.08 | F23: 7.46 | G23: IS
A24: Basic weighted-avg shares (000) | B24: 16701272 | C24: 16215963 | D24: 15744231 | E24: 15343783 | F24: 14948500 | G24: IS
A25: Diluted weighted-avg shares (000) | B25: 16864919 | C25: 16325819 | D25: 15812547 | E25: 15408095 | F25: 15004697 | G25: IS

Sheet CI_Hist
A1: Apple Inc. — Consolidated Statements of Comprehensive Income (audited)
A2: USD millions. FY2021 OCI detail not broken out in this source package (net income only); FY2022-25 per FY2024/FY2025 10-Ks.
A4: Line item | B4: FY2021A | C4: FY2022A | D4: FY2023A | E4: FY2024A | F4: FY2025A | G4: Note ref
A5: Net income | B5: 94680 | C5: 99803 | D5: 96995 | E5: 93736 | F5: 112010
A6: Change in foreign currency translation, net of tax | C6: -1511 | D6: -765 | E6: 395 | F6: -267
A7: Change in fair value of derivative instruments | C7: 3212 | D7: 323 | E7: -832 | F7: 849
A8: Adjustment for net (gains)/losses realized, derivatives | C8: -1074 | D8: -1717 | E8: -1337 | F8: 212
A9: Total unrealized gain/(loss) on derivatives | C9: 2138 | D9: -1394 | E9: -2169 | F9: 637
A10: Change in fair value of marketable debt securities | C10: -12104 | D10: 1563 | E10: 5850 | F10: 817
A11: Adjustment for net (gains)/losses realized, securities | C11: 205 | D11: 253 | E11: 204 | F11: 414
A12: Total unrealized gain/(loss) on marketable debt securities | C12: -11899 | D12: 1816 | E12: 6054 | F12: 1231
A13: Total other comprehensive income/(loss) | C13: -11272 | D13: -343 | E13: 4280 | F13: 1601
A14: Total comprehensive income | C14: 88531 | D14: 96652 | E14: 98016 | F14: 113611

Sheet BS_Hist
A1: Apple Inc. — Consolidated Balance Sheets (audited)
A2: USD millions, as of fiscal year-end (last Saturday of September). Same source basis as IS_Hist.
A4: Line item | B4: FY2021A | C4: FY2022A | D4: FY2023A | E4: FY2024A | F4: FY2025A | G4: Note ref
A5: Current assets
A6: Cash and cash equivalents | B6: 34940 | C6: 23646 | D6: 29965 | E6: 29943 | F6: 35934 | G6: BS
A7: Marketable securities (current) | B7: 27699 | C7: 24658 | D7: 31590 | E7: 35228 | F7: 18763 | G7: BS
A8: Accounts receivable, net | B8: 26278 | C8: 28184 | D8: 29508 | E8: 33410 | F8: 39777 | G8: BS
A9: Vendor non-trade receivables | B9: 25228 | C9: 32748 | D9: 31477 | E9: 32833 | F9: 33180 | G9: BS
A10: Inventories | B10: 6580 | C10: 4946 | D10: 6331 | E10: 7286 | F10: 5718 | G10: BS
A11: Other current assets | B11: 14111 | C11: 21223 | D11: 14695 | E11: 14287 | F11: 14585 | G11: BS
A12: Total current assets | B12: 134836 | C12: 135405 | D12: 143566 | E12: 152987 | F12: 147957 | G12: BS
A13: Non-current assets
A14: Marketable securities (non-current) | B14: 127877 | C14: 120805 | D14: 100544 | E14: 91479 | F14: 77723 | G14: BS
A15: Property, plant and equipment, net | B15: 39440 | C15: 42117 | D15: 43715 | E15: 45680 | F15: 49834 | G15: BS
A16: Other non-current assets | B16: 48849 | C16: 54428 | D16: 64758 | E16: 74834 | F16: 83727 | G16: BS
A17: Total non-current assets | B17: 216166 | C17: 217350 | D17: 209017 | E17: 211993 | F17: 211284 | G17: BS
A18: Total assets | B18: 351002 | C18: 352755 | D18: 352583 | E18: 364980 | F18: 359241 | G18: BS
A20: Current liabilities
A21: Accounts payable | B21: 54763 | C21: 64115 | D21: 62611 | E21: 68960 | F21: 69860 | G21: BS
A22: Other current liabilities | B22: 47493 | C22: 60845 | D22: 58829 | E22: 78304 | F22: 66387 | G22: BS
A23: Deferred revenue | B23: 7612 | C23: 7912 | D23: 8061 | E23: 8249 | F23: 9055 | G23: BS
A24: Commercial paper | B24: 6000 | C24: 9982 | D24: 5985 | E24: 9967 | F24: 7979 | G24: BS
A25: Term debt (current) | B25: 9613 | C25: 11128 | D25: 9822 | E25: 10912 | F25: 12350 | G25: BS
A26: Total current liabilities | B26: 125481 | C26: 153982 | D26: 145308 | E26: 176392 | F26: 165631 | G26: BS
A27: Non-current liabilities
A28: Term debt (non-current) | B28: 109106 | C28: 98959 | D28: 95281 | E28: 85750 | F28: 78328 | G28: BS
A29: Other non-current liabilities | B29: 53325 | C29: 49142 | D29: 49848 | E29: 45888 | F29: 41549 | G29: BS
A30: Total non-current liabilities | B30: 162431 | C30: 148101 | D30: 145129 | E30: 131638 | F30: 119877 | G30: BS
A31: Total liabilities | B31: 287912 | C31: 302083 | D31: 290437 | E31: 308030 | F31: 285508 | G31: BS
A33: Shareholders' equity
A34: Common stock and additional paid-in capital | B34: 57365 | C34: 64849 | D34: 73812 | E34: 83276 | F34: 93568 | G34: BS
A35: Retained earnings/(Accumulated deficit) | B35: 5562 | C35: -3068 | D35: -214 | E35: -19154 | F35: -14264 | G35: BS
A36: Accumulated other comprehensive income/(loss) | B36: 163 | C36: -11109 | D36: -11452 | E36: -7172 | F36: -5571 | G36: BS
A37: Total shareholders' equity | B37: 63090 | C37: 50672 | D37: 62146 | E37: 56950 | F37: 73733 | G37: BS
A38: Total liabilities and shareholders' equity | B38: 351002 | C38: 352755 | D38: 352583 | E38: 364980 | F38: 359241 | G38: BS
A40: Common shares outstanding, period-end (000) | B40: 16426786 | C40: 15943425 | D40: 15550061 | E40: 15116786 | F40: 14773260 | G40: BS

Sheet CF_Hist
A1: Apple Inc. — Consolidated Statements of Cash Flows (audited)
A2: USD millions. Same source basis as IS_Hist. Signs as published (outflows negative).
A4: Line item | B4: FY2021A | C4: FY2022A | D4: FY2023A | E4: FY2024A | F4: FY2025A | G4: Note ref
A5: Cash, cash equiv. and restricted cash, beginning balance | B5: 39789 | C5: 35929 | D5: 24977 | E5: 30737 | F5: 29943 | G5: CF
A6: Operating activities
A7: Net income | B7: 94680 | C7: 99803 | D7: 96995 | E7: 93736 | F7: 112010 | G7: CF
A8: Depreciation and amortization | B8: 11284 | C8: 11104 | D8: 11519 | E8: 11445 | F8: 11698 | G8: CF
A9: Share-based compensation expense | B9: 7906 | C9: 9038 | D9: 10833 | E9: 11688 | F9: 12863 | G9: CF
A10: Other (FY21: derived residual — see Sources_Audited) | B10: -3245 | C10: 1006 | D10: -2227 | E10: -2266 | F10: -89 | G10: CF*
A11: Changes in operating assets and liabilities
A12: Accounts receivable, net | B12: -10125 | C12: -1823 | D12: -1688 | E12: -3788 | F12: -6682 | G12: CF
A13: Vendor non-trade receivables | B13: -3903 | C13: -7520 | D13: 1271 | E13: -1356 | F13: -347 | G13: CF
A14: Inventories | B14: -2642 | C14: 1484 | D14: -1618 | E14: -1046 | F14: 1400 | G14: CF
A15: Other current and non-current assets | B15: -8042 | C15: -6499 | D15: -5684 | E15: -11731 | F15: -9197 | G15: CF
A16: Accounts payable | B16: 12326 | C16: 9448 | D16: -1889 | E16: 6020 | F16: 902 | G16: CF
A17: Other current and non-current liabilities | B17: 5799 | C17: 6110 | D17: 3031 | E17: 15552 | F17: -11076 | G17: CF
A18: Cash generated by operating activities | B18: 104038 | C18: 122151 | D18: 110543 | E18: 118254 | F18: 111482 | G18: CF
A19: Investing activities
A20: Purchases of marketable securities | B20: -109558 | C20: -76923 | D20: -29513 | E20: -48656 | F20: -24407 | G20: CF
A21: Proceeds from maturities of marketable securities | B21: 59023 | C21: 29917 | D21: 39686 | E21: 51211 | F21: 40907 | G21: CF
A22: Proceeds from sales of marketable securities | B22: 47460 | C22: 37446 | D22: 5828 | E22: 11135 | F22: 12890 | G22: CF
A23: Payments for acquisition of property, plant and equipment | B23: -11085 | C23: -10708 | D23: -10959 | E23: -9447 | F23: -12715 | G23: CF
A24: Other (investing) (FY21: derived residual — see Sources_Audited) | B24: -385 | C24: -2086 | D24: -1337 | E24: -1308 | F24: -1480 | G24: CF*
A25: Cash generated by/(used in) investing activities | B25: -14545 | C25: -22354 | D25: 3705 | E25: 2935 | F25: 15195 | G25: CF
A26: Financing activities
A27: Payments for taxes related to net share settlement of equity awards | B27: -6556 | C27: -6223 | D27: -5431 | E27: -5441 | F27: -5960 | G27: CF
A28: Payments for dividends and dividend equivalents | B28: -14467 | C28: -14841 | D28: -15025 | E28: -15234 | F28: -15421 | G28: CF
A29: Repurchases of common stock | B29: -85971 | C29: -89402 | D29: -77550 | E29: -94949 | F29: -90711 | G29: CF
A30: Proceeds from issuance of term debt, net | B30: 20393 | C30: 5465 | D30: 5228 | E30: 0 | F30: 4481 | G30: CF
A31: Repayments of term debt | B31: -8750 | C31: -9543 | D31: -11151 | E31: -9958 | F31: -10932 | G31: CF
A32: Proceeds from/(Repayments of) commercial paper, net | B32: 1022 | C32: 3955 | D32: -3978 | E32: 3960 | F32: -2032 | G32: CF
A33: Other (financing) (FY21: derived residual — see Sources_Audited) | B33: 976 | C33: -160 | D33: -581 | E33: -361 | F33: -111 | G33: CF*
A34: Cash used in financing activities | B34: -93353 | C34: -110749 | D34: -108488 | E34: -121983 | F34: -120686 | G34: CF
A35: Increase/(Decrease) in cash, cash equiv. and restricted cash | B35: -3860 | C35: -10952 | D35: 5760 | E35: -794 | F35: 5991 | G35: CF
A36: Cash, cash equiv. and restricted cash, ending balance | B36: 35929 | C36: 24977 | D36: 30737 | E36: 29943 | F36: 35934 | G36: CF
A38: Cash paid for income taxes, net (supplemental) | B38: 25385 | C38: 19573 | D38: 18679 | E38: 26102 | F38: 43369 | G38: CF

Sheet SCE_Hist
A1: Apple Inc. — Consolidated Statements of Shareholders' Equity (audited, roll-forward)
A2: USD millions. FY2021 roll-forward detail not in this source package (SCE statement for FY2021 not pulled); FY2021 shown as period-end snapshot only. FY2022-25 per FY2024/FY2025 10-Ks (SCE tab / R7).
A4: Line item | B4: FY2021A | C4: FY2022A | D4: FY2023A | E4: FY2024A | F4: FY2025A | G4: Note ref
A5: Beginning balance (start of FY) | C5: 63090 | D5: 50672 | E5: 62146 | F5: 56950
A6: Common stock issued | C6: 1175 | D6: 1346 | E6: 1423 | F6: 1498
A7: Common stock withheld, net share settlement — APIC | C7: -2971 | D7: -3521 | E7: -3993 | F7: -4452
A8: Common stock withheld, net share settlement — Retained earnings | C8: -3454 | D8: -2099 | E8: -1612 | F8: -1655
A9: Share-based compensation (APIC) | C9: 9280 | D9: 11138 | E9: 12034 | F9: 13246
A10: Net income | B10: 94680 | C10: 99803 | D10: 96995 | E10: 93736 | F10: 112010
A11: Dividends and dividend equivalents declared | C11: -14793 | D11: -14996 | E11: -15218 | F11: -15413
A12: Common stock repurchased (retained earnings) | C12: -90186 | D12: -77046 | E12: -95846 | F12: -90052
A13: Other comprehensive income/(loss) | C13: -11272 | D13: -343 | E13: 4280 | F13: 1601
A14: Ending balance (end of FY) | B14: 63090 | C14: 50672 | D14: 62146 | E14: 56950 | F14: 73733
A15: Ending balance (end of FY) | B15: 63090 | C15: 50672 | D15: 62146 | E15: 56950 | F15: 73733
A16: Dividend declared per share ($) | B16: 0.85 | C16: 0.9 | D16: 0.94 | E16: 0.98 | F16: 1.02
A17: Dividend declared per share ($) | B17: 0.85 | C17: 0.9 | D17: 0.94 | E17: 0.98 | F17: 1.02

Sheet Segment_Products
A1: Apple Inc. — Net sales and cost of sales by category (Products / Services)
A2: USD millions. Source: Revenue note, FY2024 10-K (FY22-24) and FY2025 10-K R3 (FY23-25). FY2021 category split not available in this source package.
A4: Metric | B4: FY2021A | C4: FY2022A | D4: FY2023A | E4: FY2024A | F4: FY2025A
A5: Products — Net sales | C5: 316199 | D5: 298085 | E5: 294866 | F5: 307003
A6: Products — Cost of sales | C6: 201471 | D6: 189282 | E6: 185233 | F6: 194116
A7: Products — Gross margin (calc) | B7: =IF(B5="","",B5-B6) | C7: =IF(C5="","",C5-C6) -> 114728 | D7: =IF(D5="","",D5-D6) -> 108803 | E7: =IF(E5="","",E5-E6) -> 109633 | F7: =IF(F5="","",F5-F6) -> 112887
A8: Services — Net sales | C8: 78129 | D8: 85200 | E8: 96169 | F8: 109158
A9: Services — Cost of sales | C9: 22075 | D9: 24855 | E9: 25119 | F9: 26844
A10: Services — Gross margin (calc) | B10: =IF(B8="","",B8-B9) | C10: =IF(C8="","",C8-C9) -> 56054 | D10: =IF(D8="","",D8-D9) -> 60345 | E10: =IF(E8="","",E8-E9) -> 71050 | F10: =IF(F8="","",F8-F9) -> 82314
A11: Products % of total net sales (calc) | B11: =IF(B5="","",B5/IS_Hist!B7) | C11: =IF(C5="","",C5/IS_Hist!C7) -> 0.80186799 | D11: =IF(D5="","",D5/IS_Hist!D7) -> 0.7777111 | E11: =IF(E5="","",E5/IS_Hist!E7) -> 0.75406549 | F11: =IF(F5="","",F5/IS_Hist!F7) -> 0.73770248
A12: Services % of total net sales (calc) | B12: =IF(B8="","",B8/IS_Hist!B7) | C12: =IF(C8="","",C8/IS_Hist!C7) -> 0.19813201 | D12: =IF(D8="","",D8/IS_Hist!D7) -> 0.2222889 | E12: =IF(E8="","",E8/IS_Hist!E7) -> 0.24593451 | F12: =IF(F8="","",F8/IS_Hist!F7) -> 0.26229752

Sheet Checks_TieOut
A1: Tie-out checks — Apple audited historical statements FY2021-FY2025 (USD millions; deltas must be 0, tol 0.5 abs except EPS tol 0.02)
A2: MASTER | B2: =IF(COUNTIF(H5:H61,"FAIL")=0,"OK — ALL TIE-OUTS PASS","FAIL") -> FAIL
A3: Conteo mecanizado | B3: =COUNTIF(H5:H61,"PASS")&" PASS / "&(COUNTIF(H5:H61,"PASS")+COUNTIF(H5:H61,"FAIL"))&" checks" -> 55 PASS / 56 checks
A4: Check | B4: FY2021A | C4: FY2022A | D4: FY2023A | E4: FY2024A | F4: FY2025A | H4: Status | I4: Applicable years
A5: IS: Total net sales = Products + Services | C5: =IS_Hist!C5+IS_Hist!C6-IS_Hist!C7 -> 0 | D5: =IS_Hist!D5+IS_Hist!D6-IS_Hist!D7 -> 0 | E5: =IS_Hist!E5+IS_Hist!E6-IS_Hist!E7 -> 0 | F5: =IS_Hist!F5+IS_Hist!F6-IS_Hist!F7 -> 0 | H5: =IF(AND(ABS(N(C5))<=0.5,ABS(N(D5))<=0.5,ABS(N(E5))<=0.5,ABS(N(F5))<=0.5),"PASS","FAIL") -> PASS | I5: C,D,E,F
A6: IS: Total COGS = Products + Services | C6: =IS_Hist!C8+IS_Hist!C9-IS_Hist!C10 -> 0 | D6: =IS_Hist!D8+IS_Hist!D9-IS_Hist!D10 -> 0 | E6: =IS_Hist!E8+IS_Hist!E9-IS_Hist!E10 -> 0 | F6: =IS_Hist!F8+IS_Hist!F9-IS_Hist!F10 -> 0 | H6: =IF(AND(ABS(N(C6))<=0.5,ABS(N(D6))<=0.5,ABS(N(E6))<=0.5,ABS(N(F6))<=0.5),"PASS","FAIL") -> PASS | I6: C,D,E,F
A7: IS: Gross margin = Sales − COGS | B7: =IS_Hist!B7-IS_Hist!B10-IS_Hist!B11 -> 0 | C7: =IS_Hist!C7-IS_Hist!C10-IS_Hist!C11 -> 0 | D7: =IS_Hist!D7-IS_Hist!D10-IS_Hist!D11 -> 0 | E7: =IS_Hist!E7-IS_Hist!E10-IS_Hist!E11 -> 0 | F7: =IS_Hist!F7-IS_Hist!F10-IS_Hist!F11 -> 0 | H7: =IF(AND(ABS(N(B7))<=0.5,ABS(N(C7))<=0.5,ABS(N(D7))<=0.5,ABS(N(E7))<=0.5,ABS(N(F7))<=0.5),"PASS","FAIL") -> PASS | I7: B,C,D,E,F
A8: IS: Total opex = R&D + SG&A | B8: =IS_Hist!B13+IS_Hist!B14-IS_Hist!B15 -> 0 | C8: =IS_Hist!C13+IS_Hist!C14-IS_Hist!C15 -> 0 | D8: =IS_Hist!D13+IS_Hist!D14-IS_Hist!D15 -> 0 | E8: =IS_Hist!E13+IS_Hist!E14-IS_Hist!E15 -> 0 | F8: =IS_Hist!F13+IS_Hist!F14-IS_Hist!F15 -> 0 | H8: =IF(AND(ABS(N(B8))<=0.5,ABS(N(C8))<=0.5,ABS(N(D8))<=0.5,ABS(N(E8))<=0.5,ABS(N(F8))<=0.5),"PASS","FAIL") -> PASS | I8: B,C,D,E,F
A9: IS: Operating income = Gross margin − Opex | B9: =IS_Hist!B11-IS_Hist!B15-IS_Hist!B16 -> 0 | C9: =IS_Hist!C11-IS_Hist!C15-IS_Hist!C16 -> 0 | D9: =IS_Hist!D11-IS_Hist!D15-IS_Hist!D16 -> 0 | E9: =IS_Hist!E11-IS_Hist!E15-IS_Hist!E16 -> 0 | F9: =IS_Hist!F11-IS_Hist!F15-IS_Hist!F16 -> 0 | H9: =IF(AND(ABS(N(B9))<=0.5,ABS(N(C9))<=0.5,ABS(N(D9))<=0.5,ABS(N(E9))<=0.5,ABS(N(F9))<=0.5),"PASS","FAIL") -> PASS | I9: B,C,D,E,F
A10: IS: PBT = Operating income + Other income/(expense) | B10: =IS_Hist!B16+IS_Hist!B17-IS_Hist!B18 -> 0 | C10: =IS_Hist!C16+IS_Hist!C17-IS_Hist!C18 -> 0 | D10: =IS_Hist!D16+IS_Hist!D17-IS_Hist!D18 -> 0 | E10: =IS_Hist!E16+IS_Hist!E17-IS_Hist!E18 -> 0 | F10: =IS_Hist!F16+IS_Hist!F17-IS_Hist!F18 -> 0 | H10: =IF(AND(ABS(N(B10))<=0.5,ABS(N(C10))<=0.5,ABS(N(D10))<=0.5,ABS(N(E10))<=0.5,ABS(N(F10))<=0.5),"PASS","FAIL") -> PASS | I10: B,C,D,E,F
A11: IS: NI = PBT − tax | B11: =IS_Hist!B18-IS_Hist!B19-IS_Hist!B20 -> 0 | C11: =IS_Hist!C18-IS_Hist!C19-IS_Hist!C20 -> 0 | D11: =IS_Hist!D18-IS_Hist!D19-IS_Hist!D20 -> 0 | E11: =IS_Hist!E18-IS_Hist!E19-IS_Hist!E20 -> 0 | F11: =IS_Hist!F18-IS_Hist!F19-IS_Hist!F20 -> 0 | H11: =IF(AND(ABS(N(B11))<=0.5,ABS(N(C11))<=0.5,ABS(N(D11))<=0.5,ABS(N(E11))<=0.5,ABS(N(F11))<=0.5),"PASS","FAIL") -> PASS | I11: B,C,D,E,F
A12: IS: Diluted EPS = NI / diluted shares (000mm-consistent, tol 0.02) | B12: =ROUND(IS_Hist!B20*1000/IS_Hist!B25,2)-IS_Hist!B23 -> 0 | C12: =ROUND(IS_Hist!C20*1000/IS_Hist!C25,2)-IS_Hist!C23 -> 0 | D12: =ROUND(IS_Hist!D20*1000/IS_Hist!D25,2)-IS_Hist!D23 -> 0 | E12: =ROUND(IS_Hist!E20*1000/IS_Hist!E25,2)-IS_Hist!E23 -> 0 | F12: =ROUND(IS_Hist!F20*1000/IS_Hist!F25,2)-IS_Hist!F23 -> 0 | H12: =IF(AND(ABS(N(B12))<=0.5,ABS(N(C12))<=0.5,ABS(N(D12))<=0.5,ABS(N(E12))<=0.5,ABS(N(F12))<=0.5),"PASS","FAIL") -> PASS | I12: B,C,D,E,F
A13: CI: TCI = NI + OCI | C13: =CI_Hist!C5+CI_Hist!C13-CI_Hist!C14 -> 0 | D13: =CI_Hist!D5+CI_Hist!D13-CI_Hist!D14 -> 0 | E13: =CI_Hist!E5+CI_Hist!E13-CI_Hist!E14 -> 0 | F13: =CI_Hist!F5+CI_Hist!F13-CI_Hist!F14 -> 0 | H13: =IF(AND(ABS(N(C13))<=0.5,ABS(N(D13))<=0.5,ABS(N(E13))<=0.5,ABS(N(F13))<=0.5),"PASS","FAIL") -> PASS | I13: C,D,E,F
A14: BS: Total current assets = sum of components | B14: =SUM(BS_Hist!B6:B11)-BS_Hist!B12 -> 0 | C14: =SUM(BS_Hist!C6:C11)-BS_Hist!C12 -> 0 | D14: =SUM(BS_Hist!D6:D11)-BS_Hist!D12 -> 0 | E14: =SUM(BS_Hist!E6:E11)-BS_Hist!E12 -> 0 | F14: =SUM(BS_Hist!F6:F11)-BS_Hist!F12 -> 0 | H14: =IF(AND(ABS(N(B14))<=0.5,ABS(N(C14))<=0.5,ABS(N(D14))<=0.5,ABS(N(E14))<=0.5,ABS(N(F14))<=0.5),"PASS","FAIL") -> PASS | I14: B,C,D,E,F
A15: BS: Total non-current assets = sum of components | B15: =SUM(BS_Hist!B14:B16)-BS_Hist!B17 -> 0 | C15: =SUM(BS_Hist!C14:C16)-BS_Hist!C17 -> 0 | D15: =SUM(BS_Hist!D14:D16)-BS_Hist!D17 -> 0 | E15: =SUM(BS_Hist!E14:E16)-BS_Hist!E17 -> 0 | F15: =SUM(BS_Hist!F14:F16)-BS_Hist!F17 -> 0 | H15: =IF(AND(ABS(N(B15))<=0.5,ABS(N(C15))<=0.5,ABS(N(D15))<=0.5,ABS(N(E15))<=0.5,ABS(N(F15))<=0.5),"PASS","FAIL") -> PASS | I15: B,C,D,E,F
A16: BS: Total assets = CA + NCA | B16: =BS_Hist!B12+BS_Hist!B17-BS_Hist!B18 -> 0 | C16: =BS_Hist!C12+BS_Hist!C17-BS_Hist!C18 -> 0 | D16: =BS_Hist!D12+BS_Hist!D17-BS_Hist!D18 -> 0 | E16: =BS_Hist!E12+BS_Hist!E17-BS_Hist!E18 -> 0 | F16: =BS_Hist!F12+BS_Hist!F17-BS_Hist!F18 -> 0 | H16: =IF(AND(ABS(N(B16))<=0.5,ABS(N(C16))<=0.5,ABS(N(D16))<=0.5,ABS(N(E16))<=0.5,ABS(N(F16))<=0.5),"PASS","FAIL") -> PASS | I16: B,C,D,E,F
A17: BS: Total current liabilities = sum of components | B17: =SUM(BS_Hist!B21:B25)-BS_Hist!B26 -> 0 | C17: =SUM(BS_Hist!C21:C25)-BS_Hist!C26 -> 0 | D17: =SUM(BS_Hist!D21:D25)-BS_Hist!D26 -> 0 | E17: =SUM(BS_Hist!E21:E25)-BS_Hist!E26 -> 0 | F17: =SUM(BS_Hist!F21:F25)-BS_Hist!F26 -> 0 | H17: =IF(AND(ABS(N(B17))<=0.5,ABS(N(C17))<=0.5,ABS(N(D17))<=0.5,ABS(N(E17))<=0.5,ABS(N(F17))<=0.5),"PASS","FAIL") -> PASS | I17: B,C,D,E,F
A18: BS: Total non-current liabilities = sum of components | B18: =SUM(BS_Hist!B28:B29)-BS_Hist!B30 -> 0 | C18: =SUM(BS_Hist!C28:C29)-BS_Hist!C30 -> 0 | D18: =SUM(BS_Hist!D28:D29)-BS_Hist!D30 -> 0 | E18: =SUM(BS_Hist!E28:E29)-BS_Hist!E30 -> 0 | F18: =SUM(BS_Hist!F28:F29)-BS_Hist!F30 -> 0 | H18: =IF(AND(ABS(N(B18))<=0.5,ABS(N(C18))<=0.5,ABS(N(D18))<=0.5,ABS(N(E18))<=0.5,ABS(N(F18))<=0.5),"PASS","FAIL") -> PASS | I18: B,C,D,E,F
A19: BS: Total liabilities = CL + NCL | B19: =BS_Hist!B26+BS_Hist!B30-BS_Hist!B31 -> 0 | C19: =BS_Hist!C26+BS_Hist!C30-BS_Hist!C31 -> 0 | D19: =BS_Hist!D26+BS_Hist!D30-BS_Hist!D31 -> 0 | E19: =BS_Hist!E26+BS_Hist!E30-BS_Hist!E31 -> 0 | F19: =BS_Hist!F26+BS_Hist!F30-BS_Hist!F31 -> 0 | H19: =IF(AND(ABS(N(B19))<=0.5,ABS(N(C19))<=0.5,ABS(N(D19))<=0.5,ABS(N(E19))<=0.5,ABS(N(F19))<=0.5),"PASS","FAIL") -> PASS | I19: B,C,D,E,F
A20: BS: Total equity = sum of components | B20: =SUM(BS_Hist!B34:B36)-BS_Hist!B37 -> 0 | C20: =SUM(BS_Hist!C34:C36)-BS_Hist!C37 -> 0 | D20: =SUM(BS_Hist!D34:D36)-BS_Hist!D37 -> 0 | E20: =SUM(BS_Hist!E34:E36)-BS_Hist!E37 -> 0 | F20: =SUM(BS_Hist!F34:F36)-BS_Hist!F37 -> 0 | H20: =IF(AND(ABS(N(B20))<=0.5,ABS(N(C20))<=0.5,ABS(N(D20))<=0.5,ABS(N(E20))<=0.5,ABS(N(F20))<=0.5),"PASS","FAIL") -> PASS | I20: B,C,D,E,F
A21: BS: TL&E = TL + TE | B21: =BS_Hist!B31+BS_Hist!B37-BS_Hist!B38 -> 0 | C21: =BS_Hist!C31+BS_Hist!C37-BS_Hist!C38 -> 0 | D21: =BS_Hist!D31+BS_Hist!D37-BS_Hist!D38 -> 0 | E21: =BS_Hist!E31+BS_Hist!E37-BS_Hist!E38 -> 0 | F21: =BS_Hist!F31+BS_Hist!F37-BS_Hist!F38 -> 0 | H21: =IF(AND(ABS(N(B21))<=0.5,ABS(N(C21))<=0.5,ABS(N(D21))<=0.5,ABS(N(E21))<=0.5,ABS(N(F21))<=0.5),"PASS","FAIL") -> PASS | I21: B,C,D,E,F
A22: BS: Balance (TA − TL&E) | B22: =BS_Hist!B18-BS_Hist!B38 -> 0 | C22: =BS_Hist!C18-BS_Hist!C38 -> 0 | D22: =BS_Hist!D18-BS_Hist!D38 -> 0 | E22: =BS_Hist!E18-BS_Hist!E38 -> 0 | F22: =BS_Hist!F18-BS_Hist!F38 -> 0 | H22: =IF(AND(ABS(N(B22))<=0.5,ABS(N(C22))<=0.5,ABS(N(D22))<=0.5,ABS(N(E22))<=0.5,ABS(N(F22))<=0.5),"PASS","FAIL") -> PASS | I22: B,C,D,E,F
A23: CF: CFO = NI + D&A + SBC + Other + WC changes | B23: =SUM(CF_Hist!B7:B17)-CF_Hist!B18 -> 0 | C23: =SUM(CF_Hist!C7:C17)-CF_Hist!C18 -> 0 | D23: =SUM(CF_Hist!D7:D17)-CF_Hist!D18 -> 0 | E23: =SUM(CF_Hist!E7:E17)-CF_Hist!E18 -> 0 | F23: =SUM(CF_Hist!F7:F17)-CF_Hist!F18 -> 0 | H23: =IF(AND(ABS(N(B23))<=0.5,ABS(N(C23))<=0.5,ABS(N(D23))<=0.5,ABS(N(E23))<=0.5,ABS(N(F23))<=0.5),"PASS","FAIL") -> PASS | I23: B,C,D,E,F
A24: CF: CFI = sum of investing lines | B24: =SUM(CF_Hist!B20:B24)-CF_Hist!B25 -> 0 | C24: =SUM(CF_Hist!C20:C24)-CF_Hist!C25 -> 0 | D24: =SUM(CF_Hist!D20:D24)-CF_Hist!D25 -> 0 | E24: =SUM(CF_Hist!E20:E24)-CF_Hist!E25 -> 0 | F24: =SUM(CF_Hist!F20:F24)-CF_Hist!F25 -> 0 | H24: =IF(AND(ABS(N(B24))<=0.5,ABS(N(C24))<=0.5,ABS(N(D24))<=0.5,ABS(N(E24))<=0.5,ABS(N(F24))<=0.5),"PASS","FAIL") -> PASS | I24: B,C,D,E,F
A25: CF: CFF = sum of financing lines | B25: =SUM(CF_Hist!B27:B29)+CF_Hist!B30+CF_Hist!B31+CF_Hist!B32+CF_Hist!B33-CF_Hist!B34 -> 0 | C25: =SUM(CF_Hist!C27:C29)+CF_Hist!C30+CF_Hist!C31+CF_Hist!C32+CF_Hist!C33-CF_Hist!C34 -> 0 | D25: =SUM(CF_Hist!D27:D29)+CF_Hist!D30+CF_Hist!D31+CF_Hist!D32+CF_Hist!D33-CF_Hist!D34 -> 0 | E25: =SUM(CF_Hist!E27:E29)+CF_Hist!E30+CF_Hist!E31+CF_Hist!E32+CF_Hist!E33-CF_Hist!E34 -> 0 | F25: =SUM(CF_Hist!F27:F29)+CF_Hist!F30+CF_Hist!F31+CF_Hist!F32+CF_Hist!F33-CF_Hist!F34 -> 0 | H25: =IF(AND(ABS(N(B25))<=0.5,ABS(N(C25))<=0.5,ABS(N(D25))<=0.5,ABS(N(E25))<=0.5,ABS(N(F25))<=0.5),"PASS","FAIL") -> PASS | I25: B,C,D,E,F
A26: CF: Net change = CFO + CFI + CFF | B26: =CF_Hist!B18+CF_Hist!B25+CF_Hist!B34-CF_Hist!B35 -> 0 | C26: =CF_Hist!C18+CF_Hist!C25+CF_Hist!C34-CF_Hist!C35 -> 0 | D26: =CF_Hist!D18+CF_Hist!D25+CF_Hist!D34-CF_Hist!D35 -> 0 | E26: =CF_Hist!E18+CF_Hist!E25+CF_Hist!E34-CF_Hist!E35 -> 0 | F26: =CF_Hist!F18+CF_Hist!F25+CF_Hist!F34-CF_Hist!F35 -> 0 | H26: =IF(AND(ABS(N(B26))<=0.5,ABS(N(C26))<=0.5,ABS(N(D26))<=0.5,ABS(N(E26))<=0.5,ABS(N(F26))<=0.5),"PASS","FAIL") -> PASS | I26: B,C,D,E,F
A27: CF: Ending cash = beginning + net change | B27: =CF_Hist!B5+CF_Hist!B35-CF_Hist!B36 -> 0 | C27: =CF_Hist!C5+CF_Hist!C35-CF_Hist!C36 -> 0 | D27: =CF_Hist!D5+CF_Hist!D35-CF_Hist!D36 -> 0 | E27: =CF_Hist!E5+CF_Hist!E35-CF_Hist!E36 -> 0 | F27: =CF_Hist!F5+CF_Hist!F35-CF_Hist!F36 -> 0 | H27: =IF(AND(ABS(N(B27))<=0.5,ABS(N(C27))<=0.5,ABS(N(D27))<=0.5,ABS(N(E27))<=0.5,ABS(N(F27))<=0.5),"PASS","FAIL") -> PASS | I27: B,C,D,E,F
A28: X: CF NI = IS NI | B28: =CF_Hist!B7-IS_Hist!B20 -> 0 | C28: =CF_Hist!C7-IS_Hist!C20 -> 0 | D28: =CF_Hist!D7-IS_Hist!D20 -> 0 | E28: =CF_Hist!E7-IS_Hist!E20 -> 0 | F28: =CF_Hist!F7-IS_Hist!F20 -> 0 | H28: =IF(AND(ABS(N(B28))<=0.5,ABS(N(C28))<=0.5,ABS(N(D28))<=0.5,ABS(N(E28))<=0.5,ABS(N(F28))<=0.5),"PASS","FAIL") -> PASS | I28: B,C,D,E,F
A29: SCE: Ending = Beginning + NI + issuance + withheld + SBC + div + buyback + OCI (FY22-25) | C29: =SCE_Hist!C5+SCE_Hist!C10+SCE_Hist!C6+SCE_Hist!C7+SCE_Hist!C8+SCE_Hist!C9+SCE_Hist!C11+SCE_Hist!C12+SCE_Hist!C13-SCE_Hist!C14 -> 0 | D29: =SCE_Hist!D5+SCE_Hist!D10+SCE_Hist!D6+SCE_Hist!D7+SCE_Hist!D8+SCE_Hist!D9+SCE_Hist!D11+SCE_Hist!D12+SCE_Hist!D13-SCE_Hist!D14 -> 0 | E29: =SCE_Hist!E5+SCE_Hist!E10+SCE_Hist!E6+SCE_Hist!E7+SCE_Hist!E8+SCE_Hist!E9+SCE_Hist!E11+SCE_Hist!E12+SCE_Hist!E13-SCE_Hist!E14 -> 0 | F29: =SCE_Hist!F5+SCE_Hist!F10+SCE_Hist!F6+SCE_Hist!F7+SCE_Hist!F8+SCE_Hist!F9+SCE_Hist!F11+SCE_Hist!F12+SCE_Hist!F13-SCE_Hist!F14 -> 0 | H29: =IF(AND(ABS(N(C29))<=0.5,ABS(N(D29))<=0.5,ABS(N(E29))<=0.5,ABS(N(F29))<=0.5),"PASS","FAIL") -> PASS | I29: C,D,E,F
A30: X: SCE ending equity = BS equity (all years) | B30: =SCE_Hist!B14-BS_Hist!B37 -> 0 | C30: =SCE_Hist!C14-BS_Hist!C37 -> 0 | D30: =SCE_Hist!D14-BS_Hist!D37 -> 0 | E30: =SCE_Hist!E14-BS_Hist!E37 -> 0 | F30: =SCE_Hist!F14-BS_Hist!F37 -> 0 | H30: =IF(AND(ABS(N(B30))<=0.5,ABS(N(C30))<=0.5,ABS(N(D30))<=0.5,ABS(N(E30))<=0.5,ABS(N(F30))<=0.5),"PASS","FAIL") -> PASS | I30: B,C,D,E,F
A31: SCE: Beginning FY2022A = Ending FY2021A | C31: =SCE_Hist!C5-SCE_Hist!B14 -> 0 | H31: =IF(AND(ABS(N(C31))<=0.5),"PASS","FAIL") -> PASS | I31: C
A32: SCE: Beginning FY2023A = Ending FY2022A | D32: =SCE_Hist!D5-SCE_Hist!C14 -> 0 | H32: =IF(AND(ABS(N(D32))<=0.5),"PASS","FAIL") -> PASS | I32: D
A33: SCE: Beginning FY2024A = Ending FY2023A | E33: =SCE_Hist!E5-SCE_Hist!D14 -> 0 | H33: =IF(AND(ABS(N(E33))<=0.5),"PASS","FAIL") -> PASS | I33: E
A34: SCE: Beginning FY2025A = Ending FY2024A | F34: =SCE_Hist!F5-SCE_Hist!E14 -> 0 | H34: =IF(AND(ABS(N(F34))<=0.5),"PASS","FAIL") -> PASS | I34: F
A35: CF: Beginning cash FY2022A = Ending cash FY2021A | C35: =CF_Hist!C5-CF_Hist!B36 -> 0 | H35: =IF(AND(ABS(N(C35))<=0.5),"PASS","FAIL") -> PASS | I35: C
A36: CF: Beginning cash FY2023A = Ending cash FY2022A | D36: =CF_Hist!D5-CF_Hist!C36 -> 0 | H36: =IF(AND(ABS(N(D36))<=0.5),"PASS","FAIL") -> PASS | I36: D
A37: CF: Beginning cash FY2024A = Ending cash FY2023A | E37: =CF_Hist!E5-CF_Hist!D36 -> 0 | H37: =IF(AND(ABS(N(E37))<=0.5),"PASS","FAIL") -> PASS | I37: E
A38: CF: Beginning cash FY2025A = Ending cash FY2024A | F38: =CF_Hist!F5-CF_Hist!E36 -> 0 | H38: =IF(AND(ABS(N(F38))<=0.5),"PASS","FAIL") -> PASS | I38: F
A39: COBERTURA — drivers de negocio (Drivers_MDA) y paquete de mercado (Market_Package), agregados 2026-08-14
A40: DRV: Ingresos por categoría de producto suman al total de ventas netas | B40: =Drivers_MDA!B13 -> 0 | C40: =Drivers_MDA!C13 -> 0 | D40: =Drivers_MDA!D13 -> 0 | E40: =Drivers_MDA!E13 -> 0 | F40: =Drivers_MDA!F13 -> 0 | H40: =IF(AND(ABS(N(B40))<=0.5,ABS(N(C40))<=0.5,ABS(N(D40))<=0.5,ABS(N(E40))<=0.5,ABS(N(F40))<=0.5),"PASS","FAIL") -> PASS | I40: B,C,D,E,F
A41: DRV: Ingresos por segmento reportable (geografía) suman al total de ventas netas | B41: =Drivers_MDA!B37 -> 0 | C41: =Drivers_MDA!C37 -> 0 | D41: =Drivers_MDA!D37 -> 0 | E41: =Drivers_MDA!E37 -> 0 | F41: =Drivers_MDA!F37 -> 0 | H41: =IF(AND(ABS(N(B41))<=0.5,ABS(N(C41))<=0.5,ABS(N(D41))<=0.5,ABS(N(E41))<=0.5,ABS(N(F41))<=0.5),"PASS","FAIL") -> PASS | I41: B,C,D,E,F
A42: DRV: Utilidad operativa de segmentos − R&D − gasto corporativo = utilidad operativa consolidada | B42: =Drivers_MDA!B63 -> 0 | C42: =Drivers_MDA!C63 -> 0 | D42: =Drivers_MDA!D63 -> 0 | E42: =Drivers_MDA!E63 -> 0 | F42: =Drivers_MDA!F63 -> 0 | H42: =IF(AND(ABS(N(B42))<=0.5,ABS(N(C42))<=0.5,ABS(N(D42))<=0.5,ABS(N(E42))<=0.5,ABS(N(F42))<=0.5),"PASS","FAIL") -> PASS | I42: B,C,D,E,F
A43: DRV: Products + Services (ventas netas) = total de ventas netas (FY2021 incluido) | B43: =Drivers_MDA!B76 -> 0 | C43: =Drivers_MDA!C76 -> 0 | D43: =Drivers_MDA!D76 -> 0 | E43: =Drivers_MDA!E76 -> 0 | F43: =Drivers_MDA!F76 -> 0 | H43: =IF(AND(ABS(N(B43))<=0.5,ABS(N(C43))<=0.5,ABS(N(D43))<=0.5,ABS(N(E43))<=0.5,ABS(N(F43))<=0.5),"PASS","FAIL") -> PASS | I43: B,C,D,E,F
A44: DRV: Products + Services (costo de ventas) = total costo de ventas | B44: =Drivers_MDA!B80 -> 0 | C44: =Drivers_MDA!C80 -> 0 | D44: =Drivers_MDA!D80 -> 0 | E44: =Drivers_MDA!E80 -> 0 | F44: =Drivers_MDA!F80 -> 0 | H44: =IF(AND(ABS(N(B44))<=0.5,ABS(N(C44))<=0.5,ABS(N(D44))<=0.5,ABS(N(E44))<=0.5,ABS(N(F44))<=0.5),"PASS","FAIL") -> PASS | I44: B,C,D,E,F
A45: DRV: Margen bruto Products + Services = margen bruto del estado de resultados | B45: =Drivers_MDA!B84 -> 0 | C45: =Drivers_MDA!C84 -> 0 | D45: =Drivers_MDA!D84 -> 0 | E45: =Drivers_MDA!E84 -> 0 | F45: =Drivers_MDA!F84 -> 0 | H45: =IF(AND(ABS(N(B45))<=0.5,ABS(N(C45))<=0.5,ABS(N(D45))<=0.5,ABS(N(E45))<=0.5,ABS(N(F45))<=0.5),"PASS","FAIL") -> PASS | I45: B,C,D,E,F
A46: DRV: Long-lived assets por país = PP&E neto del balance | B46: =Drivers_MDA!B105 -> 0 | C46: =Drivers_MDA!C105 -> 0 | D46: =Drivers_MDA!D105 -> 0 | E46: =Drivers_MDA!E105 -> 0 | F46: =Drivers_MDA!F105 -> 0 | H46: =IF(AND(ABS(N(B46))<=0.5,ABS(N(C46))<=0.5,ABS(N(D46))<=0.5,ABS(N(E46))<=0.5,ABS(N(F46))<=0.5),"PASS","FAIL") -> PASS | I46: B,C,D,E,F
A47: DRV: Ventas netas por país = total de ventas netas | B47: =Drivers_MDA!B110 -> 0 | C47: =Drivers_MDA!C110 -> 0 | D47: =Drivers_MDA!D110 -> 0 | E47: =Drivers_MDA!E110 -> 0 | F47: =Drivers_MDA!F110 -> 0 | H47: =IF(AND(ABS(N(B47))<=0.5,ABS(N(C47))<=0.5,ABS(N(D47))<=0.5,ABS(N(E47))<=0.5,ABS(N(F47))<=0.5),"PASS","FAIL") -> PASS | I47: B,C,D,E,F
A48: DRV: Drivers_MDA FY2022A-FY2025A coincide con Segment_Products (Products/Services, ventas y costo) | C48: =ABS(Drivers_MDA!C73-Segment_Products!C5)+ABS(Drivers_MDA!C74-Segment_Products!C8)+ABS(Drivers_MDA!C77-Segment_Products!C6)+ABS(Drivers_MDA!C78-Segment_Products!C9) -> 0 | D48: =ABS(Drivers_MDA!D73-Segment_Products!D5)+ABS(Drivers_MDA!D74-Segment_Products!D8)+ABS(Drivers_MDA!D77-Segment_Products!D6)+ABS(Drivers_MDA!D78-Segment_Products!D9) -> 0 | E48: =ABS(Drivers_MDA!E73-Segment_Products!E5)+ABS(Drivers_MDA!E74-Segment_Products!E8)+ABS(Drivers_MDA!E77-Segment_Products!E6)+ABS(Drivers_MDA!E78-Segment_Products!E9) -> 0 | F48: =ABS(Drivers_MDA!F73-Segment_Products!F5)+ABS(Drivers_MDA!F74-Segment_Products!F8)+ABS(Drivers_MDA!F77-Segment_Products!F6)+ABS(Drivers_MDA!F78-Segment_Products!F9) -> 0 | H48: =IF(AND(ABS(N(C48))<=0.5,ABS(N(D48))<=0.5,ABS(N(E48))<=0.5,ABS(N(F48))<=0.5),"PASS","FAIL") -> PASS | I48: C,D,E,F
A49: DRV: Sector_KPIs FY2023A-FY2025A coincide con Drivers_MDA por categoría de producto | D49: =ABS(Sector_KPIs!B5-Drivers_MDA!D7)+ABS(Sector_KPIs!B6-Drivers_MDA!D8)+ABS(Sector_KPIs!B7-Drivers_MDA!D9)+ABS(Sector_KPIs!B8-Drivers_MDA!D10)+ABS(Sector_KPIs!B9-Drivers_MDA!D11) -> 0 | E49: =ABS(Sector_KPIs!C5-Drivers_MDA!E7)+ABS(Sector_KPIs!C6-Drivers_MDA!E8)+ABS(Sector_KPIs!C7-Drivers_MDA!E9)+ABS(Sector_KPIs!C8-Drivers_MDA!E10)+ABS(Sector_KPIs!C9-Drivers_MDA!E11) -> 0 | F49: =ABS(Sector_KPIs!D5-Drivers_MDA!F7)+ABS(Sector_KPIs!D6-Drivers_MDA!F8)+ABS(Sector_KPIs!D7-Drivers_MDA!F9)+ABS(Sector_KPIs!D8-Drivers_MDA!F10)+ABS(Sector_KPIs!D9-Drivers_MDA!F11) -> 0 | H49: =IF(AND(ABS(N(D49))<=0.5,ABS(N(E49))<=0.5,ABS(N(F49))<=0.5),"PASS","FAIL") -> PASS | I49: D,E,F
A50: FCST: anclas FY2025A de Forecast!B5:B9 = Drivers_MDA FY2025A por categoría | F50: =ABS(Drivers_MDA!F136)+ABS(Drivers_MDA!F137)+ABS(Drivers_MDA!F138)+ABS(Drivers_MDA!F139)+ABS(Drivers_MDA!F140) -> 0 | H50: =IF(AND(ABS(N(F50))<=0.5),"PASS","FAIL") -> PASS | I50: F
A51: MKT: enterprise value contra un ancla de vintage DISTINTO — B23 debe coincidir exactamente con precio x acciones más la deuda y menos la caja de la columna comparativa del 10-Q Q3 FY2026 (Market_Package!B105 y B104, constantes tecleadas del filing, independientes de BS_Hist); además el EV debe ser positivo y quedar dentro de ±25% del EV construido con el precio fechado independiente de Valuation!G19. El término anterior de "reconstrucción desde insumos primarios" era algebraicamente idéntico a cero y se eliminó: lo que caza son el ancla y las bandas. F es el conteo de incumplimientos; 0 significa todos OK | F51: =IF(ABS(Market_Package!B23-(Market_Package!B7*Market_Package!B8+Market_Package!B105-Market_Package!B104))>0.5,1,0)+IF(Market_Package!B23<=0,1,0)+IF(ABS(Market_Package!B23/(Valuation!G19*Market_Package!B8+Market_Package!B105-Market_Package!B104)-1)>0.25,1,0) -> 0 | H51: =IF(N(F51)=0,"PASS","FAIL") -> PASS | I51: F
A52: MKT: efectivo e inversiones del paquete (B17, balance FY2025A) — tie EXACTO contra el ancla de vintage distinto (Market_Package!B104, caja al 2025-09-27 según la columna comparativa del 10-Q Q3 FY2026) y banda de ±15% contra la caja al 2026-06-27 (B82): la caja se mueve trimestre a trimestre y la deriva real observada es −9.6%. El término anterior de "reconstrucción desde subtotales" era algebraicamente idéntico a los checks 14 y 15 y se eliminó. F es el conteo de incumplimientos | F52: =IF(ABS(Market_Package!B17-Market_Package!B104)>0.5,1,0)+IF(ABS(Market_Package!B17/Market_Package!B82-1)>0.15,1,0) -> 0 | H52: =IF(N(F52)=0,"PASS","FAIL") -> PASS | I52: F
A53: MKT: deuda bruta del paquete (B21) — (1) la brecha contra la deuda que usa el DCF (Historical!F14, vía B24) debe ser exactamente el papel comercial derivado de los subtotales auditados: mecaniza el hallazgo H1; (2) tie EXACTO contra el ancla de vintage distinto (Market_Package!B105, deuda al 2025-09-27 según la columna comparativa del 10-Q Q3 FY2026); (3) banda de ±25% contra la deuda al 2026-06-27 (B83) — la deriva real FY2025A→Q3 FY2026 ya es +17.0% porque Apple retiró papel comercial y deuda a término, así que una banda más angosta caería en rojo con el libro sano; el control fino es el tie exacto del término 2. El término anterior de "reconstrucción desde subtotales" era algebraicamente idéntico a los checks 17 y 18 y se eliminó. F es el conteo de incumplimientos | F53: =IF(ABS(Market_Package!B21-Market_Package!B24-(BS_Hist!F26-BS_Hist!F21-BS_Hist!F22-BS_Hist!F23-BS_Hist!F25))>0.5,1,0)+IF(ABS(Market_Package!B21-Market_Package!B105)>0.5,1,0)+IF(ABS(Market_Package!B21/Market_Package!B83-1)>0.25,1,0) -> 0 | H53: =IF(N(F53)=0,"PASS","FAIL") -> PASS | I53: F
A54: MKT: costo de capital — guardia del enlace vivo de la tasa efectiva (B37 debe ser exactamente IS_Hist!F19/IS_Hist!F18: una tasa tecleada en duro cae) más BANDAS DE PLAUSIBILIDAD para Rf [0.5%, 12%], beta [0.3x, 2.5x], Kd [1%, 15%] y el WACC resultante [4%, 20%]. El término anterior de "reconstrucción del WACC" era algebraicamente idéntico a cero y se eliminó: lo que caza los defectos son las bandas, y una cifra plausible y equivocada dentro de banda pasa igual — limitación declarada. F es el conteo de incumplimientos | F54: =IF(ABS(Market_Package!B37-IS_Hist!F19/IS_Hist!F18)>0.0000001,1,0)+IF(OR(Market_Package!B30<0.005,Market_Package!B30>0.12),1,0)+IF(OR(Market_Package!B32<0.3,Market_Package!B32>2.5),1,0)+IF(OR(Market_Package!B34<0.01,Market_Package!B34>0.15),1,0)+IF(OR(Market_Package!B45<0.04,Market_Package!B45>0.2),1,0) -> 0 | H54: =IF(N(F54)=0,"PASS","FAIL") -> PASS | I54: F
A55: MKT: precio, acciones y capitalización — el cableado (B11 debe ser el producto de B7 por B8), el precio dentro de ±25% del precio fechado independiente de Valuation!G19, y el conteo de acciones dentro de ±3% del conteo auditado de BS_Hist!F40 (los buybacks de Apple retiran ~3% del float al año; una deriva mayor es señal de error, no de recompra). Un error de precio DENTRO de la banda de ±25% es indetectable sin un feed vivo de mercado — limitación declarada, no tapada. F es el conteo de incumplimientos | F55: =IF(ABS(Market_Package!B11-Market_Package!B7*Market_Package!B8)>0.5,1,0)+IF(ABS(Market_Package!B7/Valuation!G19-1)>0.25,1,0)+IF(ABS(Market_Package!B8/(BS_Hist!F40/1000)-1)>0.03,1,0) -> 0 | H55: =IF(N(F55)=0,"PASS","FAIL") -> PASS | I55: F
A56: MKT: procedencia de los inputs de mercado — fuente presente, FECHA presente y con serial válido, desfase relativo no mayor a 5 días entre los inputs de cotización diaria, y frescura ABSOLUTA: si la observación más reciente del paquete es anterior a HOY()−10 al recalcular, cae en FAIL. 0 significa completo | F56: =Market_Package!B89+Market_Package!B90+Market_Package!B92 -> 1 | H56: =IF(AND(ABS(N(F56))<=0),"PASS","FAIL") -> FAIL | I56: F
A57: MKT: activos líquidos del paquete = los usados hoy en el DCF (Historical!B18) | F57: =Market_Package!B27 -> 0 | H57: =IF(AND(ABS(N(F57))<=0.5),"PASS","FAIL") -> PASS | I57: F
A58: XREF: Assumptions!C12 y C13 (margen bruto Products y Services del escenario Base) coinciden EN VALOR con Drivers_MDA!F85 y F86; no están enlazadas por fórmula y este check es el único vínculo mecanizado entre ambas | F58: =ABS(Assumptions!C12-Drivers_MDA!F85)+ABS(Assumptions!C13-Drivers_MDA!F86) -> 0 | H58: =IF(AND(ABS(N(F58))<=0.0005),"PASS","FAIL") -> PASS | I58: F
A59: DRV: cruce por línea geográfica contra una fuente independiente — Greater China (segmento reportable, fila 33) contra China (país, fila 107; Apple define China incluyendo Hong Kong y Taiwán), exacto; y U.S. (país, fila 106) dentro del 75% al 95% de Americas (segmento, fila 31). Caza las permutaciones que tocan China o U.S.; cualquier otra (por ejemplo Europe con Japan, o una redistribución que conserve la suma) sigue pasando — límite declarado en Drivers_MDA!A154 | B59: =IF(ABS(Drivers_MDA!B33-Drivers_MDA!B107)>0.5,1,0)+IF(OR(Drivers_MDA!B106/Drivers_MDA!B31<0.75,Drivers_MDA!B106/Drivers_MDA!B31>0.95),1,0) -> 0 | C59: =IF(ABS(Drivers_MDA!C33-Drivers_MDA!C107)>0.5,1,0)+IF(OR(Drivers_MDA!C106/Drivers_MDA!C31<0.75,Drivers_MDA!C106/Drivers_MDA!C31>0.95),1,0) -> 0 | D59: =IF(ABS(Drivers_MDA!D33-Drivers_MDA!D107)>0.5,1,0)+IF(OR(Drivers_MDA!D106/Drivers_MDA!D31<0.75,Drivers_MDA!D106/Drivers_MDA!D31>0.95),1,0) -> 0 | E59: =IF(ABS(Drivers_MDA!E33-Drivers_MDA!E107)>0.5,1,0)+IF(OR(Drivers_MDA!E106/Drivers_MDA!E31<0.75,Drivers_MDA!E106/Drivers_MDA!E31>0.95),1,0) -> 0 | F59: =IF(ABS(Drivers_MDA!F33-Drivers_MDA!F107)>0.5,1,0)+IF(OR(Drivers_MDA!F106/Drivers_MDA!F31<0.75,Drivers_MDA!F106/Drivers_MDA!F31>0.95),1,0) -> 0 | H59: =IF(AND(N(B59)=0,N(C59)=0,N(D59)=0,N(E59)=0,N(F59)=0),"PASS","FAIL") -> PASS | I59: B,C,D,E,F
A60: DRV: márgenes brutos REPORTADOS (Drivers_MDA filas 85, 86 y 87) contra los calculados desde las cifras auditadas, con tolerancia 0.001 porque el filing los publica redondeados a 0.1pp. Mecaniza tres de las constantes que antes no tenían tie | B60: =IF(ABS(Drivers_MDA!B85-Drivers_MDA!B81/Drivers_MDA!B73)>0.001,1,0)+IF(ABS(Drivers_MDA!B86-Drivers_MDA!B82/Drivers_MDA!B74)>0.001,1,0)+IF(ABS(Drivers_MDA!B87-IS_Hist!B11/IS_Hist!B7)>0.001,1,0) -> 0 | C60: =IF(ABS(Drivers_MDA!C85-Drivers_MDA!C81/Drivers_MDA!C73)>0.001,1,0)+IF(ABS(Drivers_MDA!C86-Drivers_MDA!C82/Drivers_MDA!C74)>0.001,1,0)+IF(ABS(Drivers_MDA!C87-IS_Hist!C11/IS_Hist!C7)>0.001,1,0) -> 0 | D60: =IF(ABS(Drivers_MDA!D85-Drivers_MDA!D81/Drivers_MDA!D73)>0.001,1,0)+IF(ABS(Drivers_MDA!D86-Drivers_MDA!D82/Drivers_MDA!D74)>0.001,1,0)+IF(ABS(Drivers_MDA!D87-IS_Hist!D11/IS_Hist!D7)>0.001,1,0) -> 0 | E60: =IF(ABS(Drivers_MDA!E85-Drivers_MDA!E81/Drivers_MDA!E73)>0.001,1,0)+IF(ABS(Drivers_MDA!E86-Drivers_MDA!E82/Drivers_MDA!E74)>0.001,1,0)+IF(ABS(Drivers_MDA!E87-IS_Hist!E11/IS_Hist!E7)>0.001,1,0) -> 0 | F60: =IF(ABS(Drivers_MDA!F85-Drivers_MDA!F81/Drivers_MDA!F73)>0.001,1,0)+IF(ABS(Drivers_MDA!F86-Drivers_MDA!F82/Drivers_MDA!F74)>0.001,1,0)+IF(ABS(Drivers_MDA!F87-IS_Hist!F11/IS_Hist!F7)>0.001,1,0) -> 0 | H60: =IF(AND(N(B60)=0,N(C60)=0,N(D60)=0,N(E60)=0,N(F60)=0),"PASS","FAIL") -> PASS | I60: B,C,D,E,F
A61: DRV: BANDAS DE PLAUSIBILIDAD (esto NO es un tie) para las constantes sin tie mecanizado — empleados (fila 94), saldo de deferred revenue (96), reconocido del deferred revenue inicial (98), notionales FX (114 y 115), notional de tasa (118) y VAR FX (119). Caza un valor absurdo, pero NO verifica la cifra: una cifra plausible y equivocada pasa igual (probado: empleados +12.7% pasa). La verificación contra el filing sigue siendo manual | B61: =IF(OR(Drivers_MDA!B94<50000,Drivers_MDA!B94>500000),1,0)+IF(OR(Drivers_MDA!B96/Drivers_MDA!B12<0.005,Drivers_MDA!B96/Drivers_MDA!B12>0.1),1,0)+IF(OR(Drivers_MDA!B98/Drivers_MDA!B96<0.3,Drivers_MDA!B98/Drivers_MDA!B96>1),1,0)+IF(OR(Drivers_MDA!B114/Drivers_MDA!B12<0.05,Drivers_MDA!B114/Drivers_MDA!B12>1),1,0)+IF(OR(Drivers_MDA!B115/Drivers_MDA!B12<0.05,Drivers_MDA!B115/Drivers_MDA!B12>1),1,0)+IF(OR(Drivers_MDA!B118/Drivers_MDA!B12<0.005,Drivers_MDA!B118/Drivers_MDA!B12>0.2),1,0)+IF(OR(Drivers_MDA!B119<50,Drivers_MDA!B119>5000),1,0) -> 0 | C61: =IF(OR(Drivers_MDA!C94<50000,Drivers_MDA!C94>500000),1,0)+IF(OR(Drivers_MDA!C96/Drivers_MDA!C12<0.005,Drivers_MDA!C96/Drivers_MDA!C12>0.1),1,0)+IF(OR(Drivers_MDA!C98/Drivers_MDA!C96<0.3,Drivers_MDA!C98/Drivers_MDA!C96>1),1,0)+IF(OR(Drivers_MDA!C114/Drivers_MDA!C12<0.05,Drivers_MDA!C114/Drivers_MDA!C12>1),1,0)+IF(OR(Drivers_MDA!C115/Drivers_MDA!C12<0.05,Drivers_MDA!C115/Drivers_MDA!C12>1),1,0)+IF(OR(Drivers_MDA!C118/Drivers_MDA!C12<0.005,Drivers_MDA!C118/Drivers_MDA!C12>0.2),1,0)+IF(OR(Drivers_MDA!C119<50,Drivers_MDA!C119>5000),1,0) -> 0 | D61: =IF(OR(Drivers_MDA!D94<50000,Drivers_MDA!D94>500000),1,0)+IF(OR(Drivers_MDA!D96/Drivers_MDA!D12<0.005,Drivers_MDA!D96/Drivers_MDA!D12>0.1),1,0)+IF(OR(Drivers_MDA!D98/Drivers_MDA!D96<0.3,Drivers_MDA!D98/Drivers_MDA!D96>1),1,0)+IF(OR(Drivers_MDA!D114/Drivers_MDA!D12<0.05,Drivers_MDA!D114/Drivers_MDA!D12>1),1,0)+IF(OR(Drivers_MDA!D115/Drivers_MDA!D12<0.05,Drivers_MDA!D115/Drivers_MDA!D12>1),1,0)+IF(OR(Drivers_MDA!D118/Drivers_MDA!D12<0.005,Drivers_MDA!D118/Drivers_MDA!D12>0.2),1,0)+IF(OR(Drivers_MDA!D119<50,Drivers_MDA!D119>5000),1,0) -> 0 | E61: =IF(OR(Drivers_MDA!E94<50000,Drivers_MDA!E94>500000),1,0)+IF(OR(Drivers_MDA!E96/Drivers_MDA!E12<0.005,Drivers_MDA!E96/Drivers_MDA!E12>0.1),1,0)+IF(OR(Drivers_MDA!E98/Drivers_MDA!E96<0.3,Drivers_MDA!E98/Drivers_MDA!E96>1),1,0)+IF(OR(Drivers_MDA!E114/Drivers_MDA!E12<0.05,Drivers_MDA!E114/Drivers_MDA!E12>1),1,0)+IF(OR(Drivers_MDA!E115/Drivers_MDA!E12<0.05,Drivers_MDA!E115/Drivers_MDA!E12>1),1,0)+IF(OR(Drivers_MDA!E118/Drivers_MDA!E12<0.005,Drivers_MDA!E118/Drivers_MDA!E12>0.2),1,0)+IF(OR(Drivers_MDA!E119<50,Drivers_MDA!E119>5000),1,0) -> 0 | F61: =IF(OR(Drivers_MDA!F94<50000,Drivers_MDA!F94>500000),1,0)+IF(OR(Drivers_MDA!F96/Drivers_MDA!F12<0.005,Drivers_MDA!F96/Drivers_MDA!F12>0.1),1,0)+IF(OR(Drivers_MDA!F98/Drivers_MDA!F96<0.3,Drivers_MDA!F98/Drivers_MDA!F96>1),1,0)+IF(OR(Drivers_MDA!F114/Drivers_MDA!F12<0.05,Drivers_MDA!F114/Drivers_MDA!F12>1),1,0)+IF(OR(Drivers_MDA!F115/Drivers_MDA!F12<0.05,Drivers_MDA!F115/Drivers_MDA!F12>1),1,0)+IF(OR(Drivers_MDA!F118/Drivers_MDA!F12<0.005,Drivers_MDA!F118/Drivers_MDA!F12>0.2),1,0)+IF(OR(Drivers_MDA!F119<50,Drivers_MDA!F119>5000),1,0) -> 0 | H61: =IF(AND(N(B61)=0,N(C61)=0,N(D61)=0,N(E61)=0,N(F61)=0),"PASS","FAIL") -> PASS | I61: B,C,D,E,F

Sheet Sources_Audited
A1: Audited source register — Apple Inc. consolidated financial statements (SEC EDGAR, CIK 0000320193)
A3: Model year | B3: Primary filing (form / period / accession) | C3: R-file / evidence path | D3: XBRL tag basis (representative) | E3: Cross-check
A4: FY2021A | B4: 10-K FY ended 2021-09-25, filed 2021-10-29, accn 0000320193-21-000105 | C4: companyfacts.json (us-gaap tags, frame CY2021/FY2021, form=10-K, filed 2021-10-29) | D4: us-gaap:RevenueFromContractWithCustomerExcludingAssessedTax, :Assets, :StockholdersEquity, :NetCashProvidedByUsedInOperatingActivities, etc. | E4: BS balances (Assets=Liab+Equity) verified at extraction; CF detail verified vs NetCash*Activities aggregate tags
A5: FY2022A | B5: 10-K FY ended 2022-09-24, filed as comparative in 10-K FY2024 (accn 0000320193-24-000123); primary filing accn 0000320193-22-000108 | C5: 10-K_2024-09-28_Financial_Report.xlsx tabs: CONSOLIDATED STATEMENTS OF OPER/COMP/CASH, BALANCE SHEETS, SHAR (equity) | D5: Statement line items as tagged/rendered in FY2024 10-K R-report; matches companyfacts FY2022 duration/instant facts | E5: Cross-checked vs companyfacts.json FY2022 facts (accn 0000320193-22-000108) — all match to the dollar
A6: FY2023A | B6: 10-K FY ended 2023-09-30, filed as comparative in 10-K FY2024 (accn 0000320193-24-000123) and FY2025 (accn 0000320193-25-000079) | C6: 10-K_2024-09-28_Financial_Report.xlsx (primary) + 10-K_2025-09-27_Rfiles/R3-R8 (secondary confirmation) | D6: Statement line items; both filings agree to the dollar on FY2023 comparatives | E6: Cross-filing agreement FY2024 10-K vs FY2025 10-K confirmed for IS/BS/CF/SCE
A7: FY2024A | B7: 10-K FY ended 2024-09-28, filed 2024-11-01, accn 0000320193-24-000123 | C7: 10-K_2024-09-28_Financial_Report.xlsx tabs (primary); confirmed as FY2024 comparative in 10-K_2025-09-27_Rfiles/R3-R8 | D7: Statement line items as published | E7: Cross-filing agreement confirmed
A8: FY2025A | B8: 10-K FY ended 2025-09-27, filed 2025-10-31, accn 0000320193-25-000079 | C8: 10-K_2025-09-27_Rfiles/R3.htm (IS), R4.htm (CI), R5.htm (BS), R6.htm (BS parenthetical), R7.htm (SCE), R8.htm (CF) | D8: Statement line items as published; R-file HTML tables read via node HTML-table parse of the raw filing exhibit (read-only text extraction, not a spreadsheet tool) | E8: Matches companyfacts.json FY2025 duration/instant facts to the dollar
A10: Currency / units | B10: USD millions throughout (native reporting currency; no FX layer required per house policy — Apple reports in USD).
A11: Segment schedule | B11: Products/Services net sales + COGS: FY2021 split not available in this source package (not present in companyfacts default-dimension facts; would require member-dimensioned XBRL facts or the FY2021 10-K Revenue note, not included in this research package). FY2022-25 sourced as above.
A12: SCE FY2021 | B12: FY2021 equity roll-forward (issuance/buybacks/dividends during FY2021) not in this source package; only period-end snapshot shown for FY2021 in SCE_Hist. Gap — flagged in build report.
A13: Prior 9of10 skeleton (Historical/Sources/etc.) | B13: Left in place unmodified for reference; new statement-grade sheets (IS_Hist/CI_Hist/BS_Hist/CF_Hist/SCE_Hist/Segment_Products/Checks_TieOut/Sources_Audited/Source_Register) are additive. Gate_9of10 sheet not replicated/re-certified — self-certifying gate content ignored per instructions.
A14: CF FY2021 derived residual lines | B14: FY2021 operating "Other" (-3,245), investing "Other" (-385) and financing "Other" (976) are DERIVED PLUGS: each equals the directly-tagged FY2021 CFO/CFI/CFF subtotal (all sourced from accn 0000320193-21-000105) minus the sum of the other directly-tagged line items in that section. The FY2021 10-K’s own category detail within these residuals (e.g., deferred tax vs. other non-cash items) was not in this research package (no FY2021 Financial_Report.xlsx/R-files provided) and is not claimed as independently sourced.
A15: SCE FY2024/FY2025 buyback Total-column note | B15: Published SCE statements show a distinct smaller "Total" figure for "Common stock repurchased" in FY2024 (-95,000) and FY2025 (-89,300) vs. the retained-earnings component used here (-95,846 / -90,052) — a real, published difference (cash paid vs. cost recognized against retained earnings, e.g. unsettled repurchases), not decomposed further in this build. The retained-earnings column is what reconciles to total equity and is the value used in SCE_Hist.
A16: ACTUALIZACIÓN 2026-08-14 — brecha de A11 cerrada | B16: El split Products/Services de FY2021 SÍ es obtenible: está en el Estado Consolidado de Operaciones del 10-K FY2021 (accn 0000320193-21-000105): Products 297,392 / Services 68,425 de ventas netas; Products 192,266 / Services 20,715 de costo de ventas; y el margen bruto por linea (Products 105,126 / Services 47,710) está en Item 7 MD&A, 'Gross Margin'. Quedó cargado en Drivers_MDA filas 73-84 con tie duro contra IS_Hist. IS_Hist y Segment_Products NO se modificaron: la brecha se cierra en la capa de cobertura, no reescribiendo historia ya gateada.
A17: ACTUALIZACIÓN 2026-08-14 — capa de cobertura agregada | B17: Drivers_MDA y Market_Package son hojas nuevas, aditivas y no destructivas. Drivers_MDA solo contiene constantes publicadas (marcadas 'Reportado'), enlaces vivos a hojas históricas ('Enlace vivo') y cálculos ('Calculado'); todo lo que Apple no divulga queda marcado NOT_AVAILABLE con la razón, sin inventar ceros. Market_Package trae cada input de mercado con fuente y fecha propias y un control de procedencia mecanizado.

Sheet Source_Register
A1: Source_Register — Apple Inc. (CIK 0000320193)
A3: Item | B3: Type | C3: Accession / path | D3: Filed | E3: Coverage
A4: 10-K FY2021 | B4: SEC EDGAR filing (via companyfacts.json) | C4: 0000320193-21-000105 | D4: 44498 | E4: FY2021A IS/BS/CF
A5: 10-K FY2022 | B5: SEC EDGAR filing (via companyfacts.json cross-check) | C5: 0000320193-22-000108 | D5: 44862 | E5: FY2022A IS/BS/CF cross-check
A6: 10-K FY2023 | B6: SEC EDGAR filing (via companyfacts.json cross-check) | C6: 0000320193-23-000106 | D6: 45233 | E6: FY2023A IS/BS/CF cross-check
A7: 10-K FY2024 Financial_Report.xlsx | B7: EDGAR-generated statement workbook (research package) | C7: 0000320193-24-000123 | D7: 45597 | E7: FY2022A-FY2024A IS/CI/BS/CF/SCE primary source
A8: 10-K FY2025 R-files | B8: EDGAR R-report HTML exhibits (research package) | C8: 0000320193-25-000079 | D8: 45961 | E8: FY2023A-FY2025A IS/CI/BS/CF/SCE primary source (FY2025) + cross-check (FY2023-24)
A9: companyfacts.json | B9: SEC EDGAR companyfacts API dump (research package) | C9: n/a — API export | D9: 2026-07-20 (package pull date) | E9: FY2021A-FY2025A tag-level cross-checks; FY2021 primary source
A10: 10-Q FY2026 Q2 (Mar 28, 2026) | B10: SEC EDGAR filing (research package, not used in FY21-25 history) | C10: per submissions.json | D10: (package) | E10: Reserved for future interim update; not incorporated into this FY21-25A build
A11: 10-Q FY2026 Q3 (periodo terminado 2026-06-27) | B11: SEC EDGAR, descarga directa de R-files 2026-08-14 (no estaba en el paquete de investigación local, cuyo pull fue 2026-07-20) | C11: 0000320193-26-000020 | D11: 46234 | E11: Solo Market_Package: acciones en circulación al 2026-07-17 (portada), balance al 2026-06-27 (R4) y estado de operaciones 9M FY2026 (R2) para el memo LTM. NO entra en la historia auditada FY2021A-FY2025A.
A12: Datos de mercado fechados 2026-08-13 / 2026-08-14 | B12: Fuentes externas citadas una por una en Market_Package columna E (Tesoro de EE.UU., Damodaran/NYU Stern, stockanalysis.com, ICE BofA vía tradingeconomics) | C12: ver Market_Package!E7, E8, E30, E31, E32, E34 | D12: 2026-08-14 (fecha de recuperación) | E12: Precio de cierre, tasa libre de riesgo, prima de riesgo de mercado, beta y costo de deuda. Cada uno con su as-of propio; el control mecanizado está en Market_Package!B91 y en Checks_TieOut fila 56.
A13: 10-K FY2021 / FY2022 / FY2023 (PDF del filing, repositorio local) | B13: SEC EDGAR, PDF de los Form 10-K en 'AAPL Financial Statement/' (aapl-20210925 / 20220924 / 20230930) | C13: 0000320193-21-000105 / -22-000108 / -23-000106 | D13: 2021-10-29 / 2022-10-28 / 2023-11-03 | E13: Fuente primaria de los drivers FY2021A-FY2022A en Drivers_MDA (Item 7 MD&A y notas de segmentos/revenue), incluido el split Products/Services de FY2021 que Sources_Audited!A11 daba por no disponible.

Sheet Fwd_Assumptions
A1: Apple — Forecast drivers FY2026E-FY2030E (anchored to FY2025A base; USD millions except %)
A2: Scenario switch | B2: 2 | C2: 1=Bear, 2=Base, 3=Bull
A3: Scenario label | B3: =CHOOSE(B2,"Bear","Base","Bull") -> Base
A5: Driver | B5: Bear | C5: Base | D5: Bull | E5: Selected (per scenario switch)
A6: Revenue growth Y1 (FY26) | B6: 0.01 | C6: 0.05 | D6: 0.09 | E6: =CHOOSE($B$2,B6,C6,D6) -> 0.05
A7: Revenue growth Y2-Y5 (steady-state) | B7: 0.02 | C7: 0.06 | D7: 0.1 | E7: =CHOOSE($B$2,B7,C7,D7) -> 0.06
A8: Gross margin % | B8: 0.455 | C8: 0.47 | D8: 0.485 | E8: =CHOOSE($B$2,B8,C8,D8) -> 0.47
A9: R&D % of sales | B9: 0.085 | C9: 0.083 | D9: 0.08 | E9: =CHOOSE($B$2,B9,C9,D9) -> 0.083
A10: SG&A % of sales | B10: 0.068 | C10: 0.066 | D10: 0.064 | E10: =CHOOSE($B$2,B10,C10,D10) -> 0.066
A11: Effective tax rate | B11: 0.17 | C11: 0.16 | D11: 0.15 | E11: =CHOOSE($B$2,B11,C11,D11) -> 0.16
A12: Capex % of sales | B12: 0.032 | C12: 0.03 | D12: 0.028 | E12: =CHOOSE($B$2,B12,C12,D12) -> 0.03
A13: D&A % of sales | B13: 0.029 | C13: 0.028 | D13: 0.027 | E13: =CHOOSE($B$2,B13,C13,D13) -> 0.028
A14: SBC % of sales | B14: 0.032 | C14: 0.031 | D14: 0.03 | E14: =CHOOSE($B$2,B14,C14,D14) -> 0.031
A15: Net working capital change % of sales growth (use of cash if +) | B15: 0.01 | C15: 0.005 | D15: 0 | E15: =CHOOSE($B$2,B15,C15,D15) -> 0.005
A16: Dividend payout % of net income | B16: 0.16 | C16: 0.15 | D16: 0.14 | E16: =CHOOSE($B$2,B16,C16,D16) -> 0.15
A17: % of FCF after dividends used for buybacks | B17: 0.85 | C17: 0.95 | D17: 1 | E17: =CHOOSE($B$2,B17,C17,D17) -> 0.95

Sheet Fwd_IS
A1: Apple — Forecast Income Statement & simplified cash build, FY2026E-FY2030E
A2: USD millions. Driver-built off Fwd_Assumptions (scenario-selected column E). Anchored to FY2025A actuals in IS_Hist/CF_Hist. NOT a fully wired 3-statement forecast: no debt-maturity schedule, no share-price-based buyback share-count solve, no BS/CF forecast tabs (flagged PARTIAL in build report).
A4: Line item | B4: FY2026E | C4: FY2027E | D4: FY2028E | E4: FY2029E | F4: FY2030E
A5: Net sales | B5: =IS_Hist!$F$7*(1+B6) -> 436969.05 | C5: =B5*(1+C6) -> 463187.19 | D5: =C5*(1+D6) -> 490978.42 | E5: =D5*(1+E6) -> 520437.13 | F5: =E5*(1+F6) -> 551663.36
A6: Revenue growth % | B6: =Fwd_Assumptions!$E$6 -> 0.05 | C6: =Fwd_Assumptions!$E$7 -> 0.06 | D6: =Fwd_Assumptions!$E$7 -> 0.06 | E6: =Fwd_Assumptions!$E$7 -> 0.06 | F6: =Fwd_Assumptions!$E$7 -> 0.06
A7: Cost of sales | B7: =B5-B8 -> 231593.6 | C7: =C5-C8 -> 245489.21 | D7: =D5-D8 -> 260218.57 | E7: =E5-E8 -> 275831.68 | F7: =F5-F8 -> 292381.58
A8: Gross margin | B8: =B5*Fwd_Assumptions!$E$8 -> 205375.45 | C8: =C5*Fwd_Assumptions!$E$8 -> 217697.98 | D8: =D5*Fwd_Assumptions!$E$8 -> 230759.86 | E8: =E5*Fwd_Assumptions!$E$8 -> 244605.45 | F8: =F5*Fwd_Assumptions!$E$8 -> 259281.78
A9: Research and development | B9: =B5*Fwd_Assumptions!$E$9 -> 36268.431 | C9: =C5*Fwd_Assumptions!$E$9 -> 38444.537 | D9: =D5*Fwd_Assumptions!$E$9 -> 40751.209 | E9: =E5*Fwd_Assumptions!$E$9 -> 43196.282 | F9: =F5*Fwd_Assumptions!$E$9 -> 45788.059
A10: Selling, general and administrative | B10: =B5*Fwd_Assumptions!$E$10 -> 28839.957 | C10: =C5*Fwd_Assumptions!$E$10 -> 30570.355 | D10: =D5*Fwd_Assumptions!$E$10 -> 32404.576 | E10: =E5*Fwd_Assumptions!$E$10 -> 34348.851 | F10: =F5*Fwd_Assumptions!$E$10 -> 36409.782
A11: Operating income | B11: =B8-B9-B10 -> 140267.07 | C11: =C8-C9-C10 -> 148683.09 | D11: =D8-D9-D10 -> 157604.07 | E11: =E8-E9-E10 -> 167060.32 | F11: =F8-F9-F10 -> 177083.94
A12: Income before taxes (assume Other inc/exp = 0) | B12: =B11 -> 140267.07 | C12: =C11 -> 148683.09 | D12: =D11 -> 157604.07 | E12: =E11 -> 167060.32 | F12: =F11 -> 177083.94
A13: Provision for income taxes | B13: =B12*Fwd_Assumptions!$E$11 -> 22442.73 | C13: =C12*Fwd_Assumptions!$E$11 -> 23789.294 | D13: =D12*Fwd_Assumptions!$E$11 -> 25216.652 | E13: =E12*Fwd_Assumptions!$E$11 -> 26729.651 | F13: =F12*Fwd_Assumptions!$E$11 -> 28333.43
A14: Net income | B14: =B12-B13 -> 117824.33 | C14: =C12-C13 -> 124893.79 | D14: =D12-D13 -> 132387.42 | E14: =E12-E13 -> 140330.67 | F14: =F12-F13 -> 148750.51
A16: Depreciation and amortization | B16: =B5*Fwd_Assumptions!$E$13 -> 12235.133 | C16: =C5*Fwd_Assumptions!$E$13 -> 12969.241 | D16: =D5*Fwd_Assumptions!$E$13 -> 13747.396 | E16: =E5*Fwd_Assumptions!$E$13 -> 14572.24 | F16: =F5*Fwd_Assumptions!$E$13 -> 15446.574
A17: Capital expenditures | B17: =B5*Fwd_Assumptions!$E$12 -> 13109.072 | C17: =C5*Fwd_Assumptions!$E$12 -> 13895.616 | D17: =D5*Fwd_Assumptions!$E$12 -> 14729.353 | E17: =E5*Fwd_Assumptions!$E$12 -> 15613.114 | F17: =F5*Fwd_Assumptions!$E$12 -> 16549.901
A18: Share-based compensation | B18: =B5*Fwd_Assumptions!$E$14 -> 13546.041 | C18: =C5*Fwd_Assumptions!$E$14 -> 14358.803 | D18: =D5*Fwd_Assumptions!$E$14 -> 15220.331 | E18: =E5*Fwd_Assumptions!$E$14 -> 16133.551 | F18: =F5*Fwd_Assumptions!$E$14 -> 17101.564
A19: Change in net working capital (use of cash if +) | B19: =(B5-IS_Hist!$F$7)*Fwd_Assumptions!$E$15 -> 104.04025 | C19: =(C5-B5)*Fwd_Assumptions!$E$15 -> 131.09072 | D19: =(D5-C5)*Fwd_Assumptions!$E$15 -> 138.95616 | E19: =(E5-D5)*Fwd_Assumptions!$E$15 -> 147.29353 | F19: =(F5-E5)*Fwd_Assumptions!$E$15 -> 156.13114
A20: Cash from operating activities (simplified: NI+D&A+SBC-dWC) | B20: =B14+B16+B18-B19 -> 143501.47 | C20: =C14+C16+C18-C19 -> 152090.75 | D20: =D14+D16+D18-D19 -> 161216.19 | E20: =E14+E16+E18-E19 -> 170889.16 | F20: =F14+F16+F18-F19 -> 181142.51
A21: Free cash flow (CFO - capex) | B21: =B20-B17 -> 130392.4 | C21: =C20-C17 -> 138195.13 | D21: =D20-D17 -> 146486.84 | E21: =E20-E17 -> 155276.05 | F21: =F20-F17 -> 164592.61
A22: Dividends paid (payout % of NI) | B22: =B14*Fwd_Assumptions!$E$16 -> 17673.65 | C22: =C14*Fwd_Assumptions!$E$16 -> 18734.069 | D22: =D14*Fwd_Assumptions!$E$16 -> 19858.113 | E22: =E14*Fwd_Assumptions!$E$16 -> 21049.6 | F22: =F14*Fwd_Assumptions!$E$16 -> 22312.576
A23: FCF after dividends | B23: =B21-B22 -> 112718.75 | C23: =C21-C22 -> 119461.06 | D23: =D21-D22 -> 126628.73 | E23: =E21-E22 -> 134226.45 | F23: =F21-F22 -> 142280.04
A24: Share repurchases (assumed % of FCF-after-div) | B24: =B23*Fwd_Assumptions!$E$17 -> 107082.81 | C24: =C23*Fwd_Assumptions!$E$17 -> 113488.01 | D24: =D23*Fwd_Assumptions!$E$17 -> 120297.29 | E24: =E23*Fwd_Assumptions!$E$17 -> 127515.13 | F24: =F23*Fwd_Assumptions!$E$17 -> 135166.04
A25: Memo: cumulative buybacks+dividends vs FCF

Sheet Fwd_Summary
A1: Apple — Forecast summary (Base/Bull/Bear via Fwd_Assumptions!B2)
A2: Change Fwd_Assumptions!B2 (1/2/3) to flip scenario; all cells below recompute.
A4: Metric | B4: FY2026E | C4: FY2027E | D4: FY2028E | E4: FY2029E | F4: FY2030E
A5: Net sales | B5: =Fwd_IS!B5 -> 436969.05 | C5: =Fwd_IS!C5 -> 463187.19 | D5: =Fwd_IS!D5 -> 490978.42 | E5: =Fwd_IS!E5 -> 520437.13 | F5: =Fwd_IS!F5 -> 551663.36
A6: Revenue growth % | B6: =Fwd_IS!B6 -> 0.05 | C6: =Fwd_IS!C6 -> 0.06 | D6: =Fwd_IS!D6 -> 0.06 | E6: =Fwd_IS!E6 -> 0.06 | F6: =Fwd_IS!F6 -> 0.06
A7: Operating income | B7: =Fwd_IS!B11 -> 140267.07 | C7: =Fwd_IS!C11 -> 148683.09 | D7: =Fwd_IS!D11 -> 157604.07 | E7: =Fwd_IS!E11 -> 167060.32 | F7: =Fwd_IS!F11 -> 177083.94
A8: Net income | B8: =Fwd_IS!B14 -> 117824.33 | C8: =Fwd_IS!C14 -> 124893.79 | D8: =Fwd_IS!D14 -> 132387.42 | E8: =Fwd_IS!E14 -> 140330.67 | F8: =Fwd_IS!F14 -> 148750.51
A9: Free cash flow (CFO - capex) | B9: =Fwd_IS!B21 -> 130392.4 | C9: =Fwd_IS!C21 -> 138195.13 | D9: =Fwd_IS!D21 -> 146486.84 | E9: =Fwd_IS!E21 -> 155276.05 | F9: =Fwd_IS!F21 -> 164592.61
A10: Share repurchases (assumed % of FCF-after-div) | B10: =Fwd_IS!B24 -> 107082.81 | C10: =Fwd_IS!C24 -> 113488.01 | D10: =Fwd_IS!D24 -> 120297.29 | E10: =Fwd_IS!E24 -> 127515.13 | F10: =Fwd_IS!F24 -> 135166.04

Sheet Drivers_MDA
A1: Apple Inc. - Drivers de negocio del MD&A y disclosures (FY2021A-FY2025A)
A2: USD millones salvo indicación. CAPA DE COBERTURA ADITIVA: no altera ninguna hoja histórica. Todo dato 'Reportado' es una constante publicada; todo 'Calculado' es fórmula viva. Los 'Tie' deben ser 0.
A4: Métrica | B4: FY2021A | C4: FY2022A | D4: FY2023A | E4: FY2024A | F4: FY2025A | G4: Unidad | H4: Fuente (documento - sección - accession) | I4: Estado
A6: 1. VENTAS NETAS POR CATEGORÍA DE PRODUCTO
A7: iPhone | B7: 191973 | C7: 205489 | D7: 200583 | E7: 201183 | F7: 209586 | G7: USD m | H7: FY21-22: 10-K FY2023 (accn 0000320193-23-000106) - Item 7 MD&A, 'Products and Services Performance'; FY2021 también en 10-K FY2021 (0000320193-21-000105) | FY23-25: 10-K FY2025 (accn 0000320193-25-000079) - Item 7 MD&A 'Products and Services Performance' + Nota 2 'Revenue', R38.htm | I7: Reportado
A8: Mac | B8: 35190 | C8: 40177 | D8: 29357 | E8: 29984 | F8: 33708 | G8: USD m | H8: FY21-22: 10-K FY2023 (accn 0000320193-23-000106) - Item 7 MD&A, 'Products and Services Performance'; FY2021 también en 10-K FY2021 (0000320193-21-000105) | FY23-25: 10-K FY2025 (accn 0000320193-25-000079) - Item 7 MD&A 'Products and Services Performance' + Nota 2 'Revenue', R38.htm | I8: Reportado
A9: iPad | B9: 31862 | C9: 29292 | D9: 28300 | E9: 26694 | F9: 28023 | G9: USD m | H9: FY21-22: 10-K FY2023 (accn 0000320193-23-000106) - Item 7 MD&A, 'Products and Services Performance'; FY2021 también en 10-K FY2021 (0000320193-21-000105) | FY23-25: 10-K FY2025 (accn 0000320193-25-000079) - Item 7 MD&A 'Products and Services Performance' + Nota 2 'Revenue', R38.htm | I9: Reportado
A10: Wearables, Home and Accessories | B10: 38367 | C10: 41241 | D10: 39845 | E10: 37005 | F10: 35686 | G10: USD m | H10: FY21-22: 10-K FY2023 (accn 0000320193-23-000106) - Item 7 MD&A, 'Products and Services Performance'; FY2021 también en 10-K FY2021 (0000320193-21-000105) | FY23-25: 10-K FY2025 (accn 0000320193-25-000079) - Item 7 MD&A 'Products and Services Performance' + Nota 2 'Revenue', R38.htm | I10: Reportado
A11: Services | B11: 68425 | C11: 78129 | D11: 85200 | E11: 96169 | F11: 109158 | G11: USD m | H11: FY21-22: 10-K FY2023 (accn 0000320193-23-000106) - Item 7 MD&A, 'Products and Services Performance'; FY2021 también en 10-K FY2021 (0000320193-21-000105) | FY23-25: 10-K FY2025 (accn 0000320193-25-000079) - Item 7 MD&A 'Products and Services Performance' + Nota 2 'Revenue', R38.htm | I11: Reportado
A12: Total ventas netas por categoría (calc) | B12: =SUM(B7:B11) -> 365817 | C12: =SUM(C7:C11) -> 394328 | D12: =SUM(D7:D11) -> 383285 | E12: =SUM(E7:E11) -> 391035 | F12: =SUM(F7:F11) -> 416161 | G12: USD m | H12: Suma de las 5 categorías divulgadas | I12: Calculado
A13: Tie: categorías - IS_Hist total ventas netas | B13: =B12-IS_Hist!B7 -> 0 | C13: =C12-IS_Hist!C7 -> 0 | D13: =D12-IS_Hist!D7 -> 0 | E13: =E12-IS_Hist!E7 -> 0 | F13: =F12-IS_Hist!F7 -> 0 | G13: USD m | H13: IS_Hist!B7:F7 (estados auditados, sin modificar) | I13: Tie (debe ser 0)
A15: Mix por categoría (% de ventas netas)
A16: Mix - iPhone | B16: =B7/B$12 -> 0.52477878 | C16: =C7/C$12 -> 0.52111187 | D16: =D7/D$12 -> 0.52332598 | E16: =E7/E$12 -> 0.51448847 | F16: =F7/F$12 -> 0.50361759 | G16: % | H16: Calculado sobre el total por categoría | I16: Calculado
A17: Mix - Mac | B17: =B8/B$12 -> 0.096195639 | C17: =C8/C$12 -> 0.10188726 | D17: =D8/D$12 -> 0.076593136 | E17: =E8/E$12 -> 0.076678558 | F17: =F8/F$12 -> 0.080997499 | G17: % | H17: Calculado sobre el total por categoría | I17: Calculado
A18: Mix - iPad | B18: =B9/B$12 -> 0.087098194 | C18: =C9/C$12 -> 0.074283338 | D18: =D9/D$12 -> 0.073835397 | E18: =E9/E$12 -> 0.068264989 | F18: =F9/F$12 -> 0.06733692 | G18: % | H18: Calculado sobre el total por categoría | I18: Calculado
A19: Mix - Wearables, Home and Accessories | B19: =B10/B$12 -> 0.10488031 | C19: =C10/C$12 -> 0.10458552 | D19: =D10/D$12 -> 0.10395659 | E19: =E10/E$12 -> 0.094633473 | F19: =F10/F$12 -> 0.085750467 | G19: % | H19: Calculado sobre el total por categoría | I19: Calculado
A20: Mix - Services | B20: =B11/B$12 -> 0.18704708 | C20: =C11/C$12 -> 0.19813201 | D20: =D11/D$12 -> 0.2222889 | E20: =E11/E$12 -> 0.24593451 | F20: =F11/F$12 -> 0.26229752 | G20: % | H20: Calculado sobre el total por categoría | I20: Calculado
A22: Crecimiento interanual por categoría
A23: YoY - iPhone | B23: n.a. | C23: =C7/B7-1 -> 0.070405734 | D23: =D7/C7-1 -> -0.023874757 | E23: =E7/D7-1 -> 0.0029912804 | F23: =F7/E7-1 -> 0.041767943 | G23: % | H23: Calculado (FY2020 queda fuera de la ventana del modelo) | I23: Calculado
A24: YoY - Mac | B24: n.a. | C24: =C8/B8-1 -> 0.1417164 | D24: =D8/C8-1 -> -0.26930831 | E24: =E8/D8-1 -> 0.021357768 | F24: =F8/E8-1 -> 0.12419957 | G24: % | H24: Calculado (FY2020 queda fuera de la ventana del modelo) | I24: Calculado
A25: YoY - iPad | B25: n.a. | C25: =C9/B9-1 -> -0.080660348 | D25: =D9/C9-1 -> -0.033865902 | E25: =E9/D9-1 -> -0.056749117 | F25: =F9/E9-1 -> 0.049786469 | G25: % | H25: Calculado (FY2020 queda fuera de la ventana del modelo) | I25: Calculado
A26: YoY - Wearables, Home and Accessories | B26: n.a. | C26: =C10/B10-1 -> 0.074908124 | D26: =D10/C10-1 -> -0.03384981 | E26: =E10/D10-1 -> -0.071276195 | F26: =F10/E10-1 -> -0.035643832 | G26: % | H26: Calculado (FY2020 queda fuera de la ventana del modelo) | I26: Calculado
A27: YoY - Services | B27: n.a. | C27: =C11/B11-1 -> 0.14181951 | D27: =D11/C11-1 -> 0.090504166 | E27: =E11/D11-1 -> 0.12874413 | F27: =F11/E11-1 -> 0.13506431 | G27: % | H27: Calculado (FY2020 queda fuera de la ventana del modelo) | I27: Calculado
A28: YoY - Total ventas netas | B28: n.a. | C28: =C12/B12-1 -> 0.077937876 | D28: =D12/C12-1 -> -0.028004605 | E28: =E12/D12-1 -> 0.020219941 | F28: =F12/E12-1 -> 0.064255118 | G28: % | H28: Calculado | I28: Calculado
A30: 2. VENTAS NETAS POR SEGMENTO REPORTABLE (GEOGRAFÍA)
A31: Americas | B31: 153306 | C31: 169658 | D31: 162560 | E31: 167045 | F31: 178353 | G31: USD m | H31: FY21-22: 10-K FY2023 (0000320193-23-000106) - Item 7 MD&A 'Segment Operating Performance' + Nota 13 'Segment Information and Geographic Data' | FY23-25: 10-K FY2025 (0000320193-25-000079) - Item 7 MD&A 'Segment Operating Performance' + Nota 13, R68.htm | I31: Reportado
A32: Europe | B32: 89307 | C32: 95118 | D32: 94294 | E32: 101328 | F32: 111032 | G32: USD m | H32: FY21-22: 10-K FY2023 (0000320193-23-000106) - Item 7 MD&A 'Segment Operating Performance' + Nota 13 'Segment Information and Geographic Data' | FY23-25: 10-K FY2025 (0000320193-25-000079) - Item 7 MD&A 'Segment Operating Performance' + Nota 13, R68.htm | I32: Reportado
A33: Greater China | B33: 68366 | C33: 74200 | D33: 72559 | E33: 66952 | F33: 64377 | G33: USD m | H33: FY21-22: 10-K FY2023 (0000320193-23-000106) - Item 7 MD&A 'Segment Operating Performance' + Nota 13 'Segment Information and Geographic Data' | FY23-25: 10-K FY2025 (0000320193-25-000079) - Item 7 MD&A 'Segment Operating Performance' + Nota 13, R68.htm | I33: Reportado
A34: Japan | B34: 28482 | C34: 25977 | D34: 24257 | E34: 25052 | F34: 28703 | G34: USD m | H34: FY21-22: 10-K FY2023 (0000320193-23-000106) - Item 7 MD&A 'Segment Operating Performance' + Nota 13 'Segment Information and Geographic Data' | FY23-25: 10-K FY2025 (0000320193-25-000079) - Item 7 MD&A 'Segment Operating Performance' + Nota 13, R68.htm | I34: Reportado
A35: Rest of Asia Pacific | B35: 26356 | C35: 29375 | D35: 29615 | E35: 30658 | F35: 33696 | G35: USD m | H35: FY21-22: 10-K FY2023 (0000320193-23-000106) - Item 7 MD&A 'Segment Operating Performance' + Nota 13 'Segment Information and Geographic Data' | FY23-25: 10-K FY2025 (0000320193-25-000079) - Item 7 MD&A 'Segment Operating Performance' + Nota 13, R68.htm | I35: Reportado
A36: Total ventas netas por segmento (calc) | B36: =SUM(B31:B35) -> 365817 | C36: =SUM(C31:C35) -> 394328 | D36: =SUM(D31:D35) -> 383285 | E36: =SUM(E31:E35) -> 391035 | F36: =SUM(F31:F35) -> 416161 | G36: USD m | H36: Suma de los 5 segmentos reportables | I36: Calculado
A37: Tie: segmentos - IS_Hist total ventas netas | B37: =B36-IS_Hist!B7 -> 0 | C37: =C36-IS_Hist!C7 -> 0 | D37: =D36-IS_Hist!D7 -> 0 | E37: =E36-IS_Hist!E7 -> 0 | F37: =F36-IS_Hist!F7 -> 0 | G37: USD m | H37: IS_Hist!B7:F7 | I37: Tie (debe ser 0)
A39: Mix por segmento (% de ventas netas)
A40: Mix - Americas | B40: =B31/B$36 -> 0.41907839 | C40: =C31/C$36 -> 0.43024589 | D40: =D31/D$36 -> 0.42412304 | E40: =E31/E$36 -> 0.42718682 | F40: =F31/F$36 -> 0.42856731 | G40: % | H40: Calculado | I40: Calculado
A41: Mix - Europe | B41: =B32/B$36 -> 0.24413026 | C41: =C32/C$36 -> 0.24121543 | D41: =D32/D$36 -> 0.24601537 | E41: =E32/E$36 -> 0.2591277 | F41: =F32/F$36 -> 0.26680059 | G41: % | H41: Calculado | I41: Calculado
A42: Mix - Greater China | B42: =B33/B$36 -> 0.18688579 | C42: =C33/C$36 -> 0.18816823 | D42: =D33/D$36 -> 0.18930822 | E42: =E33/E$36 -> 0.17121741 | F42: =F33/F$36 -> 0.15469253 | G42: % | H42: Calculado | I42: Calculado
A43: Mix - Japan | B43: =B34/B$36 -> 0.077858601 | C43: =C34/C$36 -> 0.065876631 | D43: =D34/D$36 -> 0.06328711 | E43: =E34/E$36 -> 0.064065876 | F43: =F34/F$36 -> 0.068970903 | G43: % | H43: Calculado | I43: Calculado
A44: Mix - Rest of Asia Pacific | B44: =B35/B$36 -> 0.072046952 | C44: =C35/C$36 -> 0.074493822 | D44: =D35/D$36 -> 0.077266264 | E44: =E35/E$36 -> 0.078402189 | F44: =F35/F$36 -> 0.080968664 | G44: % | H44: Calculado | I44: Calculado
A46: Crecimiento interanual por segmento
A47: YoY - Americas | B47: n.a. | C47: =C31/B31-1 -> 0.10666249 | D47: =D31/C31-1 -> -0.041837108 | E47: =E31/D31-1 -> 0.027589813 | F47: =F31/E31-1 -> 0.067694334 | G47: % | H47: Calculado | I47: Calculado
A48: YoY - Europe | B48: n.a. | C48: =C32/B32-1 -> 0.065067688 | D48: =D32/C32-1 -> -0.0086629239 | E48: =E32/D32-1 -> 0.074596475 | F48: =F32/E32-1 -> 0.095768198 | G48: % | H48: Calculado | I48: Calculado
A49: YoY - Greater China | B49: n.a. | C49: =C33/B33-1 -> 0.085334816 | D49: =D33/C33-1 -> -0.022115903 | E49: =E33/D33-1 -> -0.077275045 | F49: =F33/E33-1 -> -0.03846039 | G49: % | H49: Calculado | I49: Calculado
A50: YoY - Japan | B50: n.a. | C50: =C34/B34-1 -> -0.087950284 | D50: =D34/C34-1 -> -0.066212419 | E50: =E34/D34-1 -> 0.032774045 | F50: =F34/E34-1 -> 0.14573687 | G50: % | H50: Calculado | I50: Calculado
A51: YoY - Rest of Asia Pacific | B51: n.a. | C51: =C35/B35-1 -> 0.11454697 | D51: =D35/C35-1 -> 0.0081702128 | E51: =E35/D35-1 -> 0.035218639 | F51: =F35/E35-1 -> 0.099093222 | G51: % | H51: Calculado | I51: Calculado
A53: 3. UTILIDAD OPERATIVA POR SEGMENTO Y RECONCILIACIÓN AL ESTADO DE RESULTADOS
A54: Americas - utilidad operativa | B54: 53382 | C54: 62683 | D54: 60508 | E54: 67656 | F54: 72480 | G54: USD m | H54: FY21-22: 10-K FY2022 (0000320193-22-000108) y 10-K FY2023 (0000320193-23-000106) - Nota 'Segment Information and Geographic Data', tabla por segmento reportable | FY23-25: 10-K FY2025 (0000320193-25-000079) - Nota 13, R68.htm (presentación ASU 2023-07) | I54: Reportado
A55: Europe - utilidad operativa | B55: 32505 | C55: 35233 | D55: 36098 | E55: 41790 | F55: 47739 | G55: USD m | H55: FY21-22: 10-K FY2022 (0000320193-22-000108) y 10-K FY2023 (0000320193-23-000106) - Nota 'Segment Information and Geographic Data', tabla por segmento reportable | FY23-25: 10-K FY2025 (0000320193-25-000079) - Nota 13, R68.htm (presentación ASU 2023-07) | I55: Reportado
A56: Greater China - utilidad operativa | B56: 28504 | C56: 31153 | D56: 30328 | E56: 27082 | F56: 26917 | G56: USD m | H56: FY21-22: 10-K FY2022 (0000320193-22-000108) y 10-K FY2023 (0000320193-23-000106) - Nota 'Segment Information and Geographic Data', tabla por segmento reportable | FY23-25: 10-K FY2025 (0000320193-25-000079) - Nota 13, R68.htm (presentación ASU 2023-07) | I56: Reportado
A57: Japan - utilidad operativa | B57: 12798 | C57: 12257 | D57: 11888 | E57: 12454 | F57: 13955 | G57: USD m | H57: FY21-22: 10-K FY2022 (0000320193-22-000108) y 10-K FY2023 (0000320193-23-000106) - Nota 'Segment Information and Geographic Data', tabla por segmento reportable | FY23-25: 10-K FY2025 (0000320193-25-000079) - Nota 13, R68.htm (presentación ASU 2023-07) | I57: Reportado
A58: Rest of Asia Pacific - utilidad operativa | B58: 9817 | C58: 11569 | D58: 12066 | E58: 13062 | F58: 14586 | G58: USD m | H58: FY21-22: 10-K FY2022 (0000320193-22-000108) y 10-K FY2023 (0000320193-23-000106) - Nota 'Segment Information and Geographic Data', tabla por segmento reportable | FY23-25: 10-K FY2025 (0000320193-25-000079) - Nota 13, R68.htm (presentación ASU 2023-07) | I58: Reportado
A59: Total utilidad operativa de segmentos (calc) | B59: =SUM(B54:B58) -> 137006 | C59: =SUM(C54:C58) -> 152895 | D59: =SUM(D54:D58) -> 150888 | E59: =SUM(E54:E58) -> 162044 | F59: =SUM(F54:F58) -> 175677 | G59: USD m | H59: Suma de los 5 segmentos | I59: Calculado
A60: (-) Research and development | B60: =-IS_Hist!B13 -> -21914 | C60: =-IS_Hist!C13 -> -26251 | D60: =-IS_Hist!D13 -> -29915 | E60: =-IS_Hist!E13 -> -31370 | F60: =-IS_Hist!F13 -> -34550 | G60: USD m | H60: IS_Hist!B13:F13 (mismo importe reportado en la conciliación del 10-K) | I60: Enlace vivo
A61: (-) Other corporate expenses, net (G&A) | B61: -6143 | C61: -7207 | D61: -6672 | E61: -7458 | F61: -8077 | G61: USD m | H61: FY21-22: 10-K FY2022 (0000320193-22-000108) y 10-K FY2023 (0000320193-23-000106) - Nota 'Segment Information and Geographic Data', tabla por segmento reportable | FY23-25: 10-K FY2025 (0000320193-25-000079) - Nota 13, R68.htm (presentación ASU 2023-07) - tabla de conciliación de segment operating income | I61: Reportado
A62: Utilidad operativa consolidada (calc) | B62: =B59+B60+B61 -> 108949 | C62: =C59+C60+C61 -> 119437 | D62: =D59+D60+D61 -> 114301 | E62: =E59+E60+E61 -> 123216 | F62: =F59+F60+F61 -> 133050 | G62: USD m | H62: Conciliacion reproducida | I62: Calculado
A63: Tie: conciliación - IS_Hist utilidad operativa | B63: =B62-IS_Hist!B16 -> 0 | C63: =C62-IS_Hist!C16 -> 0 | D63: =D62-IS_Hist!D16 -> 0 | E63: =E62-IS_Hist!E16 -> 0 | F63: =F62-IS_Hist!F16 -> 0 | G63: USD m | H63: IS_Hist!B16:F16 | I63: Tie (debe ser 0)
A65: Margen operativo por segmento (utilidad operativa de segmento / ventas netas del segmento)
A66: Margen operativo - Americas | B66: =B54/B31 -> 0.34820555 | C66: =C54/C31 -> 0.36946681 | D66: =D54/D31 -> 0.37221949 | E66: =E54/E31 -> 0.40501661 | F66: =F54/F31 -> 0.40638509 | G66: % | H66: Calculado | I66: Calculado
A67: Margen operativo - Europe | B67: =B55/B32 -> 0.36396923 | C67: =C55/C32 -> 0.37041359 | D67: =D55/D32 -> 0.38282393 | E67: =E55/E32 -> 0.41242302 | F67: =F55/F32 -> 0.42995713 | G67: % | H67: Calculado | I67: Calculado
A68: Margen operativo - Greater China | B68: =B56/B33 -> 0.41693239 | C68: =C56/C33 -> 0.41985175 | D68: =D56/D33 -> 0.41797709 | E68: =E56/E33 -> 0.40449875 | F68: =F56/F33 -> 0.41811517 | G68: % | H68: Calculado | I68: Calculado
A69: Margen operativo - Japan | B69: =B57/B34 -> 0.44933642 | C69: =C57/C34 -> 0.47184047 | D69: =D57/D34 -> 0.49008534 | E69: =E57/E34 -> 0.49712598 | F69: =F57/F34 -> 0.48618611 | G69: % | H69: Calculado | I69: Calculado
A70: Margen operativo - Rest of Asia Pacific | B70: =B58/B35 -> 0.37247686 | C70: =C58/C35 -> 0.3938383 | D70: =D58/D35 -> 0.40742867 | E70: =E58/E35 -> 0.42605519 | F70: =F58/F35 -> 0.43287037 | G70: % | H70: Calculado | I70: Calculado
A72: 4. ECONOMÍA PRODUCTS vs SERVICES (Apple los divulga por separado)
A73: Products - ventas netas | B73: 297392 | C73: 316199 | D73: 298085 | E73: 294866 | F73: 307003 | G73: USD m | H73: FY2021: 10-K FY2021 (0000320193-21-000105) - CONSOLIDATED STATEMENTS OF OPERATIONS (Products / Services) | FY2022-25: 10-K FY2025 (0000320193-25-000079) - CONSOLIDATED STATEMENTS OF OPERATIONS, R3.htm | I73: Reportado
A74: Services - ventas netas | B74: =B11 -> 68425 | C74: =C11 -> 78129 | D74: =D11 -> 85200 | E74: =E11 -> 96169 | F74: =F11 -> 109158 | G74: USD m | H74: Igual a la categoría Services del bloque 1 | I74: Enlace vivo
A75: Total ventas netas (calc) | B75: =B73+B74 -> 365817 | C75: =C73+C74 -> 394328 | D75: =D73+D74 -> 383285 | E75: =E73+E74 -> 391035 | F75: =F73+F74 -> 416161 | G75: USD m | H75: Calculado | I75: Calculado
A76: Tie: Products+Services - IS_Hist total ventas netas | B76: =B75-IS_Hist!B7 -> 0 | C76: =C75-IS_Hist!C7 -> 0 | D76: =D75-IS_Hist!D7 -> 0 | E76: =E75-IS_Hist!E7 -> 0 | F76: =F75-IS_Hist!F7 -> 0 | G76: USD m | H76: IS_Hist!B7:F7 | I76: Tie (debe ser 0)
A77: Products - costo de ventas | B77: 192266 | C77: 201471 | D77: 189282 | E77: 185233 | F77: 194116 | G77: USD m | H77: FY2021: 10-K FY2021 (0000320193-21-000105) - CONSOLIDATED STATEMENTS OF OPERATIONS (Products / Services) | FY2022-25: 10-K FY2025 (0000320193-25-000079) - CONSOLIDATED STATEMENTS OF OPERATIONS, R3.htm | I77: Reportado
A78: Services - costo de ventas | B78: 20715 | C78: 22075 | D78: 24855 | E78: 25119 | F78: 26844 | G78: USD m | H78: FY2021: 10-K FY2021 (0000320193-21-000105) - CONSOLIDATED STATEMENTS OF OPERATIONS (Products / Services) | FY2022-25: 10-K FY2025 (0000320193-25-000079) - CONSOLIDATED STATEMENTS OF OPERATIONS, R3.htm | I78: Reportado
A79: Total costo de ventas (calc) | B79: =B77+B78 -> 212981 | C79: =C77+C78 -> 223546 | D79: =D77+D78 -> 214137 | E79: =E77+E78 -> 210352 | F79: =F77+F78 -> 220960 | G79: USD m | H79: Calculado | I79: Calculado
A80: Tie: costo Products+Services - IS_Hist total costo de ventas | B80: =B79-IS_Hist!B10 -> 0 | C80: =C79-IS_Hist!C10 -> 0 | D80: =D79-IS_Hist!D10 -> 0 | E80: =E79-IS_Hist!E10 -> 0 | F80: =F79-IS_Hist!F10 -> 0 | G80: USD m | H80: IS_Hist!B10:F10 | I80: Tie (debe ser 0)
A81: Products - margen bruto (reportado) | B81: 105126 | C81: 114728 | D81: 108803 | E81: 109633 | F81: 112887 | G81: USD m | H81: FY21-22: 10-K FY2023 (0000320193-23-000106) - Item 7 MD&A, 'Gross Margin'; FY2021 también en 10-K FY2021 (0000320193-21-000105) Item 7 y Estado de Operaciones | FY23-25: 10-K FY2025 (0000320193-25-000079) - Item 7 MD&A 'Gross Margin' + Estado Consolidado de Operaciones, R3.htm | I81: Reportado
A82: Services - margen bruto (reportado) | B82: 47710 | C82: 56054 | D82: 60345 | E82: 71050 | F82: 82314 | G82: USD m | H82: FY21-22: 10-K FY2023 (0000320193-23-000106) - Item 7 MD&A, 'Gross Margin'; FY2021 también en 10-K FY2021 (0000320193-21-000105) Item 7 y Estado de Operaciones | FY23-25: 10-K FY2025 (0000320193-25-000079) - Item 7 MD&A 'Gross Margin' + Estado Consolidado de Operaciones, R3.htm | I82: Reportado
A83: Total margen bruto (calc) | B83: =B81+B82 -> 152836 | C83: =C81+C82 -> 170782 | D83: =D81+D82 -> 169148 | E83: =E81+E82 -> 180683 | F83: =F81+F82 -> 195201 | G83: USD m | H83: Calculado | I83: Calculado
A84: Tie: margen bruto Products+Services - IS_Hist margen bruto | B84: =B83-IS_Hist!B11 -> 0 | C84: =C83-IS_Hist!C11 -> 0 | D84: =D83-IS_Hist!D11 -> 0 | E84: =E83-IS_Hist!E11 -> 0 | F84: =F83-IS_Hist!F11 -> 0 | G84: USD m | H84: IS_Hist!B11:F11 | I84: Tie (debe ser 0)
A85: Products - margen bruto % (reportado) | B85: 0.353 | C85: 0.363 | D85: 0.365 | E85: 0.372 | F85: 0.368 | G85: % | H85: FY21-22: 10-K FY2023 (0000320193-23-000106) - Item 7 MD&A, 'Gross Margin'; FY2021 también en 10-K FY2021 (0000320193-21-000105) Item 7 y Estado de Operaciones | FY23-25: 10-K FY2025 (0000320193-25-000079) - Item 7 MD&A 'Gross Margin' + Estado Consolidado de Operaciones, R3.htm | I85: Reportado
A86: Services - margen bruto % (reportado) | B86: 0.697 | C86: 0.717 | D86: 0.708 | E86: 0.739 | F86: 0.754 | G86: % | H86: FY21-22: 10-K FY2023 (0000320193-23-000106) - Item 7 MD&A, 'Gross Margin'; FY2021 también en 10-K FY2021 (0000320193-21-000105) Item 7 y Estado de Operaciones | FY23-25: 10-K FY2025 (0000320193-25-000079) - Item 7 MD&A 'Gross Margin' + Estado Consolidado de Operaciones, R3.htm | I86: Reportado
A87: Total margen bruto % (reportado) | B87: 0.418 | C87: 0.433 | D87: 0.441 | E87: 0.462 | F87: 0.469 | G87: % | H87: FY21-22: 10-K FY2023 (0000320193-23-000106) - Item 7 MD&A, 'Gross Margin'; FY2021 también en 10-K FY2021 (0000320193-21-000105) Item 7 y Estado de Operaciones | FY23-25: 10-K FY2025 (0000320193-25-000079) - Item 7 MD&A 'Gross Margin' + Estado Consolidado de Operaciones, R3.htm | I87: Reportado
A88: Products - margen bruto % (calc) | B88: =B81/B73 -> 0.35349303 | C88: =C81/C73 -> 0.3628348 | D88: =D81/D73 -> 0.36500663 | E88: =E81/E73 -> 0.37180618 | F88: =F81/F73 -> 0.3677065 | G88: % | H88: Calculado (el reportado viene redondeado a 0.1pp) | I88: Calculado
A89: Services - margen bruto % (calc) | B89: =B82/B74 -> 0.69725977 | C89: =C82/C74 -> 0.71745447 | D89: =D82/D74 -> 0.70827465 | E89: =E82/E74 -> 0.73880356 | F89: =F82/F74 -> 0.75408124 | G89: % | H89: Calculado | I89: Calculado
A90: Services - participación en el margen bruto total | B90: =B82/B83 -> 0.31216467 | C90: =C82/C83 -> 0.3282196 | D90: =D82/D83 -> 0.35675858 | E90: =E82/E83 -> 0.39323013 | F90: =F82/F83 -> 0.42168841 | G90: % | H90: Calculado - driver central de la tesis de Apple | I90: Calculado
A91: Services - participación en ventas netas | B91: =B74/B75 -> 0.18704708 | C91: =C74/C75 -> 0.19813201 | D91: =D74/D75 -> 0.2222889 | E91: =E74/E75 -> 0.24593451 | F91: =F74/F75 -> 0.26229752 | G91: % | H91: Calculado | I91: Calculado
A93: 5. MÉTRICAS OPERATIVAS DIVULGADAS EN EL 10-K
A94: Empleados equivalentes a tiempo completo | B94: 154000 | C94: 164000 | D94: 161000 | E94: 164000 | F94: 166000 | G94: personas | H94: 10-K FY2021/2022/2023/2024/2025 - Item 1 'Business', sección 'Human Capital' (empleados equivalentes a tiempo completo) | I94: Reportado
A95: Ventas netas por empleado | B95: =B12*1000/B94 -> 2375.4351 | C95: =C12*1000/C94 -> 2404.439 | D95: =D12*1000/D94 -> 2380.6522 | E95: =E12*1000/E94 -> 2384.3598 | F95: =F12*1000/F94 -> 2506.994 | G95: USD miles | H95: Calculado | I95: Calculado
A96: Deferred revenue total (saldo) | B96: 11900 | C96: 12400 | D96: 12100 | E96: 12800 | F96: 13700 | G96: USD m | H96: 10-K FY2021-FY2025 - Nota 'Revenue' (saldo total de deferred revenue) / companyfacts us-gaap:ContractWithCustomerLiability | I96: Reportado
A97: Deferred revenue / ventas netas | B97: =B96/B12 -> 0.032529926 | C97: =C96/C12 -> 0.031445903 | D97: =D96/D12 -> 0.031569198 | E97: =E96/E12 -> 0.032733643 | F97: =F96/F12 -> 0.032919952 | G97: % | H97: Calculado | I97: Calculado
A98: Ventas netas reconocidas del deferred revenue inicial | B98: 6700 | C98: 7500 | D98: 8169 | E98: 7728 | F98: 8229 | G98: USD m | H98: 10-K FY2021-FY2025 - Nota 'Revenue' / us-gaap:ContractWithCustomerLiabilityRevenueRecognized. FY2021-FY2022 divulgados redondeados a USD 0.1bn | I98: Reportado
A99: Research and development | B99: =IS_Hist!B13 -> 21914 | C99: =IS_Hist!C13 -> 26251 | D99: =IS_Hist!D13 -> 29915 | E99: =IS_Hist!E13 -> 31370 | F99: =IS_Hist!F13 -> 34550 | G99: USD m | H99: IS_Hist!B13:F13 | I99: Enlace vivo
A100: R&D / ventas netas | B100: =B99/B12 -> 0.059904269 | C100: =C99/C12 -> 0.066571484 | D100: =D99/D12 -> 0.078048971 | E100: =E99/E12 -> 0.080222998 | F100: =F99/F12 -> 0.083020754 | G100: % | H100: Calculado | I100: Calculado
A101: Long-lived assets - U.S. | B101: 28203 | C101: 31119 | D101: 33276 | E101: 35664 | F101: 40274 | G101: USD m | H101: 10-K FY2022/2023/2024/2025 - Nota 'Segment Information and Geographic Data', tabla de long-lived assets por país | I101: Reportado
A102: Long-lived assets - China | B102: 7521 | C102: 7260 | D102: 5778 | E102: 4797 | F102: 3617 | G102: USD m | H102: 10-K FY2022/2023/2024/2025 - Nota 'Segment Information and Geographic Data', tabla de long-lived assets por país | I102: Reportado
A103: Long-lived assets - otros países | B103: 3716 | C103: 3738 | D103: 4661 | E103: 5219 | F103: 5943 | G103: USD m | H103: 10-K FY2022/2023/2024/2025 - Nota 'Segment Information and Geographic Data', tabla de long-lived assets por país | I103: Reportado
A104: Total long-lived assets (calc) | B104: =SUM(B101:B103) -> 39440 | C104: =SUM(C101:C103) -> 42117 | D104: =SUM(D101:D103) -> 43715 | E104: =SUM(E101:E103) -> 45680 | F104: =SUM(F101:F103) -> 49834 | G104: USD m | H104: Calculado | I104: Calculado
A105: Tie: long-lived assets - BS_Hist PP&E neto | B105: =B104-BS_Hist!B15 -> 0 | C105: =C104-BS_Hist!C15 -> 0 | D105: =D104-BS_Hist!D15 -> 0 | E105: =E104-BS_Hist!E15 -> 0 | F105: =F104-BS_Hist!F15 -> 0 | G105: USD m | H105: BS_Hist!B15:F15 | I105: Tie (debe ser 0)
A106: Ventas netas - U.S. | B106: 133803 | C106: 147859 | D106: 138573 | E106: 142196 | F106: 151790 | G106: USD m | H106: 10-K FY2022/2023/2024/2025 - Nota 'Segment Information and Geographic Data', tabla de net sales por país (>10% del total) | I106: Reportado
A107: Ventas netas - China | B107: 68366 | C107: 74200 | D107: 72559 | E107: 66952 | F107: 64377 | G107: USD m | H107: 10-K FY2022/2023/2024/2025 - Nota 'Segment Information and Geographic Data', tabla de net sales por país (>10% del total) | I107: Reportado
A108: Ventas netas - otros países | B108: 163648 | C108: 172269 | D108: 172153 | E108: 181887 | F108: 199994 | G108: USD m | H108: 10-K FY2022/2023/2024/2025 - Nota 'Segment Information and Geographic Data', tabla de net sales por país (>10% del total) | I108: Reportado
A109: Total ventas netas por país (calc) | B109: =SUM(B106:B108) -> 365817 | C109: =SUM(C106:C108) -> 394328 | D109: =SUM(D106:D108) -> 383285 | E109: =SUM(E106:E108) -> 391035 | F109: =SUM(F106:F108) -> 416161 | G109: USD m | H109: Calculado | I109: Calculado
A110: Tie: países - IS_Hist total ventas netas | B110: =B109-IS_Hist!B7 -> 0 | C110: =C109-IS_Hist!C7 -> 0 | D110: =D109-IS_Hist!D7 -> 0 | E110: =E109-IS_Hist!E7 -> 0 | F110: =F109-IS_Hist!F7 -> 0 | G110: USD m | H110: IS_Hist!B7:F7 | I110: Tie (debe ser 0)
A111: Concentración U.S. + China (% de ventas netas) | B111: =(B106+B107)/B109 -> 0.55265064 | C111: =(C106+C107)/C109 -> 0.56313272 | D111: =(D106+D107)/D109 -> 0.55084859 | E111: =(E106+E107)/E109 -> 0.53485749 | F111: =(F106+F107)/F109 -> 0.51943118 | G111: % | H111: Calculado | I111: Calculado
...

Sheet Market_Package
A1: Apple Inc. — Paquete de mercado fechado y costo de capital
A2: Cada input de mercado lleva su fuente y su FECHA. Los enlaces al balance y al estado de resultados son fórmulas vivas contra las hojas históricas auditadas (que esta hoja NO modifica).
A4: Concepto | B4: Valor | C4: Unidad | D4: Fecha del dato (as-of) | E4: Fuente | F4: Nota / método
A6: 1. PRECIO Y ACCIONES
A7: Precio de la acción (cierre) | B7: 305.26 | C7: USD/acción | D7: 46247 | E7: stockanalysis.com/stocks/aapl/history/ — histórico diario de AAPL | F7: Recuperado 2026-08-14. Cierre del 2026-08-13 confirmado de forma independiente por búsqueda web (USD 305.26); apertura 304.21, máx. 306.00, mín. 302.05
A8: Acciones en circulación | B8: 14594.18 | C8: millones de acciones | D8: 46220 | E8: SEC Form 10-Q Q3 FY2026, portada (accn 0000320193-26-000020), etiqueta 'Entity Common Stock, Shares Outstanding' | F8: Fuente primaria: 14,594,180 miles de acciones. Es el conteo más reciente publicado por la compañía
A9: Memo — acciones en circulación, portada del 10-K FY2025 | B9: 14776.353 | C9: millones de acciones | D9: 45947 | E9: SEC Form 10-K FY2025, portada (accn 0000320193-25-000079) | F9: Es el valor que hoy usa Valuation!G15 a través de Historical!B20
A10: Memo — acciones diluidas promedio, Q3 FY2026 (3 meses) | B10: 14714.676 | C10: millones de acciones | D10: 46200 | E10: SEC Form 10-Q Q3 FY2026, Estado Condensado de Operaciones (R2) | F10: Base diluida trimestral
A11: Capitalización de mercado | B11: =B7*B8 -> 4455019.4 | C11: USD m | D11: =D7 -> 46247 | E11: Calculado: precio de cierre x acciones en circulación | F11: Usa el conteo primario más reciente (B8), no el de la portada del 10-K
A13: 2. PUENTE A ENTERPRISE VALUE (balance FY2025A del propio modelo)
A14: Efectivo y equivalentes | B14: =BS_Hist!F6 -> 35934 | C14: USD m | D14: 45927 | E14: BS_Hist!F6 — 10-K FY2025, balance auditado | F14: Enlace vivo a la hoja histórica
A15: Valores negociables corrientes | B15: =BS_Hist!F7 -> 18763 | C15: USD m | D15: 45927 | E15: BS_Hist!F7 | F15: Enlace vivo
A16: Valores negociables no corrientes | B16: =BS_Hist!F14 -> 77723 | C16: USD m | D16: 45927 | E16: BS_Hist!F14 | F16: Enlace vivo
A17: Total efectivo e inversiones | B17: =SUM(B14:B16) -> 132420 | C17: USD m | D17: 45927 | E17: Calculado
A18: Papel comercial | B18: =BS_Hist!F24 -> 7979 | C18: USD m | D18: 45927 | E18: BS_Hist!F24 | F18: Enlace vivo
A19: Deuda de largo plazo — porción corriente | B19: =BS_Hist!F25 -> 12350 | C19: USD m | D19: 45927 | E19: BS_Hist!F25 | F19: Enlace vivo
A20: Deuda de largo plazo — no corriente | B20: =BS_Hist!F28 -> 78328 | C20: USD m | D20: 45927 | E20: BS_Hist!F28 | F20: Enlace vivo
A21: Deuda bruta total | B21: =SUM(B18:B20) -> 98657 | C21: USD m | D21: 45927 | E21: Calculado | F21: Incluye papel comercial
A22: Deuda neta / (caja neta) | B22: =B21-B17 -> -33763 | C22: USD m | D22: 45927 | E22: Calculado | F22: Negativo = caja neta
A23: Enterprise value | B23: =B11+B21-B17 -> 4421256.4 | C23: USD m | D23: 46247 | E23: Calculado: cap. de mercado + deuda bruta − efectivo e inversiones | F23: Precio al 2026-08-13 contra balance al 2025-09-27
A24: Memo — deuda usada hoy en Valuation!G13 | B24: =Historical!F14 -> 90678 | C24: USD m | D24: 45927 | E24: Historical!F14 | F24: Solo term debt: EXCLUYE el papel comercial
A25: Memo — diferencia vs la deuda bruta de esta hoja | B25: =B21-B24 -> 7979 | C25: USD m | D25: 45927 | E25: Calculado | F25: HALLAZGO: es exactamente el papel comercial (BS_Hist!F24). El puente de deuda del DCF existente subestima la deuda bruta en este monto
A26: Memo — activos líquidos usados hoy en Valuation!G12 | B26: =Historical!B18 -> 132420 | C26: USD m | D26: 45927 | E26: Historical!B18 | F26: Debe coincidir con B17
A27: Memo — diferencia de activos líquidos | B27: =B17-B26 -> 0 | C27: USD m | D27: 45927 | E27: Calculado | F27: Debe ser 0
A29: 3. COSTO DE CAPITAL
A30: Tasa libre de riesgo (UST 10 años, par yield) | B30: 0.0463 | C30: % | D30: 46247 | E30: home.treasury.gov — Daily Treasury Par Yield Curve Rates, columna '10 Yr' | F30: Fuente primaria del Tesoro de EE.UU. Misma fecha: 20Y 5.20%, 30Y 5.21%, 2Y 4.15%
A31: Prima de riesgo de mercado (ERP implícita, S&P 500) | B31: 0.0423 | C31: % | D31: 46023 | E31: A. Damodaran (NYU Stern), 'Implied Equity Risk Premiums — United States' (histimpl.html), actualización de enero 2026 | F31: ERP implícita FCFE del cierre de 2025; la tasa T-Bond que usa Damodaran en esa medición es 4.18%
A32: Beta (5 años, mensual, vs S&P 500) | B32: 1.09 | C32: x | D32: 46248 | E32: stockanalysis.com/stocks/aapl/ | F32: Cross-checks el mismo día: investing.com 1.11; gurufocus 0.9638 (ventana de estimación distinta). NO es una beta reguladora: es de proveedor
A33: Costo de capital propio (CAPM) | B33: =B30+B32*B31 -> 0.092407 | C33: % | D33: =D30 -> 46247 | E33: Calculado: Rf + beta x ERP
A34: Costo de deuda antes de impuestos | B34: 0.052 | C34: % | D34: 46247 | E34: FRED (Federal Reserve Bank of St. Louis) — serie primaria BAMLC0A2CAAEY, ICE BofA AA US Corporate Index Effective Yield; CSV de la serie descargado directo de fredgraph.csv | F34: Benchmark de mercado para emisor calificado AA+. Es el costo MARGINAL, no el cupón promedio de la deuda viva. REFRESCADO 2026-08-14: la observación del 2026-08-13 (misma fecha que el precio y que el Rf) es 5.20%. El valor anterior, 5.27%, era del 2026-08-10, venía fechado como el texto "2026-08" y citado vía una fuente secundaria (tradingeconomics); ahora se lee de la serie primaria de FRED y la fecha es un serial
A35: Memo — rango de tasa efectiva de la emisión FY2025 de Apple | B35: 4.07% - 4.83% | C35: % | D35: 45927 | E35: 10-K FY2025, Nota 8 'Debt' (R60.htm) | F35: USD 4,500m emitidos en FY2025, vencimientos 2028-2035. El stack legado 2013-2023 tiene tasas efectivas de 0.03% a 5.75%
A36: Memo — tasa promedio ponderada del papel comercial | B36: 0.0419 | C36: % | D36: 45927 | E36: 10-K FY2025, Nota 8 'Debt' (R58.htm) | F36: FY2024: 5.00%
A37: Tasa efectiva de impuestos (FY2025A del modelo) | B37: =IS_Hist!F19/IS_Hist!F18 -> 0.15610002 | C37: % | D37: 45927 | E37: IS_Hist!F19 / IS_Hist!F18 | F37: Enlace vivo. ETR reportada por Apple en FY2025: 15.6%. FY2024 fue 24.1% por el cargo de ayuda estatal de la UE
A38: Memo — tasa estatutaria federal de EE.UU. | B38: 0.21 | C38: % | D38: 45927 | E38: 10-K FY2025, Nota 6 'Income Taxes' | F38: Referencia para una versión marginal del escudo fiscal
A39: Costo de deuda después de impuestos | B39: =B34*(1-B37) -> 0.043882799 | C39: % | D39: =D34 -> 46247 | E39: Calculado: Kd x (1 − t)
A40: Valor de mercado del capital (E) | B40: =B11 -> 4455019.4 | C40: USD m | D40: =D7 -> 46247 | E40: Calculado
A41: Deuda bruta (D) | B41: =B21 -> 98657 | C41: USD m | D41: 45927 | E41: Calculado | F41: Valor en libros como proxy del valor de mercado; el valor razonable de las notas fijas al 2025-09-27 era USD 80,400m (10-K FY2025, R58)
A42: Capital total (D+E) | B42: =B40+B41 -> 4553676.4 | C42: USD m | E42: Calculado
A43: Peso del capital propio | B43: =B40/B42 -> 0.97833465 | C43: % | E43: Calculado
A44: Peso de la deuda | B44: =B41/B42 -> 0.021665352 | C44: % | E44: Calculado
A45: WACC | B45: =B43*B33+B44*B39 -> 0.091355706 | C45: % | D45: 46247 | E45: Calculado: We x Ke + Wd x Kd x (1 − t) | F45: Fórmula viva: mover B30, B31, B32 o B34 mueve el WACC
A46: Memo — WACC usado hoy en el DCF | B46: =Assumptions!F20 -> 0.095 | C46: % | D46: 46220 | E46: Assumptions!F20 (escenario activo del selector Assumptions!B3)
A47: Memo — diferencia (este paquete − modelo) | B47: =B45-B46 -> -0.0036442939 | C47: % | E47: Calculado
A49: 4. MÚLTIPLOS IMPLÍCITOS vs FY2025A DEL MODELO
A50: Ventas netas FY2025A | B50: =IS_Hist!F7 -> 416161 | C50: USD m | D50: 45927 | E50: IS_Hist!F7 | F50: Enlace vivo
A51: Utilidad operativa FY2025A | B51: =IS_Hist!F16 -> 133050 | C51: USD m | D51: 45927 | E51: IS_Hist!F16 | F51: Enlace vivo
A52: Depreciación y amortización FY2025A | B52: =CF_Hist!F8 -> 11698 | C52: USD m | D52: 45927 | E52: CF_Hist!F8 | F52: Enlace vivo
A53: EBITDA FY2025A (calc) | B53: =B51+B52 -> 144748 | C53: USD m | D53: 45927 | E53: Calculado: EBIT + D&A | F53: Apple no publica EBITDA; es una construcción del analista
A54: Utilidad neta FY2025A | B54: =IS_Hist!F20 -> 112010 | C54: USD m | D54: 45927 | E54: IS_Hist!F20 | F54: Enlace vivo
A55: UPA diluida FY2025A | B55: =IS_Hist!F23 -> 7.46 | C55: USD/acción | D55: 45927 | E55: IS_Hist!F23 | F55: Enlace vivo
A56: Flujo de efectivo de operación FY2025A | B56: =CF_Hist!F18 -> 111482 | C56: USD m | D56: 45927 | E56: CF_Hist!F18 | F56: Enlace vivo
A57: Capex FY2025A | B57: =-CF_Hist!F23 -> 12715 | C57: USD m | D57: 45927 | E57: CF_Hist!F23 (publicado como salida negativa) | F57: Enlace vivo con signo invertido
A58: Flujo de caja libre FY2025A (CFO − capex) | B58: =B56-B57 -> 98767 | C58: USD m | D58: 45927 | E58: Calculado
A59: P/E (cap. de mercado / utilidad neta) | B59: =B11/B54 -> 39.773408 | C59: x | D59: 46247 | E59: Calculado
A60: P/E (precio / UPA diluida) | B60: =B7/B55 -> 40.919571 | C60: x | D60: 46247 | E60: Calculado | F60: Difiere levemente del anterior porque usa acciones diluidas promedio y no acciones en circulación
A61: EV / Ventas | B61: =B23/B50 -> 10.623909 | C61: x | D61: 46247 | E61: Calculado
A62: EV / EBITDA | B62: =B23/B53 -> 30.544508 | C62: x | D62: 46247 | E62: Calculado
A63: EV / EBIT | B63: =B23/B51 -> 33.230037 | C63: x | D63: 46247 | E63: Calculado
A64: FCF yield (FCF / cap. de mercado) | B64: =B58/B11 -> 0.022169825 | C64: % | D64: 46247 | E64: Calculado
A65: Dividend yield (dividendos pagados FY2025A / cap. de mercado) | B65: =-CF_Hist!F28/B11 -> 0.0034614889 | C65: % | D65: 46247 | E65: CF_Hist!F28 | F65: Sobre dividendos efectivamente pagados, no sobre el dividendo declarado corriente
A66: Buyback yield (recompras FY2025A / cap. de mercado) | B66: =-CF_Hist!F29/B11 -> 0.020361528 | C66: % | D66: 46247 | E66: CF_Hist!F29
A67: Rendimiento total al accionista | B67: =B65+B66 -> 0.023823016 | C67: % | D67: 46247 | E67: Calculado
A69: 5. MEMO LTM — hasta el Q3 FY2026 (10-Q del periodo terminado 2026-06-27). FUERA del perímetro auditado del modelo.
A70: Ventas netas 9M FY2026 | B70: 364357 | C70: USD m | D70: 46200 | E70: 10-Q Q3 FY2026 (accn 0000320193-26-000020), Estado Condensado de Operaciones (R2)
A71: Ventas netas 9M FY2025 | B71: 313695 | C71: USD m | D71: 45836 | E71: 10-Q Q3 FY2026, columna comparativa
A72: Ventas netas LTM | B72: =IS_Hist!F7-B71+B70 -> 466823 | C72: USD m | D72: 46200 | E72: Calculado: FY2025A − 9M FY2025 + 9M FY2026
A73: Utilidad operativa 9M FY2026 | B73: 122432 | C73: USD m | D73: 46200 | E73: 10-Q Q3 FY2026, R2
A74: Utilidad operativa 9M FY2025 | B74: 100623 | C74: USD m | D74: 45836 | E74: 10-Q Q3 FY2026, columna comparativa
A75: Utilidad operativa LTM | B75: =IS_Hist!F16-B74+B73 -> 154859 | C75: USD m | D75: 46200 | E75: Calculado
A76: Utilidad neta 9M FY2026 | B76: 101464 | C76: USD m | D76: 46200 | E76: 10-Q Q3 FY2026, R2
A77: Utilidad neta 9M FY2025 | B77: 84544 | C77: USD m | D77: 45836 | E77: 10-Q Q3 FY2026, columna comparativa
A78: Utilidad neta LTM | B78: =IS_Hist!F20-B77+B76 -> 128930 | C78: USD m | D78: 46200 | E78: Calculado
A79: P/E LTM | B79: =B11/B78 -> 34.553784 | C79: x | D79: 46247 | E79: Calculado
A80: EV / Ventas LTM | B80: =B23/B72 -> 9.4709481 | C80: x | D80: 46247 | E80: Calculado | F80: Usa el EV construido con el balance FY2025A
A81: EV / EBIT LTM | B81: =B23/B75 -> 28.550206 | C81: x | D81: 46247 | E81: Calculado
A82: Efectivo e inversiones al 2026-06-27 | B82: 146517 | C82: USD m | D82: 46200 | E82: 10-Q Q3 FY2026, balance condensado (R4): 39,544 + 22,855 + 84,118 | F82: Ancla de vintage distinto: el check 52 exige que B17 (caja FY2025A del modelo) quede dentro de ±15% de esta cifra
A83: Deuda bruta al 2026-06-27 | B83: 84344 | C83: USD m | D83: 46200 | E83: 10-Q Q3 FY2026, balance condensado (R4): 1,997 + 11,007 + 71,340 | F83: Ancla de vintage distinto: el check 53 exige que B21 (deuda FY2025A del modelo) quede dentro de ±25% de esta cifra (la deriva real ya es +17.0%)
A84: EV con el balance al 2026-06-27 | B84: =B11+B83-B82 -> 4392846.4 | C84: USD m | D84: 46247 | E84: Calculado | F84: Referencia: no se usa en los múltiplos de arriba para no mezclar perímetros
A85: Memo — diferencia vs el EV con balance FY2025A | B85: =B84-B23 -> -28410 | C85: USD m | E85: Calculado
A87: 6. CONTROL DE PROCEDENCIA (todo input de mercado debe traer fuente y fecha)
A88: Inputs de mercado sujetos a control | B88: 6 | C88: conteo | E88: B7 precio, B8 acciones, B30 Rf, B31 ERP, B32 beta, B34 Kd | F88: Los demás valores de la hoja son enlaces vivos a hojas históricas o cálculos
A89: Inputs sin fuente | B89: =IF(LEN(E7)=0,1,0)+IF(LEN(E8)=0,1,0)+IF(LEN(E30)=0,1,0)+IF(LEN(E31)=0,1,0)+IF(LEN(E32)=0,1,0)+IF(LEN(E34)=0,1,0) -> 0 | C89: conteo | E89: Calculado | F89: Debe ser 0
A90: Inputs sin fecha valida (ausente o escrita como texto en vez de serial de fecha) | B90: =IF(OR(LEN(D7)=0,NOT(ISNUMBER(D7))),1,0)+IF(OR(LEN(D8)=0,NOT(ISNUMBER(D8))),1,0)+IF(OR(LEN(D30)=0,NOT(ISNUMBER(D30))),1,0)+IF(OR(LEN(D31)=0,NOT(ISNUMBER(D31))),1,0)+IF(OR(LEN(D32)=0,NOT(ISNUMBER(D32))),1,0)+IF(OR(LEN(D34)=0,NOT(ISNUMBER(D34))),1,0) -> 0 | C90: conteo | E90: Calculado | F90: Debe ser 0. Una fecha escrita como texto (por ejemplo "2026-08") cuenta como invalida
A91: Estado de procedencia | B91: =IF(AND(B89=0,B90=0,B92=0),"PASS","FAIL") -> FAIL | C91: estado | E91: Calculado
A92: Inputs de cotización diaria desfasados (más de 5 días entre sí) o paquete entero obsoleto (más de 10 días contra HOY() al recalcular) | B92: =IF(D7<MAX(D7,D30,D32,D34)-5,1,0)+IF(D30<MAX(D7,D30,D32,D34)-5,1,0)+IF(D34<MAX(D7,D30,D32,D34)-5,1,0)+IF(MAX(D7,D30,D32,D34)<TODAY()-10,1,0) -> 1 | C92: conteo | E92: Calculado | F92: Debe ser 0. Cubre precio (D7), Rf (D30) y Kd (D34) entre sí, y desde 2026-08-14 también la frescura ABSOLUTA: si la observación más reciente del paquete es anterior a HOY()−10 (TODAY() recalcula al abrir), cae en FAIL aunque las fechas estén alineadas entre sí — antes, poner las cuatro fechas en enero pasaba. El libro caduca solo: es diseño, no defecto. Excluye a propósito la ERP (D31, serie anual de Damodaran) y el conteo de acciones (D8, del 10-Q): observaciones de baja frecuencia, desfase declarado en L2
A93: 7. LIMITACIONES, HALLAZGOS Y CABLEADO PENDIENTE
A94: H1 — El puente de deuda del DCF existente (Valuation!G13 vía Historical!F14) usa solo term debt y omite el papel comercial. La diferencia está cuantificada en B25. Esta hoja NO corrige Valuation: lo expone.
A95: H2 — Valuation!G19 tiene el precio de mercado en duro (USD 327.50, as-of 2026-07-15) y Historical!B20 el conteo de acciones de la portada del 10-K FY2025. Para refrescar el DCF bastaría apuntar Valuation!G19 a Market_Package!B7 y Historical!B20 a Market_Package!B8; se deja sin cablear para no mover los outputs ya gateados.
A96: H3 — El WACC de esta hoja (B45) se construye desde inputs fechados; el WACC del DCF (Assumptions!C20:E20) es un supuesto de escenario. La diferencia está en B47. Cablear Assumptions!C20 a B45 rompería el diseño de escenarios Base/Bull/Bear, así que se deja como contraste.
A97: L1 — La beta es de proveedor (stockanalysis.com), no una estimación propia. Una beta calculada con retornos mensuales de 5 años contra el S&P 500 sería reproducible; el paquete de datos local no trae la serie de precios para hacerlo.
A98: L2 — La ERP es la implícita de Damodaran al 2026-01-01, no al 2026-08-13. Es la observación citable más reciente de esa serie; usarla con un Rf de agosto mezcla fechas y está declarado aquí a propósito.
A99: L3 — El costo de deuda es un benchmark de índice AA, no una curva propia de Apple. La emisión FY2025 de la propia compañía (B35) es el cross-check del emisor.
A100: L4 — El EV mezcla precio del 2026-08-13 con balance del 2025-09-27 (el balance más reciente DEL MODELO, como pide el alcance). El bloque 5 muestra el mismo EV con el balance del 2026-06-27 para dimensionar el desfase.
A101: L5 — El control de procedencia del bloque 6 exige desde 2026-08-14 que toda fecha sea un SERIAL de fecha (no texto), que los inputs de cotización diaria (precio, Rf y Kd) no difieran entre sí en más de 5 días, y que la observación más reciente no tenga más de 10 días contra HOY() al recalcular. Antes solo verificaba que la celda no estuviera vacía, y por eso dejó pasar un Kd fechado como texto "2026-08" y desfasado tres días hábiles; y hasta la segunda verificación el desfase era solo relativo, así que un paquete uniformemente obsoleto (las cuatro fechas en enero) pasaba
A103: 8. ANCLAS DE VINTAGE DISTINTO — 10-Q Q3 FY2026 (accn 0000320193-26-000020, radicado el 2026-07-31), balance condensado R4
A104: Efectivo e inversiones al 2025-09-27 según el 10-Q Q3 FY2026 (columna comparativa) | B104: 132420 | C104: USD m | D104: 45927 | E104: 10-Q Q3 FY2026 (accn 0000320193-26-000020), R4, columna "Sep. 27, 2025": 35,934 + 18,763 + 77,723 | F104: Constante tecleada del filing, NO fórmula contra BS_Hist: mismo período que el balance FY2025A del modelo pero publicada en un documento distinto (vintage independiente). Los checks 51 y 52 exigen tie EXACTO contra esta ancla: si alguien corrompe BS_Hist de forma consistente (partida y subtotal a la vez), el tie cae
A105: Deuda bruta al 2025-09-27 según el 10-Q Q3 FY2026 (columna comparativa) | B105: 98657 | C105: USD m | D105: 45927 | E105: 10-Q Q3 FY2026 (accn 0000320193-26-000020), R4, columna "Sep. 27, 2025": 7,979 + 12,350 + 78,328 | F105: Constante tecleada del filing. Los checks 51 y 53 exigen tie EXACTO contra esta ancla; incluye papel comercial, deuda a término corriente y no corriente
A106: Las cifras al 2026-06-27 de esta misma fuente viven en B82 y B83 (bloque 5) y son las anclas de BANDA de los checks 52 y 53 (±15% caja, ±25% deuda; deriva real observada: caja −9.6%, deuda +17.0% por retiro de papel comercial y deuda a término)

Sheet Claude Code Log
A1: Turn # | B1: Date | C1: User Request | D1: Action Taken | E1: Details | F1: Outcome
A2: 1 | B2: 46324.359 | C2: Prepare a public model copy | D2: Remove local paths and private build references; preserve financial formulas and inputs | E2: Agent run with MOG as the tool, checked by guard v1. The guard measured every sheet before and after the run. Changed: Change_Log: 1 cell written, at B9; Gate_9of10: 3 cells written, at E12, B24, B25; Sources_Audited: 1 cell written, at B10. Agent: OpenFinmods export | F2: Compare against source and review public copy
