Workbook

Sheet 00_Cover
A1: Cargill, Incorporated — Controlled Disclosure-Limited Model
A2: Agriculture / commodities | USD millions | Controlled version 2.0 | As of 2026-07-16
A4: Model field | B4: Value
A5: Legal entity / identifier | B5: Private family company
A6: Model archetype | B6: Revenue scenario framework; valuation suppressed
A7: Model status | B7: ='9_10_Blockers'!$B$16 -> NOT CERTIFIED — source/disclosure blocker
A8: Reporting currency | B8: USD
A9: Model units | B9: USD millions
A10: Valuation date | B10: Not applicable — disclosure blocker
A11: Active case | B11: =CHOOSE(Assumptions!$B$3,"Base","Bull","Bear") -> Base
A12: Primary source route | B12: https://www.cargill.com/doc/1432279934974/2025-cargill-annual-report.pdf
A13: Purpose | B13: Source-backed disclosed-facts model with operational decision-use gate
A14: Decision use | B14: Revenue context only; no DCF, equity value or price target
A15: Key limitation | B15: The official FY2025 annual report discloses $154bn revenue but no complete audited IS/BS/CF, net debt, ownership/share bridge or auditor opinion.
A16: Controlled lineage | B16: Cargill_Institutional_Model.xlsx | SHA-256 ea44065b22b3b7559db314a74c39fe687c0e8b1f2ffaf582cbf1044c8e314f1d
A18: Owner evidence only. The controlled workbook does not self-certify a 9/10 result. Independent review must reproduce sources, formulas, scenarios, valuation mechanics, native recalculation and visual QA.

Sheet Sources
A1: Source ledger and claim-level data lineage
A2: Every material historical and valuation input is classified as Reported, Inferred, Assumption, Document identity only, or Not disclosed. Status is formula-driven.
A4: Source ID | B4: Metric / line item | C4: Period / as-of | D4: Value | E4: Units / currency | F4: Source title | G4: Source class | H4: Exact URL / allowed local locator | I4: Page / table / row / section | J4: Retrieved | K4: Workbook destination | L4: Transformation / normalization | M4: Classification | N4: Notes / limitation | O4: Material? | P4: Mapping status
A5: CG-2021-REV | B5: Revenue | C5: FY2021 | D5: 134400 | E5: USD millions | F5: Cargill 2021 Annual Report | G5: Primary — issuer annual report | H5: https://www.cargill.com/doc/1432194192294/2021-cargill-annual-report.pdf | I5: Letter to stakeholders, page 2; $134.4bn in revenues | J5: 2026-07-16 | K5: Historical!B5 | L5: USD billions multiplied by 1,000 | M5: Reported | N5: No audited financial statements or auditor opinion presented in the narrative annual report. | O5: Yes | P5: =IF(O5<>"Yes","N/A",IF(M5="Not disclosed","BLOCKED",IF(AND(H5<>"",I5<>"",K5<>"",M5<>""),"MAPPED","MISSING"))) -> MAPPED
A6: CG-2024-REV | B6: Revenue | C6: FY2024 | D6: 160000 | E6: USD millions | F6: Cargill 2024 Annual Report | G6: Primary — issuer annual report | H6: https://www.cargill.com/doc/1432263180474/2024-annual-report.pdf | I6: Letter to stakeholders — PDF sin numeración impresa, página física 3; "Cargill recorded $160 billion in revenues in fiscal year 2024." Prior citation said "page 2"; the report carries no printed page numbers and the sentence is on the 3rd physical PDF page (re-verified 2026-07-21 against the Wayback capture used in the independent audit). | J6: 2026-07-16 | K6: Historical!E5 | L6: USD billions multiplied by 1,000 | M6: Reported | N6: No complete audited income statement, balance sheet or cash-flow statement in the 17-page report. | O6: Yes | P6: =IF(O6<>"Yes","N/A",IF(M6="Not disclosed","BLOCKED",IF(AND(H6<>"",I6<>"",K6<>"",M6<>""),"MAPPED","MISSING"))) -> MAPPED
A7: CG-2025-REV | B7: Revenue | C7: FY2025 | D7: 154000 | E7: USD millions | F7: Cargill 2025 Annual Report | G7: Primary — issuer annual report | H7: https://www.cargill.com/doc/1432279934974/2025-cargill-annual-report.pdf | I7: Letter to stakeholders — PDF sin numeración impresa, página física 3; "we recorded $154 billion in revenue in fiscal year 2025." Prior citation said "page 2"; the report carries no printed page numbers and the sentence is on the 3rd physical PDF page (re-verified 2026-07-21). | J7: 2026-07-16 | K7: Historical!F5 | L7: USD billions multiplied by 1,000 | M7: Reported | N7: Only material financial line item disclosed in the official annual report. | O7: Yes | P7: =IF(O7<>"Yes","N/A",IF(M7="Not disclosed","BLOCKED",IF(AND(H7<>"",I7<>"",K7<>"",M7<>""),"MAPPED","MISSING"))) -> MAPPED
A8: CG-2025-EMP | B8: Employees | C8: FY2025 | D8: 155000 | E8: employees | F8: Cargill 2025 Annual Report | G8: Primary — issuer annual report | H8: https://www.cargill.com/doc/1432279934974/2025-cargill-annual-report.pdf | I8: About Cargill, page 3; 155K+ employees | J8: 2026-07-16 | K8: Sector_KPIs!B5 | L8: Lower-bound presentation retained as 155,000 | M8: Reported | N8: Non-financial operating KPI. | O8: No | P8: =IF(O8<>"Yes","N/A",IF(M8="Not disclosed","BLOCKED",IF(AND(H8<>"",I8<>"",K8<>"",M8<>""),"MAPPED","MISSING"))) -> N/A
A9: CG-2025-COUNTRIES | B9: Countries of operation | C9: FY2025 | D9: 70 | E9: countries | F9: Cargill 2025 Annual Report | G9: Primary — issuer annual report | H9: https://www.cargill.com/doc/1432279934974/2025-cargill-annual-report.pdf | I9: About Cargill, page 3; 70 countries | J9: 2026-07-16 | K9: Sector_KPIs!B6 | L9: No transformation | M9: Reported | N9: Non-financial operating KPI. | O9: No | P9: =IF(O9<>"Yes","N/A",IF(M9="Not disclosed","BLOCKED",IF(AND(H9<>"",I9<>"",K9<>"",M9<>""),"MAPPED","MISSING"))) -> N/A
A10: CG-2025-MARKETS | B10: Markets served | C10: FY2025 | D10: 125 | E10: markets | F10: Cargill 2025 Annual Report | G10: Primary — issuer annual report | H10: https://www.cargill.com/doc/1432279934974/2025-cargill-annual-report.pdf | I10: About Cargill, page 3; 125 markets | J10: 2026-07-16 | K10: Sector_KPIs!B7 | L10: No transformation | M10: Reported | N10: Non-financial operating KPI. | O10: No | P10: =IF(O10<>"Yes","N/A",IF(M10="Not disclosed","BLOCKED",IF(AND(H10<>"",I10<>"",K10<>"",M10<>""),"MAPPED","MISSING"))) -> N/A
A11: CG-MISSING-GROSS-PROFIT | B11: Gross profit | C11: FY2025 | E11: USD millions unless ownership | F11: Cargill 2025 Annual Report | G11: Primary source reviewed; disclosure absent | H11: https://www.cargill.com/doc/1432279934974/2025-cargill-annual-report.pdf | I11: Official 17-page report reviewed; no audited IS/BS/CF table or auditor opinion and no claim-level line item | J11: 2026-07-16 | K11: Historical / Valuation readiness | L11: None; value intentionally not inferred | M11: Not disclosed | N11: Material disclosure blocker; headline DCF and equity value are suppressed. | O11: Yes | P11: =IF(O11<>"Yes","N/A",IF(M11="Not disclosed","BLOCKED",IF(AND(H11<>"",I11<>"",K11<>"",M11<>""),"MAPPED","MISSING"))) -> BLOCKED
A12: CG-MISSING-OPERATING-PROFIT-EBIT | B12: Operating profit / EBIT | C12: FY2025 | E12: USD millions unless ownership | F12: Cargill 2025 Annual Report | G12: Primary source reviewed; disclosure absent | H12: https://www.cargill.com/doc/1432279934974/2025-cargill-annual-report.pdf | I12: Official 17-page report reviewed; no audited IS/BS/CF table or auditor opinion and no claim-level line item | J12: 2026-07-16 | K12: Historical / Valuation readiness | L12: None; value intentionally not inferred | M12: Not disclosed | N12: Material disclosure blocker; headline DCF and equity value are suppressed. | O12: Yes | P12: =IF(O12<>"Yes","N/A",IF(M12="Not disclosed","BLOCKED",IF(AND(H12<>"",I12<>"",K12<>"",M12<>""),"MAPPED","MISSING"))) -> BLOCKED
A13: CG-MISSING-NET-INCOME-ATTRIBUTABLE | B13: Net income attributable | C13: FY2025 | E13: USD millions unless ownership | F13: Cargill 2025 Annual Report | G13: Primary source reviewed; disclosure absent | H13: https://www.cargill.com/doc/1432279934974/2025-cargill-annual-report.pdf | I13: Official 17-page report reviewed; no audited IS/BS/CF table or auditor opinion and no claim-level line item | J13: 2026-07-16 | K13: Historical / Valuation readiness | L13: None; value intentionally not inferred | M13: Not disclosed | N13: Material disclosure blocker; headline DCF and equity value are suppressed. | O13: Yes | P13: =IF(O13<>"Yes","N/A",IF(M13="Not disclosed","BLOCKED",IF(AND(H13<>"",I13<>"",K13<>"",M13<>""),"MAPPED","MISSING"))) -> BLOCKED
A14: CG-MISSING-CASH-FROM-OPERATIONS | B14: Cash from operations | C14: FY2025 | E14: USD millions unless ownership | F14: Cargill 2025 Annual Report | G14: Primary source reviewed; disclosure absent | H14: https://www.cargill.com/doc/1432279934974/2025-cargill-annual-report.pdf | I14: Official 17-page report reviewed; no audited IS/BS/CF table or auditor opinion and no claim-level line item | J14: 2026-07-16 | K14: Historical / Valuation readiness | L14: None; value intentionally not inferred | M14: Not disclosed | N14: Material disclosure blocker; headline DCF and equity value are suppressed. | O14: Yes | P14: =IF(O14<>"Yes","N/A",IF(M14="Not disclosed","BLOCKED",IF(AND(H14<>"",I14<>"",K14<>"",M14<>""),"MAPPED","MISSING"))) -> BLOCKED
A15: CG-MISSING-CAPITAL-EXPENDITURE | B15: Capital expenditure | C15: FY2025 | E15: USD millions unless ownership | F15: Cargill 2025 Annual Report | G15: Primary source reviewed; disclosure absent | H15: https://www.cargill.com/doc/1432279934974/2025-cargill-annual-report.pdf | I15: Official 17-page report reviewed; no audited IS/BS/CF table or auditor opinion and no claim-level line item | J15: 2026-07-16 | K15: Historical / Valuation readiness | L15: None; value intentionally not inferred | M15: Not disclosed | N15: Material disclosure blocker; headline DCF and equity value are suppressed. | O15: Yes | P15: =IF(O15<>"Yes","N/A",IF(M15="Not disclosed","BLOCKED",IF(AND(H15<>"",I15<>"",K15<>"",M15<>""),"MAPPED","MISSING"))) -> BLOCKED
A16: CG-MISSING-TOTAL-ASSETS | B16: Total assets | C16: FY2025 | E16: USD millions unless ownership | F16: Cargill 2025 Annual Report | G16: Primary source reviewed; disclosure absent | H16: https://www.cargill.com/doc/1432279934974/2025-cargill-annual-report.pdf | I16: Official 17-page report reviewed; no audited IS/BS/CF table or auditor opinion and no claim-level line item | J16: 2026-07-16 | K16: Historical / Valuation readiness | L16: None; value intentionally not inferred | M16: Not disclosed | N16: Material disclosure blocker; headline DCF and equity value are suppressed. | O16: Yes | P16: =IF(O16<>"Yes","N/A",IF(M16="Not disclosed","BLOCKED",IF(AND(H16<>"",I16<>"",K16<>"",M16<>""),"MAPPED","MISSING"))) -> BLOCKED
A17: CG-MISSING-TOTAL-LIABILITIES | B17: Total liabilities | C17: FY2025 | E17: USD millions unless ownership | F17: Cargill 2025 Annual Report | G17: Primary source reviewed; disclosure absent | H17: https://www.cargill.com/doc/1432279934974/2025-cargill-annual-report.pdf | I17: Official 17-page report reviewed; no audited IS/BS/CF table or auditor opinion and no claim-level line item | J17: 2026-07-16 | K17: Historical!F12 | L17: None; value intentionally not inferred | M17: Not disclosed | N17: Material disclosure blocker; headline DCF and equity value are suppressed. | O17: Yes | P17: =IF(O17<>"Yes","N/A",IF(M17="Not disclosed","BLOCKED",IF(AND(H17<>"",I17<>"",K17<>"",M17<>""),"MAPPED","MISSING"))) -> BLOCKED
A18: CG-MISSING-SHAREHOLDERS-EQUITY | B18: Shareholders' equity | C18: FY2025 | E18: USD millions unless ownership | F18: Cargill 2025 Annual Report | G18: Primary source reviewed; disclosure absent | H18: https://www.cargill.com/doc/1432279934974/2025-cargill-annual-report.pdf | I18: Official 17-page report reviewed; no audited IS/BS/CF table or auditor opinion and no claim-level line item | J18: 2026-07-16 | K18: Historical / Valuation readiness | L18: None; value intentionally not inferred | M18: Not disclosed | N18: Material disclosure blocker; headline DCF and equity value are suppressed. | O18: Yes | P18: =IF(O18<>"Yes","N/A",IF(M18="Not disclosed","BLOCKED",IF(AND(H18<>"",I18<>"",K18<>"",M18<>""),"MAPPED","MISSING"))) -> BLOCKED
A19: CG-MISSING-ADJUSTED-NET-BORROWINGS | B19: Adjusted net borrowings | C19: FY2025 | E19: USD millions unless ownership | F19: Cargill 2025 Annual Report | G19: Primary source reviewed; disclosure absent | H19: https://www.cargill.com/doc/1432279934974/2025-cargill-annual-report.pdf | I19: Official 17-page report reviewed; no audited IS/BS/CF table or auditor opinion and no claim-level line item | J19: 2026-07-16 | K19: Historical / Valuation readiness | L19: None; value intentionally not inferred | M19: Not disclosed | N19: Material disclosure blocker; headline DCF and equity value are suppressed. | O19: Yes | P19: =IF(O19<>"Yes","N/A",IF(M19="Not disclosed","BLOCKED",IF(AND(H19<>"",I19<>"",K19<>"",M19<>""),"MAPPED","MISSING"))) -> BLOCKED
A20: CG-MISSING-CASH-AND-CASH-EQUIVALENTS | B20: Cash and cash equivalents | C20: FY2025 | E20: USD millions unless ownership | F20: Cargill 2025 Annual Report | G20: Primary source reviewed; disclosure absent | H20: https://www.cargill.com/doc/1432279934974/2025-cargill-annual-report.pdf | I20: Official 17-page report reviewed; no audited IS/BS/CF table or auditor opinion and no claim-level line item | J20: 2026-07-16 | K20: Historical / Valuation readiness | L20: None; value intentionally not inferred | M20: Not disclosed | N20: Material disclosure blocker; headline DCF and equity value are suppressed. | O20: Yes | P20: =IF(O20<>"Yes","N/A",IF(M20="Not disclosed","BLOCKED",IF(AND(H20<>"",I20<>"",K20<>"",M20<>""),"MAPPED","MISSING"))) -> BLOCKED
A21: CG-MISSING-SHARES-OUTSTANDING-OWNERSHIP-BRIDGE | B21: Shares outstanding / ownership bridge | C21: FY2025 | E21: USD millions unless ownership | F21: Cargill 2025 Annual Report | G21: Primary source reviewed; disclosure absent | H21: https://www.cargill.com/doc/1432279934974/2025-cargill-annual-report.pdf | I21: Official 17-page report reviewed; no audited IS/BS/CF table or auditor opinion and no claim-level line item | J21: 2026-07-16 | K21: Historical / Valuation readiness | L21: None; value intentionally not inferred | M21: Not disclosed | N21: Material disclosure blocker; headline DCF and equity value are suppressed. | O21: Yes | P21: =IF(O21<>"Yes","N/A",IF(M21="Not disclosed","BLOCKED",IF(AND(H21<>"",I21<>"",K21<>"",M21<>""),"MAPPED","MISSING"))) -> BLOCKED
A22: CG-A-GROWTH | B22: Revenue growth | C22: FY2026E-FY2030E | D22: 0.02 | E22: % | F22: Model-owned assumption | G22: Model assumption | H22: Assumptions sheet | I22: Revenue growth scenario row | J22: 2026-07-16 | K22: Assumptions!B5:E5 | L22: Bear/Base/Bull = -5%/2%/6% | M22: Assumption | N22: Revenue-only scenario; no profitability or valuation conclusion. | O22: Yes | P22: =IF(O22<>"Yes","N/A",IF(M22="Not disclosed","BLOCKED",IF(AND(H22<>"",I22<>"",K22<>"",M22<>""),"MAPPED","MISSING"))) -> MAPPED
A23: CG-A-WACC | B23: WACC | C23: Valuation readiness | E23: % | F23: Not set — disclosure blocker | G23: Model assumption blocked | H23: Assumptions sheet | I23: WACC row intentionally blank | J23: 2026-07-16 | K23: Assumptions!B14:E14 | L23: No WACC set without FCFF/net-debt base | M23: Not disclosed | N23: Valuation input suppressed until complete audited financials are provided. | O23: Yes | P23: =IF(O23<>"Yes","N/A",IF(M23="Not disclosed","BLOCKED",IF(AND(H23<>"",I23<>"",K23<>"",M23<>""),"MAPPED","MISSING"))) -> BLOCKED
A24: CG-A-TG | B24: Terminal growth | C24: Valuation readiness | E24: % | F24: Not set — disclosure blocker | G24: Model assumption blocked | H24: Assumptions sheet | I24: Terminal growth row intentionally blank | J24: 2026-07-16 | K24: Assumptions!B15:E15 | L24: No terminal growth set without FCFF base | M24: Not disclosed | N24: Valuation input suppressed until complete audited financials are provided. | O24: Yes | P24: =IF(O24<>"Yes","N/A",IF(M24="Not disclosed","BLOCKED",IF(AND(H24<>"",I24<>"",K24<>"",M24<>""),"MAPPED","MISSING"))) -> BLOCKED
A25: CG-2022-REV | B25: Revenue | C25: FY2022 | D25: 165000 | E25: USD millions | F25: Cargill 2022 Annual Report | G25: Primary — issuer annual report | H25: https://www.cargill.com/doc/1432215917376/2022-cargill-annual-report.pdf (primary, direct fetch 403 in-session; confirmed via Wayback Machine capture: https://web.archive.org/web/20220812145333/https://www.cargill.com/doc/1432215917376/2022-cargill-annual-report.pdf) | I25: Letter to stakeholders — PDF sin numeración impresa, página física 3 (also restated p. 5, "About Cargill" infographic): "we recorded $165 billion in revenues this fiscal year, a 23% increase." Confirmed directly against the primary issuer PDF via Wayback Machine capture 20220812145333 (2026-07-21 remediation pass), superseding the prior secondary-press-only corroboration. Local archived copy: the maintainer's archive | J25: 2026-07-21 | K25: Historical!C5 | L25: USD billions multiplied by 1,000 | M25: Reported | N25: No complete audited income statement, balance sheet or cash-flow statement published; narrative annual report only. Revenue figure now confirmed directly from the primary PDF (Wayback capture), not secondary press. | O25: Yes | P25: =IF(O25<>"Yes","N/A",IF(M25="Not disclosed","BLOCKED",IF(AND(H25<>"",I25<>"",K25<>"",M25<>""),"MAPPED","MISSING"))) -> MAPPED
A26: CG-2023-REV | B26: Revenue | C26: FY2023 | D26: 177000 | E26: USD millions | F26: Cargill 2023 Annual Report | G26: Primary — issuer annual report | H26: https://www.cargill.com/about/doc/1432242761261/2023-cargill-annual-report.pdf (primary, direct fetch 403 in-session; confirmed via Wayback Machine capture: https://web.archive.org/web/20230806150828/https://www.cargill.com/about/doc/1432242761261/2023-cargill-annual-report.pdf) | I26: PDF sin numeración impresa, página física 2 ("$177B" at-a-glance infographic) and página física 4 (letter to stakeholders): "customers’ partnership, Cargill recorded $177 billion ... alone." Confirmed directly against the primary issuer PDF via Wayback Machine capture 20230806150828 (2026-07-21 remediation pass), superseding the prior secondary-press-only corroboration. Local archived copy: the maintainer's archive | J26: 2026-07-21 | K26: Historical!D5 | L26: USD billions multiplied by 1,000 | M26: Reported | N26: No complete audited income statement, balance sheet or cash-flow statement published; narrative annual report only. Revenue figure now confirmed directly from the primary PDF (Wayback capture), not secondary press. | O26: Yes | P26: =IF(O26<>"Yes","N/A",IF(M26="Not disclosed","BLOCKED",IF(AND(H26<>"",I26<>"",K26<>"",M26<>""),"MAPPED","MISSING"))) -> MAPPED
A27: CG-2026-CREDIT | B27: Credit ratings (S&P / Moody's / D&B) | C27: As published (retrieved 2026-07-21) | D27: S&P A / A-1; Moody's A2 / P-1; D&B 5A1 | E27: rating scale | F27: Cargill "Credit and financial information" page | G27: Primary — issuer investor page (live URL returned HTTP 403 to automated fetch; retrieved via Wayback Machine snapshot) | H27: https://www.cargill.com/about/financial/credit-financial-information (archived: http://web.archive.org/web/20260517174626/https://www.cargill.com/about/financial/credit-financial-information) | I27: Page body: "Standard & Poor's A / A-1; Moody's Investors Service A2 / P-1; Dun & Bradstreet 5A1 / 00-624-9189." Page also states: detailed financials are "Private access for authorized users" only, via registration at financials@cargill.com. | J27: 46224 | K27: Source_Ceiling | L27: No transformation; ratings recorded as published | M27: Reported | N27: Definitive evidence that Cargill's full financial statements are not public: the issuer's own IR page gates them behind an authorized-user portal. Used to set the Source_Ceiling assessment. | O27: Yes | P27: =IF(O27<>"Yes","N/A",IF(M27="Not disclosed","BLOCKED",IF(AND(H27<>"",I27<>"",K27<>"",M27<>""),"MAPPED","MISSING"))) -> MAPPED

Sheet Historical
A1: Historical financials
A2: USD millions. Blanks are intentional when no claim-level primary-source mapping was available.
A4: Metric | B4: 2021A | C4: 2022A | D4: 2023A | E4: 2024A | F4: 2025A | G4: Source mapping | H4: Classification
A5: Revenue | B5: 134400 | C5: 165000 | D5: 177000 | E5: 160000 | F5: 154000 | G5: Sources ledger | H5: =IF(COUNT(B5:F5)=0,"Not disclosed","Reported; see Sources") -> Reported; see Sources
A6: Gross profit | G6: Sources ledger | H6: =IF(COUNT(B6:F6)=0,"Not disclosed","Reported; see Sources") -> Not disclosed
A7: Operating profit / EBIT | G7: Sources ledger | H7: =IF(COUNT(B7:F7)=0,"Not disclosed","Reported; see Sources") -> Not disclosed
A8: Net income attributable | G8: Sources ledger | H8: =IF(COUNT(B8:F8)=0,"Not disclosed","Reported; see Sources") -> Not disclosed
A9: Cash from operations | G9: Sources ledger | H9: =IF(COUNT(B9:F9)=0,"Not disclosed","Reported; see Sources") -> Not disclosed
A10: Capital expenditure | G10: Sources ledger | H10: =IF(COUNT(B10:F10)=0,"Not disclosed","Reported; see Sources") -> Not disclosed
A11: Total assets | G11: Sources ledger | H11: =IF(COUNT(B11:F11)=0,"Not disclosed","Reported; see Sources") -> Not disclosed
A12: Total liabilities | B12: =IF(AND(B11<>"",B13<>""),B11-B13,"") | C12: =IF(AND(C11<>"",C13<>""),C11-C13,"") | D12: =IF(AND(D11<>"",D13<>""),D11-D13,"") | E12: =IF(AND(E11<>"",E13<>""),E11-E13,"") | F12: =IF(AND(F11<>"",F13<>""),F11-F13,"") | G12: Assets less equity | H12: Inferred where inputs exist
A13: Shareholders' equity | G13: Sources ledger | H13: =IF(COUNT(B13:F13)=0,"Not disclosed","Reported; see Sources") -> Not disclosed
A14: Adjusted net borrowings | G14: Sources ledger | H14: =IF(COUNT(B14:F14)=0,"Not disclosed","Reported; see Sources") -> Not disclosed
A15: Cash and cash equivalents | G15: Sources ledger | H15: =IF(COUNT(B15:F15)=0,"Not disclosed","Reported; see Sources") -> Not disclosed
A16: Shares outstanding (mm) | G16: Sources ledger | H16: =IF(COUNT(B16:F16)=0,"Not disclosed","Reported; see Sources") -> Not disclosed

Sheet Assumptions
A1: Assumptions and scenarios
A2: Blue-font cells are model inputs. Selector: 1 = Base, 2 = Bull, 3 = Bear. Active results are formulas and are not editable drivers.
A3: Scenario selector | B3: 1
A4: Metric | B4: Bear | C4: Base | D4: Bull | E4: Active | F4: Rationale / source
A5: 2026 revenue growth | B5: -0.05 | C5: 0.02 | D5: 0.06 | E5: =CHOOSE($B$3,C5,D5,B5) -> 0.02 | F5: Revenue-only model assumptions; no profitability conclusion
A6: 2026 EBIT margin | E6: =CHOOSE($B$3,C6,D6,B6) -> 0 | F6: Blocked — EBIT not disclosed
A7: 2027-2030 revenue growth | B7: -0.02 | C7: 0.02 | D7: 0.05 | E7: =CHOOSE($B$3,C7,D7,B7) -> 0.02 | F7: Revenue-only scenario; illustrative
A8: 2027-2030 EBIT margin | E8: =CHOOSE($B$3,C8,D8,B8) -> 0 | F8: Blocked — EBIT not disclosed
A9: Cash tax rate | E9: =CHOOSE($B$3,C9,D9,B9) -> 0 | F9: Blocked — tax / profit not disclosed
A10: D&A / revenue | E10: =CHOOSE($B$3,C10,D10,B10) -> 0 | F10: Blocked — D&A not disclosed
A11: 2026 capital expenditure | E11: =CHOOSE($B$3,C11,D11,B11) -> 0 | F11: Blocked — capex not disclosed
A12: 2027-2030 capex / revenue | E12: =CHOOSE($B$3,C12,D12,B12) -> 0 | F12: Blocked — capex not disclosed
A13: Operating working capital / revenue | E13: =CHOOSE($B$3,C13,D13,B13) -> 0 | F13: Blocked — working capital not disclosed
A14: WACC | E14: =CHOOSE($B$3,C14,D14,B14) -> 0 | F14: Intentionally blank until FCFF/net-debt base is sourced
A15: Terminal growth | E15: =CHOOSE($B$3,C15,D15,B15) -> 0 | F15: Intentionally blank until FCFF base is sourced
A17: Valuation and profitability inputs are intentionally blank. This is an operational control, not an incomplete styling choice: downstream forecast and valuation outputs are suppressed until material source fields are mapped.

Sheet Forecast
A1: Forecast model
A2: USD millions. Forecast outputs are formula-driven and guarded by source readiness.
A4: Metric | B4: 2025A | C4: 2026E | D4: 2027E | E4: 2028E | F4: 2029E | G4: 2030E
A5: Revenue | B5: 154000 | C5: =IF(AND(B5<>"",Assumptions!$E$5<>""),B5*(1+Assumptions!$E$5),"") -> 157080 | D5: =IF(AND(C5<>"",Assumptions!$E$7<>""),C5*(1+Assumptions!$E$7),"") -> 160221.6 | E5: =IF(AND(D5<>"",Assumptions!$E$7<>""),D5*(1+Assumptions!$E$7),"") -> 163426.03 | F5: =IF(AND(E5<>"",Assumptions!$E$7<>""),E5*(1+Assumptions!$E$7),"") -> 166694.55 | G5: =IF(AND(F5<>"",Assumptions!$E$7<>""),F5*(1+Assumptions!$E$7),"") -> 170028.44
A6: Growth | C6: =IF(AND(B5<>"",C5<>""),C5/B5-1,"") -> 0.02 | D6: =IF(AND(C5<>"",D5<>""),D5/C5-1,"") -> 0.02 | E6: =IF(AND(D5<>"",E5<>""),E5/D5-1,"") -> 0.02 | F6: =IF(AND(E5<>"",F5<>""),F5/E5-1,"") -> 0.02 | G6: =IF(AND(F5<>"",G5<>""),G5/F5-1,"") -> 0.02
A7: EBIT margin
A8: EBIT
A9: Cash tax rate
A10: NOPAT
A11: D&A
A12: Capital expenditure
A13: Operating working capital
A14: Change in NWC
A15: FCFF
A16: Adjusted net borrowings
A17: Shares outstanding (mm)
A19: Forecast guard: revenue may project only when a reported base exists. Profitability, FCFF and valuation rows remain blank because the source ledger contains material BLOCKED classifications.

Sheet Valuation
A1: Valuation readiness — headline output suppressed
A2: The workbook blocks any DCF, enterprise value, equity value or price target when material source fields are absent.
A4: Requirement | B4: Actual | C4: Expected | D4: Difference | E4: Tolerance | F4: Status | G4: Disposition / fix
A5: Reported revenue base | B5: 1 | C5: 1 | D5: =B5-C5 -> 0 | E5: 0 | F5: =IF(ABS(D5)<=E5,"PASS","BLOCKED") -> PASS | G5: Available: FY2025 revenue
A6: Reported EBIT / operating profit | B6: 0 | C6: 1 | D6: =B6-C6 -> -1 | E6: 0 | F6: =IF(ABS(D6)<=E6,"PASS","BLOCKED") -> BLOCKED | G6: Required for normalized operating profitability
A7: Cash flow / capex / working capital | B7: 0 | C7: 3 | D7: =B7-C7 -> -3 | E7: 0 | F7: =IF(ABS(D7)<=E7,"PASS","BLOCKED") -> BLOCKED | G7: Required for FCFF
A8: Cash / debt or net debt | B8: 0 | C8: 1 | D8: =B8-C8 -> -1 | E8: 0 | F8: =IF(ABS(D8)<=E8,"PASS","BLOCKED") -> BLOCKED | G8: Required for EV-to-equity bridge
A9: Ownership / share bridge | B9: 0 | C9: 1 | D9: =B9-C9 -> -1 | E9: 0 | F9: =IF(ABS(D9)<=E9,"PASS","BLOCKED") -> BLOCKED | G9: Private company ownership data not disclosed
A10: WACC and terminal method | B10: 0 | C10: 2 | D10: =B10-C10 -> -2 | E10: 0 | F10: =IF(ABS(D10)<=E10,"PASS","BLOCKED") -> BLOCKED | G10: Intentionally unset until FCFF base is sourced
A11: Headline enterprise value | B11: NOT DECISION-READY | C11: NOT DECISION-READY | F11: SUPPRESSED | G11: No numeric output is presented
A12: Headline equity value | B12: NOT DECISION-READY | C12: NOT DECISION-READY | F12: SUPPRESSED | G12: No implied precision
A13: Overall valuation gate | F13: =IF(COUNTIF(F5:F10,"BLOCKED")>0,"NOT DECISION-READY","READY FOR REVIEW") -> NOT DECISION-READY | G13: Source/disclosure blocker
A15: Exact blocker: Cargill's official 17-page FY2025 annual report discloses revenue but not a complete audited income statement, balance sheet, cash-flow statement, auditor opinion, net debt or ownership/share data. A full DCF/equity value would invent material facts.

Sheet Sensitivity
A1: Sensitivity control
A2: No valuation sensitivity is produced while the valuation gate is NOT DECISION-READY.
A4: Test | B4: Input 1 | C4: Input 2 | D4: Input 3 | E4: Output 1 | F4: Output 2 | G4: Status
A5: Revenue scenario selector | B5: 1 | C5: 2 | D5: 3 | E5: =Forecast!C5 -> 157080 | F5: =Forecast!G5 -> 170028.44 | G5: PARTIAL — revenue only
A6: Valuation sensitivity | E6: NOT DECISION-READY | F6: NOT DECISION-READY | G6: SUPPRESSED
A7: WACC / g grid | G7: SUPPRESSED
A8: Equity/share sensitivity | G8: SUPPRESSED
A9: Required fix | G9: Load claim-level audited financial inputs
A10: Blocker class | G10: SOURCE / DISCLOSURE
A12: Guardrail: a blank or zero sensitivity matrix would imply a valuation was attempted. Instead, the workbook explicitly suppresses valuation outputs until required source fields are complete.

Sheet Checks
A1: Model checks and decision-use gate
A2: Each assertion shows Actual, Expected, Difference, Tolerance, formula-driven Status and a fix hint.
A4: Check | B4: Actual | C4: Expected | D4: Difference | E4: Tolerance | F4: Status | G4: Location / fix hint
A5: Material source mappings | B5: =COUNTIF(Sources!$P$5:$P$27,"MAPPED") -> 7 | C5: =COUNTIF(Sources!$O$5:$O$27,"Yes") -> 20 | D5: =B5-C5 -> -13 | E5: 0 | F5: =IF(COUNTIF(Sources!$P$5:$P$27,"MISSING")>0,"FAIL",IF(COUNTIF(Sources!$P$5:$P$27,"BLOCKED")>0,"BLOCKED",IF(ABS(D5)<=E5,"PASS","FAIL"))) -> BLOCKED | G5: Sources!O:P; map every required field or retain BLOCKED
A6: FY2025 revenue tie | B6: =IF(Historical!F5="",0,Historical!F5) -> 154000 | C6: =IF(Sources!D7="",0,Sources!D7) -> 154000 | D6: =B6-C6 -> 0 | E6: 0.1 | F6: =IF(ABS(D6)<=E6,IF(B6=0,"BLOCKED","PASS"),"FAIL") -> PASS | G6: Historical!F5 vs claim-level Sources value
A7: FY2025 EBIT tie | B7: =IF(Historical!F7="",0,Historical!F7) -> 0 | C7: =0 -> 0 | D7: =B7-C7 -> 0 | E7: 0.1 | F7: =IF(AND(B7=0,C7=0),"BLOCKED",IF(ABS(D7)<=E7,"PASS","FAIL")) -> BLOCKED | G7: Historical!F7 vs claim-level Sources value
A8: Liabilities bridge | B8: =IF(Historical!F12="",0,Historical!F12) -> 0 | C8: =IF(AND(Historical!F11<>"",Historical!F13<>""),Historical!F11-Historical!F13,0) -> 0 | D8: =B8-C8 -> 0 | E8: 0.1 | F8: =IF(AND(B8=0,C8=0),"BLOCKED",IF(ABS(D8)<=E8,"PASS","FAIL")) -> BLOCKED | G8: Historical!F12 = assets - equity
A9: Forecast revenue populated | B9: =COUNT(Forecast!C5:G5) -> 5 | C9: 5 | D9: =B9-C9 -> 0 | E9: 0 | F9: =IF(ABS(D9)<=E9,"PASS","BLOCKED") -> PASS | G9: Forecast!C5:G5
A10: FCFF populated | B10: =COUNT(Forecast!C15:G15) -> 0 | C10: 5 | D10: =B10-C10 -> -5 | E10: 0 | F10: =IF(ABS(D10)<=E10,"PASS","BLOCKED") -> BLOCKED | G10: Forecast!C15:G15
A11: WACC exceeds terminal growth | B11: =IF(AND(Assumptions!E14<>"",Assumptions!E15<>"",Assumptions!E14>Assumptions!E15),1,0) -> 0 | C11: 1 | D11: =B11-C11 -> -1 | E11: 0 | F11: =IF(ABS(D11)<=E11,"PASS","BLOCKED") -> BLOCKED | G11: Assumptions!E14:E15
A12: DCF enterprise-value bridge | B12: =0 -> 0 | C12: =0 -> 0 | D12: =B12-C12 -> 0 | E12: 0.1 | F12: ="BLOCKED" -> BLOCKED | G12: Valuation!B14 = PV explicit + PV terminal
A13: Equity-value bridge | B13: =0 -> 0 | C13: =0 -> 0 | D13: =B13-C13 -> 0 | E13: 0.1 | F13: ="BLOCKED" -> BLOCKED | G13: Valuation!B16 = EV - adjusted net borrowings
A14: Sensitivity center tie | B14: =0 -> 0 | C14: =0 -> 0 | D14: =B14-C14 -> 0 | E14: 0.01 | F14: ="BLOCKED" -> BLOCKED | G14: Sensitivity!D7 = Valuation!B18
A15: Headline valuation suppression | B15: =COUNT(Valuation!B14:B18) -> 0 | C15: 0 | D15: =B15-C15 -> 0 | E15: 0 | F15: =IF(B15=0,"PASS — SUPPRESSED","FAIL") -> PASS — SUPPRESSED | G15: Valuation must remain NOT DECISION-READY
A16: Scenario selector valid | B16: =IF(AND(Assumptions!B3>=1,Assumptions!B3<=3),1,0) -> 1 | C16: 1 | D16: =B16-C16 -> 0 | E16: 0 | F16: =IF(ABS(D16)<=E16,"PASS","FAIL") -> PASS | G16: Assumptions!B3 must be 1, 2 or 3
A18: Overall gate | F18: =IF(COUNTIF(F5:F16,"FAIL")>0,"NOT CERTIFIED — remediable","NOT CERTIFIED — source/disclosure blocker") -> NOT CERTIFIED — source/disclosure blocker
A19: Decision use | B19: Revenue context only; no DCF, equity value or price target

Sheet Sector_KPIs
A1: Sector KPI evidence
A2: Reported operating KPIs are separated from model outputs and missing disclosure requirements.
A4: KPI | B4: 2025A | C4: 2026E | D4: Units | E4: Classification | F4: Source / formula | G4: Status | H4: Decision relevance
A5: Employees | B5: 155000 | D5: employees | E5: Reported | F5: 2025 Annual Report p.3 | G5: Mapped | H5: Operating scale
A6: Countries of operation | B6: 70 | D6: countries | E6: Reported | F6: 2025 Annual Report p.3 | G6: Mapped | H6: Geographic reach
A7: Markets served | B7: 125 | D7: markets | E7: Reported | F7: 2025 Annual Report p.3 | G7: Mapped | H7: Customer reach
A8: Revenue | B8: 154000 | C8: =Forecast!C5 -> 157080 | D8: USDm | E8: Reported / forecast | F8: 2025 Annual Report p.2 / Forecast!C5 | G8: Mapped | H8: Scale and scenario context
A9: EBIT margin | D9: % | E9: Not disclosed | F9: No audited income statement | G9: Blocked | H9: Required for profitability
A10: Capex intensity | D10: % | E10: Not disclosed | F10: No audited cash-flow statement | G10: Blocked | H10: Required for FCFF
A11: Working capital intensity | D11: % | E11: Not disclosed | F11: No audited statements | G11: Blocked | H11: Required for FCFF
A12: Net debt | D12: USDm | E12: Not disclosed | F12: No balance-sheet bridge | G12: Blocked | H12: Required for equity value

Sheet Change_Log
A1: Change log and governance
A2: Controlled version history, scope, evidence and reviewer disposition.
A4: Date | B4: Version | C4: Author / lane | D4: Change | E4: Changed sheets / ranges | F4: Evidence | G4: Reviewer status
A5: 2026-07-15 | B5: 1.0 | C5: Codex baseline | D5: Initial generic institutional model shell | E5: All baseline sheets | F5: Cargill_Institutional_Model.xlsx | G5: Superseded by controlled copy; original preserved
A6: 2026-07-16 | B6: 2.0 | C6: limited-company / consumer-agri cluster | D6: Added claim-level source ledger, corrected disclosure blocker, formula-driven suppression and H0-H9 ledger | E6: 00_Cover; Sources; Historical; Assumptions; Forecast; Valuation; Sensitivity; Checks; Sector_KPIs; Change_Log; added 9_10_Blockers | F6: Companion QA, recalc and evidence package | G6: Independent review pending
A7: 2026-07-16 | B7: 2.0 | C7: limited-company / consumer-agri cluster | D7: Preserved baseline lineage and source boundary | E7: No original workbook edits; no raw Latinex companies/objects/OCR access | F7: Original SHA-256 ea44065b22b3b7559db314a74c39fe687c0e8b1f2ffaf582cbf1044c8e314f1d | G7: Owner verified; independent package review pending
A8: 46224 | B8: 2.1 | C8: Claude (run 41538014) / all-Grok-fanout lane | D8: Elevation pass: sourced and added FY2022 ($165bn) and FY2023 ($177bn) revenue (Cargill 2022/2023 Annual Reports, cross-verified via contemporaneous press after cargill.com returned HTTP 403 to direct automated fetch), completing FY2021A-FY2025A revenue to 5/5 years. Added Sources_Audited, Checks_TieOut and Source_Ceiling sheets to align with the Samsung-pilot IG architecture within Cargill's disclosure limit. Extended Sources/Checks ranges to include the 2 new revenue rows + 1 credit-rating row (27 total); no check tolerance loosened. Independent finding: realistic ceiling is 2/10 (below the maintainer's a-priori ~5), confirmed by Cargill's own gated-financials IR page. | E8: Historical!C5:D5; Sources!A25:P27; Checks!B5,C5,F5; added Sources_Audited, Checks_TieOut, Source_Ceiling | F8: This build (wb.calculate() clean, unzip -t OK); the build report (not published) | G8: Independent review pending
A9: 2026-07-21 | B9: 2.2 | C9: Claude (remediation pass, run d849468b) | D9: Post-audit remediation: retrieved FY2022/FY2023 Cargill Annual Report PDFs directly via Wayback Machine (live cargill.com URLs still 403 to automated fetch) and archived local copies; upgraded Sources!I25/I26 and Sources_Audited!D5/D6 citations from secondary-press corroboration to primary-PDF page-level confirmation. Corrected approximate "page 2" locators on FY2024/FY2025 revenue citations (Sources!I6/I7) to physical-PDF-page locators, since neither report carries printed page numbers. | E9: Sources!H25:J26, N25:N26, I6, I7; Sources_Audited!D5:D6 | F9: the maintainer's archive (cargill_2022_annual_report.pdf, cargill_2023_annual_report.pdf, README.md); the maintainer's archive | G9: Independent review pending

Sheet 9_10_Blockers
A1: Independent 9/10 hard-gate ledger
A2: Owner evidence status only. Independent reviewer results remain pending; no owner self-certification.
A4: Gate | B4: Points | C4: Owner evidence status | D4: Evidence location | E4: Blocker / resolution | F4: Independent result
A5: H0 | B5: 5 | C5: OWNER EVIDENCE COMPLETE | D5: Controlled path, original hash, package integrity and lineage evidence | E5: Independent identity/package reproduction pending | F5: PENDING
A6: H1 | B6: 20 | C6: BLOCKED — SOURCE/DISCLOSURE | D6: Sources!A:P claim-level ledger and formula-driven mapping status | E6: The official FY2025 annual report discloses $154bn revenue but no complete audited IS/BS/CF, net debt, ownership/share bridge or auditor opinion. | F6: PENDING
A7: H2 | B7: 15 | C7: BLOCKED — SOURCE/DISCLOSURE | D7: Historical; Forecast; Checks | E7: Missing material profitability / cash-flow / balance-sheet facts | F7: PENDING
A8: H3 | B8: 10 | C8: PARTIAL — REVENUE ONLY | D8: Assumptions selector; Forecast outputs; Sensitivity | E8: Valuation channel is intentionally suppressed | F8: PENDING
A9: H4 | B9: 15 | C9: BLOCKED — SOURCE/DISCLOSURE | D9: Valuation; Sensitivity; Checks | E9: No defensible FCFF/net-debt/ownership bridge | F9: PENDING
A10: H5 | B10: 8 | C10: OWNER EVIDENCE COMPLETE | D10: Checks with Actual/Expected/Difference/Tolerance/Status/Fix hint | E10: Post-native-recalc error scan evidence required | F10: PENDING
A11: H6 | B11: 10 | C11: OWNER EVIDENCE PREPARED | D11: Companion isolated LibreOffice open/save/reopen log | E11: Independent native-recalc reproduction pending | F11: PENDING
A12: H7 | B12: 7 | C12: OWNER EVIDENCE PREPARED | D12: Companion render manifest for every user-facing sheet | E12: Independent visual review pending | F12: PENDING
A13: H8 | B13: 5 | C13: OWNER EVIDENCE COMPLETE | D13: Source mapping, model mechanics, formula gates and valuation readiness were materially changed | E13: Not a visual-only upgrade | F13: PENDING
A14: H9 | B14: 5 | C14: OWNER EVIDENCE COMPLETE | D14: 00_Cover; Change_Log; this ledger | E14: Independent governance review pending | F14: PENDING
A16: Owner package status | B16: =IF(COUNTIF(C5:C14,"BLOCKED*")>0,"NOT CERTIFIED — source/disclosure blocker","PENDING INDEPENDENT 9/10 REVIEW") -> NOT CERTIFIED — source/disclosure blocker
A18: Exact blocker: The official FY2025 annual report discloses $154bn revenue but no complete audited IS/BS/CF, net debt, ownership/share bridge or auditor opinion. Headline valuation is formula-gated and suppressed as NOT DECISION-READY.

Sheet Sources_Audited
A1: Audited/public source register — Cargill, Incorporated. Cargill is privately held: no SEC filings, no audited consolidated financial statements (IS/BS/CF) and no auditor's opinion are published for any fiscal year.
A3: Model year | B3: Source report | C3: File / URL | D3: Disclosure scope
A4: FY2021A | B4: Cargill 2021 Annual Report | C4: https://www.cargill.com/doc/1432194192294/2021-cargill-annual-report.pdf | D4: Revenue only ($134.4bn)
A5: FY2022A | B5: Cargill 2022 Annual Report | C5: https://www.cargill.com/doc/1432215917376/2022-cargill-annual-report.pdf | D5: Revenue only ($165bn). Confirmed directly against the primary issuer PDF via Wayback Machine capture 20220812145333 (2026-07-21); local copy in the maintainer's archive
A6: FY2023A | B6: Cargill 2023 Annual Report | C6: https://www.cargill.com/about/doc/1432242761261/2023-cargill-annual-report.pdf | D6: Revenue only ($177bn). Confirmed directly against the primary issuer PDF via Wayback Machine capture 20230806150828 (2026-07-21); local copy in the maintainer's archive
A7: FY2024A | B7: Cargill 2024 Annual Report | C7: https://www.cargill.com/doc/1432263180474/2024-annual-report.pdf | D7: Revenue only ($160bn)
A8: FY2025A | B8: Cargill 2025 Annual Report | C8: https://www.cargill.com/doc/1432279934974/2025-cargill-annual-report.pdf | D8: Revenue ($154bn) + non-financial KPIs (employees, countries, markets)
A9: Ongoing | B9: Cargill "Credit and financial information" page | C9: https://www.cargill.com/about/financial/credit-financial-information (Wayback: http://web.archive.org/web/20260517174626/...) | D9: Credit ratings only (S&P A/A-1, Moody's A2/P-1, D&B 5A1); page states full financials are gated behind an authorized-user portal.
A11: Notes: every Historical value is a published constant traceable to the row above (or to Sources for full claim-level lineage, columns A-P). No line item beyond revenue and the FY2025 non-financial KPIs is populated for any year — this is a disclosure limit, not an omission. All recomputation lives in Checks_TieOut. See Source_Ceiling for the realistic elevation-ceiling assessment and rationale.
A12: Currency: Cargill reports natively in USD; no FX conversion / implied-rate layer is required or applicable (unlike foreign-currency issuers such as Samsung).

Sheet Checks_TieOut
A1: Tie-out checks — Cargill disclosed data (revenue is the only multi-year line item; all deltas must be 0)
A2: MASTER | B2: =IF(COUNTIF(G5:G7,"FAIL")=0,"OK — ALL TIE-OUTS PASS (revenue-only scope)","FAIL") -> OK — ALL TIE-OUTS PASS (revenue-only scope)
A4: Check | B4: FY2021A | C4: FY2022A | D4: FY2023A | E4: FY2024A | F4: FY2025A | G4: Status
A5: Revenue: Historical = Sources claim-level ledger | B5: =Historical!B5-Sources!D5 -> 0 | C5: =Historical!C5-Sources!D25 -> 0 | D5: =Historical!D5-Sources!D26 -> 0 | E5: =Historical!E5-Sources!D6 -> 0 | F5: =Historical!F5-Sources!D7 -> 0 | G5: =IF(AND(ABS(N(B5))<=0.5,ABS(N(C5))<=0.5,ABS(N(D5))<=0.5,ABS(N(E5))<=0.5,ABS(N(F5))<=0.5),"PASS","FAIL") -> PASS
A6: No fabrication: non-revenue historical rows remain unpopulated (count, expected 0) | B6: =COUNT(Historical!B6:F11)+COUNT(Historical!B13:F16) -> 0 | G6: =IF(N(B6)=0,"PASS","FAIL") -> PASS
A7: Sources ledger has exactly 5 disclosed revenue-year entries | B7: =COUNT(Sources!D5:D7)+COUNT(Sources!D25:D26) -> 5 | G7: =IF(B7=5,"PASS","FAIL") -> PASS

Sheet Source_Ceiling
A1: Source ceiling assessment — realistic elevation limit for Cargill, Incorporated (private issuer, no SEC filings)
A3: Requirement (full IG statement-grade pattern, per Samsung pilot) | B3: Standard | C3: Available for Cargill | D3: Status
A4: 3-statement audited history (IS/BS/CF, line-item detail, 5 years) | B4: Required | C4: Not published. Cargill's public annual report is a ~15-20 page narrative/sustainability brochure with no financial statements and no auditor's opinion. | D4: BLOCKED
A5: Total revenue (top line) | B5: Required | C5: Disclosed every fiscal year FY2021-FY2025 in the letter to stakeholders. | D5: AVAILABLE (5/5 years)
A6: Gross profit / operating profit (EBIT) / net income | B6: Required | C6: Never disclosed in any public annual report reviewed (FY2021-FY2025). | D6: BLOCKED
A7: Balance sheet (assets / liabilities / equity) | B7: Required | C7: Never disclosed. No total assets, liabilities, equity, or net debt figure in any public source found. | D7: BLOCKED
A8: Cash flow statement (CFO / capex / financing) | B8: Required | C8: Never disclosed. | D8: BLOCKED
A9: Non-financial operating KPIs (employees, countries, markets) | B9: Supplementary | C9: Disclosed in the FY2025 annual report (155,000+ employees, 70 countries, 125 markets). | D9: AVAILABLE
A10: Credit ratings (proxy for creditworthiness, not a financial statement) | B10: Supplementary | C10: Disclosed on Cargill's own IR page: S&P A/A-1, Moody's A2/P-1, D&B 5A1. Same page states full financials are gated behind an authorized-user portal (financials@cargill.com registration) — this is the clearest possible confirmation that the ceiling below is not a search-effort failure. | D10: AVAILABLE (rating only)
A11: WACC / DCF valuation inputs (net debt, share count, ownership bridge) | B11: Required for valuation | C11: Not disclosed; Cargill has no public shares or ownership bridge (family-owned). | D11: BLOCKED
A13: Realistic ceiling (0-10 scale, this-session finding) | B13: the maintainer's a-priori estimate: <10, probably ~5 | C13: 2/10 | D13: BELOW PRIOR ESTIMATE
A14: Rationale for scoring below the ~5 prior estimate | B14: A "5/10" ceiling would require at least one full statement block (e.g. a complete income statement or balance sheet snapshot for one year) to exist in the public domain. For Cargill it does not: only the single revenue figure is published per year, for 5 of 5 years, plus non-financial KPIs and a credit-rating letter grade. No profitability, no balance sheet, no cash flow, no valuation-ready inputs exist publicly for any year. That ceiling is intrinsic to Cargill being a private, non-SEC-reporting issuer — it is not a research-effort gap (confirmed by the issuer's own gated financials portal, row 10).
A15: What this build did within the ceiling | B15: Filled the two missing years of the one available line item (FY2022 revenue $165bn, FY2023 revenue $177bn — both newly sourced and cited this session), completing the FY2021A-FY2025A revenue history to 5/5 years. Added Sources_Audited, Checks_TieOut and this Source_Ceiling sheet to match the Samsung-pattern architecture as far as the data permits. Historical/Forecast/Valuation/Checks/9_10_Blockers gating logic (revenue-only decision use, suppressed DCF/equity value) is preserved unchanged and remains correct given the finding above.
A16: Path to raise the ceiling (not attempted this session — flagged as next step) | B16: (a) Request access via financials@cargill.com to Cargill's authorized-user financial portal (requires an institutional relationship, e.g. as a lender/counterparty — not accessible to this research pass). (b) Check whether Moody's/S&P full credit-opinion PDFs (not just the letter-grade page) are mirrored on a public aggregator and contain summary EBITDA/leverage figures — spot-checked this session (search only) with no public full-text hit; would need direct agency portal access, which is itself gated. (c) Check SEC filings of joint ventures or minority-owned affiliates that might disclose Cargill segment data — not attempted this session.

Sheet Claude Code Log
A1: Turn # | B1: Date | C1: User Request | D1: Action Taken | E1: Details | F1: Outcome
A2: 1 | B2: 46324.359 | C2: Prepare a public model copy | D2: Remove local paths and private build references; preserve financial formulas and inputs | E2: Agent run with MOG as the tool, checked by guard v1. The guard measured every sheet before and after the run. Changed: 00_Cover: 1 cell written, at B16; Sources: 2 cells written, at I25, I26; Change_Log: 4 cells written, at F5, D8, F8, F9; Sources_Audited: 2 cells written, at D5, D6; Source_Ceiling: 1 cell written, at B13. Agent: OpenFinmods export | F2: Compare against source and review public copy
