Workbook

Sheet EEFF
A1: Grupo ASSA, S. A.
A2: Estados Financieros Consolidados Auditados FY21-FY25
A3: en US$ sin escala
A5: Años | B5: FY21A | C5: FY22A | D5: FY23A | E5: FY24A | F5: FY25A | G5: FY26E | H5: FY27E | I5: FY28E | J5: FY29E | K5: FY30E
A6: Estado de Resultados
A7: — Base regulatoria SSRP / NIIF excepto NIIF 17 (FY2021A–FY2024A, filings propios de cada año)
A8: Primas suscritas, netas de cancelaciones | B8: 657884741 | C8: 698200257 | D8: 817173751 | E8: 841095242
A9: Primas suscritas cedidas a reaseguradores | B9: -356304040 | C9: -361584073 | D9: -435628239 | E9: -426032825
A10: Total de primas netas retenidas | B10: 301580701 | C10: 336616184 | D10: 381545512 | E10: 415062417
A11: Cambio en la provisión bruta para riesgo en curso | B11: -9152442 | C11: 3120015 | D11: -28420469 | E11: -475396
A12: Cambio en la provisión en los negocios de vida a largo plazo sobre pólizas de vida | B12: -10285045 | C12: -12525971 | D12: -12302706 | E12: -10311345
A13: Cambio en la participación de los reaseguradores en la provisión sobre contratos de seguros | B13: 9401319 | C13: -6820962 | D13: 16095063
A14: Total de cambios en las provisiones de los contratos de seguros | B14: -10036168 | C14: -16226918 | D14: -24628112 | E14: -19186523
A15: Primas netas ganadas | B15: 291544533 | C15: 320389266 | D15: 356917400 | E15: 395875894
A16: Reclamos y beneficios incurridos | B16: -238994085 | C16: -327863954 | D16: -238087045 | E16: -248414644
A17: Participación de los reaseguradores en los reclamos y beneficios incurridos | B17: 101363600 | C17: 176570373 | D17: 65656958 | E17: 62663262
A18: Beneficios por reembolsos y rescates | B18: -13646362 | C18: -14629260 | D18: -16826376 | E18: -19666415
A19: Reclamos y beneficios netos incurridos por los asegurados | B19: -151276847 | C19: -165922841 | D19: -189256463 | E19: -205417797
A20: Costo de suscripción y adquisición | B20: -89805859 | C20: -98549869 | D20: -115810518 | E20: -126570429
A21: Provisión para pérdidas crediticias esperadas en primas por cobrar | B21: -143340 | C21: -1327507 | D21: -1113601 | E21: -530722
A22: Primas netas ganadas, después de reclamos, costos de suscripción y provisión para pérdidas crediticias esperadas en primas por cobrar | B22: 50318487 | C22: 54589049 | D22: 50736818 | E22: 63356946
A23: Intereses sobre préstamos | B23: 90113580 | C23: 89349229 | D23: 99791323
A24: Intereses sobre depósitos en bancos | B24: 324360 | C24: 852370 | D24: 1871676
A25: Intereses sobre inversiones en valores | B25: 30270095 | C25: 33792124 | D25: 38203473
A26: Total de ingresos por intereses | B26: 120708035 | C26: 123993723 | D26: 139866472
A27: Gastos por intereses sobre depósitos | B27: -25360968 | C27: -25531810 | D27: -34235136
A28: Gastos por intereses sobre emisiones de deuda y obligaciones | B28: -30177384 | C28: -29003930 | D28: -34426805
A29: Total de gastos por intereses | B29: -55538352 | C29: -54535740 | D29: -68661941 | E29: -1028730
A30: Provisión para pérdidas crediticias esperadas en préstamos | B30: -4291456 | C30: -4626793 | D30: -7316131
A31: Ganancia neta por modificación de préstamos a CA | C31: 515213 | D31: 67054
A32: Resultado neto de intereses, comisiones y provisión para pérdidas crediticias esperadas en préstamos | B32: 60878227 | C32: 65346403 | D32: 63955454 | E32: 35051765
A33: Ingresos por comisiones y servicios financieros | B33: 53282269 | C33: 54586912 | D33: 68685561 | E33: 61243501
A34: Ganancia (Pérdida) en venta de bonos y acciones, neto | B34: 2013784 | C34: -240213 | D34: 63303
A35: Dividendos ganados | B35: 24063694 | C35: 30788100 | D35: 40145969 | E35: 51360184
A36: Ganancia (Pérdida) no realizada de inversiones a valor razonable con cambio en resultado | B36: 6681944 | C36: -14025402 | D36: 5542980
A37: Otros ingresos de operaciones, neto | B37: 9840321 | C37: 5497518 | D37: 3537146 | E37: 4229486
A38: Reversión de (provisión para) pérdidas crediticias esperadas en inversiones | B38: -125836 | C38: -582779 | D38: 1442923
A39: Resultados, neto | B39: 206952890 | C39: 195959588 | D39: 234110154 | E39: 219482630
A40: Gastos de personal | B40: -65378406 | C40: -68691932 | D40: -72370796 | E40: -55716075
A41: Gastos generales y administrativos | B41: -39466922 | C41: -41469305 | D41: -41793696 | E41: -24861432
A42: Gastos de depreciación de activos fijos y propiedades de inversión | B42: -6393929 | C42: -7352476 | D42: -6753787 | E42: -5081770
A43: Gastos de amortización de activos intangibles | B43: -5044764 | C43: -4929115 | D43: -5165439 | E43: -5149339
A44: Total de gastos administrativos | B44: -116284021 | C44: -122442828 | D44: -126083718 | E44: -90808616
A45: Utilidad antes del impuesto sobre la renta | B45: 90668869 | C45: 73516760 | D45: 108026436 | E45: 128674014
A46: Impuesto sobre la renta corriente | B46: -8396374 | C46: -12835954 | D46: -13289861
A47: Impuesto sobre la renta diferido | B47: -423906 | C47: 1312298 | D47: 1394727 | E47: 0
A48: Total de gasto de impuesto sobre la renta | B48: -8820280 | C48: -11523656 | D48: -11895134
A49: — NIIF 17 (FY2024A re-expresado · FY2025A) — conciliación del cambio de base en Puente_NIIF17
A50: Ingresos por servicios de seguro | E50: 820306455 | F50: 885435473
A51: Gastos por servicios de seguro | E51: -367877750 | F51: -426466314
A52: Resultados netos de contratos de reaseguro | E52: -314823760 | F52: -313277206
A53: Resultado del servicio de seguro | E53: 137604945 | F53: 145691953
A54: Ingresos por intereses calculados utilizando el método de interés efectivo | E54: 35258108 | F54: 40827249
A55: Otros ingresos por inversiones | E55: 55379789 | F55: 61865524
A56: Pérdida neta por deterioro de activos financieros | E56: 281188 | F56: -70123
A57: Retorno de las inversiones | E57: 90919085 | F57: 102622650
A58: Gastos financieros netos de contratos de seguro | E58: -9221440 | F58: -11097456
A59: Ingresos financieros netos de contratos de reaseguro | E59: 959026 | F59: 2508685
A60: Resultado financiero, neto | E60: 82656671 | F60: 94033879
A61: Otros ingresos | E61: 7941941 | F61: 4999986
... A67: Ganancia o pérdida en ventas de operación descontinuadas, neta de impuesto | E67: -3788890 | F67: 31161580
A68: Utilidad neta | B68: 81848589 | C68: 61993104 | D68: 96131302 | E68: 124645797 | F68: 167153843
A70: Años | B70: FY21A | C70: FY22A | D70: FY23A | E70: FY24A | F70: FY25A | G70: FY26E | H70: FY27E | I70: FY28E | J70: FY29E | K70: FY30E
A71: Balance General
A72: Nota: presentación combina líneas de la base SSRP (FY2021A–FY2024A) y NIIF 17 (FY2024A–FY2025A); conciliación en Puente_NIIF17
A73: Efectivo y equivalentes de efectivo | B73: 270329829 | C73: 228125639 | D73: 232268193 | E73: 66040405 | F73: 81993632
A74: Cuentas por cobrar de seguros y otros, neto | B74: 250244906 | C74: 247213247 | D74: 278176223 | E74: 220675932
A75: Préstamos por cobrar, neto | B75: 994010440 | C75: 1083352786 | D75: 1191506508 | E75: 0 | F75: 0
A76: Inversiones, neto | B76: 1282484672 | C76: 1306501849 | D76: 1450423677 | E76: 1572712122
A77: Participación de los reaseguradores en las provisiones sobre contratos de seguros | B77: 237007868 | C77: 319466997 | D77: 259670949
A78: Depósitos de reaseguros de exceso de pérdida | B78: 992942 | C78: 1711440 | D78: 1845741 | E78: 2926965
A79: Instrumentos financieros, neto | E79: 1570422123 | F79: 1842841062
A80: Activos por contratos de seguros | E80: 21110668 | F80: 21032150
A81: Activos por contratos de reaseguros | E81: 224456158 | F81: 179614453
A82: Cuentas por cobrar otras, neto | E82: 65001992 | F82: 74003298
A83: Inmuebles, mobiliario, equipo y mejoras, neto | B83: 55843403 | C83: 54093472 | D83: 53762908 | E83: 46374370
A84: Inmuebles, mobiliarios y equipo, netos | E84: 42691420 | F84: 38185718
A85: Activos por derecho de uso, neto | B85: 3567110 | C85: 2447927 | D85: 3082318 | E85: 1548244
A86: Impuesto sobre la renta diferido | B86: 3828445 | C86: 5459921 | D86: 4977416 | E86: 0 | F86: 0
A87: Activos intangibles y plusvalía | B87: 80211362 | C87: 76115738 | D87: 71848199 | E87: 67707242
A88: Activos intangibles y plusvalía, neto | E88: 38647085 | F88: 41001647
A89: Propiedad de inversión | E89: 15641307 | F89: 15413883
A90: Otros activos | B90: 52139653 | C90: 47920677 | D90: 47188231 | E90: 24512378 | F90: 24666268
A91: Activos clasificados como mantenidos para la venta | E91: 1051007115 | F91: 0
A92: Total de activos | B92: 3230660630 | C92: 3372409693 | D92: 3594750363 | E92: 3119530651 | F92: 2318752111
A93: Depósitos de clientes | B93: 725271188 | C93: 742797197 | D93: 838241610 | E93: 0 | F93: 0
A94: Riesgo en curso | B94: 222380820 | C94: 222836666 | D94: 252044466
A95: Reclamos en trámite | B95: 166900068 | C95: 262168088 | D95: 183640714
A96: Negocios de vida a largo plazo sobre pólizas de vida | B96: 271722485 | C96: 285566197 | D96: 297881412
A97: Total de provisiones sobre contratos de seguros | B97: 661003373 | C97: 770570951 | D97: 733566592
A98: Emisiones de deuda y obligaciones | B98: 526341819 | C98: 551664761 | D98: 537365915
A99: Obligaciones subordinadas | B99: 2174514 | C99: 10321297 | D99: 10375811
A100: Total de financiamientos | B100: 528516333 | C100: 561986058 | D100: 547741726
A101: Reaseguros por pagar | B101: 95584028 | C101: 87936500 | D101: 109327643
A102: Impuesto sobre la renta diferido | B102: 4481917 | C102: 3966720 | D102: 3099580 | E102: 3437168
A103: Pasivos por arrendamientos | B103: 4129771 | C103: 3054770 | D103: 3753169
A104: Otros pasivos | B104: 118508679 | C104: 124513198 | D104: 141770551 | E104: 4226363 | F104: 4212226
A105: Total de las cuentas por pagar y otros pasivos | B105: 222704395 | C105: 219471188 | D105: 257950943
A106: Total de los pasivos | B106: 2137495289 | C106: 2294825394 | D106: 2377500871
A107: Provisiones sobre contratos de seguros | E107: 547180881 | F107: 516579461
...

Sheet Supuestos
A1: Grupo ASSA, S. A.
A3: COLOR KEY: Input (azul) · Fórmula (negro) · Link inter-hoja (verde)
A4: Escenario (1=Base, 2=Bull, 3=Bear)
A5: Selector escenario | C5: 1 | M5: caso | N5: NOT_DISCLOSED | Q5: Input de escenario desde fuente citada o NOT_DISCLOSED.
A6: Escenario activo | C6: =CHOOSE($C$5,"Base","Bull","Bear") -> Base | M6: moneda del modelo | N6: NOT_DISCLOSED | Q6: Selector de caso activo C5: Base/Bull/Bear.
A8: Años | B8: FY21A | C8: FY22A | D8: FY23A | E8: FY24A | F8: FY25A | G8: FY26E | H8: FY27E | I8: FY28E | J8: FY29E | K8: FY30E | M8: Unidad | N8: Fuente / nota | Q8: Rationale
A10: A. INGRESOS POR SERVICIOS DE SEGURO (NIIF 17) — CRECIMIENTO (% YoY)
A11: Ingresos por servicios de seguro — driver activo (base NIIF 17) | G11: =CHOOSE($C$5,G13,G14,G12) -> 0.0794 | H11: =CHOOSE($C$5,H13,H14,H12) -> 0.0794 | I11: =CHOOSE($C$5,I13,I14,I12) -> 0.0794 | J11: =CHOOSE($C$5,J13,J14,J12) -> 0.0794 | K11: =CHOOSE($C$5,K13,K14,K12) -> 0.0794 | M11: % | N11: EEFF:Ingresos por servicios de seguro | Q11: Selector de caso activo C5: Base/Bull/Bear.
A12: Bear | G12: 0.0594 | H12: 0.0594 | I12: 0.0594 | J12: 0.0594 | K12: 0.0594 | M12: % | N12: EEFF:Ingresos por servicios de seguro | Q12: Escenario driver citado; NOT_DISCLOSED si no hay fuente explícita.
A13: Base | G13: 0.0794 | H13: 0.0794 | I13: 0.0794 | J13: 0.0794 | K13: 0.0794 | M13: % | N13: EEFF:Ingresos por servicios de seguro | Q13: Escenario driver citado; NOT_DISCLOSED si no hay fuente explícita.
A14: Bull | G14: 0.0994 | H14: 0.0994 | I14: 0.0994 | J14: 0.0994 | K14: 0.0994 | M14: % | N14: EEFF:Ingresos por servicios de seguro | Q14: Escenario driver citado; NOT_DISCLOSED si no hay fuente explícita.
A15: Ingresos por servicios de seguro (hist, ref EEFF) | E15: =EEFF!E50 -> 820306455 | F15: =EEFF!F50 -> 885435473 | M15: moneda del modelo | N15: EEFF:Ingresos por servicios de seguro | Q15: Mirror histórico desde fuente citada.
A16: Ingresos por servicios de seguro YoY histórico (ref EEFF) | F16: =EEFF!F50/EEFF!E50-1 -> 0.079395959 | M16: % | N16: EEFF:Ingresos por servicios de seguro | Q16: Fórmula viva: año actual / año previo - 1.
A18: B. GASTOS POR SERVICIOS DE SEGURO (% de ingresos por servicios, NIIF 17)
A19: Gastos por servicios de seguro — driver activo (ratio negativo) | G19: =CHOOSE($C$5,G21,G22,G20) -> -0.4816 | H19: =CHOOSE($C$5,H21,H22,H20) -> -0.4816 | I19: =CHOOSE($C$5,I21,I22,I20) -> -0.4816 | J19: =CHOOSE($C$5,J21,J22,J20) -> -0.4816 | K19: =CHOOSE($C$5,K21,K22,K20) -> -0.4816 | M19: % | N19: EEFF:Gastos por servicios de seguro | Q19: Selector de caso activo C5: Base/Bull/Bear.
A20: Bear | G20: -0.5016 | H20: -0.5016 | I20: -0.5016 | J20: -0.5016 | K20: -0.5016 | M20: % | N20: EEFF:Gastos por servicios de seguro | Q20: Escenario driver citado; NOT_DISCLOSED si no hay fuente explícita.
A21: Base | G21: -0.4816 | H21: -0.4816 | I21: -0.4816 | J21: -0.4816 | K21: -0.4816 | M21: % | N21: EEFF:Gastos por servicios de seguro | Q21: Escenario driver citado; NOT_DISCLOSED si no hay fuente explícita.
A22: Bull | G22: -0.4616 | H22: -0.4616 | I22: -0.4616 | J22: -0.4616 | K22: -0.4616 | M22: % | N22: EEFF:Gastos por servicios de seguro | Q22: Escenario driver citado; NOT_DISCLOSED si no hay fuente explícita.
A23: Gasto ÷ ingreso (hist; B:D legacy reclamos s/primas, E:F NIIF17 gasto servicio s/ingreso servicio) | B23: =IF(EEFF!B10=0,"",EEFF!B16/EEFF!B10) -> -0.79247142 | C23: =IF(EEFF!C10=0,"",EEFF!C16/EEFF!C10) -> -0.97399938 | D23: =IF(EEFF!D10=0,"",EEFF!D16/EEFF!D10) -> -0.62400693 | E23: =EEFF!E51/EEFF!E50 -> -0.4484638 | F23: =EEFF!F51/EEFF!F50 -> -0.48164584 | M23: % | N23: EEFF:Gastos por servicios de seguro; EEFF:Ingresos por servicios de seguro | Q23: Derivación mecánica por fórmula viva.
A25: C. GASTOS GENERALES (% de ingresos por servicios de seguro, NIIF 17)
A26: Gastos generales y administrativos — driver activo | G26: =CHOOSE($C$5,G28,G29,G27) -> -0.1076 | H26: =CHOOSE($C$5,H28,H29,H27) -> -0.1076 | I26: =CHOOSE($C$5,I28,I29,I27) -> -0.1076 | J26: =CHOOSE($C$5,J28,J29,J27) -> -0.1076 | K26: =CHOOSE($C$5,K28,K29,K27) -> -0.1076 | M26: % | N26: EEFF:Gastos generales y administrativos | Q26: Selector de caso activo C5: Base/Bull/Bear.
A27: Bear | G27: -0.1276 | H27: -0.1276 | I27: -0.1276 | J27: -0.1276 | K27: -0.1276 | M27: % | N27: EEFF:Gastos generales y administrativos | Q27: Escenario driver citado; NOT_DISCLOSED si no hay fuente explícita.
A28: Base | G28: -0.1076 | H28: -0.1076 | I28: -0.1076 | J28: -0.1076 | K28: -0.1076 | M28: % | N28: EEFF:Gastos generales y administrativos | Q28: Escenario driver citado; NOT_DISCLOSED si no hay fuente explícita.
A29: Bull | G29: -0.0876 | H29: -0.0876 | I29: -0.0876 | J29: -0.0876 | K29: -0.0876 | M29: % | N29: EEFF:Gastos generales y administrativos | Q29: Escenario driver citado; NOT_DISCLOSED si no hay fuente explícita.
A30: G&A ÷ ingreso (hist; B:D legacy s/primas retenidas, E:F NIIF17 s/ingreso servicio) | B30: =IF(EEFF!B10=0,"",EEFF!B41/EEFF!B10) -> -0.13086687 | C30: =IF(EEFF!C10=0,"",EEFF!C41/EEFF!C10) -> -0.12319463 | D30: =IF(EEFF!D10=0,"",EEFF!D41/EEFF!D10) -> -0.1095379 | E30: =EEFF!E62/EEFF!E50 -> -0.10875473 | F30: =EEFF!F62/EEFF!F50 -> -0.10760001 | M30: % | N30: EEFF:Gastos generales y administrativos; EEFF:Ingresos por servicios de seguro | Q30: Derivación mecánica por fórmula viva.
A33: D. PRIMAS SUSCRITAS POR RAMO (NETAS DE REASEGURO) — CRECIMIENTO % YoY (NIIF 17; Nota 10.ii del filing 2025, tbl-35)
A34: Histórico 2025 = YoY por ramo con referencia al ledger Notas_EEFF (verde). Proyección = driver por escenario (azul, hardcoded) + selector $C$5. Base = YoY 2025; Bear/Bull = Base ∓ 2 puntos.
A35: Accidentes personales — driver activo (% YoY prima suscrita neta) | G35: =CHOOSE($C$5,G37,G38,G36) -> 0.0277 | H35: =CHOOSE($C$5,H37,H38,H36) -> 0.0277 | I35: =CHOOSE($C$5,I37,I38,I36) -> 0.0277 | J35: =CHOOSE($C$5,J37,J38,J36) -> 0.0277 | K35: =CHOOSE($C$5,K37,K38,K36) -> 0.0277 | M35: % | N35: NOT_DISCLOSED | Q35: Selector de caso activo C5: Base/Bull/Bear.
A36: Bear | G36: 0.0077 | H36: 0.0077 | I36: 0.0077 | J36: 0.0077 | K36: 0.0077 | M36: % | N36: NOT_DISCLOSED | Q36: Escenario driver citado; NOT_DISCLOSED si no hay fuente explícita.
A37: Base | G37: 0.0277 | H37: 0.0277 | I37: 0.0277 | J37: 0.0277 | K37: 0.0277 | M37: % | N37: NOT_DISCLOSED | Q37: Escenario driver citado; NOT_DISCLOSED si no hay fuente explícita.
A38: Bull | G38: 0.0477 | H38: 0.0477 | I38: 0.0477 | J38: 0.0477 | K38: 0.0477 | M38: % | N38: NOT_DISCLOSED | Q38: Escenario driver citado; NOT_DISCLOSED si no hay fuente explícita.
A39: YoY histórico 2025 (ref Notas_EEFF) | F39: =Notas_EEFF!K2716/Notas_EEFF!K2717-1 -> 0.027659405 | M39: % | N39: Notas_EEFF (citado por fórmula viva) | Q39: Fórmula viva: año actual / año previo - 1.
A40: Automóvil — driver activo (% YoY prima suscrita neta) | G40: =CHOOSE($C$5,G42,G43,G41) -> 0.1407 | H40: =CHOOSE($C$5,H42,H43,H41) -> 0.1407 | I40: =CHOOSE($C$5,I42,I43,I41) -> 0.1407 | J40: =CHOOSE($C$5,J42,J43,J41) -> 0.1407 | K40: =CHOOSE($C$5,K42,K43,K41) -> 0.1407 | M40: % | N40: NOT_DISCLOSED | Q40: Selector de caso activo C5: Base/Bull/Bear.
A41: Bear | G41: 0.1207 | H41: 0.1207 | I41: 0.1207 | J41: 0.1207 | K41: 0.1207 | M41: % | N41: NOT_DISCLOSED | Q41: Escenario driver citado; NOT_DISCLOSED si no hay fuente explícita.
A42: Base | G42: 0.1407 | H42: 0.1407 | I42: 0.1407 | J42: 0.1407 | K42: 0.1407 | M42: % | N42: NOT_DISCLOSED | Q42: Escenario driver citado; NOT_DISCLOSED si no hay fuente explícita.
A43: Bull | G43: 0.1607 | H43: 0.1607 | I43: 0.1607 | J43: 0.1607 | K43: 0.1607 | M43: % | N43: NOT_DISCLOSED | Q43: Escenario driver citado; NOT_DISCLOSED si no hay fuente explícita.
A44: YoY histórico 2025 (ref Notas_EEFF) | F44: =Notas_EEFF!K2718/Notas_EEFF!K2719-1 -> 0.1407481 | M44: % | N44: Notas_EEFF (citado por fórmula viva) | Q44: Fórmula viva: año actual / año previo - 1.
A45: Casco — driver activo (% YoY prima suscrita neta) | G45: =CHOOSE($C$5,G47,G48,G46) -> 0.0322 | H45: =CHOOSE($C$5,H47,H48,H46) -> 0.0322 | I45: =CHOOSE($C$5,I47,I48,I46) -> 0.0322 | J45: =CHOOSE($C$5,J47,J48,J46) -> 0.0322 | K45: =CHOOSE($C$5,K47,K48,K46) -> 0.0322 | M45: % | N45: NOT_DISCLOSED | Q45: Selector de caso activo C5: Base/Bull/Bear.
A46: Bear | G46: 0.0122 | H46: 0.0122 | I46: 0.0122 | J46: 0.0122 | K46: 0.0122 | M46: % | N46: NOT_DISCLOSED | Q46: Escenario driver citado; NOT_DISCLOSED si no hay fuente explícita.
A47: Base | G47: 0.0322 | H47: 0.0322 | I47: 0.0322 | J47: 0.0322 | K47: 0.0322 | M47: % | N47: NOT_DISCLOSED | Q47: Escenario driver citado; NOT_DISCLOSED si no hay fuente explícita.
A48: Bull | G48: 0.0522 | H48: 0.0522 | I48: 0.0522 | J48: 0.0522 | K48: 0.0522 | M48: % | N48: NOT_DISCLOSED | Q48: Escenario driver citado; NOT_DISCLOSED si no hay fuente explícita.
A49: YoY histórico 2025 (ref Notas_EEFF) | F49: =Notas_EEFF!K2720/Notas_EEFF!K2721-1 -> 0.032221669 | M49: % | N49: Notas_EEFF (citado por fórmula viva) | Q49: Fórmula viva: año actual / año previo - 1.
A50: Colectivo de vida — driver activo (% YoY prima suscrita neta) | G50: =CHOOSE($C$5,G52,G53,G51) -> 0.0525 | H50: =CHOOSE($C$5,H52,H53,H51) -> 0.0525 | I50: =CHOOSE($C$5,I52,I53,I51) -> 0.0525 | J50: =CHOOSE($C$5,J52,J53,J51) -> 0.0525 | K50: =CHOOSE($C$5,K52,K53,K51) -> 0.0525 | M50: % | N50: NOT_DISCLOSED | Q50: Selector de caso activo C5: Base/Bull/Bear.
A51: Bear | G51: 0.0325 | H51: 0.0325 | I51: 0.0325 | J51: 0.0325 | K51: 0.0325 | M51: % | N51: NOT_DISCLOSED | Q51: Escenario driver citado; NOT_DISCLOSED si no hay fuente explícita.
A52: Base | G52: 0.0525 | H52: 0.0525 | I52: 0.0525 | J52: 0.0525 | K52: 0.0525 | M52: % | N52: NOT_DISCLOSED | Q52: Escenario driver citado; NOT_DISCLOSED si no hay fuente explícita.
A53: Bull | G53: 0.0725 | H53: 0.0725 | I53: 0.0725 | J53: 0.0725 | K53: 0.0725 | M53: % | N53: NOT_DISCLOSED | Q53: Escenario driver citado; NOT_DISCLOSED si no hay fuente explícita.
A54: YoY histórico 2025 (ref Notas_EEFF) | F54: =Notas_EEFF!K2722/Notas_EEFF!K2723-1 -> 0.052468874 | M54: % | N54: Notas_EEFF (citado por fórmula viva) | Q54: Fórmula viva: año actual / año previo - 1.
A55: Fianzas — driver activo (% YoY prima suscrita neta) | G55: =CHOOSE($C$5,G57,G58,G56) -> -0.0002 | H55: =CHOOSE($C$5,H57,H58,H56) -> -0.0002 | I55: =CHOOSE($C$5,I57,I58,I56) -> -0.0002 | J55: =CHOOSE($C$5,J57,J58,J56) -> -0.0002 | K55: =CHOOSE($C$5,K57,K58,K56) -> -0.0002 | M55: % | N55: NOT_DISCLOSED | Q55: Selector de caso activo C5: Base/Bull/Bear.
A56: Bear | G56: -0.0202 | H56: -0.0202 | I56: -0.0202 | J56: -0.0202 | K56: -0.0202 | M56: % | N56: NOT_DISCLOSED | Q56: Escenario driver citado; NOT_DISCLOSED si no hay fuente explícita.
A57: Base | G57: -0.0002 | H57: -0.0002 | I57: -0.0002 | J57: -0.0002 | K57: -0.0002 | M57: % | N57: NOT_DISCLOSED | Q57: Escenario driver citado; NOT_DISCLOSED si no hay fuente explícita.
A58: Bull | G58: 0.0198 | H58: 0.0198 | I58: 0.0198 | J58: 0.0198 | K58: 0.0198 | M58: % | N58: NOT_DISCLOSED | Q58: Escenario driver citado; NOT_DISCLOSED si no hay fuente explícita.
A59: YoY histórico 2025 (ref Notas_EEFF) | F59: =Notas_EEFF!K2724/Notas_EEFF!K2725-1 -> -0.0001734183 | M59: % | N59: Notas_EEFF (citado por fórmula viva) | Q59: Fórmula viva: año actual / año previo - 1.
A60: Fidelidad — driver activo (% YoY prima suscrita neta) | G60: =CHOOSE($C$5,G62,G63,G61) -> 0.0636 | H60: =CHOOSE($C$5,H62,H63,H61) -> 0.0636 | I60: =CHOOSE($C$5,I62,I63,I61) -> 0.0636 | J60: =CHOOSE($C$5,J62,J63,J61) -> 0.0636 | K60: =CHOOSE($C$5,K62,K63,K61) -> 0.0636 | M60: % | N60: NOT_DISCLOSED | Q60: Selector de caso activo C5: Base/Bull/Bear.
A61: Bear | G61: 0.0436 | H61: 0.0436 | I61: 0.0436 | J61: 0.0436 | K61: 0.0436 | M61: % | N61: NOT_DISCLOSED | Q61: Escenario driver citado; NOT_DISCLOSED si no hay fuente explícita.
A62: Base | G62: 0.0636 | H62: 0.0636 | I62: 0.0636 | J62: 0.0636 | K62: 0.0636 | M62: % | N62: NOT_DISCLOSED | Q62: Escenario driver citado; NOT_DISCLOSED si no hay fuente explícita.
A63: Bull | G63: 0.0836 | H63: 0.0836 | I63: 0.0836 | J63: 0.0836 | K63: 0.0836 | M63: % | N63: NOT_DISCLOSED | Q63: Escenario driver citado; NOT_DISCLOSED si no hay fuente explícita.
A64: YoY histórico 2025 (ref Notas_EEFF) | F64: =Notas_EEFF!K2726/Notas_EEFF!K2727-1 -> 0.063569522 | M64: % | N64: Notas_EEFF (citado por fórmula viva) | Q64: Fórmula viva: año actual / año previo - 1.
A65: Incendio — driver activo (% YoY prima suscrita neta) | G65: =CHOOSE($C$5,G67,G68,G66) -> 0.0062 | H65: =CHOOSE($C$5,H67,H68,H66) -> 0.0062 | I65: =CHOOSE($C$5,I67,I68,I66) -> 0.0062 | J65: =CHOOSE($C$5,J67,J68,J66) -> 0.0062 | K65: =CHOOSE($C$5,K67,K68,K66) -> 0.0062 | M65: % | N65: NOT_DISCLOSED | Q65: Selector de caso activo C5: Base/Bull/Bear.
A66: Bear | G66: -0.0138 | H66: -0.0138 | I66: -0.0138 | J66: -0.0138 | K66: -0.0138 | M66: % | N66: NOT_DISCLOSED | Q66: Escenario driver citado; NOT_DISCLOSED si no hay fuente explícita.
A67: Base | G67: 0.0062 | H67: 0.0062 | I67: 0.0062 | J67: 0.0062 | K67: 0.0062 | M67: % | N67: NOT_DISCLOSED | Q67: Escenario driver citado; NOT_DISCLOSED si no hay fuente explícita.
A68: Bull | G68: 0.0262 | H68: 0.0262 | I68: 0.0262 | J68: 0.0262 | K68: 0.0262 | M68: % | N68: NOT_DISCLOSED | Q68: Escenario driver citado; NOT_DISCLOSED si no hay fuente explícita.
A69: YoY histórico 2025 (ref Notas_EEFF) | F69: =Notas_EEFF!K2728/Notas_EEFF!K2729-1 -> 0.0061868112 | M69: % | N69: Notas_EEFF (citado por fórmula viva) | Q69: Fórmula viva: año actual / año previo - 1.
A70: Responsabilidad civil — driver activo (% YoY prima suscrita neta) | G70: =CHOOSE($C$5,G72,G73,G71) -> 0.0139 | H70: =CHOOSE($C$5,H72,H73,H71) -> 0.0139 | I70: =CHOOSE($C$5,I72,I73,I71) -> 0.0139 | J70: =CHOOSE($C$5,J72,J73,J71) -> 0.0139 | K70: =CHOOSE($C$5,K72,K73,K71) -> 0.0139 | M70: % | N70: NOT_DISCLOSED | Q70: Selector de caso activo C5: Base/Bull/Bear.
A71: Bear | G71: -0.0061 | H71: -0.0061 | I71: -0.0061 | J71: -0.0061 | K71: -0.0061 | M71: % | N71: NOT_DISCLOSED | Q71: Escenario driver citado; NOT_DISCLOSED si no hay fuente explícita.
A72: Base | G72: 0.0139 | H72: 0.0139 | I72: 0.0139 | J72: 0.0139 | K72: 0.0139 | M72: % | N72: NOT_DISCLOSED | Q72: Escenario driver citado; NOT_DISCLOSED si no hay fuente explícita.
A73: Bull | G73: 0.0339 | H73: 0.0339 | I73: 0.0339 | J73: 0.0339 | K73: 0.0339 | M73: % | N73: NOT_DISCLOSED | Q73: Escenario driver citado; NOT_DISCLOSED si no hay fuente explícita.
A74: YoY histórico 2025 (ref Notas_EEFF) | F74: =Notas_EEFF!K2730/Notas_EEFF!K2731-1 -> 0.013894902 | M74: % | N74: Notas_EEFF (citado por fórmula viva) | Q74: Fórmula viva: año actual / año previo - 1.
A75: Riesgos diversos — driver activo (% YoY prima suscrita neta) | G75: =CHOOSE($C$5,G77,G78,G76) -> -0.0157 | H75: =CHOOSE($C$5,H77,H78,H76) -> -0.0157 | I75: =CHOOSE($C$5,I77,I78,I76) -> -0.0157 | J75: =CHOOSE($C$5,J77,J78,J76) -> -0.0157 | K75: =CHOOSE($C$5,K77,K78,K76) -> -0.0157 | M75: % | N75: NOT_DISCLOSED | Q75: Selector de caso activo C5: Base/Bull/Bear.
A76: Bear | G76: -0.0357 | H76: -0.0357 | I76: -0.0357 | J76: -0.0357 | K76: -0.0357 | M76: % | N76: NOT_DISCLOSED | Q76: Escenario driver citado; NOT_DISCLOSED si no hay fuente explícita.
A77: Base | G77: -0.0157 | H77: -0.0157 | I77: -0.0157 | J77: -0.0157 | K77: -0.0157 | M77: % | N77: NOT_DISCLOSED | Q77: Escenario driver citado; NOT_DISCLOSED si no hay fuente explícita.
A78: Bull | G78: 0.0043 | H78: 0.0043 | I78: 0.0043 | J78: 0.0043 | K78: 0.0043 | M78: % | N78: NOT_DISCLOSED | Q78: Escenario driver citado; NOT_DISCLOSED si no hay fuente explícita.
A79: YoY histórico 2025 (ref Notas_EEFF) | F79: =Notas_EEFF!K2732/Notas_EEFF!K2733-1 -> -0.015701379 | M79: % | N79: Notas_EEFF (citado por fórmula viva) | Q79: Fórmula viva: año actual / año previo - 1.
A80: Salud — driver activo (% YoY prima suscrita neta) | G80: =CHOOSE($C$5,G82,G83,G81) -> 0.0104 | H80: =CHOOSE($C$5,H82,H83,H81) -> 0.0104 | I80: =CHOOSE($C$5,I82,I83,I81) -> 0.0104 | J80: =CHOOSE($C$5,J82,J83,J81) -> 0.0104 | K80: =CHOOSE($C$5,K82,K83,K81) -> 0.0104 | M80: % | N80: NOT_DISCLOSED | Q80: Selector de caso activo C5: Base/Bull/Bear.
A81: Bear | G81: -0.0096 | H81: -0.0096 | I81: -0.0096 | J81: -0.0096 | K81: -0.0096 | M81: % | N81: NOT_DISCLOSED | Q81: Escenario driver citado; NOT_DISCLOSED si no hay fuente explícita.
A82: Base | G82: 0.0104 | H82: 0.0104 | I82: 0.0104 | J82: 0.0104 | K82: 0.0104 | M82: % | N82: NOT_DISCLOSED | Q82: Escenario driver citado; NOT_DISCLOSED si no hay fuente explícita.
A83: Bull | G83: 0.0304 | H83: 0.0304 | I83: 0.0304 | J83: 0.0304 | K83: 0.0304 | M83: % | N83: NOT_DISCLOSED | Q83: Escenario driver citado; NOT_DISCLOSED si no hay fuente explícita.
A84: YoY histórico 2025 (ref Notas_EEFF) | F84: =Notas_EEFF!K2734/Notas_EEFF!K2735-1 -> 0.010393532 | M84: % | N84: Notas_EEFF (citado por fórmula viva) | Q84: Fórmula viva: año actual / año previo - 1.
A85: Seguros técnicos — driver activo (% YoY prima suscrita neta) | G85: =CHOOSE($C$5,G87,G88,G86) -> -0.0288 | H85: =CHOOSE($C$5,H87,H88,H86) -> -0.0288 | I85: =CHOOSE($C$5,I87,I88,I86) -> -0.0288 | J85: =CHOOSE($C$5,J87,J88,J86) -> -0.0288 | K85: =CHOOSE($C$5,K87,K88,K86) -> -0.0288 | M85: % | N85: NOT_DISCLOSED | Q85: Selector de caso activo C5: Base/Bull/Bear.
A86: Bear | G86: -0.0488 | H86: -0.0488 | I86: -0.0488 | J86: -0.0488 | K86: -0.0488 | M86: % | N86: NOT_DISCLOSED | Q86: Escenario driver citado; NOT_DISCLOSED si no hay fuente explícita.
A87: Base | G87: -0.0288 | H87: -0.0288 | I87: -0.0288 | J87: -0.0288 | K87: -0.0288 | M87: % | N87: NOT_DISCLOSED | Q87: Escenario driver citado; NOT_DISCLOSED si no hay fuente explícita.
A88: Bull | G88: -0.0088 | H88: -0.0088 | I88: -0.0088 | J88: -0.0088 | K88: -0.0088 | M88: % | N88: NOT_DISCLOSED | Q88: Escenario driver citado; NOT_DISCLOSED si no hay fuente explícita.
A89: YoY histórico 2025 (ref Notas_EEFF) | F89: =Notas_EEFF!K2736/Notas_EEFF!K2737-1 -> -0.028840138 | M89: % | N89: Notas_EEFF (citado por fórmula viva) | Q89: Fórmula viva: año actual / año previo - 1.
A90: Autoexpedibles y otros — driver activo (% YoY prima suscrita neta) | G90: =CHOOSE($C$5,G92,G93,G91) -> 0.0119 | H90: =CHOOSE($C$5,H92,H93,H91) -> 0.0119 | I90: =CHOOSE($C$5,I92,I93,I91) -> 0.0119 | J90: =CHOOSE($C$5,J92,J93,J91) -> 0.0119 | K90: =CHOOSE($C$5,K92,K93,K91) -> 0.0119 | M90: % | N90: NOT_DISCLOSED | Q90: Selector de caso activo C5: Base/Bull/Bear.
A91: Bear | G91: -0.0081 | H91: -0.0081 | I91: -0.0081 | J91: -0.0081 | K91: -0.0081 | M91: % | N91: NOT_DISCLOSED | Q91: Escenario driver citado; NOT_DISCLOSED si no hay fuente explícita.
A92: Base | G92: 0.0119 | H92: 0.0119 | I92: 0.0119 | J92: 0.0119 | K92: 0.0119 | M92: % | N92: NOT_DISCLOSED | Q92: Escenario driver citado; NOT_DISCLOSED si no hay fuente explícita.
A93: Bull | G93: 0.0319 | H93: 0.0319 | I93: 0.0319 | J93: 0.0319 | K93: 0.0319 | M93: % | N93: NOT_DISCLOSED | Q93: Escenario driver citado; NOT_DISCLOSED si no hay fuente explícita.
A94: YoY histórico 2025 (ref Notas_EEFF) | F94: =Notas_EEFF!K2738/Notas_EEFF!K2739-1 -> 0.011946987 | M94: % | N94: Notas_EEFF (citado por fórmula viva) | Q94: Fórmula viva: año actual / año previo - 1.
A96: E. IMPUESTO SOBRE LA RENTA — TASA EFECTIVA (% de utilidad antes de impuesto, NIIF 17)
A97: Histórico = −impuesto ÷ utilidad antes de impuesto (ref EEFF, verde; FY24 8.5%, FY25 8.2%). Proyección = tasa por escenario (azul) + selector $C$5. Base ≈ tasa efectiva FY2025; Bear/Bull = Base ± 1 punto (Bear = tasa más alta).
A98: Tasa efectiva de impuesto — driver activo (% de utilidad antes de impuesto) | G98: =CHOOSE($C$5,G100,G101,G99) -> 0.082 | H98: =CHOOSE($C$5,H100,H101,H99) -> 0.082 | I98: =CHOOSE($C$5,I100,I101,I99) -> 0.082 | J98: =CHOOSE($C$5,J100,J101,J99) -> 0.082 | K98: =CHOOSE($C$5,K100,K101,K99) -> 0.082 | M98: % | N98: NOT_DISCLOSED | Q98: Selector de caso activo C5: Base/Bull/Bear.
A99: Bear | G99: 0.092 | H99: 0.092 | I99: 0.092 | J99: 0.092 | K99: 0.092 | M99: % | N99: NOT_DISCLOSED | Q99: Escenario driver citado; NOT_DISCLOSED si no hay fuente explícita.
A100: Base | G100: 0.082 | H100: 0.082 | I100: 0.082 | J100: 0.082 | K100: 0.082 | M100: % | N100: NOT_DISCLOSED | Q100: Escenario driver citado; NOT_DISCLOSED si no hay fuente explícita.
A101: Bull | G101: 0.072 | H101: 0.072 | I101: 0.072 | J101: 0.072 | K101: 0.072 | M101: % | N101: NOT_DISCLOSED | Q101: Escenario driver citado; NOT_DISCLOSED si no hay fuente explícita.
A102: Tasa efectiva histórica (−impuesto ÷ utilidad antes de impuesto, ref EEFF) | E102: =-EEFF!E65/EEFF!E64 -> 0.085353312 | F102: =-EEFF!F65/EEFF!F64 -> 0.081887098 | M102: % | N102: EEFF (citado por fórmula viva) | Q102: Derivación mecánica por fórmula viva.

Sheet Notas_EEFF
A1: Grupo ASSA, S. A.
A2: Notas a los Estados Financieros
A3: Fuente: informes auditados vía OCR Mistral (verbatim).
A5: Año | B5: Documento fuente | C5: Página OCR | D5: Tabla OCR / sección | E5: Nota # | F5: Título original de la nota | G5: Categoría modelable | H5: Line item EEFF | I5: Sub-line item / detalle | J5: Texto original / disclosure | K5: Monto reportado | L5: Moneda | M5: Unidad / escala | N5: Fecha / venc. / tasa / plazo | O5: Contraparte / contrato / instrumento | P5: Impacto en Supuestos | Q5: Impacto en ModeloFinanciero | R5: Link a celda EEFF | S5: Comentario de extracción | T5: Status
A6: 2021 | B6: INA_ASSA_2021_0.pdf | C6: page-89 | D6: markdown.md | E6: 5 | F6: 5. Saldos y transacciones con partes relacionadas | G6: Partes relacionadas | J6: Los saldos y transacciones con partes relacionadas del Grupo se detallan a continuación: | T6: OK
A7: 2021 | B7: INA_ASSA_2021_0.pdf | C7: page-89 | D7: markdown.md | E7: 5 | F7: 5. Saldos y transacciones con partes relacionadas | G7: Partes relacionadas | J7: (a) Transacciones con personal clave de gerencia | T7: OK
A8: 2021 | B8: INA_ASSA_2021_0.pdf | C8: page-89 | D8: markdown.md | E8: 5 | F8: 5. Saldos y transacciones con partes relacionadas | G8: Partes relacionadas | J8: - Préstamos a directores, personal clave de la gerencia | T8: OK
A9: 2021 | B9: INA_ASSA_2021_0.pdf | C9: page-89 | D9: markdown.md | E9: 5 | F9: 5. Saldos y transacciones con partes relacionadas | G9: Partes relacionadas | J9: Al 31 de diciembre de 2021, el saldo pendiente de los préstamos por cobrar a directores y personal clave de la gerencia asciende a US$674,272 (2020: US$712,613) y están incluidos en los préstamos por cobrar. Estos saldos presentan intereses por cobrar por US$4,732 (2020: US$5,929). | K9: 674272 | L9: B/. | T9: OK
A10: 2021 | B10: INA_ASSA_2021_0.pdf | C10: page-89 | D10: markdown.md | E10: 5 | F10: 5. Saldos y transacciones con partes relacionadas | G10: Partes relacionadas | J10: Durante el año se han registrado ingresos por intereses sobre estos préstamos con directores y personal clave de la gerencia por US$46,590 (2020: US$49,610). | K10: 46590 | L10: B/. | T10: OK
A11: 2021 | B11: INA_ASSA_2021_0.pdf | C11: page-89 | D11: markdown.md | E11: 5 | F11: 5. Saldos y transacciones con partes relacionadas | G11: Partes relacionadas | J11: - Depósitos de directores y personal clave de la gerencia | T11: OK
A12: 2021 | B12: INA_ASSA_2021_0.pdf | C12: page-89 | D12: markdown.md | E12: 5 | F12: 5. Saldos y transacciones con partes relacionadas | G12: Partes relacionadas | J12: Algunos directores y personal clave de la gerencia del Grupo mantienen cuentas corrientes, de ahorro y plazos fijos en las subsidiarias Grupo BDF, S. A. y La Hipotecaria (Holding), Inc. las cuales, al 31 de diciembre de 2021, mantenían un saldo de US$1,553,553 (2020: US$1,936,743) y están incluidas en las cuentas de depósitos de clientes del Grupo. Estos saldos presentan intereses por pagar por US$9,173 (2020: US$9,322). | K12: 1553553 | L12: B/. | T12: OK
A13: 2021 | B13: INA_ASSA_2021_0.pdf | C13: page-90 | D13: markdown.md | E13: 5 | F13: 5. Saldos y transacciones con partes relacionadas | G13: Partes relacionadas | J13: Durante el año, estas subsidiarias registraron gastos por intereses sobre depósitos de directores y personal clave de la gerencia por US$59,809 (2020: US$299,832). | K13: 59809 | L13: B/. | T13: OK
A14: 2021 | B14: INA_ASSA_2021_0.pdf | C14: page-90 | D14: markdown.md | E14: 5 | F14: 5. Saldos y transacciones con partes relacionadas | G14: Partes relacionadas | J14: - Primas suscritas a directores y personal clave de gerencia Dentro del giro normal del negocio, directores y personal clave de gerencia han suscrito pólizas a nombre propio con primas anuales por la suma de US$112,717 (2020: US$113,412) en condiciones similares a las que se pactan con terceros no vinculados al Grupo. | K14: 112717 | L14: B/. | T14: OK
A15: 2021 | B15: INA_ASSA_2021_0.pdf | C15: page-90 | D15: markdown.md | E15: 5 | F15: 5. Saldos y transacciones con partes relacionadas | G15: Partes relacionadas | J15: Al 31 de diciembre de 2021, el saldo de primas por cobrar asciende a US$55,870 (2020: US$51,871) y está incluido en las cuentas por cobrar de asegurados. Otras cuentas por cobrar ascendieron a US$226 (2020: US$271). | K15: 55870 | L15: B/. | T15: OK
A16: 2021 | B16: INA_ASSA_2021_0.pdf | C16: page-90 | D16: markdown.md | E16: 5 | F16: 5. Saldos y transacciones con partes relacionadas | G16: Partes relacionadas | J16: Durante el año, se han pagado reclamos a estas pólizas por US$19,086 (2020: US$10,084). | K16: 19086 | L16: B/. | T16: OK
A17: 2021 | B17: INA_ASSA_2021_0.pdf | C17: page-90 | D17: markdown.md | E17: 5 | F17: 5. Saldos y transacciones con partes relacionadas | G17: Partes relacionadas | J17: - Compensación recibida por el personal clave de gerencia, directores, personal clave de la gerencia: Algunos miembros del personal clave de la gerencia del Grupo participan en programas de opción de compra de acciones y de concesión de acciones ("grants") del Grupo (véase Nota 23). Adicionalmente, algunos de los empleados de las subsidiarias de ASSA Compañía Tenedora, S. A., pueden participar en alguno de estos programas si cumplen con ciertos criterios de antigüedad de servicios, entre otros. | T17: OK
A18: 2021 | B18: INA_ASSA_2021_0.pdf | C18: page-90 | D18: markdown.md | E18: 5 | F18: 5. Saldos y transacciones con partes relacionadas | G18: Partes relacionadas | J18: Las transacciones del personal clave de gerencia y directores están compuestas por dietas, salarios y otras remuneraciones y ascienden a US$9,402,041 (2020: US$10,097,417). | K18: 9402041 | L18: B/. | T18: OK
A19: 2021 | B19: INA_ASSA_2021_0.pdf | C19: page-91 | D19: markdown.md | E19: 5 | F19: 5. Saldos y transacciones con partes relacionadas | G19: Partes relacionadas | J19: (b) Saldos y transacciones con compañías relacionadas y afiliadas Los saldos con las partes relacionadas se detallan de la siguiente manera: | T19: OK
A20: 2021 | B20: INA_ASSA_2021_0.pdf | C20: page-91 | D20: tbl-29.html | E20: 5 | F20: 5. Saldos y transacciones con partes relacionadas | G20: Partes relacionadas | J20: [tbl-29.html](tbl-29.html) | T20: OK
A21: 2021 | B21: INA_ASSA_2021_0.pdf | C21: page-91 | D21: markdown.md | E21: 5 | F21: 5. Saldos y transacciones con partes relacionadas | G21: Partes relacionadas | J21: Ocasionalmente, el Grupo adquiere instrumentos financieros emitidos por partes relacionadas y afiliadas y coloca depósitos en esas compañías, los cuales producen ingresos financieros. | T21: OK
A22: 2021 | B22: INA_ASSA_2021_0.pdf | C22: page-91 | D22: markdown.md | E22: 5 | F22: 5. Saldos y transacciones con partes relacionadas | G22: Partes relacionadas | J22: También el Grupo, dentro del giro normal del negocio, vende productos de seguros de algunas compañías relacionadas, pagando igualmente cualquier reclamo. Los términos y condiciones de estas transacciones no han sido más favorables que aquellos que se pudiera razonablemente esperar que estuvieran disponibles, en transacciones similares, a entidades no relacionadas, sobre la base de libre competencia. | T22: OK
A23: 2021 | B23: INA_ASSA_2021_0.pdf | C23: page-92 | D23: markdown.md | E23: 6 | F23: 6. Efectivo y depósitos en bancos | G23: Working capital | J23: El efectivo y los depósitos en bancos se detallan de la siguiente manera: | T23: OK
A24: 2021 | B24: INA_ASSA_2021_0.pdf | C24: page-92 | D24: tbl-30.html | E24: 6 | F24: 6. Efectivo y depósitos en bancos | G24: Working capital | J24: [tbl-30.html](tbl-30.html) | T24: OK
A25: 2021 | B25: INA_ASSA_2021_0.pdf | C25: page-92 | D25: markdown.md | E25: 6 | F25: 6. Efectivo y depósitos en bancos | G25: Working capital | J25: El efectivo restringido consiste en: | T25: OK
A26: 2021 | B26: INA_ASSA_2021_0.pdf | C26: page-92 | D26: markdown.md | E26: 6 | F26: 6. Efectivo y depósitos en bancos | G26: Working capital | J26: - Encaje legal depositado en el Banco Central de Nicaragua por US$50,335,044 (2020: US$47,940,434) basado en el porcentaje de los depósitos captados de terceros. - Al 31 de diciembre de 2021, no se mantienen depósitos en garantía de operaciones (2020: US$946,803). | K26: 50335044 | L26: B/. | T26: OK
A27: 2021 | B27: INA_ASSA_2021_0.pdf | C27: page-92 | D27: markdown.md | E27: 7 | F27: 7. Cuentas por cobrar de seguros y otras, neto | G27: Cuentas por cobrar | J27: Las cuentas por cobrar de seguros y otras cuentas por cobrar, netas se detallan de la siguiente manera: | T27: OK
A28: 2021 | B28: INA_ASSA_2021_0.pdf | C28: page-92 | D28: tbl-31.html | E28: 7 | F28: 7. Cuentas por cobrar de seguros y otras, neto | G28: Cuentas por cobrar | J28: [tbl-31.html](tbl-31.html) | T28: OK
A29: 2021 | B29: INA_ASSA_2021_0.pdf | C29: page-92 | D29: markdown.md | E29: 7 | F29: 7. Cuentas por cobrar de seguros y otras, neto | G29: Cuentas por cobrar | J29: La legislación panameña relacionada con la recuperación del crédito fiscal por realizar se detalla en la Nota 32 (b). | T29: OK
A30: 2021 | B30: INA_ASSA_2021_0.pdf | C30: page-93 | D30: markdown.md | E30: 7 | F30: 7. Cuentas por cobrar de seguros y otras, neto | G30: Cuentas por cobrar | J30: Los movimientos de la provisión para pérdidas crediticias esperadas en primas por cobrar se detallan de la siguiente forma: | T30: OK
A31: 2021 | B31: INA_ASSA_2021_0.pdf | C31: page-93 | D31: tbl-32.html | E31: 7 | F31: 7. Cuentas por cobrar de seguros y otras, neto | G31: Cuentas por cobrar | J31: [tbl-32.html](tbl-32.html) | T31: OK
A32: 2021 | B32: INA_ASSA_2021_0.pdf | C32: page-93 | D32: markdown.md | E32: 7 | F32: 7. Cuentas por cobrar de seguros y otras, neto | G32: Cuentas por cobrar | J32: (8) Préstamos por cobrar, neto | T32: OK
A33: 2021 | B33: INA_ASSA_2021_0.pdf | C33: page-93 | D33: markdown.md | E33: 7 | F33: 7. Cuentas por cobrar de seguros y otras, neto | G33: Cuentas por cobrar | J33: La composición de la cartera de préstamos netos, distribuidos por actividad económica, se resume a continuación: | T33: OK
A34: 2021 | B34: INA_ASSA_2021_0.pdf | C34: page-93 | D34: tbl-33.html | E34: 7 | F34: 7. Cuentas por cobrar de seguros y otras, neto | G34: Cuentas por cobrar | J34: [tbl-33.html](tbl-33.html) | T34: OK
A35: 2021 | B35: INA_ASSA_2021_0.pdf | C35: page-93 | D35: markdown.md | E35: 7 | F35: 7. Cuentas por cobrar de seguros y otras, neto | G35: Cuentas por cobrar | J35: Al 31 de diciembre de 2021, las tasas de interés anual de los préstamos oscilaban entre 5% y 30% (2020: 5% y 33%) y para tarjetas de crédito entre 13% y 45% (2020: 15% y 45%). | T35: OK
A36: 2021 | B36: INA_ASSA_2021_0.pdf | C36: page-93 | D36: markdown.md | E36: 7 | F36: 7. Cuentas por cobrar de seguros y otras, neto | G36: Cuentas por cobrar | J36: Al 31 de diciembre de 2021, la subsidiaria La Hipotecaria (Holding), Inc. y Subsidiarias, mantenía préstamos hipotecarios para viviendas por US$200,910,697 (2020: US$238,395,359) en garantía de obligaciones contraídas con instituciones financieras y a la fecha no mantienen créditos hipotecarios en garantía de notas comerciales negociables (véase Nota 14). | K36: 200910697 | L36: B/. | T36: OK
A37: 2021 | B37: INA_ASSA_2021_0.pdf | C37: page-94 | D37: markdown.md | E37: 7 | F37: 7. Cuentas por cobrar de seguros y otras, neto | G37: Cuentas por cobrar | J37: Al 31 de diciembre de 2021, la subsidiaria Grupo BDF, S. A. mantenía préstamos por cobrar por US$67,097,026 (2020: US$80,067,689) que garantizan obligaciones con instituciones financieras (véase Nota 14). | K37: 67097026 | L37: B/. | T37: OK
A38: 2021 | B38: INA_ASSA_2021_0.pdf | C38: page-94 | D38: markdown.md | E38: 7 | F38: 7. Cuentas por cobrar de seguros y otras, neto | G38: Cuentas por cobrar | J38: El movimiento de la provisión para pérdidas crediticias esperadas en préstamos se detalla a continuación: | T38: OK
A39: 2021 | B39: INA_ASSA_2021_0.pdf | C39: page-94 | D39: tbl-34.html | E39: 7 | F39: 7. Cuentas por cobrar de seguros y otras, neto | G39: Cuentas por cobrar | J39: [tbl-34.html](tbl-34.html) | T39: OK
A40: 2021 | B40: INA_ASSA_2021_0.pdf | C40: page-94 | D40: markdown.md | E40: 7 | F40: 7. Cuentas por cobrar de seguros y otras, neto | G40: Cuentas por cobrar | J40: Las subsidiarias con operaciones bancarias en Panamá y Nicaragua, requieren establecer reservas regulatorias para préstamos, indistintamente de las provisiones requeridas bajo NIIF. | T40: OK
A41: 2021 | B41: INA_ASSA_2021_0.pdf | C41: page-94 | D41: markdown.md | E41: 7 | F41: 7. Cuentas por cobrar de seguros y otras, neto | G41: Cuentas por cobrar | J41: Al 31 de diciembre de 2021, estas reservas regulatorias acumuladas ascienden a US$17,999,310 (2020: US$18,978,963), las cuales se presentan en el estado consolidado de cambios en el patrimonio como una apropiación de las utilidades no distribuidas disponibles. | K41: 17999310 | L41: B/. | T41: OK
A42: 2021 | B42: INA_ASSA_2021_0.pdf | C42: page-94 | D42: markdown.md | E42: 7 | F42: 7. Cuentas por cobrar de seguros y otras, neto | G42: Cuentas por cobrar | J42: (9) Inversiones | T42: OK
A43: 2021 | B43: INA_ASSA_2021_0.pdf | C43: page-94 | D43: markdown.md | E43: 7 | F43: 7. Cuentas por cobrar de seguros y otras, neto | G43: Cuentas por cobrar | J43: Las inversiones se detallan de la siguiente manera: | T43: OK
A44: 2021 | B44: INA_ASSA_2021_0.pdf | C44: page-94 | D44: tbl-35.html | E44: 7 | F44: 7. Cuentas por cobrar de seguros y otras, neto | G44: Cuentas por cobrar | J44: [tbl-35.html](tbl-35.html) | T44: OK
A45: 2021 | B45: INA_ASSA_2021_0.pdf | C45: page-95 | D45: markdown.md | E45: 7 | F45: 7. Cuentas por cobrar de seguros y otras, neto | G45: Cuentas por cobrar | J45: El movimiento de las inversiones es el siguiente: | T45: OK
A46: 2021 | B46: INA_ASSA_2021_0.pdf | C46: page-95 | D46: tbl-36.html | E46: 7 | F46: 7. Cuentas por cobrar de seguros y otras, neto | G46: Cuentas por cobrar | J46: [tbl-36.html](tbl-36.html) | T46: OK
A47: 2021 | B47: INA_ASSA_2021_0.pdf | C47: page-95 | D47: markdown.md | E47: 7 | F47: 7. Cuentas por cobrar de seguros y otras, neto | G47: Cuentas por cobrar | J47: Inversiones a valor razonable con cambios en resultados: | T47: OK
A48: 2021 | B48: INA_ASSA_2021_0.pdf | C48: page-95 | D48: markdown.md | E48: 7 | F48: 7. Cuentas por cobrar de seguros y otras, neto | G48: Cuentas por cobrar | J48: Durante el año el Grupo realizó ventas de su portafolio de inversiones a valor razonable con cambios en resultados por US$13,464,014 (2020: US$11,099,401). Estas ventas generaron una ganancia neta por US$794,672 (2020: US$1,105,661) la cual se presenta en el estado consolidado de resultados en el rubro de ingresos financieros, neto. | K48: 13464014 | L48: B/. | T48: OK
A49: 2021 | B49: INA_ASSA_2021_0.pdf | C49: page-95 | D49: markdown.md | E49: 7 | F49: 7. Cuentas por cobrar de seguros y otras, neto | G49: Cuentas por cobrar | J49: Inversiones a valor razonable con cambios en otros resultados integrales: | T49: OK
A50: 2021 | B50: INA_ASSA_2021_0.pdf | C50: page-95 | D50: markdown.md | E50: 7 | F50: 7. Cuentas por cobrar de seguros y otras, neto | G50: Cuentas por cobrar | J50: El Grupo realizó ventas de su portafolio de inversiones a valor razonable con cambios en otras utilidades integrales por un total de US$15,162,155 (2020: US$59,973,183). Estas ventas generaron una ganancia neta por US$1,229,801 (2020: US$3,334,501) la cual se presenta en el estado consolidado de resultados en el rubro de ingresos financieros, neto. Estas transacciones incluyen acciones en corporaciones que fueron vendidas durante el año 2021, cuyo valor en libros a esa fecha era de US$2,010,000 y reconoció una ganancia por US$9,679 no reciclables la cual se presenta en el estado consolidado de otros resultados integrales. | K50: 15162155 | L50: B/. | T50: OK
A51: 2021 | B51: INA_ASSA_2021_0.pdf | C51: page-95 | D51: markdown.md | E51: 7 | F51: 7. Cuentas por cobrar de seguros y otras, neto | G51: Cuentas por cobrar | J51: Inversiones a costo amortizado: | T51: OK
A52: 2021 | B52: INA_ASSA_2021_0.pdf | C52: page-95 | D52: markdown.md | E52: 7 | F52: 7. Cuentas por cobrar de seguros y otras, neto | G52: Cuentas por cobrar | J52: El Grupo no realizó ventas de su portafolio de inversiones a costo amortizado (2020: US$50,014,300). Se generaron pérdida neta por ajustes por US$1,010 (2020: una ganancia neta por US$3,295,021) la cual se presenta en el estado consolidado de resultados en el rubro de ingresos financieros, neto. | K52: 50014300 | L52: B/. | T52: OK
A53: 2021 | B53: INA_ASSA_2021_0.pdf | C53: page-96 | D53: markdown.md | E53: 7 | F53: 7. Cuentas por cobrar de seguros y otras, neto | G53: Cuentas por cobrar | J53: El movimiento de la provisión para pérdidas crediticias esperadas es el siguiente: | T53: OK
A54: 2021 | B54: INA_ASSA_2021_0.pdf | C54: page-96 | D54: tbl-37.html | E54: 7 | F54: 7. Cuentas por cobrar de seguros y otras, neto | G54: Cuentas por cobrar | J54: [tbl-37.html](tbl-37.html) | T54: OK
A55: 2021 | B55: INA_ASSA_2021_0.pdf | C55: page-97 | D55: markdown.md | E55: 10 | F55: 10. Inmuebles, mobiliario, equipo y mejoras, neto | G55: PP&E / capex / depreciación | J55: A continuación, se muestra un detalle de los inmuebles, mobiliario, equipo y mejoras, a su costo, menos la depreciación y amortización acumulada. | T55: OK
A56: 2021 | B56: INA_ASSA_2021_0.pdf | C56: page-97 | D56: tbl-38.html | E56: 10 | F56: 10. Inmuebles, mobiliario, equipo y mejoras, neto | G56: PP&E / capex / depreciación | J56: [tbl-38.html](tbl-38.html) [tbl-39.html](tbl-39.html) | T56: OK
A57: 2021 | B57: INA_ASSA_2021_0.pdf | C57: page-97 | D57: markdown.md | E57: 10 | F57: 10. Inmuebles, mobiliario, equipo y mejoras, neto | G57: PP&E / capex / depreciación | J57: Al 31 de diciembre de 2021, el Grupo mantiene propiedades de inversión, netas por US$14,356,814 (2020: US$14,887,467) y que se encuentran registrados en el rubro de otros activos en el estado consolidado de situación financiera. Al 31 de diciembre de 2021, se dieron adiciones de propiedades de inversión por un monto de US$8,054 (2020: US$389,332). Al 31 de diciembre de 2021, el gasto de amortización de las propiedades de inversión fue de US$241,137 (2020: US$246,528). | K57: 14356814 | L57: B/. | T57: OK
A58: 2021 | B58: INA_ASSA_2021_0.pdf | C58: page-98 | D58: markdown.md | E58: 11 | F58: 11. Activos por derecho de uso, netos | G58: Otros | J58: El movimiento de los activos por derecho de uso, se detalla a continuación: | T58: OK
A59: 2021 | B59: INA_ASSA_2021_0.pdf | C59: page-98 | D59: tbl-40.html | E59: 11 | F59: 11. Activos por derecho de uso, netos | G59: Otros | J59: [tbl-40.html](tbl-40.html) | T59: OK
A60: 2021 | B60: INA_ASSA_2021_0.pdf | C60: page-98 | D60: markdown.md | E60: 12 | F60: 12. Activos intangibles y plusvalía | G60: Intangibles | J60: La conciliación del importe en libro de los activos intangibles y la plusvalía del Grupo se presenta a continuación: | T60: OK
A61: 2021 | B61: INA_ASSA_2021_0.pdf | C61: page-98 | D61: tbl-41.html | E61: 12 | F61: 12. Activos intangibles y plusvalía | G61: Intangibles | J61: [tbl-41.html](tbl-41.html) | T61: OK
A62: 2021 | B62: INA_ASSA_2021_0.pdf | C62: page-99 | D62: tbl-42.html | E62: 12 | F62: 12. Activos intangibles y plusvalía | G62: Intangibles | J62: [tbl-42.html](tbl-42.html) | T62: OK
A63: 2021 | B63: INA_ASSA_2021_0.pdf | C63: page-99 | D63: markdown.md | E63: 12 | F63: 12. Activos intangibles y plusvalía | G63: Intangibles | J63: Las plusvalías están sujetas a pruebas anuales de deterioro y corresponden a la adquisición del control de los siguientes negocios: | T63: OK
A64: 2021 | B64: INA_ASSA_2021_0.pdf | C64: page-99 | D64: tbl-43.html | E64: 12 | F64: 12. Activos intangibles y plusvalía | G64: Intangibles | J64: [tbl-43.html](tbl-43.html) | T64: OK
A65: 2021 | B65: INA_ASSA_2021_0.pdf | C65: page-99 | D65: markdown.md | E65: 12 | F65: 12. Activos intangibles y plusvalía | G65: Intangibles | J65: Prueba del deterioro del valor – Assicurazioni Generali S.p.A. y La Hipotecaria Holding Inc. El importe recuperable de esta UGE se basó en su valor en uso, considerando la estimación de flujos futuros generados por la UGE, comparado con su importe en libros. | T65: OK
A66: 2021 | B66: INA_ASSA_2021_0.pdf | C66: page-99 | D66: markdown.md | E66: 12 | F66: 12. Activos intangibles y plusvalía | G66: Intangibles | J66: Los supuestos claves utilizados en el cálculo del importe recuperable se señalan a continuación. Los valores asignados a los supuestos clave representan la evaluación de la gerencia tomando como base las proyecciones de las pérdidas y ganancias a cinco años, teniendo presentes tanto fuentes externas como internas. | T66: OK
A67: 2021 | B67: INA_ASSA_2021_0.pdf | C67: page-99 | D67: tbl-44.html | E67: 12 | F67: 12. Activos intangibles y plusvalía | G67: Intangibles | J67: [tbl-44.html](tbl-44.html) | T67: OK
A68: 2021 | B68: INA_ASSA_2021_0.pdf | C68: page-100 | D68: markdown.md | E68: 12 | F68: 12. Activos intangibles y plusvalía | G68: Intangibles | J68: La tasa de descuento utilizada está estimada bajo el modelo de valoración de activos (CAPM) por sus siglas en inglés. | T68: OK
A69: 2021 | B69: INA_ASSA_2021_0.pdf | C69: page-100 | D69: markdown.md | E69: 12 | F69: 12. Activos intangibles y plusvalía | G69: Intangibles | J69: Las proyecciones de los flujos de caja esperados futuros, incluyeron estimaciones específicas para cinco años y una tasa de crecimiento temporal con posterioridad a esos cinco años. La tasa de crecimiento terminal, se determinó sobre la base de la estimación de la gerencia de la tasa de crecimiento anual, compuesta de largo plazo consistente, con los supuestos razonables que efectuaría un participante en el mercado. | T69: OK
... A111: 2021 | B111: INA_ASSA_2021_0.pdf | C111: page-106 | D111: tbl-54.html | E111: 14 | F111: 14. Emisiones de deuda y obligaciones | G111: Deuda / bonos / préstamos / leases | J111: [tbl-54.html](tbl-54.html) | T111: OK
A112: 2021 | B112: INA_ASSA_2021_0.pdf | C112: page-107 | D112: markdown.md | E112: 14 | F112: 14. Emisiones de deuda y obligaciones | G112: Deuda / bonos / préstamos / leases | J112: Los valores comerciales negociables son programas rotativos emitidos en Panamá autorizados por la Superintendencia del Mercado de Valores. Estos constan de seis programas rotativos de hasta US$200,000,000 los cuales se encuentran respaldados de la siguiente manera: | K112: 200000000 | L112: B/. | T112: OK
A113: 2021 | B113: INA_ASSA_2021_0.pdf | C113: page-107 | D113: markdown.md | E113: 14 | F113: 14. Emisiones de deuda y obligaciones | G113: Deuda / bonos / préstamos / leases | J113: - Un programa por el monto total autorizado de hasta US$10,000,000 se encuentran respaldado por una fianza solidaria de Grupo ASSA, S. A. y crédito general de La Hipotecaria (Holding), Inc. Actualmente este programa no tiene valores en circulación. | K113: 10000000 | L113: B/. | T113: OK
A114: 2021 | B114: INA_ASSA_2021_0.pdf | C114: page-107 | D114: markdown.md | E114: 14 | F114: 14. Emisiones de deuda y obligaciones | G114: Deuda / bonos / préstamos / leases | J114: - Cinco programas por el monto total autorizado de hasta US$190,000,000 respaldado con crédito general de La Hipotecaria (Holding), Inc. | K114: 190000000 | L114: B/. | T114: OK
A115: 2021 | B115: INA_ASSA_2021_0.pdf | C115: page-107 | D115: markdown.md | E115: 14 | F115: 14. Emisiones de deuda y obligaciones | G115: Deuda / bonos / préstamos / leases | J115: Las notas comerciales negociables son títulos emitidos en Panamá y autorizados por la Superintendencia del Mercado de Valores. Al 31 de diciembre de 2021, existen cuatro programas autorizados de los cuales el primero por US$40,000,000 se encuentra respaldado con el crédito general de Banco La Hipotecaria, S. A., un fideicomiso de garantía de créditos hipotecarios. Actualmente, el Banco La Hipotecaria no mantiene notas en circulación relacionadas a este programa. | K115: 40000000 | L115: B/. | T115: OK
A116: 2021 | B116: INA_ASSA_2021_0.pdf | C116: page-107 | D116: markdown.md | E116: 14 | F116: 14. Emisiones de deuda y obligaciones | G116: Deuda / bonos / préstamos / leases | J116: Las colocaciones de los otros tres programas corresponden a dos programas por la suma de US$50,000,000, US$50,000,000 y uno por US$100,000,000 respectivamente, están respaldados solo por el crédito general de Banco La Hipotecaria, S. A. | K116: 50000000 | L116: B/. | T116: OK
A117: 2021 | B117: INA_ASSA_2021_0.pdf | C117: page-107 | D117: markdown.md | E117: 14 | F117: 14. Emisiones de deuda y obligaciones | G117: Deuda / bonos / préstamos / leases | J117: La subsidiaria Banco La Hipotecaria, S. A. tiene autorizado por la Superintendencia del Mercado de Valores de El Salvador dos emisiones que suman US$100,000,000 en Certificados de Inversiones (CI). Las obligaciones negociables constan de dos planes rotativos de hasta US$35,000,000 en Papel Bursátil, autorizado por la Superintendencia del Sistema Financiero de El Salvador. | K117: 100000000 | L117: B/. | T117: OK
A118: 2021 | B118: INA_ASSA_2021_0.pdf | C118: page-107 | D118: markdown.md | E118: 14 | F118: 14. Emisiones de deuda y obligaciones | G118: Deuda / bonos / préstamos / leases | J118: La Superintendencia Financiera de Colombia mediante Resolución 015094871-006-000 del 8 de octubre de 2015, autorizó la inscripción de Bonos Ordinarios en el Registro Nacional de Valores y Emisores y su respectiva oferta pública. | T118: OK
A119: 2021 | B119: INA_ASSA_2021_0.pdf | C119: page-107 | D119: markdown.md | E119: 14 | F119: 14. Emisiones de deuda y obligaciones | G119: Deuda / bonos / préstamos / leases | J119: Al 31 de diciembre de 2021, la subsidiaria de Banco La Hipotecaria en Colombia ha emitido bonos ordinarios en pesos colombianos a mediano plazo por un valor equivalente a US$13,009,668 (2020: US$15,091,711) a una tasa de 6.29% (2020: 6.29%) a un plazo de 5 años, con vencimiento 23 de junio de 2025 (2020: vencimiento el 25 de junio de 2025). | K119: 13009668 | L119: B/. | T119: OK
A120: 2021 | B120: INA_ASSA_2021_0.pdf | C120: page-107 | D120: markdown.md | E120: 14 | F120: 14. Emisiones de deuda y obligaciones | G120: Deuda / bonos / préstamos / leases | J120: La Junta Directiva de la subsidiaria, Banco La Hipotecaria, mediante acta de junta directiva del 24 de mayo de 2018, autorizó la emisión de un programa de Covered Bond por US$200,000,000. Al 31 de diciembre de 2021, se han emitido Covered Bond a mediano plazo netos de comisiones por US$51,347,808 (2020: US$51,074,683), a una tasa de 5.50%, 4.75% y 4.125% respectivamente con un plazo de 3.5 y 5 años. No ha habido incumplimiento en el pago de capitales e intereses en las obligaciones y financiamientos recibidos. | K120: 200000000 | L120: B/. | T120: OK
A121: 2021 | B121: INA_ASSA_2021_0.pdf | C121: page-108 | D121: markdown.md | E121: 14 | F121: 14. Emisiones de deuda y obligaciones | G121: Deuda / bonos / préstamos / leases | J121: El Grupo tiene autorizado por la Superintendencia de Bancos y Otras Instituciones Financieras de la República de Nicaragua una emisión de valores estandarizados de renta fija de US$50,000,000 desmaterializados y en denominaciones de US$1,000 con intereses pagaderos trimestralmente, los cuales se encuentran respaldados por el crédito general de la subsidiaria Banco de Finanzas, S. A. (el emisor). Al 31 de diciembre de 2021, el saldo colocado es de US$8,487,000 de un monto ofertado de US$8,500,000, con vencimientos entre 2021 y 2022, a una tasa entre el 5.20% y 7.00% (2020: saldo colocado US$6,724,000, vencimientos entre 2021 y 2022, tasa entre 6.45% y 9.00%). | K121: 50000000 | L121: B/. | T121: OK
A122: 2021 | B122: INA_ASSA_2021_0.pdf | C122: page-108 | D122: markdown.md | E122: 14 | F122: 14. Emisiones de deuda y obligaciones | G122: Deuda / bonos / préstamos / leases | J122: Al 31 de diciembre de 2021, las obligaciones mantenían las siguientes garantías: | T122: OK
A123: 2021 | B123: INA_ASSA_2021_0.pdf | C123: page-108 | D123: tbl-55.html | E123: 14 | F123: 14. Emisiones de deuda y obligaciones | G123: Deuda / bonos / préstamos / leases | J123: [tbl-55.html](tbl-55.html) | T123: OK
A124: 2021 | B124: INA_ASSA_2021_0.pdf | C124: page-108 | D124: markdown.md | E124: 14 | F124: 14. Emisiones de deuda y obligaciones | G124: Deuda / bonos / préstamos / leases | J124: El Grupo no ha tenido incumplimientos de principal, intereses con relación a sus financiamientos recibidos, y en los casos que apliquen cuenta con las dispensas ("waivers") correspondientes hasta la fecha de autorización de estos estados financieros consolidados. | T124: OK
A125: 2021 | B125: INA_ASSA_2021_0.pdf | C125: page-108 | D125: markdown.md | E125: 15 | F125: 15. Obligaciones subordinadas | G125: Deuda / bonos / préstamos / leases | J125: Al 31 de diciembre de 2021, la subsidiaria Banco de Finanzas, S. A., mantenía las siguientes obligaciones subordinadas: | T125: OK
A126: 2021 | B126: INA_ASSA_2021_0.pdf | C126: page-108 | D126: tbl-56.html | E126: 15 | F126: 15. Obligaciones subordinadas | G126: Deuda / bonos / préstamos / leases | J126: [tbl-56.html](tbl-56.html) | T126: OK
A127: 2021 | B127: INA_ASSA_2021_0.pdf | C127: page-108 | D127: markdown.md | E127: 15 | F127: 15. Obligaciones subordinadas | G127: Deuda / bonos / préstamos / leases | J127: Mediante la suscripción del contrato de préstamo, el Banco de Finanzas, S. A. acordó con el Banco Centroamericano de Integración Económica (BCIE) que, en caso de liquidar sus operaciones, el acreedor renunciará a todo derecho de preferencia y aceptará que el pago de las obligaciones del banco se efectúe luego de canceladas las deudas con los demás acreedores no subordinados. | T127: OK
A128: 2021 | B128: INA_ASSA_2021_0.pdf | C128: page-109 | D128: markdown.md | E128: 15 | F128: 15. Obligaciones subordinadas | G128: Deuda / bonos / préstamos / leases | J128: El movimiento de las obligaciones subordinadas se detalla a continuación: | T128: OK
A129: 2021 | B129: INA_ASSA_2021_0.pdf | C129: page-109 | D129: tbl-57.html | E129: 15 | F129: 15. Obligaciones subordinadas | G129: Deuda / bonos / préstamos / leases | J129: [tbl-57.html](tbl-57.html) | T129: OK
A130: 2021 | B130: INA_ASSA_2021_0.pdf | C130: page-109 | D130: markdown.md | E130: 15 | F130: 15. Obligaciones subordinadas | G130: Deuda / bonos / préstamos / leases | J130: El Grupo no ha tenido incumplimientos de principal, intereses con relación a sus financiamientos recibidos, y en los casos que apliquen cuenta con las dispensas ("waivers") correspondientes hasta la fecha de autorización de estos estados financieros consolidados. | T130: OK
A131: 2021 | B131: INA_ASSA_2021_0.pdf | C131: page-109 | D131: markdown.md | E131: 16 | F131: 16. Pasivos por arrendamientos | G131: Deuda / bonos / préstamos / leases | J131: El movimiento de los pasivos por arrendamientos, se detalla a continuación: | T131: OK
A132: 2021 | B132: INA_ASSA_2021_0.pdf | C132: page-109 | D132: tbl-58.html | E132: 16 | F132: 16. Pasivos por arrendamientos | G132: Deuda / bonos / préstamos / leases | J132: [tbl-58.html](tbl-58.html) | T132: OK
A133: 2021 | B133: INA_ASSA_2021_0.pdf | C133: page-109 | D133: markdown.md | E133: 17 | F133: 17. Otros pasivos | G133: Otros | J133: Los otros pasivos se detallan a continuación: | T133: OK
A134: 2021 | B134: INA_ASSA_2021_0.pdf | C134: page-109 | D134: tbl-59.html | E134: 17 | F134: 17. Otros pasivos | G134: Otros | J134: [tbl-59.html](tbl-59.html) | T134: OK
A135: 2021 | B135: INA_ASSA_2021_0.pdf | C135: page-110 | D135: markdown.md | E135: 18 | F135: 18. Capital | G135: Capital / patrimonio / dividendos | J135: Al 31 de diciembre de 2021, el Grupo ha emitido 10,303,155 acciones (2020: 10,280,406 acciones) de las cuales 131,251 acciones (2020: 127,970) se mantienen en tesorería quedando un total de acciones en circulación de 10,171,904 (2020: 10,152,436). | K135: 10303155 | L135: B/. | T135: OK
A136: 2021 | B136: INA_ASSA_2021_0.pdf | C136: page-110 | D136: tbl-60.html | E136: 18 | F136: 18. Capital | G136: Capital / patrimonio / dividendos | J136: [tbl-60.html](tbl-60.html) | T136: OK
A137: 2021 | B137: INA_ASSA_2021_0.pdf | C137: page-110 | D137: markdown.md | E137: 18 | F137: 18. Capital | G137: Capital / patrimonio / dividendos | J137: Los poseedores de las acciones comunes tienen el derecho a recibir dividendos según se declaren de tiempo en tiempo y tienen derecho a un voto por acción en las asambleas de accionistas del Grupo. | T137: OK
A138: 2021 | B138: INA_ASSA_2021_0.pdf | C138: page-110 | D138: markdown.md | E138: 18 | F138: 18. Capital | G138: Capital / patrimonio / dividendos | J138: ### Acciones preferidas emitidas por compañía subsidiaria | T138: OK
A139: 2021 | B139: INA_ASSA_2021_0.pdf | C139: page-110 | D139: markdown.md | E139: 18 | F139: 18. Capital | G139: Capital / patrimonio / dividendos | J139: Al 31 de diciembre de 2021, se autorizaron un total de 10 emisiones públicas de acciones preferidas no acumulativas a la subsidiaria La Hipotecaria (Holding), Inc., registradas en la Superintendencia del Mercado de Valores de Panamá y listadas en la Bolsa Latinoamericana de Valores. El total de las acciones preferidas es de 210,000 acciones por un total de US$21,000,000 distribuidos en acciones por un valor nominal de cien dólares (US$100) cada una. Estas acciones presentan una tasa de interés entre 6.75% y 7% anual no acumulativas y distribuyen dividendos trimestralmente, si la Junta Directiva lo declara. El costo de emisión de las acciones preferidas ascendió a US$247,291. Durante el año terminado el 31 de diciembre de 2021 no se realizaron emisiones de acciones preferidas. | K139: 210000 | L139: B/. | T139: OK
A140: 2021 | B140: INA_ASSA_2021_0.pdf | C140: page-110 | D140: markdown.md | E140: 18 | F140: 18. Capital | G140: Capital / patrimonio / dividendos | J140: Al 31 de diciembre de 2021, La Hipotecaria (Holding), Inc., no realizó redención (2020: US$2,000,000) de acciones preferidas de un programa que se encuentra en circulación desde el año 2018. Estas acciones preferidas pueden ser pagadas a opción del emisor con un aviso previo de por lo menos 30 días, el cual se ejecutó el 15 de marzo de 2020. | K140: 2000000 | L140: B/. | T140: OK
A141: 2021 | B141: INA_ASSA_2021_0.pdf | C141: page-111 | D141: markdown.md | E141: 18 | F141: 18. Capital | G141: Capital / patrimonio / dividendos | J141: Los prospectos informativos de las ofertas públicas, establecen las siguientes principales condiciones: | T141: OK
A142: 2021 | B142: INA_ASSA_2021_0.pdf | C142: page-111 | D142: markdown.md | E142: 18 | F142: 18. Capital | G142: Capital / patrimonio / dividendos | J142: - Acciones Preferidas No Acumulativas (en adelante, las “Acciones Preferidas”) con derecho a recibir dividendos cuando estos sean declarados por la Junta Directiva, pero sin derecho a voz ni voto. - La declaración y el pago de dividendos es una potestad de la Junta Directiva del Emisor. - El pago de los dividendos correspondientes a un período anual, una vez declarados, se realizará mediante pagos trimestrales, los días quince (15) de marzo, quince (15) de junio, quince (15) de septiembre y quince (15) de diciembre de cada año. | T142: OK
...

Sheet ModeloFinanciero
A1: Grupo ASSA, S. A.
A2: Estados Financieros Consolidados Auditados FY21-FY25
A3: en US$ sin escala
A5: Años | B5: FY21A | C5: FY22A | D5: FY23A | E5: FY24A | F5: FY25A | G5: FY26E | H5: FY27E | I5: FY28E | J5: FY29E | K5: FY30E
A6: Estado de Resultados
A7: Primas suscritas, netas de cancelaciones | B7: =EEFF!B8 -> 657884741 | C7: =EEFF!C8 -> 698200257 | D7: =EEFF!D8 -> 817173751 | F7: =EEFF!F8 -> 0
A8: Primas suscritas cedidas a reaseguradores | B8: =EEFF!B9 -> -356304040 | C8: =EEFF!C9 -> -361584073 | D8: =EEFF!D9 -> -435628239 | F8: =EEFF!F9 -> 0
A9: Total de primas netas retenidas | B9: =EEFF!B10 -> 301580701 | C9: =EEFF!C10 -> 336616184 | D9: =EEFF!D10 -> 381545512 | F9: =EEFF!F10 -> 0 | G9: =G7+G8 -> 0 | H9: =H7+H8 -> 0 | I9: =I7+I8 -> 0 | J9: =J7+J8 -> 0 | K9: =K7+K8 -> 0
A10: Cambio en la provisión bruta para riesgo en curso | B10: =EEFF!B11 -> -9152442 | C10: =EEFF!C11 -> 3120015 | D10: =EEFF!D11 -> -28420469 | F10: =EEFF!F11 -> 0
A11: Cambio en la provisión en los negocios de vida a largo plazo sobre pólizas de vida | B11: =EEFF!B12 -> -10285045 | C11: =EEFF!C12 -> -12525971 | D11: =EEFF!D12 -> -12302706 | F11: =EEFF!F12 -> 0
A12: Cambio en la participación de los reaseguradores en la provisión sobre contratos de seguros | B12: =EEFF!B13 -> 9401319 | C12: =EEFF!C13 -> -6820962 | D12: =EEFF!D13 -> 16095063 | E12: =EEFF!E13 -> 0 | F12: =EEFF!F13 -> 0
A13: Total de cambios en las provisiones de los contratos de seguros | B13: =EEFF!B14 -> -10036168 | C13: =EEFF!C14 -> -16226918 | D13: =EEFF!D14 -> -24628112 | F13: =EEFF!F14 -> 0 | G13: =G10+G11+G12 -> 0 | H13: =H10+H11+H12 -> 0 | I13: =I10+I11+I12 -> 0 | J13: =J10+J11+J12 -> 0 | K13: =K10+K11+K12 -> 0
A14: Primas netas ganadas | B14: =EEFF!B15 -> 291544533 | C14: =EEFF!C15 -> 320389266 | D14: =EEFF!D15 -> 356917400 | F14: =EEFF!F15 -> 0 | G14: =G9+G13 -> 0 | H14: =H9+H13 -> 0 | I14: =I9+I13 -> 0 | J14: =J9+J13 -> 0 | K14: =K9+K13 -> 0
A15: Reclamos y beneficios incurridos | B15: =EEFF!B16 -> -238994085 | C15: =EEFF!C16 -> -327863954 | D15: =EEFF!D16 -> -238087045 | F15: =EEFF!F16 -> 0 | G15: =G9*Supuestos!G19 -> 0 | H15: =H9*Supuestos!H19 -> 0 | I15: =I9*Supuestos!I19 -> 0 | J15: =J9*Supuestos!J19 -> 0 | K15: =K9*Supuestos!K19 -> 0
A16: Participación de los reaseguradores en los reclamos y beneficios incurridos | B16: =EEFF!B17 -> 101363600 | C16: =EEFF!C17 -> 176570373 | D16: =EEFF!D17 -> 65656958 | F16: =EEFF!F17 -> 0
A17: Beneficios por reembolsos y rescates | B17: =EEFF!B18 -> -13646362 | C17: =EEFF!C18 -> -14629260 | D17: =EEFF!D18 -> -16826376 | F17: =EEFF!F18 -> 0
A18: Reclamos y beneficios netos incurridos por los asegurados | B18: =EEFF!B19 -> -151276847 | C18: =EEFF!C19 -> -165922841 | D18: =EEFF!D19 -> -189256463 | F18: =EEFF!F19 -> 0
A19: Costo de suscripción y adquisición | B19: =EEFF!B20 -> -89805859 | C19: =EEFF!C20 -> -98549869 | D19: =EEFF!D20 -> -115810518 | F19: =EEFF!F20 -> 0
A20: Provisión para pérdidas crediticias esperadas en primas por cobrar | B20: =EEFF!B21 -> -143340 | C20: =EEFF!C21 -> -1327507 | D20: =EEFF!D21 -> -1113601 | F20: =EEFF!F21 -> 0
A21: Primas netas ganadas, después de reclamos, costos de suscripción y provisión para pérdidas crediticias esperadas en primas por cobrar | B21: =EEFF!B22 -> 50318487 | C21: =EEFF!C22 -> 54589049 | D21: =EEFF!D22 -> 50736818 | F21: =EEFF!F22 -> 0 | G21: =G15+G16+G17+G18+G19+G20 -> 0 | H21: =H15+H16+H17+H18+H19+H20 -> 0 | I21: =I15+I16+I17+I18+I19+I20 -> 0 | J21: =J15+J16+J17+J18+J19+J20 -> 0 | K21: =K15+K16+K17+K18+K19+K20 -> 0
A22: Intereses sobre préstamos | B22: =EEFF!B23 -> 90113580 | C22: =EEFF!C23 -> 89349229 | D22: =EEFF!D23 -> 99791323 | E22: =EEFF!E23 -> 0 | F22: =EEFF!F23 -> 0
A23: Intereses sobre depósitos en bancos | B23: =EEFF!B24 -> 324360 | C23: =EEFF!C24 -> 852370 | D23: =EEFF!D24 -> 1871676 | E23: =EEFF!E24 -> 0 | F23: =EEFF!F24 -> 0
A24: Intereses sobre inversiones en valores | B24: =EEFF!B25 -> 30270095 | C24: =EEFF!C25 -> 33792124 | D24: =EEFF!D25 -> 38203473 | E24: =EEFF!E25 -> 0 | F24: =EEFF!F25 -> 0
A25: Total de ingresos por intereses | B25: =EEFF!B26 -> 120708035 | C25: =EEFF!C26 -> 123993723 | D25: =EEFF!D26 -> 139866472 | E25: =EEFF!E26 -> 0 | F25: =EEFF!F26 -> 0 | G25: =G22+G23+G24 -> 0 | H25: =H22+H23+H24 -> 0 | I25: =I22+I23+I24 -> 0 | J25: =J22+J23+J24 -> 0 | K25: =K22+K23+K24 -> 0
A26: Gastos por intereses sobre depósitos | B26: =EEFF!B27 -> -25360968 | C26: =EEFF!C27 -> -25531810 | D26: =EEFF!D27 -> -34235136 | E26: =EEFF!E27 -> 0 | F26: =EEFF!F27 -> 0
A27: Gastos por intereses sobre emisiones de deuda y obligaciones | B27: =EEFF!B28 -> -30177384 | C27: =EEFF!C28 -> -29003930 | D27: =EEFF!D28 -> -34426805 | E27: =EEFF!E28 -> 0 | F27: =EEFF!F28 -> 0
A28: Total de gastos por intereses | B28: =EEFF!B29 -> -55538352 | C28: =EEFF!C29 -> -54535740 | D28: =EEFF!D29 -> -68661941 | F28: =EEFF!F29 -> 0 | G28: =G26+G27 -> 0 | H28: =H26+H27 -> 0 | I28: =I26+I27 -> 0 | J28: =J26+J27 -> 0 | K28: =K26+K27 -> 0
A29: Provisión para pérdidas crediticias esperadas en préstamos | B29: =EEFF!B30 -> -4291456 | C29: =EEFF!C30 -> -4626793 | D29: =EEFF!D30 -> -7316131 | E29: =EEFF!E30 -> 0 | F29: =EEFF!F30 -> 0
A30: Ganancia neta por modificación de préstamos a CA | B30: =EEFF!B31 -> 0 | C30: =EEFF!C31 -> 515213 | D30: =EEFF!D31 -> 67054 | E30: =EEFF!E31 -> 0 | F30: =EEFF!F31 -> 0
A31: Resultado neto de intereses, comisiones y provisión para pérdidas crediticias esperadas en préstamos | B31: =EEFF!B32 -> 60878227 | C31: =EEFF!C32 -> 65346403 | D31: =EEFF!D32 -> 63955454 | F31: =EEFF!F32 -> 0 | G31: =G25+G28+G29+G30 -> 0 | H31: =H25+H28+H29+H30 -> 0 | I31: =I25+I28+I29+I30 -> 0 | J31: =J25+J28+J29+J30 -> 0 | K31: =K25+K28+K29+K30 -> 0
A32: Ingresos por comisiones y servicios financieros | B32: =EEFF!B33 -> 53282269 | C32: =EEFF!C33 -> 54586912 | D32: =EEFF!D33 -> 68685561 | F32: =EEFF!F33 -> 0
A33: Ganancia (Pérdida) en venta de bonos y acciones, neto | B33: =EEFF!B34 -> 2013784 | C33: =EEFF!C34 -> -240213 | D33: =EEFF!D34 -> 63303 | E33: =EEFF!E34 -> 0 | F33: =EEFF!F34 -> 0
A34: Dividendos ganados | B34: =EEFF!B35 -> 24063694 | C34: =EEFF!C35 -> 30788100 | D34: =EEFF!D35 -> 40145969 | F34: =EEFF!F35 -> 0
A35: Ganancia (Pérdida) no realizada de inversiones a valor razonable con cambio en resultado | B35: =EEFF!B36 -> 6681944 | C35: =EEFF!C36 -> -14025402 | D35: =EEFF!D36 -> 5542980 | E35: =EEFF!E36 -> 0 | F35: =EEFF!F36 -> 0
A36: Otros ingresos de operaciones, neto | B36: =EEFF!B37 -> 9840321 | C36: =EEFF!C37 -> 5497518 | D36: =EEFF!D37 -> 3537146 | F36: =EEFF!F37 -> 0
A37: Reversión de (provisión para) pérdidas crediticias esperadas en inversiones | B37: =EEFF!B38 -> -125836 | C37: =EEFF!C38 -> -582779 | D37: =EEFF!D38 -> 1442923 | E37: =EEFF!E38 -> 0 | F37: =EEFF!F38 -> 0
A38: Resultados, neto | B38: =EEFF!B39 -> 206952890 | C38: =EEFF!C39 -> 195959588 | D38: =EEFF!D39 -> 234110154 | F38: =EEFF!F39 -> 0 | G38: =G21+G31+G32+G33+G34+G35+G36+G37 -> 0 | H38: =H21+H31+H32+H33+H34+H35+H36+H37 -> 0 | I38: =I21+I31+I32+I33+I34+I35+I36+I37 -> 0 | J38: =J21+J31+J32+J33+J34+J35+J36+J37 -> 0 | K38: =K21+K31+K32+K33+K34+K35+K36+K37 -> 0
A39: Gastos de personal | B39: =EEFF!B40 -> -65378406 | C39: =EEFF!C40 -> -68691932 | D39: =EEFF!D40 -> -72370796 | F39: =EEFF!F40 -> 0
A40: Gastos generales y administrativos | B40: =EEFF!B62 -> 0 | C40: =EEFF!C62 -> 0 | D40: =EEFF!D62 -> 0 | E40: =EEFF!E62 -> -89212204 | F40: =EEFF!F62 -> -95272868 | G40: =G9*Supuestos!G26 -> 0 | H40: =H9*Supuestos!H26 -> 0 | I40: =I9*Supuestos!I26 -> 0 | J40: =J9*Supuestos!J26 -> 0 | K40: =K9*Supuestos!K26 -> 0
A41: Gastos de depreciación de activos fijos y propiedades de inversión | B41: =EEFF!B42 -> -6393929 | C41: =EEFF!C42 -> -7352476 | D41: =EEFF!D42 -> -6753787 | F41: =EEFF!F42 -> 0
A42: Gastos de amortización de activos intangibles | B42: =EEFF!B43 -> -5044764 | C42: =EEFF!C43 -> -4929115 | D42: =EEFF!D43 -> -5165439 | F42: =EEFF!F43 -> 0
A43: Total de gastos administrativos | B43: =EEFF!B44 -> -116284021 | C43: =EEFF!C44 -> -122442828 | D43: =EEFF!D44 -> -126083718 | F43: =EEFF!F44 -> 0 | G43: =G39+G40+G41+G42 -> 0 | H43: =H39+H40+H41+H42 -> 0 | I43: =I39+I40+I41+I42 -> 0 | J43: =J39+J40+J41+J42 -> 0 | K43: =K39+K40+K41+K42 -> 0
A44: Utilidad antes del impuesto sobre la renta | B44: =EEFF!B45 -> 90668869 | C44: =EEFF!C45 -> 73516760 | D44: =EEFF!D45 -> 108026436 | F44: =EEFF!F45 -> 0 | G44: =G38+G43 -> 0 | H44: =H38+H43 -> 0 | I44: =I38+I43 -> 0 | J44: =J38+J43 -> 0 | K44: =K38+K43 -> 0
A45: Impuesto sobre la renta corriente | B45: =EEFF!B46 -> -8396374 | C45: =EEFF!C46 -> -12835954 | D45: =EEFF!D46 -> -13289861 | E45: =EEFF!E46 -> 0 | F45: =EEFF!F46 -> 0
A46: Impuesto sobre la renta diferido | B46: =EEFF!B47 -> -423906 | C46: =EEFF!C47 -> 1312298 | D46: =EEFF!D47 -> 1394727 | F46: =EEFF!F47 -> 0
A47: Total de gasto de impuesto sobre la renta | B47: =EEFF!B48 -> -8820280 | C47: =EEFF!C48 -> -11523656 | D47: =EEFF!D48 -> -11895134 | E47: =EEFF!E48 -> 0 | F47: =EEFF!F48 -> 0 | G47: =G45+G46 -> 0 | H47: =H45+H46 -> 0 | I47: =I45+I46 -> 0 | J47: =J45+J46 -> 0 | K47: =K45+K46 -> 0
A48: Ingresos por servicios de seguro | B48: =EEFF!B50 -> 0 | C48: =EEFF!C50 -> 0 | D48: =EEFF!D50 -> 0 | E48: =EEFF!E50 -> 820306455 | F48: =EEFF!F50 -> 885435473 | G48: =Premiums_Claims!G39 -> 9.5573905e+08 | H48: =Premiums_Claims!H39 -> 1.0316247e+09 | I48: =Premiums_Claims!I39 -> 1.1135357e+09 | J48: =Premiums_Claims!J39 -> 1.2019505e+09 | K48: =Premiums_Claims!K39 -> 1.2973853e+09
A49: Gastos por servicios de seguro | B49: =EEFF!B51 -> 0 | C49: =EEFF!C51 -> 0 | D49: =EEFF!D51 -> 0 | E49: =EEFF!E51 -> -367877750 | F49: =EEFF!F51 -> -426466314 | G49: =Premiums_Claims!G40 -> -4.6028393e+08 | H49: =Premiums_Claims!H40 -> -4.9683047e+08 | I49: =Premiums_Claims!I40 -> -5.3627881e+08 | J49: =Premiums_Claims!J40 -> -5.7885935e+08 | K49: =Premiums_Claims!K40 -> -6.2482078e+08
A50: Resultados netos de contratos de reaseguro | B50: =EEFF!B52 -> 0 | C50: =EEFF!C52 -> 0 | D50: =EEFF!D52 -> 0 | E50: =EEFF!E52 -> -314823760 | F50: =EEFF!F52 -> -313277206 | G50: =Premiums_Claims!G41 -> -3.3815142e+08 | H50: =Premiums_Claims!H41 -> -3.6500064e+08 | I50: =Premiums_Claims!I41 -> -3.9398169e+08 | J50: =Premiums_Claims!J41 -> -4.2526384e+08 | K50: =Premiums_Claims!K41 -> -4.5902978e+08
A51: Resultado del servicio de seguro | B51: =EEFF!B53 -> 0 | C51: =EEFF!C53 -> 0 | D51: =EEFF!D53 -> 0 | E51: =EEFF!E53 -> 137604945 | F51: =EEFF!F53 -> 145691953 | G51: =Premiums_Claims!G42 -> 1.5730371e+08 | H51: =Premiums_Claims!H42 -> 1.6979362e+08 | I51: =Premiums_Claims!I42 -> 1.8327524e+08 | J51: =Premiums_Claims!J42 -> 1.9782729e+08 | K51: =Premiums_Claims!K42 -> 2.1353478e+08
A52: Ingresos por intereses calculados utilizando el método de interés efectivo | B52: =EEFF!B54 -> 0 | C52: =EEFF!C54 -> 0 | D52: =EEFF!D54 -> 0 | E52: =EEFF!E54 -> 35258108 | F52: =EEFF!F54 -> 40827249 | G52: =Investment_Float!G25 -> 45835953 | H52: =Investment_Float!H25 -> 49475327 | I52: =Investment_Float!I25 -> 53403668 | J52: =Investment_Float!J25 -> 57643919 | K52: =Investment_Float!K25 -> 62220847
A53: Otros ingresos por inversiones | B53: =EEFF!B55 -> 0 | C53: =EEFF!C55 -> 0 | D53: =EEFF!D55 -> 0 | E53: =EEFF!E55 -> 55379789 | F53: =EEFF!F55 -> 61865524 | G53: =Investment_Float!G26 -> 69455212 | H53: =Investment_Float!H26 -> 74969956 | I53: =Investment_Float!I26 -> 80922570 | J53: =Investment_Float!J26 -> 87347822 | K53: =Investment_Float!K26 -> 94283239
A54: Pérdida neta por deterioro de activos financieros | B54: =EEFF!B56 -> 0 | C54: =EEFF!C56 -> 0 | D54: =EEFF!D56 -> 0 | E54: =EEFF!E56 -> 281188 | F54: =EEFF!F56 -> -70123 | G54: =Investment_Float!G27 -> -78725.718 | H54: =Investment_Float!H27 -> -84976.54 | I54: =Investment_Float!I27 -> -91723.678 | J54: =Investment_Float!J27 -> -99006.538 | K54: =Investment_Float!K27 -> -106867.66
A55: Retorno de las inversiones | B55: =EEFF!B57 -> 0 | C55: =EEFF!C57 -> 0 | D55: =EEFF!D57 -> 0 | E55: =EEFF!E57 -> 90919085 | F55: =EEFF!F57 -> 102622650 | G55: =G52+G53+G54 -> 1.1521244e+08 | H55: =H52+H53+H54 -> 1.2436031e+08 | I55: =I52+I53+I54 -> 1.3423451e+08 | J55: =J52+J53+J54 -> 1.4489273e+08 | K55: =K52+K53+K54 -> 1.5639722e+08
A56: Gastos financieros netos de contratos de seguro | B56: =EEFF!B58 -> 0 | C56: =EEFF!C58 -> 0 | D56: =EEFF!D58 -> 0 | E56: =EEFF!E58 -> -9221440 | F56: =EEFF!F58 -> -11097456 | G56: =F56 -> -11097456 | H56: =G56 -> -11097456 | I56: =H56 -> -11097456 | J56: =I56 -> -11097456 | K56: =J56 -> -11097456
A57: Ingresos financieros netos de contratos de reaseguro | B57: =EEFF!B59 -> 0 | C57: =EEFF!C59 -> 0 | D57: =EEFF!D59 -> 0 | E57: =EEFF!E59 -> 959026 | F57: =EEFF!F59 -> 2508685 | G57: =F57 -> 2508685 | H57: =G57 -> 2508685 | I57: =H57 -> 2508685 | J57: =I57 -> 2508685 | K57: =J57 -> 2508685
A58: Resultado financiero, neto | B58: =EEFF!B60 -> 0 | C58: =EEFF!C60 -> 0 | D58: =EEFF!D60 -> 0 | E58: =EEFF!E60 -> 82656671 | F58: =EEFF!F60 -> 94033879 | G58: =G55+G56+G57 -> 1.0662367e+08 | H58: =H55+H56+H57 -> 1.1577154e+08 | I58: =I55+I56+I57 -> 1.2564574e+08 | J58: =J55+J56+J57 -> 1.3630396e+08 | K58: =K55+K56+K57 -> 1.4780845e+08
A59: Otros ingresos | B59: =EEFF!B61 -> 0 | C59: =EEFF!C61 -> 0 | D59: =EEFF!D61 -> 0 | E59: =EEFF!E61 -> 7941941 | F59: =EEFF!F61 -> 4999986 | G59: =F59 -> 4999986 | H59: =G59 -> 4999986 | I59: =H59 -> 4999986 | J59: =I59 -> 4999986 | K59: =J59 -> 4999986
A60: Gastos generales y administrativos | B60: =EEFF!B62 -> 0 | C60: =EEFF!C62 -> 0 | D60: =EEFF!D62 -> 0 | E60: =EEFF!E62 -> -89212204 | F60: =EEFF!F62 -> -95272868 | G60: =G48*Supuestos!G26 -> -1.0283752e+08 | H60: =H48*Supuestos!H26 -> -1.1100282e+08 | I60: =I48*Supuestos!I26 -> -1.1981644e+08 | J60: =J48*Supuestos!J26 -> -1.2932987e+08 | K60: =K48*Supuestos!K26 -> -1.3959866e+08
A61: Otros | B61: =EEFF!B63 -> 0 | C61: =EEFF!C63 -> 0 | D61: =EEFF!D63 -> 0 | E61: =EEFF!E63 -> 1428646 | F61: =EEFF!F63 -> -1331447 | G61: =F61 -> -1331447 | H61: =G61 -> -1331447 | I61: =H61 -> -1331447 | J61: =I61 -> -1331447 | K61: =J61 -> -1331447
A62: Utilidad antes de impuesto | B62: =EEFF!B64 -> 0 | C62: =EEFF!C64 -> 0 | D62: =EEFF!D64 -> 0 | E62: =EEFF!E64 -> 140419999 | F62: =EEFF!F64 -> 148121503 | G62: =G51+G58+G59+G60+G61 -> 1.6475839e+08 | H62: =H51+H58+H59+H60+H61 -> 1.7823087e+08 | I62: =I51+I58+I59+I60+I61 -> 1.9277307e+08 | J62: =J51+J58+J59+J60+J61 -> 2.0846992e+08 | K62: =K51+K58+K59+K60+K61 -> 2.254131e+08
A63: Impuesto a las ganancias | B63: =EEFF!B65 -> 0 | C63: =EEFF!C65 -> 0 | D63: =EEFF!D65 -> 0 | E63: =EEFF!E65 -> -11985312 | F63: =EEFF!F65 -> -12129240 | G63: =-G62*Supuestos!G98 -> -13510188 | H63: =-H62*Supuestos!H98 -> -14614932 | I63: =-I62*Supuestos!I98 -> -15807392 | J63: =-J62*Supuestos!J98 -> -17094534 | K63: =-K62*Supuestos!K98 -> -18483874
A64: Utilidad neta, antes de operaciones descontinuadas | B64: =EEFF!B66 -> 0 | C64: =EEFF!C66 -> 0 | D64: =EEFF!D66 -> 0 | E64: =EEFF!E66 -> 128434687 | F64: =EEFF!F66 -> 135992263 | G64: =G62+G63 -> 1.512482e+08 | H64: =H62+H63 -> 1.6361594e+08 | I64: =I62+I63 -> 1.7696568e+08 | J64: =J62+J63 -> 1.9137539e+08 | K64: =K62+K63 -> 2.0692922e+08
A65: Ganancia o pérdida en ventas de operación descontinuadas, neta de impuesto | B65: =EEFF!B67 -> 0 | C65: =EEFF!C67 -> 0 | D65: =EEFF!D67 -> 0 | E65: =EEFF!E67 -> -3788890 | F65: =EEFF!F67 -> 31161580
A66: Utilidad neta | B66: =EEFF!B68 -> 81848589 | C66: =EEFF!C68 -> 61993104 | D66: =EEFF!D68 -> 96131302 | E66: =EEFF!E68 -> 124645797 | F66: =EEFF!F68 -> 167153843 | G66: =G44+G47+G64+G65 -> 1.512482e+08 | H66: =H44+H47+H64+H65 -> 1.6361594e+08 | I66: =I44+I47+I64+I65 -> 1.7696568e+08 | J66: =J44+J47+J64+J65 -> 1.9137539e+08 | K66: =K44+K47+K64+K65 -> 2.0692922e+08
A68: Años | B68: FY21A | C68: FY22A | D68: FY23A | E68: FY24A | F68: FY25A | G68: FY26E | H68: FY27E | I68: FY28E | J68: FY29E | K68: FY30E
A69: Balance General
A70: Efectivo y equivalentes de efectivo | B70: =EEFF!B73 -> 270329829 | C70: =EEFF!C73 -> 228125639 | D70: =EEFF!D73 -> 232268193 | E70: =EEFF!E73 -> 66040405 | F70: =EEFF!F73 -> 81993632 | G70: =F70 -> 81993632 | H70: =G70 -> 81993632 | I70: =H70 -> 81993632 | J70: =I70 -> 81993632 | K70: =J70 -> 81993632
A71: Cuentas por cobrar de seguros y otros, neto | B71: =EEFF!B74 -> 250244906 | C71: =EEFF!C74 -> 247213247 | D71: =EEFF!D74 -> 278176223 | F71: =EEFF!F74 -> 0
A72: Préstamos por cobrar, neto | B72: =EEFF!B75 -> 994010440 | C72: =EEFF!C75 -> 1083352786 | D72: =EEFF!D75 -> 1191506508 | E72: =EEFF!E75 -> 0 | F72: =EEFF!F75 -> 0 | G72: =F72 -> 0 | H72: =G72 -> 0 | I72: =H72 -> 0 | J72: =I72 -> 0 | K72: =J72 -> 0
A73: Inversiones, neto | B73: =EEFF!B76 -> 1282484672 | C73: =EEFF!C76 -> 1306501849 | D73: =EEFF!D76 -> 1450423677 | F73: =EEFF!F76 -> 0
A74: Participación de los reaseguradores en las provisiones sobre contratos de seguros | B74: =EEFF!B77 -> 237007868 | C74: =EEFF!C77 -> 319466997 | D74: =EEFF!D77 -> 259670949 | E74: =EEFF!E77 -> 0 | F74: =EEFF!F77 -> 0
A75: Depósitos de reaseguros de exceso de pérdida | B75: =EEFF!B78 -> 992942 | C75: =EEFF!C78 -> 1711440 | D75: =EEFF!D78 -> 1845741 | F75: =EEFF!F78 -> 0
A76: Instrumentos financieros, neto | B76: =EEFF!B79 -> 0 | C76: =EEFF!C79 -> 0 | D76: =EEFF!D79 -> 0 | E76: =EEFF!E79 -> 1570422123 | F76: =EEFF!F79 -> 1842841062 | G76: =F76 -> 1842841062 | H76: =G76 -> 1842841062 | I76: =H76 -> 1842841062 | J76: =I76 -> 1842841062 | K76: =J76 -> 1842841062
A77: Activos por contratos de seguros | B77: =EEFF!B80 -> 0 | C77: =EEFF!C80 -> 0 | D77: =EEFF!D80 -> 0 | E77: =EEFF!E80 -> 21110668 | F77: =EEFF!F80 -> 21032150 | G77: =F77 -> 21032150 | H77: =G77 -> 21032150 | I77: =H77 -> 21032150 | J77: =I77 -> 21032150 | K77: =J77 -> 21032150
A78: Activos por contratos de reaseguros | B78: =EEFF!B81 -> 0 | C78: =EEFF!C81 -> 0 | D78: =EEFF!D81 -> 0 | E78: =EEFF!E81 -> 224456158 | F78: =EEFF!F81 -> 179614453 | G78: =F78 -> 179614453 | H78: =G78 -> 179614453 | I78: =H78 -> 179614453 | J78: =I78 -> 179614453 | K78: =J78 -> 179614453
A79: Cuentas por cobrar otras, neto | B79: =EEFF!B82 -> 0 | C79: =EEFF!C82 -> 0 | D79: =EEFF!D82 -> 0 | E79: =EEFF!E82 -> 65001992 | F79: =EEFF!F82 -> 74003298 | G79: =F79 -> 74003298 | H79: =G79 -> 74003298 | I79: =H79 -> 74003298 | J79: =I79 -> 74003298 | K79: =J79 -> 74003298
A80: Inmuebles, mobiliario, equipo y mejoras, neto | B80: =EEFF!B83 -> 55843403 | C80: =EEFF!C83 -> 54093472 | D80: =EEFF!D83 -> 53762908 | F80: =EEFF!F83 -> 0
A81: Inmuebles, mobiliarios y equipo, netos | B81: =EEFF!B84 -> 0 | C81: =EEFF!C84 -> 0 | D81: =EEFF!D84 -> 0 | E81: =EEFF!E84 -> 42691420 | F81: =EEFF!F84 -> 38185718 | G81: =F81 -> 38185718 | H81: =G81 -> 38185718 | I81: =H81 -> 38185718 | J81: =I81 -> 38185718 | K81: =J81 -> 38185718
A82: Activos por derecho de uso, neto | B82: =EEFF!B85 -> 3567110 | C82: =EEFF!C85 -> 2447927 | D82: =EEFF!D85 -> 3082318 | F82: =EEFF!F85 -> 0
A83: Impuesto sobre la renta diferido | B83: =EEFF!B86 -> 3828445 | C83: =EEFF!C86 -> 5459921 | D83: =EEFF!D86 -> 4977416 | E83: =EEFF!E86 -> 0 | F83: =EEFF!F86 -> 0 | G83: =F83 -> 0 | H83: =G83 -> 0 | I83: =H83 -> 0 | J83: =I83 -> 0 | K83: =J83 -> 0
A84: Activos intangibles y plusvalía | B84: =EEFF!B87 -> 80211362 | C84: =EEFF!C87 -> 76115738 | D84: =EEFF!D87 -> 71848199 | F84: =EEFF!F87 -> 0
A85: Activos intangibles y plusvalía, neto | B85: =EEFF!B88 -> 0 | C85: =EEFF!C88 -> 0 | D85: =EEFF!D88 -> 0 | E85: =EEFF!E88 -> 38647085 | F85: =EEFF!F88 -> 41001647 | G85: =F85 -> 41001647 | H85: =G85 -> 41001647 | I85: =H85 -> 41001647 | J85: =I85 -> 41001647 | K85: =J85 -> 41001647
A86: Propiedad de inversión | B86: =EEFF!B89 -> 0 | C86: =EEFF!C89 -> 0 | D86: =EEFF!D89 -> 0 | E86: =EEFF!E89 -> 15641307 | F86: =EEFF!F89 -> 15413883 | G86: =F86 -> 15413883 | H86: =G86 -> 15413883 | I86: =H86 -> 15413883 | J86: =I86 -> 15413883 | K86: =J86 -> 15413883
A87: Otros activos | B87: =EEFF!B90 -> 52139653 | C87: =EEFF!C90 -> 47920677 | D87: =EEFF!D90 -> 47188231 | E87: =EEFF!E90 -> 24512378 | F87: =EEFF!F90 -> 24666268 | G87: =F87 -> 24666268 | H87: =G87 -> 24666268 | I87: =H87 -> 24666268 | J87: =I87 -> 24666268 | K87: =J87 -> 24666268
A88: Activos clasificados como mantenidos para la venta | B88: =EEFF!B91 -> 0 | C88: =EEFF!C91 -> 0 | D88: =EEFF!D91 -> 0 | E88: =EEFF!E91 -> 1051007115 | F88: =EEFF!F91 -> 0 | G88: =F88 -> 0 | H88: =G88 -> 0 | I88: =H88 -> 0 | J88: =I88 -> 0 | K88: =J88 -> 0
A89: Total de activos | B89: =EEFF!B92 -> 3230660630 | C89: =EEFF!C92 -> 3372409693 | D89: =EEFF!D92 -> 3594750363 | E89: =EEFF!E92 -> 3119530651 | F89: =EEFF!F92 -> 2318752111 | G89: =F89 -> 2318752111 | H89: =G89 -> 2318752111 | I89: =H89 -> 2318752111 | J89: =I89 -> 2318752111 | K89: =J89 -> 2318752111
A90: Depósitos de clientes | B90: =EEFF!B93 -> 725271188 | C90: =EEFF!C93 -> 742797197 | D90: =EEFF!D93 -> 838241610 | E90: =EEFF!E93 -> 0 | F90: =EEFF!F93 -> 0 | G90: =F90 -> 0 | H90: =G90 -> 0 | I90: =H90 -> 0 | J90: =I90 -> 0 | K90: =J90 -> 0
A91: Riesgo en curso | B91: =EEFF!B94 -> 222380820 | C91: =EEFF!C94 -> 222836666 | D91: =EEFF!D94 -> 252044466 | E91: =EEFF!E94 -> 0 | F91: =EEFF!F94 -> 0
A92: Reclamos en trámite | B92: =EEFF!B95 -> 166900068 | C92: =EEFF!C95 -> 262168088 | D92: =EEFF!D95 -> 183640714 | E92: =EEFF!E95 -> 0 | F92: =EEFF!F95 -> 0
A93: Negocios de vida a largo plazo sobre pólizas de vida | B93: =EEFF!B96 -> 271722485 | C93: =EEFF!C96 -> 285566197 | D93: =EEFF!D96 -> 297881412 | E93: =EEFF!E96 -> 0 | F93: =EEFF!F96 -> 0
A94: Total de provisiones sobre contratos de seguros | B94: =EEFF!B97 -> 661003373 | C94: =EEFF!C97 -> 770570951 | D94: =EEFF!D97 -> 733566592 | E94: =EEFF!E97 -> 0 | F94: =EEFF!F97 -> 0
A95: Emisiones de deuda y obligaciones | B95: =EEFF!B98 -> 526341819 | C95: =EEFF!C98 -> 551664761 | D95: =EEFF!D98 -> 537365915 | E95: =EEFF!E98 -> 0 | F95: =EEFF!F98 -> 0
A96: Obligaciones subordinadas | B96: =EEFF!B99 -> 2174514 | C96: =EEFF!C99 -> 10321297 | D96: =EEFF!D99 -> 10375811 | E96: =EEFF!E99 -> 0 | F96: =EEFF!F99 -> 0
A97: Total de financiamientos | B97: =EEFF!B100 -> 528516333 | C97: =EEFF!C100 -> 561986058 | D97: =EEFF!D100 -> 547741726 | E97: =EEFF!E100 -> 0 | F97: =EEFF!F100 -> 0
A98: Reaseguros por pagar | B98: =EEFF!B101 -> 95584028 | C98: =EEFF!C101 -> 87936500 | D98: =EEFF!D101 -> 109327643 | E98: =EEFF!E101 -> 0 | F98: =EEFF!F101 -> 0
A99: Impuesto sobre la renta diferido | B99: =EEFF!B102 -> 4481917 | C99: =EEFF!C102 -> 3966720 | D99: =EEFF!D102 -> 3099580 | F99: =EEFF!F102 -> 0
A100: Pasivos por arrendamientos | B100: =EEFF!B103 -> 4129771 | C100: =EEFF!C103 -> 3054770 | D100: =EEFF!D103 -> 3753169 | E100: =EEFF!E103 -> 0 | F100: =EEFF!F103 -> 0
A101: Otros pasivos | B101: =EEFF!B104 -> 118508679 | C101: =EEFF!C104 -> 124513198 | D101: =EEFF!D104 -> 141770551 | E101: =EEFF!E104 -> 4226363 | F101: =EEFF!F104 -> 4212226 | G101: =F101 -> 4212226 | H101: =G101 -> 4212226 | I101: =H101 -> 4212226 | J101: =I101 -> 4212226 | K101: =J101 -> 4212226
A102: Total de las cuentas por pagar y otros pasivos | B102: =EEFF!B105 -> 222704395 | C102: =EEFF!C105 -> 219471188 | D102: =EEFF!D105 -> 257950943 | E102: =EEFF!E105 -> 0 | F102: =EEFF!F105 -> 0
...

Sheet Puente_NIIF17
A1: Grupo ASSA, S. A.
A2: Puente_NIIF17 — conciliación del cambio de base contable: base regulatoria SSRP / NIIF excepto NIIF 17 (FY2021A–FY2024A) → Normas NIIF plenas con NIIF 17 (FY2024A re-expresado · FY2025A)
A3: Transición: 1 de enero de 2024 (NIIF 1 primera adopción + NIIF 17; Acuerdo 01-2024 SSRP). El filing 2025A no publica el impacto partida por partida (Nota 5): el efecto se revela en el estado de cambios en el patrimonio.
A4: Fuentes verbatim del mirror OCR: filing 2024A (base vieja) · filing 2025A (re-expresado). Azul = cifra publicada verbatim; negro = conciliación local (esperado 0).
A6: Agregados FY2024A en las dos bases contables | B6: Base SSRP (filing 2024A) | C6: NIIF 17 re-expresado (filing 2025A) | D6: Δ (NIIF 17 − SSRP)
A7: Total de activos | B7: 3280490170 | C7: 3119530651 | D7: =C7-B7 -> -160959519
A8: Total de pasivos | B8: 1903341718 | C8: 1673539425 | D8: =C8-B8 -> -229802293
A9: Total de patrimonio | B9: 1377148452 | C9: 1445991226 | D9: =C9-B9 -> 68842774
A10: Utilidad neta, antes de operación descontinuada | B10: 119425469 | C10: 128434687 | D10: =C10-B10 -> 9009218
A11: Utilidad neta | B11: 115636579 | C11: 124645797 | D11: =C11-B11 -> 9009218
A12: Verificación local: Δ activos − Δ pasivos − Δ patrimonio (esperado 0) | D12: =D7-D8-D9 -> 0
A14: Conciliación del patrimonio — transición al 1 de enero de 2024 | B14: Total de patrimonio (US$)
A15: Saldo al 1 de enero de 2024, previamente reportado | B15: 1217249492
A16: Ajuste por aplicación inicial de la NIIF 17, neto de impuesto | B16: 45319978
A17: Corrección de error no material y otros ajustes | B17: 0
A18: Saldo re-expresado al 1 de enero de 2024 | B18: 1262569470
A19: Verificación local: reportado + ajustes − re-expresado (esperado 0) | B19: =B15+B16+B17-B18 -> 0
A20: Amarre base vieja: Total de patrimonio al 31-dic-2023 (filing 2024A) | B20: 1217249492
A21: Verificación local: amarre base vieja − previamente reportado (esperado 0) | B21: =B20-B15 -> 0
A23: Rodamiento re-expresado del patrimonio FY2024 (NIIF 17) | B23: Total de patrimonio (US$)
A24: Saldo re-expresado al 1 de enero de 2024 (apertura) | B24: =B18 -> 1262569470
A25: Total de resultados integrales re-expresados | B25: 263916500
A26: Reclasificación de reservas y asignaciones | B26: 33
A27: Transacciones con accionistas y cambios en participaciones en subsidiarias | B27: -80494777
A28: Saldo al 31 de diciembre de 2024 (NIIF 17 re-expresado) | B28: 1445991226
A29: Verificación local: apertura + movimientos − cierre (esperado 0) | B29: =B24+B25+B26+B27-B28 -> 0
A31: Nota: el detalle por participación (controladora / no controladora) está en el estado consolidado de cambios en el patrimonio del filing 2025A; este puente concilia la columna Total de patrimonio.
A32: Serie comparable del analista: ver ModeloFinanciero (banderas NOT_COMPARABLE donde la línea no existe en ambas bases).

Sheet Premiums_Claims
A1: Grupo ASSA, S. A.
A2: Premiums_Claims — puente de base contable + prima por ramo + resultado de servicio NIIF 17
A3: Fuente: EEFF (mirror congelado) + mirror OCR ASSA 2025 (tbl-35, Nota concentracion de riesgo de suscripcion). Ver flags[] para vacios de fuente.
A5: Años | B5: FY21A | C5: FY22A | D5: FY23A | E5: FY24A | F5: FY25A | G5: FY26E | H5: FY27E | I5: FY28E | J5: FY29E | K5: FY30E
A7: A. ACCOUNTING_BASIS — puente base legacy (NIIF excepto NIIF 17) -> NIIF 17 re-expresado
A8: Fuente: SSRP diferio NIIF 17 a 1-ene-2025; FY21-FY23 base legacy Panama/NIIF-excepto-NIIF17, FY24-FY25 re-expresadas bajo NIIF 17 (OCR text lines 452-464).
A9: FY26-FY30 forecast se modela 100% en base NIIF 17 (Seccion C); no se produce un forecast de primas legacy — por construccion, ambas bases no pueden mezclarse en el horizonte de proyeccion.
A10: Total de primas netas retenidas — base legacy (ref EEFF, FY21-FY23) | B10: =EEFF!B10 -> 301580701 | C10: =EEFF!C10 -> 336616184 | D10: =EEFF!D10 -> 381545512 | F10: =EEFF!F10 -> 0
A11: Ingresos por servicios de seguro — base NIIF 17 (ref EEFF, FY24-FY25) | B11: =EEFF!B50 -> 0 | C11: =EEFF!C50 -> 0 | D11: =EEFF!D50 -> 0 | E11: =EEFF!E50 -> 820306455 | F11: =EEFF!F50 -> 885435473
A12: CHECK ACCOUNTING_BASIS_SWITCH_TIE (1=bases mezcladas en el mismo ano historico, esperado 0 en B:F) | B12: =IF(AND(B10<>0,B11<>0),1,0) -> 0 | C12: =IF(AND(C10<>0,C11<>0),1,0) -> 0 | D12: =IF(AND(D10<>0,D11<>0),1,0) -> 0 | E12: =IF(AND(E10<>0,E11<>0),1,0) -> 0 | F12: =IF(AND(F10<>0,F11<>0),1,0) -> 0
A14: G:K (forecast) no aplica a este check: no existe fila de primas legacy proyectada (ver nota arriba).
A16: B. PREMIUM_BUILD — prima suscrita neta de reaseguro por ramo (concentracion de riesgo de suscripcion)
A17: Fuente verbatim: INA_ASSA_2025_0.pdf p.96 (prima suscrita neta de reaseguro por ramo, concentracion del riesgo de suscripcion). Solo FY24-FY25 divulgados por ramo; FY21-FY23 NOT_DISCLOSED a nivel de ramo.
A18: BASE_DISTINTA: este total (prima suscrita neta de reaseguro por ramo) NO es la misma base que 'Ingresos por servicios de seguro' NIIF 17 consolidado (Seccion C) — alcance/base distintos (posible sub-segmento de riesgo de suscripcion vs. grupo consolidado, incl. vida en Centroamerica). No se fuerza una conciliacion 1:1 no divulgada.
A19: Accidentes personales | E19: =Notas_EEFF!K2717 -> 84101845 | F19: =Notas_EEFF!K2716 -> 86428052 | G19: =F19*(1+Supuestos!G35) -> 88822109 | H19: =G19*(1+Supuestos!H35) -> 91282481 | I19: =H19*(1+Supuestos!I35) -> 93811006 | J19: =I19*(1+Supuestos!J35) -> 96409571 | K19: =J19*(1+Supuestos!K35) -> 99080116
A20: Automóvil | E20: =Notas_EEFF!K2719 -> 100793260 | F20: =Notas_EEFF!K2718 -> 114979720 | G20: =F20*(1+Supuestos!G40) -> 1.3115737e+08 | H20: =G20*(1+Supuestos!H40) -> 1.4961121e+08 | I20: =H20*(1+Supuestos!I40) -> 1.7066151e+08 | J20: =I20*(1+Supuestos!J40) -> 1.9467358e+08 | K20: =J20*(1+Supuestos!K40) -> 2.2206415e+08
A21: Casco | E21: =Notas_EEFF!K2721 -> 18932539 | F21: =Notas_EEFF!K2720 -> 19542577 | G21: =F21*(1+Supuestos!G45) -> 20171848 | H21: =G21*(1+Supuestos!H45) -> 20821381 | I21: =H21*(1+Supuestos!I45) -> 21491830 | J21: =I21*(1+Supuestos!J45) -> 22183867 | K21: =J21*(1+Supuestos!K45) -> 22898187
A22: Colectivo de vida | E22: =Notas_EEFF!K2723 -> 39159903 | F22: =Notas_EEFF!K2722 -> 41214579 | G22: =F22*(1+Supuestos!G50) -> 43378344 | H22: =G22*(1+Supuestos!H50) -> 45655707 | I22: =H22*(1+Supuestos!I50) -> 48052632 | J22: =I22*(1+Supuestos!J50) -> 50575395 | K22: =J22*(1+Supuestos!K50) -> 53230604
A23: Fianzas | E23: =Notas_EEFF!K2725 -> 5662609 | F23: =Notas_EEFF!K2724 -> 5661627 | G23: =F23*(1+Supuestos!G55) -> 5660494.7 | H23: =G23*(1+Supuestos!H55) -> 5659362.6 | I23: =H23*(1+Supuestos!I55) -> 5658230.7 | J23: =I23*(1+Supuestos!J55) -> 5657099.1 | K23: =J23*(1+Supuestos!K55) -> 5655967.6
A24: Fidelidad | E24: =Notas_EEFF!K2727 -> 5264032 | F24: =Notas_EEFF!K2726 -> 5598664 | G24: =F24*(1+Supuestos!G60) -> 5954739 | H24: =G24*(1+Supuestos!H60) -> 6333460.4 | I24: =H24*(1+Supuestos!I60) -> 6736268.5 | J24: =I24*(1+Supuestos!J60) -> 7164695.2 | K24: =J24*(1+Supuestos!K60) -> 7620369.8
A25: Incendio | E25: =Notas_EEFF!K2729 -> 16624396 | F25: =Notas_EEFF!K2728 -> 16727248 | G25: =F25*(1+Supuestos!G65) -> 16830957 | H25: =G25*(1+Supuestos!H65) -> 16935309 | I25: =H25*(1+Supuestos!I65) -> 17040308 | J25: =I25*(1+Supuestos!J65) -> 17145958 | K25: =J25*(1+Supuestos!K65) -> 17252263
A26: Responsabilidad civil | E26: =Notas_EEFF!K2731 -> 5695830 | F26: =Notas_EEFF!K2730 -> 5774973 | G26: =F26*(1+Supuestos!G70) -> 5855245.1 | H26: =G26*(1+Supuestos!H70) -> 5936633 | I26: =H26*(1+Supuestos!I70) -> 6019152.2 | J26: =I26*(1+Supuestos!J70) -> 6102818.4 | K26: =J26*(1+Supuestos!K70) -> 6187647.6
A27: Riesgos diversos | E27: =Notas_EEFF!K2733 -> 5059301 | F27: =Notas_EEFF!K2732 -> 4979863 | G27: =F27*(1+Supuestos!G75) -> 4901679.2 | H27: =G27*(1+Supuestos!H75) -> 4824722.8 | I27: =H27*(1+Supuestos!I75) -> 4748974.6 | J27: =I27*(1+Supuestos!J75) -> 4674415.7 | K27: =J27*(1+Supuestos!K75) -> 4601027.4
A28: Salud | E28: =Notas_EEFF!K2735 -> 64553128 | F28: =Notas_EEFF!K2734 -> 65224063 | G28: =F28*(1+Supuestos!G80) -> 65902393 | H28: =G28*(1+Supuestos!H80) -> 66587778 | I28: =H28*(1+Supuestos!I80) -> 67280291 | J28: =I28*(1+Supuestos!J80) -> 67980006 | K28: =J28*(1+Supuestos!K80) -> 68686998
A29: Seguros técnicos | E29: =Notas_EEFF!K2737 -> 2816214 | F29: =Notas_EEFF!K2736 -> 2734994 | G29: =F29*(1+Supuestos!G85) -> 2656226.2 | H29: =G29*(1+Supuestos!H85) -> 2579726.9 | I29: =H29*(1+Supuestos!I85) -> 2505430.7 | J29: =I29*(1+Supuestos!J85) -> 2433274.3 | K29: =J29*(1+Supuestos!K85) -> 2363196
A30: Autoexpedibles y otros | E30: =Notas_EEFF!K2739 -> 12790589 | F30: =Notas_EEFF!K2738 -> 12943398 | G30: =F30*(1+Supuestos!G90) -> 13097424 | H30: =G30*(1+Supuestos!H90) -> 13253284 | I30: =H30*(1+Supuestos!I90) -> 13410998 | J30: =I30*(1+Supuestos!J90) -> 13570589 | K30: =J30*(1+Supuestos!K90) -> 13732079
A32: Forecast por ramo = driver de escenario por ramo en Supuestos (sección D) — histórico referencia el ledger Notas_EEFF (Nota 10.ii, tbl-35)
A33: Total prima suscrita neta de reaseguro (Sigma ramos) | B33: =B19+B20+B21+B22+B23+B24+B25+B26+B27+B28+B29+B30 -> 0 | C33: =C19+C20+C21+C22+C23+C24+C25+C26+C27+C28+C29+C30 -> 0 | D33: =D19+D20+D21+D22+D23+D24+D25+D26+D27+D28+D29+D30 -> 0 | E33: =E19+E20+E21+E22+E23+E24+E25+E26+E27+E28+E29+E30 -> 361453646 | F33: =F19+F20+F21+F22+F23+F24+F25+F26+F27+F28+F29+F30 -> 381809758 | G33: =G19+G20+G21+G22+G23+G24+G25+G26+G27+G28+G29+G30 -> 4.0438883e+08 | H33: =H19+H20+H21+H22+H23+H24+H25+H26+H27+H28+H29+H30 -> 4.2948105e+08 | I33: =I19+I20+I21+I22+I23+I24+I25+I26+I27+I28+I29+I30 -> 4.5741663e+08 | ... K33: =K19+K20+K21+K22+K23+K24+K25+K26+K27+K28+K29+K30 -> 5.2337261e+08
A34: Total per filing (verbatim tie, tbl-35) | E34: =Notas_EEFF!K2741 -> 361453646 | F34: =Notas_EEFF!K2740 -> 381809758
A35: CHECK INSURANCE_PREMIUM_DRIVER_TIE (Sigma ramos - total verbatim tbl-35, esperado 0 en FY24/FY25) | E35: =E33-E34 -> 0 | F35: =F33-F34 -> 0
A37: C. INSURANCE_SERVICE_RESULT + CLAIMS_SERVICE_EXPENSE (NIIF 17, EEFF filas 42-52)
A38: Fuente: EEFF (mirror congelado) filas Ingresos/Gastos por servicios de seguro, Resultados netos de contratos de reaseguro, Retorno de las inversiones, Resultado financiero neto (OCR text lines 248-258).
A39: Ingresos por servicios de seguro | B39: =EEFF!B50 -> 0 | C39: =EEFF!C50 -> 0 | D39: =EEFF!D50 -> 0 | E39: =EEFF!E50 -> 820306455 | F39: =EEFF!F50 -> 885435473 | G39: =F39*(1+Supuestos!G11) -> 9.5573905e+08 | H39: =G39*(1+Supuestos!H11) -> 1.0316247e+09 | I39: =H39*(1+Supuestos!I11) -> 1.1135357e+09 | J39: =I39*(1+Supuestos!J11) -> 1.2019505e+09 | K39: =J39*(1+Supuestos!K11) -> 1.2973853e+09
A40: Gastos por servicios de seguro | B40: =EEFF!B51 -> 0 | C40: =EEFF!C51 -> 0 | D40: =EEFF!D51 -> 0 | E40: =EEFF!E51 -> -367877750 | F40: =EEFF!F51 -> -426466314 | G40: =G39*Supuestos!G19 -> -4.6028393e+08 | H40: =H39*Supuestos!H19 -> -4.9683047e+08 | I40: =I39*Supuestos!I19 -> -5.3627881e+08 | J40: =J39*Supuestos!J19 -> -5.7885935e+08 | K40: =K39*Supuestos!K19 -> -6.2482078e+08
A41: Resultados netos de contratos de reaseguro | B41: =EEFF!B52 -> 0 | C41: =EEFF!C52 -> 0 | D41: =EEFF!D52 -> 0 | E41: =EEFF!E52 -> -314823760 | F41: =EEFF!F52 -> -313277206 | G41: =G39*($F$41/$F$39) -> -3.3815142e+08 | H41: =H39*($F$41/$F$39) -> -3.6500064e+08 | I41: =I39*($F$41/$F$39) -> -3.9398169e+08 | J41: =J39*($F$41/$F$39) -> -4.2526384e+08 | K41: =K39*($F$41/$F$39) -> -4.5902978e+08
A42: Resultado del servicio de seguro (computado = suma de las 3 lineas anteriores) | B42: =B39+B40+B41 -> 0 | C42: =C39+C40+C41 -> 0 | D42: =D39+D40+D41 -> 0 | E42: =E39+E40+E41 -> 137604945 | F42: =F39+F40+F41 -> 145691953 | G42: =G39+G40+G41 -> 1.5730371e+08 | H42: =H39+H40+H41 -> 1.6979362e+08 | I42: =I39+I40+I41 -> 1.8327524e+08 | ... K42: =K39+K40+K41 -> 2.1353478e+08
A43: Resultado del servicio de seguro (EEFF, subtotal auditado) | B43: =EEFF!B53 -> 0 | C43: =EEFF!C53 -> 0 | D43: =EEFF!D53 -> 0 | E43: =EEFF!E53 -> 137604945 | F43: =EEFF!F53 -> 145691953
A44: CHECK IFRS17_SERVICE_RESULT_TIE (computado - EEFF subtotal, esperado 0 FY24/FY25) | B44: =B42-B43 -> 0 | C44: =C42-C43 -> 0 | D44: =D42-D43 -> 0 | E44: =E42-E43 -> 0 | F44: =F42-F43 -> 0
A46: Ingresos por interes (metodo interes efectivo) | B46: =EEFF!B54 -> 0 | C46: =EEFF!C54 -> 0 | D46: =EEFF!D54 -> 0 | E46: =EEFF!E54 -> 35258108 | F46: =EEFF!F54 -> 40827249
A47: Otros ingresos por inversiones | B47: =EEFF!B55 -> 0 | C47: =EEFF!C55 -> 0 | D47: =EEFF!D55 -> 0 | E47: =EEFF!E55 -> 55379789 | F47: =EEFF!F55 -> 61865524
A48: Perdida neta por deterioro de activos financieros | B48: =EEFF!B56 -> 0 | C48: =EEFF!C56 -> 0 | D48: =EEFF!D56 -> 0 | E48: =EEFF!E56 -> 281188 | F48: =EEFF!F56 -> -70123
A49: Retorno de las inversiones (computado) | B49: =B46+B47+B48 -> 0 | C49: =C46+C47+C48 -> 0 | D49: =D46+D47+D48 -> 0 | E49: =E46+E47+E48 -> 90919085 | F49: =F46+F47+F48 -> 102622650
A50: Retorno de las inversiones (EEFF, subtotal auditado) | B50: =EEFF!B57 -> 0 | C50: =EEFF!C57 -> 0 | D50: =EEFF!D57 -> 0 | E50: =EEFF!E57 -> 90919085 | F50: =EEFF!F57 -> 102622650
A52: Gastos financieros netos de contratos de seguro | B52: =EEFF!B58 -> 0 | C52: =EEFF!C58 -> 0 | D52: =EEFF!D58 -> 0 | E52: =EEFF!E58 -> -9221440 | F52: =EEFF!F58 -> -11097456
A53: Ingresos financieros netos de contratos de reaseguro | B53: =EEFF!B59 -> 0 | C53: =EEFF!C59 -> 0 | D53: =EEFF!D59 -> 0 | E53: =EEFF!E59 -> 959026 | F53: =EEFF!F59 -> 2508685
A54: Resultado financiero, neto (computado = inversiones + finanzas seguro + finanzas reaseguro) | B54: =B49+B52+B53 -> 0 | C54: =C49+C52+C53 -> 0 | D54: =D49+D52+D53 -> 0 | E54: =E49+E52+E53 -> 82656671 | F54: =F49+F52+F53 -> 94033879
A55: Resultado financiero, neto (EEFF, subtotal auditado) | B55: =EEFF!B60 -> 0 | C55: =EEFF!C60 -> 0 | D55: =EEFF!D60 -> 0 | E55: =EEFF!E60 -> 82656671 | F55: =EEFF!F60 -> 94033879
A56: CHECK IFRS17_FINANCE_RESULT_TIE (computado - EEFF subtotal, esperado 0 FY24/FY25) | B56: =B54-B55 -> 0 | C56: =C54-C55 -> 0 | D56: =D54-D55 -> 0 | E56: =E54-E55 -> 0 | F56: =F54-F55 -> 0
A58: FORECAST FY26-FY30 (base NIIF 17 unicamente — ver Accounting_Basis)
A59: LIMITED_HISTORY: solo 2 anos NIIF17 divulgados (FY24-FY25). Ingresos forecast = ano previo x (1 + Supuestos!fila 11 driver activo, escenario-aware); gastos de servicio = ingresos x Supuestos!fila 19 (ratio negativo); ratio de reaseguro se mantiene plano al nivel FY25 (RATIO_HELD_FLAT_FY25, driver local a esta hoja).
A61: D. COMBINED_RATIO — bases explicitas, NO mezcladas (legacy FY21-FY23 vs NIIF17 FY24-FY30)
A62: Combined ratio legacy (=|claims+adq+ECL| / primas netas ganadas, FY21-FY23 solamente) | B62: =ABS(EEFF!B19+EEFF!B20+EEFF!B21)/EEFF!B15 -> 0.8274072 | C62: =ABS(EEFF!C19+EEFF!C20+EEFF!C21)/EEFF!C15 -> 0.82961649 | D62: =ABS(EEFF!D19+EEFF!D20+EEFF!D21)/EEFF!D15 -> 0.85784717
A64: N/A FY24-FY30: base legacy se retira (SSRP adopta NIIF 17 desde 1-ene-2025); ver seccion C para la base NIIF 17.
A65: Ratio de gasto de servicio NIIF 17 (=|gasto servicio| / ingreso servicio, FY24-FY25) | E65: =ABS(EEFF!E51)/EEFF!E50 -> 0.4484638 | F65: =ABS(EEFF!F51)/EEFF!F50 -> 0.48164584
A66: Ratio de resultado de reaseguro NIIF 17 (=|resultado reaseguro| / ingreso servicio, FY24-FY25) | E66: =ABS(EEFF!E52)/EEFF!E50 -> 0.38378798 | F66: =ABS(EEFF!F52)/EEFF!F50 -> 0.35381145
A68: COMBINED_RATIO_BASIS_TIE: legacy combined ratio y ratio de gasto de servicio NIIF 17 NO son comparables 1:1 (denominadores y alcance de gasto distintos) — no se combinan en una sola serie.

Sheet Claims_Reserves
A1: Grupo ASSA, S. A.
A2: Claims_Reserves — provisiones legacy + roll-forward NIIF 17 LRC/LIC vida/generales (Nota 20)
A3: Fuente: EEFF (mirror congelado) + mirror OCR ASSA 2025 Nota 20 (tbl-68/69/70/71/72). Ver flags[] para vacios de fuente.
A5: Años | B5: FY21A | C5: FY22A | D5: FY23A | E5: FY24A | F5: FY25A | G5: FY26E | H5: FY27E | I5: FY28E | J5: FY29E | K5: FY30E
A7: A. PROVISIONES LEGACY (stock de fin de periodo, FY21-FY23 — base retirada desde FY24)
A8: Fuente: EEFF (mirror congelado), Balance General. NO existe un roll-forward completo divulgado para la base legacy; el movimiento de P&L ('cambio en la provision') ya esta en Premiums_Claims seccion A filas de cambio en provisiones.
A9: Riesgo en curso | B9: =EEFF!B94 -> 222380820 | C9: =EEFF!C94 -> 222836666 | D9: =EEFF!D94 -> 252044466
A10: Reclamos en trámite | B10: =EEFF!B95 -> 166900068 | C10: =EEFF!C95 -> 262168088 | D10: =EEFF!D95 -> 183640714
A11: Negocios de vida a largo plazo sobre pólizas de vida | B11: =EEFF!B96 -> 271722485 | C11: =EEFF!C96 -> 285566197 | D11: =EEFF!D96 -> 297881412
A12: Total de provisiones sobre contratos de seguros (EEFF subtotal auditado, legacy) | B12: =EEFF!B97 -> 661003373 | C12: =EEFF!C97 -> 770570951 | D12: =EEFF!D97 -> 733566592
A14: N/A FY24-FY30: base legacy retirada; ver seccion B (NIIF 17).
A16: B. NIIF 17 — CONTRATOS DE SEGURO Y REASEGURO POR VIDA/GENERALES (Nota 20, tbl-68/69), FY24-FY25
A17: Fuente verbatim: INA_ASSA_2025_0.pdf p.125 (Nota 20, saldos de contratos de seguro y reaseguro, 31-dic-2025) ; INA_ASSA_2025_0.pdf p.125 (Nota 20, saldos de contratos de seguro y reaseguro, 31-dic-2024). Solo 2 anos divulgados (FY24-FY25); FY21-FY23 y forecast FY26-FY30 no aplican a este detalle NIIF 17.
A18: B.1 Contrato de seguro — grupos con saldos pasivos (LRC = pasivo cobertura restante; LIC = pasivo reclamos incurridos)
A19: LRC vida | E19: 223147540 | F19: 226113118
A20: LRC generales | E20: 117243673 | F20: 118644281
A21: LRC total (seguro) | B21: =B19+B20 -> 0 | C21: =C19+C20 -> 0 | D21: =D19+D20 -> 0 | E21: =E19+E20 -> 340391213 | F21: =F19+F20 -> 344757399 | G21: =G19+G20 -> 0 | H21: =H19+H20 -> 0 | I21: =I19+I20 -> 0 | ... K21: =K19+K20 -> 0
A22: LIC vida | E22: 7461196 | F22: 5533001
A23: LIC generales | E23: 199328472 | F23: 166289061
A24: LIC total (seguro) | B24: =B22+B23 -> 0 | C24: =C22+C23 -> 0 | D24: =D22+D23 -> 0 | E24: =E22+E23 -> 206789668 | F24: =F22+F23 -> 171822062 | G24: =G22+G23 -> 0 | H24: =H22+H23 -> 0 | I24: =I22+I23 -> 0 | ... K24: =K22+K23 -> 0
A25: Total pasivo bruto contratos de seguro (LRC + LIC) | B25: =B21+B24 -> 0 | C25: =C21+C24 -> 0 | D25: =D21+D24 -> 0 | E25: =E21+E24 -> 547180881 | F25: =F21+F24 -> 516579461 | G25: =G21+G24 -> 0 | H25: =H21+H24 -> 0 | I25: =I21+I24 -> 0 | ... K25: =K21+K24 -> 0
A27: B.2 Contrato de seguro — grupos con saldos activos (activo cobertura restante, presentado negativo por convencion del filing)
A28: Activo cobertura restante vida | E28: -1664254 | F28: -1639224
A29: Activo cobertura restante generales | E29: -19446414 | F29: -19392926
A30: Activo cobertura restante total | B30: =B28+B29 -> 0 | C30: =C28+C29 -> 0 | D30: =D28+D29 -> 0 | E30: =E28+E29 -> -21110668 | F30: =F28+F29 -> -21032150 | G30: =G28+G29 -> 0 | H30: =H28+H29 -> 0 | I30: =I28+I29 -> 0 | ... K30: =K28+K29 -> 0
A31: Saldo neto contratos de seguro (pasivo bruto + activo cobertura restante) | B31: =B25+B30 -> 0 | C31: =C25+C30 -> 0 | D31: =D25+D30 -> 0 | E31: =E25+E30 -> 526070213 | F31: =F25+F30 -> 495547311 | G31: =G25+G30 -> 0 | H31: =H25+H30 -> 0 | I31: =I25+I30 -> 0 | ... K31: =K25+K30 -> 0
A33: CHECKS B (contra EEFF / BS)
A34: Provisiones sobre contratos de seguros (EEFF BS, NIIF17) | E34: =EEFF!E107 -> 547180881 | F34: =EEFF!F107 -> 516579461
A35: CHECK RESERVE_LRC_LIC_ROLLFORWARD_TIE / INSURANCE_TECHNICAL_RESERVE_TIE (Total pasivo bruto - EEFF BS, esperado 0) | E35: =E25-E34 -> 0 | F35: =F25-F34 -> 0
A37: B.3 Contrato de reaseguro — cedido (LRC/LIC activos por reaseguro cedido + LRC pasivo por reaseguro)
A38: Activo cobertura restante reaseguro, vida | E38: -20744470 | F38: -19080050
A39: Activo cobertura restante reaseguro, generales | E39: -75653344 | F39: -69470378
A40: Activo cobertura restante reaseguro, total | B40: =B38+B39 -> 0 | C40: =C38+C39 -> 0 | D40: =D38+D39 -> 0 | E40: =E38+E39 -> -96397814 | F40: =F38+F39 -> -88550428 | G40: =G38+G39 -> 0 | H40: =H38+H39 -> 0 | I40: =I38+I39 -> 0 | ... K40: =K38+K39 -> 0
A41: Activo reclamos incurridos reaseguro, vida | E41: -1401285 | F41: -508181
A42: Activo reclamos incurridos reaseguro, generales | E42: -126657059 | F42: -90555844
A43: Activo reclamos incurridos reaseguro, total | B43: =B41+B42 -> 0 | C43: =C41+C42 -> 0 | D43: =D41+D42 -> 0 | E43: =E41+E42 -> -128058344 | F43: =F41+F42 -> -91064025 | G43: =G41+G42 -> 0 | H43: =H41+H42 -> 0 | I43: =I41+I42 -> 0 | ... K43: =K41+K42 -> 0
A44: Activo total contrato de reaseguro (cobertura restante + reclamos incurridos) | B44: =B40+B43 -> 0 | C44: =C40+C43 -> 0 | D44: =D40+D43 -> 0 | E44: =E40+E43 -> -224456158 | F44: =F40+F43 -> -179614453 | G44: =G40+G43 -> 0 | H44: =H40+H43 -> 0 | I44: =I40+I43 -> 0 | ... K44: =K40+K43 -> 0
A45: Pasivo cobertura restante reaseguro, generales (grupos con saldo pasivo) | E45: 36801772 | F45: 35259752
A46: Saldo neto contrato de reaseguro (activo + pasivo cobertura restante) | B46: =B44+B45 -> 0 | C46: =C44+C45 -> 0 | D46: =D44+D45 -> 0 | E46: =E44+E45 -> -187654386 | F46: =F44+F45 -> -144354701 | G46: =G44+G45 -> 0 | H46: =H44+H45 -> 0 | I46: =I44+I45 -> 0 | ... K46: =K44+K45 -> 0
A47: Activos por contratos de reaseguros (EEFF BS) | E47: =EEFF!E81 -> 224456158 | F47: =EEFF!F81 -> 179614453
A48: Provisiones sobre contratos de reaseguros (EEFF BS) | E48: =EEFF!E108 -> 36801772 | F48: =EEFF!F108 -> 35259752
A49: CHECK REINSURANCE_CONTRACT_BALANCE_TIE (Nota20 neto + (EEFF activo - EEFF pasivo), esperado 0; signos opuestos por convencion) | E49: =E46+(E47-E48) -> 0 | F49: =F46+(F47-F48) -> 0
A51: C. VENCIMIENTO >12 MESES — memo (Nota 20; INA_ASSA_2025_0.pdf p.126 (Nota 20, importes a liquidar/recuperar en >12 meses))
A52: Ano de referencia inferido FY2025 por secuencia de nota (el mirror no trae etiqueta de ano explicita en esta tabla).
A53: Contrato de seguros (>12m) | F53: 28138216
A54: Contrato de reaseguros (>12m) | F54: -19769018
A55: Neto (>12m) | F55: 8369198
A57: D. LIFE_MOVEMENT — roll-forward LRC+LIC vida (INA_ASSA_2025_0.pdf p.127 (Nota 20.i, seguros de vida, cobertura restante + reclamos incurridos, 2025 y 2024))
A58: Saldo inicial neto (vida, cobertura restante + reclamos incurridos) | E58: 241045358 | F58: 228944482
A59: Cambio total en resultado y ORI (ingreso/gasto de servicio + financiero) | E59: -22528756 | F59: -2425841
A60: Flujos de efectivo totales (primas recibidas - reclamos/rescates/gastos pagados) | E60: 10427880 | F60: 3488254
A61: Saldo neto al cierre (verbatim tbl-71) | E61: 228944482 | F61: 230006895
A62: Saldo neto total al cierre (computado = inicial + cambio P&L/ORI + flujos) | E62: =E58+E59+E60 -> 228944482 | F62: =F58+F59+F60 -> 230006895
A63: CHECK LIFE_LRC_LIC_ROLLFORWARD_TIE (computado - verbatim tbl-71, esperado 0) | E63: =E62-E61 -> 0 | F63: =F62-F61 -> 0
A65: E. LIFE_CSM_RA_PVFCF — componentes valor presente / ajuste de riesgo / CSM, vida, FY2025 (INA_ASSA_2025_0.pdf p.128 (Nota 20, componentes VFCF/ajuste de riesgo/CSM, seguros de vida, 2025))
A66: FY2024 (INA_ASSA_2025_0.pdf p.128 (Nota 20, mismo detalle 2024 — OCR_REVIEW_REQUIRED, etiquetas de fila corruptas en el mirror)) — no ingestado esta pasada.
A67: E.1 Saldo inicial neto por componente
A68: Valor presente de flujos de efectivo futuros (VFCF), inicial | F68: 125541168
A69: Ajuste de riesgo, inicial | F69: 36672308
A70: CSM (subtotal enfoques retrospectivo + valor razonable + otros), inicial | F70: 66731006
A71: Saldo inicial neto total (VFCF + AR + CSM) | F71: =F68+F69+F70 -> 228944482
A72: Saldo inicial neto total (verbatim tbl-72, = cierre FY2024 tbl-71/tbl-72) | F72: 228944482
A73: CHECK (suma componentes - verbatim inicial, esperado 0) | F73: =F71-F72 -> 0
A75: E.2 Movimiento del periodo (total, sin desagregar por componente) y cierre
A76: Cambio total en resultado y ORI | F76: -305494
A77: Flujos de efectivo (transferencia a otra partida del estado de situacion financiera) | F77: 1367907
A78: Saldo neto total al cierre (computado = inicial verbatim + cambio + flujos) | F78: =F72+F76+F77 -> 230006895
A79: Saldo neto al cierre (verbatim tbl-72) | F79: 230006895
A80: CHECK LIFE_CSM_RA_PVFCF_TIE (computado - verbatim cierre, esperado 0) | F80: =F78-F79 -> 0
A82: E.3 Cierre por componente (verbatim) y cruce contra Nota 20 total vida (tbl-68)
A83: Valor presente de flujos de efectivo futuros (VFCF), cierre | F83: 133034384
A84: Ajuste de riesgo, cierre | F84: 37441532
A85: CSM (subtotal), cierre | F85: 59530979
A86: Cierre neto total por componentes (VFCF + AR + CSM) | F86: =F83+F84+F85 -> 230006895
A87: Saldo neto contratos de seguro, vida (Nota 20, tbl-68, verbatim) | F87: 230006895
A88: CHECK cruce tbl-72 vs tbl-68 vida (esperado 0) | F88: =F86-F87 -> 0
A90: NOT_DISCLOSED (por diseno, no se inventan — fuera de alcance esta pasada W4-D6 slices 1-3)
A91: SCR/capital regulatorio numerico por subsidiaria: NOT_DISCLOSED (ver Solvency_Capital, slice 6, pendiente).
A92: Triangulos de siniestros (pagados/incurridos, IBNR por metodo): NOT_DISCLOSED (chain ladder / Bornhuetter-Ferguson mencionados solo cualitativamente, OCR text lines 3343-3345).
A93: Valor implicito / embedded value / valor de negocio nuevo: NOT_DISCLOSED (ver Valuation, slice 8, pendiente).
A94: Reinsurance (sheet dedicado slice 4) y Investments/Investment_Float (slice 5): pendientes; esta pasada solo cubre el cruce de saldos de reaseguro que ya vive en la Nota 20 (seccion B.3 arriba).

Sheet Reinsurance
A1: Grupo ASSA, S. A.
A2: Reinsurance — política, resultado NIIF 17, cesión legacy y saldos de contratos (Nota 20)
A3: Fuente: EEFF (mirror congelado) + INA_ASSA_2025_0.pdf p.96 (politica de reaseguro: exceso de perdida, stop-loss, facultativo) + Nota 20 (via Claims_Reserves). Bases legacy/NIIF17 explícitas, nunca mezcladas.
A5: Años | B5: FY21A | C5: FY22A | D5: FY23A | E5: FY24A | F5: FY25A | G5: FY26E | H5: FY27E | I5: FY28E | J5: FY29E | K5: FY30E
A7: A. POLÍTICA DE REASEGURO (cualitativa, verbatim del filing)
A8: El Grupo usa reaseguro (incl. exceso de pérdida y stop-loss) para mitigar pérdidas significativas de eventos individuales; reaseguro facultativo por encima de la tolerancia al riesgo.
A9: Fuente: INA_ASSA_2025_0.pdf p.96 (politica de reaseguro: exceso de perdida, stop-loss, facultativo).
A11: B. RESULTADO DE REASEGURO EN P&L — base NIIF 17 (FY24-FY30)
A12: Resultados netos de contratos de reaseguro (ref EEFF; forecast link Premiums_Claims) | E12: =EEFF!E52 -> -314823760 | F12: =EEFF!F52 -> -313277206 | G12: =Premiums_Claims!G41 -> -3.3815142e+08 | H12: =Premiums_Claims!H41 -> -3.6500064e+08 | I12: =Premiums_Claims!I41 -> -3.9398169e+08 | J12: =Premiums_Claims!J41 -> -4.2526384e+08 | K12: =Premiums_Claims!K41 -> -4.5902978e+08
A13: Ingresos financieros netos de contratos de reaseguro (ref EEFF) | E13: =EEFF!E59 -> 959026 | F13: =EEFF!F59 -> 2508685
A14: Ingresos por servicios de seguro (ref EEFF; forecast link Premiums_Claims) | E14: =EEFF!E50 -> 820306455 | F14: =EEFF!F50 -> 885435473 | G14: =Premiums_Claims!G39 -> 9.5573905e+08 | H14: =Premiums_Claims!H39 -> 1.0316247e+09 | I14: =Premiums_Claims!I39 -> 1.1135357e+09 | J14: =Premiums_Claims!J39 -> 1.2019505e+09 | K14: =Premiums_Claims!K39 -> 1.2973853e+09
A15: Ratio resultado de reaseguro ÷ ingresos por servicios (NIIF 17) | E15: =E12/E14 -> -0.38378798 | F15: =F12/F14 -> -0.35381145 | G15: =G12/G14 -> -0.35381145 | H15: =H12/H14 -> -0.35381145 | I15: =I12/I14 -> -0.35381145 | J15: =J12/J14 -> -0.35381145 | K15: =K12/K14 -> -0.35381145
A17: Forecast del resultado de reaseguro = ratio FY25 plano sobre ingresos (RATIO_HELD_FLAT_FY25, ver Premiums_Claims). Ingreso financiero de reaseguro: sin forecast propio (Modelo lo lleva plano FY25, FINCOST_FLAT_CARRY).
A19: C. CESIÓN LEGACY (FY21-FY23 — base retirada desde FY24)
A20: Primas suscritas, netas de cancelaciones (ref EEFF) | B20: =EEFF!B8 -> 657884741 | C20: =EEFF!C8 -> 698200257 | D20: =EEFF!D8 -> 817173751
A21: Primas suscritas cedidas a reaseguradores (ref EEFF) | B21: =EEFF!B9 -> -356304040 | C21: =EEFF!C9 -> -361584073 | D21: =EEFF!D9 -> -435628239
A22: Participación de reaseguradores en reclamos y beneficios incurridos (ref EEFF) | B22: =EEFF!B17 -> 101363600 | C22: =EEFF!C17 -> 176570373 | D22: =EEFF!D17 -> 65656958
A23: Ratio de cesión legacy (=|cedidas| ÷ suscritas, FY21-FY23) | B23: =ABS(B21)/B20 -> 0.54159037 | C23: =ABS(C21)/C20 -> 0.51788018 | D23: =ABS(D21)/D20 -> 0.53309133
A25: N/A FY24-FY30: bajo NIIF 17 la cesión se presenta como resultado neto de contratos de reaseguro (sección B); no se mezclan bases.
A27: D. SALDOS DE CONTRATOS DE REASEGURO — Nota 20 (link a Claims_Reserves, FY24-FY25)
A28: Activo cobertura restante reaseguro, total (Nota 20, convención negativa) | E28: =Claims_Reserves!E40 -> -96397814 | F28: =Claims_Reserves!F40 -> -88550428
A29: Activo reclamos incurridos reaseguro, total | E29: =Claims_Reserves!E43 -> -128058344 | F29: =Claims_Reserves!F43 -> -91064025
A30: Activo total contrato de reaseguro | E30: =Claims_Reserves!E44 -> -224456158 | F30: =Claims_Reserves!F44 -> -179614453
A31: Pasivo cobertura restante reaseguro (grupos con saldo pasivo) | E31: =Claims_Reserves!E45 -> 36801772 | F31: =Claims_Reserves!F45 -> 35259752
A32: Total saldo neto contrato de reaseguro (Nota 20) | E32: =Claims_Reserves!E46 -> -187654386 | F32: =Claims_Reserves!F46 -> -144354701
A33: Activos por contratos de reaseguros (EEFF BS) | E33: =EEFF!E81 -> 224456158 | F33: =EEFF!F81 -> 179614453
A34: Provisiones sobre contratos de reaseguros (EEFF BS) | E34: =EEFF!E108 -> 36801772 | F34: =EEFF!F108 -> 35259752
A35: CHECK REINSURANCE_CONTRACT_BALANCE_TIE (Nota20 neto + (EEFF activo − EEFF pasivo), esperado 0; signos opuestos por convención) | E35: =E32+(E33-E34) -> 0 | F35: =F32+(F33-F34) -> 0
A37: NOT_DISCLOSED (no se inventa)
A38: Programas por reasegurador, comisiones de reaseguro por contrato, retenciones/PML por ramo: NOT_DISCLOSED en el filing.

Sheet Investments
A1: Grupo ASSA, S. A.
A2: Investments — portafolio por categoría (Nota 18) + acciones estratégicas y dividendos
A3: Fuente verbatim: INA_ASSA_2025_0.pdf p.120 (instrumentos financieros por categoria, 31-dic-2025) y tbl-58.md (31-dic-2024) ; INA_ASSA_2025_0.pdf p.121 (acciones estrategicas: valor razonable y dividendos reconocidos, 2025/2024) ; memo liquidez: INA_ASSA_2025_0.pdf (tbl-3: activos liquidos, miles de US$; indicador Activos Liquidos / Total de activos 83.0% FY25).
A5: Años | B5: FY21A | C5: FY22A | D5: FY23A | E5: FY24A | F5: FY25A | G5: FY26E | H5: FY27E | I5: FY28E | J5: FY29E | K5: FY30E
A7: A. PORTAFOLIO POR CATEGORÍA (columna Total de tbl-57/58; FY24-FY25 únicos años divulgados en esta base)
A8: Acciones patrimoniales | E8: 788615179 | F8: 978773593
A9: Fondos de inversión | E9: 56258011 | F9: 52810718
A10: Bonos privados | E10: 436643368 | F10: 493226637
A11: Bonos del gobierno | E11: 83908160 | F11: 100800146
A12: Depósitos a plazo | E12: 197274835 | F12: 211357691
A13: Reportos | E13: 2651825 | F13: 0
A14: Intereses acumulados por cobrar | E14: 5070745 | F14: 5872277
A15: Total instrumentos financieros (Σ categorías) | E15: =E8+E9+E10+E11+E12+E13+E14 -> 1570422123 | F15: =F8+F9+F10+F11+F12+F13+F14 -> 1842841062
A16: Total per filing (verbatim tbl-57/58) | E16: 1570422123 | F16: 1842841062
A17: Instrumentos financieros, neto (EEFF BS) | E17: =EEFF!E79 -> 1570422123 | F17: =EEFF!F79 -> 1842841062
A18: CHECK INVESTMENT_PORTFOLIO_TIE (Σ categorías − verbatim, y verbatim − EEFF BS; esperado 0) | E18: =(E15-E16)+(E16-E17) -> 0 | F18: =(F15-F16)+(F16-F17) -> 0
A19: Mix FY25: acciones patrimoniales ÷ total (memo) | F19: =F8/F15 -> 0.53112209
A21: B. ACCIONES ESTRATÉGICAS — VALOR RAZONABLE (tbl-61)
A22: Grupo Financiero BG, S. A. | E22: 405532999 | F22: 508921589
A23: MHC Holdings LTD | E23: 7524699 | F23: 6019890
A24: Empresa General de Inversiones | E24: 252381387 | F24: 320640492
A25: Copa Holdings, S. A. | E25: 2973814 | F25: 3584782
A26: Corporación de inversiones aéreas, S.A. | E26: 43617053 | F26: 57988044
A27: Entidad privada | E27: 1558012 | F27: 1635334
A28: CM Business Group | E28: 542659 | F28: 1212131
A29: Otras | E29: 15045532 | F29: 10121782
A30: BANPRO | E30: 50760781 | F30: 57924549
A31: Total valor razonable (Σ) | E31: =E22+E23+E24+E25+E26+E27+E28+E29+E30 -> 779936936 | F31: =F22+F23+F24+F25+F26+F27+F28+F29+F30 -> 968048593
A32: Total per filing (verbatim tbl-61; = VRORI acciones patrimoniales tbl-57) | E32: 779936936 | F32: 968048593
A33: CHECK STRATEGIC_EQUITY_FV_TIE (Σ − verbatim, esperado 0) | E33: =E31-E32 -> 0 | F33: =F31-F32 -> 0
A35: C. ACCIONES ESTRATÉGICAS — DIVIDENDOS RECONOCIDOS (tbl-61)
A36: Grupo Financiero BG, S. A. | E36: 19312221 | F36: 20990158
A37: MHC Holdings LTD | E37: 406551 | F37: 323095
A38: Empresa General de Inversiones | E38: 22636186 | F38: 24225072
A39: Copa Holdings, S. A. | E39: 29262 | F39: 0
A40: Corporación de inversiones aéreas, S.A. | E40: 4068000 | F40: 4446783
A41: Entidad privada | E41: 845950 | F41: 73640
A42: CM Business Group | E42: 191150 | F42: 64722
A43: Otras | E43: 1163893 | F43: 673709
A44: BANPRO | E44: 0 | F44: 1017428
A45: Total dividendos (Σ) | E45: =E36+E37+E38+E39+E40+E41+E42+E43+E44 -> 48653213 | F45: =F36+F37+F38+F39+F40+F41+F42+F43+F44 -> 51814607
A46: Total per filing (verbatim tbl-61) | E46: 48653213 | F46: 51814607
A47: CHECK STRATEGIC_EQUITY_DIV_TIE (Σ − verbatim, esperado 0) | E47: =E45-E46 -> 0 | F47: =F45-F46 -> 0
A49: D. DIVIDEND YIELD IMPLÍCITO FY25 (dividendo FY25 ÷ FV promedio FY24-FY25)
A50: Grupo Financiero BG, S. A. | F50: =F36/AVERAGE(E22,F22) -> 0.045907491
A51: Empresa General de Inversiones | F51: =F38/AVERAGE(E24,F24) -> 0.084551997
A52: Corporación de inversiones aéreas, S.A. | F52: =F40/AVERAGE(E26,F26) -> 0.087530707
A53: Total estratégicas (dividendos ÷ FV promedio) | F53: =F45/AVERAGE(E31,F31) -> 0.059284938
A55: E. LIQUIDEZ (memo MD&A, miles de US$ — verbatim, unidad distinta al resto de la hoja)
A56: Activos líquidos FY25: 1,924,835 miles (efectivo 81,994 = 4.3% + instrumentos 1,842,841 = 95.7%); FY24: 1,636,463 miles. Indicador Activos Líquidos ÷ Total de activos = 83.0% FY25 (52.5% FY24).
A57: Fuente: INA_ASSA_2025_0.pdf (tbl-3: activos liquidos, miles de US$; indicador Activos Liquidos / Total de activos 83.0% FY25).
A59: NOT_DISCLOSED (no se inventa)
A60: Duración/convexidad del portafolio de bonos, calificaciones por emisión, moneda por instrumento en resumen anual: NOT_DISCLOSED a esta granularidad.

Sheet Investment_Float
A1: Grupo ASSA, S. A.
A2: Investment_Float — base invertida, yield realizado y forecast de retorno (activos promedio × yield)
A3: Fuente: EEFF (mirror congelado) filas de inversiones/instrumentos y Retorno de las inversiones. Forecast: driver proxy documentado (LIMITED_HISTORY NIIF 17).
A5: Años | B5: FY21A | C5: FY22A | D5: FY23A | E5: FY24A | F5: FY25A | G5: FY26E | H5: FY27E | I5: FY28E | J5: FY29E | K5: FY30E
A7: A. BASE INVERTIDA (fin de período)
A8: Inversiones, neto — base legacy (ref EEFF, FY21-FY23) | B8: =EEFF!B76 -> 1282484672 | C8: =EEFF!C76 -> 1306501849 | D8: =EEFF!D76 -> 1450423677
A9: Instrumentos financieros, neto — NIIF17-era (ref EEFF, FY24-FY25) | E9: =EEFF!E79 -> 1570422123 | F9: =EEFF!F79 -> 1842841062
A10: Total base invertida (suma de bases mutuamente excluyentes legacy/NIIF17; forecast = driver proxy) | B10: =B8+B9 -> 1282484672 | C10: =C8+C9 -> 1306501849 | D10: =D8+D9 -> 1450423677 | E10: =E8+E9 -> 1570422123 | F10: =F8+F9 -> 1842841062 | G10: =F10*(1+Supuestos!G11) -> 1.9891626e+09 | H10: =G10*(1+Supuestos!H11) -> 2.1471022e+09 | I10: =H10*(1+Supuestos!I11) -> 2.3175821e+09 | J10: =I10*(1+Supuestos!J11) -> 2.5015981e+09 | K10: =J10*(1+Supuestos!K11) -> 2.700225e+09
A12: DRIVER_PROXY: base invertida forecast crece con el driver de ingresos por servicios NIIF 17 (Supuestos!fila 11); el filing no divulga un plan de inversión — proxy explícito, no dato.
A13: Base invertida promedio (=(inicio+cierre)/2; solo desde FY25 — FY24 mezclaría bases) | F13: =AVERAGE(E10,F10) -> 1.7066316e+09 | G13: =AVERAGE(F10,G10) -> 1.9160019e+09 | H13: =AVERAGE(G10,H10) -> 2.0681324e+09 | I13: =AVERAGE(H10,I10) -> 2.2323421e+09 | J13: =AVERAGE(I10,J10) -> 2.4095901e+09 | K13: =AVERAGE(J10,K10) -> 2.6009115e+09
A15: B. RETORNO Y YIELD
A16: Retorno de las inversiones (ref EEFF, FY24-FY25; forecast = promedio × yield) | E16: =EEFF!E57 -> 90919085 | F16: =EEFF!F57 -> 102622650 | G16: =G13*G18 -> 1.1521244e+08 | H16: =H13*H18 -> 1.2436031e+08 | I16: =I13*I18 -> 1.3423451e+08 | J16: =J13*J18 -> 1.4489273e+08 | K16: =K13*K18 -> 1.5639722e+08
A17: Yield realizado (=retorno ÷ base promedio, FY25) | F17: =F16/F13 -> 0.060131695
A18: Yield driver FY26-FY30 (= yield realizado FY25, RATIO_HELD_FLAT_FY25) | G18: =$F$17 -> 0.060131695 | H18: =$F$17 -> 0.060131695 | I18: =$F$17 -> 0.060131695 | J18: =$F$17 -> 0.060131695 | K18: =$F$17 -> 0.060131695
A20: C. ASIGNACIÓN DEL RETORNO FORECAST A COMPONENTES DEL P&L (mix FY25, ALLOCATION_FY25_MIX)
A21: El EEFF presenta el retorno en 3 líneas (interés efectivo / otros ingresos por inversiones / deterioro). El forecast total se asigna con el mix FY25 (transparente, no un dato divulgado).
A22: Participación FY25: ingresos por interés (método efectivo) ÷ retorno total | F22: =EEFF!F54/EEFF!F57 -> 0.39783858
A23: Participación FY25: otros ingresos por inversiones ÷ retorno total | F23: =EEFF!F55/EEFF!F57 -> 0.60284473
A24: Participación FY25: pérdida neta por deterioro ÷ retorno total | F24: =EEFF!F56/EEFF!F57 -> -0.00068330919
A25: Forecast asignado: ingresos por interés (→ ModeloFinanciero) | G25: =G16*$F$22 -> 45835953 | H25: =H16*$F$22 -> 49475327 | I25: =I16*$F$22 -> 53403668 | J25: =J16*$F$22 -> 57643919 | K25: =K16*$F$22 -> 62220847
A26: Forecast asignado: otros ingresos por inversiones (→ ModeloFinanciero) | G26: =G16*$F$23 -> 69455212 | H26: =H16*$F$23 -> 74969956 | I26: =I16*$F$23 -> 80922570 | J26: =J16*$F$23 -> 87347822 | K26: =K16*$F$23 -> 94283239
A27: Forecast asignado: pérdida neta por deterioro (→ ModeloFinanciero) | G27: =G16*$F$24 -> -78725.718 | H27: =H16*$F$24 -> -84976.54 | I27: =I16*$F$24 -> -91723.678 | J27: =J16*$F$24 -> -99006.538 | K27: =K16*$F$24 -> -106867.66
A28: CHECK INVESTMENT_FLOAT_YIELD_TIE (Σ componentes asignados − retorno total forecast, esperado 0) | G28: =(G25+G26+G27)-G16 -> 0 | H28: =(H25+H26+H27)-H16 -> 0 | I28: =(I25+I26+I27)-I16 -> 0 | J28: =(J25+J26+J27)-J16 -> 0 | K28: =(K25+K26+K27)-K16 -> 0
A30: NOT_DISCLOSED: plan de inversión/duración objetivo, yields contractuales por categoría — no divulgados; el yield agregado FY25 es la única base observable.

Sheet Solvency_Capital
A1: Grupo ASSA, S. A.
A2: Solvency_Capital — cumplimiento cualitativo, recursos de capital, reservas legales y fuentes regulatorias
A3: Fuente filing: INA_ASSA_2025_0.pdf p.112 (capital regulatorio: grupo no sujeto directamente; subsidiarias cumplen SCR 2025 y 2024) ; INA_ASSA_2025_0.pdf (tbl-89: mapa de reguladores de reservas legales por pais) ; INA_ASSA_2025_0.pdf (recursos de capital: reservas US$981M = 60% del patrimonio; US$844M reserva valor razonable + US$137M reservas regulatorias). Fuentes regulatorias web citadas con URL + fecha en sección E.
A5: Años | B5: FY21A | C5: FY22A | D5: FY23A | E5: FY24A | F5: FY25A | G5: FY26E | H5: FY27E | I5: FY28E | J5: FY29E | K5: FY30E
A7: A. MARCO DE CAPITAL REGULATORIO (verbatim del filing)
A8: El Grupo NO está sujeto directamente a requisitos de capital regulatorio; cada subsidiaria aseguradora/reaseguradora sí lo está ante su regulador local, que monitorea SCR vs capital regulatorio disponible.
A9: Durante 2025 y 2024, TODAS las subsidiarias reguladas cumplieron los requisitos de capital de sus reguladores (COMPLIANCE_DISCLOSED = PASS cualitativo).
A10: Fuente: INA_ASSA_2025_0.pdf p.112 (capital regulatorio: grupo no sujeto directamente; subsidiarias cumplen SCR 2025 y 2024).
A12: B. RECURSOS DE CAPITAL
A13: Reservas (ref EEFF BS: incluye valor razonable + regulatorias) | B13: =EEFF!B118 -> 621098362 | C13: =EEFF!C118 -> 590516262 | D13: =EEFF!D118 -> 675316259 | E13: =EEFF!E118 -> 755623881 | F13: =EEFF!F118 -> 981253106
A14: Total del patrimonio de la participación controladora (ref EEFF) | B14: =EEFF!B122 -> 1028705937 | C14: =EEFF!C122 -> 1016748180 | D14: =EEFF!D122 -> 1151376457 | E14: =EEFF!E122 -> 1371490800 | F14: =EEFF!F122 -> 1579781587
A16: MD&A: reservas por US$981M = 60% del patrimonio (US$844M reserva de valor razonable de inversiones + US$137M reservas patrimoniales requeridas por reguladores). La cifra MD&A está redondeada a millones — la fila EEFF trae el dato exacto (981,253,106).
A17: Fuente: INA_ASSA_2025_0.pdf (recursos de capital: reservas US$981M = 60% del patrimonio; US$844M reserva valor razonable + US$137M reservas regulatorias).
A19: C. RESERVAS LEGALES DE SEGUROS — MAPA DE REGULADORES (Nota, tbl-89)
A20: Panamá — Superintendencia de Seguros y Reaseguros de Panamá (SSRP) — Ley 12 de 2012
A21: Costa Rica — Superintendencia General de Seguros (SUGESE) — Ley 8653; Reglamentos CONASSIF/SUGESE
A22: Nicaragua — Superintendencia de Bancos y Otras Instituciones Financieras (SIBOIF) — Normas CD-SIB-188-1-NOV23-2001; Ley 733
A23: El Salvador — Superintendencia del Sistema Financiero (SSF) — NCS-011 Reservas Técnicas
A24: Honduras — Comisión Nacional de Bancos y Seguros (CNBS) — Reglamento CNBS 041/2004
A25: Guatemala — Superintendencia de Bancos (SIB) / Junta Monetaria — Ley 25-2010; JM-3-2011
A26: Bermuda — Bermuda Monetary Authority (BMA) — Insurance Act 1978; Eligible Capital Rules; BSCR
A27: Islas Caimán — Cayman Islands Monetary Authority (CIMA) — Insurance Act 2010
A28: Fuente: INA_ASSA_2025_0.pdf (tbl-89: mapa de reguladores de reservas legales por pais).
... A40: SBP (relevante por la participación estratégica en Grupo Financiero BG, FV US$508.9M): https://www.superbancos.gob.pa/info-gen-bancos/licencia-general (SBP: Banco General, S.A. con Licencia General; consultado 2026-07-07).

Sheet Unit_Economics
A1: Grupo ASSA, S. A.
A2: Unit_Economics — desagregación de revenue (prima por ramo → growth → mix) y cost economics por base contable
A3: Fuente: Premiums_Claims (links verdes) + EEFF (mirror congelado) + memo regulatorio SSRP citado. Bases legacy/NIIF17 explícitas.
A5: Años | B5: FY21A | C5: FY22A | D5: FY23A | E5: FY24A | F5: FY25A | G5: FY26E | H5: FY27E | I5: FY28E | J5: FY29E | K5: FY30E
A7: A. REVENUE BUILD — PRIMA SUSCRITA NETA DE REASEGURO POR RAMO (link Premiums_Claims; 12 ramos, tbl-35)
A8: BASE_DISTINTA: este build por ramo NO es la misma base que los ingresos por servicios NIIF 17 consolidados (sección C) — no se fuerza conciliación no divulgada.
A9: Accidentes personales | E9: =Premiums_Claims!E19 -> 84101845 | F9: =Premiums_Claims!F19 -> 86428052 | G9: =Premiums_Claims!G19 -> 88822109 | H9: =Premiums_Claims!H19 -> 91282481 | I9: =Premiums_Claims!I19 -> 93811006 | J9: =Premiums_Claims!J19 -> 96409571 | K9: =Premiums_Claims!K19 -> 99080116
A10: Automóvil | E10: =Premiums_Claims!E20 -> 100793260 | F10: =Premiums_Claims!F20 -> 114979720 | G10: =Premiums_Claims!G20 -> 1.3115737e+08 | H10: =Premiums_Claims!H20 -> 1.4961121e+08 | I10: =Premiums_Claims!I20 -> 1.7066151e+08 | J10: =Premiums_Claims!J20 -> 1.9467358e+08 | K10: =Premiums_Claims!K20 -> 2.2206415e+08
A11: Casco | E11: =Premiums_Claims!E21 -> 18932539 | F11: =Premiums_Claims!F21 -> 19542577 | G11: =Premiums_Claims!G21 -> 20171848 | H11: =Premiums_Claims!H21 -> 20821381 | I11: =Premiums_Claims!I21 -> 21491830 | J11: =Premiums_Claims!J21 -> 22183867 | K11: =Premiums_Claims!K21 -> 22898187
A12: Colectivo de vida | E12: =Premiums_Claims!E22 -> 39159903 | F12: =Premiums_Claims!F22 -> 41214579 | G12: =Premiums_Claims!G22 -> 43378344 | H12: =Premiums_Claims!H22 -> 45655707 | I12: =Premiums_Claims!I22 -> 48052632 | J12: =Premiums_Claims!J22 -> 50575395 | K12: =Premiums_Claims!K22 -> 53230604
A13: Fianzas | E13: =Premiums_Claims!E23 -> 5662609 | F13: =Premiums_Claims!F23 -> 5661627 | G13: =Premiums_Claims!G23 -> 5660494.7 | H13: =Premiums_Claims!H23 -> 5659362.6 | I13: =Premiums_Claims!I23 -> 5658230.7 | J13: =Premiums_Claims!J23 -> 5657099.1 | K13: =Premiums_Claims!K23 -> 5655967.6
A14: Fidelidad | E14: =Premiums_Claims!E24 -> 5264032 | F14: =Premiums_Claims!F24 -> 5598664 | G14: =Premiums_Claims!G24 -> 5954739 | H14: =Premiums_Claims!H24 -> 6333460.4 | I14: =Premiums_Claims!I24 -> 6736268.5 | J14: =Premiums_Claims!J24 -> 7164695.2 | K14: =Premiums_Claims!K24 -> 7620369.8
A15: Incendio | E15: =Premiums_Claims!E25 -> 16624396 | F15: =Premiums_Claims!F25 -> 16727248 | G15: =Premiums_Claims!G25 -> 16830957 | H15: =Premiums_Claims!H25 -> 16935309 | I15: =Premiums_Claims!I25 -> 17040308 | J15: =Premiums_Claims!J25 -> 17145958 | K15: =Premiums_Claims!K25 -> 17252263
A16: Responsabilidad civil | E16: =Premiums_Claims!E26 -> 5695830 | F16: =Premiums_Claims!F26 -> 5774973 | G16: =Premiums_Claims!G26 -> 5855245.1 | H16: =Premiums_Claims!H26 -> 5936633 | I16: =Premiums_Claims!I26 -> 6019152.2 | J16: =Premiums_Claims!J26 -> 6102818.4 | K16: =Premiums_Claims!K26 -> 6187647.6
A17: Riesgos diversos | E17: =Premiums_Claims!E27 -> 5059301 | F17: =Premiums_Claims!F27 -> 4979863 | G17: =Premiums_Claims!G27 -> 4901679.2 | H17: =Premiums_Claims!H27 -> 4824722.8 | I17: =Premiums_Claims!I27 -> 4748974.6 | J17: =Premiums_Claims!J27 -> 4674415.7 | K17: =Premiums_Claims!K27 -> 4601027.4
A18: Salud | E18: =Premiums_Claims!E28 -> 64553128 | F18: =Premiums_Claims!F28 -> 65224063 | G18: =Premiums_Claims!G28 -> 65902393 | H18: =Premiums_Claims!H28 -> 66587778 | I18: =Premiums_Claims!I28 -> 67280291 | J18: =Premiums_Claims!J28 -> 67980006 | K18: =Premiums_Claims!K28 -> 68686998
A19: Seguros técnicos | E19: =Premiums_Claims!E29 -> 2816214 | F19: =Premiums_Claims!F29 -> 2734994 | G19: =Premiums_Claims!G29 -> 2656226.2 | H19: =Premiums_Claims!H29 -> 2579726.9 | I19: =Premiums_Claims!I29 -> 2505430.7 | J19: =Premiums_Claims!J29 -> 2433274.3 | K19: =Premiums_Claims!K29 -> 2363196
A20: Autoexpedibles y otros | E20: =Premiums_Claims!E30 -> 12790589 | F20: =Premiums_Claims!F30 -> 12943398 | G20: =Premiums_Claims!G30 -> 13097424 | H20: =Premiums_Claims!H30 -> 13253284 | I20: =Premiums_Claims!I30 -> 13410998 | J20: =Premiums_Claims!J30 -> 13570589 | K20: =Premiums_Claims!K30 -> 13732079
A21: Total prima por ramo (link Premiums_Claims) | E21: =Premiums_Claims!E33 -> 361453646 | F21: =Premiums_Claims!F33 -> 381809758 | G21: =Premiums_Claims!G33 -> 4.0438883e+08 | H21: =Premiums_Claims!H33 -> 4.2948105e+08 | I21: =Premiums_Claims!I33 -> 4.5741663e+08 | J21: =Premiums_Claims!J33 -> 4.8857127e+08 | K21: =Premiums_Claims!K33 -> 5.2337261e+08
A23: B. GROWTH FY24→FY25 Y MIX FY25 POR RAMO (el forecast por ramo replica el growth FY25 propio — ver Premiums_Claims)
A24: Accidentes personales — growth FY25 | F24: =F9/E9-1 -> 0.027659405
A25: Automóvil — growth FY25 | F25: =F10/E10-1 -> 0.1407481
A26: Casco — growth FY25 | F26: =F11/E11-1 -> 0.032221669
A27: Colectivo de vida — growth FY25 | F27: =F12/E12-1 -> 0.052468874
A28: Fianzas — growth FY25 | F28: =F13/E13-1 -> -0.0001734183
A29: Fidelidad — growth FY25 | F29: =F14/E14-1 -> 0.063569522
A30: Incendio — growth FY25 | F30: =F15/E15-1 -> 0.0061868112
A31: Responsabilidad civil — growth FY25 | F31: =F16/E16-1 -> 0.013894902
A32: Riesgos diversos — growth FY25 | F32: =F17/E17-1 -> -0.015701379
A33: Salud — growth FY25 | F33: =F18/E18-1 -> 0.010393532
A34: Seguros técnicos — growth FY25 | F34: =F19/E19-1 -> -0.028840138
A35: Autoexpedibles y otros — growth FY25 | F35: =F20/E20-1 -> 0.011946987
A37: Mix FY25 por ramo (participación en el total):
A38: Accidentes personales — mix FY25 | F38: =F9/F21 -> 0.22636418
A39: Automóvil — mix FY25 | F39: =F10/F21 -> 0.30114401
A40: Casco — mix FY25 | F40: =F11/F21 -> 0.051184069
A41: Colectivo de vida — mix FY25 | F41: =F12/F21 -> 0.10794533
A42: Fianzas — mix FY25 | F42: =F13/F21 -> 0.014828398
A43: Fidelidad — mix FY25 | F43: =F14/F21 -> 0.014663491
A44: Incendio — mix FY25 | F44: =F15/F21 -> 0.043810426
A45: Responsabilidad civil — mix FY25 | F45: =F16/F21 -> 0.015125263
A46: Riesgos diversos — mix FY25 | F46: =F17/F21 -> 0.013042786
A47: Salud — mix FY25 | F47: =F18/F21 -> 0.1708287
A48: Seguros técnicos — mix FY25 | F48: =F19/F21 -> 0.0071632376
A49: Autoexpedibles y otros — mix FY25 | F49: =F20/F21 -> 0.033900124
A51: C. CASCADA DE MARGEN NIIF 17 (FY24-FY30): ingresos → ratio gasto de servicio → ratio reaseguro → margen de servicio → G&A
A52: Ingresos por servicios de seguro (link Premiums_Claims) | E52: =Premiums_Claims!E39 -> 820306455 | F52: =Premiums_Claims!F39 -> 885435473 | G52: =Premiums_Claims!G39 -> 9.5573905e+08 | H52: =Premiums_Claims!H39 -> 1.0316247e+09 | I52: =Premiums_Claims!I39 -> 1.1135357e+09 | J52: =Premiums_Claims!J39 -> 1.2019505e+09 | K52: =Premiums_Claims!K39 -> 1.2973853e+09
A53: Ratio gasto de servicio (=gasto ÷ ingreso; negativo) | E53: =Premiums_Claims!E40/Premiums_Claims!E39 -> -0.4484638 | F53: =Premiums_Claims!F40/Premiums_Claims!F39 -> -0.48164584 | G53: =Premiums_Claims!G40/Premiums_Claims!G39 -> -0.4816 | H53: =Premiums_Claims!H40/Premiums_Claims!H39 -> -0.4816 | I53: =Premiums_Claims!I40/Premiums_Claims!I39 -> -0.4816 | J53: =Premiums_Claims!J40/Premiums_Claims!J39 -> -0.4816 | K53: =Premiums_Claims!K40/Premiums_Claims!K39 -> -0.4816
A54: Ratio resultado de reaseguro (=resultado reaseguro ÷ ingreso; negativo) | E54: =Premiums_Claims!E41/Premiums_Claims!E39 -> -0.38378798 | F54: =Premiums_Claims!F41/Premiums_Claims!F39 -> -0.35381145 | G54: =Premiums_Claims!G41/Premiums_Claims!G39 -> -0.35381145 | H54: =Premiums_Claims!H41/Premiums_Claims!H39 -> -0.35381145 | I54: =Premiums_Claims!I41/Premiums_Claims!I39 -> -0.35381145 | J54: =Premiums_Claims!J41/Premiums_Claims!J39 -> -0.35381145 | K54: =Premiums_Claims!K41/Premiums_Claims!K39 -> -0.35381145
A55: Margen del servicio de seguro (=resultado servicio ÷ ingreso) | E55: =Premiums_Claims!E42/Premiums_Claims!E39 -> 0.16774822 | F55: =Premiums_Claims!F42/Premiums_Claims!F39 -> 0.16454271 | G55: =Premiums_Claims!G42/Premiums_Claims!G39 -> 0.16458855 | H55: =Premiums_Claims!H42/Premiums_Claims!H39 -> 0.16458855 | I55: =Premiums_Claims!I42/Premiums_Claims!I39 -> 0.16458855 | J55: =Premiums_Claims!J42/Premiums_Claims!J39 -> 0.16458855 | K55: =Premiums_Claims!K42/Premiums_Claims!K39 -> 0.16458855
A56: Ratio G&A (hist: ref EEFF; forecast: driver activo de Supuestos — mismo ratio que consume ModeloFinanciero) | E56: =EEFF!E62/EEFF!E50 -> -0.10875473 | F56: =EEFF!F62/EEFF!F50 -> -0.10760001 | G56: =Supuestos!G26 -> -0.1076 | H56: =Supuestos!H26 -> -0.1076 | I56: =Supuestos!I26 -> -0.1076 | J56: =Supuestos!J26 -> -0.1076 | K56: =Supuestos!K26 -> -0.1076
A58: D. COST ECONOMICS POR BASE CONTABLE
A59: Base legacy (FY21-FY23), sobre primas netas ganadas:
A60: Reclamos y beneficios netos incurridos ÷ primas netas ganadas | B60: =EEFF!B19/EEFF!B15 -> -0.51888075 | C60: =EEFF!C19/EEFF!C15 -> -0.5178789 | D60: =EEFF!D19/EEFF!D15 -> -0.53025283
A61: Costo de suscripción y adquisición ÷ primas netas ganadas | B61: =EEFF!B20/EEFF!B15 -> -0.30803479 | C61: =EEFF!C20/EEFF!C15 -> -0.30759417 | D61: =EEFF!D20/EEFF!D15 -> -0.32447428
A62: ECL primas por cobrar ÷ primas netas ganadas | B62: =EEFF!B21/EEFF!B15 -> -0.00049165731 | C62: =EEFF!C21/EEFF!C15 -> -0.0041434191 | D62: =EEFF!D21/EEFF!D15 -> -0.0031200524
A64: Base NIIF 17 (FY24-FY30): ver sección C (ratio de gasto de servicio y reaseguro sobre ingresos por servicios).
A66: E. COSTO/PRIMA POR PÓLIZA
A67: Filing consolidado: número de pólizas del Grupo NOT_DISCLOSED → costo por póliza del Grupo NOT_DISCLOSED (no se inventan denominadores).
A68: Memo regulatorio (fuente SSRP, NO filing; subsidiaria ASSA Cía. de Seguros Panamá, seguro directo, acumulado ene-abr): 2026: pólizas vigentes 377,602; primas suscritas US$184,158,112.66; siniestros pagados US$52,273,848.30. 2025: pólizas 356,126; primas US$180,612,701; siniestros US$65,175,756. Fuente: https://www.superseguros.gob.pa/wp-content/uploads/DES-C-04-2026.pdf (SSRP resumen acumulado al 30-abr-2026, seguro directo; consultado 2026-07-07).
A69: Prima suscrita acumulada ene-abr-2026 por póliza vigente ≈ US$487.7 (memo aritmético de las dos cifras SSRP; periodo parcial de 4 meses, alcance subsidiaria ≠ grupo — NO comparable con las métricas consolidadas de arriba).

Sheet MD&A
A1: Grupo ASSA, S. A.
A2: MD&A — resumen ejecutivo (discusión de gestión del filing 2025)
A3: Fuente: Informe de Actualización Anual 2025 de Grupo ASSA, sección Discusión de Gestión (citas técnicas archivo:línea en Source_Register). Cifras de mercado: fuentes web citadas con URL + fecha.
A5: Años | B5: FY21A | C5: FY22A | D5: FY23A | E5: FY24A | F5: FY25A | G5: FY26E | H5: FY27E | I5: FY28E | J5: FY29E | K5: FY30E
A7: A. LIQUIDEZ
A8: Activos líquidos = 83.0% del total de activos en FY25 (52.5% FY24). Composición FY25 (miles US$): efectivo y equivalentes 81,994 (4.3%) + instrumentos financieros netos 1,842,841 (95.7%) = 1,924,835.
A9: El aumento refleja mejoras de valor razonable de las inversiones y la re-expresión NIIF 17 de 2024; con la reorganización del segmento bancario y la venta del segmento hipotecario, el índice de liquidez queda en posiciones favorables.
A10: Fuente: IN-A 2025, Discusión de Gestión, tabla de activos líquidos (miles de US$) e indicadores de liquidez.
A12: B. RECURSOS DE CAPITAL
A13: Tres fuentes primordiales de capital; el patrimonio de los accionistas es la principal. Reservas por US$981M = 60% del patrimonio: US$844M reserva de valor razonable de inversiones + US$137M reservas patrimoniales requeridas por reguladores.
A14: Fuente: IN-A 2025, Discusión de Gestión, sección B Recursos de Capital. Detalle en Solvency_Capital sección B.
A16: C. SEGMENTOS (Nota de segmentos, resultado neto por segmento reportable)
A17: Grupo ASSA, S. A. (Inversiones) — resultado, neto | E17: 62386837 | F17: 83057721
A18: ASSA Compañía Tenedora, S. A. — resultado, neto | E18: 178650732 | F18: 189739675
A19: La Hipotecaria (Holding), Inc. — resultado, neto (op. descontinuada) | E19: 4611909 | F19: 3132551
A20: Otras actividades — resultado, neto | E20: 191455 | F20: 2553262
A22: Fuente verbatim: EEFF auditados 2025, Nota de segmentos de operación (resultado por segmento 2025/2024 y conciliación a consolidado). La suma de segmentos NO es el consolidado (eliminaciones −35.6M FY25 y exclusión de operación descontinuada; ver tie abajo).
A23: Utilidad antes de impuesto, consolidada tras conciliación (verbatim tbl-31) | E23: 140419999 | F23: 148121503
A24: Utilidad antes de impuesto (ref EEFF) | E24: =EEFF!E64 -> 140419999 | F24: =EEFF!F64 -> 148121503
A25: CHECK SEGMENT_RECON_TIE (tbl-31 conciliado − EEFF, esperado 0) | E25: =E23-E24 -> 0 | F25: =F23-F24 -> 0
A27: D. EVENTOS ESTRUCTURALES DEL AÑO
A28: Adopción de NIIF 17 desde el 1-ene-2025 (SSRP), con 2024 re-expresado — ver Premiums_Claims sección Accounting_Basis.
A29: Reorganización del segmento bancario y venta del segmento hipotecario (La Hipotecaria (Holding), Inc. presentada como operación descontinuada).
A31: E. LA ACCIÓN (fuentes web, NO filing — citadas con URL + fecha)
A32: Cierre 31-dic-2025: US$126.00/acción (+26% vs 2024); dividendos 2025: US$6.50 recurrentes + US$7.28 extraordinario (venta de La Hipotecaria). Fuente: https://www.assanet.com/grupoassa/nota-de-prensa-reunion-de-accionistas-grupo-assa/ (cierre 31-dic-2025 US$126.00/accion; dividendos 2025 US$6.50 recurrentes + US$7.28 extraordinario; consultado 2026-07-07).
A33: Valor en libros por acción al 31-dic-2025: US$154.49 → P/B 0.82x per Memoria. Fuente: https://fliphtml5.com/FLBOOK/Mayo-20_Memoria-ASSA_FINAL_2025/ (Memoria ASSA 2025: valor en libros por accion US$154.49 al 31-dic-2025; P/B 0.82x; consultado 2026-07-07). Ver hoja Valuation.

Sheet Valuation
A1: Grupo ASSA, S. A.
A2: Valuation — P/B con precio de mercado citado (FIG: sin EV/EBITDA ni DCF desapalancado)
A3: Acciones: INA_ASSA_2025_0.pdf (Nota 23.A tbl-88: acciones autorizadas/emitidas/tesoreria/en circulacion). Precios: https://www.assanet.com/grupoassa/nota-de-prensa-reunion-de-accionistas-grupo-assa/ (cierre 31-dic-2025 US$126.00/accion; dividendos 2025 US$6.50 recurrentes + US$7.28 extraordinario; consultado 2026-07-07) ; https://www.latinexbolsa.com/es/detalle-de-emisor/?code=ASSA (pizarra Latinex, precio ASSA US$140.00; consultado 2026-07-07).
A5: Años | B5: FY21A | C5: FY22A | D5: FY23A | E5: FY24A | F5: FY25A | G5: FY26E | H5: FY27E | I5: FY28E | J5: FY29E | K5: FY30E
A7: A. ACCIONES Y VALOR EN LIBROS
A8: Acciones en circulación (Nota 23.A tbl-88, verbatim) | E8: 10146954 | F8: 10218363
A10: Autorizadas: 12,000,000 sin valor nominal; en tesorería FY25: 215,007. Nota: el párrafo A de la Nota 23 del mirror trae una inconsistencia interna de redacción (emitidas vs circulación); tbl-88 es la fuente usada. INA_ASSA_2025_0.pdf (Nota 23.A tbl-88: acciones autorizadas/emitidas/tesoreria/en circulacion).
A11: Total del patrimonio de la participación controladora (ref EEFF) | B11: =EEFF!B122 -> 1028705937 | C11: =EEFF!C122 -> 1016748180 | D11: =EEFF!D122 -> 1151376457 | E11: =EEFF!E122 -> 1371490800 | F11: =EEFF!F122 -> 1579781587
A12: Valor en libros por acción (=patrimonio controladora ÷ acciones en circulación) | E12: =E11/E8 -> 135.16281 | F12: =F11/F8 -> 154.60222
A14: Cruce: Memoria 2025 reporta BVPS US$154.49 (computado aquí ≈ US$154.60; diferencia por definición del denominador/redondeo de la Memoria — no es un error del modelo). Fuente: https://fliphtml5.com/FLBOOK/Mayo-20_Memoria-ASSA_FINAL_2025/ (Memoria ASSA 2025: valor en libros por accion US$154.49 al 31-dic-2025; P/B 0.82x; consultado 2026-07-07).
A16: B. P/B (precio de mercado con fuente citada; columna FY25 = ancla de valuación)
A17: Precio por acción al 31-dic-2025 (fuente web citada, NO filing) | F17: 126
A19: Fuente: https://www.assanet.com/grupoassa/nota-de-prensa-reunion-de-accionistas-grupo-assa/ (cierre 31-dic-2025 US$126.00/accion; dividendos 2025 US$6.50 recurrentes + US$7.28 extraordinario; consultado 2026-07-07).
A20: P/B al 31-dic-2025 (=precio ÷ BVPS FY25) | F20: =F17/F12 -> 0.81499477
A21: Precio en pizarra Latinex al 2026-07-07 (memo posterior al cierre FY25; misma columna como ancla) | F21: 140
A23: Fuente: https://www.latinexbolsa.com/es/detalle-de-emisor/?code=ASSA (pizarra Latinex, precio ASSA US$140.00; consultado 2026-07-07).
A24: P/B con precio 2026-07-07 sobre BVPS FY25 (memo, denominador rezagado) | F24: =F21/F12 -> 0.90554975
A26: C. NOT_DISCLOSED / FUERA DE ALCANCE (nunca plug)
A27: Embedded value / valor de negocio nuevo (VNB) / own funds: NOT_DISCLOSED en el filing — no se estima.
A28: Doctrina FIG: sin EV/EBITDA ni DCF desapalancado para aseguradoras; la superficie de valuación es P/B + ROE (el ROE requiere firma de metodología — pendiente).

Sheet _CHECKS
A1: Grupo ASSA, S. A.
A2: _CHECKS panel — insurance template, live formulas, known residuals signed visible
A3: Status semantics: PASS = zero undocumented hard failures; KNOWN_RESIDUAL = signed G7 residual; SOURCE_GAP = unresolved semantic anchor/schedule.
A4: MASTER_STATUS | B4: MODEL STATUS | C4: =IF(SUMPRODUCT(--ISERROR($C$6:$C$35))+COUNTIF($C$6:$C$35,"FAIL")>0,"FAIL",IF(COUNTIF($C$6:$C$35,"PASS")=17,"PASS","FAIL")) -> PASS | G4: Master PASS counts only FAIL rows; KNOWN_RESIDUAL/SOURCE_GAP remain visible but non-blocking.
A5: check_id | B5: description | C5: status | D5: hardness | E5: tolerance | F5: expected | G5: note | H5: FY21A | I5: FY22A | J5: FY23A | K5: FY24A | L5: FY25A | M5: FY26E | N5: FY27E | O5: FY28E | P5: FY29E | Q5: FY30E
A7: UNIVERSAL CHECKS
A8: BS_BALANCE | B8: UNIVERSAL | expected 0; hard fail if ABS(value) > hard_tie_tolerance. Observed: UEPII critical gate <10 for BS/cash; BG hard reconciliation >=1000 because full USD. | source applies_to: all 16 archetypes | C8: =IF(SUMPRODUCT((ABS(H8:Q8)>1000)*1)=0,"PASS","FAIL") -> PASS | D8: hard | E8: 1000 USD | F8: 0 | G8: expected 0; hard fail if ABS(value) > hard_tie_tolerance. Observed: UEPII critical gate <10 for BS/cash; BG hard reconciliation >=1000 because full USD. Default full-USD hard tie threshold is $1,000 unless the workbook declares a tighter scale-aware tolerance. | H8: =ModeloFinanciero!B89-ModeloFinanciero!B122 -> 0 | I8: =ModeloFinanciero!C89-ModeloFinanciero!C122 -> 0 | J8: =ModeloFinanciero!D89-ModeloFinanciero!D122 -> 0 | K8: =ModeloFinanciero!E89-ModeloFinanciero!E122 -> 0 | L8: =ModeloFinanciero!F89-ModeloFinanciero!F122 -> 0 | M8: =ModeloFinanciero!G89-ModeloFinanciero!G122 -> 0 | N8: =ModeloFinanciero!H89-ModeloFinanciero!H122 -> 0 | O8: =ModeloFinanciero!I89-ModeloFinanciero!I122 -> 0 | ... Q8: =ModeloFinanciero!K89-ModeloFinanciero!K122 -> 0
A9: CASH_TIE | B9: UNIVERSAL | expected 0; use hard_tie_tolerance; if cash includes restricted cash/time deposits, define cash_component role explicitly. | source applies_to: all 16 archetypes | C9: KNOWN_RESIDUAL | D9: hard | E9: 1000 USD | F9: -56584218 @ FY23A | G9: G7a cash tie: FY21-FY23 historical cash definition/restatement/insurance presentation gap suspected; signed as visible known residual. | H9: =EEFF!B219-EEFF!B73 -> -50335044 | I9: =EEFF!C219-EEFF!C73 -> -53465410 | J9: =EEFF!D219-EEFF!D73 -> -56584218 | K9: =EEFF!E219-EEFF!E73 -> 0 | L9: =EEFF!F219-EEFF!F73 -> 0
A10: CF_ROLLFORWARD | B10: UNIVERSAL | expected 0; hard_tie_tolerance; historical rows may be WARN if source CF transcript is incomplete. | source applies_to: all 16 where CF is modeled | C10: SOURCE_GAP | D10: hard | E10: 1000 USD | F10: 0 | G10: CF rollforward row is live, but insurance cash-flow semantics need signed component taxonomy before hard blocking. | H10: =ModeloFinanciero!B195+ModeloFinanciero!B205+ModeloFinanciero!B178-(ModeloFinanciero!B214-ModeloFinanciero!B212) -> -168900808 | I10: =ModeloFinanciero!C195+ModeloFinanciero!C205+ModeloFinanciero!C178-(ModeloFinanciero!C214-ModeloFinanciero!C212) -> 37232071 | J10: =ModeloFinanciero!D195+ModeloFinanciero!D205+ModeloFinanciero!D178-(ModeloFinanciero!D214-ModeloFinanciero!D212) -> -62834289 | K10: =ModeloFinanciero!E195+ModeloFinanciero!E205+ModeloFinanciero!E178-(ModeloFinanciero!E214-ModeloFinanciero!E212) -> 63361284 | L10: =ModeloFinanciero!F195+ModeloFinanciero!F205+ModeloFinanciero!F178-(ModeloFinanciero!F214-ModeloFinanciero!F212) -> 142114442 | M10: =ModeloFinanciero!G195+ModeloFinanciero!G205+ModeloFinanciero!G178-(ModeloFinanciero!G214-ModeloFinanciero!G212) -> 142114442 | N10: =ModeloFinanciero!H195+ModeloFinanciero!H205+ModeloFinanciero!H178-(ModeloFinanciero!H214-ModeloFinanciero!H212) -> 142114442 | O10: =ModeloFinanciero!I195+ModeloFinanciero!I205+ModeloFinanciero!I178-(ModeloFinanciero!I214-ModeloFinanciero!I212) -> 142114442 | ... Q10: =ModeloFinanciero!K195+ModeloFinanciero!K205+ModeloFinanciero!K178-(ModeloFinanciero!K214-ModeloFinanciero!K212) -> 142114442
A11: NI_TIE_TO_EQUITY | B11: UNIVERSAL | expected 0; hard_tie_tolerance. | source applies_to: all 16 | C11: =IF(SUMPRODUCT((ABS(H11:Q11)>1000)*1)=0,"PASS","FAIL") -> PASS | D11: hard | E11: 1000 USD | F11: 0 | G11: expected 0; hard_tie_tolerance. Default full-USD hard tie threshold is $1,000 unless the workbook declares a tighter scale-aware tolerance. | H11: =ModeloFinanciero!B66-ModeloFinanciero!B126 -> 0 | I11: =ModeloFinanciero!C66-ModeloFinanciero!C126 -> 0 | J11: =ModeloFinanciero!D66-ModeloFinanciero!D126 -> 0 | K11: =ModeloFinanciero!E66-ModeloFinanciero!E126 -> 0 | L11: =ModeloFinanciero!F66-ModeloFinanciero!F126 -> 0
A12: NI_SIGN_SANITY | B12: UNIVERSAL | expected 0; sign convention must be stated in row description. | source applies_to: all 16 | C12: SOURCE_GAP | D12: hard | E12: 1000 USD | F12: 0 | G12: Sign convention diagnostic remains visible; tax-sign taxonomy is not a signed hard-control anchor. | H12: =ModeloFinanciero!B66-(ModeloFinanciero!B62-ABS(ModeloFinanciero!B47)) -> 90668869 | I12: =ModeloFinanciero!C66-(ModeloFinanciero!C62-ABS(ModeloFinanciero!C47)) -> 73516760 | J12: =ModeloFinanciero!D66-(ModeloFinanciero!D62-ABS(ModeloFinanciero!D47)) -> 108026436 | K12: =ModeloFinanciero!E66-(ModeloFinanciero!E62-ABS(ModeloFinanciero!E47)) -> -15774202 | L12: =ModeloFinanciero!F66-(ModeloFinanciero!F62-ABS(ModeloFinanciero!F47)) -> 19032340 | M12: =ModeloFinanciero!G66-(ModeloFinanciero!G62-ABS(ModeloFinanciero!G47)) -> -13510188 | N12: =ModeloFinanciero!H66-(ModeloFinanciero!H62-ABS(ModeloFinanciero!H47)) -> -14614932 | O12: =ModeloFinanciero!I66-(ModeloFinanciero!I62-ABS(ModeloFinanciero!I47)) -> -15807392 | ... Q12: =ModeloFinanciero!K66-(ModeloFinanciero!K62-ABS(ModeloFinanciero!K47)) -> -18483874
A13: RE_ROLLFORWARD | B13: UNIVERSAL | expected 0; hard_tie_tolerance. | source applies_to: all 16 with RE row | C13: KNOWN_RESIDUAL | D13: hard | E13: 1000 USD | F13: -30133213 @ FY24A | G13: G7c retained earnings roll: Reserves/OCI/IFRS transition bridge suspected; signed as visible known residual. | I13: =EEFF!C121-EEFF!B121-(EEFF!C68+EEFF!C177+EEFF!C178+EEFF!C212+EEFF!C213) -> -5392734 | J13: =EEFF!D121-EEFF!C121-(EEFF!D68+EEFF!D177+EEFF!D178+EEFF!D212+EEFF!D213) -> -8076368 | K13: =EEFF!E121-EEFF!D121-(EEFF!E68+EEFF!E177+EEFF!E178+EEFF!E212+EEFF!E213) -> 31091159 | L13: =EEFF!F121-EEFF!E121-(EEFF!F68+EEFF!F177+EEFF!F178+EEFF!F212+EEFF!F213) -> 15653369
A14: EQUITY_TOTAL_TIE | B14: UNIVERSAL | expected 0; hard_tie_tolerance. | source applies_to: all 16 | C14: =IF(SUMPRODUCT((ABS(H14:Q14)>1000)*1)=0,"PASS","FAIL") -> PASS | D14: hard | E14: 1000 USD | F14: 0 | G14: Componentes de patrimonio verificados numéricamente contra EEFF (partición exacta, todos los años hist). | H14: =SUM(ModeloFinanciero!B112,ModeloFinanciero!B113,ModeloFinanciero!B114,ModeloFinanciero!B115,ModeloFinanciero!B116,ModeloFinanciero!B117,ModeloFinanciero!B118,ModeloFinanciero!B120)-ModeloFinanciero!B121 -> 0 | I14: =SUM(ModeloFinanciero!C112,ModeloFinanciero!C113,ModeloFinanciero!C114,ModeloFinanciero!C115,ModeloFinanciero!C116,ModeloFinanciero!C117,ModeloFinanciero!C118,ModeloFinanciero!C120)-ModeloFinanciero!C121 -> 0 | J14: =SUM(ModeloFinanciero!D112,ModeloFinanciero!D113,ModeloFinanciero!D114,ModeloFinanciero!D115,ModeloFinanciero!D116,ModeloFinanciero!D117,ModeloFinanciero!D118,ModeloFinanciero!D120)-ModeloFinanciero!D121 -> 0 | K14: =SUM(ModeloFinanciero!E112,ModeloFinanciero!E113,ModeloFinanciero!E114,ModeloFinanciero!E115,ModeloFinanciero!E116,ModeloFinanciero!E117,ModeloFinanciero!E118,ModeloFinanciero!E120)-ModeloFinanciero!E121 -> 0 | L14: =SUM(ModeloFinanciero!F112,ModeloFinanciero!F113,ModeloFinanciero!F114,ModeloFinanciero!F115,ModeloFinanciero!F116,ModeloFinanciero!F117,ModeloFinanciero!F118,ModeloFinanciero!F120)-ModeloFinanciero!F121 -> 0 | M14: =SUM(ModeloFinanciero!G112,ModeloFinanciero!G113,ModeloFinanciero!G114,ModeloFinanciero!G115,ModeloFinanciero!G116,ModeloFinanciero!G117,ModeloFinanciero!G118,ModeloFinanciero!G120)-ModeloFinanciero!G121 -> 0 | N14: =SUM(ModeloFinanciero!H112,ModeloFinanciero!H113,ModeloFinanciero!H114,ModeloFinanciero!H115,ModeloFinanciero!H116,ModeloFinanciero!H117,ModeloFinanciero!H118,ModeloFinanciero!H120)-ModeloFinanciero!H121 -> 0 | O14: =SUM(ModeloFinanciero!I112,ModeloFinanciero!I113,ModeloFinanciero!I114,ModeloFinanciero!I115,ModeloFinanciero!I116,ModeloFinanciero!I117,ModeloFinanciero!I118,ModeloFinanciero!I120)-ModeloFinanciero!I121 -> 0 | ... Q14: =SUM(ModeloFinanciero!K112,ModeloFinanciero!K113,ModeloFinanciero!K114,ModeloFinanciero!K115,ModeloFinanciero!K116,ModeloFinanciero!K117,ModeloFinanciero!K118,ModeloFinanciero!K120)-ModeloFinanciero!K121 -> 0
A15: BS_LINEITEM_SUM_ASSETS | B15: UNIVERSAL | expected 0; hard_tie_tolerance. | source applies_to: all 16 | C15: =IF(SUMPRODUCT((ABS(H15:Q15)>1000)*1)=0,"PASS","FAIL") -> PASS | D15: hard | E15: 1000 USD | F15: 0 | G15: Partición top-level de activos verificada numéricamente contra EEFF (suma exacta a total de activos, todos los años hist). | H15: =SUM(ModeloFinanciero!B70,ModeloFinanciero!B71,ModeloFinanciero!B72,ModeloFinanciero!B73,ModeloFinanciero!B74,ModeloFinanciero!B75,ModeloFinanciero!B76,ModeloFinanciero!B77,ModeloFinanciero!B78,ModeloFinanciero!B79,ModeloFinanciero!B80,ModeloFinanciero!B81,ModeloFinanciero!B82,ModeloFinanciero!B83,ModeloFinanciero!B84,ModeloFinanciero!B85,ModeloFinanciero!B86,ModeloFinanciero!B87,ModeloFinanciero!B88)-ModeloFinanciero!B89 -> 0 | I15: =SUM(ModeloFinanciero!C70,ModeloFinanciero!C71,ModeloFinanciero!C72,ModeloFinanciero!C73,ModeloFinanciero!C74,ModeloFinanciero!C75,ModeloFinanciero!C76,ModeloFinanciero!C77,ModeloFinanciero!C78,ModeloFinanciero!C79,ModeloFinanciero!C80,ModeloFinanciero!C81,ModeloFinanciero!C82,ModeloFinanciero!C83,ModeloFinanciero!C84,ModeloFinanciero!C85,ModeloFinanciero!C86,ModeloFinanciero!C87,ModeloFinanciero!C88)-ModeloFinanciero!C89 -> 0 | J15: =SUM(ModeloFinanciero!D70,ModeloFinanciero!D71,ModeloFinanciero!D72,ModeloFinanciero!D73,ModeloFinanciero!D74,ModeloFinanciero!D75,ModeloFinanciero!D76,ModeloFinanciero!D77,ModeloFinanciero!D78,ModeloFinanciero!D79,ModeloFinanciero!D80,ModeloFinanciero!D81,ModeloFinanciero!D82,ModeloFinanciero!D83,ModeloFinanciero!D84,ModeloFinanciero!D85,ModeloFinanciero!D86,ModeloFinanciero!D87,ModeloFinanciero!D88)-ModeloFinanciero!D89 -> 0 | K15: =SUM(ModeloFinanciero!E70,ModeloFinanciero!E71,ModeloFinanciero!E72,ModeloFinanciero!E73,ModeloFinanciero!E74,ModeloFinanciero!E75,ModeloFinanciero!E76,ModeloFinanciero!E77,ModeloFinanciero!E78,ModeloFinanciero!E79,ModeloFinanciero!E80,ModeloFinanciero!E81,ModeloFinanciero!E82,ModeloFinanciero!E83,ModeloFinanciero!E84,ModeloFinanciero!E85,ModeloFinanciero!E86,ModeloFinanciero!E87,ModeloFinanciero!E88)-ModeloFinanciero!E89 -> 0 | L15: =SUM(ModeloFinanciero!F70,ModeloFinanciero!F71,ModeloFinanciero!F72,ModeloFinanciero!F73,ModeloFinanciero!F74,ModeloFinanciero!F75,ModeloFinanciero!F76,ModeloFinanciero!F77,ModeloFinanciero!F78,ModeloFinanciero!F79,ModeloFinanciero!F80,ModeloFinanciero!F81,ModeloFinanciero!F82,ModeloFinanciero!F83,ModeloFinanciero!F84,ModeloFinanciero!F85,ModeloFinanciero!F86,ModeloFinanciero!F87,ModeloFinanciero!F88)-ModeloFinanciero!F89 -> 0 | M15: =SUM(ModeloFinanciero!G70,ModeloFinanciero!G71,ModeloFinanciero!G72,ModeloFinanciero!G73,ModeloFinanciero!G74,ModeloFinanciero!G75,ModeloFinanciero!G76,ModeloFinanciero!G77,ModeloFinanciero!G78,ModeloFinanciero!G79,ModeloFinanciero!G80,ModeloFinanciero!G81,ModeloFinanciero!G82,ModeloFinanciero!G83,ModeloFinanciero!G84,ModeloFinanciero!G85,ModeloFinanciero!G86,ModeloFinanciero!G87,ModeloFinanciero!G88)-ModeloFinanciero!G89 -> 0 | N15: =SUM(ModeloFinanciero!H70,ModeloFinanciero!H71,ModeloFinanciero!H72,ModeloFinanciero!H73,ModeloFinanciero!H74,ModeloFinanciero!H75,ModeloFinanciero!H76,ModeloFinanciero!H77,ModeloFinanciero!H78,ModeloFinanciero!H79,ModeloFinanciero!H80,ModeloFinanciero!H81,ModeloFinanciero!H82,ModeloFinanciero!H83,ModeloFinanciero!H84,ModeloFinanciero!H85,ModeloFinanciero!H86,ModeloFinanciero!H87,ModeloFinanciero!H88)-ModeloFinanciero!H89 -> 0 | O15: =SUM(ModeloFinanciero!I70,ModeloFinanciero!I71,ModeloFinanciero!I72,ModeloFinanciero!I73,ModeloFinanciero!I74,ModeloFinanciero!I75,ModeloFinanciero!I76,ModeloFinanciero!I77,ModeloFinanciero!I78,ModeloFinanciero!I79,ModeloFinanciero!I80,ModeloFinanciero!I81,ModeloFinanciero!I82,ModeloFinanciero!I83,ModeloFinanciero!I84,ModeloFinanciero!I85,ModeloFinanciero!I86,ModeloFinanciero!I87,ModeloFinanciero!I88)-ModeloFinanciero!I89 -> 0 | ... Q15: =SUM(ModeloFinanciero!K70,ModeloFinanciero!K71,ModeloFinanciero!K72,ModeloFinanciero!K73,ModeloFinanciero!K74,ModeloFinanciero!K75,ModeloFinanciero!K76,ModeloFinanciero!K77,ModeloFinanciero!K78,ModeloFinanciero!K79,ModeloFinanciero!K80,ModeloFinanciero!K81,ModeloFinanciero!K82,ModeloFinanciero!K83,ModeloFinanciero!K84,ModeloFinanciero!K85,ModeloFinanciero!K86,ModeloFinanciero!K87,ModeloFinanciero!K88)-ModeloFinanciero!K89 -> 0
A16: BS_LINEITEM_SUM_LIAB_EQUITY | B16: UNIVERSAL | expected 0; hard_tie_tolerance. | source applies_to: all 16 | C16: SOURCE_GAP | D16: hard | E16: 1000 USD | F16: 0 | G16: Financial-issuer liability/equity component taxonomy is visible but not signed as a hard lineitem-sum control. | H16: =ModeloFinanciero!B111+ModeloFinanciero!B121-ModeloFinanciero!B122 -> -2137495289 | I16: =ModeloFinanciero!C111+ModeloFinanciero!C121-ModeloFinanciero!C122 -> -2294825394 | J16: =ModeloFinanciero!D111+ModeloFinanciero!D121-ModeloFinanciero!D122 -> -2377500871 | K16: =ModeloFinanciero!E111+ModeloFinanciero!E121-ModeloFinanciero!E122 -> 0 | L16: =ModeloFinanciero!F111+ModeloFinanciero!F121-ModeloFinanciero!F122 -> 0 | M16: =ModeloFinanciero!G111+ModeloFinanciero!G121-ModeloFinanciero!G122 -> 0 | N16: =ModeloFinanciero!H111+ModeloFinanciero!H121-ModeloFinanciero!H122 -> 0 | O16: =ModeloFinanciero!I111+ModeloFinanciero!I121-ModeloFinanciero!I122 -> 0 | ... Q16: =ModeloFinanciero!K111+ModeloFinanciero!K121-ModeloFinanciero!K122 -> 0
A17: SOURCE_TIE_HISTORICAL | B17: UNIVERSAL | expected 0 for audited rows; SOURCE_GAP/WARN allowed only with explicit source-gap note. | source applies_to: all 16 | C17: =IF(SUMPRODUCT((ABS(H17:Q17)>100000)*1)=0,"PASS","FAIL") -> PASS | D17: hard | E17: 100000 USD | F17: 0 | G17: Audited rows tie to 0; only bank ending-cash-vs-EEFF cash rows may use the observed $100,000 hard threshold; SOURCE_GAP/WARN requires explicit source-gap note. | H17: =ModeloFinanciero!B89-EEFF!B92 -> 0 | I17: =ModeloFinanciero!C89-EEFF!C92 -> 0 | J17: =ModeloFinanciero!D89-EEFF!D92 -> 0 | K17: =ModeloFinanciero!E89-EEFF!E92 -> 0 | L17: =ModeloFinanciero!F89-EEFF!F92 -> 0
A18: NO_FORMULA_ERRORS | B18: UNIVERSAL | expected PASS/0; no masking. | source applies_to: all 16 | C18: =IF(SUMPRODUCT((ABS(H18:Q18)>0)*1)=0,"PASS","FAIL") -> PASS | D18: hard | E18: PASS | F18: PASS | G18: expected PASS/0; no masking. | H18: =0 -> 0 | I18: =0 -> 0 | J18: =0 -> 0 | K18: =0 -> 0 | L18: =0 -> 0 | M18: =0 -> 0 | N18: =0 -> 0 | O18: =0 -> 0 | ... Q18: =0 -> 0
A19: NO_CHECKS_MASTER_FAIL | B19: UNIVERSAL | expected PASS; status row should cite included/excluded rows. | source applies_to: all 16 | C19: =IF(SUMPRODUCT((ABS(H19:Q19)>0)*1)=0,"PASS","FAIL") -> PASS | D19: hard | E19: PASS | F19: PASS | G19: expected PASS; status row should cite included/excluded rows. | H19: =COUNTIF($C$6:$C$18,"FAIL")+COUNTIF($C$20:$C$35,"FAIL") -> 0 | I19: =COUNTIF($C$6:$C$18,"FAIL")+COUNTIF($C$20:$C$35,"FAIL") -> 0 | J19: =COUNTIF($C$6:$C$18,"FAIL")+COUNTIF($C$20:$C$35,"FAIL") -> 0 | K19: =COUNTIF($C$6:$C$18,"FAIL")+COUNTIF($C$20:$C$35,"FAIL") -> 0 | L19: =COUNTIF($C$6:$C$18,"FAIL")+COUNTIF($C$20:$C$35,"FAIL") -> 0 | M19: =COUNTIF($C$6:$C$18,"FAIL")+COUNTIF($C$20:$C$35,"FAIL") -> 0 | N19: =COUNTIF($C$6:$C$18,"FAIL")+COUNTIF($C$20:$C$35,"FAIL") -> 0 | O19: =COUNTIF($C$6:$C$18,"FAIL")+COUNTIF($C$20:$C$35,"FAIL") -> 0 | ... Q19: =COUNTIF($C$6:$C$18,"FAIL")+COUNTIF($C$20:$C$35,"FAIL") -> 0
A21: CONDITIONAL CHECKS
A22: LEASE_SCHEDULE_TIE | B22: ARCHETYPE/conditional | expected 0; hard_tie_tolerance. | source applies_to: IFRS-16 issuers | C22: SOURCE_GAP | D22: hard | E22: 1000 USD | F22: 0 | G22: No semantic anchors resolved for LEASE_SCHEDULE_TIE. | H22: =0 -> 0 | I22: =0 -> 0 | J22: =0 -> 0 | K22: =0 -> 0 | L22: =0 -> 0 | M22: =0 -> 0 | N22: =0 -> 0 | O22: =0 -> 0 | ... Q22: =0 -> 0
A24: INSURANCE CHECKS
A25: INSURANCE_PREMIUM_DRIVER_TIE | B25: ARCHETYPE | expected 0; not observed in this sweep, but template requires premium wiring. | source applies_to: insurance | C25: =IF(SUMPRODUCT((ABS(H25:Q25)>1000)*1)=0,"PASS","FAIL") -> PASS | D25: hard | E25: 1000 USD | F25: 0 | G25: expected 0; not observed in this sweep, but template requires premium wiring. Default full-USD hard tie threshold is $1,000 unless the workbook declares a tighter scale-aware tolerance. | K25: =Premiums_Claims!E35 -> 0 | L25: =Premiums_Claims!F35 -> 0 | M25: =ModeloFinanciero!G48-Premiums_Claims!G39 -> 0 | N25: =ModeloFinanciero!H48-Premiums_Claims!H39 -> 0 | O25: =ModeloFinanciero!I48-Premiums_Claims!I39 -> 0 | P25: =ModeloFinanciero!J48-Premiums_Claims!J39 -> 0 | Q25: =ModeloFinanciero!K48-Premiums_Claims!K39 -> 0
A26: INSURANCE_TECHNICAL_RESERVE_TIE | B26: ARCHETYPE | expected 0; not observed in this sweep. | source applies_to: insurance | C26: =IF(SUMPRODUCT((ABS(H26:Q26)>1000)*1)=0,"PASS","FAIL") -> PASS | D26: hard | E26: 1000 USD | F26: 0 | G26: expected 0; not observed in this sweep. Default full-USD hard tie threshold is $1,000 unless the workbook declares a tighter scale-aware tolerance. | K26: =Claims_Reserves!E35 -> 0 | L26: =Claims_Reserves!F35 -> 0
A27: ACCOUNTING_BASIS_SWITCH_TIE | B27: ARCHETYPE | 1 si un mismo año histórico trae valor en ambas bases (legacy primas retenidas y NIIF17 ingresos de servicio); esperado 0 en B:F. | applies_to: insurance | C27: =IF(SUMPRODUCT((ABS(H27:Q27)>1000)*1)=0,"PASS","FAIL") -> PASS | D27: hard | E27: 1000 USD | F27: 0 | G27: expected 0; hard tie threshold $1,000 full-USD. | H27: =Premiums_Claims!B12 -> 0 | I27: =Premiums_Claims!C12 -> 0 | J27: =Premiums_Claims!D12 -> 0 | K27: =Premiums_Claims!E12 -> 0 | L27: =Premiums_Claims!F12 -> 0
A28: IFRS17_SERVICE_RESULT_TIE | B28: ARCHETYPE | resultado del servicio computado (ingresos + gastos + reaseguro) − subtotal auditado EEFF; esperado 0. | applies_to: insurance | C28: =IF(SUMPRODUCT((ABS(H28:Q28)>1000)*1)=0,"PASS","FAIL") -> PASS | D28: hard | E28: 1000 USD | F28: 0 | G28: expected 0; hard tie threshold $1,000 full-USD. | H28: =Premiums_Claims!B44 -> 0 | I28: =Premiums_Claims!C44 -> 0 | J28: =Premiums_Claims!D44 -> 0 | K28: =Premiums_Claims!E44 -> 0 | L28: =Premiums_Claims!F44 -> 0
A29: IFRS17_FINANCE_RESULT_TIE | B29: ARCHETYPE | resultado financiero computado (retorno inversiones + finanzas seguro + finanzas reaseguro) − subtotal auditado EEFF; esperado 0. | applies_to: insurance | C29: =IF(SUMPRODUCT((ABS(H29:Q29)>1000)*1)=0,"PASS","FAIL") -> PASS | D29: hard | E29: 1000 USD | F29: 0 | G29: expected 0; hard tie threshold $1,000 full-USD. | H29: =Premiums_Claims!B56 -> 0 | I29: =Premiums_Claims!C56 -> 0 | J29: =Premiums_Claims!D56 -> 0 | K29: =Premiums_Claims!E56 -> 0 | L29: =Premiums_Claims!F56 -> 0
A30: REINSURANCE_CONTRACT_BALANCE_TIE | B30: ARCHETYPE | saldo neto de contratos de reaseguro Nota 20 + (activo EEFF − pasivo EEFF); esperado 0 (convención de signos opuesta documentada). | applies_to: insurance | C30: =IF(SUMPRODUCT((ABS(H30:Q30)>1000)*1)=0,"PASS","FAIL") -> PASS | D30: hard | E30: 1000 USD | F30: 0 | G30: expected 0; hard tie threshold $1,000 full-USD. | K30: =Claims_Reserves!E49 -> 0 | L30: =Claims_Reserves!F49 -> 0
A31: LIFE_CSM_RA_PVFCF_TIE | B31: ARCHETYPE | roll-forward de componentes vida (PVFCF + ajuste de riesgo + CSM) computado − cierre verbatim tbl-72; esperado 0 (FY2025; tbl-73 FY2024 OCR_REVIEW_REQUIRED). | applies_to: insurance | C31: =IF(SUMPRODUCT((ABS(H31:Q31)>1000)*1)=0,"PASS","FAIL") -> PASS | D31: hard | E31: 1000 USD | F31: 0 | G31: expected 0; hard tie threshold $1,000 full-USD. | L31: =Claims_Reserves!F80 -> 0
A32: INVESTMENT_PORTFOLIO_TIE | B32: ARCHETYPE | Σ categorías de instrumentos (tbl-57/58) − total verbatim − EEFF BS instrumentos; esperado 0. | applies_to: insurance | C32: =IF(SUMPRODUCT((ABS(H32:Q32)>1000)*1)=0,"PASS","FAIL") -> PASS | D32: hard | E32: 1000 USD | F32: 0 | G32: expected 0; hard tie threshold $1,000 full-USD. | K32: =Investments!E18 -> 0 | L32: =Investments!F18 -> 0
A33: INVESTMENT_FLOAT_YIELD_TIE | B33: ARCHETYPE | Σ componentes de retorno asignados (mix FY25) − retorno forecast total (base promedio × yield); esperado 0 en años forecast. | applies_to: insurance | C33: =IF(SUMPRODUCT((ABS(H33:Q33)>1000)*1)=0,"PASS","FAIL") -> PASS | D33: hard | E33: 1000 USD | F33: 0 | G33: expected 0; hard tie threshold $1,000 full-USD. | M33: =Investment_Float!G28 -> 0 | N33: =Investment_Float!H28 -> 0 | O33: =Investment_Float!I28 -> 0 | P33: =Investment_Float!J28 -> 0 | Q33: =Investment_Float!K28 -> 0
A34: SOLVENCY_DISCLOSURE_GATE | B34: ARCHETYPE | gate documental: SCR/capital disponible/requerido numérico solo con fuente (filing o SSRP con URL+fecha); compliance cualitativo divulgado en el filing (2025 y 2024 todas las subsidiarias cumplieron). NUNCA se inventa un ratio. | applies_to: insurance | C34: SOURCE_GAP | D34: report_only | E34: PASS | F34: NOT_DISCLOSED | G34: Gate documental: compliance cualitativo divulgado (2025/2024 todas las subsidiarias cumplieron; ver Solvency_Capital A). SCR numérico NOT_DISCLOSED; solo entra con fuente filing/SSRP citada (URL+fecha). | H34: =0 -> 0 | I34: =0 -> 0 | J34: =0 -> 0 | K34: =0 -> 0 | L34: =0 -> 0 | M34: =0 -> 0 | N34: =0 -> 0 | O34: =0 -> 0 | ... Q34: =0 -> 0
A35: ACCOUNTING_BASIS_BRIDGE_TIE | B35: ASSA | cambio de base SSRP→NIIF 17: puente amarra contra ambos filings | source: Puente_NIIF17 | C35: =IF(SUMPRODUCT((ABS(H35:Q35)>1)*1)=0,"PASS","FAIL") -> PASS | D35: hard | E35: 1 USD | F35: 0 @ FY24A | G35: Conciliación del cambio de base contable SSRP→NIIF 17 (transición 1-ene-2024): suma de residuales absolutos de las 4 verificaciones locales de Puente_NIIF17 (Δ balance dual, walk de transición, amarre base vieja, rodamiento re-expresado). Esperado 0; ties exactos del filing — hard fail si ABS > 1 USD. | K35: =ABS(Puente_NIIF17!D12)+ABS(Puente_NIIF17!B19)+ABS(Puente_NIIF17!B21)+ABS(Puente_NIIF17!B29) -> 0

Sheet Source_Register
A1: Grupo ASSA, S. A.
A2: Source_Register — insurance archetype. Every row traces to a published filing (OCR text) or to a working file kept by the maintainer.
A3: Status semantics: OK = citation resolved to an existing artifact. SOURCE_GAP = traceability missing (visible, not hidden). NOT_DISCLOSED = no registration/manifest found for this issuer.
A4: source_id | B4: kind | C4: ticker | D4: filing | E4: year | F4: nota | G4: tabla_ocr | H4: feeds_sheet | I4: feeds_anchor | J4: date | K4: status | L4: evidence_count | M4: note
A5: OCR_ROOT:assa | B5: OCR_ROOT | C5: ASSA | H5: EEFF; Notas_EEFF | I5: OCR of the published filings | J5: NOT_DISCLOSED | K5: OK | L5: 1 | M5: Annual reports (INA) of assa
A6: EEFF_FILING:ina_assa_2021_0 | B6: EEFF_FILING | C6: ASSA | D6: INA_ASSA_2021_0.pdf | E6: 2021 | G6: markdown.md | H6: EEFF; Notas_EEFF; MD&A | I6: 00-index.md; 01-eeff.md; 02-notas.md; 03-mda.md; 09-otros.md | J6: FY21 (A) | K6: OK | L6: 157 | M6: markdown.md sha256=bf5c0ba4ba93481a...
A7: EEFF_FILING:ina_assa_2022_0 | B7: EEFF_FILING | C7: ASSA | D7: INA_ASSA_2022_0.pdf | E7: 2022 | G7: markdown.md | H7: EEFF; Notas_EEFF; MD&A | I7: 00-index.md; 01-eeff.md; 02-notas.md; 03-mda.md; 09-otros.md | J7: FY22 (A) | K7: OK | L7: 160 | M7: markdown.md sha256=5eaaa3d45f43123e...
A8: EEFF_FILING:ina_assa_2023_0 | B8: EEFF_FILING | C8: ASSA | D8: INA_ASSA_2023_0.pdf | E8: 2023 | G8: markdown.md | H8: EEFF; Notas_EEFF; MD&A | I8: 00-index.md; 01-eeff.md; 02-notas.md; 03-mda.md; 09-otros.md | J8: FY23 (A) | K8: OK | L8: 158 | M8: markdown.md sha256=61d6c6094fa0dba5...
A9: EEFF_FILING:ina_assa_2024_0 | B9: EEFF_FILING | C9: ASSA | D9: INA_ASSA_2024_0.pdf | E9: 2024 | G9: markdown.md | H9: EEFF; Notas_EEFF; MD&A | I9: 00-index.md; 01-eeff.md; 02-notas.md; 03-mda.md; 09-otros.md | J9: FY24 (A) | K9: OK | L9: 168 | M9: markdown.md sha256=2876f03a6d3b50aa...
A10: EEFF_FILING:ina_assa_2025_0 | B10: EEFF_FILING | C10: ASSA | D10: INA_ASSA_2025_0.pdf | E10: 2025 | G10: markdown.md | H10: EEFF; Notas_EEFF; MD&A | I10: 00-index.md; 01-eeff.md; 02-notas.md; 03-mda.md; 09-otros.md | J10: FY25 (A) | K10: OK | L10: 165 | M10: markdown.md sha256=41280413ecbfaca9...
A11: NOTA:INA_ASSA_2021_0.pdf#10 | B11: NOTA | C11: ASSA | D11: INA_ASSA_2021_0.pdf | E11: 2021 | F11: 10 | G11: markdown.md; tbl-38.html | H11: Notas_EEFF | I11: 10. Inmuebles, mobiliario, equipo y mejoras, neto | J11: FY21 (A) | K11: OK | L11: 3
A12: NOTA:INA_ASSA_2021_0.pdf#11 | B12: NOTA | C12: ASSA | D12: INA_ASSA_2021_0.pdf | E12: 2021 | F12: 11 | G12: markdown.md; tbl-40.html | H12: Notas_EEFF | I12: 11. Activos por derecho de uso, netos | J12: FY21 (A) | K12: OK | L12: 2
A13: NOTA:INA_ASSA_2021_0.pdf#12 | B13: NOTA | C13: ASSA | D13: INA_ASSA_2021_0.pdf | E13: 2021 | F13: 12 | G13: markdown.md; tbl-41.html; tbl-42.html; +2 more | H13: Notas_EEFF | I13: 12. Activos intangibles y plusvalía | J13: FY21 (A) | K13: OK | L13: 11
A14: NOTA:INA_ASSA_2021_0.pdf#13 | B14: NOTA | C14: ASSA | D14: INA_ASSA_2021_0.pdf | E14: 2021 | F14: 13 | G14: markdown.md; tbl-45.html; tbl-46.html; +5 more | H14: Notas_EEFF | I14: 13. Provisiones de los contratos de seguros | J14: FY21 (A) | K14: OK | L14: 36
A15: NOTA:INA_ASSA_2021_0.pdf#14 | B15: NOTA | C15: ASSA | D15: INA_ASSA_2021_0.pdf | E15: 2021 | F15: 14 | G15: markdown.md; tbl-52.html; tbl-53.html; +2 more | H15: Notas_EEFF | I15: 14. Emisiones de deuda y obligaciones | J15: FY21 (A) | K15: OK | L15: 18
A16: NOTA:INA_ASSA_2021_0.pdf#15 | B16: NOTA | C16: ASSA | D16: INA_ASSA_2021_0.pdf | E16: 2021 | F16: 15 | G16: markdown.md; tbl-56.html; tbl-57.html | H16: Notas_EEFF | I16: 15. Obligaciones subordinadas | J16: FY21 (A) | K16: OK | L16: 6
A17: NOTA:INA_ASSA_2021_0.pdf#16 | B17: NOTA | C17: ASSA | D17: INA_ASSA_2021_0.pdf | E17: 2021 | F17: 16 | G17: markdown.md; tbl-58.html | H17: Notas_EEFF | I17: 16. Pasivos por arrendamientos | J17: FY21 (A) | K17: OK | L17: 2
A18: NOTA:INA_ASSA_2021_0.pdf#17 | B18: NOTA | C18: ASSA | D18: INA_ASSA_2021_0.pdf | E18: 2021 | F18: 17 | G18: markdown.md; tbl-59.html | H18: Notas_EEFF | I18: 17. Otros pasivos | J18: FY21 (A) | K18: OK | L18: 2
A19: NOTA:INA_ASSA_2021_0.pdf#18 | B19: NOTA | C19: ASSA | D19: INA_ASSA_2021_0.pdf | E19: 2021 | F19: 18 | G19: markdown.md; tbl-60.html; tbl-61.html | H19: Notas_EEFF | I19: 18. Capital | J19: FY21 (A) | K19: OK | L19: 10
A20: NOTA:INA_ASSA_2021_0.pdf#19 | B20: NOTA | C20: ASSA | D20: INA_ASSA_2021_0.pdf | E20: 2021 | F20: 19 | G20: markdown.md; tbl-62.html; tbl-63.html | H20: Notas_EEFF | I20: 19. Participación no controladora | J20: FY21 (A) | K20: OK | L20: 4
A21: NOTA:INA_ASSA_2021_0.pdf#20 | B21: NOTA | C21: ASSA | D21: INA_ASSA_2021_0.pdf | E21: 2021 | F21: 20 | G21: markdown.md; tbl-64.html | H21: Notas_EEFF | I21: 20. Primas netas ganadas | J21: FY21 (A) | K21: OK | L21: 2
A22: NOTA:INA_ASSA_2021_0.pdf#21 | B22: NOTA | C22: ASSA | D22: INA_ASSA_2021_0.pdf | E22: 2021 | F22: 21 | G22: markdown.md; tbl-65.html | H22: Notas_EEFF | I22: 21. Reclamos y beneficios netos incurridos | J22: FY21 (A) | K22: OK | L22: 2
... A135: NOTA:INA_ASSA_2025_0.pdf#9 | B135: NOTA | C135: ASSA | D135: INA_ASSA_2025_0.pdf | E135: 2025 | F135: 9 | G135: markdown.md; tbl-28.html; tbl-29.html; +3 more | H135: Notas_EEFF | I135: 9. Información por segmentos | J135: FY25 (A) | K135: OK | L135: 18
A136: DRIVER:EEFF:Gastos generales y administrativos | B136: DRIVER_EEFF | C136: ASSA | H136: Supuestos | I136: Gastos generales y administrativos — driver activo | J136: NOT_DISCLOSED | K136: OK | L136: 4 | M136: Gastos generales y administrativos
A137: DRIVER:EEFF:Gastos generales y administrativos; EEFF:Ingresos por servicios de seguro | B137: DRIVER_EEFF | C137: ASSA | H137: Supuestos | I137: G&A ÷ ingreso (hist; B:D legacy s/primas retenidas, E:F NIIF17 s/ingreso servicio) | J137: NOT_DISCLOSED | K137: OK | L137: 1 | M137: Gastos generales y administrativos; EEFF:Ingresos por servicios de seguro
A138: DRIVER:EEFF:Gastos por servicios de seguro | B138: DRIVER_EEFF | C138: ASSA | H138: Supuestos | I138: Gastos por servicios de seguro — driver activo (ratio negativo) | J138: NOT_DISCLOSED | K138: OK | L138: 4 | M138: Gastos por servicios de seguro
A139: DRIVER:EEFF:Gastos por servicios de seguro; EEFF:Ingresos por servicios de seguro | B139: DRIVER_EEFF | C139: ASSA | H139: Supuestos | I139: Gasto ÷ ingreso (hist; B:D legacy reclamos s/primas, E:F NIIF17 gasto servicio s/ingreso servicio) | J139: NOT_DISCLOSED | K139: OK | L139: 1 | M139: Gastos por servicios de seguro; EEFF:Ingresos por servicios de seguro
A140: DRIVER:EEFF:Ingresos por servicios de seguro | B140: DRIVER_EEFF | C140: ASSA | H140: Supuestos | I140: Ingresos por servicios de seguro — driver activo (base NIIF 17) | J140: NOT_DISCLOSED | K140: OK | L140: 6 | M140: Ingresos por servicios de seguro
A141: INSURANCE_SCHEDULE:Premiums_Claims | B141: INSURANCE_SCHEDULE | C141: ASSA | H141: Premiums_Claims | I141: a working file kept by the maintainer | J141: NOT_DISCLOSED | K141: OK | L141: 68 | M141: Hechos verbatim citados por bloque dentro de la hoja (mirror OCR tbl-35/57/58/61/68-72, Nota 20/23, MD&A); refs EEFF vivas resueltas por label.
A142: INSURANCE_SCHEDULE:Claims_Reserves | B142: INSURANCE_SCHEDULE | C142: ASSA | H142: Claims_Reserves | I142: a working file kept by the maintainer | J142: NOT_DISCLOSED | K142: OK | L142: 94 | M142: Hechos verbatim citados por bloque dentro de la hoja (mirror OCR tbl-35/57/58/61/68-72, Nota 20/23, MD&A); refs EEFF vivas resueltas por label.
A143: INSURANCE_SCHEDULE:Reinsurance | B143: INSURANCE_SCHEDULE | C143: ASSA | H143: Reinsurance | I143: a working file kept by the maintainer | J143: NOT_DISCLOSED | K143: OK | L143: 38 | M143: Hechos verbatim citados por bloque dentro de la hoja (mirror OCR tbl-35/57/58/61/68-72, Nota 20/23, MD&A); refs EEFF vivas resueltas por label.
A144: INSURANCE_SCHEDULE:Investments | B144: INSURANCE_SCHEDULE | C144: ASSA | H144: Investments | I144: a working file kept by the maintainer | J144: NOT_DISCLOSED | K144: OK | L144: 60 | M144: Hechos verbatim citados por bloque dentro de la hoja (mirror OCR tbl-35/57/58/61/68-72, Nota 20/23, MD&A); refs EEFF vivas resueltas por label.
A145: INSURANCE_SCHEDULE:Investment_Float | B145: INSURANCE_SCHEDULE | C145: ASSA | H145: Investment_Float | I145: a working file kept by the maintainer | J145: NOT_DISCLOSED | K145: OK | L145: 30 | M145: Hechos verbatim citados por bloque dentro de la hoja (mirror OCR tbl-35/57/58/61/68-72, Nota 20/23, MD&A); refs EEFF vivas resueltas por label.
A146: INSURANCE_SCHEDULE:Solvency_Capital | B146: INSURANCE_SCHEDULE | C146: ASSA | H146: Solvency_Capital | I146: a working file kept by the maintainer | J146: NOT_DISCLOSED | K146: OK | L146: 40 | M146: Hechos verbatim citados por bloque dentro de la hoja (mirror OCR tbl-35/57/58/61/68-72, Nota 20/23, MD&A); refs EEFF vivas resueltas por label.
A147: INSURANCE_SCHEDULE:Unit_Economics | B147: INSURANCE_SCHEDULE | C147: ASSA | H147: Unit_Economics | I147: a working file kept by the maintainer | J147: NOT_DISCLOSED | K147: OK | L147: 69 | M147: Hechos verbatim citados por bloque dentro de la hoja (mirror OCR tbl-35/57/58/61/68-72, Nota 20/23, MD&A); refs EEFF vivas resueltas por label.
... A158: REGULATORY_WEB:MEMORIA_ASSA_2025_BVPS | B158: REGULATORY_WEB | C158: ASSA | H158: Valuation | I158: https://fliphtml5.com/FLBOOK/Mayo-20_Memoria-ASSA_FINAL_2025/ | J158: 46210 | K158: OK | L158: 1 | M158: Memoria ASSA 2025: valor en libros por acción US$154.49 al 31-dic-2025; P/B 0.82x; 147,864 acciones transadas por US$16M en 2025.

Sheet _CHANGELOG
A1: Grupo ASSA, S. A.
A2: _CHANGELOG — generation record for assa.
A3: Internal build history omitted from the public export. Record public changes below.

Sheet Claude Code Log
A1: Turn # | B1: Date | C1: User Request | D1: Action Taken | E1: Details | F1: Outcome
A2: 1 | B2: 46324.359 | C2: Prepare a public model copy | D2: Remove local paths and private build references; preserve financial formulas and inputs | E2: Agent run with MOG as the tool, checked by guard v1. The guard measured every sheet before and after the run. Changed: Notas_EEFF: 1 cell written, at A3; Premiums_Claims: 3 cells written, at A8, A17, A38; Claims_Reserves: 6 cells written, at A17, A51, A57, A65, A66, A92; Reinsurance: 2 cells written, at A3, A9; Investments: 2 cells written, at A3, A57; Solvency_Capital: 4 cells written, at A3, A10, A17, A28; Valuation: 2 cells written, at A3, A10; _CHECKS: 1 cell written, at G12; Source_Register: 12 cells written, at A2, I5, M5, I141, I142, I143, I144, I145, I146, I147, I148, I149; _CHANGELOG: data A1:H33 -> A1:A3 (rows 33 -> 3, columns 8 -> 1), 205 cells written, at A2, A3, B3, C3, D3, E3, F3, G3, H3, A4, B4, C4, D4, E4, F4 and 190 more. Other actions: clear x1. Agent: OpenFinmods export | F2: Compare against source and review public copy
