Workbook

Sheet EEFF
A1: UEP Penonomé II, S. A.
A2: Estados Financieros Auditados FY21-FY25
A3: en US$ sin escala
A5: Años | B5: FY21A | C5: FY22A | D5: FY23A | E5: FY24A | F5: FY25A | G5: FY26E | H5: FY27E | I5: FY28E | J5: FY29E | K5: FY30E
A6: Estado de Resultado
A7: Ingresos por energía | B7: 42036085 | C7: 40987418 | D7: 54587421 | E7: 42653811 | F7: 42404701
A8: Costos de bienes y servicios | B8: -22857327 | C8: -21858853 | D8: -25573871 | E8: -25736347 | F8: -24413955
A9: Utilidad bruta | B9: 19178758 | C9: 19128565 | D9: 29013550 | E9: 16917464 | F9: 17990746
A10: Gastos administrativos | B10: -3266942 | C10: -3405988 | D10: -4482435 | E10: -3436087 | F10: -3908720
A11: Utilidad operativa | B11: 15911816 | C11: 15722577 | D11: 24531115 | E11: 13481377 | F11: 14082026
A12: Costos financieros, neto | B12: -14126147 | C12: -9881077 | D12: -16142876 | E12: -15193459 | F12: -14336109
A13: Otros ingresos | B13: 34397 | C13: 130429 | D13: 6770 | E13: 1010 | F13: 81975
A14: Pérdida antes del impuesto sobre la renta | B14: 1820066 | C14: 5971929 | D14: 8395009 | E14: -1711072 | F14: -172108
A15: Impuesto sobre la renta | B15: -2683428 | C15: 599370 | D15: -820467 | E15: -681267 | F15: -497187
A16: Pérdida del año | B16: -863362 | C16: 6571299 | D16: 7574542 | E16: -2392339 | F16: -669295
A18: Años | B18: FY21A | C18: FY22A | D18: FY23A | E18: FY24A | F18: FY25A | G18: FY26E | H18: FY27E | I18: FY28E | J18: FY29E | K18: FY30E
A19: Balance General
A20: Efectivo y equivalentes de efectivo | B20: 5485501 | C20: 5490195 | D20: 17396949 | E20: 4118908 | F20: 5197344
A21: Deudores comerciales y otras cuentas por cobrar | B21: 8440721 | C21: 6989164 | D21: 7127866 | E21: 3904545 | F21: 4837614
A22: Deuda por cobrar a parte relacionada | B22: 898932 | C22: 996982 | D22: 1138080 | E22: 1239674 | F22: 1332322
A23: Gastos pagados por adelantado | B23: 1954336 | C23: 4991808 | D23: 1291507 | E23: 1963129 | F23: 860787
A24: Inventario | B24: 38791 | C24: 40685 | D24: 51726 | E24: 71702 | F24: 84203
A25: Total de activos corrientes | B25: 16818281 | C25: 18508834 | D25: 27006128 | E25: 11297958 | F25: 12312270
A26: Planta y equipo, neto | B26: 216209163 | C26: 202848696 | D26: 193996920 | E26: 180311071 | F26: 167298071
A27: Plusvalía | B27: 20000000 | C27: 20000000 | D27: 20000000 | E27: 20000000 | F27: 20000000
A28: Deuda por cobrar a parte relacionada | B28: 21480114 | C28: 20483131 | D28: 19345052 | E28: 18105378 | F28: 16773057
A29: Activos intangibles, neto | B29: 109685 | C29: 105268 | D29: 100851 | E29: 96435 | F29: 92018
A30: Fondo de cesantía | C30: 13934 | D30: 17359 | E30: 21782 | F30: 26510
A31: Total de activos no corrientes | B31: 257798962 | C31: 243451029 | D31: 233460182 | E31: 218534666 | F31: 204189656
A32: Total de activos | B32: 274617243 | C32: 261959863 | D32: 260466310 | E32: 229832624 | F32: 216501926
A33: Bonos por pagar | B33: 14299859 | C33: 15240126 | D33: 16627445 | E33: 17584115 | F33: 18400181
A34: Proveedores y otras cuentas por pagar | B34: 2652919 | C34: 1285733 | D34: 2536737 | E34: 1419947 | F34: 2311149
A35: Pasivos por arrendamiento | B35: 157731 | C35: 192094 | D35: 229888 | E35: 271410 | F35: 316983
A36: Total de pasivos corrientes | B36: 17110509 | C36: 16717953 | D36: 19394070 | E36: 19275472 | F36: 21028313
A37: Pasivos por arrendamiento | B37: 8232437 | C37: 8040342 | D37: 7810454 | E37: 7539044 | F37: 7222062
A38: Impuesto sobre la renta diferido | B38: 1204764 | C38: 605394 | D38: 1425861 | E38: 2107128 | F38: 2604315
A39: Provisiones | B39: 0 | C39: 347922 | D39: 374016 | E39: 402067 | F39: 432222
A40: Bonos por pagar | B40: 234949078 | C40: 224181572 | D40: 211820687 | E40: 198290030 | F40: 183665429
A41: Instrumento financiero derivado | B41: 7625074
A42: Total de pasivos no corrientes | B42: 252011353 | C42: 233175230 | D42: 221431018 | E42: 208338269 | F42: 193924028
A43: Total de pasivos | B43: 269121862 | C43: 249893183 | D43: 240825088 | E43: 227613741 | F43: 214952341
A44: Acciones comunes con un valor nominal de US$1 cada una; autorizadas y emitidas: 1,050 acciones | B44: 1050 | C44: 1050 | D44: 1050 | E44: 1050 | F44: 1050
A45: Contribución de capital | B45: 55974250 | C45: 55974250 | D45: 55974250 | E45: 48518792 | F45: 48518792
A46: Déficit acumulado | B46: -50345915 | C46: -43774616 | D46: -36200074 | E46: -46166955 | F46: -46836250
A47: Impuesto complementario | B47: -134004 | C47: -134004 | D47: -134004 | E47: -134004 | F47: -134007
A48: Total de patrimonio | B48: 5495381 | C48: 12066680 | D48: 19641222 | E48: 2218883 | F48: 1549585
A49: Total de pasivos y patrimonio | B49: 274617243 | C49: 261959863 | D49: 260466310 | E49: 229832624 | F49: 216501926
A51: Años | B51: FY21A | C51: FY22A | D51: FY23A | E51: FY24A | F51: FY25A | G51: FY26E | H51: FY27E | I51: FY28E | J51: FY29E | K51: FY30E
A52: Estado de Flujos de Efectivo
A53: Pérdida antes del impuestos sobre la renta | B53: 1820066 | C53: 5971929 | D53: 8395009 | E53: -1711072 | F53: -172108
A54: Depreciación y amortización | B54: 13917163 | C54: 13936348 | D54: 13947153 | E54: 13994812 | F54: 14031702
A55: Amortización de costos financieros | B55: 461118 | C55: 488495 | D55: 488115 | E55: 465343 | F55: 417400
A56: Intereses sobre bonos y pasivos por arrendamiento | B56: 19633409 | C56: 17427534 | D56: 16034326 | E56: 15277290 | F56: 14368965
A57: Interés ganado | B57: -1491219 | C57: -1429818 | D57: -1366104 | E57: -1300441 | F57: -1221639
A58: Ganancia en valor razonable de instrumento financiero derivado | B58: -4708923 | C58: -7338074
A59: Deudores comerciales y otras cuentas por cobrar | B59: -11432 | C59: 1436789 | D59: -156919 | E59: 3206463 | F59: -953435
A60: Proveedores, otras cuentas por pagar y provisiones | B60: -2200385 | C60: -608700 | D60: 1301174 | E60: -1088704 | F60: 921357
A61: Gastos pagados por adelantado y fondo de cesantía | B61: -1320164 | C61: -3051406 | D61: 3696876 | E61: -676045 | F61: 1097614
A62: Inventario | B62: -16578 | C62: -1894 | D62: -11041 | E62: -19976 | F62: -12501
A63: Impuesto sobre la renta pagado | B63: -946740
A64: Efectivo neto provisto por actividades de operación | B64: 25136315 | C64: 26831203 | D64: 42328589 | E64: 28147670 | F64: 28477355
A65: Adiciones de planta y equipo | B65: -93485 | C65: -556464 | D65: -5097893 | E65: -282082 | F65: -984285
A66: Adiciones de activos intangibles | B66: -125421 | C66: -15000 | D66: -17143 | E66: -22500 | F66: -30000
A67: Cobro de préstamo entre partes relacionadas | B67: 885999 | C67: 898933 | D67: 996981 | E67: 1138080 | F67: 1239673
A68: Intereses recibidos - con partes relacionadas | B68: 1178171 | C68: 1444586 | D68: 1384321 | E68: 1317299 | F68: 1242005
A69: Efectivo neto provisto por actividades de inversión | B69: 1845264 | C69: 1772055 | D69: -2733734 | E69: 2150797 | F69: 1467393
A70: Pago de bonos emitidos | B70: -10003000 | C70: -10149000 | D70: -11256000 | E70: -12849000 | F70: -13996000
A71: Intereses pagados | B71: -16123503 | C71: -18004832 | D71: -15629088 | E71: -14872390 | F71: -14022320
A72: Intereses pagados por arrendamiento | D72: -610919 | E72: -595230 | F72: -576580
A73: Pago por instrumento financiero derivado | B73: 0 | C73: -287000
A74: Dividendos pagados | D74: 0 | E74: -7574542 | F74: 0
A75: Reducción de capital | B75: -10000000 | D75: 0 | E75: -7455458 | F75: 0
A76: Pagos de principal de arrendamiento | B76: -126524 | C76: -157732 | D76: -192094 | E76: -229888 | F76: -271409
A77: Impuesto complementario | B77: -114851 | E77: 0 | F77: -3
A78: Efectivo neto utilizado en actividades de financiamiento | B78: -36367878 | C78: -28598564 | D78: -27688101 | E78: -43576508 | F78: -28866312
A79: Aumento (disminución) neto en efectivo y equivalentes de efectivo | B79: -9386299 | C79: 4694 | D79: 11906754 | E79: -13278041 | F79: 1078436
A80: Efectivo y equivalentes de efectivo al inicio del año | B80: 14871800 | C80: 5485501 | D80: 5490195 | E80: 17396949 | F80: 4118908
A81: Efectivo y equivalentes de efectivo al final del año | B81: 5485501 | C81: 5490195 | D81: 17396949 | E81: 4118908 | F81: 5197344

Sheet Supuestos
A1: UEP Penonomé II, S. A.
A3: COLOR KEY: Input (azul) · Fórmula (negro) · Link inter-hoja (verde)
A4: Escenario (1=Base, 2=Bull, 3=Bear)
A5: Selector escenario | C5: 1 | M5: caso | N5: NOT_DISCLOSED | Q5: Input de escenario desde fuente citada o NOT_DISCLOSED.
A6: Escenario activo | C6: =CHOOSE($C$5,"Base","Bull","Bear") -> Base | M6: moneda del modelo | N6: NOT_DISCLOSED | Q6: Selector de caso activo C5: Base/Bull/Bear.
A8: Años | B8: FY21A | C8: FY22A | D8: FY23A | E8: FY24A | F8: FY25A | G8: FY26E | H8: FY27E | I8: FY28E | J8: FY29E | K8: FY30E | M8: Unidad | N8: Fuente / nota | Q8: Rationale
A10: A. PRODUCCIÓN POR PARQUE (MWh neto = MW × 8.760 h × CF neto; el CF histórico ya embebe wake+AVF)
A11: Factor de planta NETO (CF) — activo | B11: 0.2304 | C11: 0.2028 | D11: 0.2838 | E11: 0.2147 | F11: 0.2243 | G11: =CHOOSE($C$5,G13,G14,G12) -> 0.215 | H11: =CHOOSE($C$5,H13,H14,H12) -> 0.215 | I11: =CHOOSE($C$5,I13,I14,I12) -> 0.215 | J11: =CHOOSE($C$5,J13,J14,J12) -> 0.21 | K11: =CHOOSE($C$5,K13,K14,K12) -> 0.21 | M11: % | N11: a working file kept by the maintainer | Q11: Selector de caso activo C5: Base/Bull/Bear.
A12: Bear | G12: 0.195 | H12: 0.195 | I12: 0.195 | J12: 0.195 | K12: 0.19 | M12: % | N12: a working file kept by the maintainer | Q12: Escenario driver citado; NOT_DISCLOSED si no hay fuente explícita.
A13: Base | G13: 0.215 | H13: 0.215 | I13: 0.215 | J13: 0.21 | K13: 0.21 | M13: % | N13: a working file kept by the maintainer | Q13: Escenario driver citado; NOT_DISCLOSED si no hay fuente explícita.
A14: Bull | G14: 0.245 | H14: 0.245 | I14: 0.245 | J14: 0.24 | K14: 0.24 | M14: % | N14: a working file kept by the maintainer | Q14: Escenario driver citado; NOT_DISCLOSED si no hay fuente explícita.
A15: Disponibilidad (AVF) — memo (ya embebida en CF neto) | B15: 0.9381 | C15: 0.957 | D15: 0.9337 | E15: 0.9366 | F15: 0.9597 | G15: 0.96 | H15: 0.96 | I15: 0.96 | J15: 0.96 | K15: 0.96 | M15: % | N15: a working file kept by the maintainer | Q15: Input de escenario desde fuente citada o NOT_DISCLOSED.
A16: Horas / año | B16: 8760 | C16: 8760 | D16: 8760 | E16: 8784 | F16: 8760 | G16: 8760 | H16: 8760 | I16: 8760 | J16: 8760 | K16: 8760 | M16: horas/año | N16: a working file kept by the maintainer | Q16: Input de escenario desde fuente citada o NOT_DISCLOSED.
A17: Nuevo Chagres — 62.5 MW (wake 12.4%) | G17: =62.5*G16*G11 -> 117712.5 | H17: =62.5*H16*H11 -> 117712.5 | I17: =62.5*I16*I11 -> 117712.5 | J17: =62.5*J16*J11 -> 114975 | K17: =62.5*K16*K11 -> 114975 | M17: MW | N17: a working file kept by the maintainer | Q17: Derivación mecánica por fórmula viva.
A18: Rosa de los Vientos I — 52.5 MW (wake 8.0%) | G18: =52.5*G16*G11 -> 98878.5 | H18: =52.5*H16*H11 -> 98878.5 | I18: =52.5*I16*I11 -> 98878.5 | J18: =52.5*J16*J11 -> 96579 | K18: =52.5*K16*K11 -> 96579 | M18: MW | N18: a working file kept by the maintainer | Q18: Derivación mecánica por fórmula viva.
A19: Rosa de los Vientos II — 50 MW (wake 6.0%) | G19: =50*G16*G11 -> 94170 | H19: =50*H16*H11 -> 94170 | I19: =50*I16*I11 -> 94170 | J19: =50*J16*J11 -> 91980 | K19: =50*K16*K11 -> 91980 | M19: MW | N19: a working file kept by the maintainer | Q19: Derivación mecánica por fórmula viva.
A20: Marañón — 17.5 MW (wake 7.0%) | G20: =17.5*G16*G11 -> 32959.5 | H20: =17.5*H16*H11 -> 32959.5 | I20: =17.5*I16*I11 -> 32959.5 | J20: =17.5*J16*J11 -> 32193 | K20: =17.5*K16*K11 -> 32193 | M20: MW | N20: a working file kept by the maintainer | Q20: Derivación mecánica por fórmula viva.
A21: Portobelo Ballestillas — 32.5 MW (wake 8.0%) | G21: =32.5*G16*G11 -> 61210.5 | H21: =32.5*H16*H11 -> 61210.5 | I21: =32.5*I16*I11 -> 61210.5 | J21: =32.5*J16*J11 -> 59787 | K21: =32.5*K16*K11 -> 59787 | M21: MW | N21: a working file kept by the maintainer | Q21: Derivación mecánica por fórmula viva.
A22: Generación neta total (MWh) | B22: 433950 | C22: 381870 | D22: 534600 | E22: 405420 | F22: 422370 | G22: =G17+G18+G19+G20+G21 -> 404931 | H22: =H17+H18+H19+H20+H21 -> 404931 | I22: =I17+I18+I19+I20+I21 -> 404931 | J22: =J17+J18+J19+J20+J21 -> 395514 | K22: =K17+K18+K19+K20+K21 -> 395514 | M22: MWh | N22: a working file kept by the maintainer | Q22: Suma mecánica del bloque.
A24: B. PRECIOS POR FUENTE ($/MWh)
A25: PPA contratado ($/MWh, 75% fijo + 25% IPC) | G25: 112.359 | H25: 112.921 | I25: 113.485 | J25: 114.053 | K25: 114.623 | M25: MWh | N25: a working file kept by the maintainer | Q25: Input de escenario desde fuente citada o NOT_DISCLOSED.
A26: Spot / merchant ($/MWh) — activo | B26: 74.16 | C26: 148.76 | D26: 112.45 | E26: 133.91 | F26: 66.44 | G26: =CHOOSE($C$5,G28,G29,G27) -> 60 | H26: =CHOOSE($C$5,H28,H29,H27) -> 57 | I26: =CHOOSE($C$5,I28,I29,I27) -> 54 | J26: =CHOOSE($C$5,J28,J29,J27) -> 51 | K26: =CHOOSE($C$5,K28,K29,K27) -> 50 | M26: MWh | N26: a working file kept by the maintainer | Q26: Selector de caso activo C5: Base/Bull/Bear.
A27: Bear | G27: 50 | H27: 47 | I27: 44 | J27: 41 | K27: 40 | M27: moneda del modelo | N27: a working file kept by the maintainer | Q27: Escenario driver citado; NOT_DISCLOSED si no hay fuente explícita.
A28: Base | G28: 60 | H28: 57 | I28: 54 | J28: 51 | K28: 50 | M28: moneda del modelo | N28: a working file kept by the maintainer | Q28: Escenario driver citado; NOT_DISCLOSED si no hay fuente explícita.
A29: Bull | G29: 70 | H29: 67 | I29: 64 | J29: 61 | K29: 60 | M29: moneda del modelo | N29: a working file kept by the maintainer | Q29: Escenario driver citado; NOT_DISCLOSED si no hay fuente explícita.
A30: Reserva Tecnisol ($/MWh) | G30: 73.3 | H30: 73.3 | I30: 73.3 | J30: 73.3 | K30: 73.3 | M30: MWh | N30: a working file kept by the maintainer | Q30: Input de escenario desde fuente citada o NOT_DISCLOSED.
A32: C. VOLUMEN POR CANAL (MWh, con cliffs PPA por parque)
A33: MWh PPA contratado (DISCOs) | B33: 337870 | C33: 299330 | D33: 418780 | E33: 320080 | F33: 347300 | G33: =1*G17+1*G18+1*G20+1*G21 -> 310761 | H33: =1*H17+1*H18+1*H20+1*H21 -> 310761 | I33: =1*I17+1*I18+1*I20+1*I21 -> 310761 | J33: =0.5*J17+0.5*J18+1*J20+1*J21 -> 197757 | K33: =1*K20+1*K21 -> 91980 | M33: MWh | N33: a working file kept by the maintainer | Q33: Derivación mecánica por fórmula viva.
A34: MWh reserva (Tecnisol, Rosa II) | B34: 27870 | C34: 24710 | D34: 43220 | E34: 34000 | F34: 38160 | G34: 34000 | H34: 34000 | I34: 34000 | J34: 34000 | K34: 34000 | M34: MWh | N34: a working file kept by the maintainer | Q34: Input de escenario desde fuente citada o NOT_DISCLOSED.
A35: MWh spot / merchant (residual) | B35: 56140 | C35: 49820 | D35: 61470 | E35: 42710 | F35: 26840 | G35: =MAX(0,G22-G33-G34) -> 60170 | H35: =MAX(0,H22-H33-H34) -> 60170 | I35: =MAX(0,I22-I33-I34) -> 60170 | J35: =MAX(0,J22-J33-J34) -> 163757 | K35: =MAX(0,K22-K33-K34) -> 269534 | M35: MWh | N35: a working file kept by the maintainer | Q35: Derivación mecánica por fórmula viva.
A37: D. INGRESO POR FUENTE ($ = MWh × precio)
A38: Ingreso energía FY25A (auditado, ref EEFF) | B38: =EEFF!B7 -> 42036085 | C38: =EEFF!C7 -> 40987418 | D38: =EEFF!D7 -> 54587421 | E38: =EEFF!E7 -> 42653811 | F38: =EEFF!F7 -> 42404701 | M38: MWh | N38: EEFF:Ingresos por energía | Q38: Mirror histórico desde fuente citada.
A39: Ingreso PPA | G39: =G33*G25 -> 34916795 | H39: =H33*H25 -> 35091443 | I39: =I33*I25 -> 35266712 | J39: =J33*J25 -> 22554779 | K39: =K33*K25 -> 10543024 | M39: moneda del modelo | N39: a working file kept by the maintainer | Q39: Derivación mecánica por fórmula viva.
A40: Ingreso reserva Tecnisol | B40: 1819919 | C40: 1613353 | D40: 2822042 | E40: 2220153 | F40: 2492069 | G40: =G34*G30 -> 2492200 | H40: =H34*H30 -> 2492200 | I40: =I34*I30 -> 2492200 | J40: =J34*J30 -> 2492200 | K40: =K34*K30 -> 2492200 | M40: moneda del modelo | N40: a working file kept by the maintainer | Q40: Derivación mecánica por fórmula viva.
A41: Ingreso spot / merchant | B41: =B35*B26 -> 4163342.4 | C41: =C35*C26 -> 7411223.2 | D41: =D35*D26 -> 6912301.5 | E41: =E35*E26 -> 5719296.1 | F41: =F35*F26 -> 1783249.6 | G41: =G35*G26 -> 3610200 | H41: =H35*H26 -> 3429690 | I41: =I35*I26 -> 3249180 | ... K41: =K35*K26 -> 13476700 | M41: moneda del modelo | N41: a working file kept by the maintainer | Q41: Derivación mecánica por fórmula viva.
A42: Compensación pérdidas transmisión | G42: 700000 | H42: 700000 | I42: 700000 | J42: 700000 | K42: 700000 | M42: moneda del modelo | N42: a working file kept by the maintainer | Q42: Input de escenario desde fuente citada o NOT_DISCLOSED.
A43: (memo) Potencia firme — embebida en PPA $/MWh (no sumada) | G43: 49.5 | H43: 49.5 | I43: 49.5 | J43: 49.5 | K43: 49.5 | M43: MWh | N43: a working file kept by the maintainer | Q43: Derivación mecánica declarada por el plan.
A44: TOTAL INGRESO ENERGÍA | B44: =B38 -> 42036085 | C44: =C38 -> 40987418 | D44: =D38 -> 54587421 | E44: =E38 -> 42653811 | F44: =F38 -> 42404701 | G44: =G39+G40+G41+G42 -> 41719195 | H44: =H39+H40+H41+H42 -> 41713333 | I44: =I39+I40+I41+I42 -> 41708092 | J44: =J39+J40+J41+J42 -> 34098586 | K44: =K39+K40+K41+K42 -> 27211924 | M44: MWh | N44: a working file kept by the maintainer | Q44: Suma mecánica del bloque.
A46: E. O&M Y COSTOS OPERATIVOS ($)
A47: O&M variable ($/MWh) [Goldwind SMA] | B47: =B48/B22 -> 16.803941 | C47: =C48/C22 -> 16.441072 | D47: =D48/D22 -> 14.581163 | E47: =E48/E22 -> 17.057489 | F47: =F48/F22 -> 16.98029 | G47: 17 | H47: 17 | I47: 17 | J47: 17 | K47: 17 | M47: MWh | N47: a working file kept by the maintainer | Q47: Derivación mecánica por fórmula viva.
A48: O&M variable total ($) | B48: 7292070 | C48: 6278352 | D48: 7795090 | E48: 6915447 | F48: 7171965 | G48: =G47*G22 -> 6883827 | H48: =H47*H22 -> 6883827 | I48: =I47*I22 -> 6883827 | J48: =J47*J22 -> 6723738 | K48: =K47*K22 -> 6723738 | M48: moneda del modelo | N48: a working file kept by the maintainer | Q48: Derivación mecánica por fórmula viva.
A49: O&M fijo: subestación (AES) | B49: 569159 | C49: 534132 | D49: 471510 | E49: 466858 | F49: 444576 | G49: 445000 | H49: 445000 | I49: 445000 | J49: 445000 | K49: 445000 | M49: moneda del modelo | N49: a working file kept by the maintainer | Q49: Input de escenario desde fuente citada o NOT_DISCLOSED.
A50: O&M fijo: compensación wake (AES) | B50: 512088 | C50: 637229 | D50: 820324 | E50: 392259 | F50: 250877 | G50: 258000 | H50: 265000 | I50: 273000 | J50: 281000 | K50: 290000 | M50: moneda del modelo | N50: a working file kept by the maintainer | Q50: Input de escenario desde fuente citada o NOT_DISCLOSED.
A51: O&M fijo: reserva mantenimiento mayor (MMR) | G51: 645000 | H51: 645000 | I51: 645000 | J51: 645000 | K51: 645000 | M51: moneda del modelo | N51: a working file kept by the maintainer | Q51: Input de escenario desde fuente citada o NOT_DISCLOSED.
A52: Seguros | B52: 842589 | C52: 905626 | D52: 987481 | E52: 1054607 | F52: 976273 | G52: 500000 | H52: 500000 | I52: 500000 | J52: 500000 | K52: 500000 | M52: moneda del modelo | N52: a working file kept by the maintainer | Q52: Input de escenario desde fuente citada o NOT_DISCLOSED.
A53: Depreciación y amortización | B53: 13917163 | C53: 13936348 | D53: 13947153 | E53: 13994812 | F53: 14031702 | G53: 14000000 | H53: 14000000 | I53: 14000000 | J53: 14000000 | K53: 14000000 | M53: moneda del modelo | N53: a working file kept by the maintainer | Q53: Input de escenario desde fuente citada o NOT_DISCLOSED.
A54: TOTAL COSTO DE ENERGÍA (COGS) | B54: =-EEFF!B8 -> 22857327 | C54: =-EEFF!C8 -> 21858853 | D54: =-EEFF!D8 -> 25573871 | E54: =-EEFF!E8 -> 25736347 | F54: =-EEFF!F8 -> 24413955 | G54: =G48+G49+G50+G51+G52+G53 -> 22731827 | H54: =H48+H49+H50+H51+H52+H53 -> 22738827 | I54: =I48+I49+I50+I51+I52+I53 -> 22746827 | J54: =J48+J49+J50+J51+J52+J53 -> 22594738 | K54: =K48+K49+K50+K51+K52+K53 -> 22603738 | M54: MWh | N54: a working file kept by the maintainer | Q54: Suma mecánica del bloque.
A55: Gasto admin (CMA InterEnergy) | B55: 322500 | C55: 322500 | D55: 1290000 | E55: 322500 | F55: 1290000 | G55: 1290000 | H55: 1290000 | I55: 1290000 | J55: 1290000 | K55: 1290000 | M55: moneda del modelo | N55: a working file kept by the maintainer | Q55: Input de escenario desde fuente citada o NOT_DISCLOSED.
A56: Cargo transmisión ASEP | B56: 860729 | C56: 703317 | D56: 2784099 | E56: 3573302 | F56: 2117820 | G56: 2120000 | H56: 2120000 | I56: 2120000 | J56: 2120000 | K56: 2120000 | M56: moneda del modelo | N56: a working file kept by the maintainer | Q56: Input de escenario desde fuente citada o NOT_DISCLOSED.
A57: Otros G&A | G57: 250000 | H57: 250000 | I57: 250000 | J57: 250000 | K57: 250000 | M57: moneda del modelo | N57: a working file kept by the maintainer | Q57: Input de escenario desde fuente citada o NOT_DISCLOSED.
A58: TOTAL GASTOS ADMIN (G&A) | B58: =-EEFF!B10 -> 3266942 | C58: =-EEFF!C10 -> 3405988 | D58: =-EEFF!D10 -> 4482435 | E58: =-EEFF!E10 -> 3436087 | F58: =-EEFF!F10 -> 3908720 | G58: =G55+G56+G57 -> 3660000 | H58: =H55+H56+H57 -> 3660000 | I58: =I55+I56+I57 -> 3660000 | J58: =J55+J56+J57 -> 3660000 | K58: =K55+K56+K57 -> 3660000 | M58: moneda del modelo | N58: a working file kept by the maintainer | Q58: Suma mecánica del bloque.

Sheet Notas_EEFF
A1: UEP Penonomé II, S. A.
A2: Notas a los Estados Financieros
A3: Fuente: Estados Financieros Auditados FY21-FY25 (OCR Mistral). Entidad: UEP Penonomé II, S. A. STANDALONE (no Grupo Tecnisol combinado, no Fideicomiso FID-135). Notas verbatim en español. Años: 2025/2024 del informe INA_UEPPSA_2025; 2023 del INA_UEPPSA_2024; 2022 del INA_UEPPSA_2023; 2021 del INA_UEPPSA_2022 (criterio: informe más reciente para años solapados).
A5: Año | B5: Documento fuente | C5: Página OCR | D5: Tabla OCR / sección | E5: Nota # | F5: Título original de la nota | G5: Categoría modelable | H5: Line item EEFF | I5: Sub-line item / detalle | J5: Texto original / disclosure | K5: Monto reportado | L5: Moneda | M5: Unidad / escala | N5: Fecha / venc. / tasa / plazo | O5: Contraparte / contrato / instrumento | P5: Impacto en Supuestos | Q5: Impacto en ModeloFinanciero | R5: Link a celda EEFF | S5: Comentario de extracción | T5: Status
A6: 2025 | B6: INA_UEPPSA_2025_0.pdf | C6: page-36 | D6: markdown.md | E6: 1. Información General | F6: 1. Información General | G6: Otros | I6: Constitución y actividad | J6: UEP Penonomé II, S. A. (la “Compañía”) se constituyó el 18 de enero de 2013 bajo las leyes de la República de Panamá. La Compañía se dedica a la producción de electricidad a través de cinco parques eólicos ubicados en Penonomé, Provincia de Coclé, República de Panamá. | L6: US$ | M6: sin escala | N6: 18 de enero de 2013 | P6: Define el activo: 5 parques eólicos, 215 MW; base del build de generación. | T6: OK
A7: 2025 | B7: INA_UEPPSA_2025_0.pdf | C7: page-36 | D7: markdown.md | E7: 1. Información General | F7: 1. Información General | G7: Partes relacionadas | I7: Controladora última | J7: La última sociedad controladora de UEP Penonomé II, S. A. es Basic Energy Ltd., constituida en las Bahamas. | L7: US$ | M7: sin escala | O7: Basic Energy Ltd. (Bahamas) | T7: OK
A8: 2025 | B8: INA_UEPPSA_2025_0.pdf | C8: page-36 | D8: markdown.md | E8: 1. Información General | F8: 1. Información General | G8: Otros | I8: Licencia ASEP | J8: El regulador local, la Autoridad Nacional de Servicios Públicos (ASEP), aprobó la licencia de generación de electricidad de la Compañía con capacidad de 215 MW (Nota 19). | K8: 215 | L8: US$ | M8: MW | O8: ASEP | P8: Capacidad instalada 215 MW = techo físico de generación. | T8: OK
A9: 2025 | B9: INA_UEPPSA_2025_0.pdf | C9: page-36 | D9: markdown.md | E9: 1. Información General | F9: 1. Información General | G9: Otros | I9: Domicilio | J9: La Compañía está ubicada en Edificio Plaza 58, Piso 9, Calle 58E, Obarrío, República de Panamá, y las turbinas eólicas están ubicadas en Penonomé, Provincia de Coclé, República de Panamá. | L9: US$ | M9: sin escala | T9: OK
A10: 2025 | B10: INA_UEPPSA_2025_0.pdf | C10: page-36 | D10: markdown.md | E10: 1. Información General | F10: 1. Información General | G10: Subsequent events | I10: Aprobación de emisión | J10: Estos estados financieros han sido aprobados para su emisión por el Gerente de Finanzas el 28 de febrero de 2026. | L10: US$ | M10: sin escala | N10: 28 de febrero de 2026 | T10: OK
A11: 2025 | B11: INA_UEPPSA_2025_0.pdf | C11: page-37 | D11: markdown.md | E11: 2. Resumen de las Políticas Contables Materiales | F11: 2. Resumen de las Políticas Contables Materiales | G11: Políticas contables | I11: Base de Preparación | J11: Los estados financieros de la Compañía han sido preparados de acuerdo con las Normas Internacionales de Información Financiera emitidas por la Junta de Normas Internacionales de Contabilidad (IASB, por sus siglas en inglés) (Normas de Contabilidad NIIF). Los estados financieros han sido preparados sobre la base del costo histórico. En los estados financieros de la Compañía no se presenta el Estado de Otro Resultado Integral, debido a que no hay partidas que requieran una presentación separada de este estado. La preparación de los estados financieros en conformidad con las Normas de Contabilidad NIIF requiere el uso de ciertas estimaciones de contabilidad críticas. También requiere que la Administración use su juicio en el proceso de la aplicación de las políticas contables de la Compañía. Las áreas que involucran un alto grado de juicio o complejidad, o áreas donde los supuestos y estimaciones son significativos para los estados financieros, se revelan en la Nota 4. | L11: US$ | M11: sin escala | Q11: NIIF, costo histórico; sin OCI. Base contable del modelo. | T11: OK
A12: 2025 | B12: INA_UEPPSA_2025_0.pdf | C12: page-37 | D12: markdown.md | E12: 2. Resumen de las Políticas Contables Materiales | F12: 2. Resumen de las Políticas Contables Materiales | G12: Políticas contables | I12: Nuevas Normas y Enmiendas Adoptadas por la Compañía (NIC 21) | J12: La Compañía ha aplicado las siguientes modificaciones por primera vez para su período de reporte anual que comienza el 1 de enero de 2025: Falta de Convertibilidad - Modificaciones a la NIC 21, “Efectos de las variaciones en las tasas de cambio de la Moneda Extranjera”... La Compañía determinó que las modificaciones no tuvieron un impacto significativo en sus estados financieros. | L12: US$ | M12: sin escala | N12: vigente 1 enero 2025 | T12: OK
A13: 2025 | B13: INA_UEPPSA_2025_0.pdf | C13: page-37 | D13: markdown.md | E13: 2. Resumen de las Políticas Contables Materiales | F13: 2. Resumen de las Políticas Contables Materiales | G13: Políticas contables | I13: Decisiones del Comité de Interpretaciones de las NIIF (NIC 38; garantías) | J13: En 2025 se emitieron las siguientes decisiones que podrían ser relevantes...: Reconocimiento de Activos Intangibles por Gastos Relacionados con el Clima (NIC 38)... Garantías Emitidas sobre Obligaciones de Otras Entidades... La Compañía determinó que las interpretaciones no tuvieron un impacto significativo en sus estados financieros. | L13: US$ | M13: sin escala | T13: OK
A14: 2025 | B14: INA_UEPPSA_2025_0.pdf | C14: page-38 | D14: markdown.md | E14: 2. Resumen de las Políticas Contables Materiales | F14: 2. Resumen de las Políticas Contables Materiales | G14: Políticas contables | I14: Nuevas Normas no Adoptadas (NIIF 9/7 clasificación y medición) | J14: Se han publicado ciertas nuevas normas contables y modificaciones... que la Compañía no ha adoptado anticipadamente. Modificaciones a la Clasificación y Medición de Instrumentos Financieros - Modificaciones a las NIIF 9 y NIIF 7. ... estarán vigentes para los períodos anuales que comiencen a partir del 1 de enero de 2026, permitiéndose su aplicación anticipada. La administración está evaluando las implicaciones detalladas... | L14: US$ | M14: sin escala | N14: vigente 1 enero 2026 | T14: OK
A15: 2025 | B15: INA_UEPPSA_2025_0.pdf | C15: page-38 | D15: markdown.md | E15: 2. Resumen de las Políticas Contables Materiales | F15: 2. Resumen de las Políticas Contables Materiales | G15: Políticas contables | I15: Nuevas Normas no Adoptadas (NIIF 9/7 electricidad dependiente de la naturaleza) | J15: Contratos que Hacen Referencia a la Electricidad Dependiente de la Naturaleza - Modificaciones a las NIIF 9 y NIIF 7: ... (a) aclaran la aplicación del criterio de “uso propio” a los contratos de electricidad dependiente de la naturaleza; (b) permiten la contabilidad de coberturas si estos contratos se utilizan como instrumentos de cobertura; y (c) añaden nuevos requisitos de información a revelar... estarán vigentes para los periodos anuales que comiencen a partir del 1 de enero de 2026, permitiéndose su aplicación anticipada. | L15: US$ | M15: sin escala | N15: vigente 1 enero 2026 | T15: OK
A16: 2025 | B16: INA_UEPPSA_2025_0.pdf | C16: page-38 | D16: markdown.md | E16: 2. Resumen de las Políticas Contables Materiales | F16: 2. Resumen de las Políticas Contables Materiales | G16: Políticas contables | I16: Nuevas Normas no Adoptadas (NIIF 18) | J16: NIIF 18, “Presentación y revelación en estados financieros”... La NIIF 18 entró en vigor el 1 de enero de 2027 y aún no ha sido adoptada por la Compañía. ... La Compañía informa actualmente a los accionistas sobre una medida de EBITDA ajustado. La Compañía espera que esta medida cumpla con la definición de una medida de rendimiento definida por la administración. | L16: US$ | M16: sin escala | N16: vigente 1 enero 2027 | Q16: La Compañía reporta EBITDA ajustado a accionistas (medida de gestión). | T16: OK
A17: 2025 | B17: INA_UEPPSA_2025_0.pdf | C17: page-40 | D17: markdown.md | E17: 2. Resumen de las Políticas Contables Materiales | F17: 2. Resumen de las Políticas Contables Materiales | G17: Políticas contables | I17: Unidad Monetaria y Moneda Funcional | J17: Los estados financieros están expresados en dólares (US$), unidad monetaria de los Estados Unidos de América, la cual está a la par con el Balboa (B/.), unidad monetaria de la República de Panamá. El dólar (US$) circula y es de libre cambio en la República de Panamá y es la moneda funcional. | L17: US$ | M17: sin escala | Q17: Moneda funcional US$ (=B/. 1:1); sin exposición FX material. | T17: OK
A18: 2025 | B18: INA_UEPPSA_2025_0.pdf | C18: page-40 | D18: markdown.md | E18: 2. Resumen de las Políticas Contables Materiales | F18: 2. Resumen de las Políticas Contables Materiales | G18: Segmentos | I18: Información de Segmento | J18: Las operaciones del negocio de la Compañía están organizadas y manejadas como un solo segmento de negocios que es el de operar las plantas generadoras dentro del entorno económico de generación eléctrica. Adicionalmente, la organización interna y de reporte de la Compañía está predominantemente basada en un solo segmento de negocio. | L18: US$ | M18: sin escala | Q18: Un solo segmento (generación eléctrica) → modelo single-segment. | T18: OK
A19: 2025 | B19: INA_UEPPSA_2025_0.pdf | C19: page-40 | D19: markdown.md | E19: 2. Resumen de las Políticas Contables Materiales | F19: 2. Resumen de las Políticas Contables Materiales | G19: Cuentas por cobrar | I19: Activos Financieros / Deudores Comerciales (ECL NIIF 9 simplificado) | J19: La Compañía clasifica sus activos financieros en la categoría de préstamos y cuentas por cobrar... Los deudores se reconocen inicialmente por el monto de la contraprestación... y posteriormente se miden al costo amortizado utilizando el método de interés efectivo, menos la provisión por deterioro... Se establece una provisión por deterioro de cuentas comerciales por cobrar aplicando el enfoque simplificado de la NIIF 9 para medir las pérdidas crediticias esperadas... | L19: US$ | M19: sin escala | P19: AR a costo amortizado; ECL enfoque simplificado. | T19: OK
A20: 2025 | B20: INA_UEPPSA_2025_0.pdf | C20: page-40 | D20: markdown.md | E20: 2. Resumen de las Políticas Contables Materiales | F20: 2. Resumen de las Políticas Contables Materiales | G20: Working capital | I20: Gastos Pagados por Adelantado | J20: Los gastos pagados por anticipado están relacionados principalmente con anticipos a proveedores, seguros pagados por anticipado y cartas de crédito. ... Los gastos pagados por anticipado y otros activos se registran inicialmente como activos, pero su valor se reconoce a lo largo del tiempo en el estado de resultados. | L20: US$ | M20: sin escala | T20: OK
A21: 2025 | B21: INA_UEPPSA_2025_0.pdf | C21: page-41 | D21: markdown.md | E21: 2. Resumen de las Políticas Contables Materiales | F21: 2. Resumen de las Políticas Contables Materiales | G21: PP&E / capex / depreciación | I21: Planta y Equipo | J21: La planta y equipo se registran al costo, menos la depreciación, amortización acumulada y las pérdidas por deterioro. La depreciación y amortización se calculan con el método de línea recta sobre la vida útil estimada del activo. ... La Compañía cuenta con un programa de mantenimiento... basado en las horas de operación equivalentes (EOH). ... La planta y el equipo incluyen los intereses de los financiamientos que se atribuyen directamente a la construcción de los activos. | L21: US$ | M21: sin escala | P21: Depreciación lineal sobre vida útil; capitaliza intereses de construcción. | T21: OK
A22: 2025 | B22: INA_UEPPSA_2025_0.pdf | C22: page-42 | D22: tbl-13.html | E22: 2. Resumen de las Políticas Contables Materiales | F22: 2. Resumen de las Políticas Contables Materiales | G22: PP&E / capex / depreciación | I22: Tasas de depreciación y amortización | J22: Equipo de transporte | L22: US$ | M22: % | N22: 25% | P22: Tasa de depreciación anual por clase de activo (input del schedule de PP&E). | T22: OK
A23: 2025 | B23: INA_UEPPSA_2025_0.pdf | C23: page-42 | D23: tbl-13.html | E23: 2. Resumen de las Políticas Contables Materiales | F23: 2. Resumen de las Políticas Contables Materiales | G23: PP&E / capex / depreciación | I23: Tasas de depreciación y amortización | J23: Edificios | L23: US$ | M23: % | N23: 2.50% | T23: OK
A24: 2025 | B24: INA_UEPPSA_2025_0.pdf | C24: page-42 | D24: tbl-13.html | E24: 2. Resumen de las Políticas Contables Materiales | F24: 2. Resumen de las Políticas Contables Materiales | G24: PP&E / capex / depreciación | I24: Tasas de depreciación y amortización | J24: Herramientas, equipo menor y otros activos | L24: US$ | M24: % | N24: 25% | T24: OK
A25: 2025 | B25: INA_UEPPSA_2025_0.pdf | C25: page-42 | D25: tbl-13.html | E25: 2. Resumen de las Políticas Contables Materiales | F25: 2. Resumen de las Políticas Contables Materiales | G25: PP&E / capex / depreciación | I25: Tasas de depreciación y amortización | J25: Mobiliario y equipo de oficina | L25: US$ | M25: % | N25: 25% | T25: OK
A26: 2025 | B26: INA_UEPPSA_2025_0.pdf | C26: page-42 | D26: tbl-13.html | E26: 2. Resumen de las Políticas Contables Materiales | F26: 2. Resumen de las Políticas Contables Materiales | G26: PP&E / capex / depreciación | I26: Tasas de depreciación y amortización | J26: Instalaciones de planta y generadores | L26: US$ | M26: % | N26: 5% - 10% | P26: Generadores 5%-10% → vida útil ~10-20 años; driver clave de la depreciación. | T26: OK
A27: 2025 | B27: INA_UEPPSA_2025_0.pdf | C27: page-42 | D27: tbl-13.html | E27: 2. Resumen de las Políticas Contables Materiales | F27: 2. Resumen de las Políticas Contables Materiales | G27: PP&E / capex / depreciación | I27: Tasas de depreciación y amortización | J27: Propiedad arrendada | L27: US$ | M27: % | N27: 5% | T27: OK
A28: 2025 | B28: INA_UEPPSA_2025_0.pdf | C28: page-41 | D28: markdown.md | E28: 2. Resumen de las Políticas Contables Materiales | F28: 2. Resumen de las Políticas Contables Materiales | G28: Inventario | I28: Inventario | J28: Consisten en piezas de repuesto consumibles... Los inventarios se valúan al costo o al valor neto realizable, el que sea menor. ... El costo se determina utilizando el método de costo promedio ponderado. Se establece una provisión para el inventario obsoleto de piezas de repuesto... | L28: US$ | M28: sin escala | P28: Inventario = repuestos; costo promedio ponderado. | T28: OK
A29: 2025 | B29: INA_UEPPSA_2025_0.pdf | C29: page-41 | D29: markdown.md | E29: 2. Resumen de las Políticas Contables Materiales | F29: 2. Resumen de las Políticas Contables Materiales | G29: Políticas contables | I29: Deterioro de Activos de Larga Vida | J29: La planta y equipo y otros activos no corrientes... son revisados por deterioro cuando eventos o cambios en las circunstancias indiquen que el valor en libros puede no ser recuperable. Los activos intangibles que tienen una vida útil indefinida no están sujetos a amortización y se prueban anualmente por deterioro... el monto recuperable es el mayor del valor razonable de un activo menos los costos de disposición y el valor en uso. | L29: US$ | M29: sin escala | T29: OK
A30: 2025 | B30: INA_UEPPSA_2025_0.pdf | C30: page-41 | D30: markdown.md | E30: 2. Resumen de las Políticas Contables Materiales | F30: 2. Resumen de las Políticas Contables Materiales | G30: Deuda / bonos / préstamos / leases | I30: Pasivos por Arrendamiento (NIIF 16) | J30: La Compañía aplica la NIIF 16 Arrendamientos... Al inicio de un arrendamiento, la Compañía reconoce un activo por derecho de uso (ROU) y un pasivo por arrendamiento, medido inicialmente al valor presente de los pagos futuros... Los pagos por arrendamiento se descuentan utilizando la tasa de interés implícita en el arrendamiento, cuando sea fácilmente determinable. | L30: US$ | M30: sin escala | P30: ROU/lease bajo NIIF 16; ver Nota 9 (tasa descuento 7.5%). | T30: OK
A31: 2025 | B31: INA_UEPPSA_2025_0.pdf | C31: page-41 | D31: markdown.md | E31: 2. Resumen de las Políticas Contables Materiales | F31: 2. Resumen de las Políticas Contables Materiales | G31: Intangibles | I31: Activos Intangibles - Servidumbre por Derecho de Paso | J31: Servidumbre por Derecho de Paso: Representa el valor atribuible al derecho de paso de una línea de transmisión de alta tensión por un período de 25 años, en virtud de un contrato a largo plazo con el propietario del terreno y las Compañías. Los activos intangibles se reconocen al costo y posteriormente se miden al costo menos la amortización acumulada... a lo largo de su vida útil estimada de 25 años. | L31: US$ | M31: sin escala | N31: 25 años | P31: Intangible = servidumbre, amortización lineal 25 años. | T31: OK
A32: 2025 | B32: INA_UEPPSA_2025_0.pdf | C32: page-41 | D32: markdown.md | E32: 2. Resumen de las Políticas Contables Materiales | F32: 2. Resumen de las Políticas Contables Materiales | G32: Intangibles | I32: Plusvalía | J32: La plusvalía surge y representa el exceso de la contraprestación transferida... sobre el valor razonable de los activos netos identificables adquiridos. La plusvalía no se amortiza, pero se comprueba su deterioro anualmente... | L32: US$ | M32: sin escala | P32: Plusvalía no se amortiza; test de deterioro anual (Nota 11). | T32: OK
A33: 2025 | B33: INA_UEPPSA_2025_0.pdf | C33: page-41 | D33: markdown.md | E33: 2. Resumen de las Políticas Contables Materiales | F33: 2. Resumen de las Políticas Contables Materiales | G33: Cuentas por pagar | I33: Proveedores y Otras Cuentas por Pagar | J33: Los proveedores y otras cuentas por pagar son obligaciones de pago por bienes o servicios... Se reconocen inicialmente a su valor razonable y posteriormente se miden a costo amortizado utilizando el método del interés efectivo. | L33: US$ | M33: sin escala | T33: OK
A34: 2025 | B34: INA_UEPPSA_2025_0.pdf | C34: page-41 | D34: markdown.md | E34: 2. Resumen de las Políticas Contables Materiales | F34: 2. Resumen de las Políticas Contables Materiales | G34: PP&E / capex / depreciación | I34: Provisión - Obligación de Retiro de Activos (ARO) | J34: La provisión para obligaciones por retiro de activos (ARO) se mide al valor actual de los desembolsos que se espera que sean necesarios para liquidar la obligación... La Compañía ha reconocido obligaciones no corrientes para el desmantelamiento y la retirada de sus activos al final de su vida útil. | L34: US$ | M34: sin escala | P34: ARO de desmantelamiento; ver Provisiones (EEFF) y costo financiero de desmantelamiento. | T34: OK
A35: 2025 | B35: INA_UEPPSA_2025_0.pdf | C35: page-41 | D35: markdown.md | E35: 2. Resumen de las Políticas Contables Materiales | F35: 2. Resumen de las Políticas Contables Materiales | G35: Deuda / bonos / préstamos / leases | I35: Bonos por Pagar | J35: Los bonos por pagar se reconocen inicialmente a su valor razonable, neto de los costos de transacción incurridos. Los bonos por pagar se registran posteriormente a costo amortizado utilizando el método de interés efectivo; se clasifican como pasivos corrientes a menos que la Compañía mantenga el derecho incondicional de diferir el pasivo durante al menos doce meses... | L35: US$ | M35: sin escala | P35: Bonos a costo amortizado (interés efectivo); ver Nota 13. | T35: OK
A36: 2025 | B36: INA_UEPPSA_2025_0.pdf | C36: page-41 | D36: markdown.md | E36: 2. Resumen de las Políticas Contables Materiales | F36: 2. Resumen de las Políticas Contables Materiales | G36: Intereses | I36: Costos Financieros | J36: Los costos financieros generales y específicos directamente atribuidos a la adquisición, construcción o producción de activos calificados... se añaden al costo de dichos activos... Todos los costos financieros se reconocen en el estado del resultado en el período en que se incurren. | L36: US$ | M36: sin escala | T36: OK
A37: 2025 | B37: INA_UEPPSA_2025_0.pdf | C37: page-41 | D37: markdown.md | E37: 2. Resumen de las Políticas Contables Materiales | F37: 2. Resumen de las Políticas Contables Materiales | G37: Impuestos | I37: Impuesto sobre la Renta Corriente y Diferido | J37: El gasto del impuesto sobre la renta para el período comprende del impuesto sobre la renta corriente y diferido... El impuesto sobre la renta diferido se provisiona en su totalidad utilizando el método de pasivo, cuando surgen diferencias temporarias entre las bases fiscales de los activos y pasivos y sus valores en libros... se determina utilizando las tasas impositivas que han sido promulgadas o sustancialmente promulgadas a la fecha del balance general... | L37: US$ | M37: sin escala | P37: ISR corriente + diferido (método de pasivo). Ver Nota 18 (tasa 25%/CAIR). | T37: OK
A38: 2025 | B38: INA_UEPPSA_2025_0.pdf | C38: page-41 | D38: markdown.md | E38: 2. Resumen de las Políticas Contables Materiales | F38: 2. Resumen de las Políticas Contables Materiales | G38: Opex | I38: Beneficio a Empleados | J38: Plan de Beneficios Definidos para Colaboradores (prima de antigüedad e indemnización): La Ley del Trabajo panameña estableció una prima de antigüedad de servicio... equivalente al 1.92% de los salarios pagados en el año... La Ley No. 44 de 12 de agosto de 1995 estableció... la obligación del empleador de constituir un fondo de cesantías... Plan de Contribución Definida: De acuerdo con la Ley No.51 del 27 de diciembre de 2005... La contribución para el año asciende a US$41,351 (2024: US$36,259). | K38: 41351 | L38: US$ | M38: sin escala | N38: prima antigüedad 1.92% | P38: Beneficios laborales (prima antigüedad 1.92%; fondo de cesantía). | T38: OK
A39: 2025 | B39: INA_UEPPSA_2025_0.pdf | C39: page-41 | D39: markdown.md | E39: 2. Resumen de las Políticas Contables Materiales | F39: 2. Resumen de las Políticas Contables Materiales | G39: Capital / patrimonio / dividendos | I39: Patrimonio | J39: El patrimonio está constituido por: Acciones comunes... acciones ordinarias nominativas no endosables de US$1 de valor nominal cada una. Contribución de capital: representa el exceso sobre el valor nominal del valor razonable de la contraprestación recibida... Déficit acumulado: representa las ganancias y pérdidas acumuladas. Se realiza una provisión para dividendos por el monto de cualquier dividendo declarado, debidamente autorizado por la Junta Directiva... | L39: US$ | M39: sin escala | T39: OK
A40: 2025 | B40: INA_UEPPSA_2025_0.pdf | C40: page-41 | D40: markdown.md | E40: 2. Resumen de las Políticas Contables Materiales | F40: 2. Resumen de las Políticas Contables Materiales | G40: Ingresos | I40: Reconocimiento de Ingresos por Energía (NIIF 15) | J40: La Compañía reconoce los ingresos por energía en los períodos en que entrega electricidad. Los precios contratados son facturados según las provisiones aplicables a los contratos de venta de energía y las ventas de mercado ocasional se facturan según los precios actuales del mercado. La unidad de medida de los precios contratados es dólar por megavatio hora ($/MWh). ... Según la NIIF 15, la Compañía reconoció los ingresos de los contratos con clientes en base al modelo de cinco pasos... la Compañía continúa reconociendo ingresos a lo largo del tiempo en lugar de un tiempo determinado. | L40: US$ | M40: $/MWh | P40: Ingreso = energía entregada; PPA + mercado ocasional; precios en $/MWh. | Q40: Driver de ingresos: MWh × $/MWh (contratado vs ocasional). | T40: OK
A41: 2025 | B41: INA_UEPPSA_2025_0.pdf | C41: page-47 | D41: markdown.md | E41: 3. Administración de Riesgos Financieros | F41: 3. Administración de Riesgos Financieros | G41: Riesgo financiero | I41: Factores de Riesgos Financieros | J41: Las actividades de la Compañía la exponen a una variedad de riesgos financieros: riesgo de mercado (incluyendo riesgo de moneda, riesgo de tasa de interés del valor razonable y riesgo de tasa de interés de flujo de efectivo), riesgo de crédito y riesgo de liquidez. La gestión del riesgo financiero es llevada a cabo por el Gerente General y el Director del Departamento de Finanzas bajo la supervisión de la Junta Directiva. | L41: US$ | M41: sin escala | T41: OK
A42: 2025 | B42: INA_UEPPSA_2025_0.pdf | C42: page-47 | D42: markdown.md | E42: 3. Administración de Riesgos Financieros | F42: 3. Administración de Riesgos Financieros | G42: Riesgo financiero | I42: Riesgo de Mercado - Riesgo Cambiario | J42: La Compañía no está sustancialmente expuesta a la fluctuación del cambio de moneda extranjera ya que sus ingresos, gastos y balances están expresados principalmente en dólares americanos (US$). | L42: US$ | M42: sin escala | T42: OK
A43: 2025 | B43: INA_UEPPSA_2025_0.pdf | C43: page-48 | D43: markdown.md | E43: 3. Administración de Riesgos Financieros | F43: 3. Administración de Riesgos Financieros | G43: Riesgo financiero | I43: Riesgo de Tasa de Interés / Sensibilidad | J43: El riesgo de la tasa de interés se origina principalmente de los bonos a largo plazo con tasas de interés fijas. La Compañía ha emitido bonos a una tasa de interés fija (Nota 13). | L43: US$ | M43: sin escala | P43: Deuda a tasa FIJA (6.5%) → sin riesgo de tasa flotante en el modelo. | T43: OK
A44: 2025 | B44: INA_UEPPSA_2025_0.pdf | C44: page-48 | D44: markdown.md | E44: 3. Administración de Riesgos Financieros | F44: 3. Administración de Riesgos Financieros | G44: Riesgo financiero | I44: Riesgo de Crédito - concentración | J44: La Compañía cuenta con una concentración de sus ingresos y cuentas por cobrar con las tres empresas distribuidoras que operan en la República de Panamá. Las ventas de energía a estos clientes representan aproximadamente 93% (2024: 84%) del total de los ingresos y 90% (2024: 89%) del total de las cuentas por cobrar al final del período. ... Por cada contrato de compra de energía (PPA) se requiere una garantía y el término de pago de las facturas... está promediado en un rango de 30 días... No se presentaron eventos de incumplimiento debido a facturas no pagadas al 31 de diciembre de 2025 y 2024. | L44: US$ | M44: sin escala | N44: cobro ~30 días | P44: Concentración: 3 DISCOs = 93% ingresos (2024:84%), 90% AR; cobro ~30 días. | Q44: DSO ~30 días para el working capital. | T44: OK
A45: 2025 | B45: INA_UEPPSA_2025_0.pdf | C45: page-48 | D45: markdown.md | E45: 3. Administración de Riesgos Financieros | F45: 3. Administración de Riesgos Financieros | G45: Riesgo financiero | I45: Riesgo de Liquidez | J45: El riesgo de liquidez es el riesgo de la Compañía de no cumplir con todas sus obligaciones. La Compañía reduce este riesgo manteniendo los niveles adecuados de efectivo... Los pasivos corrientes se cubren por el flujo de efectivo generado de las operaciones. | L45: US$ | M45: sin escala | T45: OK
A46: 2025 | B46: INA_UEPPSA_2025_0.pdf | C46: page-51 | D46: markdown.md | E46: 3. Administración de Riesgos Financieros | F46: 3. Administración de Riesgos Financieros | G46: Capital / patrimonio / dividendos | I46: Gestión de Riesgo de Capital (deuda/EBITDA) | J46: Los objetivos de la Compañía al administrar el capital son salvaguardar la habilidad de la Compañía de continuar como negocio en marcha... El capital es monitoreado por la relación deuda (bonos por pagar) a EBITDA. | L46: US$ | M46: sin escala | P46: Métrica de capital = Bonos/EBITDA (ver tabla índice EBITDA). | T46: OK
A47: 2025 | B47: INA_UEPPSA_2025_0.pdf | C47: page-51 | D47: markdown.md | E47: 3. Administración de Riesgos Financieros | F47: 3. Administración de Riesgos Financieros | G47: Instrumentos financieros | I47: Estimación del Valor Razonable | J47: El valor en libros del efectivo y equivalentes de efectivo, deudores comerciales y otras cuentas por cobrar, proveedores y otras cuentas por pagar se aproxima a su valor razonable debido a la naturaleza a corto plazo. El valor razonable de los bonos por pagar se detalla en la Nota 13. | L47: US$ | M47: sin escala | T47: OK
A48: 2025 | B48: INA_UEPPSA_2025_0.pdf | C48: page-48 | D48: tbl-14.html | E48: 3. Administración de Riesgos Financieros | F48: 3. Administración de Riesgos Financieros | G48: Riesgo financiero | I48: Calidad crediticia (efectivo en bancos y cuentas de fondo fiduciario) | J48: A+/AA- (2024: A+/AA-) | K48: 5128577 | L48: US$ | M48: sin escala | T48: OK
A49: 2025 | B49: INA_UEPPSA_2025_0.pdf | C49: page-48 | D49: tbl-14.html | E49: 3. Administración de Riesgos Financieros | F49: 3. Administración de Riesgos Financieros | G49: Riesgo financiero | I49: Calidad crediticia (efectivo en bancos y cuentas de fondo fiduciario) | J49: BB/BBB- (2024: BBB-/BB+) | K49: 67367 | L49: US$ | M49: sin escala | T49: OK
A50: 2025 | B50: INA_UEPPSA_2025_0.pdf | C50: page-48 | D50: tbl-14.html | E50: 3. Administración de Riesgos Financieros | F50: 3. Administración de Riesgos Financieros | G50: Riesgo financiero | I50: Calidad crediticia (efectivo en bancos y cuentas de fondo fiduciario) | J50: Total efectivo en bancos y cuentas de fondo fiduciario | K50: 5195944 | L50: US$ | M50: sin escala | S50: fila de total (sin etiqueta en el original) | T50: OK
A51: 2024 | B51: INA_UEPPSA_2025_0.pdf | C51: page-48 | D51: tbl-14.html | E51: 3. Administración de Riesgos Financieros | F51: 3. Administración de Riesgos Financieros | G51: Riesgo financiero | I51: Calidad crediticia (efectivo en bancos y cuentas de fondo fiduciario) | J51: A+/AA- (2024: A+/AA-) | K51: 4022162 | L51: US$ | M51: sin escala | T51: OK
A52: 2024 | B52: INA_UEPPSA_2025_0.pdf | C52: page-48 | D52: tbl-14.html | E52: 3. Administración de Riesgos Financieros | F52: 3. Administración de Riesgos Financieros | G52: Riesgo financiero | I52: Calidad crediticia (efectivo en bancos y cuentas de fondo fiduciario) | J52: BB/BBB- (2024: BBB-/BB+) | K52: 95346 | L52: US$ | M52: sin escala | T52: OK
A53: 2024 | B53: INA_UEPPSA_2025_0.pdf | C53: page-48 | D53: tbl-14.html | E53: 3. Administración de Riesgos Financieros | F53: 3. Administración de Riesgos Financieros | G53: Riesgo financiero | I53: Calidad crediticia (efectivo en bancos y cuentas de fondo fiduciario) | J53: Total efectivo en bancos y cuentas de fondo fiduciario | K53: 4117508 | L53: US$ | M53: sin escala | S53: fila de total (sin etiqueta en el original) | T53: OK
A54: 2023 | B54: INA_UEPPSA_2024_0.pdf | C54: page-48 | D54: tbl-14.html | E54: 3. Administración de Riesgos Financieros | F54: 3. Administración de Riesgos Financieros | G54: Riesgo financiero | I54: Calidad crediticia (efectivo en bancos y cuentas de fondo fiduciario) | J54: A+/AA- (2023: A+/AA-) | K54: 2237142 | L54: US$ | M54: sin escala | T54: OK
A55: 2023 | B55: INA_UEPPSA_2024_0.pdf | C55: page-48 | D55: tbl-14.html | E55: 3. Administración de Riesgos Financieros | F55: 3. Administración de Riesgos Financieros | G55: Riesgo financiero | I55: Calidad crediticia (efectivo en bancos y cuentas de fondo fiduciario) | J55: BB/BBB- (2023: BBB-/BB+) | K55: 15158407 | L55: US$ | M55: sin escala | T55: OK
A56: 2023 | B56: INA_UEPPSA_2024_0.pdf | C56: page-48 | D56: tbl-14.html | E56: 3. Administración de Riesgos Financieros | F56: 3. Administración de Riesgos Financieros | G56: Riesgo financiero | I56: Calidad crediticia (efectivo en bancos y cuentas de fondo fiduciario) | J56: Total efectivo en bancos y cuentas de fondos fiduciarios | K56: 17395549 | L56: US$ | M56: sin escala | S56: fila de total | T56: OK
A57: 2022 | B57: INA_UEPPSA_2023_0.pdf | C57: page-49 | D57: tbl-14.html | E57: 3. Administración de Riesgos Financieros | F57: 3. Administración de Riesgos Financieros | G57: Riesgo financiero | I57: Calidad crediticia (efectivo en bancos y cuentas de fondo fiduciario) | J57: A+/AA- (2022:A) | K57: 5323019 | L57: US$ | M57: sin escala | T57: OK
A58: 2022 | B58: INA_UEPPSA_2023_0.pdf | C58: page-49 | D58: tbl-14.html | E58: 3. Administración de Riesgos Financieros | F58: 3. Administración de Riesgos Financieros | G58: Riesgo financiero | I58: Calidad crediticia (efectivo en bancos y cuentas de fondo fiduciario) | J58: BBB-/BB+ (2022:AA-) | K58: 165776 | L58: US$ | M58: sin escala | T58: OK
A59: 2022 | B59: INA_UEPPSA_2023_0.pdf | C59: page-49 | D59: tbl-14.html | E59: 3. Administración de Riesgos Financieros | F59: 3. Administración de Riesgos Financieros | G59: Riesgo financiero | I59: Calidad crediticia (efectivo en bancos y cuentas de fondo fiduciario) | J59: Total efectivo en bancos y cuentas de fondos fiduciarios | K59: 5488795 | L59: US$ | M59: sin escala | S59: fila de total | T59: OK
A60: 2021 | B60: INA_UEPPSA_2022_0.pdf | C60: page-48 | D60: tbl-14.html | E60: 3. Administración de Riesgos Financieros | F60: 3. Administración de Riesgos Financieros | G60: Riesgo financiero | I60: Calidad crediticia (efectivo en bancos y cuentas de fondo fiduciario) | J60: Efectivo en bancos y cuentas de fondos fiduciarios (A y AA-) | K60: 5484101 | L60: US$ | M60: sin escala | T60: OK
A61: 2025 | B61: INA_UEPPSA_2025_0.pdf | C61: page-49 | D61: tbl-15.html | E61: 3. Administración de Riesgos Financieros | F61: 3. Administración de Riesgos Financieros | G61: Riesgo financiero | I61: Análisis de vencimientos - pasivos financieros no derivados (flujos contractuales no descontados) | J61: Bonos por pagar: Menos de 1 año 28143108; Entre 1 y 2 años 28213588; Entre 2 y 5 años 76436455; Más de 5 años 163773388; Total 296566539 | K61: 296566539 | L61: US$ | M61: sin escala | N61: flujos contractuales no descontados | Q61: Perfil de vencimientos de deuda/leases (laddering) para el schedule de deuda. | T61: OK
A62: 2025 | B62: INA_UEPPSA_2025_0.pdf | C62: page-49 | D62: tbl-15.html | E62: 3. Administración de Riesgos Financieros | F62: 3. Administración de Riesgos Financieros | G62: Riesgo financiero | I62: Análisis de vencimientos - pasivos financieros no derivados (flujos contractuales no descontados) | J62: Pasivos por arrendamiento: Menos de 1 año 871662; Entre 1 y 2 años 896165; Entre 2 y 5 años 2844363; Más de 5 años 6996168; Total 11608358 | K62: 11608358 | L62: US$ | M62: sin escala | N62: flujos contractuales no descontados | Q62: Perfil de vencimientos de deuda/leases (laddering) para el schedule de deuda. | T62: OK
A63: 2025 | B63: INA_UEPPSA_2025_0.pdf | C63: page-49 | D63: tbl-15.html | E63: 3. Administración de Riesgos Financieros | F63: 3. Administración de Riesgos Financieros | G63: Riesgo financiero | I63: Análisis de vencimientos - pasivos financieros no derivados (flujos contractuales no descontados) | J63: Proveedores y otras cuentas por pagar: Menos de 1 año 2311149; Entre 1 y 2 años -; Entre 2 y 5 años -; Más de 5 años -; Total 2311149 | K63: 2311149 | L63: US$ | M63: sin escala | N63: flujos contractuales no descontados | Q63: Perfil de vencimientos de deuda/leases (laddering) para el schedule de deuda. | T63: OK
A64: 2024 | B64: INA_UEPPSA_2025_0.pdf | C64: page-49 | D64: tbl-15.html | E64: 3. Administración de Riesgos Financieros | F64: 3. Administración de Riesgos Financieros | G64: Riesgo financiero | I64: Análisis de vencimientos - pasivos financieros no derivados (flujos contractuales no descontados) | J64: Bonos por pagar: Menos de 1 año 28018320; Entre 1 y 2 años 28143108; Entre 2 y 5 años 84043095; Más de 5 años 184380335; Total 324584858 | K64: 324584858 | L64: US$ | M64: sin escala | N64: flujos contractuales no descontados | Q64: Perfil de vencimientos de deuda/leases (laddering) para el schedule de deuda. | T64: OK
A65: 2024 | B65: INA_UEPPSA_2025_0.pdf | C65: page-49 | D65: tbl-15.html | E65: 3. Administración de Riesgos Financieros | F65: 3. Administración de Riesgos Financieros | G65: Riesgo financiero | I65: Análisis de vencimientos - pasivos financieros no derivados (flujos contractuales no descontados) | J65: Pasivos por arrendamiento: Menos de 1 año 847990; Entre 1 y 2 años 871662; Entre 2 y 5 años 2765507; Más de 5 años 7971188; Total 12456347 | K65: 12456347 | L65: US$ | M65: sin escala | N65: flujos contractuales no descontados | Q65: Perfil de vencimientos de deuda/leases (laddering) para el schedule de deuda. | T65: OK
A66: 2024 | B66: INA_UEPPSA_2025_0.pdf | C66: page-49 | D66: tbl-15.html | E66: 3. Administración de Riesgos Financieros | F66: 3. Administración de Riesgos Financieros | G66: Riesgo financiero | I66: Análisis de vencimientos - pasivos financieros no derivados (flujos contractuales no descontados) | J66: Proveedores y otras cuentas por pagar: Menos de 1 año 1419947; Entre 1 y 2 años -; Entre 2 y 5 años -; Más de 5 años -; Total 1419947 | K66: 1419947 | L66: US$ | M66: sin escala | N66: flujos contractuales no descontados | Q66: Perfil de vencimientos de deuda/leases (laddering) para el schedule de deuda. | T66: OK
A67: 2023 | B67: INA_UEPPSA_2024_0.pdf | C67: page-49 | D67: tbl-15.html | E67: 3. Administración de Riesgos Financieros | F67: 3. Administración de Riesgos Financieros | G67: Riesgo financiero | I67: Análisis de vencimientos - pasivos financieros no derivados (flujos contractuales no descontados) | J67: Bonos por pagar: Menos de 1 año 27721390; Entre 1 y 2 años 28018320; Entre 2 y 5 años 84269735; Más de 5 años 212296803; Total 352306248 | K67: 352306248 | L67: US$ | M67: sin escala | N67: flujos contractuales no descontados | Q67: Perfil de vencimientos de deuda/leases (laddering) para el schedule de deuda. | T67: OK
A68: 2023 | B68: INA_UEPPSA_2024_0.pdf | C68: page-49 | D68: tbl-15.html | E68: 3. Administración de Riesgos Financieros | F68: 3. Administración de Riesgos Financieros | G68: Riesgo financiero | I68: Análisis de vencimientos - pasivos financieros no derivados (flujos contractuales no descontados) | J68: Pasivos por arrendamiento: Menos de 1 año 825118; Entre 1 y 2 años 847990; Entre 2 y 5 años 2689361; Más de 5 años 8918996; Total 13281465 | K68: 13281465 | L68: US$ | M68: sin escala | N68: flujos contractuales no descontados | Q68: Perfil de vencimientos de deuda/leases (laddering) para el schedule de deuda. | T68: OK
A69: 2023 | B69: INA_UEPPSA_2024_0.pdf | C69: page-49 | D69: tbl-15.html | E69: 3. Administración de Riesgos Financieros | F69: 3. Administración de Riesgos Financieros | G69: Riesgo financiero | I69: Análisis de vencimientos - pasivos financieros no derivados (flujos contractuales no descontados) | J69: Proveedores y otras cuentas por pagar: Menos de 1 año 2536737; Entre 1 y 2 años -; Entre 2 y 5 años -; Más de 5 años -; Total 2536737 | K69: 2536737 | L69: US$ | M69: sin escala | N69: flujos contractuales no descontados | Q69: Perfil de vencimientos de deuda/leases (laddering) para el schedule de deuda. | T69: OK
A70: 2022 | B70: INA_UEPPSA_2023_0.pdf | C70: page-50 | D70: tbl-15.html | E70: 3. Administración de Riesgos Financieros | F70: 3. Administración de Riesgos Financieros | G70: Riesgo financiero | I70: Análisis de vencimientos - pasivos financieros no derivados (flujos contractuales no descontados) | J70: Bonos por pagar: Menos de 1 año 26885088; Entre 1 y 2 años 27721390; Entre 2 y 5 años 84375015; Más de 5 años 240209843; Total 379191336 | K70: 379191336 | L70: US$ | M70: sin escala | N70: flujos contractuales no descontados | Q70: Perfil de vencimientos de deuda/leases (laddering) para el schedule de deuda. | T70: OK
A71: 2022 | B71: INA_UEPPSA_2023_0.pdf | C71: page-50 | D71: tbl-15.html | E71: 3. Administración de Riesgos Financieros | F71: 3. Administración de Riesgos Financieros | G71: Riesgo financiero | I71: Análisis de vencimientos - pasivos financieros no derivados (flujos contractuales no descontados) | J71: Pasivos por arrendamiento: Menos de 1 año 803013; Entre 1 y 2 años 825118; Entre 2 y 5 años 2615817; Más de 5 años 9840530; Total 14084478 | K71: 14084478 | L71: US$ | M71: sin escala | N71: flujos contractuales no descontados | Q71: Perfil de vencimientos de deuda/leases (laddering) para el schedule de deuda. | T71: OK
A72: 2022 | B72: INA_UEPPSA_2023_0.pdf | C72: page-50 | D72: tbl-15.html | E72: 3. Administración de Riesgos Financieros | F72: 3. Administración de Riesgos Financieros | G72: Riesgo financiero | I72: Análisis de vencimientos - pasivos financieros no derivados (flujos contractuales no descontados) | J72: Proveedores y otras cuentas por pagar: Menos de 1 año 1285733; Entre 1 y 2 años -; Entre 2 y 5 años -; Más de 5 años -; Total 1285733 | K72: 1285733 | L72: US$ | M72: sin escala | N72: flujos contractuales no descontados | Q72: Perfil de vencimientos de deuda/leases (laddering) para el schedule de deuda. | T72: OK
... A75: 2021 | B75: INA_UEPPSA_2022_0.pdf | C75: page-49 | D75: tbl-15.html | E75: 3. Administración de Riesgos Financieros | F75: 3. Administración de Riesgos Financieros | G75: Riesgo financiero | I75: Análisis de vencimientos - pasivos financieros no derivados (flujos contractuales no descontados) | J75: Proveedores y otras cuentas por pagar: Menos de 1 año 2652919; Entre 1 y 2 años -; Entre 2 y 5 años -; Más de 5 años -; Total 2652919 | K75: 2652919 | L75: US$ | M75: sin escala | N75: flujos contractuales no descontados | Q75: Perfil de vencimientos de deuda/leases (laddering) para el schedule de deuda. | T75: OK
A76: 2025 | B76: INA_UEPPSA_2025_0.pdf | C76: page-50 | D76: tbl-16.html | E76: 3. Administración de Riesgos Financieros | F76: 3. Administración de Riesgos Financieros | G76: Deuda / bonos / préstamos / leases | H76: Efectivo y equivalentes de efectivo | I76: Conciliación de deuda neta (composición) | J76: Efectivo y equivalentes de efectivo | K76: 5197344 | L76: US$ | M76: sin escala | R76: EEFF!F20 | T76: OK
A77: 2025 | B77: INA_UEPPSA_2025_0.pdf | C77: page-50 | D77: tbl-16.html | E77: 3. Administración de Riesgos Financieros | F77: 3. Administración de Riesgos Financieros | G77: Deuda / bonos / préstamos / leases | I77: Conciliación de deuda neta (composición) | J77: Bonos por pagar | K77: -204411000 | L77: US$ | M77: sin escala | T77: OK
A78: 2025 | B78: INA_UEPPSA_2025_0.pdf | C78: page-50 | D78: tbl-16.html | E78: 3. Administración de Riesgos Financieros | F78: 3. Administración de Riesgos Financieros | G78: Deuda / bonos / préstamos / leases | I78: Conciliación de deuda neta (composición) | J78: Pasivos por arrendamiento | K78: -7539045 | L78: US$ | M78: sin escala | T78: OK
A79: 2025 | B79: INA_UEPPSA_2025_0.pdf | C79: page-50 | D79: tbl-16.html | E79: 3. Administración de Riesgos Financieros | F79: 3. Administración de Riesgos Financieros | G79: Deuda / bonos / préstamos / leases | I79: Conciliación de deuda neta (composición) | J79: Deuda neta | K79: -206752701 | L79: US$ | M79: sin escala | Q79: Deuda neta = base de credit metrics. | S79: subtotal deuda neta | T79: OK
A80: 2024 | B80: INA_UEPPSA_2025_0.pdf | C80: page-50 | D80: tbl-16.html | E80: 3. Administración de Riesgos Financieros | F80: 3. Administración de Riesgos Financieros | G80: Deuda / bonos / préstamos / leases | H80: Efectivo y equivalentes de efectivo | I80: Conciliación de deuda neta (composición) | J80: Efectivo y equivalentes de efectivo | K80: 4118908 | L80: US$ | M80: sin escala | R80: EEFF!E20 | T80: OK
A81: 2024 | B81: INA_UEPPSA_2025_0.pdf | C81: page-50 | D81: tbl-16.html | E81: 3. Administración de Riesgos Financieros | F81: 3. Administración de Riesgos Financieros | G81: Deuda / bonos / préstamos / leases | I81: Conciliación de deuda neta (composición) | J81: Bonos por pagar | K81: -218407000 | L81: US$ | M81: sin escala | T81: OK
A82: 2024 | B82: INA_UEPPSA_2025_0.pdf | C82: page-50 | D82: tbl-16.html | E82: 3. Administración de Riesgos Financieros | F82: 3. Administración de Riesgos Financieros | G82: Deuda / bonos / préstamos / leases | I82: Conciliación de deuda neta (composición) | J82: Pasivos por arrendamiento | K82: -7810454 | L82: US$ | M82: sin escala | T82: OK
A83: 2024 | B83: INA_UEPPSA_2025_0.pdf | C83: page-50 | D83: tbl-16.html | E83: 3. Administración de Riesgos Financieros | F83: 3. Administración de Riesgos Financieros | G83: Deuda / bonos / préstamos / leases | I83: Conciliación de deuda neta (composición) | J83: Deuda neta | K83: -222098546 | L83: US$ | M83: sin escala | Q83: Deuda neta = base de credit metrics. | S83: subtotal deuda neta | T83: OK
A84: 2023 | B84: INA_UEPPSA_2024_0.pdf | C84: page-50 | D84: tbl-16.html | E84: 3. Administración de Riesgos Financieros | F84: 3. Administración de Riesgos Financieros | G84: Deuda / bonos / préstamos / leases | H84: Efectivo y equivalentes de efectivo | I84: Conciliación de deuda neta (composición) | J84: Efectivo y equivalentes de efectivo | K84: 17396949 | L84: US$ | M84: sin escala | R84: EEFF!D20 | T84: OK
A85: 2023 | B85: INA_UEPPSA_2024_0.pdf | C85: page-50 | D85: tbl-16.html | E85: 3. Administración de Riesgos Financieros | F85: 3. Administración de Riesgos Financieros | G85: Deuda / bonos / préstamos / leases | I85: Conciliación de deuda neta (composición) | J85: Bonos por pagar | K85: -231256000 | L85: US$ | M85: sin escala | T85: OK
A86: 2023 | B86: INA_UEPPSA_2024_0.pdf | C86: page-50 | D86: tbl-16.html | E86: 3. Administración de Riesgos Financieros | F86: 3. Administración de Riesgos Financieros | G86: Deuda / bonos / préstamos / leases | I86: Conciliación de deuda neta (composición) | J86: Pasivos por arrendamiento | K86: -8040342 | L86: US$ | M86: sin escala | T86: OK
A87: 2023 | B87: INA_UEPPSA_2024_0.pdf | C87: page-50 | D87: tbl-16.html | E87: 3. Administración de Riesgos Financieros | F87: 3. Administración de Riesgos Financieros | G87: Deuda / bonos / préstamos / leases | I87: Conciliación de deuda neta (composición) | J87: Deuda neta | K87: -221899393 | L87: US$ | M87: sin escala | S87: subtotal | T87: OK
A88: 2022 | B88: INA_UEPPSA_2023_0.pdf | C88: page-50 | D88: tbl-16.html | E88: 3. Administración de Riesgos Financieros | F88: 3. Administración de Riesgos Financieros | G88: Deuda / bonos / préstamos / leases | H88: Efectivo y equivalentes de efectivo | I88: Conciliación de deuda neta (composición) | J88: Efectivo y equivalentes de efectivo | K88: 5490195 | L88: US$ | M88: sin escala | R88: EEFF!C20 | T88: OK
A89: 2022 | B89: INA_UEPPSA_2023_0.pdf | C89: page-50 | D89: tbl-16.html | E89: 3. Administración de Riesgos Financieros | F89: 3. Administración de Riesgos Financieros | G89: Deuda / bonos / préstamos / leases | I89: Conciliación de deuda neta (composición) | J89: Bonos por pagar | K89: -242512000 | L89: US$ | M89: sin escala | T89: OK
A90: 2022 | B90: INA_UEPPSA_2023_0.pdf | C90: page-50 | D90: tbl-16.html | E90: 3. Administración de Riesgos Financieros | F90: 3. Administración de Riesgos Financieros | G90: Deuda / bonos / préstamos / leases | I90: Conciliación de deuda neta (composición) | J90: Pasivos por arrendamiento | K90: -8232436 | L90: US$ | M90: sin escala | T90: OK
A91: 2022 | B91: INA_UEPPSA_2023_0.pdf | C91: page-50 | D91: tbl-16.html | E91: 3. Administración de Riesgos Financieros | F91: 3. Administración de Riesgos Financieros | G91: Deuda / bonos / préstamos / leases | I91: Conciliación de deuda neta (composición) | J91: Deuda neta | K91: -245254241 | L91: US$ | M91: sin escala | S91: subtotal | T91: OK
A92: 2021 | B92: INA_UEPPSA_2022_0.pdf | C92: page-49 | D92: tbl-16.html | E92: 3. Administración de Riesgos Financieros | F92: 3. Administración de Riesgos Financieros | G92: Deuda / bonos / préstamos / leases | H92: Efectivo y equivalentes de efectivo | I92: Conciliación de deuda neta (composición) | J92: Efectivo y equivalentes de efectivo | K92: 5485501 | L92: US$ | M92: sin escala | R92: EEFF!B20 | T92: OK
A93: 2021 | B93: INA_UEPPSA_2022_0.pdf | C93: page-49 | D93: tbl-16.html | E93: 3. Administración de Riesgos Financieros | F93: 3. Administración de Riesgos Financieros | G93: Deuda / bonos / préstamos / leases | I93: Conciliación de deuda neta (composición) | J93: Bonos por pagar | K93: -252661000 | L93: US$ | M93: sin escala | T93: OK
A94: 2021 | B94: INA_UEPPSA_2022_0.pdf | C94: page-49 | D94: tbl-16.html | E94: 3. Administración de Riesgos Financieros | F94: 3. Administración de Riesgos Financieros | G94: Deuda / bonos / préstamos / leases | I94: Conciliación de deuda neta (composición) | J94: Pasivos por arrendamiento | K94: -8390168 | L94: US$ | M94: sin escala | T94: OK
A95: 2021 | B95: INA_UEPPSA_2022_0.pdf | C95: page-49 | D95: tbl-16.html | E95: 3. Administración de Riesgos Financieros | F95: 3. Administración de Riesgos Financieros | G95: Deuda / bonos / préstamos / leases | I95: Conciliación de deuda neta (composición) | J95: Deuda neta | K95: -255565667 | L95: US$ | M95: sin escala | S95: subtotal | T95: OK
A96: 2025 | B96: INA_UEPPSA_2025_0.pdf | C96: page-50 | D96: tbl-17.html | E96: 3. Administración de Riesgos Financieros | F96: 3. Administración de Riesgos Financieros | G96: Deuda / bonos / préstamos / leases | I96: Conciliación de movimientos de deuda neta | J96: 31 de diciembre de 2023 (saldo): Pasivos por Arrendamiento -8040342; Bonos por Pagar -231256000; Sub-total -239296342; Efectivo y Equivalentes 17396949; Total -221899393 | K96: -221899393 | L96: US$ | M96: sin escala | Q96: Movimiento de deuda neta (pagos de bonos/leases y flujo de efectivo). | T96: OK
A97: 2025 | B97: INA_UEPPSA_2025_0.pdf | C97: page-50 | D97: tbl-17.html | E97: 3. Administración de Riesgos Financieros | F97: 3. Administración de Riesgos Financieros | G97: Deuda / bonos / préstamos / leases | I97: Conciliación de movimientos de deuda neta | J97: Pago (2024): Pasivos por Arrendamiento 229888; Bonos por Pagar 12849000; Sub-total 13078888; Efectivo y Equivalentes ; Total 13078888 | K97: 13078888 | L97: US$ | M97: sin escala | Q97: Movimiento de deuda neta (pagos de bonos/leases y flujo de efectivo). | T97: OK
A98: 2025 | B98: INA_UEPPSA_2025_0.pdf | C98: page-50 | D98: tbl-17.html | E98: 3. Administración de Riesgos Financieros | F98: 3. Administración de Riesgos Financieros | G98: Deuda / bonos / préstamos / leases | I98: Conciliación de movimientos de deuda neta | J98: Flujo de efectivo (2024): Pasivos por Arrendamiento ; Bonos por Pagar ; Sub-total ; Efectivo y Equivalentes -13278041; Total -13278041 | K98: -13278041 | L98: US$ | M98: sin escala | Q98: Movimiento de deuda neta (pagos de bonos/leases y flujo de efectivo). | T98: OK
A99: 2025 | B99: INA_UEPPSA_2025_0.pdf | C99: page-50 | D99: tbl-17.html | E99: 3. Administración de Riesgos Financieros | F99: 3. Administración de Riesgos Financieros | G99: Deuda / bonos / préstamos / leases | I99: Conciliación de movimientos de deuda neta | J99: 31 de diciembre de 2024 (saldo): Pasivos por Arrendamiento -7810454; Bonos por Pagar -218407000; Sub-total -226217454; Efectivo y Equivalentes 4118908; Total -222098546 | K99: -222098546 | L99: US$ | M99: sin escala | Q99: Movimiento de deuda neta (pagos de bonos/leases y flujo de efectivo). | T99: OK
A100: 2025 | B100: INA_UEPPSA_2025_0.pdf | C100: page-50 | D100: tbl-17.html | E100: 3. Administración de Riesgos Financieros | F100: 3. Administración de Riesgos Financieros | G100: Deuda / bonos / préstamos / leases | I100: Conciliación de movimientos de deuda neta | J100: Pago (2025): Pasivos por Arrendamiento 271409; Bonos por Pagar 13996000; Sub-total 14267409; Efectivo y Equivalentes -; Total 14267409 | K100: 14267409 | L100: US$ | M100: sin escala | Q100: Movimiento de deuda neta (pagos de bonos/leases y flujo de efectivo). | T100: OK
A101: 2025 | B101: INA_UEPPSA_2025_0.pdf | C101: page-50 | D101: tbl-17.html | E101: 3. Administración de Riesgos Financieros | F101: 3. Administración de Riesgos Financieros | G101: Deuda / bonos / préstamos / leases | I101: Conciliación de movimientos de deuda neta | J101: Flujo de efectivo (2025): Pasivos por Arrendamiento -; Bonos por Pagar -; Sub-total -; Efectivo y Equivalentes 1078436; Total 1078436 | K101: 1078436 | L101: US$ | M101: sin escala | Q101: Movimiento de deuda neta (pagos de bonos/leases y flujo de efectivo). | T101: OK
A102: 2025 | B102: INA_UEPPSA_2025_0.pdf | C102: page-50 | D102: tbl-17.html | E102: 3. Administración de Riesgos Financieros | F102: 3. Administración de Riesgos Financieros | G102: Deuda / bonos / préstamos / leases | I102: Conciliación de movimientos de deuda neta | J102: 31 de diciembre de 2025 (saldo): Pasivos por Arrendamiento -7539045; Bonos por Pagar -204411000; Sub-total -211950045; Efectivo y Equivalentes 5197344; Total -206752701 | K102: -206752701 | L102: US$ | M102: sin escala | Q102: Movimiento de deuda neta (pagos de bonos/leases y flujo de efectivo). | T102: OK
A103: 2021 | B103: INA_UEPPSA_2022_0.pdf | C103: page-50 | D103: tbl-17.html | E103: 3. Administración de Riesgos Financieros | F103: 3. Administración de Riesgos Financieros | G103: Deuda / bonos / préstamos / leases | I103: Conciliación de movimientos de deuda neta | J103: 31 de diciembre de 2020 (saldo): Pasivos por Arrendamiento -8516692; Bonos por Pagar -262664000; Sub-total -271180692; Efectivo y Equivalentes 14871800; Total -256308892 | K103: -256308892 | L103: US$ | M103: sin escala | Q103: Movimiento de deuda neta (pagos de bonos/leases y flujo de efectivo). | T103: OK
...

Sheet ModeloFinanciero
A1: UEP Penonomé II, S. A.
A2: Estados Financieros Auditados FY21-FY25
A3: en US$ sin escala
A5: Años | B5: FY21A | C5: FY22A | D5: FY23A | E5: FY24A | F5: FY25A | G5: FY26E | H5: FY27E | I5: FY28E | J5: FY29E | K5: FY30E
A6: Estado de Resultado
A7: Ingresos por energía | B7: =EEFF!B7 -> 42036085 | C7: =EEFF!C7 -> 40987418 | D7: =EEFF!D7 -> 54587421 | E7: =EEFF!E7 -> 42653811 | F7: =EEFF!F7 -> 42404701 | G7: =Supuestos!G44 -> 41719195 | H7: =Supuestos!H44 -> 41713333 | I7: =Supuestos!I44 -> 41708092 | J7: =Supuestos!J44 -> 34098586 | K7: =Supuestos!K44 -> 27211924
A8: Costos de bienes y servicios | B8: =EEFF!B8 -> -22857327 | C8: =EEFF!C8 -> -21858853 | D8: =EEFF!D8 -> -25573871 | E8: =EEFF!E8 -> -25736347 | F8: =EEFF!F8 -> -24413955 | G8: =-Supuestos!G54 -> -22731827 | H8: =-Supuestos!H54 -> -22738827 | I8: =-Supuestos!I54 -> -22746827 | J8: =-Supuestos!J54 -> -22594738 | K8: =-Supuestos!K54 -> -22603738
A9: Utilidad bruta | B9: =EEFF!B9 -> 19178758 | C9: =EEFF!C9 -> 19128565 | D9: =EEFF!D9 -> 29013550 | E9: =EEFF!E9 -> 16917464 | F9: =EEFF!F9 -> 17990746 | G9: =G7+G8 -> 18987368 | H9: =H7+H8 -> 18974506 | I9: =I7+I8 -> 18961265 | J9: =J7+J8 -> 11503848 | K9: =K7+K8 -> 4608185.5
A10: Gastos administrativos | B10: =EEFF!B10 -> -3266942 | C10: =EEFF!C10 -> -3405988 | D10: =EEFF!D10 -> -4482435 | E10: =EEFF!E10 -> -3436087 | F10: =EEFF!F10 -> -3908720 | G10: =-Supuestos!G58 -> -3660000 | H10: =-Supuestos!H58 -> -3660000 | I10: =-Supuestos!I58 -> -3660000 | J10: =-Supuestos!J58 -> -3660000 | K10: =-Supuestos!K58 -> -3660000
A11: Utilidad operativa | B11: =EEFF!B11 -> 15911816 | C11: =EEFF!C11 -> 15722577 | D11: =EEFF!D11 -> 24531115 | E11: =EEFF!E11 -> 13481377 | F11: =EEFF!F11 -> 14082026 | G11: =G9+G10 -> 15327368 | H11: =H9+H10 -> 15314506 | I11: =I9+I10 -> 15301265 | J11: =J9+J10 -> 7843848.1 | K11: =K9+K10 -> 948185.54
A12: Costos financieros, neto | B12: =EEFF!B12 -> -14126147 | C12: =EEFF!C12 -> -9881077 | D12: =EEFF!D12 -> -16142876 | E12: =EEFF!E12 -> -15193459 | F12: =EEFF!F12 -> -14336109 | G12: =F12 -> -14336109 | H12: =G12 -> -14336109 | I12: =H12 -> -14336109 | J12: =I12 -> -14336109 | K12: =J12 -> -14336109
A13: Otros ingresos | B13: =EEFF!B13 -> 34397 | C13: =EEFF!C13 -> 130429 | D13: =EEFF!D13 -> 6770 | E13: =EEFF!E13 -> 1010 | F13: =EEFF!F13 -> 81975 | G13: =F13 -> 81975 | H13: =G13 -> 81975 | I13: =H13 -> 81975 | J13: =I13 -> 81975 | K13: =J13 -> 81975
A14: Pérdida antes del impuesto sobre la renta | B14: =EEFF!B14 -> 1820066 | C14: =EEFF!C14 -> 5971929 | D14: =EEFF!D14 -> 8395009 | E14: =EEFF!E14 -> -1711072 | F14: =EEFF!F14 -> -172108 | G14: =G11+G12+G13 -> 1073234.2 | H14: =H11+H12+H13 -> 1060371.9 | I14: =I11+I12+I13 -> 1047131.1 | J14: =J11+J12+J13 -> -6410285.9 | K14: =K11+K12+K13 -> -13305948
A15: Impuesto sobre la renta | B15: =EEFF!B15 -> -2683428 | C15: =EEFF!C15 -> 599370 | D15: =EEFF!D15 -> -820467 | E15: =EEFF!E15 -> -681267 | F15: =EEFF!F15 -> -497187 | G15: =F15 -> -497187 | H15: =G15 -> -497187 | I15: =H15 -> -497187 | J15: =I15 -> -497187 | K15: =J15 -> -497187
A16: Pérdida del año | B16: =EEFF!B16 -> -863362 | C16: =EEFF!C16 -> 6571299 | D16: =EEFF!D16 -> 7574542 | E16: =EEFF!E16 -> -2392339 | F16: =EEFF!F16 -> -669295 | G16: =G14+G15 -> 576047.2 | H16: =H14+H15 -> 563184.88 | I16: =I14+I15 -> 549944.09 | J16: =J14+J15 -> -6907472.9 | K16: =K14+K15 -> -13803135
A18: Años | B18: FY21A | C18: FY22A | D18: FY23A | E18: FY24A | F18: FY25A | G18: FY26E | H18: FY27E | I18: FY28E | J18: FY29E | K18: FY30E
A19: Balance General
A20: Efectivo y equivalentes de efectivo | B20: =EEFF!B20 -> 5485501 | C20: =EEFF!C20 -> 5490195 | D20: =EEFF!D20 -> 17396949 | E20: =EEFF!E20 -> 4118908 | F20: =EEFF!F20 -> 5197344 | G20: =F20 -> 5197344 | H20: =G20 -> 5197344 | I20: =H20 -> 5197344 | J20: =I20 -> 5197344 | K20: =J20 -> 5197344
A21: Deudores comerciales y otras cuentas por cobrar | B21: =EEFF!B21 -> 8440721 | C21: =EEFF!C21 -> 6989164 | D21: =EEFF!D21 -> 7127866 | E21: =EEFF!E21 -> 3904545 | F21: =EEFF!F21 -> 4837614 | G21: =F21 -> 4837614 | H21: =G21 -> 4837614 | I21: =H21 -> 4837614 | J21: =I21 -> 4837614 | K21: =J21 -> 4837614
A22: Deuda por cobrar a parte relacionada | B22: =EEFF!B28 -> 21480114 | C22: =EEFF!C28 -> 20483131 | D22: =EEFF!D28 -> 19345052 | E22: =EEFF!E28 -> 18105378 | F22: =EEFF!F28 -> 16773057 | G22: =F22 -> 16773057 | H22: =G22 -> 16773057 | I22: =H22 -> 16773057 | J22: =I22 -> 16773057 | K22: =J22 -> 16773057
A23: Gastos pagados por adelantado | B23: =EEFF!B23 -> 1954336 | C23: =EEFF!C23 -> 4991808 | D23: =EEFF!D23 -> 1291507 | E23: =EEFF!E23 -> 1963129 | F23: =EEFF!F23 -> 860787 | G23: =F23 -> 860787 | H23: =G23 -> 860787 | I23: =H23 -> 860787 | J23: =I23 -> 860787 | K23: =J23 -> 860787
A24: Inventario | B24: =EEFF!B24 -> 38791 | C24: =EEFF!C24 -> 40685 | D24: =EEFF!D24 -> 51726 | E24: =EEFF!E24 -> 71702 | F24: =EEFF!F24 -> 84203 | G24: =F24 -> 84203 | H24: =G24 -> 84203 | I24: =H24 -> 84203 | J24: =I24 -> 84203 | K24: =J24 -> 84203
A25: Total de activos corrientes | B25: =EEFF!B25 -> 16818281 | C25: =EEFF!C25 -> 18508834 | D25: =EEFF!D25 -> 27006128 | E25: =EEFF!E25 -> 11297958 | F25: =EEFF!F25 -> 12312270 | G25: =F25 -> 12312270 | H25: =G25 -> 12312270 | I25: =H25 -> 12312270 | J25: =I25 -> 12312270 | K25: =J25 -> 12312270
A26: Planta y equipo, neto | B26: =EEFF!B26 -> 216209163 | C26: =EEFF!C26 -> 202848696 | D26: =EEFF!D26 -> 193996920 | E26: =EEFF!E26 -> 180311071 | F26: =EEFF!F26 -> 167298071 | G26: =F26 -> 167298071 | H26: =G26 -> 167298071 | I26: =H26 -> 167298071 | J26: =I26 -> 167298071 | K26: =J26 -> 167298071
A27: Plusvalía | B27: =EEFF!B27 -> 20000000 | C27: =EEFF!C27 -> 20000000 | D27: =EEFF!D27 -> 20000000 | E27: =EEFF!E27 -> 20000000 | F27: =EEFF!F27 -> 20000000 | G27: =F27 -> 20000000 | H27: =G27 -> 20000000 | I27: =H27 -> 20000000 | J27: =I27 -> 20000000 | K27: =J27 -> 20000000
A28: Deuda por cobrar a parte relacionada | B28: =EEFF!B28 -> 21480114 | C28: =EEFF!C28 -> 20483131 | D28: =EEFF!D28 -> 19345052 | E28: =EEFF!E28 -> 18105378 | F28: =EEFF!F28 -> 16773057 | G28: =F28 -> 16773057 | H28: =G28 -> 16773057 | I28: =H28 -> 16773057 | J28: =I28 -> 16773057 | K28: =J28 -> 16773057
A29: Activos intangibles, neto | B29: =EEFF!B29 -> 109685 | C29: =EEFF!C29 -> 105268 | D29: =EEFF!D29 -> 100851 | E29: =EEFF!E29 -> 96435 | F29: =EEFF!F29 -> 92018 | G29: =F29 -> 92018 | H29: =G29 -> 92018 | I29: =H29 -> 92018 | J29: =I29 -> 92018 | K29: =J29 -> 92018
A30: Fondo de cesantía | B30: =EEFF!B30 -> 0 | C30: =EEFF!C30 -> 13934 | D30: =EEFF!D30 -> 17359 | E30: =EEFF!E30 -> 21782 | F30: =EEFF!F30 -> 26510 | G30: =F30 -> 26510 | H30: =G30 -> 26510 | I30: =H30 -> 26510 | J30: =I30 -> 26510 | K30: =J30 -> 26510
A31: Total de activos no corrientes | B31: =EEFF!B31 -> 257798962 | C31: =EEFF!C31 -> 243451029 | D31: =EEFF!D31 -> 233460182 | E31: =EEFF!E31 -> 218534666 | F31: =EEFF!F31 -> 204189656 | G31: =F31 -> 204189656 | H31: =G31 -> 204189656 | I31: =H31 -> 204189656 | J31: =I31 -> 204189656 | K31: =J31 -> 204189656
A32: Total de activos | B32: =EEFF!B32 -> 274617243 | C32: =EEFF!C32 -> 261959863 | D32: =EEFF!D32 -> 260466310 | E32: =EEFF!E32 -> 229832624 | F32: =EEFF!F32 -> 216501926 | G32: =F32 -> 216501926 | H32: =G32 -> 216501926 | I32: =H32 -> 216501926 | J32: =I32 -> 216501926 | K32: =J32 -> 216501926
A33: Bonos por pagar | B33: =EEFF!B40 -> 234949078 | C33: =EEFF!C40 -> 224181572 | D33: =EEFF!D40 -> 211820687 | E33: =EEFF!E40 -> 198290030 | F33: =EEFF!F40 -> 183665429 | G33: =F33 -> 183665429 | H33: =G33 -> 183665429 | I33: =H33 -> 183665429 | J33: =I33 -> 183665429 | K33: =J33 -> 183665429
A34: Proveedores y otras cuentas por pagar | B34: =EEFF!B34 -> 2652919 | C34: =EEFF!C34 -> 1285733 | D34: =EEFF!D34 -> 2536737 | E34: =EEFF!E34 -> 1419947 | F34: =EEFF!F34 -> 2311149 | G34: =F34 -> 2311149 | H34: =G34 -> 2311149 | I34: =H34 -> 2311149 | J34: =I34 -> 2311149 | K34: =J34 -> 2311149
A35: Pasivos por arrendamiento | B35: =EEFF!B37 -> 8232437 | C35: =EEFF!C37 -> 8040342 | D35: =EEFF!D37 -> 7810454 | E35: =EEFF!E37 -> 7539044 | F35: =EEFF!F37 -> 7222062 | G35: =F35 -> 7222062 | H35: =G35 -> 7222062 | I35: =H35 -> 7222062 | J35: =I35 -> 7222062 | K35: =J35 -> 7222062
A36: Total de pasivos corrientes | B36: =EEFF!B36 -> 17110509 | C36: =EEFF!C36 -> 16717953 | D36: =EEFF!D36 -> 19394070 | E36: =EEFF!E36 -> 19275472 | F36: =EEFF!F36 -> 21028313 | G36: =F36 -> 21028313 | H36: =G36 -> 21028313 | I36: =H36 -> 21028313 | J36: =I36 -> 21028313 | K36: =J36 -> 21028313
A37: Pasivos por arrendamiento | B37: =EEFF!B37 -> 8232437 | C37: =EEFF!C37 -> 8040342 | D37: =EEFF!D37 -> 7810454 | E37: =EEFF!E37 -> 7539044 | F37: =EEFF!F37 -> 7222062 | G37: =F37 -> 7222062 | H37: =G37 -> 7222062 | I37: =H37 -> 7222062 | J37: =I37 -> 7222062 | K37: =J37 -> 7222062
A38: Impuesto sobre la renta diferido | B38: =EEFF!B38 -> 1204764 | C38: =EEFF!C38 -> 605394 | D38: =EEFF!D38 -> 1425861 | E38: =EEFF!E38 -> 2107128 | F38: =EEFF!F38 -> 2604315 | G38: =F38 -> 2604315 | H38: =G38 -> 2604315 | I38: =H38 -> 2604315 | J38: =I38 -> 2604315 | K38: =J38 -> 2604315
A39: Provisiones | B39: =EEFF!B39 -> 0 | C39: =EEFF!C39 -> 347922 | D39: =EEFF!D39 -> 374016 | E39: =EEFF!E39 -> 402067 | F39: =EEFF!F39 -> 432222 | G39: =F39 -> 432222 | H39: =G39 -> 432222 | I39: =H39 -> 432222 | J39: =I39 -> 432222 | K39: =J39 -> 432222
A40: Bonos por pagar | B40: =EEFF!B40 -> 234949078 | C40: =EEFF!C40 -> 224181572 | D40: =EEFF!D40 -> 211820687 | E40: =EEFF!E40 -> 198290030 | F40: =EEFF!F40 -> 183665429 | G40: =F40 -> 183665429 | H40: =G40 -> 183665429 | I40: =H40 -> 183665429 | J40: =I40 -> 183665429 | K40: =J40 -> 183665429
A41: Instrumento financiero derivado | B41: =EEFF!B41 -> 7625074 | C41: =EEFF!C41 -> 0 | D41: =EEFF!D41 -> 0 | E41: =EEFF!E41 -> 0 | F41: =EEFF!F41 -> 0
A42: Total de pasivos no corrientes | B42: =EEFF!B42 -> 252011353 | C42: =EEFF!C42 -> 233175230 | D42: =EEFF!D42 -> 221431018 | E42: =EEFF!E42 -> 208338269 | F42: =EEFF!F42 -> 193924028 | G42: =F42 -> 193924028 | H42: =G42 -> 193924028 | I42: =H42 -> 193924028 | J42: =I42 -> 193924028 | K42: =J42 -> 193924028
A43: Total de pasivos | B43: =EEFF!B43 -> 269121862 | C43: =EEFF!C43 -> 249893183 | D43: =EEFF!D43 -> 240825088 | E43: =EEFF!E43 -> 227613741 | F43: =EEFF!F43 -> 214952341 | G43: =F43 -> 214952341 | H43: =G43 -> 214952341 | I43: =H43 -> 214952341 | J43: =I43 -> 214952341 | K43: =J43 -> 214952341
A44: Acciones comunes con un valor nominal de US$1 cada una; autorizadas y emitidas: 1,050 acciones | B44: =EEFF!B44 -> 1050 | C44: =EEFF!C44 -> 1050 | D44: =EEFF!D44 -> 1050 | E44: =EEFF!E44 -> 1050 | F44: =EEFF!F44 -> 1050 | G44: =F44 -> 1050 | H44: =G44 -> 1050 | I44: =H44 -> 1050 | J44: =I44 -> 1050 | K44: =J44 -> 1050
A45: Contribución de capital | B45: =EEFF!B45 -> 55974250 | C45: =EEFF!C45 -> 55974250 | D45: =EEFF!D45 -> 55974250 | E45: =EEFF!E45 -> 48518792 | F45: =EEFF!F45 -> 48518792 | G45: =F45 -> 48518792 | H45: =G45 -> 48518792 | I45: =H45 -> 48518792 | J45: =I45 -> 48518792 | K45: =J45 -> 48518792
A46: Déficit acumulado | B46: =EEFF!B46 -> -50345915 | C46: =EEFF!C46 -> -43774616 | D46: =EEFF!D46 -> -36200074 | E46: =EEFF!E46 -> -46166955 | F46: =EEFF!F46 -> -46836250 | G46: =F46 -> -46836250 | H46: =G46 -> -46836250 | I46: =H46 -> -46836250 | J46: =I46 -> -46836250 | K46: =J46 -> -46836250
A47: Impuesto complementario | B47: =EEFF!B47 -> -134004 | C47: =EEFF!C47 -> -134004 | D47: =EEFF!D47 -> -134004 | E47: =EEFF!E47 -> -134004 | F47: =EEFF!F47 -> -134007 | G47: =F47 -> -134007 | H47: =G47 -> -134007 | I47: =H47 -> -134007 | J47: =I47 -> -134007 | K47: =J47 -> -134007
A48: Total de patrimonio | B48: =EEFF!B48 -> 5495381 | C48: =EEFF!C48 -> 12066680 | D48: =EEFF!D48 -> 19641222 | E48: =EEFF!E48 -> 2218883 | F48: =EEFF!F48 -> 1549585 | G48: =F48 -> 1549585 | H48: =G48 -> 1549585 | I48: =H48 -> 1549585 | J48: =I48 -> 1549585 | K48: =J48 -> 1549585
A49: Total de pasivos y patrimonio | B49: =EEFF!B49 -> 274617243 | C49: =EEFF!C49 -> 261959863 | D49: =EEFF!D49 -> 260466310 | E49: =EEFF!E49 -> 229832624 | F49: =EEFF!F49 -> 216501926 | G49: =F49 -> 216501926 | H49: =G49 -> 216501926 | I49: =H49 -> 216501926 | J49: =I49 -> 216501926 | K49: =J49 -> 216501926
A51: Años | B51: FY21A | C51: FY22A | D51: FY23A | E51: FY24A | F51: FY25A | G51: FY26E | H51: FY27E | I51: FY28E | J51: FY29E | K51: FY30E
A52: Estado de Flujos de Efectivo
A53: Pérdida antes del impuestos sobre la renta | B53: =EEFF!B53 -> 1820066 | C53: =EEFF!C53 -> 5971929 | D53: =EEFF!D53 -> 8395009 | E53: =EEFF!E53 -> -1711072 | F53: =EEFF!F53 -> -172108 | G53: =F53 -> -172108 | H53: =G53 -> -172108 | I53: =H53 -> -172108 | J53: =I53 -> -172108 | K53: =J53 -> -172108
A54: Depreciación y amortización | B54: =EEFF!B54 -> 13917163 | C54: =EEFF!C54 -> 13936348 | D54: =EEFF!D54 -> 13947153 | E54: =EEFF!E54 -> 13994812 | F54: =EEFF!F54 -> 14031702 | G54: =F54 -> 14031702 | H54: =G54 -> 14031702 | I54: =H54 -> 14031702 | J54: =I54 -> 14031702 | K54: =J54 -> 14031702
A55: Amortización de costos financieros | B55: =EEFF!B55 -> 461118 | C55: =EEFF!C55 -> 488495 | D55: =EEFF!D55 -> 488115 | E55: =EEFF!E55 -> 465343 | F55: =EEFF!F55 -> 417400 | G55: =F55 -> 417400 | H55: =G55 -> 417400 | I55: =H55 -> 417400 | J55: =I55 -> 417400 | K55: =J55 -> 417400
A56: Intereses sobre bonos y pasivos por arrendamiento | B56: =EEFF!B56 -> 19633409 | C56: =EEFF!C56 -> 17427534 | D56: =EEFF!D56 -> 16034326 | E56: =EEFF!E56 -> 15277290 | F56: =EEFF!F56 -> 14368965 | G56: =F56 -> 14368965 | H56: =G56 -> 14368965 | I56: =H56 -> 14368965 | J56: =I56 -> 14368965 | K56: =J56 -> 14368965
A57: Interés ganado | B57: =EEFF!B57 -> -1491219 | C57: =EEFF!C57 -> -1429818 | D57: =EEFF!D57 -> -1366104 | E57: =EEFF!E57 -> -1300441 | F57: =EEFF!F57 -> -1221639 | G57: =F57 -> -1221639 | H57: =G57 -> -1221639 | I57: =H57 -> -1221639 | J57: =I57 -> -1221639 | K57: =J57 -> -1221639
A58: Ganancia en valor razonable de instrumento financiero derivado | B58: =EEFF!B58 -> -4708923 | C58: =EEFF!C58 -> -7338074 | D58: =EEFF!D58 -> 0 | E58: =EEFF!E58 -> 0 | F58: =EEFF!F58 -> 0
A59: Deudores comerciales y otras cuentas por cobrar | B59: =EEFF!B59 -> -11432 | C59: =EEFF!C59 -> 1436789 | D59: =EEFF!D59 -> -156919 | E59: =EEFF!E59 -> 3206463 | F59: =EEFF!F59 -> -953435 | G59: =F59 -> -953435 | H59: =G59 -> -953435 | I59: =H59 -> -953435 | J59: =I59 -> -953435 | K59: =J59 -> -953435
A60: Proveedores, otras cuentas por pagar y provisiones | B60: =EEFF!B60 -> -2200385 | C60: =EEFF!C60 -> -608700 | D60: =EEFF!D60 -> 1301174 | E60: =EEFF!E60 -> -1088704 | F60: =EEFF!F60 -> 921357 | G60: =F60 -> 921357 | H60: =G60 -> 921357 | I60: =H60 -> 921357 | J60: =I60 -> 921357 | K60: =J60 -> 921357
A61: Gastos pagados por adelantado y fondo de cesantía | B61: =EEFF!B61 -> -1320164 | C61: =EEFF!C61 -> -3051406 | D61: =EEFF!D61 -> 3696876 | E61: =EEFF!E61 -> -676045 | F61: =EEFF!F61 -> 1097614 | G61: =F61 -> 1097614 | H61: =G61 -> 1097614 | I61: =H61 -> 1097614 | J61: =I61 -> 1097614 | K61: =J61 -> 1097614
A62: Inventario | B62: =EEFF!B62 -> -16578 | C62: =EEFF!C62 -> -1894 | D62: =EEFF!D62 -> -11041 | E62: =EEFF!E62 -> -19976 | F62: =EEFF!F62 -> -12501 | G62: =F62 -> -12501 | H62: =G62 -> -12501 | I62: =H62 -> -12501 | J62: =I62 -> -12501 | K62: =J62 -> -12501
A63: Impuesto sobre la renta pagado | B63: =EEFF!B63 -> -946740 | C63: =EEFF!C63 -> 0 | D63: =EEFF!D63 -> 0 | E63: =EEFF!E63 -> 0 | F63: =EEFF!F63 -> 0
A64: Efectivo neto provisto por actividades de operación | B64: =EEFF!B64 -> 25136315 | C64: =EEFF!C64 -> 26831203 | D64: =EEFF!D64 -> 42328589 | E64: =EEFF!E64 -> 28147670 | F64: =EEFF!F64 -> 28477355 | G64: =F64 -> 28477355 | H64: =G64 -> 28477355 | I64: =H64 -> 28477355 | J64: =I64 -> 28477355 | K64: =J64 -> 28477355
A65: Adiciones de planta y equipo | B65: =EEFF!B65 -> -93485 | C65: =EEFF!C65 -> -556464 | D65: =EEFF!D65 -> -5097893 | E65: =EEFF!E65 -> -282082 | F65: =EEFF!F65 -> -984285 | G65: =F65 -> -984285 | H65: =G65 -> -984285 | I65: =H65 -> -984285 | J65: =I65 -> -984285 | K65: =J65 -> -984285
A66: Adiciones de activos intangibles | B66: =EEFF!B66 -> -125421 | C66: =EEFF!C66 -> -15000 | D66: =EEFF!D66 -> -17143 | E66: =EEFF!E66 -> -22500 | F66: =EEFF!F66 -> -30000 | G66: =F66 -> -30000 | H66: =G66 -> -30000 | I66: =H66 -> -30000 | J66: =I66 -> -30000 | K66: =J66 -> -30000
A67: Cobro de préstamo entre partes relacionadas | B67: =EEFF!B67 -> 885999 | C67: =EEFF!C67 -> 898933 | D67: =EEFF!D67 -> 996981 | E67: =EEFF!E67 -> 1138080 | F67: =EEFF!F67 -> 1239673 | G67: =F67 -> 1239673 | H67: =G67 -> 1239673 | I67: =H67 -> 1239673 | J67: =I67 -> 1239673 | K67: =J67 -> 1239673
A68: Intereses recibidos - con partes relacionadas | B68: =EEFF!B68 -> 1178171 | C68: =EEFF!C68 -> 1444586 | D68: =EEFF!D68 -> 1384321 | E68: =EEFF!E68 -> 1317299 | F68: =EEFF!F68 -> 1242005 | G68: =F68 -> 1242005 | H68: =G68 -> 1242005 | I68: =H68 -> 1242005 | J68: =I68 -> 1242005 | K68: =J68 -> 1242005
A69: Efectivo neto provisto por actividades de inversión | B69: =EEFF!B69 -> 1845264 | C69: =EEFF!C69 -> 1772055 | D69: =EEFF!D69 -> -2733734 | E69: =EEFF!E69 -> 2150797 | F69: =EEFF!F69 -> 1467393 | G69: =F69 -> 1467393 | H69: =G69 -> 1467393 | I69: =H69 -> 1467393 | J69: =I69 -> 1467393 | K69: =J69 -> 1467393
A70: Pago de bonos emitidos | B70: =EEFF!B70 -> -10003000 | C70: =EEFF!C70 -> -10149000 | D70: =EEFF!D70 -> -11256000 | E70: =EEFF!E70 -> -12849000 | F70: =EEFF!F70 -> -13996000 | G70: =F70 -> -13996000 | H70: =G70 -> -13996000 | I70: =H70 -> -13996000 | J70: =I70 -> -13996000 | K70: =J70 -> -13996000
A71: Intereses pagados | B71: =EEFF!B71 -> -16123503 | C71: =EEFF!C71 -> -18004832 | D71: =EEFF!D71 -> -15629088 | E71: =EEFF!E71 -> -14872390 | F71: =EEFF!F71 -> -14022320 | G71: =F71 -> -14022320 | H71: =G71 -> -14022320 | I71: =H71 -> -14022320 | J71: =I71 -> -14022320 | K71: =J71 -> -14022320
A72: Intereses pagados por arrendamiento | B72: =EEFF!B72 -> 0 | C72: =EEFF!C72 -> 0 | D72: =EEFF!D72 -> -610919 | E72: =EEFF!E72 -> -595230 | F72: =EEFF!F72 -> -576580 | G72: =F72 -> -576580 | H72: =G72 -> -576580 | I72: =H72 -> -576580 | J72: =I72 -> -576580 | K72: =J72 -> -576580
A73: Pago por instrumento financiero derivado | B73: =EEFF!B73 -> 0 | C73: =EEFF!C73 -> -287000 | D73: =EEFF!D73 -> 0 | E73: =EEFF!E73 -> 0 | F73: =EEFF!F73 -> 0
A74: Dividendos pagados | B74: =EEFF!B74 -> 0 | C74: =EEFF!C74 -> 0 | D74: =EEFF!D74 -> 0 | E74: =EEFF!E74 -> -7574542 | F74: =EEFF!F74 -> 0 | G74: =F74 -> 0 | H74: =G74 -> 0 | I74: =H74 -> 0 | J74: =I74 -> 0 | K74: =J74 -> 0
A75: Reducción de capital | B75: =EEFF!B75 -> -10000000 | C75: =EEFF!C75 -> 0 | D75: =EEFF!D75 -> 0 | E75: =EEFF!E75 -> -7455458 | F75: =EEFF!F75 -> 0 | G75: =F75 -> 0 | H75: =G75 -> 0 | I75: =H75 -> 0 | J75: =I75 -> 0 | K75: =J75 -> 0
A76: Pagos de principal de arrendamiento | B76: =EEFF!B76 -> -126524 | C76: =EEFF!C76 -> -157732 | D76: =EEFF!D76 -> -192094 | E76: =EEFF!E76 -> -229888 | F76: =EEFF!F76 -> -271409 | G76: =F76 -> -271409 | H76: =G76 -> -271409 | I76: =H76 -> -271409 | J76: =I76 -> -271409 | K76: =J76 -> -271409
A77: Impuesto complementario | B77: =EEFF!B77 -> -114851 | C77: =EEFF!C77 -> 0 | D77: =EEFF!D77 -> 0 | E77: =EEFF!E77 -> 0 | F77: =EEFF!F77 -> -3 | G77: =F77 -> -3 | H77: =G77 -> -3 | I77: =H77 -> -3 | J77: =I77 -> -3 | K77: =J77 -> -3
A78: Efectivo neto utilizado en actividades de financiamiento | B78: =EEFF!B78 -> -36367878 | C78: =EEFF!C78 -> -28598564 | D78: =EEFF!D78 -> -27688101 | E78: =EEFF!E78 -> -43576508 | F78: =EEFF!F78 -> -28866312 | G78: =F78 -> -28866312 | H78: =G78 -> -28866312 | I78: =H78 -> -28866312 | J78: =I78 -> -28866312 | K78: =J78 -> -28866312
A79: Aumento (disminución) neto en efectivo y equivalentes de efectivo | B79: =EEFF!B79 -> -9386299 | C79: =EEFF!C79 -> 4694 | D79: =EEFF!D79 -> 11906754 | E79: =EEFF!E79 -> -13278041 | F79: =EEFF!F79 -> 1078436 | G79: =F79 -> 1078436 | H79: =G79 -> 1078436 | I79: =H79 -> 1078436 | J79: =I79 -> 1078436 | K79: =J79 -> 1078436
A80: Efectivo y equivalentes de efectivo al inicio del año | B80: =EEFF!B80 -> 14871800 | C80: =EEFF!C80 -> 5485501 | D80: =EEFF!D80 -> 5490195 | E80: =EEFF!E80 -> 17396949 | F80: =EEFF!F80 -> 4118908 | G80: =F80 -> 4118908 | H80: =G80 -> 4118908 | I80: =H80 -> 4118908 | J80: =I80 -> 4118908 | K80: =J80 -> 4118908
A81: Efectivo y equivalentes de efectivo al final del año | B81: =EEFF!B81 -> 5485501 | C81: =EEFF!C81 -> 5490195 | D81: =EEFF!D81 -> 17396949 | E81: =EEFF!E81 -> 4118908 | F81: =EEFF!F81 -> 5197344 | G81: =F81 -> 5197344 | H81: =G81 -> 5197344 | I81: =H81 -> 5197344 | J81: =I81 -> 5197344 | K81: =J81 -> 5197344

Sheet _CHECKS
A1: UEP Penonomé II, S. A.
A2: _CHECKS panel — power template, live formulas, known residuals signed visible
A3: Status semantics: PASS = zero undocumented hard failures; KNOWN_RESIDUAL = signed G7 residual; SOURCE_GAP = unresolved semantic anchor/schedule.
A4: MASTER_STATUS | B4: MODEL STATUS | C4: =IF(COUNTIF($C$6:$C$37,"FAIL")=0,"PASS","FAIL") -> PASS | G4: Master PASS counts only FAIL rows; KNOWN_RESIDUAL/SOURCE_GAP remain visible but non-blocking.
A5: check_id | B5: description | C5: status | D5: hardness | E5: tolerance | F5: expected | G5: note | H5: FY21A | I5: FY22A | J5: FY23A | K5: FY24A | L5: FY25A | M5: FY26E | N5: FY27E | O5: FY28E | P5: FY29E | Q5: FY30E
A7: UNIVERSAL CHECKS
A8: BS_BALANCE | B8: UNIVERSAL | expected 0; hard fail if ABS(value) > hard_tie_tolerance. Observed: UEPII critical gate <10 for BS/cash; BG hard reconciliation >=1000 because full USD. | source applies_to: all 16 archetypes | C8: =IF(SUMPRODUCT((ABS(H8:Q8)>1000)*1)=0,"PASS","FAIL") -> PASS | D8: hard | E8: 1000 USD | F8: 0 | G8: expected 0; hard fail if ABS(value) > hard_tie_tolerance. Observed: UEPII critical gate <10 for BS/cash; BG hard reconciliation >=1000 because full USD. Default full-USD hard tie threshold is $1,000 unless the workbook declares a tighter scale-aware tolerance. | H8: =ModeloFinanciero!B32-ModeloFinanciero!B49 -> 0 | I8: =ModeloFinanciero!C32-ModeloFinanciero!C49 -> 0 | J8: =ModeloFinanciero!D32-ModeloFinanciero!D49 -> 0 | K8: =ModeloFinanciero!E32-ModeloFinanciero!E49 -> 0 | L8: =ModeloFinanciero!F32-ModeloFinanciero!F49 -> 0 | M8: =ModeloFinanciero!G32-ModeloFinanciero!G49 -> 0 | N8: =ModeloFinanciero!H32-ModeloFinanciero!H49 -> 0 | O8: =ModeloFinanciero!I32-ModeloFinanciero!I49 -> 0 | ... Q8: =ModeloFinanciero!K32-ModeloFinanciero!K49 -> 0
A9: CASH_TIE | B9: UNIVERSAL | expected 0; use hard_tie_tolerance; if cash includes restricted cash/time deposits, define cash_component role explicitly. | source applies_to: all 16 archetypes | C9: =IF(SUMPRODUCT((ABS(H9:Q9)>1000)*1)=0,"PASS","FAIL") -> PASS | D9: hard | E9: 1000 USD | F9: 0 | G9: Observed hard tie threshold for model-to-model cash residuals; define cash-component role when restricted cash/time deposits exist. | H9: =ModeloFinanciero!B81-ModeloFinanciero!B20 -> 0 | I9: =ModeloFinanciero!C81-ModeloFinanciero!C20 -> 0 | J9: =ModeloFinanciero!D81-ModeloFinanciero!D20 -> 0 | K9: =ModeloFinanciero!E81-ModeloFinanciero!E20 -> 0 | L9: =ModeloFinanciero!F81-ModeloFinanciero!F20 -> 0
A10: CF_ROLLFORWARD | B10: UNIVERSAL | expected 0; hard_tie_tolerance; historical rows may be WARN if source CF transcript is incomplete. | source applies_to: all 16 where CF is modeled | C10: =IF(SUMPRODUCT((ABS(H10:Q10)>1000)*1)=0,"PASS","FAIL") -> PASS | D10: hard | E10: 1000 USD | F10: 0 | G10: expected 0; hard_tie_tolerance; historical rows may be WARN if source CF transcript is incomplete. Default full-USD hard tie threshold is $1,000 unless the workbook declares a tighter scale-aware tolerance. | H10: =ModeloFinanciero!B64+ModeloFinanciero!B69+ModeloFinanciero!B78-(ModeloFinanciero!B81-ModeloFinanciero!B80) -> 0 | I10: =ModeloFinanciero!C64+ModeloFinanciero!C69+ModeloFinanciero!C78-(ModeloFinanciero!C81-ModeloFinanciero!C80) -> 0 | J10: =ModeloFinanciero!D64+ModeloFinanciero!D69+ModeloFinanciero!D78-(ModeloFinanciero!D81-ModeloFinanciero!D80) -> 0 | K10: =ModeloFinanciero!E64+ModeloFinanciero!E69+ModeloFinanciero!E78-(ModeloFinanciero!E81-ModeloFinanciero!E80) -> 0 | L10: =ModeloFinanciero!F64+ModeloFinanciero!F69+ModeloFinanciero!F78-(ModeloFinanciero!F81-ModeloFinanciero!F80) -> 0 | M10: =ModeloFinanciero!G64+ModeloFinanciero!G69+ModeloFinanciero!G78-(ModeloFinanciero!G81-ModeloFinanciero!G80) -> 0 | N10: =ModeloFinanciero!H64+ModeloFinanciero!H69+ModeloFinanciero!H78-(ModeloFinanciero!H81-ModeloFinanciero!H80) -> 0 | O10: =ModeloFinanciero!I64+ModeloFinanciero!I69+ModeloFinanciero!I78-(ModeloFinanciero!I81-ModeloFinanciero!I80) -> 0 | ... Q10: =ModeloFinanciero!K64+ModeloFinanciero!K69+ModeloFinanciero!K78-(ModeloFinanciero!K81-ModeloFinanciero!K80) -> 0
A11: NI_TIE_TO_EQUITY | B11: UNIVERSAL | expected 0; hard_tie_tolerance. | source applies_to: all 16 | C11: SOURCE_GAP | D11: hard | E11: 1000 USD | F11: 0 | G11: No semantic anchors resolved for NI_TIE_TO_EQUITY. | H11: =0 -> 0 | I11: =0 -> 0 | J11: =0 -> 0 | K11: =0 -> 0 | L11: =0 -> 0 | M11: =0 -> 0 | N11: =0 -> 0 | O11: =0 -> 0 | ... Q11: =0 -> 0
A12: NI_SIGN_SANITY | B12: UNIVERSAL | expected 0; sign convention must be stated in row description. | source applies_to: all 16 | C12: SOURCE_GAP | D12: hard | E12: 1000 USD | F12: 0 | G12: No semantic anchors resolved for NI_SIGN_SANITY. | H12: =0 -> 0 | I12: =0 -> 0 | J12: =0 -> 0 | K12: =0 -> 0 | L12: =0 -> 0 | M12: =0 -> 0 | N12: =0 -> 0 | O12: =0 -> 0 | ... Q12: =0 -> 0
A13: RE_ROLLFORWARD | B13: UNIVERSAL | expected 0; hard_tie_tolerance. | source applies_to: all 16 with RE row | C13: SOURCE_GAP | D13: hard | E13: 1000 USD | F13: 0 | G13: No semantic anchors resolved for RE_ROLLFORWARD. | H13: =0 -> 0 | I13: =0 -> 0 | J13: =0 -> 0 | K13: =0 -> 0 | L13: =0 -> 0 | M13: =0 -> 0 | N13: =0 -> 0 | O13: =0 -> 0 | ... Q13: =0 -> 0
A14: EQUITY_TOTAL_TIE | B14: UNIVERSAL | expected 0; hard_tie_tolerance. | source applies_to: all 16 | C14: =IF(SUMPRODUCT((ABS(H14:Q14)>1000)*1)=0,"PASS","FAIL") -> PASS | D14: hard | E14: 1000 USD | F14: 0 | G14: expected 0; hard_tie_tolerance. Default full-USD hard tie threshold is $1,000 unless the workbook declares a tighter scale-aware tolerance. | H14: =SUM(ModeloFinanciero!B44,ModeloFinanciero!B45,ModeloFinanciero!B46,ModeloFinanciero!B47)-ModeloFinanciero!B48 -> 0 | I14: =SUM(ModeloFinanciero!C44,ModeloFinanciero!C45,ModeloFinanciero!C46,ModeloFinanciero!C47)-ModeloFinanciero!C48 -> 0 | J14: =SUM(ModeloFinanciero!D44,ModeloFinanciero!D45,ModeloFinanciero!D46,ModeloFinanciero!D47)-ModeloFinanciero!D48 -> 0 | K14: =SUM(ModeloFinanciero!E44,ModeloFinanciero!E45,ModeloFinanciero!E46,ModeloFinanciero!E47)-ModeloFinanciero!E48 -> 0 | L14: =SUM(ModeloFinanciero!F44,ModeloFinanciero!F45,ModeloFinanciero!F46,ModeloFinanciero!F47)-ModeloFinanciero!F48 -> 0 | M14: =SUM(ModeloFinanciero!G44,ModeloFinanciero!G45,ModeloFinanciero!G46,ModeloFinanciero!G47)-ModeloFinanciero!G48 -> 0 | N14: =SUM(ModeloFinanciero!H44,ModeloFinanciero!H45,ModeloFinanciero!H46,ModeloFinanciero!H47)-ModeloFinanciero!H48 -> 0 | O14: =SUM(ModeloFinanciero!I44,ModeloFinanciero!I45,ModeloFinanciero!I46,ModeloFinanciero!I47)-ModeloFinanciero!I48 -> 0 | ... Q14: =SUM(ModeloFinanciero!K44,ModeloFinanciero!K45,ModeloFinanciero!K46,ModeloFinanciero!K47)-ModeloFinanciero!K48 -> 0
A15: BS_LINEITEM_SUM_ASSETS | B15: UNIVERSAL | expected 0; hard_tie_tolerance. | source applies_to: all 16 | C15: =IF(SUMPRODUCT((ABS(H15:Q15)>1000)*1)=0,"PASS","FAIL") -> PASS | D15: hard | E15: 1000 USD | F15: 0 | G15: expected 0; hard_tie_tolerance. Default full-USD hard tie threshold is $1,000 unless the workbook declares a tighter scale-aware tolerance. | H15: =SUM(ModeloFinanciero!B25,ModeloFinanciero!B31)-ModeloFinanciero!B32 -> 0 | I15: =SUM(ModeloFinanciero!C25,ModeloFinanciero!C31)-ModeloFinanciero!C32 -> 0 | J15: =SUM(ModeloFinanciero!D25,ModeloFinanciero!D31)-ModeloFinanciero!D32 -> 0 | K15: =SUM(ModeloFinanciero!E25,ModeloFinanciero!E31)-ModeloFinanciero!E32 -> 0 | L15: =SUM(ModeloFinanciero!F25,ModeloFinanciero!F31)-ModeloFinanciero!F32 -> 0 | M15: =SUM(ModeloFinanciero!G25,ModeloFinanciero!G31)-ModeloFinanciero!G32 -> 0 | N15: =SUM(ModeloFinanciero!H25,ModeloFinanciero!H31)-ModeloFinanciero!H32 -> 0 | O15: =SUM(ModeloFinanciero!I25,ModeloFinanciero!I31)-ModeloFinanciero!I32 -> 0 | ... Q15: =SUM(ModeloFinanciero!K25,ModeloFinanciero!K31)-ModeloFinanciero!K32 -> 0
A16: BS_LINEITEM_SUM_LIAB_EQUITY | B16: UNIVERSAL | expected 0; hard_tie_tolerance. | source applies_to: all 16 | C16: =IF(SUMPRODUCT((ABS(H16:Q16)>1000)*1)=0,"PASS","FAIL") -> PASS | D16: hard | E16: 1000 USD | F16: 0 | G16: expected 0; hard_tie_tolerance. Default full-USD hard tie threshold is $1,000 unless the workbook declares a tighter scale-aware tolerance. | H16: =ModeloFinanciero!B43+ModeloFinanciero!B48-ModeloFinanciero!B49 -> 0 | I16: =ModeloFinanciero!C43+ModeloFinanciero!C48-ModeloFinanciero!C49 -> 0 | J16: =ModeloFinanciero!D43+ModeloFinanciero!D48-ModeloFinanciero!D49 -> 0 | K16: =ModeloFinanciero!E43+ModeloFinanciero!E48-ModeloFinanciero!E49 -> 0 | L16: =ModeloFinanciero!F43+ModeloFinanciero!F48-ModeloFinanciero!F49 -> 0 | M16: =ModeloFinanciero!G43+ModeloFinanciero!G48-ModeloFinanciero!G49 -> 0 | N16: =ModeloFinanciero!H43+ModeloFinanciero!H48-ModeloFinanciero!H49 -> 0 | O16: =ModeloFinanciero!I43+ModeloFinanciero!I48-ModeloFinanciero!I49 -> 0 | ... Q16: =ModeloFinanciero!K43+ModeloFinanciero!K48-ModeloFinanciero!K49 -> 0
A17: SOURCE_TIE_HISTORICAL | B17: UNIVERSAL | expected 0 for audited rows; SOURCE_GAP/WARN allowed only with explicit source-gap note. | source applies_to: all 16 | C17: =IF(SUMPRODUCT((ABS(H17:Q17)>100000)*1)=0,"PASS","FAIL") -> PASS | D17: hard | E17: 100000 USD | F17: 0 | G17: Audited rows tie to 0; only bank ending-cash-vs-EEFF cash rows may use the observed $100,000 hard threshold; SOURCE_GAP/WARN requires explicit source-gap note. | H17: =ModeloFinanciero!B32-EEFF!B32 -> 0 | I17: =ModeloFinanciero!C32-EEFF!C32 -> 0 | J17: =ModeloFinanciero!D32-EEFF!D32 -> 0 | K17: =ModeloFinanciero!E32-EEFF!E32 -> 0 | L17: =ModeloFinanciero!F32-EEFF!F32 -> 0
A18: NO_FORMULA_ERRORS | B18: UNIVERSAL | expected PASS/0; no masking. | source applies_to: all 16 | C18: =IF(SUMPRODUCT((ABS(H18:Q18)>0)*1)=0,"PASS","FAIL") -> PASS | D18: hard | E18: PASS | F18: PASS | G18: expected PASS/0; no masking. | H18: =0 -> 0 | I18: =0 -> 0 | J18: =0 -> 0 | K18: =0 -> 0 | L18: =0 -> 0 | M18: =0 -> 0 | N18: =0 -> 0 | O18: =0 -> 0 | ... Q18: =0 -> 0
A19: NO_CHECKS_MASTER_FAIL | B19: UNIVERSAL | expected PASS; status row should cite included/excluded rows. | source applies_to: all 16 | C19: =IF(SUMPRODUCT((ABS(H19:Q19)>0)*1)=0,"PASS","FAIL") -> PASS | D19: hard | E19: PASS | F19: PASS | G19: expected PASS; status row should cite included/excluded rows. | H19: =COUNTIF($C$6:$C$18,"FAIL")+COUNTIF($C$20:$C$37,"FAIL") -> 0 | I19: =COUNTIF($C$6:$C$18,"FAIL")+COUNTIF($C$20:$C$37,"FAIL") -> 0 | J19: =COUNTIF($C$6:$C$18,"FAIL")+COUNTIF($C$20:$C$37,"FAIL") -> 0 | K19: =COUNTIF($C$6:$C$18,"FAIL")+COUNTIF($C$20:$C$37,"FAIL") -> 0 | L19: =COUNTIF($C$6:$C$18,"FAIL")+COUNTIF($C$20:$C$37,"FAIL") -> 0 | M19: =COUNTIF($C$6:$C$18,"FAIL")+COUNTIF($C$20:$C$37,"FAIL") -> 0 | N19: =COUNTIF($C$6:$C$18,"FAIL")+COUNTIF($C$20:$C$37,"FAIL") -> 0 | O19: =COUNTIF($C$6:$C$18,"FAIL")+COUNTIF($C$20:$C$37,"FAIL") -> 0 | ... Q19: =COUNTIF($C$6:$C$18,"FAIL")+COUNTIF($C$20:$C$37,"FAIL") -> 0
A21: CONDITIONAL CHECKS
A22: PPE_SCHEDULE_TIE | B22: ARCHETYPE/conditional | expected 0; hard_tie_tolerance. | source applies_to: operating-EBITDA, power, utility, downstream fuel, other non-financials | C22: SOURCE_GAP | D22: hard | E22: 1000 USD | F22: 0 | G22: No semantic anchors resolved for PPE_SCHEDULE_TIE. | H22: =0 -> 0 | I22: =0 -> 0 | J22: =0 -> 0 | K22: =0 -> 0 | L22: =0 -> 0 | M22: =0 -> 0 | N22: =0 -> 0 | O22: =0 -> 0 | ... Q22: =0 -> 0
A23: LEASE_SCHEDULE_TIE | B23: ARCHETYPE/conditional | expected 0; hard_tie_tolerance. | source applies_to: IFRS-16 issuers | C23: SOURCE_GAP | D23: hard | E23: 1000 USD | F23: 0 | G23: No semantic anchors resolved for LEASE_SCHEDULE_TIE. | H23: =0 -> 0 | I23: =0 -> 0 | J23: =0 -> 0 | K23: =0 -> 0 | L23: =0 -> 0 | M23: =0 -> 0 | N23: =0 -> 0 | O23: =0 -> 0 | ... Q23: =0 -> 0
A24: DEBT_SCHEDULE_TIE | B24: ARCHETYPE/conditional | expected 0; hard_tie_tolerance; project-finance debt can include accrued interest/unamortized cost roles. | source applies_to: non-bank-lender, power, utility, operating-EBITDA with debt | C24: SOURCE_GAP | D24: hard | E24: 1000 USD | F24: 0 | G24: No semantic anchors resolved for DEBT_SCHEDULE_TIE. | H24: =0 -> 0 | I24: =0 -> 0 | J24: =0 -> 0 | K24: =0 -> 0 | L24: =0 -> 0 | M24: =0 -> 0 | N24: =0 -> 0 | O24: =0 -> 0 | ... Q24: =0 -> 0
A26: POWER CHECKS
A27: POWER_REVENUE_BUILD_TIE | B27: ARCHETYPE | expected 0; hard_tie_tolerance. | source applies_to: power, utility | C27: =IF(SUMPRODUCT((ABS(H27:Q27)>1000)*1)=0,"PASS","FAIL") -> PASS | D27: hard | E27: 1000 USD | F27: 0 | G27: expected 0; hard_tie_tolerance. Default full-USD hard tie threshold is $1,000 unless the workbook declares a tighter scale-aware tolerance. | M27: =Supuestos!G44-ModeloFinanciero!G7 -> 0 | N27: =Supuestos!H44-ModeloFinanciero!H7 -> 0 | O27: =Supuestos!I44-ModeloFinanciero!I7 -> 0 | P27: =Supuestos!J44-ModeloFinanciero!J7 -> 0 | Q27: =Supuestos!K44-ModeloFinanciero!K7 -> 0
A28: POWER_CHANNEL_VOLUME_TIE | B28: ARCHETYPE | expected 0; observed UEPII uses N/A for years without channel split. | source applies_to: power, utility | C28: SOURCE_GAP | D28: hard | E28: volume_tolerance | F28: 0 | G28: No semantic anchors resolved for POWER_CHANNEL_VOLUME_TIE. | H28: =0 -> 0 | I28: =0 -> 0 | J28: =0 -> 0 | K28: =0 -> 0 | L28: =0 -> 0 | M28: =0 -> 0 | N28: =0 -> 0 | O28: =0 -> 0 | ... Q28: =0 -> 0
A29: POWER_CAPACITY_CEILING | B29: ARCHETYPE | PASS/FAIL or 0/1; threshold from hours-per-year parameter. | source applies_to: power, utility | C29: SOURCE_GAP | D29: hard | E29: PASS | F29: PASS | G29: Installed-capacity ceiling needs an addressable capacity-driver row before the live check can be rendered without hardcoded formula constants. | H29: =0 -> 0 | I29: =0 -> 0 | J29: =0 -> 0 | K29: =0 -> 0 | L29: =0 -> 0 | M29: =0 -> 0 | N29: =0 -> 0 | O29: =0 -> 0 | ... Q29: =0 -> 0
A30: POWER_DSRA_COVERAGE | B30: ARCHETYPE | expected 0; UEPII tail uses <=1 tolerance in U2 rows. | source applies_to: project-finance power/utility | C30: SOURCE_GAP | D30: hard | E30: 1 model currency or ratio residual | F30: 0 | G30: No semantic anchors resolved for POWER_DSRA_COVERAGE. | H30: =0 -> 0 | I30: =0 -> 0 | J30: =0 -> 0 | K30: =0 -> 0 | L30: =0 -> 0 | M30: =0 -> 0 | N30: =0 -> 0 | O30: =0 -> 0 | ... Q30: =0 -> 0
A31: POWER_DSCR_COVENANT | B31: ARCHETYPE | must be >=0 or explicit business-warning text; not always a mechanical blocker. | source applies_to: project-finance power/utility | C31: SOURCE_GAP | D31: soft | E31: 0 cushion | F31: >=0 | G31: No semantic anchors resolved for POWER_DSCR_COVENANT. | H31: =0 -> 0 | I31: =0 -> 0 | J31: =0 -> 0 | K31: =0 -> 0 | L31: =0 -> 0 | M31: =0 -> 0 | N31: =0 -> 0 | O31: =0 -> 0 | ... Q31: =0 -> 0
A32: POWER_DEBT_FACE_ZERO | B32: ARCHETYPE | PASS/FAIL; tail-life projects. | source applies_to: finite-life project finance | C32: SOURCE_GAP | D32: hard | E32: PASS | F32: PASS | G32: No semantic anchors resolved for POWER_DEBT_FACE_ZERO. | H32: =0 -> 0 | I32: =0 -> 0 | J32: =0 -> 0 | K32: =0 -> 0 | L32: =0 -> 0 | M32: =0 -> 0 | N32: =0 -> 0 | O32: =0 -> 0 | ... Q32: =0 -> 0
A33: OPERATING_GP_OR_EBITDA_TIE | B33: ARCHETYPE | expected 0; hard_tie_tolerance. | source applies_to: operating-EBITDA, downstream fuel, power when EBITDA is used | C33: SOURCE_GAP | D33: hard | E33: 1000 USD | F33: 0 | G33: No semantic anchors resolved for OPERATING_GP_OR_EBITDA_TIE. | H33: =0 -> 0 | I33: =0 -> 0 | J33: =0 -> 0 | K33: =0 -> 0 | L33: =0 -> 0 | M33: =0 -> 0 | N33: =0 -> 0 | O33: =0 -> 0 | ... Q33: =0 -> 0
A35: ISSUER-SPECIFIC CHECKS
A36: UEPII_TECNISOL_ELIMINATION | B36: ISSUER | expected 0; UEPII-only intercompany/Tecnisol logic. | source applies_to: uepii-penonome only | C36: SOURCE_GAP | D36: hard | E36: 1000 USD | F36: 0 | G36: No semantic anchors resolved for UEPII_TECNISOL_ELIMINATION. | H36: =0 -> 0 | I36: =0 -> 0 | J36: =0 -> 0 | K36: =0 -> 0 | L36: =0 -> 0 | M36: =0 -> 0 | N36: =0 -> 0 | O36: =0 -> 0 | ... Q36: =0 -> 0
A37: UEPII_FINITE_LIFE_DCF | B37: ISSUER | PASS/FAIL; UEPII U2 checks. | source applies_to: uepii-penonome only | C37: SOURCE_GAP | D37: hard | E37: PASS | F37: PASS | G37: No semantic anchors resolved for UEPII_FINITE_LIFE_DCF. | H37: =0 -> 0 | I37: =0 -> 0 | J37: =0 -> 0 | K37: =0 -> 0 | L37: =0 -> 0 | M37: =0 -> 0 | N37: =0 -> 0 | O37: =0 -> 0 | ... Q37: =0 -> 0

Sheet Generation_PPA
A1: UEP Penonomé II, S. A.
A2: Generation_PPA - source-visible MW/MWh, price, and revenue bridge
A3: en US$ sin escala
A4: Filing facts only; use NOT_DISCLOSED where notes/MD&A are silent
A5: Anios | B5: FY21A | C5: FY22A | D5: FY23A | E5: FY24A | F5: FY25A | G5: FY26E | H5: FY27E | I5: FY28E | J5: FY29E | K5: FY30E
A7: A. Capacity and generation (MW -> MWh)
A8: Capacity MW - Nuevo Chagres | F8: 62.5 | G8: 62.5 | H8: 62.5 | I8: 62.5 | J8: 62.5 | K8: 62.5
A9: Capacity MW - Rosa de los Vientos I | F9: 52.5 | G9: 52.5 | H9: 52.5 | I9: 52.5 | J9: 52.5 | K9: 52.5
A10: Capacity MW - Rosa de los Vientos II | F10: 50 | G10: 50 | H10: 50 | I10: 50 | J10: 50 | K10: 50
A11: Capacity MW - Marañón | F11: 17.5 | G11: 17.5 | H11: 17.5 | I11: 17.5 | J11: 17.5 | K11: 17.5
A12: Capacity MW - Portobelo Ballestillas | F12: 32.5 | G12: 32.5 | H12: 32.5 | I12: 32.5 | J12: 32.5 | K12: 32.5
A13: Total visible capacity (MW) | F13: =F8+F9+F10+F11+F12 -> 215 | G13: =G8+G9+G10+G11+G12 -> 215 | H13: =H8+H9+H10+H11+H12 -> 215 | I13: =I8+I9+I10+I11+I12 -> 215 | J13: =J8+J9+J10+J11+J12 -> 215 | K13: =K8+K9+K10+K11+K12 -> 215
A15: Availability / AVF (if disclosed; memo) | B15: NOT_DISCLOSED | C15: NOT_DISCLOSED | D15: NOT_DISCLOSED | E15: NOT_DISCLOSED | F15: 0.9366 | G15: 0.96 | H15: 0.96 | I15: 0.96 | J15: 0.96 | K15: 0.96
A16: Plant factor / net CF - active | B16: NOT_DISCLOSED | C16: NOT_DISCLOSED | D16: NOT_DISCLOSED | E16: NOT_DISCLOSED | F16: 0.2147 | G16: =G18 -> 0.215 | H16: =H18 -> 0.215 | I16: =I18 -> 0.215 | J16: =J18 -> 0.21 | K16: =K18 -> 0.21
A17: Bear | G17: 0.195 | H17: 0.195 | I17: 0.195 | J17: 0.195 | K17: 0.19
A18: Base | G18: 0.215 | H18: 0.215 | I18: 0.215 | J18: 0.21 | K18: 0.21
A19: Bull | G19: 0.245 | H19: 0.245 | I19: 0.245 | J19: 0.24 | K19: 0.24
A20: Hours per year | G20: 8760 | H20: 8760 | I20: 8760 | J20: 8760 | K20: 8760
A21: Generation MWh - Nuevo Chagres | B21: NOT_DISCLOSED | C21: NOT_DISCLOSED | D21: NOT_DISCLOSED | E21: NOT_DISCLOSED | F21: NOT_DISCLOSED | G21: =G8*G20*G16 -> 117712.5 | H21: =H8*H20*H16 -> 117712.5 | I21: =I8*I20*I16 -> 117712.5 | J21: =J8*J20*J16 -> 114975 | K21: =K8*K20*K16 -> 114975
A22: Generation MWh - Rosa de los Vientos I | B22: NOT_DISCLOSED | C22: NOT_DISCLOSED | D22: NOT_DISCLOSED | E22: NOT_DISCLOSED | F22: NOT_DISCLOSED | G22: =G9*G20*G16 -> 98878.5 | H22: =H9*H20*H16 -> 98878.5 | I22: =I9*I20*I16 -> 98878.5 | J22: =J9*J20*J16 -> 96579 | K22: =K9*K20*K16 -> 96579
A23: Generation MWh - Rosa de los Vientos II | B23: NOT_DISCLOSED | C23: NOT_DISCLOSED | D23: NOT_DISCLOSED | E23: NOT_DISCLOSED | F23: NOT_DISCLOSED | G23: =G10*G20*G16 -> 94170 | H23: =H10*H20*H16 -> 94170 | I23: =I10*I20*I16 -> 94170 | J23: =J10*J20*J16 -> 91980 | K23: =K10*K20*K16 -> 91980
A24: Generation MWh - Marañón | B24: NOT_DISCLOSED | C24: NOT_DISCLOSED | D24: NOT_DISCLOSED | E24: NOT_DISCLOSED | F24: NOT_DISCLOSED | G24: =G11*G20*G16 -> 32959.5 | H24: =H11*H20*H16 -> 32959.5 | I24: =I11*I20*I16 -> 32959.5 | J24: =J11*J20*J16 -> 32193 | K24: =K11*K20*K16 -> 32193
A25: Generation MWh - Portobelo Ballestillas | B25: NOT_DISCLOSED | C25: NOT_DISCLOSED | D25: NOT_DISCLOSED | E25: NOT_DISCLOSED | F25: NOT_DISCLOSED | G25: =G12*G20*G16 -> 61210.5 | H25: =H12*H20*H16 -> 61210.5 | I25: =I12*I20*I16 -> 61210.5 | J25: =J12*J20*J16 -> 59787 | K25: =K12*K20*K16 -> 59787
A26: Historical generation MWh from filing | B26: NOT_DISCLOSED | C26: NOT_DISCLOSED | D26: NOT_DISCLOSED | E26: NOT_DISCLOSED | F26: 405420 | G26: NOT_DISCLOSED | H26: NOT_DISCLOSED | I26: NOT_DISCLOSED | J26: NOT_DISCLOSED | K26: NOT_DISCLOSED
A27: Total generation MWh | B27: NOT_DISCLOSED | C27: NOT_DISCLOSED | D27: NOT_DISCLOSED | E27: NOT_DISCLOSED | F27: 405420 | G27: =G21+G22+G23+G24+G25 -> 404931 | H27: =H21+H22+H23+H24+H25 -> 404931 | I27: =I21+I22+I23+I24+I25 -> 404931 | J27: =J21+J22+J23+J24+J25 -> 395514 | K27: =K21+K22+K23+K24+K25 -> 395514
A29: B. Price drivers ($/MWh)
A30: PPA / contracted price ($/MWh) | B30: NOT_DISCLOSED | C30: NOT_DISCLOSED | D30: NOT_DISCLOSED | E30: NOT_DISCLOSED | F30: NOT_DISCLOSED | G30: 112.359 | H30: 112.921 | I30: 113.485 | J30: 114.053 | K30: 114.623
A31: Spot / merchant price ($/MWh) - active | B31: NOT_DISCLOSED | C31: NOT_DISCLOSED | D31: NOT_DISCLOSED | E31: NOT_DISCLOSED | F31: 66.44 | G31: =G33 -> 60 | H31: =H33 -> 57 | I31: =I33 -> 54 | J31: =J33 -> 51 | K31: =K33 -> 50
A32: Bear | G32: 50 | H32: 47 | I32: 44 | J32: 41 | K32: 40
A33: Base | G33: 60 | H33: 57 | I33: 54 | J33: 51 | K33: 50
A34: Bull | G34: 70 | H34: 67 | I34: 64 | J34: 61 | K34: 60
A35: Reserve price ($/MWh) | G35: 73.3 | H35: 73.3 | I35: 73.3 | J35: 73.3 | K35: 73.3
A37: C. Channel MWh
A38: PPA active fraction - Nuevo Chagres | B38: NOT_DISCLOSED | C38: NOT_DISCLOSED | D38: NOT_DISCLOSED | E38: NOT_DISCLOSED | F38: NOT_DISCLOSED | G38: 1 | H38: 1 | I38: 1 | J38: 0.5 | K38: 0
A39: PPA active fraction - Rosa de los Vientos I | B39: NOT_DISCLOSED | C39: NOT_DISCLOSED | D39: NOT_DISCLOSED | E39: NOT_DISCLOSED | F39: NOT_DISCLOSED | G39: 1 | H39: 1 | I39: 1 | J39: 0.5 | K39: 0
A40: PPA active fraction - Rosa de los Vientos II | B40: NOT_DISCLOSED | C40: NOT_DISCLOSED | D40: NOT_DISCLOSED | E40: NOT_DISCLOSED | F40: NOT_DISCLOSED | G40: 0 | H40: 0 | I40: 0 | J40: 0 | K40: 0
A41: PPA active fraction - Marañón | B41: NOT_DISCLOSED | C41: NOT_DISCLOSED | D41: NOT_DISCLOSED | E41: NOT_DISCLOSED | F41: NOT_DISCLOSED | G41: 1 | H41: 1 | I41: 1 | J41: 1 | K41: 1
A42: PPA active fraction - Portobelo Ballestillas | B42: NOT_DISCLOSED | C42: NOT_DISCLOSED | D42: NOT_DISCLOSED | E42: NOT_DISCLOSED | F42: NOT_DISCLOSED | G42: 1 | H42: 1 | I42: 1 | J42: 1 | K42: 1
A43: Contracted / PPA MWh | B43: NOT_DISCLOSED | C43: NOT_DISCLOSED | D43: NOT_DISCLOSED | E43: NOT_DISCLOSED | F43: NOT_DISCLOSED | G43: =G21*G38+G22*G39+G23*G40+G24*G41+G25*G42 -> 310761 | H43: =H21*H38+H22*H39+H23*H40+H24*H41+H25*H42 -> 310761 | I43: =I21*I38+I22*I39+I23*I40+I24*I41+I25*I42 -> 310761 | J43: =J21*J38+J22*J39+J23*J40+J24*J41+J25*J42 -> 197757 | K43: =K21*K38+K22*K39+K23*K40+K24*K41+K25*K42 -> 91980
A44: Reserve MWh | B44: NOT_DISCLOSED | C44: NOT_DISCLOSED | D44: NOT_DISCLOSED | E44: NOT_DISCLOSED | F44: NOT_DISCLOSED | G44: 34000 | H44: 34000 | I44: 34000 | J44: 34000 | K44: 34000
A45: Spot / merchant MWh | B45: NOT_DISCLOSED | C45: NOT_DISCLOSED | D45: NOT_DISCLOSED | E45: NOT_DISCLOSED | F45: NOT_DISCLOSED | G45: =MAX(0,G27-G43-G44) -> 60170 | H45: =MAX(0,H27-H43-H44) -> 60170 | I45: =MAX(0,I27-I43-I44) -> 60170 | J45: =MAX(0,J27-J43-J44) -> 163757 | K45: =MAX(0,K27-K43-K44) -> 269534
A47: D. Revenue bridge (MWh x price)
A48: Modelo revenue line | B48: =ModeloFinanciero!B7 -> 42036085 | C48: =ModeloFinanciero!C7 -> 40987418 | D48: =ModeloFinanciero!D7 -> 54587421 | E48: =ModeloFinanciero!E7 -> 42653811 | F48: =ModeloFinanciero!F7 -> 42404701 | G48: =ModeloFinanciero!G7 -> 41719195 | H48: =ModeloFinanciero!H7 -> 41713333 | I48: =ModeloFinanciero!I7 -> 41708092 | ... K48: =ModeloFinanciero!K7 -> 27211924
A49: PPA revenue | B49: NOT_DISCLOSED | C49: NOT_DISCLOSED | D49: NOT_DISCLOSED | E49: NOT_DISCLOSED | F49: NOT_DISCLOSED | G49: =G43*G30 -> 34916795 | H49: =H43*H30 -> 35091443 | I49: =I43*I30 -> 35266712 | J49: =J43*J30 -> 22554779 | K49: =K43*K30 -> 10543024
A50: Reserve revenue | B50: NOT_DISCLOSED | C50: NOT_DISCLOSED | D50: NOT_DISCLOSED | E50: NOT_DISCLOSED | F50: 2492069 | G50: =G44*G35 -> 2492200 | H50: =H44*H35 -> 2492200 | I50: =I44*I35 -> 2492200 | J50: =J44*J35 -> 2492200 | K50: =K44*K35 -> 2492200
A51: Spot / merchant revenue | B51: NOT_DISCLOSED | C51: NOT_DISCLOSED | D51: NOT_DISCLOSED | E51: NOT_DISCLOSED | F51: NOT_DISCLOSED | G51: =G45*G31 -> 3610200 | H51: =H45*H31 -> 3429690 | I51: =I45*I31 -> 3249180 | J51: =J45*J31 -> 8351607 | K51: =K45*K31 -> 13476700
A52: Other energy revenue / transmission / regional | B52: NOT_DISCLOSED | C52: NOT_DISCLOSED | D52: NOT_DISCLOSED | E52: NOT_DISCLOSED | F52: NOT_DISCLOSED | G52: 700000 | H52: 700000 | I52: 700000 | J52: 700000 | K52: 700000
A53: Total energy revenue (Generation_PPA) | B53: =B48 -> 42036085 | C53: =C48 -> 40987418 | D53: =D48 -> 54587421 | E53: =E48 -> 42653811 | F53: =F48 -> 42404701 | G53: =G49+G51+G50+G52 -> 41719195 | H53: =H49+H51+H50+H52 -> 41713333 | I53: =I49+I51+I50+I52 -> 41708092 | J53: =J49+J51+J50+J52 -> 34098586 | K53: =K49+K51+K50+K52 -> 27211924
A54: Implied total price ($/MWh = revenue / MWh) | B54: =IF(ISNUMBER(B27),IF(B27=0,"",B53/B27),"") | C54: =IF(ISNUMBER(C27),IF(C27=0,"",C53/C27),"") | D54: =IF(ISNUMBER(D27),IF(D27=0,"",D53/D27),"") | E54: =IF(ISNUMBER(E27),IF(E27=0,"",E53/E27),"") | F54: =IF(ISNUMBER(F27),IF(F27=0,"",F53/F27),"") -> 104.5945 | G54: =IF(ISNUMBER(G27),IF(G27=0,"",G53/G27),"") -> 103.02791 | H54: =IF(ISNUMBER(H27),IF(H27=0,"",H53/H27),"") -> 103.01343 | I54: =IF(ISNUMBER(I27),IF(I27=0,"",I53/I27),"") -> 103.00049 | ... K54: =IF(ISNUMBER(K27),IF(K27=0,"",K53/K27),"") -> 68.801417
A55: Revenue tie tolerance | B55: 1 | C55: 1 | D55: 1 | E55: 1 | F55: 1 | G55: 1 | H55: 1 | I55: 1 | J55: 1 | K55: 1
A56: Tie: Generation_PPA revenue - Modelo revenue | B56: =B53-B48 -> 0 | C56: =C53-C48 -> 0 | D56: =D53-D48 -> 0 | E56: =E53-E48 -> 0 | F56: =F53-F48 -> 0 | G56: =G53-G48 -> 0 | H56: =H53-H48 -> 0 | I56: =I53-I48 -> 0 | ... K56: =K53-K48 -> 0

Sheet Source_Register
A1: UEP Penonomé II, S. A.
A2: Source_Register — power archetype. Every row traces to a published filing (OCR text) or to a working file kept by the maintainer.
A3: Status semantics: OK = citation resolved to an existing artifact. SOURCE_GAP = traceability missing (visible, not hidden). NOT_DISCLOSED = no registration/manifest found for this issuer.
A4: source_id | B4: kind | C4: ticker | D4: filing | E4: year | F4: nota | G4: tabla_ocr | H4: feeds_sheet | I4: feeds_anchor | J4: date | K4: status | L4: evidence_count | M4: note
A5: OCR_ROOT:uepii-penonome | B5: OCR_ROOT | C5: UEPPSA | H5: EEFF; Notas_EEFF | I5: OCR of the published filings | J5: NOT_DISCLOSED | K5: OK | L5: 1 | M5: Annual reports (INA) of uepii-penonome
A6: EEFF_FILING:ina_y_eeff_uep_ii_y_garantes_diciembre_2021 | B6: EEFF_FILING | C6: UEPPSA | D6: INA-Y-EEFF-UEP-II-Y-GARANTES-DICIEMBRE-2021.pdf | G6: markdown.md | H6: EEFF; Notas_EEFF; MD&A | I6: 00-index.md; 01-eeff.md; 02-notas.md; 03-mda.md; 09-otros.md | J6: NOT_DISCLOSED | K6: OK | L6: 159 | M6: markdown.md sha256=87c5c989706ca593...
A7: EEFF_FILING:ina_ueppsa_2022_0 | B7: EEFF_FILING | C7: UEPPSA | D7: INA_UEPPSA_2022_0.pdf | E7: 2022 | G7: markdown.md | H7: EEFF; Notas_EEFF; MD&A | I7: 00-index.md; 01-eeff.md; 02-notas.md; 03-mda.md; 09-otros.md | J7: 2022 | K7: OK | L7: 159 | M7: markdown.md sha256=2f02ce6d20802661...
A8: EEFF_FILING:ina_ueppsa_2023_0 | B8: EEFF_FILING | C8: UEPPSA | D8: INA_UEPPSA_2023_0.pdf | E8: 2023 | G8: markdown.md | H8: EEFF; Notas_EEFF; MD&A | I8: 00-index.md; 01-eeff.md; 02-notas.md; 03-mda.md; 09-otros.md | J8: 2023 | K8: OK | L8: 158 | M8: markdown.md sha256=02e4644995c71b91...
A9: EEFF_FILING:ina_ueppsa_2024_0 | B9: EEFF_FILING | C9: UEPPSA | D9: INA_UEPPSA_2024_0.pdf | E9: 2024 | G9: markdown.md | H9: EEFF; Notas_EEFF; MD&A | I9: 00-index.md; 01-eeff.md; 02-notas.md; 03-mda.md; 09-otros.md | J9: 2024 | K9: OK | L9: 151 | M9: markdown.md sha256=9cc582a2ff7f35bc...
A10: EEFF_FILING:ina_ueppsa_2025_0 | B10: EEFF_FILING | C10: UEPPSA | D10: INA_UEPPSA_2025_0.pdf | E10: 2025 | G10: markdown.md | H10: EEFF; Notas_EEFF; MD&A | I10: 00-index.md; 01-eeff.md; 02-notas.md; 03-mda.md; 09-otros.md | J10: 2025 | K10: OK | L10: 157 | M10: markdown.md sha256=de88c39c19962afe...
A11: NOTA:INA_UEPPSA_2022_0.pdf#10. Activos Intangibles | B11: NOTA | C11: UEPPSA | D11: INA_UEPPSA_2022_0.pdf | E11: 2021 | F11: 10. Activos Intangibles | G11: tbl-26.html | H11: Notas_EEFF | I11: 10. Activos Intangibles | J11: 2021 | K11: OK | L11: 7
A12: NOTA:INA_UEPPSA_2022_0.pdf#12. Proveedores y Otras Cuentas por Pagar | B12: NOTA | C12: UEPPSA | D12: INA_UEPPSA_2022_0.pdf | E12: 2021 | F12: 12. Proveedores y Otras Cuentas por Pagar | G12: tbl-27.html | H12: Notas_EEFF | I12: 12. Proveedores y Otras Cuentas por Pagar | J12: 2021 | K12: OK | L12: 5
A13: NOTA:INA_UEPPSA_2022_0.pdf#13. Bonos por Pagar | B13: NOTA | C13: UEPPSA | D13: INA_UEPPSA_2022_0.pdf | E13: 2021 | F13: 13. Bonos por Pagar | G13: tbl-28.html; tbl-29.html; tbl-30.html | H13: Notas_EEFF | I13: 13. Bonos por Pagar | J13: 2021 | K13: OK | L13: 15
A14: NOTA:INA_UEPPSA_2022_0.pdf#14. Patrimonio de los Accionistas | B14: NOTA | C14: UEPPSA | D14: INA_UEPPSA_2022_0.pdf | E14: 2021 | F14: 14. Patrimonio de los Accionistas | G14: tbl-31.html | H14: Notas_EEFF | I14: 14. Patrimonio de los Accionistas | J14: 2021 | K14: OK | L14: 1
A15: NOTA:INA_UEPPSA_2022_0.pdf#15. Costos y Gastos | B15: NOTA | C15: UEPPSA | D15: INA_UEPPSA_2022_0.pdf | E15: 2021 | F15: 15. Costos y Gastos | G15: tbl-33.html; tbl-34.html | H15: Notas_EEFF | I15: 15. Costos y Gastos | J15: 2021 | K15: OK | L15: 24
A16: NOTA:INA_UEPPSA_2022_0.pdf#16. Saldos y Transacciones con Partes Relacionadas | B16: NOTA | C16: UEPPSA | D16: INA_UEPPSA_2022_0.pdf | E16: 2021 | F16: 16. Saldos y Transacciones con Partes Relacionadas | G16: tbl-35.html; tbl-36.html; tbl-37.html | H16: Notas_EEFF | I16: 16. Saldos y Transacciones con Partes Relacionadas | J16: 2021 | K16: OK | L16: 19
A17: NOTA:INA_UEPPSA_2022_0.pdf#17. Costos Financieros, Neto | B17: NOTA | C17: UEPPSA | D17: INA_UEPPSA_2022_0.pdf | E17: 2021 | F17: 17. Costos Financieros, Neto | G17: tbl-38.html | H17: Notas_EEFF | I17: 17. Costos Financieros, Neto | J17: 2021 | K17: OK | L17: 9
A18: NOTA:INA_UEPPSA_2022_0.pdf#18. Impuesto sobre la Renta | B18: NOTA | C18: UEPPSA | D18: INA_UEPPSA_2022_0.pdf | E18: 2021 | F18: 18. Impuesto sobre la Renta | G18: tbl-39.html; tbl-40.html; tbl-41.html | H18: Notas_EEFF | I18: 18. Impuesto sobre la Renta | J18: 2021 | K18: OK | L18: 17
A19: NOTA:INA_UEPPSA_2022_0.pdf#3. Administración de Riesgos Financieros | B19: NOTA | C19: UEPPSA | D19: INA_UEPPSA_2022_0.pdf | E19: 2021 | F19: 3. Administración de Riesgos Financieros | G19: tbl-14.html; tbl-15.html; tbl-16.html; +2 more | H19: Notas_EEFF | I19: 3. Administración de Riesgos Financieros | J19: 2021 | K19: OK | L19: 19
A20: NOTA:INA_UEPPSA_2022_0.pdf#5. Efectivo y Equivalentes de Efectivo para el Estado de Flujos de Efectivo | B20: NOTA | C20: UEPPSA | D20: INA_UEPPSA_2022_0.pdf | E20: 2021 | F20: 5. Efectivo y Equivalentes de Efectivo para el Estado de Flujos de Efectivo | G20: tbl-19.html | H20: Notas_EEFF | I20: 5. Efectivo y Equivalentes de Efectivo para el Estado de Flujos de Efectivo | J20: 2021 | K20: OK | L20: 5
A21: NOTA:INA_UEPPSA_2022_0.pdf#6. Fondo Fiduciario de Uso Específico | B21: NOTA | C21: UEPPSA | D21: INA_UEPPSA_2022_0.pdf | E21: 2021 | F21: 6. Fondo Fiduciario de Uso Específico | G21: tbl-20.html | H21: Notas_EEFF | I21: 6. Fondo Fiduciario de Uso Específico | J21: 2021 | K21: OK | L21: 9
A22: NOTA:INA_UEPPSA_2022_0.pdf#7. Deudores Comerciales y Otras Cuentas por Cobrar | B22: NOTA | C22: UEPPSA | D22: INA_UEPPSA_2022_0.pdf | E22: 2021 | F22: 7. Deudores Comerciales y Otras Cuentas por Cobrar | G22: tbl-21.html | H22: Notas_EEFF | I22: 7. Deudores Comerciales y Otras Cuentas por Cobrar | J22: 2021 | K22: OK | L22: 5
... A53: NOTA:INA_UEPPSA_2024_0.pdf#9. Arrendamientos | B53: NOTA | C53: UEPPSA | D53: INA_UEPPSA_2024_0.pdf | E53: 2023 | F53: 9. Arrendamientos | G53: tbl-23.html; tbl-24.html; tbl-25.html | H53: Notas_EEFF | I53: 9. Arrendamientos | J53: 2023 | K53: OK | L53: 11
A54: NOTA:INA_UEPPSA_2025_0.pdf#(line item EEFF sin nota dedicada) | B54: NOTA | C54: UEPPSA | D54: INA_UEPPSA_2025_0.pdf | E54: 2025 | F54: (line item EEFF sin nota dedicada) | H54: Notas_EEFF | I54: (line item EEFF sin nota dedicada) | J54: 2025 | K54: OK | L54: 8
A55: NOTA:INA_UEPPSA_2025_0.pdf#1. Información General | B55: NOTA | C55: UEPPSA | D55: INA_UEPPSA_2025_0.pdf | E55: 2025 | F55: 1. Información General | G55: markdown.md | H55: Notas_EEFF | I55: 1. Información General | J55: 2025 | K55: OK | L55: 5
A56: NOTA:INA_UEPPSA_2025_0.pdf#10. Activos Intangibles | B56: NOTA | C56: UEPPSA | D56: INA_UEPPSA_2025_0.pdf | E56: 2025 | F56: 10. Activos Intangibles | G56: markdown.md; tbl-27.html | H56: Notas_EEFF | I56: 10. Activos Intangibles | J56: 2025 | K56: OK | L56: 15
A57: NOTA:INA_UEPPSA_2025_0.pdf#11. Plusvalía | B57: NOTA | C57: UEPPSA | D57: INA_UEPPSA_2025_0.pdf | E57: 2025 | F57: 11. Plusvalía | G57: markdown.md; tbl-28.html | H57: Notas_EEFF | I57: 11. Plusvalía | J57: 2025 | K57: OK | L57: 5
A58: NOTA:INA_UEPPSA_2025_0.pdf#12. Proveedores y Otras Cuentas por Pagar | B58: NOTA | C58: UEPPSA | D58: INA_UEPPSA_2025_0.pdf | E58: 2025 | F58: 12. Proveedores y Otras Cuentas por Pagar | G58: tbl-29.html | H58: Notas_EEFF | I58: 12. Proveedores y Otras Cuentas por Pagar | J58: 2025 | K58: OK | L58: 8
A59: NOTA:INA_UEPPSA_2025_0.pdf#13. Bonos por Pagar | B59: NOTA | C59: UEPPSA | D59: INA_UEPPSA_2025_0.pdf | E59: 2025 | F59: 13. Bonos por Pagar | G59: markdown.md; tbl-30.html; tbl-31.html | H59: Notas_EEFF | I59: 13. Bonos por Pagar | J59: 2025 | K59: OK | L59: 38
A60: NOTA:INA_UEPPSA_2025_0.pdf#14. Patrimonio de los Accionistas | B60: NOTA | C60: UEPPSA | D60: INA_UEPPSA_2025_0.pdf | E60: 2025 | F60: 14. Patrimonio de los Accionistas | G60: markdown.md; tbl-32.html | H60: Notas_EEFF | I60: 14. Patrimonio de los Accionistas | J60: 2025 | K60: OK | L60: 8
A61: NOTA:INA_UEPPSA_2025_0.pdf#15. Costos y Gastos | B61: NOTA | C61: UEPPSA | D61: INA_UEPPSA_2025_0.pdf | E61: 2025 | F61: 15. Costos y Gastos | G61: tbl-33.html; tbl-34.html | H61: Notas_EEFF | I61: 15. Costos y Gastos | J61: 2025 | K61: OK | L61: 54
A62: NOTA:INA_UEPPSA_2025_0.pdf#16. Saldos y Transacciones con Partes Relacionadas | B62: NOTA | C62: UEPPSA | D62: INA_UEPPSA_2025_0.pdf | E62: 2025 | F62: 16. Saldos y Transacciones con Partes Relacionadas | G62: markdown.md; tbl-35.html; tbl-36.html | H62: Notas_EEFF | I62: 16. Saldos y Transacciones con Partes Relacionadas | J62: 2025 | K62: OK | L62: 42
A63: NOTA:INA_UEPPSA_2025_0.pdf#17. Costos Financieros, Neto | B63: NOTA | C63: UEPPSA | D63: INA_UEPPSA_2025_0.pdf | E63: 2025 | F63: 17. Costos Financieros, Neto | G63: tbl-37.html | H63: Notas_EEFF | I63: 17. Costos Financieros, Neto | J63: 2025 | K63: OK | L63: 14
A64: NOTA:INA_UEPPSA_2025_0.pdf#18. Impuesto sobre la Renta | B64: NOTA | C64: UEPPSA | D64: INA_UEPPSA_2025_0.pdf | E64: 2025 | F64: 18. Impuesto sobre la Renta | G64: markdown.md; tbl-38.html; tbl-39.html; +1 more | H64: Notas_EEFF | I64: 18. Impuesto sobre la Renta | J64: 2025 | K64: OK | L64: 23
A65: NOTA:INA_UEPPSA_2025_0.pdf#19. Compromisos | B65: NOTA | C65: UEPPSA | D65: INA_UEPPSA_2025_0.pdf | E65: 2025 | F65: 19. Compromisos | G65: markdown.md | H65: Notas_EEFF | I65: 19. Compromisos | J65: 2025 | K65: OK | L65: 11
A66: NOTA:INA_UEPPSA_2025_0.pdf#2. Resumen de las Políticas Contables Materiales | B66: NOTA | C66: UEPPSA | D66: INA_UEPPSA_2025_0.pdf | E66: 2025 | F66: 2. Resumen de las Políticas Contables Materiales | G66: markdown.md; tbl-13.html | H66: Notas_EEFF | I66: 2. Resumen de las Políticas Contables Materiales | J66: 2025 | K66: OK | L66: 30
... A73: NOTA:INA_UEPPSA_2025_0.pdf#9. Arrendamientos | B73: NOTA | C73: UEPPSA | D73: INA_UEPPSA_2025_0.pdf | E73: 2025 | F73: 9. Arrendamientos | G73: markdown.md; tbl-24.html; tbl-25.html; +1 more | H73: Notas_EEFF | I73: 9. Arrendamientos | J73: 2025 | K73: OK | L73: 23
A74: DRIVER:EEFF:Ingresos por energía | B74: DRIVER_EEFF | C74: UEPPSA | H74: Supuestos | I74: Ingreso energía FY25 (A) (auditado, ref EEFF) | J74: NOT_DISCLOSED | K74: OK | L74: 1 | M74: Ingresos por energía
A75: DRIVER:a working file kept by the maintainer | B75: DRIVER_DATA | C75: UEPPSA | H75: Supuestos | I75: Factor de planta NETO (CF) — activo | J75: NOT_DISCLOSED | K75: OK | L75: 39 | M75: a working file kept by the maintainer
A76: REGULATOR:SMV:uepii-penonome | B76: REGULATOR | H76: Source_Register | I76: https://supervalores.gob.pa/listado-de-emisores-con-valores-registrados/ | J76: 46210 | K76: OK | L76: 1 | M76: SMV (supervalores.gob.pa) — emisor con valores registrados: Bonos Garantizados Senior (UEP Penonomé II, S.A.). Listado oficial consultado 2026-07-07.
A77: REGULATOR:SBP:uepii-penonome | B77: REGULATOR | H77: Source_Register | I77: https://www.superbancos.gob.pa/ | J77: 46210 | K77: NOT_FOUND | L77: 0 | M77: No aplica / sin dato específico del emisor en SBP (no es entidad bancaria supervisada).

Sheet _CHANGELOG
A1: UEP Penonomé II, S. A.
A2: _CHANGELOG — generation record for uepii-penonome.
A3: Internal build history omitted from the public export. Record public changes below.

Sheet MDA
A1: UEP Penonomé II, S. A.
A2: MD&A — IN-A FY2025 (UEP Penonomé II, S.A.), Sección "Análisis de Resultados Financieros y Operativos" (transcripción verbatim del filing público; linaje archivo-línea en Source_Register).
A3: Il. ANÁLISIS DE RESULTADOS FINANCIEROS Y OPERATIVOS
A4: La información financiera está expresada en miles de dólares estadounidenses.
A5: A. Liquidez
A6: Expresado en US$000 al 31 de Diciembre | al 31 de Diciembre
A7: 2025 2025
A8: Flujos de efectivo de las actividades de operacién
A9: Utilidad antes del impuesto (172) (1,711)
A10: Partidas para conciliar la utilidad neta con el efectivo
A11: neto provisto por las actividades de operación: 27,596 28,437
A12: Cambios en activos y pasivos de operación 1,053 1,422
... A97: relación al mismo período del 2024.
A98: 11
A99: ```
A100: ## PDF Page 13
A101: ```text
A102: D. Análisis de perspectivas
A103: Para el año 2025, el Parque Eólico sufrió una disminución en el recurso eólico respecto al
A104: año 2024 durante la época seca debido a la transición de las condiciones ENSO neutrales
A105: hacia condiciones de La Niña, mientras que durante el año 2024 el fenómeno de "El Niño”
A106: estuvo presente durante la época seca. Esta transición provocó una disminución en el
A107: recurso viento, resultando en una menor producción con respecto al año anterior donde la
A108: producción en los meses de mayor producción se vio afectada positivamente por las
A109: condiciones de "El Niño".
A110: A nivel de margen variable en el primer trimestre de 2026, se espera que los resultados
... A122: en comparación con el año 2024.
A123: 12
A124: ```
A125: ## PDF Page 14
A126: ```text

Sheet Claude Code Log
A1: Turn # | B1: Date | C1: User Request | D1: Action Taken | E1: Details | F1: Outcome
A2: 1 | B2: 46324.359 | C2: Prepare a public model copy | D2: Remove local paths and private build references; preserve financial formulas and inputs | E2: Agent run with MOG as the tool, checked by guard v1. The guard measured every sheet before and after the run. Changed: Supuestos: 39 cells written, at N11, N12, N13, N14, N15, N16, N17, N18, N19, N20, N21, N22, N25, N26, N27 and 24 more; Source_Register: 5 cells written, at A2, I5, M5, A75, M75; _CHANGELOG: data A1:H31 -> A1:A3 (rows 31 -> 3, columns 8 -> 1), 192 cells written, at A2, A3, B3, C3, D3, E3, F3, G3, H3, A4, B4, C4, D4, E4, F4 and 177 more. Other actions: clear x1. Agent: OpenFinmods export | F2: Compare against source and review public copy
