Workbook

Sheet 00_Cover
A1: The Coca-Cola Company (KO) — 9/10 Re-gated Institutional Model
A2: Owner-prepared submission; independent reviewer reproduction is required before certification
A4: Model snapshot
A5: Legal entity | B5: The Coca-Cola Company
A6: Ticker | B6: KO
A7: Latest filing | B7: 2025-12-31 10-K filed 2026-02-20
A8: SEC accession | B8: 0001628280-26-010047
A9: Market price | B9: 82.45
A10: Market as-of | B10: 2026-07-15
A11: Active scenario | B11: =Assumptions!B4 -> Base
A12: DCF value / share | B12: =Valuation!G18 -> 53.269184
A13: Upside / (downside) | B13: =Valuation!G20 -> -0.35392135
A14: Gate decision | B14: =Gate_9of10!B17 -> OWNER READY — INDEPENDENT REVIEW REQUIRED
A15: What changed in the 9/10 re-gate
A16: What changed in the 9/10 re-gate
A17: 1 | B17: Replaced generic Sources sheet with target-cell provenance ledger
A18: 2 | B18: Replaced generic assumptions with company-specific operating drivers
A19: 3 | B19: Scenario selector now changes multiple operating outputs and the DCF
A20: 4 | B20: Debt, liquid assets and share-count valuation bridges are explicit
A21: 5 | B21: Checks are formula-driven; Gate_9of10 states owner evidence and review status
A22: 6 | B22: All original workbook files remain preserved; this is a new derivative output

Sheet Sources
A1: The Coca-Cola Company — Source Provenance Ledger
A2: Every populated hardcoded historical or driver input is mapped to a target cell with period, value, unit, taxonomy/locator, accession and exact URL.
A4: Source ID | B4: Legal Entity | C4: Target Cell | D4: Metric | E4: Period / As-of | F4: Reported Value | G4: Units | H4: Currency | I4: Taxonomy / Locator | J4: Start | K4: End | L4: FY / FP | M4: Form | N4: Filed | O4: Accession | P4: Exact URL | Q4: Retrieved | R4: Source Class | S4: Transform / Mapping | T4: Verification | U4: Limitation / Disposition | V4: Complete?
A5: 1 | B5: The Coca-Cola Company | C5: Historical!B5 | D5: Revenue | E5: 2021A | F5: 38655 | G5: USD millions | H5: USD | I5: us-gaap:Revenues | J5: 2021-01-01 | K5: 2021-12-31 | L5: 2023/FY | M5: 10-K | N5: 2024-02-20 | O5: 0000021344-24-000009 | P5: https://www.sec.gov/Archives/edgar/data/21344/000002134424000009/0000021344-24-000009-index.htm | Q5: 2026-07-16 | R5: Primary - SEC filing / Company Facts | S5: USD divided by 1,000,000; sign as presented | T5: Matched legal entity, period, form, filed date, accession and target | U5: None identified | V5: =IF(COUNTA(A5:U5)=21,"OK","MISSING") -> OK
A6: 2 | B6: The Coca-Cola Company | C6: Historical!C5 | D6: Revenue | E6: 2022A | F6: 43004 | G6: USD millions | H6: USD | I6: us-gaap:Revenues | J6: 2022-01-01 | K6: 2022-12-31 | L6: 2024/FY | M6: 10-K | N6: 2025-02-20 | O6: 0000021344-25-000011 | P6: https://www.sec.gov/Archives/edgar/data/21344/000002134425000011/0000021344-25-000011-index.htm | Q6: 2026-07-16 | R6: Primary - SEC filing / Company Facts | S6: USD divided by 1,000,000; sign as presented | T6: Matched legal entity, period, form, filed date, accession and target | U6: None identified | V6: =IF(COUNTA(A6:U6)=21,"OK","MISSING") -> OK
A7: 3 | B7: The Coca-Cola Company | C7: Historical!D5 | D7: Revenue | E7: 2023A | F7: 45754 | G7: USD millions | H7: USD | I7: us-gaap:Revenues | J7: 2023-01-01 | K7: 2023-12-31 | L7: 2025/FY | M7: 10-K | N7: 2026-02-20 | O7: 0001628280-26-010047 | P7: https://www.sec.gov/Archives/edgar/data/21344/000162828026010047/0001628280-26-010047-index.htm | Q7: 2026-07-16 | R7: Primary - SEC filing / Company Facts | S7: USD divided by 1,000,000; sign as presented | T7: Matched legal entity, period, form, filed date, accession and target | U7: None identified | V7: =IF(COUNTA(A7:U7)=21,"OK","MISSING") -> OK
A8: 4 | B8: The Coca-Cola Company | C8: Historical!E5 | D8: Revenue | E8: 2024A | F8: 47061 | G8: USD millions | H8: USD | I8: us-gaap:Revenues | J8: 2024-01-01 | K8: 2024-12-31 | L8: 2025/FY | M8: 10-K | N8: 2026-02-20 | O8: 0001628280-26-010047 | P8: https://www.sec.gov/Archives/edgar/data/21344/000162828026010047/0001628280-26-010047-index.htm | Q8: 2026-07-16 | R8: Primary - SEC filing / Company Facts | S8: USD divided by 1,000,000; sign as presented | T8: Matched legal entity, period, form, filed date, accession and target | U8: None identified | V8: =IF(COUNTA(A8:U8)=21,"OK","MISSING") -> OK
A9: 5 | B9: The Coca-Cola Company | C9: Historical!F5 | D9: Revenue | E9: 2025A | F9: 47941 | G9: USD millions | H9: USD | I9: us-gaap:Revenues | J9: 2025-01-01 | K9: 2025-12-31 | L9: 2025/FY | M9: 10-K | N9: 2026-02-20 | O9: 0001628280-26-010047 | P9: https://www.sec.gov/Archives/edgar/data/21344/000162828026010047/0001628280-26-010047-index.htm | Q9: 2026-07-16 | R9: Primary - SEC filing / Company Facts | S9: USD divided by 1,000,000; sign as presented | T9: Matched legal entity, period, form, filed date, accession and target | U9: None identified | V9: =IF(COUNTA(A9:U9)=21,"OK","MISSING") -> OK
A10: 6 | B10: The Coca-Cola Company | C10: Historical!B6 | D10: Gross profit | E10: 2021A | F10: 23298 | G10: USD millions | H10: USD | I10: us-gaap:GrossProfit | J10: 2021-01-01 | K10: 2021-12-31 | L10: 2023/FY | M10: 10-K | N10: 2024-02-20 | O10: 0000021344-24-000009 | P10: https://www.sec.gov/Archives/edgar/data/21344/000002134424000009/0000021344-24-000009-index.htm | Q10: 2026-07-16 | R10: Primary - SEC filing / Company Facts | S10: USD divided by 1,000,000; sign as presented | T10: Matched legal entity, period, form, filed date, accession and target | U10: None identified | V10: =IF(COUNTA(A10:U10)=21,"OK","MISSING") -> OK
A11: 7 | B11: The Coca-Cola Company | C11: Historical!C6 | D11: Gross profit | E11: 2022A | F11: 25004 | G11: USD millions | H11: USD | I11: us-gaap:GrossProfit | J11: 2022-01-01 | K11: 2022-12-31 | L11: 2024/FY | M11: 10-K | N11: 2025-02-20 | O11: 0000021344-25-000011 | P11: https://www.sec.gov/Archives/edgar/data/21344/000002134425000011/0000021344-25-000011-index.htm | Q11: 2026-07-16 | R11: Primary - SEC filing / Company Facts | S11: USD divided by 1,000,000; sign as presented | T11: Matched legal entity, period, form, filed date, accession and target | U11: None identified | V11: =IF(COUNTA(A11:U11)=21,"OK","MISSING") -> OK
A12: 8 | B12: The Coca-Cola Company | C12: Historical!D6 | D12: Gross profit | E12: 2023A | F12: 27234 | G12: USD millions | H12: USD | I12: us-gaap:GrossProfit | J12: 2023-01-01 | K12: 2023-12-31 | L12: 2025/FY | M12: 10-K | N12: 2026-02-20 | O12: 0001628280-26-010047 | P12: https://www.sec.gov/Archives/edgar/data/21344/000162828026010047/0001628280-26-010047-index.htm | Q12: 2026-07-16 | R12: Primary - SEC filing / Company Facts | S12: USD divided by 1,000,000; sign as presented | T12: Matched legal entity, period, form, filed date, accession and target | U12: None identified | V12: =IF(COUNTA(A12:U12)=21,"OK","MISSING") -> OK
A13: 9 | B13: The Coca-Cola Company | C13: Historical!E6 | D13: Gross profit | E13: 2024A | F13: 28737 | G13: USD millions | H13: USD | I13: us-gaap:GrossProfit | J13: 2024-01-01 | K13: 2024-12-31 | L13: 2025/FY | M13: 10-K | N13: 2026-02-20 | O13: 0001628280-26-010047 | P13: https://www.sec.gov/Archives/edgar/data/21344/000162828026010047/0001628280-26-010047-index.htm | Q13: 2026-07-16 | R13: Primary - SEC filing / Company Facts | S13: USD divided by 1,000,000; sign as presented | T13: Matched legal entity, period, form, filed date, accession and target | U13: None identified | V13: =IF(COUNTA(A13:U13)=21,"OK","MISSING") -> OK
A14: 10 | B14: The Coca-Cola Company | C14: Historical!F6 | D14: Gross profit | E14: 2025A | F14: 29544 | G14: USD millions | H14: USD | I14: us-gaap:GrossProfit | J14: 2025-01-01 | K14: 2025-12-31 | L14: 2025/FY | M14: 10-K | N14: 2026-02-20 | O14: 0001628280-26-010047 | P14: https://www.sec.gov/Archives/edgar/data/21344/000162828026010047/0001628280-26-010047-index.htm | Q14: 2026-07-16 | R14: Primary - SEC filing / Company Facts | S14: USD divided by 1,000,000; sign as presented | T14: Matched legal entity, period, form, filed date, accession and target | U14: None identified | V14: =IF(COUNTA(A14:U14)=21,"OK","MISSING") -> OK
A15: 11 | B15: The Coca-Cola Company | C15: Historical!B7 | D15: Operating income / EBIT | E15: 2021A | F15: 10308 | G15: USD millions | H15: USD | I15: us-gaap:OperatingIncomeLoss | J15: 2021-01-01 | K15: 2021-12-31 | L15: 2023/FY | M15: 10-K | N15: 2024-02-20 | O15: 0000021344-24-000009 | P15: https://www.sec.gov/Archives/edgar/data/21344/000002134424000009/0000021344-24-000009-index.htm | Q15: 2026-07-16 | R15: Primary - SEC filing / Company Facts | S15: USD divided by 1,000,000; sign as presented | T15: Matched legal entity, period, form, filed date, accession and target | U15: None identified | V15: =IF(COUNTA(A15:U15)=21,"OK","MISSING") -> OK
A16: 12 | B16: The Coca-Cola Company | C16: Historical!C7 | D16: Operating income / EBIT | E16: 2022A | F16: 10909 | G16: USD millions | H16: USD | I16: us-gaap:OperatingIncomeLoss | J16: 2022-01-01 | K16: 2022-12-31 | L16: 2024/FY | M16: 10-K | N16: 2025-02-20 | O16: 0000021344-25-000011 | P16: https://www.sec.gov/Archives/edgar/data/21344/000002134425000011/0000021344-25-000011-index.htm | Q16: 2026-07-16 | R16: Primary - SEC filing / Company Facts | S16: USD divided by 1,000,000; sign as presented | T16: Matched legal entity, period, form, filed date, accession and target | U16: None identified | V16: =IF(COUNTA(A16:U16)=21,"OK","MISSING") -> OK
... A69: 65 | B69: The Coca-Cola Company | C69: Valuation!G19 | D69: Market close | E69: 2026-07-15 | F69: 82.45 | G69: USD per share | H69: USD | I69: Secondary market:Historical daily close | J69: N/A - instant | K69: 2026-07-15 | L69: N/A | M69: Market data | N69: 2026-07-15 | O69: N/A - market data | P69: https://ph.investing.com/equities/coca-cola-co-historical-data | Q69: 2026-07-16 | R69: Secondary - dated market close | S69: Closing price as displayed; no FX | T69: Date and close matched on cited historical-price surface | U69: Secondary market source; refresh before transaction use | V69: =IF(COUNTA(A69:U69)=21,"OK","MISSING") -> OK
A71: Ledger completeness | G71: =COUNTIF(V5:V69,"OK") -> 65 | H71: 65 | I71: =IF(G71=H71,"OK","REVIEW") -> OK

Sheet Historical
A1: The Coca-Cola Company — Historical Financials
A2: SEC 10-K / Company Facts lineage; USD millions except per-share data and shares
A4: Metric | B4: 2021A | C4: 2022A | D4: 2023A | E4: 2024A | F4: 2025A
A5: Revenue | B5: 38655 | C5: 43004 | D5: 45754 | E5: 47061 | F5: 47941
A6: Gross profit | B6: 23298 | C6: 25004 | D6: 27234 | E6: 28737 | F6: 29544
A7: Operating income / EBIT | B7: 10308 | C7: 10909 | D7: 11311 | E7: 9992 | F7: 13762
A8: Net income | B8: 9771 | C8: 9542 | D8: 10714 | E8: 10631 | F8: 13107
A9: Cash from operations | B9: 12625 | C9: 11018 | D9: 11599 | E9: 6805 | F9: 7408
A10: Capital expenditures | B10: 1367 | C10: 1484 | D10: 1852 | E10: 2064 | F10: 2112
A11: Total assets | B11: 94354 | C11: 92763 | D11: 97703 | E11: 100549 | F11: 104816
A12: Shareholders' equity | B12: 22999 | C12: 24105 | D12: 25941 | E12: 24856 | F12: 32169
A13: Cash and equivalents | B13: 9684 | C13: 9519 | D13: 9366 | E13: 10828 | F13: 10270
A14: Total debt | D14: 37507 | E14: 43023 | F14: 43941
A15: Diluted weighted-average shares | B15: 4340 | C15: 4350 | D15: 4339 | E15: 4320 | F15: 4313
A17: Bridge policy | B17: Latest balance-sheet cash policy
A18: Liquid assets used in DCF | B18: =B23 -> 10270 | F18: USD millions
A19: Debt used in DCF | B19: =SUM(B24:B25) -> 43997 | F19: USD millions
A20: Share count used in DCF | B20: 4300.723 | F20: million shares
A22: Coca-Cola valuation bridge | B22: 2025A | C22: Policy | D22: USD m | E22: Source | F22: Status
A23: Cash and equivalents | B23: =F13 -> 10270 | C23: Included | D23: USD m | E23: Historical latest balance | F23: Formula link
A24: Debt including current maturities | B24: =F14 -> 43941 | C24: Included | D24: USD m | E24: Historical latest balance | F24: Formula link
A25: Other short-term borrowings | B25: 56 | C25: Included | D25: USD m | E25: us-gaap:OtherShortTermBorrowings | F25: OK

Sheet Assumptions
A1: The Coca-Cola Company — Scenario Assumptions
A2: Selector drives operating revenues/margins and the DCF; blue/amber cells are editable inputs
A3: Scenario selector (1 Base / 2 Bull / 3 Bear) | B3: 1 | G3: Input
A4: Active scenario | B4: =CHOOSE(B3,"Base","Bull","Bear") -> Base | G4: Formula
A6: Assumption | B6: Units | C6: Base | D6: Bull | E6: Bear | F6: Active | G6: Rationale / evidence
A7: Unit case volume contribution | B7: % | C7: 0.015 | D7: 0.025 | E7: 0 | F7: =CHOOSE($B$3,C7,D7,E7) -> 0.015 | G7: 2025 system unit cases 33.8bn; driver contribution
A8: Price / mix contribution | B8: % | C8: 0.04 | D8: 0.05 | E8: 0.025 | F8: =CHOOSE($B$3,C8,D8,E8) -> 0.04 | G8: 2025 reported price/mix contribution +4%
A9: Foreign-exchange contribution | B9: % | C9: 0 | D9: 0.01 | E9: -0.02 | F9: =CHOOSE($B$3,C9,D9,E9) -> 0 | G9: Scenario FX translation contribution
A10: Structural / acquisition contribution | B10: % | C10: 0 | D10: 0.005 | E10: -0.01 | F10: =CHOOSE($B$3,C10,D10,E10) -> 0 | G10: Scenario portfolio contribution
A11: Operating margin | B11: % | C11: 0.29 | D11: 0.31 | E11: 0.27 | F11: =CHOOSE($B$3,C11,D11,E11) -> 0.29 | G11: Normalized consolidated operating margin
A12: Cash tax rate | B12: % | C12: 0.19 | D12: 0.175 | E12: 0.21 | F12: =CHOOSE($B$3,C12,D12,E12) -> 0.19 | G12: Normalized cash tax rate
A13: D&A as % revenue | B13: % | C13: 0.045 | D13: 0.047 | E13: 0.043 | F13: =CHOOSE($B$3,C13,D13,E13) -> 0.045 | G13: Normalized D&A intensity
A14: Capex as % revenue | B14: % | C14: 0.045 | D14: 0.04 | E14: 0.05 | F14: =CHOOSE($B$3,C14,D14,E14) -> 0.045 | G14: Normalized capex intensity
A15: NWC investment / revenue growth | B15: % | C15: 0.01 | D15: 0.005 | E15: 0.015 | F15: =CHOOSE($B$3,C15,D15,E15) -> 0.01 | G15: FCFF working-capital policy
A16: WACC | B16: % | C16: 0.075 | D16: 0.068 | E16: 0.085 | F16: =CHOOSE($B$3,C16,D16,E16) -> 0.075 | G16: DCF discount-rate scenario
A17: Terminal growth | B17: % | C17: 0.025 | D17: 0.03 | E17: 0.02 | F17: =CHOOSE($B$3,C17,D17,E17) -> 0.025 | G17: DCF perpetual-growth scenario

Sheet Forecast
A1: The Coca-Cola Company — Operating Forecast
A2: Scenario-linked driver build; USD millions except shares and per-share data
A4: Metric | B4: 2025A | C4: 2026E | D4: 2027E | E4: 2028E | F4: 2029E | G4: 2030E
A5: Unit case volume contribution | B5: 0.01 | C5: =Assumptions!F7 -> 0.015 | D5: =Assumptions!F7 -> 0.015 | E5: =Assumptions!F7 -> 0.015 | F5: =Assumptions!F7 -> 0.015 | G5: =Assumptions!F7 -> 0.015
A6: Price / mix contribution | B6: 0.04 | C6: =Assumptions!F8 -> 0.04 | D6: =Assumptions!F8 -> 0.04 | E6: =Assumptions!F8 -> 0.04 | F6: =Assumptions!F8 -> 0.04 | G6: =Assumptions!F8 -> 0.04
A7: FX contribution | B7: -0.02 | C7: =Assumptions!F9 -> 0 | D7: =Assumptions!F9 -> 0 | E7: =Assumptions!F9 -> 0 | F7: =Assumptions!F9 -> 0 | G7: =Assumptions!F9 -> 0
A8: Structural contribution | B8: -0.01 | C8: =Assumptions!F10 -> 0 | D8: =Assumptions!F10 -> 0 | E8: =Assumptions!F10 -> 0 | F8: =Assumptions!F10 -> 0 | G8: =Assumptions!F10 -> 0
A9: Revenue growth | B9: 0.02 | C9: =SUM(C5:C8) -> 0.055 | D9: =SUM(D5:D8) -> 0.055 | E9: =SUM(E5:E8) -> 0.055 | F9: =SUM(F5:F8) -> 0.055 | G9: =SUM(G5:G8) -> 0.055
A10: Revenue | B10: 47941 | C10: =B10*(1+C9) -> 50577.755 | D10: =C10*(1+D9) -> 53359.532 | E10: =D10*(1+E9) -> 56294.306 | F10: =E10*(1+F9) -> 59390.493 | G10: =F10*(1+G9) -> 62656.97
A11: EBIT | B11: 13200 | C11: =C10*Assumptions!F11 -> 14667.549 | D11: =D10*Assumptions!F11 -> 15474.264 | E11: =E10*Assumptions!F11 -> 16325.349 | F11: =F10*Assumptions!F11 -> 17223.243 | G11: =G10*Assumptions!F11 -> 18170.521
A12: Cash taxes | B12: =-B11*Assumptions!F12 -> -2508 | C12: =-C11*Assumptions!F12 -> -2786.8343 | D12: =-D11*Assumptions!F12 -> -2940.1102 | E12: =-E11*Assumptions!F12 -> -3101.8162 | F12: =-F11*Assumptions!F12 -> -3272.4161 | G12: =-G11*Assumptions!F12 -> -3452.399
A13: NOPAT | B13: =SUM(B11:B12) -> 10692 | C13: =SUM(C11:C12) -> 11880.715 | D13: =SUM(D11:D12) -> 12534.154 | E13: =SUM(E11:E12) -> 13223.532 | F13: =SUM(F11:F12) -> 13950.827 | G13: =SUM(G11:G12) -> 14718.122
A14: D&A | B14: 0 | C14: =C10*Assumptions!F13 -> 2275.999 | D14: =D10*Assumptions!F13 -> 2401.1789 | E14: =E10*Assumptions!F13 -> 2533.2438 | F14: =F10*Assumptions!F13 -> 2672.5722 | G14: =G10*Assumptions!F13 -> 2819.5636
A15: Capital expenditures | B15: 0 | C15: =-C10*Assumptions!F14 -> -2275.999 | D15: =-D10*Assumptions!F14 -> -2401.1789 | E15: =-E10*Assumptions!F14 -> -2533.2438 | F15: =-F10*Assumptions!F14 -> -2672.5722 | G15: =-G10*Assumptions!F14 -> -2819.5636
A16: Change in NWC | B16: 0 | C16: =-(C10-B10)*Assumptions!F15 -> -26.36755 | D16: =-(D10-C10)*Assumptions!F15 -> -27.817765 | E16: =-(E10-D10)*Assumptions!F15 -> -29.347742 | F16: =-(F10-E10)*Assumptions!F15 -> -30.961868 | G16: =-(G10-F10)*Assumptions!F15 -> -32.664771
A17: FCFF | B17: 0 | C17: =SUM(C13:C16) -> 11854.347 | D17: =SUM(D13:D16) -> 12506.336 | E17: =SUM(E13:E16) -> 13194.185 | F17: =SUM(F13:F16) -> 13919.865 | G17: =SUM(G13:G16) -> 14685.457

Sheet Valuation
A1: The Coca-Cola Company — DCF Valuation
A2: Unlevered FCFF; liquid-asset and debt bridge policies are explicit
A4: DCF item | B4: Year 1 | C4: Year 2 | D4: Year 3 | E4: Year 4 | F4: Year 5 | G4: Bridge / output
A5: FCFF | B5: =Forecast!C17 -> 11854.347 | C5: =Forecast!D17 -> 12506.336 | D5: =Forecast!E17 -> 13194.185 | E5: =Forecast!F17 -> 13919.865 | F5: =Forecast!G17 -> 14685.457
A6: Discount period | B6: 1 | C6: 2 | D6: 3 | E6: 4 | F6: 5
A7: Discount factor | B7: =1/(1+Assumptions!F16)^B6 -> 0.93023256 | C7: =1/(1+Assumptions!F16)^C6 -> 0.86533261 | D7: =1/(1+Assumptions!F16)^D6 -> 0.80496057 | E7: =1/(1+Assumptions!F16)^E6 -> 0.74880053 | F7: =1/(1+Assumptions!F16)^F6 -> 0.69655863
A8: Present value of FCFF | B8: =B5*B7 -> 11027.3 | C8: =C5*C7 -> 10822.141 | D8: =D5*D7 -> 10620.798 | E8: =E5*E7 -> 10423.202 | F8: =F5*F7 -> 10229.282
A9: Terminal value | F9: =F5*(1+Assumptions!F17)/(Assumptions!F16-Assumptions!F17) -> 301051.88
A10: PV of terminal value | F10: =F9*F7 -> 209700.28
A11: Enterprise value | G11: =SUM(B8:F8)+F10 -> 262823.01
A12: Liquid assets | G12: =Historical!B18 -> 10270
A13: Debt | G13: =Historical!B19 -> 43997
A14: Equity value | G14: =G11+G12-G13 -> 229096.01
A15: Shares outstanding / diluted policy | G15: =Historical!B20 -> 4300.723
A17: Per-share outputs
A18: DCF value / share | G18: =G14/G15 -> 53.269184
A19: Market price | G19: 82.45
A20: Upside / (downside) | G20: =G18/G19-1 -> -0.35392135
A21: Market as-of | G21: 2026-07-15

Sheet Sensitivity
A1: The Coca-Cola Company — DCF Sensitivity
A2: Implied value per share across WACC and terminal-growth assumptions
A4: WACC / TGR | B4: 0.015 | C4: 0.02 | D4: 0.025 | E4: 0.03 | F4: 0.035
A5: 0.065 | B5: =(SUM(Valuation!B8:F8)+Forecast!G17*(1+B$4)/($A5-B$4)*Valuation!F7+Valuation!G12-Valuation!G13)/Valuation!G15 -> 52.793484 | C5: =(SUM(Valuation!B8:F8)+Forecast!G17*(1+C$4)/($A5-C$4)*Valuation!F7+Valuation!G12-Valuation!G13)/Valuation!G15 -> 58.422607 | D5: =(SUM(Valuation!B8:F8)+Forecast!G17*(1+D$4)/($A5-D$4)*Valuation!F7+Valuation!G12-Valuation!G13)/Valuation!G15 -> 65.459012 | E5: =(SUM(Valuation!B8:F8)+Forecast!G17*(1+E$4)/($A5-E$4)*Valuation!F7+Valuation!G12-Valuation!G13)/Valuation!G15 -> 74.505817 | F5: =(SUM(Valuation!B8:F8)+Forecast!G17*(1+F$4)/($A5-F$4)*Valuation!F7+Valuation!G12-Valuation!G13)/Valuation!G15 -> 86.568225
A6: 0.07 | B6: =(SUM(Valuation!B8:F8)+Forecast!G17*(1+B$4)/($A6-B$4)*Valuation!F7+Valuation!G12-Valuation!G13)/Valuation!G15 -> 48.404065 | C6: =(SUM(Valuation!B8:F8)+Forecast!G17*(1+C$4)/($A6-C$4)*Valuation!F7+Valuation!G12-Valuation!G13)/Valuation!G15 -> 53.031334 | D6: =(SUM(Valuation!B8:F8)+Forecast!G17*(1+D$4)/($A6-D$4)*Valuation!F7+Valuation!G12-Valuation!G13)/Valuation!G15 -> 58.686885 | E6: =(SUM(Valuation!B8:F8)+Forecast!G17*(1+E$4)/($A6-E$4)*Valuation!F7+Valuation!G12-Valuation!G13)/Valuation!G15 -> 65.756325 | F6: =(SUM(Valuation!B8:F8)+Forecast!G17*(1+F$4)/($A6-F$4)*Valuation!F7+Valuation!G12-Valuation!G13)/Valuation!G15 -> 74.845604
A7: 0.075 | B7: =(SUM(Valuation!B8:F8)+Forecast!G17*(1+B$4)/($A7-B$4)*Valuation!F7+Valuation!G12-Valuation!G13)/Valuation!G15 -> 44.746216 | C7: =(SUM(Valuation!B8:F8)+Forecast!G17*(1+C$4)/($A7-C$4)*Valuation!F7+Valuation!G12-Valuation!G13)/Valuation!G15 -> 48.620292 | D7: =(SUM(Valuation!B8:F8)+Forecast!G17*(1+D$4)/($A7-D$4)*Valuation!F7+Valuation!G12-Valuation!G13)/Valuation!G15 -> 53.269184 | E7: =(SUM(Valuation!B8:F8)+Forecast!G17*(1+E$4)/($A7-E$4)*Valuation!F7+Valuation!G12-Valuation!G13)/Valuation!G15 -> 58.951164 | F7: =(SUM(Valuation!B8:F8)+Forecast!G17*(1+F$4)/($A7-F$4)*Valuation!F7+Valuation!G12-Valuation!G13)/Valuation!G15 -> 66.053637
A8: 0.08 | B8: =(SUM(Valuation!B8:F8)+Forecast!G17*(1+B$4)/($A8-B$4)*Valuation!F7+Valuation!G12-Valuation!G13)/Valuation!G15 -> 41.651113 | C8: =(SUM(Valuation!B8:F8)+Forecast!G17*(1+C$4)/($A8-C$4)*Valuation!F7+Valuation!G12-Valuation!G13)/Valuation!G15 -> 44.944424 | D8: =(SUM(Valuation!B8:F8)+Forecast!G17*(1+D$4)/($A8-D$4)*Valuation!F7+Valuation!G12-Valuation!G13)/Valuation!G15 -> 48.83652 | E8: =(SUM(Valuation!B8:F8)+Forecast!G17*(1+E$4)/($A8-E$4)*Valuation!F7+Valuation!G12-Valuation!G13)/Valuation!G15 -> 53.507035 | F8: =(SUM(Valuation!B8:F8)+Forecast!G17*(1+F$4)/($A8-F$4)*Valuation!F7+Valuation!G12-Valuation!G13)/Valuation!G15 -> 59.215442
A9: 0.085 | B9: =(SUM(Valuation!B8:F8)+Forecast!G17*(1+B$4)/($A9-B$4)*Valuation!F7+Valuation!G12-Valuation!G13)/Valuation!G15 -> 38.998167 | C9: =(SUM(Valuation!B8:F8)+Forecast!G17*(1+C$4)/($A9-C$4)*Valuation!F7+Valuation!G12-Valuation!G13)/Valuation!G15 -> 41.834074 | D9: =(SUM(Valuation!B8:F8)+Forecast!G17*(1+D$4)/($A9-D$4)*Valuation!F7+Valuation!G12-Valuation!G13)/Valuation!G15 -> 45.142633 | E9: =(SUM(Valuation!B8:F8)+Forecast!G17*(1+E$4)/($A9-E$4)*Valuation!F7+Valuation!G12-Valuation!G13)/Valuation!G15 -> 49.052747 | F9: =(SUM(Valuation!B8:F8)+Forecast!G17*(1+F$4)/($A9-F$4)*Valuation!F7+Valuation!G12-Valuation!G13)/Valuation!G15 -> 53.744885
B11: Central cross-check
B12: Active WACC | C12: =Assumptions!F16 -> 0.075
B13: Active TGR | C13: =Assumptions!F17 -> 0.025
B14: Active DCF value/share | C14: =Valuation!G18 -> 53.269184

Sheet Checks
A1: The Coca-Cola Company — Model Checks
A2: Overall status is formula-driven from assertions; source completeness is linked to the provenance ledger
A4: Assertion | B4: Actual | C4: Expected | D4: Difference | E4: Tolerance | F4: Status | G4: Fix hint
A5: Source ledger complete | B5: =Sources!I71 -> OK | C5: OK | F5: =IF(B5=C5,"OK","REVIEW") -> OK | G5: Complete every mandatory provenance field
A6: Scenario selector valid | B6: =Assumptions!B3 -> 1 | C6: 1 | D6: =IF(AND(B6>=1,B6<=3),0,1) -> 0 | E6: 0 | F6: =IF(D6=E6,"OK","REVIEW") -> OK | G6: Set Assumptions!B3 to 1, 2 or 3
A7: Forecast revenue positive | B7: =Forecast!C10 -> 50577.755 | C7: 0 | D7: =IF(B7>0,0,1) -> 0 | E7: 0 | F7: =IF(D7=E7,"OK","REVIEW") -> OK | G7: Inspect revenue-driver formulas
A8: Five EBIT periods populated | B8: =COUNT(Forecast!C11:G11) -> 5 | C8: 5 | D8: =ABS(B8-C8) -> 0 | E8: 0 | F8: =IF(D8=E8,"OK","REVIEW") -> OK | G8: Inspect margin and opex build
A9: Five FCFF periods populated | B9: =COUNT(Forecast!C17:G17) -> 5 | C9: 5 | D9: =ABS(B9-C9) -> 0 | E9: 0 | F9: =IF(D9=E9,"OK","REVIEW") -> OK | G9: Inspect NOPAT, D&A, capex and NWC
A10: Latest historical capex source present | B10: =COUNT(Historical!F10) -> 1 | C10: 1 | D10: =ABS(B10-C10) -> 0 | E10: 0.1 | F10: =IF(D10<=E10,"OK","REVIEW") -> OK | G10: Historical inputs are positive as reported; forecast expense/capex anchors are negative model outflows
A11: DCF equity bridge | B11: =Valuation!G14 -> 229096.01 | C11: =Valuation!G11+Valuation!G12-Valuation!G13 -> 229096.01 | D11: =ABS(B11-C11) -> 0 | E11: 0.1 | F11: =IF(D11<=E11,"OK","REVIEW") -> OK | G11: Inspect EV, liquid assets and total debt
A12: DCF per-share identity | B12: =Valuation!G18 -> 53.269184 | C12: =Valuation!G14/Valuation!G15 -> 53.269184 | D12: =ABS(B12-C12) -> 0 | E12: 0.001 | F12: =IF(D12<=E12,"OK","REVIEW") -> OK | G12: Inspect shares bridge
A13: Market price positive and sourced | B13: =Valuation!G19 -> 82.45 | C13: 0 | D13: =IF(B13>0,0,1) -> 0 | E13: 0 | F13: =IF(D13=E13,"OK","REVIEW") -> OK | G13: Update the dated market source row in Sources
A15: Overall status | F15: =IF(COUNTIF(F5:F13,"OK")=9,"OK","REVIEW") -> OK

Sheet Sector_KPIs
A1: The Coca-Cola Company — Company Operating Drivers
A2: Company-specific reported driver history; formulas reconcile the model totals to historical revenue where applicable
A4: Metric | B4: 2024A | C4: 2025A | D4: Units | E4: Source / locator | F4: Status | G4: Model use
A5: System unit cases | B5: 33.7 | C5: 33.8 | D5: billion cases | E5: 2025 Form 10-K, operating review | F5: Reported | G5: Volume anchor
A6: Consolidated revenue | B6: 47061 | C6: 47941 | D6: USD m | E6: 2025 Form 10-K | F6: Reported | G6: Revenue anchor
A7: Volume contribution | C7: 0.01 | D7: % | E7: 2025 Form 10-K revenue contribution bridge | F7: Reported | G7: Scenario driver
A8: Price / mix contribution | C8: 0.04 | D8: % | E8: 2025 Form 10-K revenue contribution bridge | F8: Reported | G8: Scenario driver
A9: FX contribution | C9: -0.02 | D9: % | E9: 2025 Form 10-K revenue contribution bridge | F9: Reported | G9: Scenario driver
A10: Acquisition / divestiture contribution | C10: -0.01 | D10: % | E10: 2025 Form 10-K revenue contribution bridge | F10: Reported | G10: Scenario driver
A11: Total reported revenue growth | C11: 0.02 | D11: % | E11: 2025 Form 10-K revenue contribution bridge | F11: Reported | G11: Cross-check

Sheet Change_Log
A1: The Coca-Cola Company — Change Log
A2: Re-gating work performed without overwriting the prior workbook
A4: Timestamp (UTC) | B4: Scope | C4: Change | D4: Evidence | E4: Prior hash | F4: Preparer | G4: Disposition
A5: Build 2026-07-17T02:33:12.208Z | B5: Source lineage | C5: Added line-item target-cell provenance ledger | D5: Sources + SEC Company Facts / 10-K | E5: 2d7d208c175d48f0001dbe569fc7cd0c298f02fd51e1cb5f8d76b241a6261b48 | F5: Codex | G5: Ready for independent review
A6: Build 2026-07-17T02:33:12.208Z | B6: Operating model | C6: Added company-specific revenue and margin drivers | D6: Sector_KPIs, Assumptions, Forecast | E6: 2d7d208c175d48f0001dbe569fc7cd0c298f02fd51e1cb5f8d76b241a6261b48 | F6: Codex | G6: Ready for independent review
A7: Build 2026-07-17T02:33:12.208Z | B7: Valuation | C7: Rebuilt FCFF DCF, bridge and sensitivity | D7: Valuation + Sensitivity | E7: 2d7d208c175d48f0001dbe569fc7cd0c298f02fd51e1cb5f8d76b241a6261b48 | F7: Codex | G7: Ready for independent review
A8: Build 2026-07-17T02:33:12.208Z | B8: Governance | C8: Added formula-driven checks and Gate_9of10 | D8: Checks + Gate_9of10 | E8: 2d7d208c175d48f0001dbe569fc7cd0c298f02fd51e1cb5f8d76b241a6261b48 | F8: Codex | G8: Owner submission only
A9: 46224 | B9: Ola 2 elevation: added IS_Hist/BS_Hist/CF_Hist (full 5-yr FY2021A-FY2025A audited line-item detail, USD mm, R3/R5/R7.htm + companyfacts.json cited), Checks_TieOut (24 cross-statement/subtotal/continuity checks), Sources_Audited (per-block citation + gap register), Forecast_IG (driver-built Base/Bull/Bear FY2026E-FY2030E). Root untouched; v2 saved under the maintainer's archive. Built via Mog SDK only. Known gaps: FY2021-22 CF custom-tag (ko:) line splits and FY2021-22 BS non-current-asset residual ($1,603mm/$1,136mm) — both disclosed and quantified in Sources_Audited, not estimated. | C9: Claude (run 24e4a1f1)
A10: Build 2026-08-14 (UTC) | B10: Capa de cobertura (Ola 1 flota internacional, plantilla del piloto Apple) | C10: Agregadas 2 hojas nuevas: Drivers_MDA (drivers del MD&A FY2021A-FY2025A: volumen, bridge de ingresos, segmentos con quiebre de presentación declarado, concentrado vs producto terminado en dólares por la Nota 3, FX, commodities, working capital con detalle de la Nota 21, dividendos, NOT_AVAILABLE declarados, memo dual-vintage FY2023, puente al motor) y Market_Package (precio 87.42 al 2026-08-13, acciones 4,302.549m del 10-Q Q2 FY2026, EV, WACC fechado 5.88%, múltiplos, LTM al Q2 FY2026, control de procedencia, hallazgos H1-H4). Agregados 21 checks (32-52) en Checks_TieOut más el conteo mecanizado B3. ÚNICA celda preexistente modificada: Checks_TieOut!B2 (rango del MASTER ampliado de H5:H30 a H5:H52 para que los checks nuevos puedan reprobarlo). Todo lo demás es estrictamente aditivo; cero cambios en hojas históricas, Forecast, Valuation, Assumptions o Gate_9of10. | D10: Drivers_MDA!A1:I177; Market_Package!A1:F107; Checks_TieOut!A31:H52; fuentes: 5 10-K locales (pdftotext) + 10-Q Q2 FY2026 descargado de EDGAR (accn 0001628280-26-050503) + Treasury/FRED/Damodaran/stockanalysis con fecha | E10: e5f93ad944a76f3ffa8e7f049359a4ac43155bfb1a66f44b4955c0f992f2b2d2 | F10: Claude (builder de cobertura KO, corrida 2026-08-14) | G10: Aditivo; pendiente revisión independiente

Sheet Gate_9of10
A1: The Coca-Cola Company — Gate 9/10 Owner Submission
A2: Independent review is a separate role; this sheet does not self-certify the workbook
A4: Gate | B4: Weight | C4: Owner status | D4: Blocker class | E4: Exact evidence range | F4: Native / visual evidence | G4: Independent action | H4: Notes
A5: H0 Controlled lineage / package | B5: 5 | C5: PASS | D5: None identified | E5: Change_Log!A4:G8; final .xlsx | F5: Prior hash preserved; OOXML integrity PASS 2026-07-17T02:36:50.241Z | G5: Reproduce lineage and package test | H5: Final JSON carries prior and final hashes
A6: H1 Source fidelity | B6: 20 | C6: PASS | D6: None identified | E6: Sources!A4:V500 | F6: SEC target-cell ledger + formula completeness | G6: Sample and reproduce ledger mappings | H6: Every populated hardcoded historical/driver cell mapped
A7: H2 Historical / formula / schedule mechanics | B7: 15 | C7: PASS | D7: None identified | E7: Historical!A4:F26; Forecast!A4:G30 | F7: Five-year historicals and formula-driven operating build | G7: Reperform historical and forecast ties | H7: Reported values preserved; forecast cells formula-driven
A8: H3 Scenario / sensitivity | B8: 10 | C8: PASS | D8: None identified | E8: Assumptions!A3:G30; Sensitivity!A4:G14 | F8: Base/Bull/Bear selector + dynamic DCF sensitivity | G8: Perturb selector 1/2/3 and reset to 1 | H8: Evidence JSON records exact outputs
A9: H4 Valuation fit / mechanics | B9: 15 | C9: PASS | D9: None identified | E9: Valuation!A4:G21; Historical!A17:F26 | F9: FCFF, bridge and per-share DCF | G9: Reperform DCF and balance-sheet bridge | H9: Debt/liquid asset/share policies explicit
A10: H5 Checks / error state | B10: 8 | C10: PASS | D10: None identified | E10: Checks!A4:G14 | F10: Formula-driven checks OK and zero formula-error matches 2026-07-17T02:33:56.001Z | G10: Reproduce checks and formula-error scan | H10: Final scan repeated after gate promotion
A11: H6 Native recalc / reproducibility | B11: 10 | C11: PASS | D11: None identified | E11: Checks!A4:G14 | F11: LibreOfficeDev 26.8.0.0.alpha0 2c87e51eeaa2b413ff4ae097b2705eea1995d8e5; save/reopen completed 2026-07-17T02:33:56.001Z | G11: Reopen and reproduce in native engine | H11: Final recalc repeated after gate promotion; evidence JSON carries hashes
A12: H7 Post-recalc all-sheet visual QA | B12: 7 | C12: PASS | D12: None identified | E12: internal QA evidence (not published) | F12: All 11 sheets rendered in preflight 2026-07-17T02:33:56.001Z; final render repeated after promotion | G12: Inspect preview manifest | H12: Final JSON carries per-sheet manifest
A13: H8 Material economic upgrade | B13: 5 | C13: PASS | D13: None identified | E13: Sector_KPIs!A4:G40; Assumptions!A6:G30; Forecast!A4:G30 | F13: Company-specific driver and margin build | G13: Challenge economic usefulness | H13: No relabel-only sector shell
A14: H9 Governance / limitations / handoff | B14: 5 | C14: PASS | D14: None identified | E14: Change_Log!A4:G8; Gate_9of10!A4:H26 | F14: Owner/reviewer separation and limitations explicit | G14: Assign independent reviewer | H14: No self-certification; evidence JSON is handoff surface
A16: Owner score | B16: =SUMIF(C5:C14,"PASS",B5:B14) -> 100
A17: Decision | B17: =IF(B16=100,"OWNER READY — INDEPENDENT REVIEW REQUIRED","PENDING OWNER QA") -> OWNER READY — INDEPENDENT REVIEW REQUIRED
A18: Overall model status | B18: =Checks!F15 -> OK
A20: Native recalculation / review metadata
A21: Build timestamp UTC | B21: Build 2026-07-17T02:33:12.208Z
A22: Required native engine | B22: LibreOfficeDev 26.8.0.0.alpha0 2c87e51eeaa2b413ff4ae097b2705eea1995d8e5
A23: Final native timestamp | B23: Native preflight 2026-07-17T02:33:56.001Z; final recalc after promotion 2026-07-17T02:36:52.392Z
A24: Visual manifest | B24: internal QA evidence (not published)
A25: Evidence manifest | B25: internal QA evidence (not published)
A26: Independent certification | B26: Not performed by owner-preparer

Sheet IS_Hist
A1: The Coca-Cola Company — Consolidated Statements of Income (audited), Ola 2
A2: USD millions except per-share data and shares. FY2023-FY2025 per FY2025 10-K (R3.htm); FY2021-FY2022 per SEC companyfacts.json us-gaap tags. All tie-outs in Checks_TieOut.
A4: Line item | B4: FY2021A | C4: FY2022A | D4: FY2023A | E4: FY2024A | F4: FY2025A | H4: Source
A5: Net operating revenues | B5: 38655 | C5: 43004 | D5: 45754 | E5: 47061 | F5: 47941 | H5: R3/us-gaap:Revenues
A6: Cost of goods sold | B6: 15357 | C6: 18000 | D6: 18520 | E6: 18324 | F6: 18397 | H6: R3/us-gaap:CostOfGoodsAndServicesSold
A7: Gross profit | B7: 23298 | C7: 25004 | D7: 27234 | E7: 28737 | F7: 29544 | H7: R3/us-gaap:GrossProfit
A8: Selling, general and administrative expenses | B8: 12144 | C8: 12880 | D8: 13972 | E8: 14582 | F8: 14521 | H8: R3/us-gaap:SellingGeneralAndAdministrativeExpense
A9: Other operating charges | B9: 846 | C9: 1215 | D9: 1951 | E9: 4163 | F9: 1261 | H9: us-gaap:OtherCostAndExpenseOperating (21-22) / R3 (23-25)
A10: Operating income | B10: 10308 | C10: 10909 | D10: 11311 | E10: 9992 | F10: 13762 | H10: R3/us-gaap:OperatingIncomeLoss
A11: Interest income | B11: 276 | C11: 449 | D11: 907 | E11: 988 | F11: 786 | H11: R3/us-gaap:InvestmentIncomeInterest
A12: Interest expense | B12: 1597 | C12: 882 | D12: 1527 | E12: 1656 | F12: 1654 | H12: R3/us-gaap:InterestExpense
A13: Equity income (loss) — net | B13: 1438 | C13: 1472 | D13: 1691 | E13: 1770 | F13: 2031 | H13: R3/us-gaap:IncomeLossFromEquityMethodInvestments
A14: Other income (loss) — net | B14: 2000 | C14: -262 | D14: 570 | E14: 1992 | F14: 1073 | H14: R3/us-gaap:OtherNonoperatingIncomeExpense
A15: Income before income taxes | B15: 12425 | C15: 11686 | D15: 12952 | E15: 13086 | F15: 15998 | H15: R3/us-gaap:IncomeLossFromContinuingOperationsBeforeIncomeTaxes...
A16: Income taxes | B16: 2621 | C16: 2115 | D16: 2249 | E16: 2437 | F16: 2861 | H16: R3/us-gaap:IncomeTaxExpenseBenefit
... A24: Average shares outstanding — diluted (millions) | B24: 4340 | C24: 4350 | D24: 4339 | E24: 4320 | F24: 4313 | H24: R3/us-gaap:WeightedAverageNumberOfDilutedSharesOutstanding

Sheet BS_Hist
A1: The Coca-Cola Company — Consolidated Balance Sheets (audited), Ola 2
A2: USD millions, as of Dec 31. FY2024-FY2025 per FY2025 10-K (R5.htm); FY2021-FY2023 per companyfacts.json. See Sources_Audited for the held-for-sale presentation note and the FY21/22 non-current-asset reconciling residual.
A4: Line item | B4: FY2021A | C4: FY2022A | D4: FY2023A | E4: FY2024A | F4: FY2025A | H4: Source
A5: Current assets
A6: Cash and cash equivalents | B6: 9684 | C6: 9519 | D6: 9366 | E6: 10828 | F6: 10270 | H6: R5/us-gaap:CashAndCashEquivalentsAtCarryingValue
A7: Short-term investments | B7: 1242 | C7: 1043 | D7: 2997 | E7: 2020 | F7: 3602 | H7: us-gaap:OtherShortTermInvestments
A8: Marketable securities | B8: 1699 | C8: 1069 | D8: 1300 | E8: 1723 | F8: 1934 | H8: us-gaap:MarketableSecurities
A9: Trade accounts receivable, net | B9: 3512 | C9: 3487 | D9: 3410 | E9: 3569 | F9: 3038 | H9: us-gaap:AccountsReceivableNetCurrent
A10: Inventories | B10: 3414 | C10: 4233 | D10: 4424 | E10: 4728 | F10: 4425 | H10: us-gaap:InventoryNet
A11: Prepaid expenses and other current assets | B11: 2994 | C11: 3240 | D11: 5235 | E11: 2998 | F11: 2433 | H11: us-gaap:PrepaidExpenseAndOtherAssetsCurrent
A12: Assets held for sale (memo FY21-23; on-subtotal FY24-25) | B12: 674 | C12: 602 | D12: 2094 | E12: 131 | F12: 5342 | H12: us-gaap:AssetsOfDisposalGroupIncludingDiscontinuedOperation
A13: Total current assets (published) | B13: 22545 | C13: 22591 | D13: 26732 | E13: 25997 | F13: 31044 | H13: R5/us-gaap:AssetsCurrent
A14: Non-current assets
A15: Equity method investments | B15: 17598 | C15: 18264 | D15: 19671 | E15: 18087 | F15: 20235 | H15: us-gaap:EquityMethodInvestments
A16: Deferred income tax assets | B16: 2129 | C16: 1746 | D16: 1561 | E16: 1319 | F16: 1206 | H16: us-gaap:DeferredIncomeTaxAssetsNet
A17: Property, plant and equipment — net | B17: 9920 | C17: 9841 | D17: 9236 | E17: 10303 | F17: 9613 | H17: R5/us-gaap:PropertyPlantAndEquipmentNet
A18: Trademarks with indefinite lives | B18: 14465 | C18: 14214 | D18: 14349 | E18: 13301 | F18: 12531 | H18: us-gaap:IndefiniteLivedTrademarks
A19: Goodwill | B19: 19363 | C19: 18782 | D19: 18358 | E19: 18139 | F19: 15491 | H19: R5/us-gaap:Goodwill
A20: Other noncurrent assets | B20: 6731 | C20: 6189 | D20: 7796 | E20: 13403 | F20: 14696 | H20: us-gaap:OtherAssetsNoncurrent
A21: Unallocated non-current assets (reconciling residual — GAP, see Sources_Audited) | B21: 1603 | C21: 1136 | D21: 0 | E21: 0 | F21: 0 | H21: plug = Assets − TotalCA − sum(above NCA lines)
A22: Total non-current assets (published) | B22: 71809 | C22: 70172 | D22: 70971 | E22: 74552 | F22: 73772 | H22: Derived: Assets − Total current assets
A23: Total assets | B23: 94354 | C23: 92763 | D23: 97703 | E23: 100549 | F23: 104816 | H23: R5/us-gaap:Assets
A25: Current liabilities
A26: Accounts payable and accrued expenses | B26: 14619 | C26: 15749 | D26: 15485 | E26: 21712 | F26: 14813 | H26: us-gaap:AccountsPayableAndAccruedLiabilitiesCurrent
A27: Loans and notes payable | B27: 3307 | C27: 2373 | D27: 4557 | E27: 1499 | F27: 1551 | H27: us-gaap:ShortTermBorrowings (21) / NotesAndLoansPayable (22-25)
A28: Current maturities of long-term debt | B28: 1338 | C28: 399 | D28: 1960 | E28: 648 | F28: 1822 | H28: us-gaap:LongTermDebtCurrent (21-22) / LongTermDebtAndCapitalLeaseObligationsCurrent (23-25)
A29: Accrued income taxes | B29: 686 | C29: 1203 | D29: 1569 | E29: 1387 | F29: 525 | H29: us-gaap:AccruedIncomeTaxesCurrent
A30: Liabilities held for sale (memo FY21-23; on-subtotal FY24-25) | B30: 157 | C30: 160 | D30: 719 | E30: 3 | F30: 2570 | H30: us-gaap:LiabilitiesOfDisposalGroupIncludingDiscontinuedOperation
A31: Total current liabilities (published) | B31: 19950 | C31: 19724 | D31: 23571 | E31: 25249 | F31: 21281 | H31: R5/us-gaap:LiabilitiesCurrent
A32: Non-current liabilities
A33: Long-term debt | B33: 38116 | C33: 36377 | D33: 35547 | E33: 42375 | F33: 42119 | H33: us-gaap:LongTermDebtNoncurrent (21-23) / LongTermDebtAndCapitalLeaseObligations (24-25)
A34: Other noncurrent liabilities | B34: 8607 | C34: 7922 | D34: 8466 | E34: 4084 | F34: 4735 | H34: us-gaap:OtherLiabilitiesNoncurrent
A35: Deferred income tax liabilities | B35: 2821 | C35: 2914 | D35: 2639 | E35: 2469 | F35: 2406 | H35: us-gaap:DeferredIncomeTaxLiabilitiesNet
A36: Total non-current liabilities (published) | B36: 49544 | C36: 47213 | D36: 46652 | E36: 48928 | F36: 49260 | H36: Derived: Total liabilities − Total current liabilities
A37: Total liabilities | B37: 69494 | C37: 66937 | D37: 70223 | E37: 74177 | F37: 70541 | H37: Derived: LiabilitiesAndStockholdersEquity − StockholdersEquityIncl.NCI
A39: Shareowners' equity
A40: Common stock, $0.25 par value | B40: 1760 | C40: 1760 | D40: 1760 | E40: 1760 | F40: 1760 | H40: R5/us-gaap:CommonStockValue
A41: Capital surplus | B41: 18116 | C41: 18822 | D41: 19209 | E41: 19801 | F41: 20581 | H41: us-gaap:AdditionalPaidInCapitalCommonStock
A42: Reinvested earnings | B42: 69094 | C42: 71019 | D42: 73782 | E42: 76054 | F42: 80382 | H42: us-gaap:RetainedEarningsAccumulatedDeficit
A43: Accumulated other comprehensive income (loss) | B43: -14330 | C43: -14895 | D43: -14275 | E43: -16843 | F43: -14131 | H43: us-gaap:AccumulatedOtherComprehensiveIncomeLossNetOfTax
A44: Treasury stock, at cost | B44: -51641 | C44: -52601 | D44: -54535 | E44: -55916 | F44: -56423 | H44: us-gaap:TreasuryStockValue
A45: Equity attributable to shareowners of The Coca-Cola Company | B45: 22999 | C45: 24105 | D45: 25941 | E45: 24856 | F45: 32169 | H45: R5/us-gaap:StockholdersEquity
A46: Equity attributable to noncontrolling interests | B46: 1861 | C46: 1721 | D46: 1539 | E46: 1516 | F46: 2106 | H46: us-gaap:MinorityInterest
A47: Total equity | B47: 24860 | C47: 25826 | D47: 27480 | E47: 26372 | F47: 34275 | H47: us-gaap:StockholdersEquityIncludingPortionAttributableToNCI
A48: Total liabilities and equity | B48: 94354 | C48: 92763 | D48: 97703 | E48: 100549 | F48: 104816 | H48: R5/us-gaap:LiabilitiesAndStockholdersEquity

Sheet CF_Hist
A1: The Coca-Cola Company — Consolidated Statements of Cash Flows (audited), Ola 2
A2: USD millions. FY2023-FY2025 full line detail per FY2025 10-K (R7.htm); FY2021-FY2022 combines 3 custom-tagged (ko:) line items per section into one sized reconciling row (GAP in granularity only — subtotals are exact). See Sources_Audited.
A4: Line item | B4: FY2021A | C4: FY2022A | D4: FY2023A | E4: FY2024A | F4: FY2025A | H4: Source
A5: Operating activities
A6: Consolidated net income | B6: 9804 | C6: 9571 | D6: 10703 | E6: 10649 | F6: 13137 | H6: R7/us-gaap:ProfitLoss (=IS)
A7: Depreciation and amortization | B7: 1452 | C7: 1260 | D7: 1128 | E7: 1075 | F7: 1050 | H7: R7/us-gaap:DepreciationDepletionAndAmortization
A8: Stock-based compensation expense | B8: 337 | C8: 356 | D8: 254 | E8: 286 | F8: 279 | H8: R7/us-gaap:ShareBasedCompensation
A9: Deferred income taxes | B9: 894 | C9: -122 | D9: -2 | E9: -11 | F9: 517 | H9: R7/us-gaap:DeferredIncomeTaxExpenseBenefit
A10: Equity (income) loss — net of dividends | B10: -615 | C10: -838 | D10: -1019 | E10: -802 | F10: -1038 | H10: R7/us-gaap:IncomeLossFromEquityMethodInvestmentsNetOfDividendsOrDistributions (sign flipped)
A11: Foreign currency adjustments | C11: 203 | D11: 175 | E11: -110 | F11: 191 | H11: us-gaap:ForeignCurrencyTransactionGainLossBeforeTax (sign flipped; 21 n/a)
A12: Significant (gains) losses — net | D12: -492 | E12: -1737 | F12: -713 | H12: R7 (23-25 only; custom tag not in companyfacts pull for 21-22)
A13: Other operating charges | B13: 506 | C13: 1086 | D13: 1741 | E13: 4000 | F13: 1052 | H13: R7/us-gaap:OtherOperatingActivitiesCashFlowStatement
A14: Other items | D14: -43 | E14: -311 | F14: 141 | H14: R7 (23-25 only; custom tag not in companyfacts pull for 21-22)
A15: Net change in operating assets and liabilities | B15: 1325 | C15: -605 | D15: -846 | E15: -6234 | F15: -7208 | H15: us-gaap:IncreaseDecreaseInOperatingCapital (sign flipped)
A16: Significant gains/losses + other items, net (GAP reconciling — FY21-22 combined, see note) | B16: -1078 | C16: 107 | H16: plug = published CFO − sum(tagged lines above, incl. FX where available)
A17: Net cash provided by operating activities | B17: 12625 | C17: 11018 | D17: 11599 | E17: 6805 | F17: 7408 | H17: R7/us-gaap:NetCashProvidedByUsedInOperatingActivities
A19: Investing activities
A20: Purchases of investments | D20: -6698 | E20: -5640 | F20: -6160 | H20: R7 (23-25 only)
A21: Proceeds from disposals of investments | D21: 4354 | E21: 6589 | F21: 4665 | H21: R7 (23-25 only)
A22: Acquisitions of businesses, equity method investments and nonmarketable securities | D22: -62 | E22: -315 | F22: -461 | H22: R7 (23-25 only)
A23: Proceeds from disposals of businesses, equity method investments and nonmarketable securities | D23: 430 | E23: 3485 | F23: 3567 | H23: R7 (23-25 only)
A24: Purchases of property, plant and equipment | B24: -1367 | C24: -1484 | D24: -1852 | E24: -2064 | F24: -2112 | H24: R7/us-gaap:PaymentsToAcquirePropertyPlantAndEquipment
A25: Proceeds from disposals of property, plant and equipment | B25: 108 | C25: 75 | D25: 74 | E25: 40 | F25: 13 | H25: R7/us-gaap:ProceedsFromSaleOfPropertyPlantAndEquipment
A26: Collateral (paid) received associated with hedging activities — net | D26: 366 | E26: 235 | F26: 330 | H26: R7 (23-25 only)
A27: Other investing activities | D27: 39 | E27: 194 | F27: 91 | H27: R7 (23-25 only)
A28: Other investing activities, net (GAP reconciling — FY21-22 combined, see note) | B28: -1506 | C28: 646 | H28: plug = published CFI − sum(tagged lines above)
A29: Net cash provided by (used in) investing activities | B29: -2765 | C29: -763 | D29: -3349 | E29: 2524 | F29: -67 | H29: R7/us-gaap:NetCashProvidedByUsedInInvestingActivities
A31: Financing activities
A32: Issuances of loans, notes payable and long-term debt | D32: 6891 | E32: 12061 | F32: 4980 | H32: R7 (23-25 only)
A33: Payments of loans, notes payable and long-term debt | D33: -5034 | E33: -9533 | F33: -4967 | H33: R7 (23-25 only)
A34: Issuances of stock | B34: 702 | C34: 837 | D34: 539 | E34: 747 | F34: 313 | H34: R7/us-gaap:ProceedsFromIssuanceOfCommonStock
A35: Purchases of stock for treasury | B35: -111 | C35: -1418 | D35: -2289 | E35: -1795 | F35: -746 | H35: R7/us-gaap:PaymentsForRepurchaseOfCommonStock
A36: Dividends | B36: -7252 | C36: -7616 | D36: -7952 | E36: -8359 | F36: -8779 | H36: R7/us-gaap:PaymentsOfDividends
A37: Proceeds from noncontrolling interests | D37: 0 | E37: 0 | F37: 1338 | H37: R7/us-gaap:ProceedsFromMinorityShareholders
A38: Other financing activities | B38: -353 | C38: -1095 | D38: -465 | E38: -31 | F38: -279 | H38: R7/us-gaap:ProceedsFromPaymentsForOtherFinancingActivities
A39: Net debt issuances/(repayments), net (GAP reconciling — FY21-22 combined, see note) | B39: 228 | C39: -958 | H39: plug = published CFF − sum(tagged lines above)
A40: Net cash provided by (used in) financing activities | B40: -6786 | C40: -10250 | D40: -8310 | E40: -6910 | F40: -8140 | H40: R7/us-gaap:NetCashProvidedByUsedInFinancingActivities
A42: Cash and cash equivalents (incl. restricted cash)
A43: Effect of exchange rate changes on cash | B43: -159 | C43: -205 | D43: -73 | E43: -623 | F43: 321 | H43: R7/us-gaap:EffectOfExchangeRateOnCash...
A44: Net increase (decrease) in cash, cash equivalents, restricted cash and restricted cash equivalents | B44: 2915 | C44: -200 | D44: -133 | E44: 1796 | F44: -478 | H44: R7/us-gaap:CashCashEquivalentsRestrictedCash...PeriodIncreaseDecrease
A45: Cash, cash equivalents, restricted cash and restricted cash equivalents — beginning of year | B45: 7110 | C45: 10025 | D45: 9825 | E45: 9692 | F45: 11488 | H45: derived by chain from R7 begin/end (FY23-25 exact; FY21-22 backed out)
A46: Cash, cash equivalents, restricted cash and restricted cash equivalents — end of year | B46: 10025 | C46: 9825 | D46: 9692 | E46: 11488 | F46: 11010 | H46: R7 (23-25 exact) / chained (21-22)
A47: Restricted cash and restricted cash equivalents (memo; FY23-25 only) | D47: 326 | E47: 660 | F47: 740 | H47: R7/us-gaap:RestrictedCashAndCashEquivalents (memo)
A48: Cash and cash equivalents (BS figure) | B48: 9684 | C48: 9519 | D48: 9366 | E48: 10828 | F48: 10270 | H48: R5-BS/us-gaap:CashAndCashEquivalentsAtCarryingValue

Sheet Checks_TieOut
A1: Checks_TieOut — Ola 2 statement-grade tie-outs (all deltas must be 0; USD millions)
A2: MASTER | B2: =IF(COUNTIF(H5:H52,"FAIL")=0,"OK — ALL TIE-OUTS PASS","FAIL") -> FAIL
A3: Conteo mecanizado | B3: =COUNTIF(H5:H52,"PASS")&" PASS / "&(COUNTIF(H5:H52,"PASS")+COUNTIF(H5:H52,"FAIL"))&" checks" -> 46 PASS / 47 checks
A4: Check | B4: FY2021A | C4: FY2022A | D4: FY2023A | E4: FY2024A | F4: FY2025A | H4: Status
A5: IS: Gross profit = Revenue − COGS | B5: =IS_Hist!B5-IS_Hist!B6-IS_Hist!B7 -> 0 | C5: =IS_Hist!C5-IS_Hist!C6-IS_Hist!C7 -> 0 | D5: =IS_Hist!D5-IS_Hist!D6-IS_Hist!D7 -> 0 | E5: =IS_Hist!E5-IS_Hist!E6-IS_Hist!E7 -> 0 | F5: =IS_Hist!F5-IS_Hist!F6-IS_Hist!F7 -> 0 | H5: =IF(AND(ABS(N(B5))<=5,ABS(N(C5))<=5,ABS(N(D5))<=5,ABS(N(E5))<=5,ABS(N(F5))<=5),"PASS","FAIL") -> PASS
A6: IS: Operating income = GP − SG&A − Other opg charges | B6: =IS_Hist!B7-IS_Hist!B8-IS_Hist!B9-IS_Hist!B10 -> 0 | C6: =IS_Hist!C7-IS_Hist!C8-IS_Hist!C9-IS_Hist!C10 -> 0 | D6: =IS_Hist!D7-IS_Hist!D8-IS_Hist!D9-IS_Hist!D10 -> 0 | E6: =IS_Hist!E7-IS_Hist!E8-IS_Hist!E9-IS_Hist!E10 -> 0 | F6: =IS_Hist!F7-IS_Hist!F8-IS_Hist!F9-IS_Hist!F10 -> 0 | H6: =IF(AND(ABS(N(B6))<=5,ABS(N(C6))<=5,ABS(N(D6))<=5,ABS(N(E6))<=5,ABS(N(F6))<=5),"PASS","FAIL") -> PASS
A7: IS: Pretax income chain | B7: =IS_Hist!B10+IS_Hist!B11-IS_Hist!B12+IS_Hist!B13+IS_Hist!B14-IS_Hist!B15 -> 0 | C7: =IS_Hist!C10+IS_Hist!C11-IS_Hist!C12+IS_Hist!C13+IS_Hist!C14-IS_Hist!C15 -> 0 | D7: =IS_Hist!D10+IS_Hist!D11-IS_Hist!D12+IS_Hist!D13+IS_Hist!D14-IS_Hist!D15 -> 0 | E7: =IS_Hist!E10+IS_Hist!E11-IS_Hist!E12+IS_Hist!E13+IS_Hist!E14-IS_Hist!E15 -> 0 | F7: =IS_Hist!F10+IS_Hist!F11-IS_Hist!F12+IS_Hist!F13+IS_Hist!F14-IS_Hist!F15 -> 0 | H7: =IF(AND(ABS(N(B7))<=5,ABS(N(C7))<=5,ABS(N(D7))<=5,ABS(N(E7))<=5,ABS(N(F7))<=5),"PASS","FAIL") -> PASS
A8: IS: Consolidated NI = Pretax − tax | B8: =IS_Hist!B15-IS_Hist!B16-IS_Hist!B17 -> 0 | C8: =IS_Hist!C15-IS_Hist!C16-IS_Hist!C17 -> 0 | D8: =IS_Hist!D15-IS_Hist!D16-IS_Hist!D17 -> 0 | E8: =IS_Hist!E15-IS_Hist!E16-IS_Hist!E17 -> 0 | F8: =IS_Hist!F15-IS_Hist!F16-IS_Hist!F17 -> 0 | H8: =IF(AND(ABS(N(B8))<=5,ABS(N(C8))<=5,ABS(N(D8))<=5,ABS(N(E8))<=5,ABS(N(F8))<=5),"PASS","FAIL") -> PASS
A9: IS: NI attributable = Consolidated − NCI | B9: =IS_Hist!B17-IS_Hist!B18-IS_Hist!B19 -> 0 | C9: =IS_Hist!C17-IS_Hist!C18-IS_Hist!C19 -> 0 | D9: =IS_Hist!D17-IS_Hist!D18-IS_Hist!D19 -> 0 | E9: =IS_Hist!E17-IS_Hist!E18-IS_Hist!E19 -> 0 | F9: =IS_Hist!F17-IS_Hist!F18-IS_Hist!F19 -> 0 | H9: =IF(AND(ABS(N(B9))<=5,ABS(N(C9))<=5,ABS(N(D9))<=5,ABS(N(E9))<=5,ABS(N(F9))<=5),"PASS","FAIL") -> PASS
A10: BS: Total current assets (published, FY21-23 excl. AHFS) | B10: =SUM(BS_Hist!B6:B11)-BS_Hist!B13 -> 0 | C10: =SUM(BS_Hist!C6:C11)-BS_Hist!C13 -> 0 | D10: =SUM(BS_Hist!D6:D11)-BS_Hist!D13 -> 0 | E10: =SUM(BS_Hist!E6:E12)-BS_Hist!E13 -> 0 | F10: =SUM(BS_Hist!F6:F12)-BS_Hist!F13 -> 0 | H10: =IF(AND(ABS(N(B10))<=5,ABS(N(C10))<=5,ABS(N(D10))<=5,ABS(N(E10))<=5,ABS(N(F10))<=5),"PASS","FAIL") -> PASS
A11: BS: Total non-current assets (published) = TA − TCA | B11: =BS_Hist!B23-BS_Hist!B13-BS_Hist!B22 -> 0 | C11: =BS_Hist!C23-BS_Hist!C13-BS_Hist!C22 -> 0 | D11: =BS_Hist!D23-BS_Hist!D13-BS_Hist!D22 -> 0 | E11: =BS_Hist!E23-BS_Hist!E13-BS_Hist!E22 -> 0 | F11: =BS_Hist!F23-BS_Hist!F13-BS_Hist!F22 -> 0 | H11: =IF(AND(ABS(N(B11))<=5,ABS(N(C11))<=5,ABS(N(D11))<=5,ABS(N(E11))<=5,ABS(N(F11))<=5),"PASS","FAIL") -> PASS
A12: BS: Non-current asset detail sum = published NCA (incl. residual line) | B12: =SUM(BS_Hist!B15:B21)-BS_Hist!B22 -> 0 | C12: =SUM(BS_Hist!C15:C21)-BS_Hist!C22 -> 0 | D12: =SUM(BS_Hist!D15:D21)-BS_Hist!D22 -> 0 | E12: =SUM(BS_Hist!E15:E21)-BS_Hist!E22 -> 0 | F12: =SUM(BS_Hist!F15:F21)-BS_Hist!F22 -> 0 | H12: =IF(AND(ABS(N(B12))<=5,ABS(N(C12))<=5,ABS(N(D12))<=5,ABS(N(E12))<=5,ABS(N(F12))<=5),"PASS","FAIL") -> PASS
A13: BS: Total assets = TCA + TNCA | B13: =BS_Hist!B13+BS_Hist!B22-BS_Hist!B23 -> 0 | C13: =BS_Hist!C13+BS_Hist!C22-BS_Hist!C23 -> 0 | D13: =BS_Hist!D13+BS_Hist!D22-BS_Hist!D23 -> 0 | E13: =BS_Hist!E13+BS_Hist!E22-BS_Hist!E23 -> 0 | F13: =BS_Hist!F13+BS_Hist!F22-BS_Hist!F23 -> 0 | H13: =IF(AND(ABS(N(B13))<=5,ABS(N(C13))<=5,ABS(N(D13))<=5,ABS(N(E13))<=5,ABS(N(F13))<=5),"PASS","FAIL") -> PASS
A14: BS: Total current liabilities (published, FY21-23 excl. LHFS) | B14: =SUM(BS_Hist!B26:B29)-BS_Hist!B31 -> 0 | C14: =SUM(BS_Hist!C26:C29)-BS_Hist!C31 -> 0 | D14: =SUM(BS_Hist!D26:D29)-BS_Hist!D31 -> 0 | E14: =SUM(BS_Hist!E26:E30)-BS_Hist!E31 -> 0 | F14: =SUM(BS_Hist!F26:F30)-BS_Hist!F31 -> 0 | H14: =IF(AND(ABS(N(B14))<=5,ABS(N(C14))<=5,ABS(N(D14))<=5,ABS(N(E14))<=5,ABS(N(F14))<=5),"PASS","FAIL") -> PASS
A15: BS: Non-current liabilities sum = published NCL | B15: =SUM(BS_Hist!B33:B35)-BS_Hist!B36 -> 0 | C15: =SUM(BS_Hist!C33:C35)-BS_Hist!C36 -> 0 | D15: =SUM(BS_Hist!D33:D35)-BS_Hist!D36 -> 0 | E15: =SUM(BS_Hist!E33:E35)-BS_Hist!E36 -> 0 | F15: =SUM(BS_Hist!F33:F35)-BS_Hist!F36 -> 0 | H15: =IF(AND(ABS(N(B15))<=5,ABS(N(C15))<=5,ABS(N(D15))<=5,ABS(N(E15))<=5,ABS(N(F15))<=5),"PASS","FAIL") -> PASS
A16: BS: Total liabilities = TCL + TNCL | B16: =BS_Hist!B31+BS_Hist!B36-BS_Hist!B37 -> 0 | C16: =BS_Hist!C31+BS_Hist!C36-BS_Hist!C37 -> 0 | D16: =BS_Hist!D31+BS_Hist!D36-BS_Hist!D37 -> 0 | E16: =BS_Hist!E31+BS_Hist!E36-BS_Hist!E37 -> 0 | F16: =BS_Hist!F31+BS_Hist!F36-BS_Hist!F37 -> 0 | H16: =IF(AND(ABS(N(B16))<=5,ABS(N(C16))<=5,ABS(N(D16))<=5,ABS(N(E16))<=5,ABS(N(F16))<=5),"PASS","FAIL") -> PASS
A17: BS: Parent equity sum = published | B17: =SUM(BS_Hist!B40:B44)-BS_Hist!B45 -> 0 | C17: =SUM(BS_Hist!C40:C44)-BS_Hist!C45 -> 0 | D17: =SUM(BS_Hist!D40:D44)-BS_Hist!D45 -> 0 | E17: =SUM(BS_Hist!E40:E44)-BS_Hist!E45 -> 0 | F17: =SUM(BS_Hist!F40:F44)-BS_Hist!F45 -> 0 | H17: =IF(AND(ABS(N(B17))<=5,ABS(N(C17))<=5,ABS(N(D17))<=5,ABS(N(E17))<=5,ABS(N(F17))<=5),"PASS","FAIL") -> PASS
A18: BS: Total equity = parent + NCI | B18: =BS_Hist!B45+BS_Hist!B46-BS_Hist!B47 -> 0 | C18: =BS_Hist!C45+BS_Hist!C46-BS_Hist!C47 -> 0 | D18: =BS_Hist!D45+BS_Hist!D46-BS_Hist!D47 -> 0 | E18: =BS_Hist!E45+BS_Hist!E46-BS_Hist!E47 -> 0 | F18: =BS_Hist!F45+BS_Hist!F46-BS_Hist!F47 -> 0 | H18: =IF(AND(ABS(N(B18))<=5,ABS(N(C18))<=5,ABS(N(D18))<=5,ABS(N(E18))<=5,ABS(N(F18))<=5),"PASS","FAIL") -> PASS
A19: BS: TL&E = TL + TE | B19: =BS_Hist!B37+BS_Hist!B47-BS_Hist!B48 -> 0 | C19: =BS_Hist!C37+BS_Hist!C47-BS_Hist!C48 -> 0 | D19: =BS_Hist!D37+BS_Hist!D47-BS_Hist!D48 -> 0 | E19: =BS_Hist!E37+BS_Hist!E47-BS_Hist!E48 -> 0 | F19: =BS_Hist!F37+BS_Hist!F47-BS_Hist!F48 -> 0 | H19: =IF(AND(ABS(N(B19))<=5,ABS(N(C19))<=5,ABS(N(D19))<=5,ABS(N(E19))<=5,ABS(N(F19))<=5),"PASS","FAIL") -> PASS
A20: BS: Balance (TA − TL&E) | B20: =BS_Hist!B23-BS_Hist!B48 -> 0 | C20: =BS_Hist!C23-BS_Hist!C48 -> 0 | D20: =BS_Hist!D23-BS_Hist!D48 -> 0 | E20: =BS_Hist!E23-BS_Hist!E48 -> 0 | F20: =BS_Hist!F23-BS_Hist!F48 -> 0 | H20: =IF(AND(ABS(N(B20))<=5,ABS(N(C20))<=5,ABS(N(D20))<=5,ABS(N(E20))<=5,ABS(N(F20))<=5),"PASS","FAIL") -> PASS
A21: X: RE rollforward = RE(t-1) + NI attrib − dividends paid (±$5mm decl-vs-paid timing) | B21: =0 -> 0 | C21: =BS_Hist!B42+IS_Hist!C19+CF_Hist!C36-BS_Hist!C42 -> 1 | D21: =BS_Hist!C42+IS_Hist!D19+CF_Hist!D36-BS_Hist!D42 -> -1 | E21: =BS_Hist!D42+IS_Hist!E19+CF_Hist!E36-BS_Hist!E42 -> 0 | F21: =BS_Hist!E42+IS_Hist!F19+CF_Hist!F36-BS_Hist!F42 -> 0 | H21: =IF(AND(ABS(N(B21))<=5,ABS(N(C21))<=5,ABS(N(D21))<=5,ABS(N(E21))<=5,ABS(N(F21))<=5),"PASS","FAIL") -> PASS
A22: CF: Net cash from operations chain (sum of section) | B22: =SUM(CF_Hist!B6:B16)-CF_Hist!B17 -> 0 | C22: =SUM(CF_Hist!C6:C16)-CF_Hist!C17 -> 0 | D22: =SUM(CF_Hist!D6:D16)-CF_Hist!D17 -> 0 | E22: =SUM(CF_Hist!E6:E16)-CF_Hist!E17 -> 0 | F22: =SUM(CF_Hist!F6:F16)-CF_Hist!F17 -> 0 | H22: =IF(AND(ABS(N(B22))<=5,ABS(N(C22))<=5,ABS(N(D22))<=5,ABS(N(E22))<=5,ABS(N(F22))<=5),"PASS","FAIL") -> PASS
A23: CF: Net cash from investing chain (sum of section) | B23: =SUM(CF_Hist!B20:B28)-CF_Hist!B29 -> 0 | C23: =SUM(CF_Hist!C20:C28)-CF_Hist!C29 -> 0 | D23: =SUM(CF_Hist!D20:D28)-CF_Hist!D29 -> 0 | E23: =SUM(CF_Hist!E20:E28)-CF_Hist!E29 -> 0 | F23: =SUM(CF_Hist!F20:F28)-CF_Hist!F29 -> 0 | H23: =IF(AND(ABS(N(B23))<=5,ABS(N(C23))<=5,ABS(N(D23))<=5,ABS(N(E23))<=5,ABS(N(F23))<=5),"PASS","FAIL") -> PASS
A24: CF: Net cash from financing chain (sum of section) | B24: =SUM(CF_Hist!B32:B39)-CF_Hist!B40 -> 0 | C24: =SUM(CF_Hist!C32:C39)-CF_Hist!C40 -> 0 | D24: =SUM(CF_Hist!D32:D39)-CF_Hist!D40 -> 0 | E24: =SUM(CF_Hist!E32:E39)-CF_Hist!E40 -> 0 | F24: =SUM(CF_Hist!F32:F39)-CF_Hist!F40 -> 0 | H24: =IF(AND(ABS(N(B24))<=5,ABS(N(C24))<=5,ABS(N(D24))<=5,ABS(N(E24))<=5,ABS(N(F24))<=5),"PASS","FAIL") -> PASS
A25: CF: Net change (incl. restricted) = CFO+CFI+CFF+FX | B25: =CF_Hist!B17+CF_Hist!B29+CF_Hist!B40+CF_Hist!B43-CF_Hist!B44 -> 0 | C25: =CF_Hist!C17+CF_Hist!C29+CF_Hist!C40+CF_Hist!C43-CF_Hist!C44 -> 0 | D25: =CF_Hist!D17+CF_Hist!D29+CF_Hist!D40+CF_Hist!D43-CF_Hist!D44 -> 0 | E25: =CF_Hist!E17+CF_Hist!E29+CF_Hist!E40+CF_Hist!E43-CF_Hist!E44 -> 0 | F25: =CF_Hist!F17+CF_Hist!F29+CF_Hist!F40+CF_Hist!F43-CF_Hist!F44 -> 0 | H25: =IF(AND(ABS(N(B25))<=5,ABS(N(C25))<=5,ABS(N(D25))<=5,ABS(N(E25))<=5,ABS(N(F25))<=5),"PASS","FAIL") -> PASS
A26: CF: End cash(incl.restr.) = Begin + net change | B26: =CF_Hist!B45+CF_Hist!B44-CF_Hist!B46 -> 0 | C26: =CF_Hist!C45+CF_Hist!C44-CF_Hist!C46 -> 0 | D26: =CF_Hist!D45+CF_Hist!D44-CF_Hist!D46 -> 0 | E26: =CF_Hist!E45+CF_Hist!E44-CF_Hist!E46 -> 0 | F26: =CF_Hist!F45+CF_Hist!F44-CF_Hist!F46 -> 0 | H26: =IF(AND(ABS(N(B26))<=5,ABS(N(C26))<=5,ABS(N(D26))<=5,ABS(N(E26))<=5,ABS(N(F26))<=5),"PASS","FAIL") -> PASS
A27: CF: Beginning cash continuity (t begin = t-1 end), FY22-25 | B27: =0 -> 0 | C27: =CF_Hist!C45-CF_Hist!B46 -> 0 | D27: =CF_Hist!D45-CF_Hist!C46 -> 0 | E27: =CF_Hist!E45-CF_Hist!D46 -> 0 | F27: =CF_Hist!F45-CF_Hist!E46 -> 0 | H27: =IF(AND(ABS(N(B27))<=5,ABS(N(C27))<=5,ABS(N(D27))<=5,ABS(N(E27))<=5,ABS(N(F27))<=5),"PASS","FAIL") -> PASS
A28: X: CF Consolidated NI = IS Consolidated NI | B28: =CF_Hist!B6-IS_Hist!B17 -> 0 | C28: =CF_Hist!C6-IS_Hist!C17 -> 0 | D28: =CF_Hist!D6-IS_Hist!D17 -> 0 | E28: =CF_Hist!E6-IS_Hist!E17 -> 0 | F28: =CF_Hist!F6-IS_Hist!F17 -> 0 | H28: =IF(AND(ABS(N(B28))<=5,ABS(N(C28))<=5,ABS(N(D28))<=5,ABS(N(E28))<=5,ABS(N(F28))<=5),"PASS","FAIL") -> PASS
A29: X: BS cash = CF Hist BS-figure cash (all 5 yrs, direct tag match) | B29: =BS_Hist!B6-CF_Hist!B48 -> 0 | C29: =BS_Hist!C6-CF_Hist!C48 -> 0 | D29: =BS_Hist!D6-CF_Hist!D48 -> 0 | E29: =BS_Hist!E6-CF_Hist!E48 -> 0 | F29: =BS_Hist!F6-CF_Hist!F48 -> 0 | H29: =IF(AND(ABS(N(B29))<=5,ABS(N(C29))<=5,ABS(N(D29))<=5,ABS(N(E29))<=5,ABS(N(F29))<=5),"PASS","FAIL") -> PASS
A30: X: FY23-25 end cash(incl.restr.) = BS cash + memo restricted | B30: =0 -> 0 | C30: =0 -> 0 | D30: =CF_Hist!D46-CF_Hist!D48-CF_Hist!D47 -> 0 | E30: =CF_Hist!E46-CF_Hist!E48-CF_Hist!E47 -> 0 | F30: =CF_Hist!F46-CF_Hist!F48-CF_Hist!F47 -> 0 | H30: =IF(AND(ABS(N(B30))<=5,ABS(N(C30))<=5,ABS(N(D30))<=5,ABS(N(E30))<=5,ABS(N(F30))<=5),"PASS","FAIL") -> PASS
A31: COBERTURA — drivers de negocio (Drivers_MDA) y paquete de mercado (Market_Package), agregados 2026-08-14. Plantilla del piloto Apple con los checks endurecidos post-refutación: cada check compara contra celdas INDEPENDIENTES (otra hoja, otro documento u otro vintage), nunca contra su propia definición.
A32: DRV: Ventas netas a terceros por segmento suman a IS_Hist ventas netas (FY21-22 presentación original con Global Ventures; FY23-25 re-presentada) | B32: =Drivers_MDA!B34 -> 0 | C32: =Drivers_MDA!C34 -> 0 | D32: =Drivers_MDA!D34 -> 0 | E32: =Drivers_MDA!E34 -> 0 | F32: =Drivers_MDA!F34 -> 0 | H32: =IF(AND(ABS(N(B32))<=0.5,ABS(N(C32))<=0.5,ABS(N(D32))<=0.5,ABS(N(E32))<=0.5,ABS(N(F32))<=0.5),"PASS","FAIL") -> PASS
A33: DRV: Utilidad operativa por segmento + Corporate = IS_Hist utilidad operativa (conciliación del emisor reproducida) | B33: =Drivers_MDA!B52 -> 0 | C33: =Drivers_MDA!C52 -> 0 | D33: =Drivers_MDA!D52 -> 0 | E33: =Drivers_MDA!E52 -> 0 | F33: =Drivers_MDA!F52 -> 0 | H33: =IF(AND(ABS(N(B33))<=0.5,ABS(N(C33))<=0.5,ABS(N(D33))<=0.5,ABS(N(E33))<=0.5,ABS(N(F33))<=0.5),"PASS","FAIL") -> PASS
A34: DRV: COGS por segmento (FY23-25, incl. Corporate y eliminaciones) = IS_Hist costo de ventas | D34: =Drivers_MDA!D70 -> 0 | E34: =Drivers_MDA!E70 -> 0 | F34: =Drivers_MDA!F70 -> 0 | H34: =IF(AND(ABS(N(D34))<=0.5,ABS(N(E34))<=0.5,ABS(N(F34))<=0.5),"PASS","FAIL") -> PASS
A35: DRV: bridge de ingresos del MD&A — la suma de componentes coincide con el total reportado (±1.5pp de redondeo a 1%) Y el total reportado coincide con el crecimiento real de IS_Hist (±1.5pp). FY2021 solo el primer término (FY2020 fuera de ventana). F es conteo de incumplimientos | B35: =IF(ABS(Drivers_MDA!B21-Drivers_MDA!B20)>0.015,1,0) -> 0 | C35: =IF(ABS(Drivers_MDA!C21-Drivers_MDA!C20)>0.015,1,0)+IF(ABS(Drivers_MDA!C20-Drivers_MDA!C22)>0.015,1,0) -> 0 | D35: =IF(ABS(Drivers_MDA!D21-Drivers_MDA!D20)>0.015,1,0)+IF(ABS(Drivers_MDA!D20-Drivers_MDA!D22)>0.015,1,0) -> 0 | E35: =IF(ABS(Drivers_MDA!E21-Drivers_MDA!E20)>0.015,1,0)+IF(ABS(Drivers_MDA!E20-Drivers_MDA!E22)>0.015,1,0) -> 0 | F35: =IF(ABS(Drivers_MDA!F21-Drivers_MDA!F20)>0.015,1,0)+IF(ABS(Drivers_MDA!F20-Drivers_MDA!F22)>0.015,1,0) -> 0 | H35: =IF(AND(N(B35)=0,N(C35)=0,N(D35)=0,N(E35)=0,N(F35)=0),"PASS","FAIL") -> PASS
A36: XREF: Sector_KPIs (bridge FY2025 C7:C11, unit cases B5:C5 y ancla de ingresos B6:C6) = Drivers_MDA / IS_Hist — constantes preexistentes de otra hoja contra la serie del filing | F36: =Drivers_MDA!F168+Drivers_MDA!F169+Drivers_MDA!F170 -> 0 | H36: =IF(AND(ABS(N(F36))<=0.0000001),"PASS","FAIL") -> PASS
A37: FCST: anclas del motor — Forecast!B5:B9 = bridge FY2025 reportado del MD&A y Forecast!B10 = IS_Hist!F5 (suma de |deltas| de Drivers_MDA!F162:F167) | F37: =ABS(Drivers_MDA!F162)+ABS(Drivers_MDA!F163)+ABS(Drivers_MDA!F164)+ABS(Drivers_MDA!F165)+ABS(Drivers_MDA!F166)+ABS(Drivers_MDA!F167) -> 0 | H37: =IF(AND(ABS(N(F37))<=0.0000001),"PASS","FAIL") -> PASS
A38: DRV: splits concentrado/producto terminado — el split de volumen suma 100% cada año, el % de ingresos REPORTADO coincide con el calculado desde la Nota 3 (±0.5pp de redondeo) y el % de concentrado queda en banda [40%,70%]. F es conteo de incumplimientos | B38: =IF(ABS(Drivers_MDA!B12-1)>0.0000001,1,0)+IF(ABS(Drivers_MDA!B79)>0.005,1,0)+IF(OR(Drivers_MDA!B77<0.4,Drivers_MDA!B77>0.7),1,0) -> 0 | C38: =IF(ABS(Drivers_MDA!C12-1)>0.0000001,1,0)+IF(ABS(Drivers_MDA!C79)>0.005,1,0)+IF(OR(Drivers_MDA!C77<0.4,Drivers_MDA!C77>0.7),1,0) -> 0 | D38: =IF(ABS(Drivers_MDA!D12-1)>0.0000001,1,0)+IF(ABS(Drivers_MDA!D79)>0.005,1,0)+IF(OR(Drivers_MDA!D77<0.4,Drivers_MDA!D77>0.7),1,0) -> 0 | E38: =IF(ABS(Drivers_MDA!E12-1)>0.0000001,1,0)+IF(ABS(Drivers_MDA!E79)>0.005,1,0)+IF(OR(Drivers_MDA!E77<0.4,Drivers_MDA!E77>0.7),1,0) -> 0 | F38: =IF(ABS(Drivers_MDA!F12-1)>0.0000001,1,0)+IF(ABS(Drivers_MDA!F79)>0.005,1,0)+IF(OR(Drivers_MDA!F77<0.4,Drivers_MDA!F77>0.7),1,0) -> 0 | H38: =IF(AND(N(B38)=0,N(C38)=0,N(D38)=0,N(E38)=0,N(F38)=0),"PASS","FAIL") -> PASS
A39: DRV: Nota 3 en dólares — concentrado + producto terminado = IS_Hist ventas netas Y EE.UU. + Internacional = IS_Hist ventas netas (dos particiones independientes del mismo total). F es conteo de incumplimientos | B39: =IF(ABS(Drivers_MDA!B76)>0.5,1,0)+IF(ABS(Drivers_MDA!B82)>0.5,1,0) -> 0 | C39: =IF(ABS(Drivers_MDA!C76)>0.5,1,0)+IF(ABS(Drivers_MDA!C82)>0.5,1,0) -> 0 | D39: =IF(ABS(Drivers_MDA!D76)>0.5,1,0)+IF(ABS(Drivers_MDA!D82)>0.5,1,0) -> 0 | E39: =IF(ABS(Drivers_MDA!E76)>0.5,1,0)+IF(ABS(Drivers_MDA!E82)>0.5,1,0) -> 0 | F39: =IF(ABS(Drivers_MDA!F76)>0.5,1,0)+IF(ABS(Drivers_MDA!F82)>0.5,1,0) -> 0 | H39: =IF(AND(N(B39)=0,N(C39)=0,N(D39)=0,N(E39)=0,N(F39)=0),"PASS","FAIL") -> PASS
A40: DRV: FX y commodities — Item 7A vs Nota 3 Internacional (±50 por redondeo a 0.1bn) todos los años; y en FY2025 la composición de la Nota 16 = notional total del Item 7A (FX y commodities, dos secciones independientes del filing). F es conteo de incumplimientos | B40: =IF(ABS(Drivers_MDA!B88)>50,1,0) -> 0 | C40: =IF(ABS(Drivers_MDA!C88)>50,1,0) -> 0 | D40: =IF(ABS(Drivers_MDA!D88)>50,1,0) -> 0 | E40: =IF(ABS(Drivers_MDA!E88)>50,1,0) -> 0 | F40: =IF(ABS(Drivers_MDA!F88)>50,1,0)+IF(ABS(Drivers_MDA!F97)>0.5,1,0)+IF(ABS(Drivers_MDA!F108)>0.5,1,0) -> 0 | H40: =IF(AND(N(B40)=0,N(C40)=0,N(D40)=0,N(E40)=0,N(F40)=0),"PASS","FAIL") -> PASS
A41: DRV: detalle de working capital de la Nota 21 (seis líneas, FY23-25) suma exactamente al cambio neto en activos y pasivos operativos de CF_Hist | D41: =Drivers_MDA!D130 -> 0 | E41: =Drivers_MDA!E130 -> 0 | F41: =Drivers_MDA!F130 -> 0 | H41: =IF(AND(ABS(N(D41))<=0.5,ABS(N(E41))<=0.5,ABS(N(F41))<=0.5),"PASS","FAIL") -> PASS
A42: DRV: dividendos — DPS declarado × acciones diluidas promedio (IS_Hist) dentro de ±2% de los dividendos pagados del CF (timing declarado-vs-pagado; deriva real 0.2%-0.6%). F es conteo de incumplimientos | B42: =IF(ABS(Drivers_MDA!B139)>0.02,1,0) -> 0 | C42: =IF(ABS(Drivers_MDA!C139)>0.02,1,0) -> 0 | D42: =IF(ABS(Drivers_MDA!D139)>0.02,1,0) -> 0 | E42: =IF(ABS(Drivers_MDA!E139)>0.02,1,0) -> 0 | F42: =IF(ABS(Drivers_MDA!F139)>0.02,1,0) -> 0 | H42: =IF(AND(N(B42)=0,N(C42)=0,N(D42)=0,N(E42)=0,N(F42)=0),"PASS","FAIL") -> PASS
A43: DRV: ventas internacionales (Nota 3) en banda [50%,70%] de las ventas totales (serie real: 60%-66%). F es conteo de incumplimientos | B43: =IF(OR(Drivers_MDA!B83<0.5,Drivers_MDA!B83>0.7),1,0) -> 0 | C43: =IF(OR(Drivers_MDA!C83<0.5,Drivers_MDA!C83>0.7),1,0) -> 0 | D43: =IF(OR(Drivers_MDA!D83<0.5,Drivers_MDA!D83>0.7),1,0) -> 0 | E43: =IF(OR(Drivers_MDA!E83<0.5,Drivers_MDA!E83>0.7),1,0) -> 0 | F43: =IF(OR(Drivers_MDA!F83<0.5,Drivers_MDA!F83>0.7),1,0) -> 0 | H43: =IF(AND(N(B43)=0,N(C43)=0,N(D43)=0,N(E43)=0,N(F43)=0),"PASS","FAIL") -> PASS
A44: DRV: BANDAS DE PLAUSIBILIDAD (NO es tie) para constantes sin tie mecanizado — empleados [30k,150k], unit cases [25,40]bn, ingreso por caja [1.0,2.0] USD, notional FX/ventas [10%,100%], notional commodities/COGS [0.5%,15%]. Caza un valor absurdo; una cifra plausible y equivocada pasa igual — limitación declarada en Drivers_MDA!A175 | B44: =IF(OR(Drivers_MDA!B133<30000,Drivers_MDA!B133>150000),1,0)+IF(OR(Drivers_MDA!B7<25,Drivers_MDA!B7>40),1,0)+IF(OR(Drivers_MDA!B9<1,Drivers_MDA!B9>2),1,0)+IF(OR(Drivers_MDA!B90<0.1,Drivers_MDA!B90>1),1,0)+IF(OR(Drivers_MDA!B105<0.005,Drivers_MDA!B105>0.15),1,0) -> 0 | C44: =IF(OR(Drivers_MDA!C133<30000,Drivers_MDA!C133>150000),1,0)+IF(OR(Drivers_MDA!C7<25,Drivers_MDA!C7>40),1,0)+IF(OR(Drivers_MDA!C9<1,Drivers_MDA!C9>2),1,0)+IF(OR(Drivers_MDA!C90<0.1,Drivers_MDA!C90>1),1,0)+IF(OR(Drivers_MDA!C105<0.005,Drivers_MDA!C105>0.15),1,0) -> 0 | D44: =IF(OR(Drivers_MDA!D133<30000,Drivers_MDA!D133>150000),1,0)+IF(OR(Drivers_MDA!D7<25,Drivers_MDA!D7>40),1,0)+IF(OR(Drivers_MDA!D9<1,Drivers_MDA!D9>2),1,0)+IF(OR(Drivers_MDA!D90<0.1,Drivers_MDA!D90>1),1,0)+IF(OR(Drivers_MDA!D105<0.005,Drivers_MDA!D105>0.15),1,0) -> 0 | E44: =IF(OR(Drivers_MDA!E133<30000,Drivers_MDA!E133>150000),1,0)+IF(OR(Drivers_MDA!E7<25,Drivers_MDA!E7>40),1,0)+IF(OR(Drivers_MDA!E9<1,Drivers_MDA!E9>2),1,0)+IF(OR(Drivers_MDA!E90<0.1,Drivers_MDA!E90>1),1,0)+IF(OR(Drivers_MDA!E105<0.005,Drivers_MDA!E105>0.15),1,0) -> 0 | F44: =IF(OR(Drivers_MDA!F133<30000,Drivers_MDA!F133>150000),1,0)+IF(OR(Drivers_MDA!F7<25,Drivers_MDA!F7>40),1,0)+IF(OR(Drivers_MDA!F9<1,Drivers_MDA!F9>2),1,0)+IF(OR(Drivers_MDA!F90<0.1,Drivers_MDA!F90>1),1,0)+IF(OR(Drivers_MDA!F105<0.005,Drivers_MDA!F105>0.15),1,0) -> 0 | H44: =IF(AND(N(B44)=0,N(C44)=0,N(D44)=0,N(E44)=0,N(F44)=0),"PASS","FAIL") -> PASS
A45: MKT: enterprise value contra ancla de vintage DISTINTO — B23 = precio × acciones + deuda − caja de la columna comparativa del 10-Q Q2 FY2026 (Market_Package!B107 y B106, constantes del filing, independientes de BS_Hist); EV > 0; y dentro de ±25% del EV construido con el precio fechado independiente de Valuation!G19 (deriva real +5.6%). F es conteo de incumplimientos | F45: =IF(ABS(Market_Package!B23-(Market_Package!B7*Market_Package!B8+Market_Package!B107-Market_Package!B106))>0.5,1,0)+IF(Market_Package!B23<=0,1,0)+IF(ABS(Market_Package!B23/(Valuation!G19*Market_Package!B8+Market_Package!B107-Market_Package!B106)-1)>0.25,1,0) -> 0 | H45: =IF(N(F45)=0,"PASS","FAIL") -> PASS
A46: MKT: efectivo e inversiones del paquete (B17, balance FY2025A) — tie EXACTO contra el ancla de vintage distinto (B106, caja al 2025-12-31 según el 10-Q Q2 FY2026) y banda ±15% contra la posición al 2026-07-03 (B82; deriva real −3.5%). F es conteo de incumplimientos | F46: =IF(ABS(Market_Package!B17-Market_Package!B106)>0.5,1,0)+IF(ABS(Market_Package!B17/Market_Package!B82-1)>0.15,1,0) -> 0 | H46: =IF(N(F46)=0,"PASS","FAIL") -> PASS
A47: MKT: deuda bruta del paquete (B21) — (1) la brecha contra la deuda del DCF es EXACTAMENTE los loans/notes payable del balance menos los 56 ya incluidos (mecaniza el hallazgo H1: B21−B24 = BS_Hist!F27−Historical!B25; equivale a exigir BS_Hist!F28+F33 = tag combinado de Historical); (2) tie EXACTO contra el ancla de vintage distinto (B107); (3) banda ±25% contra la deuda al 2026-07-03 (B83; deriva real +4.5%). F es conteo de incumplimientos | F47: =IF(ABS(Market_Package!B21-Market_Package!B24-(BS_Hist!F27-Historical!B25))>0.5,1,0)+IF(ABS(Market_Package!B21-Market_Package!B107)>0.5,1,0)+IF(ABS(Market_Package!B21/Market_Package!B83-1)>0.25,1,0) -> 0 | H47: =IF(N(F47)=0,"PASS","FAIL") -> PASS
A48: MKT: activos líquidos — la brecha del paquete vs los del DCF es EXACTAMENTE las inversiones de corto plazo + valores negociables (mecaniza el hallazgo H2: B17−B26 = BS_Hist!F7+F8; equivale a exigir BS_Hist!F6 = caja de Historical, dos constantes de builds distintos). F es conteo de incumplimientos | F48: =IF(ABS(Market_Package!B17-Market_Package!B26-(BS_Hist!F7+BS_Hist!F8))>0.5,1,0) -> 0 | H48: =IF(N(F48)=0,"PASS","FAIL") -> PASS
A49: MKT: costo de capital — guardia del enlace vivo de la tasa efectiva (B37 debe ser exactamente IS_Hist!F16/IS_Hist!F15: una tasa tecleada en duro cae) + BANDAS DE PLAUSIBILIDAD para Rf [0.5%,12%], beta [0.1x,1.5x], Kd [1%,15%] y WACC [3%,20%]. Una cifra plausible y equivocada dentro de banda pasa igual — limitación declarada. F es conteo de incumplimientos | F49: =IF(ABS(Market_Package!B37-IS_Hist!F16/IS_Hist!F15)>0.0000001,1,0)+IF(OR(Market_Package!B30<0.005,Market_Package!B30>0.12),1,0)+IF(OR(Market_Package!B32<0.1,Market_Package!B32>1.5),1,0)+IF(OR(Market_Package!B34<0.01,Market_Package!B34>0.15),1,0)+IF(OR(Market_Package!B45<0.03,Market_Package!B45>0.2),1,0) -> 0 | H49: =IF(N(F49)=0,"PASS","FAIL") -> PASS
A50: MKT: precio, acciones y capitalización — cableado (B11 = B7 × B8), precio dentro de ±25% del precio fechado independiente de Valuation!G19 (deriva real +6.0%), y acciones dentro de ±3% del conteo del DCF (Historical!B20; deriva real +0.04%). Un error de precio DENTRO de la banda es indetectable sin feed vivo — limitación declarada. F es conteo de incumplimientos | F50: =IF(ABS(Market_Package!B11-Market_Package!B7*Market_Package!B8)>0.5,1,0)+IF(ABS(Market_Package!B7/Valuation!G19-1)>0.25,1,0)+IF(ABS(Market_Package!B8/Historical!B20-1)>0.03,1,0) -> 0 | H50: =IF(N(F50)=0,"PASS","FAIL") -> PASS
A51: MKT: procedencia de los inputs de mercado — fuente presente, fecha con serial válido, desfase relativo ≤5 días entre inputs de cotización diaria (precio, Rf, beta, Kd), y frescura ABSOLUTA: si la observación más reciente es anterior a HOY()−10 al recalcular, cae en FAIL. 0 significa completo | F51: =Market_Package!B89+Market_Package!B90+Market_Package!B92 -> 1 | H51: =IF(AND(ABS(N(F51))<=0),"PASS","FAIL") -> FAIL
A52: DRV: dual-vintage FY2023 — la presentación ORIGINAL del 10-K FY2023 (memo con Global Ventures, constantes independientes) suma al mismo total consolidado de IS_Hist FY2023 | D52: =Drivers_MDA!D158 -> 0 | H52: =IF(AND(ABS(N(D52))<=0.5),"PASS","FAIL") -> PASS

Sheet Sources_Audited
A1: Sources_Audited — Ola 2 citation register (EDGAR: CIK 0000021344, The Coca-Cola Company)
A3: Block | B3: Years | C3: Primary source | D3: Locator | E3: Notes / gaps
A4: IS_Hist | B4: FY2023-FY2025 | C4: 10-K filed 2026-02-20, accession 0001628280-26-010047 | D4: R3.htm ("CONSOLIDATED STATEMENTS OF INCOME") | E4: Exact published $mm values; validated bit-for-bit against companyfacts.json us-gaap tags for the same years.
A5: IS_Hist | B5: FY2021-FY2022 | C5: SEC companyfacts API (frames aggregated from FY2021/FY2022/FY2023 10-Ks) | D5: companyfacts.json — us-gaap:Revenues, CostOfGoodsAndServicesSold, GrossProfit, SellingGeneralAndAdministrativeExpense, OtherCostAndExpenseOperating, OperatingIncomeLoss, InvestmentIncomeInterest, InterestExpense, IncomeLossFromEquityMethodInvestments, OtherNonoperatingIncomeExpense, IncomeLossFromContinuingOperationsBeforeIncomeTaxes..., IncomeTaxExpenseBenefit, ProfitLoss, NetIncomeLossAttributableToNoncontrollingInterest, NetIncomeLoss, EarningsPerShareBasic/Diluted (USD/shares unit), WeightedAverageNumberOfSharesOutstandingBasic/Diluted | E5: No gaps — every IS line has a direct tag for both years; all internal tie-outs (Gross profit, Operating income, Pretax, NI chains) PASS exactly.
A6: BS_Hist | B6: FY2024-FY2025 | C6: 10-K filed 2026-02-20, accession 0001628280-26-010047 | D6: R5.htm ("CONSOLIDATED BALANCE SHEETS") | E6: Exact; ties in full with no residual.
A7: BS_Hist | B7: FY2021-FY2023 | C7: SEC companyfacts API | D7: companyfacts.json — us-gaap:CashAndCashEquivalentsAtCarryingValue, OtherShortTermInvestments, MarketableSecurities, AccountsReceivableNetCurrent, InventoryNet, PrepaidExpenseAndOtherAssetsCurrent, AssetsOfDisposalGroupIncludingDiscontinuedOperation, AssetsCurrent, EquityMethodInvestments, DeferredIncomeTaxAssetsNet, PropertyPlantAndEquipmentNet, IndefiniteLivedTrademarks, Goodwill, OtherAssetsNoncurrent, Assets, AccountsPayableAndAccruedLiabilitiesCurrent, ShortTermBorrowings/NotesAndLoansPayable, LongTermDebtCurrent/LongTermDebtAndCapitalLeaseObligationsCurrent, AccruedIncomeTaxesCurrent, LiabilitiesOfDisposalGroupIncludingDiscontinuedOperation, LiabilitiesCurrent, LongTermDebtNoncurrent/LongTermDebtAndCapitalLeaseObligations, OtherLiabilitiesNoncurrent, DeferredIncomeTaxLiabilitiesNet, CommonStockValue, AdditionalPaidInCapitalCommonStock, RetainedEarningsAccumulatedDeficit, AccumulatedOtherComprehensiveIncomeLossNetOfTax, TreasuryStockValue, StockholdersEquity, MinorityInterest, StockholdersEquityIncludingPortionAttributableToNCI, LiabilitiesAndStockholdersEquity | E7: GAPS (both quantified, not estimated): (1) FY2021-FY2023 'Assets held for sale'/'Liabilities held for sale' verified NOT included in that year's published current subtotal (unlike FY24-25) — confirmed by exact reconciliation of tagged components to the published AssetsCurrent/LiabilitiesCurrent totals; treated as memo lines for FY21-23, on-subtotal for FY24-25 (see Checks_TieOut, year-conditional formula). (2) FY2021 non-current assets short by $1,603mm and FY2022 by $1,136mm vs. the audited Total Assets constant after summing all identified non-current tags — likely a component (e.g. 'other investments'/finance-lease assets) reclassified into 'Other noncurrent assets' starting the FY2023 10-K and not separately resolvable from this companyfacts pull. Booked as a single labeled 'Unallocated non-current assets (reconciling residual)' row so BS_Hist ties exactly to the audited Total Assets constant every year. FY2023-FY2025 have zero residual.
A8: CF_Hist | B8: FY2023-FY2025 | C8: 10-K filed 2026-02-20, accession 0001628280-26-010047 | D8: R7.htm ("CONSOLIDATED STATEMENTS OF CASH FLOWS") | E8: Exact, full line-item detail.
A9: CF_Hist | B9: FY2021-FY2022 | C9: SEC companyfacts API | D9: companyfacts.json — us-gaap:DepreciationDepletionAndAmortization, ShareBasedCompensation, DeferredIncomeTaxExpenseBenefit, IncomeLossFromEquityMethodInvestmentsNetOfDividendsOrDistributions, ForeignCurrencyTransactionGainLossBeforeTax (FY22 only), OtherOperatingActivitiesCashFlowStatement, IncreaseDecreaseInOperatingCapital, NetCashProvidedByUsedInOperatingActivities, PaymentsToAcquirePropertyPlantAndEquipment, ProceedsFromSaleOfPropertyPlantAndEquipment, NetCashProvidedByUsedInInvestingActivities, ProceedsFromIssuanceOfCommonStock, PaymentsForRepurchaseOfCommonStock, PaymentsOfDividends, ProceedsFromPaymentsForOtherFinancingActivities, NetCashProvidedByUsedInFinancingActivities, EffectOfExchangeRateOnCash..., CashCashEquivalentsRestrictedCash...PeriodIncreaseDecrease | E9: GAP (disclosed, not estimated): this companyfacts.json pull contains only the 'dei' and 'us-gaap' taxonomies — Coca-Cola's custom 'ko:' namespace tags (used for e.g. 'Significant gains/losses — net', 'Other items', FY2021 FX adjustment, and most FY21-22 CFI/CFF sub-lines) were not fetched, so those individual line items cannot be split for FY2021-FY2022. Each CF section combines its unavailable custom-tag lines into ONE row labeled '...GAP reconciling — FY21-22 combined', computed as published section subtotal minus the sum of available tagged lines — i.e. the total is exact and audited; only the internal split of that residual is unresolved. Recommend re-pulling company facts with the ko: namespace, or sourcing the FY2021/FY2022 10-Ks' own R-files, to close this gap in a future pass.
A10: CF_Hist beginning/end cash FY21-22 | B10: FY2021-FY2022 | C10: Derived, not directly tagged | D10: Chained backward from the FY2023 10-K R7.htm beginning-of-2023 balance ($9,825mm) using the tagged net-change-in-cash figures for FY2022 and FY2021 | E10: Exact by construction (chain identity verified in Checks_TieOut); FY2021/FY2022 restricted-cash memo split not available (companyfacts pull has no tag before FY2023), so BS-cash vs. CF-end-cash(incl. restricted) cross-check is only run for FY2023-FY2025.
A11: Excluded/ignored | B11: n/a | C11: Gate_9of10 sheet | D11: n/a | E11: Self-certifying legacy sheet per Ola 2 build rules — not read, not replicated, not relied upon.
A13: Unit/scale check performed (Ola 1 "/1000" lesson): companyfacts.json values are absolute USD (e.g. Revenues FY2025 = 47,941,000,000); this workbook presents USD MILLIONS throughout IS_Hist/BS_Hist/CF_Hist, i.e. every value above was divided by 1,000,000 before being entered as a constant. Cross-checked against R3/R5/R7.htm which are natively labeled "$ in Millions" — exact match confirms no scale error.

Sheet Forecast_IG
A1: Forecast_IG — 5-year driver-built forecast (Base/Bull/Bear), anchored to audited FY2025A
A2: USD millions. Scenario toggle in B5 (1=Base, 2=Bull, 3=Bear). Revenue and margins normalized off FY2023-FY2025 3-yr average to avoid over-anchoring on FY2025A one-off items (large other income, low other operating charges). PARTIAL: driver set is revenue growth / gross margin / opex ratio / tax rate only — no segment, FX, or working-capital schedule build in this pass.
A4: Scenario (1=Base,2=Bull,3=Bear) | B4: Value
B5: 1
A6: Driver | B6: Base | C6: Bull | D6: Bear | E6: Selected
A7: Revenue growth, %/yr | B7: 0.05 | C7: 0.07 | D7: 0.02 | E7: =CHOOSE($B$5,B7,C7,D7) -> 0.05
A8: Gross margin, % of revenue | B8: =AVERAGE(IS_Hist!D7:F7)/AVERAGE(IS_Hist!D5:F5) -> 0.60754071 | C8: =B8+0.01 -> 0.61754071 | D8: =B8-0.015 -> 0.59254071 | E8: =CHOOSE($B$5,B8,C8,D8) -> 0.60754071
A9: SG&A, % of revenue | B9: =AVERAGE(IS_Hist!D8:F8)/AVERAGE(IS_Hist!D5:F5) -> 0.30602603 | C9: =B9-0.003 -> 0.30302603 | D9: =B9+0.005 -> 0.31102603 | E9: =CHOOSE($B$5,B9,C9,D9) -> 0.30602603
A10: Other operating charges, % of revenue | B10: =AVERAGE(IS_Hist!D9:F9)/AVERAGE(IS_Hist!D5:F5) -> 0.052395635 | C10: =B10 -> 0.052395635 | D10: =B10+0.005 -> 0.057395635 | E10: =CHOOSE($B$5,B10,C10,D10) -> 0.052395635
A11: Net interest + equity income + other, % of revenue | B11: =AVERAGE((IS_Hist!D11:F11-IS_Hist!D12:F12+IS_Hist!D13:F13+IS_Hist!D14:F14))/AVERAGE(IS_Hist!D5:F5) -> 0.04952542 | C11: =B11+0.002 -> 0.05152542 | D11: =B11-0.005 -> 0.04452542 | E11: =CHOOSE($B$5,B11,C11,D11) -> 0.04952542
A12: Effective tax rate, % | B12: =AVERAGE(IS_Hist!D16:F16)/AVERAGE(IS_Hist!D15:F15) -> 0.17953659 | C12: =B12-0.01 -> 0.16953659 | D12: =B12+0.01 -> 0.18953659 | E12: =CHOOSE($B$5,B12,C12,D12) -> 0.17953659
A13: NCI, % of consolidated net income | B13: =AVERAGE(IS_Hist!D18:F18)/AVERAGE(IS_Hist!D17:F17) -> 0.0010728058 | C13: =B13 -> 0.0010728058 | D13: =B13 -> 0.0010728058 | E13: =CHOOSE($B$5,B13,C13,D13) -> 0.0010728058
A15: Line item | B15: FY2026E | C15: FY2027E | D15: FY2028E | E15: FY2029E | F15: FY2030E
A16: Revenue | B16: =IS_Hist!F5*(1+$E$7) -> 50338.05 | C16: =B16*(1+$E$7) -> 52854.953 | D16: =C16*(1+$E$7) -> 55497.7 | E16: =D16*(1+$E$7) -> 58272.585 | F16: =E16*(1+$E$7) -> 61186.214
A17: Gross profit | B17: =B16*$E$8 -> 30582.415 | C17: =C16*$E$8 -> 32111.535 | D17: =D16*$E$8 -> 33717.112 | E17: =E16*$E$8 -> 35402.968 | F17: =F16*$E$8 -> 37173.116
A18: SG&A | B18: =-B16*$E$9 -> -15404.754 | C18: =-C16*$E$9 -> -16174.991 | D18: =-D16*$E$9 -> -16983.741 | E18: =-E16*$E$9 -> -17832.928 | F18: =-F16*$E$9 -> -18724.574
A19: Other operating charges | B19: =-B16*$E$10 -> -2637.4941 | C19: =-C16*$E$10 -> -2769.3688 | D19: =-D16*$E$10 -> -2907.8372 | E19: =-E16*$E$10 -> -3053.2291 | F19: =-F16*$E$10 -> -3205.8906
A20: Operating income | B20: =B17+B18+B19 -> 12540.167 | C20: =C17+C18+C19 -> 13167.175 | D20: =D17+D18+D19 -> 13825.534 | E20: =E17+E18+E19 -> 14516.811 | F20: =F17+F18+F19 -> 15242.651
A21: Net interest + equity income + other | B21: =B16*$E$11 -> 2493.0131 | C21: =C16*$E$11 -> 2617.6637 | D21: =D16*$E$11 -> 2748.5469 | E21: =E16*$E$11 -> 2885.9742 | F21: =F16*$E$11 -> 3030.273
A22: Pretax income | B22: =B20+B21 -> 15033.18 | C22: =C20+C21 -> 15784.839 | D22: =D20+D21 -> 16574.081 | E22: =E20+E21 -> 17402.785 | F22: =F20+F21 -> 18272.924
A23: Income taxes | B23: =-B22*$E$12 -> -2699.0058 | C23: =-C22*$E$12 -> -2833.9561 | D23: =-D22*$E$12 -> -2975.6539 | E23: =-E22*$E$12 -> -3124.4366 | F23: =-F22*$E$12 -> -3280.6584
A24: Consolidated net income | B24: =B22+B23 -> 12334.174 | C24: =C22+C23 -> 12950.883 | D24: =D22+D23 -> 13598.427 | E24: =E22+E23 -> 14278.348 | F24: =F22+F23 -> 14992.266
A25: NCI | B25: =-B24*$E$13 -> -13.232174 | C25: =-C24*$E$13 -> -13.893782 | D25: =-D24*$E$13 -> -14.588472 | E25: =-E24*$E$13 -> -15.317895 | F25: =-F24*$E$13 -> -16.08379
A26: Net income attributable to shareowners | B26: =B24+B25 -> 12320.942 | C26: =C24+C25 -> 12936.989 | D26: =D24+D25 -> 13583.838 | E26: =E24+E25 -> 14263.03 | F26: =F24+F25 -> 14976.182

Sheet Drivers_MDA
A1: The Coca-Cola Company (KO) — Drivers de negocio del MD&A y disclosures (FY2021A–FY2025A)
A2: USD millones salvo indicación. CAPA DE COBERTURA ADITIVA: no altera ninguna hoja histórica. Todo dato 'Reportado' es una constante publicada; todo 'Calculado' es fórmula viva. Los 'Tie' deben ser 0. Año fiscal de KO = año calendario (cierre 31-dic). Fuentes primarias: los cinco 10-K locales leídos con pdftotext (accessions en la fila 173).
A4: Métrica | B4: FY2021A | C4: FY2022A | D4: FY2023A | E4: FY2024A | F4: FY2025A | G4: Unidad | H4: Fuente (documento - sección - accession) | I4: Estado
A6: 1. VOLUMEN DEL SISTEMA
A7: Unit cases vendidos por el sistema Coca-Cola | B7: 31.3 | C7: 32.7 | D7: 33.3 | E7: 33.7 | F7: 33.8 | G7: miles de millones de cajas unidad | H7: Item 7 MD&A, 'Unit Case Volume' de cada 10-K: 31.3 (FY21, accn 0000021344-22-000009), 32.7 (FY22, 0000021344-23-000011), 33.3 (FY23, 0000021344-24-000009), 33.7 (FY24, 0000021344-25-000011), 33.8 (FY25, 0001628280-26-010047) | I7: Reportado
A8: Crecimiento interanual de unit cases (calc) | B8: n.a. | C8: =C7/B7-1 -> 0.044728435 | D8: =D7/C7-1 -> 0.018348624 | E8: =E7/D7-1 -> 0.012012012 | F8: =F7/E7-1 -> 0.0029673591 | G8: % | H8: Calculado (FY2020 fuera de la ventana del modelo) | I8: Calculado
A9: Ingreso por unit case (calc) | B9: =IS_Hist!B5/(B7*1000) -> 1.234984 | C9: =IS_Hist!C5/(C7*1000) -> 1.315107 | D9: =IS_Hist!D5/(D7*1000) -> 1.373994 | E9: =IS_Hist!E5/(E7*1000) -> 1.3964688 | F9: =IS_Hist!F5/(F7*1000) -> 1.4183728 | G9: USD/caja unidad | H9: Calculado: IS_Hist ventas netas / unit cases | I9: Calculado
A10: % del volumen mundial atribuible a operaciones de concentrado | B10: 0.83 | C10: 0.82 | D10: 0.83 | E10: 0.85 | F10: 0.85 | G10: % | H10: Item 7 MD&A, tabla '% of total worldwide unit case volume attributable to concentrate operations and finished product operations' de cada 10-K | I10: Reportado
A11: % del volumen mundial atribuible a operaciones de producto terminado | B11: 0.17 | C11: 0.18 | D11: 0.17 | E11: 0.15 | F11: 0.15 | G11: % | H11: Misma tabla del Item 7 MD&A | I11: Reportado
A12: Suma de los dos splits de volumen (calc, debe ser 100%) | B12: =B10+B11 -> 1 | C12: =C10+C11 -> 1 | D12: =D10+D11 -> 1 | E12: =E10+E11 -> 1 | F12: =F10+F11 -> 1 | G12: % | H12: Calculado | I12: Calculado
A15: 2. BRIDGE DE INGRESOS DEL MD&A (contribución % al cambio de ventas netas vs año anterior; el emisor redondea cada componente a 1%)
A16: Volumen (concentrate sales / unit cases según segmento) | B16: 0.09 | C16: 0.05 | D16: 0.02 | E16: 0.02 | F16: 0.01 | G16: % | H16: Item 7 MD&A 'Net Operating Revenues', tabla de factores (consolidado) de cada 10-K. FY2021 10-K accn 0000021344-22-000009 | FY2022 10-K 0000021344-23-000011 | FY2023 10-K 0000021344-24-000009 | FY2024 10-K 0000021344-25-000011 | FY2025 10-K 0001628280-26-010047 | I16: Reportado
A17: Precio / mix | B17: 0.06 | C17: 0.11 | D17: 0.1 | E17: 0.11 | F17: 0.04 | G17: % | H17: Item 7 MD&A 'Net Operating Revenues', tabla de factores (consolidado) de cada 10-K. FY2021 10-K accn 0000021344-22-000009 | FY2022 10-K 0000021344-23-000011 | FY2023 10-K 0000021344-24-000009 | FY2024 10-K 0000021344-25-000011 | FY2025 10-K 0001628280-26-010047 | I17: Reportado
A18: Tipo de cambio (FX) | B18: 0.01 | C18: -0.07 | D18: -0.04 | E18: -0.05 | F18: -0.02 | G18: % | H18: Item 7 MD&A 'Net Operating Revenues', tabla de factores (consolidado) de cada 10-K. FY2021 10-K accn 0000021344-22-000009 | FY2022 10-K 0000021344-23-000011 | FY2023 10-K 0000021344-24-000009 | FY2024 10-K 0000021344-25-000011 | FY2025 10-K 0001628280-26-010047 | I18: Reportado
A19: Adquisiciones y desinversiones (incl. cambios estructurales) | B19: 0 | C19: 0.02 | D19: -0.01 | E19: -0.04 | F19: -0.01 | G19: % | H19: Item 7 MD&A 'Net Operating Revenues', tabla de factores (consolidado) de cada 10-K. FY2021 10-K accn 0000021344-22-000009 | FY2022 10-K 0000021344-23-000011 | FY2023 10-K 0000021344-24-000009 | FY2024 10-K 0000021344-25-000011 | FY2025 10-K 0001628280-26-010047 | I19: Reportado
A20: Total reportado | B20: 0.17 | C20: 0.11 | D20: 0.06 | E20: 0.03 | F20: 0.02 | G20: % | H20: Item 7 MD&A 'Net Operating Revenues', tabla de factores (consolidado) de cada 10-K. FY2021 10-K accn 0000021344-22-000009 | FY2022 10-K 0000021344-23-000011 | FY2023 10-K 0000021344-24-000009 | FY2024 10-K 0000021344-25-000011 | FY2025 10-K 0001628280-26-010047. FY2021 es el cambio vs FY2020 (fuera de la ventana del modelo) | I20: Reportado
A21: Suma de componentes (calc; puede diferir del total por redondeo, declarado por el emisor) | B21: =SUM(B16:B19) -> 0.16 | C21: =SUM(C16:C19) -> 0.11 | D21: =SUM(D16:D19) -> 0.07 | E21: =SUM(E16:E19) -> 0.04 | F21: =SUM(F16:F19) -> 0.02 | G21: % | H21: Calculado | I21: Calculado
A22: Crecimiento real de ventas netas (calc, IS_Hist) | B22: n.a. | C22: =IS_Hist!C5/IS_Hist!B5-1 -> 0.11250808 | D22: =IS_Hist!D5/IS_Hist!C5-1 -> 0.06394754 | E22: =IS_Hist!E5/IS_Hist!D5-1 -> 0.028565808 | F22: =IS_Hist!F5/IS_Hist!E5-1 -> 0.018699135 | G22: % | H22: Calculado. FY2021 n.a. (FY2020 fuera de ventana) | I22: Calculado
A23: Delta total reportado − crecimiento real (calc; tolerancia de redondeo ±1.5pp) | B23: n.a. | C23: =C20-C22 -> -0.0025080843 | D23: =D20-D22 -> -0.0039475398 | E23: =E20-E22 -> 0.0014341915 | F23: =F20-F22 -> 0.0013008648 | G23: % | H23: Calculado | I23: Calculado
A25: 3. VENTAS NETAS A TERCEROS POR SEGMENTO OPERATIVO. QUIEBRE DE PRESENTACIÓN DECLARADO: FY2023–FY2025 según el 10-K FY2025 (Global Ventures disuelto y absorbido en los segmentos geográficos; los fees de Monster re-asignados; períodos anteriores re-presentados). FY2021–FY2022 según la presentación original del 10-K FY2023 (incluye Global Ventures). Las líneas NO son comparables entre vintages; los totales sí (ver bloque 10).
A26: EMEA (Europe, Middle East & Africa) | B26: 6564 | C26: 6896 | D26: 10152 | E26: 10278 | F26: 10833 | G26: USD m | H26: FY21-22: 10-K FY2023 (0000021344-24-000009), Nota 20 'Operating Segments', fila 'Third party' | FY23-25: 10-K FY2025 (0001628280-26-010047), Nota 20 'Operating Segments', fila 'Third party' | I26: Reportado
A27: Latin America | B27: 4143 | C27: 4910 | D27: 5834 | E27: 6471 | F27: 6331 | G27: USD m | H27: FY21-22: 10-K FY2023 (0000021344-24-000009), Nota 20 'Operating Segments', fila 'Third party' | FY23-25: 10-K FY2025 (0001628280-26-010047), Nota 20 'Operating Segments', fila 'Third party' | I27: Reportado
A28: North America | B28: 13184 | C28: 15667 | D28: 16965 | E28: 18860 | F28: 19579 | G28: USD m | H28: FY21-22: 10-K FY2023 (0000021344-24-000009), Nota 20 'Operating Segments', fila 'Third party' | FY23-25: 10-K FY2025 (0001628280-26-010047), Nota 20 'Operating Segments', fila 'Third party' | I28: Reportado
A29: Asia Pacific | B29: 4682 | C29: 4711 | D29: 4811 | E29: 5127 | F29: 5328 | G29: USD m | H29: FY21-22: 10-K FY2023 (0000021344-24-000009), Nota 20 'Operating Segments', fila 'Third party' | FY23-25: 10-K FY2025 (0001628280-26-010047), Nota 20 'Operating Segments', fila 'Third party' | I29: Reportado
A30: Global Ventures (solo FY21-22; absorbido en la re-presentación del 10-K FY2025) | B30: 2805 | C30: 2843 | D30: n.a. (recast) | E30: n.a. (recast) | F30: n.a. (recast) | G30: USD m | H30: FY21-22: 10-K FY2023 (0000021344-24-000009), Nota 20 'Operating Segments', fila 'Third party' | FY23-25: 10-K FY2025 (0001628280-26-010047), Nota 20 'Operating Segments', fila 'Third party' | I30: Reportado (FY21-22)
A31: Bottling Investments | B31: 7194 | C31: 7883 | D31: 7852 | E31: 6215 | F31: 5726 | G31: USD m | H31: FY21-22: 10-K FY2023 (0000021344-24-000009), Nota 20 'Operating Segments', fila 'Third party' | FY23-25: 10-K FY2025 (0001628280-26-010047), Nota 20 'Operating Segments', fila 'Third party' | I31: Reportado
A32: Corporate | B32: 83 | C32: 94 | D32: 140 | E32: 110 | F32: 144 | G32: USD m | H32: FY21-22: 10-K FY2023 (0000021344-24-000009), Nota 20 'Operating Segments', fila 'Third party' | FY23-25: 10-K FY2025 (0001628280-26-010047), Nota 20 'Operating Segments', fila 'Third party' | I32: Reportado
A33: Total ventas netas a terceros (calc) | B33: =SUM(B26:B32) -> 38655 | C33: =SUM(C26:C32) -> 43004 | D33: =SUM(D26:D32) -> 45754 | E33: =SUM(E26:E32) -> 47061 | F33: =SUM(F26:F32) -> 47941 | G33: USD m | H33: Suma de los segmentos divulgados (SUM ignora las celdas de texto del recast) | I33: Calculado
A34: Tie: segmentos − IS_Hist ventas netas | B34: =B33-IS_Hist!B5 -> 0 | C34: =C33-IS_Hist!C5 -> 0 | D34: =D33-IS_Hist!D5 -> 0 | E34: =E33-IS_Hist!E5 -> 0 | F34: =F33-IS_Hist!F5 -> 0 | G34: USD m | H34: IS_Hist!B5:F5 (estados auditados, sin modificar) | I34: Tie (debe ser 0)
A36: Mix por segmento (% de ventas netas consolidadas; recordar el quiebre de presentación FY22→FY23)
A37: Mix - EMEA | B37: =B26/B$33 -> 0.16980986 | C37: =C26/C$33 -> 0.16035718 | D37: =D26/D$33 -> 0.22188224 | E37: =E26/E$33 -> 0.2183974 | F37: =F26/F$33 -> 0.22596525 | G37: % | H37: Calculado sobre el total a terceros | I37: Calculado
A38: Mix - Latin America | B38: =B27/B$33 -> 0.10717889 | C38: =C27/C$33 -> 0.11417543 | D38: =D27/D$33 -> 0.12750798 | E38: =E27/E$33 -> 0.13750239 | F38: =F27/F$33 -> 0.13205815 | G38: % | H38: Calculado sobre el total a terceros | I38: Calculado
A39: Mix - North America | B39: =B28/B$33 -> 0.34106843 | C39: =C28/C$33 -> 0.36431495 | D39: =D28/D$33 -> 0.37078725 | E39: =E28/E$33 -> 0.40075647 | F39: =F28/F$33 -> 0.40839782 | G39: % | H39: Calculado sobre el total a terceros | I39: Calculado
A40: Mix - Asia Pacific | B40: =B29/B$33 -> 0.12112275 | C40: =C29/C$33 -> 0.10954795 | D40: =D29/D$33 -> 0.10514928 | E40: =E29/E$33 -> 0.10894371 | F40: =F29/F$33 -> 0.11113661 | G40: % | H40: Calculado sobre el total a terceros | I40: Calculado
A41: Mix - Bottling Investments | B41: =B31/B$33 -> 0.18610788 | C41: =C31/C$33 -> 0.18330853 | D41: =D31/D$33 -> 0.17161341 | E41: =E31/E$33 -> 0.13206264 | F41: =F31/F$33 -> 0.11943848 | G41: % | H41: Calculado sobre el total a terceros | I41: Calculado
A43: UTILIDAD OPERATIVA POR SEGMENTO Y RECONCILIACIÓN AL ESTADO DE RESULTADOS (la conciliación del emisor: suma de segmentos + Corporate = utilidad operativa consolidada)
A44: EMEA - utilidad operativa | B44: 3735 | C44: 3958 | D44: 4323 | E44: 4255 | F44: 4298 | G44: USD m | H44: FY21-22: 10-K FY2023 (0000021344-24-000009), Nota 20, fila 'Operating income (loss)' | FY23-25: 10-K FY2025 (0001628280-26-010047), Nota 20, fila 'Operating income (loss)' | I44: Reportado
A45: Latin America - utilidad operativa | B45: 2534 | C45: 2870 | D45: 3436 | E45: 3792 | F45: 3742 | G45: USD m | H45: FY21-22: 10-K FY2023 (0000021344-24-000009), Nota 20, fila 'Operating income (loss)' | FY23-25: 10-K FY2025 (0001628280-26-010047), Nota 20, fila 'Operating income (loss)' | I45: Reportado
A46: North America - utilidad operativa | B46: 3331 | C46: 3742 | D46: 4634 | E46: 4556 | F46: 5070 | G46: USD m | H46: FY21-22: 10-K FY2023 (0000021344-24-000009), Nota 20, fila 'Operating income (loss)' | FY23-25: 10-K FY2025 (0001628280-26-010047), Nota 20, fila 'Operating income (loss)' | I46: Reportado
A47: Asia Pacific - utilidad operativa | B47: 2325 | C47: 2303 | D47: 2057 | E47: 2156 | F47: 2042 | G47: USD m | H47: FY21-22: 10-K FY2023 (0000021344-24-000009), Nota 20, fila 'Operating income (loss)' | FY23-25: 10-K FY2025 (0001628280-26-010047), Nota 20, fila 'Operating income (loss)' | I47: Reportado
A48: Global Ventures - utilidad operativa (solo FY21-22) | B48: 293 | C48: 185 | D48: n.a. (recast) | E48: n.a. (recast) | F48: n.a. (recast) | G48: USD m | H48: FY21-22: 10-K FY2023 (0000021344-24-000009), Nota 20, fila 'Operating income (loss)' | FY23-25: 10-K FY2025 (0001628280-26-010047), Nota 20, fila 'Operating income (loss)' | I48: Reportado (FY21-22)
A49: Bottling Investments - utilidad operativa | B49: 473 | C49: 487 | D49: 578 | E49: 496 | F49: 426 | G49: USD m | H49: FY21-22: 10-K FY2023 (0000021344-24-000009), Nota 20, fila 'Operating income (loss)' | FY23-25: 10-K FY2025 (0001628280-26-010047), Nota 20, fila 'Operating income (loss)' | I49: Reportado
A50: Corporate - utilidad (pérdida) operativa | B50: -2383 | C50: -2636 | D50: -3717 | E50: -5263 | F50: -1816 | G50: USD m | H50: FY21-22: 10-K FY2023 (0000021344-24-000009), Nota 20, fila 'Operating income (loss)' | FY23-25: 10-K FY2025 (0001628280-26-010047), Nota 20, fila 'Operating income (loss)' | I50: Reportado
A51: Utilidad operativa consolidada (calc) | B51: =SUM(B44:B50) -> 10308 | C51: =SUM(C44:C50) -> 10909 | D51: =SUM(D44:D50) -> 11311 | E51: =SUM(E44:E50) -> 9992 | F51: =SUM(F44:F50) -> 13762 | G51: USD m | H51: Conciliación del emisor reproducida como fórmula viva | I51: Calculado
A52: Tie: reconciliación − IS_Hist utilidad operativa | B52: =B51-IS_Hist!B10 -> 0 | C52: =C51-IS_Hist!C10 -> 0 | D52: =D51-IS_Hist!D10 -> 0 | E52: =E51-IS_Hist!E10 -> 0 | F52: =F51-IS_Hist!F10 -> 0 | G52: USD m | H52: IS_Hist!B10:F10 | I52: Tie (debe ser 0)
A54: Margen operativo por segmento (calc; utilidad operativa del segmento / ventas a terceros del segmento)
A55: Margen operativo - EMEA | B55: =B44/B26 -> 0.5690128 | C55: =C44/C26 -> 0.57395592 | D55: =D44/D26 -> 0.42582742 | E55: =E44/E26 -> 0.41399105 | F55: =F44/F26 -> 0.39675067 | G55: % | H55: Calculado | I55: Calculado
A56: Margen operativo - Latin America | B56: =B45/B27 -> 0.61163408 | C56: =C45/C27 -> 0.58452138 | D56: =D45/D27 -> 0.58896126 | E56: =E45/E27 -> 0.58599907 | F56: =F45/F27 -> 0.59105986 | G56: % | H56: Calculado | I56: Calculado
A57: Margen operativo - North America | B57: =B46/B28 -> 0.25265473 | C57: =C46/C28 -> 0.23884598 | D57: =D46/D28 -> 0.2731506 | E57: =E46/E28 -> 0.24156946 | F57: =F46/F28 -> 0.25895092 | G57: % | H57: Calculado | I57: Calculado
A58: Margen operativo - Asia Pacific | B58: =B47/B29 -> 0.49658266 | C58: =C47/C29 -> 0.48885587 | D58: =D47/D29 -> 0.42756184 | E58: =E47/E29 -> 0.42051882 | F58: =F47/F29 -> 0.38325826 | G58: % | H58: Calculado | I58: Calculado
A59: Margen operativo - Bottling Investments | B59: =B49/B31 -> 0.065749235 | C59: =C49/C31 -> 0.061778511 | D59: =D49/D31 -> 0.073611819 | E59: =E49/E31 -> 0.079806919 | F59: =F49/F31 -> 0.074397485 | G59: % | H59: Calculado | I59: Calculado
A61: COGS POR SEGMENTO (solo FY2023–FY2025; el 10-K FY2025 divulga el costo por segmento con Corporate y eliminaciones en la nueva presentación)
A62: COGS - EMEA | B62: n.a. | C62: n.a. | D62: 2970 | E62: 3083 | F62: 3294 | G62: USD m | H62: 10-K FY2025 (0001628280-26-010047), Nota 20, fila 'Cost of goods sold' por segmento | I62: Reportado (solo FY23-25)
A63: COGS - Latin America | B63: n.a. | C63: n.a. | D63: 1040 | E63: 1099 | F63: 1109 | G63: USD m | H63: 10-K FY2025 (0001628280-26-010047), Nota 20, fila 'Cost of goods sold' por segmento | I63: Reportado (solo FY23-25)
A64: COGS - North America | B64: n.a. | C64: n.a. | D64: 8791 | E64: 9595 | F64: 9438 | G64: USD m | H64: 10-K FY2025 (0001628280-26-010047), Nota 20, fila 'Cost of goods sold' por segmento | I64: Reportado (solo FY23-25)
A65: COGS - Asia Pacific | B65: n.a. | C65: n.a. | D65: 1644 | E65: 1689 | F65: 1788 | G65: USD m | H65: 10-K FY2025 (0001628280-26-010047), Nota 20, fila 'Cost of goods sold' por segmento | I65: Reportado (solo FY23-25)
A66: COGS - Bottling Investments | B66: n.a. | C66: n.a. | D66: 5615 | E66: 4251 | F66: 3948 | G66: USD m | H66: 10-K FY2025 (0001628280-26-010047), Nota 20, fila 'Cost of goods sold' por segmento | I66: Reportado (solo FY23-25)
A67: COGS - Corporate | B67: n.a. | C67: n.a. | D67: -107 | E67: -229 | F67: -171 | G67: USD m | H67: 10-K FY2025 (0001628280-26-010047), Nota 20, fila 'Cost of goods sold' por segmento | I67: Reportado (solo FY23-25)
A68: COGS - Eliminaciones | B68: n.a. | C68: n.a. | D68: -1433 | E68: -1164 | F68: -1009 | G68: USD m | H68: 10-K FY2025 (0001628280-26-010047), Nota 20, fila 'Cost of goods sold' por segmento | I68: Reportado (solo FY23-25)
A69: Total COGS por segmento (calc) | D69: =SUM(D62:D68) -> 18520 | E69: =SUM(E62:E68) -> 18324 | F69: =SUM(F62:F68) -> 18397 | G69: USD m | H69: Calculado | I69: Calculado
A70: Tie: COGS segmentos − IS_Hist costo de ventas | D70: =D69-IS_Hist!D6 -> 0 | E70: =E69-IS_Hist!E6 -> 0 | F70: =F69-IS_Hist!F6 -> 0 | G70: USD m | H70: IS_Hist!D6:F6 | I70: Tie (debe ser 0)
A72: 4. OPERACIONES DE CONCENTRADO VS PRODUCTO TERMINADO (Nota 3 'Revenue Recognition' — dólares; Item 7 MD&A — porcentajes redondeados)
A73: Ventas netas - operaciones de concentrado | B73: 21799 | C73: 24071 | D73: 26539 | E73: 27725 | F73: 28462 | G73: USD m | H73: FY21-22: 10-K FY2023 (0000021344-24-000009), Nota 3 'Revenue Recognition', tabla de desagregación EE.UU./Internacional × línea de negocio | FY23-25: 10-K FY2025 (0001628280-26-010047), Nota 3, misma tabla | I73: Reportado
A74: Ventas netas - operaciones de producto terminado | B74: 16856 | C74: 18933 | D74: 19215 | E74: 19336 | F74: 19479 | G74: USD m | H74: FY21-22: 10-K FY2023 (0000021344-24-000009), Nota 3 'Revenue Recognition', tabla de desagregación EE.UU./Internacional × línea de negocio | FY23-25: 10-K FY2025 (0001628280-26-010047), Nota 3, misma tabla | I74: Reportado
A75: Total (calc) | B75: =B73+B74 -> 38655 | C75: =C73+C74 -> 43004 | D75: =D73+D74 -> 45754 | E75: =E73+E74 -> 47061 | F75: =F73+F74 -> 47941 | G75: USD m | H75: Calculado | I75: Calculado
A76: Tie: concentrado + producto terminado − IS_Hist ventas netas | B76: =B75-IS_Hist!B5 -> 0 | C76: =C75-IS_Hist!C5 -> 0 | D76: =D75-IS_Hist!D5 -> 0 | E76: =E75-IS_Hist!E5 -> 0 | F76: =F75-IS_Hist!F5 -> 0 | G76: USD m | H76: IS_Hist!B5:F5 | I76: Tie (debe ser 0)
A77: % de ventas de concentrado reportado (MD&A, redondeado a 1%) | B77: 0.56 | C77: 0.56 | D77: 0.58 | E77: 0.59 | F77: 0.59 | G77: % | H77: Item 7 MD&A, tabla '% of total net operating revenues attributable to concentrate operations...' de cada 10-K | I77: Reportado
A78: % de concentrado calculado desde la Nota 3 (calc) | B78: =B73/B75 -> 0.56393739 | C78: =C73/C75 -> 0.55973863 | D78: =D73/D75 -> 0.58003672 | E78: =E73/E75 -> 0.589129 | F78: =F73/F75 -> 0.59368807 | G78: % | H78: Calculado | I78: Calculado
A79: Delta % reportado − calculado (redondeo del emisor a 1% → tolerancia ±0.5pp) | B79: =B77-B78 -> -0.0039373949 | C79: =C77-C78 -> 0.00026137104 | D79: =D77-D78 -> -3.6718101e-05 | E79: =E77-E78 -> 0.00087099722 | F79: =F77-F78 -> -0.0036880749 | G79: % | H79: Calculado | I79: Calculado
A80: Ventas netas - Estados Unidos (Nota 3) | B80: 13010 | C80: 15413 | D80: 16550 | E80: 18362 | F80: 19127 | G80: USD m | H80: FY21-22: 10-K FY2023 (0000021344-24-000009), Nota 3 'Revenue Recognition', tabla de desagregación EE.UU./Internacional × línea de negocio | FY23-25: 10-K FY2025 (0001628280-26-010047), Nota 3, misma tabla | I80: Reportado
A81: Ventas netas - Internacional (Nota 3) | B81: 25645 | C81: 27591 | D81: 29204 | E81: 28699 | F81: 28814 | G81: USD m | H81: FY21-22: 10-K FY2023 (0000021344-24-000009), Nota 3 'Revenue Recognition', tabla de desagregación EE.UU./Internacional × línea de negocio | FY23-25: 10-K FY2025 (0001628280-26-010047), Nota 3, misma tabla | I81: Reportado
A82: Tie: EE.UU. + Internacional − IS_Hist ventas netas | B82: =B80+B81-IS_Hist!B5 -> 0 | C82: =C80+C81-IS_Hist!C5 -> 0 | D82: =D80+D81-IS_Hist!D5 -> 0 | E82: =E80+E81-IS_Hist!E5 -> 0 | F82: =F80+F81-IS_Hist!F5 -> 0 | G82: USD m | H82: IS_Hist!B5:F5 | I82: Tie (debe ser 0)
A83: % internacional de las ventas netas (calc) | B83: =B81/IS_Hist!B5 -> 0.66343293 | C83: =C81/IS_Hist!C5 -> 0.64159148 | D83: =D81/IS_Hist!D5 -> 0.63828299 | E83: =E81/IS_Hist!E5 -> 0.60982555 | F83: =F81/IS_Hist!F5 -> 0.60103043 | G83: % | H83: Calculado | I83: Calculado
A84: Memo cualitativo: las operaciones de producto terminado generan más ingreso por caja pero MENOR margen bruto que las de concentrado (declaración del emisor, Item 1) | G84: texto | H84: 10-K FY2025, Item 1 'Business' — 'Generally, finished product operations generate higher net operating revenues but lower gross profit margins than concentrate operations' | I84: Reportado (cualitativo)
A86: 5. DRIVERS DE TIPO DE CAMBIO (FX)
A87: Ventas netas generadas fuera de EE.UU. según Item 7A (redondeado a USD 0.1bn por el emisor) | B87: 25600 | C87: 27600 | D87: 29200 | E87: 28700 | F87: 28800 | G87: USD m | H87: Item 7A 'Quantitative and Qualitative Disclosures About Market Risk' - 'Foreign Currency Exchange Rates' de cada 10-K: 25.6/27.6/29.2/28.7/28.8 USD bn | I87: Reportado
A88: Tie: Item 7A − Nota 3 Internacional (dos secciones independientes del filing; tolerancia ±50 por el redondeo a 0.1bn) | B88: =B87-B81 -> -45 | C88: =C87-C81 -> 9 | D88: =D87-D81 -> -4 | E88: =E87-E81 -> 1 | F88: =F87-F81 -> -14 | G88: USD m | H88: Fila 81 (Nota 3) vs fila 87 (Item 7A) | I88: Tie (±50)
A89: Notional total de derivados FX | B89: 13691 | C89: 11370 | D89: 17505 | E89: 18442 | F89: 21128 | G89: USD m | H89: Item 7A 'Foreign Currency Exchange Rates' de cada 10-K (incluye designados y económicos) | I89: Reportado
A90: Notional FX / ventas netas (calc) | B90: =B89/IS_Hist!B5 -> 0.35418445 | C90: =C89/IS_Hist!C5 -> 0.26439401 | D90: =D89/IS_Hist!D5 -> 0.3825895 | E90: =E89/IS_Hist!E5 -> 0.39187438 | F90: =F89/IS_Hist!F5 -> 0.44070837 | G90: x | H90: Calculado | I90: Calculado
A91: Composición del notional FX FY2025 (Nota 16 'Hedging Transactions and Derivative Financial Instruments'):
A92: Designado - cash flow hedge de flujos pronosticados | F92: 9760 | G92: USD m | H92: 10-K FY2025 (0001628280-26-010047), Nota 16, 'foreign currency cash flow hedging program' | I92: Reportado (solo FY2025)
A93: Designado - cross-currency swaps (activos/pasivos en moneda extranjera) | F93: 557 | G93: USD m | H93: 10-K FY2025, Nota 16 | I93: Reportado (solo FY2025)
A94: Designado - net investment hedge (solo CONTRATOS FX; la deuda en moneda extranjera del programa no es un derivado) | F94: 1067 | G94: USD m | H94: 10-K FY2025, Nota 16, tabla de net investment hedges | I94: Reportado (solo FY2025)
A95: Económico (no designado) | F95: 9744 | G95: USD m | H95: 10-K FY2025, Nota 16, economic (non-designated) hedging | I95: Reportado (solo FY2025)
A96: Suma de la composición (calc) | F96: =SUM(F92:F95) -> 21128 | G96: USD m | H96: Calculado | I96: Calculado
A97: Tie: composición de la Nota 16 − notional total del Item 7A (dos secciones independientes del filing) | F97: =F96-F89 -> 0 | G97: USD m | H97: Fila 89 vs fila 96 | I97: Tie (debe ser 0)
A98: Sensibilidad FY2025: Δ valor razonable si el USD se debilita 10% - derivados designados | F98: -609 | G98: USD m | H98: 10-K FY2025, Item 7A | I98: Reportado (solo FY2025)
A99: Sensibilidad FY2025: ídem - derivados NO designados | F99: -123 | G99: USD m | H99: 10-K FY2025, Item 7A | I99: Reportado (solo FY2025)
A100: Memo: deuda denominada en moneda extranjera designada como net investment hedge (no es derivado; fuera del notional) | F100: 14998 | G100: USD m | H100: 10-K FY2025, Nota 16, tabla de net investment hedges | I100: Reportado (solo FY2025)
A101: Guía del emisor para 2026: espera impacto FX FAVORABLE en ventas netas (spot + coberturas vigentes) | G101: texto | H101: 10-K FY2025, Item 7 MD&A 'Net Operating Revenues' | I101: Reportado (cualitativo)
A103: 6. COBERTURAS DE COMMODITIES (sweeteners, metales, jugos, PET, combustibles)
A104: Notional total de derivados de commodities | B104: 918 | C104: 371 | D104: 379 | E104: 386 | F104: 535 | G104: USD m | H104: Item 7A 'Commodity Prices' de cada 10-K | I104: Reportado
A105: Notional commodities / costo de ventas (calc) | B105: =B104/IS_Hist!B6 -> 0.0597773 | C105: =C104/IS_Hist!C6 -> 0.020611111 | D105: =D104/IS_Hist!D6 -> 0.020464363 | E105: =E104/IS_Hist!E6 -> 0.02106527 | F105: =F104/IS_Hist!F6 -> 0.029080828 | G105: x | H105: Calculado | I105: Calculado
A106: FY2025 - designado cash flow hedge | F106: 53 | G106: USD m | H106: 10-K FY2025, Nota 16, commodity cash flow hedging program | I106: Reportado (solo FY2025)
A107: FY2025 - económico (no designado) | F107: 482 | G107: USD m | H107: 10-K FY2025, Nota 16 | I107: Reportado (solo FY2025)
A108: Tie: composición de la Nota 16 − notional total del Item 7A | F108: =F106+F107-F104 -> 0 | G108: USD m | H108: Fila 104 vs 106+107 | I108: Tie (debe ser 0)
A109: Sensibilidad FY2025: Δ valor razonable si commodities caen 10% - designados | F109: 3 | G109: USD m | H109: 10-K FY2025, Item 7A | I109: Reportado (solo FY2025)
A110: Sensibilidad FY2025: ídem - NO designados | F110: -33 | G110: USD m | H110: 10-K FY2025, Item 7A | I110: Reportado (solo FY2025)
A111: Gestión primaria del riesgo de commodities: supplier pricing agreements (los derivados son complemento) | G111: texto | H111: 10-K FY2025, Item 7A 'Commodity Prices' | I111: Reportado (cualitativo)
A113: 7. WORKING CAPITAL (enlaces vivos a las hojas históricas auditadas + detalle de la Nota 21 del 10-K FY2025)
...

Sheet Market_Package
A1: The Coca-Cola Company (KO) — Paquete de mercado fechado y costo de capital
A2: Cada input de mercado lleva su fuente y su FECHA (serial). Los enlaces al balance y al estado de resultados son fórmulas vivas contra las hojas históricas auditadas (que esta hoja NO modifica). Fechas: 46247 = 2026-08-13, 46248 = 2026-08-14, 46230 = 2026-07-27, 46206 = 2026-07-03, 46023 = 2026-01-01, 46022 = 2025-12-31, 45835 = 2025-06-27.
A4: Concepto | B4: Valor | C4: Unidad | D4: Fecha del dato (as-of) | E4: Fuente | F4: Nota / método
A6: 1. PRECIO Y ACCIONES
A7: Precio de la acción (cierre) | B7: 87.42 | C7: USD/acción | D7: 46247 | E7: stockanalysis.com/stocks/ko/history/ — histórico diario de KO | F7: Recuperado 2026-08-14. Cierre del 2026-08-13: apertura 87.14, máx 87.75, mín 86.91, volumen 9,974,842. CONFIRMADO de forma independiente contra Yahoo Finance (chart API v8): cierre 2026-08-13 = 87.42; los cierres del 08-11 (86.48) y 08-12 (86.71) también coinciden entre ambas fuentes
A8: Acciones en circulación | B8: 4302.5492 | C8: millones de acciones | D8: 46230 | E8: SEC Form 10-Q Q2 FY2026, portada (accn 0001628280-26-050503), 'Shares Outstanding as of July 27, 2026' | F8: 4,302,549,243 acciones de USD 0.25 par. Es el conteo más reciente publicado por la compañía. Descargado de EDGAR el 2026-08-14 (no estaba en el paquete local)
A9: Memo — acciones usadas hoy en el DCF (Historical!B20) | B9: =Historical!B20 -> 4300.723 | C9: millones de acciones | E9: Historical!B20 (política de acciones del DCF) | F9: Enlace vivo. 4,300.723m; deriva vs el conteo del 10-Q: +0.04%
A10: Memo — acciones diluidas promedio, 6M FY2026 | B10: 4313 | C10: millones de acciones | D10: 46206 | E10: 10-Q Q2 FY2026, Estado Condensado de Resultados | F10: Base diluida promedio del semestre
A11: Capitalización de mercado | B11: =B7*B8 -> 376128.85 | C11: USD m | D11: =D7 -> 46247 | E11: Calculado: precio de cierre × acciones en circulación | F11: Usa el conteo primario más reciente (B8), no el del DCF
A13: 2. PUENTE A ENTERPRISE VALUE (balance FY2025A del propio modelo, 2025-12-31)
A14: Efectivo y equivalentes | B14: =BS_Hist!F6 -> 10270 | C14: USD m | D14: 46022 | E14: BS_Hist!F6 — 10-K FY2025, balance auditado | F14: Enlace vivo a la hoja histórica
A15: Inversiones de corto plazo | B15: =BS_Hist!F7 -> 3602 | C15: USD m | D15: 46022 | E15: BS_Hist!F7 | F15: Enlace vivo
A16: Valores negociables (marketable securities) | B16: =BS_Hist!F8 -> 1934 | C16: USD m | D16: 46022 | E16: BS_Hist!F8 | F16: Enlace vivo
A17: Total efectivo e inversiones | B17: =SUM(B14:B16) -> 15806 | C17: USD m | D17: 46022 | E17: Calculado
A18: Loans and notes payable (papel comercial y similares) | B18: =BS_Hist!F27 -> 1551 | C18: USD m | D18: 46022 | E18: BS_Hist!F27 | F18: Enlace vivo
A19: Porción corriente de la deuda de largo plazo | B19: =BS_Hist!F28 -> 1822 | C19: USD m | D19: 46022 | E19: BS_Hist!F28 | F19: Enlace vivo
A20: Deuda de largo plazo | B20: =BS_Hist!F33 -> 42119 | C20: USD m | D20: 46022 | E20: BS_Hist!F33 | F20: Enlace vivo
A21: Deuda bruta total | B21: =SUM(B18:B20) -> 45492 | C21: USD m | D21: 46022 | E21: Calculado | F21: Incluye loans and notes payable
A22: Deuda neta | B22: =B21-B17 -> 29686 | C22: USD m | D22: 46022 | E22: Calculado | F22: Positivo = deuda neta
A23: Enterprise value | B23: =B11+B21-B17 -> 405814.85 | C23: USD m | D23: =D7 -> 46247 | E23: Calculado: cap. de mercado + deuda bruta − efectivo e inversiones | F23: Precio al 2026-08-13 contra balance al 2025-12-31
A24: Memo — deuda usada hoy en Valuation!G13 (vía Historical!B19) | B24: =Historical!B19 -> 43997 | C24: USD m | D24: 46022 | E24: Historical!B19 | F24: Tag combinado LongTermDebtAndCapitalLeaseObligationsIncludingCurrentMaturities (43,941) + other short-term borrowings (56)
A25: Memo — diferencia vs la deuda bruta de esta hoja | B25: =B21-B24 -> 1495 | C25: USD m | D25: 46022 | E25: Calculado | F25: HALLAZGO H1: son los loans and notes payable del balance (BS_Hist!F27 = 1,551) menos los 56 de other short-term borrowings ya incluidos (Historical!B25). El puente de deuda del DCF subestima la deuda bruta en 1,495. NO se corrige aquí: se expone y el check 47 lo mecaniza
A26: Memo — activos líquidos usados hoy en Valuation!G12 (vía Historical!B18) | B26: =Historical!B18 -> 10270 | C26: USD m | D26: 46022 | E26: Historical!B18 | F26: Política declarada del DCF: solo caja
A27: Memo — diferencia de activos líquidos | B27: =B17-B26 -> 5536 | C27: USD m | D27: 46022 | E27: Calculado | F27: HALLAZGO H2: el DCF omite las inversiones de corto plazo (3,602) y los valores negociables (1,934) = 5,536 (exactamente BS_Hist!F7+F8). El check 48 lo mecaniza
A29: 3. COSTO DE CAPITAL
A30: Tasa libre de riesgo (UST 10 años, par yield) | B30: 0.0463 | C30: % | D30: 46247 | E30: home.treasury.gov — Daily Treasury Par Yield Curve Rates, columna '10 Yr' (CSV primario descargado 2026-08-14) | F30: Fuente primaria del Tesoro de EE.UU. Misma fecha: 20Y 5.20%, 30Y 5.21%, 2Y 4.15%. Mismo Rf fechado que el resto de la flota USD de esta corrida (un solo Rf del Tesoro por corrida, patrón del playbook)
A31: Prima de riesgo de mercado (ERP implícita, S&P 500) | B31: 0.0423 | C31: % | D31: 46023 | E31: A. Damodaran (NYU Stern), 'Implied Equity Risk Premiums — United States' (histimpl.html), actualización de enero 2026 | F31: ERP implícita FCFE del cierre de 2025; misma ERP fechada que el resto de la flota USD de esta corrida
A32: Beta (5 años, mensual, vs S&P 500) | B32: 0.34 | C32: x | D32: 46248 | E32: stockanalysis.com/stocks/ko/ | F32: PROVEEDOR ÚNICO en esta corrida: los cross-checks intentados quedaron inaccesibles desde esta sesión (investing.com 403, WSJ 401, Yahoo quoteSummary bloqueado por crumb). Limitación L1. Nivel plausible para un consumer staple defensivo. NO es una beta propia: es de proveedor
A33: Costo de capital propio (CAPM) | B33: =B30+B32*B31 -> 0.060682 | C33: % | D33: =D30 -> 46247 | E33: Calculado: Rf + beta × ERP
A34: Costo de deuda antes de impuestos | B34: 0.0521 | C34: % | D34: 46247 | E34: FRED (Federal Reserve Bank of St. Louis) — serie primaria BAMLC0A3CAEY, ICE BofA Single-A US Corporate Index Effective Yield; fredgraph.csv descargado 2026-08-14 | F34: Benchmark de índice para emisor calificado A+/A1 (la calificación del propio KO según su 10-K FY2025: S&P 'A+', Moody's 'A1'; papel comercial A-1/P-1). Observación del 2026-08-13. Referencia AA misma fecha: 5.20% (BAMLC0A2CAAEY). Es el costo MARGINAL de mercado, no el cupón promedio de la deuda viva
A35: Memo — calificación crediticia del emisor | B35: A+ (S&P) / A1 (Moody's) | C35: rating | D35: 46022 | E35: 10-K FY2025, Item 7 MD&A 'Liquidity, Capital Resources and Financial Position' | F35: Divulgada al 2025-12-31 en el propio filing
A37: Tasa efectiva de impuestos (FY2025A del modelo) | B37: =IS_Hist!F16/IS_Hist!F15 -> 0.17883485 | C37: % | D37: 46022 | E37: IS_Hist!F16 / IS_Hist!F15 | F37: Enlace vivo: 2,861 / 15,998 = 17.9%. El check 49 exige que siga siendo enlace vivo
A38: Memo — tasa estatutaria federal de EE.UU. | B38: 0.21 | C38: % | D38: 46022 | E38: 10-K FY2025, nota de impuestos | F38: Referencia para una versión marginal del escudo fiscal
A39: Costo de deuda después de impuestos | B39: =B34*(1-B37) -> 0.042782704 | C39: % | D39: =D34 -> 46247 | E39: Calculado: Kd × (1 − t)
A40: Valor de mercado del capital (E) | B40: =B11 -> 376128.85 | C40: USD m | D40: =D7 -> 46247 | E40: Calculado
A41: Deuda bruta (D) | B41: =B21 -> 45492 | C41: USD m | D41: 46022 | E41: Calculado | F41: Valor en libros como proxy del valor de mercado
A42: Capital total (D+E) | B42: =B40+B41 -> 421620.85 | C42: USD m | E42: Calculado
A43: Peso del capital propio | B43: =B40/B42 -> 0.89210211 | C43: % | E43: Calculado
A44: Peso de la deuda | B44: =B41/B42 -> 0.10789789 | C44: % | E44: Calculado
A45: WACC | B45: =B43*B33+B44*B39 -> 0.058750704 | C45: % | D45: 46247 | E45: Calculado: We × Ke + Wd × Kd × (1 − t) | F45: Fórmula viva: mover B30, B31, B32 o B34 mueve el WACC
A46: Memo — WACC usado hoy en el DCF (escenario activo) | B46: =Assumptions!F16 -> 0.075 | C46: % | E46: Assumptions!F16 (selector Assumptions!B3) | F46: Escenario Base: 7.5%
A47: Memo — diferencia (este paquete − modelo) | B47: =B45-B46 -> -0.016249296 | C47: % | E47: Calculado | F47: HALLAZGO H4 (contraste, no error): la beta de proveedor 0.34 produce Ke 6.07% y WACC 5.88%, muy por debajo del 7.5% del escenario Base. Cablearlo movería outputs gateados y rompería el diseño Base/Bull/Bear: se deja como contraste declarado
A49: 4. MÚLTIPLOS IMPLÍCITOS vs FY2025A DEL MODELO
A50: Ventas netas FY2025A | B50: =IS_Hist!F5 -> 47941 | C50: USD m | D50: 46022 | E50: IS_Hist!F5 | F50: Enlace vivo
A51: Utilidad operativa FY2025A | B51: =IS_Hist!F10 -> 13762 | C51: USD m | D51: 46022 | E51: IS_Hist!F10 | F51: Enlace vivo
A52: Depreciación y amortización FY2025A | B52: =CF_Hist!F7 -> 1050 | C52: USD m | D52: 46022 | E52: CF_Hist!F7 | F52: Enlace vivo
A53: EBITDA FY2025A (calc) | B53: =B51+B52 -> 14812 | C53: USD m | D53: 46022 | E53: Calculado: EBIT + D&A | F53: KO no publica EBITDA; es una construcción del analista
A54: Utilidad neta atribuible FY2025A | B54: =IS_Hist!F19 -> 13107 | C54: USD m | D54: 46022 | E54: IS_Hist!F19 | F54: Enlace vivo
A55: UPA diluida FY2025A | B55: =IS_Hist!F22 -> 3.04 | C55: USD/acción | D55: 46022 | E55: IS_Hist!F22 | F55: Enlace vivo
A56: Flujo de efectivo de operación FY2025A | B56: =CF_Hist!F17 -> 7408 | C56: USD m | D56: 46022 | E56: CF_Hist!F17 | F56: Enlace vivo
A57: Capex FY2025A | B57: =-CF_Hist!F24 -> 2112 | C57: USD m | D57: 46022 | E57: CF_Hist!F24 (publicado como salida negativa) | F57: Enlace vivo con signo invertido
A58: Flujo de caja libre FY2025A (CFO − capex) | B58: =B56-B57 -> 5296 | C58: USD m | D58: 46022 | E58: Calculado | F58: NOTA: el CFO FY2024-FY2025 está deprimido por salidas grandes de working capital (Nota 21: prepagados −5,667 en FY2024; payables/acumulados −6,612 en FY2025). El FCF yield resultante subestima la generación normalizada — declarado, no ajustado
A59: P/E (cap. de mercado / utilidad neta atribuible) | B59: =B11/B54 -> 28.696792 | C59: x | D59: =D7 -> 46247 | E59: Calculado
A60: P/E (precio / UPA diluida) | B60: =B7/B55 -> 28.756579 | C60: x | D60: =D7 -> 46247 | E60: Calculado | F60: Difiere levemente del anterior porque usa acciones diluidas promedio y no acciones en circulación
A61: EV / Ventas | B61: =B23/B50 -> 8.4648809 | C61: x | D61: =D7 -> 46247 | E61: Calculado
A62: EV / EBITDA | B62: =B23/B53 -> 27.397708 | C62: x | D62: =D7 -> 46247 | E62: Calculado
A63: EV / EBIT | B63: =B23/B51 -> 29.488073 | C63: x | D63: =D7 -> 46247 | E63: Calculado
A64: FCF yield (FCF / cap. de mercado) | B64: =B58/B11 -> 0.014080281 | C64: % | D64: =D7 -> 46247 | E64: Calculado | F64: Ver la nota de B58: FCF deprimido por working capital
A65: Dividend yield (dividendos pagados FY2025A / cap. de mercado) | B65: =-CF_Hist!F36/B11 -> 0.023340406 | C65: % | D65: =D7 -> 46247 | E65: CF_Hist!F36 | F65: Sobre dividendos efectivamente pagados (8,779), no sobre el dividendo declarado corriente (2.04 → 2.33% también, coincide)
A66: Buyback yield (recompras FY2025A / cap. de mercado) | B66: =-CF_Hist!F35/B11 -> 0.0019833629 | C66: % | D66: =D7 -> 46247 | E66: CF_Hist!F35 | F66: KO recompra poco: 746 en FY2025
A67: Rendimiento total al accionista | B67: =B65+B66 -> 0.025323768 | C67: % | D67: =D7 -> 46247 | E67: Calculado
A69: 5. MEMO LTM — al Q2 FY2026 (10-Q del período terminado 2026-07-03, accn 0001628280-26-050503). FUERA del perímetro auditado del modelo.
A70: Ventas netas 6M FY2026 | B70: 25852 | C70: USD m | D70: 46206 | E70: 10-Q Q2 FY2026, Estado Condensado de Resultados
A71: Ventas netas 6M FY2025 | B71: 23664 | C71: USD m | D71: 45835 | E71: 10-Q Q2 FY2026, columna comparativa
A72: Ventas netas LTM | B72: =IS_Hist!F5-B71+B70 -> 50129 | C72: USD m | D72: 46206 | E72: Calculado: FY2025A − 6M FY2025 + 6M FY2026
A73: Utilidad operativa 6M FY2026 | B73: 9031 | C73: USD m | D73: 46206 | E73: 10-Q Q2 FY2026
A74: Utilidad operativa 6M FY2025 | B74: 7939 | C74: USD m | D74: 45835 | E74: 10-Q Q2 FY2026, columna comparativa
A75: Utilidad operativa LTM | B75: =IS_Hist!F10-B74+B73 -> 14854 | C75: USD m | D75: 46206 | E75: Calculado
A76: Utilidad neta atribuible 6M FY2026 | B76: 8349 | C76: USD m | D76: 46206 | E76: 10-Q Q2 FY2026
A77: Utilidad neta atribuible 6M FY2025 | B77: 7140 | C77: USD m | D77: 45835 | E77: 10-Q Q2 FY2026, columna comparativa
A78: Utilidad neta atribuible LTM | B78: =IS_Hist!F19-B77+B76 -> 14316 | C78: USD m | D78: 46206 | E78: Calculado
A79: P/E LTM | B79: =B11/B78 -> 26.27332 | C79: x | D79: =D7 -> 46247 | E79: Calculado
A80: EV / Ventas LTM | B80: =B23/B72 -> 8.0954109 | C80: x | D80: =D7 -> 46247 | E80: Calculado | F80: Usa el EV construido con el balance FY2025A
A81: EV / EBIT LTM | B81: =B23/B75 -> 27.320241 | C81: x | D81: =D7 -> 46247 | E81: Calculado
A82: Efectivo e inversiones al 2026-07-03 | B82: 16371 | C82: USD m | D82: 46206 | E82: 10-Q Q2 FY2026, balance condensado: 12,907 + 622 + 2,842 | F82: Ancla de vintage distinto: el check 46 exige que B17 (posición FY2025A del modelo) quede dentro de ±15% de esta cifra (deriva real −3.5%)
A83: Deuda bruta al 2026-07-03 | B83: 43543 | C83: USD m | D83: 46206 | E83: 10-Q Q2 FY2026, balance condensado: 48 + 6,494 + 37,001 | F83: Ancla de vintage distinto: el check 47 exige ±25% (deriva real +4.5% del modelo sobre esta cifra)
A84: EV con el balance al 2026-07-03 | B84: =B11+B83-B82 -> 403300.85 | C84: USD m | D84: =D7 -> 46247 | E84: Calculado | F84: Referencia: no se usa en los múltiplos de arriba para no mezclar perímetros
A85: Memo — diferencia vs el EV con balance FY2025A | B85: =B84-B23 -> -2514 | C85: USD m | E85: Calculado
A87: 6. CONTROL DE PROCEDENCIA (todo input de mercado debe traer fuente y fecha con serial válido)
A88: Inputs de mercado sujetos a control | B88: 6 | C88: conteo | E88: B7 precio, B8 acciones, B30 Rf, B31 ERP, B32 beta, B34 Kd | F88: Los demás valores de la hoja son enlaces vivos a hojas históricas o cálculos
A89: Inputs sin fuente | B89: =IF(LEN(E7)=0,1,0)+IF(LEN(E8)=0,1,0)+IF(LEN(E30)=0,1,0)+IF(LEN(E31)=0,1,0)+IF(LEN(E32)=0,1,0)+IF(LEN(E34)=0,1,0) -> 0 | C89: conteo | E89: Calculado | F89: Debe ser 0
A90: Inputs sin fecha válida (ausente o escrita como texto en vez de serial de fecha) | B90: =IF(OR(LEN(D7)=0,NOT(ISNUMBER(D7))),1,0)+IF(OR(LEN(D8)=0,NOT(ISNUMBER(D8))),1,0)+IF(OR(LEN(D30)=0,NOT(ISNUMBER(D30))),1,0)+IF(OR(LEN(D31)=0,NOT(ISNUMBER(D31))),1,0)+IF(OR(LEN(D32)=0,NOT(ISNUMBER(D32))),1,0)+IF(OR(LEN(D34)=0,NOT(ISNUMBER(D34))),1,0) -> 0 | C90: conteo | E90: Calculado | F90: Debe ser 0. Una fecha escrita como texto (p.ej. "2026-08") cuenta como inválida
A91: Estado de procedencia | B91: =IF(AND(B89=0,B90=0,B92=0),"PASS","FAIL") -> FAIL | C91: estado | E91: Calculado
A92: Inputs de cotización diaria desfasados (más de 5 días entre sí) o paquete entero obsoleto (más de 10 días contra HOY() al recalcular) | B92: =IF(D7<MAX(D7,D30,D32,D34)-5,1,0)+IF(D30<MAX(D7,D30,D32,D34)-5,1,0)+IF(D34<MAX(D7,D30,D32,D34)-5,1,0)+IF(MAX(D7,D30,D32,D34)<TODAY()-10,1,0) -> 1 | C92: conteo | E92: Calculado | F92: Debe ser 0. Cubre precio (D7), Rf (D30), beta (D32) y Kd (D34) entre sí, y la frescura ABSOLUTA contra HOY(): el libro caduca solo a los 10 días — es diseño, no defecto (patrón Apple post-refutación). Excluye a propósito la ERP (D31, serie anual de Damodaran) y el conteo de acciones (D8, del 10-Q): observaciones de baja frecuencia, desfase declarado en L2
A94: 7. LIMITACIONES, HALLAZGOS Y CABLEADO PENDIENTE
A95: H1 — El puente de deuda del DCF (Valuation!G13 vía Historical!B19) usa el tag combinado de deuda (43,941) + other short-term borrowings (56) y OMITE los loans and notes payable del balance (1,551): subestima la deuda bruta en 1,495 (cuantificado en B25). Esta hoja NO corrige Valuation: lo expone, y el check 47 lo mecaniza.
A96: H2 — Los activos líquidos del DCF (Valuation!G12 vía Historical!B18) son SOLO caja (10,270) y omiten las inversiones de corto plazo (3,602) y los valores negociables (1,934) = 5,536 (cuantificado en B27; exactamente BS_Hist!F7+F8). Check 48. Nota: incluir los 5,536 de líquidos y los 1,495 de deuda elevaría el equity value neto en ~4,041 (+0.9% del equity), direccionalmente favorable al DCF.
A97: H3 — Valuation!G19 tiene el precio en duro (USD 82.45, as-of 2026-07-15, hoy desfasado ~1 mes; la deriva real vs B7 es +6.0%) y Historical!B20 el conteo de acciones del 10-K FY2025. Para refrescar el DCF bastaría apuntar Valuation!G19 a B7 y Historical!B20 a B8; NO se hizo para no mover outputs ya gateados.
A98: H4 — El WACC de esta hoja (B45, 5.88%, inputs fechados) queda 1.62pp POR DEBAJO del WACC del escenario Base del DCF (7.5%). Un WACC de 5.88% con TGR 2.5% subiría el DCF sustancialmente: el escenario Base del modelo es conservador contra el mercado de hoy. Se deja como contraste (cablearlo rompería el diseño Base/Bull/Bear).
A99: L1 — La beta es de proveedor único (stockanalysis.com, 0.34): los cross-checks intentados (investing.com, WSJ, Yahoo quoteSummary) estuvieron inaccesibles desde esta sesión. Una beta calculada con retornos propios sería reproducible; el paquete local no trae la serie de precios para hacerlo.
A100: L2 — La ERP es la implícita de Damodaran al 2026-01-01, no al 2026-08-13. Es la observación citable más reciente de esa serie; usarla con un Rf de agosto mezcla fechas y está declarado a propósito (igual que en el resto de la flota USD de esta corrida).
A101: L3 — El costo de deuda es un benchmark de índice Single-A (BAMLC0A3CAEY), no una curva propia de KO. El memo B35 (rating A+/A1 divulgado en el propio 10-K) es el amarre del emisor a la elección del índice.
A102: L4 — El EV mezcla precio del 2026-08-13 con balance del 2025-12-31 (el balance más reciente DEL MODELO, como pide el alcance). El bloque 5 muestra el mismo EV con el balance del 2026-07-03 para dimensionar el desfase (−2,514).
A103: L5 — EBITDA (B53) no es una métrica GAAP: es EBIT + D&A del CF, construcción del analista. L6 — El FCF FY2025A está deprimido por working capital (ver B58): los yields sobre FCF corriente subestiman la generación normalizada.
A105: 8. ANCLAS DE VINTAGE DISTINTO — 10-Q Q2 FY2026 (accn 0001628280-26-050503, radicado 2026-07-29), balance condensado, columna comparativa "December 31, 2025"
A106: Efectivo e inversiones al 2025-12-31 según el 10-Q Q2 FY2026 (columna comparativa) | B106: 15806 | C106: USD m | D106: 46022 | E106: 10-Q Q2 FY2026 (accn 0001628280-26-050503), balance condensado, columna "December 31, 2025": 10,270 + 3,602 + 1,934 | F106: Constante tecleada del filing, NO fórmula contra BS_Hist: mismo período que el balance FY2025A del modelo pero publicada en un documento distinto (vintage independiente). Los checks 45 y 46 exigen tie EXACTO contra esta ancla
A107: Deuda bruta al 2025-12-31 según el 10-Q Q2 FY2026 (columna comparativa) | B107: 45492 | C107: USD m | D107: 46022 | E107: 10-Q Q2 FY2026 (accn 0001628280-26-050503), balance condensado, columna "December 31, 2025": 1,551 + 1,822 + 42,119 | F107: Constante tecleada del filing. Los checks 45 y 47 exigen tie EXACTO; incluye loans and notes payable, porción corriente y deuda de largo plazo

Sheet Claude Code Log
A1: Turn # | B1: Date | C1: User Request | D1: Action Taken | E1: Details | F1: Outcome
A2: 1 | B2: 46324.359 | C2: Prepare a public model copy | D2: Remove local paths and private build references; preserve financial formulas and inputs | E2: Agent run with MOG as the tool, checked by guard v1. The guard measured every sheet before and after the run. Changed: Change_Log: 1 cell written, at B9; Gate_9of10: 3 cells written, at E12, B24, B25; Sources_Audited: 6 cells written, at D4, D5, D6, D7, D8, D9. Agent: OpenFinmods export | F2: Compare against source and review public copy
