Workbook

Sheet EEFF
A1: Global Bank Corporation y Subsidiarias
A2: Estados Financieros Auditados FY21-FY25
A3: en B/. sin escala
A5: Años | B5: FY21A | C5: FY22A | D5: FY23A | E5: FY24A | F5: FY25A | G5: FY26E | H5: FY27E | I5: FY28E | J5: FY29E | K5: FY30E
A6: Estado consolidado de ganancia o pérdida
A7: Ingresos por intereses | B7: 436095180 | C7: 419112916 | D7: 454333887 | E7: 503666534 | F7: 523500468
A8: Gasto por intereses | B8: -263333029 | C8: -238053406 | D8: -281836291 | E8: -350182264 | F8: -366248027
A9: Ingresos neto por intereses | B9: 172762151 | C9: 181059510 | D9: 172497596 | E9: 153484270 | F9: 157252441
A10: Comisiones ganadas | B10: 48561754 | C10: 57798314 | D10: 66344055 | E10: 69992300 | F10: 70656110
A11: Gastos por comisiones | B11: -13491941 | C11: -19374865 | D11: -22088949 | E11: -24919428 | F11: -26262774
A12: Ingresos neto por comisiones | B12: 35069813 | C12: 38423449 | D12: 44255106 | E12: 45072872 | F12: 44393336
A13: Ingresos neto por intereses y comisiones, antes de provisión | B13: 207831964 | C13: 219482959 | D13: 216752702 | E13: 198557142 | F13: 201645777
A14: Provisión para préstamos incobrables | B14: 83497811 | C14: 59032479 | D14: 48957742 | E14: 34695854 | F14: 28431911
A15: Reversión de provisión riesgo país | B15: 1206330 | C15: -905789 | D15: 363938 | E15: -326333 | F15: -613051
A16: Reversión de provisión para inversiones | B16: 500143 | C16: 2897059 | D16: 474038 | E16: -60659 | F16: -198747
A17: Total de provisiones | B17: 85204284 | C17: 61023749 | D17: 49795718 | E17: 34308862 | F17: 27620113
A18: Ingresos neto por intereses y comisiones, después de provisión | B18: 122627680 | C18: 158459210 | D18: 166956984 | E18: 164248280 | F18: 174025664
... A33: Ganancia del año | B33: 26593150 | C33: 37263494 | D33: 47505926 | E33: 47832787 | F33: 48262456
A35: Años | B35: FY21A | C35: FY22A | D35: FY23A | E35: FY24A | F35: FY25A | G35: FY26E | H35: FY27E | I35: FY28E | J35: FY29E | K35: FY30E
A36: Estado consolidado de situación financiera
A37: Efectivo y depósitos en banco | B37: 508316487 | C37: 422163231 | D37: 354965856 | E37: 378198724 | F37: 433699566
A38: Valores comprados bajo acuerdos de reventa | B38: 306301 | C38: 285200 | D38: 3547807 | E38: 4956931 | F38: 4997637
A39: Inversiones en valores, neto | B39: 1110163904 | C39: 1079204941 | D39: 1053410069 | E39: 1049326162 | F39: 1136648533
A40: Préstamos, neto | B40: 6007976619 | C40: 6138222161 | D40: 6212554475 | E40: 6315709567 | F40: 6141543608
A41: Propiedades, mobiliario, equipo y mejoras | B41: 195030353 | C41: 197759650 | D41: 190418187 | E41: 191401031 | F41: 192001647
A42: Activos por derechos de uso | B42: 19425507 | C42: 15584822 | D42: 13301035 | E42: 11291589 | F42: 9660940
A43: Activos varios | B43: 482324722 | C43: 547376430 | D43: 584781470 | E43: 569398628 | F43: 584449645
A44: Total de activos | B44: 8323543893 | C44: 8400596435 | D44: 8412978899 | E44: 8520282632 | F44: 8503001576
A45: Depósitos de clientes | B45: 5189459231 | C45: 5178659636 | D45: 5205576287 | E45: 5264634266 | F45: 5715472860
A46: Depósitos de bancos | B46: 44910134 | C46: 64413383 | D46: 82919955 | E46: 80815921 | F46: 16750000
A47: Intereses acumulados por pagar | B47: 40781723 | C47: 32169806 | D47: 33051550 | E47: 36197140 | F47: 40586551
A48: Total de depósitos | B48: 5275151088 | C48: 5275242825 | D48: 5321547792 | E48: 5381647327 | F48: 5772809411
... A52: Bonos corporativos | B52: 1055663563 | C52: 439235300 | D52: 388450729 | E52: 374440557 | F52: 374069381
A53: Bonos subordinados | B53: 7833557
A54: Bonos perpetuos | B54: 160763868 | C54: 177495857 | D54: 177965873 | E54: 178016538 | F54: 177320865
A55: Intereses acumulados por pagar | B55: 14036040 | C55: 13211416 | D55: 25606793 | E55: 25872345 | F55: 23085224
A56: Total de financiamientos | B56: 2121472574 | C56: 2228809260 | D56: 2244910728 | E56: 2270922588 | F56: 1844742611
A57: Pasivos por arrendamientos | B57: 20847797 | C57: 17277420 | D57: 15302729 | E57: 12991713 | F57: 11539789
A58: Pasivos varios | B58: 116353854 | C58: 119112591 | D58: 119464406 | E58: 123345219 | F58: 105129335
A59: Total de pasivos | B59: 7533825313 | C59: 7640442096 | D59: 7701225655 | E59: 7788906847 | F59: 7734221146
A60: Acciones comunes | B60: 270202657 | C60: 270202657 | D60: 270202657 | E60: 270202657 | F60: 274702657
A61: Capital pagado en exceso | B61: 1755574 | C61: 1974519 | D61: 2252695 | E61: 2247763 | F61: 2292335
A62: Reservas de capital | B62: 42382907 | C62: 43269167 | D62: 44175479 | E62: 45124877 | F62: 46137123
A63: Reservas regulatorias | B63: 99613232 | C63: 101983796 | D63: 104142557 | E63: 108133638 | F63: 112628772
A64: Reserva de valor razonable | B64: 3356143 | C64: -37694923 | D64: -37365976 | E64: -29751677 | F64: -17574839
A65: Cambios netos en instrumentos de cobertura | D65: 0 | E65: -69008 | F65: -2164703
A66: Utilidades no distribuidas | B66: 372408067 | C66: 380419123 | D66: 328345832 | E66: 335487535 | F66: 352759085
A67: Total de patrimonio del accionista | B67: 789718580 | C67: 760154339 | D67: 711753244 | E67: 731375785 | F67: 768780430
A68: Total de pasivos y patrimonio | B68: 8323543893 | C68: 8400596435 | D68: 8412978899 | E68: 8520282632 | F68: 8503001576
A70: Años | B70: FY21A | C70: FY22A | D70: FY23A | E70: FY24A | F70: FY25A | G70: FY26E | H70: FY27E | I70: FY28E | J70: FY29E | K70: FY30E
A71: Estado consolidado de flujos de efectivo
A72: Ganancia del año | B72: 26593150 | C72: 37263494 | D72: 47505926 | E72: 47832787 | F72: 48262456
A73: Depreciación y amortización | B73: 21305412 | C73: 20767901 | D73: 18258300 | E73: 17607972 | F73: 17639914
A74: Pérdida (ganancia) en venta de propiedad, mobiliario y equipo | B74: -5101 | C74: -178437 | D74: -667208 | E74: -308684 | F74: 211392
A75: Descartes de activo fijo | B75: 31927 | C75: 215502 | D75: 5296399 | E75: 1241711 | F75: 3354830
A76: Ganancia en venta de valores al valor razonable con cambios en ORI, neto | B76: -7527134 | C76: -1154420 | D76: -388602 | E76: -309926 | F76: -795290
A77: Pérdida (ganancia) en instrumentos al valor razonable con cambios en resultados, neto | B77: -202943 | C77: 680871 | D77: -60788 | E77: -2840346 | F77: 85947
A78: Provisión para pérdidas en préstamos | B78: 83497811 | C78: 59032479 | D78: 48957742 | E78: 34695854 | F78: 28431911
A79: Reversión de provisión para inversiones, neto | B79: 500143 | C79: 2897059 | D79: 474038 | E79: -60659 | F79: -198747
A80: Impuesto sobre la renta | B80: -8852593 | C80: -1581230 | D80: 3464904 | E80: 1167130 | F80: 1801744
A81: Ingresos neto por intereses | B81: -436095180 | C81: -419112916 | D81: -454333887 | E81: -503666534 | F81: -523500468
A82: Gastos de intereses | B82: 263333029 | C82: 238053406 | D82: 281836291 | E82: 350182264 | F82: 366248027
A83: Plan de acciones restringidas | B83: -243733 | C83: 218945 | D83: 278176 | E83: -4932 | F83: 44572
... A99: Compra de inversiones con cambios en resultados | B99: -27877749 | C99: -3470625 | D99: -27239077 | E99: -2701032 | F99: -27539340
A100: Ventas y redenciones de inversiones con cambios en resultados | C100: 0 | D100: 157944 | E100: 2506131 | F100: 29786790
A101: Compra de inversiones a costo amortizado | B101: -46980293 | C101: -36519100 | D101: -16311184 | E101: -4999950 | F101: -28574308
A102: Redenciones y amortizaciones de inversiones a costo amortizado | B102: 12697532 | C102: 16147228 | D102: 18866685 | E102: 26521562 | F102: 46934901
A103: Compra de propiedades, mobiliario y equipo | B103: -11948720 | C103: -19038187 | D103: -12386108 | E103: -16279740 | F103: -18621372
A104: Procedente de las ventas de propiedad, mobiliario y equipo | B104: 5101 | C104: 178437 | D104: 667208 | E104: 308684 | F104: -211392
A105: Flujos neto de efectivo (utilizado en) generado por las actividades de inversión | B105: -80714926 | C105: -32089343 | D105: 13988110 | E105: 3015490 | F105: -92685306
A106: Pagos efectuados por operaciones de acuerdos de recompra | C106: 0 | D106: -23655642 | E106: -70009751 | F106: -47610933
A107: Producto de valores vendidos bajo acuerdos de recompra | B107: 0 | C107: 93665393 | D107: 0 | E107: 47610933 | F107: 37321723
A108: Obligaciones recibidas con instituciones financieras | B108: 732853771 | C108: 1844685880 | D108: 1766870623 | E108: 2262358381 | F108: 1209969512
A109: Obligaciones pagadas con instituciones financieras | B109: -930857868 | C109: -1241689596 | D109: -1670398393 | E109: -2194963355 | F109: -1620006309
A110: Producto de la emisión de valores comerciales negociables | B110: 7850000 | C110: 16595000 | D110: 9545000 | E110: 2000000 | F110: 0
A111: Pagos por redención de valores comerciales negociables | B111: -24300000 | C111: -6850000 | D111: -26140000 | E111: 0 | F111: -2000000
A112: Producto de la emisión de bonos | B112: 23850000 | C112: 16601000 | D112: 600000 | E112: 64489000 | F112: 0
A113: Redenciones y recompra de bonos | B113: -82646050 | C113: -625806718 | D113: -51308097 | E113: -78347220 | F113: -1290375
A114: Dividendos pagados acciones comunes | B114: -20033073 | C114: -23664251 | D114: -95002266 | E114: -35336599 | F114: -25134617
A115: Aparte de capital | E115: 0 | F115: 4500000
A116: Pago de arrendamiento | B116: -3119419 | C116: -2860865 | D116: -1974691 | E116: -2311016 | F116: -1451924
A117: Impuesto complementario | B117: -490801 | C117: -540609 | D117: -511878 | E117: -700955 | F117: -348909
A118: Flujos neto de efectivo utilizado en las actividades de financiación | B118: -296893440 | C118: 70135234 | D118: -92973344 | E118: -5210582 | F118: -446051832
A119: Aumento neto en efectivo y equivalentes de efectivo | B119: -85261962 | C119: -58663745 | D119: -68355569 | E119: 7841819 | F119: 37568157
A120: Efectivo y equivalentes de efectivo al inicio del año | B120: 559251757 | C120: 473989795 | D120: 415326050 | E120: 346970481 | F120: 354812300
A121: Efectivo y equivalentes de efectivo al final del año | B121: 473989795 | C121: 415326050 | D121: 346970481 | E121: 354812300 | F121: 392380457

Sheet Supuestos
A1: Global Bank Corporation y Subsidiarias
A3: COLOR KEY: Input (azul) · Fórmula (negro) · Link inter-hoja (verde)
A4: Escenario (1=Base, 2=Bull, 3=Bear)
A5: Selector escenario | C5: 1 | M5: caso | N5: NOT_DISCLOSED | Q5: Input de escenario desde fuente citada o NOT_DISCLOSED.
A6: Escenario activo | C6: =CHOOSE($C$5,"Base","Bull","Bear") -> Base | M6: moneda del modelo | N6: NOT_DISCLOSED | Q6: Selector de caso activo C5: Base/Bull/Bear.
A8: Años | B8: FY21A | C8: FY22A | D8: FY23A | E8: FY24A | F8: FY25A | G8: FY26E | H8: FY27E | I8: FY28E | J8: FY29E | K8: FY30E | M8: Unidad | N8: Fuente / nota | Q8: Rationale
A10: A. INGRESO POR INTERESES — CRECIMIENTO (% YoY)
A11: Ingresos por intereses — driver activo | G11: =CHOOSE($C$5,G13,G14,G12) -> 0.0394 | H11: =CHOOSE($C$5,H13,H14,H12) -> 0.0394 | I11: =CHOOSE($C$5,I13,I14,I12) -> 0.0394 | J11: =CHOOSE($C$5,J13,J14,J12) -> 0.0394 | K11: =CHOOSE($C$5,K13,K14,K12) -> 0.0394 | M11: % | N11: driver_tree:interest_income_growth | Q11: Selector de caso activo C5: Base/Bull/Bear.
A12: Bear | G12: 0.0194 | H12: 0.0194 | I12: 0.0194 | J12: 0.0194 | K12: 0.0194 | M12: % | N12: driver_tree:interest_income_growth | Q12: Escenario driver citado; NOT_DISCLOSED si no hay fuente explícita.
A13: Base | G13: 0.0394 | H13: 0.0394 | I13: 0.0394 | J13: 0.0394 | K13: 0.0394 | M13: % | N13: driver_tree:interest_income_growth | Q13: Escenario driver citado; NOT_DISCLOSED si no hay fuente explícita.
A14: Bull | G14: 0.0594 | H14: 0.0594 | I14: 0.0594 | J14: 0.0594 | K14: 0.0594 | M14: % | N14: driver_tree:interest_income_growth | Q14: Escenario driver citado; NOT_DISCLOSED si no hay fuente explícita.
A15: Ingresos por intereses (hist, ref EEFF) | B15: =EEFF!B7 -> 436095180 | C15: =EEFF!C7 -> 419112916 | D15: =EEFF!D7 -> 454333887 | E15: =EEFF!E7 -> 503666534 | F15: =EEFF!F7 -> 523500468 | M15: moneda del modelo | N15: EEFF:Ingresos por intereses@row7 | Q15: Mirror histórico desde fuente citada.
A16: Ingresos por intereses YoY histórico (ref EEFF) | C16: =EEFF!C7/EEFF!B7-1 -> -0.038941646 | D16: =EEFF!D7/EEFF!C7-1 -> 0.08403695 | E16: =EEFF!E7/EEFF!D7-1 -> 0.10858236 | F16: =EEFF!F7/EEFF!E7-1 -> 0.039379098 | M16: % | N16: EEFF:Ingresos por intereses@row7 | Q16: Fórmula viva: año actual / año previo - 1.
A18: B. GASTO POR INTERESES (% de ingreso x int.)
A19: Gasto por intereses — driver activo | G19: =CHOOSE($C$5,G21,G22,G20) -> -0.6996 | H19: =CHOOSE($C$5,H21,H22,H20) -> -0.6996 | I19: =CHOOSE($C$5,I21,I22,I20) -> -0.6996 | J19: =CHOOSE($C$5,J21,J22,J20) -> -0.6996 | K19: =CHOOSE($C$5,K21,K22,K20) -> -0.6996 | M19: % | N19: driver_tree:interest_expense_ratio | Q19: Selector de caso activo C5: Base/Bull/Bear.
A20: Bear | G20: -0.6796 | H20: -0.6796 | I20: -0.6796 | J20: -0.6796 | K20: -0.6796 | M20: % | N20: driver_tree:interest_expense_ratio | Q20: Escenario driver citado; NOT_DISCLOSED si no hay fuente explícita.
A21: Base | G21: -0.6996 | H21: -0.6996 | I21: -0.6996 | J21: -0.6996 | K21: -0.6996 | M21: % | N21: driver_tree:interest_expense_ratio | Q21: Escenario driver citado; NOT_DISCLOSED si no hay fuente explícita.
A22: Bull | G22: -0.7196 | H22: -0.7196 | I22: -0.7196 | J22: -0.7196 | K22: -0.7196 | M22: % | N22: driver_tree:interest_expense_ratio | Q22: Escenario driver citado; NOT_DISCLOSED si no hay fuente explícita.
A23: Gasto por intereses ÷ ingresos (hist, ref EEFF) | B23: =EEFF!B8/EEFF!B7 -> -0.60384302 | C23: =EEFF!C8/EEFF!C7 -> -0.56799349 | D23: =EEFF!D8/EEFF!D7 -> -0.62032857 | E23: =EEFF!E8/EEFF!E7 -> -0.69526609 | F23: =EEFF!F8/EEFF!F7 -> -0.69961356 | M23: % | N23: EEFF:Gasto por intereses@row8; EEFF:Ingresos por intereses@row7 | Q23: Mirror histórico desde fuente citada.
A25: C. CARTERA DE PRÉSTAMOS (crecimiento % YoY)
A26: Préstamos, neto (hist, ref EEFF) | B26: =EEFF!B40 -> 6007976619 | C26: =EEFF!C40 -> 6138222161 | D26: =EEFF!D40 -> 6212554475 | E26: =EEFF!E40 -> 6315709567 | F26: =EEFF!F40 -> 6141543608 | M26: moneda del modelo | N26: EEFF:Préstamos, neto@row40 | Q26: Mirror histórico desde fuente citada.
A27: Préstamos, neto YoY histórico (ref EEFF) | C27: =EEFF!C40/EEFF!B40-1 -> 0.02167877 | D27: =EEFF!D40/EEFF!C40-1 -> 0.012109746 | E27: =EEFF!E40/EEFF!D40-1 -> 0.016604296 | F27: =EEFF!F40/EEFF!E40-1 -> -0.027576626 | M27: % | N27: EEFF:Préstamos, neto@row40 | Q27: Fórmula viva: año actual / año previo - 1.
A28: Crecimiento de préstamos netos (% YoY) — driver activo | G28: =CHOOSE($C$5,G30,G31,G29) -> 0.0057 | H28: =CHOOSE($C$5,H30,H31,H29) -> 0.0057 | I28: =CHOOSE($C$5,I30,I31,I29) -> 0.0057 | J28: =CHOOSE($C$5,J30,J31,J29) -> 0.0057 | K28: =CHOOSE($C$5,K30,K31,K29) -> 0.0057 | M28: % | N28: driver_tree:loan_growth; macro_assumptions:gdp_growth_nominal=0.04 | Q28: Selector de caso activo C5: Base/Bull/Bear.
A29: Bear | G29: 0 | H29: 0 | I29: 0 | J29: 0 | K29: 0 | M29: % | N29: driver_tree:loan_growth; macro_assumptions:gdp_growth_nominal=0.04 | Q29: Floor firmado: si base > PIB, bear = PIB; si base <= PIB, bear = 0%; sin tasa negativa.
A30: Base | G30: 0.0057 | H30: 0.0057 | I30: 0.0057 | J30: 0.0057 | K30: 0.0057 | M30: % | N30: driver_tree:loan_growth; macro_assumptions:gdp_growth_nominal=0.04 | Q30: Base = max(promedio histórico, 0%) para volumen de intermediación/cartera.
A31: Bull | G31: 0.0257 | H31: 0.0257 | I31: 0.0257 | J31: 0.0257 | K31: 0.0257 | M31: % | N31: driver_tree:loan_growth; macro_assumptions:gdp_growth_nominal=0.04 | Q31: Bull = base + spread declarado; sin tasa negativa.
A33: D. DEPÓSITOS DE CLIENTES (crecimiento % YoY)
A34: Depósitos de clientes (hist, ref EEFF) | B34: =EEFF!B45 -> 5189459231 | C34: =EEFF!C45 -> 5178659636 | D34: =EEFF!D45 -> 5205576287 | E34: =EEFF!E45 -> 5264634266 | F34: =EEFF!F45 -> 5715472860 | M34: moneda del modelo | N34: EEFF:Depósitos de clientes@row45 | Q34: Mirror histórico desde fuente citada.
A35: Depósitos de clientes YoY histórico (ref EEFF) | C35: =EEFF!C45/EEFF!B45-1 -> -0.0020810637 | D35: =EEFF!D45/EEFF!C45-1 -> 0.0051976096 | E35: =EEFF!E45/EEFF!D45-1 -> 0.011345138 | F35: =EEFF!F45/EEFF!E45-1 -> 0.085635311 | M35: % | N35: EEFF:Depósitos de clientes@row45 | Q35: Fórmula viva: año actual / año previo - 1.
A36: Crecimiento de depósitos de clientes (% YoY) — driver activo | G36: =CHOOSE($C$5,G38,G39,G37) -> 0.025 | H36: =CHOOSE($C$5,H38,H39,H37) -> 0.025 | I36: =CHOOSE($C$5,I38,I39,I37) -> 0.025 | J36: =CHOOSE($C$5,J38,J39,J37) -> 0.025 | K36: =CHOOSE($C$5,K38,K39,K37) -> 0.025 | M36: % | N36: driver_tree:deposit_growth; macro_assumptions:gdp_growth_nominal=0.04 | Q36: Selector de caso activo C5: Base/Bull/Bear.
A37: Bear | G37: 0 | H37: 0 | I37: 0 | J37: 0 | K37: 0 | M37: % | N37: driver_tree:deposit_growth; macro_assumptions:gdp_growth_nominal=0.04 | Q37: Floor firmado: si base > PIB, bear = PIB; si base <= PIB, bear = 0%; sin tasa negativa.
A38: Base | G38: 0.025 | H38: 0.025 | I38: 0.025 | J38: 0.025 | K38: 0.025 | M38: % | N38: driver_tree:deposit_growth; macro_assumptions:gdp_growth_nominal=0.04 | Q38: Base = max(promedio histórico, 0%) para volumen de intermediación/cartera.
A39: Bull | G39: 0.045 | H39: 0.045 | I39: 0.045 | J39: 0.045 | K39: 0.045 | M39: % | N39: driver_tree:deposit_growth; macro_assumptions:gdp_growth_nominal=0.04 | Q39: Bull = base + spread declarado; sin tasa negativa.
A41: E. PROVISIÓN CREDITICIA (tasa sobre préstamos)
A42: Provisión para préstamos incobrables (hist, ref EEFF) | B42: =EEFF!B14 -> 83497811 | C42: =EEFF!C14 -> 59032479 | D42: =EEFF!D14 -> 48957742 | E42: =EEFF!E14 -> 34695854 | F42: =EEFF!F14 -> 28431911 | M42: moneda del modelo | N42: EEFF:Provisión para préstamos incobrables@row14 | Q42: Mirror histórico desde fuente citada.
A43: Provisión / préstamos netos (hist, ref EEFF) | C43: =EEFF!C14/EEFF!B40 -> 0.0098256839 | D43: =EEFF!D14/EEFF!C40 -> 0.007975883 | E43: =EEFF!E14/EEFF!D40 -> 0.0055847967 | F43: =EEFF!F14/EEFF!E40 -> 0.0045017762 | M43: % | N43: EEFF:Provisión para préstamos incobrables@row14; EEFF:Préstamos, neto@row40 | Q43: Mirror histórico desde fuente citada.
A44: Tasa de provisión sobre préstamos BOP — driver activo | G44: =CHOOSE($C$5,G46,G47,G45) -> 0.0045 | H44: =CHOOSE($C$5,H46,H47,H45) -> 0.0045 | I44: =CHOOSE($C$5,I46,I47,I45) -> 0.0045 | J44: =CHOOSE($C$5,J46,J47,J45) -> 0.0045 | K44: =CHOOSE($C$5,K46,K47,K45) -> 0.0045 | M44: % | N44: driver_tree:credit_provision_rate | Q44: Selector de caso activo C5: Base/Bull/Bear.
A45: Bear | G45: 0.006 | H45: 0.006 | I45: 0.006 | J45: 0.006 | K45: 0.006 | M45: % | N45: driver_tree:credit_provision_rate | Q45: Escenario driver citado; NOT_DISCLOSED si no hay fuente explícita.
A46: Base | G46: 0.0045 | H46: 0.0045 | I46: 0.0045 | J46: 0.0045 | K46: 0.0045 | M46: % | N46: driver_tree:credit_provision_rate | Q46: Escenario driver citado; NOT_DISCLOSED si no hay fuente explícita.
A47: Bull | G47: 0.003 | H47: 0.003 | I47: 0.003 | J47: 0.003 | K47: 0.003 | M47: % | N47: driver_tree:credit_provision_rate | Q47: Escenario driver citado; NOT_DISCLOSED si no hay fuente explícita.
A49: F. COMISIONES GANADAS (crecimiento % YoY)
A50: Crecimiento de comisiones ganadas (% YoY) — driver activo | G50: =CHOOSE($C$5,G52,G53,G51) -> 0.0095 | H50: =CHOOSE($C$5,H52,H53,H51) -> 0.0095 | I50: =CHOOSE($C$5,I52,I53,I51) -> 0.0095 | J50: =CHOOSE($C$5,J52,J53,J51) -> 0.0095 | K50: =CHOOSE($C$5,K52,K53,K51) -> 0.0095 | M50: % | N50: driver_tree:fee_growth | Q50: Selector de caso activo C5: Base/Bull/Bear.
A51: Bear | G51: 0 | H51: 0 | I51: 0 | J51: 0 | K51: 0 | M51: % | N51: driver_tree:fee_growth | Q51: Escenario driver citado; NOT_DISCLOSED si no hay fuente explícita.
A52: Base | G52: 0.0095 | H52: 0.0095 | I52: 0.0095 | J52: 0.0095 | K52: 0.0095 | M52: % | N52: driver_tree:fee_growth | Q52: Escenario driver citado; NOT_DISCLOSED si no hay fuente explícita.
A53: Bull | G53: 0.0295 | H53: 0.0295 | I53: 0.0295 | J53: 0.0295 | K53: 0.0295 | M53: % | N53: driver_tree:fee_growth | Q53: Escenario driver citado; NOT_DISCLOSED si no hay fuente explícita.
A54: Comisiones ganadas (hist, ref EEFF) | B54: =EEFF!B10 -> 48561754 | C54: =EEFF!C10 -> 57798314 | D54: =EEFF!D10 -> 66344055 | E54: =EEFF!E10 -> 69992300 | F54: =EEFF!F10 -> 70656110 | M54: moneda del modelo | N54: EEFF:Comisiones ganadas@row10 | Q54: Mirror histórico desde fuente citada.
A55: Comisiones ganadas YoY histórico (ref EEFF) | C55: =EEFF!C10/EEFF!B10-1 -> 0.19020236 | D55: =EEFF!D10/EEFF!C10-1 -> 0.1478545 | E55: =EEFF!E10/EEFF!D10-1 -> 0.05498978 | F55: =EEFF!F10/EEFF!E10-1 -> 0.0094840432 | M55: % | N55: EEFF:Comisiones ganadas@row10 | Q55: Fórmula viva: año actual / año previo - 1.
A57: G. OTROS INGRESOS (crecimiento % YoY)
A58: Crecimiento de otros ingresos (% YoY) — driver activo | G58: =CHOOSE($C$5,G60,G61,G59) -> 0 | H58: =CHOOSE($C$5,H60,H61,H59) -> 0 | I58: =CHOOSE($C$5,I60,I61,I59) -> 0 | J58: =CHOOSE($C$5,J60,J61,J59) -> 0 | K58: =CHOOSE($C$5,K60,K61,K59) -> 0 | M58: % | N58: driver_tree:other_income_growth | Q58: Selector de caso activo C5: Base/Bull/Bear.
A59: Bear | G59: 0 | H59: 0 | I59: 0 | J59: 0 | K59: 0 | M59: % | N59: driver_tree:other_income_growth | Q59: Escenario driver citado; NOT_DISCLOSED si no hay fuente explícita.
A60: Base | G60: 0 | H60: 0 | I60: 0 | J60: 0 | K60: 0 | M60: % | N60: driver_tree:other_income_growth | Q60: Escenario driver citado; NOT_DISCLOSED si no hay fuente explícita.
A61: Bull | G61: 0.02 | H61: 0.02 | I61: 0.02 | J61: 0.02 | K61: 0.02 | M61: % | N61: driver_tree:other_income_growth | Q61: Escenario driver citado; NOT_DISCLOSED si no hay fuente explícita.
A62: Otros ingresos (hist, ref EEFF) | B62: =EEFF!B19 -> 22758298 | C62: =EEFF!C19 -> 13838072 | D62: =EEFF!D19 -> 22011709 | E62: =EEFF!E19 -> 30401234 | F62: =EEFF!F19 -> 21055991 | M62: moneda del modelo | N62: EEFF:Otros ingresos@row19 | Q62: Mirror histórico desde fuente citada.
A63: Otros ingresos YoY histórico (ref EEFF) | C63: =EEFF!C19/EEFF!B19-1 -> -0.39195488 | D63: =EEFF!D19/EEFF!C19-1 -> 0.59066299 | E63: =EEFF!E19/EEFF!D19-1 -> 0.38113919 | F63: =EEFF!F19/EEFF!E19-1 -> -0.30739683 | M63: % | N63: EEFF:Otros ingresos@row19 | Q63: Fórmula viva: año actual / año previo - 1.
A65: H. GASTOS OPERATIVOS (crecimiento % YoY)
A66: Crecimiento de gastos operativos (% YoY) — driver activo | G66: =CHOOSE($C$5,G68,G69,G67) -> -0.0043 | H66: =CHOOSE($C$5,H68,H69,H67) -> -0.0043 | I66: =CHOOSE($C$5,I68,I69,I67) -> -0.0043 | J66: =CHOOSE($C$5,J68,J69,J67) -> -0.0043 | K66: =CHOOSE($C$5,K68,K69,K67) -> -0.0043 | M66: % | N66: driver_tree:operating_expense_growth | Q66: Selector de caso activo C5: Base/Bull/Bear.
A67: Bear | G67: 0.0057 | H67: 0.0057 | I67: 0.0057 | J67: 0.0057 | K67: 0.0057 | M67: % | N67: driver_tree:operating_expense_growth | Q67: Escenario driver citado; NOT_DISCLOSED si no hay fuente explícita.
A68: Base | G68: -0.0043 | H68: -0.0043 | I68: -0.0043 | J68: -0.0043 | K68: -0.0043 | M68: % | N68: driver_tree:operating_expense_growth | Q68: Escenario driver citado; NOT_DISCLOSED si no hay fuente explícita.
A69: Bull | G69: -0.0143 | H69: -0.0143 | I69: -0.0143 | J69: -0.0143 | K69: -0.0143 | M69: % | N69: driver_tree:operating_expense_growth | Q69: Escenario driver citado; NOT_DISCLOSED si no hay fuente explícita.
A70: Total de otros gastos (hist, ref EEFF) | B70: =EEFF!B28 -> 127645421 | C70: =EEFF!C28 -> 136615018 | D70: =EEFF!D28 -> 137997863 | E70: =EEFF!E28 -> 145649597 | F70: =EEFF!F28 -> 145017455 | M70: moneda del modelo | N70: EEFF:Total de otros gastos@row28 | Q70: Mirror histórico desde fuente citada.
A71: Total de otros gastos YoY histórico (ref EEFF) | C71: =EEFF!C28/EEFF!B28-1 -> 0.070269634 | D71: =EEFF!D28/EEFF!C28-1 -> 0.010122203 | E71: =EEFF!E28/EEFF!D28-1 -> 0.055448206 | F71: =EEFF!F28/EEFF!E28-1 -> -0.0043401562 | M71: % | N71: EEFF:Total de otros gastos@row28 | Q71: Fórmula viva: año actual / año previo - 1.

Sheet Notas_EEFF
A1: Global Bank Corporation y Subsidiarias
A2: Notas a los Estados Financieros
A3: Fuente: informes auditados vía OCR Mistral (verbatim).
A5: Año | B5: Documento fuente | C5: Página OCR | D5: Tabla OCR / sección | E5: Nota # | F5: Título original de la nota | G5: Categoría modelable | H5: Line item EEFF | I5: Sub-line item / detalle | J5: Texto original / disclosure | K5: Monto reportado | L5: Moneda | M5: Unidad / escala | N5: Fecha / venc. / tasa / plazo | O5: Contraparte / contrato / instrumento | P5: Impacto en Supuestos | Q5: Impacto en ModeloFinanciero | R5: Link a celda EEFF | S5: Comentario de extracción | T5: Status
A6: 2021 | B6: INA_GLOBAN_2021_0.pdf | C6: page-104 | D6: markdown.md | E6: 3 | F6: 3. Base de preparación | G6: Políticas contables | J6: ### 3.1 Estado de cumplimiento | T6: OK
A7: 2021 | B7: INA_GLOBAN_2021_0.pdf | C7: page-104 | D7: markdown.md | E7: 3 | F7: 3. Base de preparación | G7: Políticas contables | J7: Los estados financieros consolidados han sido preparados de conformidad con las Normas Internacionales de Información Financiera (NIIF's), emitidas por IASB. | T7: OK
A8: 2021 | B8: INA_GLOBAN_2021_0.pdf | C8: page-104 | D8: markdown.md | E8: 3 | F8: 3. Base de preparación | G8: Políticas contables | J8: - 15 - | T8: OK
A9: 2021 | B9: INA_GLOBAN_2021_0.pdf | C9: page-105 | D9: markdown.md | E9: 3 | F9: 3. Base de preparación | G9: Políticas contables | J9: ## 3.2 Base de preparación | T9: OK
A10: 2021 | B10: INA_GLOBAN_2021_0.pdf | C10: page-105 | D10: markdown.md | E10: 3 | F10: 3. Base de preparación | G10: Políticas contables | J10: Los estados financieros consolidados han sido preparados bajo la base del costo histórico, excepto por las inversiones al valor razonable con cambios en resultados; las inversiones al valor razonable con cambios en otros resultados integrales, los activos o pasivos con coberturas de valor razonable y los instrumentos derivados los cuales se presentan a su valor razonable. | T10: OK
A11: 2021 | B11: INA_GLOBAN_2021_0.pdf | C11: page-105 | D11: markdown.md | E11: 3 | F11: 3. Base de preparación | G11: Políticas contables | J11: El costo histórico generalmente se basa en el valor razonable de la contraprestación entregada a cambio de bienes y servicios. | T11: OK
A12: 2021 | B12: INA_GLOBAN_2021_0.pdf | C12: page-105 | D12: markdown.md | E12: 3 | F12: 3. Base de preparación | G12: Políticas contables | J12: Valor razonable es el precio que se recibiría por vender un activo o pagar para transferir un pasivo en una transacción ordenada entre participantes del mercado en la fecha de valoración, independientemente de si ese precio es observable directamente o estimado utilizando otra técnica de valoración directa. Al estimar el valor razonable de un activo o un pasivo, se tiene en cuenta las características del activo o pasivo si los participantes del mercado toman en cuenta esas características a la hora de fijar el precio del activo o pasivo a la fecha de medición. El valor razonable a efectos de valoración y/o revelación en los estados financieros consolidados se determina de la forma previamente dicha, a excepción de las transacciones de pagos basados en acciones que se encuentran dentro del alcance de la NIIF 2, las operaciones de leasing que están dentro del alcance de la NIIF 16, y mediciones que tienen algunas similitudes con valor razonable, pero que no son valor razonable, tales como el valor neto realizable de la NIC 2 o el valor en uso de la NIC 36. | T12: OK
A13: 2021 | B13: INA_GLOBAN_2021_0.pdf | C13: page-105 | D13: markdown.md | E13: 3 | F13: 3. Base de preparación | G13: Políticas contables | J13: Los estados financieros consolidados han sido preparados por la Administración asumiendo que el Banco continuará operando como un negocio en marcha. El impacto COVID-19 sobre las operaciones del Banco se describen en la Nota 34 de los estados financieros consolidados. | T13: OK
A14: 2021 | B14: INA_GLOBAN_2021_0.pdf | C14: page-105 | D14: markdown.md | E14: 3 | F14: 3. Base de preparación | G14: Políticas contables | J14: ## 3.3 Base de consolidación | T14: OK
A15: 2021 | B15: INA_GLOBAN_2021_0.pdf | C15: page-105 | D15: markdown.md | E15: 3 | F15: 3. Base de preparación | G15: Políticas contables | J15: Los estados financieros consolidados incluyen los del Banco y sus subsidiarias en las que tiene control. El control se obtiene cuando se cumplen todos los criterios a continuación: | T15: OK
A16: 2021 | B16: INA_GLOBAN_2021_0.pdf | C16: page-105 | D16: markdown.md | E16: 3 | F16: 3. Base de preparación | G16: Políticas contables | J16: - Tiene poder sobre la inversión; - Está expuesto, o tiene los derechos, a los rendimientos variables derivados de su participación con dicha entidad, y - Tiene la capacidad de afectar tales rendimientos a través de su poder sobre la entidad en la que invierte. | T16: OK
A17: 2021 | B17: INA_GLOBAN_2021_0.pdf | C17: page-105 | D17: markdown.md | E17: 3 | F17: 3. Base de preparación | G17: Políticas contables | J17: El Banco reevalúa si controla una entidad si los hechos y circunstancias indican que hay cambios en uno o más de los tres elementos de control que se listaron anteriormente. | T17: OK
... A346: 2021 | B346: INA_GLOBAN_2021_0.pdf | C346: page-135 | D346: markdown.md | E346: 4 | F346: 4. Administración de riesgos financieros | G346: Riesgo financiero | J346: ## Depósitos a plazo colocados en bancos | T346: OK
A347: 2021 | B347: INA_GLOBAN_2021_0.pdf | C347: page-135 | D347: markdown.md | E347: 4 | F347: 4. Administración de riesgos financieros | G347: Riesgo financiero | J347: Al 30 de junio de 2021, se mantiene depósitos a plazo en bancos por B/.292,938,297 (2020: B/.312,958,879). Los depósitos a plazo en bancos son mantenidos en instituciones financieras locales y extranjeras. Estas instituciones cuentan con calificaciones locales y/o internacionales, en su mayoría con grado de inversión internacional de al menos BBB- según Fitch Ratings o Standard and Poors, o Baa3 por Moody's. | K347: 292938297 | L347: B/. | T347: OK
A348: 2021 | B348: INA_GLOBAN_2021_0.pdf | C348: page-135 | D348: markdown.md | E348: 4 | F348: 4. Administración de riesgos financieros | G348: Riesgo financiero | J348: - 46 - | T348: OK
A349: 2021 | B349: INA_GLOBAN_2021_0.pdf | C349: page-136 | D349: markdown.md | E349: 4 | F349: 4. Administración de riesgos financieros | G349: Riesgo financiero | J349: ## 4.2.2.4 Concentración del riesgo de crédito | T349: OK
A350: 2021 | B350: INA_GLOBAN_2021_0.pdf | C350: page-136 | D350: markdown.md | E350: 4 | F350: 4. Administración de riesgos financieros | G350: Riesgo financiero | J350: El Banco monitorea la concentración de riesgo de crédito por sector y ubicación geográfica. El análisis de la concentración de los riesgos de crédito a la fecha de los estados financieros consolidados es la siguiente: | T350: OK
A351: 2021 | B351: INA_GLOBAN_2021_0.pdf | C351: page-136 | D351: tbl-85.html | E351: 4 | F351: 4. Administración de riesgos financieros | G351: Riesgo financiero | J351: [tbl-85.html](tbl-85.html) | T351: OK
A352: 2021 | B352: INA_GLOBAN_2021_0.pdf | C352: page-136 | D352: markdown.md | E352: 4 | F352: 4. Administración de riesgos financieros | G352: Riesgo financiero | J352: En la concentración por sector, el rubro de otros préstamos corresponde a facilidades crediticias a entidades bancarias, cooperativas, compañías de seguros, empresas financieras, gobierno, organismos internacionales y organizaciones no gubernamentales. | T352: OK
A353: 2021 | B353: INA_GLOBAN_2021_0.pdf | C353: page-136 | D353: markdown.md | E353: 4 | F353: 4. Administración de riesgos financieros | G353: Riesgo financiero | J353: Las concentraciones geográficas de la cartera de préstamos están basadas, en la ubicación del deudor. En cuanto a la concentración geográfica para las inversiones está basada en el domicilio del emisor de la inversión. | T353: OK
A354: 2021 | B354: INA_GLOBAN_2021_0.pdf | C354: page-136 | D354: markdown.md | E354: 4 | F354: 4. Administración de riesgos financieros | G354: Riesgo financiero | J354: - 47 - | T354: OK
A355: 2021 | B355: INA_GLOBAN_2021_0.pdf | C355: page-137 | D355: markdown.md | E355: 4 | F355: 4. Administración de riesgos financieros | G355: Riesgo financiero | J355: ## 4.3 Riesgo de liquidez o financiamiento | T355: OK
A356: 2021 | B356: INA_GLOBAN_2021_0.pdf | C356: page-137 | D356: markdown.md | E356: 4 | F356: 4. Administración de riesgos financieros | G356: Riesgo financiero | J356: El riesgo de liquidez se define como el riesgo de que el Banco se encuentre dificultades para obtener los fondos para cumplir con sus compromisos u obligaciones a tiempo. | T356: OK
A357: 2021 | B357: INA_GLOBAN_2021_0.pdf | C357: page-137 | D357: markdown.md | E357: 4 | F357: 4. Administración de riesgos financieros | G357: Riesgo financiero | J357: La Regulación Bancaria en Panamá requiere que los bancos de licencia general mantengan en todo momento un saldo mínimo de activos líquidos, según definición en el Acuerdo No. 4-2008 de la Superintendencia de Bancos de Panamá, no inferior al 30% de sus depósitos, sin embargo, producto de las estrictas políticas de liquidez para la cobertura de sus operaciones pasivas, la liquidez del Banco en base a esta norma al 30 de junio de 2021 fue 49.33% (2020: 50.27%). | T357: OK
A358: 2021 | B358: INA_GLOBAN_2021_0.pdf | C358: page-137 | D358: markdown.md | E358: 4 | F358: 4. Administración de riesgos financieros | G358: Riesgo financiero | J358: El riesgo de liquidez ocasionado por el descalce de plazos entre activos y pasivos es medido utilizando el Gap de liquidez o calce financiero. En este análisis se realizan simulaciones y escenarios de "stress" basados en las dificultades que pudieran ocasionar una falta de liquidez, tales como: retiros inesperados de fondos aportados por acreedores o clientes, deterioro de la calidad de la cartera de préstamos, volatilidad de los recursos captados, etc. | T358: OK
A359: 2021 | B359: INA_GLOBAN_2021_0.pdf | C359: page-137 | D359: markdown.md | E359: 4 | F359: 4. Administración de riesgos financieros | G359: Riesgo financiero | J359: A continuación, se detallan los índices de liquidez legal correspondientes al margen de activos líquidos sobre los depósitos recibidos de clientes del Banco a la fecha de los estados financieros consolidados, como sigue: | T359: OK
... A397: 2022 | B397: INA_GLOBAN_2022_0.pdf | C397: page-151 | D397: tbl-96.html | E397: 6 | F397: 6. Saldos y transacciones con partes relacionadas | G397: Partes relacionadas | J397: [tbl-96.html](tbl-96.html) | T397: OK
A398: 2022 | B398: INA_GLOBAN_2022_0.pdf | C398: page-151 | D398: markdown.md | E398: 6 | F398: 6. Saldos y transacciones con partes relacionadas | G398: Partes relacionadas | J398: Al 30 de junio de 2022, los colaterales que garantizan los créditos a partes relacionadas sumaban B/.127,071,808 (2021: B/.114,125,430), los cuales corresponden a garantías inmuebles, muebles y títulos en valores. | K398: 127071808 | L398: B/. | T398: OK
A399: 2022 | B399: INA_GLOBAN_2022_0.pdf | C399: page-151 | D399: markdown.md | E399: 6 | F399: 6. Saldos y transacciones con partes relacionadas | G399: Partes relacionadas | J399: Al 30 de junio de 2022, no hay préstamos con partes relacionadas con indicios de deterioro. Al 30 de junio de 2022, los préstamos con partes relacionadas tienen fecha de vencimiento entre julio 2022 hasta abril 2052 y tasas de interés anual que oscilan entre $2.75\%$ y $7.25\%$ (2021: tienen vencimiento entre julio de 2021 hasta julio de 2051 y tasas de interés anual que oscilan entre $2.75\%$ y $8.00\%$). | K399: 2.75 | L399: B/. | T399: OK
A400: 2022 | B400: INA_GLOBAN_2022_0.pdf | C400: page-152 | D400: tbl-97.html | E400: 7 | F400: 7. Efectivo y equivalentes de efectivo | G400: Working capital | J400: [tbl-97.html](tbl-97.html) | T400: OK
A401: 2022 | B401: INA_GLOBAN_2022_0.pdf | C401: page-152 | D401: markdown.md | E401: 7 | F401: 7. Efectivo y equivalentes de efectivo | G401: Working capital | J401: Al 30 de junio de 2022, existían depósitos a plazo fijo con vencimientos originales mayor a 90 días por B/.2,430,414 (2021: B/.32,599,556). Además, existen depósitos a plazo fijo restringidos por B/.4,227,529 (2021: B/.1,482,735) que garantizan obligaciones financieras. | K401: 2430414 | L401: B/. | T401: OK
A402: 2022 | B402: INA_GLOBAN_2022_0.pdf | C402: page-152 | D402: markdown.md | E402: 8 | F402: 8. Valores comprados bajo acuerdos de reventa | G402: Ingresos | J402: Al 30 de junio de 2022, los valores comprados bajo acuerdos de reventa por B/.285,200 (2021: B/.306,301) con vencimiento en mayo y junio 2023 (2021: con vencimiento en septiembre 2021, mayo 2022 y junio 2022), están garantizados por acciones y bonos de empresas que cotizan en la Bolsa de Valores de Panamá. | K402: 285200 | L402: B/. | T402: OK
A403: 2022 | B403: INA_GLOBAN_2022_0.pdf | C403: page-152 | D403: markdown.md | E403: 9 | F403: 9. Inversiones en valores, neto | G403: Otros | J403: A continuación, el detalle de las inversiones en valores: | T403: OK
A404: 2022 | B404: INA_GLOBAN_2022_0.pdf | C404: page-152 | D404: tbl-98.html | E404: 9 | F404: 9. Inversiones en valores, neto | G404: Otros | J404: [tbl-98.html](tbl-98.html) | T404: OK
A405: 2022 | B405: INA_GLOBAN_2022_0.pdf | C405: page-152 | D405: markdown.md | E405: 9 | F405: 9. Inversiones en valores, neto | G405: Otros | J405: - 66 - | T405: OK
A406: 2022 | B406: INA_GLOBAN_2022_0.pdf | C406: page-153 | D406: markdown.md | E406: 9 | F406: 9. Inversiones en valores, neto | G406: Otros | J406: ## 9.1 Valores al valor razonable con cambios en otros resultados integrales | T406: OK
A407: 2022 | B407: INA_GLOBAN_2022_0.pdf | C407: page-153 | D407: tbl-99.html | E407: 9 | F407: 9. Inversiones en valores, neto | G407: Otros | J407: [tbl-99.html](tbl-99.html) | T407: OK
A408: 2022 | B408: INA_GLOBAN_2022_0.pdf | C408: page-153 | D408: markdown.md | E408: 9 | F408: 9. Inversiones en valores, neto | G408: Otros | J408: Las tasas de interés anual que devengaban las inversiones al valor razonable con cambios en otros resultados integrales oscilaban entre 1.00% y 9.375%. (2021: 1.00% y 9.38%). | T408: OK
A409: 2022 | B409: INA_GLOBAN_2022_0.pdf | C409: page-153 | D409: markdown.md | E409: 9 | F409: 9. Inversiones en valores, neto | G409: Otros | J409: Al 30 de junio de 2022, existen inversiones al valor razonable con cambios en otros resultados integrales por B/.109,470,267 (2021: B/.22,900,630), que garantizan obligaciones con instituciones financieras. (Véase Nota 16). En adición, al 30 de junio de 2022, existen inversiones al valor razonable con cambios en otros resultados integrales por B/.56,280,642 que garantizan acuerdos de recompra. (Véase Nota 15). | K409: 109470267 | L409: B/. | T409: OK
A410: 2022 | B410: INA_GLOBAN_2022_0.pdf | C410: page-153 | D410: markdown.md | E410: 9 | F410: 9. Inversiones en valores, neto | G410: Otros | J410: Al 30 de junio de 2022, el Banco realizó ventas y redenciones de inversiones por B/.438,213,712 (2021: B/.1,645,314,605) y como resultado se registró una ganancia de B/.1,154,420 (2021: B/.7,527,134), que se incluye en el estado consolidado de ganancia o pérdida. | K410: 438213712 | L410: B/. | T410: OK
A411: 2022 | B411: INA_GLOBAN_2022_0.pdf | C411: page-153 | D411: markdown.md | E411: 9 | F411: 9. Inversiones en valores, neto | G411: Otros | J411: - 67 - | T411: OK
A412: 2022 | B412: INA_GLOBAN_2022_0.pdf | C412: page-154 | D412: markdown.md | E412: 9 | F412: 9. Inversiones en valores, neto | G412: Otros | J412: ## 9.2 Valores al valor razonable con cambios en resultados | T412: OK
A413: 2022 | B413: INA_GLOBAN_2022_0.pdf | C413: page-154 | D413: markdown.md | E413: 9 | F413: 9. Inversiones en valores, neto | G413: Otros | J413: Los valores al valor razonable con cambios en resultados se presentan a continuación: | T413: OK
A414: 2022 | B414: INA_GLOBAN_2022_0.pdf | C414: page-154 | D414: tbl-100.html | E414: 9 | F414: 9. Inversiones en valores, neto | G414: Otros | J414: [tbl-100.html](tbl-100.html) | T414: OK
A415: 2022 | B415: INA_GLOBAN_2022_0.pdf | C415: page-154 | D415: markdown.md | E415: 9 | F415: 9. Inversiones en valores, neto | G415: Otros | J415: No hubo ventas de valores al valor razonable con cambios en resultados durante los años terminados en 2022 y 2021. | T415: OK
A416: 2022 | B416: INA_GLOBAN_2022_0.pdf | C416: page-154 | D416: markdown.md | E416: 9 | F416: 9. Inversiones en valores, neto | G416: Otros | J416: ## 9.3 Valores a costo amortizado | T416: OK
A417: 2022 | B417: INA_GLOBAN_2022_0.pdf | C417: page-154 | D417: tbl-101.html | E417: 9 | F417: 9. Inversiones en valores, neto | G417: Otros | J417: [tbl-101.html](tbl-101.html) | T417: OK
A418: 2022 | B418: INA_GLOBAN_2022_0.pdf | C418: page-154 | D418: markdown.md | E418: 9 | F418: 9. Inversiones en valores, neto | G418: Otros | J418: Al 30 de junio de 2022, la tasa de interés anual, que devengan los valores a costo amortizado oscila entre el 1.00% y 8.875% (2021: 2.252% y 8.875%). | T418: OK
A419: 2022 | B419: INA_GLOBAN_2022_0.pdf | C419: page-154 | D419: markdown.md | E419: 9 | F419: 9. Inversiones en valores, neto | G419: Otros | J419: Al 30 de junio de 2022, existen valores a costo amortizado por B/.19,793,200 (2021: B/.50,755,968), que garantizan obligaciones con instituciones financieras. (Véase Nota 16). En adición, al 30 de junio de 2022, existen inversiones a costo amortizado por B/.47,176,727 que garantizan acuerdos de recompra. (Véase Nota 15). | K419: 19793200 | L419: B/. | T419: OK
A420: 2022 | B420: INA_GLOBAN_2022_0.pdf | C420: page-154 | D420: markdown.md | E420: 9 | F420: 9. Inversiones en valores, neto | G420: Otros | J420: - 68 - | T420: OK
A421: 2022 | B421: INA_GLOBAN_2022_0.pdf | C421: page-155 | D421: tbl-102.html | E421: 10 | F421: 10. Préstamos, neto | G421: Deuda / bonos / préstamos / leases | J421: [tbl-102.html](tbl-102.html) | T421: OK
A422: 2022 | B422: INA_GLOBAN_2022_0.pdf | C422: page-155 | D422: markdown.md | E422: 10 | F422: 10. Préstamos, neto | G422: Deuda / bonos / préstamos / leases | J422: Al 30 de junio de 2022, la cartera de préstamos devenga intereses dentro de un rango de tasas de 0.75% hasta 25.99% (2021: 0.75% hasta 30%). | T422: OK
A423: 2022 | B423: INA_GLOBAN_2022_0.pdf | C423: page-155 | D423: markdown.md | E423: 10 | F423: 10. Préstamos, neto | G423: Deuda / bonos / préstamos / leases | J423: Al 30 de junio de 2022, existen préstamos que garantizan bonos corporativos por un total de B/.129,803,846 (2021: B/.131,118,018). (Véase Nota 18). | K423: 129803846 | L423: B/. | T423: OK
A424: 2022 | B424: INA_GLOBAN_2022_0.pdf | C424: page-155 | D424: markdown.md | E424: 10 | F424: 10. Préstamos, neto | G424: Deuda / bonos / préstamos / leases | J424: - 69 - | T424: OK
A425: 2022 | B425: INA_GLOBAN_2022_0.pdf | C425: page-156 | D425: markdown.md | E425: 10 | F425: 10. Préstamos, neto | G425: Deuda / bonos / préstamos / leases | J425: La clasificación por tipo de tasa de interés de la cartera crediticia se detalla a continuación: | T425: OK
A426: 2022 | B426: INA_GLOBAN_2022_0.pdf | C426: page-156 | D426: tbl-103.html | E426: 10 | F426: 10. Préstamos, neto | G426: Deuda / bonos / préstamos / leases | J426: [tbl-103.html](tbl-103.html) | T426: OK
A427: 2022 | B427: INA_GLOBAN_2022_0.pdf | C427: page-156 | D427: markdown.md | E427: 10 | F427: 10. Préstamos, neto | G427: Deuda / bonos / préstamos / leases | J427: ## Arrendamientos financieros | T427: OK
A428: 2022 | B428: INA_GLOBAN_2022_0.pdf | C428: page-156 | D428: markdown.md | E428: 10 | F428: 10. Préstamos, neto | G428: Deuda / bonos / préstamos / leases | J428: El saldo de los arrendamientos financieros neto y el perfil de vencimiento se resumen como sigue: | T428: OK
A429: 2022 | B429: INA_GLOBAN_2022_0.pdf | C429: page-156 | D429: tbl-104.html | E429: 10 | F429: 10. Préstamos, neto | G429: Deuda / bonos / préstamos / leases | J429: [tbl-104.html](tbl-104.html) | T429: OK
A430: 2022 | B430: INA_GLOBAN_2022_0.pdf | C430: page-156 | D430: markdown.md | E430: 10 | F430: 10. Préstamos, neto | G430: Deuda / bonos / préstamos / leases | J430: ## Préstamos renegociados | T430: OK
A431: 2022 | B431: INA_GLOBAN_2022_0.pdf | C431: page-156 | D431: markdown.md | E431: 10 | F431: 10. Préstamos, neto | G431: Deuda / bonos / préstamos / leases | J431: Las actividades de renegociación incluyen acuerdos de pago, planes de administración externa aprobados y modificación del plan de pagos. Las políticas y las prácticas de renegociación se basan en indicadores o criterios que, a juicio de la Administración, indican que el pago muy probablemente continuará. Estas políticas se encuentran en continua revisión. | T431: OK
A432: 2022 | B432: INA_GLOBAN_2022_0.pdf | C432: page-156 | D432: markdown.md | E432: 10 | F432: 10. Préstamos, neto | G432: Deuda / bonos / préstamos / leases | J432: Al 30 de junio de 2022, los préstamos renegociados que de otra forma estarían vencidos o deteriorados totalizan B/.100,364,155 (2021: B/.117,985,958). | K432: 100364155 | L432: B/. | T432: OK
A433: 2022 | B433: INA_GLOBAN_2022_0.pdf | C433: page-156 | D433: tbl-105.html | E433: 10 | F433: 10. Préstamos, neto | G433: Deuda / bonos / préstamos / leases | J433: [tbl-105.html](tbl-105.html) | T433: OK
A434: 2022 | B434: INA_GLOBAN_2022_0.pdf | C434: page-156 | D434: markdown.md | E434: 10 | F434: 10. Préstamos, neto | G434: Deuda / bonos / préstamos / leases | J434: En adición, al 30 de junio de 2022, un total de B/.278,591,051 (2021: B/.956,852,818) de préstamos categorizados como modificados según el Acuerdo No.2-2021 fueron renegociados en sus términos, modificando su plan de pago, tasas de interés, entre otros. | K434: 278591051 | L434: B/. | T434: OK
A435: 2022 | B435: INA_GLOBAN_2022_0.pdf | C435: page-156 | D435: markdown.md | E435: 10 | F435: 10. Préstamos, neto | G435: Deuda / bonos / préstamos / leases | J435: - 70 - | T435: OK
A436: 2022 | B436: INA_GLOBAN_2022_0.pdf | C436: page-157 | D436: tbl-106.html | E436: 11 | F436: 11. Propiedades, mobiliario, equipo y mejoras | G436: PP&E / capex / depreciación | J436: [tbl-106.html](tbl-106.html) | T436: OK
A437: 2022 | B437: INA_GLOBAN_2022_0.pdf | C437: page-157 | D437: markdown.md | E437: 11 | F437: 11. Propiedades, mobiliario, equipo y mejoras | G437: PP&E / capex / depreciación | J437: - 71 - | T437: OK
A438: 2022 | B438: INA_GLOBAN_2022_0.pdf | C438: page-158 | D438: markdown.md | E438: 12 | F438: 12. Activos por derecho de uso y pasivos por arrendamientos | G438: Deuda / bonos / préstamos / leases | J438: ### a) Activos por derecho de uso | T438: OK
A439: 2022 | B439: INA_GLOBAN_2022_0.pdf | C439: page-158 | D439: markdown.md | E439: 12 | F439: 12. Activos por derecho de uso y pasivos por arrendamientos | G439: Deuda / bonos / préstamos / leases | J439: Los activos por derecho de uso se presentan a continuación: | T439: OK
A440: 2022 | B440: INA_GLOBAN_2022_0.pdf | C440: page-158 | D440: tbl-107.html | E440: 12 | F440: 12. Activos por derecho de uso y pasivos por arrendamientos | G440: Deuda / bonos / préstamos / leases | J440: [tbl-107.html](tbl-107.html) | T440: OK
A441: 2022 | B441: INA_GLOBAN_2022_0.pdf | C441: page-158 | D441: markdown.md | E441: 12 | F441: 12. Activos por derecho de uso y pasivos por arrendamientos | G441: Deuda / bonos / préstamos / leases | J441: Montos reconocidos en el estado consolidado de ganancia o pérdida: | T441: OK
A442: 2022 | B442: INA_GLOBAN_2022_0.pdf | C442: page-158 | D442: tbl-108.html | E442: 12 | F442: 12. Activos por derecho de uso y pasivos por arrendamientos | G442: Deuda / bonos / préstamos / leases | J442: [tbl-108.html](tbl-108.html) | T442: OK
A443: 2022 | B443: INA_GLOBAN_2022_0.pdf | C443: page-158 | D443: markdown.md | E443: 12 | F443: 12. Activos por derecho de uso y pasivos por arrendamientos | G443: Deuda / bonos / préstamos / leases | J443: ### b) Pasivos por arrendamientos | T443: OK
A444: 2022 | B444: INA_GLOBAN_2022_0.pdf | C444: page-158 | D444: markdown.md | E444: 12 | F444: 12. Activos por derecho de uso y pasivos por arrendamientos | G444: Deuda / bonos / préstamos / leases | J444: El siguiente cuadro muestra los plazos de vencimiento de los compromisos contingentes por arrendamiento operacional bajo la norma NIIF 16. | T444: OK
A445: 2022 | B445: INA_GLOBAN_2022_0.pdf | C445: page-158 | D445: tbl-109.html | E445: 12 | F445: 12. Activos por derecho de uso y pasivos por arrendamientos | G445: Deuda / bonos / préstamos / leases | J445: [tbl-109.html](tbl-109.html) | T445: OK
A446: 2022 | B446: INA_GLOBAN_2022_0.pdf | C446: page-158 | D446: markdown.md | E446: 12 | F446: 12. Activos por derecho de uso y pasivos por arrendamientos | G446: Deuda / bonos / préstamos / leases | J446: El Banco no enfrenta un riesgo de liquidez significativo con respecto a sus pasivos por arrendamiento. Los pasivos por arrendamiento se mantienen conforme a la operación del Banco. | T446: OK
... A453: 2022 | B453: INA_GLOBAN_2022_0.pdf | C453: page-159 | D453: markdown.md | E453: 13 | F453: 13. Activos varios | G453: Otros | J453: ## (c) Propiedades de inversión | T453: OK
A454: 2022 | B454: INA_GLOBAN_2022_0.pdf | C454: page-159 | D454: markdown.md | E454: 13 | F454: 13. Activos varios | G454: Otros | J454: Al 30 de junio de 2022, las propiedades de inversión constan de inmueble para futuro desarrollo con un valor de B/.86,861,200 (2021: B/.66,861,200) según avalúo efectuado por Avalúos Inspecciones y Construcción, evaluador independiente del Banco con experiencia y capacidad realizando estas evaluaciones. El valor razonable se basa en la metodología de mercado en donde el precio de venta por metro cuadrado del terreno es el dato de entrada más relevante. El valor razonable ha sido clasificado en el nivel 3 de la jerarquía de valuación de la NIIF 13. | K454: 86861200 | L454: B/. | T454: OK
A455: 2022 | B455: INA_GLOBAN_2022_0.pdf | C455: page-159 | D455: markdown.md | E455: 13 | F455: 13. Activos varios | G455: Otros | J455: - 73 - | T455: OK
A456: 2022 | B456: INA_GLOBAN_2022_0.pdf | C456: page-160 | D456: tbl-112.html | E456: 13 | F456: 13. Activos varios | G456: Otros | J456: [tbl-112.html](tbl-112.html) | T456: OK
A457: 2022 | B457: INA_GLOBAN_2022_0.pdf | C457: page-160 | D457: markdown.md | E457: 13 | F457: 13. Activos varios | G457: Otros | J457: Con el fin de comprobar un deterioro en plusvalía u otros activos intangibles, se hace periódicamente una valuación de los diversos activos (contratos, carteras) o negocios adquiridos por el Banco que han generado dichas plusvalías o intangibles. El Banco utiliza principalmente el modelo de descuento de flujos futuros de los activos o negocios correspondientes o métodos alternos de valuación de negocios incluyendo múltiplos de utilidades o de patrimonio, dependiendo del caso. | T457: OK
A458: 2022 | B458: INA_GLOBAN_2022_0.pdf | C458: page-160 | D458: markdown.md | E458: 13 | F458: 13. Activos varios | G458: Otros | J458: Al 30 de junio de 2022 y 2021, no se reconocieron pérdidas por deterioro en plusvalía o intangibles. La valuación que se hizo mediante el método de descuento de los flujos futuros netos generados por los activos o negocios adquiridos indica que el valor presente de estos excede el monto de plusvalía o activos intangibles en libros. | T458: OK
A459: 2022 | B459: INA_GLOBAN_2022_0.pdf | C459: page-160 | D459: markdown.md | E459: 13 | F459: 13. Activos varios | G459: Otros | J459: Para llevar a cabo la valuación de los activos y negocios adquiridos se proyectaron los flujos netos esperados de los activos o negocios, por períodos de cinco años, e igualmente se define un crecimiento a perpetuidad o múltiplo de flujos al final del período de la proyección de flujos para estimar el flujo terminal. Las tasas de crecimiento en los activos o negocios fluctúan en base a la naturaleza de cada uno, mientras que la tasa de crecimiento perpetua está en 3.5%. | T459: OK
A460: 2022 | B460: INA_GLOBAN_2022_0.pdf | C460: page-160 | D460: markdown.md | E460: 13 | F460: 13. Activos varios | G460: Otros | J460: - Para determinar las tasas de crecimiento de los activos o negocios se utilizó como referencia el crecimiento, desempeño, y métricas históricas reales de los activos o negocios pertinentes, sus perspectivas futuras, el crecimiento macroeconómico anticipado del país el cual se encuentra entre 4% y 5% durante los cinco años de proyección. Los segmentos o negocios en evaluación, al igual que los planes de negocios del Banco y tasas de crecimiento esperadas en general, al igual para los negocios específicos en evaluación. | T460: OK
A461: 2022 | B461: INA_GLOBAN_2022_0.pdf | C461: page-160 | D461: markdown.md | E461: 13 | F461: 13. Activos varios | G461: Otros | J461: - Para calcular el valor presente de los flujos futuros y determinar el valor de los activos y negocios que están siendo evaluados se utilizó como tasa de descuento el costo de capital promedio estimado para los períodos de tiempo contemplados, cuando la unidad de negocios evaluada es el Banco; cuando se descuentan flujos de fondos activos o unidades con un perfil distinto al Banco, se utiliza el costo de capital aplicable a esa actividad en caso de diferir. El costo de capital está en función de las tasas de interés promedio a largo plazo de instrumentos AAA en dólares, de la prima por riesgo país, y de la prima de retorno para inversiones de capital aplicable. El costo de capital del Banco es de 11% aproximadamente. | T461: OK
A462: 2022 | B462: INA_GLOBAN_2022_0.pdf | C462: page-160 | D462: markdown.md | E462: 13 | F462: 13. Activos varios | G462: Otros | J462: - Los principales supuestos antes descritos, pueden cambiar a medida que las condiciones económicas y del mercado cambien. El Banco estima que los cambios razonablemente posibles bajo estos supuestos no afecten el importe recuperable de las unidades de negocio o disminuya por debajo del valor del importe en libros. | T462: OK
A463: 2022 | B463: INA_GLOBAN_2022_0.pdf | C463: page-160 | D463: markdown.md | E463: 13 | F463: 13. Activos varios | G463: Otros | J463: El gasto de la amortización se presenta en el estado consolidado de ganancia o pérdida en el rubro de depreciación y amortización. | T463: OK
A464: 2022 | B464: INA_GLOBAN_2022_0.pdf | C464: page-160 | D464: markdown.md | E464: 13 | F464: 13. Activos varios | G464: Otros | J464: - 74 - | T464: OK
A465: 2022 | B465: INA_GLOBAN_2022_0.pdf | C465: page-161 | D465: markdown.md | E465: 13 | F465: 13. Activos varios | G465: Otros | J465: # Global Bank Corporation y Subsidiarias | T465: OK
A466: 2022 | B466: INA_GLOBAN_2022_0.pdf | C466: page-161 | D466: markdown.md | E466: 13 | F466: 13. Activos varios | G466: Otros | J466: ## Notas a los estados financieros consolidados por el año terminado el 30 de junio de 2022 (En balboas) | T466: OK
... A475: 2022 | B475: INA_GLOBAN_2022_0.pdf | C475: page-162 | D475: tbl-115.html | E475: 14 | F475: 14. Depósitos de clientes | G475: Otros | J475: [tbl-115.html](tbl-115.html) | T475: OK
A476: 2022 | B476: INA_GLOBAN_2022_0.pdf | C476: page-162 | D476: markdown.md | E476: 15 | F476: 15. Valores vendidos bajo acuerdos de recompra | G476: Otros | J476: Al 30 de junio de 2022, se mantienen acuerdos de recompra por B/.93,665,393, garantizados por inversiones al valor razonable con cambios en otros resultados integrales por B/.56,280,642 y valores a costo amortizado por B/.47,176,727, a tasa de interés entre 1.00% y 4.17%, con vencimiento en agosto 2022, septiembre 2022 y junio 2023. | K476: 93665393 | L476: B/. | T476: OK
A477: 2022 | B477: INA_GLOBAN_2022_0.pdf | C477: page-162 | D477: markdown.md | E477: 15 | F477: 15. Valores vendidos bajo acuerdos de recompra | G477: Otros | J477: - 76 - | T477: OK
A478: 2022 | B478: INA_GLOBAN_2022_0.pdf | C478: page-163 | D478: markdown.md | E478: 15 | F478: 15. Valores vendidos bajo acuerdos de recompra | G478: Otros | J478: Los valores vendidos bajo acuerdos de recompra a costo amortizado se detallan a continuación: | T478: OK
A479: 2022 | B479: INA_GLOBAN_2022_0.pdf | C479: page-163 | D479: tbl-116.html | E479: 15 | F479: 15. Valores vendidos bajo acuerdos de recompra | G479: Otros | J479: [tbl-116.html](tbl-116.html) | T479: OK
A480: 2022 | B480: INA_GLOBAN_2022_0.pdf | C480: page-163 | D480: tbl-117.html | E480: 16 | F480: 16. Obligaciones con instituciones financieras | G480: Deuda / bonos / préstamos / leases | J480: [tbl-117.html](tbl-117.html) | T480: OK
...

Sheet ModeloFinanciero
A1: Global Bank Corporation y Subsidiarias
A2: Estados Financieros Auditados FY21-FY25
A3: en B/. sin escala
A5: Años | B5: FY21A | C5: FY22A | D5: FY23A | E5: FY24A | F5: FY25A | G5: FY26E | H5: FY27E | I5: FY28E | J5: FY29E | K5: FY30E
A6: Estado consolidado de ganancia o pérdida
A7: Ingresos por intereses | B7: =EEFF!B7 -> 436095180 | C7: =EEFF!C7 -> 419112916 | D7: =EEFF!D7 -> 454333887 | E7: =EEFF!E7 -> 503666534 | F7: =EEFF!F7 -> 523500468 | G7: =F7*(1+Supuestos!G11) -> 5.4412639e+08 | H7: =G7*(1+Supuestos!H11) -> 5.6556497e+08 | I7: =H7*(1+Supuestos!I11) -> 5.8784823e+08 | J7: =I7*(1+Supuestos!J11) -> 6.1100945e+08 | K7: =J7*(1+Supuestos!K11) -> 6.3508322e+08
A8: Gasto por intereses | B8: =EEFF!B8 -> -263333029 | C8: =EEFF!C8 -> -238053406 | D8: =EEFF!D8 -> -281836291 | E8: =EEFF!E8 -> -350182264 | F8: =EEFF!F8 -> -366248027 | G8: =G7*Supuestos!G19 -> -3.8067082e+08 | H8: =H7*Supuestos!H19 -> -3.9566925e+08 | I8: =I7*Supuestos!I19 -> -4.1125862e+08 | J8: =J7*Supuestos!J19 -> -4.2746221e+08 | K8: =K7*Supuestos!K19 -> -4.4430422e+08
A9: Ingresos neto por intereses | B9: =EEFF!B9 -> 172762151 | C9: =EEFF!C9 -> 181059510 | D9: =EEFF!D9 -> 172497596 | E9: =EEFF!E9 -> 153484270 | F9: =EEFF!F9 -> 157252441 | G9: =G7+G8 -> 1.6345557e+08 | H9: =H7+H8 -> 1.6989572e+08 | I9: =I7+I8 -> 1.7658961e+08 | J9: =J7+J8 -> 1.8354724e+08 | K9: =K7+K8 -> 1.90779e+08
A10: Comisiones ganadas | B10: =EEFF!B10 -> 48561754 | C10: =EEFF!C10 -> 57798314 | D10: =EEFF!D10 -> 66344055 | E10: =EEFF!E10 -> 69992300 | F10: =EEFF!F10 -> 70656110 | G10: =F10*(1+Supuestos!G50) -> 71327343 | H10: =G10*(1+Supuestos!H50) -> 72004953 | I10: =H10*(1+Supuestos!I50) -> 72689000 | J10: =I10*(1+Supuestos!J50) -> 73379545 | K10: =J10*(1+Supuestos!K50) -> 74076651
A11: Gastos por comisiones | B11: =EEFF!B11 -> -13491941 | C11: =EEFF!C11 -> -19374865 | D11: =EEFF!D11 -> -22088949 | E11: =EEFF!E11 -> -24919428 | F11: =EEFF!F11 -> -26262774 | G11: =F11 -> -26262774 | H11: =G11 -> -26262774 | I11: =H11 -> -26262774 | J11: =I11 -> -26262774 | K11: =J11 -> -26262774
A12: Ingresos neto por comisiones | B12: =EEFF!B12 -> 35069813 | C12: =EEFF!C12 -> 38423449 | D12: =EEFF!D12 -> 44255106 | E12: =EEFF!E12 -> 45072872 | F12: =EEFF!F12 -> 44393336 | G12: =G10+G11 -> 45064569 | H12: =H10+H11 -> 45742179 | I12: =I10+I11 -> 46426226 | J12: =J10+J11 -> 47116771 | K12: =K10+K11 -> 47813877
A13: Ingresos neto por intereses y comisiones, antes de provisión | B13: =EEFF!B13 -> 207831964 | C13: =EEFF!C13 -> 219482959 | D13: =EEFF!D13 -> 216752702 | E13: =EEFF!E13 -> 198557142 | F13: =EEFF!F13 -> 201645777 | G13: =G9+G12 -> 2.0852014e+08 | H13: =H9+H12 -> 2.1563789e+08 | I13: =I9+I12 -> 2.2301583e+08 | J13: =J9+J12 -> 2.3066401e+08 | K13: =K9+K12 -> 2.3859288e+08
A14: Provisión para préstamos incobrables | B14: =EEFF!B14 -> 83497811 | C14: =EEFF!C14 -> 59032479 | D14: =EEFF!D14 -> 48957742 | E14: =EEFF!E14 -> 34695854 | F14: =EEFF!F14 -> 28431911 | G14: =Supuestos!G44*F40 -> 27636946 | H14: =Supuestos!H44*G40 -> 27794477 | I14: =Supuestos!I44*H40 -> 27952905 | J14: =Supuestos!J44*I40 -> 28112237 | K14: =Supuestos!K44*J40 -> 28272477
A15: Reversión de provisión riesgo país | B15: =EEFF!B15 -> 1206330 | C15: =EEFF!C15 -> -905789 | D15: =EEFF!D15 -> 363938 | E15: =EEFF!E15 -> -326333 | F15: =EEFF!F15 -> -613051 | G15: =F15 -> -613051 | H15: =G15 -> -613051 | I15: =H15 -> -613051 | J15: =I15 -> -613051 | K15: =J15 -> -613051
A16: Reversión de provisión para inversiones | B16: =EEFF!B16 -> 500143 | C16: =EEFF!C16 -> 2897059 | D16: =EEFF!D16 -> 474038 | E16: =EEFF!E16 -> -60659 | F16: =EEFF!F16 -> -198747 | G16: =F16 -> -198747 | H16: =G16 -> -198747 | I16: =H16 -> -198747 | J16: =I16 -> -198747 | K16: =J16 -> -198747
A17: Total de provisiones | B17: =EEFF!B17 -> 85204284 | C17: =EEFF!C17 -> 61023749 | D17: =EEFF!D17 -> 49795718 | E17: =EEFF!E17 -> 34308862 | F17: =EEFF!F17 -> 27620113 | G17: =G14+G15+G16 -> 26825148 | H17: =H14+H15+H16 -> 26982679 | I17: =I14+I15+I16 -> 27141107 | J17: =J14+J15+J16 -> 27300439 | K17: =K14+K15+K16 -> 27460679
A18: Ingresos neto por intereses y comisiones, después de provisión | B18: =EEFF!B18 -> 122627680 | C18: =EEFF!C18 -> 158459210 | D18: =EEFF!D18 -> 166956984 | E18: =EEFF!E18 -> 164248280 | F18: =EEFF!F18 -> 174025664 | G18: =G13-G17 -> 1.8169499e+08 | H18: =H13-H17 -> 1.8865522e+08 | I18: =I13-I17 -> 1.9587473e+08 | J18: =J13-J17 -> 2.0336357e+08 | K18: =K13-K17 -> 2.111322e+08
A19: Otros ingresos | B19: =EEFF!B19 -> 22758298 | C19: =EEFF!C19 -> 13838072 | D19: =EEFF!D19 -> 22011709 | E19: =EEFF!E19 -> 30401234 | F19: =EEFF!F19 -> 21055991 | G19: =F19*(1+Supuestos!G58) -> 21055991 | H19: =G19*(1+Supuestos!H58) -> 21055991 | I19: =H19*(1+Supuestos!I58) -> 21055991 | J19: =I19*(1+Supuestos!J58) -> 21055991 | K19: =J19*(1+Supuestos!K58) -> 21055991
A20: Salarios y otras remuneraciones | B20: =EEFF!B20 -> 57113674 | C20: =EEFF!C20 -> 59798894 | D20: =EEFF!D20 -> 61331282 | E20: =EEFF!E20 -> 63916541 | F20: =EEFF!F20 -> 61774195 | G20: =F20*(1+Supuestos!G66) -> 61508566 | H20: =G20*(1+Supuestos!H66) -> 61244079 | I20: =H20*(1+Supuestos!I66) -> 60980730 | J20: =I20*(1+Supuestos!J66) -> 60718512 | K20: =J20*(1+Supuestos!K66) -> 60457423
A21: Honorarios profesionales | B21: =EEFF!B21 -> 7726797 | C21: =EEFF!C21 -> 9285792 | D21: =EEFF!D21 -> 10360389 | E21: =EEFF!E21 -> 10744135 | F21: =EEFF!F21 -> 10044980 | G21: =F21*(1+Supuestos!G66) -> 10001787 | H21: =G21*(1+Supuestos!H66) -> 9958778.9 | I21: =H21*(1+Supuestos!I66) -> 9915956.2 | J21: =I21*(1+Supuestos!J66) -> 9873317.5 | K21: =J21*(1+Supuestos!K66) -> 9830862.3
A22: Depreciación y amortización | B22: =EEFF!B22 -> 21305412 | C22: =EEFF!C22 -> 20767901 | D22: =EEFF!D22 -> 18258300 | E22: =EEFF!E22 -> 17607972 | F22: =EEFF!F22 -> 17639914 | G22: =F22*(1+Supuestos!G66) -> 17564062 | H22: =G22*(1+Supuestos!H66) -> 17488537 | I22: =H22*(1+Supuestos!I66) -> 17413336 | J22: =I22*(1+Supuestos!J66) -> 17338459 | K22: =J22*(1+Supuestos!K66) -> 17263903
A23: Publicidad y propaganda | B23: =EEFF!B23 -> 2263252 | C23: =EEFF!C23 -> 2575329 | D23: =EEFF!D23 -> 3117156 | E23: =EEFF!E23 -> 3474398 | F23: =EEFF!F23 -> 3701527 | G23: =F23*(1+Supuestos!G66) -> 3685610.4 | H23: =G23*(1+Supuestos!H66) -> 3669762.3 | I23: =H23*(1+Supuestos!I66) -> 3653982.3 | J23: =I23*(1+Supuestos!J66) -> 3638270.2 | K23: =J23*(1+Supuestos!K66) -> 3622625.6
A24: Mantenimiento y reparaciones | B24: =EEFF!B24 -> 9755794 | C24: =EEFF!C24 -> 10603499 | D24: =EEFF!D24 -> 11309827 | E24: =EEFF!E24 -> 11390367 | F24: =EEFF!F24 -> 11351516 | G24: =F24*(1+Supuestos!G66) -> 11302704 | H24: =G24*(1+Supuestos!H66) -> 11254103 | I24: =H24*(1+Supuestos!I66) -> 11205710 | J24: =I24*(1+Supuestos!J66) -> 11157526 | K24: =J24*(1+Supuestos!K66) -> 11109548
A25: Alquileres | B25: =EEFF!B25 -> 2537829 | C25: =EEFF!C25 -> 3306085 | D25: =EEFF!D25 -> 4015359 | E25: =EEFF!E25 -> 5569274 | F25: =EEFF!F25 -> 6446523 | G25: =F25*(1+Supuestos!G66) -> 6418803 | H25: =G25*(1+Supuestos!H66) -> 6391202.1 | I25: =H25*(1+Supuestos!I66) -> 6363719.9 | J25: =I25*(1+Supuestos!J66) -> 6336355.9 | K25: =J25*(1+Supuestos!K66) -> 6309109.6
A26: Impuestos varios | B26: =EEFF!B26 -> 5568403 | C26: =EEFF!C26 -> 6408887 | D26: =EEFF!D26 -> 6222827 | E26: =EEFF!E26 -> 6603103 | F26: =EEFF!F26 -> 8078593 | G26: =F26*(1+Supuestos!G66) -> 8043855.1 | H26: =G26*(1+Supuestos!H66) -> 8009266.5 | I26: =H26*(1+Supuestos!I66) -> 7974826.6 | J26: =I26*(1+Supuestos!J66) -> 7940534.9 | K26: =J26*(1+Supuestos!K66) -> 7906390.6
A27: Otros gastos | B27: =EEFF!B27 -> 21374260 | C27: =EEFF!C27 -> 23868631 | D27: =EEFF!D27 -> 23382723 | E27: =EEFF!E27 -> 26343807 | F27: =EEFF!F27 -> 25980207 | G27: =F27*(1+Supuestos!G66) -> 25868492 | H27: =G27*(1+Supuestos!H66) -> 25757258 | I27: =H27*(1+Supuestos!I66) -> 25646501 | J27: =I27*(1+Supuestos!J66) -> 25536221 | K27: =J27*(1+Supuestos!K66) -> 25426416
A28: Total de otros gastos | B28: =EEFF!B28 -> 127645421 | C28: =EEFF!C28 -> 136615018 | D28: =EEFF!D28 -> 137997863 | E28: =EEFF!E28 -> 145649597 | F28: =EEFF!F28 -> 145017455 | G28: =G20+G21+G22+G23+G24+G25+G26+G27 -> 1.4439388e+08 | H28: =H20+H21+H22+H23+H24+H25+H26+H27 -> 1.4377299e+08 | I28: =I20+I21+I22+I23+I24+I25+I26+I27 -> 1.4315476e+08 | J28: =J20+J21+J22+J23+J24+J25+J26+J27 -> 1.425392e+08 | K28: =K20+K21+K22+K23+K24+K25+K26+K27 -> 1.4192628e+08
A29: Ganancia antes del impuesto sobre la renta | B29: =EEFF!B29 -> 17740557 | C29: =EEFF!C29 -> 35682264 | D29: =EEFF!D29 -> 50970830 | E29: =EEFF!E29 -> 48999917 | F29: =EEFF!F29 -> 50064200 | G29: =G18+G19-G28 -> 58357098 | H29: =H18+H19-H28 -> 65938221 | I29: =I18+I19-I28 -> 73775954 | J29: =J18+J19-J28 -> 81880364 | K29: =K18+K19-K28 -> 90261910
A30: Impuesto sobre la renta - Corriente | B30: =EEFF!B30 -> 3895556 | C30: =EEFF!C30 -> 3667996 | D30: =EEFF!D30 -> 3825471 | E30: =EEFF!E30 -> 4298464 | F30: =EEFF!F30 -> 4236515 | G30: =F30 -> 4236515 | H30: =G30 -> 4236515 | I30: =H30 -> 4236515 | J30: =I30 -> 4236515 | K30: =J30 -> 4236515
A31: Impuesto sobre la renta - Diferido | B31: =EEFF!B31 -> -12748149 | C31: =EEFF!C31 -> -5249226 | D31: =EEFF!D31 -> -360567 | E31: =EEFF!E31 -> -3131334 | F31: =EEFF!F31 -> -2434771 | G31: =F31 -> -2434771 | H31: =G31 -> -2434771 | I31: =H31 -> -2434771 | J31: =I31 -> -2434771 | K31: =J31 -> -2434771
A32: Impuesto sobre la renta | B32: =EEFF!B32 -> -8852593 | C32: =EEFF!C32 -> -1581230 | D32: =EEFF!D32 -> 3464904 | E32: =EEFF!E32 -> 1167130 | F32: =EEFF!F32 -> 1801744 | G32: =G30+G31 -> 1801744 | H32: =H30+H31 -> 1801744 | I32: =I30+I31 -> 1801744 | J32: =J30+J31 -> 1801744 | K32: =K30+K31 -> 1801744
A33: Ganancia del año | B33: =EEFF!B33 -> 26593150 | C33: =EEFF!C33 -> 37263494 | D33: =EEFF!D33 -> 47505926 | E33: =EEFF!E33 -> 47832787 | F33: =EEFF!F33 -> 48262456 | G33: =G29-G32 -> 56555354 | H33: =H29-H32 -> 64136477 | I33: =I29-I32 -> 71974210 | J33: =J29-J32 -> 80078620 | K33: =K29-K32 -> 88460166
A35: Años | B35: FY21A | C35: FY22A | D35: FY23A | E35: FY24A | F35: FY25A | G35: FY26E | H35: FY27E | I35: FY28E | J35: FY29E | K35: FY30E
A36: Estado consolidado de situación financiera
A37: Efectivo y depósitos en banco | B37: =EEFF!B37 -> 508316487 | C37: =EEFF!C37 -> 422163231 | D37: =EEFF!D37 -> 354965856 | E37: =EEFF!E37 -> 378198724 | F37: =EEFF!F37 -> 433699566 | G37: =F37 -> 433699566 | H37: =G37 -> 433699566 | I37: =H37 -> 433699566 | J37: =I37 -> 433699566 | K37: =J37 -> 433699566
A38: Valores comprados bajo acuerdos de reventa | B38: =EEFF!B38 -> 306301 | C38: =EEFF!C38 -> 285200 | D38: =EEFF!D38 -> 3547807 | E38: =EEFF!E38 -> 4956931 | F38: =EEFF!F38 -> 4997637 | G38: =F38 -> 4997637 | H38: =G38 -> 4997637 | I38: =H38 -> 4997637 | J38: =I38 -> 4997637 | K38: =J38 -> 4997637
A39: Inversiones en valores, neto | B39: =EEFF!B39 -> 1110163904 | C39: =EEFF!C39 -> 1079204941 | D39: =EEFF!D39 -> 1053410069 | E39: =EEFF!E39 -> 1049326162 | F39: =EEFF!F39 -> 1136648533 | G39: =F39+MAX(0,G127) -> 1.2270272e+09 | H39: =G39+MAX(0,H127) -> 1.3382799e+09 | I39: =H39+MAX(0,I127) -> 1.4529933e+09 | J39: =I39+MAX(0,J127) -> 1.571258e+09 | K39: =J39+MAX(0,K127) -> 1.6931665e+09
A40: Préstamos, neto | B40: =EEFF!B40 -> 6007976619 | C40: =EEFF!C40 -> 6138222161 | D40: =EEFF!D40 -> 6212554475 | E40: =EEFF!E40 -> 6315709567 | F40: =EEFF!F40 -> 6141543608 | G40: =F40*(1+Supuestos!G28) -> 6.1765504e+09 | H40: =G40*(1+Supuestos!H28) -> 6.2117567e+09 | I40: =H40*(1+Supuestos!I28) -> 6.2471638e+09 | J40: =I40*(1+Supuestos!J28) -> 6.2827726e+09 | K40: =J40*(1+Supuestos!K28) -> 6.3185844e+09
A41: Propiedades, mobiliario, equipo y mejoras | B41: =EEFF!B41 -> 195030353 | C41: =EEFF!C41 -> 197759650 | D41: =EEFF!D41 -> 190418187 | E41: =EEFF!E41 -> 191401031 | F41: =EEFF!F41 -> 192001647 | G41: =F41 -> 192001647 | H41: =G41 -> 192001647 | I41: =H41 -> 192001647 | J41: =I41 -> 192001647 | K41: =J41 -> 192001647
A42: Activos por derechos de uso | B42: =EEFF!B42 -> 19425507 | C42: =EEFF!C42 -> 15584822 | D42: =EEFF!D42 -> 13301035 | E42: =EEFF!E42 -> 11291589 | F42: =EEFF!F42 -> 9660940 | G42: =F42 -> 9660940 | H42: =G42 -> 9660940 | I42: =H42 -> 9660940 | J42: =I42 -> 9660940 | K42: =J42 -> 9660940
A43: Activos varios | B43: =EEFF!B43 -> 482324722 | C43: =EEFF!C43 -> 547376430 | D43: =EEFF!D43 -> 584781470 | E43: =EEFF!E43 -> 569398628 | F43: =EEFF!F43 -> 584449645 | G43: =F43 -> 584449645 | H43: =G43 -> 584449645 | I43: =H43 -> 584449645 | J43: =I43 -> 584449645 | K43: =J43 -> 584449645
A44: Total de activos | B44: =EEFF!B44 -> 8323543893 | C44: =EEFF!C44 -> 8400596435 | D44: =EEFF!D44 -> 8412978899 | E44: =EEFF!E44 -> 8520282632 | F44: =EEFF!F44 -> 8503001576 | G44: =G37+G38+G39+G40+G41+G42+G43 -> 8.6283871e+09 | H44: =H37+H38+H39+H40+H41+H42+H43 -> 8.7748461e+09 | I44: =I37+I38+I39+I40+I41+I42+I43 -> 8.9249665e+09 | J44: =J37+J38+J39+J40+J41+J42+J43 -> 9.07884e+09 | K44: =K37+K38+K39+K40+K41+K42+K43 -> 9.2365603e+09
A45: Depósitos de clientes | B45: =EEFF!B45 -> 5189459231 | C45: =EEFF!C45 -> 5178659636 | D45: =EEFF!D45 -> 5205576287 | E45: =EEFF!E45 -> 5264634266 | F45: =EEFF!F45 -> 5715472860 | G45: =F45*(1+Supuestos!G36) -> 5.8583597e+09 | H45: =G45*(1+Supuestos!H36) -> 6.0048187e+09 | I45: =H45*(1+Supuestos!I36) -> 6.1549391e+09 | J45: =I45*(1+Supuestos!J36) -> 6.3088126e+09 | K45: =J45*(1+Supuestos!K36) -> 6.4665329e+09
A46: Depósitos de bancos | B46: =EEFF!B46 -> 44910134 | C46: =EEFF!C46 -> 64413383 | D46: =EEFF!D46 -> 82919955 | E46: =EEFF!E46 -> 80815921 | F46: =EEFF!F46 -> 16750000 | G46: =F46 -> 16750000 | H46: =G46 -> 16750000 | I46: =H46 -> 16750000 | J46: =I46 -> 16750000 | K46: =J46 -> 16750000
A47: Intereses acumulados por pagar | B47: =EEFF!B55 -> 14036040 | C47: =EEFF!C55 -> 13211416 | D47: =EEFF!D55 -> 25606793 | E47: =EEFF!E55 -> 25872345 | F47: =EEFF!F55 -> 23085224 | G47: =F47 -> 23085224 | H47: =G47 -> 23085224 | I47: =H47 -> 23085224 | J47: =I47 -> 23085224 | K47: =J47 -> 23085224
A48: Total de depósitos | B48: =EEFF!B48 -> 5275151088 | C48: =EEFF!C48 -> 5275242825 | D48: =EEFF!D48 -> 5321547792 | E48: =EEFF!E48 -> 5381647327 | F48: =EEFF!F48 -> 5772809411 | G48: =G45+G46+G47 -> 5.8981949e+09 | H48: =H45+H46+H47 -> 6.0446539e+09 | I48: =I45+I46+I47 -> 6.1947744e+09 | J48: =J45+J46+J47 -> 6.3486478e+09 | K48: =K45+K46+K47 -> 6.5063682e+09
A49: Valores vendidos bajo acuerdos de recompra | B49: =EEFF!B49 -> 0 | C49: =EEFF!C49 -> 93665393 | D49: =EEFF!D49 -> 70009751 | E49: =EEFF!E49 -> 47610933 | F49: =EEFF!F49 -> 37321723 | G49: =F49 -> 37321723 | H49: =G49 -> 37321723 | I49: =H49 -> 37321723 | J49: =I49 -> 37321723 | K49: =J49 -> 37321723
A50: Obligaciones con instituciones financieras | B50: =EEFF!B50 -> 876325546 | C50: =EEFF!C50 -> 1488606294 | D50: =EEFF!D50 -> 1582877582 | E50: =EEFF!E50 -> 1642982215 | F50: =EEFF!F50 -> 1232945418 | G50: =F50+MAX(0,-G127) -> 1232945418 | H50: =G50+MAX(0,-H127) -> 1232945418 | I50: =H50+MAX(0,-I127) -> 1232945418 | J50: =I50+MAX(0,-J127) -> 1232945418 | K50: =J50+MAX(0,-K127) -> 1232945418
A51: Valores comerciales negociables (VCNs) | B51: =EEFF!B51 -> 6850000 | C51: =EEFF!C51 -> 16595000 | D51: =EEFF!D51 -> 0 | E51: =EEFF!E51 -> 2000000 | F51: =EEFF!F51 -> 0 | G51: =F51 -> 0 | H51: =G51 -> 0 | I51: =H51 -> 0 | J51: =I51 -> 0 | K51: =J51 -> 0
A52: Bonos corporativos | B52: =EEFF!B52 -> 1055663563 | C52: =EEFF!C52 -> 439235300 | D52: =EEFF!D52 -> 388450729 | E52: =EEFF!E52 -> 374440557 | F52: =EEFF!F52 -> 374069381 | G52: =F52 -> 374069381 | H52: =G52 -> 374069381 | I52: =H52 -> 374069381 | J52: =I52 -> 374069381 | K52: =J52 -> 374069381
A53: Bonos subordinados | B53: =EEFF!B53 -> 7833557 | C53: =EEFF!C53 -> 0 | D53: =EEFF!D53 -> 0 | E53: =EEFF!E53 -> 0 | F53: =EEFF!F53 -> 0
A54: Bonos perpetuos | B54: =EEFF!B54 -> 160763868 | C54: =EEFF!C54 -> 177495857 | D54: =EEFF!D54 -> 177965873 | E54: =EEFF!E54 -> 178016538 | F54: =EEFF!F54 -> 177320865 | G54: =F54 -> 177320865 | H54: =G54 -> 177320865 | I54: =H54 -> 177320865 | J54: =I54 -> 177320865 | K54: =J54 -> 177320865
A55: Intereses acumulados por pagar | B55: =EEFF!B55 -> 14036040 | C55: =EEFF!C55 -> 13211416 | D55: =EEFF!D55 -> 25606793 | E55: =EEFF!E55 -> 25872345 | F55: =EEFF!F55 -> 23085224 | G55: =F55 -> 23085224 | H55: =G55 -> 23085224 | I55: =H55 -> 23085224 | J55: =I55 -> 23085224 | K55: =J55 -> 23085224
A56: Total de financiamientos | B56: =EEFF!B56 -> 2121472574 | C56: =EEFF!C56 -> 2228809260 | D56: =EEFF!D56 -> 2244910728 | E56: =EEFF!E56 -> 2270922588 | F56: =EEFF!F56 -> 1844742611 | G56: =G49+G50+G51+G52+G53+G54+G55 -> 1844742611 | H56: =H49+H50+H51+H52+H53+H54+H55 -> 1844742611 | I56: =I49+I50+I51+I52+I53+I54+I55 -> 1844742611 | J56: =J49+J50+J51+J52+J53+J54+J55 -> 1844742611 | K56: =K49+K50+K51+K52+K53+K54+K55 -> 1844742611
A57: Pasivos por arrendamientos | B57: =EEFF!B57 -> 20847797 | C57: =EEFF!C57 -> 17277420 | D57: =EEFF!D57 -> 15302729 | E57: =EEFF!E57 -> 12991713 | F57: =EEFF!F57 -> 11539789 | G57: =F57 -> 11539789 | H57: =G57 -> 11539789 | I57: =H57 -> 11539789 | J57: =I57 -> 11539789 | K57: =J57 -> 11539789
A58: Pasivos varios | B58: =EEFF!B58 -> 116353854 | C58: =EEFF!C58 -> 119112591 | D58: =EEFF!D58 -> 119464406 | E58: =EEFF!E58 -> 123345219 | F58: =EEFF!F58 -> 105129335 | G58: =F58 -> 105129335 | H58: =G58 -> 105129335 | I58: =H58 -> 105129335 | J58: =I58 -> 105129335 | K58: =J58 -> 105129335
A59: Total de pasivos | B59: =EEFF!B59 -> 7533825313 | C59: =EEFF!C59 -> 7640442096 | D59: =EEFF!D59 -> 7701225655 | E59: =EEFF!E59 -> 7788906847 | F59: =EEFF!F59 -> 7734221146 | G59: =G48+G56+G57+G58 -> 7.8596066e+09 | H59: =H48+H56+H57+H58 -> 8.0060656e+09 | I59: =I48+I56+I57+I58 -> 8.1561861e+09 | J59: =J48+J56+J57+J58 -> 8.3100596e+09 | K59: =K48+K56+K57+K58 -> 8.4677799e+09
A60: Acciones comunes | B60: =EEFF!B60 -> 270202657 | C60: =EEFF!C60 -> 270202657 | D60: =EEFF!D60 -> 270202657 | E60: =EEFF!E60 -> 270202657 | F60: =EEFF!F60 -> 274702657 | G60: =F60 -> 274702657 | H60: =G60 -> 274702657 | I60: =H60 -> 274702657 | J60: =I60 -> 274702657 | K60: =J60 -> 274702657
A61: Capital pagado en exceso | B61: =EEFF!B61 -> 1755574 | C61: =EEFF!C61 -> 1974519 | D61: =EEFF!D61 -> 2252695 | E61: =EEFF!E61 -> 2247763 | F61: =EEFF!F61 -> 2292335 | G61: =F61 -> 2292335 | H61: =G61 -> 2292335 | I61: =H61 -> 2292335 | J61: =I61 -> 2292335 | K61: =J61 -> 2292335
A62: Reservas de capital | B62: =EEFF!B62 -> 42382907 | C62: =EEFF!C62 -> 43269167 | D62: =EEFF!D62 -> 44175479 | E62: =EEFF!E62 -> 45124877 | F62: =EEFF!F62 -> 46137123 | G62: =F62 -> 46137123 | H62: =G62 -> 46137123 | I62: =H62 -> 46137123 | J62: =I62 -> 46137123 | K62: =J62 -> 46137123
A63: Reservas regulatorias | B63: =EEFF!B63 -> 99613232 | C63: =EEFF!C63 -> 101983796 | D63: =EEFF!D63 -> 104142557 | E63: =EEFF!E63 -> 108133638 | F63: =EEFF!F63 -> 112628772 | G63: =F63 -> 112628772 | H63: =G63 -> 112628772 | I63: =H63 -> 112628772 | J63: =I63 -> 112628772 | K63: =J63 -> 112628772
A64: Reserva de valor razonable | B64: =EEFF!B64 -> 3356143 | C64: =EEFF!C64 -> -37694923 | D64: =EEFF!D64 -> -37365976 | E64: =EEFF!E64 -> -29751677 | F64: =EEFF!F64 -> -17574839 | G64: =F64 -> -17574839 | H64: =G64 -> -17574839 | I64: =H64 -> -17574839 | J64: =I64 -> -17574839 | K64: =J64 -> -17574839
A65: Cambios netos en instrumentos de cobertura | B65: =EEFF!B65 -> 0 | C65: =EEFF!C65 -> 0 | D65: =EEFF!D65 -> 0 | E65: =EEFF!E65 -> -69008 | F65: =EEFF!F65 -> -2164703 | G65: =F65 -> -2164703 | H65: =G65 -> -2164703 | I65: =H65 -> -2164703 | J65: =I65 -> -2164703 | K65: =J65 -> -2164703
A66: Utilidades no distribuidas | B66: =EEFF!B66 -> 372408067 | C66: =EEFF!C66 -> 380419123 | D66: =EEFF!D66 -> 328345832 | E66: =EEFF!E66 -> 335487535 | F66: =EEFF!F66 -> 352759085 | G66: =F66 -> 352759085 | H66: =G66 -> 352759085 | I66: =H66 -> 352759085 | J66: =I66 -> 352759085 | K66: =J66 -> 352759085
A67: Total de patrimonio del accionista | B67: =EEFF!B67 -> 789718580 | C67: =EEFF!C67 -> 760154339 | D67: =EEFF!D67 -> 711753244 | E67: =EEFF!E67 -> 731375785 | F67: =EEFF!F67 -> 768780430 | G67: =G60+G61+G62+G63+G64+G65+G66 -> 768780430 | H67: =H60+H61+H62+H63+H64+H65+H66 -> 768780430 | I67: =I60+I61+I62+I63+I64+I65+I66 -> 768780430 | J67: =J60+J61+J62+J63+J64+J65+J66 -> 768780430 | K67: =K60+K61+K62+K63+K64+K65+K66 -> 768780430
A68: Total de pasivos y patrimonio | B68: =EEFF!B68 -> 8323543893 | C68: =EEFF!C68 -> 8400596435 | D68: =EEFF!D68 -> 8412978899 | E68: =EEFF!E68 -> 8520282632 | F68: =EEFF!F68 -> 8503001576 | G68: =G59+G67 -> 8.6283871e+09 | H68: =H59+H67 -> 8.7748461e+09 | I68: =I59+I67 -> 8.9249665e+09 | J68: =J59+J67 -> 9.07884e+09 | K68: =K59+K67 -> 9.2365603e+09
A70: Años | B70: FY21A | C70: FY22A | D70: FY23A | E70: FY24A | F70: FY25A | G70: FY26E | H70: FY27E | I70: FY28E | J70: FY29E | K70: FY30E
A71: Estado consolidado de flujos de efectivo
A72: Ganancia del año | B72: =EEFF!B72 -> 26593150 | C72: =EEFF!C72 -> 37263494 | D72: =EEFF!D72 -> 47505926 | E72: =EEFF!E72 -> 47832787 | F72: =EEFF!F72 -> 48262456 | G72: =F72 -> 48262456 | H72: =G72 -> 48262456 | I72: =H72 -> 48262456 | J72: =I72 -> 48262456 | K72: =J72 -> 48262456
A73: Depreciación y amortización | B73: =EEFF!B73 -> 21305412 | C73: =EEFF!C73 -> 20767901 | D73: =EEFF!D73 -> 18258300 | E73: =EEFF!E73 -> 17607972 | F73: =EEFF!F73 -> 17639914 | G73: =F73 -> 17639914 | H73: =G73 -> 17639914 | I73: =H73 -> 17639914 | J73: =I73 -> 17639914 | K73: =J73 -> 17639914
A74: Pérdida (ganancia) en venta de propiedad, mobiliario y equipo | B74: =EEFF!B74 -> -5101 | C74: =EEFF!C74 -> -178437 | D74: =EEFF!D74 -> -667208 | E74: =EEFF!E74 -> -308684 | F74: =EEFF!F74 -> 211392 | G74: =F74 -> 211392 | H74: =G74 -> 211392 | I74: =H74 -> 211392 | J74: =I74 -> 211392 | K74: =J74 -> 211392
A75: Descartes de activo fijo | B75: =EEFF!B75 -> 31927 | C75: =EEFF!C75 -> 215502 | D75: =EEFF!D75 -> 5296399 | E75: =EEFF!E75 -> 1241711 | F75: =EEFF!F75 -> 3354830 | G75: =F75 -> 3354830 | H75: =G75 -> 3354830 | I75: =H75 -> 3354830 | J75: =I75 -> 3354830 | K75: =J75 -> 3354830
A76: Ganancia en venta de valores al valor razonable con cambios en ORI, neto | B76: =EEFF!B76 -> -7527134 | C76: =EEFF!C76 -> -1154420 | D76: =EEFF!D76 -> -388602 | E76: =EEFF!E76 -> -309926 | F76: =EEFF!F76 -> -795290 | G76: =F76 -> -795290 | H76: =G76 -> -795290 | I76: =H76 -> -795290 | J76: =I76 -> -795290 | K76: =J76 -> -795290
A77: Pérdida (ganancia) en instrumentos al valor razonable con cambios en resultados, neto | B77: =EEFF!B77 -> -202943 | C77: =EEFF!C77 -> 680871 | D77: =EEFF!D77 -> -60788 | E77: =EEFF!E77 -> -2840346 | F77: =EEFF!F77 -> 85947 | G77: =F77 -> 85947 | H77: =G77 -> 85947 | I77: =H77 -> 85947 | J77: =I77 -> 85947 | K77: =J77 -> 85947
A78: Provisión para pérdidas en préstamos | B78: =EEFF!B78 -> 83497811 | C78: =EEFF!C78 -> 59032479 | D78: =EEFF!D78 -> 48957742 | E78: =EEFF!E78 -> 34695854 | F78: =EEFF!F78 -> 28431911 | G78: =F78 -> 28431911 | H78: =G78 -> 28431911 | I78: =H78 -> 28431911 | J78: =I78 -> 28431911 | K78: =J78 -> 28431911
A79: Reversión de provisión para inversiones, neto | B79: =EEFF!B79 -> 500143 | C79: =EEFF!C79 -> 2897059 | D79: =EEFF!D79 -> 474038 | E79: =EEFF!E79 -> -60659 | F79: =EEFF!F79 -> -198747 | G79: =F79 -> -198747 | H79: =G79 -> -198747 | I79: =H79 -> -198747 | J79: =I79 -> -198747 | K79: =J79 -> -198747
A80: Impuesto sobre la renta | B80: =EEFF!B80 -> -8852593 | C80: =EEFF!C80 -> -1581230 | D80: =EEFF!D80 -> 3464904 | E80: =EEFF!E80 -> 1167130 | F80: =EEFF!F80 -> 1801744 | G80: =F80 -> 1801744 | H80: =G80 -> 1801744 | I80: =H80 -> 1801744 | J80: =I80 -> 1801744 | K80: =J80 -> 1801744
A81: Ingresos neto por intereses | B81: =EEFF!B81 -> -436095180 | C81: =EEFF!C81 -> -419112916 | D81: =EEFF!D81 -> -454333887 | E81: =EEFF!E81 -> -503666534 | F81: =EEFF!F81 -> -523500468 | G81: =F81 -> -523500468 | H81: =G81 -> -523500468 | I81: =H81 -> -523500468 | J81: =I81 -> -523500468 | K81: =J81 -> -523500468
A82: Gastos de intereses | B82: =EEFF!B82 -> 263333029 | C82: =EEFF!C82 -> 238053406 | D82: =EEFF!D82 -> 281836291 | E82: =EEFF!E82 -> 350182264 | F82: =EEFF!F82 -> 366248027 | G82: =F82 -> 366248027 | H82: =G82 -> 366248027 | I82: =H82 -> 366248027 | J82: =I82 -> 366248027 | K82: =J82 -> 366248027
A83: Plan de acciones restringidas | B83: =EEFF!B83 -> -243733 | C83: =EEFF!C83 -> 218945 | D83: =EEFF!D83 -> 278176 | E83: =EEFF!E83 -> -4932 | F83: =EEFF!F83 -> 44572 | G83: =F83 -> 44572 | H83: =G83 -> 44572 | I83: =H83 -> 44572 | J83: =I83 -> 44572 | K83: =J83 -> 44572
... A121: Efectivo y equivalentes de efectivo al final del año | B121: =EEFF!B121 -> 473989795 | C121: =EEFF!C121 -> 415326050 | D121: =EEFF!D121 -> 346970481 | E121: =EEFF!E121 -> 354812300 | F121: =EEFF!F121 -> 392380457 | G121: =F121 -> 392380457 | H121: =G121 -> 392380457 | I121: =H121 -> 392380457 | J121: =I121 -> 392380457 | K121: =J121 -> 392380457
A124: BALANCEO DE FONDEO (memo — compacto bancario; nunca caja-residual)
A125: (memo) Fondeo pre-balanceo (pasivos sin balanceador + patrimonio) | G125: =G48+F50+G49+G51+G52+G53+G54+G55+G57+G58+G67 -> 8.6283871e+09 | H125: =H48+G50+H49+H51+H52+H53+H54+H55+H57+H58+H67 -> 8.7748461e+09 | I125: =I48+H50+I49+I51+I52+I53+I54+I55+I57+I58+I67 -> 8.9249665e+09 | J125: =J48+I50+J49+J51+J52+J53+J54+J55+J57+J58+J67 -> 9.07884e+09 | K125: =K48+J50+K49+K51+K52+K53+K54+K55+K57+K58+K67 -> 9.2365603e+09
A126: (memo) Activos pre-balanceo (sin balanceador de inversiones) | G126: =F39+G37+G38+G40+G41+G42+G43 -> 8.5380084e+09 | H126: =G39+H37+H38+H40+H41+H42+H43 -> 8.6635934e+09 | I126: =H39+I37+I38+I40+I41+I42+I43 -> 8.8102531e+09 | J126: =I39+J37+J38+J40+J41+J42+J43 -> 8.9605754e+09 | K126: =J39+K37+K38+K40+K41+K42+K43 -> 9.1146518e+09
A127: (memo) Brecha de fondeo (+exceso → inversiones / −faltante → obligación) | G127: =G125-G126 -> 90378696 | H127: =H125-H126 -> 1.1125265e+08 | I127: =I125-I126 -> 1.1471345e+08 | J127: =J125-J126 -> 1.1826465e+08 | K127: =K125-K126 -> 1.2190851e+08

Sheet Loan_Book
A1: Global Bank Corporation y Subsidiarias
A2: Loan_Book — cartera bruta por producto (driver del activo, R5)
A3: Histórico verbatim Nota 10 del INA_GLOBAN_2025_0.pdf; forecast = crecimiento de cartera de Supuestos (mix constante).
A5: Años | B5: FY24A | C5: FY25A | D5: FY26E | E5: FY27E | F5: FY28E | G5: FY29E | H5: FY30E
A7: A. CARTERA BRUTA POR PRODUCTO
A8: Sector interno - Consumo | B8: 1164047707 | C8: 1218732493 | D8: =C8*(1+Supuestos!G28) -> 1.2256793e+09 | E8: =D8*(1+Supuestos!H28) -> 1.2326656e+09 | F8: =E8*(1+Supuestos!I28) -> 1.2396918e+09 | G8: =F8*(1+Supuestos!J28) -> 1.2467581e+09 | H8: =G8*(1+Supuestos!K28) -> 1.2538646e+09
A9: Sector interno - Comerciales | B9: 1187948076 | C9: 1164209384 | D9: =C9*(1+Supuestos!G28) -> 1.1708454e+09 | E9: =D9*(1+Supuestos!H28) -> 1.1775192e+09 | F9: =E9*(1+Supuestos!I28) -> 1.1842311e+09 | G9: =F9*(1+Supuestos!J28) -> 1.1909812e+09 | H9: =G9*(1+Supuestos!K28) -> 1.1977698e+09
A10: Sector interno - Agropecuario | B10: 339486359 | C10: 309346401 | D10: =C10*(1+Supuestos!G28) -> 3.1110968e+08 | E10: =D10*(1+Supuestos!H28) -> 3.12883e+08 | F10: =E10*(1+Supuestos!I28) -> 3.1466643e+08 | G10: =F10*(1+Supuestos!J28) -> 3.1646003e+08 | H10: =G10*(1+Supuestos!K28) -> 3.1826385e+08
A11: Sector interno - Prendarios | B11: 148156201 | C11: 144449704 | D11: =C11*(1+Supuestos!G28) -> 1.4527307e+08 | E11: =D11*(1+Supuestos!H28) -> 1.4610112e+08 | F11: =E11*(1+Supuestos!I28) -> 1.469339e+08 | G11: =F11*(1+Supuestos!J28) -> 1.4777142e+08 | H11: =G11*(1+Supuestos!K28) -> 1.4861372e+08
A12: Sector interno - Sobregiros | B12: 118731610 | C12: 105641732 | D12: =C12*(1+Supuestos!G28) -> 1.0624389e+08 | E12: =D12*(1+Supuestos!H28) -> 1.0684948e+08 | F12: =E12*(1+Supuestos!I28) -> 1.0745852e+08 | G12: =F12*(1+Supuestos!J28) -> 1.0807104e+08 | H12: =G12*(1+Supuestos!K28) -> 1.0868704e+08
A13: Sector interno - Hipotecarios | B13: 1918375745 | C13: 1840267760 | D13: =C13*(1+Supuestos!G28) -> 1.8507573e+09 | E13: =D13*(1+Supuestos!H28) -> 1.8613066e+09 | F13: =E13*(1+Supuestos!I28) -> 1.8719161e+09 | G13: =F13*(1+Supuestos!J28) -> 1.882586e+09 | H13: =G13*(1+Supuestos!K28) -> 1.8933167e+09
A14: Sector interno - Industriales | B14: 305881168 | C14: 317318291 | D14: =C14*(1+Supuestos!G28) -> 3.1912701e+08 | E14: =D14*(1+Supuestos!H28) -> 3.2094603e+08 | F14: =E14*(1+Supuestos!I28) -> 3.2277542e+08 | G14: =F14*(1+Supuestos!J28) -> 3.2461524e+08 | H14: =G14*(1+Supuestos!K28) -> 3.2646555e+08
A15: Sector interno - Construcción | B15: 401298736 | C15: 391932776 | D15: =C15*(1+Supuestos!G28) -> 3.9416679e+08 | E15: =D15*(1+Supuestos!H28) -> 3.9641354e+08 | F15: =E15*(1+Supuestos!I28) -> 3.986731e+08 | G15: =F15*(1+Supuestos!J28) -> 4.0094554e+08 | H15: =G15*(1+Supuestos!K28) -> 4.0323093e+08
A16: Sector interno - Arrendamientos financieros | B16: 47163874 | C16: 37539795 | D16: =C16*(1+Supuestos!G28) -> 37753772 | E16: =D16*(1+Supuestos!H28) -> 37968968 | F16: =E16*(1+Supuestos!I28) -> 38185391 | G16: =F16*(1+Supuestos!J28) -> 38403048 | H16: =G16*(1+Supuestos!K28) -> 38621946
A17: Sector interno - Facturas descontadas | B17: 304285310 | C17: 183852054 | D17: =C17*(1+Supuestos!G28) -> 1.8490001e+08 | E17: =D17*(1+Supuestos!H28) -> 1.8595394e+08 | F17: =E17*(1+Supuestos!I28) -> 1.8701388e+08 | G17: =F17*(1+Supuestos!J28) -> 1.8807986e+08 | H17: =G17*(1+Supuestos!K28) -> 1.8915191e+08
A18: Sector externo - Comerciales | B18: 282077170 | C18: 335111161 | D18: =C18*(1+Supuestos!G28) -> 3.3702129e+08 | E18: =D18*(1+Supuestos!H28) -> 3.3894232e+08 | F18: =E18*(1+Supuestos!I28) -> 3.4087429e+08 | G18: =F18*(1+Supuestos!J28) -> 3.4281727e+08 | H18: =G18*(1+Supuestos!K28) -> 3.4477133e+08
A19: Sector externo - Agropecuarios | B19: 0 | C19: 9076680 | D19: =C19*(1+Supuestos!G28) -> 9128417.1 | E19: =D19*(1+Supuestos!H28) -> 9180449.1 | F19: =E19*(1+Supuestos!I28) -> 9232777.6 | G19: =F19*(1+Supuestos!J28) -> 9285404.4 | H19: =G19*(1+Supuestos!K28) -> 9338331.3
A20: Sector externo - Industriales | B20: 151560596 | C20: 106246377 | D20: =C20*(1+Supuestos!G28) -> 1.0685198e+08 | E20: =D20*(1+Supuestos!H28) -> 1.0746104e+08 | F20: =E20*(1+Supuestos!I28) -> 1.0807357e+08 | G20: =F20*(1+Supuestos!J28) -> 1.0868958e+08 | H20: =G20*(1+Supuestos!K28) -> 1.0930912e+08
A21: Sector externo - Construcción | B21: 1876711 | C21: 1548623 | D21: =C21*(1+Supuestos!G28) -> 1557450.2 | E21: =D21*(1+Supuestos!H28) -> 1566327.6 | F21: =E21*(1+Supuestos!I28) -> 1575255.7 | G21: =F21*(1+Supuestos!J28) -> 1584234.6 | H21: =G21*(1+Supuestos!K28) -> 1593264.8
A22: Sector externo - Prendarios | B22: 9470022 | C22: 29470022 | D22: =C22*(1+Supuestos!G28) -> 29638001 | E22: =D22*(1+Supuestos!H28) -> 29806938 | F22: =E22*(1+Supuestos!I28) -> 29976837 | G22: =F22*(1+Supuestos!J28) -> 30147705 | H22: =G22*(1+Supuestos!K28) -> 30319547
A23: Sector externo - Sobregiro | B23: 19275275 | C23: 21297833 | D23: =C23*(1+Supuestos!G28) -> 21419231 | E23: =D23*(1+Supuestos!H28) -> 21541320 | F23: =E23*(1+Supuestos!I28) -> 21664106 | G23: =F23*(1+Supuestos!J28) -> 21787591 | H23: =G23*(1+Supuestos!K28) -> 21911780
A24: Total cartera bruta | B24: =B8+B9+B10+B11+B12+B13+B14+B15+B16+B17+B18+B19+B20+B21+B22+B23 -> 6399634560 | C24: =C8+C9+C10+C11+C12+C13+C14+C15+C16+C17+C18+C19+C20+C21+C22+C23 -> 6216041086 | D24: =D8+D9+D10+D11+D12+D13+D14+D15+D16+D17+D18+D19+D20+D21+D22+D23 -> 6.2514725e+09 | E24: =E8+E9+E10+E11+E12+E13+E14+E15+E16+E17+E18+E19+E20+E21+E22+E23 -> 6.2871059e+09 | F24: =F8+F9+F10+F11+F12+F13+F14+F15+F16+F17+F18+F19+F20+F21+F22+F23 -> 6.3229424e+09 | G24: =G8+G9+G10+G11+G12+G13+G14+G15+G16+G17+G18+G19+G20+G21+G22+G23 -> 6.3589832e+09 | H24: =H8+H9+H10+H11+H12+H13+H14+H15+H16+H17+H18+H19+H20+H21+H22+H23 -> 6.3952294e+09
A26: B. TIE-OUT CONTRA MODELOFINANCIERO (check 13)
A27: Cartera bruta según ModeloFinanciero (BS) | B27: =ModeloFinanciero!E40 -> 6315709567 | C27: =ModeloFinanciero!F40 -> 6141543608 | D27: =ModeloFinanciero!G40 -> 6.1765504e+09 | E27: =ModeloFinanciero!H40 -> 6.2117567e+09 | F27: =ModeloFinanciero!I40 -> 6.2471638e+09 | G27: =ModeloFinanciero!J40 -> 6.2827726e+09 | H27: =ModeloFinanciero!K40 -> 6.3185844e+09
A28: CHECK Δ Loan_Book − Modelo (=0 OK) | B28: =B24-B27 -> 83924993 | C28: =C24-C27 -> 74497478 | D28: =D24-D27 -> 74922114 | E28: =E24-E27 -> 75349170 | F28: =F24-F27 -> 75778660 | G28: =G24-G27 -> 76210598 | H28: =H24-H27 -> 76644999
A30: DRIVER_DETAIL_PENDING: yields/crecimiento por producto no divulgados — todos los productos crecen al driver agregado (mix constante).

Sheet Deposits_Funding
A1: Global Bank Corporation y Subsidiarias
A2: Deposits_Funding — depósitos por tipo + financiamientos (el pasivo del spread, R5)
A3: Histórico verbatim Nota 14; forecast = crecimiento de depósitos de Supuestos. Financiamientos = referencias al ModeloFinanciero (el balanceador vive allá, R2).
A5: Años | B5: FY24A | C5: FY25A | D5: FY26E | E5: FY27E | F5: FY28E | G5: FY29E | H5: FY30E
A7: A. DEPÓSITOS POR TIPO (base de la nota)
A8: A la vista | B8: 467235160 | C8: 518103988 | D8: =C8*(1+Supuestos!G36) -> 5.3105659e+08 | E8: =D8*(1+Supuestos!H36) -> 5.44333e+08 | F8: =E8*(1+Supuestos!I36) -> 5.5794133e+08 | G8: =F8*(1+Supuestos!J36) -> 5.7188986e+08 | H8: =G8*(1+Supuestos!K36) -> 5.8618711e+08
A9: Ahorros | B9: 1081312202 | C9: 1147463446 | D9: =C9*(1+Supuestos!G36) -> 1.17615e+09 | E9: =D9*(1+Supuestos!H36) -> 1.2055538e+09 | F9: =E9*(1+Supuestos!I36) -> 1.2356926e+09 | G9: =F9*(1+Supuestos!J36) -> 1.2665849e+09 | H9: =G9*(1+Supuestos!K36) -> 1.2982496e+09
A10: Plazo fijo | B10: 3716086904 | C10: 4049905426 | D10: =C10*(1+Supuestos!G36) -> 4.1511531e+09 | E10: =D10*(1+Supuestos!H36) -> 4.2549319e+09 | F10: =E10*(1+Supuestos!I36) -> 4.3613052e+09 | G10: =F10*(1+Supuestos!J36) -> 4.4703378e+09 | H10: =G10*(1+Supuestos!K36) -> 4.5820963e+09
A11: Total depósitos (base nota) | B11: =B8+B9+B10 -> 5264634266 | C11: =C8+C9+C10 -> 5715472860 | D11: =D8+D9+D10 -> 5.8583597e+09 | E11: =E8+E9+E10 -> 6.0048187e+09 | F11: =F8+F9+F10 -> 6.1549391e+09 | G11: =G8+G9+G10 -> 6.3088126e+09 | H11: =H8+H9+H10 -> 6.4665329e+09
A13: B. CONCILIACIÓN CONTRA MODELOFINANCIERO (check 14)
A14: Total de depósitos según ModeloFinanciero (BS) | B14: =ModeloFinanciero!E48 -> 5381647327 | C14: =ModeloFinanciero!F48 -> 5772809411 | D14: =ModeloFinanciero!G48 -> 5.8981949e+09 | E14: =ModeloFinanciero!H48 -> 6.0446539e+09 | F14: =ModeloFinanciero!I48 -> 6.1947744e+09 | G14: =ModeloFinanciero!J48 -> 6.3486478e+09 | H14: =ModeloFinanciero!K48 -> 6.5063682e+09
A15: Δ conciliación (interbancarios + intereses acumulados, según filing) | B15: =B14-B11 -> 117013061 | C15: =C14-C11 -> 57336551 | D15: =D14-D11 -> 39835224 | E15: =E14-E11 -> 39835224 | F15: =F14-F11 -> 39835224 | G15: =G14-G11 -> 39835224 | H15: =H14-H11 -> 39835224
A17: C. FINANCIAMIENTOS Y COSTO (referencias)
A18: Total de financiamientos (ModeloFinanciero) | B18: =ModeloFinanciero!E56 -> 2270922588 | C18: =ModeloFinanciero!F56 -> 1844742611 | D18: =ModeloFinanciero!G56 -> 1844742611 | E18: =ModeloFinanciero!H56 -> 1844742611 | F18: =ModeloFinanciero!I56 -> 1844742611 | G18: =ModeloFinanciero!J56 -> 1844742611 | H18: =ModeloFinanciero!K56 -> 1844742611
A19: Costo de depósitos — driver activo (Supuestos) | D19: =Supuestos!G19 -> -0.6996 | E19: =Supuestos!H19 -> -0.6996 | F19: =Supuestos!I19 -> -0.6996 | G19: =Supuestos!J19 -> -0.6996 | H19: =Supuestos!K19 -> -0.6996
A20: Costo de financiamientos — driver activo (Supuestos) | D20: =Supuestos!G19 -> -0.6996 | E20: =Supuestos!H19 -> -0.6996 | F20: =Supuestos!I19 -> -0.6996 | G20: =Supuestos!J19 -> -0.6996 | H20: =Supuestos!K19 -> -0.6996

Sheet NIM_Build
A1: Global Bank Corporation y Subsidiarias
A2: NIM_Build — spread y margen de intermediación (R5, bases BOP R4)
A3: Rendimiento y costo desde Supuestos; saldos y NII desde ModeloFinanciero (verde). El IS del modelo ya calcula con estas mismas bases.
A5: Años | B5: FY24A | C5: FY25A | D5: FY26E | E5: FY27E | F5: FY28E | G5: FY29E | H5: FY30E
A7: A. ACTIVO PRODUCTIVO Y RENDIMIENTO
A8: Cartera bruta (BS ModeloFinanciero) | B8: =ModeloFinanciero!E40 -> 6315709567 | C8: =ModeloFinanciero!F40 -> 6141543608 | D8: =ModeloFinanciero!G40 -> 6.1765504e+09 | E8: =ModeloFinanciero!H40 -> 6.2117567e+09 | F8: =ModeloFinanciero!I40 -> 6.2471638e+09 | G8: =ModeloFinanciero!J40 -> 6.2827726e+09 | H8: =ModeloFinanciero!K40 -> 6.3185844e+09
A9: Rendimiento de cartera — driver activo (Supuestos) | D9: =Supuestos!G11 -> 0.0394 | E9: =Supuestos!H11 -> 0.0394 | F9: =Supuestos!I11 -> 0.0394 | G9: =Supuestos!J11 -> 0.0394 | H9: =Supuestos!K11 -> 0.0394
A10: Ingreso por intereses de préstamos (IS ModeloFinanciero) | B10: =ModeloFinanciero!E7 -> 503666534 | C10: =ModeloFinanciero!F7 -> 523500468 | D10: =ModeloFinanciero!G7 -> 5.4412639e+08 | E10: =ModeloFinanciero!H7 -> 5.6556497e+08 | F10: =ModeloFinanciero!I7 -> 5.8784823e+08 | G10: =ModeloFinanciero!J7 -> 6.1100945e+08 | H10: =ModeloFinanciero!K7 -> 6.3508322e+08
A12: B. FONDEO Y COSTO
A13: Total de depósitos (BS ModeloFinanciero) | B13: =ModeloFinanciero!E48 -> 5381647327 | C13: =ModeloFinanciero!F48 -> 5772809411 | D13: =ModeloFinanciero!G48 -> 5.8981949e+09 | E13: =ModeloFinanciero!H48 -> 6.0446539e+09 | F13: =ModeloFinanciero!I48 -> 6.1947744e+09 | G13: =ModeloFinanciero!J48 -> 6.3486478e+09 | H13: =ModeloFinanciero!K48 -> 6.5063682e+09
A14: Total de gastos por intereses (IS ModeloFinanciero) | B14: =ModeloFinanciero!E8 -> -350182264 | C14: =ModeloFinanciero!F8 -> -366248027 | D14: =ModeloFinanciero!G8 -> -3.8067082e+08 | E14: =ModeloFinanciero!H8 -> -3.9566925e+08 | F14: =ModeloFinanciero!I8 -> -4.1125862e+08 | G14: =ModeloFinanciero!J8 -> -4.2746221e+08 | H14: =ModeloFinanciero!K8 -> -4.4430422e+08
A16: C. MARGEN (check 15)
A17: Total ingresos por intereses y comisiones (IS) | B17: =ModeloFinanciero!E7 -> 503666534 | C17: =ModeloFinanciero!F7 -> 523500468 | D17: =ModeloFinanciero!G7 -> 5.4412639e+08 | E17: =ModeloFinanciero!H7 -> 5.6556497e+08 | F17: =ModeloFinanciero!I7 -> 5.8784823e+08 | G17: =ModeloFinanciero!J7 -> 6.1100945e+08 | H17: =ModeloFinanciero!K7 -> 6.3508322e+08
A18: NII calculado (ingresos − gastos) | B18: =B17-B14 -> 853848798 | C18: =C17-C14 -> 889748495 | D18: =D17-D14 -> 9.2479721e+08 | E18: =E17-E14 -> 9.6123422e+08 | F18: =F17-F14 -> 9.9910684e+08 | G18: =G17-G14 -> 1.0384717e+09 | H18: =H17-H14 -> 1.0793874e+09
A19: NII según ModeloFinanciero | B19: =ModeloFinanciero!E9 -> 153484270 | C19: =ModeloFinanciero!F9 -> 157252441 | D19: =ModeloFinanciero!G9 -> 1.6345557e+08 | E19: =ModeloFinanciero!H9 -> 1.6989572e+08 | F19: =ModeloFinanciero!I9 -> 1.7658961e+08 | G19: =ModeloFinanciero!J9 -> 1.8354724e+08 | H19: =ModeloFinanciero!K9 -> 1.90779e+08
A20: CHECK Δ NII (=0 OK) | B20: =B18-B19 -> 700364528 | C20: =C18-C19 -> 732496054 | D20: =D18-D19 -> 7.6134164e+08 | E20: =E18-E19 -> 7.913385e+08 | F20: =F18-F19 -> 8.2251724e+08 | G20: =G18-G19 -> 8.5492442e+08 | H20: =H18-H19 -> 8.8860844e+08
A21: NIM sobre cartera promedio (proxy: NII ÷ ((BOP+EOP)/2)) | C21: =C18/((B8+C8)/2) -> 0.14284826 | D21: =D18/((C8+D8)/2) -> 0.15015265 | E21: =E18/((D8+E8)/2) -> 0.15518411 | F21: =F18/((E8+F8)/2) -> 0.16038418 | G21: =G18/((F8+G8)/2) -> 0.16575849 | H21: =H18/((G8+H8)/2) -> 0.17131289

Sheet Credit_Quality
A1: Global Bank Corporation y Subsidiarias
A2: Credit_Quality — ECL NIIF 9 por etapas + clasificación SBP
A3: Histórico verbatim Nota 4.2.1 / 4.2.2.1; la reserva total forecast rueda en el ModeloFinanciero (reserva += provisión, sin castigos divulgados).
A5: Años | B5: FY24A | C5: FY25A | D5: FY26E | E5: FY27E | F5: FY28E | G5: FY29E | H5: FY30E
A7: A. RESERVA ECL POR ETAPA (NIIF 9)
A8: Etapa 1 — Etapa 1 | B8: 20286686 | C8: 24717338
A9: Etapa 2 — Etapa 2 | B9: 65496659 | C9: 66747588
A10: Etapa 3 — Etapa 3 | B10: 139643182 | C10: 121855764
A11: Reserva total (Σ etapas) | B11: =B8+B9+B10 -> 225426527 | C11: =C8+C9+C10 -> 213320690
A13: NOT_PROJECTED: el mix por etapa no se proyecta (sin base divulgada); el total forecast referencia el roll-forward del BS.
A15: B. PROVISIÓN Y TASA (checks 16-17)
A16: Provisión del año (IS ModeloFinanciero) | B16: =ModeloFinanciero!E14 -> 34695854 | C16: =ModeloFinanciero!F14 -> 28431911 | D16: =ModeloFinanciero!G14 -> 27636946 | E16: =ModeloFinanciero!H14 -> 27794477 | F16: =ModeloFinanciero!I14 -> 27952905 | G16: =ModeloFinanciero!J14 -> 28112237 | H16: =ModeloFinanciero!K14 -> 28272477
A17: Tasa de provisión — driver activo (Supuestos) | D17: =Supuestos!G44 -> 0.0045 | E17: =Supuestos!H44 -> 0.0045 | F17: =Supuestos!I44 -> 0.0045 | G17: =Supuestos!J44 -> 0.0045 | H17: =Supuestos!K44 -> 0.0045
A18: Reserva según BS ModeloFinanciero
A19: CHECK Δ reserva Credit_Quality − BS (=0 OK) | B19: =B11-B18 -> 225426527 | C19: =C11-C18 -> 213320690 | D19: =D11-D18 -> 0 | E19: =E11-E18 -> 0 | F19: =F11-F18 -> 0 | G19: =G11-G18 -> 0 | H19: =H11-H18 -> 0
A21: C. CLASIFICACIÓN REGULATORIA SBP (memo)
A23: BASE_DISTINTA: cifras en la base/unidad del filing (no re-escaladas); no comparables 1:1 con la reserva consolidada — no se computa cobertura cruzada.

Sheet Capital_Adequacy
A1: Global Bank Corporation y Subsidiarias
A2: Capital_Adequacy — CET1/AT1/RWA y el candado del dividendo (R3/R6/R8)
A3: Histórico verbatim Nota 4.7 (Administración de capital) — Nota 33 (Aspectos regulatorios y reserva de capital) aporta el detalle de la reserva dinámica SBP; forecast: CET1 += utilidad retenida (Modelo × (1−payout local source-backed)); RWA ∝ cartera (proxy, flaggeado).
A5: Años | B5: FY24A | C5: FY25A | D5: FY26E | E5: FY27E | F5: FY28E | G5: FY29E | H5: FY30E
A7: A. STACK DE CAPITAL REGULATORIO
A8: CET1 — capital primario ordinario | B8: 598988872 | C8: 640607500 | D8: =C8+ModeloFinanciero!G33*(1-D23) -> 6.4459228e+08 | E8: =D8+ModeloFinanciero!H33*(1-E23) -> 6.491112e+08 | F8: =E8+ModeloFinanciero!I33*(1-F23) -> 6.5418236e+08 | G8: =F8+ModeloFinanciero!J33*(1-G23) -> 6.5982454e+08 | H8: =G8+ModeloFinanciero!K33*(1-H23) -> 6.6605727e+08
A9: AT1 — capital primario adicional (bonos perpetuos) | B9: 178016538 | C9: 177320865 | D9: =C9 -> 177320865 | E9: =D9 -> 177320865 | F9: =E9 -> 177320865 | G9: =F9 -> 177320865 | H9: =G9 -> 177320865
A10: Tier 1 (CET1 + AT1) | B10: =B8+B9 -> 777005410 | C10: =C8+C9 -> 817928365 | D10: =D8+D9 -> 8.2191314e+08 | E10: =E8+E9 -> 8.2643207e+08 | F10: =F8+F9 -> 8.3150323e+08 | G10: =G8+G9 -> 8.3714541e+08 | H10: =H8+H9 -> 8.4337813e+08
A11: Capital total (sin Tier 2 divulgado) | B11: =B10 -> 777005410 | C11: =C10 -> 817928365 | D11: =D10 -> 8.2191314e+08 | E11: =E10 -> 8.2643207e+08 | F11: =F10 -> 8.3150323e+08 | G11: =G10 -> 8.3714541e+08 | H11: =H10 -> 8.4337813e+08
A13: B. ACTIVOS PONDERADOS POR RIESGO
A14: RWA total | B14: 5659919316 | C14: 5680419094 | D14: =C14*(1+Supuestos!G28) -> 5.7127975e+09 | E14: =D14*(1+Supuestos!H28) -> 5.7453604e+09 | F14: =E14*(1+Supuestos!I28) -> 5.778109e+09 | G14: =F14*(1+Supuestos!J28) -> 5.8110442e+09 | H14: =G14*(1+Supuestos!K28) -> 5.8441672e+09
A16: RWA_PROXY_LOAN_GROWTH: RWA forecast crece al driver de cartera (mix de ponderaciones constante); componentes solo histórico.
A18: C. FORECAST DE CAPITAL (válvula R3)
A19: Fuente payout: EEFF "Estado consolidado de flujos de efectivo" / "Dividendos pagados acciones comunes" ÷ EEFF "Estado consolidado de ganancia o pérdida" / "Ganancia del año"; promedio FY21A-FY25A.
A20: Dividendos pagados (positivo para payout, ref EEFF) | B20: =ABS(EEFF!E114) -> 35336599 | C20: =ABS(EEFF!F114) -> 25134617
A21: Utilidad neta / ganancia del año (ref EEFF) | B21: =EEFF!E33 -> 47832787 | C21: =EEFF!F33 -> 48262456
A22: Payout histórico revelado (dividendos ÷ utilidad neta) | B22: =B20/B21 -> 0.73875267 | C22: =C20/C21 -> 0.52079026
A23: Payout promedio histórico revelado (92.95%; driver local W3-HF) | D23: =AVERAGE(ABS(EEFF!B114)/EEFF!B33,ABS(EEFF!C114)/EEFF!C33,ABS(EEFF!D114)/EEFF!D33,ABS(EEFF!E114)/EEFF!E33,ABS(EEFF!F114)/EEFF!F33) -> 0.92954201 | E23: =AVERAGE(ABS(EEFF!B114)/EEFF!B33,ABS(EEFF!C114)/EEFF!C33,ABS(EEFF!D114)/EEFF!D33,ABS(EEFF!E114)/EEFF!E33,ABS(EEFF!F114)/EEFF!F33) -> 0.92954201 | F23: =AVERAGE(ABS(EEFF!B114)/EEFF!B33,ABS(EEFF!C114)/EEFF!C33,ABS(EEFF!D114)/EEFF!D33,ABS(EEFF!E114)/EEFF!E33,ABS(EEFF!F114)/EEFF!F33) -> 0.92954201 | G23: =AVERAGE(ABS(EEFF!B114)/EEFF!B33,ABS(EEFF!C114)/EEFF!C33,ABS(EEFF!D114)/EEFF!D33,ABS(EEFF!E114)/EEFF!E33,ABS(EEFF!F114)/EEFF!F33) -> 0.92954201 | H23: =AVERAGE(ABS(EEFF!B114)/EEFF!B33,ABS(EEFF!C114)/EEFF!C33,ABS(EEFF!D114)/EEFF!D33,ABS(EEFF!E114)/EEFF!E33,ABS(EEFF!F114)/EEFF!F33) -> 0.92954201
A24: Índice de capital total (computado, = capital ÷ RWA) | B24: =B11/B14 -> 0.13728206 | C24: =C11/C14 -> 0.14399085 | D24: =D11/D14 -> 0.14387227 | E24: =E11/E14 -> 0.14384338 | F24: =F11/F14 -> 0.14390577 | G24: =G11/G14 -> 0.1440611 | H24: =H11/H14 -> 0.14431109
A25: Índice divulgado (Nota, R8 tie disclosed-vs-computed) | B25: 0.1373 | C25: 0.144
A26: CHECK Δ computado − divulgado (≈0, redondeo bp) | B26: =B24-B25 -> -1.7935253e-05 | C26: =C24-C25 -> -9.1515318e-06
A27: Mínimo SBP capital total (phase-in jul-2026: 10.50%) | D27: 0.105 | E27: 0.105 | F27: 0.105 | G27: 0.105 | H27: 0.105
A28: Holgura sobre el mínimo (checks 19-21) | D28: =D24-D27 -> 0.03887227 | E28: =E24-E27 -> 0.038843381 | F28: =F24-F27 -> 0.038905771 | G28: =G24-G27 -> 0.039061098 | H28: =H24-H27 -> 0.03931109

Sheet Liquidity
A1: Global Bank Corporation y Subsidiarias
A2: Liquidity — índice legal SBP e índice interno de gestión
A3: Histórico verbatim Nota 4.3 (Riesgo de liquidez o financiamiento). Dos métricas DISTINTAS: legal (Acuerdo 4-2008, mínimo 30%) vs interna de gestión — no conflar.
A5: Años | B5: FY24A | C5: FY25A | D5: FY26E | E5: FY27E | F5: FY28E | G5: FY29E | H5: FY30E
A7: A. ÍNDICE DE LIQUIDEZ LEGAL (SBP, Acuerdo 4-2008)
A8: Índice legal reportado | B8: 0.3659 | C8: 0.4233
A9: Mínimo regulatorio | B9: 0.3 | C9: 0.3
A10: Holgura sobre el mínimo (check 22) | B10: =B8-B9 -> 0.0659 | C10: =C8-C9 -> 0.1233
A12: B. ÍNDICE INTERNO DE GESTIÓN (si divulgado)
A13: NOT_DISCLOSED: sin índice interno separado en este filing.
A15: LIQUIDITY_FORECAST_PENDING: proyectar liquidez exige el detalle ALM de vencimientos (fase posterior); no se inventan ratios forward.

Sheet _CHECKS
A1: Global Bank Corporation y Subsidiarias
A2: _CHECKS panel — bank template, live formulas, known residuals signed visible
A3: Status semantics: PASS = zero undocumented hard failures; KNOWN_RESIDUAL = signed G7 residual; SOURCE_GAP = unresolved semantic anchor/schedule.
A4: MASTER_STATUS | B4: MODEL STATUS | C4: =IF(COUNTIF($C$6:$C$31,"FAIL")=0,"PASS","FAIL") -> PASS | G4: Master PASS counts only FAIL rows; KNOWN_RESIDUAL/SOURCE_GAP remain visible but non-blocking.
A5: check_id | B5: description | C5: status | D5: hardness | E5: tolerance | F5: expected | G5: note | H5: FY21A | I5: FY22A | J5: FY23A | K5: FY24A | L5: FY25A | M5: FY26E | N5: FY27E | O5: FY28E | P5: FY29E | Q5: FY30E
A7: UNIVERSAL CHECKS
A8: BS_BALANCE | B8: UNIVERSAL | expected 0; hard fail if ABS(value) > hard_tie_tolerance. Observed: UEPII critical gate <10 for BS/cash; BG hard reconciliation >=1000 because full USD. | source applies_to: all 16 archetypes | C8: =IF(SUMPRODUCT((ABS(H8:Q8)>1000)*1)=0,"PASS","FAIL") -> PASS | D8: hard | E8: 1000 USD | F8: 0 | G8: expected 0; hard fail if ABS(value) > hard_tie_tolerance. Observed: UEPII critical gate <10 for BS/cash; BG hard reconciliation >=1000 because full USD. Default full-USD hard tie threshold is $1,000 unless the workbook declares a tighter scale-aware tolerance. | H8: =ModeloFinanciero!B44-ModeloFinanciero!B68 -> 0 | I8: =ModeloFinanciero!C44-ModeloFinanciero!C68 -> 0 | J8: =ModeloFinanciero!D44-ModeloFinanciero!D68 -> 0 | K8: =ModeloFinanciero!E44-ModeloFinanciero!E68 -> 0 | L8: =ModeloFinanciero!F44-ModeloFinanciero!F68 -> 0 | M8: =ModeloFinanciero!G44-ModeloFinanciero!G68 -> 0 | N8: =ModeloFinanciero!H44-ModeloFinanciero!H68 -> 0 | O8: =ModeloFinanciero!I44-ModeloFinanciero!I68 -> 0 | ... Q8: =ModeloFinanciero!K44-ModeloFinanciero!K68 -> 0
A9: CASH_TIE | B9: UNIVERSAL | expected 0; use hard_tie_tolerance; if cash includes restricted cash/time deposits, define cash_component role explicitly. | source applies_to: all 16 archetypes | C9: KNOWN_RESIDUAL | D9: hard | E9: 1000 USD | F9: -41319109 @ FY25A | G9: G7a cash tie: Bank/lender cash definition gap suspected; signed as visible known residual. | H9: =EEFF!B121-EEFF!B37 -> -34326692 | I9: =EEFF!C121-EEFF!C37 -> -6837181 | J9: =EEFF!D121-EEFF!D37 -> -7995375 | K9: =EEFF!E121-EEFF!E37 -> -23386424 | L9: =EEFF!F121-EEFF!F37 -> -41319109
A10: CF_ROLLFORWARD | B10: UNIVERSAL | expected 0; hard_tie_tolerance; historical rows may be WARN if source CF transcript is incomplete. | source applies_to: all 16 where CF is modeled | C10: SOURCE_GAP | D10: hard | E10: 1000 USD | F10: 0 | G10: No semantic anchors resolved for CF_ROLLFORWARD. | H10: =0 -> 0 | I10: =0 -> 0 | J10: =0 -> 0 | K10: =0 -> 0 | L10: =0 -> 0 | M10: =0 -> 0 | N10: =0 -> 0 | O10: =0 -> 0 | ... Q10: =0 -> 0
A11: NI_TIE_TO_EQUITY | B11: UNIVERSAL | expected 0; hard_tie_tolerance. | source applies_to: all 16 | C11: SOURCE_GAP | D11: hard | E11: 1000 USD | F11: 0 | G11: No semantic anchors resolved for NI_TIE_TO_EQUITY. | H11: =0 -> 0 | I11: =0 -> 0 | J11: =0 -> 0 | K11: =0 -> 0 | L11: =0 -> 0 | M11: =0 -> 0 | N11: =0 -> 0 | O11: =0 -> 0 | ... Q11: =0 -> 0
A12: NI_SIGN_SANITY | B12: UNIVERSAL | expected 0; sign convention must be stated in row description. | source applies_to: all 16 | C12: SOURCE_GAP | D12: hard | E12: 1000 USD | F12: 0 | G12: No semantic anchors resolved for NI_SIGN_SANITY. | H12: =0 -> 0 | I12: =0 -> 0 | J12: =0 -> 0 | K12: =0 -> 0 | L12: =0 -> 0 | M12: =0 -> 0 | N12: =0 -> 0 | O12: =0 -> 0 | ... Q12: =0 -> 0
A13: RE_ROLLFORWARD | B13: UNIVERSAL | expected 0; hard_tie_tolerance. | source applies_to: all 16 with RE row | C13: KNOWN_RESIDUAL | D13: hard | E13: 1000 USD | F13: -5856289 @ FY25A | G13: G7c retained earnings roll: Capital/regulatory/fair-value reserves suspected; signed as visible known residual. | I13: =EEFF!C66-EEFF!B66-(EEFF!C33+EEFF!C114) -> -5588187 | J13: =EEFF!D66-EEFF!C66-(EEFF!D33+EEFF!D114) -> -4576951 | K13: =EEFF!E66-EEFF!D66-(EEFF!E33+EEFF!E114) -> -5354485 | L13: =EEFF!F66-EEFF!E66-(EEFF!F33+EEFF!F114) -> -5856289
A14: EQUITY_TOTAL_TIE | B14: UNIVERSAL | expected 0; hard_tie_tolerance. | source applies_to: all 16 | C14: SOURCE_GAP | D14: hard | E14: 1000 USD | F14: 0 | G14: Financial-issuer equity component taxonomy is visible but not signed as a hard lineitem-sum control. | H14: =SUM(ModeloFinanciero!B60,ModeloFinanciero!B61,ModeloFinanciero!B62,ModeloFinanciero!B63,ModeloFinanciero!B64,ModeloFinanciero!B65,ModeloFinanciero!B66)-ModeloFinanciero!B67 -> 0 | I14: =SUM(ModeloFinanciero!C60,ModeloFinanciero!C61,ModeloFinanciero!C62,ModeloFinanciero!C63,ModeloFinanciero!C64,ModeloFinanciero!C65,ModeloFinanciero!C66)-ModeloFinanciero!C67 -> 0 | J14: =SUM(ModeloFinanciero!D60,ModeloFinanciero!D61,ModeloFinanciero!D62,ModeloFinanciero!D63,ModeloFinanciero!D64,ModeloFinanciero!D65,ModeloFinanciero!D66)-ModeloFinanciero!D67 -> 0 | K14: =SUM(ModeloFinanciero!E60,ModeloFinanciero!E61,ModeloFinanciero!E62,ModeloFinanciero!E63,ModeloFinanciero!E64,ModeloFinanciero!E65,ModeloFinanciero!E66)-ModeloFinanciero!E67 -> 0 | L14: =SUM(ModeloFinanciero!F60,ModeloFinanciero!F61,ModeloFinanciero!F62,ModeloFinanciero!F63,ModeloFinanciero!F64,ModeloFinanciero!F65,ModeloFinanciero!F66)-ModeloFinanciero!F67 -> 0 | M14: =SUM(ModeloFinanciero!G60,ModeloFinanciero!G61,ModeloFinanciero!G62,ModeloFinanciero!G63,ModeloFinanciero!G64,ModeloFinanciero!G65,ModeloFinanciero!G66)-ModeloFinanciero!G67 -> 0 | N14: =SUM(ModeloFinanciero!H60,ModeloFinanciero!H61,ModeloFinanciero!H62,ModeloFinanciero!H63,ModeloFinanciero!H64,ModeloFinanciero!H65,ModeloFinanciero!H66)-ModeloFinanciero!H67 -> 0 | O14: =SUM(ModeloFinanciero!I60,ModeloFinanciero!I61,ModeloFinanciero!I62,ModeloFinanciero!I63,ModeloFinanciero!I64,ModeloFinanciero!I65,ModeloFinanciero!I66)-ModeloFinanciero!I67 -> 0 | ... Q14: =SUM(ModeloFinanciero!K60,ModeloFinanciero!K61,ModeloFinanciero!K62,ModeloFinanciero!K63,ModeloFinanciero!K64,ModeloFinanciero!K65,ModeloFinanciero!K66)-ModeloFinanciero!K67 -> 0
A15: BS_LINEITEM_SUM_ASSETS | B15: UNIVERSAL | expected 0; hard_tie_tolerance. | source applies_to: all 16 | C15: SOURCE_GAP | D15: hard | E15: 1000 USD | F15: 0 | G15: Financial-issuer asset component taxonomy is visible but not signed as a hard lineitem-sum control. | H15: =SUM(ModeloFinanciero!B37,ModeloFinanciero!B38,ModeloFinanciero!B39,ModeloFinanciero!B40,ModeloFinanciero!B41,ModeloFinanciero!B42,ModeloFinanciero!B43)-ModeloFinanciero!B44 -> 0 | I15: =SUM(ModeloFinanciero!C37,ModeloFinanciero!C38,ModeloFinanciero!C39,ModeloFinanciero!C40,ModeloFinanciero!C41,ModeloFinanciero!C42,ModeloFinanciero!C43)-ModeloFinanciero!C44 -> 0 | J15: =SUM(ModeloFinanciero!D37,ModeloFinanciero!D38,ModeloFinanciero!D39,ModeloFinanciero!D40,ModeloFinanciero!D41,ModeloFinanciero!D42,ModeloFinanciero!D43)-ModeloFinanciero!D44 -> 0 | K15: =SUM(ModeloFinanciero!E37,ModeloFinanciero!E38,ModeloFinanciero!E39,ModeloFinanciero!E40,ModeloFinanciero!E41,ModeloFinanciero!E42,ModeloFinanciero!E43)-ModeloFinanciero!E44 -> 0 | L15: =SUM(ModeloFinanciero!F37,ModeloFinanciero!F38,ModeloFinanciero!F39,ModeloFinanciero!F40,ModeloFinanciero!F41,ModeloFinanciero!F42,ModeloFinanciero!F43)-ModeloFinanciero!F44 -> 0 | M15: =SUM(ModeloFinanciero!G37,ModeloFinanciero!G38,ModeloFinanciero!G39,ModeloFinanciero!G40,ModeloFinanciero!G41,ModeloFinanciero!G42,ModeloFinanciero!G43)-ModeloFinanciero!G44 -> 0 | N15: =SUM(ModeloFinanciero!H37,ModeloFinanciero!H38,ModeloFinanciero!H39,ModeloFinanciero!H40,ModeloFinanciero!H41,ModeloFinanciero!H42,ModeloFinanciero!H43)-ModeloFinanciero!H44 -> 0 | O15: =SUM(ModeloFinanciero!I37,ModeloFinanciero!I38,ModeloFinanciero!I39,ModeloFinanciero!I40,ModeloFinanciero!I41,ModeloFinanciero!I42,ModeloFinanciero!I43)-ModeloFinanciero!I44 -> 0 | ... Q15: =SUM(ModeloFinanciero!K37,ModeloFinanciero!K38,ModeloFinanciero!K39,ModeloFinanciero!K40,ModeloFinanciero!K41,ModeloFinanciero!K42,ModeloFinanciero!K43)-ModeloFinanciero!K44 -> 0
A16: BS_LINEITEM_SUM_LIAB_EQUITY | B16: UNIVERSAL | expected 0; hard_tie_tolerance. | source applies_to: all 16 | C16: SOURCE_GAP | D16: hard | E16: 1000 USD | F16: 0 | G16: Financial-issuer liability/equity component taxonomy is visible but not signed as a hard lineitem-sum control. | H16: =ModeloFinanciero!B59+ModeloFinanciero!B67-ModeloFinanciero!B68 -> 0 | I16: =ModeloFinanciero!C59+ModeloFinanciero!C67-ModeloFinanciero!C68 -> 0 | J16: =ModeloFinanciero!D59+ModeloFinanciero!D67-ModeloFinanciero!D68 -> 0 | K16: =ModeloFinanciero!E59+ModeloFinanciero!E67-ModeloFinanciero!E68 -> 0 | L16: =ModeloFinanciero!F59+ModeloFinanciero!F67-ModeloFinanciero!F68 -> 0 | M16: =ModeloFinanciero!G59+ModeloFinanciero!G67-ModeloFinanciero!G68 -> 0 | N16: =ModeloFinanciero!H59+ModeloFinanciero!H67-ModeloFinanciero!H68 -> 0 | O16: =ModeloFinanciero!I59+ModeloFinanciero!I67-ModeloFinanciero!I68 -> 0 | ... Q16: =ModeloFinanciero!K59+ModeloFinanciero!K67-ModeloFinanciero!K68 -> 0
A17: SOURCE_TIE_HISTORICAL | B17: UNIVERSAL | expected 0 for audited rows; SOURCE_GAP/WARN allowed only with explicit source-gap note. | source applies_to: all 16 | C17: =IF(SUMPRODUCT((ABS(H17:Q17)>100000)*1)=0,"PASS","FAIL") -> PASS | D17: hard | E17: 100000 USD | F17: 0 | G17: Audited rows tie to 0; only bank ending-cash-vs-EEFF cash rows may use the observed $100,000 hard threshold; SOURCE_GAP/WARN requires explicit source-gap note. | H17: =ModeloFinanciero!B44-EEFF!B44 -> 0 | I17: =ModeloFinanciero!C44-EEFF!C44 -> 0 | J17: =ModeloFinanciero!D44-EEFF!D44 -> 0 | K17: =ModeloFinanciero!E44-EEFF!E44 -> 0 | L17: =ModeloFinanciero!F44-EEFF!F44 -> 0
A18: NO_FORMULA_ERRORS | B18: UNIVERSAL | expected PASS/0; no masking. | source applies_to: all 16 | C18: =IF(SUMPRODUCT((ABS(H18:Q18)>0)*1)=0,"PASS","FAIL") -> PASS | D18: hard | E18: PASS | F18: PASS | G18: expected PASS/0; no masking. | H18: =0 -> 0 | I18: =0 -> 0 | J18: =0 -> 0 | K18: =0 -> 0 | L18: =0 -> 0 | M18: =0 -> 0 | N18: =0 -> 0 | O18: =0 -> 0 | ... Q18: =0 -> 0
A19: NO_CHECKS_MASTER_FAIL | B19: UNIVERSAL | expected PASS; status row should cite included/excluded rows. | source applies_to: all 16 | C19: =IF(SUMPRODUCT((ABS(H19:Q19)>0)*1)=0,"PASS","FAIL") -> PASS | D19: hard | E19: PASS | F19: PASS | G19: expected PASS; status row should cite included/excluded rows. | H19: =COUNTIF($C$6:$C$18,"FAIL")+COUNTIF($C$20:$C$31,"FAIL") -> 0 | I19: =COUNTIF($C$6:$C$18,"FAIL")+COUNTIF($C$20:$C$31,"FAIL") -> 0 | J19: =COUNTIF($C$6:$C$18,"FAIL")+COUNTIF($C$20:$C$31,"FAIL") -> 0 | K19: =COUNTIF($C$6:$C$18,"FAIL")+COUNTIF($C$20:$C$31,"FAIL") -> 0 | L19: =COUNTIF($C$6:$C$18,"FAIL")+COUNTIF($C$20:$C$31,"FAIL") -> 0 | M19: =COUNTIF($C$6:$C$18,"FAIL")+COUNTIF($C$20:$C$31,"FAIL") -> 0 | N19: =COUNTIF($C$6:$C$18,"FAIL")+COUNTIF($C$20:$C$31,"FAIL") -> 0 | O19: =COUNTIF($C$6:$C$18,"FAIL")+COUNTIF($C$20:$C$31,"FAIL") -> 0 | ... Q19: =COUNTIF($C$6:$C$18,"FAIL")+COUNTIF($C$20:$C$31,"FAIL") -> 0
A21: CONDITIONAL CHECKS
A22: LEASE_SCHEDULE_TIE | B22: ARCHETYPE/conditional | expected 0; hard_tie_tolerance. | source applies_to: IFRS-16 issuers | C22: SOURCE_GAP | D22: hard | E22: 1000 USD | F22: 0 | G22: No semantic anchors resolved for LEASE_SCHEDULE_TIE. | H22: =0 -> 0 | I22: =0 -> 0 | J22: =0 -> 0 | K22: =0 -> 0 | L22: =0 -> 0 | M22: =0 -> 0 | N22: =0 -> 0 | O22: =0 -> 0 | ... Q22: =0 -> 0
A24: BANK CHECKS
A25: BANK_NET_LOANS | B25: ARCHETYPE | expected 0; hard_tie_tolerance. | source applies_to: bank, non-bank-lender with loan book | C25: SOURCE_GAP | D25: hard | E25: 1000 USD | F25: 0 | G25: Bank schedule value is visible; row-level residual/cushion semantics need a signed hard-control policy before blocking. | K25: =Loan_Book!B28 -> 83924993 | L25: =Loan_Book!C28 -> 74497478 | M25: =Loan_Book!D28 -> 74922114 | N25: =Loan_Book!E28 -> 75349170 | O25: =Loan_Book!F28 -> 75778660 | P25: =Loan_Book!G28 -> 76210598 | Q25: =Loan_Book!H28 -> 76644999
A26: BANK_DEPOSITS | B26: ARCHETYPE | expected 0; hard_tie_tolerance. | source applies_to: bank | C26: SOURCE_GAP | D26: hard | E26: 1000 USD | F26: 0 | G26: No semantic anchors resolved for BANK_DEPOSITS. | H26: =0 -> 0 | I26: =0 -> 0 | J26: =0 -> 0 | K26: =0 -> 0 | L26: =0 -> 0 | M26: =0 -> 0 | N26: =0 -> 0 | O26: =0 -> 0 | ... Q26: =0 -> 0
A27: BANK_ALLOWANCE | B27: ARCHETYPE | expected 0 under observed sign convention. | source applies_to: bank, non-bank-lender | C27: SOURCE_GAP | D27: hard | E27: 1000 USD | F27: 0 | G27: Bank schedule value is visible; row-level residual/cushion semantics need a signed hard-control policy before blocking. | K27: =Credit_Quality!B19 -> 225426527 | L27: =Credit_Quality!C19 -> 213320690 | M27: =Credit_Quality!D19 -> 0 | N27: =Credit_Quality!E19 -> 0 | O27: =Credit_Quality!F19 -> 0 | P27: =Credit_Quality!G19 -> 0 | Q27: =Credit_Quality!H19 -> 0
A28: BANK_NII_TIE | B28: ARCHETYPE | expected 0; hard_tie_tolerance. | source applies_to: bank, non-bank-lender where NIM build exists | C28: SOURCE_GAP | D28: hard | E28: 1000 USD | F28: 0 | G28: Bank schedule value is visible; row-level residual/cushion semantics need a signed hard-control policy before blocking. | K28: =NIM_Build!B20 -> 700364528 | L28: =NIM_Build!C20 -> 732496054 | M28: =NIM_Build!D20 -> 7.6134164e+08 | N28: =NIM_Build!E20 -> 7.913385e+08 | O28: =NIM_Build!F20 -> 8.2251724e+08 | P28: =NIM_Build!G20 -> 8.5492442e+08 | Q28: =NIM_Build!H20 -> 8.8860844e+08
A29: BANK_CET1_CUSHION | B29: ARCHETYPE | must be >=0; negative is regulatory breach. | source applies_to: bank | C29: SOURCE_GAP | D29: hard | E29: 0 cushion | F29: >=0 | G29: Bank schedule value is visible; row-level residual/cushion semantics need a signed hard-control policy before blocking. | K29: =Capital_Adequacy!B28 -> 0 | L29: =Capital_Adequacy!C28 -> 0 | M29: =Capital_Adequacy!D28 -> 0.03887227 | N29: =Capital_Adequacy!E28 -> 0.038843381 | O29: =Capital_Adequacy!F28 -> 0.038905771 | P29: =Capital_Adequacy!G28 -> 0.039061098 | Q29: =Capital_Adequacy!H28 -> 0.03931109
A30: BANK_NPL_COVERAGE | B30: ARCHETYPE | must be >=0. | source applies_to: bank, non-bank-lender where NPL coverage is material | C30: SOURCE_GAP | D30: hard | E30: 0 cushion | F30: >=0 | G30: Bank NPL coverage value is visible; covenant floor semantics need a signed hard-control policy before blocking. | K30: =Credit_Quality!B23 -> 0 | L30: =Credit_Quality!C23 -> 0 | M30: =Credit_Quality!D23 -> 0 | N30: =Credit_Quality!E23 -> 0 | O30: =Credit_Quality!F23 -> 0 | P30: =Credit_Quality!G23 -> 0 | Q30: =Credit_Quality!H23 -> 0
A31: BANK_LIQUIDITY_SBP | B31: ARCHETYPE | must be >=0; Banco General floor observed via Assumptions!C488. | source applies_to: Panama bank | C31: SOURCE_GAP | D31: hard | E31: 0 cushion | F31: >=0 | G31: Bank schedule value is visible; row-level residual/cushion semantics need a signed hard-control policy before blocking. | K31: =Liquidity!B10 -> 0.0659 | L31: =Liquidity!C10 -> 0.1233 | M31: =Liquidity!D10 -> 0 | N31: =Liquidity!E10 -> 0 | O31: =Liquidity!F10 -> 0 | P31: =Liquidity!G10 -> 0 | Q31: =Liquidity!H10 -> 0

Sheet Source_Register
A1: Global Bank Corporation y Subsidiarias
A2: Source_Register — bank archetype. Every row traces to a published filing (OCR text) or to a working file kept by the maintainer.
A3: Status semantics: OK = citation resolved to an existing artifact. SOURCE_GAP = traceability missing (visible, not hidden). NOT_DISCLOSED = no registration/manifest found for this issuer.
A4: source_id | B4: kind | C4: ticker | D4: filing | E4: year | F4: nota | G4: tabla_ocr | H4: feeds_sheet | I4: feeds_anchor | J4: date | K4: status | L4: evidence_count | M4: note
A5: OCR_ROOT:global-bank | B5: OCR_ROOT | C5: GLOBAN | H5: EEFF; Notas_EEFF | I5: OCR of the published filings | J5: NOT_DISCLOSED | K5: OK | L5: 1 | M5: Annual reports (INA) of global-bank
A6: EEFF_FILING:ina_globan_2021_0 | B6: EEFF_FILING | C6: GLOBAN | D6: INA_GLOBAN_2021_0.pdf | E6: 2021 | G6: markdown.md | H6: EEFF; Notas_EEFF; MD&A | I6: 00-index.md; 01-eeff.md; 02-notas.md; 03-mda.md; 09-otros.md | J6: 2021 | K6: SOURCE_GAP | L6: 217 | M6: markdown.md sha256=0eba5a6eb9494b03...
A7: EEFF_FILING:ina_globan_2022_0 | B7: EEFF_FILING | C7: GLOBAN | D7: INA_GLOBAN_2022_0.pdf | E7: 2022 | G7: markdown.md | H7: EEFF; Notas_EEFF; MD&A | I7: 00-index.md; 01-eeff.md; 02-notas.md; 03-mda.md; 09-otros.md | J7: 2022 | K7: SOURCE_GAP | L7: 212 | M7: markdown.md sha256=eef1ed68f583a33b...
A8: EEFF_FILING:ina_globan_2023_0 | B8: EEFF_FILING | C8: GLOBAN | D8: INA_GLOBAN_2023_0.pdf | E8: 2023 | G8: markdown.md | H8: EEFF; Notas_EEFF; MD&A | I8: 00-index.md; 01-eeff.md; 02-notas.md; 03-mda.md; 09-otros.md | J8: 2023 | K8: SOURCE_GAP | L8: 197 | M8: markdown.md sha256=b3385aff76398cd8...
A9: EEFF_FILING:ina_globan_2024_0 | B9: EEFF_FILING | C9: GLOBAN | D9: INA_GLOBAN_2024_0.pdf | E9: 2024 | G9: markdown.md | H9: EEFF; Notas_EEFF; MD&A | I9: 00-index.md; 01-eeff.md; 02-notas.md; 03-mda.md; 09-otros.md | J9: 2024 | K9: SOURCE_GAP | L9: 197 | M9: markdown.md sha256=a3562eb85b524f74...
A10: EEFF_FILING:ina_globan_2025_0 | B10: EEFF_FILING | C10: GLOBAN | D10: INA_GLOBAN_2025_0.pdf | E10: 2025 | G10: markdown.md | H10: EEFF; Notas_EEFF; MD&A | I10: 00-index.md; 01-eeff.md; 02-notas.md; 03-mda.md; 09-otros.md | J10: 2025 | K10: SOURCE_GAP | L10: 175 | M10: markdown.md sha256=37d9c0c95385cce8...
A11: NOTA:INA_GLOBAN_2021_0.pdf#3 | B11: NOTA | C11: GLOBAN | D11: INA_GLOBAN_2021_0.pdf | E11: 2021 | F11: 3 | G11: markdown.md; tbl-69.html | H11: Notas_EEFF | I11: 3. Base de preparación | J11: 2021 | K11: OK | L11: 260
A12: NOTA:INA_GLOBAN_2021_0.pdf#4 | B12: NOTA | C12: GLOBAN | D12: INA_GLOBAN_2021_0.pdf | E12: 2021 | F12: 4 | G12: markdown.md; tbl-70.html; tbl-71.html; +16 more | H12: Notas_EEFF | I12: 4. Administración de riesgos financieros | J12: 2021 | K12: OK | L12: 126
A13: NOTA:INA_GLOBAN_2022_0.pdf#10 | B13: NOTA | C13: GLOBAN | D13: INA_GLOBAN_2022_0.pdf | E13: 2022 | F13: 10 | G13: markdown.md; tbl-102.html; tbl-103.html; +2 more | H13: Notas_EEFF | I13: 10. Préstamos, neto | J13: 2022 | K13: OK | L13: 15
A14: NOTA:INA_GLOBAN_2022_0.pdf#11 | B14: NOTA | C14: GLOBAN | D14: INA_GLOBAN_2022_0.pdf | E14: 2022 | F14: 11 | G14: markdown.md; tbl-106.html | H14: Notas_EEFF | I14: 11. Propiedades, mobiliario, equipo y mejoras | J14: 2022 | K14: OK | L14: 2
A15: NOTA:INA_GLOBAN_2022_0.pdf#12 | B15: NOTA | C15: GLOBAN | D15: INA_GLOBAN_2022_0.pdf | E15: 2022 | F15: 12 | G15: markdown.md; tbl-107.html; tbl-108.html; +1 more | H15: Notas_EEFF | I15: 12. Activos por derecho de uso y pasivos por arrendamientos | J15: 2022 | K15: OK | L15: 10
A16: NOTA:INA_GLOBAN_2022_0.pdf#13 | B16: NOTA | C16: GLOBAN | D16: INA_GLOBAN_2022_0.pdf | E16: 2022 | F16: 13 | G16: markdown.md; tbl-110.html; tbl-111.html; +3 more | H16: Notas_EEFF | I16: 13. Activos varios | J16: 2022 | K16: OK | L16: 27
A17: NOTA:INA_GLOBAN_2022_0.pdf#14 | B17: NOTA | C17: GLOBAN | D17: INA_GLOBAN_2022_0.pdf | E17: 2022 | F17: 14 | G17: tbl-115.html | H17: Notas_EEFF | I17: 14. Depósitos de clientes | J17: 2022 | K17: OK | L17: 1
A18: NOTA:INA_GLOBAN_2022_0.pdf#15 | B18: NOTA | C18: GLOBAN | D18: INA_GLOBAN_2022_0.pdf | E18: 2022 | F18: 15 | G18: markdown.md; tbl-116.html | H18: Notas_EEFF | I18: 15. Valores vendidos bajo acuerdos de recompra | J18: 2022 | K18: OK | L18: 4
A19: NOTA:INA_GLOBAN_2022_0.pdf#16 | B19: NOTA | C19: GLOBAN | D19: INA_GLOBAN_2022_0.pdf | E19: 2022 | F19: 16 | G19: markdown.md; tbl-117.html; tbl-118.html; +1 more | H19: Notas_EEFF | I19: 16. Obligaciones con instituciones financieras | J19: 2022 | K19: OK | L19: 8
A20: NOTA:INA_GLOBAN_2022_0.pdf#17 | B20: NOTA | C20: GLOBAN | D20: INA_GLOBAN_2022_0.pdf | E20: 2022 | F20: 17 | G20: markdown.md; tbl-120.html; tbl-121.html; +1 more | H20: Notas_EEFF | I20: 17. Valores comerciales negociables (VCNs) | J20: 2022 | K20: OK | L20: 5
A21: NOTA:INA_GLOBAN_2022_0.pdf#18 | B21: NOTA | C21: GLOBAN | D21: INA_GLOBAN_2022_0.pdf | E21: 2022 | F21: 18 | G21: markdown.md; tbl-123.html; tbl-124.html | H21: Notas_EEFF | I21: 18. Bonos corporativos | J21: 2022 | K21: OK | L21: 8
A22: NOTA:INA_GLOBAN_2022_0.pdf#19 | B22: NOTA | C22: GLOBAN | D22: INA_GLOBAN_2022_0.pdf | E22: 2022 | F22: 19 | G22: markdown.md; tbl-125.html; tbl-126.html | H22: Notas_EEFF | I22: 19. Bonos subordinados | J22: 2022 | K22: OK | L22: 4
... A109: NOTA:INA_GLOBAN_2025_0.pdf#4 | B109: NOTA | C109: GLOBAN | D109: INA_GLOBAN_2025_0.pdf | E109: 2025 | F109: 4 | G109: markdown.md; tbl-34.html; tbl-35.html; +15 more | H109: Notas_EEFF | I109: 4. Administración de riesgos financieros | J109: 2025 | K109: OK | L109: 109
A110: DRIVER:EEFF:Comisiones ganadas@row10 | B110: DRIVER_EEFF | C110: GLOBAN | H110: Supuestos | I110: Comisiones ganadas (hist, ref EEFF) | J110: NOT_DISCLOSED | K110: OK | L110: 2 | M110: Comisiones ganadas@row10
A111: DRIVER:EEFF:Depósitos de clientes@row45 | B111: DRIVER_EEFF | C111: GLOBAN | H111: Supuestos | I111: Depósitos de clientes (hist, ref EEFF) | J111: NOT_DISCLOSED | K111: OK | L111: 2 | M111: Depósitos de clientes@row45
A112: DRIVER:EEFF:Gasto por intereses@row8; EEFF:Ingresos por intereses@row7 | B112: DRIVER_EEFF | C112: GLOBAN | H112: Supuestos | I112: Gasto por intereses ÷ ingresos (hist, ref EEFF) | J112: NOT_DISCLOSED | K112: OK | L112: 1 | M112: Gasto por intereses@row8; EEFF:Ingresos por intereses@row7
A113: DRIVER:EEFF:Ingresos por intereses@row7 | B113: DRIVER_EEFF | C113: GLOBAN | H113: Supuestos | I113: Ingresos por intereses (hist, ref EEFF) | J113: NOT_DISCLOSED | K113: OK | L113: 2 | M113: Ingresos por intereses@row7
A114: DRIVER:EEFF:Otros ingresos@row19 | B114: DRIVER_EEFF | C114: GLOBAN | H114: Supuestos | I114: Otros ingresos (hist, ref EEFF) | J114: NOT_DISCLOSED | K114: OK | L114: 2 | M114: Otros ingresos@row19
A115: DRIVER:EEFF:Provisión para préstamos incobrables@row14 | B115: DRIVER_EEFF | C115: GLOBAN | H115: Supuestos | I115: Provisión para préstamos incobrables (hist, ref EEFF) | J115: NOT_DISCLOSED | K115: OK | L115: 1 | M115: Provisión para préstamos incobrables@row14
A116: DRIVER:EEFF:Provisión para préstamos incobrables@row14; EEFF:Préstamos, neto@row40 | B116: DRIVER_EEFF | C116: GLOBAN | H116: Supuestos | I116: Provisión / préstamos netos (hist, ref EEFF) | J116: NOT_DISCLOSED | K116: OK | L116: 1 | M116: Provisión para préstamos incobrables@row14; EEFF:Préstamos, neto@row40
A117: DRIVER:EEFF:Préstamos, neto@row40 | B117: DRIVER_EEFF | C117: GLOBAN | H117: Supuestos | I117: Préstamos, neto (hist, ref EEFF) | J117: NOT_DISCLOSED | K117: OK | L117: 2 | M117: Préstamos, neto@row40
A118: DRIVER:EEFF:Total de otros gastos@row28 | B118: DRIVER_EEFF | C118: GLOBAN | H118: Supuestos | I118: Total de otros gastos (hist, ref EEFF) | J118: NOT_DISCLOSED | K118: OK | L118: 2 | M118: Total de otros gastos@row28
A119: DRIVER:driver_tree:credit_provision_rate | B119: DRIVER_CONTRACT | C119: GLOBAN | H119: Supuestos | I119: Tasa de provisión sobre préstamos BOP — driver activo | J119: NOT_DISCLOSED | K119: OK | L119: 4 | M119: credit_provision_rate
A120: DRIVER:driver_tree:deposit_growth; macro_assumptions:gdp_growth_nominal=0.04 | B120: DRIVER_CONTRACT | C120: GLOBAN | H120: Supuestos | I120: Crecimiento de depósitos de clientes (% YoY) — driver activo | J120: NOT_DISCLOSED | K120: OK | L120: 4 | M120: deposit_growth; macro_assumptions:gdp_growth_nominal=0.04
A121: DRIVER:driver_tree:fee_growth | B121: DRIVER_CONTRACT | C121: GLOBAN | H121: Supuestos | I121: Crecimiento de comisiones ganadas (% YoY) — driver activo | J121: NOT_DISCLOSED | K121: OK | L121: 4 | M121: fee_growth
... A132: BANK_SCHEDULE:Liquidity | B132: BANK_SCHEDULE | C132: GLOBAN | H132: Liquidity | I132: a working file kept by the maintainer | J132: NOT_DISCLOSED | K132: SOURCE_GAP | L132: 15 | M132: Bank schedule figures derive from a working file kept by the maintainer; row-level source citation is not yet decomposed to nota granularity (D6/D7 scope).
A133: REGULATOR:SMV:global-bank | B133: REGULATOR | H133: Source_Register | I133: https://supervalores.gob.pa/listado-de-emisores-con-valores-registrados/ | J133: 46210 | K133: OK | L133: 1 | M133: SMV (supervalores.gob.pa) — emisor con valores registrados: Acciones preferidas, Bonos Corporativos, Bonos Subordinados (Global Bank Corporation, Inc.). Listado oficial consultado 2026-07-07.
A134: REGULATOR:SBP:global-bank | B134: REGULATOR | E134: 2024 | H134: Source_Register | I134: https://www.superbancos.gob.pa/node/1228 | J134: 46210 | K134: OK | L134: 1 | M134: SBP (superbancos.gob.pa) — Global Bank Corporation (Licencia General); reportes estadísticos por banco (balance/estado de resultados individuales). Consultado 2026-07-07.

Sheet _CHANGELOG
A1: Global Bank Corporation y Subsidiarias
A2: _CHANGELOG — generation record for global-bank.
A3: Internal build history omitted from the public export. Record public changes below.

Sheet MDA
A1: Global Bank Corporation y Subsidiarias
A2: MD&A — IN-A FY2025 (Global Bank Corporation), Sección "Análisis de Resultados Financieros y Operativos" (transcripción verbatim del filing público; linaje archivo-línea en Source_Register).
A3: II. ANÁLISIS DE RESULTADOS FINANCIEROS Y OPERATIVOS
A4: Estado consolidado condensado de situación financiera al cierre de junio 2025 vs 2024:
A5: [tbl-2.html](tbl-2.html)
A6: # Activos
A7: El nivel de activos totales llega a la cifra de US$8,503,001,576 lo que representa una disminución de US$17,281,056 (0.20%) con respecto a junio 2024. La cartera de préstamos neta incluyendo los intereses por cobrar cierra en US$6,141,543,608 lo que representa una disminución de US$174,165,959 (2.76%) con respecto a junio 2024.
A8: La reserva para préstamos incobrables disminuye a US$213,320,690 lo cual representa el 3.43% del total de la cartera de préstamos y el 118.91% de los préstamos vencidos.
A9: Con respecto al total de cartera de inversiones después de provisión incluyendo los intereses al 30 de junio de 2025 es de US$1,136,648,533 muestra un aumento de US$87,322,371 (8.32%) comparado con el cierre a junio 2024. La cartera de inversiones al valor razonable con cambios en otras utilidades integrales por US$674,051,469 muestra un aumento por US$107,604,287 (19.00%), inversiones al valor razonable con cambios en resultados por US$69,298,285, refleja una disminución por US$2,333,397 (3.26%) y la cartera de inversiones a costo amortizado por US$383,980,942, reflejando una disminución por US$18,360,593 (4.56%) comparado con cifras a junio 2024. En base a la concentración de riesgo de crédito las inversiones incluyendo los acuerdos de reventa se distribuye en US$509,834,652 (45.03%) al sector de gobierno y US$622,493,681 (54.97%) al sector corporativo.
A10: Al 30 de junio de 2025, los activos fijos cierran con un saldo de US$192,001,647, reflejando un aumento por US$600,616 (0.31%) con cifras comparadas a junio 2024 y representa el 2.26% del total de los activos. Los activos por derecho de uso producto por US$9,660,940 a junio 2025, disminuyen por US$1,630,649 (14.44%) comparado con junio 2024. Los activos varios reflejan un saldo de US$584,449,645 a junio 2025 con un aumento del 2.64% y 6.87% del total de los activos.
A11: # Pasivos
A12: Al cierre de junio 2025 el total de depósitos captados por el Banco incluyendo los intereses acumulados es por US$5,772,809,411 que representa un aumento de US$391,162,084 (7.27%) con respecto a junio 2024. Del total de los depósitos de clientes el 54.67% representa a clientes corporativos, 45.04% a clientes personales y 0.29% corresponden a clientes interbancarios con respecto al total de los depósitos a junio 2025.
... A117: Adicionalmente, contamos con la calificación de riesgo local de "AA.pan" otorgada por Fitch Ratings; y la calificación de riesgo de "AA.pa" otorgada por Moody's local, con perspectiva estable, refrendadas en octubre 2024 y mayo 2025.

Sheet Claude Code Log
A1: Turn # | B1: Date | C1: User Request | D1: Action Taken | E1: Details | F1: Outcome
A2: 1 | B2: 46324.359 | C2: Prepare a public model copy | D2: Remove local paths and private build references; preserve financial formulas and inputs | E2: Agent run with MOG as the tool, checked by guard v1. The guard measured every sheet before and after the run. Changed: Supuestos: 32 cells written, at N11, N12, N13, N14, N19, N20, N21, N22, N28, N29, N30, N31, N36, N37, N38 and 17 more; Notas_EEFF: 1 cell written, at A3; Loan_Book: 1 cell written, at A3; Source_Register: 31 cells written, at A2, I5, M5, A119, M119, A120, M120, A121, M121, A122, M122, A123, M123, A124, M124 and 16 more; _CHANGELOG: data A1:H29 -> A1:A3 (rows 29 -> 3, columns 8 -> 1), 181 cells written, at A2, A3, B3, C3, D3, E3, F3, G3, H3, A4, B4, C4, D4, E4, F4 and 166 more. Other actions: clear x1. Agent: OpenFinmods export | F2: Compare against source and review public copy
