Workbook

Sheet Claude Log
A1: Turn # | B1: Date | C1: User Request | D1: Action Taken | E1: Details | F1: Outcome
A2: 1 | B2: 2026-10-27 | C2: Fill up the blank cells in the selected drivers block (Assumptions!A52:K76). | D2: Filled history (2019A-2025A) on the Active rows and the 2026E column for price per ad, other revenue, Reality Labs and DAP. | E2: History links to Revenue_Hist rows 27, 28, 30 and growth of rows 8 and 10 (2019A blank: no prior year). 2026E Base/Bull/Bear derived from Interim_Bridge and the Q4 guidance inputs (J:L rows 10, 13, 14); DAP 2026E = Sep 2026 / Dec 2025 average. Active row = CHOOSE on $B$5. Formats: 0.00%, italic, green for cross-sheet links. Neighbouring cells still show 0.0%, not touched. | F2: Assumptions!I61 equals Revenue_Build!C8 (12.65%). Rows 77+ (cash costs, legal charges) were outside the selection and not reviewed.
A3: 2 | B3: 2026-10-27 | C3: Asked to fill the rest of the drivers block (Assumptions!A52:K111). | D3: Filled history on Active rows 81, 91, 101, 111 (2019A-2025A), H96, H106 and 2026E Base/Bull/Bear + Active for cash costs, legal charges, RL operating loss and DPS growth. | E3: Cash costs = (total costs - D&A) / revenue, legal charges not stripped from history (none tagged in the workbook). Capex = -(PP&E purchases + finance-lease principal). Tax = provision / pre-tax. Buybacks = repurchases / (CFO - capex - dividends - RSU tax). 2026E: cash costs from guidance J:L rows 10-11 less legal and D&A; legal = Interim_Bridge!D13; RL = 9M + Q4 scenario; DPS = I39 vs 2025A. Tax and buybacks 2026E left blank (label says 2027E onward; 2026E set by bridge inputs). | F3: Base 2026E cash costs 53.63% (ties to note 53.6%); RL Base (18,500). Open: legal history B:H, RL history B:G, DPS 2024A growth not in workbook.

Sheet 00_Cover
A1: Meta Platforms, Inc. (Facebook, Inc. until 28 October 2021) | Financial model: statements as filed, 10-year forecast, valuation and credit
A3: What this workbook holds
A4: Every line of the five audited statements in each Form 10-K for fiscal 2019 to fiscal 2025.
A5: The statements: income, comprehensive income, balance sheet, stockholders' equity, cash flows.
A6: The nine months to 30 September 2025 and 2026 come from the Q3 Form 10-Q. These are not audited.
A7: Forecast 2026E-2035E with Base, Bull and Bear (switch: Assumptions!C5); valuation (DCF, FCFE, reverse DCF, comps, sum of the parts); credit metrics.
A8: How to read it
A9: Each period comes from the filing that first reported it. A later recast is listed on the Recasts sheet, not applied.
A10: Units: USD millions, except per-share amounts (USD) and share counts (millions).
A11: Signs follow the filing. A number in parentheses in the filing is negative here.
A12: A dash means the filing shows a dash or zero. An empty cell means the filing does not show that line for that period.
A13: If a filing changed only the wording of a line, the line keeps one row. Column O shows the earlier wording.
... A17: Source of every number: the inline XBRL of the filing on SEC EDGAR (CIK 0001326801).
A19: Master check (all checks on the Checks sheet) | D19: =Checks!C4 -> OK
A21: Filing | B21: Form | C21: Period end | D21: Filed | E21: Accession number | F21: Columns taken from it | G21: Link
A22: Form 10-K for fiscal 2019 | B22: 10-K | C22: 43830 | D22: 43860 | E22: 0001326801-20-000013 | F22: 2019A | G22: https://www.sec.gov/Archives/edgar/data/1326801/000132680120000013/fb-12312019x10k.htm
A23: Form 10-K for fiscal 2020 | B23: 10-K | C23: 44196 | D23: 44224 | E23: 0001326801-21-000014 | F23: 2020A | G23: https://www.sec.gov/Archives/edgar/data/1326801/000132680121000014/fb-20201231.htm
A24: Form 10-K for fiscal 2021 | B24: 10-K | C24: 44561 | D24: 44595 | E24: 0001326801-22-000018 | F24: 2021A | G24: https://www.sec.gov/Archives/edgar/data/1326801/000132680122000018/fb-20211231.htm
A25: Form 10-K for fiscal 2022 | B25: 10-K | C25: 44926 | D25: 44959 | E25: 0001326801-23-000013 | F25: 2022A | G25: https://www.sec.gov/Archives/edgar/data/1326801/000132680123000013/meta-20221231.htm
A26: Form 10-K for fiscal 2023 | B26: 10-K | C26: 45291 | D26: 45324 | E26: 0001326801-24-000012 | F26: 2023A | G26: https://www.sec.gov/Archives/edgar/data/1326801/000132680124000012/meta-20231231.htm
A27: Form 10-K for fiscal 2024 | B27: 10-K | C27: 45657 | D27: 45687 | E27: 0001326801-25-000017 | F27: 2024A | G27: https://www.sec.gov/Archives/edgar/data/1326801/000132680125000017/meta-20241231.htm
A28: Form 10-K for fiscal 2025 | B28: 10-K | C28: 46022 | D28: 46051 | E28: 0001628280-26-003942 | F28: 2025A | G28: https://www.sec.gov/Archives/edgar/data/1326801/000162828026003942/meta-20251231.htm
A29: Form 10-Q for the quarter ended 2025-09-30 | B29: 10-Q | C29: 45930 | D29: 45960 | E29: 0001628280-25-047240 | F29: 9M 2025A, Sep 2025A | G29: https://www.sec.gov/Archives/edgar/data/1326801/000162828025047240/meta-20250930.htm
A30: Form 10-Q for the quarter ended 2026-09-30 | B30: 10-Q | C30: 46295 | D30: 46317 | E30: 0001628280-26-066773 | F30: 9M 2026A, Sep 2026A | G30: https://www.sec.gov/Archives/edgar/data/1326801/000162828026066773/meta-20260930.htm
A32: Sheets | B32: What it shows
A33: IS_Hist | B33: Consolidated statements of income
A34: CI_Hist | B34: Consolidated statements of comprehensive income
A35: BS_Hist | B35: Consolidated balance sheets, with the parenthetical share data
A36: CF_Hist | B36: Consolidated statements of cash flows, with supplemental data
A37: SCE_Hist | B37: Consolidated statements of stockholders' equity, as a roll-forward per component
A38: Revenue_Hist | B38: Revenue by source, segment and region (audited notes), Meta's reported drivers, and ratios
A39: Assumptions | B39: Every forecast input: Base, Bull and Bear rows, the active row and the scenario switch (C5)
A40: Interim_Bridge | B40: 2026E = nine months actual (10-Q) + fourth quarter from guidance
A41: Revenue_Build | B41: Advertising = ads shown x price per ad; other revenue; Reality Labs
A42: Schedules | B42: Capex and depreciation by vintage, working capital, debt, cash, equity and shares
A43: Forecast_3Stmt | B43: Integrated income statement, balance sheet and cash flow, 2025A-2035E
... A54: Claude Code Log | B54: Log of every scripted change to this workbook
A56: Model outputs (active scenario)
A57: Active scenario | D57: =Assumptions!B6 -> Base
A58: Share price, 26 Oct 2026 (USD) | D58: =Market_Package!B8 -> 630.56
A59: DCF value per share, perpetuity (USD) | D59: =DCF!B36 -> 495.7717
A60: Upside / (downside) | D60: =DCF!B38 -> -0.21375968
A61: DCF value per share, exit multiple (USD) | D61: =DCF!B45 -> 654.83062
A62: FCFE value per share (USD) | D62: =Valuation!B30 -> 533.08645
A63: Comps: AI mega-caps median EV / EBITDA (USD per share) | D63: =Valuation!E54 -> 980.21487
A64: Growth the price implies after 2035 | D64: =Valuation!B9 -> 0.047921146
A65: Revenue 2027E | D65: =Forecast_3Stmt!D10 -> 304976.58
A66: Operating margin 2027E | D66: =Forecast_3Stmt!D18 -> 0.31677792
A67: Free cash flow 2027E | D67: =Forecast_3Stmt!D69 -> -41199.109
A68: Net debt / EBITDA 2027E | D68: =Debt_Credit!K69 -> 0.55819491
A69: Scenario table status | D69: =Scenario_Summary!B27 -> current

Sheet IS_Hist
A1: Meta Platforms, Inc. | Consolidated Statements of Income
A2: USD millions, except per-share amounts (USD) and share counts (millions). Each period as first reported in its own filing.
B3: Audited (Form 10-K) | I3: Unaudited (Form 10-Q)
A4: Fiscal year ends 31 December | B4: 2019A | C4: 2020A | D4: 2021A | E4: 2022A | F4: 2023A | G4: 2024A | H4: 2025A | I4: 9M 2025A | J4: 9M 2026A | M4: Comentarios FG | N4: XBRL concept (latest filing) | O4: Earlier wording of this line
A6: Revenue | B6: 70697 | C6: 85965 | D6: 117929 | E6: 116609 | F6: 134902 | G6: 164501 | H6: 200966 | I6: 141073 | J6: 181712 | N6: RevenueFromContractWithCustomerExcludingAssessedTax
A8: Costs and expenses:
A9: Cost of revenue | B9: 12770 | C9: 16692 | D9: 22649 | E9: 25249 | F9: 25959 | G9: 30161 | H9: 36175 | I9: 25269 | J9: 34917 | N9: CostOfRevenue
A10: Research and development | B10: 13600 | C10: 18447 | D10: 24655 | E10: 35338 | F10: 38483 | G10: 43873 | H10: 57372 | I10: 40237 | J10: 59409 | N10: ResearchAndDevelopmentExpense
A11: Marketing and sales | B11: 9876 | C11: 11591 | D11: 14043 | E11: 15262 | F11: 12301 | G11: 11347 | H11: 11991 | I11: 8581 | J11: 9672 | N11: SellingAndMarketingExpense
A12: General and administrative | B12: 10465 | C12: 6564 | D12: 9829 | E12: 11816 | F12: 11408 | G12: 9740 | H12: 12152 | I12: 8455 | J12: 23079 | N12: GeneralAndAdministrativeExpense
A13: Total costs and expenses | B13: 46711 | C13: 53294 | D13: 71176 | E13: 87665 | F13: 88151 | G13: 95121 | H13: 117690 | I13: 82542 | J13: 127077 | N13: CostsAndExpenses
A15: Income from operations | B15: 23986 | C15: 32671 | D15: 46753 | E15: 28944 | F15: 46751 | G15: 69380 | H15: 83276 | I15: 58531 | J15: 54635 | N15: OperatingIncomeLoss
A17: Interest and other income, net | B17: 826 | C17: 509 | D17: 531 | E17: -125 | F17: 677 | G17: 1283 | H17: 2656 | I17: 2047 | J17: -1126 | N17: NonoperatingIncomeExpense | O17: Interest and other income (expense), net
A18: Income before provision for income taxes | B18: 24812 | C18: 33180 | D18: 47284 | E18: 28819 | F18: 47428 | G18: 70663 | H18: 85932 | I18: 60578 | J18: 53509 | N18: IncomeLossFromContinuingOperationsBeforeIncomeTaxesExtraordinaryItemsNoncontrollingInterest | O18: Income before income taxes
A20: Provision for income taxes | B20: 6327 | C20: 4034 | D20: 7914 | E20: 5619 | F20: 8330 | G20: 8303 | H20: 25474 | I20: 22888 | J20: 1028 | N20: IncomeTaxExpenseBenefit
A21: Net income | B21: 18485 | C21: 29146 | D21: 39370 | E21: 23200 | F21: 39098 | G21: 62360 | H21: 60458 | I21: 37690 | J21: 52481 | N21: NetIncomeLoss
A23: Less: Net income attributable to participating securities | B23: 0 | C23: 0 | N23: UndistributedEarningsLossAllocatedToParticipatingSecuritiesBasic
A24: Net income attributable to Class A and Class B common stockholders | B24: 18485 | C24: 29146 | N24: NetIncomeLossAvailableToCommonStockholdersBasic
A26: Earnings per share: | O26: Earnings per share attributable to Class A and Class B common stockholders:
A27: Basic | B27: 6.48 | C27: 10.22 | D27: 13.99 | E27: 8.63 | F27: 15.19 | G27: 24.61 | H27: 23.98 | I27: 14.96 | J27: 20.64 | N27: EarningsPerShareBasic
A28: Diluted | B28: 6.43 | C28: 10.09 | D28: 13.77 | E28: 8.59 | F28: 14.87 | G28: 23.86 | H28: 23.49 | I28: 14.62 | J28: 20.44 | N28: EarningsPerShareDiluted
A30: Weighted-average shares used to compute earnings per share: | O30: Weighted-average shares used to compute earnings per share attributable to Class A and Class B common stockholders:
A31: Basic | B31: 2854 | C31: 2851 | D31: 2815 | E31: 2687 | F31: 2574 | G31: 2534 | H31: 2521 | I31: 2520 | J31: 2543 | N31: WeightedAverageNumberOfSharesOutstandingBasic
A32: Diluted | B32: 2876 | C32: 2888 | D32: 2859 | E32: 2702 | F32: 2629 | G32: 2614 | H32: 2574 | I32: 2578 | J32: 2568 | N32: WeightedAverageNumberOfDilutedSharesOutstanding
A34: Share-based compensation expense included in costs and expenses:
A35: Cost of revenue | B35: 377 | C35: 447 | D35: 577 | E35: 768 | N35: AllocatedShareBasedCompensationExpense
A36: Research and development | B36: 3488 | C36: 4918 | D36: 7106 | E36: 9361 | N36: AllocatedShareBasedCompensationExpense
A37: Marketing and sales | B37: 569 | C37: 691 | D37: 837 | E37: 1004 | N37: AllocatedShareBasedCompensationExpense
A38: General and administrative | B38: 402 | C38: 480 | D38: 644 | E38: 859 | N38: AllocatedShareBasedCompensationExpense
A39: Total share-based compensation expense | B39: 4836 | C39: 6536 | D39: 9164 | E39: 11992 | N39: AllocatedShareBasedCompensationExpense
A41: Checks (each should be zero)
A42: Costs and expenses add to the total | B42: =B9+B10+B11+B12-B13 -> 0 | C42: =C9+C10+C11+C12-C13 -> 0 | D42: =D9+D10+D11+D12-D13 -> 0 | E42: =E9+E10+E11+E12-E13 -> 0 | F42: =F9+F10+F11+F12-F13 -> 0 | G42: =G9+G10+G11+G12-G13 -> 0 | H42: =H9+H10+H11+H12-H13 -> 0 | I42: =I9+I10+I11+I12-I13 -> 0 | J42: =J9+J10+J11+J12-J13 -> 0
A43: Revenue less total costs equals income from operations | B43: =B6-B13-B15 -> 0 | C43: =C6-C13-C15 -> 0 | D43: =D6-D13-D15 -> 0 | E43: =E6-E13-E15 -> 0 | F43: =F6-F13-F15 -> 0 | G43: =G6-G13-G15 -> 0 | H43: =H6-H13-H15 -> 0 | I43: =I6-I13-I15 -> 0 | J43: =J6-J13-J15 -> 0
A44: Operating income plus other income equals pre-tax income | B44: =B15+B17-B18 -> 0 | C44: =C15+C17-C18 -> 0 | D44: =D15+D17-D18 -> 0 | E44: =E15+E17-E18 -> 0 | F44: =F15+F17-F18 -> 0 | G44: =G15+G17-G18 -> 0 | H44: =H15+H17-H18 -> 0 | I44: =I15+I17-I18 -> 0 | J44: =J15+J17-J18 -> 0
A45: Pre-tax income less tax equals net income | B45: =B18-B20-B21 -> 0 | C45: =C18-C20-C21 -> 0 | D45: =D18-D20-D21 -> 0 | E45: =E18-E20-E21 -> 0 | F45: =F18-F20-F21 -> 0 | G45: =G18-G20-G21 -> 0 | H45: =H18-H20-H21 -> 0 | I45: =I18-I20-I21 -> 0 | J45: =J18-J20-J21 -> 0
A46: Net income less participating securities equals net income to common | B46: =B21+B23-B24 -> 0 | C46: =C21+C23-C24 -> 0
A47: Share-based compensation by function adds to the total | B47: =B35+B36+B37+B38-B39 -> 0 | C47: =C35+C36+C37+C38-C39 -> 0 | D47: =D35+D36+D37+D38-D39 -> 0 | E47: =E35+E36+E37+E38-E39 -> 0
A48: Net income equals the cash flow statement | B48: =B21-CF_Hist!B7 -> 0 | C48: =C21-CF_Hist!C7 -> 0 | D48: =D21-CF_Hist!D7 -> 0 | E48: =E21-CF_Hist!E7 -> 0 | F48: =F21-CF_Hist!F7 -> 0 | G48: =G21-CF_Hist!G7 -> 0 | H48: =H21-CF_Hist!H7 -> 0 | I48: =I21-CF_Hist!I7 -> 0 | J48: =J21-CF_Hist!J7 -> 0
A49: Net income equals the comprehensive income statement | B49: =B21-CI_Hist!B6 -> 0 | C49: =C21-CI_Hist!C6 -> 0 | D49: =D21-CI_Hist!D6 -> 0 | E49: =E21-CI_Hist!E6 -> 0 | F49: =F21-CI_Hist!F6 -> 0 | G49: =G21-CI_Hist!G6 -> 0 | H49: =H21-CI_Hist!H6 -> 0 | I49: =I21-CI_Hist!I6 -> 0 | J49: =J21-CI_Hist!J6 -> 0
A50: Net income equals the retained earnings roll-forward | B50: =B21-SCE_Hist!B49 -> 0 | C50: =C21-SCE_Hist!C49 -> 0 | D50: =D21-SCE_Hist!D49 -> 0 | E50: =E21-SCE_Hist!E49 -> 0 | F50: =F21-SCE_Hist!F49 -> 0 | G50: =G21-SCE_Hist!G49 -> 0 | H50: =H21-SCE_Hist!H49 -> 0 | I50: =I21-SCE_Hist!I49 -> 0 | J50: =J21-SCE_Hist!J49 -> 0

Sheet CI_Hist
A1: Meta Platforms, Inc. | Consolidated Statements of Comprehensive Income
A2: USD millions, except per-share amounts (USD) and share counts (millions). Each period as first reported in its own filing.
B3: Audited (Form 10-K) | I3: Unaudited (Form 10-Q)
A4: Fiscal year ends 31 December | B4: 2019A | C4: 2020A | D4: 2021A | E4: 2022A | F4: 2023A | G4: 2024A | H4: 2025A | I4: 9M 2025A | J4: 9M 2026A | M4: Comentarios FG | N4: XBRL concept (latest filing) | O4: Earlier wording of this line
A6: Net income | B6: 18485 | C6: 29146 | D6: 39370 | E6: 23200 | F6: 39098 | G6: 62360 | H6: 60458 | I6: 37690 | J6: 52481 | N6: NetIncomeLoss
A8: Other comprehensive income (loss):
A9: Change in foreign currency translation adjustment, net of tax | B9: -151 | C9: 1056 | D9: -1116 | E9: -1184 | F9: 618 | G9: -1413 | H9: 2693 | I9: 2598 | J9: -638 | N9: OtherComprehensiveIncomeLossForeignCurrencyTransactionAndTranslationAdjustmentNetOfTax
A10: Change in unrealized gain (loss) on available-for-sale investments and other, net of tax | B10: 422 | C10: 360 | D10: -504 | E10: -1653 | F10: 757 | G10: 471 | H10: 675 | I10: 658 | J10: -833 | N10: OtherComprehensiveIncomeLossAvailableForSaleSecuritiesAdjustmentAndOtherNetofTax, OtherComprehensiveIncomeLossAvailableForSaleSecuritiesAdjustmentAndOtherNetofTax, OtherComprehensiveIncomeUnrealizedHoldingGainLossOnSecuritiesArisingDuringPeriodNetOfTax | O10: Change in unrealized gain/loss on available-for-sale investments and other, net of tax
A11: Comprehensive income | B11: 18756 | C11: 30562 | D11: 37750 | E11: 20363 | F11: 40473 | G11: 61418 | H11: 63826 | I11: 40946 | J11: 51010 | N11: ComprehensiveIncomeNetOfTax
A13: Checks (each should be zero)
A14: Net income plus other comprehensive income equals comprehensive income | B14: =B6+B9+B10-B11 -> 0 | C14: =C6+C9+C10-C11 -> 0 | D14: =D6+D9+D10-D11 -> 0 | E14: =E6+E9+E10-E11 -> 0 | F14: =F6+F9+F10-F11 -> 0 | G14: =G6+G9+G10-G11 -> 0 | H14: =H6+H9+H10-H11 -> 0 | I14: =I6+I9+I10-I11 -> 0 | J14: =J6+J9+J10-J11 -> 0
A15: Other comprehensive income equals the equity roll-forward | B15: =B9+B10-SCE_Hist!B44 -> 0 | C15: =C9+C10-SCE_Hist!C44 -> 0 | D15: =D9+D10-SCE_Hist!D44 -> 0 | E15: =E9+E10-SCE_Hist!E44 -> 0 | F15: =F9+F10-SCE_Hist!F44 -> 0 | G15: =G9+G10-SCE_Hist!G44 -> 0 | H15: =H9+H10-SCE_Hist!H44 -> 0 | I15: =I9+I10-SCE_Hist!I44 -> 0 | J15: =J9+J10-SCE_Hist!J44 -> 0

Sheet BS_Hist
A1: Meta Platforms, Inc. | Consolidated Balance Sheets
A2: USD millions, except per-share amounts (USD) and share counts (millions). Each period as first reported in its own filing.
B3: Audited (Form 10-K) | I3: Unaudited (Form 10-Q)
A4: Fiscal year ends 31 December | B4: 2019A | C4: 2020A | D4: 2021A | E4: 2022A | F4: 2023A | G4: 2024A | H4: 2025A | I4: Sep 2025A | J4: Sep 2026A | M4: Comentarios FG | N4: XBRL concept (latest filing) | O4: Earlier wording of this line
A6: Assets | J6: =+J7+J48 -> 127746
J7: =+J10+J9-H10+H9 -> 72603
A8: Current assets: | J8: =+(J10+J9)/(H10+H9) -> 1.0105035
A9: Cash and cash equivalents | B9: 19079 | C9: 17576 | D9: 16601 | E9: 14681 | F9: 41862 | G9: 43889 | H9: 35873 | I9: 10187 | J9: 11222 | N9: CashAndCashEquivalentsAtCarryingValue
A10: Marketable securities | B10: 35776 | C10: 44378 | D10: 31397 | E10: 26057 | F10: 23541 | G10: 33926 | H10: 45719 | I10: 34261 | J10: 71227 | N10: AvailableForSaleSecuritiesDebtSecuritiesCurrent, MarketableSecuritiesCurrent
A11: Accounts receivable, net | B11: 9518 | C11: 11335 | D11: 14039 | E11: 13466 | F11: 16169 | G11: 16994 | H11: 19769 | I11: 17297 | J11: 22716 | N11: AccountsReceivableNetCurrent | O11: Accounts receivable, net of allowances of $114 million and $92 million as of December 31, 2020 and 2019, respectively | Accounts receivable, net of allowances of $206 and $229 as of December 31, 2019 and December 31, 2018, respectively
A12: Prepaid expenses and other current assets | B12: 1852 | C12: 2381 | D12: 4629 | E12: 5345 | F12: 3793 | G12: 5236 | H12: 7361 | I12: 11373 | J12: 14735 | N12: PrepaidExpenseAndOtherAssetsCurrent
A13: Total current assets | B13: 66225 | C13: 75670 | D13: 66666 | E13: 59549 | F13: 85365 | G13: 100045 | H13: 108722 | I13: 73118 | J13: 119900 | N13: AssetsCurrent
J14: =+(J16)/(H16) -> 1.4354989
A15: Non-marketable equity investments | C15: 6234 | D15: 6775 | E15: 6201 | F15: 6141 | G15: 6070 | H15: 27524 | I15: 25074 | J15: 32624 | N15: NonmarketableEquitySecuritiesCarryingValue, NonmarketableEquitySecuritiesCarryingValue, EquitySecuritiesWithoutReadilyDeterminableFairValueAmount | O15: Non-marketable equity securities | Equity investments
A16: Property and equipment, net | B16: 35323 | C16: 45633 | D16: 57809 | E16: 79518 | F16: 96587 | G16: 121346 | H16: 176400 | I16: 160270 | J16: 253222 | N16: PropertyPlantAndEquipmentAndFinanceLeaseRightofUseAssetAfterAccumulatedDepreciationAndAmortization, PropertyPlantAndEquipmentAndFinanceLeaseRightOfUseAssetAfterAccumulatedDepreciationAndAmortization
A17: Operating lease right-of-use assets | B17: 9460 | C17: 9348 | D17: 12155 | E17: 12673 | F17: 13294 | G17: 14922 | H17: 20404 | I17: 17372 | J17: 26576 | N17: OperatingLeaseRightOfUseAsset | O17: Operating lease right-of-use assets, net
A18: Intangible assets, net | B18: 894 | C18: 623 | D18: 634 | E18: 897 | F18: 788 | N18: IntangibleAssetsNetExcludingGoodwill
A19: Goodwill | B19: 18715 | C19: 19050 | D19: 19197 | E19: 20306 | F19: 20654 | G19: 20654 | H19: 24534 | I19: 21158 | J19: 23421 | N19: Goodwill
A20: Other assets | B20: 2759 | C20: 2758 | D20: 2751 | E20: 6583 | F20: 6794 | G20: 13017 | H20: 8437 | I20: 6852 | J20: 23093 | N20: OtherAssetsNoncurrent
A21: Total assets | B21: 133376 | C21: 159316 | D21: 165987 | E21: 185727 | F21: 229623 | G21: 276054 | H21: 366021 | I21: 303844 | J21: 478836 | N21: Assets
H22: =+H21/B21-1 -> 1.7442793
A23: Liabilities and stockholders' equity
A25: Current liabilities:
A26: Accounts payable | B26: 1363 | C26: 1331 | D26: 4083 | E26: 4990 | F26: 4849 | G26: 7687 | H26: 8894 | I26: 7798 | J26: 19097 | N26: AccountsPayableCurrent, AccountsPayableTradeCurrent
A27: Partners payable | B27: 886 | C27: 1093 | D27: 1052 | E27: 1117 | F27: 863 | N27: AccountsPayableOtherCurrent, AccountsPayableTradeCurrent
A28: Operating lease liabilities, current | B28: 800 | C28: 1023 | D28: 1127 | E28: 1367 | F28: 1623 | G28: 1942 | H28: 2213 | I28: 2113 | J28: 2522 | N28: OperatingLeaseLiabilityCurrent
A29: Accrued expenses and other current liabilities | B29: 11735 | C29: 11152 | D29: 14312 | E29: 19552 | F29: 24625 | G29: 23967 | H29: 30729 | I29: 27047 | J29: 41392 | N29: AccruedLiabilitiesCurrent
A30: Deferred revenue and deposits | B30: 269 | C30: 382 | D30: 561 | N30: ContractWithCustomerLiabilityAndUnusedDeposits, ContractWithCustomerLiabilityCurrent
A31: Total current liabilities | B31: 15053 | C31: 14981 | D31: 21135 | E31: 27026 | F31: 31960 | G31: 33596 | H31: 41836 | I31: 36958 | J31: 63011 | N31: LiabilitiesCurrent
A33: Operating lease liabilities, non-current | B33: 9524 | C33: 9631 | D33: 12746 | E33: 15301 | F33: 17226 | G33: 18292 | H33: 22940 | I33: 20113 | J33: 28651 | N33: OperatingLeaseLiabilityNoncurrent
A34: Long-term debt | E34: 9923 | F34: 18385 | G34: 28826 | H34: 58744 | I34: 28834 | J34: 80922 | N34: LongTermDebtNoncurrent
A35: Long-term income taxes | G35: 9987 | H35: 21005 | I35: 11738 | J35: 20521 | N35: AccruedIncomeTaxesNoncurrent
A36: Other liabilities | B36: 7745 | C36: 6414 | D36: 7227 | E36: 7764 | F36: 8884 | G36: 2716 | H36: 4253 | I36: 12135 | J36: 13345 | N36: OtherLiabilitiesNoncurrent
A37: Total liabilities | B37: 32322 | C37: 31026 | D37: 41108 | E37: 60014 | F37: 76455 | G37: 93417 | H37: 148778 | I37: 109778 | J37: 206450 | N37: Liabilities
J38: =+J37-H37 -> 57672
A39: Commitments and contingencies
A41: Stockholders' equity:
A42: Common stock and additional paid-in capital, $0.000006 par value | J42: 108244 | N42: CommonStocksIncludingAdditionalPaidInCapital | O42: Common stock and additional paid-in capital, $0.000006 par value; 5,000 million Class A shares authorized, 2,214 million and 2,187 million shares issued and outstanding, as of September 30, 2026 and December 31, 2025, respectively; 4,141 million Class B shares authorized, 342 million and 343 million shares issued and outstanding, as of September 30, 2026 and December 31, 2025, respectively
A43: Common stock, $0.000006 par value | B43: 0 | C43: 0 | D43: 0 | E43: 0 | F43: 0 | G43: 0 | H43: 0 | I43: 0 | N43: CommonStockValue | O43: Common stock, $0.000006 par value; 5,000 million Class A shares authorized, 2,187 million and 2,190 million shares issued and outstanding, as of December 31, 2025 and 2024, respectively; 4,141 million Class B shares authorized, 343 million and 344 million shares issued and outstanding, as of December 31, 2025 and 2024, respectively | Common stock, $0.000006 par value; 5,000 million Class A shares authorized, 2,190 million and 2,211 million shares issued and outstanding, as of December 31, 2024 and 2023, respectively; 4,141 million Class B shares authorized, 344 million and 350 million shares issued and outstanding, as of December 31, 2024 and 2023, respectively | Common stock, $0.000006 par value; 5,000 million Class A shares authorized, 2,211 million and 2,247 million shares issued and outstanding, as of December 31, 2023 and 2022, respectively; 4,141 million Class B shares authorized, 350 million and 367 million shares issued and outstanding, as of December 31, 2023 and 2022, respectively | Common stock, $0.000006 par value; 5,000 million Class A shares authorized, 2,247 million and 2,328 million shares issued and outstanding, as of December 31, 2022 and 2021, respectively; 4,141 million Class B shares authorized, 367 million and 413 million shares issued and outstanding, as of December 31, 2022 and 2021, respectively | Common stock, $0.000006 par value; 5,000 million Class A shares authorized, 2,328 million and 2,406 million shares issued and outstanding, as of December 31, 2021 and 2020, respectively; 4,141 million Class B shares authorized, 413 million and 443 million shares issued and outstanding, as of December 31, 2021 and 2020, respectively | Common stock, $0.000006 par value; 5,000 million Class A shares authorized, 2,406 million and 2,407 million shares issued and outstanding, as of December 31, 2020 and 2019, respectively; 4,141 million Class B shares authorized, 443 million and 445 million shares issued and outstanding, as of December 31, 2020 and 2019, respectively | Common stock, $0.000006 par value; 5,000 million Class A shares authorized, 2,407 million and 2,385 million shares issued and outstanding, as of December 31, 2019 and December 31, 2018, respectively; 4,141 million Class B shares authorized, 445 million and 469 million shares issued and outstanding, as of December 31, 2019 and December 31, 2018, respectively. | Common stock, $0.000006 par value; 5,000 million Class A shares authorized, 2,178 million and 2,190 million shares issued and outstanding, as of September 30, 2025 and December 31, 2024, respectively; 4,141 million Class B shares authorized, 343 million and 344 million shares issued and outstanding, as of September 30, 2025 and December 31, 2024, respectively
A44: Additional paid-in capital | B44: 45851 | C44: 50018 | D44: 55811 | E44: 64444 | F44: 73253 | G44: 83228 | H44: 95793 | I44: 92330 | N44: AdditionalPaidInCapital
A45: Accumulated other comprehensive income (loss) | B45: -489 | C45: 927 | D45: -693 | E45: -3530 | F45: -2155 | G45: -3097 | H45: 271 | I45: 159 | J45: -1200 | N45: AccumulatedOtherComprehensiveIncomeLossNetOfTax | O45: Accumulated other comprehensive loss
A46: Retained earnings | B46: 55692 | C46: 77345 | D46: 69761 | E46: 64799 | F46: 82070 | G46: 102506 | H46: 121179 | I46: 101577 | J46: 165342 | N46: RetainedEarningsAccumulatedDeficit
A47: Total stockholders' equity | B47: 101054 | C47: 128290 | D47: 124879 | E47: 125713 | F47: 153168 | G47: 182637 | H47: 217243 | I47: 194066 | J47: 272386 | N47: StockholdersEquity
J48: =+J47-H47 -> 55143
A49: Total liabilities and stockholders' equity | B49: 133376 | C49: 159316 | D49: 165987 | E49: 185727 | F49: 229623 | G49: 276054 | H49: 366021 | I49: 303844 | J49: 478836 | N49: LiabilitiesAndStockholdersEquity
A51: Memo: balance sheet parenthetical (from the face of the balance sheet)
A52: Accounts receivable, allowances for doubtful accounts | B52: 206 | C52: 114
A53: Common stock, par value per share (USD) | B53: 6e-06 | C53: 6e-06 | D53: 6e-06 | E53: 6e-06 | F53: 6e-06 | G53: 6e-06 | H53: 6e-06 | I53: 6e-06 | J53: 6e-06
A54: Class A common stock, shares authorized (millions) | B54: 5000 | C54: 5000 | D54: 5000 | E54: 5000 | F54: 5000 | G54: 5000 | H54: 5000 | I54: 5000 | J54: 5000
A55: Class A common stock, shares issued (millions) | B55: 2407 | C55: 2406 | D55: 2328 | E55: 2247 | F55: 2211 | G55: 2190 | H55: 2187 | I55: 2178 | J55: 2214
A56: Class A common stock, shares outstanding (millions) | B56: 2407 | C56: 2406 | D56: 2328 | E56: 2247 | F56: 2211 | G56: 2190 | H56: 2187 | I56: 2178 | J56: 2214
A57: Class B common stock, shares authorized (millions) | B57: 4141 | C57: 4141 | D57: 4141 | E57: 4141 | F57: 4141 | G57: 4141 | H57: 4141 | I57: 4141 | J57: 4141
A58: Class B common stock, shares issued (millions) | B58: 445 | C58: 443 | D58: 413 | E58: 367 | F58: 350 | G58: 344 | H58: 343 | I58: 343 | J58: 342
A59: Class B common stock, shares outstanding (millions) | B59: 445 | C59: 443 | D59: 413 | E59: 367 | F59: 350 | G59: 344 | H59: 343 | I59: 343 | J59: 342
A61: Checks (each should be zero)
A62: Current assets add to the total | B62: =B9+B10+B11+B12-B13 -> 0 | C62: =C9+C10+C11+C12-C13 -> 0 | D62: =D9+D10+D11+D12-D13 -> 0 | E62: =E9+E10+E11+E12-E13 -> 0 | F62: =F9+F10+F11+F12-F13 -> 0 | G62: =G9+G10+G11+G12-G13 -> 0 | H62: =H9+H10+H11+H12-H13 -> 0 | I62: =I9+I10+I11+I12-I13 -> 0 | J62: =J9+J10+J11+J12-J13 -> 0
A63: Current plus non-current assets equal total assets | B63: =B13+B16+B17+B18+B19+B20-B21 -> 0 | C63: =C13+C15+C16+C17+C18+C19+C20-C21 -> 0 | D63: =D13+D15+D16+D17+D18+D19+D20-D21 -> 0 | E63: =E13+E15+E16+E17+E18+E19+E20-E21 -> 0 | F63: =F13+F15+F16+F17+F18+F19+F20-F21 -> 0 | G63: =G13+G15+G16+G17+G19+G20-G21 -> 0 | H63: =H13+H15+H16+H17+H19+H20-H21 -> 0 | I63: =I13+I15+I16+I17+I19+I20-I21 -> 0 | J63: =J13+J15+J16+J17+J19+J20-J21 -> 0
A64: Current liabilities add to the total | B64: =B26+B27+B28+B29+B30-B31 -> 0 | C64: =C26+C27+C28+C29+C30-C31 -> 0 | D64: =D26+D27+D28+D29+D30-D31 -> 0 | E64: =E26+E27+E28+E29-E31 -> 0 | F64: =F26+F27+F28+F29-F31 -> 0 | G64: =G26+G28+G29-G31 -> 0 | H64: =H26+H28+H29-H31 -> 0 | I64: =I26+I28+I29-I31 -> 0 | J64: =J26+J28+J29-J31 -> 0
A65: Current plus non-current liabilities equal total liabilities | B65: =B31+B33+B36-B37 -> 0 | C65: =C31+C33+C36-C37 -> 0 | D65: =D31+D33+D36-D37 -> 0 | E65: =E31+E33+E34+E36-E37 -> 0 | F65: =F31+F33+F34+F36-F37 -> 0 | G65: =G31+G33+G34+G35+G36-G37 -> 0 | H65: =H31+H33+H34+H35+H36-H37 -> 0 | I65: =I31+I33+I34+I35+I36-I37 -> 0 | J65: =J31+J33+J34+J35+J36-J37 -> 0
A66: Equity lines add to total stockholders' equity | B66: =B43+B44+B45+B46-B47 -> 0 | C66: =C43+C44+C45+C46-C47 -> 0 | D66: =D43+D44+D45+D46-D47 -> 0 | E66: =E43+E44+E45+E46-E47 -> 0 | F66: =F43+F44+F45+F46-F47 -> 0 | G66: =G43+G44+G45+G46-G47 -> 0 | H66: =H43+H44+H45+H46-H47 -> 0 | I66: =I43+I44+I45+I46-I47 -> 0 | J66: =J42+J45+J46-J47 -> 0
A67: Liabilities plus equity equal the reported total | B67: =B37+B47-B49 -> 0 | C67: =C37+C47-C49 -> 0 | D67: =D37+D47-D49 -> 0 | E67: =E37+E47-E49 -> 0 | F67: =F37+F47-F49 -> 0 | G67: =G37+G47-G49 -> 0 | H67: =H37+H47-H49 -> 0 | I67: =I37+I47-I49 -> 0 | J67: =J37+J47-J49 -> 0
A68: Total assets equal total liabilities and equity | B68: =B21-B49 -> 0 | C68: =C21-C49 -> 0 | D68: =D21-D49 -> 0 | E68: =E21-E49 -> 0 | F68: =F21-F49 -> 0 | G68: =G21-G49 -> 0 | H68: =H21-H49 -> 0 | I68: =I21-I49 -> 0 | J68: =J21-J49 -> 0
A69: Cash equals the cash flow reconciliation | B69: =B9-CF_Hist!B62 -> 0 | C69: =C9-CF_Hist!C62 -> 0 | D69: =D9-CF_Hist!D62 -> 0 | E69: =E9-CF_Hist!E62 -> 0 | F69: =F9-CF_Hist!F62 -> 0 | G69: =G9-CF_Hist!G62 -> 0 | H69: =H9-CF_Hist!H62 -> 0 | I69: =I9-CF_Hist!I62 -> 0 | J69: =J9-CF_Hist!J62 -> 0
A70: Total equity equals the equity roll-forward | B70: =B47-SCE_Hist!B18 -> 0 | C70: =C47-SCE_Hist!C18 -> 0 | D70: =D47-SCE_Hist!D18 -> 0 | E70: =E47-SCE_Hist!E18 -> 0 | F70: =F47-SCE_Hist!F18 -> 0 | G70: =G47-SCE_Hist!G18 -> 0 | H70: =H47-SCE_Hist!H18 -> 0 | I70: =I47-SCE_Hist!I18 -> 0 | J70: =J47-SCE_Hist!J18 -> 0
A71: Retained earnings equal the equity roll-forward | B71: =B46-SCE_Hist!B54 -> 0 | C71: =C46-SCE_Hist!C54 -> 0 | D71: =D46-SCE_Hist!D54 -> 0 | E71: =E46-SCE_Hist!E54 -> 0 | F71: =F46-SCE_Hist!F54 -> 0 | G71: =G46-SCE_Hist!G54 -> 0 | H71: =H46-SCE_Hist!H54 -> 0 | I71: =I46-SCE_Hist!I54 -> 0 | J71: =J46-SCE_Hist!J54 -> 0
A72: AOCI equals the equity roll-forward | B72: =B45-SCE_Hist!B45 -> 0 | C72: =C45-SCE_Hist!C45 -> 0 | D72: =D45-SCE_Hist!D45 -> 0 | E72: =E45-SCE_Hist!E45 -> 0 | F72: =F45-SCE_Hist!F45 -> 0 | G72: =G45-SCE_Hist!G45 -> 0 | H72: =H45-SCE_Hist!H45 -> 0 | I72: =I45-SCE_Hist!I45 -> 0 | J72: =J45-SCE_Hist!J45 -> 0
A73: Common stock and APIC equal the equity roll-forward | B73: =B43+B44-SCE_Hist!B31-SCE_Hist!B40 -> 0 | C73: =C43+C44-SCE_Hist!C31-SCE_Hist!C40 -> 0 | D73: =D43+D44-SCE_Hist!D31-SCE_Hist!D40 -> 0 | E73: =E43+E44-SCE_Hist!E31-SCE_Hist!E40 -> 0 | F73: =F43+F44-SCE_Hist!F31-SCE_Hist!F40 -> 0 | G73: =G43+G44-SCE_Hist!G31-SCE_Hist!G40 -> 0 | H73: =H43+H44-SCE_Hist!H31-SCE_Hist!H40 -> 0 | I73: =I43+I44-SCE_Hist!I31-SCE_Hist!I40 -> 0 | J73: =J42-0-SCE_Hist!J40 -> 0
A74: Class A plus Class B shares equal the equity roll-forward | B74: =B56+B59-SCE_Hist!B27 -> 0 | C74: =C56+C59-SCE_Hist!C27 -> 0 | D74: =D56+D59-SCE_Hist!D27 -> 0 | E74: =E56+E59-SCE_Hist!E27 -> 0 | F74: =F56+F59-SCE_Hist!F27 -> 0 | G74: =G56+G59-SCE_Hist!G27 -> 0 | H74: =H56+H59-SCE_Hist!H27 -> 0 | I74: =I56+I59-SCE_Hist!I27 -> 0 | J74: =J56+J59-SCE_Hist!J27 -> 0

Sheet CF_Hist
A1: Meta Platforms, Inc. | Consolidated Statements of Cash Flows
A2: USD millions, except per-share amounts (USD) and share counts (millions). Each period as first reported in its own filing.
B3: Audited (Form 10-K) | I3: Unaudited (Form 10-Q)
A4: Fiscal year ends 31 December | B4: 2019A | C4: 2020A | D4: 2021A | E4: 2022A | F4: 2023A | G4: 2024A | H4: 2025A | I4: 9M 2025A | J4: 9M 2026A | M4: Comentarios FG | N4: XBRL concept (latest filing) | O4: Earlier wording of this line
A6: Cash flows from operating activities
A7: Net income | B7: 18485 | C7: 29146 | D7: 39370 | E7: 23200 | F7: 39098 | G7: 62360 | H7: 60458 | I7: 37690 | J7: 52481 | N7: NetIncomeLoss
A9: Adjustments to reconcile net income to net cash provided by operating activities:
A10: Depreciation and amortization | B10: 5741 | C10: 6862 | D10: 7967 | E10: 8686 | F10: 11178 | G10: 15498 | H10: 18616 | I10: 13205 | J10: 19509 | N10: DepreciationDepletionAndAmortization
A11: Share-based compensation | B11: 4836 | C11: 6536 | D11: 9164 | E11: 11992 | F11: 14027 | G11: 16690 | H11: 20427 | I11: 14537 | J11: 21053 | N11: ShareBasedCompensation
A12: Deferred income taxes | B12: -37 | C12: -1192 | D12: 609 | E12: -3286 | F12: 131 | G12: -4738 | H12: 18738 | I12: 17704 | J12: 3685 | N12: DeferredIncomeTaxExpenseBenefit, DeferredIncomeTaxesAndTaxCredits
A13: Unrealized gain on marketable equity securities | I13: -548 | N13: EquitySecuritiesFvNiUnrealizedGainLoss
A14: Unrealized (gain) loss on equity investments | H14: -1138 | J14: 1204 | N14: UnrealizedGainLossOnMarketableAndNonmarketableEquityInvestments | O14: Unrealized (gain) and loss on equity investments
A15: Impairment charges for facilities consolidation | E15: 2218 | F15: 2432 | G15: 383 | H15: 0 | N15: ImpairmentOfLongLivedAssetsHeldForUse, RestructuringCharges | O15: Impairment charges for facilities consolidation, net | Impairment charges for leases and leasehold improvements
A16: Data center assets abandonment | E16: 1341 | F16: -224 | G16: 0 | N16: RestructuringCharges | O16: Abandonment charges for data center assets
A17: Fair value adjustments for non-marketable securities | E17: 463 | N17: EquitySecuritiesFvNiGainLoss
A18: Other | B18: 39 | C18: 118 | D18: -127 | E18: 178 | F18: 635 | G18: 87 | H18: -416 | I18: -453 | J18: -402 | N18: OtherNoncashIncomeExpense
A20: Changes in assets and liabilities:
A21: Accounts receivable | B21: -1961 | C21: -1512 | D21: -3110 | E21: 231 | F21: -2399 | G21: -1485 | H21: -1815 | I21: 660 | J21: -3272 | N21: IncreaseDecreaseInAccountsReceivable
A22: Prepaid expenses and other current assets | B22: 47 | C22: 135 | D22: -1750 | E22: 162 | F22: 559 | G22: -698 | H22: -89 | I22: -348 | J22: -4166 | N22: IncreaseDecreaseInPrepaidDeferredExpenseAndOtherAssets
A23: Other assets | B23: 41 | C23: -34 | D23: -349 | E23: -106 | F23: -80 | G23: -270 | H23: -481 | I23: -209 | J23: -4973 | N23: IncreaseDecreaseInOtherOperatingAssets
A24: Accounts payable | B24: 113 | C24: -17 | D24: 1436 | E24: 210 | F24: 51 | G24: 373 | H24: -14 | I24: -637 | J24: 1242 | N24: IncreaseDecreaseInAccountsPayableTrade
A25: Partners payable | B25: 348 | C25: 178 | D25: -12 | E25: 90 | F25: -271 | N25: IncreaseDecreaseInOtherAccountsPayable
A26: Accrued expenses and other current liabilities | B26: 7300 | C26: -1054 | D26: 3357 | E26: 4210 | F26: 5352 | G26: 323 | H26: 1077 | I26: -2883 | J26: 7602 | N26: IncreaseDecreaseInAccruedLiabilities
A27: Deferred revenue and deposits | B27: 123 | C27: 108 | D27: 187 | N27: IncreaseDecreaseInContractWithCustomerLiability
A28: Other liabilities | B28: 1239 | C28: -527 | D28: 941 | E28: 886 | F28: 624 | G28: 2805 | H28: 437 | I28: 868 | J28: 2910 | N28: IncreaseDecreaseInOtherNoncurrentLiabilities
A29: Net cash provided by operating activities | B29: 36314 | C29: 38747 | D29: 57683 | E29: 50475 | F29: 71113 | G29: 91328 | H29: 115800 | I29: 79586 | J29: 96873 | N29: NetCashProvidedByUsedInOperatingActivities
A31: Cash flows from investing activities
A32: Purchases of property and equipment | B32: -15102 | C32: -15115 | D32: -18567 | E32: -31431 | F32: -27266 | G32: -37256 | H32: -69691 | I32: -48308 | J32: -83055 | N32: PaymentsToAcquirePropertyPlantAndEquipment | O32: Purchases of property and equipment, net
A33: Proceeds relating to property and equipment | E33: 245 | F33: 221 | N33: ProceedsFromSaleOfPropertyPlantAndEquipment
A34: Purchases of marketable securities | B34: -23910 | C34: -33930 | D34: -30407 | E34: -9626 | F34: -2982 | G34: -25542 | H34: -36929 | I34: -22349 | J34: -117467 | N34: PaymentsToAcquireAvailableForSaleSecuritiesDebt, PaymentsToAcquireMarketableSecurities | O34: Purchases of marketable debt securities
A35: Sales of marketable debt securities | B35: 9565 | C35: 11787 | D35: 31671 | E35: 11083 | N35: ProceedsFromSaleOfAvailableForSaleSecuritiesDebt | O35: Sales of marketable securities
A36: Maturities of marketable debt securities | B36: 10152 | C36: 13984 | D36: 10915 | E36: 2075 | N36: ProceedsFromMaturitiesPrepaymentsAndCallsOfAvailableForSaleSecurities | O36: Maturities of marketable securities
A37: Sales and maturities of marketable securities | F37: 6184 | G37: 15789 | H37: 26874 | I37: 23761 | J37: 88837 | N37: ProceedsFromSaleAndMaturityOfAvailableForSaleSecurities, ProceedsFromSaleAndMaturityOfMarketableSecurities | O37: Sales and maturities of marketable debt securities
A38: Payments for held-for-sale assets | H38: -2432 | I38: -1797 | J38: -1612 | N38: PaymentsForHeldForSaleAssets
A39: Proceeds from Venture distribution | H39: 2554 | J39: 1037 | N39: ProceedsFromOneTimeVentureDistribution, EquityMethodInvestmentDividendsOrDistributions | O39: Proceeds from data center venture distribution
A40: Purchases of non-marketable equity investments | C40: -6361 | D40: -47 | E40: -5 | H40: -18330 | I40: -18260 | J40: -2544 | N40: PaymentsForEquitySecuritiesWithoutReadilyDeterminableFairValue, PaymentsForEquitySecuritiesWithoutReadilyDeterminableFairValue | O40: Purchases of non-marketable equity securities | Purchases of equity investments | Payments for non-marketable equity investments
A41: Acquisitions of businesses and intangible assets | B41: -508 | C41: -388 | D41: -851 | E41: -1312 | F41: -629 | G41: -270 | H41: -4231 | I41: -815 | J41: -584 | N41: PaymentsToAcquireBusinessesNetOfCashAcquiredAndPurchasesOfIntangibleAndOtherAssets, PaymentsToAcquireBusinessesNetOfCashAcquiredAndPurchasesOfIntangibleAndOtherAssets | O41: Acquisitions of businesses, net of cash acquired, and purchases of intangible assets
A42: Other investing activities | B42: -61 | C42: -36 | D42: -284 | E42: 1 | F42: -23 | G42: 129 | H42: 182 | I42: -48 | J42: 1079 | N42: PaymentsForProceedsFromOtherInvestingActivities | O42: Other investing activities, net
A43: Net cash used in investing activities | B43: -19864 | C43: -30059 | D43: -7570 | E43: -28970 | F43: -24495 | G43: -47150 | H43: -102003 | I43: -67816 | J43: -114309 | N43: NetCashProvidedByUsedInInvestingActivities
A45: Cash flows from financing activities
A46: Taxes paid related to net share settlement of equity awards | B46: -2337 | C46: -3564 | D46: -5515 | E46: -3595 | F46: -7012 | G46: -13770 | H46: -18400 | I46: -14128 | J46: -12768 | N46: PaymentsRelatedToTaxWithholdingForShareBasedCompensation
A47: Repurchases of Class A common stock | B47: -4202 | C47: -6272 | D47: -44537 | E47: -27956 | F47: -19774 | G47: -30125 | H47: -26248 | I47: -26248 | J47: 0 | N47: PaymentsForRepurchaseOfCommonStock
A48: Payments for dividends and dividend equivalents | G48: -5072 | H48: -5324 | I48: -3986 | J48: -4060 | N48: PaymentsOfDividends
A49: Proceeds from issuance of long-term debt, net | E49: 9921 | F49: 8455 | G49: 10432 | H49: 29906 | I49: 0 | J49: 24910 | N49: ProceedsFromIssuanceOfLongTermDebt
A50: Principal payments on finance leases | B50: -552 | C50: -604 | D50: -677 | E50: -850 | F50: -1058 | G50: -1969 | H50: -2524 | I50: -1770 | J50: -2769 | N50: FinanceLeasePrincipalPayments
A51: Net change in overdraft in cash pooling entities | B51: -223 | C51: 24 | D51: 14 | N51: ProceedsFromRepaymentsOfBankOverdrafts
A52: Other financing activities | B52: 15 | C52: 124 | D52: -13 | E52: 344 | F52: -111 | G52: -277 | H52: 2220 | I52: 613 | J52: -2631 | N52: ProceedsFromPaymentsForOtherFinancingActivities | O52: Other financing activities, net
A53: Net cash used in financing activities | B53: -7299 | C53: -10292 | D53: -50728 | E53: -22136 | F53: -19500 | G53: -40781 | H53: -20370 | I53: -45519 | J53: 2682 | N53: NetCashProvidedByUsedInFinancingActivities | O53: Net cash provided by (used in) financing activities
A55: Effect of exchange rate changes on cash, cash equivalents, and restricted cash equivalents | B55: 4 | C55: 279 | D55: -474 | E55: -638 | F55: 113 | G55: -786 | H55: 235 | I55: 252 | J55: 8 | N55: EffectOfExchangeRateOnCashCashEquivalentsRestrictedCashAndRestrictedCashEquivalents | O55: Effect of exchange rate changes on cash, cash equivalents, and restricted cash | Effect of exchange rate changes on cash, cash equivalents, restricted cash, and restricted cash equivalents
A56: Net increase (decrease) in cash, cash equivalents, and restricted cash equivalents | B56: 9155 | C56: -1325 | D56: -1089 | E56: -1269 | F56: 27231 | G56: 2611 | H56: -6338 | I56: -33497 | J56: -14746 | N56: CashCashEquivalentsRestrictedCashAndRestrictedCashEquivalentsPeriodIncreaseDecreaseIncludingExchangeRateEffect | O56: Net increase (decrease) in cash, cash equivalents, and restricted cash | Net decrease in cash, cash equivalents, and restricted cash | Net decrease in cash, cash equivalents, restricted cash, and restricted cash equivalents
A58: Cash, cash equivalents, and restricted cash equivalents at beginning of the period | B58: 10124 | C58: 19279 | D58: 17954 | E58: 16865 | F58: 15596 | G58: 42827 | H58: 45438 | I58: 45438 | J58: 39100 | N58: CashCashEquivalentsRestrictedCashAndRestrictedCashEquivalents | O58: Cash, cash equivalents, and restricted cash at beginning of the period | Cash, cash equivalents, restricted cash, and restricted cash equivalents at beginning of the period
A59: Cash, cash equivalents, and restricted cash equivalents at end of the period | B59: 19279 | C59: 17954 | D59: 16865 | E59: 15596 | F59: 42827 | G59: 45438 | H59: 39100 | I59: 11941 | J59: 24354 | N59: CashCashEquivalentsRestrictedCashAndRestrictedCashEquivalents | O59: Cash, cash equivalents, and restricted cash at end of the period | Cash, cash equivalents, restricted cash, and restricted cash equivalents at end of the period
A61: Reconciliation of cash, cash equivalents, and restricted cash equivalents to the consolidated balance sheets | O61: Reconciliation of cash, cash equivalents, and restricted cash to the consolidated balance sheets | Reconciliation of cash, cash equivalents, restricted cash, and restricted cash equivalents to the condensed consolidated balance sheets | Reconciliation of cash, cash equivalents, and restricted cash equivalents to the condensed consolidated balance sheets
A62: Cash and cash equivalents | B62: 19079 | C62: 17576 | D62: 16601 | E62: 14681 | F62: 41862 | G62: 43889 | H62: 35873 | I62: 10187 | J62: 11222 | N62: CashAndCashEquivalentsAtCarryingValue
A63: Restricted cash equivalents, included in prepaid expenses and other current assets | B63: 8 | C63: 241 | D63: 149 | E63: 294 | F63: 99 | G63: 353 | H63: 837 | I63: 142 | J63: 597 | N63: RestrictedCashAndCashEquivalents, RestrictedCashAndCashEquivalentsAtCarryingValue | O63: Restricted cash, included in prepaid expenses and other current assets | Restricted cash and restricted cash equivalents, included in prepaid expenses and other current assets
A64: Restricted cash equivalents, included in other assets | B64: 192 | C64: 137 | D64: 115 | E64: 621 | F64: 866 | G64: 1196 | H64: 2390 | I64: 1612 | J64: 12535 | N64: RestrictedCashAndCashEquivalents, RestrictedCashAndCashEquivalentsNoncurrent | O64: Restricted cash, included in other assets | Restricted cash and restricted cash equivalents, included in other assets
A65: Total cash, cash equivalents, and restricted cash equivalents | B65: 19279 | C65: 17954 | D65: 16865 | E65: 15596 | F65: 42827 | G65: 45438 | H65: 39100 | I65: 11941 | J65: 24354 | N65: (untagged in the filing), CashCashEquivalentsRestrictedCashAndRestrictedCashEquivalents | O65: Total cash, cash equivalents, and restricted cash | Total cash, cash equivalents, restricted cash, and restricted cash equivalents
A67: Supplemental cash flow data
A68: Cash paid for income taxes, net | B68: 5182 | C68: 4229 | D68: 8525 | E68: 6407 | F68: 6607 | G68: 10554 | H68: 7578 | I68: 6293 | J68: 2926 | N68: IncomeTaxesPaidNet | O68: Cash paid for income taxes
A69: Cash paid for interest, net of amounts capitalized | F69: 448 | G69: 486 | H69: 696 | I69: 603 | J69: 1368 | N69: InterestPaidNet
A71: Non-cash investing and financing activities: | O71: Non-cash investing activities:
A72: Net change in prepaids and liabilities related to property and equipment | B72: -153 | N72: IncreaseDecreaseInPrepaidsAndLiabilitiesRelatedToPropertyAndEquipmentAdditions
A73: Property and equipment in accounts payable and accrued expenses and other current liabilities | B73: 1887 | C73: 2201 | D73: 3404 | E73: 3319 | F73: 4105 | G73: 7127 | H73: 9331 | I73: 9136 | J73: 21109 | N73: CapitalExpendituresIncurredButNotYetPaid | O73: Property and equipment in accounts payable and accrued liabilities
A74: Acquisition of businesses and intangible assets in accounts payable, accrued expenses and other current liabilities, and other liabilities | C74: 118 | D74: 73 | E74: 291 | F74: 119 | G74: 172 | H74: 2659 | I74: 1931 | J74: 1593 | N74: AcquisitionIncurredButNotYetPaid, AcquisitionIncurredButNotYetPaid, AcquisitionOfBusinessAndIntangibleAssets | O74: Acquisition of businesses and intangible assets in accrued expenses and other current liabilities and other liabilities | Acquisition of businesses in accrued expenses and other current liabilities and other liabilities
A75: Other current assets through financing arrangement in accrued expenses and other current liabilities | D75: 508 | E75: 16 | F75: 15 | N75: OtherSignificantNoncashTransaction, OtherSignificantNoncashTransaction
A76: Repurchases of Class A common stock in accrued expenses and other current liabilities | D76: 340 | E76: 310 | F76: 474 | G76: 0 | N76: RepurchaseOfCommonStockInAccruedExpensesAndOtherCurrentLiabilities, RepurchaseOfCommonStockInAccruedExpensesAndOtherCurrentLiabilities
A78: Checks (each should be zero)
A79: Operating lines add to net cash from operating activities | B79: =B7+B10+B11+B12+B18+B21+B22+B23+B24+B25+B26+B27+B28-B29 -> 0 | C79: =C7+C10+C11+C12+C18+C21+C22+C23+C24+C25+C26+C27+C28-C29 -> 0 | D79: =D7+D10+D11+D12+D18+D21+D22+D23+D24+D25+D26+D27+D28-D29 -> 0 | E79: =E7+E10+E11+E12+E15+E16+E17+E18+E21+E22+E23+E24+E25+E26+E28-E29 -> 0 | F79: =F7+F10+F11+F12+F15+F16+F18+F21+F22+F23+F24+F25+F26+F28-F29 -> 0 | G79: =G7+G10+G11+G12+G15+G16+G18+G21+G22+G23+G24+G26+G28-G29 -> 0 | H79: =H7+H10+H11+H12+H14+H15+H18+H21+H22+H23+H24+H26+H28-H29 -> 0 | I79: =I7+I10+I11+I12+I13+I18+I21+I22+I23+I24+I26+I28-I29 -> 0 | J79: =J7+J10+J11+J12+J14+J18+J21+J22+J23+J24+J26+J28-J29 -> 0
A80: Investing lines add to net cash from investing activities | B80: =B32+B34+B35+B36+B41+B42-B43 -> 0 | C80: =C32+C34+C35+C36+C40+C41+C42-C43 -> 0 | D80: =D32+D34+D35+D36+D40+D41+D42-D43 -> 0 | E80: =E32+E33+E34+E35+E36+E40+E41+E42-E43 -> 0 | F80: =F32+F33+F34+F37+F41+F42-F43 -> 0 | G80: =G32+G34+G37+G41+G42-G43 -> 0 | H80: =H32+H34+H37+H38+H39+H40+H41+H42-H43 -> 0 | I80: =I32+I34+I37+I38+I40+I41+I42-I43 -> 0 | J80: =J32+J34+J37+J38+J39+J40+J41+J42-J43 -> 0
A81: Financing lines add to net cash from financing activities | B81: =B46+B47+B50+B51+B52-B53 -> 0 | C81: =C46+C47+C50+C51+C52-C53 -> 0 | D81: =D46+D47+D50+D51+D52-D53 -> 0 | E81: =E46+E47+E49+E50+E52-E53 -> 0 | F81: =F46+F47+F49+F50+F52-F53 -> 0 | G81: =G46+G47+G48+G49+G50+G52-G53 -> 0 | H81: =H46+H47+H48+H49+H50+H52-H53 -> 0 | I81: =I46+I47+I48+I49+I50+I52-I53 -> 0 | J81: =J46+J47+J48+J49+J50+J52-J53 -> 0
A82: Three activities plus exchange rate effect equal the net change | B82: =B29+B43+B53+B55-B56 -> 0 | C82: =C29+C43+C53+C55-C56 -> 0 | D82: =D29+D43+D53+D55-D56 -> 0 | E82: =E29+E43+E53+E55-E56 -> 0 | F82: =F29+F43+F53+F55-F56 -> 0 | G82: =G29+G43+G53+G55-G56 -> 0 | H82: =H29+H43+H53+H55-H56 -> 0 | I82: =I29+I43+I53+I55-I56 -> 0 | J82: =J29+J43+J53+J55-J56 -> 0
A83: Beginning cash plus net change equals ending cash | B83: =B58+B56-B59 -> 0 | C83: =C58+C56-C59 -> 0 | D83: =D58+D56-D59 -> 0 | E83: =E58+E56-E59 -> 0 | F83: =F58+F56-F59 -> 0 | G83: =G58+G56-G59 -> 0 | H83: =H58+H56-H59 -> 0 | I83: =I58+I56-I59 -> 0 | J83: =J58+J56-J59 -> 0
A84: Reconciliation lines add to the total | B84: =B62+B63+B64-B65 -> 0 | C84: =C62+C63+C64-C65 -> 0 | D84: =D62+D63+D64-D65 -> 0 | E84: =E62+E63+E64-E65 -> 0 | F84: =F62+F63+F64-F65 -> 0 | G84: =G62+G63+G64-G65 -> 0 | H84: =H62+H63+H64-H65 -> 0 | I84: =I62+I63+I64-I65 -> 0 | J84: =J62+J63+J64-J65 -> 0
A85: Reconciliation total equals ending cash | B85: =B65-B59 -> 0 | C85: =C65-C59 -> 0 | D85: =D65-D59 -> 0 | E85: =E65-E59 -> 0 | F85: =F65-F59 -> 0 | G85: =G65-G59 -> 0 | H85: =H65-H59 -> 0 | I85: =I65-I59 -> 0 | J85: =J65-J59 -> 0
A86: Beginning cash equals the prior year's ending cash | C86: =C58-B59 -> 0 | D86: =D58-C59 -> 0 | E86: =E58-D59 -> 0 | F86: =F58-E59 -> 0 | G86: =G58-F59 -> 0 | H86: =H58-G59 -> 0 | J86: =J58-H59 -> 0

Sheet SCE_Hist
A1: Meta Platforms, Inc. | Consolidated Statements of Stockholders' Equity (roll-forward by component)
A2: USD millions; shares in millions. Each column of the filed statement is shown here as one block, years across.
B3: Audited (Form 10-K) | I3: Unaudited (Form 10-Q)
A4: Fiscal year ends 31 December | B4: 2019A | C4: 2020A | D4: 2021A | E4: 2022A | F4: 2023A | G4: 2024A | H4: 2025A | I4: 9M 2025A | J4: 9M 2026A | M4: Comentarios FG | N4: XBRL concept (latest filing) | O4: Earlier wording of this line
A6: Total stockholders' equity
A7: Balance at beginning of period | B7: 84127 | C7: 101054 | D7: 128290 | E7: 124879 | F7: 125713 | G7: 153168 | H7: 182637 | I7: 182637 | J7: 217243
A8: Net income | B8: 18485 | C8: 29146 | D8: 39370 | E8: 23200 | F8: 39098 | G8: 62360 | H8: 60458 | I8: 37690 | J8: 52481
A9: Other comprehensive income (loss) | B9: 271 | C9: 1416 | D9: -1620 | E9: -2837 | F9: 1375 | G9: -942 | H9: 3368 | I9: 3256 | J9: -1471 | O9: Other comprehensive income | Other comprehensive loss
A10: Issuance of common stock for cash upon exercise of stock options | B10: 15
A11: Issuance of common stock for settlement of RSUs | B11: 0 | C11: 0 | D11: 0
A12: Issuance of common stock | H12: 450 | I12: 450
A13: Shares withheld related to net share settlement | B13: -2581 | C13: -3564 | D13: -5515 | E13: -3595 | F13: -7012 | G13: -13770 | H13: -18400 | I13: -14128 | J13: -12768 | O13: Shares withheld related to net share settlement and other
A14: Share-based compensation | B14: 4836 | C14: 6536 | D14: 9164 | E14: 11992 | F14: 14027 | G14: 16690 | H14: 20427 | I14: 14537 | J14: 21053
A15: Share repurchases | B15: -4099 | C15: -6298 | D15: -44810 | E15: -27926 | F15: -20033 | G15: -29754 | H15: -26264 | I15: -26319
A16: Dividends and dividend equivalents declared | G16: -5121 | H16: -5421 | I16: -4052 | J16: -4152 | O16: Dividends and dividend equivalents declared ($2.00 per share)
A17: Other | G17: 6 | H17: -12 | I17: -5
A18: Balance at end of period | B18: 101054 | C18: 128290 | D18: 124879 | E18: 125713 | F18: 153168 | G18: 182637 | H18: 217243 | I18: 194066 | J18: 272386
A20: Class A and Class B common stock: shares (millions)
A21: Balance at beginning of period | B21: 2854 | C21: 2852 | D21: 2849 | E21: 2741 | F21: 2614 | G21: 2561 | H21: 2534 | I21: 2534 | J21: 2530
A22: Issuance of common stock for cash upon exercise of stock options | B22: 1
A23: Issuance of common stock for settlement of RSUs | B23: 32 | C23: 38 | D23: 45
A24: Issuance of common stock | E24: 54 | F24: 65 | G24: 65 | H24: 63 | I24: 47 | J24: 47
A25: Shares withheld related to net share settlement | B25: -13 | C25: -14 | D25: -17 | E25: -20 | F25: -26 | G25: -27 | H25: -27 | I25: -20 | J25: -21 | O25: Shares withheld related to net share settlement and other
A26: Share repurchases | B26: -22 | C26: -27 | D26: -136 | E26: -161 | F26: -92 | G26: -65 | H26: -40 | I26: -40
A27: Balance at end of period | B27: 2852 | C27: 2849 | D27: 2741 | E27: 2614 | F27: 2561 | G27: 2534 | H27: 2530 | I27: 2521 | J27: 2556
A29: Class A and Class B common stock: par value
A30: Balance at beginning of period | B30: 0 | C30: 0 | D30: 0 | E30: 0 | F30: 0 | G30: 0 | H30: 0 | I30: 0
A31: Balance at end of period | B31: 0 | C31: 0 | D31: 0 | E31: 0 | F31: 0 | G31: 0 | H31: 0 | I31: 0
A33: Additional paid-in capital
A34: Balance at beginning of period | B34: 42906 | C34: 45851 | D34: 50018 | E34: 55811 | F34: 64444 | G34: 73253 | H34: 83228 | I34: 83228 | J34: 95793
A35: Issuance of common stock for cash upon exercise of stock options | B35: 15
A36: Issuance of common stock | H36: 450 | I36: 450
A37: Shares withheld related to net share settlement | B37: -1906 | C37: -2369 | D37: -3371 | E37: -3359 | F37: -5218 | G37: -6721 | H37: -8312 | I37: -5880 | J37: -8602 | O37: Shares withheld related to net share settlement and other
A38: Share-based compensation | B38: 4836 | C38: 6536 | D38: 9164 | E38: 11992 | F38: 14027 | G38: 16690 | H38: 20427 | I38: 14537 | J38: 21053
A39: Other | G39: 6 | I39: -5
A40: Balance at end of period | B40: 45851 | C40: 50018 | D40: 55811 | E40: 64444 | F40: 73253 | G40: 83228 | H40: 95793 | I40: 92330 | J40: 108244 | O40: 9M 2026A: the Q3 2026 10-Q shows common stock and additional paid-in capital as one column; that column is shown here (par value is USD 0).
A42: Accumulated other comprehensive income (loss)
A43: Balance at beginning of period | B43: -760 | C43: -489 | D43: 927 | E43: -693 | F43: -3530 | G43: -2155 | H43: -3097 | I43: -3097 | J43: 271
A44: Other comprehensive income (loss) | B44: 271 | C44: 1416 | D44: -1620 | E44: -2837 | F44: 1375 | G44: -942 | H44: 3368 | I44: 3256 | J44: -1471 | O44: Other comprehensive income | Other comprehensive loss
A45: Balance at end of period | B45: -489 | C45: 927 | D45: -693 | E45: -3530 | F45: -2155 | G45: -3097 | H45: 271 | I45: 159 | J45: -1200
A47: Retained earnings
A48: Balance at beginning of period | B48: 41981 | C48: 55692 | D48: 77345 | E48: 69761 | F48: 64799 | G48: 82070 | H48: 102506 | I48: 102506 | J48: 121179
A49: Net income | B49: 18485 | C49: 29146 | D49: 39370 | E49: 23200 | F49: 39098 | G49: 62360 | H49: 60458 | I49: 37690 | J49: 52481
A50: Shares withheld related to net share settlement | B50: -675 | C50: -1195 | D50: -2144 | E50: -236 | F50: -1794 | G50: -7049 | H50: -10088 | I50: -8248 | J50: -4166 | O50: Shares withheld related to net share settlement and other
A51: Share repurchases | B51: -4099 | C51: -6298 | D51: -44810 | E51: -27926 | F51: -20033 | G51: -29754 | H51: -26264 | I51: -26319
A52: Dividends and dividend equivalents declared | G52: -5121 | H52: -5421 | I52: -4052 | J52: -4152 | O52: Dividends and dividend equivalents declared ($2.00 per share)
A53: Other | H53: -12
A54: Balance at end of period | B54: 55692 | C54: 77345 | D54: 69761 | E54: 64799 | F54: 82070 | G54: 102506 | H54: 121179 | I54: 101577 | J54: 165342
A56: Memo: dividends and dividend equivalents declared per share (USD) | G56: 2 | H56: 2.1 | I56: 1.575 | J56: 1.575
A58: Checks (each should be zero)
A59: Total stockholders' equity: beginning plus movements equal ending | B59: =B7+B8+B9+B10+B11+B13+B14+B15-B18 -> 0 | C59: =C7+C8+C9+C11+C13+C14+C15-C18 -> 0 | D59: =D7+D8+D9+D11+D13+D14+D15-D18 -> 0 | E59: =E7+E8+E9+E13+E14+E15-E18 -> 0 | F59: =F7+F8+F9+F13+F14+F15-F18 -> 0 | G59: =G7+G8+G9+G13+G14+G15+G16+G17-G18 -> 0 | H59: =H7+H8+H9+H12+H13+H14+H15+H16+H17-H18 -> 0 | I59: =I7+I8+I9+I12+I13+I14+I15+I16+I17-I18 -> 0 | J59: =J7+J8+J9+J13+J14+J16-J18 -> 0
A60: Class A and Class B common stock: shares (millions): beginning plus movements equal ending | B60: =B21+B22+B23+B25+B26-B27 -> 0 | C60: =C21+C23+C25+C26-C27 -> 0 | D60: =D21+D23+D25+D26-D27 -> 0 | E60: =E21+E24+E25+E26-E27 -> 0 | F60: =F21+F24+F25+F26-F27 -> 0 | G60: =G21+G24+G25+G26-G27 -> 0 | H60: =H21+H24+H25+H26-H27 -> 0 | I60: =I21+I24+I25+I26-I27 -> 0 | J60: =J21+J24+J25-J27 -> 0
A61: Class A and Class B common stock: par value: beginning plus movements equal ending | B61: =B30+0-B31 -> 0 | C61: =C30+0-C31 -> 0 | D61: =D30+0-D31 -> 0 | E61: =E30+0-E31 -> 0 | F61: =F30+0-F31 -> 0 | G61: =G30+0-G31 -> 0 | H61: =H30+0-H31 -> 0 | I61: =I30+0-I31 -> 0
A62: Additional paid-in capital: beginning plus movements equal ending | B62: =B34+B35+B37+B38-B40 -> 0 | C62: =C34+C37+C38-C40 -> 0 | D62: =D34+D37+D38-D40 -> 0 | E62: =E34+E37+E38-E40 -> 0 | F62: =F34+F37+F38-F40 -> 0 | G62: =G34+G37+G38+G39-G40 -> 0 | H62: =H34+H36+H37+H38-H40 -> 0 | I62: =I34+I36+I37+I38+I39-I40 -> 0 | J62: =J34+J37+J38-J40 -> 0
A63: Accumulated other comprehensive income (loss): beginning plus movements equal ending | B63: =B43+B44-B45 -> 0 | C63: =C43+C44-C45 -> 0 | D63: =D43+D44-D45 -> 0 | E63: =E43+E44-E45 -> 0 | F63: =F43+F44-F45 -> 0 | G63: =G43+G44-G45 -> 0 | H63: =H43+H44-H45 -> 0 | I63: =I43+I44-I45 -> 0 | J63: =J43+J44-J45 -> 0
A64: Retained earnings: beginning plus movements equal ending | B64: =B48+B49+B50+B51-B54 -> 0 | C64: =C48+C49+C50+C51-C54 -> 0 | D64: =D48+D49+D50+D51-D54 -> 0 | E64: =E48+E49+E50+E51-E54 -> 0 | F64: =F48+F49+F50+F51-F54 -> 0 | G64: =G48+G49+G50+G51+G52-G54 -> 0 | H64: =H48+H49+H50+H51+H52+H53-H54 -> 0 | I64: =I48+I49+I50+I51+I52-I54 -> 0 | J64: =J48+J49+J50+J52-J54 -> 0
A65: Components add to total equity (beginning) | B65: =B30+B34+B43+B48-B7 -> 0 | C65: =C30+C34+C43+C48-C7 -> 0 | D65: =D30+D34+D43+D48-D7 -> 0 | E65: =E30+E34+E43+E48-E7 -> 0 | F65: =F30+F34+F43+F48-F7 -> 0 | G65: =G30+G34+G43+G48-G7 -> 0 | H65: =H30+H34+H43+H48-H7 -> 0 | I65: =I30+I34+I43+I48-I7 -> 0 | J65: =J34+J43+J48-J7 -> 0
A66: Components add to total equity (end) | B66: =B31+B40+B45+B54-B18 -> 0 | C66: =C31+C40+C45+C54-C18 -> 0 | D66: =D31+D40+D45+D54-D18 -> 0 | E66: =E31+E40+E45+E54-E18 -> 0 | F66: =F31+F40+F45+F54-F18 -> 0 | G66: =G31+G40+G45+G54-G18 -> 0 | H66: =H31+H40+H45+H54-H18 -> 0 | I66: =I31+I40+I45+I54-I18 -> 0 | J66: =J40+J45+J54-J18 -> 0
A67: Beginning equity equals the prior year-end | C67: =C7-B18 -> 0 | D67: =D7-C18 -> 0 | E67: =E7-D18 -> 0 | F67: =F7-E18 -> 0 | G67: =G7-F18 -> 0 | H67: =H7-G18 -> 0 | I67: =I7-G18 -> 0 | J67: =J7-H18 -> 0

Sheet Revenue_Hist
A1: Meta Platforms, Inc. | Revenue: sources, segments, regions and drivers
A2: USD millions unless the row says otherwise. Each number comes from the filing that first reported it. Sections A and B: audited notes. Section C: management's discussion, not audited. Section D: formulas.
B3: Form 10-K | I3: Form 10-Q
A4: Fiscal year ends 31 December | B4: 2019A | C4: 2020A | D4: 2021A | E4: 2022A | F4: 2023A | G4: 2024A | H4: 2025A | I4: 9M 2025A | J4: 9M 2026A | M4: Comentarios FG | N4: Where in the filing | O4: Note
A6: A. Revenue by source and by segment (audited note)
A7: Advertising | B7: 69655 | C7: 84169 | D7: 114934 | E7: 113642 | F7: 131948 | G7: 160633 | H7: 196175 | I7: 138037 | J7: 177449 | N7: Notes: Revenue (by source and by segment)
A8: Other revenue | B8: 541 | C8: 657 | D8: 721 | E8: 808 | F8: 1058 | G8: 1722 | H8: 2584 | I8: 1784 | J8: 2987 | N8: Notes: Revenue (by source and by segment) | O8: 2019A and 2020A first reported in the 2021 10-K, the first 10-K with two segments. Mainly business messaging and Meta Verified.
A9: Family of Apps | B9: 70196 | C9: 84826 | D9: 115655 | E9: 114450 | F9: 133006 | G9: 162355 | H9: 198759 | I9: 139821 | J9: 180436 | N9: Notes: Revenue (by source and by segment) | O9: 2019A and 2020A first reported in the 2021 10-K, the first 10-K with two segments.
A10: Reality Labs | B10: 501 | C10: 1139 | D10: 2274 | E10: 2159 | F10: 1896 | G10: 2146 | H10: 2207 | I10: 1252 | J10: 1276 | N10: Notes: Revenue (by source and by segment) | O10: 2019A and 2020A first reported in the 2021 10-K, the first 10-K with two segments. Hardware, software and content.
A11: Total revenue | B11: 70697 | C11: 85965 | D11: 117929 | E11: 116609 | F11: 134902 | G11: 164501 | H11: 200966 | I11: 141073 | J11: 181712 | N11: Notes: Revenue (by source and by segment)
A13: Memo: other revenue as reported before the segment split | B13: 1042 | C13: 1796 | N13: Notes: Revenue (by source and by segment) | O13: The 2019 and 2020 10-Ks show one other-revenue line that includes Reality Labs. The 2021 10-K split it (see Recasts).
A14: Memo: total revenue per the income statement | B14: =IS_Hist!B6 -> 70697 | C14: =IS_Hist!C6 -> 85965 | D14: =IS_Hist!D6 -> 117929 | E14: =IS_Hist!E6 -> 116609 | F14: =IS_Hist!F6 -> 134902 | G14: =IS_Hist!G6 -> 164501 | H14: =IS_Hist!H6 -> 200966 | I14: =IS_Hist!I6 -> 141073 | J14: =IS_Hist!J6 -> 181712
A16: B. Revenue by region, by the customer's address (audited note) | O16: Region = the address of the customer (the advertiser), not the place of the user.
A17: United States and Canada | B17: 32206 | C17: 38433 | D17: 51541 | E17: 50150 | F17: 52888 | G17: 63207 | H17: 78866 | I17: 55031 | J17: 71346 | N17: Notes: Revenue (by geography)
A18: Europe | B18: 16826 | C18: 20349 | D18: 29057 | E18: 26681 | F18: 31210 | G18: 38361 | H18: 46569 | I18: 32315 | J18: 41272 | N18: Notes: Revenue (by geography) | O18: Includes Russia and Turkey.
A19: Asia-Pacific | B19: 15406 | C19: 19848 | D19: 26739 | E19: 27760 | F19: 36154 | G19: 45009 | H19: 53817 | I19: 38401 | J19: 48511 | N19: Notes: Revenue (by geography)
A20: Rest of World | B20: 6259 | C20: 7335 | D20: 10592 | E20: 12018 | F20: 14650 | G20: 17924 | H20: 21714 | I20: 15326 | J20: 20583 | N20: Notes: Revenue (by geography) | O20: Africa, Latin America and the Middle East.
A21: Total revenue | B21: 70697 | C21: 85965 | D21: 117929 | E21: 116609 | F21: 134902 | G21: 164501 | H21: 200966 | I21: 141073 | J21: 181712 | N21: Notes: Revenue (by geography)
A23: Memo: United States | B23: 30230 | C23: 36250 | D23: 48380 | E23: 47200 | F23: 49780 | G23: 59730 | H23: 74780 | N23: Notes: Revenue (footnote to the geography table) | O23: Given in USD billions with two decimals. The 10-Qs do not give it.
A24: Memo: China (customers based in China) | D24: 7590 | E24: 7400 | F24: 13690 | G24: 18350 | N24: Notes: Revenue (footnote to the geography table) | O24: Given in USD billions with two decimals. First given in the 2023 10-K, for 2021A to 2023A. The 2025 10-K does not give it.
A26: C. Drivers reported by Meta (management's discussion, not audited) | O26: The sentence behind each number: evidence/driver_sentences.tsv in the run folder 2026-10-26_meta-pestana-ingresos.
A27: Ad impressions delivered: change on a year earlier | B27: 0.33 | C27: 0.34 | D27: 0.1 | E27: 0.18 | F27: 0.28 | G27: 0.11 | H27: 0.12 | I27: 0.1 | J27: 0.14 | N27: Management's discussion: results of operations, revenue | O27: Meta gives whole percents. 9M columns: the nine months against the same nine months a year earlier.
A28: Average price per ad: change on a year earlier | B28: -0.05 | C28: -0.1 | D28: 0.24 | E28: -0.16 | F28: -0.09 | G28: 0.1 | H28: 0.09 | I28: 0.1 | J28: 0.13 | N28: Management's discussion: results of operations, revenue | O28: Meta gives whole percents.
A29: Daily active people, DAP (billions) | B29: 2.26 | C29: 2.6 | D29: 2.82 | E29: 2.96 | F29: 3.19 | G29: 3.35 | H29: 3.58 | I29: 3.54 | J29: 3.64 | N29: Management's discussion: key user metrics | O29: Average for December in the 10-K columns; average for September in the 10-Q columns.
A30: Daily active people: change on a year earlier | B30: 0.11 | C30: 0.15 | D30: 0.08 | E30: 0.05 | F30: 0.08 | G30: 0.05 | H30: 0.07 | I30: 0.08 | J30: 0.03 | N30: Management's discussion: key user metrics
A31: Facebook daily active users, DAU (billions) | B31: 1.66 | C31: 1.84 | D31: 1.93 | E31: 2 | F31: 2.11 | N31: Management's discussion: key user metrics | O31: Average for December. Facebook only. Meta stopped this metric after 2023.
A32: Average revenue per person, ARPP (USD): definition to 2023 | B32: 25.57 | C32: 27.51 | D32: 33.68 | E32: 31.79 | F32: 34.72 | N32: Management's discussion: monetization metrics | O32: Total revenue divided by monthly active people; sum of four quarters.
A33: Average revenue per person, ARPP (USD): definition from 2024 | G33: 49.63 | H33: 57.03 | N33: Management's discussion: monetization metrics | O33: Family of Apps revenue divided by daily active people; sum of four quarters. The 2024 10-K recast the 2023 quarters; their sum is 43.15 (not typed here).
A34: Facebook average revenue per user, ARPU (USD) | B34: 29.25 | C34: 32.03 | D34: 40.96 | E34: 39.63 | F34: 44.6 | N34: Management's discussion: monetization metrics | O34: Facebook only; sum of four quarters. Meta stopped this metric after 2023.
A35: Effect of exchange rates on revenue | B35: -1670 | C35: -120 | D35: 1640 | E35: -5960 | F35: 374 | G35: -874 | H35: -418 | I35: -906 | J35: 2320 | N35: Management's discussion: foreign exchange impact on revenue | O35: Revenue less revenue at the prior year's exchange rates. Meta says 'higher' or 'lower' in words; the sign is ours: negative = the dollar cut revenue.
A37: D. Calculated here (formulas, not in the filings)
A38: Revenue: growth on the prior period | C38: =C11/B11-1 -> 0.2159639 | D38: =D11/C11-1 -> 0.37182574 | E38: =E11/D11-1 -> -0.011193176 | F38: =F11/E11-1 -> 0.15687468 | G38: =G11/F11-1 -> 0.21941113 | H38: =H11/G11-1 -> 0.22167038 | J38: =J11/I11-1 -> 0.28807072
A39: Advertising revenue: growth on the prior period | C39: =C7/B7-1 -> 0.20836982 | D39: =D7/C7-1 -> 0.36551462 | E39: =E7/D7-1 -> -0.011241234 | F39: =F7/E7-1 -> 0.16108481 | G39: =G7/F7-1 -> 0.21739625 | H39: =H7/G7-1 -> 0.22126213 | J39: =J7/I7-1 -> 0.28551765
A40: Ads shown x price per ad: implied advertising growth | B40: =(1+B27)*(1+B28)-1 -> 0.2635 | C40: =(1+C27)*(1+C28)-1 -> 0.206 | D40: =(1+D27)*(1+D28)-1 -> 0.364 | E40: =(1+E27)*(1+E28)-1 -> -0.0088 | F40: =(1+F27)*(1+F28)-1 -> 0.1648 | G40: =(1+G27)*(1+G28)-1 -> 0.221 | H40: =(1+H27)*(1+H28)-1 -> 0.2208 | I40: =(1+I27)*(1+I28)-1 -> 0.21 | J40: =(1+J27)*(1+J28)-1 -> 0.2882 | O40: (1 + change in ads shown) x (1 + change in price per ad) - 1.
A41: Gap: implied less actual advertising growth | C41: =C40-C39 -> -0.0023698227 | D41: =D40-D39 -> -0.0015146194 | E41: =E40-E39 -> 0.0024412341 | F41: =F40-F39 -> 0.0037151898 | G41: =G40-G39 -> 0.003603753 | H41: =H40-H39 -> -0.00046213169 | J41: =J40-J39 -> 0.0026823489 | O41: Not a check. Meta rounds both changes to whole percents, so a gap up to about 1 point is normal.
A42: Revenue: growth at the prior year's exchange rates | C42: =(C11-C35)/B11-1 -> 0.21766129 | D42: =(D11-D35)/C11-1 -> 0.35274821 | E42: =(E11-E35)/D11-1 -> 0.039345708 | F42: =(F11-F35)/E11-1 -> 0.15366738 | G42: =(G11-G35)/F11-1 -> 0.22588991 | H42: =(H11-H35)/G11-1 -> 0.2242114 | J42: =(J11-J35)/I11-1 -> 0.27162533 | O42: (Revenue - exchange-rate effect) / prior-period revenue - 1.
A43: Advertising: share of revenue | B43: =B7/B11 -> 0.98526104 | C43: =C7/C11 -> 0.97910778 | D43: =D7/D11 -> 0.97460336 | E43: =E7/E11 -> 0.97455599 | F43: =F7/F11 -> 0.97810262 | G43: =G7/G11 -> 0.97648647 | H43: =H7/H11 -> 0.97616015 | I43: =I7/I11 -> 0.97847923 | J43: =J7/J11 -> 0.9765398
A44: Reality Labs: share of revenue | B44: =B10/B11 -> 0.0070865808 | C44: =C10/C11 -> 0.013249578 | D44: =D10/D11 -> 0.019282789 | E44: =E10/E11 -> 0.018514866 | F44: =F10/F11 -> 0.014054647 | G44: =G10/G11 -> 0.013045513 | H44: =H10/H11 -> 0.010981957 | I44: =I10/I11 -> 0.0088748378 | J44: =J10/J11 -> 0.0070221009
A46: Index, 2019A = 1.00 (full years only) | O46: Each index compounds the yearly changes from 2019A.
A47: Ads shown | B47: =1 -> 1 | C47: =B47*(1+C27) -> 1.34 | D47: =C47*(1+D27) -> 1.474 | E47: =D47*(1+E27) -> 1.73932 | F47: =E47*(1+F27) -> 2.2263296 | G47: =F47*(1+G27) -> 2.4712259 | H47: =G47*(1+H27) -> 2.767773
A48: Price per ad | B48: =1 -> 1 | C48: =B48*(1+C28) -> 0.9 | D48: =C48*(1+D28) -> 1.116 | E48: =D48*(1+E28) -> 0.93744 | F48: =E48*(1+F28) -> 0.8530704 | G48: =F48*(1+G28) -> 0.93837744 | H48: =G48*(1+H28) -> 1.0228314
A49: Ads shown x price per ad | B49: =B47*B48 -> 1 | C49: =C47*C48 -> 1.206 | D49: =D47*D48 -> 1.644984 | E49: =E47*E48 -> 1.6305081 | F49: =F47*F48 -> 1.8992159 | G49: =G47*G48 -> 2.3189426 | H49: =H47*H48 -> 2.8309651
A50: Advertising revenue, actual | B50: =B7/B7 -> 1 | C50: =C7/B7 -> 1.2083698 | D50: =D7/B7 -> 1.6500467 | E50: =E7/B7 -> 1.6314981 | F50: =F7/B7 -> 1.8943077 | G50: =G7/B7 -> 2.306123 | H50: =H7/B7 -> 2.8163807
A51: Daily active people (December) | B51: =B29/B29 -> 1 | C51: =C29/B29 -> 1.1504425 | D51: =D29/B29 -> 1.2477876 | E51: =E29/B29 -> 1.3097345 | F51: =F29/B29 -> 1.4115044 | G51: =G29/B29 -> 1.4823009 | H51: =H29/B29 -> 1.5840708
A52: Ads shown per daily active person (estimate) | B52: =B47/B51 -> 1 | C52: =C47/C51 -> 1.1647692 | D52: =D47/D51 -> 1.1812908 | E52: =E47/E51 -> 1.3279943 | F52: =F47/F51 -> 1.5772743 | G52: =G47/G51 -> 1.6671554 | H52: =H47/H51 -> 1.7472533 | O52: Estimate: ads shown index / people index. It divides a full-year count by a December average.
A54: Share of revenue by region
A55: United States and Canada | B55: =B17/B21 -> 0.45554974 | C55: =C17/C21 -> 0.4470773 | D55: =D17/D21 -> 0.43705111 | E55: =E17/E21 -> 0.43006972 | F55: =F17/F21 -> 0.39204756 | G55: =G17/G21 -> 0.38423475 | H55: =H17/H21 -> 0.39243454 | I55: =I17/I21 -> 0.39008882 | J55: =J17/J21 -> 0.3926323
A56: Europe | B56: =B18/B21 -> 0.23800161 | C56: =C18/C21 -> 0.23671262 | D56: =D18/D21 -> 0.24639402 | E56: =E18/E21 -> 0.22880738 | F56: =F18/F21 -> 0.23135313 | G56: =G18/G21 -> 0.23319615 | H56: =H18/H21 -> 0.23172576 | I56: =I18/I21 -> 0.2290658 | J56: =J18/J21 -> 0.22712864
A57: Asia-Pacific | B57: =B19/B21 -> 0.21791589 | C57: =C19/C21 -> 0.23088466 | D57: =D19/D21 -> 0.22673812 | E57: =E19/E21 -> 0.23806053 | F57: =F19/F21 -> 0.26800196 | G57: =G19/G21 -> 0.27360928 | H57: =H19/H21 -> 0.26779157 | I57: =I19/I21 -> 0.27220659 | J57: =J19/J21 -> 0.26696641
A58: Rest of World | B58: =B20/B21 -> 0.088532752 | C58: =C20/C21 -> 0.085325423 | D58: =D20/D21 -> 0.089816754 | E58: =E20/E21 -> 0.10306237 | F58: =F20/F21 -> 0.10859735 | G58: =G20/G21 -> 0.10895982 | H58: =H20/H21 -> 0.10804813 | I58: =I20/I21 -> 0.10863879 | J58: =J20/J21 -> 0.11327265
A59: China (customers based in China) | D59: =D24/D11 -> 0.064360759 | E59: =E24/E11 -> 0.063459939 | F59: =F24/F11 -> 0.10148108 | G59: =G24/G11 -> 0.11154947
A61: Checks (each should be zero)
A62: Advertising plus other revenue equals Family of Apps | B62: =B7+B8-B9 -> 0 | C62: =C7+C8-C9 -> 0 | D62: =D7+D8-D9 -> 0 | E62: =E7+E8-E9 -> 0 | F62: =F7+F8-F9 -> 0 | G62: =G7+G8-G9 -> 0 | H62: =H7+H8-H9 -> 0 | I62: =I7+I8-I9 -> 0 | J62: =J7+J8-J9 -> 0
A63: Family of Apps plus Reality Labs equals total revenue | B63: =B9+B10-B11 -> 0 | C63: =C9+C10-C11 -> 0 | D63: =D9+D10-D11 -> 0 | E63: =E9+E10-E11 -> 0 | F63: =F9+F10-F11 -> 0 | G63: =G9+G10-G11 -> 0 | H63: =H9+H10-H11 -> 0 | I63: =I9+I10-I11 -> 0 | J63: =J9+J10-J11 -> 0
A64: Revenue by source equals the income statement | B64: =B11-B14 -> 0 | C64: =C11-C14 -> 0 | D64: =D11-D14 -> 0 | E64: =E11-E14 -> 0 | F64: =F11-F14 -> 0 | G64: =G11-G14 -> 0 | H64: =H11-H14 -> 0 | I64: =I11-I14 -> 0 | J64: =J11-J14 -> 0
A65: Regions add to total revenue | B65: =B17+B18+B19+B20-B21 -> 0 | C65: =C17+C18+C19+C20-C21 -> 0 | D65: =D17+D18+D19+D20-D21 -> 0 | E65: =E17+E18+E19+E20-E21 -> 0 | F65: =F17+F18+F19+F20-F21 -> 0 | G65: =G17+G18+G19+G20-G21 -> 0 | H65: =H17+H18+H19+H20-H21 -> 0 | I65: =I17+I18+I19+I20-I21 -> 0 | J65: =J17+J18+J19+J20-J21 -> 0
A66: Revenue by region equals the income statement | B66: =B21-B14 -> 0 | C66: =C21-C14 -> 0 | D66: =D21-D14 -> 0 | E66: =E21-E14 -> 0 | F66: =F21-F14 -> 0 | G66: =G21-G14 -> 0 | H66: =H21-H14 -> 0 | I66: =I21-I14 -> 0 | J66: =J21-J14 -> 0
A67: Before the split: advertising plus other revenue equals total revenue | B67: =B7+B13-B11 -> 0 | C67: =C7+C13-C11 -> 0
A68: The split: other revenue plus Reality Labs equals the earlier other revenue | B68: =B8+B10-B13 -> 0 | C68: =C8+C10-C13 -> 0

Sheet Assumptions
A1: Meta Platforms, Inc. | Assumptions and scenarios | F1: 15
A2: Blue cells are inputs. Each driver has Base, Bull and Bear rows; the Active row follows the switch in C5. USD millions unless stated.
H3: Actual | I3: Forecast
A4: Fiscal year ends 31 December | B4: 2019 | C4: =+B4+1 -> 2020 | D4: =+C4+1 -> 2021 | E4: =+D4+1 -> 2022 | F4: =+E4+1 -> 2023 | G4: =+F4+1 -> 2024 | H4: =+G4+1 -> 2025 | I4: =+H4+1 -> 2026 | J4: =+I4+1 -> 2027 | ... R4: =+Q4+1 -> 2035 | S4: Comentarios FG | T4: Source / derivation
A5: Scenario switch: 1 = Base, 2 = Bull, 3 = Bear | B5: 1 | T5: Same convention as the house templates (Supuestos!C5).
A6: Active scenario | B6: =CHOOSE(B5,"Base","Bull","Bear") -> Base
A8: A. 2026E bridge and valuation inputs (one value per scenario)
I9: Active | J9: Base | K9: Bull | L9: Bear
A10: Q4 2026E revenue (USD m) | I10: =CHOOSE($B$5,J10,K10,L10) -> 74500 | J10: 74500 | K10: 76000 | L10: 73000 | T10: Guidance USD 73-76 bn (Q3 2026 earnings, 21 Oct 2026): midpoint, top, bottom.
A11: FY2026E total costs and expenses (USD m) | I11: =CHOOSE($B$5,J11,K11,L11) -> 177000 | J11: 177000 | K11: 175000 | L11: 179000 | T11: Guidance USD 175-179 bn including the legal charge (Q3 2026 earnings call).
A12: Q4 2026E effective tax rate | I12: =CHOOSE($B$5,J12,K12,L12) -> 0.16 | J12: 0.16 | K12: 0.15 | L12: 0.17 | T12: Guidance 15-17% (Q3 2026 earnings call).
A13: Q4 2026E other revenue: growth on Q4 2025 | I13: =CHOOSE($B$5,J13,K13,L13) -> 0.6 | J13: 0.6 | K13: 0.7 | L13: 0.5 | T13: 9M 2026 +67% (10-Q).
A14: Q4 2026E Reality Labs revenue (USD m) | I14: =CHOOSE($B$5,J14,K14,L14) -> 955 | J14: 955 | K14: 1050 | L14: 900 | T14: Q4 2025 = 955 (FY2025 less 9M 2025). Base flat (9M 2026 +2%).
A15: Q4 2026E Reality Labs operating loss (USD m) | I15: =CHOOSE($B$5,J15,K15,L15) -> -5725 | J15: -5725 | K15: -5225 | L15: -6225 | T15: FY2026 loss guidance USD 18-19 bn less 9M loss 12,775.
A16: Terminal growth (after 2035E) | I16: =CHOOSE($B$5,J16,K16,L16) -> 0.03 | J16: 0.03 | K16: 0.035 | L16: 0.025 | T16: Below the 10-year Treasury yield (5.00%); near long-run nominal GDP. Analyst input.
A17: Terminal return on new invested capital | I17: =CHOOSE($B$5,J17,K17,L17) -> 0.2 | J17: 0.2 | K17: 0.3 | L17: 0.12 | T17: Reinvestment = growth / ROIC (Damodaran). Meta's pre-AI ROIC was about 30%. Analyst input.
A18: Exit EV / EBITDA multiple (2035E) | I18: =CHOOSE($B$5,J18,K18,L18) -> 10 | J18: 10 | K18: 12 | L18: 7 | T18: Cross-check only. LTM EV/EBITDA today about 14x-16x; a 2035 exit sees lower growth. Analyst input.
A19: Terminal return on equity (FCFE method) | I19: =CHOOSE($B$5,J19,K19,L19) -> 0.25 | J19: 0.25 | K19: 0.3 | L19: 0.15 | T19: Reinvestment of equity = growth / ROE. Analyst input.
A21: B. Inputs that do not change with the scenario
A22: Q4 2026E interest and other income, net (USD m) | I22: -200 | T22: Interest income on about USD 82 bn of cash at 3.5% less interest on USD 84 bn of notes at 4.8%, per quarter.
A23: Q4 2026E interest expense on the notes (USD m) | I23: 1000 | T23: USD 84 bn x 4.8% / 4.
A24: Q4 2026E depreciation and amortization (USD m) | I24: 8200 | T24: Q3 2026 depreciation 6,810 grows about 15% a quarter, plus about 340 of amortization (10-Q).
A25: Q4 2026E share-based compensation (USD m) | I25: 7000 | T25: 9M 2026: 21,053 (10-Q), so about 7,000 a quarter.
A26: Q4 2026E taxes paid on RSU net share settlement (USD m) | I26: 4250 | T26: 9M 2026: 12,768 (10-Q), so about 4,250 a quarter.
A27: Q4 2026E dividends paid (USD m) | I27: 1360 | T27: Q3 2026 payments USD 1.36 bn (press release).
A28: Q4 2026E new debt issued (USD m) | I28: 0 | T28: No issue announced after 30 Sep 2026.
A29: Q4 2026E share buybacks (USD m) | I29: 0 | T29: No buybacks in 9M 2026 (10-Q).
A30: 9M 2026 legal charges in costs (USD m) | I30: 11890 | T30: Multistate attorneys general agreement charges (10-Q, G&A discussion).
A31: Interest income yield on cash and marketable securities | I31: 0.035 | T31: Between the 2025 realized yield (about 2.7%) and the 3-month bill (4.22%, Treasury, 26 Oct 2026). Analyst input.
A32: Interest rate on debt (on beginning balance) | I32: 0.048 | T32: Coupons 3.50%-6.45% (10-Q Note 9); new issues near 5.3%-6.5%. Analyst input.
A33: Minimum cash and marketable securities: % of revenue | I33: 0.25 | T33: Meta held 34% of LTM revenue at 30 Sep 2026; S&P expects a neutral net debt position. Analyst policy input.
... A45: Sensitivity: capex scale versus the scenario path | I45: 0 | T45: Keep at 0. The Sensitivity sheet moves it.
A46: Accounts receivable: % of revenue | I46: =BS_Hist!H11/IS_Hist!H6 -> 0.098369874 | T46: 2025A ratio, held flat (link to the audited balance sheet).
A47: Prepaid expenses and other current assets: % of revenue | I47: =BS_Hist!H12/IS_Hist!H6 -> 0.036628086 | T47: 2025A ratio, held flat (link to the audited balance sheet).
A48: Accounts payable: % of revenue | I48: =BS_Hist!H26/IS_Hist!H6 -> 0.044256242 | T48: 2025A ratio, held flat (link to the audited balance sheet).
A49: Accrued expenses and other current liabilities: % of revenue | I49: =BS_Hist!H29/IS_Hist!H6 -> 0.15290646 | T49: 2025A ratio, held flat (link to the audited balance sheet).
A51: C. Drivers by year (Base, Bull, Bear and the active row)
A52: Ad impressions delivered: growth on a year earlier | T52: 2026E: 9M 2026 +14%, Q3 +10% (10-Q), so about 13% for the year. Later years fade with people growth (DAP +3% in Sep 2026) and ad load. Analyst input.
A53: Base | I53: 0.13 | J53: 0.1 | K53: 0.09 | L53: 0.08 | M53: 0.07 | N53: 0.06 | O53: 0.05 | P53: 0.04 | Q53: 0.035 | R53: 0.03
A54: Bull | I54: 0.14 | J54: 0.11 | K54: 0.1 | L54: 0.09 | M54: 0.08 | N54: 0.07 | O54: 0.06 | P54: 0.05 | Q54: 0.04 | R54: 0.035
A55: Bear | I55: 0.12 | J55: 0.09 | K55: 0.08 | L55: 0.07 | M55: 0.06 | N55: 0.05 | O55: 0.04 | P55: 0.04 | Q55: 0.03 | R55: 0.03
A56: Active | B56: =Revenue_Hist!B27 -> 0.33 | C56: =Revenue_Hist!C27 -> 0.34 | D56: =Revenue_Hist!D27 -> 0.1 | E56: =Revenue_Hist!E27 -> 0.18 | F56: =Revenue_Hist!F27 -> 0.28 | G56: =Revenue_Hist!G27 -> 0.11 | H56: =Revenue_Hist!H27 -> 0.12 | I56: =CHOOSE($B$5,I53,I54,I55) -> 0.13 | J56: =CHOOSE($B$5,J53,J54,J55) -> 0.1 | K56: =CHOOSE($B$5,K53,K54,K55) -> 0.09 | L56: =CHOOSE($B$5,L53,L54,L55) -> 0.08 | M56: =CHOOSE($B$5,M53,M54,M55) -> 0.07 | N56: =CHOOSE($B$5,N53,N54,N55) -> 0.06 | O56: =CHOOSE($B$5,O53,O54,O55) -> 0.05 | P56: =CHOOSE($B$5,P53,P54,P55) -> 0.04 | ... R56: =CHOOSE($B$5,R53,R54,R55) -> 0.03
A57: Average price per ad: growth on a year earlier (2026E is derived in Revenue_Build) | T57: Base 2027E: ads x price = +18.8%, near Moody's +18% expectation for 2027 (Investing.com, 2026). Bull: capex pays off, price keeps the 2024-2026 pace (+9% to +14%) and fades. Bear: price returns to its 2019-2025 average (about 0%). Analyst input.
A58: Base | I58: =((Interim_Bridge!$B$7+$J$10-Interim_Bridge!$F$8*(1+$J$13)-$J$14)/Revenue_Hist!$H$7)/(1+I53)-1 -> 0.126473 | J58: 0.08 | K58: 0.07 | L58: 0.06 | M58: 0.05 | N58: 0.04 | O58: 0.04 | P58: 0.035 | Q58: 0.03 | R58: 0.025
A59: Bull | I59: =((Interim_Bridge!$B$7+$K$10-Interim_Bridge!$F$8*(1+$K$13)-$K$14)/Revenue_Hist!$H$7)/(1+I54)-1 -> 0.12251637 | J59: 0.12 | K59: 0.11 | L59: 0.1 | M59: 0.08 | N59: 0.07 | O59: 0.06 | P59: 0.05 | Q59: 0.04 | R59: 0.035
A60: Bear | I60: =((Interim_Bridge!$B$7+$L$10-Interim_Bridge!$F$8*(1+$L$13)-$L$14)/Revenue_Hist!$H$7)/(1+I55)-1 -> 0.13031823 | J60: 0.04 | K60: 0.02 | L60: 0.01 | M60: 0 | N60: 0 | O60: 0 | P60: 0 | Q60: 0 | R60: 0
A61: Active | B61: =Revenue_Hist!B28 -> -0.05 | C61: =Revenue_Hist!C28 -> -0.1 | D61: =Revenue_Hist!D28 -> 0.24 | E61: =Revenue_Hist!E28 -> -0.16 | F61: =Revenue_Hist!F28 -> -0.09 | G61: =Revenue_Hist!G28 -> 0.1 | H61: =Revenue_Hist!H28 -> 0.09 | I61: =CHOOSE($B$5,I58,I59,I60) -> 0.126473 | J61: =CHOOSE($B$5,J58,J59,J60) -> 0.08 | K61: =CHOOSE($B$5,K58,K59,K60) -> 0.07 | L61: =CHOOSE($B$5,L58,L59,L60) -> 0.06 | M61: =CHOOSE($B$5,M58,M59,M60) -> 0.05 | N61: =CHOOSE($B$5,N58,N59,N60) -> 0.04 | O61: =CHOOSE($B$5,O58,O59,O60) -> 0.04 | P61: =CHOOSE($B$5,P58,P59,P60) -> 0.035 | ... R61: =CHOOSE($B$5,R58,R59,R60) -> 0.025
A62: Family of Apps other revenue: growth on a year earlier | T62: 2025A +50%, 9M 2026 +67% (business messaging, Meta Verified). Fades. Analyst input.
A63: Base | I63: =(Interim_Bridge!$B$8+Interim_Bridge!$F$8*(1+$J$13))/Revenue_Hist!$H$8-1 -> 0.65131579 | J63: 0.4 | K63: 0.3 | L63: 0.25 | M63: 0.2 | N63: 0.15 | O63: 0.12 | P63: 0.1 | Q63: 0.08 | R63: 0.06
A64: Bull | I64: =(Interim_Bridge!$B$8+Interim_Bridge!$F$8*(1+$K$13))/Revenue_Hist!$H$8-1 -> 0.68227554 | J64: 0.5 | K64: 0.4 | L64: 0.3 | M64: 0.25 | N64: 0.2 | O64: 0.15 | P64: 0.12 | Q64: 0.1 | R64: 0.08
A65: Bear | I65: =(Interim_Bridge!$B$8+Interim_Bridge!$F$8*(1+$L$13))/Revenue_Hist!$H$8-1 -> 0.62035604 | J65: 0.25 | K65: 0.2 | L65: 0.15 | M65: 0.1 | N65: 0.08 | O65: 0.06 | P65: 0.05 | Q65: 0.04 | R65: 0.04
A66: Active | C66: =Revenue_Hist!C8/Revenue_Hist!B8-1 -> 0.21441774 | D66: =Revenue_Hist!D8/Revenue_Hist!C8-1 -> 0.097412481 | E66: =Revenue_Hist!E8/Revenue_Hist!D8-1 -> 0.12066574 | F66: =Revenue_Hist!F8/Revenue_Hist!E8-1 -> 0.30940594 | G66: =Revenue_Hist!G8/Revenue_Hist!F8-1 -> 0.62759924 | H66: =Revenue_Hist!H8/Revenue_Hist!G8-1 -> 0.50058072 | I66: =CHOOSE($B$5,I63,I64,I65) -> 0.65131579 | J66: =CHOOSE($B$5,J63,J64,J65) -> 0.4 | K66: =CHOOSE($B$5,K63,K64,K65) -> 0.3 | L66: =CHOOSE($B$5,L63,L64,L65) -> 0.25 | M66: =CHOOSE($B$5,M63,M64,M65) -> 0.2 | N66: =CHOOSE($B$5,N63,N64,N65) -> 0.15 | O66: =CHOOSE($B$5,O63,O64,O65) -> 0.12 | P66: =CHOOSE($B$5,P63,P64,P65) -> 0.1 | ... R66: =CHOOSE($B$5,R63,R64,R65) -> 0.06
A67: Reality Labs revenue: growth on a year earlier | T67: 9M 2026 +2% (10-Q). Bull: AI glasses scale. Analyst input.
A68: Base | I68: =(Interim_Bridge!$B$9+$J$14)/Revenue_Hist!$H$10-1 -> 0.01087449 | J68: 0.05 | K68: 0.05 | L68: 0.05 | M68: 0.05 | N68: 0.05 | O68: 0.05 | P68: 0.05 | Q68: 0.05 | R68: 0.05
A69: Bull | I69: =(Interim_Bridge!$B$9+$K$14)/Revenue_Hist!$H$10-1 -> 0.053919348 | J69: 0.15 | K69: 0.15 | L69: 0.12 | M69: 0.1 | N69: 0.1 | O69: 0.08 | P69: 0.08 | Q69: 0.06 | R69: 0.06
A70: Bear | I70: =(Interim_Bridge!$B$9+$L$14)/Revenue_Hist!$H$10-1 -> -0.014046217 | J70: 0 | K70: 0 | L70: 0 | M70: 0 | N70: 0 | O70: 0 | P70: 0 | Q70: 0 | R70: 0
A71: Active | C71: =Revenue_Hist!C10/Revenue_Hist!B10-1 -> 1.2734531 | D71: =Revenue_Hist!D10/Revenue_Hist!C10-1 -> 0.99648815 | E71: =Revenue_Hist!E10/Revenue_Hist!D10-1 -> -0.05057168 | F71: =Revenue_Hist!F10/Revenue_Hist!E10-1 -> -0.12181566 | G71: =Revenue_Hist!G10/Revenue_Hist!F10-1 -> 0.13185654 | H71: =Revenue_Hist!H10/Revenue_Hist!G10-1 -> 0.028424977 | I71: =CHOOSE($B$5,I68,I69,I70) -> 0.01087449 | J71: =CHOOSE($B$5,J68,J69,J70) -> 0.05 | K71: =CHOOSE($B$5,K68,K69,K70) -> 0.05 | L71: =CHOOSE($B$5,L68,L69,L70) -> 0.05 | M71: =CHOOSE($B$5,M68,M69,M70) -> 0.05 | N71: =CHOOSE($B$5,N68,N69,N70) -> 0.05 | O71: =CHOOSE($B$5,O68,O69,O70) -> 0.05 | P71: =CHOOSE($B$5,P68,P69,P70) -> 0.05 | ... R71: =CHOOSE($B$5,R68,R69,R70) -> 0.05
A72: Daily active people: growth on a year earlier (memo, revenue per person) | T72: DAP +3% in Sep 2026 (10-Q). Memo only; it does not drive revenue.
A73: Base | I73: =Revenue_Hist!$J$29/Revenue_Hist!$H$29-1 -> 0.016759777 | J73: 0.025 | K73: 0.02 | L73: 0.02 | M73: 0.015 | N73: 0.015 | O73: 0.01 | P73: 0.01 | Q73: 0.01 | R73: 0.01
A74: Bull | I74: =Revenue_Hist!$J$29/Revenue_Hist!$H$29-1 -> 0.016759777 | J74: 0.03 | K74: 0.025 | L74: 0.025 | M74: 0.02 | N74: 0.02 | O74: 0.015 | P74: 0.015 | Q74: 0.01 | R74: 0.01
A75: Bear | I75: =Revenue_Hist!$J$29/Revenue_Hist!$H$29-1 -> 0.016759777 | J75: 0.015 | K75: 0.01 | L75: 0.01 | M75: 0.005 | N75: 0.005 | O75: 0.005 | P75: 0.005 | Q75: 0.005 | R75: 0.005
A76: Active | B76: =Revenue_Hist!B30 -> 0.11 | C76: =Revenue_Hist!C30 -> 0.15 | D76: =Revenue_Hist!D30 -> 0.08 | E76: =Revenue_Hist!E30 -> 0.05 | F76: =Revenue_Hist!F30 -> 0.08 | G76: =Revenue_Hist!G30 -> 0.05 | H76: =Revenue_Hist!H30 -> 0.07 | I76: =CHOOSE($B$5,I73,I74,I75) -> 0.016759777 | J76: =CHOOSE($B$5,J73,J74,J75) -> 0.025 | K76: =CHOOSE($B$5,K73,K74,K75) -> 0.02 | L76: =CHOOSE($B$5,L73,L74,L75) -> 0.02 | M76: =CHOOSE($B$5,M73,M74,M75) -> 0.015 | N76: =CHOOSE($B$5,N73,N74,N75) -> 0.015 | O76: =CHOOSE($B$5,O73,O74,O75) -> 0.01 | P76: =CHOOSE($B$5,P73,P74,P75) -> 0.01 | ... R76: =CHOOSE($B$5,R73,R74,R75) -> 0.01
A77: Cash costs excluding D&A and one-off legal charges: % of revenue | T77: 2025A 49.3%; 2026E 53.6% excluding the USD 11.89 bn legal charge (cloud, AI token and staff costs). Base falls 0.875 pp a year from 54% to 47% (operating leverage; headcount -15% in 2026). Analyst input.
A78: Base | I78: =($J$11-Interim_Bridge!$D$13-Interim_Bridge!$D$17)/(IS_Hist!$J$6+$J$10) -> 0.53627855 | J78: 0.54 | K78: 0.531 | L78: 0.523 | M78: 0.514 | N78: 0.505 | O78: 0.496 | P78: 0.488 | Q78: 0.479 | R78: 0.47
A79: Bull | I79: =($K$11-Interim_Bridge!$D$13-Interim_Bridge!$D$17)/(IS_Hist!$J$6+$K$10) -> 0.52539657 | J79: 0.53 | K79: 0.5175 | L79: 0.505 | M79: 0.4925 | N79: 0.48 | O79: 0.4675 | P79: 0.455 | Q79: 0.4425 | R79: 0.43
A80: Bear | I80: =($L$11-Interim_Bridge!$D$13-Interim_Bridge!$D$17)/(IS_Hist!$J$6+$L$10) -> 0.5472887 | J80: 0.55 | K80: 0.545 | L80: 0.54 | M80: 0.535 | N80: 0.53 | O80: 0.525 | P80: 0.52 | Q80: 0.515 | R80: 0.51
A81: Active | B81: =(IS_Hist!B13-CF_Hist!B10)/IS_Hist!B6 -> 0.5795154 | C81: =(IS_Hist!C13-CF_Hist!C10)/IS_Hist!C6 -> 0.5401268 | D81: =(IS_Hist!D13-CF_Hist!D10)/IS_Hist!D6 -> 0.535992 | E81: =(IS_Hist!E13-CF_Hist!E10)/IS_Hist!E6 -> 0.67729764 | F81: =(IS_Hist!F13-CF_Hist!F10)/IS_Hist!F6 -> 0.57058457 | G81: =(IS_Hist!G13-CF_Hist!G10)/IS_Hist!G6 -> 0.48402745 | H81: =(IS_Hist!H13-CF_Hist!H10)/IS_Hist!H6 -> 0.49298886 | I81: =CHOOSE($B$5,I78,I79,I80) -> 0.53627855 | J81: =CHOOSE($B$5,J78,J79,J80) -> 0.54 | K81: =CHOOSE($B$5,K78,K79,K80) -> 0.531 | L81: =CHOOSE($B$5,L78,L79,L80) -> 0.523 | M81: =CHOOSE($B$5,M78,M79,M80) -> 0.514 | N81: =CHOOSE($B$5,N78,N79,N80) -> 0.505 | O81: =CHOOSE($B$5,O78,O79,O80) -> 0.496 | P81: =CHOOSE($B$5,P78,P79,P80) -> 0.488 | ... R81: =CHOOSE($B$5,R78,R79,R80) -> 0.47
A82: Legal charges outside the run-rate (USD m) | T82: Bear: the USD 25 bn New Mexico civil penalty (ordered 21 Oct 2026, under appeal; 10-Q Note 10) is paid in 2027E. Base and Bull: covered by amounts Meta has accrued.
A83: Base | I83: =Interim_Bridge!$D$13 -> 11890 | J83: 0 | K83: 0 | L83: 0 | M83: 0 | N83: 0 | O83: 0 | P83: 0 | Q83: 0 | R83: 0
A84: Bull | I84: =Interim_Bridge!$D$13 -> 11890 | J84: 0 | K84: 0 | L84: 0 | M84: 0 | N84: 0 | O84: 0 | P84: 0 | Q84: 0 | R84: 0
A85: Bear | I85: =Interim_Bridge!$D$13 -> 11890 | J85: 25000 | K85: 0 | L85: 0 | M85: 0 | N85: 0 | O85: 0 | P85: 0 | Q85: 0 | R85: 0
A86: Active | I86: =CHOOSE($B$5,I83,I84,I85) -> 11890 | J86: =CHOOSE($B$5,J83,J84,J85) -> 0 | K86: =CHOOSE($B$5,K83,K84,K85) -> 0 | L86: =CHOOSE($B$5,L83,L84,L85) -> 0 | M86: =CHOOSE($B$5,M83,M84,M85) -> 0 | N86: =CHOOSE($B$5,N83,N84,N85) -> 0 | O86: =CHOOSE($B$5,O83,O84,O85) -> 0 | P86: =CHOOSE($B$5,P83,P84,P85) -> 0 | ... R86: =CHOOSE($B$5,R83,R84,R85) -> 0
A87: Capital expenditures incl. finance-lease principal, Meta's definition (USD m) | T87: 2026E: guidance USD 135-145 bn (Q3 2026 10-Q); Base midpoint, Bull and Bear top. 2027E Base: midpoint of pre-earnings estimates USD 193-205 bn (Investing.com, 22 Oct 2026). Bull and Bear spend the same through 2028E (the payoff test); Bear cuts from 2029E when price stalls.
A88: Base | I88: 140000 | J88: 199000 | K88: 205000 | L88: 200000 | M88: 190000 | N88: 185000 | O88: 185000 | P88: 190000 | Q88: 195000 | R88: 200000
A89: Bull | I89: 145000 | J89: 215000 | K89: 235000 | L89: 240000 | M89: 235000 | N89: 230000 | O89: 230000 | P89: 235000 | Q89: 240000 | R89: 245000
A90: Bear | I90: 145000 | J90: 215000 | K90: 235000 | L90: 210000 | M90: 185000 | N90: 170000 | O90: 160000 | P90: 155000 | Q90: 155000 | R90: 155000
A91: Active | B91: =-(CF_Hist!B32+CF_Hist!B50) -> 15654 | C91: =-(CF_Hist!C32+CF_Hist!C50) -> 15719 | D91: =-(CF_Hist!D32+CF_Hist!D50) -> 19244 | E91: =-(CF_Hist!E32+CF_Hist!E50) -> 32281 | F91: =-(CF_Hist!F32+CF_Hist!F50) -> 28324 | G91: =-(CF_Hist!G32+CF_Hist!G50) -> 39225 | H91: =-(CF_Hist!H32+CF_Hist!H50) -> 72215 | I91: =CHOOSE($B$5,I88,I89,I90) -> 140000 | J91: =CHOOSE($B$5,J88,J89,J90) -> 199000 | K91: =CHOOSE($B$5,K88,K89,K90) -> 205000 | L91: =CHOOSE($B$5,L88,L89,L90) -> 200000 | M91: =CHOOSE($B$5,M88,M89,M90) -> 190000 | N91: =CHOOSE($B$5,N88,N89,N90) -> 185000 | O91: =CHOOSE($B$5,O88,O89,O90) -> 185000 | P91: =CHOOSE($B$5,P88,P89,P90) -> 190000 | ... R91: =CHOOSE($B$5,R88,R89,R90) -> 200000
A92: Reality Labs operating income (loss) (memo, USD m) | T92: Meta: 2026 loss USD 18-19 bn (10-Q); 2027 about USD 15 bn (Q3 2026 call). Memo for the sum of the parts; total costs come from the cash-cost ratio and D&A.
A93: Base | I93: =Interim_Bridge!$B$15+$J$15 -> -18500 | J93: -15000 | K93: -13500 | L93: -12000 | M93: -10500 | N93: -9000 | O93: -7500 | P93: -6000 | Q93: -5000 | R93: -4000
A94: Bull | I94: =Interim_Bridge!$B$15+$K$15 -> -18000 | J94: -14000 | K94: -11000 | L94: -8000 | M94: -5000 | N94: -3000 | O94: -1000 | P94: 0 | Q94: 1000 | R94: 2000
A95: Bear | I95: =Interim_Bridge!$B$15+$L$15 -> -19000 | J95: -16000 | K95: -16000 | L95: -15000 | M95: -15000 | N95: -14000 | O95: -14000 | P95: -13000 | Q95: -13000 | R95: -12000
A96: Active | H96: =Interim_Bridge!G15 -> -19193 | I96: =CHOOSE($B$5,I93,I94,I95) -> -18500 | J96: =CHOOSE($B$5,J93,J94,J95) -> -15000 | K96: =CHOOSE($B$5,K93,K94,K95) -> -13500 | L96: =CHOOSE($B$5,L93,L94,L95) -> -12000 | M96: =CHOOSE($B$5,M93,M94,M95) -> -10500 | N96: =CHOOSE($B$5,N93,N94,N95) -> -9000 | O96: =CHOOSE($B$5,O93,O94,O95) -> -7500 | P96: =CHOOSE($B$5,P93,P94,P95) -> -6000 | ... R96: =CHOOSE($B$5,R93,R94,R95) -> -4000
A97: Effective tax rate (2027E onward) | T97: Q3 2026 rate excluding the legal charge: 17% (press release); Q4 2026 guidance 15-17%. Analyst input.
A98: Base | J98: 0.17 | K98: 0.17 | L98: 0.17 | M98: 0.17 | N98: 0.17 | O98: 0.17 | P98: 0.17 | Q98: 0.17 | R98: 0.17
A99: Bull | J99: 0.15 | K99: 0.15 | L99: 0.15 | M99: 0.15 | N99: 0.15 | O99: 0.15 | P99: 0.15 | Q99: 0.15 | R99: 0.15
A100: Bear | J100: 0.2 | K100: 0.2 | L100: 0.2 | M100: 0.2 | N100: 0.2 | O100: 0.2 | P100: 0.2 | Q100: 0.2 | R100: 0.2
A101: Active | B101: =IS_Hist!B20/IS_Hist!B18 -> 0.25499758 | C101: =IS_Hist!C20/IS_Hist!C18 -> 0.12157926 | D101: =IS_Hist!D20/IS_Hist!D18 -> 0.16737163 | E101: =IS_Hist!E20/IS_Hist!E18 -> 0.19497554 | F101: =IS_Hist!F20/IS_Hist!F18 -> 0.17563465 | G101: =IS_Hist!G20/IS_Hist!G18 -> 0.11750138 | H101: =IS_Hist!H20/IS_Hist!H18 -> 0.2964437 | J101: =CHOOSE($B$5,J98,J99,J100) -> 0.17 | K101: =CHOOSE($B$5,K98,K99,K100) -> 0.17 | L101: =CHOOSE($B$5,L98,L99,L100) -> 0.17 | M101: =CHOOSE($B$5,M98,M99,M100) -> 0.17 | N101: =CHOOSE($B$5,N98,N99,N100) -> 0.17 | O101: =CHOOSE($B$5,O98,O99,O100) -> 0.17 | P101: =CHOOSE($B$5,P98,P99,P100) -> 0.17 | Q101: =CHOOSE($B$5,Q98,Q99,Q100) -> 0.17 | R101: =CHOOSE($B$5,R98,R99,R100) -> 0.17
A102: Dividend per share: growth | T102: 2026 quarterly dividend USD 0.525, flat on 2025 (10-Q). Analyst input.
A103: Base | I103: =$I$39/SCE_Hist!$H$56-1 -> 0 | J103: 0.05 | K103: 0.05 | L103: 0.05 | M103: 0.05 | N103: 0.05 | O103: 0.05 | P103: 0.05 | Q103: 0.05 | R103: 0.05
A104: Bull | I104: =$I$39/SCE_Hist!$H$56-1 -> 0 | J104: 0.08 | K104: 0.08 | L104: 0.08 | M104: 0.08 | N104: 0.08 | O104: 0.08 | P104: 0.08 | Q104: 0.08 | R104: 0.08
A105: Bear | I105: =$I$39/SCE_Hist!$H$56-1 -> 0 | J105: 0 | K105: 0 | L105: 0 | M105: 0 | N105: 0 | O105: 0 | P105: 0 | Q105: 0 | R105: 0
A106: Active | H106: =SCE_Hist!H56/SCE_Hist!G56-1 -> 0.05 | I106: =CHOOSE($B$5,I103,I104,I105) -> 0 | J106: =CHOOSE($B$5,J103,J104,J105) -> 0.05 | K106: =CHOOSE($B$5,K103,K104,K105) -> 0.05 | L106: =CHOOSE($B$5,L103,L104,L105) -> 0.05 | M106: =CHOOSE($B$5,M103,M104,M105) -> 0.05 | N106: =CHOOSE($B$5,N103,N104,N105) -> 0.05 | O106: =CHOOSE($B$5,O103,O104,O105) -> 0.05 | P106: =CHOOSE($B$5,P103,P104,P105) -> 0.05 | ... R106: =CHOOSE($B$5,R103,R104,R105) -> 0.05
A107: Buybacks: share of free cash flow after dividends and RSU tax payments | T107: Meta bought no shares in 9M 2026 (10-Q). Applied only when that free cash flow is positive. Analyst input.
A108: Base | J108: 0.75 | K108: 0.75 | L108: 0.75 | M108: 0.75 | N108: 0.75 | O108: 0.75 | P108: 0.75 | Q108: 0.75 | R108: 0.75
A109: Bull | J109: 0.9 | K109: 0.9 | L109: 0.9 | M109: 0.9 | N109: 0.9 | O109: 0.9 | P109: 0.9 | Q109: 0.9 | R109: 0.9
A110: Bear | J110: 0.5 | K110: 0.5 | L110: 0.5 | M110: 0.5 | N110: 0.5 | O110: 0.5 | P110: 0.5 | Q110: 0.5 | R110: 0.5
A111: Active | B111: =-CF_Hist!B47/(CF_Hist!B29+CF_Hist!B32+CF_Hist!B50+CF_Hist!B48+CF_Hist!B46) -> 0.22932926 | C111: =-CF_Hist!C47/(CF_Hist!C29+CF_Hist!C32+CF_Hist!C50+CF_Hist!C48+CF_Hist!C46) -> 0.32223592 | D111: =-CF_Hist!D47/(CF_Hist!D29+CF_Hist!D32+CF_Hist!D50+CF_Hist!D48+CF_Hist!D46) -> 1.3527214 | E111: =-CF_Hist!E47/(CF_Hist!E29+CF_Hist!E32+CF_Hist!E50+CF_Hist!E48+CF_Hist!E46) -> 1.9149257 | F111: =-CF_Hist!F47/(CF_Hist!F29+CF_Hist!F32+CF_Hist!F50+CF_Hist!F48+CF_Hist!F46) -> 0.55270146 | G111: =-CF_Hist!G47/(CF_Hist!G29+CF_Hist!G32+CF_Hist!G50+CF_Hist!G48+CF_Hist!G46) -> 0.9057154 | H111: =-CF_Hist!H47/(CF_Hist!H29+CF_Hist!H32+CF_Hist!H50+CF_Hist!H48+CF_Hist!H46) -> 1.321585 | J111: =CHOOSE($B$5,J108,J109,J110) -> 0.75 | K111: =CHOOSE($B$5,K108,K109,K110) -> 0.75 | L111: =CHOOSE($B$5,L108,L109,L110) -> 0.75 | M111: =CHOOSE($B$5,M108,M109,M110) -> 0.75 | N111: =CHOOSE($B$5,N108,N109,N110) -> 0.75 | O111: =CHOOSE($B$5,O108,O109,O110) -> 0.75 | P111: =CHOOSE($B$5,P108,P109,P110) -> 0.75 | Q111: =CHOOSE($B$5,Q108,Q109,Q110) -> 0.75 | R111: =CHOOSE($B$5,R108,R109,R110) -> 0.75

Sheet Interim_Bridge
A1: Meta Platforms, Inc. | 2026E bridge: nine months actual plus fourth quarter estimate
A2: 9M columns link to the 10-Q sheets; Q4 2026E comes from guidance and inputs on Assumptions. USD millions.
A4: Line | B4: 9M 2026A | C4: Q4 2026E | D4: FY2026E | E4: 9M 2025A | F4: Q4 2025A | G4: FY2025A | H4: Comentarios FG | I4: Source / derivation
A6: Revenue
A7: Advertising | B7: =Revenue_Hist!J7 -> 177449 | C7: =C10-C8-C9 -> 72265 | D7: =B7+C7 -> 249714 | E7: =Revenue_Hist!I7 -> 138037 | F7: =G7-E7 -> 58138 | G7: =Revenue_Hist!H7 -> 196175 | I7: Q4 2026E = Q4 revenue guidance less other revenue and Reality Labs.
A8: Other revenue | B8: =Revenue_Hist!J8 -> 2987 | C8: =F8*(1+Assumptions!$I$13) -> 1280 | D8: =B8+C8 -> 4267 | E8: =Revenue_Hist!I8 -> 1784 | F8: =G8-E8 -> 800 | G8: =Revenue_Hist!H8 -> 2584
A9: Reality Labs | B9: =Revenue_Hist!J10 -> 1276 | C9: =Assumptions!$I$14 -> 955 | D9: =B9+C9 -> 2231 | E9: =Revenue_Hist!I10 -> 1252 | F9: =G9-E9 -> 955 | G9: =Revenue_Hist!H10 -> 2207
A10: Total revenue | B10: =IS_Hist!J6 -> 181712 | C10: =Assumptions!$I$10 -> 74500 | D10: =B10+C10 -> 256212 | E10: =IS_Hist!I6 -> 141073 | F10: =G10-E10 -> 59893 | G10: =IS_Hist!H6 -> 200966 | I10: Q4 guidance USD 73-76 bn.
A12: Total costs and expenses | B12: =IS_Hist!J13 -> 127077 | C12: =Assumptions!$I$11-B12 -> 49923 | D12: =B12+C12 -> 177000 | E12: =IS_Hist!I13 -> 82542 | F12: =G12-E12 -> 35148 | G12: =IS_Hist!H13 -> 117690 | I12: Q4 2026E = FY2026 guidance (USD 175-179 bn) less 9M actual.
A13: of which legal charges outside the run-rate | B13: =Assumptions!$I$30 -> 11890 | C13: 0 | D13: =B13+C13 -> 11890 | E13: 0 | F13: =G13-E13 -> 0 | G13: 0 | I13: Attorneys general agreement, 10-Q.
A14: Income from operations | B14: =B10-B12 -> 54635 | C14: =C10-C12 -> 24577 | D14: =B14+C14 -> 79212 | E14: =E10-E12 -> 58531 | F14: =G14-E14 -> 24745 | G14: =G10-G12 -> 83276
A15: Reality Labs income (loss) from operations | B15: -12775 | C15: =Assumptions!$I$15 -> -5725 | D15: =B15+C15 -> -18500 | E15: -13171 | F15: =G15-E15 -> -6022 | G15: -19193 | I15: 10-Q and 10-K segment notes (XBRL OperatingIncomeLoss, RealityLabsMember).
A16: Family of Apps income from operations | B16: =B14-B15 -> 67410 | C16: =C14-C15 -> 30302 | D16: =B16+C16 -> 97712 | E16: =E14-E15 -> 71702 | F16: =G16-E16 -> 30767 | G16: =G14-G15 -> 102469
A17: Depreciation and amortization | B17: =CF_Hist!J10 -> 19509 | C17: =Assumptions!$I$24 -> 8200 | D17: =B17+C17 -> 27709 | E17: =CF_Hist!I10 -> 13205 | F17: =G17-E17 -> 5411 | G17: =CF_Hist!H10 -> 18616
A18: EBITDA (income from operations + D&A) | B18: =B14+B17 -> 74144 | C18: =C14+C17 -> 32777 | D18: =B18+C18 -> 106921 | E18: =E14+E17 -> 71736 | F18: =G18-E18 -> 30156 | G18: =G14+G17 -> 101892
A19: Interest and other income, net | B19: =IS_Hist!J17 -> -1126 | C19: =Assumptions!$I$22 -> -200 | D19: =B19+C19 -> -1326 | E19: =IS_Hist!I17 -> 2047 | F19: =G19-E19 -> 609 | G19: =IS_Hist!H17 -> 2656
A20: memo: interest expense on the notes | B20: 2170 | C20: =Assumptions!$I$23 -> 1000 | D20: =B20+C20 -> 3170 | E20: 668 | F20: =G20-E20 -> 422 | G20: 1090 | I20: 10-Q Note 9 and 10-K Note 9 (net of capitalized interest).
A21: Income before provision for income taxes | B21: =B14+B19 -> 53509 | C21: =C14+C19 -> 24377 | D21: =B21+C21 -> 77886 | E21: =E14+E19 -> 60578 | F21: =G21-E21 -> 25354 | G21: =G14+G19 -> 85932
A22: Provision for income taxes | B22: =IS_Hist!J20 -> 1028 | C22: =C21*Assumptions!$I$12 -> 3900.32 | D22: =B22+C22 -> 4928.32 | E22: =IS_Hist!I20 -> 22888 | F22: =G22-E22 -> 2586 | G22: =IS_Hist!H20 -> 25474 | I22: 9M 2026 includes an 8.03 bn CAMT tax benefit; 9M 2025 a 15.93 bn charge (10-Q).
A23: Net income | B23: =B21-B22 -> 52481 | C23: =C21-C22 -> 20476.68 | D23: =B23+C23 -> 72957.68 | E23: =E21-E22 -> 37690 | F23: =G23-E23 -> 22768 | G23: =G21-G22 -> 60458
A25: Cash flow items
A26: Net cash provided by operating activities (memo) | B26: =CF_Hist!J29 -> 96873 | E26: =CF_Hist!I29 -> 79586 | F26: =G26-E26 -> 36214 | G26: =CF_Hist!H29 -> 115800
A27: Share-based compensation | B27: =CF_Hist!J11 -> 21053 | C27: =Assumptions!$I$25 -> 7000 | D27: =B27+C27 -> 28053 | E27: =CF_Hist!I11 -> 14537 | F27: =G27-E27 -> 5890 | G27: =CF_Hist!H11 -> 20427
A28: Capital expenditures incl. finance-lease principal | B28: =-(CF_Hist!J32+CF_Hist!J50) -> 85824 | C28: =Assumptions!I91-B28 -> 54176 | D28: =B28+C28 -> 140000 | E28: =-(CF_Hist!I32+CF_Hist!I50) -> 50078 | F28: =G28-E28 -> 22137 | G28: =-(CF_Hist!H32+CF_Hist!H50) -> 72215 | I28: Meta's definition: purchases of property and equipment plus principal payments on finance leases. FY2026E = guidance (Assumptions).
A29: Dividends paid | B29: =-CF_Hist!J48 -> 4060 | C29: =Assumptions!$I$27 -> 1360 | D29: =B29+C29 -> 5420 | E29: =-CF_Hist!I48 -> 3986 | F29: =G29-E29 -> 1338 | G29: =-CF_Hist!H48 -> 5324
A30: Share buybacks | B30: =-CF_Hist!J47 -> 0 | C30: =Assumptions!$I$29 -> 0 | D30: =B30+C30 -> 0 | E30: =-CF_Hist!I47 -> 26248 | F30: =G30-E30 -> 0 | G30: =-CF_Hist!H47 -> 26248
A31: Taxes paid on RSU net share settlement | B31: =-CF_Hist!J46 -> 12768 | C31: =Assumptions!$I$26 -> 4250 | D31: =B31+C31 -> 17018 | E31: =-CF_Hist!I46 -> 14128 | F31: =G31-E31 -> 4272 | G31: =-CF_Hist!H46 -> 18400
A32: Proceeds from new long-term debt | B32: =CF_Hist!J49 -> 24910 | C32: =Assumptions!$I$28 -> 0 | D32: =B32+C32 -> 24910 | E32: =CF_Hist!I49 -> 0 | F32: =G32-E32 -> 29906 | G32: =CF_Hist!H49 -> 29906
A34: Revenue growth on the same period a year earlier | B34: =B10/E10-1 -> 0.28807072 | C34: =C10/F10-1 -> 0.24388493 | D34: =D10/G10-1 -> 0.27490222
A36: Checks (each should be zero)
A37: Segments add to total revenue | B37: =ROUND(B7+B8+B9-B10,2) -> 0 | C37: =ROUND(C7+C8+C9-C10,2) -> 0 | D37: =ROUND(D7+D8+D9-D10,2) -> 0 | E37: =ROUND(E7+E8+E9-E10,2) -> 0 | F37: =ROUND(F7+F8+F9-F10,2) -> 0 | G37: =ROUND(G7+G8+G9-G10,2) -> 0
A38: Income from operations ties to the income statement | B38: =ROUND(B14-IS_Hist!J15,2) -> 0 | E38: =ROUND(E14-IS_Hist!I15,2) -> 0 | G38: =ROUND(G14-IS_Hist!H15,2) -> 0
A39: Net income ties to the income statement | B39: =ROUND(B23-IS_Hist!J21,2) -> 0 | E39: =ROUND(E23-IS_Hist!I21,2) -> 0 | G39: =ROUND(G23-IS_Hist!H21,2) -> 0
A40: FY2026E costs equal the guidance input | D40: =ROUND(D12-Assumptions!$I$11,2) -> 0

Sheet Revenue_Build
A1: Meta Platforms, Inc. | Revenue build: ads shown x price per ad
A2: Advertising revenue grows with the number of ads shown and the average price per ad, the two numbers Meta reports each year.
B3: Actual | C3: Forecast
A4: Fiscal year ends 31 December | B4: 2025A | C4: 2026E | D4: 2027E | E4: 2028E | F4: 2029E | G4: 2030E | H4: 2031E | I4: 2032E | J4: 2033E | K4: 2034E | L4: 2035E | M4: Comentarios FG | N4: Source / derivation
A6: Advertising
A7: Ad impressions: growth | C7: =Assumptions!I56 -> 0.13 | D7: =Assumptions!J56 -> 0.1 | E7: =Assumptions!K56 -> 0.09 | F7: =Assumptions!L56 -> 0.08 | G7: =Assumptions!M56 -> 0.07 | H7: =Assumptions!N56 -> 0.06 | I7: =Assumptions!O56 -> 0.05 | J7: =Assumptions!P56 -> 0.04 | ... L7: =Assumptions!R56 -> 0.03
A8: Average price per ad: growth (2026E derived) | C8: =(1+C10)/(1+C7)-1 -> 0.126473 | D8: =Assumptions!J61+Assumptions!$I$44 -> 0.08 | E8: =Assumptions!K61+Assumptions!$I$44 -> 0.07 | F8: =Assumptions!L61+Assumptions!$I$44 -> 0.06 | G8: =Assumptions!M61+Assumptions!$I$44 -> 0.05 | H8: =Assumptions!N61+Assumptions!$I$44 -> 0.04 | I8: =Assumptions!O61+Assumptions!$I$44 -> 0.04 | J8: =Assumptions!P61+Assumptions!$I$44 -> 0.035 | K8: =Assumptions!Q61+Assumptions!$I$44 -> 0.03 | L8: =Assumptions!R61+Assumptions!$I$44 -> 0.025 | N8: 2026E: (1 + ad revenue growth) / (1 + impressions growth) - 1. Later years: Assumptions plus the sensitivity shift.
A9: Advertising revenue | B9: =Revenue_Hist!H7 -> 196175 | C9: =Interim_Bridge!D7 -> 249714 | D9: =C9*(1+D7)*(1+D8) -> 296660.23 | E9: =D9*(1+E7)*(1+E8) -> 345994.83 | F9: =E9*(1+F7)*(1+F8) -> 396094.88 | G9: =F9*(1+G7)*(1+G8) -> 445012.6 | H9: =G9*(1+H7)*(1+H8) -> 490581.89 | I9: =H9*(1+I7)*(1+I8) -> 535715.42 | J9: =I9*(1+J7)*(1+J8) -> 576644.08 | K9: =J9*(1+K7)*(1+K8) -> 614731.42 | L9: =K9*(1+L7)*(1+L8) -> 649002.7
A10: Advertising revenue: growth | C10: =C9/B9-1 -> 0.27291449 | D10: =D9/C9-1 -> 0.188 | E10: =E9/D9-1 -> 0.1663 | F10: =F9/E9-1 -> 0.1448 | G10: =G9/F9-1 -> 0.1235 | H10: =H9/G9-1 -> 0.1024 | I10: =I9/H9-1 -> 0.092 | J10: =J9/I9-1 -> 0.0764 | ... L10: =L9/K9-1 -> 0.05575
A12: Revenue by segment
A13: Advertising | B13: =B9 -> 196175 | C13: =C9 -> 249714 | D13: =D9 -> 296660.23 | E13: =E9 -> 345994.83 | F13: =F9 -> 396094.88 | G13: =G9 -> 445012.6 | H13: =H9 -> 490581.89 | I13: =I9 -> 535715.42 | ... L13: =L9 -> 649002.7
A14: Other revenue | B14: =Revenue_Hist!H8 -> 2584 | C14: =Interim_Bridge!D8 -> 4267 | D14: =C14*(1+Assumptions!J66) -> 5973.8 | E14: =D14*(1+Assumptions!K66) -> 7765.94 | F14: =E14*(1+Assumptions!L66) -> 9707.425 | G14: =F14*(1+Assumptions!M66) -> 11648.91 | H14: =G14*(1+Assumptions!N66) -> 13396.246 | I14: =H14*(1+Assumptions!O66) -> 15003.796 | J14: =I14*(1+Assumptions!P66) -> 16504.176 | K14: =J14*(1+Assumptions!Q66) -> 17824.51 | L14: =K14*(1+Assumptions!R66) -> 18893.98
A15: Family of Apps | B15: =B13+B14 -> 198759 | C15: =C13+C14 -> 253981 | D15: =D13+D14 -> 302634.03 | E15: =E13+E14 -> 353760.77 | F15: =F13+F14 -> 405802.3 | G15: =G13+G14 -> 456661.51 | H15: =H13+H14 -> 503978.13 | I15: =I13+I14 -> 550719.22 | ... L15: =L13+L14 -> 667896.68
A16: Reality Labs | B16: =Revenue_Hist!H10 -> 2207 | C16: =Interim_Bridge!D9 -> 2231 | D16: =C16*(1+Assumptions!J71) -> 2342.55 | E16: =D16*(1+Assumptions!K71) -> 2459.6775 | F16: =E16*(1+Assumptions!L71) -> 2582.6614 | G16: =F16*(1+Assumptions!M71) -> 2711.7944 | H16: =G16*(1+Assumptions!N71) -> 2847.3842 | I16: =H16*(1+Assumptions!O71) -> 2989.7534 | J16: =I16*(1+Assumptions!P71) -> 3139.241 | K16: =J16*(1+Assumptions!Q71) -> 3296.2031 | L16: =K16*(1+Assumptions!R71) -> 3461.0132
A17: Total revenue | B17: =B15+B16 -> 200966 | C17: =C15+C16 -> 256212 | D17: =D15+D16 -> 304976.58 | E17: =E15+E16 -> 356220.45 | F17: =F15+F16 -> 408384.97 | G17: =G15+G16 -> 459373.3 | H17: =H15+H16 -> 506825.52 | I17: =I15+I16 -> 553708.97 | ... L17: =L15+L16 -> 671357.69
A18: Total revenue: growth | C18: =C17/B17-1 -> 0.27490222 | D18: =D17/C17-1 -> 0.19032903 | E18: =E17/D17-1 -> 0.16802557 | F18: =F17/E17-1 -> 0.14643887 | G18: =G17/F17-1 -> 0.12485361 | H18: =H17/G17-1 -> 0.10329772 | I18: =I17/H17-1 -> 0.092504128 | J18: =J17/I17-1 -> 0.07689694 | ... L18: =L17/K17-1 -> 0.055839331
A19: Advertising: share of revenue | B19: =B9/B17 -> 0.97616015 | C19: =C9/C17 -> 0.97463819 | D19: =D9/D17 -> 0.97273118 | E19: =E9/E17 -> 0.97129413 | F19: =F9/F17 -> 0.96990563 | G19: =G9/G17 -> 0.96873849 | H19: =H9/H17 -> 0.96795025 | I19: =I9/I17 -> 0.9675036 | ... L19: =L9/L17 -> 0.96670181
A21: People (memo; does not drive revenue)
A22: Daily active people, year-end (billions) | B22: =Revenue_Hist!H29 -> 3.58 | C22: =Revenue_Hist!J29 -> 3.64 | D22: =C22*(1+Assumptions!J76) -> 3.731 | E22: =D22*(1+Assumptions!K76) -> 3.80562 | F22: =E22*(1+Assumptions!L76) -> 3.8817324 | G22: =F22*(1+Assumptions!M76) -> 3.9399584 | H22: =G22*(1+Assumptions!N76) -> 3.9990578 | I22: =H22*(1+Assumptions!O76) -> 4.0390483 | J22: =I22*(1+Assumptions!P76) -> 4.0794388 | K22: =J22*(1+Assumptions!Q76) -> 4.1202332 | L22: =K22*(1+Assumptions!R76) -> 4.1614355 | N22: 2025A: December 2025 average; 2026E: September 2026 average (latest).
A23: Family of Apps revenue per daily active person (USD) | B23: =B15/(B22*1000) -> 55.519274 | C23: =C15/(C22*1000) -> 69.775 | D23: =D15/(D22*1000) -> 81.113383 | E23: =E15/(E22*1000) -> 92.95746 | F23: =F15/(F22*1000) -> 104.54155 | G23: =G15/(G22*1000) -> 115.90516 | H23: =H15/(H22*1000) -> 126.02422 | I23: =I15/(I22*1000) -> 136.34876 | ... L23: =L15/(L22*1000) -> 160.4967
A24: Ads shown per person: index, 2025A = 1.00 | B24: 1 | C24: =B24*(1+C7)/(C22/B22) -> 1.1113736 | D24: =C24*(1+D7)/(D22/C22) -> 1.1926936 | E24: =D24*(1+E7)/(E22/D22) -> 1.2745452 | F24: =E24*(1+F7)/(F22/E22) -> 1.3495184 | G24: =F24*(1+G7)/(G22/F22) -> 1.422645 | H24: =G24*(1+H7)/(H22/G22) -> 1.485718 | I24: =H24*(1+I7)/(I22/H22) -> 1.5445583 | J24: =I24*(1+J7)/(J22/I22) -> 1.5904362 | ... L24: =K24*(1+L7)/(L22/K22) -> 1.6620768
A26: Checks (each should be zero)
A27: 2025A total revenue equals the income statement | B27: =ROUND(B17-IS_Hist!H6,2) -> 0
A28: 2026E total revenue equals the bridge | C28: =ROUND(C17-Interim_Bridge!D10,2) -> 0

Sheet Schedules
A1: Meta Platforms, Inc. | Schedules: capex and depreciation, working capital, debt, cash, equity and shares
A2: USD millions; shares in millions; per-share in USD. Interest uses beginning balances, so the model has no circular reference.
B3: Actual | C3: Forecast
A4: Fiscal year ends 31 December | B4: 2025A | C4: 2026E | D4: 2027E | E4: 2028E | F4: 2029E | G4: 2030E | H4: 2031E | I4: 2032E | J4: 2033E | K4: 2034E | L4: 2035E | M4: Comentarios FG | N4: Source / derivation
A6: Property and equipment
A7: Capital expenditures incl. finance-lease principal | B7: =-(CF_Hist!H32+CF_Hist!H50) -> 72215 | C7: =Interim_Bridge!D28 -> 140000 | D7: =Assumptions!J91*(1+Assumptions!$I$45) -> 199000 | E7: =Assumptions!K91*(1+Assumptions!$I$45) -> 205000 | F7: =Assumptions!L91*(1+Assumptions!$I$45) -> 200000 | G7: =Assumptions!M91*(1+Assumptions!$I$45) -> 190000 | H7: =Assumptions!N91*(1+Assumptions!$I$45) -> 185000 | I7: =Assumptions!O91*(1+Assumptions!$I$45) -> 185000 | J7: =Assumptions!P91*(1+Assumptions!$I$45) -> 190000 | K7: =Assumptions!Q91*(1+Assumptions!$I$45) -> 195000 | L7: =Assumptions!R91*(1+Assumptions!$I$45) -> 200000
A8: Capex: % of revenue | B8: =B7/Revenue_Build!B17 -> 0.35933939 | C8: =C7/Revenue_Build!C17 -> 0.54642249 | D8: =D7/Revenue_Build!D17 -> 0.65250912 | E8: =E7/Revenue_Build!E17 -> 0.57548634 | F8: =F7/Revenue_Build!F17 -> 0.48973399 | G8: =G7/Revenue_Build!G17 -> 0.41360697 | H8: =H7/Revenue_Build!H17 -> 0.36501714 | I8: =I7/Revenue_Build!I17 -> 0.33411053 | ... L8: =L7/Revenue_Build!L17 -> 0.29790379
A9: Depreciation and amortization | B9: =CF_Hist!H10 -> 18616 | C9: =Interim_Bridge!D17 -> 27709 | D9: =D34 -> 43679.382 | E9: =E34 -> 62498.382 | F9: =F34 -> 82372.564 | G9: =G34 -> 100583.93 | H9: =H34 -> 114964.38 | I9: =I34 -> 122805.29 | J9: =J34 -> 125459.84 | K9: =K34 -> 128073.47 | L9: =L34 -> 131696.2 | N9: 2026E: 9M actual + Q4 estimate. 2027E onward: the vintage table below.
A10: D&A: % of revenue | B10: =B9/Revenue_Build!B17 -> 0.092632585 | C10: =C9/Revenue_Build!C17 -> 0.10814872 | D10: =D9/Revenue_Build!D17 -> 0.14322208 | E10: =E9/Revenue_Build!E17 -> 0.17544861 | F10: =F9/Revenue_Build!F17 -> 0.20170322 | G10: =G9/Revenue_Build!G17 -> 0.21895902 | H10: =H9/Revenue_Build!H17 -> 0.22683227 | I10: =I9/Revenue_Build!I17 -> 0.22178671 | ... L10: =L9/Revenue_Build!L17 -> 0.19616398
A11: Property and equipment, net: beginning | C11: =B12 -> 176400 | D11: =C12 -> 288691 | E11: =D12 -> 444011.62 | F11: =E12 -> 586513.24 | G11: =F12 -> 704140.67 | H11: =G12 -> 793556.75 | I11: =H12 -> 863592.36 | J11: =I12 -> 925787.07 | ... L11: =K12 -> 1057253.8
A12: Property and equipment, net: ending | B12: =BS_Hist!H16 -> 176400 | C12: =C11+C7-C9 -> 288691 | D12: =D11+D7-D9 -> 444011.62 | E12: =E11+E7-E9 -> 586513.24 | F12: =F11+F7-F9 -> 704140.67 | G12: =G11+G7-G9 -> 793556.75 | H12: =H11+H7-H9 -> 863592.36 | I12: =I11+I7-I9 -> 925787.07 | J12: =J11+J7-J9 -> 990327.24 | ... L12: =L11+L7-L9 -> 1125557.6
A14: Depreciation by capex vintage | N14: Servers (share in Assumptions) over their life with a half year in year one; the rest after the construction lag over the building life. Calibrated to D&A 2019A-2025A.
A15: Capex of 2017 | B15: 6733 | C15: =B15*(Assumptions!$I$40*IF(9<Assumptions!$I$41+0.5,MIN(1,Assumptions!$I$41+0.5-9)/Assumptions!$I$41,0)+(1-Assumptions!$I$40)*IF(9-Assumptions!$I$43<0,0,IF(9-Assumptions!$I$43=0,0.5/Assumptions!$I$42,IF(9-Assumptions!$I$43<Assumptions!$I$42+0.5,MIN(1,Assumptions!$I$42+0.5-(9-Assumptions!$I$43))/Assumptions!$I$42,0)))) -> 134.66 | D15: =B15*(Assumptions!$I$40*IF(10<Assumptions!$I$41+0.5,MIN(1,Assumptions!$I$41+0.5-10)/Assumptions!$I$41,0)+(1-Assumptions!$I$40)*IF(10-Assumptions!$I$43<0,0,IF(10-Assumptions!$I$43=0,0.5/Assumptions!$I$42,IF(10-Assumptions!$I$43<Assumptions!$I$42+0.5,MIN(1,Assumptions!$I$42+0.5-(10-Assumptions!$I$43))/Assumptions!$I$42,0)))) -> 134.66 | E15: =B15*(Assumptions!$I$40*IF(11<Assumptions!$I$41+0.5,MIN(1,Assumptions!$I$41+0.5-11)/Assumptions!$I$41,0)+(1-Assumptions!$I$40)*IF(11-Assumptions!$I$43<0,0,IF(11-Assumptions!$I$43=0,0.5/Assumptions!$I$42,IF(11-Assumptions!$I$43<Assumptions!$I$42+0.5,MIN(1,Assumptions!$I$42+0.5-(11-Assumptions!$I$43))/Assumptions!$I$42,0)))) -> 134.66 | F15: =B15*(Assumptions!$I$40*IF(12<Assumptions!$I$41+0.5,MIN(1,Assumptions!$I$41+0.5-12)/Assumptions!$I$41,0)+(1-Assumptions!$I$40)*IF(12-Assumptions!$I$43<0,0,IF(12-Assumptions!$I$43=0,0.5/Assumptions!$I$42,IF(12-Assumptions!$I$43<Assumptions!$I$42+0.5,MIN(1,Assumptions!$I$42+0.5-(12-Assumptions!$I$43))/Assumptions!$I$42,0)))) -> 134.66 | G15: =B15*(Assumptions!$I$40*IF(13<Assumptions!$I$41+0.5,MIN(1,Assumptions!$I$41+0.5-13)/Assumptions!$I$41,0)+(1-Assumptions!$I$40)*IF(13-Assumptions!$I$43<0,0,IF(13-Assumptions!$I$43=0,0.5/Assumptions!$I$42,IF(13-Assumptions!$I$43<Assumptions!$I$42+0.5,MIN(1,Assumptions!$I$42+0.5-(13-Assumptions!$I$43))/Assumptions!$I$42,0)))) -> 134.66 | H15: =B15*(Assumptions!$I$40*IF(14<Assumptions!$I$41+0.5,MIN(1,Assumptions!$I$41+0.5-14)/Assumptions!$I$41,0)+(1-Assumptions!$I$40)*IF(14-Assumptions!$I$43<0,0,IF(14-Assumptions!$I$43=0,0.5/Assumptions!$I$42,IF(14-Assumptions!$I$43<Assumptions!$I$42+0.5,MIN(1,Assumptions!$I$42+0.5-(14-Assumptions!$I$43))/Assumptions!$I$42,0)))) -> 134.66 | I15: =B15*(Assumptions!$I$40*IF(15<Assumptions!$I$41+0.5,MIN(1,Assumptions!$I$41+0.5-15)/Assumptions!$I$41,0)+(1-Assumptions!$I$40)*IF(15-Assumptions!$I$43<0,0,IF(15-Assumptions!$I$43=0,0.5/Assumptions!$I$42,IF(15-Assumptions!$I$43<Assumptions!$I$42+0.5,MIN(1,Assumptions!$I$42+0.5-(15-Assumptions!$I$43))/Assumptions!$I$42,0)))) -> 134.66 | J15: =B15*(Assumptions!$I$40*IF(16<Assumptions!$I$41+0.5,MIN(1,Assumptions!$I$41+0.5-16)/Assumptions!$I$41,0)+(1-Assumptions!$I$40)*IF(16-Assumptions!$I$43<0,0,IF(16-Assumptions!$I$43=0,0.5/Assumptions!$I$42,IF(16-Assumptions!$I$43<Assumptions!$I$42+0.5,MIN(1,Assumptions!$I$42+0.5-(16-Assumptions!$I$43))/Assumptions!$I$42,0)))) -> 134.66 | K15: =B15*(Assumptions!$I$40*IF(17<Assumptions!$I$41+0.5,MIN(1,Assumptions!$I$41+0.5-17)/Assumptions!$I$41,0)+(1-Assumptions!$I$40)*IF(17-Assumptions!$I$43<0,0,IF(17-Assumptions!$I$43=0,0.5/Assumptions!$I$42,IF(17-Assumptions!$I$43<Assumptions!$I$42+0.5,MIN(1,Assumptions!$I$42+0.5-(17-Assumptions!$I$43))/Assumptions!$I$42,0)))) -> 134.66 | L15: =B15*(Assumptions!$I$40*IF(18<Assumptions!$I$41+0.5,MIN(1,Assumptions!$I$41+0.5-18)/Assumptions!$I$41,0)+(1-Assumptions!$I$40)*IF(18-Assumptions!$I$43<0,0,IF(18-Assumptions!$I$43=0,0.5/Assumptions!$I$42,IF(18-Assumptions!$I$43<Assumptions!$I$42+0.5,MIN(1,Assumptions!$I$42+0.5-(18-Assumptions!$I$43))/Assumptions!$I$42,0)))) -> 134.66 | N15: 10-K FY2019 comparative (finance-lease principal not available)
A16: Capex of 2018 | B16: 13915 | C16: =B16*(Assumptions!$I$40*IF(8<Assumptions!$I$41+0.5,MIN(1,Assumptions!$I$41+0.5-8)/Assumptions!$I$41,0)+(1-Assumptions!$I$40)*IF(8-Assumptions!$I$43<0,0,IF(8-Assumptions!$I$43=0,0.5/Assumptions!$I$42,IF(8-Assumptions!$I$43<Assumptions!$I$42+0.5,MIN(1,Assumptions!$I$42+0.5-(8-Assumptions!$I$43))/Assumptions!$I$42,0)))) -> 278.3 | D16: =B16*(Assumptions!$I$40*IF(9<Assumptions!$I$41+0.5,MIN(1,Assumptions!$I$41+0.5-9)/Assumptions!$I$41,0)+(1-Assumptions!$I$40)*IF(9-Assumptions!$I$43<0,0,IF(9-Assumptions!$I$43=0,0.5/Assumptions!$I$42,IF(9-Assumptions!$I$43<Assumptions!$I$42+0.5,MIN(1,Assumptions!$I$42+0.5-(9-Assumptions!$I$43))/Assumptions!$I$42,0)))) -> 278.3 | E16: =B16*(Assumptions!$I$40*IF(10<Assumptions!$I$41+0.5,MIN(1,Assumptions!$I$41+0.5-10)/Assumptions!$I$41,0)+(1-Assumptions!$I$40)*IF(10-Assumptions!$I$43<0,0,IF(10-Assumptions!$I$43=0,0.5/Assumptions!$I$42,IF(10-Assumptions!$I$43<Assumptions!$I$42+0.5,MIN(1,Assumptions!$I$42+0.5-(10-Assumptions!$I$43))/Assumptions!$I$42,0)))) -> 278.3 | F16: =B16*(Assumptions!$I$40*IF(11<Assumptions!$I$41+0.5,MIN(1,Assumptions!$I$41+0.5-11)/Assumptions!$I$41,0)+(1-Assumptions!$I$40)*IF(11-Assumptions!$I$43<0,0,IF(11-Assumptions!$I$43=0,0.5/Assumptions!$I$42,IF(11-Assumptions!$I$43<Assumptions!$I$42+0.5,MIN(1,Assumptions!$I$42+0.5-(11-Assumptions!$I$43))/Assumptions!$I$42,0)))) -> 278.3 | G16: =B16*(Assumptions!$I$40*IF(12<Assumptions!$I$41+0.5,MIN(1,Assumptions!$I$41+0.5-12)/Assumptions!$I$41,0)+(1-Assumptions!$I$40)*IF(12-Assumptions!$I$43<0,0,IF(12-Assumptions!$I$43=0,0.5/Assumptions!$I$42,IF(12-Assumptions!$I$43<Assumptions!$I$42+0.5,MIN(1,Assumptions!$I$42+0.5-(12-Assumptions!$I$43))/Assumptions!$I$42,0)))) -> 278.3 | H16: =B16*(Assumptions!$I$40*IF(13<Assumptions!$I$41+0.5,MIN(1,Assumptions!$I$41+0.5-13)/Assumptions!$I$41,0)+(1-Assumptions!$I$40)*IF(13-Assumptions!$I$43<0,0,IF(13-Assumptions!$I$43=0,0.5/Assumptions!$I$42,IF(13-Assumptions!$I$43<Assumptions!$I$42+0.5,MIN(1,Assumptions!$I$42+0.5-(13-Assumptions!$I$43))/Assumptions!$I$42,0)))) -> 278.3 | I16: =B16*(Assumptions!$I$40*IF(14<Assumptions!$I$41+0.5,MIN(1,Assumptions!$I$41+0.5-14)/Assumptions!$I$41,0)+(1-Assumptions!$I$40)*IF(14-Assumptions!$I$43<0,0,IF(14-Assumptions!$I$43=0,0.5/Assumptions!$I$42,IF(14-Assumptions!$I$43<Assumptions!$I$42+0.5,MIN(1,Assumptions!$I$42+0.5-(14-Assumptions!$I$43))/Assumptions!$I$42,0)))) -> 278.3 | J16: =B16*(Assumptions!$I$40*IF(15<Assumptions!$I$41+0.5,MIN(1,Assumptions!$I$41+0.5-15)/Assumptions!$I$41,0)+(1-Assumptions!$I$40)*IF(15-Assumptions!$I$43<0,0,IF(15-Assumptions!$I$43=0,0.5/Assumptions!$I$42,IF(15-Assumptions!$I$43<Assumptions!$I$42+0.5,MIN(1,Assumptions!$I$42+0.5-(15-Assumptions!$I$43))/Assumptions!$I$42,0)))) -> 278.3 | K16: =B16*(Assumptions!$I$40*IF(16<Assumptions!$I$41+0.5,MIN(1,Assumptions!$I$41+0.5-16)/Assumptions!$I$41,0)+(1-Assumptions!$I$40)*IF(16-Assumptions!$I$43<0,0,IF(16-Assumptions!$I$43=0,0.5/Assumptions!$I$42,IF(16-Assumptions!$I$43<Assumptions!$I$42+0.5,MIN(1,Assumptions!$I$42+0.5-(16-Assumptions!$I$43))/Assumptions!$I$42,0)))) -> 278.3 | L16: =B16*(Assumptions!$I$40*IF(17<Assumptions!$I$41+0.5,MIN(1,Assumptions!$I$41+0.5-17)/Assumptions!$I$41,0)+(1-Assumptions!$I$40)*IF(17-Assumptions!$I$43<0,0,IF(17-Assumptions!$I$43=0,0.5/Assumptions!$I$42,IF(17-Assumptions!$I$43<Assumptions!$I$42+0.5,MIN(1,Assumptions!$I$42+0.5-(17-Assumptions!$I$43))/Assumptions!$I$42,0)))) -> 278.3 | N16: 10-K FY2019 comparative (finance-lease principal not available)
A17: Capex of 2019 | B17: =-(CF_Hist!B32+CF_Hist!B50) -> 15654 | C17: =B17*(Assumptions!$I$40*IF(7<Assumptions!$I$41+0.5,MIN(1,Assumptions!$I$41+0.5-7)/Assumptions!$I$41,0)+(1-Assumptions!$I$40)*IF(7-Assumptions!$I$43<0,0,IF(7-Assumptions!$I$43=0,0.5/Assumptions!$I$42,IF(7-Assumptions!$I$43<Assumptions!$I$42+0.5,MIN(1,Assumptions!$I$42+0.5-(7-Assumptions!$I$43))/Assumptions!$I$42,0)))) -> 313.08 | D17: =B17*(Assumptions!$I$40*IF(8<Assumptions!$I$41+0.5,MIN(1,Assumptions!$I$41+0.5-8)/Assumptions!$I$41,0)+(1-Assumptions!$I$40)*IF(8-Assumptions!$I$43<0,0,IF(8-Assumptions!$I$43=0,0.5/Assumptions!$I$42,IF(8-Assumptions!$I$43<Assumptions!$I$42+0.5,MIN(1,Assumptions!$I$42+0.5-(8-Assumptions!$I$43))/Assumptions!$I$42,0)))) -> 313.08 | E17: =B17*(Assumptions!$I$40*IF(9<Assumptions!$I$41+0.5,MIN(1,Assumptions!$I$41+0.5-9)/Assumptions!$I$41,0)+(1-Assumptions!$I$40)*IF(9-Assumptions!$I$43<0,0,IF(9-Assumptions!$I$43=0,0.5/Assumptions!$I$42,IF(9-Assumptions!$I$43<Assumptions!$I$42+0.5,MIN(1,Assumptions!$I$42+0.5-(9-Assumptions!$I$43))/Assumptions!$I$42,0)))) -> 313.08 | F17: =B17*(Assumptions!$I$40*IF(10<Assumptions!$I$41+0.5,MIN(1,Assumptions!$I$41+0.5-10)/Assumptions!$I$41,0)+(1-Assumptions!$I$40)*IF(10-Assumptions!$I$43<0,0,IF(10-Assumptions!$I$43=0,0.5/Assumptions!$I$42,IF(10-Assumptions!$I$43<Assumptions!$I$42+0.5,MIN(1,Assumptions!$I$42+0.5-(10-Assumptions!$I$43))/Assumptions!$I$42,0)))) -> 313.08 | G17: =B17*(Assumptions!$I$40*IF(11<Assumptions!$I$41+0.5,MIN(1,Assumptions!$I$41+0.5-11)/Assumptions!$I$41,0)+(1-Assumptions!$I$40)*IF(11-Assumptions!$I$43<0,0,IF(11-Assumptions!$I$43=0,0.5/Assumptions!$I$42,IF(11-Assumptions!$I$43<Assumptions!$I$42+0.5,MIN(1,Assumptions!$I$42+0.5-(11-Assumptions!$I$43))/Assumptions!$I$42,0)))) -> 313.08 | H17: =B17*(Assumptions!$I$40*IF(12<Assumptions!$I$41+0.5,MIN(1,Assumptions!$I$41+0.5-12)/Assumptions!$I$41,0)+(1-Assumptions!$I$40)*IF(12-Assumptions!$I$43<0,0,IF(12-Assumptions!$I$43=0,0.5/Assumptions!$I$42,IF(12-Assumptions!$I$43<Assumptions!$I$42+0.5,MIN(1,Assumptions!$I$42+0.5-(12-Assumptions!$I$43))/Assumptions!$I$42,0)))) -> 313.08 | I17: =B17*(Assumptions!$I$40*IF(13<Assumptions!$I$41+0.5,MIN(1,Assumptions!$I$41+0.5-13)/Assumptions!$I$41,0)+(1-Assumptions!$I$40)*IF(13-Assumptions!$I$43<0,0,IF(13-Assumptions!$I$43=0,0.5/Assumptions!$I$42,IF(13-Assumptions!$I$43<Assumptions!$I$42+0.5,MIN(1,Assumptions!$I$42+0.5-(13-Assumptions!$I$43))/Assumptions!$I$42,0)))) -> 313.08 | J17: =B17*(Assumptions!$I$40*IF(14<Assumptions!$I$41+0.5,MIN(1,Assumptions!$I$41+0.5-14)/Assumptions!$I$41,0)+(1-Assumptions!$I$40)*IF(14-Assumptions!$I$43<0,0,IF(14-Assumptions!$I$43=0,0.5/Assumptions!$I$42,IF(14-Assumptions!$I$43<Assumptions!$I$42+0.5,MIN(1,Assumptions!$I$42+0.5-(14-Assumptions!$I$43))/Assumptions!$I$42,0)))) -> 313.08 | K17: =B17*(Assumptions!$I$40*IF(15<Assumptions!$I$41+0.5,MIN(1,Assumptions!$I$41+0.5-15)/Assumptions!$I$41,0)+(1-Assumptions!$I$40)*IF(15-Assumptions!$I$43<0,0,IF(15-Assumptions!$I$43=0,0.5/Assumptions!$I$42,IF(15-Assumptions!$I$43<Assumptions!$I$42+0.5,MIN(1,Assumptions!$I$42+0.5-(15-Assumptions!$I$43))/Assumptions!$I$42,0)))) -> 313.08 | L17: =B17*(Assumptions!$I$40*IF(16<Assumptions!$I$41+0.5,MIN(1,Assumptions!$I$41+0.5-16)/Assumptions!$I$41,0)+(1-Assumptions!$I$40)*IF(16-Assumptions!$I$43<0,0,IF(16-Assumptions!$I$43=0,0.5/Assumptions!$I$42,IF(16-Assumptions!$I$43<Assumptions!$I$42+0.5,MIN(1,Assumptions!$I$42+0.5-(16-Assumptions!$I$43))/Assumptions!$I$42,0)))) -> 313.08
A18: Capex of 2020 | B18: =-(CF_Hist!C32+CF_Hist!C50) -> 15719 | C18: =B18*(Assumptions!$I$40*IF(6<Assumptions!$I$41+0.5,MIN(1,Assumptions!$I$41+0.5-6)/Assumptions!$I$41,0)+(1-Assumptions!$I$40)*IF(6-Assumptions!$I$43<0,0,IF(6-Assumptions!$I$43=0,0.5/Assumptions!$I$42,IF(6-Assumptions!$I$43<Assumptions!$I$42+0.5,MIN(1,Assumptions!$I$42+0.5-(6-Assumptions!$I$43))/Assumptions!$I$42,0)))) -> 314.38 | D18: =B18*(Assumptions!$I$40*IF(7<Assumptions!$I$41+0.5,MIN(1,Assumptions!$I$41+0.5-7)/Assumptions!$I$41,0)+(1-Assumptions!$I$40)*IF(7-Assumptions!$I$43<0,0,IF(7-Assumptions!$I$43=0,0.5/Assumptions!$I$42,IF(7-Assumptions!$I$43<Assumptions!$I$42+0.5,MIN(1,Assumptions!$I$42+0.5-(7-Assumptions!$I$43))/Assumptions!$I$42,0)))) -> 314.38 | E18: =B18*(Assumptions!$I$40*IF(8<Assumptions!$I$41+0.5,MIN(1,Assumptions!$I$41+0.5-8)/Assumptions!$I$41,0)+(1-Assumptions!$I$40)*IF(8-Assumptions!$I$43<0,0,IF(8-Assumptions!$I$43=0,0.5/Assumptions!$I$42,IF(8-Assumptions!$I$43<Assumptions!$I$42+0.5,MIN(1,Assumptions!$I$42+0.5-(8-Assumptions!$I$43))/Assumptions!$I$42,0)))) -> 314.38 | F18: =B18*(Assumptions!$I$40*IF(9<Assumptions!$I$41+0.5,MIN(1,Assumptions!$I$41+0.5-9)/Assumptions!$I$41,0)+(1-Assumptions!$I$40)*IF(9-Assumptions!$I$43<0,0,IF(9-Assumptions!$I$43=0,0.5/Assumptions!$I$42,IF(9-Assumptions!$I$43<Assumptions!$I$42+0.5,MIN(1,Assumptions!$I$42+0.5-(9-Assumptions!$I$43))/Assumptions!$I$42,0)))) -> 314.38 | G18: =B18*(Assumptions!$I$40*IF(10<Assumptions!$I$41+0.5,MIN(1,Assumptions!$I$41+0.5-10)/Assumptions!$I$41,0)+(1-Assumptions!$I$40)*IF(10-Assumptions!$I$43<0,0,IF(10-Assumptions!$I$43=0,0.5/Assumptions!$I$42,IF(10-Assumptions!$I$43<Assumptions!$I$42+0.5,MIN(1,Assumptions!$I$42+0.5-(10-Assumptions!$I$43))/Assumptions!$I$42,0)))) -> 314.38 | H18: =B18*(Assumptions!$I$40*IF(11<Assumptions!$I$41+0.5,MIN(1,Assumptions!$I$41+0.5-11)/Assumptions!$I$41,0)+(1-Assumptions!$I$40)*IF(11-Assumptions!$I$43<0,0,IF(11-Assumptions!$I$43=0,0.5/Assumptions!$I$42,IF(11-Assumptions!$I$43<Assumptions!$I$42+0.5,MIN(1,Assumptions!$I$42+0.5-(11-Assumptions!$I$43))/Assumptions!$I$42,0)))) -> 314.38 | I18: =B18*(Assumptions!$I$40*IF(12<Assumptions!$I$41+0.5,MIN(1,Assumptions!$I$41+0.5-12)/Assumptions!$I$41,0)+(1-Assumptions!$I$40)*IF(12-Assumptions!$I$43<0,0,IF(12-Assumptions!$I$43=0,0.5/Assumptions!$I$42,IF(12-Assumptions!$I$43<Assumptions!$I$42+0.5,MIN(1,Assumptions!$I$42+0.5-(12-Assumptions!$I$43))/Assumptions!$I$42,0)))) -> 314.38 | J18: =B18*(Assumptions!$I$40*IF(13<Assumptions!$I$41+0.5,MIN(1,Assumptions!$I$41+0.5-13)/Assumptions!$I$41,0)+(1-Assumptions!$I$40)*IF(13-Assumptions!$I$43<0,0,IF(13-Assumptions!$I$43=0,0.5/Assumptions!$I$42,IF(13-Assumptions!$I$43<Assumptions!$I$42+0.5,MIN(1,Assumptions!$I$42+0.5-(13-Assumptions!$I$43))/Assumptions!$I$42,0)))) -> 314.38 | K18: =B18*(Assumptions!$I$40*IF(14<Assumptions!$I$41+0.5,MIN(1,Assumptions!$I$41+0.5-14)/Assumptions!$I$41,0)+(1-Assumptions!$I$40)*IF(14-Assumptions!$I$43<0,0,IF(14-Assumptions!$I$43=0,0.5/Assumptions!$I$42,IF(14-Assumptions!$I$43<Assumptions!$I$42+0.5,MIN(1,Assumptions!$I$42+0.5-(14-Assumptions!$I$43))/Assumptions!$I$42,0)))) -> 314.38 | L18: =B18*(Assumptions!$I$40*IF(15<Assumptions!$I$41+0.5,MIN(1,Assumptions!$I$41+0.5-15)/Assumptions!$I$41,0)+(1-Assumptions!$I$40)*IF(15-Assumptions!$I$43<0,0,IF(15-Assumptions!$I$43=0,0.5/Assumptions!$I$42,IF(15-Assumptions!$I$43<Assumptions!$I$42+0.5,MIN(1,Assumptions!$I$42+0.5-(15-Assumptions!$I$43))/Assumptions!$I$42,0)))) -> 314.38
A19: Capex of 2021 | B19: =-(CF_Hist!D32+CF_Hist!D50) -> 19244 | C19: =B19*(Assumptions!$I$40*IF(5<Assumptions!$I$41+0.5,MIN(1,Assumptions!$I$41+0.5-5)/Assumptions!$I$41,0)+(1-Assumptions!$I$40)*IF(5-Assumptions!$I$43<0,0,IF(5-Assumptions!$I$43=0,0.5/Assumptions!$I$42,IF(5-Assumptions!$I$43<Assumptions!$I$42+0.5,MIN(1,Assumptions!$I$42+0.5-(5-Assumptions!$I$43))/Assumptions!$I$42,0)))) -> 2134.3345 | D19: =B19*(Assumptions!$I$40*IF(6<Assumptions!$I$41+0.5,MIN(1,Assumptions!$I$41+0.5-6)/Assumptions!$I$41,0)+(1-Assumptions!$I$40)*IF(6-Assumptions!$I$43<0,0,IF(6-Assumptions!$I$43=0,0.5/Assumptions!$I$42,IF(6-Assumptions!$I$43<Assumptions!$I$42+0.5,MIN(1,Assumptions!$I$42+0.5-(6-Assumptions!$I$43))/Assumptions!$I$42,0)))) -> 384.88 | E19: =B19*(Assumptions!$I$40*IF(7<Assumptions!$I$41+0.5,MIN(1,Assumptions!$I$41+0.5-7)/Assumptions!$I$41,0)+(1-Assumptions!$I$40)*IF(7-Assumptions!$I$43<0,0,IF(7-Assumptions!$I$43=0,0.5/Assumptions!$I$42,IF(7-Assumptions!$I$43<Assumptions!$I$42+0.5,MIN(1,Assumptions!$I$42+0.5-(7-Assumptions!$I$43))/Assumptions!$I$42,0)))) -> 384.88 | F19: =B19*(Assumptions!$I$40*IF(8<Assumptions!$I$41+0.5,MIN(1,Assumptions!$I$41+0.5-8)/Assumptions!$I$41,0)+(1-Assumptions!$I$40)*IF(8-Assumptions!$I$43<0,0,IF(8-Assumptions!$I$43=0,0.5/Assumptions!$I$42,IF(8-Assumptions!$I$43<Assumptions!$I$42+0.5,MIN(1,Assumptions!$I$42+0.5-(8-Assumptions!$I$43))/Assumptions!$I$42,0)))) -> 384.88 | G19: =B19*(Assumptions!$I$40*IF(9<Assumptions!$I$41+0.5,MIN(1,Assumptions!$I$41+0.5-9)/Assumptions!$I$41,0)+(1-Assumptions!$I$40)*IF(9-Assumptions!$I$43<0,0,IF(9-Assumptions!$I$43=0,0.5/Assumptions!$I$42,IF(9-Assumptions!$I$43<Assumptions!$I$42+0.5,MIN(1,Assumptions!$I$42+0.5-(9-Assumptions!$I$43))/Assumptions!$I$42,0)))) -> 384.88 | H19: =B19*(Assumptions!$I$40*IF(10<Assumptions!$I$41+0.5,MIN(1,Assumptions!$I$41+0.5-10)/Assumptions!$I$41,0)+(1-Assumptions!$I$40)*IF(10-Assumptions!$I$43<0,0,IF(10-Assumptions!$I$43=0,0.5/Assumptions!$I$42,IF(10-Assumptions!$I$43<Assumptions!$I$42+0.5,MIN(1,Assumptions!$I$42+0.5-(10-Assumptions!$I$43))/Assumptions!$I$42,0)))) -> 384.88 | I19: =B19*(Assumptions!$I$40*IF(11<Assumptions!$I$41+0.5,MIN(1,Assumptions!$I$41+0.5-11)/Assumptions!$I$41,0)+(1-Assumptions!$I$40)*IF(11-Assumptions!$I$43<0,0,IF(11-Assumptions!$I$43=0,0.5/Assumptions!$I$42,IF(11-Assumptions!$I$43<Assumptions!$I$42+0.5,MIN(1,Assumptions!$I$42+0.5-(11-Assumptions!$I$43))/Assumptions!$I$42,0)))) -> 384.88 | J19: =B19*(Assumptions!$I$40*IF(12<Assumptions!$I$41+0.5,MIN(1,Assumptions!$I$41+0.5-12)/Assumptions!$I$41,0)+(1-Assumptions!$I$40)*IF(12-Assumptions!$I$43<0,0,IF(12-Assumptions!$I$43=0,0.5/Assumptions!$I$42,IF(12-Assumptions!$I$43<Assumptions!$I$42+0.5,MIN(1,Assumptions!$I$42+0.5-(12-Assumptions!$I$43))/Assumptions!$I$42,0)))) -> 384.88 | K19: =B19*(Assumptions!$I$40*IF(13<Assumptions!$I$41+0.5,MIN(1,Assumptions!$I$41+0.5-13)/Assumptions!$I$41,0)+(1-Assumptions!$I$40)*IF(13-Assumptions!$I$43<0,0,IF(13-Assumptions!$I$43=0,0.5/Assumptions!$I$42,IF(13-Assumptions!$I$43<Assumptions!$I$42+0.5,MIN(1,Assumptions!$I$42+0.5-(13-Assumptions!$I$43))/Assumptions!$I$42,0)))) -> 384.88 | L19: =B19*(Assumptions!$I$40*IF(14<Assumptions!$I$41+0.5,MIN(1,Assumptions!$I$41+0.5-14)/Assumptions!$I$41,0)+(1-Assumptions!$I$40)*IF(14-Assumptions!$I$43<0,0,IF(14-Assumptions!$I$43=0,0.5/Assumptions!$I$42,IF(14-Assumptions!$I$43<Assumptions!$I$42+0.5,MIN(1,Assumptions!$I$42+0.5-(14-Assumptions!$I$43))/Assumptions!$I$42,0)))) -> 384.88
A20: Capex of 2022 | B20: =-(CF_Hist!E32+CF_Hist!E50) -> 32281 | C20: =B20*(Assumptions!$I$40*IF(4<Assumptions!$I$41+0.5,MIN(1,Assumptions!$I$41+0.5-4)/Assumptions!$I$41,0)+(1-Assumptions!$I$40)*IF(4-Assumptions!$I$43<0,0,IF(4-Assumptions!$I$43=0,0.5/Assumptions!$I$42,IF(4-Assumptions!$I$43<Assumptions!$I$42+0.5,MIN(1,Assumptions!$I$42+0.5-(4-Assumptions!$I$43))/Assumptions!$I$42,0)))) -> 3580.2564 | D20: =B20*(Assumptions!$I$40*IF(5<Assumptions!$I$41+0.5,MIN(1,Assumptions!$I$41+0.5-5)/Assumptions!$I$41,0)+(1-Assumptions!$I$40)*IF(5-Assumptions!$I$43<0,0,IF(5-Assumptions!$I$43=0,0.5/Assumptions!$I$42,IF(5-Assumptions!$I$43<Assumptions!$I$42+0.5,MIN(1,Assumptions!$I$42+0.5-(5-Assumptions!$I$43))/Assumptions!$I$42,0)))) -> 3580.2564 | E20: =B20*(Assumptions!$I$40*IF(6<Assumptions!$I$41+0.5,MIN(1,Assumptions!$I$41+0.5-6)/Assumptions!$I$41,0)+(1-Assumptions!$I$40)*IF(6-Assumptions!$I$43<0,0,IF(6-Assumptions!$I$43=0,0.5/Assumptions!$I$42,IF(6-Assumptions!$I$43<Assumptions!$I$42+0.5,MIN(1,Assumptions!$I$42+0.5-(6-Assumptions!$I$43))/Assumptions!$I$42,0)))) -> 645.62 | F20: =B20*(Assumptions!$I$40*IF(7<Assumptions!$I$41+0.5,MIN(1,Assumptions!$I$41+0.5-7)/Assumptions!$I$41,0)+(1-Assumptions!$I$40)*IF(7-Assumptions!$I$43<0,0,IF(7-Assumptions!$I$43=0,0.5/Assumptions!$I$42,IF(7-Assumptions!$I$43<Assumptions!$I$42+0.5,MIN(1,Assumptions!$I$42+0.5-(7-Assumptions!$I$43))/Assumptions!$I$42,0)))) -> 645.62 | G20: =B20*(Assumptions!$I$40*IF(8<Assumptions!$I$41+0.5,MIN(1,Assumptions!$I$41+0.5-8)/Assumptions!$I$41,0)+(1-Assumptions!$I$40)*IF(8-Assumptions!$I$43<0,0,IF(8-Assumptions!$I$43=0,0.5/Assumptions!$I$42,IF(8-Assumptions!$I$43<Assumptions!$I$42+0.5,MIN(1,Assumptions!$I$42+0.5-(8-Assumptions!$I$43))/Assumptions!$I$42,0)))) -> 645.62 | H20: =B20*(Assumptions!$I$40*IF(9<Assumptions!$I$41+0.5,MIN(1,Assumptions!$I$41+0.5-9)/Assumptions!$I$41,0)+(1-Assumptions!$I$40)*IF(9-Assumptions!$I$43<0,0,IF(9-Assumptions!$I$43=0,0.5/Assumptions!$I$42,IF(9-Assumptions!$I$43<Assumptions!$I$42+0.5,MIN(1,Assumptions!$I$42+0.5-(9-Assumptions!$I$43))/Assumptions!$I$42,0)))) -> 645.62 | I20: =B20*(Assumptions!$I$40*IF(10<Assumptions!$I$41+0.5,MIN(1,Assumptions!$I$41+0.5-10)/Assumptions!$I$41,0)+(1-Assumptions!$I$40)*IF(10-Assumptions!$I$43<0,0,IF(10-Assumptions!$I$43=0,0.5/Assumptions!$I$42,IF(10-Assumptions!$I$43<Assumptions!$I$42+0.5,MIN(1,Assumptions!$I$42+0.5-(10-Assumptions!$I$43))/Assumptions!$I$42,0)))) -> 645.62 | J20: =B20*(Assumptions!$I$40*IF(11<Assumptions!$I$41+0.5,MIN(1,Assumptions!$I$41+0.5-11)/Assumptions!$I$41,0)+(1-Assumptions!$I$40)*IF(11-Assumptions!$I$43<0,0,IF(11-Assumptions!$I$43=0,0.5/Assumptions!$I$42,IF(11-Assumptions!$I$43<Assumptions!$I$42+0.5,MIN(1,Assumptions!$I$42+0.5-(11-Assumptions!$I$43))/Assumptions!$I$42,0)))) -> 645.62 | K20: =B20*(Assumptions!$I$40*IF(12<Assumptions!$I$41+0.5,MIN(1,Assumptions!$I$41+0.5-12)/Assumptions!$I$41,0)+(1-Assumptions!$I$40)*IF(12-Assumptions!$I$43<0,0,IF(12-Assumptions!$I$43=0,0.5/Assumptions!$I$42,IF(12-Assumptions!$I$43<Assumptions!$I$42+0.5,MIN(1,Assumptions!$I$42+0.5-(12-Assumptions!$I$43))/Assumptions!$I$42,0)))) -> 645.62 | L20: =B20*(Assumptions!$I$40*IF(13<Assumptions!$I$41+0.5,MIN(1,Assumptions!$I$41+0.5-13)/Assumptions!$I$41,0)+(1-Assumptions!$I$40)*IF(13-Assumptions!$I$43<0,0,IF(13-Assumptions!$I$43=0,0.5/Assumptions!$I$42,IF(13-Assumptions!$I$43<Assumptions!$I$42+0.5,MIN(1,Assumptions!$I$42+0.5-(13-Assumptions!$I$43))/Assumptions!$I$42,0)))) -> 645.62
A21: Capex of 2023 | B21: =-(CF_Hist!F32+CF_Hist!F50) -> 28324 | C21: =B21*(Assumptions!$I$40*IF(3<Assumptions!$I$41+0.5,MIN(1,Assumptions!$I$41+0.5-3)/Assumptions!$I$41,0)+(1-Assumptions!$I$40)*IF(3-Assumptions!$I$43<0,0,IF(3-Assumptions!$I$43=0,0.5/Assumptions!$I$42,IF(3-Assumptions!$I$43<Assumptions!$I$42+0.5,MIN(1,Assumptions!$I$42+0.5-(3-Assumptions!$I$43))/Assumptions!$I$42,0)))) -> 3141.3891 | D21: =B21*(Assumptions!$I$40*IF(4<Assumptions!$I$41+0.5,MIN(1,Assumptions!$I$41+0.5-4)/Assumptions!$I$41,0)+(1-Assumptions!$I$40)*IF(4-Assumptions!$I$43<0,0,IF(4-Assumptions!$I$43=0,0.5/Assumptions!$I$42,IF(4-Assumptions!$I$43<Assumptions!$I$42+0.5,MIN(1,Assumptions!$I$42+0.5-(4-Assumptions!$I$43))/Assumptions!$I$42,0)))) -> 3141.3891 | E21: =B21*(Assumptions!$I$40*IF(5<Assumptions!$I$41+0.5,MIN(1,Assumptions!$I$41+0.5-5)/Assumptions!$I$41,0)+(1-Assumptions!$I$40)*IF(5-Assumptions!$I$43<0,0,IF(5-Assumptions!$I$43=0,0.5/Assumptions!$I$42,IF(5-Assumptions!$I$43<Assumptions!$I$42+0.5,MIN(1,Assumptions!$I$42+0.5-(5-Assumptions!$I$43))/Assumptions!$I$42,0)))) -> 3141.3891 | F21: =B21*(Assumptions!$I$40*IF(6<Assumptions!$I$41+0.5,MIN(1,Assumptions!$I$41+0.5-6)/Assumptions!$I$41,0)+(1-Assumptions!$I$40)*IF(6-Assumptions!$I$43<0,0,IF(6-Assumptions!$I$43=0,0.5/Assumptions!$I$42,IF(6-Assumptions!$I$43<Assumptions!$I$42+0.5,MIN(1,Assumptions!$I$42+0.5-(6-Assumptions!$I$43))/Assumptions!$I$42,0)))) -> 566.48 | G21: =B21*(Assumptions!$I$40*IF(7<Assumptions!$I$41+0.5,MIN(1,Assumptions!$I$41+0.5-7)/Assumptions!$I$41,0)+(1-Assumptions!$I$40)*IF(7-Assumptions!$I$43<0,0,IF(7-Assumptions!$I$43=0,0.5/Assumptions!$I$42,IF(7-Assumptions!$I$43<Assumptions!$I$42+0.5,MIN(1,Assumptions!$I$42+0.5-(7-Assumptions!$I$43))/Assumptions!$I$42,0)))) -> 566.48 | H21: =B21*(Assumptions!$I$40*IF(8<Assumptions!$I$41+0.5,MIN(1,Assumptions!$I$41+0.5-8)/Assumptions!$I$41,0)+(1-Assumptions!$I$40)*IF(8-Assumptions!$I$43<0,0,IF(8-Assumptions!$I$43=0,0.5/Assumptions!$I$42,IF(8-Assumptions!$I$43<Assumptions!$I$42+0.5,MIN(1,Assumptions!$I$42+0.5-(8-Assumptions!$I$43))/Assumptions!$I$42,0)))) -> 566.48 | I21: =B21*(Assumptions!$I$40*IF(9<Assumptions!$I$41+0.5,MIN(1,Assumptions!$I$41+0.5-9)/Assumptions!$I$41,0)+(1-Assumptions!$I$40)*IF(9-Assumptions!$I$43<0,0,IF(9-Assumptions!$I$43=0,0.5/Assumptions!$I$42,IF(9-Assumptions!$I$43<Assumptions!$I$42+0.5,MIN(1,Assumptions!$I$42+0.5-(9-Assumptions!$I$43))/Assumptions!$I$42,0)))) -> 566.48 | J21: =B21*(Assumptions!$I$40*IF(10<Assumptions!$I$41+0.5,MIN(1,Assumptions!$I$41+0.5-10)/Assumptions!$I$41,0)+(1-Assumptions!$I$40)*IF(10-Assumptions!$I$43<0,0,IF(10-Assumptions!$I$43=0,0.5/Assumptions!$I$42,IF(10-Assumptions!$I$43<Assumptions!$I$42+0.5,MIN(1,Assumptions!$I$42+0.5-(10-Assumptions!$I$43))/Assumptions!$I$42,0)))) -> 566.48 | K21: =B21*(Assumptions!$I$40*IF(11<Assumptions!$I$41+0.5,MIN(1,Assumptions!$I$41+0.5-11)/Assumptions!$I$41,0)+(1-Assumptions!$I$40)*IF(11-Assumptions!$I$43<0,0,IF(11-Assumptions!$I$43=0,0.5/Assumptions!$I$42,IF(11-Assumptions!$I$43<Assumptions!$I$42+0.5,MIN(1,Assumptions!$I$42+0.5-(11-Assumptions!$I$43))/Assumptions!$I$42,0)))) -> 566.48 | L21: =B21*(Assumptions!$I$40*IF(12<Assumptions!$I$41+0.5,MIN(1,Assumptions!$I$41+0.5-12)/Assumptions!$I$41,0)+(1-Assumptions!$I$40)*IF(12-Assumptions!$I$43<0,0,IF(12-Assumptions!$I$43=0,0.5/Assumptions!$I$42,IF(12-Assumptions!$I$43<Assumptions!$I$42+0.5,MIN(1,Assumptions!$I$42+0.5-(12-Assumptions!$I$43))/Assumptions!$I$42,0)))) -> 566.48
A22: Capex of 2024 | B22: =-(CF_Hist!G32+CF_Hist!G50) -> 39225 | C22: =B22*(Assumptions!$I$40*IF(2<Assumptions!$I$41+0.5,MIN(1,Assumptions!$I$41+0.5-2)/Assumptions!$I$41,0)+(1-Assumptions!$I$40)*IF(2-Assumptions!$I$43<0,0,IF(2-Assumptions!$I$43=0,0.5/Assumptions!$I$42,IF(2-Assumptions!$I$43<Assumptions!$I$42+0.5,MIN(1,Assumptions!$I$42+0.5-(2-Assumptions!$I$43))/Assumptions!$I$42,0)))) -> 4350.4091 | D22: =B22*(Assumptions!$I$40*IF(3<Assumptions!$I$41+0.5,MIN(1,Assumptions!$I$41+0.5-3)/Assumptions!$I$41,0)+(1-Assumptions!$I$40)*IF(3-Assumptions!$I$43<0,0,IF(3-Assumptions!$I$43=0,0.5/Assumptions!$I$42,IF(3-Assumptions!$I$43<Assumptions!$I$42+0.5,MIN(1,Assumptions!$I$42+0.5-(3-Assumptions!$I$43))/Assumptions!$I$42,0)))) -> 4350.4091 | E22: =B22*(Assumptions!$I$40*IF(4<Assumptions!$I$41+0.5,MIN(1,Assumptions!$I$41+0.5-4)/Assumptions!$I$41,0)+(1-Assumptions!$I$40)*IF(4-Assumptions!$I$43<0,0,IF(4-Assumptions!$I$43=0,0.5/Assumptions!$I$42,IF(4-Assumptions!$I$43<Assumptions!$I$42+0.5,MIN(1,Assumptions!$I$42+0.5-(4-Assumptions!$I$43))/Assumptions!$I$42,0)))) -> 4350.4091 | F22: =B22*(Assumptions!$I$40*IF(5<Assumptions!$I$41+0.5,MIN(1,Assumptions!$I$41+0.5-5)/Assumptions!$I$41,0)+(1-Assumptions!$I$40)*IF(5-Assumptions!$I$43<0,0,IF(5-Assumptions!$I$43=0,0.5/Assumptions!$I$42,IF(5-Assumptions!$I$43<Assumptions!$I$42+0.5,MIN(1,Assumptions!$I$42+0.5-(5-Assumptions!$I$43))/Assumptions!$I$42,0)))) -> 4350.4091 | G22: =B22*(Assumptions!$I$40*IF(6<Assumptions!$I$41+0.5,MIN(1,Assumptions!$I$41+0.5-6)/Assumptions!$I$41,0)+(1-Assumptions!$I$40)*IF(6-Assumptions!$I$43<0,0,IF(6-Assumptions!$I$43=0,0.5/Assumptions!$I$42,IF(6-Assumptions!$I$43<Assumptions!$I$42+0.5,MIN(1,Assumptions!$I$42+0.5-(6-Assumptions!$I$43))/Assumptions!$I$42,0)))) -> 784.5 | H22: =B22*(Assumptions!$I$40*IF(7<Assumptions!$I$41+0.5,MIN(1,Assumptions!$I$41+0.5-7)/Assumptions!$I$41,0)+(1-Assumptions!$I$40)*IF(7-Assumptions!$I$43<0,0,IF(7-Assumptions!$I$43=0,0.5/Assumptions!$I$42,IF(7-Assumptions!$I$43<Assumptions!$I$42+0.5,MIN(1,Assumptions!$I$42+0.5-(7-Assumptions!$I$43))/Assumptions!$I$42,0)))) -> 784.5 | I22: =B22*(Assumptions!$I$40*IF(8<Assumptions!$I$41+0.5,MIN(1,Assumptions!$I$41+0.5-8)/Assumptions!$I$41,0)+(1-Assumptions!$I$40)*IF(8-Assumptions!$I$43<0,0,IF(8-Assumptions!$I$43=0,0.5/Assumptions!$I$42,IF(8-Assumptions!$I$43<Assumptions!$I$42+0.5,MIN(1,Assumptions!$I$42+0.5-(8-Assumptions!$I$43))/Assumptions!$I$42,0)))) -> 784.5 | J22: =B22*(Assumptions!$I$40*IF(9<Assumptions!$I$41+0.5,MIN(1,Assumptions!$I$41+0.5-9)/Assumptions!$I$41,0)+(1-Assumptions!$I$40)*IF(9-Assumptions!$I$43<0,0,IF(9-Assumptions!$I$43=0,0.5/Assumptions!$I$42,IF(9-Assumptions!$I$43<Assumptions!$I$42+0.5,MIN(1,Assumptions!$I$42+0.5-(9-Assumptions!$I$43))/Assumptions!$I$42,0)))) -> 784.5 | K22: =B22*(Assumptions!$I$40*IF(10<Assumptions!$I$41+0.5,MIN(1,Assumptions!$I$41+0.5-10)/Assumptions!$I$41,0)+(1-Assumptions!$I$40)*IF(10-Assumptions!$I$43<0,0,IF(10-Assumptions!$I$43=0,0.5/Assumptions!$I$42,IF(10-Assumptions!$I$43<Assumptions!$I$42+0.5,MIN(1,Assumptions!$I$42+0.5-(10-Assumptions!$I$43))/Assumptions!$I$42,0)))) -> 784.5 | L22: =B22*(Assumptions!$I$40*IF(11<Assumptions!$I$41+0.5,MIN(1,Assumptions!$I$41+0.5-11)/Assumptions!$I$41,0)+(1-Assumptions!$I$40)*IF(11-Assumptions!$I$43<0,0,IF(11-Assumptions!$I$43=0,0.5/Assumptions!$I$42,IF(11-Assumptions!$I$43<Assumptions!$I$42+0.5,MIN(1,Assumptions!$I$42+0.5-(11-Assumptions!$I$43))/Assumptions!$I$42,0)))) -> 784.5
A23: Capex of 2025 | B23: =-(CF_Hist!H32+CF_Hist!H50) -> 72215 | C23: =B23*(Assumptions!$I$40*IF(1<Assumptions!$I$41+0.5,MIN(1,Assumptions!$I$41+0.5-1)/Assumptions!$I$41,0)+(1-Assumptions!$I$40)*IF(1-Assumptions!$I$43<0,0,IF(1-Assumptions!$I$43=0,0.5/Assumptions!$I$42,IF(1-Assumptions!$I$43<Assumptions!$I$42+0.5,MIN(1,Assumptions!$I$42+0.5-(1-Assumptions!$I$43))/Assumptions!$I$42,0)))) -> 7287.15 | D23: =B23*(Assumptions!$I$40*IF(2<Assumptions!$I$41+0.5,MIN(1,Assumptions!$I$41+0.5-2)/Assumptions!$I$41,0)+(1-Assumptions!$I$40)*IF(2-Assumptions!$I$43<0,0,IF(2-Assumptions!$I$43=0,0.5/Assumptions!$I$42,IF(2-Assumptions!$I$43<Assumptions!$I$42+0.5,MIN(1,Assumptions!$I$42+0.5-(2-Assumptions!$I$43))/Assumptions!$I$42,0)))) -> 8009.3 | E23: =B23*(Assumptions!$I$40*IF(3<Assumptions!$I$41+0.5,MIN(1,Assumptions!$I$41+0.5-3)/Assumptions!$I$41,0)+(1-Assumptions!$I$40)*IF(3-Assumptions!$I$43<0,0,IF(3-Assumptions!$I$43=0,0.5/Assumptions!$I$42,IF(3-Assumptions!$I$43<Assumptions!$I$42+0.5,MIN(1,Assumptions!$I$42+0.5-(3-Assumptions!$I$43))/Assumptions!$I$42,0)))) -> 8009.3 | F23: =B23*(Assumptions!$I$40*IF(4<Assumptions!$I$41+0.5,MIN(1,Assumptions!$I$41+0.5-4)/Assumptions!$I$41,0)+(1-Assumptions!$I$40)*IF(4-Assumptions!$I$43<0,0,IF(4-Assumptions!$I$43=0,0.5/Assumptions!$I$42,IF(4-Assumptions!$I$43<Assumptions!$I$42+0.5,MIN(1,Assumptions!$I$42+0.5-(4-Assumptions!$I$43))/Assumptions!$I$42,0)))) -> 8009.3 | G23: =B23*(Assumptions!$I$40*IF(5<Assumptions!$I$41+0.5,MIN(1,Assumptions!$I$41+0.5-5)/Assumptions!$I$41,0)+(1-Assumptions!$I$40)*IF(5-Assumptions!$I$43<0,0,IF(5-Assumptions!$I$43=0,0.5/Assumptions!$I$42,IF(5-Assumptions!$I$43<Assumptions!$I$42+0.5,MIN(1,Assumptions!$I$42+0.5-(5-Assumptions!$I$43))/Assumptions!$I$42,0)))) -> 8009.3 | H23: =B23*(Assumptions!$I$40*IF(6<Assumptions!$I$41+0.5,MIN(1,Assumptions!$I$41+0.5-6)/Assumptions!$I$41,0)+(1-Assumptions!$I$40)*IF(6-Assumptions!$I$43<0,0,IF(6-Assumptions!$I$43=0,0.5/Assumptions!$I$42,IF(6-Assumptions!$I$43<Assumptions!$I$42+0.5,MIN(1,Assumptions!$I$42+0.5-(6-Assumptions!$I$43))/Assumptions!$I$42,0)))) -> 1444.3 | I23: =B23*(Assumptions!$I$40*IF(7<Assumptions!$I$41+0.5,MIN(1,Assumptions!$I$41+0.5-7)/Assumptions!$I$41,0)+(1-Assumptions!$I$40)*IF(7-Assumptions!$I$43<0,0,IF(7-Assumptions!$I$43=0,0.5/Assumptions!$I$42,IF(7-Assumptions!$I$43<Assumptions!$I$42+0.5,MIN(1,Assumptions!$I$42+0.5-(7-Assumptions!$I$43))/Assumptions!$I$42,0)))) -> 1444.3 | J23: =B23*(Assumptions!$I$40*IF(8<Assumptions!$I$41+0.5,MIN(1,Assumptions!$I$41+0.5-8)/Assumptions!$I$41,0)+(1-Assumptions!$I$40)*IF(8-Assumptions!$I$43<0,0,IF(8-Assumptions!$I$43=0,0.5/Assumptions!$I$42,IF(8-Assumptions!$I$43<Assumptions!$I$42+0.5,MIN(1,Assumptions!$I$42+0.5-(8-Assumptions!$I$43))/Assumptions!$I$42,0)))) -> 1444.3 | K23: =B23*(Assumptions!$I$40*IF(9<Assumptions!$I$41+0.5,MIN(1,Assumptions!$I$41+0.5-9)/Assumptions!$I$41,0)+(1-Assumptions!$I$40)*IF(9-Assumptions!$I$43<0,0,IF(9-Assumptions!$I$43=0,0.5/Assumptions!$I$42,IF(9-Assumptions!$I$43<Assumptions!$I$42+0.5,MIN(1,Assumptions!$I$42+0.5-(9-Assumptions!$I$43))/Assumptions!$I$42,0)))) -> 1444.3 | L23: =B23*(Assumptions!$I$40*IF(10<Assumptions!$I$41+0.5,MIN(1,Assumptions!$I$41+0.5-10)/Assumptions!$I$41,0)+(1-Assumptions!$I$40)*IF(10-Assumptions!$I$43<0,0,IF(10-Assumptions!$I$43=0,0.5/Assumptions!$I$42,IF(10-Assumptions!$I$43<Assumptions!$I$42+0.5,MIN(1,Assumptions!$I$42+0.5-(10-Assumptions!$I$43))/Assumptions!$I$42,0)))) -> 1444.3
A24: Capex of 2026 | B24: =C7 -> 140000 | C24: =B24*(Assumptions!$I$40*0.5/Assumptions!$I$41+(1-Assumptions!$I$40)*IF(0-Assumptions!$I$43<0,0,IF(0-Assumptions!$I$43=0,0.5/Assumptions!$I$42,IF(0-Assumptions!$I$43<Assumptions!$I$42+0.5,MIN(1,Assumptions!$I$42+0.5-(0-Assumptions!$I$43))/Assumptions!$I$42,0)))) -> 6363.6364 | D24: =B24*(Assumptions!$I$40*IF(1<Assumptions!$I$41+0.5,MIN(1,Assumptions!$I$41+0.5-1)/Assumptions!$I$41,0)+(1-Assumptions!$I$40)*IF(1-Assumptions!$I$43<0,0,IF(1-Assumptions!$I$43=0,0.5/Assumptions!$I$42,IF(1-Assumptions!$I$43<Assumptions!$I$42+0.5,MIN(1,Assumptions!$I$42+0.5-(1-Assumptions!$I$43))/Assumptions!$I$42,0)))) -> 14127.273 | E24: =B24*(Assumptions!$I$40*IF(2<Assumptions!$I$41+0.5,MIN(1,Assumptions!$I$41+0.5-2)/Assumptions!$I$41,0)+(1-Assumptions!$I$40)*IF(2-Assumptions!$I$43<0,0,IF(2-Assumptions!$I$43=0,0.5/Assumptions!$I$42,IF(2-Assumptions!$I$43<Assumptions!$I$42+0.5,MIN(1,Assumptions!$I$42+0.5-(2-Assumptions!$I$43))/Assumptions!$I$42,0)))) -> 15527.273 | F24: =B24*(Assumptions!$I$40*IF(3<Assumptions!$I$41+0.5,MIN(1,Assumptions!$I$41+0.5-3)/Assumptions!$I$41,0)+(1-Assumptions!$I$40)*IF(3-Assumptions!$I$43<0,0,IF(3-Assumptions!$I$43=0,0.5/Assumptions!$I$42,IF(3-Assumptions!$I$43<Assumptions!$I$42+0.5,MIN(1,Assumptions!$I$42+0.5-(3-Assumptions!$I$43))/Assumptions!$I$42,0)))) -> 15527.273 | G24: =B24*(Assumptions!$I$40*IF(4<Assumptions!$I$41+0.5,MIN(1,Assumptions!$I$41+0.5-4)/Assumptions!$I$41,0)+(1-Assumptions!$I$40)*IF(4-Assumptions!$I$43<0,0,IF(4-Assumptions!$I$43=0,0.5/Assumptions!$I$42,IF(4-Assumptions!$I$43<Assumptions!$I$42+0.5,MIN(1,Assumptions!$I$42+0.5-(4-Assumptions!$I$43))/Assumptions!$I$42,0)))) -> 15527.273 | H24: =B24*(Assumptions!$I$40*IF(5<Assumptions!$I$41+0.5,MIN(1,Assumptions!$I$41+0.5-5)/Assumptions!$I$41,0)+(1-Assumptions!$I$40)*IF(5-Assumptions!$I$43<0,0,IF(5-Assumptions!$I$43=0,0.5/Assumptions!$I$42,IF(5-Assumptions!$I$43<Assumptions!$I$42+0.5,MIN(1,Assumptions!$I$42+0.5-(5-Assumptions!$I$43))/Assumptions!$I$42,0)))) -> 15527.273 | I24: =B24*(Assumptions!$I$40*IF(6<Assumptions!$I$41+0.5,MIN(1,Assumptions!$I$41+0.5-6)/Assumptions!$I$41,0)+(1-Assumptions!$I$40)*IF(6-Assumptions!$I$43<0,0,IF(6-Assumptions!$I$43=0,0.5/Assumptions!$I$42,IF(6-Assumptions!$I$43<Assumptions!$I$42+0.5,MIN(1,Assumptions!$I$42+0.5-(6-Assumptions!$I$43))/Assumptions!$I$42,0)))) -> 2800 | J24: =B24*(Assumptions!$I$40*IF(7<Assumptions!$I$41+0.5,MIN(1,Assumptions!$I$41+0.5-7)/Assumptions!$I$41,0)+(1-Assumptions!$I$40)*IF(7-Assumptions!$I$43<0,0,IF(7-Assumptions!$I$43=0,0.5/Assumptions!$I$42,IF(7-Assumptions!$I$43<Assumptions!$I$42+0.5,MIN(1,Assumptions!$I$42+0.5-(7-Assumptions!$I$43))/Assumptions!$I$42,0)))) -> 2800 | K24: =B24*(Assumptions!$I$40*IF(8<Assumptions!$I$41+0.5,MIN(1,Assumptions!$I$41+0.5-8)/Assumptions!$I$41,0)+(1-Assumptions!$I$40)*IF(8-Assumptions!$I$43<0,0,IF(8-Assumptions!$I$43=0,0.5/Assumptions!$I$42,IF(8-Assumptions!$I$43<Assumptions!$I$42+0.5,MIN(1,Assumptions!$I$42+0.5-(8-Assumptions!$I$43))/Assumptions!$I$42,0)))) -> 2800 | L24: =B24*(Assumptions!$I$40*IF(9<Assumptions!$I$41+0.5,MIN(1,Assumptions!$I$41+0.5-9)/Assumptions!$I$41,0)+(1-Assumptions!$I$40)*IF(9-Assumptions!$I$43<0,0,IF(9-Assumptions!$I$43=0,0.5/Assumptions!$I$42,IF(9-Assumptions!$I$43<Assumptions!$I$42+0.5,MIN(1,Assumptions!$I$42+0.5-(9-Assumptions!$I$43))/Assumptions!$I$42,0)))) -> 2800
A25: Capex of 2027 | B25: =D7 -> 199000 | D25: =B25*(Assumptions!$I$40*0.5/Assumptions!$I$41+(1-Assumptions!$I$40)*IF(0-Assumptions!$I$43<0,0,IF(0-Assumptions!$I$43=0,0.5/Assumptions!$I$42,IF(0-Assumptions!$I$43<Assumptions!$I$42+0.5,MIN(1,Assumptions!$I$42+0.5-(0-Assumptions!$I$43))/Assumptions!$I$42,0)))) -> 9045.4545 | E25: =B25*(Assumptions!$I$40*IF(1<Assumptions!$I$41+0.5,MIN(1,Assumptions!$I$41+0.5-1)/Assumptions!$I$41,0)+(1-Assumptions!$I$40)*IF(1-Assumptions!$I$43<0,0,IF(1-Assumptions!$I$43=0,0.5/Assumptions!$I$42,IF(1-Assumptions!$I$43<Assumptions!$I$42+0.5,MIN(1,Assumptions!$I$42+0.5-(1-Assumptions!$I$43))/Assumptions!$I$42,0)))) -> 20080.909 | F25: =B25*(Assumptions!$I$40*IF(2<Assumptions!$I$41+0.5,MIN(1,Assumptions!$I$41+0.5-2)/Assumptions!$I$41,0)+(1-Assumptions!$I$40)*IF(2-Assumptions!$I$43<0,0,IF(2-Assumptions!$I$43=0,0.5/Assumptions!$I$42,IF(2-Assumptions!$I$43<Assumptions!$I$42+0.5,MIN(1,Assumptions!$I$42+0.5-(2-Assumptions!$I$43))/Assumptions!$I$42,0)))) -> 22070.909 | G25: =B25*(Assumptions!$I$40*IF(3<Assumptions!$I$41+0.5,MIN(1,Assumptions!$I$41+0.5-3)/Assumptions!$I$41,0)+(1-Assumptions!$I$40)*IF(3-Assumptions!$I$43<0,0,IF(3-Assumptions!$I$43=0,0.5/Assumptions!$I$42,IF(3-Assumptions!$I$43<Assumptions!$I$42+0.5,MIN(1,Assumptions!$I$42+0.5-(3-Assumptions!$I$43))/Assumptions!$I$42,0)))) -> 22070.909 | H25: =B25*(Assumptions!$I$40*IF(4<Assumptions!$I$41+0.5,MIN(1,Assumptions!$I$41+0.5-4)/Assumptions!$I$41,0)+(1-Assumptions!$I$40)*IF(4-Assumptions!$I$43<0,0,IF(4-Assumptions!$I$43=0,0.5/Assumptions!$I$42,IF(4-Assumptions!$I$43<Assumptions!$I$42+0.5,MIN(1,Assumptions!$I$42+0.5-(4-Assumptions!$I$43))/Assumptions!$I$42,0)))) -> 22070.909 | I25: =B25*(Assumptions!$I$40*IF(5<Assumptions!$I$41+0.5,MIN(1,Assumptions!$I$41+0.5-5)/Assumptions!$I$41,0)+(1-Assumptions!$I$40)*IF(5-Assumptions!$I$43<0,0,IF(5-Assumptions!$I$43=0,0.5/Assumptions!$I$42,IF(5-Assumptions!$I$43<Assumptions!$I$42+0.5,MIN(1,Assumptions!$I$42+0.5-(5-Assumptions!$I$43))/Assumptions!$I$42,0)))) -> 22070.909 | J25: =B25*(Assumptions!$I$40*IF(6<Assumptions!$I$41+0.5,MIN(1,Assumptions!$I$41+0.5-6)/Assumptions!$I$41,0)+(1-Assumptions!$I$40)*IF(6-Assumptions!$I$43<0,0,IF(6-Assumptions!$I$43=0,0.5/Assumptions!$I$42,IF(6-Assumptions!$I$43<Assumptions!$I$42+0.5,MIN(1,Assumptions!$I$42+0.5-(6-Assumptions!$I$43))/Assumptions!$I$42,0)))) -> 3980 | K25: =B25*(Assumptions!$I$40*IF(7<Assumptions!$I$41+0.5,MIN(1,Assumptions!$I$41+0.5-7)/Assumptions!$I$41,0)+(1-Assumptions!$I$40)*IF(7-Assumptions!$I$43<0,0,IF(7-Assumptions!$I$43=0,0.5/Assumptions!$I$42,IF(7-Assumptions!$I$43<Assumptions!$I$42+0.5,MIN(1,Assumptions!$I$42+0.5-(7-Assumptions!$I$43))/Assumptions!$I$42,0)))) -> 3980 | L25: =B25*(Assumptions!$I$40*IF(8<Assumptions!$I$41+0.5,MIN(1,Assumptions!$I$41+0.5-8)/Assumptions!$I$41,0)+(1-Assumptions!$I$40)*IF(8-Assumptions!$I$43<0,0,IF(8-Assumptions!$I$43=0,0.5/Assumptions!$I$42,IF(8-Assumptions!$I$43<Assumptions!$I$42+0.5,MIN(1,Assumptions!$I$42+0.5-(8-Assumptions!$I$43))/Assumptions!$I$42,0)))) -> 3980
A26: Capex of 2028 | B26: =E7 -> 205000 | E26: =B26*(Assumptions!$I$40*0.5/Assumptions!$I$41+(1-Assumptions!$I$40)*IF(0-Assumptions!$I$43<0,0,IF(0-Assumptions!$I$43=0,0.5/Assumptions!$I$42,IF(0-Assumptions!$I$43<Assumptions!$I$42+0.5,MIN(1,Assumptions!$I$42+0.5-(0-Assumptions!$I$43))/Assumptions!$I$42,0)))) -> 9318.1818 | F26: =B26*(Assumptions!$I$40*IF(1<Assumptions!$I$41+0.5,MIN(1,Assumptions!$I$41+0.5-1)/Assumptions!$I$41,0)+(1-Assumptions!$I$40)*IF(1-Assumptions!$I$43<0,0,IF(1-Assumptions!$I$43=0,0.5/Assumptions!$I$42,IF(1-Assumptions!$I$43<Assumptions!$I$42+0.5,MIN(1,Assumptions!$I$42+0.5-(1-Assumptions!$I$43))/Assumptions!$I$42,0)))) -> 20686.364 | G26: =B26*(Assumptions!$I$40*IF(2<Assumptions!$I$41+0.5,MIN(1,Assumptions!$I$41+0.5-2)/Assumptions!$I$41,0)+(1-Assumptions!$I$40)*IF(2-Assumptions!$I$43<0,0,IF(2-Assumptions!$I$43=0,0.5/Assumptions!$I$42,IF(2-Assumptions!$I$43<Assumptions!$I$42+0.5,MIN(1,Assumptions!$I$42+0.5-(2-Assumptions!$I$43))/Assumptions!$I$42,0)))) -> 22736.364 | H26: =B26*(Assumptions!$I$40*IF(3<Assumptions!$I$41+0.5,MIN(1,Assumptions!$I$41+0.5-3)/Assumptions!$I$41,0)+(1-Assumptions!$I$40)*IF(3-Assumptions!$I$43<0,0,IF(3-Assumptions!$I$43=0,0.5/Assumptions!$I$42,IF(3-Assumptions!$I$43<Assumptions!$I$42+0.5,MIN(1,Assumptions!$I$42+0.5-(3-Assumptions!$I$43))/Assumptions!$I$42,0)))) -> 22736.364 | I26: =B26*(Assumptions!$I$40*IF(4<Assumptions!$I$41+0.5,MIN(1,Assumptions!$I$41+0.5-4)/Assumptions!$I$41,0)+(1-Assumptions!$I$40)*IF(4-Assumptions!$I$43<0,0,IF(4-Assumptions!$I$43=0,0.5/Assumptions!$I$42,IF(4-Assumptions!$I$43<Assumptions!$I$42+0.5,MIN(1,Assumptions!$I$42+0.5-(4-Assumptions!$I$43))/Assumptions!$I$42,0)))) -> 22736.364 | J26: =B26*(Assumptions!$I$40*IF(5<Assumptions!$I$41+0.5,MIN(1,Assumptions!$I$41+0.5-5)/Assumptions!$I$41,0)+(1-Assumptions!$I$40)*IF(5-Assumptions!$I$43<0,0,IF(5-Assumptions!$I$43=0,0.5/Assumptions!$I$42,IF(5-Assumptions!$I$43<Assumptions!$I$42+0.5,MIN(1,Assumptions!$I$42+0.5-(5-Assumptions!$I$43))/Assumptions!$I$42,0)))) -> 22736.364 | K26: =B26*(Assumptions!$I$40*IF(6<Assumptions!$I$41+0.5,MIN(1,Assumptions!$I$41+0.5-6)/Assumptions!$I$41,0)+(1-Assumptions!$I$40)*IF(6-Assumptions!$I$43<0,0,IF(6-Assumptions!$I$43=0,0.5/Assumptions!$I$42,IF(6-Assumptions!$I$43<Assumptions!$I$42+0.5,MIN(1,Assumptions!$I$42+0.5-(6-Assumptions!$I$43))/Assumptions!$I$42,0)))) -> 4100 | L26: =B26*(Assumptions!$I$40*IF(7<Assumptions!$I$41+0.5,MIN(1,Assumptions!$I$41+0.5-7)/Assumptions!$I$41,0)+(1-Assumptions!$I$40)*IF(7-Assumptions!$I$43<0,0,IF(7-Assumptions!$I$43=0,0.5/Assumptions!$I$42,IF(7-Assumptions!$I$43<Assumptions!$I$42+0.5,MIN(1,Assumptions!$I$42+0.5-(7-Assumptions!$I$43))/Assumptions!$I$42,0)))) -> 4100
A27: Capex of 2029 | B27: =F7 -> 200000 | F27: =B27*(Assumptions!$I$40*0.5/Assumptions!$I$41+(1-Assumptions!$I$40)*IF(0-Assumptions!$I$43<0,0,IF(0-Assumptions!$I$43=0,0.5/Assumptions!$I$42,IF(0-Assumptions!$I$43<Assumptions!$I$42+0.5,MIN(1,Assumptions!$I$42+0.5-(0-Assumptions!$I$43))/Assumptions!$I$42,0)))) -> 9090.9091 | G27: =B27*(Assumptions!$I$40*IF(1<Assumptions!$I$41+0.5,MIN(1,Assumptions!$I$41+0.5-1)/Assumptions!$I$41,0)+(1-Assumptions!$I$40)*IF(1-Assumptions!$I$43<0,0,IF(1-Assumptions!$I$43=0,0.5/Assumptions!$I$42,IF(1-Assumptions!$I$43<Assumptions!$I$42+0.5,MIN(1,Assumptions!$I$42+0.5-(1-Assumptions!$I$43))/Assumptions!$I$42,0)))) -> 20181.818 | H27: =B27*(Assumptions!$I$40*IF(2<Assumptions!$I$41+0.5,MIN(1,Assumptions!$I$41+0.5-2)/Assumptions!$I$41,0)+(1-Assumptions!$I$40)*IF(2-Assumptions!$I$43<0,0,IF(2-Assumptions!$I$43=0,0.5/Assumptions!$I$42,IF(2-Assumptions!$I$43<Assumptions!$I$42+0.5,MIN(1,Assumptions!$I$42+0.5-(2-Assumptions!$I$43))/Assumptions!$I$42,0)))) -> 22181.818 | I27: =B27*(Assumptions!$I$40*IF(3<Assumptions!$I$41+0.5,MIN(1,Assumptions!$I$41+0.5-3)/Assumptions!$I$41,0)+(1-Assumptions!$I$40)*IF(3-Assumptions!$I$43<0,0,IF(3-Assumptions!$I$43=0,0.5/Assumptions!$I$42,IF(3-Assumptions!$I$43<Assumptions!$I$42+0.5,MIN(1,Assumptions!$I$42+0.5-(3-Assumptions!$I$43))/Assumptions!$I$42,0)))) -> 22181.818 | J27: =B27*(Assumptions!$I$40*IF(4<Assumptions!$I$41+0.5,MIN(1,Assumptions!$I$41+0.5-4)/Assumptions!$I$41,0)+(1-Assumptions!$I$40)*IF(4-Assumptions!$I$43<0,0,IF(4-Assumptions!$I$43=0,0.5/Assumptions!$I$42,IF(4-Assumptions!$I$43<Assumptions!$I$42+0.5,MIN(1,Assumptions!$I$42+0.5-(4-Assumptions!$I$43))/Assumptions!$I$42,0)))) -> 22181.818 | K27: =B27*(Assumptions!$I$40*IF(5<Assumptions!$I$41+0.5,MIN(1,Assumptions!$I$41+0.5-5)/Assumptions!$I$41,0)+(1-Assumptions!$I$40)*IF(5-Assumptions!$I$43<0,0,IF(5-Assumptions!$I$43=0,0.5/Assumptions!$I$42,IF(5-Assumptions!$I$43<Assumptions!$I$42+0.5,MIN(1,Assumptions!$I$42+0.5-(5-Assumptions!$I$43))/Assumptions!$I$42,0)))) -> 22181.818 | L27: =B27*(Assumptions!$I$40*IF(6<Assumptions!$I$41+0.5,MIN(1,Assumptions!$I$41+0.5-6)/Assumptions!$I$41,0)+(1-Assumptions!$I$40)*IF(6-Assumptions!$I$43<0,0,IF(6-Assumptions!$I$43=0,0.5/Assumptions!$I$42,IF(6-Assumptions!$I$43<Assumptions!$I$42+0.5,MIN(1,Assumptions!$I$42+0.5-(6-Assumptions!$I$43))/Assumptions!$I$42,0)))) -> 4000
A28: Capex of 2030 | B28: =G7 -> 190000 | G28: =B28*(Assumptions!$I$40*0.5/Assumptions!$I$41+(1-Assumptions!$I$40)*IF(0-Assumptions!$I$43<0,0,IF(0-Assumptions!$I$43=0,0.5/Assumptions!$I$42,IF(0-Assumptions!$I$43<Assumptions!$I$42+0.5,MIN(1,Assumptions!$I$42+0.5-(0-Assumptions!$I$43))/Assumptions!$I$42,0)))) -> 8636.3636 | H28: =B28*(Assumptions!$I$40*IF(1<Assumptions!$I$41+0.5,MIN(1,Assumptions!$I$41+0.5-1)/Assumptions!$I$41,0)+(1-Assumptions!$I$40)*IF(1-Assumptions!$I$43<0,0,IF(1-Assumptions!$I$43=0,0.5/Assumptions!$I$42,IF(1-Assumptions!$I$43<Assumptions!$I$42+0.5,MIN(1,Assumptions!$I$42+0.5-(1-Assumptions!$I$43))/Assumptions!$I$42,0)))) -> 19172.727 | I28: =B28*(Assumptions!$I$40*IF(2<Assumptions!$I$41+0.5,MIN(1,Assumptions!$I$41+0.5-2)/Assumptions!$I$41,0)+(1-Assumptions!$I$40)*IF(2-Assumptions!$I$43<0,0,IF(2-Assumptions!$I$43=0,0.5/Assumptions!$I$42,IF(2-Assumptions!$I$43<Assumptions!$I$42+0.5,MIN(1,Assumptions!$I$42+0.5-(2-Assumptions!$I$43))/Assumptions!$I$42,0)))) -> 21072.727 | J28: =B28*(Assumptions!$I$40*IF(3<Assumptions!$I$41+0.5,MIN(1,Assumptions!$I$41+0.5-3)/Assumptions!$I$41,0)+(1-Assumptions!$I$40)*IF(3-Assumptions!$I$43<0,0,IF(3-Assumptions!$I$43=0,0.5/Assumptions!$I$42,IF(3-Assumptions!$I$43<Assumptions!$I$42+0.5,MIN(1,Assumptions!$I$42+0.5-(3-Assumptions!$I$43))/Assumptions!$I$42,0)))) -> 21072.727 | K28: =B28*(Assumptions!$I$40*IF(4<Assumptions!$I$41+0.5,MIN(1,Assumptions!$I$41+0.5-4)/Assumptions!$I$41,0)+(1-Assumptions!$I$40)*IF(4-Assumptions!$I$43<0,0,IF(4-Assumptions!$I$43=0,0.5/Assumptions!$I$42,IF(4-Assumptions!$I$43<Assumptions!$I$42+0.5,MIN(1,Assumptions!$I$42+0.5-(4-Assumptions!$I$43))/Assumptions!$I$42,0)))) -> 21072.727 | L28: =B28*(Assumptions!$I$40*IF(5<Assumptions!$I$41+0.5,MIN(1,Assumptions!$I$41+0.5-5)/Assumptions!$I$41,0)+(1-Assumptions!$I$40)*IF(5-Assumptions!$I$43<0,0,IF(5-Assumptions!$I$43=0,0.5/Assumptions!$I$42,IF(5-Assumptions!$I$43<Assumptions!$I$42+0.5,MIN(1,Assumptions!$I$42+0.5-(5-Assumptions!$I$43))/Assumptions!$I$42,0)))) -> 21072.727
A29: Capex of 2031 | B29: =H7 -> 185000 | H29: =B29*(Assumptions!$I$40*0.5/Assumptions!$I$41+(1-Assumptions!$I$40)*IF(0-Assumptions!$I$43<0,0,IF(0-Assumptions!$I$43=0,0.5/Assumptions!$I$42,IF(0-Assumptions!$I$43<Assumptions!$I$42+0.5,MIN(1,Assumptions!$I$42+0.5-(0-Assumptions!$I$43))/Assumptions!$I$42,0)))) -> 8409.0909 | I29: =B29*(Assumptions!$I$40*IF(1<Assumptions!$I$41+0.5,MIN(1,Assumptions!$I$41+0.5-1)/Assumptions!$I$41,0)+(1-Assumptions!$I$40)*IF(1-Assumptions!$I$43<0,0,IF(1-Assumptions!$I$43=0,0.5/Assumptions!$I$42,IF(1-Assumptions!$I$43<Assumptions!$I$42+0.5,MIN(1,Assumptions!$I$42+0.5-(1-Assumptions!$I$43))/Assumptions!$I$42,0)))) -> 18668.182 | J29: =B29*(Assumptions!$I$40*IF(2<Assumptions!$I$41+0.5,MIN(1,Assumptions!$I$41+0.5-2)/Assumptions!$I$41,0)+(1-Assumptions!$I$40)*IF(2-Assumptions!$I$43<0,0,IF(2-Assumptions!$I$43=0,0.5/Assumptions!$I$42,IF(2-Assumptions!$I$43<Assumptions!$I$42+0.5,MIN(1,Assumptions!$I$42+0.5-(2-Assumptions!$I$43))/Assumptions!$I$42,0)))) -> 20518.182 | K29: =B29*(Assumptions!$I$40*IF(3<Assumptions!$I$41+0.5,MIN(1,Assumptions!$I$41+0.5-3)/Assumptions!$I$41,0)+(1-Assumptions!$I$40)*IF(3-Assumptions!$I$43<0,0,IF(3-Assumptions!$I$43=0,0.5/Assumptions!$I$42,IF(3-Assumptions!$I$43<Assumptions!$I$42+0.5,MIN(1,Assumptions!$I$42+0.5-(3-Assumptions!$I$43))/Assumptions!$I$42,0)))) -> 20518.182 | L29: =B29*(Assumptions!$I$40*IF(4<Assumptions!$I$41+0.5,MIN(1,Assumptions!$I$41+0.5-4)/Assumptions!$I$41,0)+(1-Assumptions!$I$40)*IF(4-Assumptions!$I$43<0,0,IF(4-Assumptions!$I$43=0,0.5/Assumptions!$I$42,IF(4-Assumptions!$I$43<Assumptions!$I$42+0.5,MIN(1,Assumptions!$I$42+0.5-(4-Assumptions!$I$43))/Assumptions!$I$42,0)))) -> 20518.182
A30: Capex of 2032 | B30: =I7 -> 185000 | I30: =B30*(Assumptions!$I$40*0.5/Assumptions!$I$41+(1-Assumptions!$I$40)*IF(0-Assumptions!$I$43<0,0,IF(0-Assumptions!$I$43=0,0.5/Assumptions!$I$42,IF(0-Assumptions!$I$43<Assumptions!$I$42+0.5,MIN(1,Assumptions!$I$42+0.5-(0-Assumptions!$I$43))/Assumptions!$I$42,0)))) -> 8409.0909 | J30: =B30*(Assumptions!$I$40*IF(1<Assumptions!$I$41+0.5,MIN(1,Assumptions!$I$41+0.5-1)/Assumptions!$I$41,0)+(1-Assumptions!$I$40)*IF(1-Assumptions!$I$43<0,0,IF(1-Assumptions!$I$43=0,0.5/Assumptions!$I$42,IF(1-Assumptions!$I$43<Assumptions!$I$42+0.5,MIN(1,Assumptions!$I$42+0.5-(1-Assumptions!$I$43))/Assumptions!$I$42,0)))) -> 18668.182 | K30: =B30*(Assumptions!$I$40*IF(2<Assumptions!$I$41+0.5,MIN(1,Assumptions!$I$41+0.5-2)/Assumptions!$I$41,0)+(1-Assumptions!$I$40)*IF(2-Assumptions!$I$43<0,0,IF(2-Assumptions!$I$43=0,0.5/Assumptions!$I$42,IF(2-Assumptions!$I$43<Assumptions!$I$42+0.5,MIN(1,Assumptions!$I$42+0.5-(2-Assumptions!$I$43))/Assumptions!$I$42,0)))) -> 20518.182 | L30: =B30*(Assumptions!$I$40*IF(3<Assumptions!$I$41+0.5,MIN(1,Assumptions!$I$41+0.5-3)/Assumptions!$I$41,0)+(1-Assumptions!$I$40)*IF(3-Assumptions!$I$43<0,0,IF(3-Assumptions!$I$43=0,0.5/Assumptions!$I$42,IF(3-Assumptions!$I$43<Assumptions!$I$42+0.5,MIN(1,Assumptions!$I$42+0.5-(3-Assumptions!$I$43))/Assumptions!$I$42,0)))) -> 20518.182
A31: Capex of 2033 | B31: =J7 -> 190000 | J31: =B31*(Assumptions!$I$40*0.5/Assumptions!$I$41+(1-Assumptions!$I$40)*IF(0-Assumptions!$I$43<0,0,IF(0-Assumptions!$I$43=0,0.5/Assumptions!$I$42,IF(0-Assumptions!$I$43<Assumptions!$I$42+0.5,MIN(1,Assumptions!$I$42+0.5-(0-Assumptions!$I$43))/Assumptions!$I$42,0)))) -> 8636.3636 | K31: =B31*(Assumptions!$I$40*IF(1<Assumptions!$I$41+0.5,MIN(1,Assumptions!$I$41+0.5-1)/Assumptions!$I$41,0)+(1-Assumptions!$I$40)*IF(1-Assumptions!$I$43<0,0,IF(1-Assumptions!$I$43=0,0.5/Assumptions!$I$42,IF(1-Assumptions!$I$43<Assumptions!$I$42+0.5,MIN(1,Assumptions!$I$42+0.5-(1-Assumptions!$I$43))/Assumptions!$I$42,0)))) -> 19172.727 | L31: =B31*(Assumptions!$I$40*IF(2<Assumptions!$I$41+0.5,MIN(1,Assumptions!$I$41+0.5-2)/Assumptions!$I$41,0)+(1-Assumptions!$I$40)*IF(2-Assumptions!$I$43<0,0,IF(2-Assumptions!$I$43=0,0.5/Assumptions!$I$42,IF(2-Assumptions!$I$43<Assumptions!$I$42+0.5,MIN(1,Assumptions!$I$42+0.5-(2-Assumptions!$I$43))/Assumptions!$I$42,0)))) -> 21072.727
A32: Capex of 2034 | B32: =K7 -> 195000 | K32: =B32*(Assumptions!$I$40*0.5/Assumptions!$I$41+(1-Assumptions!$I$40)*IF(0-Assumptions!$I$43<0,0,IF(0-Assumptions!$I$43=0,0.5/Assumptions!$I$42,IF(0-Assumptions!$I$43<Assumptions!$I$42+0.5,MIN(1,Assumptions!$I$42+0.5-(0-Assumptions!$I$43))/Assumptions!$I$42,0)))) -> 8863.6364 | L32: =B32*(Assumptions!$I$40*IF(1<Assumptions!$I$41+0.5,MIN(1,Assumptions!$I$41+0.5-1)/Assumptions!$I$41,0)+(1-Assumptions!$I$40)*IF(1-Assumptions!$I$43<0,0,IF(1-Assumptions!$I$43=0,0.5/Assumptions!$I$42,IF(1-Assumptions!$I$43<Assumptions!$I$42+0.5,MIN(1,Assumptions!$I$42+0.5-(1-Assumptions!$I$43))/Assumptions!$I$42,0)))) -> 19677.273
A33: Capex of 2035 | B33: =L7 -> 200000 | L33: =B33*(Assumptions!$I$40*0.5/Assumptions!$I$41+(1-Assumptions!$I$40)*IF(0-Assumptions!$I$43<0,0,IF(0-Assumptions!$I$43=0,0.5/Assumptions!$I$42,IF(0-Assumptions!$I$43<Assumptions!$I$42+0.5,MIN(1,Assumptions!$I$42+0.5-(0-Assumptions!$I$43))/Assumptions!$I$42,0)))) -> 9090.9091
A34: D&A from the vintage method | C34: =SUM(C15:C33) -> 27897.595 | D34: =SUM(D15:D33) -> 43679.382 | E34: =SUM(E15:E33) -> 62498.382 | F34: =SUM(F15:F33) -> 82372.564 | G34: =SUM(G15:G33) -> 100583.93 | H34: =SUM(H15:H33) -> 114964.38 | I34: =SUM(I15:I33) -> 122805.29 | J34: =SUM(J15:J33) -> 125459.84 | ... L34: =SUM(L15:L33) -> 131696.2
A35: 2026E: vintage method less the D&A used (memo) | C35: =C34-C9 -> 188.59545
A37: Working capital
A38: Accounts receivable | B38: =BS_Hist!H11 -> 19769 | C38: =Revenue_Build!C17*Assumptions!$I$46 -> 25203.542 | D38: =Revenue_Build!D17*Assumptions!$I$46 -> 30000.508 | E38: =Revenue_Build!E17*Assumptions!$I$46 -> 35041.36 | F38: =Revenue_Build!F17*Assumptions!$I$46 -> 40172.777 | G38: =Revenue_Build!G17*Assumptions!$I$46 -> 45188.494 | H38: =Revenue_Build!H17*Assumptions!$I$46 -> 49856.362 | I38: =Revenue_Build!I17*Assumptions!$I$46 -> 54468.281 | J38: =Revenue_Build!J17*Assumptions!$I$46 -> 58656.726 | ... L38: =Revenue_Build!L17*Assumptions!$I$46 -> 66041.371
A39: Prepaid expenses and other current assets | B39: =BS_Hist!H12 -> 7361 | C39: =Revenue_Build!C17*Assumptions!$I$47 -> 9384.5553 | D39: =Revenue_Build!D17*Assumptions!$I$47 -> 11170.709 | E39: =Revenue_Build!E17*Assumptions!$I$47 -> 13047.673 | F39: =Revenue_Build!F17*Assumptions!$I$47 -> 14958.36 | G39: =Revenue_Build!G17*Assumptions!$I$47 -> 16825.965 | H39: =Revenue_Build!H17*Assumptions!$I$47 -> 18564.049 | I39: =Revenue_Build!I17*Assumptions!$I$47 -> 20281.3 | J39: =Revenue_Build!J17*Assumptions!$I$47 -> 21840.87 | ... L39: =Revenue_Build!L17*Assumptions!$I$47 -> 24590.547
A40: Accounts payable | B40: =BS_Hist!H26 -> 8894 | C40: =Revenue_Build!C17*Assumptions!$I$48 -> 11338.98 | D40: =Revenue_Build!D17*Assumptions!$I$48 -> 13497.118 | E40: =Revenue_Build!E17*Assumptions!$I$48 -> 15764.978 | F40: =Revenue_Build!F17*Assumptions!$I$48 -> 18073.584 | G40: =Revenue_Build!G17*Assumptions!$I$48 -> 20330.136 | H40: =Revenue_Build!H17*Assumptions!$I$48 -> 22430.193 | I40: =Revenue_Build!I17*Assumptions!$I$48 -> 24505.078 | J40: =Revenue_Build!J17*Assumptions!$I$48 -> 26389.444 | ... L40: =Revenue_Build!L17*Assumptions!$I$48 -> 29711.769
A41: Accrued expenses and other current liabilities | B41: =BS_Hist!H29 -> 30729 | C41: =Revenue_Build!C17*Assumptions!$I$49 -> 39176.47 | D41: =Revenue_Build!D17*Assumptions!$I$49 -> 46632.89 | E41: =Revenue_Build!E17*Assumptions!$I$49 -> 54468.408 | F41: =Revenue_Build!F17*Assumptions!$I$49 -> 62444.7 | G41: =Revenue_Build!G17*Assumptions!$I$49 -> 70241.146 | H41: =Revenue_Build!H17*Assumptions!$I$49 -> 77496.897 | I41: =Revenue_Build!I17*Assumptions!$I$49 -> 84665.68 | J41: =Revenue_Build!J17*Assumptions!$I$49 -> 91176.211 | ... L41: =Revenue_Build!L17*Assumptions!$I$49 -> 102654.93
A42: Net operating working capital | B42: =B38+B39-B40-B41 -> -12493 | C42: =C38+C39-C40-C41 -> -15927.353 | D42: =D38+D39-D40-D41 -> -18958.791 | E42: =E38+E39-E40-E41 -> -22144.353 | F42: =F38+F39-F40-F41 -> -25387.147 | G42: =G38+G39-G40-G41 -> -28556.824 | H42: =H38+H39-H40-H41 -> -31506.679 | I42: =I38+I39-I40-I41 -> -34421.177 | ... L42: =L38+L39-L40-L41 -> -41734.779
A43: Cash flow from working capital (negative = cash used) | C43: =-(C42-B42) -> 3434.3535 | D43: =-(D42-C42) -> 3031.4378 | E43: =-(E42-D42) -> 3185.5617 | F43: =-(F42-E42) -> 3242.794 | G43: =-(G42-F42) -> 3169.6769 | H43: =-(H42-G42) -> 2949.8549 | I43: =-(I42-H42) -> 2914.4978 | J43: =-(J42-I42) -> 2646.8831 | ... L43: =-(L42-K42) -> 2207.1939
A45: Debt (carrying value)
A46: Debt: beginning | C46: =B49 -> 58744 | D46: =C49 -> 83654 | E46: =D49 -> 154552.88 | F46: =E49 -> 220502.07 | G46: =F49 -> 256503.44 | H46: =G49 -> 265863.28 | I46: =H49 -> 266592.79 | J46: =I49 -> 266592.79 | ... L46: =K49 -> 266592.79
A47: New debt issued | C47: =Interim_Bridge!D32 -> 24910 | D47: =MAX(0,D59-D60) -> 73648.878 | E47: =MAX(0,E59-E60) -> 67449.197 | F47: =MAX(0,F59-F60) -> 37001.369 | G47: =MAX(0,G59-G60) -> 14359.835 | H47: =MAX(0,H59-H60) -> 729.51321 | I47: =MAX(0,I59-I60) -> 0 | J47: =MAX(0,J59-J60) -> 0 | K47: =MAX(0,K59-K60) -> 0 | L47: =MAX(0,L59-L60) -> 0 | N47: 2026E: actual 9M issue (USD 25 bn May 2026 notes, net) + Q4 input. Later: borrow only to restore the minimum cash.
A48: Scheduled repayments | C48: 0 | D48: 2750 | E48: 1500 | F48: 1000 | G48: 5000 | H48: 0 | I48: 0 | J48: 0 | K48: 0 | L48: 0 | N48: 10-Q Note 9 principal by year: 2027 2,750; 2028 1,500; 2029 1,000; 2030 5,000; later maturities (73,750) are assumed refinanced.
A49: Debt: ending | B49: =BS_Hist!H34 -> 58744 | C49: =C46+C47-C48 -> 83654 | D49: =D46+D47-D48 -> 154552.88 | E49: =E46+E47-E48 -> 220502.07 | F49: =F46+F47-F48 -> 256503.44 | G49: =G46+G47-G48 -> 265863.28 | H49: =H46+H47-H48 -> 266592.79 | I49: =I46+I47-I48 -> 266592.79 | J49: =J46+J47-J48 -> 266592.79 | ... L49: =L46+L47-L48 -> 266592.79
A50: Interest expense | C50: =Interim_Bridge!D20 -> 3170 | D50: =D46*Assumptions!$I$32 -> 4015.392 | E50: =E46*Assumptions!$I$32 -> 7418.5381 | F50: =F46*Assumptions!$I$32 -> 10584.1 | G50: =G46*Assumptions!$I$32 -> 12312.165 | H50: =H46*Assumptions!$I$32 -> 12761.437 | I50: =I46*Assumptions!$I$32 -> 12796.454 | J50: =J46*Assumptions!$I$32 -> 12796.454 | K50: =K46*Assumptions!$I$32 -> 12796.454 | L50: =L46*Assumptions!$I$32 -> 12796.454
A52: Cash and marketable securities
A53: Cash and marketable securities: beginning | C53: =Forecast_3Stmt!B35 -> 81592 | D53: =Forecast_3Stmt!C35 -> 76218.033 | E53: =Forecast_3Stmt!D35 -> 76244.145 | F53: =Forecast_3Stmt!E35 -> 89055.112 | G53: =Forecast_3Stmt!F35 -> 102096.24 | H53: =Forecast_3Stmt!G35 -> 114843.33 | I53: =Forecast_3Stmt!H35 -> 126706.38 | J53: =Forecast_3Stmt!I35 -> 144308.75 | ... L53: =Forecast_3Stmt!K35 -> 193182.16
A54: Free cash flow (operating cash flow less capex) | C54: =Forecast_3Stmt!C59+Forecast_3Stmt!C60 -> -7845.9665 | D54: =Forecast_3Stmt!D59+Forecast_3Stmt!D60 -> -41199.109 | E54: =Forecast_3Stmt!E59+Forecast_3Stmt!E60 -> -19063.128 | F54: =Forecast_3Stmt!F59+Forecast_3Stmt!F60 -> 15612.492 | G54: =Forecast_3Stmt!G59+Forecast_3Stmt!G60 -> 56551.942 | H54: =Forecast_3Stmt!H59+Forecast_3Stmt!H60 -> 91683.949 | I54: =Forecast_3Stmt!I59+Forecast_3Stmt!I60 -> 121618.14 | J54: =Forecast_3Stmt!J59+Forecast_3Stmt!J60 -> 143554.69 | ... L54: =Forecast_3Stmt!L59+Forecast_3Stmt!L60 -> 185409.24
A55: Dividend per share (USD) | C55: =Assumptions!$I$39 -> 2.1 | D55: =C55*(1+Assumptions!J106) -> 2.205 | E55: =D55*(1+Assumptions!K106) -> 2.31525 | F55: =E55*(1+Assumptions!L106) -> 2.4310125 | G55: =F55*(1+Assumptions!M106) -> 2.5525631 | H55: =G55*(1+Assumptions!N106) -> 2.6801913 | I55: =H55*(1+Assumptions!O106) -> 2.8142008 | J55: =I55*(1+Assumptions!P106) -> 2.9549109 | K55: =J55*(1+Assumptions!Q106) -> 3.1026564 | L55: =K55*(1+Assumptions!R106) -> 3.2577893
A56: Dividends | C56: =Interim_Bridge!D29 -> 5420 | D56: =D55*D65 -> 5656.7511 | E56: =E55*E65 -> 6022.7429 | F56: =F55*F65 -> 6412.4144 | G56: =G55*G65 -> 6827.2976 | H56: =H55*H65 -> 7237.276 | I56: =I55*I65 -> 7604.0748 | J56: =J55*J65 -> 7940.1148 | K56: =K55*K65 -> 8262.9362 | L56: =L55*L65 -> 8573.8882
A57: Taxes paid on RSU net share settlement | C57: =Interim_Bridge!D31 -> 17018 | D57: =Forecast_3Stmt!D32*Assumptions!$I$37 -> 24016.906 | E57: =Forecast_3Stmt!E32*Assumptions!$I$37 -> 28052.36 | F57: =Forecast_3Stmt!F32*Assumptions!$I$37 -> 32160.316 | G57: =Forecast_3Stmt!G32*Assumptions!$I$37 -> 36175.648 | H57: =Forecast_3Stmt!H32*Assumptions!$I$37 -> 39912.51 | I57: =Forecast_3Stmt!I32*Assumptions!$I$37 -> 43604.581 | J57: =Forecast_3Stmt!J32*Assumptions!$I$37 -> 46957.64 | K57: =Forecast_3Stmt!K32*Assumptions!$I$37 -> 50073.356 | L57: =Forecast_3Stmt!L32*Assumptions!$I$37 -> 52869.418
A58: Share buybacks | C58: =Interim_Bridge!D30 -> 0 | D58: =MAX(0,D54-D56-D57)*Assumptions!J111 -> 0 | E58: =MAX(0,E54-E56-E57)*Assumptions!K111 -> 0 | F58: =MAX(0,F54-F56-F57)*Assumptions!L111 -> 0 | G58: =MAX(0,G54-G56-G57)*Assumptions!M111 -> 10161.748 | H58: =MAX(0,H54-H56-H57)*Assumptions!N111 -> 33400.623 | I58: =MAX(0,I54-I56-I57)*Assumptions!O111 -> 52807.112 | J58: =MAX(0,J54-J56-J57)*Assumptions!P111 -> 66492.7 | K58: =MAX(0,K54-K56-K57)*Assumptions!Q111 -> 80127.54 | L58: =MAX(0,L54-L56-L57)*Assumptions!R111 -> 92974.449
A59: Minimum cash and marketable securities | C59: =Revenue_Build!C17*Assumptions!$I$33 -> 64053 | D59: =Revenue_Build!D17*Assumptions!$I$33 -> 76244.145 | E59: =Revenue_Build!E17*Assumptions!$I$33 -> 89055.112 | F59: =Revenue_Build!F17*Assumptions!$I$33 -> 102096.24 | G59: =Revenue_Build!G17*Assumptions!$I$33 -> 114843.33 | H59: =Revenue_Build!H17*Assumptions!$I$33 -> 126706.38 | I59: =Revenue_Build!I17*Assumptions!$I$33 -> 138427.24 | J59: =Revenue_Build!J17*Assumptions!$I$33 -> 149071.87 | ... L59: =Revenue_Build!L17*Assumptions!$I$33 -> 167839.42
A60: Cash before new debt | C60: =C53+C54-C56-C57-C58-C48 -> 51308.033 | D60: =D53+D54-D56-D57-D58-D48 -> 2595.2678 | E60: =E53+E54-E56-E57-E58-E48 -> 21605.915 | F60: =F53+F54-F56-F57-F58-F48 -> 65094.873 | G60: =G53+G54-G56-G57-G58-G48 -> 100483.49 | H60: =H53+H54-H56-H57-H58-H48 -> 125976.87 | I60: =I53+I54-I56-I57-I58-I48 -> 144308.75 | J60: =J53+J54-J56-J57-J58-J48 -> 166472.98 | ... L60: =L53+L54-L56-L57-L58-L48 -> 224173.65
A61: Cash and marketable securities: ending | C61: =C60+C47 -> 76218.033 | D61: =D60+D47 -> 76244.145 | E61: =E60+E47 -> 89055.112 | F61: =F60+F47 -> 102096.24 | G61: =G60+G47 -> 114843.33 | H61: =H60+H47 -> 126706.38 | I61: =I60+I47 -> 144308.75 | J61: =J60+J47 -> 166472.98 | ... L61: =L60+L47 -> 224173.65
A63: Equity and shares
A64: Buyback share price (USD) | C64: =Market_Package!B8*(1+Assumptions!$I$36)^0 -> 630.56 | D64: =Market_Package!B8*(1+Assumptions!$I$36)^1 -> 681.0048 | E64: =Market_Package!B8*(1+Assumptions!$I$36)^2 -> 735.48518 | F64: =Market_Package!B8*(1+Assumptions!$I$36)^3 -> 794.324 | G64: =Market_Package!B8*(1+Assumptions!$I$36)^4 -> 857.86992 | H64: =Market_Package!B8*(1+Assumptions!$I$36)^5 -> 926.49951 | I64: =Market_Package!B8*(1+Assumptions!$I$36)^6 -> 1000.6195 | J64: =Market_Package!B8*(1+Assumptions!$I$36)^7 -> 1080.669 | K64: =Market_Package!B8*(1+Assumptions!$I$36)^8 -> 1167.1226 | L64: =Market_Package!B8*(1+Assumptions!$I$36)^9 -> 1260.4924
A65: Class A + B shares: beginning | C65: =B68 -> 2530 | D65: =C68 -> 2565.42 | E65: =D68 -> 2601.3359 | F65: =E68 -> 2637.7546 | G65: =F68 -> 2674.6831 | H65: =G68 -> 2700.2834 | I65: =H68 -> 2702.037 | J65: =I68 -> 2687.0911 | ... L65: =K68 -> 2631.8118
A66: Shares issued to employees (gross) | C66: =C65*Assumptions!$I$34 -> 35.42 | D66: =D65*Assumptions!$I$34 -> 35.91588 | E66: =E65*Assumptions!$I$34 -> 36.418702 | F66: =F65*Assumptions!$I$34 -> 36.928564 | G66: =G65*Assumptions!$I$34 -> 37.445564 | H66: =H65*Assumptions!$I$34 -> 37.803967 | I66: =I65*Assumptions!$I$34 -> 37.828518 | J66: =J65*Assumptions!$I$34 -> 37.619276 | ... L66: =L65*Assumptions!$I$34 -> 36.845365
A67: Shares bought back | C67: =C58/C64 -> 0 | D67: =D58/D64 -> 0 | E67: =E58/E64 -> 0 | F67: =F58/F64 -> 0 | G67: =G58/G64 -> 11.845325 | H67: =H58/H64 -> 36.05034 | I67: =I58/I64 -> 52.77442 | J67: =J58/J64 -> 61.5292 | ... L67: =L58/L64 -> 73.760423
A68: Class A + B shares: ending | B68: =BS_Hist!H56+BS_Hist!H59 -> 2530 | C68: =C65+C66-C67 -> 2565.42 | D68: =D65+D66-D67 -> 2601.3359 | E68: =E65+E66-E67 -> 2637.7546 | F68: =F65+F66-F67 -> 2674.6831 | G68: =G65+G66-G67 -> 2700.2834 | H68: =H65+H66-H67 -> 2702.037 | I68: =I65+I66-I67 -> 2687.0911 | J68: =J65+J66-J67 -> 2663.1812 | ... L68: =L65+L66-L67 -> 2594.8967
A69: Diluted shares: average | C69: =(C65+C68)/2+Assumptions!$I$35 -> 2568.71 | D69: =(D65+D68)/2+Assumptions!$I$35 -> 2604.3779 | E69: =(E65+E68)/2+Assumptions!$I$35 -> 2640.5452 | F69: =(F65+F68)/2+Assumptions!$I$35 -> 2677.2189 | G69: =(G65+G68)/2+Assumptions!$I$35 -> 2708.4833 | H69: =(H65+H68)/2+Assumptions!$I$35 -> 2722.1602 | I69: =(I65+I68)/2+Assumptions!$I$35 -> 2715.5641 | J69: =(J65+J68)/2+Assumptions!$I$35 -> 2696.1361 | ... L69: =(L65+L68)/2+Assumptions!$I$35 -> 2634.3543
A70: Stockholders' equity: beginning | C70: =B74 -> 217243 | D70: =C74 -> 295815.68 | E70: =D74 -> 377232.09 | F70: =E74 -> 463409.92 | G70: =F74 -> 554834.32 | H70: =G74 -> 644467.97 | I70: =H74 -> 722687.27 | J70: =I74 -> 799569.86 | ... L70: =K74 -> 974803.55
A71: Plus net income | C71: =Forecast_3Stmt!C28 -> 72957.68 | D71: =Forecast_3Stmt!D28 -> 79067.531 | E71: =Forecast_3Stmt!E28 -> 82849.782 | F71: =Forecast_3Stmt!F28 -> 87116.712 | G71: =Forecast_3Stmt!G28 -> 94564.142 | H71: =Forecast_3Stmt!H28 -> 105553.03 | I71: =Forecast_3Stmt!I28 -> 122758.91 | J71: =Forecast_3Stmt!J28 -> 142837.78 | ... L71: =Forecast_3Stmt!L28 -> 181013.29
A72: Plus share-based compensation | C72: =Forecast_3Stmt!C32 -> 28053 | D72: =Forecast_3Stmt!D32 -> 32022.541 | E72: =Forecast_3Stmt!E32 -> 37403.147 | F72: =Forecast_3Stmt!F32 -> 42880.421 | G72: =Forecast_3Stmt!G32 -> 48234.197 | H72: =Forecast_3Stmt!H32 -> 53216.679 | I72: =Forecast_3Stmt!I32 -> 58139.442 | J72: =Forecast_3Stmt!J32 -> 62610.187 | ... L72: =Forecast_3Stmt!L32 -> 70492.558
A73: Less RSU taxes, buybacks and dividends | C73: =-(C57+C58+C56) -> -22438 | D73: =-(D57+D58+D56) -> -29673.657 | E73: =-(E57+E58+E56) -> -34075.103 | F73: =-(F57+F58+F56) -> -38572.73 | G73: =-(G57+G58+G56) -> -53164.693 | H73: =-(H57+H58+H56) -> -80550.408 | I73: =-(I57+I58+I56) -> -104015.77 | J73: =-(J57+J58+J56) -> -121390.46 | ... L73: =-(L57+L58+L56) -> -154417.76
A74: Stockholders' equity: ending | B74: =BS_Hist!H47 -> 217243 | C74: =C70+C71+C72+C73 -> 295815.68 | D74: =D70+D71+D72+D73 -> 377232.09 | E74: =E70+E71+E72+E73 -> 463409.92 | F74: =F70+F71+F72+F73 -> 554834.32 | G74: =G70+G71+G72+G73 -> 644467.97 | H74: =H70+H71+H72+H73 -> 722687.27 | I74: =I70+I71+I72+I73 -> 799569.86 | J74: =J70+J71+J72+J73 -> 883627.37 | ... L74: =L70+L71+L72+L73 -> 1071891.6
A76: Checks (each should be zero)
A77: Cash never falls below the minimum | D77: =ROUND(MIN(0,D61-D59),2) -> 0 | E77: =ROUND(MIN(0,E61-E59),2) -> 0 | F77: =ROUND(MIN(0,F61-F59),2) -> 0 | G77: =ROUND(MIN(0,G61-G59),2) -> 0 | H77: =ROUND(MIN(0,H61-H59),2) -> 0 | I77: =ROUND(MIN(0,I61-I59),2) -> 0 | J77: =ROUND(MIN(0,J61-J59),2) -> 0 | K77: =ROUND(MIN(0,K61-K59),2) -> 0 | L77: =ROUND(MIN(0,L61-L59),2) -> 0
A78: Debt is never negative | C78: =ROUND(MIN(0,C49),2) -> 0 | D78: =ROUND(MIN(0,D49),2) -> 0 | E78: =ROUND(MIN(0,E49),2) -> 0 | F78: =ROUND(MIN(0,F49),2) -> 0 | G78: =ROUND(MIN(0,G49),2) -> 0 | H78: =ROUND(MIN(0,H49),2) -> 0 | I78: =ROUND(MIN(0,I49),2) -> 0 | J78: =ROUND(MIN(0,J49),2) -> 0 | ... L78: =ROUND(MIN(0,L49),2) -> 0
A79: Property and equipment roll-forward: ending = beginning + capex - D&A | C79: =ROUND(C12-B12-C7+C9,2) -> 0 | D79: =ROUND(D12-C12-D7+D9,2) -> 0 | E79: =ROUND(E12-D12-E7+E9,2) -> 0 | F79: =ROUND(F12-E12-F7+F9,2) -> 0 | G79: =ROUND(G12-F12-G7+G9,2) -> 0 | H79: =ROUND(H12-G12-H7+H9,2) -> 0 | I79: =ROUND(I12-H12-I7+I9,2) -> 0 | J79: =ROUND(J12-I12-J7+J9,2) -> 0 | ... L79: =ROUND(L12-K12-L7+L9,2) -> 0

Sheet Forecast_3Stmt
A1: Meta Platforms, Inc. | Integrated forecast: income statement, balance sheet, cash flow
A2: 2025A links to the audited statements; 2026E = 9M actual + Q4 estimate (Interim_Bridge); 2027E-2035E from the drivers. Cash includes marketable securities.
B3: Actual | C3: Forecast
A4: Fiscal year ends 31 December | B4: 2025A | C4: 2026E | D4: 2027E | E4: 2028E | F4: 2029E | G4: 2030E | H4: 2031E | I4: 2032E | J4: 2033E | K4: 2034E | L4: 2035E | M4: Comentarios FG | N4: Source / derivation
A6: Income statement
A7: Advertising | B7: =Revenue_Build!B13 -> 196175 | C7: =Revenue_Build!C13 -> 249714 | D7: =Revenue_Build!D13 -> 296660.23 | E7: =Revenue_Build!E13 -> 345994.83 | F7: =Revenue_Build!F13 -> 396094.88 | G7: =Revenue_Build!G13 -> 445012.6 | H7: =Revenue_Build!H13 -> 490581.89 | I7: =Revenue_Build!I13 -> 535715.42 | ... L7: =Revenue_Build!L13 -> 649002.7
A8: Other revenue | B8: =Revenue_Build!B14 -> 2584 | C8: =Revenue_Build!C14 -> 4267 | D8: =Revenue_Build!D14 -> 5973.8 | E8: =Revenue_Build!E14 -> 7765.94 | F8: =Revenue_Build!F14 -> 9707.425 | G8: =Revenue_Build!G14 -> 11648.91 | H8: =Revenue_Build!H14 -> 13396.246 | I8: =Revenue_Build!I14 -> 15003.796 | ... L8: =Revenue_Build!L14 -> 18893.98
A9: Reality Labs | B9: =Revenue_Build!B16 -> 2207 | C9: =Revenue_Build!C16 -> 2231 | D9: =Revenue_Build!D16 -> 2342.55 | E9: =Revenue_Build!E16 -> 2459.6775 | F9: =Revenue_Build!F16 -> 2582.6614 | G9: =Revenue_Build!G16 -> 2711.7944 | H9: =Revenue_Build!H16 -> 2847.3842 | I9: =Revenue_Build!I16 -> 2989.7534 | ... L9: =Revenue_Build!L16 -> 3461.0132
A10: Revenue | B10: =B7+B8+B9 -> 200966 | C10: =C7+C8+C9 -> 256212 | D10: =D7+D8+D9 -> 304976.58 | E10: =E7+E8+E9 -> 356220.45 | F10: =F7+F8+F9 -> 408384.97 | G10: =G7+G8+G9 -> 459373.3 | H10: =H7+H8+H9 -> 506825.52 | I10: =I7+I8+I9 -> 553708.97 | ... L10: =L7+L8+L9 -> 671357.69
A11: Revenue growth | C11: =C10/B10-1 -> 0.27490222 | D11: =D10/C10-1 -> 0.19032903 | E11: =E10/D10-1 -> 0.16802557 | F11: =F10/E10-1 -> 0.14643887 | G11: =G10/F10-1 -> 0.12485361 | H11: =H10/G10-1 -> 0.10329772 | I11: =I10/H10-1 -> 0.092504128 | J11: =J10/I10-1 -> 0.07689694 | ... L11: =L10/K10-1 -> 0.055839331
A12: Cash costs excluding D&A and one-off legal charges | B12: =IS_Hist!H13-CF_Hist!H10 -> 99074 | C12: =Interim_Bridge!D12-Interim_Bridge!D17-Interim_Bridge!D13 -> 137401 | D12: =D10*Assumptions!J81 -> 164687.35 | E12: =E10*Assumptions!K81 -> 189153.06 | F12: =F10*Assumptions!L81 -> 213585.34 | G12: =G10*Assumptions!M81 -> 236117.88 | H12: =H10*Assumptions!N81 -> 255946.89 | I12: =I10*Assumptions!O81 -> 274639.65 | J12: =J10*Assumptions!P81 -> 290988.3 | K12: =K10*Assumptions!Q81 -> 304573.17 | L12: =L10*Assumptions!R81 -> 315538.11 | N12: Includes share-based compensation, third-party cloud and AI token costs.
A13: % of revenue | B13: =B12/B10 -> 0.49298886 | C13: =C12/C10 -> 0.53627855 | D13: =D12/D10 -> 0.54 | E13: =E12/E10 -> 0.531 | F13: =F12/F10 -> 0.523 | G13: =G12/G10 -> 0.514 | H13: =H12/H10 -> 0.505 | I13: =I12/I10 -> 0.496 | ... L13: =L12/L10 -> 0.47
A14: Legal charges outside the run-rate | B14: 0 | C14: =Interim_Bridge!D13 -> 11890 | D14: =Assumptions!J86 -> 0 | E14: =Assumptions!K86 -> 0 | F14: =Assumptions!L86 -> 0 | G14: =Assumptions!M86 -> 0 | H14: =Assumptions!N86 -> 0 | I14: =Assumptions!O86 -> 0 | J14: =Assumptions!P86 -> 0 | K14: =Assumptions!Q86 -> 0 | L14: =Assumptions!R86 -> 0
A15: Depreciation and amortization | B15: =Schedules!B9 -> 18616 | C15: =Schedules!C9 -> 27709 | D15: =Schedules!D9 -> 43679.382 | E15: =Schedules!E9 -> 62498.382 | F15: =Schedules!F9 -> 82372.564 | G15: =Schedules!G9 -> 100583.93 | H15: =Schedules!H9 -> 114964.38 | I15: =Schedules!I9 -> 122805.29 | ... L15: =Schedules!L9 -> 131696.2
A16: Total costs and expenses | B16: =B12+B14+B15 -> 117690 | C16: =C12+C14+C15 -> 177000 | D16: =D12+D14+D15 -> 208366.74 | E16: =E12+E14+E15 -> 251651.44 | F16: =F12+F14+F15 -> 295957.9 | G16: =G12+G14+G15 -> 336701.8 | H16: =H12+H14+H15 -> 370911.27 | I16: =I12+I14+I15 -> 397444.94 | ... L16: =L12+L14+L15 -> 447234.31
A17: Income from operations | B17: =B10-B16 -> 83276 | C17: =C10-C16 -> 79212 | D17: =D10-D16 -> 96609.846 | E17: =E10-E16 -> 104569.01 | F17: =F10-F16 -> 112427.07 | G17: =G10-G16 -> 122671.5 | H17: =H10-H16 -> 135914.25 | I17: =I10-I16 -> 156264.03 | ... L17: =L10-L16 -> 224123.38
A18: Operating margin | B18: =B17/B10 -> 0.41437855 | C18: =C17/C10 -> 0.30916585 | D18: =D17/D10 -> 0.31677792 | E18: =E17/E10 -> 0.29355139 | F18: =F17/F10 -> 0.27529678 | G18: =G17/G10 -> 0.26704098 | H18: =H17/H10 -> 0.26816773 | I18: =I17/I10 -> 0.28221329 | ... L18: =L17/L10 -> 0.33383602
A19: memo: Reality Labs income (loss) from operations | B19: =Interim_Bridge!G15 -> -19193 | C19: =Interim_Bridge!D15 -> -18500 | D19: =Assumptions!J96 -> -15000 | E19: =Assumptions!K96 -> -13500 | F19: =Assumptions!L96 -> -12000 | G19: =Assumptions!M96 -> -10500 | H19: =Assumptions!N96 -> -9000 | I19: =Assumptions!O96 -> -7500 | J19: =Assumptions!P96 -> -6000 | K19: =Assumptions!Q96 -> -5000 | L19: =Assumptions!R96 -> -4000
A20: memo: Family of Apps income from operations | B20: =B17-B19 -> 102469 | C20: =C17-C19 -> 97712 | D20: =D17-D19 -> 111609.85 | E20: =E17-E19 -> 118069.01 | F20: =F17-F19 -> 124427.07 | G20: =G17-G19 -> 133171.5 | H20: =H17-H19 -> 144914.25 | I20: =I17-I19 -> 163764.03 | ... L20: =L17-L19 -> 228123.38
A21: memo: EBITDA | B21: =B17+B15 -> 101892 | C21: =C17+C15 -> 106921 | D21: =D17+D15 -> 140289.23 | E21: =E17+E15 -> 167067.39 | F21: =F17+F15 -> 194799.63 | G21: =G17+G15 -> 223255.42 | H21: =H17+H15 -> 250878.63 | I21: =I17+I15 -> 279069.32 | ... L21: =L17+L15 -> 355819.58
A22: Interest income | D22: =C35*Assumptions!$I$31 -> 2667.6312 | E22: =D35*Assumptions!$I$31 -> 2668.5451 | F22: =E35*Assumptions!$I$31 -> 3116.9289 | G22: =F35*Assumptions!$I$31 -> 3573.3685 | H22: =G35*Assumptions!$I$31 -> 4019.5164 | I22: =H35*Assumptions!$I$31 -> 4434.7233 | J22: =I35*Assumptions!$I$31 -> 5050.8063 | K22: =J35*Assumptions!$I$31 -> 5826.5544 | L22: =K35*Assumptions!$I$31 -> 6761.3757
A23: Interest expense | C23: =Schedules!C50 -> 3170 | D23: =Schedules!D50 -> 4015.392 | E23: =Schedules!E50 -> 7418.5381 | F23: =Schedules!F50 -> 10584.1 | G23: =Schedules!G50 -> 12312.165 | H23: =Schedules!H50 -> 12761.437 | I23: =Schedules!I50 -> 12796.454 | J23: =Schedules!J50 -> 12796.454 | ... L23: =Schedules!L50 -> 12796.454 | N23: 2026E is a memo inside the bridge line below.
A24: Interest and other income, net | B24: =IS_Hist!H17 -> 2656 | C24: =Interim_Bridge!D19 -> -1326 | D24: =D22-D23 -> -1347.7608 | E24: =E22-E23 -> -4749.993 | F24: =F22-F23 -> -7467.1707 | G24: =G22-G23 -> -8738.7968 | H24: =H22-H23 -> -8741.9209 | I24: =I22-I23 -> -8361.7307 | J24: =J22-J23 -> -7745.6477 | K24: =K22-K23 -> -6969.8995 | L24: =L22-L23 -> -6035.0782
A25: Income before provision for income taxes | B25: =B17+B24 -> 85932 | C25: =C17+C24 -> 77886 | D25: =D17+D24 -> 95262.085 | E25: =E17+E24 -> 99819.014 | F25: =F17+F24 -> 104959.89 | G25: =G17+G24 -> 113932.7 | H25: =H17+H24 -> 127172.33 | I25: =I17+I24 -> 147902.3 | ... L25: =L17+L24 -> 218088.3
A26: Provision for income taxes | B26: =IS_Hist!H20 -> 25474 | C26: =Interim_Bridge!D22 -> 4928.32 | D26: =D25*Assumptions!J101 -> 16194.554 | E26: =E25*Assumptions!K101 -> 16969.232 | F26: =F25*Assumptions!L101 -> 17843.182 | G26: =G25*Assumptions!M101 -> 19368.559 | H26: =H25*Assumptions!N101 -> 21619.296 | I26: =I25*Assumptions!O101 -> 25143.391 | J26: =J25*Assumptions!P101 -> 29255.931 | K26: =K25*Assumptions!Q101 -> 33360.05 | L26: =L25*Assumptions!R101 -> 37075.011
A27: Effective tax rate | B27: =B26/B25 -> 0.2964437 | C27: =C26/C25 -> 0.06327607 | D27: =D26/D25 -> 0.17 | E27: =E26/E25 -> 0.17 | F27: =F26/F25 -> 0.17 | G27: =G26/G25 -> 0.17 | H27: =H26/H25 -> 0.17 | I27: =I26/I25 -> 0.17 | ... L27: =L26/L25 -> 0.17
A28: Net income | B28: =B25-B26 -> 60458 | C28: =C25-C26 -> 72957.68 | D28: =D25-D26 -> 79067.531 | E28: =E25-E26 -> 82849.782 | F28: =F25-F26 -> 87116.712 | G28: =G25-G26 -> 94564.142 | H28: =H25-H26 -> 105553.03 | I28: =I25-I26 -> 122758.91 | ... L28: =L25-L26 -> 181013.29
A29: Diluted shares (average, m) | B29: =IS_Hist!H32 -> 2574 | C29: =Schedules!C69 -> 2568.71 | D29: =Schedules!D69 -> 2604.3779 | E29: =Schedules!E69 -> 2640.5452 | F29: =Schedules!F69 -> 2677.2189 | G29: =Schedules!G69 -> 2708.4833 | H29: =Schedules!H69 -> 2722.1602 | I29: =Schedules!I69 -> 2715.5641 | J29: =Schedules!J69 -> 2696.1361 | ... L29: =Schedules!L69 -> 2634.3543
A30: Diluted earnings per share (USD) | B30: =B28/B29 -> 23.487956 | C30: =C28/C29 -> 28.402459 | D30: =D28/D29 -> 30.359469 | E30: =E28/E29 -> 31.376013 | F30: =F28/F29 -> 32.540004 | G30: =G28/G29 -> 34.914058 | H30: =H28/H29 -> 38.775467 | I30: =I28/I29 -> 45.205676 | ... L30: =L28/L29 -> 68.712583
A31: Dividend per share (USD) | C31: =Schedules!C55 -> 2.1 | D31: =Schedules!D55 -> 2.205 | E31: =Schedules!E55 -> 2.31525 | F31: =Schedules!F55 -> 2.4310125 | G31: =Schedules!G55 -> 2.5525631 | H31: =Schedules!H55 -> 2.6801913 | I31: =Schedules!I55 -> 2.8142008 | J31: =Schedules!J55 -> 2.9549109 | ... L31: =Schedules!L55 -> 3.2577893
A32: Share-based compensation (memo) | B32: =CF_Hist!H11 -> 20427 | C32: =Interim_Bridge!D27 -> 28053 | D32: =D10*Assumptions!$I$38 -> 32022.541 | E32: =E10*Assumptions!$I$38 -> 37403.147 | F32: =F10*Assumptions!$I$38 -> 42880.421 | G32: =G10*Assumptions!$I$38 -> 48234.197 | H32: =H10*Assumptions!$I$38 -> 53216.679 | I32: =I10*Assumptions!$I$38 -> 58139.442 | J32: =J10*Assumptions!$I$38 -> 62610.187 | K32: =K10*Assumptions!$I$38 -> 66764.474 | L32: =L10*Assumptions!$I$38 -> 70492.558
A34: Balance sheet (31 December)
A35: Cash and marketable securities | B35: =BS_Hist!H9+BS_Hist!H10 -> 81592 | C35: =C68 -> 76218.033 | D35: =D68 -> 76244.145 | E35: =E68 -> 89055.112 | F35: =F68 -> 102096.24 | G35: =G68 -> 114843.33 | H35: =H68 -> 126706.38 | I35: =I68 -> 144308.75 | J35: =J68 -> 166472.98 | ... L35: =L68 -> 224173.65
A36: Accounts receivable, net | B36: =BS_Hist!H11 -> 19769 | C36: =Schedules!C38 -> 25203.542 | D36: =Schedules!D38 -> 30000.508 | E36: =Schedules!E38 -> 35041.36 | F36: =Schedules!F38 -> 40172.777 | G36: =Schedules!G38 -> 45188.494 | H36: =Schedules!H38 -> 49856.362 | I36: =Schedules!I38 -> 54468.281 | J36: =Schedules!J38 -> 58656.726 | ... L36: =Schedules!L38 -> 66041.371
A37: Prepaid expenses and other current assets | B37: =BS_Hist!H12 -> 7361 | C37: =Schedules!C39 -> 9384.5553 | D37: =Schedules!D39 -> 11170.709 | E37: =Schedules!E39 -> 13047.673 | F37: =Schedules!F39 -> 14958.36 | G37: =Schedules!G39 -> 16825.965 | H37: =Schedules!H39 -> 18564.049 | I37: =Schedules!I39 -> 20281.3 | J37: =Schedules!J39 -> 21840.87 | ... L37: =Schedules!L39 -> 24590.547
A38: Non-marketable equity investments | B38: =BS_Hist!H15 -> 27524 | C38: =B38 -> 27524 | D38: =C38 -> 27524 | E38: =D38 -> 27524 | F38: =E38 -> 27524 | G38: =F38 -> 27524 | H38: =G38 -> 27524 | I38: =H38 -> 27524 | J38: =I38 -> 27524 | ... L38: =K38 -> 27524
A39: Property and equipment, net | B39: =BS_Hist!H16 -> 176400 | C39: =Schedules!C12 -> 288691 | D39: =Schedules!D12 -> 444011.62 | E39: =Schedules!E12 -> 586513.24 | F39: =Schedules!F12 -> 704140.67 | G39: =Schedules!G12 -> 793556.75 | H39: =Schedules!H12 -> 863592.36 | I39: =Schedules!I12 -> 925787.07 | J39: =Schedules!J12 -> 990327.24 | ... L39: =Schedules!L12 -> 1125557.6
A40: Operating lease right-of-use assets | B40: =BS_Hist!H17 -> 20404 | C40: =B40 -> 20404 | D40: =C40 -> 20404 | E40: =D40 -> 20404 | F40: =E40 -> 20404 | G40: =F40 -> 20404 | H40: =G40 -> 20404 | I40: =H40 -> 20404 | J40: =I40 -> 20404 | ... L40: =K40 -> 20404
A41: Goodwill and intangible assets | B41: =BS_Hist!H18+BS_Hist!H19 -> 24534 | C41: =B41 -> 24534 | D41: =C41 -> 24534 | E41: =D41 -> 24534 | F41: =E41 -> 24534 | G41: =F41 -> 24534 | H41: =G41 -> 24534 | I41: =H41 -> 24534 | J41: =I41 -> 24534 | ... L41: =K41 -> 24534
A42: Other assets | B42: =BS_Hist!H20 -> 8437 | C42: =B42 -> 8437 | D42: =C42 -> 8437 | E42: =D42 -> 8437 | F42: =E42 -> 8437 | G42: =F42 -> 8437 | H42: =G42 -> 8437 | I42: =H42 -> 8437 | J42: =I42 -> 8437 | ... L42: =K42 -> 8437
A43: Total assets | B43: =SUM(B35:B42) -> 366021 | C43: =SUM(C35:C42) -> 480396.13 | D43: =SUM(D35:D42) -> 642325.98 | E43: =SUM(E35:E42) -> 804556.38 | F43: =SUM(F35:F42) -> 942267.05 | G43: =SUM(G35:G42) -> 1051313.5 | H43: =SUM(H35:H42) -> 1139618.2 | I43: =SUM(I35:I42) -> 1225744.4 | ... L43: =SUM(L35:L42) -> 1521262.1
A44: Accounts payable | B44: =BS_Hist!H26 -> 8894 | C44: =Schedules!C40 -> 11338.98 | D44: =Schedules!D40 -> 13497.118 | E44: =Schedules!E40 -> 15764.978 | F44: =Schedules!F40 -> 18073.584 | G44: =Schedules!G40 -> 20330.136 | H44: =Schedules!H40 -> 22430.193 | I44: =Schedules!I40 -> 24505.078 | J44: =Schedules!J40 -> 26389.444 | ... L44: =Schedules!L40 -> 29711.769
A45: Accrued expenses and other current liabilities | B45: =BS_Hist!H29 -> 30729 | C45: =Schedules!C41 -> 39176.47 | D45: =Schedules!D41 -> 46632.89 | E45: =Schedules!E41 -> 54468.408 | F45: =Schedules!F41 -> 62444.7 | G45: =Schedules!G41 -> 70241.146 | H45: =Schedules!H41 -> 77496.897 | I45: =Schedules!I41 -> 84665.68 | J45: =Schedules!J41 -> 91176.211 | ... L45: =Schedules!L41 -> 102654.93
A46: Operating lease liabilities (current + non-current) | B46: =BS_Hist!H28+BS_Hist!H33 -> 25153 | C46: =B46 -> 25153 | D46: =C46 -> 25153 | E46: =D46 -> 25153 | F46: =E46 -> 25153 | G46: =F46 -> 25153 | H46: =G46 -> 25153 | I46: =H46 -> 25153 | J46: =I46 -> 25153 | ... L46: =K46 -> 25153
A47: Long-term debt (incl. current portion) | B47: =BS_Hist!H34 -> 58744 | C47: =Schedules!C49 -> 83654 | D47: =Schedules!D49 -> 154552.88 | E47: =Schedules!E49 -> 220502.07 | F47: =Schedules!F49 -> 256503.44 | G47: =Schedules!G49 -> 265863.28 | H47: =Schedules!H49 -> 266592.79 | I47: =Schedules!I49 -> 266592.79 | J47: =Schedules!J49 -> 266592.79 | ... L47: =Schedules!L49 -> 266592.79
A48: Long-term income taxes | B48: =BS_Hist!H35 -> 21005 | C48: =B48 -> 21005 | D48: =C48 -> 21005 | E48: =D48 -> 21005 | F48: =E48 -> 21005 | G48: =F48 -> 21005 | H48: =G48 -> 21005 | I48: =H48 -> 21005 | J48: =I48 -> 21005 | ... L48: =K48 -> 21005
A49: Other liabilities | B49: =BS_Hist!H36 -> 4253 | C49: =B49 -> 4253 | D49: =C49 -> 4253 | E49: =D49 -> 4253 | F49: =E49 -> 4253 | G49: =F49 -> 4253 | H49: =G49 -> 4253 | I49: =H49 -> 4253 | J49: =I49 -> 4253 | ... L49: =K49 -> 4253
A50: Total liabilities | B50: =SUM(B44:B49) -> 148778 | C50: =SUM(C44:C49) -> 184580.45 | D50: =SUM(D44:D49) -> 265093.89 | E50: =SUM(E44:E49) -> 341146.46 | F50: =SUM(F44:F49) -> 387432.73 | G50: =SUM(G44:G49) -> 406845.56 | H50: =SUM(H44:H49) -> 416930.88 | I50: =SUM(I44:I49) -> 426174.55 | ... L50: =SUM(L44:L49) -> 449370.49
A51: Total stockholders' equity | B51: =BS_Hist!H47 -> 217243 | C51: =Schedules!C74 -> 295815.68 | D51: =Schedules!D74 -> 377232.09 | E51: =Schedules!E74 -> 463409.92 | F51: =Schedules!F74 -> 554834.32 | G51: =Schedules!G74 -> 644467.97 | H51: =Schedules!H74 -> 722687.27 | I51: =Schedules!I74 -> 799569.86 | J51: =Schedules!J74 -> 883627.37 | ... L51: =Schedules!L74 -> 1071891.6
A52: Total liabilities and stockholders' equity | B52: =B50+B51 -> 366021 | C52: =C50+C51 -> 480396.13 | D52: =D50+D51 -> 642325.98 | E52: =E50+E51 -> 804556.38 | F52: =F50+F51 -> 942267.05 | G52: =G50+G51 -> 1051313.5 | H52: =H50+H51 -> 1139618.2 | I52: =I50+I51 -> 1225744.4 | ... L52: =L50+L51 -> 1521262.1
A54: Cash flow statement
A55: Net income | B55: =B28 -> 60458 | C55: =C28 -> 72957.68 | D55: =D28 -> 79067.531 | E55: =E28 -> 82849.782 | F55: =F28 -> 87116.712 | G55: =G28 -> 94564.142 | H55: =H28 -> 105553.03 | I55: =I28 -> 122758.91 | ... L55: =L28 -> 181013.29
A56: Depreciation and amortization | B56: =B15 -> 18616 | C56: =C15 -> 27709 | D56: =D15 -> 43679.382 | E56: =E15 -> 62498.382 | F56: =F15 -> 82372.564 | G56: =G15 -> 100583.93 | H56: =H15 -> 114964.38 | I56: =I15 -> 122805.29 | ... L56: =L15 -> 131696.2
A57: Share-based compensation | B57: =B32 -> 20427 | C57: =C32 -> 28053 | D57: =D32 -> 32022.541 | E57: =E32 -> 37403.147 | F57: =F32 -> 42880.421 | G57: =G32 -> 48234.197 | H57: =H32 -> 53216.679 | I57: =I32 -> 58139.442 | ... L57: =L32 -> 70492.558
A58: Working capital and other operating items | B58: =CF_Hist!H29-B55-B56-B57 -> 16299 | C58: =Schedules!C43 -> 3434.3535 | D58: =Schedules!D43 -> 3031.4378 | E58: =Schedules!E43 -> 3185.5617 | F58: =Schedules!F43 -> 3242.794 | G58: =Schedules!G43 -> 3169.6769 | H58: =Schedules!H43 -> 2949.8549 | I58: =Schedules!I43 -> 2914.4978 | J58: =Schedules!J43 -> 2646.8831 | ... L58: =Schedules!L43 -> 2207.1939 | N58: 2025A: all other operating lines of the audited statement. Forecast: working capital only.
A59: Net cash provided by operating activities | B59: =SUM(B55:B58) -> 115800 | C59: =SUM(C55:C58) -> 132154.03 | D59: =SUM(D55:D58) -> 157800.89 | E59: =SUM(E55:E58) -> 185936.87 | F59: =SUM(F55:F58) -> 215612.49 | G59: =SUM(G55:G58) -> 246551.94 | H59: =SUM(H55:H58) -> 276683.95 | I59: =SUM(I55:I58) -> 306618.14 | ... L59: =SUM(L55:L58) -> 385409.24
A60: Capital expenditures incl. finance-lease principal | B60: =CF_Hist!H32+CF_Hist!H50 -> -72215 | C60: =-Schedules!C7 -> -140000 | D60: =-Schedules!D7 -> -199000 | E60: =-Schedules!E7 -> -205000 | F60: =-Schedules!F7 -> -200000 | G60: =-Schedules!G7 -> -190000 | H60: =-Schedules!H7 -> -185000 | I60: =-Schedules!I7 -> -185000 | J60: =-Schedules!J7 -> -190000 | ... L60: =-Schedules!L7 -> -200000
A61: New debt issued | C61: =Schedules!C47 -> 24910 | D61: =Schedules!D47 -> 73648.878 | E61: =Schedules!E47 -> 67449.197 | F61: =Schedules!F47 -> 37001.369 | G61: =Schedules!G47 -> 14359.835 | H61: =Schedules!H47 -> 729.51321 | I61: =Schedules!I47 -> 0 | J61: =Schedules!J47 -> 0 | ... L61: =Schedules!L47 -> 0
A62: Debt repaid | C62: =-Schedules!C48 -> 0 | D62: =-Schedules!D48 -> -2750 | E62: =-Schedules!E48 -> -1500 | F62: =-Schedules!F48 -> -1000 | G62: =-Schedules!G48 -> -5000 | H62: =-Schedules!H48 -> 0 | I62: =-Schedules!I48 -> 0 | J62: =-Schedules!J48 -> 0 | ... L62: =-Schedules!L48 -> 0
A63: Dividends | C63: =-Schedules!C56 -> -5420 | D63: =-Schedules!D56 -> -5656.7511 | E63: =-Schedules!E56 -> -6022.7429 | F63: =-Schedules!F56 -> -6412.4144 | G63: =-Schedules!G56 -> -6827.2976 | H63: =-Schedules!H56 -> -7237.276 | I63: =-Schedules!I56 -> -7604.0748 | J63: =-Schedules!J56 -> -7940.1148 | ... L63: =-Schedules!L56 -> -8573.8882
A64: Share buybacks | C64: =-Schedules!C58 -> 0 | D64: =-Schedules!D58 -> 0 | E64: =-Schedules!E58 -> 0 | F64: =-Schedules!F58 -> 0 | G64: =-Schedules!G58 -> -10161.748 | H64: =-Schedules!H58 -> -33400.623 | I64: =-Schedules!I58 -> -52807.112 | J64: =-Schedules!J58 -> -66492.7 | ... L64: =-Schedules!L58 -> -92974.449
A65: Taxes paid on RSU net share settlement | C65: =-Schedules!C57 -> -17018 | D65: =-Schedules!D57 -> -24016.906 | E65: =-Schedules!E57 -> -28052.36 | F65: =-Schedules!F57 -> -32160.316 | G65: =-Schedules!G57 -> -36175.648 | H65: =-Schedules!H57 -> -39912.51 | I65: =-Schedules!I57 -> -43604.581 | J65: =-Schedules!J57 -> -46957.64 | ... L65: =-Schedules!L57 -> -52869.418
A66: Net change in cash and marketable securities | C66: =SUM(C59:C65) -> -5373.9665 | D66: =SUM(D59:D65) -> 26.112037 | E66: =SUM(E59:E65) -> 12810.966 | F66: =SUM(F59:F65) -> 13041.13 | G66: =SUM(G59:G65) -> 12747.084 | H66: =SUM(H59:H65) -> 11863.054 | I66: =SUM(I59:I65) -> 17602.371 | J66: =SUM(J59:J65) -> 22164.233 | ... L66: =SUM(L59:L65) -> 30991.483
A67: Cash and marketable securities: beginning | C67: =B35 -> 81592 | D67: =C35 -> 76218.033 | E67: =D35 -> 76244.145 | F67: =E35 -> 89055.112 | G67: =F35 -> 102096.24 | H67: =G35 -> 114843.33 | I67: =H35 -> 126706.38 | J67: =I35 -> 144308.75 | ... L67: =K35 -> 193182.16
A68: Cash and marketable securities: ending | C68: =C67+C66 -> 76218.033 | D68: =D67+D66 -> 76244.145 | E68: =E67+E66 -> 89055.112 | F68: =F67+F66 -> 102096.24 | G68: =G67+G66 -> 114843.33 | H68: =H67+H66 -> 126706.38 | I68: =I67+I66 -> 144308.75 | J68: =J67+J66 -> 166472.98 | ... L68: =L67+L66 -> 224173.65
A69: Free cash flow (memo) | B69: =B59+B60 -> 43585 | C69: =C59+C60 -> -7845.9665 | D69: =D59+D60 -> -41199.109 | E69: =E59+E60 -> -19063.128 | F69: =F59+F60 -> 15612.492 | G69: =G59+G60 -> 56551.942 | H69: =H59+H60 -> 91683.949 | I69: =I59+I60 -> 121618.14 | ... L69: =L59+L60 -> 185409.24
A70: Free cash flow margin | B70: =B69/B10 -> 0.21687748 | C70: =C69/C10 -> -0.030622947 | D70: =D69/D10 -> -0.13508942 | E70: =E69/E10 -> -0.053514973 | F70: =F69/F10 -> 0.038229839 | G70: =G69/G10 -> 0.12310672 | H70: =H69/H10 -> 0.18089845 | I70: =I69/I10 -> 0.21964271 | ... L70: =L69/L10 -> 0.27617057
A72: Checks (each should be zero)
A73: Balance sheet balances | B73: =ROUND(B43-B52,2) -> 0 | C73: =ROUND(C43-C52,2) -> 0 | D73: =ROUND(D43-D52,2) -> 0 | E73: =ROUND(E43-E52,2) -> 0 | F73: =ROUND(F43-F52,2) -> 0 | G73: =ROUND(G43-G52,2) -> 0 | H73: =ROUND(H43-H52,2) -> 0 | I73: =ROUND(I43-I52,2) -> 0 | ... L73: =ROUND(L43-L52,2) -> 0
A74: 2025A total assets equal the audited balance sheet | B74: =ROUND(B43-BS_Hist!H21,2) -> 0
A75: 2025A total costs equal the audited income statement | B75: =ROUND(B16-IS_Hist!H13,2) -> 0
A76: Ending cash equals the cash schedule | C76: =ROUND(C68-Schedules!C61,2) -> 0 | D76: =ROUND(D68-Schedules!D61,2) -> 0 | E76: =ROUND(E68-Schedules!E61,2) -> 0 | F76: =ROUND(F68-Schedules!F61,2) -> 0 | G76: =ROUND(G68-Schedules!G61,2) -> 0 | H76: =ROUND(H68-Schedules!H61,2) -> 0 | I76: =ROUND(I68-Schedules!I61,2) -> 0 | J76: =ROUND(J68-Schedules!J61,2) -> 0 | ... L76: =ROUND(L68-Schedules!L61,2) -> 0
A77: 2026E net income equals the bridge | C77: =ROUND(C28-Interim_Bridge!D23,2) -> 0
A78: Equity roll-forward: change equals net income + SBC - RSU taxes - buybacks - dividends | C78: =ROUND(C51-B51-C28-C32+Schedules!C57+Schedules!C58+Schedules!C56,2) -> 0 | D78: =ROUND(D51-C51-D28-D32+Schedules!D57+Schedules!D58+Schedules!D56,2) -> 0 | E78: =ROUND(E51-D51-E28-E32+Schedules!E57+Schedules!E58+Schedules!E56,2) -> 0 | F78: =ROUND(F51-E51-F28-F32+Schedules!F57+Schedules!F58+Schedules!F56,2) -> 0 | G78: =ROUND(G51-F51-G28-G32+Schedules!G57+Schedules!G58+Schedules!G56,2) -> 0 | H78: =ROUND(H51-G51-H28-H32+Schedules!H57+Schedules!H58+Schedules!H56,2) -> 0 | I78: =ROUND(I51-H51-I28-I32+Schedules!I57+Schedules!I58+Schedules!I56,2) -> 0 | J78: =ROUND(J51-I51-J28-J32+Schedules!J57+Schedules!J58+Schedules!J56,2) -> 0 | ... L78: =ROUND(L51-K51-L28-L32+Schedules!L57+Schedules!L58+Schedules!L56,2) -> 0

Sheet Debt_Credit
A1: Meta Platforms, Inc. | Debt, liquidity and credit metrics
A2: Notes, maturities, debt-like items and ratings at 30 Sep 2026; credit ratios for 2019A-2025A, LTM and 2026E-2035E (active scenario). USD millions.
A4: A. Senior notes outstanding (10-Q Note 9)
A5: Issue | B5: Maturities | C5: Stated rates | D5: Effective rates | E5: Face 30 Sep 2026 | F5: Face 31 Dec 2025
A6: August 2022 Notes | B6: 2027-2062 | C6: 3.50%-4.65% | D6: 3.63%-4.71% | E6: 10000 | F6: 10000
A7: May 2023 Notes | B7: 2028-2063 | C7: 4.60%-5.75% | D7: 4.68%-5.79% | E7: 8500 | F7: 8500
A8: August 2024 Notes | B8: 2029-2064 | C8: 4.30%-5.55% | D8: 4.42%-5.60% | E8: 10500 | F8: 10500
A9: November 2025 Notes | B9: 2030-2065 | C9: 4.20%-5.75% | D9: 4.27%-5.77% | E9: 30000 | F9: 30000
A10: May 2026 Notes | B10: 2031-2066 | C10: 4.55%-6.45% | D10: 4.60%-6.48% | E10: 25000 | F10: 0
A11: Total face value | E11: =SUM(E6:E10) -> 84000 | F11: =SUM(F6:F10) -> 59000
A12: Unamortized discount and issuance costs | E12: -331 | F12: -256
A13: Carrying value | E13: =E11+E12 -> 83669 | F13: =F11+F12 -> 58744
A14: of which current | E14: 2747 | F14: 0
A15: Fair value | E15: 73310 | F15: 57220
A16: Financial covenants: none ('We are not subject to any financial covenants under the Notes', 10-Q Note 9).
A18: B. Principal due by year (10-Q Note 9)
A19: Remainder of 2026 | B19: 0
A20: 2027 | B20: 2750
A21: 2028 | B21: 1500
A22: 2029 | B22: 1000
A23: 2030 | B23: 5000
A24: Thereafter | B24: 73750
A25: Total | B25: =SUM(B19:B24) -> 84000
A27: C. Liquidity, debt-like and off-balance-sheet items at 30 Sep 2026
A28: Cash and marketable securities | B28: =Market_Package!B20 -> 82449 | C28: Market_Package
A29: Operating lease liabilities | B29: =BS_Hist!J28+BS_Hist!J33 -> 31173 | C29: Q3 2026 10-Q balance sheet
A30: Finance lease liabilities | B30: =Market_Package!B23 -> 1184 | C30: 10-K FY2025 (latest disclosed)
A31: Legal-related accrued liabilities | B31: =Market_Package!B26 -> 19881 | C31: 10-Q Note 8
A32: Leases signed but not yet commenced | B32: 355730 | C32: 10-Q Note 10: data centers, energy, colocation; start 2026-2036, terms up to 30 years
A33: Non-cancelable contractual commitments | B33: 454520 | C33: 10-Q Note 10: mostly third-party cloud capacity, servers, network, energy
A34: of which due in the rest of 2026 | B34: 45850 | C34: 10-Q Note 10
A35: of which due in 2027 | B35: 121410 | C35: 10-Q Note 10
A36: Contingent obligation to buy cloud capacity | B36: 14720 | C36: 10-Q Note 10: over five years; may fall if the provider resells
A37: Data center ventures: maximum exposure | B37: 68404 | C37: 10-Q Note 5: equity 4,732 + lease commitments 18,476 + funding 3,703 + residual value guarantees 41,493
A38: of which residual value guarantees | B38: 41493 | C38: 10-Q Note 5
A39: New Mexico civil penalty ordered 21 Oct 2026 | B39: 25000 | C39: 10-Q Note 10: 15% post-judgment interest; Meta accrued an undisclosed amount and will appeal
A41: D. Credit ratings
A42: Moody's | B42: Aa3, stable | C42: Affirmed 2026 (Investing.com); Aa3 on May 2026 notes (FWP 30 Apr 2026)
A43: S&P Global | B43: AA-, stable | C43: S&P, 30 Oct 2025; AA- on May 2026 notes (FWP 30 Apr 2026)
