Workbook

Sheet 00_Cover
A1: Taiwan Semiconductor Manufacturing Company Limited — Regated institutional model
A2: Native-currency, source-ledgered semiconductor model | 2026-07-16 | owner-ready, independent certification pending
A4: Model identifier | B4: TSMC_9of10_Regated
A5: Ticker / CIK | B5: TSM / 0001046179
A6: Reporting currency / scale | B6: TWD / TWD millions
A7: Latest historical period | B7: FY2025A
A8: Forecast horizon | B8: Five fiscal years
A9: Valuation method | B9: Unlevered DCF to USD traded-security value
A10: Scenario control | B10: Assumptions!B3 — 1 Base / 2 Bull / 3 Bear
A11: Source gate | B11: Formula-driven exact claim ledger
A12: Native recalculation | B12: LibreOffice 26.2.4.2; two isolated-profile passes + reopen
A13: Architecture | B13: Prior ten-sheet order preserved; Gate_9of10 appended last
A14: Decision status | B14: READY FOR INDEPENDENT 9/10 REVIEW — not self-certified
A16: Use sequence: Sources → Historical → Assumptions → Forecast → Valuation → Sensitivity → Checks → Gate_9of10. Forecasts are estimates. Historical values remain in native currency; only the final security bridge uses dated FX and ADR ratio.

Sheet Sources
A1: Claim-level source and provenance ledger
A2: Every historical hardcode and external valuation input carries exact identity, period, value, locator, accession/URL, target, transform and review status.
A4: Source ID | B4: Legal entity / identifier | C4: Metric / line item | D4: Value | E4: Unit | F4: Period / as-of | G4: Source / class | H4: Taxonomy / claim locator | I4: Form | J4: Filed | K4: Accession | L4: Target cell | M4: Scale / FX / sign transform | N4: Exact official URL | O4: Retrieved | P4: Preparer | Q4: Verification | R4: Limitation / disposition
A5: TSMC-S001 | B5: Taiwan Semiconductor Manufacturing Company Limited | TSM | CIK 0001046179 | C5: Revenue | D5: 1587415 | E5: TWDm | F5: 2021-12-31 | G5: 20-F / Official regulator filing / XBRL | H5: ifrs-full:RevenueFromContractsWithCustomers | I5: 20-F | J5: 2024-04-18 | K5: 0001193125-24-099840 | L5: Historical!B5 | M5: TWD / 1e6; sign preserved | N5: https://www.sec.gov/Archives/edgar/data/1046179/000119312524099840/0001193125-24-099840-index.html | O5: 2026-07-16 | P5: Codex / semiconductor cluster | Q5: VERIFIED | R5: None
A6: TSMC-S002 | B6: Taiwan Semiconductor Manufacturing Company Limited | TSM | CIK 0001046179 | C6: Revenue | D6: 2263891.3 | E6: TWDm | F6: 2022-12-31 | G6: 20-F / Official regulator filing / XBRL | H6: ifrs-full:RevenueFromContractsWithCustomers | I6: 20-F | J6: 2025-04-17 | K6: 0001193125-25-083423 | L6: Historical!C5 | M6: TWD / 1e6; sign preserved | N6: https://www.sec.gov/Archives/edgar/data/1046179/000119312525083423/0001193125-25-083423-index.html | O6: 2026-07-16 | P6: Codex / semiconductor cluster | Q6: VERIFIED | R6: None
A7: TSMC-S003 | B7: Taiwan Semiconductor Manufacturing Company Limited | TSM | CIK 0001046179 | C7: Revenue | D7: 2161735.8 | E7: TWDm | F7: 2023-12-31 | G7: 20-F / Official regulator filing / XBRL | H7: ifrs-full:RevenueFromContractsWithCustomers | I7: 20-F | J7: 2025-04-17 | K7: 0001193125-25-083423 | L7: Historical!D5 | M7: TWD / 1e6; sign preserved | N7: https://www.sec.gov/Archives/edgar/data/1046179/000119312525083423/0001193125-25-083423-index.html | O7: 2026-07-16 | P7: Codex / semiconductor cluster | Q7: VERIFIED | R7: None
A8: TSMC-S004 | B8: Taiwan Semiconductor Manufacturing Company Limited | TSM | CIK 0001046179 | C8: Revenue | D8: 2894307.7 | E8: TWDm | F8: 2024-12-31 | G8: 20-F / Official regulator filing / XBRL | H8: ifrs-full:RevenueFromContractsWithCustomers | I8: 20-F | J8: 2025-04-17 | K8: 0001193125-25-083423 | L8: Historical!E5 | M8: TWD / 1e6; sign preserved | N8: https://www.sec.gov/Archives/edgar/data/1046179/000119312525083423/0001193125-25-083423-index.html | O8: 2026-07-16 | P8: Codex / semiconductor cluster | Q8: VERIFIED | R8: None
A9: TSMC-S005 | B9: Taiwan Semiconductor Manufacturing Company Limited | TSM | CIK 0001046179 | C9: Revenue | D9: 3809054.3 | E9: TWDm | F9: 2025-12-31 | G9: 20-F / Official regulator filing / XBRL | H9: ifrs-full:RevenueFromContractsWithCustomers; context c-1 | I9: 20-F | J9: 2026-04-16 | K9: 0001628280-26-025362 | L9: Historical!F5 | M9: TWD / 1e6; sign preserved | N9: https://www.sec.gov/Archives/edgar/data/1046179/000162828026025362/tsm-20251231.htm | O9: 2026-07-16 | P9: Codex / semiconductor cluster | Q9: VERIFIED | R9: None
A10: TSMC-S006 | B10: Taiwan Semiconductor Manufacturing Company Limited | TSM | CIK 0001046179 | C10: Gross profit | D10: 819537.3 | E10: TWDm | F10: 2021-12-31 | G10: 20-F / Official regulator filing / XBRL | H10: ifrs-full:GrossProfit | I10: 20-F | J10: 2024-04-18 | K10: 0001193125-24-099840 | L10: Historical!B7 | M10: TWD / 1e6; sign preserved | N10: https://www.sec.gov/Archives/edgar/data/1046179/000119312524099840/0001193125-24-099840-index.html | O10: 2026-07-16 | P10: Codex / semiconductor cluster | Q10: VERIFIED | R10: None
A11: TSMC-S007 | B11: Taiwan Semiconductor Manufacturing Company Limited | TSM | CIK 0001046179 | C11: Gross profit | D11: 1348354.8 | E11: TWDm | F11: 2022-12-31 | G11: 20-F / Official regulator filing / XBRL | H11: ifrs-full:GrossProfit | I11: 20-F | J11: 2025-04-17 | K11: 0001193125-25-083423 | L11: Historical!C7 | M11: TWD / 1e6; sign preserved | N11: https://www.sec.gov/Archives/edgar/data/1046179/000119312525083423/0001193125-25-083423-index.html | O11: 2026-07-16 | P11: Codex / semiconductor cluster | Q11: VERIFIED | R11: None
A12: TSMC-S008 | B12: Taiwan Semiconductor Manufacturing Company Limited | TSM | CIK 0001046179 | C12: Gross profit | D12: 1175110.6 | E12: TWDm | F12: 2023-12-31 | G12: 20-F / Official regulator filing / XBRL | H12: ifrs-full:GrossProfit | I12: 20-F | J12: 2025-04-17 | K12: 0001193125-25-083423 | L12: Historical!D7 | M12: TWD / 1e6; sign preserved | N12: https://www.sec.gov/Archives/edgar/data/1046179/000119312525083423/0001193125-25-083423-index.html | O12: 2026-07-16 | P12: Codex / semiconductor cluster | Q12: VERIFIED | R12: None
A13: TSMC-S009 | B13: Taiwan Semiconductor Manufacturing Company Limited | TSM | CIK 0001046179 | C13: Gross profit | D13: 1624353.6 | E13: TWDm | F13: 2024-12-31 | G13: 20-F / Official regulator filing / XBRL | H13: ifrs-full:GrossProfit | I13: 20-F | J13: 2025-04-17 | K13: 0001193125-25-083423 | L13: Historical!E7 | M13: TWD / 1e6; sign preserved | N13: https://www.sec.gov/Archives/edgar/data/1046179/000119312525083423/0001193125-25-083423-index.html | O13: 2026-07-16 | P13: Codex / semiconductor cluster | Q13: VERIFIED | R13: None
A14: TSMC-S010 | B14: Taiwan Semiconductor Manufacturing Company Limited | TSM | CIK 0001046179 | C14: Gross profit | D14: 2281294 | E14: TWDm | F14: 2025-12-31 | G14: 20-F / Official regulator filing / XBRL | H14: ifrs-full:GrossProfit; context c-1 | I14: 20-F | J14: 2026-04-16 | K14: 0001628280-26-025362 | L14: Historical!F7 | M14: TWD / 1e6; sign preserved | N14: https://www.sec.gov/Archives/edgar/data/1046179/000162828026025362/tsm-20251231.htm | O14: 2026-07-16 | P14: Codex / semiconductor cluster | Q14: VERIFIED | R14: None
A15: TSMC-S011 | B15: Taiwan Semiconductor Manufacturing Company Limited | TSM | CIK 0001046179 | C15: Operating income | D15: 649980.9 | E15: TWDm | F15: 2021-12-31 | G15: 20-F / Official regulator filing / XBRL | H15: ifrs-full:ProfitLossFromOperatingActivities | I15: 20-F | J15: 2024-04-18 | K15: 0001193125-24-099840 | L15: Historical!B9 | M15: TWD / 1e6; sign preserved | N15: https://www.sec.gov/Archives/edgar/data/1046179/000119312524099840/0001193125-24-099840-index.html | O15: 2026-07-16 | P15: Codex / semiconductor cluster | Q15: VERIFIED | R15: None
A16: TSMC-S012 | B16: Taiwan Semiconductor Manufacturing Company Limited | TSM | CIK 0001046179 | C16: Operating income | D16: 1121278.9 | E16: TWDm | F16: 2022-12-31 | G16: 20-F / Official regulator filing / XBRL | H16: ifrs-full:ProfitLossFromOperatingActivities | I16: 20-F | J16: 2025-04-17 | K16: 0001193125-25-083423 | L16: Historical!C9 | M16: TWD / 1e6; sign preserved | N16: https://www.sec.gov/Archives/edgar/data/1046179/000119312525083423/0001193125-25-083423-index.html | O16: 2026-07-16 | P16: Codex / semiconductor cluster | Q16: VERIFIED | R16: None
... A107: TSMC-S103 | B107: Taiwan Semiconductor Manufacturing Company Limited | TSM | CIK 0001046179 | C107: Terminal growth | D107: 0.04 | E107: model input | F107: Forecast horizon | G107: Model input / Forecast assumption / model input | H107: Base/Bull/Bear estimate | I107: Model input | J107: 2026-07-16 | K107: n/a | L107: Assumptions!B21:D21 | M107: blue model input | N107: https://www.sec.gov/Archives/edgar/data/1046179/000162828026025362/tsm-20251231.htm | O107: 2026-07-16 | P107: Codex / semiconductor cluster | Q107: VERIFIED | R107: Not a reported fact
A110: Ola 2 elevation (run 24e4a1f1): see Sources_Audited tab for the real, independently-sourced claim ledger (20-F R-files + companyfacts.json). This legacy tab and its COUNTIF-based "VERIFIED" flags are retained unmodified per no-weaken-checks policy but are self-referential (they check label presence in this own tab, not an external source) -- do not rely on them as the audit trail going forward.

Sheet Historical
A1: Historical financials
A2: TWD millions; native reported history. Percent rows are formula-derived.
A4: Metric | B4: FY2021A | C4: FY2022A | D4: FY2023A | E4: FY2024A | F4: FY2025A | G4: Unit | H4: Source coverage
A5: Revenue | B5: 1587415 | C5: 2263891.3 | D5: 2161735.8 | E5: 2894307.7 | F5: 3809054.3 | G5: TWD millions | H5: =IF(COUNTIF(Sources!$C$5:$C$107,"Revenue")>=1,"VERIFIED","CHECK") -> VERIFIED
A6: Growth | C6: =IF(B5<>0,C5/B5-1,0) -> 0.42614962 | D6: =IF(C5<>0,D5/C5-1,0) -> -0.045123854 | E6: =IF(D5<>0,E5/D5-1,0) -> 0.33888133 | F6: =IF(E5<>0,F5/E5-1,0) -> 0.31605023 | G6: % | H6: Formula-derived
A7: Gross profit | B7: 819537.3 | C7: 1348354.8 | D7: 1175110.6 | E7: 1624353.6 | F7: 2281294 | G7: TWD millions | H7: =IF(COUNTIF(Sources!$C$5:$C$107,"Gross profit")>=1,"VERIFIED","CHECK") -> VERIFIED
A8: Gross margin | B8: =IF(B5<>0,B7/B5,0) -> 0.51627161 | C8: =IF(C5<>0,C7/C5,0) -> 0.59559167 | D8: =IF(D5<>0,D7/D5,0) -> 0.54359585 | E8: =IF(E5<>0,E7/E5,0) -> 0.56122354 | F8: =IF(F5<>0,F7/F5,0) -> 0.59891349 | G8: % | H8: Formula-derived
A9: Operating income | B9: 649980.9 | C9: 1121278.9 | D9: 921465.6 | E9: 1322053 | F9: 1936091.7 | G9: TWD millions | H9: =IF(COUNTIF(Sources!$C$5:$C$107,"Operating income")>=1,"VERIFIED","CHECK") -> VERIFIED
A10: Operating margin | B10: =IF(B5<>0,B9/B5,0) -> 0.40945871 | C10: =IF(C5<>0,C9/C5,0) -> 0.49528831 | D10: =IF(D5<>0,D9/D5,0) -> 0.4262619 | E10: =IF(E5<>0,E9/E5,0) -> 0.45677693 | F10: =IF(F5<>0,F9/F5,0) -> 0.50828672 | G10: % | H10: Formula-derived
A11: Net income attributable / consolidated | B11: 592359.2 | C11: 992923.4 | D11: 851740 | E11: 1158380.2 | F11: 1697604 | G11: TWD millions | H11: =IF(COUNTIF(Sources!$C$5:$C$107,"Net income attributable / consolidated")>=1,"VERIFIED","CHECK") -> VERIFIED
A12: Cash flow from operations | B12: 1112160.7 | C12: 1610599.2 | D12: 1241967.3 | E12: 1826177.1 | F12: 2274975.6 | G12: TWD millions | H12: =IF(COUNTIF(Sources!$C$5:$C$107,"Cash flow from operations")>=1,"VERIFIED","CHECK") -> VERIFIED
A13: Capital expenditure | B13: 839195.7 | C13: 1082672.1 | D13: 949816.8 | E13: 956006.5 | F13: 1272410.5 | G13: TWD millions | H13: =IF(COUNTIF(Sources!$C$5:$C$107,"Capital expenditure")>=1,"VERIFIED","CHECK") -> VERIFIED
A14: Research and development | B14: 124734.8 | C14: 163262.2 | D14: 182370.2 | E14: 204181.8 | F14: 246427.2 | G14: TWD millions | H14: =IF(COUNTIF(Sources!$C$5:$C$107,"Research and development")>=1,"VERIFIED","CHECK") -> VERIFIED
A15: Total assets | B15: 3725302.2 | C15: 4964459.1 | D15: 5532196.6 | E15: 6691764.7 | F15: 7932842.5 | G15: TWD millions | H15: =IF(COUNTIF(Sources!$C$5:$C$107,"Total assets")>=1,"VERIFIED","CHECK") -> VERIFIED
A16: Total liabilities | B16: 1573619.7 | C16: 2046626.7 | D16: 2078330.1 | E16: 2412493.1 | F16: 2536623.3 | G16: TWD millions | H16: =IF(COUNTIF(Sources!$C$5:$C$107,"Total liabilities")>=1,"VERIFIED","CHECK") -> VERIFIED
A17: Equity attributable / stockholders' equity | B17: 2149259.8 | C17: 2903019.7 | D17: 3429522.4 | E17: 4244266.5 | F17: 5355038.7 | G17: TWD millions | H17: =IF(COUNTIF(Sources!$C$5:$C$107,"Equity attributable / stockholders' equity")>=1,"VERIFIED","CHECK") -> VERIFIED
A18: Cash and cash equivalents | B18: 1064990.2 | C18: 1342814.1 | D18: 1465427.8 | E18: 2127627 | F18: 2767856.4 | G18: TWD millions | H18: =IF(COUNTIF(Sources!$C$5:$C$107,"Cash and cash equivalents")>=1,"VERIFIED","CHECK") -> VERIFIED
A19: Interest-bearing debt | B19: 617946.4 | C19: 858410.3 | D19: 927576.1 | E19: 1018286.8 | F19: 1032987.7 | G19: TWD millions | H19: =IF(AND(COUNTIF(Sources!$C$5:$C$107,"Debt component: CurrentPortionOfLongtermBorrowings")>=1,COUNTIF(Sources!$C$5:$C$107,"Debt component: NoncurrentPortionOfNoncurrentBondsIssued")>=1,COUNTIF(Sources!$C$5:$C$107,"Debt component: LongtermBorrowings")>=1),"VERIFIED","CHECK") -> VERIFIED
A20: Diluted weighted-average shares | B20: 25930.3 | C20: 25929.4 | D20: 25929.3 | E20: 25929.7 | F20: 25930.6 | G20: millions of shares | H20: =IF(COUNTIF(Sources!$C$5:$C$107,"Diluted weighted-average shares")>=1,"VERIFIED","CHECK") -> VERIFIED

Sheet Assumptions
A1: Scenario assumptions
A2: Blue = input; green = selected formula. Selector 1 Base / 2 Bull / 3 Bear. TWD stays native through DCF.
A3: Scenario selector | B3: 1
A4: Driver | B4: Base | C4: Bull | D4: Bear | E4: Active | F4: Classification / rationale
A5: Wafer shipment growth — Y1 | B5: 0.1 | C5: 0.14 | D5: 0.04 | E5: =CHOOSE($B$3,B5,C5,D5) -> 0.1 | F5: Company-specific revenue driver estimate
A6: Wafer shipment growth — Y5 | B6: 0.06 | C6: 0.09 | D6: 0.03 | E6: =CHOOSE($B$3,B6,C6,D6) -> 0.06 | F6: Company-specific revenue driver estimate
A7: Blended revenue / wafer growth — Y1 | B7: 0.08 | C7: 0.12 | D7: 0.03 | E7: =CHOOSE($B$3,B7,C7,D7) -> 0.08 | F7: Company-specific revenue driver estimate
A8: Blended revenue / wafer growth — Y5 | B8: 0.04 | C8: 0.07 | D8: 0.01 | E8: =CHOOSE($B$3,B8,C8,D8) -> 0.04 | F8: Company-specific revenue driver estimate
A9: Advanced-node mix annual change — Y1 | B9: 0.035 | C9: 0.045 | D9: 0.02 | E9: =CHOOSE($B$3,B9,C9,D9) -> 0.035 | F9: Company-specific revenue driver estimate
A10: Advanced-node mix annual change — Y5 | B10: 0.02 | C10: 0.03 | D10: 0.01 | E10: =CHOOSE($B$3,B10,C10,D10) -> 0.02 | F10: Company-specific revenue driver estimate
A11: Gross margin — Y1 | B11: 0.605 | C11: 0.62 | D11: 0.575 | E11: =CHOOSE($B$3,B11,C11,D11) -> 0.605 | F11: Operating / FCFF estimate
A12: Gross margin — Y5 | B12: 0.615 | C12: 0.64 | D12: 0.58 | E12: =CHOOSE($B$3,B12,C12,D12) -> 0.615 | F12: Operating / FCFF estimate
A13: R&D / revenue | B13: 0.065 | C13: 0.062 | D13: 0.07 | E13: =CHOOSE($B$3,B13,C13,D13) -> 0.065 | F13: Operating / FCFF estimate
A14: Other operating expense / revenue | B14: 0.026 | C14: 0.023 | D14: 0.03 | E14: =CHOOSE($B$3,B14,C14,D14) -> 0.026 | F14: Operating / FCFF estimate
A15: Cash tax rate | B15: 0.15 | C15: 0.14 | D15: 0.17 | E15: =CHOOSE($B$3,B15,C15,D15) -> 0.15 | F15: Operating / FCFF estimate
A16: D&A / revenue | B16: 0.18 | C16: 0.19 | D16: 0.17 | E16: =CHOOSE($B$3,B16,C16,D16) -> 0.18 | F16: Operating / FCFF estimate
... A24: Current traded-security price (USD) | B24: 419.48 | C24: 419.48 | D24: 419.48 | E24: =CHOOSE($B$3,B24,C24,D24) -> 419.48 | F24: Dated market / structural bridge

Sheet Forecast
A1: Company-specific operating forecast
A2: TWD millions; sector operating drivers build revenue bottom-up.
A4: Metric | B4: FY2025A | C4: FY2026E | D4: FY2027E | E4: FY2028E | F4: FY2029E | G4: FY2030E
A5: Wafer shipments (m 12-inch eq.) | B5: 15 | C5: =B5*(1+Assumptions!$E$5) -> 16.5 | D5: =C5*(1+Assumptions!$E$5+(Assumptions!$E$6-Assumptions!$E$5)*1/4) -> 17.985 | E5: =D5*(1+Assumptions!$E$5+(Assumptions!$E$6-Assumptions!$E$5)*2/4) -> 19.4238 | F5: =E5*(1+Assumptions!$E$5+(Assumptions!$E$6-Assumptions!$E$5)*3/4) -> 20.783466 | G5: =F5*(1+Assumptions!$E$5+(Assumptions!$E$6-Assumptions!$E$5)*4/4) -> 22.030474
A6: Blended revenue / wafer (TWD thousands) | B6: 253936.95 | C6: =B6*(1+Assumptions!$E$7) -> 274251.91 | D6: =C6*(1+Assumptions!$E$7+(Assumptions!$E$8-Assumptions!$E$7)*1/4) -> 293449.54 | E6: =D6*(1+Assumptions!$E$7+(Assumptions!$E$8-Assumptions!$E$7)*2/4) -> 311056.52 | F6: =E6*(1+Assumptions!$E$7+(Assumptions!$E$8-Assumptions!$E$7)*3/4) -> 326609.34 | G6: =F6*(1+Assumptions!$E$7+(Assumptions!$E$8-Assumptions!$E$7)*4/4) -> 339673.72
A7: Advanced technologies mix | B7: 0.74 | C7: =MIN(0.95,B7+Assumptions!$E$9) -> 0.775 | D7: =MIN(0.95,C7+Assumptions!$E$9+(Assumptions!$E$10-Assumptions!$E$9)*1/4) -> 0.80625 | E7: =MIN(0.95,D7+Assumptions!$E$9+(Assumptions!$E$10-Assumptions!$E$9)*2/4) -> 0.83375 | F7: =MIN(0.95,E7+Assumptions!$E$9+(Assumptions!$E$10-Assumptions!$E$9)*3/4) -> 0.8575 | G7: =MIN(0.95,F7+Assumptions!$E$9+(Assumptions!$E$10-Assumptions!$E$9)*4/4) -> 0.8775
A8: Total revenue | B8: =B5*B6 -> 3809054.3 | C8: =C5*C6 -> 4525156.5 | D8: =D5*D6 -> 5277690 | E8: =E5*E6 -> 6041899.6 | F8: =F5*F6 -> 6788074.1 | G8: =G5*G6 -> 7483172.9
A9: Revenue growth | B9: =Historical!F6 -> 0.31605023 | C9: =IF(B8<>0,C8/B8-1,0) -> 0.188 | D9: =IF(C8<>0,D8/C8-1,0) -> 0.1663 | E9: =IF(D8<>0,E8/D8-1,0) -> 0.1448 | F9: =IF(E8<>0,F8/E8-1,0) -> 0.1235 | G9: =IF(F8<>0,G8/F8-1,0) -> 0.1024
A10: Gross margin | B10: =Historical!F8 -> 0.59891349 | C10: =Assumptions!$E$11 -> 0.605 | D10: =Assumptions!$E$11+(Assumptions!$E$12-Assumptions!$E$11)*1/4 -> 0.6075 | E10: =Assumptions!$E$11+(Assumptions!$E$12-Assumptions!$E$11)*2/4 -> 0.61 | F10: =Assumptions!$E$11+(Assumptions!$E$12-Assumptions!$E$11)*3/4 -> 0.6125 | G10: =Assumptions!$E$11+(Assumptions!$E$12-Assumptions!$E$11)*4/4 -> 0.615
A11: Gross profit | B11: =B8*B10 -> 2281294 | C11: =C8*C10 -> 2737719.7 | D11: =D8*D10 -> 3206196.7 | E11: =E8*E10 -> 3685558.7 | F11: =F8*F10 -> 4157695.4 | G11: =G8*G10 -> 4602151.4
A12: R&D / revenue | B12: =IF(B8<>0,Historical!F14/B8,0) -> 0.064695113 | C12: =Assumptions!$E$13 -> 0.065 | D12: =Assumptions!$E$13 -> 0.065 | E12: =Assumptions!$E$13 -> 0.065 | F12: =Assumptions!$E$13 -> 0.065 | G12: =Assumptions!$E$13 -> 0.065
A13: R&D | B13: =Historical!F14 -> 246427.2 | C13: =C8*C12 -> 294135.17 | D13: =D8*D12 -> 343049.85 | E13: =E8*E12 -> 392723.47 | F13: =F8*F12 -> 441224.82 | G13: =G8*G12 -> 486406.24
A14: Other operating expense / revenue | B14: =IF(B8<>0,(B11-Historical!F9-B13)/B8,0) -> 0.02593166 | C14: =Assumptions!$E$14 -> 0.026 | D14: =Assumptions!$E$14 -> 0.026 | E14: =Assumptions!$E$14 -> 0.026 | F14: =Assumptions!$E$14 -> 0.026 | G14: =Assumptions!$E$14 -> 0.026
A15: Other operating expense | B15: =B8*B14 -> 98775.1 | C15: =C8*C14 -> 117654.07 | D15: =D8*D14 -> 137219.94 | E15: =E8*E14 -> 157089.39 | F15: =F8*F14 -> 176489.93 | G15: =G8*G14 -> 194562.5
A16: Operating income | B16: =B11-B13-B15 -> 1936091.7 | C16: =C11-C13-C15 -> 2325930.4 | D16: =D11-D13-D15 -> 2725926.9 | E16: =E11-E13-E15 -> 3135745.9 | F16: =F11-F13-F15 -> 3539980.7 | G16: =G11-G13-G15 -> 3921182.6
A17: Operating margin | B17: =IF(B8<>0,B16/B8,0) -> 0.50828672 | C17: =IF(C8<>0,C16/C8,0) -> 0.514 | D17: =IF(D8<>0,D16/D8,0) -> 0.5165 | E17: =IF(E8<>0,E16/E8,0) -> 0.519 | F17: =IF(F8<>0,F16/F8,0) -> 0.5215 | G17: =IF(G8<>0,G16/G8,0) -> 0.524
A18: Cash tax rate | B18: =Assumptions!E15 -> 0.15 | C18: =Assumptions!$E$15 -> 0.15 | D18: =Assumptions!$E$15 -> 0.15 | E18: =Assumptions!$E$15 -> 0.15 | F18: =Assumptions!$E$15 -> 0.15 | G18: =Assumptions!$E$15 -> 0.15
A19: NOPAT | B19: =B16*(1-B18) -> 1645677.9 | C19: =C16*(1-C18) -> 1977040.9 | D19: =D16*(1-D18) -> 2317037.9 | E19: =E16*(1-E18) -> 2665384 | F19: =F16*(1-F18) -> 3008983.6 | G19: =G16*(1-G18) -> 3333005.2
A20: D&A / revenue | B20: =Assumptions!E16 -> 0.18 | C20: =Assumptions!$E$16 -> 0.18 | D20: =Assumptions!$E$16 -> 0.18 | E20: =Assumptions!$E$16 -> 0.18 | F20: =Assumptions!$E$16 -> 0.18 | G20: =Assumptions!$E$16 -> 0.18
A21: D&A | B21: =B8*B20 -> 685629.77 | C21: =C8*C20 -> 814528.17 | D21: =D8*D20 -> 949984.21 | E21: =E8*E20 -> 1087541.9 | F21: =F8*F20 -> 1221853.3 | G21: =G8*G20 -> 1346971.1
A22: Capex / revenue | B22: =IF(B8<>0,Historical!F13/B8,0) -> 0.33404893 | C22: =Assumptions!$E$17 -> 0.33 | D22: =Assumptions!$E$17+(Assumptions!$E$18-Assumptions!$E$17)*1/4 -> 0.315 | E22: =Assumptions!$E$17+(Assumptions!$E$18-Assumptions!$E$17)*2/4 -> 0.3 | F22: =Assumptions!$E$17+(Assumptions!$E$18-Assumptions!$E$17)*3/4 -> 0.285 | G22: =Assumptions!$E$17+(Assumptions!$E$18-Assumptions!$E$17)*4/4 -> 0.27
A23: Capital expenditure | B23: =Historical!F13 -> 1272410.5 | C23: =C8*C22 -> 1493301.6 | D23: =D8*D22 -> 1662472.4 | E23: =E8*E22 -> 1812569.9 | F23: =F8*F22 -> 1934601.1 | G23: =G8*G22 -> 2020456.7
A24: Change in NWC | B24: 0 | C24: =MAX(0,(C8-B8)*Assumptions!$E$19) -> 17902.555 | D24: =MAX(0,(D8-C8)*Assumptions!$E$19) -> 18813.338 | E24: =MAX(0,(E8-D8)*Assumptions!$E$19) -> 19105.238 | F24: =MAX(0,(F8-E8)*Assumptions!$E$19) -> 18654.365 | G24: =MAX(0,(G8-F8)*Assumptions!$E$19) -> 17377.47
A25: FCFF | B25: =B19+B21-B23-B24 -> 1058897.2 | C25: =C19+C21-C23-C24 -> 1280364.8 | D25: =D19+D21-D23-D24 -> 1585736.4 | E25: =E19+E21-E23-E24 -> 1921250.8 | F25: =F19+F21-F23-F24 -> 2277581.4 | G25: =G19+G21-G23-G24 -> 2642142.2
A26: Cash / liquidity | B26: 2767856.4 | C26: =$B$26 -> 2767856.4 | D26: =$B$26 -> 2767856.4 | E26: =$B$26 -> 2767856.4 | F26: =$B$26 -> 2767856.4 | G26: =$B$26 -> 2767856.4
A27: Interest-bearing debt | B27: 1032987.7 | C27: =$B$27 -> 1032987.7 | D27: =$B$27 -> 1032987.7 | E27: =$B$27 -> 1032987.7 | F27: =$B$27 -> 1032987.7 | G27: =$B$27 -> 1032987.7
A28: Diluted shares | B28: 25930.6 | C28: =$B$28 -> 25930.6 | D28: =$B$28 -> 25930.6 | E28: =$B$28 -> 25930.6 | F28: =$B$28 -> 25930.6 | G28: =$B$28 -> 25930.6

Sheet Valuation
A1: Discounted cash flow valuation
A2: TWD millions; DCF stays native through equity value. Final line converts to the USD traded security.
A4: Metric | B4: Year 1 | C4: Year 2 | D4: Year 3 | E4: Year 4 | F4: Year 5 | G4: Output
A5: FCFF | B5: =Forecast!C25 -> 1280364.8 | C5: =Forecast!D25 -> 1585736.4 | D5: =Forecast!E25 -> 1921250.8 | E5: =Forecast!F25 -> 2277581.4 | F5: =Forecast!G25 -> 2642142.2
A6: Discount factor | B6: =1/(1+Assumptions!$E$20)^1 -> 0.91743119 | C6: =1/(1+Assumptions!$E$20)^2 -> 0.84167999 | D6: =1/(1+Assumptions!$E$20)^3 -> 0.77218348 | E6: =1/(1+Assumptions!$E$20)^4 -> 0.70842521 | F6: =1/(1+Assumptions!$E$20)^5 -> 0.64993139
A7: PV of FCFF | B7: =B5*B6 -> 1174646.6 | C7: =C5*C6 -> 1334682.6 | D7: =D5*D6 -> 1483558.1 | E7: =E5*E6 -> 1613496.1 | F7: =F5*F6 -> 1717211.1
A9: Output | B9: Value
A10: PV explicit FCFF | B10: =SUM(B7:F7) -> 7323594.6
A11: Terminal value | B11: =IF(Assumptions!$E$20>Assumptions!$E$21,F5*(1+Assumptions!$E$21)/(Assumptions!$E$20-Assumptions!$E$21),0) -> 54956558
A12: PV terminal value | B12: =B11*F6 -> 35717992
A13: Enterprise value | B13: =B10+B12 -> 43041586
A14: Cash / liquidity | B14: =Forecast!B26 -> 2767856.4
A15: Interest-bearing debt | B15: =Forecast!B27 -> 1032987.7
A16: Equity value | B16: =B13+B14-B15 -> 44776455
A17: Diluted shares (mm) | B17: =Forecast!B28 -> 25930.6
A18: Implied TWD / ordinary share | B18: =IF(B17>0,B16/B17,0) -> 1726.7805
A19: FX conversion input | B19: =Assumptions!E22 -> 32.21
A20: Ordinary shares per traded security | B20: =Assumptions!E23 -> 5
A21: Implied USD / traded security | B21: =B18/Assumptions!$E$22*Assumptions!$E$23 -> 268.05038
A22: Current traded-security price (USD) | B22: =Assumptions!E24 -> 419.48
A23: Upside / (downside) | B23: =IF(B22>0,B21/B22-1,0) -> -0.36099367

Sheet Sensitivity
A1: DCF sensitivity — implied USD / traded security
A2: Dynamic per-share matrix; center is active WACC / terminal growth.
A4: Terminal growth / WACC | B4: =Assumptions!$E$20+-0.02 -> 0.07 | C4: =Assumptions!$E$20+-0.01 -> 0.08 | D4: =Assumptions!$E$20+0 -> 0.09 | E4: =Assumptions!$E$20+0.01 -> 0.1 | F4: =Assumptions!$E$20+0.02 -> 0.11
A5: =Assumptions!$E$21+-0.01 -> 0.03 | B5: =((Valuation!$B$5/(1+B$4)^1+Valuation!$C$5/(1+B$4)^2+Valuation!$D$5/(1+B$4)^3+Valuation!$E$5/(1+B$4)^4+Valuation!$F$5/(1+B$4)^5+IF(B$4>$A5,Valuation!$F$5*(1+$A5)/(B$4-$A5)/(1+B$4)^5,0)+Valuation!$B$14-Valuation!$B$15)/Valuation!$B$17)/Assumptions!$E$22*Assumptions!$E$23 -> 347.29774 | C5: =((Valuation!$B$5/(1+C$4)^1+Valuation!$C$5/(1+C$4)^2+Valuation!$D$5/(1+C$4)^3+Valuation!$E$5/(1+C$4)^4+Valuation!$F$5/(1+C$4)^5+IF(C$4>$A5,Valuation!$F$5*(1+$A5)/(C$4-$A5)/(1+C$4)^5,0)+Valuation!$B$14-Valuation!$B$15)/Valuation!$B$17)/Assumptions!$E$22*Assumptions!$E$23 -> 277.29196 | D5: =((Valuation!$B$5/(1+D$4)^1+Valuation!$C$5/(1+D$4)^2+Valuation!$D$5/(1+D$4)^3+Valuation!$E$5/(1+D$4)^4+Valuation!$F$5/(1+D$4)^5+IF(D$4>$A5,Valuation!$F$5*(1+$A5)/(D$4-$A5)/(1+D$4)^5,0)+Valuation!$B$14-Valuation!$B$15)/Valuation!$B$17)/Assumptions!$E$22*Assumptions!$E$23 -> 230.69994 | E5: =((Valuation!$B$5/(1+E$4)^1+Valuation!$C$5/(1+E$4)^2+Valuation!$D$5/(1+E$4)^3+Valuation!$E$5/(1+E$4)^4+Valuation!$F$5/(1+E$4)^5+IF(E$4>$A5,Valuation!$F$5*(1+$A5)/(E$4-$A5)/(1+E$4)^5,0)+Valuation!$B$14-Valuation!$B$15)/Valuation!$B$17)/Assumptions!$E$22*Assumptions!$E$23 -> 197.48407 | F5: =((Valuation!$B$5/(1+F$4)^1+Valuation!$C$5/(1+F$4)^2+Valuation!$D$5/(1+F$4)^3+Valuation!$E$5/(1+F$4)^4+Valuation!$F$5/(1+F$4)^5+IF(F$4>$A5,Valuation!$F$5*(1+$A5)/(F$4-$A5)/(1+F$4)^5,0)+Valuation!$B$14-Valuation!$B$15)/Valuation!$B$17)/Assumptions!$E$22*Assumptions!$E$23 -> 172.6257
A6: =Assumptions!$E$21+-0.005 -> 0.035 | B6: =((Valuation!$B$5/(1+B$4)^1+Valuation!$C$5/(1+B$4)^2+Valuation!$D$5/(1+B$4)^3+Valuation!$E$5/(1+B$4)^4+Valuation!$F$5/(1+B$4)^5+IF(B$4>$A6,Valuation!$F$5*(1+$A6)/(B$4-$A6)/(1+B$4)^5,0)+Valuation!$B$14-Valuation!$B$15)/Valuation!$B$17)/Assumptions!$E$22*Assumptions!$E$23 -> 390.39302 | C6: =((Valuation!$B$5/(1+C$4)^1+Valuation!$C$5/(1+C$4)^2+Valuation!$D$5/(1+C$4)^3+Valuation!$E$5/(1+C$4)^4+Valuation!$F$5/(1+C$4)^5+IF(C$4>$A6,Valuation!$F$5*(1+$A6)/(C$4-$A6)/(1+C$4)^5,0)+Valuation!$B$14-Valuation!$B$15)/Valuation!$B$17)/Assumptions!$E$22*Assumptions!$E$23 -> 303.12737 | D6: =((Valuation!$B$5/(1+D$4)^1+Valuation!$C$5/(1+D$4)^2+Valuation!$D$5/(1+D$4)^3+Valuation!$E$5/(1+D$4)^4+Valuation!$F$5/(1+D$4)^5+IF(D$4>$A6,Valuation!$F$5*(1+$A6)/(D$4-$A6)/(1+D$4)^5,0)+Valuation!$B$14-Valuation!$B$15)/Valuation!$B$17)/Assumptions!$E$22*Assumptions!$E$23 -> 247.67741 | E6: =((Valuation!$B$5/(1+E$4)^1+Valuation!$C$5/(1+E$4)^2+Valuation!$D$5/(1+E$4)^3+Valuation!$E$5/(1+E$4)^4+Valuation!$F$5/(1+E$4)^5+IF(E$4>$A6,Valuation!$F$5*(1+$A6)/(E$4-$A6)/(1+E$4)^5,0)+Valuation!$B$14-Valuation!$B$15)/Valuation!$B$17)/Assumptions!$E$22*Assumptions!$E$23 -> 209.35571 | F6: =((Valuation!$B$5/(1+F$4)^1+Valuation!$C$5/(1+F$4)^2+Valuation!$D$5/(1+F$4)^3+Valuation!$E$5/(1+F$4)^4+Valuation!$F$5/(1+F$4)^5+IF(F$4>$A6,Valuation!$F$5*(1+$A6)/(F$4-$A6)/(1+F$4)^5,0)+Valuation!$B$14-Valuation!$B$15)/Valuation!$B$17)/Assumptions!$E$22*Assumptions!$E$23 -> 181.30829
A7: =Assumptions!$E$21+0 -> 0.04 | B7: =((Valuation!$B$5/(1+B$4)^1+Valuation!$C$5/(1+B$4)^2+Valuation!$D$5/(1+B$4)^3+Valuation!$E$5/(1+B$4)^4+Valuation!$F$5/(1+B$4)^5+IF(B$4>$A7,Valuation!$F$5*(1+$A7)/(B$4-$A7)/(1+B$4)^5,0)+Valuation!$B$14-Valuation!$B$15)/Valuation!$B$17)/Assumptions!$E$22*Assumptions!$E$23 -> 447.8534 | C7: =((Valuation!$B$5/(1+C$4)^1+Valuation!$C$5/(1+C$4)^2+Valuation!$D$5/(1+C$4)^3+Valuation!$E$5/(1+C$4)^4+Valuation!$F$5/(1+C$4)^5+IF(C$4>$A7,Valuation!$F$5*(1+$A7)/(C$4-$A7)/(1+C$4)^5,0)+Valuation!$B$14-Valuation!$B$15)/Valuation!$B$17)/Assumptions!$E$22*Assumptions!$E$23 -> 335.42163 | D7: =((Valuation!$B$5/(1+D$4)^1+Valuation!$C$5/(1+D$4)^2+Valuation!$D$5/(1+D$4)^3+Valuation!$E$5/(1+D$4)^4+Valuation!$F$5/(1+D$4)^5+IF(D$4>$A7,Valuation!$F$5*(1+$A7)/(D$4-$A7)/(1+D$4)^5,0)+Valuation!$B$14-Valuation!$B$15)/Valuation!$B$17)/Assumptions!$E$22*Assumptions!$E$23 -> 268.05038 | E7: =((Valuation!$B$5/(1+E$4)^1+Valuation!$C$5/(1+E$4)^2+Valuation!$D$5/(1+E$4)^3+Valuation!$E$5/(1+E$4)^4+Valuation!$F$5/(1+E$4)^5+IF(E$4>$A7,Valuation!$F$5*(1+$A7)/(E$4-$A7)/(1+E$4)^5,0)+Valuation!$B$14-Valuation!$B$15)/Valuation!$B$17)/Assumptions!$E$22*Assumptions!$E$23 -> 223.20596 | F7: =((Valuation!$B$5/(1+F$4)^1+Valuation!$C$5/(1+F$4)^2+Valuation!$D$5/(1+F$4)^3+Valuation!$E$5/(1+F$4)^4+Valuation!$F$5/(1+F$4)^5+IF(F$4>$A7,Valuation!$F$5*(1+$A7)/(F$4-$A7)/(1+F$4)^5,0)+Valuation!$B$14-Valuation!$B$15)/Valuation!$B$17)/Assumptions!$E$22*Assumptions!$E$23 -> 191.23127
A8: =Assumptions!$E$21+0.005 -> 0.045 | B8: =((Valuation!$B$5/(1+B$4)^1+Valuation!$C$5/(1+B$4)^2+Valuation!$D$5/(1+B$4)^3+Valuation!$E$5/(1+B$4)^4+Valuation!$F$5/(1+B$4)^5+IF(B$4>$A8,Valuation!$F$5*(1+$A8)/(B$4-$A8)/(1+B$4)^5,0)+Valuation!$B$14-Valuation!$B$15)/Valuation!$B$17)/Assumptions!$E$22*Assumptions!$E$23 -> 528.29793 | C8: =((Valuation!$B$5/(1+C$4)^1+Valuation!$C$5/(1+C$4)^2+Valuation!$D$5/(1+C$4)^3+Valuation!$E$5/(1+C$4)^4+Valuation!$F$5/(1+C$4)^5+IF(C$4>$A8,Valuation!$F$5*(1+$A8)/(C$4-$A8)/(1+C$4)^5,0)+Valuation!$B$14-Valuation!$B$15)/Valuation!$B$17)/Assumptions!$E$22*Assumptions!$E$23 -> 376.94282 | D8: =((Valuation!$B$5/(1+D$4)^1+Valuation!$C$5/(1+D$4)^2+Valuation!$D$5/(1+D$4)^3+Valuation!$E$5/(1+D$4)^4+Valuation!$F$5/(1+D$4)^5+IF(D$4>$A8,Valuation!$F$5*(1+$A8)/(D$4-$A8)/(1+D$4)^5,0)+Valuation!$B$14-Valuation!$B$15)/Valuation!$B$17)/Assumptions!$E$22*Assumptions!$E$23 -> 292.95067 | E8: =((Valuation!$B$5/(1+E$4)^1+Valuation!$C$5/(1+E$4)^2+Valuation!$D$5/(1+E$4)^3+Valuation!$E$5/(1+E$4)^4+Valuation!$F$5/(1+E$4)^5+IF(E$4>$A8,Valuation!$F$5*(1+$A8)/(E$4-$A8)/(1+E$4)^5,0)+Valuation!$B$14-Valuation!$B$15)/Valuation!$B$17)/Assumptions!$E$22*Assumptions!$E$23 -> 239.57444 | F8: =((Valuation!$B$5/(1+F$4)^1+Valuation!$C$5/(1+F$4)^2+Valuation!$D$5/(1+F$4)^3+Valuation!$E$5/(1+F$4)^4+Valuation!$F$5/(1+F$4)^5+IF(F$4>$A8,Valuation!$F$5*(1+$A8)/(F$4-$A8)/(1+F$4)^5,0)+Valuation!$B$14-Valuation!$B$15)/Valuation!$B$17)/Assumptions!$E$22*Assumptions!$E$23 -> 202.68085
A9: =Assumptions!$E$21+0.01 -> 0.05 | B9: =((Valuation!$B$5/(1+B$4)^1+Valuation!$C$5/(1+B$4)^2+Valuation!$D$5/(1+B$4)^3+Valuation!$E$5/(1+B$4)^4+Valuation!$F$5/(1+B$4)^5+IF(B$4>$A9,Valuation!$F$5*(1+$A9)/(B$4-$A9)/(1+B$4)^5,0)+Valuation!$B$14-Valuation!$B$15)/Valuation!$B$17)/Assumptions!$E$22*Assumptions!$E$23 -> 648.96473 | C9: =((Valuation!$B$5/(1+C$4)^1+Valuation!$C$5/(1+C$4)^2+Valuation!$D$5/(1+C$4)^3+Valuation!$E$5/(1+C$4)^4+Valuation!$F$5/(1+C$4)^5+IF(C$4>$A9,Valuation!$F$5*(1+$A9)/(C$4-$A9)/(1+C$4)^5,0)+Valuation!$B$14-Valuation!$B$15)/Valuation!$B$17)/Assumptions!$E$22*Assumptions!$E$23 -> 432.30442 | D9: =((Valuation!$B$5/(1+D$4)^1+Valuation!$C$5/(1+D$4)^2+Valuation!$D$5/(1+D$4)^3+Valuation!$E$5/(1+D$4)^4+Valuation!$F$5/(1+D$4)^5+IF(D$4>$A9,Valuation!$F$5*(1+$A9)/(D$4-$A9)/(1+D$4)^5,0)+Valuation!$B$14-Valuation!$B$15)/Valuation!$B$17)/Assumptions!$E$22*Assumptions!$E$23 -> 324.07603 | E9: =((Valuation!$B$5/(1+E$4)^1+Valuation!$C$5/(1+E$4)^2+Valuation!$D$5/(1+E$4)^3+Valuation!$E$5/(1+E$4)^4+Valuation!$F$5/(1+E$4)^5+IF(E$4>$A9,Valuation!$F$5*(1+$A9)/(E$4-$A9)/(1+E$4)^5,0)+Valuation!$B$14-Valuation!$B$15)/Valuation!$B$17)/Assumptions!$E$22*Assumptions!$E$23 -> 259.21661 | F9: =((Valuation!$B$5/(1+F$4)^1+Valuation!$C$5/(1+F$4)^2+Valuation!$D$5/(1+F$4)^3+Valuation!$E$5/(1+F$4)^4+Valuation!$F$5/(1+F$4)^5+IF(F$4>$A9,Valuation!$F$5*(1+$A9)/(F$4-$A9)/(1+F$4)^5,0)+Valuation!$B$14-Valuation!$B$15)/Valuation!$B$17)/Assumptions!$E$22*Assumptions!$E$23 -> 216.03869

Sheet Checks
A1: Formula-driven model checks
A2: Critical checks must pass after native recalculation/reopen; source coverage is computed, never hardcoded.
A4: Assertion | B4: Actual | C4: Expected | D4: Difference | E4: Tolerance | F4: Status | G4: Severity | H4: Fix hint
A5: Source records verified | B5: =COUNTIF(Sources!$Q$5:$Q$107,"VERIFIED") -> 103 | C5: =COUNTA(Sources!$A$5:$A$107) -> 103 | D5: =B5-C5 -> 0 | E5: 0 | F5: =IF(AND(D5=0,C5>0),"PASS","FAIL") -> PASS | G5: Critical | H5: Complete missing ledger rows
A6: Historical source coverage | B6: =COUNTIF(Historical!$H$5:$H$20,"CHECK") -> 0 | C6: 0 | D6: =B6-C6 -> 0 | E6: 0 | F6: =IF(ABS(D6)<=E6,"PASS","FAIL") -> PASS | G6: Critical | H6: Resolve metric-to-source mapping
A7: Revenue driver tie | B7: =Forecast!G8 -> 7483172.9 | C7: =Forecast!G5*Forecast!G6 -> 7483172.9 | D7: =B7-C7 -> 0 | E7: 0.1 | F7: =IF(ABS(D7)<=E7,"PASS","FAIL") -> PASS | G7: Critical | H7: Repair bottom-up formula
A8: Operating income tie | B8: =Forecast!G16 -> 3921182.6 | C8: =Forecast!G11-Forecast!G13-Forecast!G15 -> 3921182.6 | D8: =B8-C8 -> 0 | E8: 0.1 | F8: =IF(ABS(D8)<=E8,"PASS","FAIL") -> PASS | G8: Critical | H8: Repair operating formula
A9: FCFF tie | B9: =Forecast!G25 -> 2642142.2 | C9: =Forecast!G19+Forecast!G21-Forecast!G23-Forecast!G24 -> 2642142.2 | D9: =B9-C9 -> 0 | E9: 0.1 | F9: =IF(ABS(D9)<=E9,"PASS","FAIL") -> PASS | G9: Critical | H9: Repair FCFF formula
A10: WACC exceeds terminal growth | B10: =Assumptions!E20 -> 0.09 | C10: =Assumptions!E21 -> 0.04 | D10: =B10-C10 -> 0.05 | E10: 0 | F10: =IF(D10>E10,"PASS","FAIL") -> PASS | G10: Critical | H10: Adjust WACC / g
A11: Valuation bridge | B11: =Valuation!B16 -> 44776455 | C11: =Valuation!B13+Valuation!B14-Valuation!B15 -> 44776455 | D11: =B11-C11 -> 0 | E11: 0.1 | F11: =IF(ABS(D11)<=E11,"PASS","FAIL") -> PASS | G11: Critical | H11: Repair bridge
A12: Sensitivity center tie | B12: =Sensitivity!D7 -> 268.05038 | C12: =Valuation!B21 -> 268.05038 | D12: =B12-C12 -> 0 | E12: 0.1 | F12: =IF(ABS(D12)<=E12,"PASS","FAIL") -> PASS | G12: Critical | H12: Repair matrix
A13: Scenario selector valid | B13: =Assumptions!B3 -> 1 | C13: 1 | D13: =IF(OR(B13=1,B13=2,B13=3),0,1) -> 0 | E13: 0 | F13: =IF(D13=0,"PASS","FAIL") -> PASS | G13: Critical | H13: Reset 1/2/3
A14: Forecast revenue non-negative | B14: =MIN(Forecast!C8:G8) -> 4525156.5 | C14: 0 | D14: =B14-C14 -> 4525156.5 | E14: 0 | F14: =IF(D14>=0,"PASS","FAIL") -> PASS | G14: Critical | H14: Review drivers
A15: Cash and debt non-negative | B15: =MIN(Forecast!B26:G27) -> 1032987.7 | C15: 0 | D15: =B15-C15 -> 1032987.7 | E15: 0 | F15: =IF(D15>=0,"PASS","FAIL") -> PASS | G15: Critical | H15: Review balances
A16: Traded-security price positive | B16: =Valuation!B21 -> 268.05038 | C16: 0 | D16: =B16-C16 -> 268.05038 | E16: 0 | F16: =IF(D16>0,"PASS","FAIL") -> PASS | G16: Critical | H16: Review FX / ADR bridge
A17: Semantic KPI links | B17: 8 | C17: 8 | D17: =B17-C17 -> 0 | E17: 0 | F17: =IF(AND(ABS(Sector_KPIs!D5-Forecast!G5)<0.1,ISTEXT(Sector_KPIs!D6),ABS(Sector_KPIs!D7-Forecast!G7)<0.000001,ISTEXT(Sector_KPIs!D8),ABS(Sector_KPIs!D9-Forecast!G6)<0.1,ABS(Sector_KPIs!D10-Forecast!G10)<0.000001,ABS(Sector_KPIs!D11-Forecast!G12)<0.000001,ISTEXT(Sector_KPIs!D12)),"PASS","FAIL") -> PASS | G17: Critical | H17: Repair company-specific KPI links
A18: KPI unit / range sanity | B18: =1 -> 1 | C18: =1 -> 1 | D18: =B18-C18 -> 0 | E18: 0 | F18: =IF(AND(Sector_KPIs!B5>0,Sector_KPIs!B6>0,Sector_KPIs!B7>=0,Sector_KPIs!B7<=1,Sector_KPIs!B8>=0,Sector_KPIs!B8<=1,Sector_KPIs!B9>10000,Sector_KPIs!B9<1000000,Sector_KPIs!B10>=0,Sector_KPIs!B10<=1,Sector_KPIs!B11>=0,Sector_KPIs!B11<=1,Sector_KPIs!B12=1,Sector_KPIs!D5>0,Sector_KPIs!D7>=0,Sector_KPIs!D7<=1,Sector_KPIs!D9>10000,Sector_KPIs!D9<1000000,Sector_KPIs!D10>=0,Sector_KPIs!D10<=1,Sector_KPIs!D11>=0,Sector_KPIs!D11<=1),"PASS","FAIL") -> PASS | G18: Critical | H18: Repair units or economic ranges
A19: Source target-cell link coverage | B19: =COUNTA(Sources!$L$5:$L$107) -> 103 | C19: =COUNTA(Sources!$A$5:$A$107) -> 103 | D19: =B19-C19 -> 0 | E19: 0 | F19: =IF(ABS(D19)<=E19,"PASS","FAIL") -> PASS | G19: Critical | H19: Add exact sheet-and-cell targets
A20: Source unit completeness | B20: =COUNTBLANK(Sources!$E$5:$E$107) -> 0 | C20: 0 | D20: =B20-C20 -> 0 | E20: 0 | F20: =IF(ABS(D20)<=E20,"PASS","FAIL") -> PASS | G20: Critical | H20: Populate source units
A21: Exact source URL completeness | B21: =COUNTA(Sources!$N$5:$N$107) -> 103 | C21: =COUNTA(Sources!$A$5:$A$107) -> 103 | D21: =B21-C21 -> 0 | E21: 0 | F21: =IF(ABS(D21)<=E21,"PASS","FAIL") -> PASS | G21: Critical | H21: Use exact primary-source URLs
A23: Overall gate | B23: =IF(COUNTIF(F5:F21,"FAIL")=0,"PASS","FAIL") -> PASS
A24: Decision use | B24: Owner-ready only after independent review

Sheet Sector_KPIs
A1: Semiconductor operating KPI framework
A2: Reported sector drivers plus formula-linked active outputs; no generic blanks.
A4: KPI | B4: Reported latest | C4: Unit | D4: Forecast / active output | E4: Source / method | F4: Status
A5: Wafer shipments | B5: 15 | C5: m 12-inch equivalent | D5: =Forecast!G5 -> 22.030474 | E5: Official FY2025 annual report | F5: =IF(COUNTIF(Sources!$L$5:$L$107,"Sector_KPIs!B5")>=1,"VERIFIED","CHECK") -> VERIFIED
A6: Annual capacity | B6: 17 | C6: m 12-inch equivalent | D6: ="Context only / reported capacity" -> Context only / reported capacity | E6: Official FY2025 annual report; more than 17m | F6: =IF(COUNTIF(Sources!$L$5:$L$107,"Sector_KPIs!B6")>=1,"VERIFIED","CHECK") -> VERIFIED
A7: Advanced technologies mix | B7: 0.74 | C7: % wafer revenue | D7: =Forecast!G7 -> 0.8775 | E7: 7nm and below | F7: =IF(COUNTIF(Sources!$L$5:$L$107,"Sector_KPIs!B7")>=1,"VERIFIED","CHECK") -> VERIFIED
A8: 3nm mix | B8: 0.24 | C8: % wafer revenue | D8: ="Context only / reported node mix" -> Context only / reported node mix | E8: Official FY2025 annual report | F8: =IF(COUNTIF(Sources!$L$5:$L$107,"Sector_KPIs!B8")>=1,"VERIFIED","CHECK") -> VERIFIED
A9: Blended revenue / wafer | B9: =IF(B5<>0,Historical!F5/B5,0) -> 253936.95 | C9: TWD / wafer | D9: =Forecast!G6 -> 339673.72 | E9: Formula-derived: TWDm revenue divided by million wafers | F9: =IF(COUNTIF(Sources!$L$5:$L$107,"Sector_KPIs!B9")>=1,"VERIFIED","CHECK") -> VERIFIED
A10: Gross margin | B10: =Historical!F8 -> 0.59891349 | C10: % | D10: =Forecast!G10 -> 0.615 | E10: SEC FY2025 20-F / formula-derived | F10: =IF(COUNTIF(Sources!$L$5:$L$107,"Sector_KPIs!B10")>=1,"VERIFIED","CHECK") -> VERIFIED
A11: R&D intensity | B11: =IF(Historical!F5<>0,Historical!F14/Historical!F5,0) -> 0.064695113 | C11: % | D11: =Forecast!G12 -> 0.065 | E11: SEC FY2025 20-F / formula-derived | F11: =IF(COUNTIF(Sources!$L$5:$L$107,"Sector_KPIs!B11")>=1,"VERIFIED","CHECK") -> VERIFIED
A12: 2nm high-volume manufacturing | B12: 1 | C12: milestone | D12: ="Context only / reported milestone" -> Context only / reported milestone | E12: Q4 FY2025 commencement | F12: =IF(COUNTIF(Sources!$L$5:$L$107,"Sector_KPIs!B12")>=1,"VERIFIED","CHECK") -> VERIFIED

Sheet Change_Log
A1: Change log and governance
A2: Controlled rebuild; prior workbook preserved unchanged.
A4: Date | B4: Version | C4: Author | D4: Change | E4: Evidence | F4: Reviewer status | G4: Disposition
A5: 2026-07-16 | B5: 2.0 | C5: Codex | D5: Preserved prior ten sheets; appended Gate_9of10 | E5: Prior SHA-256 dbde913bb4c66e4f95db6e558a5f2d365555e8274a0e46127715a0ba22f5e655 | F5: Builder verified | G5: No overwrite
A6: 2026-07-16 | B6: 2.0 | C6: Codex | D6: Native-currency exact-source history | E6: Sources + Historical | F6: Builder verified | G6: Independent review pending
A7: 2026-07-16 | B7: 2.0 | C7: Codex | D7: Company-specific forecast, DCF, sensitivity and checks | E7: Forecast + Valuation + Checks | F7: Builder verified | G7: Independent review pending
A8: 2026-07-16 | B8: 2.0 | C8: Codex | D8: Native recalc/reopen and full-sheet QA | E8: internal QA evidence (not published) | F8: Post-LO evidence | G8: Independent review pending
A9: 2026-07-16 | B9: 2.1 | C9: Codex | D9: Repaired KPI semantics, exact source targets, unit/range/link gates and TSMC H1/H2/H5 | E9: Sector_KPIs + Sources + Checks + Gate_9of10 | F9: High-effort repair; independent review pending | G9: Frozen only after native recalc and hash-bound QA
A11: 46224 | B11: Ola 2 IG elevation: added IS_Hist/BS_Hist/CF_Hist/USD_Hist (TWD native, FY2021A-FY2025A; full line detail FY2023-25 or FY2024-25 per 20-F R-files, summary aggregates FY2021-22/23 per companyfacts.json, gaps documented not estimated), Sources_Audited (real claim ledger), Checks_TieOut (26 real cross-checks against independently entered source constants, replacing self-referential label-lookup checks), Forecast_v2 (5yr driver-built Base/Bull/Bear off FY2025A). Legacy Checks/Sources/Gate_9of10/Forecast/Historical/Valuation left unmodified (no check weakened, no sheet deleted). Root workbook untouched; built via Mog SDK only. | C11: Claude (run 24e4a1f1)
A13: 46248 | B13: 2.2-cobertura | C13: Claude Opus 5 (capa de cobertura, Ola 1 de la flota internacional) | D13: Capa de cobertura 2026-08-14, patron del piloto Apple (post-refutacion): se agregaron las hojas Drivers_MDA (drivers del MD&A del Form 20-F FY2021A-FY2025A: ingresos por plataforma, geografia y producto con ties duros al IS auditado; wafer revenue por nodo en absolutos con tie al wafer revenue; embarques, capacidad y utilizacion implicita; concentracion de clientes; FX promedio; empleados; capex y expansion global Arizona/Kumamoto/Dresde; bloque geopolitico cualitativo; NOT_AVAILABLE declarados; puente a Forecast_v2) y Market_Package (precio ADS, acciones, market cap, spot TWD/USD, puente a EV, Rf/ERP/beta/Kd/tasa efectiva, WACC fechado, multiplos FY2025A, control de procedencia mecanizado, hallazgos H1-H4 y limitaciones L1-L6). 17 tie-outs nuevos en Checks_TieOut (filas 29-45) + conteo mecanizado en B3; el rango del gate maestro B2 paso de H5:H27 a H5:H45 (endurece, no debilita). UNICA celda preexistente modificada: Checks_TieOut!B2. Ninguna hoja historica ni el DCF fueron tocados; hallazgos declarados, no corregidos. Construido solo con Mog SDK. | E13: SHA-256 previo 3f12d5027a534e51f36614ca43079082b83495893e2900cfd7baddc6dbe8f18b; respaldo pre-cobertura en scratchpad de la corrida. Fuentes: 20-F FY2022 accn 0001193125-23-107214, FY2023 accn 0001193125-24-099840, FY2024 accn 0001193125-25-083423, FY2025 accn 0001628280-26-025362 (PDFs locales tsmc/, pdftotext -layout); mercado: stockanalysis.com, tradingeconomics.com, treasury.gov, Damodaran -- cada input fechado en Market_Package col D. | F13: Builder verificado; refutacion independiente pendiente | G13: Aditivo. Los 23 checks originales quedan intactos y en PASS; master ampliado a 40 checks

Sheet Gate_9of10
A1: 9-of-10 gate evidence
A2: Owner evidence register aligned exactly to the governing independent rubric; PASS means ready for review, not self-certification.
A4: Gate | B4: Weight | C4: Earned | D4: Status | E4: Exact workbook / external evidence | F4: Blocker class | G4: Notes
A5: H0 Controlled lineage / package | B5: 5 | C5: =IF(D5="PASS",B5,0) -> 5 | D5: PASS | E5: Change_Log!A5:G5; internal QA evidence (not published) | F5: Lineage | G5: Prior file preserved; 10-sheet order + Gate_9of10
A6: H1 Source fidelity | B6: 20 | C6: =IF(D6="PASS",B6,0) -> 20 | D6: =IF(AND(Checks!F5="PASS",Checks!F6="PASS",COUNTIF(Checks!F19:F21,"FAIL")=0),"PASS","FAIL") -> PASS | E6: Sources!A4:R; Checks!A5:F6; Checks!A19:F21 | F6: Source | G6: Claim-level exact-source ledger
A7: H2 Historical / formula / schedule mechanics | B7: 15 | C7: =IF(D7="PASS",B7,0) -> 15 | D7: =IF(AND(COUNTIF(Historical!H5:H20,"CHECK")=0,COUNTIF(Checks!F7:F9,"FAIL")=0,Checks!F17="PASS",Checks!F18="PASS"),"PASS","FAIL") -> PASS | E7: Historical!A4:H20; Forecast!A5:G28; Sector_KPIs!A4:F12; Checks!A7:F9; Checks!A17:F18 | F7: Mechanics | G7: Native history and formula-driven operating schedule
A8: H3 Scenario / sensitivity | B8: 10 | C8: =IF(D8="PASS",B8,0) -> 10 | D8: =IF(AND(Checks!F12="PASS",Checks!F13="PASS"),"PASS","FAIL") -> PASS | E8: Assumptions!B3:E24; Sensitivity!A4:F9; Checks!A12:F13 | F8: Scenario | G8: B/B/B perturb-reset evidence in support JSON
A9: H4 Valuation fit / mechanics | B9: 15 | C9: =IF(D9="PASS",B9,0) -> 15 | D9: =IF(AND(Checks!F10="PASS",Checks!F11="PASS",Checks!F12="PASS",Valuation!B21>0),"PASS","FAIL") -> PASS | E9: Valuation!A4:G23; Checks!A10:F12 | F9: Valuation | G9: Native-currency DCF and dated security bridge
A10: H5 Checks / error state | B10: 8 | C10: =IF(D10="PASS",B10,0) -> 8 | D10: =IF(Checks!B23="PASS","PASS","FAIL") -> PASS | E10: Checks!A4:H23; internal QA evidence (not published) | F10: Checks | G10: All critical checks and post-recalc error scan
A11: H6 Native recalc / reproducibility | B11: 10 | C11: =IF(D11="PASS",B11,0) -> 10 | D11: PASS | E11: internal QA evidence (not published) | native LibreOffice x2 + reopen | F11: Recalc | G11: Two unique LibreOffice profiles; evidence bound to final SHA-256
A12: H7 Post-recalc visual QA | B12: 7 | C12: =IF(D12="PASS",B12,0) -> 7 | D12: PASS | E12: internal QA evidence (not published) | F12: Visual | G12: Every final sheet rendered and reviewed
A13: H8 Economic upgrade | B13: 5 | C13: =IF(D13="PASS",B13,0) -> 5 | D13: =IF(AND(Forecast!G8>0,COUNTIF(Sector_KPIs!F5:F12,"VERIFIED")=8,Checks!F17="PASS",Checks!F18="PASS"),"PASS","FAIL") -> PASS | E13: Forecast!A5:G28; Sector_KPIs!A4:F | F13: Economics | G13: Company-specific semiconductor operating build
A14: H9 Governance / handoff | B14: 5 | C14: =IF(D14="PASS",B14,0) -> 5 | D14: PASS | E14: 00_Cover!A14:B18; Change_Log!A4:G8; Gate_9of10!A16:B18 | F14: Governance | G14: Independent certification remains pending
A16: Owner score | B16: =SUM(C5:C14) -> 100
A17: Decision | B17: =IF(AND(B16>=90,COUNTIF(D5:D14,"FAIL")=0),"READY FOR INDEPENDENT 9/10 REVIEW","OWNER DEMOTION / REMEDIATE") -> READY FOR INDEPENDENT 9/10 REVIEW
A18: Independent certification | B18: PENDING

Sheet IS_Hist
A1: TSMC -- Consolidated Statements of Profit or Loss (audited, IFRS)
A2: TWD millions. FY2023A-FY2025A per FY2025 20-F R4 (full line detail). FY2021A-FY2022A per SEC EDGAR companyfacts.json ifrs-full tags (as originally reported comparative figures) -- opex/non-op detail for those two years not in this package, left blank rather than estimated.
A4: Line item | B4: FY2021A | C4: FY2022A | D4: FY2023A | E4: FY2024A | F4: FY2025A | H4: Note/Tag ref
A5: Net revenue | B5: 1587415 | C5: 2263891.3 | D5: 2161735.8 | E5: 2894307.7 | F5: 3809054.3 | H5: R4 / ifrs-full:Revenue
A6: Cost of revenue | B6: 767877.7 | C6: 915536.5 | D6: 986625.2 | E6: 1269954.1 | F6: 1527760.3 | H6: R4 / ifrs-full:CostOfSales
A7: Gross profit | B7: 819537.3 | C7: 1348354.8 | D7: 1175110.6 | E7: 1624353.6 | F7: 2281294 | H7: R4 / ifrs-full:GrossProfit
A8: Operating expenses
A9: Research and development | D9: 182370.2 | E9: 204181.8 | F9: 246427.2 | H9: R4 (FY23-25 only)
A10: General and administrative | D10: 60872.8 | E10: 83745 | F10: 82304.3 | H10: R4 (FY23-25 only)
A11: Marketing | D11: 10590.7 | E11: 13143.6 | F11: 16918.1 | H11: R4 (FY23-25 only)
A12: Total operating expenses | D12: 253833.7 | E12: 301070.4 | F12: 345649.6 | H12: R4 (FY23-25 only)
A13: Other operating income and expenses, net | D13: 188.7 | E13: -1230.2 | F13: 447.3 | H13: R4 (FY23-25 only)
A14: Income from operations | D14: 921465.6 | E14: 1322053 | F14: 1936091.7 | H14: R4 (FY23-25 only; FY21-22 not separately disclosed in companyfacts)
A15: Non-operating income and expenses
A16: Share of profits of associates | D16: 4800.2 | E16: 4880.7 | F16: 5488.5 | H16: R4 (FY23-25 only)
A17: Interest income | D17: 60293.9 | E17: 87213.4 | F17: 105739.1 | H17: R4 (FY23-25 only)
A18: Other income | D18: 480 | E18: 566.9 | F18: 591.7 | H18: R4 (FY23-25 only)
A19: Foreign exchange gain (loss), net | D19: -2685.4 | E19: 10000.8 | F19: 13831.3 | H19: R4 (FY23-25 only)
A20: Finance costs | D20: -11999.4 | E20: -10495.4 | F20: -12370.4 | H20: R4 (FY23-25 only)
A21: Other gains and losses, net | D21: 6961.6 | E21: -8379.4 | F21: -7717.2 | H21: R4 (FY23-25 only)
A22: Total non-operating income and expenses | D22: 57850.9 | E22: 83787 | F22: 105563 | H22: R4 (FY23-25 only)
A23: Income before income tax | B23: 663036 | C23: 1144072.2 | D23: 979316.5 | E23: 1405840 | F23: 2041654.7 | H23: R4 / ifrs-full:ProfitLossBeforeTax
A24: Income tax expense | B24: 70155.4 | C24: 150777.5 | D24: 128288.8 | E24: 248316.1 | F24: 346529.8 | H24: R4 / ifrs-full:IncomeTaxExpenseContinuingOperations
A25: Net income | B25: 592880.6 | C25: 993294.7 | D25: 851027.7 | E25: 1157523.9 | F25: 1695124.9 | H25: R4 / ifrs-full:ProfitLoss
A26: Net income attributable to:
A27: Owners of the parent (EPS numerator) | D27: 851740 | E27: 1158380.2 | F27: 1697604 | H27: R139 EPS Details (FY23-25 only)
A28: Non-controlling interests | D28: -712.3 | E28: -856.3 | F28: -2479.1 | H28: derived: NI - parent (FY23-25 only)
A30: Earnings per share - basic (TWD) | D30: 32.85 | E30: 44.68 | F30: 65.47 | H30: R139
A31: Earnings per share - diluted (TWD) | D31: 32.85 | E31: 44.67 | F31: 65.47 | H31: R139

Sheet BS_Hist
A1: TSMC -- Consolidated Statements of Financial Position (audited, IFRS)
A2: TWD millions, as of Dec 31. FY2024A-FY2025A per FY2025 20-F R3 (full line detail). FY2021A-FY2023A summary aggregates only per companyfacts.json.
A4: Line item | B4: FY2021A | C4: FY2022A | D4: FY2023A | E4: FY2024A | F4: FY2025A | H4: Note/Tag ref
A5: CURRENT ASSETS
A6: Cash and cash equivalents | B6: 1064990.2 | C6: 1342814.1 | D6: 1465427.8 | E6: 2127627 | F6: 2767856.4 | H6: R3 (FY24-25) / ifrs-full:CashAndCashEquivalents (FY21-23)
A7: Financial assets at FVTPL | E7: 207.7 | F7: 100.2 | H7: R3 (FY24-25 only)
A8: Financial assets at FVOCI | E8: 192202.7 | F8: 175692.7 | H8: R3 (FY24-25 only)
A9: Financial assets at amortized cost | E9: 101971.3 | F9: 124945.5 | H9: R3 (FY24-25 only)
A10: Hedging financial assets | E10: 11 | F10: 0 | H10: R3 (FY24-25 only)
A11: Notes and accounts receivable, net | E11: 270683.2 | F11: 279051.6 | H11: R3 (FY24-25 only)
A12: Receivables from related parties | E12: 1404.5 | F12: 2739.5 | H12: R3 (FY24-25 only)
A13: Other receivables from related parties | E13: 0.2 | F13: 268.1 | H13: R3 (FY24-25 only)
A14: Inventories | B14: 193102.3 | C14: 221149.1 | D14: 250997.1 | E14: 287868.8 | F14: 288109.5 | H14: R3 (FY24-25) / ifrs-full:Inventories (FY21-23)
A15: Other financial assets | E15: 63138.3 | F15: 59702.9 | H15: R3 (FY24-25 only)
A16: Other current assets | E16: 43237.4 | F16: 118664.4 | H16: R3 (FY24-25 only)
A17: Total current assets | B17: 1607072.9 | C17: 2052896.7 | D17: 2194032.9 | E17: 3088352.1 | F17: 3817130.8 | H17: R3 (FY24-25) / ifrs-full:CurrentAssets (FY21-23)
A18: NONCURRENT ASSETS
A19: Financial assets at FVTPL (noncurrent) | E19: 15199.8 | F19: 15032.1 | H19: R3 (FY24-25 only)
A20: Financial assets at FVOCI (noncurrent) | E20: 7822.9 | F20: 8797.2 | H20: R3 (FY24-25 only)
A21: Financial assets at amortized cost (noncurrent) | E21: 88596.5 | F21: 110507.8 | H21: R3 (FY24-25 only)
A22: Investments accounted for using equity method | E22: 37247.8 | F22: 37851.9 | H22: R3 (FY24-25 only)
A23: Property, plant and equipment | B23: 1975118.7 | C23: 2693837 | D23: 3064475 | E23: 3234980.1 | F23: 3691840.9 | H23: R3 (FY24-25) / ifrs-full:PropertyPlantAndEquipment (FY21-23)
A24: Right-of-use assets | E24: 40128.4 | F24: 43918.9 | H24: R3 (FY24-25 only)
A25: Intangible assets | E25: 26282.5 | F25: 24952.6 | H25: R3 (FY24-25 only)
A26: Deferred income tax assets | E26: 65943.3 | F26: 62940.3 | H26: R3 (FY24-25 only)
A27: Refundable deposits | E27: 5495.9 | F27: 4242.6 | H27: R3 (FY24-25 only)
A28: Other noncurrent assets | E28: 81715.4 | F28: 115627.4 | H28: R3 (FY24-25 only)
A29: Total noncurrent assets | B29: 2118229.3 | C29: 2911562.4 | D29: 3338163.7 | E29: 3603412.6 | F29: 4115711.7 | H29: R3 (FY24-25) / ifrs-full:NoncurrentAssets (FY21-23)
A30: TOTAL ASSETS | B30: 3725302.2 | C30: 4964459.1 | D30: 5532196.6 | E30: 6691764.7 | F30: 7932842.5 | H30: R3 (FY24-25) / ifrs-full:Assets (FY21-23)
A32: CURRENT LIABILITIES
A33: Financial liabilities at FVTPL | E33: 466.5 | F33: 3083.9 | H33: R3 (FY24-25 only)
A34: Hedging financial liabilities | E34: 0 | F34: 0.8 | H34: R3 (FY24-25 only)
A35: Accounts payable | E35: 72800.6 | F35: 82551.6 | H35: R3 (FY24-25 only)
A36: Payables to related parties | E36: 1426 | F36: 1778.7 | H36: R3 (FY24-25 only)
A37: Salary and bonus payable | E37: 47451.5 | F37: 63872.9 | H37: R3 (FY24-25 only)
A38: Accrued profit sharing bonus to employees & directors | E38: 70871.2 | F38: 103355.3 | H38: R3 (FY24-25 only)
A39: Payables to contractors and equipment suppliers | E39: 192635.2 | F39: 177730.3 | H39: R3 (FY24-25 only)
A40: Cash dividends payable | E40: 220418.8 | F40: 285258.1 | H40: R3 (FY24-25 only)
A41: Income tax payable | E41: 191569.4 | F41: 266732.6 | H41: R3 (FY24-25 only)
A42: Long-term liabilities - current portion | E42: 59857.9 | F42: 136925.7 | H42: R3 (FY24-25 only)
A43: Accrued expenses and other current liabilities | E43: 451158.8 | F43: 401124.1 | H43: R3 (FY24-25 only)
A44: Total current liabilities | B44: 758352.8 | C44: 986563.6 | D44: 942805.1 | E44: 1308655.9 | F44: 1522414 | H44: R3 (FY24-25) / ifrs-full:CurrentLiabilities (FY21-23)
A45: NONCURRENT LIABILITIES
A46: Bonds payable | E46: 926604.5 | F46: 856227.5 | H46: R3 (FY24-25 only)
A47: Long-term bank loans | E47: 31824.4 | F47: 39834.5 | H47: R3 (FY24-25 only)
A48: Deferred income tax liabilities | E48: 3988.5 | F48: 3888.8 | H48: R3 (FY24-25 only)
A49: Lease liabilities | E49: 28755.3 | F49: 31595 | H49: R3 (FY24-25 only)
A50: Net defined benefit liability | E50: 7580.7 | F50: 6012.3 | H50: R3 (FY24-25 only)
A51: Guarantee deposits | E51: 845.6 | F51: 764.2 | H51: R3 (FY24-25 only)
A52: Others | E52: 104238.2 | F52: 75887 | H52: R3 (FY24-25 only)
A53: Total noncurrent liabilities | B53: 815266.9 | C53: 1060063.1 | D53: 1135525 | E53: 1103837.2 | F53: 1014209.3 | H53: R3 (FY24-25) / ifrs-full:NoncurrentLiabilities (FY21-23)
A54: TOTAL LIABILITIES | B54: 1573619.7 | C54: 2046626.7 | D54: 2078330.1 | E54: 2412493.1 | F54: 2536623.3 | H54: R3 (FY24-25) / ifrs-full:Liabilities (FY21-23)
A56: EQUITY ATTRIBUTABLE TO SHAREHOLDERS OF THE PARENT
A57: Capital stock | E57: 259327.3 | F57: 259325.3 | H57: R3 (FY24-25 only)
A58: Capital surplus | E58: 73260.8 | F58: 73445.6 | H58: R3 (FY24-25 only)
A59: Retained earnings - legal capital reserve | E59: 311147 | F59: 311147 | H59: R3 (FY24-25 only)
A60: Retained earnings - special capital reserve | E60: 0 | F60: 87284.5 | H60: R3 (FY24-25 only)
A61: Retained earnings - unappropriated | E61: 3561826.4 | F61: 4640512.7 | H61: R3 (FY24-25 only)
A62: Total retained earnings | E62: 3872973.4 | F62: 5038944.2 | H62: R3 (FY24-25 only)
A63: Others (OCI reserves) | E63: 38705 | F63: -16676.4 | H63: R3 (FY24-25 only)
A64: Equity attributable to shareholders of the parent | B64: 2149259.8 | C64: 2903019.7 | D64: 3429522.4 | E64: 4244266.5 | F64: 5355038.7 | H64: R3 (FY24-25) / ifrs-full:EquityAttributableToOwnersOfParent (FY21-23)
A65: Non-controlling interests | B65: 2422.7 | C65: 14812.7 | D65: 24344.1 | E65: 35005.1 | F65: 41180.5 | H65: R3 (FY24-25) / ifrs-full:NoncontrollingInterests (FY21-23)
A66: Total equity | B66: 2151682.5 | C66: 2917832.4 | D66: 3453866.5 | E66: 4279271.6 | F66: 5396219.2 | H66: R3 (FY24-25) / ifrs-full:Equity (FY21-23)
A67: TOTAL LIABILITIES AND EQUITY | B67: 3725302.2 | C67: 4964459.1 | D67: 5532196.6 | E67: 6691764.7 | F67: 7932842.5 | H67: R3 (FY24-25); FY21-23 = TL+TE (source states TOTAL only)

Sheet CF_Hist
A1: TSMC -- Consolidated Statements of Cash Flows (audited, IFRS)
A2: TWD millions. FY2023A-FY2025A per FY2025 20-F R6 (line items netted into logical groups per line-item column H). FY2021A-FY2022A summary per companyfacts.json; FX effect for those years is an implied residual (documented).
A4: Line item | B4: FY2021A | C4: FY2022A | D4: FY2023A | E4: FY2024A | F4: FY2025A | H4: Note/Tag ref
A5: OPERATING ACTIVITIES
A6: Income before income tax | D6: 979316.5 | E6: 1405840 | F6: 2041654.7 | H6: R6 (FY23-25 only)
A7: Depreciation expense | D7: 522932.7 | E7: 653610.5 | F7: 679684 | H7: R6 (FY23-25 only)
A8: Amortization expense | D8: 9258.2 | E8: 9186.1 | F8: 8412.4 | H8: R6 (FY23-25 only)
A9: Other operating adjustments (net) | D9: -52813 | E9: -72170.3 | F9: -90466 | H9: R6 (FY23-25 only; ECL/finance costs/associates/interest income/SBC/disposal & impairment/FX/dividend income/other, netted)
A10: Changes in operating assets and liabilities (net) | D10: -56852 | E10: 13350.9 | F10: -96752 | H10: R6 (FY23-25 only)
A11: Cash generated from operations | D11: 1401842.4 | E11: 2009817.2 | F11: 2542533.1 | H11: R6 (FY23-25 only)
A12: Income taxes paid | D12: -159875.1 | E12: -183640.1 | F12: -267557.5 | H12: R6 (FY23-25 only)
A13: Net cash generated by operating activities | B13: 1112160.7 | C13: 1610599.2 | D13: 1241967.3 | E13: 1826177.1 | F13: 2274975.6 | H13: R6 (FY23-25) / ifrs-full:CashFlowsFromUsedInOperatingActivities (FY21-22)
A14: INVESTING ACTIVITIES
A15: Acquisitions of property, plant and equipment | D15: -949816.8 | E15: -956006.5 | F15: -1272410.5 | H15: R6 (FY23-25 only)
A16: Acquisitions of intangible assets | D16: -5518.4 | E16: -8875.7 | F16: -10146.9 | H16: R6 (FY23-25 only)
A17: Acquisitions of financial instruments (FVTPL/FVOCI/amortized cost/hedging) | D17: -226282 | E17: -244361.5 | F17: -256003.5 | H17: R6 (FY23-25 only)
A18: Proceeds from disposal/redemption of financial instruments | D18: 170304.4 | E18: 186035.4 | F18: 218256 | H18: R6 (FY23-25 only)
A19: Proceeds from disposal of PP&E / intangible assets | D19: 707 | E19: 951.8 | F19: 797 | H19: R6 (FY23-25 only)
A20: Interest received | D20: 55887.2 | E20: 76434.1 | F20: 98954.7 | H20: R6 (FY23-25 only)
A21: Proceeds from government grants | D21: 47545.9 | E21: 75164.3 | F21: 76258.8 | H21: R6 (FY23-25 only)
A22: Dividends received (other + equity-method) | D22: 3521.6 | E22: 3507 | F22: 3939.6 | H22: R6 (FY23-25 only)
A23: Other investing activities (net) | D23: -2469.5 | E23: 2308.3 | F23: -4038.6 | H23: R6 (FY23-25 only; refundable deposits, derivative de-recognition, other)
A24: Net cash used in investing activities | B24: -836365.8 | C24: -1190928.3 | D24: -906120.6 | E24: -864842.8 | F24: -1144393.4 | H24: R6 (FY23-25) / ifrs-full:CashFlowsFromUsedInInvestingActivities (FY21-22)
A25: FINANCING ACTIVITIES
A26: Proceeds from issuance of bonds | D26: 85700 | E26: 34300 | F26: 86900 | H26: R6 (FY23-25 only)
A27: Repayment of bonds | D27: -18100 | E27: -7000 | F27: -54310 | H27: R6 (FY23-25 only)
A28: Proceeds from long-term bank loans | D28: 2450 | E28: 30897 | F28: 10658.4 | H28: R6 (FY23-25 only)
A29: Repayment of long-term bank loans | D29: -1756.9 | E29: -2295.6 | F29: -2710 | H29: R6 (FY23-25 only)
A30: Interest paid | D30: -17359 | E30: -18751.2 | F30: -19128.8 | H30: R6 (FY23-25 only)
A31: Cash dividends paid | D31: -291721.9 | E31: -363055.2 | F31: -466779.2 | H31: R6 (FY23-25 only)
A32: Increase in non-controlling interests | D32: 11048.8 | E32: 12177.6 | F32: 8295.4 | H32: R6 (FY23-25 only)
A33: Other financing activities (net) | D33: 24844.8 | E33: -32574.6 | F33: -3270.4 | H33: R6 (FY23-25 only; hedging bank-loan liabilities, transaction costs, treasury stock, leases, guarantee deposits, donations; FY2024 carries a TWD 1.0mm source-rounding residual vs the published total)
A34: Net cash used in financing activities | B34: 136608.5 | C34: -200244 | D34: -204894.2 | E34: -346301 | F34: -440344.6 | H34: R6 (FY23-25) / ifrs-full:CashFlowsFromUsedInFinancingActivities (FY21-22)
A35: Effect of exchange rate changes on cash | B35: -7583.8 | C35: 58397 | D35: -8338.8 | E35: 47165.9 | F35: -50008.2 | H35: R6 (FY23-25 only); FY21-22 = implied residual, not separately published
A36: Net increase (decrease) in cash | B36: 404819.6 | C36: 277823.9 | D36: 122613.7 | E36: 662199.2 | F36: 640229.4 | H36: R6 (FY23-25) / ifrs-full:IncreaseDecreaseInCashAndCashEquivalents (FY21-22)
A37: Cash and cash equivalents, beginning of year | B37: 660170.6 | C37: 1064990.2 | D37: 1342814.1 | E37: 1465427.8 | F37: 2127627 | H37: BS prior year / companyfacts
A38: Cash and cash equivalents, end of year | B38: 1064990.2 | C38: 1342814.1 | D38: 1465427.8 | E38: 2127627 | F38: 2767856.4 | H38: R6 (FY23-25) / ifrs-full:CashAndCashEquivalents

Sheet USD_Hist
A1: TSMC -- USD convenience translation (Note 9, FY2025A only)
A2: Source-documented USD amounts exist only for FY2025A (Note 9, "U.S. Dollar Amounts"); no independently sourced rate for FY2021A-FY2024A in this filing, so those columns are intentionally blank (not backed into from a modeled rate).
A4: Line item | B4: FY2021A | C4: FY2022A | D4: FY2023A | E4: FY2024A | F4: FY2025A | H4: Note/Tag ref
A5: Note 9 convenience translation rate (TWD per USD) | F5: 31.37 | H5: R4/R3/R6 Note 9 (implied from as-filed USD col)
A7: Net revenue (USD mm) | F7: 121423.5 | H7: R4 Note 9 column
A8: Gross profit (USD mm) | F8: 72722.2 | H8: R4 Note 9 column
A9: Income from operations (USD mm) | F9: 61717.9 | H9: R4 Note 9 column
A10: Net income (USD mm) | F10: 54036.5 | H10: R4 Note 9 column
A12: Total assets (USD mm) | F12: 252879.9 | H12: R3 Note 9 column
A13: Total liabilities (USD mm) | F13: 80861.4 | H13: R3 Note 9 column
A14: Total equity (USD mm) | F14: 172018.5 | H14: R3 Note 9 column
A16: Net cash generated by operating activities (USD mm) | F16: 72520.7 | H16: R6 Note 9 column
A17: Net cash used in investing activities (USD mm) | F17: -36480.5 | H17: R6 Note 9 column
A18: Net cash used in financing activities (USD mm) | F18: -14037.1 | H18: R6 Note 9 column

Sheet Checks_TieOut
A1: Real tie-out checks -- audited historical statements vs independently entered source constants (TWD millions). Supersedes the self-referential label-lookup "checks" on the legacy Checks/Gate_9of10 tabs (left in place, not weakened).
A2: MASTER | B2: =IF(COUNTIF(H5:H45,"FAIL")=0,"OK -- ALL TIE-OUTS PASS","FAIL") -> FAIL
A3: Conteo mecanizado | B3: =COUNTIF(H5:H45,"PASS")&" PASS / "&(COUNTIF(H5:H45,"PASS")+COUNTIF(H5:H45,"FAIL"))&" checks" -> 39 PASS / 40 checks
A4: Check | B4: FY2021A | C4: FY2022A | D4: FY2023A | E4: FY2024A | F4: FY2025A | H4: Status
A5: IS: Gross profit = Revenue - COGS | B5: =IS_Hist!B5-IS_Hist!B6-IS_Hist!B7 -> 0 | C5: =IS_Hist!C5-IS_Hist!C6-IS_Hist!C7 -> 0 | D5: =IS_Hist!D5-IS_Hist!D6-IS_Hist!D7 -> 0 | E5: =IS_Hist!E5-IS_Hist!E6-IS_Hist!E7 -> 0 | F5: =IS_Hist!F5-IS_Hist!F6-IS_Hist!F7 -> 0 | H5: =IF(AND(ABS(N(B5))<=0.6,ABS(N(C5))<=0.6,ABS(N(D5))<=0.6,ABS(N(E5))<=0.6,ABS(N(F5))<=0.6),"PASS","FAIL") -> PASS
A6: IS: Net income = PBT - tax | B6: =IS_Hist!B23-IS_Hist!B24-IS_Hist!B25 -> 0 | C6: =IS_Hist!C23-IS_Hist!C24-IS_Hist!C25 -> 0 | D6: =IS_Hist!D23-IS_Hist!D24-IS_Hist!D25 -> 0 | E6: =IS_Hist!E23-IS_Hist!E24-IS_Hist!E25 -> 0 | F6: =IS_Hist!F23-IS_Hist!F24-IS_Hist!F25 -> 0 | H6: =IF(AND(ABS(N(B6))<=0.6,ABS(N(C6))<=0.6,ABS(N(D6))<=0.6,ABS(N(E6))<=0.6,ABS(N(F6))<=0.6),"PASS","FAIL") -> PASS
A7: IS: Op income chain (GP - opex + other op, FY23-25) | D7: =IS_Hist!D7-IS_Hist!D12+IS_Hist!D13-IS_Hist!D14 -> 0 | E7: =IS_Hist!E7-IS_Hist!E12+IS_Hist!E13-IS_Hist!E14 -> 0 | F7: =IS_Hist!F7-IS_Hist!F12+IS_Hist!F13-IS_Hist!F14 -> 0 | H7: =IF(AND(ABS(N(D7))<=0.6,ABS(N(E7))<=0.6,ABS(N(F7))<=0.6),"PASS","FAIL") -> PASS
A8: IS: PBT chain (op income + non-op, FY23-25) | D8: =IS_Hist!D14+IS_Hist!D22-IS_Hist!D23 -> 0 | E8: =IS_Hist!E14+IS_Hist!E22-IS_Hist!E23 -> 0 | F8: =IS_Hist!F14+IS_Hist!F22-IS_Hist!F23 -> 0 | H8: =IF(AND(ABS(N(D8))<=0.6,ABS(N(E8))<=0.6,ABS(N(F8))<=0.6),"PASS","FAIL") -> PASS
A9: IS: NI = parent + NCI (FY23-25) | D9: =IS_Hist!D27+IS_Hist!D28-IS_Hist!D25 -> 0 | E9: =IS_Hist!E27+IS_Hist!E28-IS_Hist!E25 -> 0 | F9: =IS_Hist!F27+IS_Hist!F28-IS_Hist!F25 -> 0 | H9: =IF(AND(ABS(N(D9))<=0.6,ABS(N(E9))<=0.6,ABS(N(F9))<=0.6),"PASS","FAIL") -> PASS
A10: BS: Total current assets sum (FY24-25) | E10: =SUM(BS_Hist!E6:E16)-BS_Hist!E17 -> 0 | F10: =SUM(BS_Hist!F6:F16)-BS_Hist!F17 -> 0 | H10: =IF(AND(ABS(N(E10))<=0.6,ABS(N(F10))<=0.6),"PASS","FAIL") -> PASS
A11: BS: Total noncurrent assets sum (FY24-25) | E11: =SUM(BS_Hist!E19:E28)-BS_Hist!E29 -> 0 | F11: =SUM(BS_Hist!F19:F28)-BS_Hist!F29 -> 0 | H11: =IF(AND(ABS(N(E11))<=0.6,ABS(N(F11))<=0.6),"PASS","FAIL") -> PASS
A12: BS: Total assets = CA + NCA (all years) | B12: =BS_Hist!B17+BS_Hist!B29-BS_Hist!B30 -> 0 | C12: =BS_Hist!C17+BS_Hist!C29-BS_Hist!C30 -> 0 | D12: =BS_Hist!D17+BS_Hist!D29-BS_Hist!D30 -> 0 | E12: =BS_Hist!E17+BS_Hist!E29-BS_Hist!E30 -> 0 | F12: =BS_Hist!F17+BS_Hist!F29-BS_Hist!F30 -> 0 | H12: =IF(AND(ABS(N(B12))<=0.6,ABS(N(C12))<=0.6,ABS(N(D12))<=0.6,ABS(N(E12))<=0.6,ABS(N(F12))<=0.6),"PASS","FAIL") -> PASS
A13: BS: Total current liabilities sum (FY24-25) | E13: =SUM(BS_Hist!E33:E43)-BS_Hist!E44 -> 0 | F13: =SUM(BS_Hist!F33:F43)-BS_Hist!F44 -> 0 | H13: =IF(AND(ABS(N(E13))<=0.6,ABS(N(F13))<=0.6),"PASS","FAIL") -> PASS
A14: BS: Total noncurrent liabilities sum (FY24-25) | E14: =SUM(BS_Hist!E46:E52)-BS_Hist!E53 -> 0 | F14: =SUM(BS_Hist!F46:F52)-BS_Hist!F53 -> 0 | H14: =IF(AND(ABS(N(E14))<=0.6,ABS(N(F14))<=0.6),"PASS","FAIL") -> PASS
A15: BS: Total liabilities = CL + NCL (all years) | B15: =BS_Hist!B44+BS_Hist!B53-BS_Hist!B54 -> 0 | C15: =BS_Hist!C44+BS_Hist!C53-BS_Hist!C54 -> 0 | D15: =BS_Hist!D44+BS_Hist!D53-BS_Hist!D54 -> 0 | E15: =BS_Hist!E44+BS_Hist!E53-BS_Hist!E54 -> 0 | F15: =BS_Hist!F44+BS_Hist!F53-BS_Hist!F54 -> 0 | H15: =IF(AND(ABS(N(B15))<=0.6,ABS(N(C15))<=0.6,ABS(N(D15))<=0.6,ABS(N(E15))<=0.6,ABS(N(F15))<=0.6),"PASS","FAIL") -> PASS
A16: BS: Retained earnings sum = total RE (FY24-25) | E16: =SUM(BS_Hist!E59:E61)-BS_Hist!E62 -> 0 | F16: =SUM(BS_Hist!F59:F61)-BS_Hist!F62 -> 0 | H16: =IF(AND(ABS(N(E16))<=0.6,ABS(N(F16))<=0.6),"PASS","FAIL") -> PASS
A17: BS: Parent equity sum (FY24-25) | E17: =BS_Hist!E57+BS_Hist!E58+BS_Hist!E62+BS_Hist!E63-BS_Hist!E64 -> 0 | F17: =BS_Hist!F57+BS_Hist!F58+BS_Hist!F62+BS_Hist!F63-BS_Hist!F64 -> 0 | H17: =IF(AND(ABS(N(E17))<=0.6,ABS(N(F17))<=0.6),"PASS","FAIL") -> PASS
A18: BS: Total equity = parent + NCI (all years) | B18: =BS_Hist!B64+BS_Hist!B65-BS_Hist!B66 -> 0 | C18: =BS_Hist!C64+BS_Hist!C65-BS_Hist!C66 -> 0 | D18: =BS_Hist!D64+BS_Hist!D65-BS_Hist!D66 -> 0 | E18: =BS_Hist!E64+BS_Hist!E65-BS_Hist!E66 -> 0 | F18: =BS_Hist!F64+BS_Hist!F65-BS_Hist!F66 -> 0 | H18: =IF(AND(ABS(N(B18))<=0.6,ABS(N(C18))<=0.6,ABS(N(D18))<=0.6,ABS(N(E18))<=0.6,ABS(N(F18))<=0.6),"PASS","FAIL") -> PASS
A19: BS: TL&E = TL + TE (all years) | B19: =BS_Hist!B54+BS_Hist!B66-BS_Hist!B67 -> 0 | C19: =BS_Hist!C54+BS_Hist!C66-BS_Hist!C67 -> 0 | D19: =BS_Hist!D54+BS_Hist!D66-BS_Hist!D67 -> 0 | E19: =BS_Hist!E54+BS_Hist!E66-BS_Hist!E67 -> 0 | F19: =BS_Hist!F54+BS_Hist!F66-BS_Hist!F67 -> 0 | H19: =IF(AND(ABS(N(B19))<=0.6,ABS(N(C19))<=0.6,ABS(N(D19))<=0.6,ABS(N(E19))<=0.6,ABS(N(F19))<=0.6),"PASS","FAIL") -> PASS
A20: BS: Balance sheet balances (TA - TL&E, all years) | B20: =BS_Hist!B30-BS_Hist!B67 -> 0 | C20: =BS_Hist!C30-BS_Hist!C67 -> 0 | D20: =BS_Hist!D30-BS_Hist!D67 -> 0 | E20: =BS_Hist!E30-BS_Hist!E67 -> 0 | F20: =BS_Hist!F30-BS_Hist!F67 -> 0 | H20: =IF(AND(ABS(N(B20))<=0.6,ABS(N(C20))<=0.6,ABS(N(D20))<=0.6,ABS(N(E20))<=0.6,ABS(N(F20))<=0.6),"PASS","FAIL") -> PASS
A21: CF: CFO chain (FY23-25) | D21: =CF_Hist!D11+CF_Hist!D12-CF_Hist!D13 -> 0 | E21: =CF_Hist!E11+CF_Hist!E12-CF_Hist!E13 -> 0 | F21: =CF_Hist!F11+CF_Hist!F12-CF_Hist!F13 -> 0 | H21: =IF(AND(ABS(N(D21))<=0.6,ABS(N(E21))<=0.6,ABS(N(F21))<=0.6),"PASS","FAIL") -> PASS
A22: CF: Cash generated from ops = PBT + adjustments (FY23-25) | D22: =CF_Hist!D6+CF_Hist!D7+CF_Hist!D8+CF_Hist!D9+CF_Hist!D10-CF_Hist!D11 -> 0 | E22: =CF_Hist!E6+CF_Hist!E7+CF_Hist!E8+CF_Hist!E9+CF_Hist!E10-CF_Hist!E11 -> 0 | F22: =CF_Hist!F6+CF_Hist!F7+CF_Hist!F8+CF_Hist!F9+CF_Hist!F10-CF_Hist!F11 -> 0 | H22: =IF(AND(ABS(N(D22))<=0.6,ABS(N(E22))<=0.6,ABS(N(F22))<=0.6),"PASS","FAIL") -> PASS
A23: CF: Net change = CFO + CFI + CFF + FX (all years) | B23: =CF_Hist!B13+CF_Hist!B24+CF_Hist!B34+CF_Hist!B35-CF_Hist!B36 -> 0 | C23: =CF_Hist!C13+CF_Hist!C24+CF_Hist!C34+CF_Hist!C35-CF_Hist!C36 -> 0 | D23: =CF_Hist!D13+CF_Hist!D24+CF_Hist!D34+CF_Hist!D35-CF_Hist!D36 -> 0 | E23: =CF_Hist!E13+CF_Hist!E24+CF_Hist!E34+CF_Hist!E35-CF_Hist!E36 -> 0 | F23: =CF_Hist!F13+CF_Hist!F24+CF_Hist!F34+CF_Hist!F35-CF_Hist!F36 -> 0 | H23: =IF(AND(ABS(N(B23))<=0.6,ABS(N(C23))<=0.6,ABS(N(D23))<=0.6,ABS(N(E23))<=0.6,ABS(N(F23))<=0.6),"PASS","FAIL") -> PASS
A24: CF: End cash = begin + change (all years) | B24: =CF_Hist!B37+CF_Hist!B36-CF_Hist!B38 -> 0 | C24: =CF_Hist!C37+CF_Hist!C36-CF_Hist!C38 -> 0 | D24: =CF_Hist!D37+CF_Hist!D36-CF_Hist!D38 -> 0 | E24: =CF_Hist!E37+CF_Hist!E36-CF_Hist!E38 -> 0 | F24: =CF_Hist!F37+CF_Hist!F36-CF_Hist!F38 -> 0 | H24: =IF(AND(ABS(N(B24))<=0.6,ABS(N(C24))<=0.6,ABS(N(D24))<=0.6,ABS(N(E24))<=0.6,ABS(N(F24))<=0.6),"PASS","FAIL") -> PASS
A25: CF: Beginning cash = prior year end cash (FY22-25) | C25: =CF_Hist!C37-CF_Hist!B38 -> 0 | D25: =CF_Hist!D37-CF_Hist!C38 -> 0 | E25: =CF_Hist!E37-CF_Hist!D38 -> 0 | F25: =CF_Hist!F37-CF_Hist!E38 -> 0 | H25: =IF(AND(ABS(N(C25))<=0.6,ABS(N(D25))<=0.6,ABS(N(E25))<=0.6,ABS(N(F25))<=0.6),"PASS","FAIL") -> PASS
A26: X: CF end cash = BS cash (all years) | B26: =CF_Hist!B38-BS_Hist!B6 -> 0 | C26: =CF_Hist!C38-BS_Hist!C6 -> 0 | D26: =CF_Hist!D38-BS_Hist!D6 -> 0 | E26: =CF_Hist!E38-BS_Hist!E6 -> 0 | F26: =CF_Hist!F38-BS_Hist!F6 -> 0 | H26: =IF(AND(ABS(N(B26))<=0.6,ABS(N(C26))<=0.6,ABS(N(D26))<=0.6,ABS(N(E26))<=0.6,ABS(N(F26))<=0.6),"PASS","FAIL") -> PASS
A27: X: CF income before tax = IS income before tax (FY23-25) | D27: =CF_Hist!D6-IS_Hist!D23 -> 0 | E27: =CF_Hist!E6-IS_Hist!E23 -> 0 | F27: =CF_Hist!F6-IS_Hist!F23 -> 0 | H27: =IF(AND(ABS(N(D27))<=0.6,ABS(N(E27))<=0.6,ABS(N(F27))<=0.6),"PASS","FAIL") -> PASS
A28: COBERTURA -- Drivers_MDA y Market_Package, agregados 2026-08-14 (checks 29-45). Regla de diseño: cada check compara contra celdas INDEPENDIENTES (otra hoja, otra fuente, otro vintage de entrada) o acota bandas que un defecto real puede romper; los términos de recableado se declaran como tales. Nada tautológico, nada con tolerancia absurda.
A29: DRV: Ingresos por plataforma suman a las ventas netas del IS auditado (constantes de la Nota de ingresos vs constantes del R4/companyfacts -- entradas independientes) | B29: =Drivers_MDA!B14 -> 0 | C29: =Drivers_MDA!C14 -> 0 | D29: =Drivers_MDA!D14 -> 0 | E29: =Drivers_MDA!E14 -> 0 | F29: =Drivers_MDA!F14 -> 0 | H29: =IF(AND(ABS(N(B29))<=0.6,ABS(N(C29))<=0.6,ABS(N(D29))<=0.6,ABS(N(E29))<=0.6,ABS(N(F29))<=0.6),"PASS","FAIL") -> PASS
A30: DRV: Ingresos por geografía (HQ del cliente) suman a las ventas netas del IS auditado | B30: =Drivers_MDA!B38 -> 0 | C30: =Drivers_MDA!C38 -> 0 | D30: =Drivers_MDA!D38 -> 0 | E30: =Drivers_MDA!E38 -> 0 | F30: =Drivers_MDA!F38 -> 0 | H30: =IF(AND(ABS(N(B30))<=0.6,ABS(N(C30))<=0.6,ABS(N(D30))<=0.6,ABS(N(E30))<=0.6,ABS(N(F30))<=0.6),"PASS","FAIL") -> PASS
A31: DRV: Wafer + Otros (desagregación de producto) = ventas netas del IS auditado | B31: =Drivers_MDA!B51 -> 0 | C31: =Drivers_MDA!C51 -> 0 | D31: =Drivers_MDA!D51 -> 0 | E31: =Drivers_MDA!E51 -> 0 | F31: =Drivers_MDA!F51 -> 0 | H31: =IF(AND(ABS(N(B31))<=0.6,ABS(N(C31))<=0.6,ABS(N(D31))<=0.6,ABS(N(E31))<=0.6,ABS(N(F31))<=0.6),"PASS","FAIL") -> PASS
A32: DRV: Los doce nodos suman al wafer revenue publicado (ambos lados tecleados de la misma Nota pero en filas distintas: caza typos y omisiones de fila, no permutaciones -- limite declarado en Drivers_MDA!A148) | B32: =Drivers_MDA!B70 -> 0 | C32: =Drivers_MDA!C70 -> 0 | D32: =Drivers_MDA!D70 -> 0 | E32: =Drivers_MDA!E70 -> 0 | F32: =Drivers_MDA!F70 -> 0 | H32: =IF(AND(ABS(N(B32))<=0.6,ABS(N(C32))<=0.6,ABS(N(D32))<=0.6,ABS(N(E32))<=0.6,ABS(N(F32))<=0.6),"PASS","FAIL") -> PASS
A33: DRV: Mix 3/5/7nm CALCULADO de los absolutos vs los enteros REPORTADOS en la tabla del Item 5. Tolerancia 1.5pp por columna = 3 nodos x 0.5pp de redondeo a entero del emisor. Puede fallar: un absoluto corrupto mueve el calculado y la tabla no lo sigue | B33: =ABS(N(Drivers_MDA!B72)-N(Drivers_MDA!B77))+ABS(Drivers_MDA!B73-Drivers_MDA!B78)+ABS(Drivers_MDA!B74-Drivers_MDA!B79) -> 0.0067029545 | C33: =ABS(N(Drivers_MDA!C72)-N(Drivers_MDA!C77))+ABS(Drivers_MDA!C73-Drivers_MDA!C78)+ABS(Drivers_MDA!C74-Drivers_MDA!C79) -> 0.0059441685 | D33: =ABS(N(Drivers_MDA!D72)-N(Drivers_MDA!D77))+ABS(Drivers_MDA!D73-Drivers_MDA!D78)+ABS(Drivers_MDA!D74-Drivers_MDA!D79) -> 0.0071090695 | E33: =ABS(N(Drivers_MDA!E72)-N(Drivers_MDA!E77))+ABS(Drivers_MDA!E73-Drivers_MDA!E78)+ABS(Drivers_MDA!E74-Drivers_MDA!E79) -> 0.0095437321 | F33: =ABS(N(Drivers_MDA!F72)-N(Drivers_MDA!F77))+ABS(Drivers_MDA!F73-Drivers_MDA!F78)+ABS(Drivers_MDA!F74-Drivers_MDA!F79) -> 0.0036109753 | H33: =IF(AND(ABS(N(B33))<=0.015,ABS(N(C33))<=0.015,ABS(N(D33))<=0.015,ABS(N(E33))<=0.015,ABS(N(F33))<=0.015),"PASS","FAIL") -> PASS
A34: DRV: Avanzado (7nm y menores) calculado vs el porcentaje REPORTADO en prosa (50/53/58/69/74). Tolerancia 1.5pp: la prosa del emisor suma enteros redondeados (FY2022: 52.4% exacto vs 53% publicado) | B34: =ABS(Drivers_MDA!B75-Drivers_MDA!B76) -> 4.2944558e-05 | C34: =ABS(Drivers_MDA!C75-Drivers_MDA!C76) -> 0.0059441685 | D34: =ABS(Drivers_MDA!D75-Drivers_MDA!D76) -> 0.0014639445 | E34: =ABS(Drivers_MDA!E75-Drivers_MDA!E76) -> 0.0010583193 | F34: =ABS(Drivers_MDA!F75-Drivers_MDA!F76) -> 0.0036109753 | H34: =IF(AND(ABS(N(B34))<=0.015,ABS(N(C34))<=0.015,ABS(N(D34))<=0.015,ABS(N(E34))<=0.015,ABS(N(F34))<=0.015),"PASS","FAIL") -> PASS
A35: DRV: Wafer % del total calculado vs la prosa "aproximadamente 89/88/87/87/86%" del Item 4. Tolerancia 1pp (el emisor redondea a entero) | B35: =ABS(Drivers_MDA!B52-Drivers_MDA!B53) -> 0.004724064 | C35: =ABS(Drivers_MDA!C52-Drivers_MDA!C53) -> 0.0001627481 | D35: =ABS(Drivers_MDA!D52-Drivers_MDA!D53) -> 0.00083634365 | E35: =ABS(Drivers_MDA!E52-Drivers_MDA!E53) -> 0.0012391215 | F35: =ABS(Drivers_MDA!F52-Drivers_MDA!F53) -> 0.00084881909 | H35: =IF(AND(ABS(N(B35))<=0.01,ABS(N(C35))<=0.01,ABS(N(D35))<=0.01,ABS(N(E35))<=0.01,ABS(N(F35))<=0.01),"PASS","FAIL") -> PASS
A36: X-KPI: FY2025 de Drivers_MDA contra Sector_KPIs (hoja legada, entradas independientes del build de julio): mix 3nm vs B8, avanzado vs B7, embarques vs B5 (+-0.5mm), capacidad vs B6 (+-0.5mm), ingreso/wafer vs B9 (+-2%: B9 usa el redondeo "15" del emisor y esta hoja usa 15.022 exactos). F cuenta incumplimientos; 0 = todos OK | F36: =IF(ABS(N(Drivers_MDA!F72)-Sector_KPIs!B8)>0.005,1,0)+IF(ABS(Drivers_MDA!F75-Sector_KPIs!B7)>0.005,1,0)+IF(ABS(Drivers_MDA!F83-Sector_KPIs!B5)>0.5,1,0)+IF(ABS(Drivers_MDA!F84-Sector_KPIs!B6)>0.5,1,0)+IF(ABS(Drivers_MDA!F86/Sector_KPIs!B9-1)>0.02,1,0)+IF(ABS(Drivers_MDA!F117-Sector_KPIs!B12)>0,1,0) -> 0 | H36: =IF(N(F36)=0,"PASS","FAIL") -> PASS
A37: DRV: Utilización implícita en banda [50%, 115%] los cinco años. Banda, no tie: la capacidad del emisor es "aproximada" y FY2021-22 supera 100% por redondeo -- una cifra plausible y equivocada pasa (limite declarado) | B37: =IF(OR(Drivers_MDA!B85<0.5,Drivers_MDA!B85>1.15),1,0) -> 0 | C37: =IF(OR(Drivers_MDA!C85<0.5,Drivers_MDA!C85>1.15),1,0) -> 0 | D37: =IF(OR(Drivers_MDA!D85<0.5,Drivers_MDA!D85>1.15),1,0) -> 0 | E37: =IF(OR(Drivers_MDA!E85<0.5,Drivers_MDA!E85>1.15),1,0) -> 0 | F37: =IF(OR(Drivers_MDA!F85<0.5,Drivers_MDA!F85>1.15),1,0) -> 0 | H37: =IF(AND(N(B37)=0,N(C37)=0,N(D37)=0,N(E37)=0,N(F37)=0),"PASS","FAIL") -> PASS
A38: DRV: BANDAS DE PLAUSIBILIDAD (no es tie) para las constantes sin amarre mecanizado: empleados [40k, 200k], top-10 clientes [50%, 100%], cliente mayor [5%, 50%], FX promedio [25, 40]. Caza un valor absurdo; NO verifica la cifra -- verificacion manual contra el filing (Drivers_MDA!A147) | B38: =IF(OR(Drivers_MDA!B100<40000,Drivers_MDA!B100>200000),1,0)+IF(OR(Drivers_MDA!B91<0.5,Drivers_MDA!B91>1),1,0)+IF(OR(Drivers_MDA!B92<0.05,Drivers_MDA!B92>0.5),1,0)+IF(OR(Drivers_MDA!B94<25,Drivers_MDA!B94>40),1,0) -> 0 | C38: =IF(OR(Drivers_MDA!C100<40000,Drivers_MDA!C100>200000),1,0)+IF(OR(Drivers_MDA!C91<0.5,Drivers_MDA!C91>1),1,0)+IF(OR(Drivers_MDA!C92<0.05,Drivers_MDA!C92>0.5),1,0)+IF(OR(Drivers_MDA!C94<25,Drivers_MDA!C94>40),1,0) -> 0 | D38: =IF(OR(Drivers_MDA!D100<40000,Drivers_MDA!D100>200000),1,0)+IF(OR(Drivers_MDA!D91<0.5,Drivers_MDA!D91>1),1,0)+IF(OR(Drivers_MDA!D92<0.05,Drivers_MDA!D92>0.5),1,0)+IF(OR(Drivers_MDA!D94<25,Drivers_MDA!D94>40),1,0) -> 0 | E38: =IF(OR(Drivers_MDA!E100<40000,Drivers_MDA!E100>200000),1,0)+IF(OR(Drivers_MDA!E91<0.5,Drivers_MDA!E91>1),1,0)+IF(OR(Drivers_MDA!E92<0.05,Drivers_MDA!E92>0.5),1,0)+IF(OR(Drivers_MDA!E94<25,Drivers_MDA!E94>40),1,0) -> 0 | F38: =IF(OR(Drivers_MDA!F100<40000,Drivers_MDA!F100>200000),1,0)+IF(OR(Drivers_MDA!F91<0.5,Drivers_MDA!F91>1),1,0)+IF(OR(Drivers_MDA!F92<0.05,Drivers_MDA!F92>0.5),1,0)+IF(OR(Drivers_MDA!F94<25,Drivers_MDA!F94>40),1,0) -> 0 | H38: =IF(AND(N(B38)=0,N(C38)=0,N(D38)=0,N(E38)=0,N(F38)=0),"PASS","FAIL") -> PASS
A39: FCST: Las cinco anclas FY2025A de Forecast_v2 (base de revenue, GM%, opex%, non-op%, tasa impositiva -- constantes del build de julio) = los ratios del IS auditado. Tolerancia 1e-6. Caza si alguien mueve el IS o el forecast sin el otro | F39: =ABS(Drivers_MDA!F137)+ABS(Drivers_MDA!F138)+ABS(Drivers_MDA!F139)+ABS(Drivers_MDA!F140)+ABS(Drivers_MDA!F141) -> 0 | H39: =IF(ABS(N(F39))<=0.000001,"PASS","FAIL") -> PASS
A40: MKT: Precio, acciones y capitalizacion -- cableado (B11=B7*B10 y B10=B8/B9: un hardcode cae), precio dentro de +-25% del precio fechado independiente del modelo (Assumptions!E24, build 2026-07-16), y acciones dentro de +-1% de las diluidas promedio del XBRL (Historical!F20 -- TSMC no recompra; deriva real 0.007%). Un error de precio DENTRO de la banda es indetectable sin feed vivo -- limite declarado. F cuenta incumplimientos | F40: =IF(ABS(Market_Package!B11-Market_Package!B7*Market_Package!B10)>0.5,1,0)+IF(ABS(Market_Package!B10-Market_Package!B8/Market_Package!B9)>0.5,1,0)+IF(ABS(Market_Package!B7/Assumptions!E24-1)>0.25,1,0)+IF(ABS(Market_Package!B8/Historical!F20-1)>0.01,1,0) -> 0 | H40: =IF(N(F40)=0,"PASS","FAIL") -> PASS
A41: MKT: Deuda y caja del paquete contra DOS entradas independientes: los componentes del R3 (BS_Hist F42+F46+F47 y F6) deben igualar los agregados del ledger XBRL (Historical!F19 y F18, tecleados de companyfacts en el build de julio) y los del DCF (Valuation!B15 y B14, constantes de Forecast). Mecaniza que la definicion de deuda del DCF reconcilia componente a componente. F cuenta incumplimientos | F41: =IF(ABS(Market_Package!B21-Historical!F19)>0.6,1,0)+IF(ABS(Market_Package!B16-Historical!F18)>0.6,1,0)+IF(ABS(Market_Package!B21-Valuation!B15)>0.6,1,0)+IF(ABS(Market_Package!B16-Valuation!B14)>0.6,1,0) -> 0 | H41: =IF(N(F41)=0,"PASS","FAIL") -> PASS
A42: MKT: Costo de capital -- guardia del enlace vivo de la tasa efectiva (B36 debe ser exactamente IS_Hist F24/F23: una tasa tecleada en duro cae) mas BANDAS DE PLAUSIBILIDAD: Rf [0.5%, 12%], ERP [1%, 10%], beta [0.3x, 2.5x], Kd [0.1%, 15%], WACC [4%, 20%]. Una cifra plausible y equivocada dentro de banda pasa -- limite declarado (patron Apple check 54). F cuenta incumplimientos | F42: =IF(ABS(Market_Package!B36-IS_Hist!F24/IS_Hist!F23)>0.0000001,1,0)+IF(OR(Market_Package!B31<0.005,Market_Package!B31>0.12),1,0)+IF(OR(Market_Package!B32<0.01,Market_Package!B32>0.1),1,0)+IF(OR(Market_Package!B33<0.3,Market_Package!B33>2.5),1,0)+IF(OR(Market_Package!B35<0.001,Market_Package!B35>0.15),1,0)+IF(OR(Market_Package!B40<0.04,Market_Package!B40>0.2),1,0) -> 0 | H42: =IF(N(F42)=0,"PASS","FAIL") -> PASS
A43: MKT: Coherencia FX -- spot fechado dentro de +-10% del rate estructural del modelo (Assumptions!E22), dentro de +-15% del rate Note 9 del filing (USD_Hist!F5), y en banda absoluta [25, 40] TWD/USD. Tres anclas independientes; un spot con un digito corrido (3.2 o 320) cae por las tres. F cuenta incumplimientos | F43: =IF(ABS(Market_Package!B12/Assumptions!E22-1)>0.1,1,0)+IF(ABS(Market_Package!B12/USD_Hist!F5-1)>0.15,1,0)+IF(OR(Market_Package!B12<25,Market_Package!B12>40),1,0) -> 0 | H43: =IF(N(F43)=0,"PASS","FAIL") -> PASS
A44: MKT: Enterprise value -- recableado completo desde los insumos primarios (precio, acciones, ratio ADS, spot, deuda y caja de BS_Hist: caza un hardcode en CUALQUIER celda intermedia del puente), EV > 0, y banda EV/Ventas [5x, 40x] contra el IS auditado. El termino de recableado es identidad cuando las formulas estan intactas -- lo que caza defectos reales son la banda y el termino de signo, declarado. F cuenta incumplimientos | F44: =IF(ABS(Market_Package!B23-(Market_Package!B7*(Market_Package!B8/Market_Package!B9)*Market_Package!B12+Market_Package!B21-Market_Package!B16))>1,1,0)+IF(Market_Package!B23<=0,1,0)+IF(OR(Market_Package!B23/IS_Hist!F5<5,Market_Package!B23/IS_Hist!F5>40),1,0) -> 0 | H44: =IF(N(F44)=0,"PASS","FAIL") -> PASS
A45: MKT: Procedencia de los inputs de mercado -- fuente presente, FECHA presente con serial valido, desfase <=5 dias entre las cotizaciones diarias (precio, spot, Rf, beta), y frescura ABSOLUTA: si la observacion mas reciente es anterior a HOY()-10 al recalcular, cae en FAIL (el paquete caduca por diseno el 2026-08-24). 0 = completo | F45: =Market_Package!B64+Market_Package!B65+Market_Package!B66+Market_Package!B67 -> 1 | H45: =IF(N(F45)=0,"PASS","FAIL") -> FAIL
A47: INFORMATIVO -- FUERA DEL RANGO DEL GATE (H5:H45); estas filas no computan PASS/FAIL y no inflan el conteo:
A48: DCF vs mercado: el DCF Base implica USD 268.05/ADS contra 430.49 de mercado (-37.7%, celda F de esta fila, viva). Es tesis de valuacion, no identidad verificable -- por eso vive fuera del COUNTIF (regla dura 3 de la flota) | F48: =Market_Package!B58 -> -0.37733658
A49: Gate_9of10 NO lee esta hoja (igual que nunca leyo los 23 checks originales): el gate operativo de la cobertura es B2/B3. Cablearlo exigiria modificar Checks!F15 -- fuera del presupuesto de celdas de esta corrida (solo B2 podia tocarse); pendiente declarado para una corrida con mandato de gate

Sheet Sources_Audited
A1: Audited source register -- TSMC 20-F (EDGAR) IFRS consolidated statements + XBRL companyfacts
A3: Model year(s) | B3: Source document | C3: R-file / XBRL key | D3: Local path
A4: FY2023A-FY2025A (full statement detail) | B4: FY2025 Form 20-F (filed 2026), Financial Statements exhibit, R-files R3 (BS), R4 (IS/OCI), R5 (SCE), R6 (CF); note detail R77-R168 | C4: R3.htm / R4.htm / R5.htm / R6.htm | D4: the maintainer's archive
A5: FY2021A-FY2022A (summary aggregates only) | B5: SEC EDGAR companyfacts API, as originally reported in TSMC comparative-period 20-F columns | C5: ifrs-full:Revenue, CostOfSales, GrossProfit, ProfitLossBeforeTax, IncomeTaxExpenseContinuingOperations, ProfitLoss, Assets, Liabilities, Equity, CurrentAssets, NoncurrentAssets, CurrentLiabilities, NoncurrentLiabilities, EquityAttributableToOwnersOfParent, NoncontrollingInterests, CashAndCashEquivalents, Inventories, PropertyPlantAndEquipment, CashFlowsFromUsedIn{Operating,Investing,Financing}Activities, IncreaseDecreaseInCashAndCashEquivalents, Basic/DilutedEarningsLossPerShare | D5: the maintainer's archive
A6: FY2025A USD convenience translation | B6: 20-F Note 9 "U.S. Dollar Amounts" -- single reporting-date rate applied to FY2025A only (per as-filed USD columns in R3/R4/R6); not a restatement of prior years | C6: Implied rate ~31.3724 TWD/USD (derived from as-filed USD column, not separately stated as a single number in the R-file text) | D6: same R-files as row 4
A8: Known gaps (honest, not filled): FY2021A-FY2022A operating-expense and non-operating detail; FY2021A-FY2023A full balance-sheet line items; full SCE (R5) rollforward detail beyond the BS-tie reconciliation. All would require the FY2022/FY2023 20-F R-files, which are outside this package -- see Checks_TieOut and the build report (not published) for exact scope.
A9: This sheet supersedes/complements the legacy "Sources" tab, whose self-referential COUNTIF-based checks are documented but not altered per instruction (never weaken an existing check).

Sheet Forecast_v2
A1: TSMC Forecast v2 -- 5-year driver-built (Base/Bull/Bear), anchored to FY2025A audited base. TWD millions. | H1: Base scenario key rows: growth=6 rev=7 gp=9 opex=11 opinc=12 pbt=15 ni=17
A2: Drivers: revenue growth (scenario input), gross margin = FY2025A margin +/- scenario delta, opex % of revenue = FY2025A ratio +/- scenario delta, non-operating income held at FY2025A % of revenue, tax rate = FY2025A effective rate. Simplified single-line model; not a full 3-statement build.
A3: FY2025A base: Revenue 3,809,054.3 GM% 59.89 Opex% 9.07 Tax rate 16.97
B4: FY2026E | C4: FY2027E | D4: FY2028E | E4: FY2029E | F4: FY2030E
A5: H:Base scenario
A6: Revenue growth % | B6: 0.1 | C6: 0.1 | D6: 0.1 | E6: 0.1 | F6: 0.1 | H6: assumption
A7: Revenue | B7: =3809054.3*(1+B6) -> 4189959.7 | C7: =B7*(1+C6) -> 4608955.7 | D7: =C7*(1+D6) -> 5069851.3 | E7: =D7*(1+E6) -> 5576836.4 | F7: =E7*(1+F6) -> 6134520
A8: Gross margin % | B8: 0.59891349 | C8: 0.59891349 | D8: 0.59891349 | E8: 0.59891349 | F8: 0.59891349
A9: Gross profit | B9: =B7*B8 -> 2509423.4 | C9: =C7*C8 -> 2760365.7 | D9: =D7*D8 -> 3036402.3 | E9: =E7*E8 -> 3340042.5 | F9: =F7*F8 -> 3674046.8
A10: Operating expenses (% of revenue) | B10: 0.090744204 | C10: 0.090744204 | D10: 0.090744204 | E10: 0.090744204 | F10: 0.090744204
A11: Operating expenses | B11: =B7*B10 -> 380214.56 | C11: =C7*C10 -> 418236.02 | D11: =D7*D10 -> 460059.62 | E11: =E7*E10 -> 506065.58 | F11: =F7*F10 -> 556672.14
A12: Income from operations | B12: =B9-B11 -> 2129208.8 | C12: =C9-C11 -> 2342129.7 | D12: =D9-D11 -> 2576342.7 | E12: =E9-E11 -> 2833977 | F12: =F9-F11 -> 3117374.7
A13: Non-operating income (% of revenue, held at FY2025A ratio) | B13: 0.027713703 | C13: 0.027713703 | D13: 0.027713703 | E13: 0.027713703 | F13: 0.027713703
A14: Non-operating income | B14: =B7*B13 -> 116119.3 | C14: =C7*C13 -> 127731.23 | D14: =D7*D13 -> 140504.35 | E14: =E7*E13 -> 154554.79 | F14: =F7*F13 -> 170010.27
A15: Income before tax | B15: =B12+B14 -> 2245328.1 | C15: =C12+C14 -> 2469861 | D15: =D12+D14 -> 2716847 | E15: =E12+E14 -> 2988531.8 | F15: =F12+F14 -> 3287384.9
A16: Tax rate (held at FY2025A effective rate) | B16: 0.16972988 | C16: 0.16972988 | D16: 0.16972988 | E16: 0.16972988 | F16: 0.16972988
A17: Net income | B17: =B15*(1-B16) -> 1864228.9 | C17: =C15*(1-C16) -> 2050651.8 | D17: =D15*(1-D16) -> 2255716.9 | E17: =E15*(1-E16) -> 2481288.6 | F17: =F15*(1-F16) -> 2729417.5
A19: H:Bull scenario
A20: Revenue growth % | B20: 0.16 | C20: 0.16 | D20: 0.16 | E20: 0.16 | F20: 0.16 | H20: assumption
A21: Revenue | B21: =3809054.3*(1+B20) -> 4418503 | C21: =B21*(1+C20) -> 5125463.5 | D21: =C21*(1+D20) -> 5945537.6 | E21: =D21*(1+E20) -> 6896823.6 | F21: =E21*(1+F20) -> 8000315.4
A22: Gross margin % | B22: 0.60891349 | C22: 0.60891349 | D22: 0.60891349 | E22: 0.60891349 | F22: 0.60891349
A23: Gross profit | B23: =B21*B22 -> 2690486.1 | C23: =C21*C22 -> 3120963.8 | D23: =D21*D22 -> 3620318.1 | E23: =E21*E22 -> 4199568.9 | F23: =F21*F22 -> 4871500
A24: Operating expenses (% of revenue) | B24: 0.087744204 | C24: 0.087744204 | D24: 0.087744204 | E24: 0.087744204 | F24: 0.087744204
A25: Operating expenses | B25: =B21*B24 -> 387698.03 | C25: =C21*C24 -> 449729.71 | D25: =D21*D24 -> 521686.47 | E25: =E21*E24 -> 605156.3 | F25: =F21*F24 -> 701981.31
A26: Income from operations | B26: =B23-B25 -> 2302788 | C26: =C23-C25 -> 2671234.1 | D26: =D23-D25 -> 3098631.6 | E26: =E23-E25 -> 3594412.6 | F26: =F23-F25 -> 4169518.7
A27: Non-operating income (% of revenue, held at FY2025A ratio) | B27: 0.027713703 | C27: 0.027713703 | D27: 0.027713703 | E27: 0.027713703 | F27: 0.027713703
A28: Non-operating income | B28: =B21*B27 -> 122453.08 | C28: =C21*C27 -> 142045.57 | D28: =D21*D27 -> 164772.86 | E28: =E21*E27 -> 191136.52 | F28: =F21*F27 -> 221718.37
A29: Income before tax | B29: =B26+B28 -> 2425241.1 | C29: =C26+C28 -> 2813279.7 | D29: =D26+D28 -> 3263404.5 | E29: =E26+E28 -> 3785549.2 | F29: =F26+F28 -> 4391237
A30: Tax rate (held at FY2025A effective rate) | B30: 0.16972988 | C30: 0.16972988 | D30: 0.16972988 | E30: 0.16972988 | F30: 0.16972988
A31: Net income | B31: =B29*(1-B30) -> 2013605.2 | C31: =C29*(1-C30) -> 2335782.1 | D31: =D29*(1-D30) -> 2709507.2 | E31: =E29*(1-E30) -> 3143028.4 | F31: =F29*(1-F30) -> 3645912.9
A33: H:Bear scenario
A34: Revenue growth % | B34: 0.02 | C34: 0.02 | D34: 0.02 | E34: 0.02 | F34: 0.02 | H34: assumption
A35: Revenue | B35: =3809054.3*(1+B34) -> 3885235.4 | C35: =B35*(1+C34) -> 3962940.1 | D35: =C35*(1+D34) -> 4042198.9 | E35: =D35*(1+E34) -> 4123042.9 | F35: =E35*(1+F34) -> 4205503.7
A36: Gross margin % | B36: 0.57891349 | C36: 0.57891349 | D36: 0.57891349 | E36: 0.57891349 | F36: 0.57891349
A37: Gross profit | B37: =B35*B36 -> 2249215.2 | C37: =C35*C36 -> 2294199.5 | D37: =D35*D36 -> 2340083.5 | E37: =E35*E36 -> 2386885.1 | F37: =F35*F36 -> 2434622.8
A38: Operating expenses (% of revenue) | B38: 0.095744204 | C38: 0.095744204 | D38: 0.095744204 | E38: 0.095744204 | F38: 0.095744204
A39: Operating expenses | B39: =B35*B38 -> 371988.77 | C39: =C35*C38 -> 379428.54 | D39: =D35*D38 -> 387017.12 | E39: =E35*E38 -> 394757.46 | F39: =F35*F38 -> 402652.61
A40: Income from operations | B40: =B37-B39 -> 1877226.4 | C40: =C37-C39 -> 1914770.9 | D40: =D37-D39 -> 1953066.4 | E40: =E37-E39 -> 1992127.7 | F40: =F37-F39 -> 2031970.2
A41: Non-operating income (% of revenue, held at FY2025A ratio) | B41: 0.027713703 | C41: 0.027713703 | D41: 0.027713703 | E41: 0.027713703 | F41: 0.027713703
A42: Non-operating income | B42: =B35*B41 -> 107674.26 | C42: =C35*C41 -> 109827.75 | D42: =D35*D41 -> 112024.3 | E42: =E35*E41 -> 114264.79 | F42: =F35*F41 -> 116550.08
A43: Income before tax | B43: =B40+B42 -> 1984900.7 | C43: =C40+C42 -> 2024598.7 | D43: =D40+D42 -> 2065090.7 | E43: =E40+E42 -> 2106392.5 | F43: =F40+F42 -> 2148520.3
A44: Tax rate (held at FY2025A effective rate) | B44: 0.16972988 | C44: 0.16972988 | D44: 0.16972988 | E44: 0.16972988 | F44: 0.16972988
A45: Net income | B45: =B43*(1-B44) -> 1648003.7 | C45: =C43*(1-C44) -> 1680963.8 | D45: =D43*(1-D44) -> 1714583.1 | E45: =E43*(1-E44) -> 1748874.7 | F45: =F43*(1-F44) -> 1783852.2

Sheet Drivers_MDA
A1: TSMC — Drivers de negocio del MD&A y los disclosures del Form 20-F (capa de cobertura, FY2021A–FY2025A)
A2: TWD millones salvo indicación. Capa ADITIVA construida 2026-08-14: ninguna hoja histórica fue modificada. Regla: lo no divulgado queda en blanco o n.d. — no se inventan ceros. Fuentes: 20-F FY2022 (accn 0001193125-23-107214) para FY2021-22; 20-F FY2025 (accn 0001628280-26-025362) para FY2023-25; 20-F FY2023 (accn 0001193125-24-099840) y 20-F FY2024 (accn 0001193125-25-083423) para tasas cambiarias promedio intermedias. Los checks 29-45 de Checks_TieOut gatean esta hoja.
A4: Métrica | B4: FY2021A | C4: FY2022A | D4: FY2023A | E4: FY2024A | F4: FY2025A | G4: Unidad | H4: Fuente (documento · sección · accession) | I4: Estado
A6: BLOQUE 1 — INGRESOS POR PLATAFORMA (TWD mm)
A7: High Performance Computing | B7: 587780.1 | C7: 932383.7 | D7: 934768.6 | E7: 1476890.6 | F7: 2192931 | G7: TWD mm | H7: FY21-22: Nota 23 'Net Revenue', 20-F FY2022 (accn 0001193125-23-107214) · FY23-25: Nota 22 'Net Revenue', 20-F FY2025 (accn 0001628280-26-025362) | I7: Reportado
A8: Smartphone | B8: 695091.2 | C8: 888879.2 | D8: 814914.3 | E8: 1005130.5 | F8: 1110816.4 | G8: TWD mm | H8: FY21-22: Nota 23 'Net Revenue', 20-F FY2022 (accn 0001193125-23-107214) · FY23-25: Nota 22 'Net Revenue', 20-F FY2025 (accn 0001628280-26-025362) | I8: Reportado
A9: Internet of Things | B9: 133006 | C9: 196115 | D9: 161916.5 | E9: 165516.2 | F9: 191046.8 | G9: TWD mm | H9: FY21-22: Nota 23 'Net Revenue', 20-F FY2022 (accn 0001193125-23-107214) · FY23-25: Nota 22 'Net Revenue', 20-F FY2025 (accn 0001628280-26-025362) | I9: Reportado
A10: Automotive | B10: 67076.4 | C10: 116381 | D10: 133654.3 | E10: 139323.1 | F10: 186667 | G10: TWD mm | H10: FY21-22: Nota 23 'Net Revenue', 20-F FY2022 (accn 0001193125-23-107214) · FY23-25: Nota 22 'Net Revenue', 20-F FY2025 (accn 0001628280-26-025362) | I10: Reportado
A11: Digital Consumer Electronics | B11: 55577.2 | C11: 56158.8 | D11: 46999.8 | E11: 47960.4 | F11: 47996.5 | G11: TWD mm | H11: FY21-22: Nota 23 'Net Revenue', 20-F FY2022 (accn 0001193125-23-107214) · FY23-25: Nota 22 'Net Revenue', 20-F FY2025 (accn 0001628280-26-025362) | I11: Reportado
A12: Others | B12: 48884.1 | C12: 73973.6 | D12: 69482.3 | E12: 59486.9 | F12: 79596.6 | G12: TWD mm | H12: FY21-22: Nota 23 'Net Revenue', 20-F FY2022 (accn 0001193125-23-107214) · FY23-25: Nota 22 'Net Revenue', 20-F FY2025 (accn 0001628280-26-025362) | I12: Reportado
A13: Total plataformas | B13: =SUM(B7:B12) -> 1587415 | C13: =SUM(C7:C12) -> 2263891.3 | D13: =SUM(D7:D12) -> 2161735.8 | E13: =SUM(E7:E12) -> 2894307.7 | F13: =SUM(F7:F12) -> 3809054.3 | G13: TWD mm | I13: Calculado
A14: Tie: total plataformas − ventas netas (IS_Hist) | B14: =B13-IS_Hist!B5 -> 0 | C14: =C13-IS_Hist!C5 -> 0 | D14: =D13-IS_Hist!D5 -> 0 | E14: =E13-IS_Hist!E5 -> 0 | F14: =F13-IS_Hist!F5 -> 0 | G14: TWD mm | H14: Check 29 de Checks_TieOut | I14: Tie
A16: Mix HPC | B16: =B7/B$13 -> 0.37027501 | C16: =C7/C$13 -> 0.41185003 | D16: =D7/D$13 -> 0.43241575 | E16: =E7/E$13 -> 0.51027422 | F16: =F7/F$13 -> 0.57571534 | G16: % | I16: Calculado
A17: Mix Smartphone | B17: =B8/B$13 -> 0.43787617 | C17: =C8/C$13 -> 0.39263334 | D17: =D8/D$13 -> 0.3769722 | E17: =E8/E$13 -> 0.34727838 | F17: =F8/F$13 -> 0.29162525 | G17: % | I17: Calculado
A18: Mix IoT | B18: =B9/B$13 -> 0.083787793 | C18: =C9/C$13 -> 0.086627392 | D18: =D9/D$13 -> 0.074901151 | E18: =E9/E$13 -> 0.057186802 | F18: =F9/F$13 -> 0.050155967 | G18: % | I18: Calculado
A19: Mix Automotive | B19: =B10/B$13 -> 0.042255113 | C19: =C10/C$13 -> 0.051407504 | D19: =D10/D$13 -> 0.061827306 | E19: =E10/E$13 -> 0.048136934 | F19: =F10/F$13 -> 0.049006127 | G19: % | I19: Calculado
A20: Mix DCE | B20: =B11/B$13 -> 0.035011134 | C20: =C11/C$13 -> 0.024806315 | D20: =D11/D$13 -> 0.021741695 | E20: =E11/E$13 -> 0.016570595 | F20: =F11/F$13 -> 0.012600634 | G20: % | I20: Calculado
A21: Mix Others | B21: =B12/B$13 -> 0.030794783 | C21: =C12/C$13 -> 0.03267542 | D21: =D12/D$13 -> 0.032141902 | E21: =E12/E$13 -> 0.020553067 | F21: =F12/F$13 -> 0.020896683 | G21: % | I21: Calculado
A23: YoY HPC | B23: n.a. | C23: =C7/B7-1 -> 0.5862798 | D23: =D7/C7-1 -> 0.0025578525 | E23: =E7/D7-1 -> 0.57995316 | F23: =F7/E7-1 -> 0.48482968 | G23: % | I23: Calculado
A24: YoY Smartphone | B24: n.a. | C24: =C8/B8-1 -> 0.27879507 | D24: =D8/C8-1 -> -0.08321142 | E24: =E8/D8-1 -> 0.23341866 | F24: =F8/E8-1 -> 0.10514645 | G24: % | I24: Calculado
A25: YoY IoT | B25: n.a. | C25: =C9/B9-1 -> 0.47448235 | D25: =D9/C9-1 -> -0.17437983 | E25: =E9/D9-1 -> 0.022231829 | F25: =F9/E9-1 -> 0.15424835 | G25: % | I25: Calculado
A26: YoY Automotive | B26: n.a. | C26: =C10/B10-1 -> 0.73505137 | D26: =D10/C10-1 -> 0.14842027 | E26: =E10/D10-1 -> 0.042413899 | F26: =F10/E10-1 -> 0.33981371 | G26: % | I26: Calculado
A27: YoY DCE | B27: n.a. | C27: =C11/B11-1 -> 0.010464723 | D27: =D11/C11-1 -> -0.16309109 | E27: =E11/D11-1 -> 0.020438385 | F27: =F11/E11-1 -> 0.00075270431 | G27: % | I27: Calculado
A28: YoY Others | B28: n.a. | C28: =C12/B12-1 -> 0.51324459 | D28: =D12/C12-1 -> -0.060714904 | E28: =E12/D12-1 -> -0.14385534 | F28: =F12/E12-1 -> 0.33805258 | G28: % | I28: Calculado
A30: BLOQUE 2 — INGRESOS POR GEOGRAFÍA (HQ del cliente, TWD mm)
A31: Taiwán | B31: 203963.7 | C31: 210470.8 | D31: 149777.4 | E31: 270413.5 | F31: 299445.8 | G31: TWD mm | H31: FY21-22: Nota 23, 20-F FY2022 (accn 0001193125-23-107214) · FY23-25: Nota 22, 20-F FY2025 (accn 0001628280-26-025362) — 'categorized mainly based on the countries where the customers are headquartered' | I31: Reportado
A32: Estados Unidos | B32: 1015996.4 | C32: 1493328.8 | D32: 1408841.9 | E32: 1992280.4 | F32: 2834692.1 | G32: TWD mm | H32: FY21-22: Nota 23, 20-F FY2022 (accn 0001193125-23-107214) · FY23-25: Nota 22, 20-F FY2025 (accn 0001628280-26-025362) — 'categorized mainly based on the countries where the customers are headquartered' | I32: Reportado
A33: China | B33: 164552.1 | C33: 245168.8 | D33: 267154.1 | E33: 331673.3 | F33: 327502.8 | G33: TWD mm | H33: FY21-22: Nota 23, 20-F FY2022 (accn 0001193125-23-107214) · FY23-25: Nota 22, 20-F FY2025 (accn 0001628280-26-025362) — 'categorized mainly based on the countries where the customers are headquartered' | I33: Reportado
A34: Japón | B34: 71920.8 | C34: 119099.3 | D34: 132072 | E34: 144239.9 | F34: 150427.9 | G34: TWD mm | H34: FY21-22: Nota 23, 20-F FY2022 (accn 0001193125-23-107214) · FY23-25: Nota 22, 20-F FY2025 (accn 0001628280-26-025362) — 'categorized mainly based on the countries where the customers are headquartered' | I34: Reportado
A35: Europa, Medio Oriente y África | B35: 89010.1 | C35: 123767.1 | D35: 117348.2 | E35: 102760.9 | F35: 126584.1 | G35: TWD mm | H35: FY21-22: Nota 23, 20-F FY2022 (accn 0001193125-23-107214) · FY23-25: Nota 22, 20-F FY2025 (accn 0001628280-26-025362) — 'categorized mainly based on the countries where the customers are headquartered' | I35: Reportado
A36: Otros | B36: 41971.9 | C36: 72056.5 | D36: 86542.2 | E36: 52939.7 | F36: 70401.6 | G36: TWD mm | H36: FY21-22: Nota 23, 20-F FY2022 (accn 0001193125-23-107214) · FY23-25: Nota 22, 20-F FY2025 (accn 0001628280-26-025362) — 'categorized mainly based on the countries where the customers are headquartered' | I36: Reportado
A37: Total geografías | B37: =SUM(B31:B36) -> 1587415 | C37: =SUM(C31:C36) -> 2263891.3 | D37: =SUM(D31:D36) -> 2161735.8 | E37: =SUM(E31:E36) -> 2894307.7 | F37: =SUM(F31:F36) -> 3809054.3 | G37: TWD mm | I37: Calculado
A38: Tie: total geografías − ventas netas (IS_Hist) | B38: =B37-IS_Hist!B5 -> 0 | C38: =C37-IS_Hist!C5 -> 0 | D38: =D37-IS_Hist!D5 -> 0 | E38: =E37-IS_Hist!E5 -> 0 | F38: =F37-IS_Hist!F5 -> 0 | G38: TWD mm | H38: Check 30 de Checks_TieOut | I38: Tie
A40: Mix Taiwán | B40: =B31/B$37 -> 0.12848795 | C40: =C31/C$37 -> 0.092968598 | D40: =D31/D$37 -> 0.06928571 | E40: =E31/E$37 -> 0.093429424 | F40: =F31/F$37 -> 0.078614211 | G40: % | I40: Calculado
A41: Mix Estados Unidos | B41: =B32/B$37 -> 0.640032 | C41: =C32/C$37 -> 0.6596292 | D41: =D32/D$37 -> 0.65171789 | E41: =E32/E$37 -> 0.68834437 | F41: =F32/F$37 -> 0.7441984 | G41: % | I41: Calculado
A42: Mix China | B42: =B33/B$37 -> 0.10366042 | C42: =C33/C$37 -> 0.10829531 | D42: =D33/D$37 -> 0.12358314 | E42: =E33/E$37 -> 0.11459504 | F42: =F33/F$37 -> 0.085980082 | G42: % | I42: Calculado
A43: Mix Japón | B43: =B34/B$37 -> 0.045306867 | C43: =C34/C$37 -> 0.052608224 | D43: =D34/D$37 -> 0.061095348 | E43: =E34/E$37 -> 0.049835717 | F43: =F34/F$37 -> 0.039492191 | G43: % | I43: Calculado
A44: Mix EMEA | B44: =B35/B$37 -> 0.056072357 | C44: =C35/C$37 -> 0.054670072 | D44: =D35/D$37 -> 0.054284247 | E44: =E35/E$37 -> 0.035504484 | F44: =F35/F$37 -> 0.033232422 | G44: % | I44: Calculado
A45: Mix Otros | B45: =B36/B$37 -> 0.026440408 | C45: =C36/C$37 -> 0.031828604 | D45: =D36/D$37 -> 0.040033662 | E45: =E36/E$37 -> 0.018290972 | F45: =F36/F$37 -> 0.018482698 | G45: % | I45: Calculado
A47: BLOQUE 3 — DESAGREGACIÓN DE PRODUCTO: WAFER VS OTROS (TWD mm)
A48: Wafer | B48: 1405300.3 | C48: 1991855.9 | D48: 1882518.1 | E48: 2514461.3 | F48: 3272553.5 | G48: TWD mm | H48: FY21-22: Nota 23 'Product', 20-F FY2022 (accn 0001193125-23-107214) · FY23-25: Nota 22 'Product', 20-F FY2025 (accn 0001628280-26-025362) | I48: Reportado
A49: Otros (no-wafer) | B49: 182114.7 | C49: 272035.4 | D49: 279217.7 | E49: 379846.4 | F49: 536500.8 | G49: TWD mm | H49: FY21-22: Nota 23 'Product', 20-F FY2022 (accn 0001193125-23-107214) · FY23-25: Nota 22 'Product', 20-F FY2025 (accn 0001628280-26-025362) | I49: Reportado
A50: Total producto | B50: =SUM(B48:B49) -> 1587415 | C50: =SUM(C48:C49) -> 2263891.3 | D50: =SUM(D48:D49) -> 2161735.8 | E50: =SUM(E48:E49) -> 2894307.7 | F50: =SUM(F48:F49) -> 3809054.3 | G50: TWD mm | I50: Calculado
A51: Tie: total producto − ventas netas (IS_Hist) | B51: =B50-IS_Hist!B5 -> 0 | C51: =C50-IS_Hist!C5 -> 0 | D51: =D50-IS_Hist!D5 -> 0 | E51: =E50-IS_Hist!E5 -> 0 | F51: =F50-IS_Hist!F5 -> 0 | G51: TWD mm | H51: Check 31 de Checks_TieOut | I51: Tie
A52: Wafer % del total (calculado) | B52: =B48/B50 -> 0.88527594 | C52: =C48/C50 -> 0.87983725 | D52: =D48/D50 -> 0.87083634 | E52: =E48/E50 -> 0.86876088 | F52: =F48/F50 -> 0.85915118 | G52: % | I52: Calculado
A53: Wafer % reportado (prosa: "aproximadamente") | B53: 0.89 | C53: 0.88 | D53: 0.87 | E53: 0.87 | F53: 0.86 | G53: % | H53: Item 4 'The Principal Source of Our Revenue' de cada 20-F (prosa, redondeado por el emisor) | I53: Reportado
A55: BLOQUE 4 — WAFER REVENUE POR NODO (TWD mm; la Nota de ingresos publica los absolutos)
A56: 3-nanómetros | D56: 108045.3 | E56: 459530.2 | F56: 794341.4 | G56: TWD mm | H56: FY21-22: Nota 23 'Resolution', 20-F FY2022 (accn 0001193125-23-107214) · FY23-25: Nota 22 'Resolution', 20-F FY2025 (accn 0001628280-26-025362) · FY21-22: la nota no trae fila de 3nm (HVM arrancó dic-2022) — en blanco, no cero | I56: Reportado
A57: 5-nanómetros | B57: 262327.4 | C57: 508689.9 | D57: 629300.4 | E57: 861318.9 | F57: 1179907.2 | G57: TWD mm | H57: FY21-22: Nota 23 'Resolution', 20-F FY2022 (accn 0001193125-23-107214) · FY23-25: Nota 22 'Resolution', 20-F FY2025 (accn 0001628280-26-025362) | I57: Reportado
A58: 7-nanómetros | B58: 440383.1 | C58: 535153.8 | D58: 357270.7 | E58: 416790.3 | F58: 459258.1 | G58: TWD mm | H58: FY21-22: Nota 23 'Resolution', 20-F FY2022 (accn 0001193125-23-107214) · FY23-25: Nota 22 'Resolution', 20-F FY2025 (accn 0001628280-26-025362) | I58: Reportado
A59: 10-nanómetros | B59: 660 | C59: 24.9 | G59: TWD mm | H59: FY21-22: Nota 23 'Resolution', 20-F FY2022 (accn 0001193125-23-107214) · FY23-25: Nota 22 'Resolution', 20-F FY2025 (accn 0001628280-26-025362) · FY23-25: la nota del 20-F FY2025 ya no trae fila de 10nm — en blanco, no cero | I59: Reportado
A60: 16-nanómetros | B60: 191058.9 | C60: 258544.3 | D60: 191306.1 | E60: 202383.7 | F60: 215722.1 | G60: TWD mm | H60: FY21-22: Nota 23 'Resolution', 20-F FY2022 (accn 0001193125-23-107214) · FY23-25: Nota 22 'Resolution', 20-F FY2025 (accn 0001628280-26-025362) | I60: Reportado
A61: 20-nanómetros | B61: 5668.8 | C61: 8853.3 | D61: 10359 | E61: 4077.2 | F61: 4304.9 | G61: TWD mm | H61: FY21-22: Nota 23 'Resolution', 20-F FY2022 (accn 0001193125-23-107214) · FY23-25: Nota 22 'Resolution', 20-F FY2025 (accn 0001628280-26-025362) | I61: Reportado
A62: 28-nanómetros | B62: 153066.6 | C62: 206611.9 | D62: 186924.9 | E62: 188155 | F62: 225134.2 | G62: TWD mm | H62: FY21-22: Nota 23 'Resolution', 20-F FY2022 (accn 0001193125-23-107214) · FY23-25: Nota 22 'Resolution', 20-F FY2025 (accn 0001628280-26-025362) | I62: Reportado
A63: 40/45-nanómetros | B63: 103413.6 | C63: 145546.2 | D63: 114667.4 | E63: 108468.2 | F63: 95582.7 | G63: TWD mm | H63: FY21-22: Nota 23 'Resolution', 20-F FY2022 (accn 0001193125-23-107214) · FY23-25: Nota 22 'Resolution', 20-F FY2025 (accn 0001628280-26-025362) | I63: Reportado
A64: 65-nanómetros | B64: 66467.9 | C64: 93288.6 | D64: 107425.4 | E64: 93120.1 | F64: 120399.3 | G64: TWD mm | H64: FY21-22: Nota 23 'Resolution', 20-F FY2022 (accn 0001193125-23-107214) · FY23-25: Nota 22 'Resolution', 20-F FY2025 (accn 0001628280-26-025362) | I64: Reportado
A65: 90-nanómetros | B65: 32260.3 | C65: 40184.2 | D65: 25642 | E65: 21509.3 | F65: 21358.7 | G65: TWD mm | H65: FY21-22: Nota 23 'Resolution', 20-F FY2022 (accn 0001193125-23-107214) · FY23-25: Nota 22 'Resolution', 20-F FY2025 (accn 0001628280-26-025362) | I65: Reportado
A66: 0.11/0.13 micras | B66: 40558.5 | C66: 57992.3 | D66: 47149.3 | E66: 52442.8 | F66: 48846.1 | G66: TWD mm | H66: FY21-22: Nota 23 'Resolution', 20-F FY2022 (accn 0001193125-23-107214) · FY23-25: Nota 22 'Resolution', 20-F FY2025 (accn 0001628280-26-025362) | I66: Reportado
A67: 0.15/0.18 micras | B67: 86700.3 | C67: 110571.2 | D67: 86614.2 | E67: 90796.8 | F67: 88293.7 | G67: TWD mm | H67: FY21-22: Nota 23 'Resolution', 20-F FY2022 (accn 0001193125-23-107214) · FY23-25: Nota 22 'Resolution', 20-F FY2025 (accn 0001628280-26-025362) | I67: Reportado
A68: 0.25 micras y mayores | B68: 22734.9 | C68: 26395.3 | D68: 17813.4 | E68: 15868.8 | F68: 19405.1 | G68: TWD mm | H68: FY21-22: Nota 23 'Resolution', 20-F FY2022 (accn 0001193125-23-107214) · FY23-25: Nota 22 'Resolution', 20-F FY2025 (accn 0001628280-26-025362) | I68: Reportado
A69: Total por nodo | B69: =SUM(B56:B68) -> 1405300.3 | C69: =SUM(C56:C68) -> 1991855.9 | D69: =SUM(D56:D68) -> 1882518.1 | E69: =SUM(E56:E68) -> 2514461.3 | F69: =SUM(F56:F68) -> 3272553.5 | G69: TWD mm | I69: Calculado
A70: Tie: total por nodo − wafer revenue (fila 48) | B70: =B69-B48 -> 0 | C70: =C69-C48 -> 0 | D70: =D69-D48 -> 0 | E70: =E69-E48 -> 0 | F70: =F69-F48 -> 0 | G70: TWD mm | H70: Check 32 de Checks_TieOut | I70: Tie
A72: Mix 3nm (calculado del absoluto) | B72: =IF(N(B56)=0,"n.d.",B56/B$69) -> n.d. | C72: =IF(N(C56)=0,"n.d.",C56/C$69) -> n.d. | D72: =IF(N(D56)=0,"n.d.",D56/D$69) -> 0.05739403 | E72: =IF(N(E56)=0,"n.d.",E56/E$69) -> 0.18275493 | F72: =IF(N(F56)=0,"n.d.",F56/F$69) -> 0.24272832 | G72: % wafer revenue | I72: Calculado
A73: Mix 5nm (calculado) | B73: =B57/B$69 -> 0.18667 | C73: =C57/C$69 -> 0.25538489 | D73: =D57/D$69 -> 0.33428651 | E73: =E57/E$69 -> 0.3425461 | F73: =F57/F$69 -> 0.36054634 | G73: % wafer revenue | I73: Calculado
A74: Mix 7nm (calculado) | B74: =B58/B$69 -> 0.31337295 | C74: =C58/C$69 -> 0.26867094 | D74: =D58/D$69 -> 0.18978341 | E74: =E58/E$69 -> 0.16575729 | F74: =F58/F$69 -> 0.14033632 | G74: % wafer revenue | I74: Calculado
A75: Avanzado (7nm y menores) calculado | B75: =(N(B56)+B57+B58)/B69 -> 0.50004294 | C75: =(N(C56)+C57+C58)/C69 -> 0.52405583 | D75: =(N(D56)+D57+D58)/D69 -> 0.58146394 | E75: =(N(E56)+E57+E58)/E69 -> 0.69105832 | F75: =(N(F56)+F57+F58)/F69 -> 0.74361098 | G75: % wafer revenue | I75: Calculado
A76: Avanzado (7nm y menores) REPORTADO | B76: 0.5 | C76: 0.53 | D76: 0.58 | E76: 0.69 | F76: 0.74 | G76: % wafer revenue | H76: Prosa del Item 5 de cada 20-F ('Advanced technologies (7-nanometer and below) accounted for…'); suma de porcentajes redondeados a enteros — tolerancia 1.5pp en el check 34 | I76: Reportado
A77: Mix 3nm REPORTADO (tabla, enteros) | D77: 0.06 | E77: 0.18 | F77: 0.24 | G77: % wafer revenue | H77: Tabla 'breakdown of wafer revenue by circuit resolution', Item 5, 20-F FY2025 (accn 0001628280-26-025362) | I77: Reportado
A78: Mix 5nm REPORTADO (tabla, enteros) | B78: 0.19 | C78: 0.26 | D78: 0.33 | E78: 0.34 | F78: 0.36 | G78: % wafer revenue | H78: Tablas Item 5: FY21-22 20-F FY2022 (accn 0001193125-23-107214); FY23-25 20-F FY2025 (accn 0001628280-26-025362) | I78: Reportado
A79: Mix 7nm REPORTADO (tabla, enteros) | B79: 0.31 | C79: 0.27 | D79: 0.19 | E79: 0.17 | F79: 0.14 | G79: % wafer revenue | H79: Tablas Item 5: FY21-22 20-F FY2022 (accn 0001193125-23-107214); FY23-25 20-F FY2025 (accn 0001628280-26-025362) | I79: Reportado
A81: BLOQUE 5 — WAFERS, CAPACIDAD Y PRECIO
A82: Embarques de wafers (miles, equiv. 12") | B82: 14179 | C82: 15253 | D82: 12002 | E82: 12910 | F82: 15022 | G82: miles de wafers | H82: Tabla del Item 5 'Wafer (12-inch equivalent) shipment': FY21-22 20-F FY2022 (accn 0001193125-23-107214); FY23-25 20-F FY2025 (accn 0001628280-26-025362) | I82: Reportado
A83: Embarques de wafers (millones) | B83: =B82/1000 -> 14.179 | C83: =C82/1000 -> 15.253 | D83: =D82/1000 -> 12.002 | E83: =E82/1000 -> 12.91 | F83: =F82/1000 -> 15.022 | G83: mm wafers | I83: Calculado
A84: Capacidad anual (millones, equiv. 12") | B84: 14 | C84: 15 | D84: 16 | E84: 17 | F84: 17 | G84: mm wafers | H84: Item 4 de cada 20-F: cifras 'approximately'; FY2025 el emisor dice que la capacidad 'excedió 17 millones' — se registra 17 como piso | I84: Reportado
A85: Utilización implícita (embarques/capacidad) | B85: =B83/B84 -> 1.0127857 | C85: =C83/C84 -> 1.0168667 | D85: =D83/D84 -> 0.750125 | E85: =E83/E84 -> 0.75941176 | F85: =F83/F84 -> 0.88364706 | G85: % | I85: Calculado
A86: Ingreso total por wafer | B86: =IS_Hist!B5/B83 -> 111955.36 | C86: =IS_Hist!C5/C83 -> 148422.69 | D86: =IS_Hist!D5/D83 -> 180114.63 | E86: =IS_Hist!E5/E83 -> 224191.15 | F86: =IS_Hist!F5/F83 -> 253565.06 | G86: TWD/wafer | H86: Ventas netas IS_Hist ÷ embarques (fila 83). Cruza contra Sector_KPIs!B9 en el check 36 | I86: Calculado
A87: Wafer revenue por wafer (ASP blended) | B87: =B48/B83 -> 99111.383 | C87: =C48/C83 -> 130587.81 | D87: =D48/D83 -> 156850.37 | E87: =E48/E83 -> 194768.5 | F87: =F48/F83 -> 217850.72 | G87: TWD/wafer | H87: Wafer revenue (fila 48) ÷ embarques — excluye ingresos no-wafer | I87: Calculado
A88: YoY del ASP blended | B88: n.a. | C88: =C87/B87-1 -> 0.31758642 | D88: =D87/C87-1 -> 0.2011103 | E88: =E87/D87-1 -> 0.24174716 | F88: =F87/E87-1 -> 0.11851106 | G88: % | I88: Calculado
A90: BLOQUE 6 — CONCENTRACIÓN DE CLIENTES, FX Y PASIVOS DE CONTRATO
A91: Diez clientes mayores (% ventas netas) | B91: 0.71 | C91: 0.68 | D91: 0.7 | E91: 0.76 | F91: 0.78 | G91: % | H91: Item 3 Risk Factors de cada 20-F; FY23-25 confirmados en 20-F FY2025 (accn 0001628280-26-025362) | I91: Reportado
A92: Cliente mayor (% ventas netas) | B92: 0.26 | C92: 0.23 | D92: 0.25 | E92: 0.22 | F92: 0.19 | G92: % | H92: Item 3 Risk Factors de cada 20-F; FY23-25 en 20-F FY2025 (accn 0001628280-26-025362) | I92: Reportado
A93: Segundo cliente (% ventas netas) | B93: 0.1 | C93: <10% | D93: 0.11 | E93: 0.12 | F93: 0.17 | G93: % | H93: Item 3 Risk Factors; FY2022 el emisor solo dice 'less than 10%' — se transcribe tal cual, sin inventar cifra | I93: Reportado
A94: TWD/USD promedio ponderado del año | B94: 27.94 | C94: 29.84 | D94: 31.19 | E94: 32.13 | F94: 31.11 | G94: TWD/USD | H94: Prosa 'Foreign Currency Exchange Rate' del Item 5: FY21-22 20-F FY2022 (accn 0001193125-23-107214); FY2023 20-F FY2023 (accn 0001193125-24-099840); FY2024-25 20-F FY2025 (accn 0001628280-26-025362) | I94: Reportado
A95: Tasa de conversión Note 9 (cierre FY2025) | F95: =USD_Hist!F5 -> 31.37 | G95: TWD/USD | H95: USD_Hist!F5 (implícita de la columna USD del propio filing) | I95: Enlace vivo
A96: Contract liabilities (pasivos de contrato) | D96: 52736.4 | E96: 89435.4 | F96: 49954.4 | G96: TWD mm | H96: Nota 22.b 'Contract balances', 20-F FY2025 (accn 0001628280-26-025362) — la columna FY2023 es el saldo al 2024-01-01; FY21-22 fuera del paquete (en blanco, no cero) | I96: Reportado
A97: Contract liabilities % ventas | D97: =D96/IS_Hist!D5 -> 0.024395396 | E97: =E96/IS_Hist!E5 -> 0.030900446 | F97: =F96/IS_Hist!F5 -> 0.013114646 | G97: % | I97: Calculado
A99: BLOQUE 7 — EMPLEADOS
A100: Empleados totales (cierre de año) | B100: 65152 | C100: 73090 | D100: 76478 | E100: 83825 | F100: 90557 | G100: personas | H100: Item 6 'Employees': FY21-22 20-F FY2022 (accn 0001193125-23-107214); FY23-25 20-F FY2025 (accn 0001628280-26-025362) | I100: Reportado
A101: Ventas por empleado | B101: =IS_Hist!B5/B100 -> 24.364793 | C101: =IS_Hist!C5/C100 -> 30.974022 | D101: =IS_Hist!D5/D100 -> 28.266113 | E101: =IS_Hist!E5/E100 -> 34.527977 | F101: =IS_Hist!F5/F100 -> 42.062505 | G101: TWD mm/persona | I101: Calculado
A102: Empleados en China | D102: 4484 | E102: 4478 | F102: 4402 | G102: personas | H102: Item 6, tabla por ubicación, 20-F FY2025 (accn 0001628280-26-025362) (FY21-22 no cargado — está en el 20-F FY2022 pero fuera del alcance de esta capa) | I102: Reportado
A103: Empleados en Norteamérica | D103: 2668 | E103: 4497 | F103: 5290 | G103: personas | H103: Item 6, 20-F FY2025 (accn 0001628280-26-025362) | I103: Reportado
A104: Empleados en Japón | D104: 804 | E104: 1791 | F104: 2447 | G104: personas | H104: Item 6, 20-F FY2025 (accn 0001628280-26-025362) | I104: Reportado
A105: Empleados en Europa | D105: 60 | E105: 78 | F105: 209 | G105: personas | H105: Item 6, 20-F FY2025 (accn 0001628280-26-025362) | I105: Reportado
A106: Empleados fuera de Taiwán (% del total) | D106: =SUM(D102:D105)/D100 -> 0.10481446 | E106: =SUM(E102:E105)/E100 -> 0.12936475 | F106: =SUM(F102:F105)/F100 -> 0.13635611 | G106: % | H106: Suma filas 102-105 ÷ fila 100; excluye Corea (2 personas) | I106: Calculado
A108: BLOQUE 8 — CAPEX Y EXPANSIÓN GLOBAL
A109: Capex | B109: =Historical!B13 -> 839195.7 | C109: =Historical!C13 -> 1082672.1 | D109: =Historical!D13 -> 949816.8 | E109: =Historical!E13 -> 956006.5 | F109: =Historical!F13 -> 1272410.5 | G109: TWD mm | H109: Historical!B13:F13 (ledger de Sources); FY2025 confirmado en Item 5: NT$1,272,411 mm = US$40,895 mm al promedio 31.11 | I109: Enlace vivo
A110: Capex / ventas | B110: =B109/IS_Hist!B5 -> 0.52865552 | C110: =C109/IS_Hist!C5 -> 0.47823502 | D110: =D109/IS_Hist!D5 -> 0.43937691 | E110: =E109/IS_Hist!E5 -> 0.33030576 | F110: =F109/IS_Hist!F5 -> 0.33404893 | G110: % | I110: Calculado
A111: Guía de capex 2026E — mínimo | F111: 52 | G111: USD bn | H111: Item 5 'Liquidity and Capital Resources', 20-F FY2025 (accn 0001628280-26-025362): 'expected to be between US$52 billion and US$56 billion' | I111: Reportado
A112: Guía de capex 2026E — máximo | F112: 56 | G112: USD bn | H112: Item 5, 20-F FY2025 (accn 0001628280-26-025362) | I112: Reportado
A113: Arizona (TSMC Arizona, Fab 21) | F113: 1a fab en HVM desde fin-2024; 2a en construcción; 3a iniciada en 2025; terreno adicional adquirido en 2026 | G113: — | H113: Item 4 'Our Subsidiaries and Affiliates', 20-F FY2025 (accn 0001628280-26-025362) · DOC Direct Funding Agreement nov-2024: hasta USD 6.6bn directos + hasta USD 5bn en préstamos | I113: Cualitativo
...

Sheet Market_Package
A1: TSMC — Paquete de mercado (capa de cobertura, corrida 2026-08-14)
A2: Todo input de mercado trae fuente (col E) y FECHA como serial (col D). El DCF del modelo NO fue recableado: hallazgos H1-H3 declarados en el bloque 7. Los checks 40-45 de Checks_TieOut gatean esta hoja. El emisor reporta en TWD; el valor negociado (TSM, NYSE) es un ADS de 5 acciones ordinarias en USD.
A4: Concepto | B4: Valor | C4: Unidad | D4: As-of (serial) | E4: Fuente | F4: Nota / método
A6: BLOQUE 1 — PRECIO, ACCIONES Y CAPITALIZACIÓN
A7: Precio de cierre del ADS (TSM, NYSE) | B7: 430.49 | C7: USD/ADS | D7: 46247 | E7: stockanalysis.com, historial diario TSM (cierre 2026-08-13); confirmado vía investing.com (cierre previo de la sesión 2026-08-14) | F7: Cierre completo más reciente al momento de la corrida; el cierre del propio 2026-08-14 aún estaba liquidándose y no se usa
A8: Acciones ordinarias en circulación | B8: 25932.53 | C8: mm acciones | D8: 46022 | E8: 20-F FY2025 R3: capital stock 259,325.3 TWD mm ÷ par TWD 10 (accn 0001628280-26-025362) | F8: Cross: diluidas promedio 25,930.6 (Historical!F20, XBRL) — deriva 0.007%; TSMC no recompra. Gateado en check 40
A9: Acciones ordinarias por ADS | B9: =Assumptions!E23 -> 5 | C9: ord/ADS | D9: 46022 | E9: Portada del 20-F; Assumptions!E23 (enlace vivo) | F9: Enlace vivo — si el modelo cambia el ratio, este paquete lo hereda
A10: ADS equivalentes | B10: =B8/B9 -> 5186.506 | C10: mm ADS | F10: Calculado: B8/B9
A11: Capitalización de mercado (USD) | B11: =B7*B10 -> 2232739 | C11: USD mm | F11: Calculado: B7*B10. Cross externo: finviz reporta USD 2,211bn con el precio intradía 426.35 del 2026-08-14 — coherente
A12: Spot TWD/USD | B12: 32.007 | C12: TWD/USD | D12: 46248 | E12: tradingeconomics.com USDTWD, cierre de sesión 2026-08-14; cross: xe.com mid-market 31.975 el mismo día (−0.10%) | F12: Bandas contra el rate del modelo (32.21) y el Note 9 (31.37) en el check 43
A13: Capitalización de mercado (TWD) | B13: =B11*B12 -> 71463276 | C13: TWD mm | F13: Calculado: B11*B12 — para múltiplos contra los estados en TWD
A15: BLOQUE 2 — PUENTE A EV CON EL BALANCE FY2025A DEL MODELO (TWD mm, enlaces vivos a BS_Hist)
A16: Caja y equivalentes | B16: =BS_Hist!F6 -> 2767856.4 | C16: TWD mm | F16: Enlace vivo BS_Hist!F6; misma definición de liquidez que usa el DCF (Valuation!B14) — gateado en check 41
A17: Memo: activos financieros corrientes NO incluidos (FVTPL+FVOCI+costo amortizado) | B17: =BS_Hist!F7+BS_Hist!F8+BS_Hist!F9 -> 300738.4 | C17: TWD mm | F17: H1: fuera de la definición de liquidez del DCF; cuantificado aquí, no corregido
A18: Deuda: porción corriente de pasivos de largo plazo | B18: =BS_Hist!F42 -> 136925.7 | C18: TWD mm | F18: Enlace vivo BS_Hist!F42
A19: Deuda: bonos por pagar (no corriente) | B19: =BS_Hist!F46 -> 856227.5 | C19: TWD mm | F19: Enlace vivo BS_Hist!F46
A20: Deuda: préstamos bancarios de largo plazo (no corriente) | B20: =BS_Hist!F47 -> 39834.5 | C20: TWD mm | F20: Enlace vivo BS_Hist!F47
A21: Deuda bruta con intereses | B21: =SUM(B18:B20) -> 1032987.7 | C21: TWD mm | F21: SUM(B18:B20). El 20-F FY2025 (Item 5) declara deuda LP agregada de NT$1,032,988 mm y préstamos de corto plazo nil — coincide
A22: Caja neta (caja − deuda bruta) | B22: =B16-B21 -> 1734868.7 | C22: TWD mm | F22: TSMC es caja neta positiva
A23: Enterprise value (TWD) | B23: =B13+B21-B16 -> 69728407 | C23: TWD mm | F23: =B13+B21-B16; gateado en check 44 (recableado + banda EV/Ventas)
A24: Enterprise value (USD) | B24: =B23/B12 -> 2178536.2 | C24: USD mm | F24: =B23/B12
A25: Deuda que usa el DCF existente | B25: =Valuation!B15 -> 1032987.7 | C25: TWD mm | F25: Enlace vivo Valuation!B15 (← Forecast!B27, constante del ledger)
A26: Delta: deuda del paquete − deuda del DCF | B26: =B21-B25 -> 0 | C26: TWD mm | F26: 0 = ambas definiciones coinciden componente a componente (sin análogo del hallazgo H1 de Apple en la deuda); mecanizado en check 41
A27: Memo: pasivos por arrendamiento no corrientes (fuera de la definición de deuda) | B27: =BS_Hist!F49 -> 31595 | C27: TWD mm | F27: Declarado: la definición de deuda del modelo excluye arrendamientos (ledger de Sources, 'excludes leases'); este es el monto no corriente visible en BS_Hist
A28: Nota: la deuda del paquete y la del DCF coinciden; la diferencia de definición está en la LIQUIDEZ (H1), no en la deuda.
A30: BLOQUE 3 — COSTO DE CAPITAL (fechado)
A31: Rf — UST 10Y par yield | B31: 0.0463 | C31: % | D31: 46247 | E31: home.treasury.gov, Daily Treasury Par Yield Curve, columna 10 Yr, 2026-08-13 (primaria; CSV verificado en la corrida Apple del mismo día) | F31: Captura única por corrida de flota (playbook, esqueleto §7): mismo Rf que el piloto Apple
A32: ERP implícita del S&P 500 | B32: 0.0423 | C32: % | D32: 46023 | E32: Damodaran (NYU Stern), histimpl.html, actualización enero 2026 | F32: L2: ERP de EE.UU. SIN prima de riesgo país de Taiwán — declarado, no tapado (el ADS cotiza en NYSE; la producción está concentrada en Taiwán)
A33: Beta 5A mensual del ADS | B33: 1.26 | C33: x | D33: 46248 | E33: stockanalysis.com, TSM statistics, 2026-08-14 | F33: L1: finviz reporta 1.40 el mismo día — la varianza entre proveedores mueve Ke de 9.96% a 10.55%; se usa el proveedor del piloto Apple
A34: Ke (CAPM) | B34: =B31+B33*B32 -> 0.099598 | C34: % | F34: =B31+B33*B32
A35: Kd efectivo implícito (antes de impuestos) | B35: =-IS_Hist!F20/((Historical!E19+Historical!F19)/2) -> 0.012061184 | C35: % | F35: Calculado retrospectivo: finance costs FY2025 (IS_Hist!F20) ÷ deuda promedio FY2024-25 (Historical!E19:F19). Memo del emisor: cupones fijos 0.41%–4.63% (20-F FY2025, Item 5)
A36: Tasa efectiva de impuestos FY2025A | B36: =IS_Hist!F24/IS_Hist!F23 -> 0.16972988 | C36: % | F36: Enlace vivo IS_Hist!F24/F23 — guardia en check 42: una tasa tecleada en duro cae
A37: Kd después de impuestos | B37: =B35*(1-B36) -> 0.010014041 | C37: %
A38: We (peso del equity, a mercado) | B38: =B13/(B13+B21) -> 0.98575116 | C38: %
A39: Wd (peso de la deuda) | B39: =B21/(B13+B21) -> 0.01424884 | C39: %
A40: WACC fechado | B40: =B38*B34+B39*B37 -> 0.098321532 | C40: % | F40: =B38*B34+B39*B37; bandas de plausibilidad en check 42
A41: WACC del escenario Base del modelo | B41: =Assumptions!B20 -> 0.09 | C41: % | F41: Enlace vivo Assumptions!B20
A42: Delta: WACC fechado − Base | B42: =B40-B41 -> 0.0083215325 | C42: pp | F42: H3: +0.83pp; el rango Bull 8.2% / Bear 10.2% del modelo sigue abrazando el valor fechado. No corregido
A44: BLOQUE 4 — MÚLTIPLOS IMPLÍCITOS CONTRA FY2025A (enlaces vivos a los estados auditados)
A45: EBITDA FY2025A | B45: =IS_Hist!F14+CF_Hist!F7+CF_Hist!F8 -> 2624188.1 | C45: TWD mm | F45: Construcción del analista: EBIT (IS_Hist!F14) + depreciación (CF_Hist!F7) + amortización (CF_Hist!F8). TSMC no publica EBITDA — no-IFRS (L5)
A46: FCF FY2025A (CFO − capex) | B46: =CF_Hist!F13+CF_Hist!F15 -> 1002565.1 | C46: TWD mm | F46: =CF_Hist!F13+CF_Hist!F15 (F15 ya es negativo)
A47: P/E (cap. de mercado TWD / utilidad del controlador) | B47: =B13/IS_Hist!F27 -> 42.096553 | C47: x
A48: P/E vía UPA diluida | B48: =(B7/B9*B12)/IS_Hist!F31 -> 42.091625 | C48: x | F48: Precio por ordinaria en TWD (B7/B9*B12) ÷ UPA diluida (IS_Hist!F31) — cross del B47
A49: EV/Ventas | B49: =B23/IS_Hist!F5 -> 18.305963 | C49: x
A50: EV/EBITDA | B50: =B23/B45 -> 26.571421 | C50: x
A51: EV/EBIT | B51: =B23/IS_Hist!F14 -> 36.015034 | C51: x
A52: P/B (cap. mercado / patrimonio del controlador) | B52: =B13/BS_Hist!F64 -> 13.345053 | C52: x
A53: FCF yield | B53: =B46/B13 -> 0.014029095 | C53: %
A54: Dividend yield (dividendos pagados FY2025) | B54: =-CF_Hist!F31/B13 -> 0.0065317353 | C54: % | F54: =-CF_Hist!F31/B13 (F31 es salida negativa)
A56: BLOQUE 5 — CONTRA EL DCF EXISTENTE (declarado, no recableado)
A57: Precio implícito del DCF (Base) | B57: =Valuation!B21 -> 268.05038 | C57: USD/ADS | F57: Enlace vivo Valuation!B21
A58: Upside/(downside) implícito del DCF vs precio de mercado fechado | B58: =B57/B7-1 -> -0.37733658 | C58: % | F58: INFORMATIVO: es tesis, no identidad — vive FUERA del rango del gate (fila informativa de Checks_TieOut)
A59: Precio que usa el modelo (Assumptions!E24) | B59: =Assumptions!E24 -> 419.48 | C59: USD/ADS | F59: H2: fechado en el build 2026-07-16; enlace vivo
A60: Deriva: precio de mercado fechado vs precio del modelo | B60: =B7/B59-1 -> 0.026246782 | C60: % | F60: +2.6% — banda de ±25% en check 40
A61: Spot que usa el modelo (Assumptions!E22) | B61: =Assumptions!E22 -> 32.21 | C61: TWD/USD | F61: Deriva −0.6% vs B12; banda de ±10% en check 43
A63: BLOQUE 6 — CONTROL DE PROCEDENCIA MECANIZADO (0 = completo/OK; gateado en check 45)
A64: Fuentes presentes en los seis inputs de mercado (B7, B8, B12, B31, B32, B33) | B64: =IF(LEN(E7)=0,1,0)+IF(LEN(E8)=0,1,0)+IF(LEN(E12)=0,1,0)+IF(LEN(E31)=0,1,0)+IF(LEN(E32)=0,1,0)+IF(LEN(E33)=0,1,0) -> 0
A65: Fechas presentes y con serial numérico válido | B65: =IF(ISNUMBER(D7),0,1)+IF(ISNUMBER(D8),0,1)+IF(ISNUMBER(D12),0,1)+IF(ISNUMBER(D31),0,1)+IF(ISNUMBER(D32),0,1)+IF(ISNUMBER(D33),0,1) -> 0
A66: Desfase entre cotizaciones diarias (precio, spot, Rf, beta) ≤ 5 días | B66: =IF(MAX(D7,D12,D31,D33)-MIN(D7,D12,D31,D33)>5,1,0) -> 0
A67: Frescura absoluta: la observación diaria más reciente no puede ser anterior a HOY()−10 al recalcular | B67: =IF(MAX(D7,D12,D31,D33)<TODAY()-10,1,0) -> 1
A68: Estado del bloque de procedencia | B68: =IF(B64+B65+B66+B67=0,"PASS","FAIL") -> FAIL
A70: BLOQUE 7 — HALLAZGOS Y LIMITACIONES (declarados, no corregidos)
A71: H1 — La definición de liquidez del DCF (Forecast!B26 → Valuation!B14) es SOLO caja y equivalentes: excluye los activos financieros corrientes de B17 (300,738.4 TWD mm, 7.9% de las ventas FY2025). El EV de este paquete usa la misma definición por comparabilidad; incluir B17 bajaría el EV ~0.43%. Corregirlo movería outputs gateados del DCF — queda declarado.
A72: H2 — El precio del modelo (Assumptions!E24 = 419.48, build 2026-07-16) está desfasado +2.6% contra el cierre fechado 430.49 del 2026-08-13. Refrescarlo movería Valuation!B23 (upside/downside). Instrucción exacta: Assumptions!B24:D24 ← Market_Package!B7 con su fecha.
A73: H3 — WACC fechado 9.83% vs 9.00% del escenario Base (+0.83pp), impulsado por beta 1.26 y Rf 4.63%. Bull 8.2% / Bear 10.2% siguen abrazando el valor fechado. Instrucción: Assumptions!B20 ← Market_Package!B40 si se decide re-datar el DCF.
A74: H4 — Prima/descuento del ADS contra la acción local (TWSE 2330): NO medida — el precio de TWSE está fuera del paquete de fuentes de esta corrida. El precio implícito local sería B7/B9*B12 = ~2,756 TWD/acción.
A75: L1 — Beta de proveedor, no propia: stockanalysis 1.26 vs finviz 1.40 el mismo día. La varianza entre proveedores es material (±0.6pp de Ke).
A76: L2 — ERP implícita de EE.UU. sin prima de riesgo país de Taiwán. El riesgo cross-strait queda cualitativo (Drivers_MDA bloque 9), no cargado al costo de capital.
A77: L3 — Kd efectivo retrospectivo (finance costs / deuda promedio = 1.21%), no curva de mercado; consistente con los cupones divulgados 0.41%–4.63%. Con Wd = 1.4%, el efecto en el WACC es de segundo orden.
A78: L4 — El EV mezcla precio de ago-2026 con balance de dic-2025. No hay vintage intermedio local (los 6-K trimestrales de 2026 no están en el paquete) — a diferencia del piloto Apple, no hay ancla de vintage distinto para el balance; se compensa con los ties cross-fuente del check 41.
A79: L5 — EBITDA es construcción no-IFRS del analista (EBIT + D&A del estado de flujos).
A80: L6 — Mezcla de fechas: ERP de ene-2026 con precio/Rf/beta/spot de ago-2026. A propósito y fechada; el check 45 exige coherencia solo entre las cotizaciones diarias.

Sheet Claude Code Log
A1: Turn # | B1: Date | C1: User Request | D1: Action Taken | E1: Details | F1: Outcome
A2: 1 | B2: 46324.359 | C2: Prepare a public model copy | D2: Remove local paths and private build references; preserve financial formulas and inputs | E2: Agent run with MOG as the tool, checked by guard v1. The guard measured every sheet before and after the run. Changed: Change_Log: 1 cell written, at E8; Gate_9of10: 4 cells written, at E5, E10, E11, E12; Sources_Audited: 3 cells written, at D4, D5, A8. Agent: OpenFinmods export | F2: Compare against source and review public copy
