Workbook

Sheet 00_Cover
A1: Berkshire Hathaway Inc. - Insurance & Diversified Holdco SOTP
A2: USD millions except per-share data | FY2025 actual | sector-correct controlled rebuild
A4: Model field | B4: Value
A5: Legal entity | B5: Berkshire Hathaway Inc.
A6: Ticker | B6: BRK.B
A7: CIK | B7: 0001067983
A8: Model archetype | B8: Insurance + diversified holding company SOTP
A9: Primary valuation | B9: Net investments + segment earnings capitalization
A10: Secondary cross-check | B10: Price / book and earnings bridge
A11: Reporting/model currency | B11: USD / USD millions
A12: Actual period | B12: Year ended 2025-12-31
A13: Source filing | B13: 2025 Form 10-K filed 2026-03-02
A14: Scenario | B14: =Assumptions!E4 -> Base
A15: Overall model status | B15: =Checks!F15 -> PASS
A16: Independent status | B16: PENDING INDEPENDENT REVIEW
A18: Use: change only blue/yellow assumption cells. Historical facts are hardcoded from the claim-level Sources ledger; formulas and cross-sheet links remain traceable.

Sheet Sources
A1: Claim-level source ledger
A2: Every material reported hardcode maps to an exact filing, locator and workbook destination.
A4: Source ID | B4: Legal entity | C4: Metric | D4: Reported value | E4: Units | F4: Period | G4: Basis / context | H4: Claim locator | I4: Form | J4: Filed | K4: Accession | L4: Exact official URL | M4: Workbook destination | N4: Transformation | O4: Class | P4: Status
A5: BRK25-REV | B5: Berkshire Hathaway Inc. | C5: Total revenues | D5: 371444 | E5: USD mm | F5: FY2025 | G5: Consolidated | H5: Annual report PDF p.92 / K-67, total revenues | I5: 10-K | J5: 2026-03-02 | K5: 0001193125-26-083899 | L5: https://www.berkshirehathaway.com/2025ar/2025ar.pdf | M5: Historical!C5 | N5: Direct; dollars in millions | O5: Primary filing | P5: PASS
A6: BRK25-NI | B6: Berkshire Hathaway Inc. | C6: Net income attributable to Berkshire shareholders | D6: 66968 | E6: USD mm | F6: FY2025 | G6: Consolidated | H6: Annual report PDF p.58 / K-34; us-gaap:NetIncomeLoss | I6: 10-K | J6: 2026-03-02 | K6: 0001193125-26-083899 | L6: https://www.sec.gov/Archives/edgar/data/1067983/000119312526083899/brka-20251231.htm | M6: Historical!C6 | N6: Direct; dollars in millions | O6: Primary filing | P6: PASS
A7: BRK25-EQ | B7: Berkshire Hathaway Inc. | C7: Shareholders equity | D7: 717419 | E7: USD mm | F7: 2025-12-31 | G7: Consolidated | H7: Annual report PDF p.91 / K-66; us-gaap:StockholdersEquity | I7: 10-K | J7: 2026-03-02 | K7: 0001193125-26-083899 | L7: https://www.sec.gov/Archives/edgar/data/1067983/000119312526083899/brka-20251231.htm | M7: Historical!C7 | N7: Direct; dollars in millions | O7: Primary filing | P7: PASS
A8: BRK25-CASH | B8: Berkshire Hathaway Inc. | C8: Insurance and other cash, equivalents and Treasury Bills | D8: 369000 | E8: USD mm | F8: 2025-12-31 | G8: Insurance and other businesses | H8: Annual report PDF p.77 / K-52, Financial Condition | I8: 10-K | J8: 2026-03-02 | K8: 0001193125-26-083899 | L8: https://www.berkshirehathaway.com/2025ar/2025ar.pdf | M8: Historical!C8 | N8: Rounded issuer disclosure | O8: Primary filing | P8: PASS
A9: BRK25-SEC | B9: Berkshire Hathaway Inc. | C9: Equity and fixed maturity securities | D9: 315600 | E9: USD mm | F9: 2025-12-31 | G9: Excludes equity-method investments | H9: Annual report PDF p.77 / K-52, Financial Condition | I9: 10-K | J9: 2026-03-02 | K9: 0001193125-26-083899 | L9: https://www.berkshirehathaway.com/2025ar/2025ar.pdf | M9: Historical!C9 | N9: Rounded issuer disclosure | O9: Primary filing | P9: PASS
A10: BRK25-FLOAT | B10: Berkshire Hathaway Inc. | C10: Insurance float | D10: 176000 | E10: USD mm | F10: 2025-12-31 | G10: Approximate policyholder funds | H10: Annual report PDF p.65 / K-40 | I10: 10-K | J10: 2026-03-02 | K10: 0001193125-26-083899 | L10: https://www.berkshirehathaway.com/2025ar/2025ar.pdf | M10: Historical!C10 | N10: Rounded issuer disclosure | O10: Primary filing | P10: PASS
A11: BRK25-DEBT | B11: Berkshire Hathaway Inc. | C11: Borrowings excluding BHE and BNSF | D11: 45800 | E11: USD mm | F11: 2025-12-31 | G11: Berkshire + BHFC | H11: Annual report PDF p.77 / K-52, Financial Condition | I11: 10-K | J11: 2026-03-02 | K11: 0001193125-26-083899 | L11: https://www.berkshirehathaway.com/2025ar/2025ar.pdf | M11: Historical!C11 | N11: Rounded issuer disclosure | O11: Primary filing | P11: PASS
A12: BRK25-UW | B12: Berkshire Hathaway Inc. | C12: Insurance underwriting after-tax earnings | D12: 7258 | E12: USD mm | F12: FY2025 | G12: Operating earnings | H12: Annual report PDF p.58 / K-34 | I12: 10-K | J12: 2026-03-02 | K12: 0001193125-26-083899 | L12: https://www.berkshirehathaway.com/2025ar/2025ar.pdf | M12: Historical!C13 | N12: Direct; excludes investment gains | O12: Primary filing | P12: PASS
A13: BRK25-INV | B13: Berkshire Hathaway Inc. | C13: Insurance investment after-tax income | D13: 12513 | E13: USD mm | F13: FY2025 | G13: Operating earnings | H13: Annual report PDF p.58 / K-34 | I13: 10-K | J13: 2026-03-02 | K13: 0001193125-26-083899 | L13: https://www.berkshirehathaway.com/2025ar/2025ar.pdf | M13: Historical!C14 | N13: Direct | O13: Primary filing | P13: PASS
A14: BRK25-BNSF | B14: BNSF Railway | C14: Net earnings | D14: 5476 | E14: USD mm | F14: FY2025 | G14: Attributable to Berkshire | H14: Annual report PDF p.58 / K-34 and p.65 / K-41 | I14: 10-K | J14: 2026-03-02 | K14: 0001193125-26-083899 | L14: https://www.berkshirehathaway.com/2025ar/2025ar.pdf | M14: Historical!C15 | N14: Direct | O14: Primary filing | P14: PASS
A15: BRK25-BHE | B15: Berkshire Hathaway Energy | C15: Net earnings | D15: 3979 | E15: USD mm | F15: FY2025 | G15: Attributable to Berkshire | H15: Annual report PDF p.68 / K-44 | I15: 10-K | J15: 2026-03-02 | K15: 0001193125-26-083899 | L15: https://www.berkshirehathaway.com/2025ar/2025ar.pdf | M15: Historical!C16 | N15: Direct | O15: Primary filing | P15: PASS
A16: BRK25-MSR | B16: Berkshire Hathaway Inc. | C16: Manufacturing, service and retailing net earnings | D16: 13647 | E16: USD mm | F16: FY2025 | G16: Operating earnings | H16: Annual report PDF p.58 / K-34 and p.70 / K-46 | I16: 10-K | J16: 2026-03-02 | K16: 0001193125-26-083899 | L16: https://www.berkshirehathaway.com/2025ar/2025ar.pdf | M16: Historical!C17 | N16: Direct | O16: Primary filing | P16: PASS
... A24: BRK24-FLOAT | B24: Berkshire Hathaway Inc. | C24: Insurance float | D24: 171000 | E24: USD mm | F24: 2024-12-31 | G24: Comparative | H24: Annual report PDF p.65 / K-40 | I24: 10-K | J24: 2026-03-02 | K24: 0001193125-26-083899 | L24: https://www.berkshirehathaway.com/2025ar/2025ar.pdf | M24: Historical!B10 | N24: Rounded issuer disclosure | O24: Primary filing | P24: PASS
A25: Completeness | O25: =COUNTIF(P5:P24,"PASS") -> 20 | P25: =IF(O25=20,"PASS","FAIL") -> PASS

Sheet Historical
A1: Historical and segment evidence
A2: Reported values; formulas only where explicitly derived.
A4: Metric | B4: 2024A | C4: 2025A
A5: Total revenues | B5: 371433 | C5: 371444
A6: Net income attributable | B6: 88995 | C6: 66968
A7: Shareholders equity | B7: 649368 | C7: 717419
A8: Cash + Treasury Bills | B8: 330805 | C8: 369000
A9: Equity + fixed maturity securities | B9: 286952 | C9: 315600
A10: Insurance float | B10: 171000 | C10: 176000
A11: Borrowings excl. BNSF/BHE | B11: 44885 | C11: 45800
A13: Insurance underwriting earnings | B13: 9020 | C13: 7258
A14: Insurance investment income | B14: 13670 | C14: 12513
A15: BNSF earnings | B15: 5031 | C15: 5476
A16: BHE earnings | B16: 3730 | C16: 3979
A17: Manufacturing/service/retailing earnings | B17: 13072 | C17: 13647
A18: Other earnings | B18: 2914 | C18: 1613
A19: Operating earnings excluding investment gains | B19: =SUM(B13:B18) -> 47437 | C19: =SUM(C13:C18) -> 44486
A21: Equivalent Class B shares (mm) | B21: 2156.5803 | C21: 2157.3351

Sheet Assumptions
A1: Scenario assumptions
A2: 1 = Base, 2 = Bull, 3 = Bear. Blue/yellow cells are editable model assumptions.
A4: Scenario selector | B4: 1 | E4: =IF(B4=1,"Base",IF(B4=2,"Bull",IF(B4=3,"Bear","INVALID"))) -> Base
A6: Driver | B6: Base | C6: Bull | D6: Bear | E6: Active
A7: Underwriting earnings growth | B7: 0.02 | C7: 0.07 | D7: -0.1 | E7: =IF($B$4=1,B7,IF($B$4=2,C7,D7)) -> 0.02
A8: BNSF earnings growth | B8: 0.05 | C8: 0.07 | D8: 0 | E8: =IF($B$4=1,B8,IF($B$4=2,C8,D8)) -> 0.05
A9: BHE earnings growth | B9: 0.04 | C9: 0.06 | D9: -0.03 | E9: =IF($B$4=1,B9,IF($B$4=2,C9,D9)) -> 0.04
A10: Manufacturing/service/retailing growth | B10: 0.04 | C10: 0.06 | D10: 0 | E10: =IF($B$4=1,B10,IF($B$4=2,C10,D10)) -> 0.04
A11: Other earnings growth | B11: 0.02 | C11: 0.04 | D11: -0.1 | E11: =IF($B$4=1,B11,IF($B$4=2,C11,D11)) -> 0.02
A12: Net investment asset growth | B12: 0.03 | C12: 0.05 | D12: -0.02 | E12: =IF($B$4=1,B12,IF($B$4=2,C12,D12)) -> 0.03
A13: Underwriting multiple | B13: 12 | C13: 14 | D13: 9 | E13: =IF($B$4=1,B13,IF($B$4=2,C13,D13)) -> 12
A14: BNSF multiple | B14: 16 | C14: 18 | D14: 13 | E14: =IF($B$4=1,B14,IF($B$4=2,C14,D14)) -> 16
A15: BHE multiple | B15: 17 | C15: 19 | D15: 14 | E15: =IF($B$4=1,B15,IF($B$4=2,C15,D15)) -> 17
A16: Manufacturing/service/retailing multiple | B16: 18 | C16: 20 | D16: 14 | E16: =IF($B$4=1,B16,IF($B$4=2,C16,D16)) -> 18
A17: Other multiple | B17: 10 | C17: 12 | D17: 7 | E17: =IF($B$4=1,B17,IF($B$4=2,C17,D17)) -> 10
A18: Price / book cross-check | B18: 1.25 | C18: 1.4 | D18: 1 | E18: =IF($B$4=1,B18,IF($B$4=2,C18,D18)) -> 1.25
A19: Net investment haircut | B19: 0 | C19: 0.03 | D19: 0.1 | E19: =IF($B$4=1,B19,IF($B$4=2,C19,D19)) -> 0

Sheet Operating_Model
A1: Berkshire operating architecture
A2: Separates insurance float/investments from after-tax operating businesses to avoid double counting.
A4: Metric | B4: 2025A | C4: 2026E | D4: 2027E | E4: 2028E | F4: 2029E | G4: 2030E | H4: Driver
A5: Insurance underwriting earnings | B5: =Historical!C13 -> 7258 | C5: =B5*(1+Assumptions!$E$7) -> 7403.16 | D5: =C5*(1+Assumptions!$E$7) -> 7551.2232 | E5: =D5*(1+Assumptions!$E$7) -> 7702.2477 | F5: =E5*(1+Assumptions!$E$7) -> 7856.2926 | G5: =F5*(1+Assumptions!$E$7) -> 8013.4185 | H5: Assumptions!E7
A6: BNSF earnings | B6: =Historical!C15 -> 5476 | C6: =B6*(1+Assumptions!$E$8) -> 5749.8 | D6: =C6*(1+Assumptions!$E$8) -> 6037.29 | E6: =D6*(1+Assumptions!$E$8) -> 6339.1545 | F6: =E6*(1+Assumptions!$E$8) -> 6656.1122 | G6: =F6*(1+Assumptions!$E$8) -> 6988.9178 | H6: Assumptions!E8
A7: BHE earnings | B7: =Historical!C16 -> 3979 | C7: =B7*(1+Assumptions!$E$9) -> 4138.16 | D7: =C7*(1+Assumptions!$E$9) -> 4303.6864 | E7: =D7*(1+Assumptions!$E$9) -> 4475.8339 | F7: =E7*(1+Assumptions!$E$9) -> 4654.8672 | G7: =F7*(1+Assumptions!$E$9) -> 4841.0619 | H7: Assumptions!E9
A8: Manufacturing/service/retailing earnings | B8: =Historical!C17 -> 13647 | C8: =B8*(1+Assumptions!$E$10) -> 14192.88 | D8: =C8*(1+Assumptions!$E$10) -> 14760.595 | E8: =D8*(1+Assumptions!$E$10) -> 15351.019 | F8: =E8*(1+Assumptions!$E$10) -> 15965.06 | G8: =F8*(1+Assumptions!$E$10) -> 16603.662 | H8: Assumptions!E10
A9: Other earnings | B9: =Historical!C18 -> 1613 | C9: =B9*(1+Assumptions!$E$11) -> 1645.26 | D9: =C9*(1+Assumptions!$E$11) -> 1678.1652 | E9: =D9*(1+Assumptions!$E$11) -> 1711.7285 | F9: =E9*(1+Assumptions!$E$11) -> 1745.9631 | G9: =F9*(1+Assumptions!$E$11) -> 1780.8823 | H9: Assumptions!E11
A10: Operating earnings subtotal | B10: =SUM(B5:B9) -> 31973 | C10: =SUM(C5:C9) -> 33129.26 | D10: =SUM(D5:D9) -> 34330.96 | E10: =SUM(E5:E9) -> 35579.984 | F10: =SUM(F5:F9) -> 36878.295 | G10: =SUM(G5:G9) -> 38227.943
A11: Net investment assets before haircut | B11: =Historical!C8+Historical!C9-Historical!C10-Historical!C11 -> 462800 | C11: =B11*(1+Assumptions!$E$12) -> 476684 | D11: =C11*(1+Assumptions!$E$12) -> 490984.52 | E11: =D11*(1+Assumptions!$E$12) -> 505714.06 | F11: =E11*(1+Assumptions!$E$12) -> 520885.48 | G11: =F11*(1+Assumptions!$E$12) -> 536512.04 | H11: Assumptions!E12
A12: Net investment assets after haircut | B12: =B11*(1-Assumptions!E19) -> 462800 | C12: =C11*(1-Assumptions!$E$19) -> 476684 | D12: =D11*(1-Assumptions!$E$19) -> 490984.52 | E12: =E11*(1-Assumptions!$E$19) -> 505714.06 | F12: =F11*(1-Assumptions!$E$19) -> 520885.48 | G12: =G11*(1-Assumptions!$E$19) -> 536512.04 | H12: Assumptions!E19

Sheet Forecast
A1: Forecast summary
A2: Formula-driven segment earnings and net investment asset outlook.
A4: Metric | B4: 2025A | C4: 2026E | D4: 2027E | E4: 2028E | F4: 2029E | G4: 2030E
A5: Operating earnings | B5: =Operating_Model!B10 -> 31973 | C5: =Operating_Model!C10 -> 33129.26 | D5: =Operating_Model!D10 -> 34330.96 | E5: =Operating_Model!E10 -> 35579.984 | F5: =Operating_Model!F10 -> 36878.295 | G5: =Operating_Model!G10 -> 38227.943
A6: Net investment assets | B6: =Operating_Model!B12 -> 462800 | C6: =Operating_Model!C12 -> 476684 | D6: =Operating_Model!D12 -> 490984.52 | E6: =Operating_Model!E12 -> 505714.06 | F6: =Operating_Model!F12 -> 520885.48 | G6: =Operating_Model!G12 -> 536512.04
A7: Shareholders equity | B7: =Historical!C7 -> 717419 | C7: =B7+C5 -> 750548.26 | D7: =C7+D5 -> 784879.22 | E7: =D7+E5 -> 820459.2 | F7: =E7+F5 -> 857337.5 | G7: =F7+G5 -> 895565.44
A8: ROE | B8: =B5/B7 -> 0.044566704 | C8: =C5/AVERAGE(B7:C7) -> 0.045136238 | D8: =D5/AVERAGE(C7:D7) -> 0.044718439 | E8: =E5/AVERAGE(D7:E7) -> 0.044327081 | F8: =F5/AVERAGE(E7:F7) -> 0.043960385 | G8: =G5/AVERAGE(F7:G7) -> 0.043616725

Sheet Valuation
A1: Sum-of-the-parts valuation
A2: Net investment assets plus separately capitalized after-tax operating earnings; insurance investment income is excluded from earnings multiples to prevent double counting.
A4: Component | B4: 2026E earnings / asset | C4: Multiple | D4: Gross value | E4: Adjustment | F4: Equity contribution | G4: Method | H4: Source / driver
A5: Net investment assets | B5: =Operating_Model!C12 -> 476684 | D5: =B5 -> 476684 | E5: 0 | F5: =D5 -> 476684 | G5: Asset value | H5: Operating_Model
A6: Insurance underwriting | B6: =Operating_Model!C5 -> 7403.16 | C6: =Assumptions!E13 -> 12 | D6: =B6*C6 -> 88837.92 | E6: 0 | F6: =D6+E6 -> 88837.92 | G6: P/E | H6: Forecast earnings
A7: BNSF | B7: =Operating_Model!C6 -> 5749.8 | C7: =Assumptions!E14 -> 16 | D7: =B7*C7 -> 91996.8 | E7: 0 | F7: =D7+E7 -> 91996.8 | G7: P/E | H7: Forecast earnings
A8: BHE | B8: =Operating_Model!C7 -> 4138.16 | C8: =Assumptions!E15 -> 17 | D8: =B8*C8 -> 70348.72 | E8: 0 | F8: =D8+E8 -> 70348.72 | G8: P/E | H8: Forecast earnings
A9: Manufacturing/service/retailing | B9: =Operating_Model!C8 -> 14192.88 | C9: =Assumptions!E16 -> 18 | D9: =B9*C9 -> 255471.84 | E9: 0 | F9: =D9+E9 -> 255471.84 | G9: P/E | H9: Forecast earnings
A10: Other | B10: =Operating_Model!C9 -> 1645.26 | C10: =Assumptions!E17 -> 10 | D10: =B10*C10 -> 16452.6 | E10: 0 | F10: =D10+E10 -> 16452.6 | G10: P/E | H10: Forecast earnings
A12: Output | B12: Value
A13: SOTP equity value | B13: =SUM(F5:F10) -> 999791.88
A14: Equivalent Class B shares (mm) | B14: =Historical!C21 -> 2157.3351
A15: Implied value per Class B share | B15: =B13/B14 -> 463.43837
A16: Price / book cross-check | B16: =Historical!C7*Assumptions!E18/Historical!C21 -> 415.68588

Sheet Sensitivity
A1: Dynamic SOTP sensitivity
A2: Rows vary underwriting multiple; columns vary manufacturing/service/retailing multiple. Every cell recalculates the underlying SOTP.
A4: UW / MSR | B4: 14 | C4: 16 | D4: 18 | E4: 20 | F4: 22
A5: 8 | B5: =(Valuation!F5+Valuation!B6*$A5+Valuation!F7+Valuation!F8+Valuation!B9*B$4+Valuation!F10)/Historical!C21 -> 423.3963 | C5: =(Valuation!F5+Valuation!B6*$A5+Valuation!F7+Valuation!F8+Valuation!B9*C$4+Valuation!F10)/Historical!C21 -> 436.55409 | D5: =(Valuation!F5+Valuation!B6*$A5+Valuation!F7+Valuation!F8+Valuation!B9*D$4+Valuation!F10)/Historical!C21 -> 449.71188 | E5: =(Valuation!F5+Valuation!B6*$A5+Valuation!F7+Valuation!F8+Valuation!B9*E$4+Valuation!F10)/Historical!C21 -> 462.86967 | F5: =(Valuation!F5+Valuation!B6*$A5+Valuation!F7+Valuation!F8+Valuation!B9*F$4+Valuation!F10)/Historical!C21 -> 476.02746
A6: 10 | B6: =(Valuation!F5+Valuation!B6*$A6+Valuation!F7+Valuation!F8+Valuation!B9*B$4+Valuation!F10)/Historical!C21 -> 430.25955 | C6: =(Valuation!F5+Valuation!B6*$A6+Valuation!F7+Valuation!F8+Valuation!B9*C$4+Valuation!F10)/Historical!C21 -> 443.41734 | D6: =(Valuation!F5+Valuation!B6*$A6+Valuation!F7+Valuation!F8+Valuation!B9*D$4+Valuation!F10)/Historical!C21 -> 456.57512 | E6: =(Valuation!F5+Valuation!B6*$A6+Valuation!F7+Valuation!F8+Valuation!B9*E$4+Valuation!F10)/Historical!C21 -> 469.73291 | F6: =(Valuation!F5+Valuation!B6*$A6+Valuation!F7+Valuation!F8+Valuation!B9*F$4+Valuation!F10)/Historical!C21 -> 482.8907
A7: 12 | B7: =(Valuation!F5+Valuation!B6*$A7+Valuation!F7+Valuation!F8+Valuation!B9*B$4+Valuation!F10)/Historical!C21 -> 437.12279 | C7: =(Valuation!F5+Valuation!B6*$A7+Valuation!F7+Valuation!F8+Valuation!B9*C$4+Valuation!F10)/Historical!C21 -> 450.28058 | D7: =(Valuation!F5+Valuation!B6*$A7+Valuation!F7+Valuation!F8+Valuation!B9*D$4+Valuation!F10)/Historical!C21 -> 463.43837 | E7: =(Valuation!F5+Valuation!B6*$A7+Valuation!F7+Valuation!F8+Valuation!B9*E$4+Valuation!F10)/Historical!C21 -> 476.59616 | F7: =(Valuation!F5+Valuation!B6*$A7+Valuation!F7+Valuation!F8+Valuation!B9*F$4+Valuation!F10)/Historical!C21 -> 489.75395
A8: 14 | B8: =(Valuation!F5+Valuation!B6*$A8+Valuation!F7+Valuation!F8+Valuation!B9*B$4+Valuation!F10)/Historical!C21 -> 443.98604 | C8: =(Valuation!F5+Valuation!B6*$A8+Valuation!F7+Valuation!F8+Valuation!B9*C$4+Valuation!F10)/Historical!C21 -> 457.14383 | D8: =(Valuation!F5+Valuation!B6*$A8+Valuation!F7+Valuation!F8+Valuation!B9*D$4+Valuation!F10)/Historical!C21 -> 470.30162 | E8: =(Valuation!F5+Valuation!B6*$A8+Valuation!F7+Valuation!F8+Valuation!B9*E$4+Valuation!F10)/Historical!C21 -> 483.4594 | F8: =(Valuation!F5+Valuation!B6*$A8+Valuation!F7+Valuation!F8+Valuation!B9*F$4+Valuation!F10)/Historical!C21 -> 496.61719
A9: 16 | B9: =(Valuation!F5+Valuation!B6*$A9+Valuation!F7+Valuation!F8+Valuation!B9*B$4+Valuation!F10)/Historical!C21 -> 450.84928 | C9: =(Valuation!F5+Valuation!B6*$A9+Valuation!F7+Valuation!F8+Valuation!B9*C$4+Valuation!F10)/Historical!C21 -> 464.00707 | D9: =(Valuation!F5+Valuation!B6*$A9+Valuation!F7+Valuation!F8+Valuation!B9*D$4+Valuation!F10)/Historical!C21 -> 477.16486 | E9: =(Valuation!F5+Valuation!B6*$A9+Valuation!F7+Valuation!F8+Valuation!B9*E$4+Valuation!F10)/Historical!C21 -> 490.32265 | F9: =(Valuation!F5+Valuation!B6*$A9+Valuation!F7+Valuation!F8+Valuation!B9*F$4+Valuation!F10)/Historical!C21 -> 503.48044

Sheet Checks
A1: Model checks
A2: One assertion per row. Overall status is formula-driven and cannot be manually painted green.
A4: Check | B4: Actual | C4: Expected | D4: Difference | E4: Tolerance | F4: Status | G4: Severity | H4: Location / fix hint
A5: Source ledger completeness | B5: =Sources!O25 -> 20 | C5: 20 | D5: =B5-C5 -> 0 | E5: 0 | F5: =IF(ABS(D5)<=E5,"PASS","FAIL") -> PASS | G5: Critical | H5: Sources!A4:P25
A6: Operating earnings tie | B6: =Historical!C19 -> 44486 | C6: 44486 | D6: =B6-C6 -> 0 | E6: 0.1 | F6: =IF(ABS(D6)<=E6,"PASS","FAIL") -> PASS | G6: Critical | H6: Historical!C13:C19
A7: Net investment asset bridge | B7: =Operating_Model!B11 -> 462800 | C7: 462800 | D7: =B7-C7 -> 0 | E7: 1 | F7: =IF(ABS(D7)<=E7,"PASS","FAIL") -> PASS | G7: Critical | H7: Operating_Model!B11
A8: Scenario selector valid | B8: =Assumptions!B4 -> 1 | C8: 1 | D8: =0 -> 0 | E8: 0 | F8: =IF(AND(B8>=1,B8<=3),"PASS","FAIL") -> PASS | G8: Critical | H8: Assumptions!B4
A9: Float below investable assets | B9: =Historical!C10 -> 176000 | C9: =Historical!C8+Historical!C9 -> 684600 | D9: =C9-B9 -> 508600 | E9: 0 | F9: =IF(D9>=E9,"PASS","FAIL") -> PASS | G9: Critical | H9: Historical!C8:C10
A10: SOTP total formula tie | B10: =Valuation!B13 -> 999791.88 | C10: =SUM(Valuation!F5:F10) -> 999791.88 | D10: =B10-C10 -> 0 | E10: 0.1 | F10: =IF(ABS(D10)<=E10,"PASS","FAIL") -> PASS | G10: Critical | H10: Valuation!F5:F10
A11: Sensitivity center ties valuation | B11: =Sensitivity!D7 -> 463.43837 | C11: =Valuation!B15 -> 463.43837 | D11: =B11-C11 -> 0 | E11: 0.01 | F11: =IF(ABS(D11)<=E11,"PASS","FAIL") -> PASS | G11: Critical | H11: Sensitivity!D7 / Valuation!B15
A12: Forecast values non-negative | B12: =MIN(Operating_Model!C5:G12) -> 1645.26 | C12: 0 | D12: =B12-C12 -> 1645.26 | E12: 0 | F12: =IF(D12>=E12,"PASS","FAIL") -> PASS | G12: Critical | H12: Operating_Model!C5:G12
A13: Equivalent share count positive | B13: =Historical!C21 -> 2157.3351 | C13: 0 | D13: =B13-C13 -> 2157.3351 | E13: 0 | F13: =IF(D13>E13,"PASS","FAIL") -> PASS | G13: Critical | H13: Historical!C21
A14: Forecast engine propagates through 2030 | B14: =COUNTIF(Operating_Model!D5:G12,0) -> 0 | C14: 0 | D14: =B14-C14 -> 0 | E14: 0 | F14: =IF(ABS(D14)<=E14,"PASS","FAIL") -> PASS | G14: Critical | H14: Operating_Model!D5:G12
A15: Overall model status | F15: =IF(COUNTIF(F5:F14,"FAIL")=0,"PASS","FAIL") -> PASS | H15: All critical checks must pass

Sheet Gate_9of10
A1: Owner 9/10 submission gate
A2: Owner evidence only; final certification belongs to the independent reviewer after the workbook hash is frozen.
A4: Gate | B4: Weight | C4: Owner status | D4: Blocker class | E4: Workbook evidence | F4: External evidence pointer | G4: Reviewer note | H4: Score
A5: H0 Controlled lineage / OOXML | B5: 5 | C5: PASS | D5: None | E5: 00_Cover; Change_Log | F5: internal QA evidence (not published) | G5: Original hash + controlled hash recorded externally | H5: 5
A6: H1 Source fidelity / provenance | B6: 20 | C6: PASS | D6: None | E6: Sources!A4:P25 | F6: BRK 2025 10-K + annual report PDF | G6: 20 claim-level mappings | H6: 20
A7: H2 Formula and schedule mechanics | B7: 15 | C7: PASS | D7: None | E7: Operating_Model; Forecast | F7: Scenario evidence | G7: Sector-correct float/investment/segment architecture | H7: 15
A8: H3 Scenarios / sensitivity | B8: 10 | C8: PASS | D8: None | E8: Assumptions; Sensitivity | F8: Scenario perturbation log | G8: Dynamic base/bull/bear and two-factor SOTP | H8: 10
A9: H4 Valuation fit / mechanics | B9: 15 | C9: PASS | D9: None | E9: Valuation!A4:H16 | F9: SOTP evidence | G9: No bank-shell residual-income misclassification | H9: 15
A10: H5 Checks / error state | B10: 8 | C10: PASS | D10: None | E10: Checks!A4:H15 | F10: Post-recalc error scan | G10: Formula-driven overall status | H10: 8
A11: H6 Native recalculation | B11: 10 | C11: PASS | D11: None | E11: Gate_9of10!A17:H20 | F11: Native recalc log | G11: Two isolated-profile LibreOfficeDev passes plus artifact-tool reopen and error scan | H11: 10
A12: H7 Post-recalc visual QA | B12: 7 | C12: PASS | D12: None | E12: All user-facing sheets | F12: Final preview manifest | G12: Every user-facing sheet rendered and reviewed; manifest is hash-bound after final pass | H12: 7
A13: H8 Material economic upgrade | B13: 5 | C13: PASS | D13: None | E13: Operating_Model; Valuation | F13: Change_Log | G13: Insurance/diversified SOTP replaces generic bank shell | H13: 5
A14: H9 Governance / handoff | B14: 5 | C14: PASS | D14: None | E14: 00_Cover; Change_Log | F14: Evidence JSON | G14: Independent certification pending | H14: 5
A16: Owner score | H16: =SUM(H5:H14) -> 100
A17: Owner decision | C17: =IF(H16>=90,"SUBMITTED FOR INDEPENDENT 9/10 REVIEW","NOT READY") -> SUBMITTED FOR INDEPENDENT 9/10 REVIEW
A19: Native engine | B19: LibreOfficeDev 26.8.0.0.alpha0 2c87e51eeaa2b413ff4ae097b2705eea1995d8e5
A20: Lifecycle | B20: RECALC / SAVE / CLOSE / REOPEN x2
A21: Owner evidence | B21: internal QA evidence (not published)

Sheet Change_Log
A1: Change log and governance
A2: Controlled rebuild and review trail.
A4: Date | B4: Version | C4: Author | D4: Change | E4: Evidence | F4: Reviewer status
A5: 2026-07-16 | B5: 2.0 | C5: Codex | D5: Rebuilt Berkshire as insurance/diversified holdco SOTP | E5: Sources; Operating_Model; Valuation | F5: Owner complete
A6: 2026-07-16 | B6: 2.0 | C6: Codex | D6: Added claim-level 2025 10-K and PDF locators | E6: Sources!A4:P25 | F6: Owner complete
A7: 2026-07-16 | B7: 2.0 | C7: Codex | D7: Added formula-driven scenarios, sensitivities and checks | E7: Assumptions; Sensitivity; Checks | F7: Owner complete
A8: 2026-07-16 | B8: 2.0 | C8: Independent reviewer | D8: Certification decision | E8: Frozen workbook hash | F8: Pending

Sheet Claude Code Log
A1: Turn # | B1: Date | C1: User Request | D1: Action Taken | E1: Details | F1: Outcome
A2: 1 | B2: 46324.359 | C2: Prepare a public model copy | D2: Remove local paths and private build references; preserve financial formulas and inputs | E2: Agent run with MOG as the tool, checked by guard v1. The guard measured every sheet before and after the run. Changed: Gate_9of10: 2 cells written, at F5, B21. Agent: OpenFinmods export | F2: Compare against source and review public copy
