Workbook

Sheet 00_Cover
A1: NIKE, Inc. (NKE) — 9/10 Re-gated Institutional Model
A2: Owner-prepared submission; independent reviewer reproduction is required before certification
A4: Model snapshot
A5: Legal entity | B5: NIKE, Inc.
A6: Ticker | B6: NKE
A7: Latest filing | B7: 2026-05-31 10-K filed 2026-07-15
A8: SEC accession | B8: 0000320187-26-000088
A9: Market price | B9: 42.77
A10: Market as-of | B10: 2026-07-15
A11: Active scenario | B11: =Assumptions!B4 -> Base
A12: DCF value / share | B12: =Valuation!G18 -> 31.932642
A13: Upside / (downside) | B13: =Valuation!G20 -> -0.25338691
A14: Gate decision | B14: =Gate_9of10!B17 -> OWNER READY — INDEPENDENT REVIEW REQUIRED
A16: What changed in the 9/10 re-gate
A17: 1 | B17: Replaced generic Sources sheet with target-cell provenance ledger
A18: 2 | B18: Replaced generic assumptions with company-specific operating drivers
A19: 3 | B19: Scenario selector now changes multiple operating outputs and the DCF
A20: 4 | B20: Debt, liquid assets and share-count valuation bridges are explicit
A21: 5 | B21: Checks are formula-driven; Gate_9of10 states owner evidence and review status
A22: 6 | B22: All original workbook files remain preserved; this is a new derivative output

Sheet Sources
A1: NIKE, Inc. — Source Provenance Ledger
A2: Every populated hardcoded historical or driver input is mapped to a target cell with period, value, unit, taxonomy/locator, accession and exact URL.
A4: Source ID | B4: Legal Entity | C4: Target Cell | D4: Metric | E4: Period / As-of | F4: Reported Value | G4: Units | H4: Currency | I4: Taxonomy / Locator | J4: Start | K4: End | L4: FY / FP | M4: Form | N4: Filed | O4: Accession | P4: Exact URL | Q4: Retrieved | R4: Source Class | S4: Transform / Mapping | T4: Verification | U4: Limitation / Disposition | V4: Complete?
A5: 1 | B5: NIKE, Inc. | C5: Historical!B5 | D5: Revenue | E5: 2022A | F5: 46710 | G5: USD millions | H5: USD | I5: us-gaap:RevenueFromContractWithCustomerExcludingAssessedTax | J5: 2021-06-01 | K5: 2022-05-31 | L5: 2024/FY | M5: 10-K | N5: 2024-07-25 | O5: 0000320187-24-000044 | P5: https://www.sec.gov/Archives/edgar/data/320187/000032018724000044/0000320187-24-000044-index.htm | Q5: 2026-07-16 | R5: Primary - SEC filing / Company Facts | S5: USD divided by 1,000,000; sign as presented | T5: Matched legal entity, period, form, filed date, accession and target | U5: None identified | V5: =IF(COUNTA(A5:U5)=21,"OK","MISSING") -> OK
A6: 2 | B6: NIKE, Inc. | C6: Historical!C5 | D6: Revenue | E6: 2023A | F6: 51217 | G6: USD millions | H6: USD | I6: us-gaap:RevenueFromContractWithCustomerExcludingAssessedTax | J6: 2022-06-01 | K6: 2023-05-31 | L6: 2025/FY | M6: 10-K | N6: 2025-07-17 | O6: 0000320187-25-000047 | P6: https://www.sec.gov/Archives/edgar/data/320187/000032018725000047/0000320187-25-000047-index.htm | Q6: 2026-07-16 | R6: Primary - SEC filing / Company Facts | S6: USD divided by 1,000,000; sign as presented | T6: Matched legal entity, period, form, filed date, accession and target | U6: None identified | V6: =IF(COUNTA(A6:U6)=21,"OK","MISSING") -> OK
A7: 3 | B7: NIKE, Inc. | C7: Historical!D5 | D7: Revenue | E7: 2024A | F7: 51362 | G7: USD millions | H7: USD | I7: us-gaap:RevenueFromContractWithCustomerExcludingAssessedTax | J7: 2023-06-01 | K7: 2024-05-31 | L7: 2026/FY | M7: 10-K | N7: 2026-07-15 | O7: 0000320187-26-000088 | P7: https://www.sec.gov/Archives/edgar/data/320187/000032018726000088/0000320187-26-000088-index.htm | Q7: 2026-07-16 | R7: Primary - SEC filing / Company Facts | S7: USD divided by 1,000,000; sign as presented | T7: Matched legal entity, period, form, filed date, accession and target | U7: None identified | V7: =IF(COUNTA(A7:U7)=21,"OK","MISSING") -> OK
A8: 4 | B8: NIKE, Inc. | C8: Historical!E5 | D8: Revenue | E8: 2025A | F8: 46309 | G8: USD millions | H8: USD | I8: us-gaap:RevenueFromContractWithCustomerExcludingAssessedTax | J8: 2024-06-01 | K8: 2025-05-31 | L8: 2026/FY | M8: 10-K | N8: 2026-07-15 | O8: 0000320187-26-000088 | P8: https://www.sec.gov/Archives/edgar/data/320187/000032018726000088/0000320187-26-000088-index.htm | Q8: 2026-07-16 | R8: Primary - SEC filing / Company Facts | S8: USD divided by 1,000,000; sign as presented | T8: Matched legal entity, period, form, filed date, accession and target | U8: None identified | V8: =IF(COUNTA(A8:U8)=21,"OK","MISSING") -> OK
A9: 5 | B9: NIKE, Inc. | C9: Historical!F5 | D9: Revenue | E9: 2026A | F9: 46398 | G9: USD millions | H9: USD | I9: us-gaap:RevenueFromContractWithCustomerExcludingAssessedTax | J9: 2025-06-01 | K9: 2026-05-31 | L9: 2026/FY | M9: 10-K | N9: 2026-07-15 | O9: 0000320187-26-000088 | P9: https://www.sec.gov/Archives/edgar/data/320187/000032018726000088/0000320187-26-000088-index.htm | Q9: 2026-07-16 | R9: Primary - SEC filing / Company Facts | S9: USD divided by 1,000,000; sign as presented | T9: Matched legal entity, period, form, filed date, accession and target | U9: None identified | V9: =IF(COUNTA(A9:U9)=21,"OK","MISSING") -> OK
A10: 6 | B10: NIKE, Inc. | C10: Historical!B6 | D10: Gross profit | E10: 2022A | F10: 21479 | G10: USD millions | H10: USD | I10: us-gaap:GrossProfit | J10: 2021-06-01 | K10: 2022-05-31 | L10: 2024/FY | M10: 10-K | N10: 2024-07-25 | O10: 0000320187-24-000044 | P10: https://www.sec.gov/Archives/edgar/data/320187/000032018724000044/0000320187-24-000044-index.htm | Q10: 2026-07-16 | R10: Primary - SEC filing / Company Facts | S10: USD divided by 1,000,000; sign as presented | T10: Matched legal entity, period, form, filed date, accession and target | U10: None identified | V10: =IF(COUNTA(A10:U10)=21,"OK","MISSING") -> OK
A11: 7 | B11: NIKE, Inc. | C11: Historical!C6 | D11: Gross profit | E11: 2023A | F11: 22292 | G11: USD millions | H11: USD | I11: us-gaap:GrossProfit | J11: 2022-06-01 | K11: 2023-05-31 | L11: 2025/FY | M11: 10-K | N11: 2025-07-17 | O11: 0000320187-25-000047 | P11: https://www.sec.gov/Archives/edgar/data/320187/000032018725000047/0000320187-25-000047-index.htm | Q11: 2026-07-16 | R11: Primary - SEC filing / Company Facts | S11: USD divided by 1,000,000; sign as presented | T11: Matched legal entity, period, form, filed date, accession and target | U11: None identified | V11: =IF(COUNTA(A11:U11)=21,"OK","MISSING") -> OK
A12: 8 | B12: NIKE, Inc. | C12: Historical!D6 | D12: Gross profit | E12: 2024A | F12: 22887 | G12: USD millions | H12: USD | I12: us-gaap:GrossProfit | J12: 2023-06-01 | K12: 2024-05-31 | L12: 2026/FY | M12: 10-K | N12: 2026-07-15 | O12: 0000320187-26-000088 | P12: https://www.sec.gov/Archives/edgar/data/320187/000032018726000088/0000320187-26-000088-index.htm | Q12: 2026-07-16 | R12: Primary - SEC filing / Company Facts | S12: USD divided by 1,000,000; sign as presented | T12: Matched legal entity, period, form, filed date, accession and target | U12: None identified | V12: =IF(COUNTA(A12:U12)=21,"OK","MISSING") -> OK
A13: 9 | B13: NIKE, Inc. | C13: Historical!E6 | D13: Gross profit | E13: 2025A | F13: 19790 | G13: USD millions | H13: USD | I13: us-gaap:GrossProfit | J13: 2024-06-01 | K13: 2025-05-31 | L13: 2026/FY | M13: 10-K | N13: 2026-07-15 | O13: 0000320187-26-000088 | P13: https://www.sec.gov/Archives/edgar/data/320187/000032018726000088/0000320187-26-000088-index.htm | Q13: 2026-07-16 | R13: Primary - SEC filing / Company Facts | S13: USD divided by 1,000,000; sign as presented | T13: Matched legal entity, period, form, filed date, accession and target | U13: None identified | V13: =IF(COUNTA(A13:U13)=21,"OK","MISSING") -> OK
A14: 10 | B14: NIKE, Inc. | C14: Historical!F6 | D14: Gross profit | E14: 2026A | F14: 19911 | G14: USD millions | H14: USD | I14: us-gaap:GrossProfit | J14: 2025-06-01 | K14: 2026-05-31 | L14: 2026/FY | M14: 10-K | N14: 2026-07-15 | O14: 0000320187-26-000088 | P14: https://www.sec.gov/Archives/edgar/data/320187/000032018726000088/0000320187-26-000088-index.htm | Q14: 2026-07-16 | R14: Primary - SEC filing / Company Facts | S14: USD divided by 1,000,000; sign as presented | T14: Matched legal entity, period, form, filed date, accession and target | U14: None identified | V14: =IF(COUNTA(A14:U14)=21,"OK","MISSING") -> OK
A15: 11 | B15: NIKE, Inc. | C15: Historical!D7 | D15: Operating income / EBIT | E15: 2024A | F15: 6539 | G15: USD millions | H15: USD | I15: 10-K table:Earnings before interest and taxes | J15: Annual period | K15: 2024-05-31 | L15: FY | M15: 10-K | N15: 2026-07-15 | O15: 0000320187-26-000088 | P15: https://www.sec.gov/Archives/edgar/data/320187/000032018726000088/nke-20260531.htm | Q15: 2026-07-16 | R15: Primary - SEC filing / Company Facts | S15: Reported USD millions; sign as presented | T15: Matched legal entity, period, form, filed date, accession and target | U15: Company-defined non-GAAP EBIT table; used only for operating trend | V15: =IF(COUNTA(A15:U15)=21,"OK","MISSING") -> OK
A16: 12 | B16: NIKE, Inc. | C16: Historical!E7 | D16: Operating income / EBIT | E16: 2025A | F16: 3778 | G16: USD millions | H16: USD | I16: 10-K table:Earnings before interest and taxes | J16: Annual period | K16: 2025-05-31 | L16: FY | M16: 10-K | N16: 2026-07-15 | O16: 0000320187-26-000088 | P16: https://www.sec.gov/Archives/edgar/data/320187/000032018726000088/nke-20260531.htm | Q16: 2026-07-16 | R16: Primary - SEC filing / Company Facts | S16: Reported USD millions; sign as presented | T16: Matched legal entity, period, form, filed date, accession and target | U16: Company-defined non-GAAP EBIT table; used only for operating trend | V16: =IF(COUNTA(A16:U16)=21,"OK","MISSING") -> OK
... A86: 82 | B86: NIKE, Inc. | C86: Valuation!G19 | D86: Market close | E86: 2026-07-15 | F86: 42.77 | G86: USD per share | H86: USD | I86: Secondary market:Historical daily close | J86: N/A - instant | K86: 2026-07-15 | L86: N/A | M86: Market data | N86: 2026-07-15 | O86: N/A - market data | P86: https://id.investing.com/equities/nike-historical-data | Q86: 2026-07-16 | R86: Secondary - dated market close | S86: Closing price as displayed; no FX | T86: Date and close matched on cited historical-price surface | U86: Secondary market source; refresh before transaction use | V86: =IF(COUNTA(A86:U86)=21,"OK","MISSING") -> OK
A88: Ledger completeness | G88: =COUNTIF(V5:V86,"OK") -> 82 | H88: 82 | I88: =IF(G88=H88,"OK","REVIEW") -> OK

Sheet Historical
A1: NIKE, Inc. — Historical Financials
A2: SEC 10-K / Company Facts lineage; USD millions except per-share data and shares
A4: Metric | B4: 2022A | C4: 2023A | D4: 2024A | E4: 2025A | F4: 2026A
A5: Revenue | B5: 46710 | C5: 51217 | D5: 51362 | E5: 46309 | F5: 46398
A6: Gross profit | B6: 21479 | C6: 22292 | D6: 22887 | E6: 19790 | F6: 19911
A7: Operating income / EBIT | D7: 6539 | E7: 3778 | F7: 3850
A8: Net income | B8: 6046 | C8: 5070 | D8: 5700 | E8: 3219 | F8: 3108
A9: Cash from operations | B9: 5188 | C9: 5841 | D9: 7429 | E9: 3698 | F9: 2868
A10: Capital expenditures | B10: 758 | C10: 969 | D10: 812 | E10: 430 | F10: 684
A11: Total assets | B11: 40321 | C11: 37531 | D11: 38110 | E11: 36579 | F11: 38410
A12: Shareholders' equity | B12: 15281 | C12: 14004 | D12: 14430 | E12: 13213 | F12: 14865
A13: Cash and equivalents | B13: 8574 | C13: 7441 | D13: 9860 | E13: 7464 | F13: 7563
A14: Total debt | B14: 9420 | C14: 8927 | D14: 8903 | E14: 7961 | F14: 7942
A15: Diluted weighted-average shares | B15: 1610.8 | C15: 1569.8 | D15: 1529.7 | E15: 1487.6 | F15: 1481
A17: Bridge policy | B17: Latest balance-sheet cash policy
A18: Liquid assets used in DCF | B18: =F13 -> 7563 | F18: USD millions
A19: Debt used in DCF | B19: =F14 -> 7942 | F19: USD millions
A20: Share count used in DCF | B20: 1481 | F20: million shares
A22: NIKE valuation bridge | B22: 2026A | C22: Policy | D22: USD m | E22: Source | F22: Status
A23: Cash and equivalents | B23: =F13 -> 7563 | C23: Included | D23: USD m | E23: Historical latest balance | F23: Formula link
A24: Total debt | B24: =F14 -> 7942 | C24: Included | D24: USD m | E24: Historical latest balance | F24: Formula link

Sheet Assumptions
A1: NIKE, Inc. — Scenario Assumptions
A2: Selector drives operating revenues/margins and the DCF; blue/amber cells are editable inputs
A3: Scenario selector (1 Base / 2 Bull / 3 Bear) | B3: 1 | G3: Input
A4: Active scenario | B4: =CHOOSE(B3,"Base","Bull","Bear") -> Base | G4: Formula
A6: Assumption | B6: Units | C6: Base | D6: Bull | E6: Bear | F6: Active | G6: Rationale / evidence
A7: Wholesale revenue growth | B7: % | C7: 0.04 | D7: 0.07 | E7: 0 | F7: =CHOOSE($B$3,C7,D7,E7) -> 0.04 | G7: 2026 wholesale revenue USD 28,058m
A8: Direct-to-consumer revenue growth | B8: % | C8: 0 | D8: 0.04 | E8: -0.04 | F8: =CHOOSE($B$3,C8,D8,E8) -> 0 | G8: 2026 NIKE Direct revenue USD 18,197m
A9: Other revenue growth | B9: % | C9: 0 | D9: 0.03 | E9: -0.05 | F9: =CHOOSE($B$3,C9,D9,E9) -> 0 | G9: 2026 other revenue USD 143m
A10: Gross margin | B10: % | C10: 0.46 | D10: 0.48 | E10: 0.43 | F10: =CHOOSE($B$3,C10,D10,E10) -> 0.46 | G10: Scenario gross margin
A11: SG&A as % revenue | B11: % | C11: 0.375 | D11: 0.36 | E11: 0.39 | F11: =CHOOSE($B$3,C11,D11,E11) -> 0.375 | G11: Scenario demand creation + overhead
A12: Cash tax rate | B12: % | C12: 0.205 | D12: 0.19 | E12: 0.22 | F12: =CHOOSE($B$3,C12,D12,E12) -> 0.205 | G12: Normalized cash tax rate
A13: D&A as % revenue | B13: % | C13: 0.018 | D13: 0.02 | E13: 0.016 | F13: =CHOOSE($B$3,C13,D13,E13) -> 0.018 | G13: Normalized D&A intensity
A14: Capex as % revenue | B14: % | C14: 0.015 | D14: 0.012 | E14: 0.02 | F14: =CHOOSE($B$3,C14,D14,E14) -> 0.015 | G14: Normalized capex intensity
A15: NWC investment / revenue growth | B15: % | C15: 0.015 | D15: 0.01 | E15: 0.02 | F15: =CHOOSE($B$3,C15,D15,E15) -> 0.015 | G15: FCFF working-capital policy
A16: WACC | B16: % | C16: 0.095 | D16: 0.085 | E16: 0.105 | F16: =CHOOSE($B$3,C16,D16,E16) -> 0.095 | G16: DCF discount-rate scenario
A17: Terminal growth | B17: % | C17: 0.025 | D17: 0.03 | E17: 0.02 | F17: =CHOOSE($B$3,C17,D17,E17) -> 0.025 | G17: DCF perpetual-growth scenario

Sheet Forecast
A1: NIKE, Inc. — Operating Forecast
A2: Scenario-linked driver build; USD millions except shares and per-share data
A4: Metric | B4: 2026A | C4: 2027E | D4: 2028E | E4: 2029E | F4: 2030E | G4: 2031E
A5: Wholesale revenue | B5: 28058 | C5: =B5*(1+Assumptions!F7) -> 29180.32 | D5: =C5*(1+Assumptions!F7) -> 30347.533 | E5: =D5*(1+Assumptions!F7) -> 31561.434 | F5: =E5*(1+Assumptions!F7) -> 32823.891 | G5: =F5*(1+Assumptions!F7) -> 34136.847
A6: Direct-to-consumer revenue | B6: 18197 | C6: =B6*(1+Assumptions!F8) -> 18197 | D6: =C6*(1+Assumptions!F8) -> 18197 | E6: =D6*(1+Assumptions!F8) -> 18197 | F6: =E6*(1+Assumptions!F8) -> 18197 | G6: =F6*(1+Assumptions!F8) -> 18197
A7: Other revenue | B7: 143 | C7: =B7*(1+Assumptions!F9) -> 143 | D7: =C7*(1+Assumptions!F9) -> 143 | E7: =D7*(1+Assumptions!F9) -> 143 | F7: =E7*(1+Assumptions!F9) -> 143 | G7: =F7*(1+Assumptions!F9) -> 143
A8: Total revenue | B8: =SUM(B5:B7) -> 46398 | C8: =SUM(C5:C7) -> 47520.32 | D8: =SUM(D5:D7) -> 48687.533 | E8: =SUM(E5:E7) -> 49901.434 | F8: =SUM(F5:F7) -> 51163.891 | G8: =SUM(G5:G7) -> 52476.847
A9: Gross profit | B9: 21344 | C9: =C8*Assumptions!F10 -> 21859.347 | D9: =D8*Assumptions!F10 -> 22396.265 | E9: =E8*Assumptions!F10 -> 22954.66 | F9: =F8*Assumptions!F10 -> 23535.39 | G9: =G8*Assumptions!F10 -> 24139.35
A10: SG&A | B10: -17494 | C10: =-C8*Assumptions!F11 -> -17820.12 | D10: =-D8*Assumptions!F11 -> -18257.825 | E10: =-E8*Assumptions!F11 -> -18713.038 | F10: =-F8*Assumptions!F11 -> -19186.459 | G10: =-G8*Assumptions!F11 -> -19678.818
A11: EBIT | B11: =SUM(B9:B10) -> 3850 | C11: =SUM(C9:C10) -> 4039.2272 | D11: =SUM(D9:D10) -> 4138.4403 | E11: =SUM(E9:E10) -> 4241.6219 | F11: =SUM(F9:F10) -> 4348.9308 | G11: =SUM(G9:G10) -> 4460.532
A12: Cash taxes | B12: =-B11*Assumptions!F12 -> -789.25 | C12: =-C11*Assumptions!F12 -> -828.04158 | D12: =-D11*Assumptions!F12 -> -848.38026 | E12: =-E11*Assumptions!F12 -> -869.53249 | F12: =-F11*Assumptions!F12 -> -891.53081 | G12: =-G11*Assumptions!F12 -> -914.40906
A13: NOPAT | B13: =SUM(B11:B12) -> 3060.75 | C13: =SUM(C11:C12) -> 3211.1856 | D13: =SUM(D11:D12) -> 3290.06 | E13: =SUM(E11:E12) -> 3372.0894 | F13: =SUM(F11:F12) -> 3457.4 | G13: =SUM(G11:G12) -> 3546.1229
A14: D&A | B14: 0 | C14: =C8*Assumptions!F13 -> 855.36576 | D14: =D8*Assumptions!F13 -> 876.37559 | E14: =E8*Assumptions!F13 -> 898.22581 | F14: =F8*Assumptions!F13 -> 920.95005 | G14: =G8*Assumptions!F13 -> 944.58325
A15: Capital expenditures | B15: 0 | C15: =-C8*Assumptions!F14 -> -712.8048 | D15: =-D8*Assumptions!F14 -> -730.31299 | E15: =-E8*Assumptions!F14 -> -748.52151 | F15: =-F8*Assumptions!F14 -> -767.45837 | G15: =-G8*Assumptions!F14 -> -787.15271
A16: Change in NWC | B16: 0 | C16: =-(C8-B8)*Assumptions!F15 -> -16.8348 | D16: =-(D8-C8)*Assumptions!F15 -> -17.508192 | E16: =-(E8-D8)*Assumptions!F15 -> -18.20852 | F16: =-(F8-E8)*Assumptions!F15 -> -18.93686 | G16: =-(G8-F8)*Assumptions!F15 -> -19.694335
A17: FCFF | B17: 0 | C17: =SUM(C13:C16) -> 3336.9118 | D17: =SUM(D13:D16) -> 3418.6144 | E17: =SUM(E13:E16) -> 3503.5852 | F17: =SUM(F13:F16) -> 3591.9548 | G17: =SUM(G13:G16) -> 3683.8592

Sheet Valuation
A1: NIKE, Inc. — DCF Valuation
A2: Unlevered FCFF; liquid-asset and debt bridge policies are explicit
A4: DCF item | B4: Year 1 | C4: Year 2 | D4: Year 3 | E4: Year 4 | F4: Year 5 | G4: Bridge / output
A5: FCFF | B5: =Forecast!C17 -> 3336.9118 | C5: =Forecast!D17 -> 3418.6144 | D5: =Forecast!E17 -> 3503.5852 | E5: =Forecast!F17 -> 3591.9548 | F5: =Forecast!G17 -> 3683.8592
A6: Discount period | B6: 1 | C6: 2 | D6: 3 | E6: 4 | F6: 5
A7: Discount factor | B7: =1/(1+Assumptions!F16)^B6 -> 0.91324201 | C7: =1/(1+Assumptions!F16)^C6 -> 0.83401097 | D7: =1/(1+Assumptions!F16)^D6 -> 0.76165385 | E7: =1/(1+Assumptions!F16)^E6 -> 0.69557429 | F7: =1/(1+Assumptions!F16)^F6 -> 0.63522767
A8: Present value of FCFF | B8: =B5*B7 -> 3047.408 | C8: =C5*C7 -> 2851.1619 | D8: =D5*D7 -> 2668.5192 | E8: =E5*E7 -> 2498.4714 | F8: =F5*F7 -> 2340.0892
A9: Terminal value | F9: =F5*(1+Assumptions!F17)/(Assumptions!F16-Assumptions!F17) -> 53942.223
A10: PV of terminal value | F10: =F9*F7 -> 34265.593
A11: Enterprise value | G11: =SUM(B8:F8)+F10 -> 47671.242
A12: Liquid assets | G12: =Historical!B18 -> 7563
A13: Debt | G13: =Historical!B19 -> 7942
A14: Equity value | G14: =G11+G12-G13 -> 47292.242
A15: Shares outstanding / diluted policy | G15: =Historical!B20 -> 1481
A17: Per-share outputs
A18: DCF value / share | G18: =G14/G15 -> 31.932642
A19: Market price | G19: 42.77
A20: Upside / (downside) | G20: =G18/G19-1 -> -0.25338691
A21: Market as-of | G21: 2026-07-15

Sheet Sensitivity
A1: NIKE, Inc. — DCF Sensitivity
A2: Implied value per share across WACC and terminal-growth assumptions
A4: WACC / TGR | B4: 0.015 | C4: 0.02 | D4: 0.025 | E4: 0.03 | F4: 0.035
A5: 0.08 | B5: =(SUM(Valuation!B8:F8)+Forecast!G17*(1+B$4)/($A5-B$4)*Valuation!F7+Valuation!G12-Valuation!G13)/Valuation!G15 -> 33.469307 | C5: =(SUM(Valuation!B8:F8)+Forecast!G17*(1+C$4)/($A5-C$4)*Valuation!F7+Valuation!G12-Valuation!G13)/Valuation!G15 -> 35.657101 | D5: =(SUM(Valuation!B8:F8)+Forecast!G17*(1+D$4)/($A5-D$4)*Valuation!F7+Valuation!G12-Valuation!G13)/Valuation!G15 -> 38.242677 | E5: =(SUM(Valuation!B8:F8)+Forecast!G17*(1+E$4)/($A5-E$4)*Valuation!F7+Valuation!G12-Valuation!G13)/Valuation!G15 -> 41.345367 | F5: =(SUM(Valuation!B8:F8)+Forecast!G17*(1+F$4)/($A5-F$4)*Valuation!F7+Valuation!G12-Valuation!G13)/Valuation!G15 -> 45.137544
A6: 0.0875 | B6: =(SUM(Valuation!B8:F8)+Forecast!G17*(1+B$4)/($A6-B$4)*Valuation!F7+Valuation!G12-Valuation!G13)/Valuation!G15 -> 30.91688 | C6: =(SUM(Valuation!B8:F8)+Forecast!G17*(1+C$4)/($A6-C$4)*Valuation!F7+Valuation!G12-Valuation!G13)/Valuation!G15 -> 32.672517 | D6: =(SUM(Valuation!B8:F8)+Forecast!G17*(1+D$4)/($A6-D$4)*Valuation!F7+Valuation!G12-Valuation!G13)/Valuation!G15 -> 34.709057 | E6: =(SUM(Valuation!B8:F8)+Forecast!G17*(1+E$4)/($A6-E$4)*Valuation!F7+Valuation!G12-Valuation!G13)/Valuation!G15 -> 37.099777 | F6: =(SUM(Valuation!B8:F8)+Forecast!G17*(1+F$4)/($A6-F$4)*Valuation!F7+Valuation!G12-Valuation!G13)/Valuation!G15 -> 39.945873
A7: 0.095 | B7: =(SUM(Valuation!B8:F8)+Forecast!G17*(1+B$4)/($A7-B$4)*Valuation!F7+Valuation!G12-Valuation!G13)/Valuation!G15 -> 28.843033 | C7: =(SUM(Valuation!B8:F8)+Forecast!G17*(1+C$4)/($A7-C$4)*Valuation!F7+Valuation!G12-Valuation!G13)/Valuation!G15 -> 30.28485 | D7: =(SUM(Valuation!B8:F8)+Forecast!G17*(1+D$4)/($A7-D$4)*Valuation!F7+Valuation!G12-Valuation!G13)/Valuation!G15 -> 31.932642 | E7: =(SUM(Valuation!B8:F8)+Forecast!G17*(1+E$4)/($A7-E$4)*Valuation!F7+Valuation!G12-Valuation!G13)/Valuation!G15 -> 33.833939 | F7: =(SUM(Valuation!B8:F8)+Forecast!G17*(1+F$4)/($A7-F$4)*Valuation!F7+Valuation!G12-Valuation!G13)/Valuation!G15 -> 36.05212
A8: 0.1025 | B8: =(SUM(Valuation!B8:F8)+Forecast!G17*(1+B$4)/($A8-B$4)*Valuation!F7+Valuation!G12-Valuation!G13)/Valuation!G15 -> 27.124703 | C8: =(SUM(Valuation!B8:F8)+Forecast!G17*(1+C$4)/($A8-C$4)*Valuation!F7+Valuation!G12-Valuation!G13)/Valuation!G15 -> 28.331305 | D8: =(SUM(Valuation!B8:F8)+Forecast!G17*(1+D$4)/($A8-D$4)*Valuation!F7+Valuation!G12-Valuation!G13)/Valuation!G15 -> 29.693597 | E8: =(SUM(Valuation!B8:F8)+Forecast!G17*(1+E$4)/($A8-E$4)*Valuation!F7+Valuation!G12-Valuation!G13)/Valuation!G15 -> 31.243792 | F8: =(SUM(Valuation!B8:F8)+Forecast!G17*(1+F$4)/($A8-F$4)*Valuation!F7+Valuation!G12-Valuation!G13)/Valuation!G15 -> 33.023645
A9: 0.11 | B9: =(SUM(Valuation!B8:F8)+Forecast!G17*(1+B$4)/($A9-B$4)*Valuation!F7+Valuation!G12-Valuation!G13)/Valuation!G15 -> 25.677688 | C9: =(SUM(Valuation!B8:F8)+Forecast!G17*(1+C$4)/($A9-C$4)*Valuation!F7+Valuation!G12-Valuation!G13)/Valuation!G15 -> 26.70335 | D9: =(SUM(Valuation!B8:F8)+Forecast!G17*(1+D$4)/($A9-D$4)*Valuation!F7+Valuation!G12-Valuation!G13)/Valuation!G15 -> 27.849678 | E9: =(SUM(Valuation!B8:F8)+Forecast!G17*(1+E$4)/($A9-E$4)*Valuation!F7+Valuation!G12-Valuation!G13)/Valuation!G15 -> 29.139297 | F9: =(SUM(Valuation!B8:F8)+Forecast!G17*(1+F$4)/($A9-F$4)*Valuation!F7+Valuation!G12-Valuation!G13)/Valuation!G15 -> 30.600865
B11: Central cross-check
B12: Active WACC | C12: =Assumptions!F16 -> 0.095
B13: Active TGR | C13: =Assumptions!F17 -> 0.025
B14: Active DCF value/share | C14: =Valuation!G18 -> 31.932642

Sheet Checks
A1: NIKE, Inc. — Model Checks
A2: Overall status is formula-driven from assertions; source completeness is linked to the provenance ledger
A4: Assertion | B4: Actual | C4: Expected | D4: Difference | E4: Tolerance | F4: Status | G4: Fix hint
A5: Source ledger complete | B5: =Sources!I88 -> OK | C5: OK | F5: =IF(B5=C5,"OK","REVIEW") -> OK | G5: Complete every mandatory provenance field
A6: Scenario selector valid | B6: =Assumptions!B3 -> 1 | C6: 1 | D6: =IF(AND(B6>=1,B6<=3),0,1) -> 0 | E6: 0 | F6: =IF(D6=E6,"OK","REVIEW") -> OK | G6: Set Assumptions!B3 to 1, 2 or 3
A7: Forecast revenue positive | B7: =Forecast!C8 -> 47520.32 | C7: 0 | D7: =IF(B7>0,0,1) -> 0 | E7: 0 | F7: =IF(D7=E7,"OK","REVIEW") -> OK | G7: Inspect revenue-driver formulas
A8: Five EBIT periods populated | B8: =COUNT(Forecast!C11:G11) -> 5 | C8: 5 | D8: =ABS(B8-C8) -> 0 | E8: 0 | F8: =IF(D8=E8,"OK","REVIEW") -> OK | G8: Inspect margin and opex build
A9: Five FCFF periods populated | B9: =COUNT(Forecast!C17:G17) -> 5 | C9: 5 | D9: =ABS(B9-C9) -> 0 | E9: 0 | F9: =IF(D9=E9,"OK","REVIEW") -> OK | G9: Inspect NOPAT, D&A, capex and NWC
A10: Latest historical capex source present | B10: =COUNT(Historical!F10) -> 1 | C10: 1 | D10: =ABS(B10-C10) -> 0 | E10: 0.1 | F10: =IF(D10<=E10,"OK","REVIEW") -> OK | G10: Historical inputs are positive as reported; forecast expense/capex anchors are negative model outflows
A11: DCF equity bridge | B11: =Valuation!G14 -> 47292.242 | C11: =Valuation!G11+Valuation!G12-Valuation!G13 -> 47292.242 | D11: =ABS(B11-C11) -> 0 | E11: 0.1 | F11: =IF(D11<=E11,"OK","REVIEW") -> OK | G11: Inspect EV, liquid assets and total debt
A12: DCF per-share identity | B12: =Valuation!G18 -> 31.932642 | C12: =Valuation!G14/Valuation!G15 -> 31.932642 | D12: =ABS(B12-C12) -> 0 | E12: 0.001 | F12: =IF(D12<=E12,"OK","REVIEW") -> OK | G12: Inspect shares bridge
A13: Market price positive and sourced | B13: =Valuation!G19 -> 42.77 | C13: 0 | D13: =IF(B13>0,0,1) -> 0 | E13: 0 | F13: =IF(D13=E13,"OK","REVIEW") -> OK | G13: Update the dated market source row in Sources
A15: Overall status | F15: =IF(COUNTIF(F5:F13,"OK")=9,"OK","REVIEW") -> OK

Sheet Sector_KPIs
A1: NIKE, Inc. — Company Operating Drivers
A2: Company-specific reported driver history; formulas reconcile the model totals to historical revenue where applicable
A4: Metric | B4: 2024A | C4: 2025A | D4: 2026A | E4: Units | F4: Source / locator | G4: Status
A5: Footwear revenue | B5: 35227 | C5: 30967 | D5: 30538 | E5: USD m | F5: 2026 Form 10-K product table | G5: Reported
A6: Apparel revenue | B6: 13868 | C6: 13045 | D6: 13497 | E6: USD m | F6: 2026 Form 10-K product table | G6: Reported
A7: Equipment revenue | B7: 2112 | C7: 2223 | D7: 2220 | E7: USD m | F7: 2026 Form 10-K product table | G7: Reported
A8: Other revenue | B8: 155 | C8: 74 | D8: 143 | E8: USD m | F8: 2026 Form 10-K product table | G8: Reported
A9: Product revenue total | B9: =SUM(B5:B8) -> 51362 | C9: =SUM(C5:C8) -> 46309 | D9: =SUM(D5:D8) -> 46398 | E9: USD m | F9: Sum of product categories | G9: Formula
A10: Wholesale revenue | B10: 28856 | C10: 26758 | D10: 28058 | E10: USD m | F10: 2026 Form 10-K channel table | G10: Reported
A11: Direct-to-consumer revenue | B11: 22351 | C11: 19477 | D11: 18197 | E11: USD m | F11: 2026 Form 10-K channel table | G11: Reported
A12: Other revenue | B12: 155 | C12: 74 | D12: 143 | E12: USD m | F12: 2026 Form 10-K channel table | G12: Reported
A13: Channel revenue total | B13: =SUM(B10:B12) -> 51362 | C13: =SUM(C10:C12) -> 46309 | D13: =SUM(D10:D12) -> 46398 | E13: USD m | F13: Sum of channels | G13: Formula
A14: EBIT | B14: 6539 | C14: 3778 | D14: 3850 | E14: USD m | F14: 2026 Form 10-K company-defined EBIT table | G14: Reported
A15: EBIT margin | B15: 0.127 | C15: 0.082 | D15: 0.083 | E15: % | F15: 2026 Form 10-K company-defined EBIT table | G15: Reported

Sheet Change_Log
A1: NIKE, Inc. — Change Log
A2: Re-gating work performed without overwriting the prior workbook
A4: Timestamp (UTC) | B4: Scope | C4: Change | D4: Evidence | E4: Prior hash | F4: Preparer | G4: Disposition
A5: Build 2026-07-17T02:33:12.208Z | B5: Source lineage | C5: Added line-item target-cell provenance ledger | D5: Sources + SEC Company Facts / 10-K | E5: 0c9c89d705b6fdef1190b06fec9206ce02ba146dafed6d149c27655e9bc4cd8e | F5: Codex | G5: Ready for independent review
A6: Build 2026-07-17T02:33:12.208Z | B6: Operating model | C6: Added company-specific revenue and margin drivers | D6: Sector_KPIs, Assumptions, Forecast | E6: 0c9c89d705b6fdef1190b06fec9206ce02ba146dafed6d149c27655e9bc4cd8e | F6: Codex | G6: Ready for independent review
A7: Build 2026-07-17T02:33:12.208Z | B7: Valuation | C7: Rebuilt FCFF DCF, bridge and sensitivity | D7: Valuation + Sensitivity | E7: 0c9c89d705b6fdef1190b06fec9206ce02ba146dafed6d149c27655e9bc4cd8e | F7: Codex | G7: Ready for independent review
A8: Build 2026-07-17T02:33:12.208Z | B8: Governance | C8: Added formula-driven checks and Gate_9of10 | D8: Checks + Gate_9of10 | E8: 0c9c89d705b6fdef1190b06fec9206ce02ba146dafed6d149c27655e9bc4cd8e | F8: Codex | G8: Owner submission only

Sheet Gate_9of10
A1: NIKE, Inc. — Gate 9/10 Owner Submission
A2: Independent review is a separate role; this sheet does not self-certify the workbook
A4: Gate | B4: Weight | C4: Owner status | D4: Blocker class | E4: Exact evidence range | F4: Native / visual evidence | G4: Independent action | H4: Notes
A5: H0 Controlled lineage / package | B5: 5 | C5: PASS | D5: None identified | E5: Change_Log!A4:G8; final .xlsx | F5: Prior hash preserved; OOXML integrity PASS 2026-07-17T02:36:50.245Z | G5: Reproduce lineage and package test | H5: Final JSON carries prior and final hashes
A6: H1 Source fidelity | B6: 20 | C6: PASS | D6: None identified | E6: Sources!A4:V500 | F6: SEC target-cell ledger + formula completeness | G6: Sample and reproduce ledger mappings | H6: Every populated hardcoded historical/driver cell mapped
A7: H2 Historical / formula / schedule mechanics | B7: 15 | C7: PASS | D7: None identified | E7: Historical!A4:F26; Forecast!A4:G30 | F7: Five-year historicals and formula-driven operating build | G7: Reperform historical and forecast ties | H7: Reported values preserved; forecast cells formula-driven
A8: H3 Scenario / sensitivity | B8: 10 | C8: PASS | D8: None identified | E8: Assumptions!A3:G30; Sensitivity!A4:G14 | F8: Base/Bull/Bear selector + dynamic DCF sensitivity | G8: Perturb selector 1/2/3 and reset to 1 | H8: Evidence JSON records exact outputs
A9: H4 Valuation fit / mechanics | B9: 15 | C9: PASS | D9: None identified | E9: Valuation!A4:G21; Historical!A17:F26 | F9: FCFF, bridge and per-share DCF | G9: Reperform DCF and balance-sheet bridge | H9: Debt/liquid asset/share policies explicit
A10: H5 Checks / error state | B10: 8 | C10: PASS | D10: None identified | E10: Checks!A4:G14 | F10: Formula-driven checks OK and zero formula-error matches 2026-07-17T02:33:57.150Z | G10: Reproduce checks and formula-error scan | H10: Final scan repeated after gate promotion
A11: H6 Native recalc / reproducibility | B11: 10 | C11: PASS | D11: None identified | E11: Checks!A4:G14 | F11: LibreOfficeDev 26.8.0.0.alpha0 2c87e51eeaa2b413ff4ae097b2705eea1995d8e5; save/reopen completed 2026-07-17T02:33:57.150Z | G11: Reopen and reproduce in native engine | H11: Final recalc repeated after gate promotion; evidence JSON carries hashes
A12: H7 Post-recalc all-sheet visual QA | B12: 7 | C12: PASS | D12: None identified | E12: internal QA evidence (not published) | F12: All 11 sheets rendered in preflight 2026-07-17T02:33:57.150Z; final render repeated after promotion | G12: Inspect preview manifest | H12: Final JSON carries per-sheet manifest
A13: H8 Material economic upgrade | B13: 5 | C13: PASS | D13: None identified | E13: Sector_KPIs!A4:G40; Assumptions!A6:G30; Forecast!A4:G30 | F13: Company-specific driver and margin build | G13: Challenge economic usefulness | H13: No relabel-only sector shell
A14: H9 Governance / limitations / handoff | B14: 5 | C14: PASS | D14: None identified | E14: Change_Log!A4:G8; Gate_9of10!A4:H26 | F14: Owner/reviewer separation and limitations explicit | G14: Assign independent reviewer | H14: No self-certification; evidence JSON is handoff surface
A16: Owner score | B16: =SUMIF(C5:C14,"PASS",B5:B14) -> 100
A17: Decision | B17: =IF(B16=100,"OWNER READY — INDEPENDENT REVIEW REQUIRED","PENDING OWNER QA") -> OWNER READY — INDEPENDENT REVIEW REQUIRED
A18: Overall model status | B18: =Checks!F15 -> OK
A20: Native recalculation / review metadata
A21: Build timestamp UTC | B21: Build 2026-07-17T02:33:12.208Z
A22: Required native engine | B22: LibreOfficeDev 26.8.0.0.alpha0 2c87e51eeaa2b413ff4ae097b2705eea1995d8e5
A23: Final native timestamp | B23: Native preflight 2026-07-17T02:33:57.150Z; final recalc after promotion 2026-07-17T02:36:52.714Z
A24: Visual manifest | B24: internal QA evidence (not published)
A25: Evidence manifest | B25: internal QA evidence (not published)
A26: Independent certification | B26: Not performed by owner-preparer

Sheet Claude Code Log
A1: Turn # | B1: Date | C1: User Request | D1: Action Taken | E1: Details | F1: Outcome
A2: 1 | B2: 46324.359 | C2: Prepare a public model copy | D2: Remove local paths and private build references; preserve financial formulas and inputs | E2: Agent run with MOG as the tool, checked by guard v1. The guard measured every sheet before and after the run. Changed: Gate_9of10: 3 cells written, at E12, B24, B25. Agent: OpenFinmods export | F2: Compare against source and review public copy
