Workbook

Sheet 00_Cover
A1: Grupo Cibest / Bancolombia — Controlled Bank Model | B1: Grupo Cibest / Bancolombia — Controlled Bank Model | C1: Grupo Cibest / Bancolombia — Controlled Bank Model | D1: Grupo Cibest / Bancolombia — Controlled Bank Model | E1: Grupo Cibest / Bancolombia — Controlled Bank Model | F1: Grupo Cibest / Bancolombia — Controlled Bank Model | G1: Grupo Cibest / Bancolombia — Controlled Bank Model | H1: Grupo Cibest / Bancolombia — Controlled Bank Model
A2: COP billions unless stated | 2025A base | 2026E–2030E forecast | Controlled 9/10 re-gate | B2: COP billions unless stated | 2025A base | 2026E–2030E forecast | Controlled 9/10 re-gate | C2: COP billions unless stated | 2025A base | 2026E–2030E forecast | Controlled 9/10 re-gate | D2: COP billions unless stated | 2025A base | 2026E–2030E forecast | Controlled 9/10 re-gate | E2: COP billions unless stated | 2025A base | 2026E–2030E forecast | Controlled 9/10 re-gate | F2: COP billions unless stated | 2025A base | 2026E–2030E forecast | Controlled 9/10 re-gate | G2: COP billions unless stated | 2025A base | 2026E–2030E forecast | Controlled 9/10 re-gate | H2: COP billions unless stated | 2025A base | 2026E–2030E forecast | Controlled 9/10 re-gate
A4: Model field | B4: Value
A5: Legal entity / perimeter | B5: Grupo Cibest S.A. consolidated; Bancolombia predecessor periods are not silently stitched
A6: Ticker / CIK | B6: CIB | current CIK 0002058897 | predecessor CIK 0001071371
A7: Archetype | B7: Bank / financial holding company; loan, funding, credit, capital and payout schedules
A8: Valuation | B8: Residual income primary; dividend discount cross-check; deposits are operating funding, not debt
A9: Currency / units | B9: COP billions; no current-FX restatement of historical periods
A10: Historical perimeter | B10: 2024A and 2025A shown on 4Q25 pro-forma including Banistmo basis for comparability
A11: Forecast horizon | B11: 2026E–2030E
A12: Active scenario | B12: =Assumptions!E3 -> Base
A13: Model status | B13: =Checks!B15 -> PASS
A14: Valuation as-of | B14: 2025-12-31; intrinsic value only, no unsourced market price
A15: Primary filing | B15: Grupo Cibest 2025 Form 20-F, accession 0002058897-26-000125
A16: Operating evidence | B16: Grupo Cibest 4Q25 Form 6-K, accession 0002058897-26-000013
A17: Main limitation | B17: Banistmo sale/perimeter transition and adjusted 2025 earnings require explicit pro-forma treatment
A18: Independent certification | B18: Pending independent-gate reproduction; owner evidence is not self-certification
A19: Controlled output | B19: Bancolombia_9of10_Regated.xlsx
A20: Original preserved | B20: Bancolombia_Institutional_Model.xlsx
A22: Use this controlled workbook only after the Checks sheet reads PASS. Historical values are hardcoded sourced facts. Blue-font cells are editable assumptions. Green-font formulas link across sheets. The active scenario must be returned to Base after testing. | B22: Use this controlled workbook only after the Checks sheet reads PASS. Historical values are hardcoded sourced facts. Blue-font cells are editable assumptions. Green-font formulas link across sheets. The active scenario must be returned to Base after testing. | C22: Use this controlled workbook only after the Checks sheet reads PASS. Historical values are hardcoded sourced facts. Blue-font cells are editable assumptions. Green-font formulas link across sheets. The active scenario must be returned to Base after testing. | D22: Use this controlled workbook only after the Checks sheet reads PASS. Historical values are hardcoded sourced facts. Blue-font cells are editable assumptions. Green-font formulas link across sheets. The active scenario must be returned to Base after testing. | E22: Use this controlled workbook only after the Checks sheet reads PASS. Historical values are hardcoded sourced facts. Blue-font cells are editable assumptions. Green-font formulas link across sheets. The active scenario must be returned to Base after testing. | F22: Use this controlled workbook only after the Checks sheet reads PASS. Historical values are hardcoded sourced facts. Blue-font cells are editable assumptions. Green-font formulas link across sheets. The active scenario must be returned to Base after testing. | G22: Use this controlled workbook only after the Checks sheet reads PASS. Historical values are hardcoded sourced facts. Blue-font cells are editable assumptions. Green-font formulas link across sheets. The active scenario must be returned to Base after testing. | H22: Use this controlled workbook only after the Checks sheet reads PASS. Historical values are hardcoded sourced facts. Blue-font cells are editable assumptions. Green-font formulas link across sheets. The active scenario must be returned to Base after testing.
A23: Use this controlled workbook only after the Checks sheet reads PASS. Historical values are hardcoded sourced facts. Blue-font cells are editable assumptions. Green-font formulas link across sheets. The active scenario must be returned to Base after testing. | B23: Use this controlled workbook only after the Checks sheet reads PASS. Historical values are hardcoded sourced facts. Blue-font cells are editable assumptions. Green-font formulas link across sheets. The active scenario must be returned to Base after testing. | C23: Use this controlled workbook only after the Checks sheet reads PASS. Historical values are hardcoded sourced facts. Blue-font cells are editable assumptions. Green-font formulas link across sheets. The active scenario must be returned to Base after testing. | D23: Use this controlled workbook only after the Checks sheet reads PASS. Historical values are hardcoded sourced facts. Blue-font cells are editable assumptions. Green-font formulas link across sheets. The active scenario must be returned to Base after testing. | E23: Use this controlled workbook only after the Checks sheet reads PASS. Historical values are hardcoded sourced facts. Blue-font cells are editable assumptions. Green-font formulas link across sheets. The active scenario must be returned to Base after testing. | F23: Use this controlled workbook only after the Checks sheet reads PASS. Historical values are hardcoded sourced facts. Blue-font cells are editable assumptions. Green-font formulas link across sheets. The active scenario must be returned to Base after testing. | G23: Use this controlled workbook only after the Checks sheet reads PASS. Historical values are hardcoded sourced facts. Blue-font cells are editable assumptions. Green-font formulas link across sheets. The active scenario must be returned to Base after testing. | H23: Use this controlled workbook only after the Checks sheet reads PASS. Historical values are hardcoded sourced facts. Blue-font cells are editable assumptions. Green-font formulas link across sheets. The active scenario must be returned to Base after testing.
A24: Use this controlled workbook only after the Checks sheet reads PASS. Historical values are hardcoded sourced facts. Blue-font cells are editable assumptions. Green-font formulas link across sheets. The active scenario must be returned to Base after testing. | B24: Use this controlled workbook only after the Checks sheet reads PASS. Historical values are hardcoded sourced facts. Blue-font cells are editable assumptions. Green-font formulas link across sheets. The active scenario must be returned to Base after testing. | C24: Use this controlled workbook only after the Checks sheet reads PASS. Historical values are hardcoded sourced facts. Blue-font cells are editable assumptions. Green-font formulas link across sheets. The active scenario must be returned to Base after testing. | D24: Use this controlled workbook only after the Checks sheet reads PASS. Historical values are hardcoded sourced facts. Blue-font cells are editable assumptions. Green-font formulas link across sheets. The active scenario must be returned to Base after testing. | E24: Use this controlled workbook only after the Checks sheet reads PASS. Historical values are hardcoded sourced facts. Blue-font cells are editable assumptions. Green-font formulas link across sheets. The active scenario must be returned to Base after testing. | F24: Use this controlled workbook only after the Checks sheet reads PASS. Historical values are hardcoded sourced facts. Blue-font cells are editable assumptions. Green-font formulas link across sheets. The active scenario must be returned to Base after testing. | G24: Use this controlled workbook only after the Checks sheet reads PASS. Historical values are hardcoded sourced facts. Blue-font cells are editable assumptions. Green-font formulas link across sheets. The active scenario must be returned to Base after testing. | H24: Use this controlled workbook only after the Checks sheet reads PASS. Historical values are hardcoded sourced facts. Blue-font cells are editable assumptions. Green-font formulas link across sheets. The active scenario must be returned to Base after testing.
A25: Use this controlled workbook only after the Checks sheet reads PASS. Historical values are hardcoded sourced facts. Blue-font cells are editable assumptions. Green-font formulas link across sheets. The active scenario must be returned to Base after testing. | B25: Use this controlled workbook only after the Checks sheet reads PASS. Historical values are hardcoded sourced facts. Blue-font cells are editable assumptions. Green-font formulas link across sheets. The active scenario must be returned to Base after testing. | C25: Use this controlled workbook only after the Checks sheet reads PASS. Historical values are hardcoded sourced facts. Blue-font cells are editable assumptions. Green-font formulas link across sheets. The active scenario must be returned to Base after testing. | D25: Use this controlled workbook only after the Checks sheet reads PASS. Historical values are hardcoded sourced facts. Blue-font cells are editable assumptions. Green-font formulas link across sheets. The active scenario must be returned to Base after testing. | E25: Use this controlled workbook only after the Checks sheet reads PASS. Historical values are hardcoded sourced facts. Blue-font cells are editable assumptions. Green-font formulas link across sheets. The active scenario must be returned to Base after testing. | F25: Use this controlled workbook only after the Checks sheet reads PASS. Historical values are hardcoded sourced facts. Blue-font cells are editable assumptions. Green-font formulas link across sheets. The active scenario must be returned to Base after testing. | G25: Use this controlled workbook only after the Checks sheet reads PASS. Historical values are hardcoded sourced facts. Blue-font cells are editable assumptions. Green-font formulas link across sheets. The active scenario must be returned to Base after testing. | H25: Use this controlled workbook only after the Checks sheet reads PASS. Historical values are hardcoded sourced facts. Blue-font cells are editable assumptions. Green-font formulas link across sheets. The active scenario must be returned to Base after testing.

Sheet Sources
A1: Claim-level source ledger | B1: Claim-level source ledger | C1: Claim-level source ledger | D1: Claim-level source ledger | E1: Claim-level source ledger | F1: Claim-level source ledger | G1: Claim-level source ledger | H1: Claim-level source ledger | I1: Claim-level source ledger | J1: Claim-level source ledger | K1: Claim-level source ledger | L1: Claim-level source ledger | M1: Claim-level source ledger | N1: Claim-level source ledger | O1: Claim-level source ledger | P1: Claim-level source ledger
A2: Each material historical input maps metric, value, period, unit, exact filing, accession, target cell and transformation. | B2: Each material historical input maps metric, value, period, unit, exact filing, accession, target cell and transformation. | C2: Each material historical input maps metric, value, period, unit, exact filing, accession, target cell and transformation. | D2: Each material historical input maps metric, value, period, unit, exact filing, accession, target cell and transformation. | E2: Each material historical input maps metric, value, period, unit, exact filing, accession, target cell and transformation. | F2: Each material historical input maps metric, value, period, unit, exact filing, accession, target cell and transformation. | G2: Each material historical input maps metric, value, period, unit, exact filing, accession, target cell and transformation. | H2: Each material historical input maps metric, value, period, unit, exact filing, accession, target cell and transformation. | I2: Each material historical input maps metric, value, period, unit, exact filing, accession, target cell and transformation. | J2: Each material historical input maps metric, value, period, unit, exact filing, accession, target cell and transformation. | K2: Each material historical input maps metric, value, period, unit, exact filing, accession, target cell and transformation. | L2: Each material historical input maps metric, value, period, unit, exact filing, accession, target cell and transformation. | M2: Each material historical input maps metric, value, period, unit, exact filing, accession, target cell and transformation. | N2: Each material historical input maps metric, value, period, unit, exact filing, accession, target cell and transformation. | O2: Each material historical input maps metric, value, period, unit, exact filing, accession, target cell and transformation. | P2: Each material historical input maps metric, value, period, unit, exact filing, accession, target cell and transformation.
A4: Source ID | B4: Legal entity | C4: Metric | D4: Reported value | E4: Unit | F4: Period | G4: Basis | H4: Taxonomy / exact locator | I4: Form | J4: Filed / published | K4: Accession | L4: Exact official URL | M4: Workbook target | N4: Scale / FX / sign / perimeter transformation | O4: Class | P4: Status
A5: BC24-ASSETS | B5: Grupo Cibest / Bancolombia predecessor | C5: Total assets | D5: 372215.38 | E5: COP bn | F5: 2024-12-31 | G5: 4Q25 pro-forma incl. Banistmo | H5: 4Q25 6-K consolidated statement; ifrs-full:Assets | I5: 6-K | J5: 2026-02-23 | K5: 0002058897-26-000013 | L5: https://www.sec.gov/Archives/edgar/data/2058897/000205889726000013/grupocibestsa6-kpr4q25.htm | M5: Historical!B5 | N5: COP million / 1,000; no FX; comparative pro-forma perimeter | O5: Primary filing | P5: =IF(AND(C5<>"",D5<>"",E5<>"",F5<>"",H5<>"",I5<>"",J5<>"",K5<>"",L5<>"",M5<>"",N5<>"",O5<>""),"PASS","FAIL") -> PASS
A6: BC25-ASSETS | B6: Grupo Cibest S.A. | C6: Total assets | D6: 384657.72 | E6: COP bn | F6: 2025-12-31 | G6: 4Q25 pro-forma incl. Banistmo | H6: 4Q25 6-K consolidated statement; ifrs-full:Assets | I6: 6-K | J6: 2026-02-23 | K6: 0002058897-26-000013 | L6: https://www.sec.gov/Archives/edgar/data/2058897/000205889726000013/grupocibestsa6-kpr4q25.htm | M6: Historical!C5 | N6: COP million / 1,000; no FX; pro-forma incl. Banistmo | O6: Primary filing | P6: =IF(AND(C6<>"",D6<>"",E6<>"",F6<>"",H6<>"",I6<>"",J6<>"",K6<>"",L6<>"",M6<>"",N6<>"",O6<>""),"PASS","FAIL") -> PASS
A7: BC24-LOANS | B7: Grupo Cibest / Bancolombia predecessor | C7: Gross loans | D7: 279453.91 | E7: COP bn | F7: 2024-12-31 | G7: 4Q25 pro-forma incl. Banistmo | H7: 4Q25 6-K loan portfolio table; ifrs-full:LoansAndAdvancesToCustomers | I7: 6-K | J7: 2026-02-23 | K7: 0002058897-26-000013 | L7: https://www.sec.gov/Archives/edgar/data/2058897/000205889726000013/grupocibestsa6-kpr4q25.htm | M7: Historical!B6 | N7: COP million / 1,000; gross; no FX; comparative pro-forma perimeter | O7: Primary filing | P7: =IF(AND(C7<>"",D7<>"",E7<>"",F7<>"",H7<>"",I7<>"",J7<>"",K7<>"",L7<>"",M7<>"",N7<>"",O7<>""),"PASS","FAIL") -> PASS
A8: BC25-LOANS | B8: Grupo Cibest S.A. | C8: Gross loans | D8: 285207.4 | E8: COP bn | F8: 2025-12-31 | G8: 4Q25 pro-forma incl. Banistmo | H8: 4Q25 6-K total loan portfolio table; ifrs-full:LoansAndAdvancesToCustomers | I8: 6-K | J8: 2026-02-23 | K8: 0002058897-26-000013 | L8: https://www.sec.gov/Archives/edgar/data/2058897/000205889726000013/grupocibestsa6-kpr4q25.htm | M8: Historical!C6 | N8: COP million / 1,000; gross; no FX; pro-forma incl. Banistmo | O8: Primary filing | P8: =IF(AND(C8<>"",D8<>"",E8<>"",F8<>"",H8<>"",I8<>"",J8<>"",K8<>"",L8<>"",M8<>"",N8<>"",O8<>""),"PASS","FAIL") -> PASS
A9: BC24-DEPOSITS | B9: Grupo Cibest / Bancolombia predecessor | C9: Customer deposits | D9: 279059.4 | E9: COP bn | F9: 2024-12-31 | G9: 4Q25 pro-forma incl. Banistmo | H9: 4Q25 6-K consolidated statement; ifrs-full:DepositsFromCustomers | I9: 6-K | J9: 2026-02-23 | K9: 0002058897-26-000013 | L9: https://www.sec.gov/Archives/edgar/data/2058897/000205889726000013/grupocibestsa6-kpr4q25.htm | M9: Historical!B7 | N9: COP million / 1,000; no FX; comparative pro-forma perimeter | O9: Primary filing | P9: =IF(AND(C9<>"",D9<>"",E9<>"",F9<>"",H9<>"",I9<>"",J9<>"",K9<>"",L9<>"",M9<>"",N9<>"",O9<>""),"PASS","FAIL") -> PASS
A10: BC25-DEPOSITS | B10: Grupo Cibest S.A. | C10: Customer deposits | D10: 291707.47 | E10: COP bn | F10: 2025-12-31 | G10: 4Q25 pro-forma incl. Banistmo | H10: 4Q25 6-K consolidated statement; ifrs-full:DepositsFromCustomers | I10: 6-K | J10: 2026-02-23 | K10: 0002058897-26-000013 | L10: https://www.sec.gov/Archives/edgar/data/2058897/000205889726000013/grupocibestsa6-kpr4q25.htm | M10: Historical!C7 | N10: COP million / 1,000; no FX; pro-forma incl. Banistmo | O10: Primary filing | P10: =IF(AND(C10<>"",D10<>"",E10<>"",F10<>"",H10<>"",I10<>"",J10<>"",K10<>"",L10<>"",M10<>"",N10<>"",O10<>""),"PASS","FAIL") -> PASS
A11: BC24-EQUITY | B11: Grupo Cibest / Bancolombia predecessor | C11: Equity attributable to parent | D11: 43542.468 | E11: COP bn | F11: 2024-12-31 | G11: 4Q25 pro-forma incl. Banistmo | H11: 4Q25 6-K consolidated statement; ifrs-full:EquityAttributableToOwnersOfParent | I11: 6-K | J11: 2026-02-23 | K11: 0002058897-26-000013 | L11: https://www.sec.gov/Archives/edgar/data/2058897/000205889726000013/grupocibestsa6-kpr4q25.htm | M11: Historical!B8 | N11: COP million / 1,000; no FX; comparative pro-forma perimeter | O11: Primary filing | P11: =IF(AND(C11<>"",D11<>"",E11<>"",F11<>"",H11<>"",I11<>"",J11<>"",K11<>"",L11<>"",M11<>"",N11<>"",O11<>""),"PASS","FAIL") -> PASS
A12: BC25-EQUITY | B12: Grupo Cibest S.A. | C12: Equity attributable to parent | D12: 43092.745 | E12: COP bn | F12: 2025-12-31 | G12: 4Q25 pro-forma incl. Banistmo | H12: 4Q25 6-K consolidated statement; ifrs-full:EquityAttributableToOwnersOfParent | I12: 6-K | J12: 2026-02-23 | K12: 0002058897-26-000013 | L12: https://www.sec.gov/Archives/edgar/data/2058897/000205889726000013/grupocibestsa6-kpr4q25.htm | M12: Historical!C8 | N12: COP million / 1,000; no FX; pro-forma incl. Banistmo | O12: Primary filing | P12: =IF(AND(C12<>"",D12<>"",E12<>"",F12<>"",H12<>"",I12<>"",J12<>"",K12<>"",L12<>"",M12<>"",N12<>"",O12<>""),"PASS","FAIL") -> PASS
A13: BC24-NI | B13: Bancolombia S.A. predecessor | C13: Net income attributable | D13: 6267.744 | E13: COP bn | F13: FY2024 | G13: Reported | H13: 2024 annual management report / 20-F discussion; ifrs-full:ProfitLossAttributableToOwnersOfParent | I13: 20-F / 6-K | J13: 2025-03-28 / 2025-04-07 | K13: 0001071371-25-000053 / 0001071371-25-000062 | L13: https://www.sec.gov/Archives/edgar/data/1071371/000107137125000062/ex991-annualreportofbancol.htm | M13: Historical!B9 | N13: COP million / 1,000; no FX; predecessor legal entity disclosed | O13: Primary filing | P13: =IF(AND(C13<>"",D13<>"",E13<>"",F13<>"",H13<>"",I13<>"",J13<>"",K13<>"",L13<>"",M13<>"",N13<>"",O13<>""),"PASS","FAIL") -> PASS
A14: BC25-ADJNI | B14: Grupo Cibest S.A. | C14: Adjusted net income ex-Banistmo sale | D14: 7276.23 | E14: COP bn | F14: FY2025 | G14: Management adjusted continuing basis | H14: 4Q25 6-K income statement discussion; issuer non-GAAP, no taxonomy tag | I14: 6-K | J14: 2026-02-23 | K14: 0002058897-26-000013 | L14: https://www.sec.gov/Archives/edgar/data/2058897/000205889726000013/grupocibestsa6-kpr4q25.htm | M14: Historical!C9 | N14: COP million / 1,000; excludes COP 3.4tn goodwill impairment from Banistmo sale | O14: Primary filing / adjusted | P14: =IF(AND(C14<>"",D14<>"",E14<>"",F14<>"",H14<>"",I14<>"",J14<>"",K14<>"",L14<>"",M14<>"",N14<>"",O14<>""),"PASS","FAIL") -> PASS
A15: BC25-REPNI | B15: Grupo Cibest S.A. | C15: Reported net income | D15: 3821 | E15: COP bn | F15: FY2025 | G15: Reported | H15: 4Q25 6-K income statement discussion; ifrs-full:ProfitLossAttributableToOwnersOfParent | I15: 6-K | J15: 2026-02-23 | K15: 0002058897-26-000013 | L15: https://www.sec.gov/Archives/edgar/data/2058897/000205889726000013/grupocibestsa6-kpr4q25.htm | M15: Historical!C10 | N15: COP million / 1,000; no FX; includes Banistmo goodwill impairment | O15: Primary filing | P15: =IF(AND(C15<>"",D15<>"",E15<>"",F15<>"",H15<>"",I15<>"",J15<>"",K15<>"",L15<>"",M15<>"",N15<>"",O15<>""),"PASS","FAIL") -> PASS
A16: BC24-NIM | B16: Grupo Cibest / Bancolombia predecessor | C16: Quarterly annualized consolidated NIM | D16: 0.0599 | E16: % | F16: 4Q2024 | G16: Comparable 4Q | H16: 4Q25 6-K NIM table; issuer operating ratio | I16: 6-K | J16: 2026-02-23 | K16: 0002058897-26-000013 | L16: https://www.sec.gov/Archives/edgar/data/2058897/000205889726000013/grupocibestsa6-kpr4q25.htm | M16: Historical!B11 | N16: Direct ratio; no FX; comparative pro-forma disclosure | O16: Primary filing | P16: =IF(AND(C16<>"",D16<>"",E16<>"",F16<>"",H16<>"",I16<>"",J16<>"",K16<>"",L16<>"",M16<>"",N16<>"",O16<>""),"PASS","FAIL") -> PASS
... A27: BC25-SHARES | B27: Grupo Cibest S.A. | C27: Reported EPS used to derive equivalent shares | D27: 4045 | E27: COP/share | F27: FY2025 | G27: Reported EPS; derived share count | H27: 2025 20-F Item 5: COP 3,821bn attributable net income and COP 4,045 EPS | I27: 20-F | J27: 2026-04-08 | K27: 0002058897-26-000125 | L27: https://www.sec.gov/Archives/edgar/data/2058897/000205889726000125/cib-20251231.htm | M27: Historical!B19:C19; Assumptions!B18:E18; Valuation!G24:G25 | N27: COP 3,821bn x 1,000 / COP 4,045 per share = 944.623mm equivalent shares; rounded only for display | O27: Primary filing / derived | P27: =IF(AND(C27<>"",D27<>"",E27<>"",F27<>"",H27<>"",I27<>"",J27<>"",K27<>"",L27<>"",M27<>"",N27<>"",O27<>""),"PASS","FAIL") -> PASS
A28: Completeness | O28: =COUNTIF(P5:P27,"PASS") -> 23 | P28: =IF(O28=23,"PASS","FAIL") -> PASS

Sheet Historical
A1: Historical bank economics | B1: Historical bank economics | C1: Historical bank economics | D1: Historical bank economics | E1: Historical bank economics | F1: Historical bank economics | G1: Historical bank economics | H1: Historical bank economics
A2: COP billions except ratios and shares. 2024A/2025A use explicit pro-forma perimeter notes; no current FX across history. | B2: COP billions except ratios and shares. 2024A/2025A use explicit pro-forma perimeter notes; no current FX across history. | C2: COP billions except ratios and shares. 2024A/2025A use explicit pro-forma perimeter notes; no current FX across history. | D2: COP billions except ratios and shares. 2024A/2025A use explicit pro-forma perimeter notes; no current FX across history. | E2: COP billions except ratios and shares. 2024A/2025A use explicit pro-forma perimeter notes; no current FX across history. | F2: COP billions except ratios and shares. 2024A/2025A use explicit pro-forma perimeter notes; no current FX across history. | G2: COP billions except ratios and shares. 2024A/2025A use explicit pro-forma perimeter notes; no current FX across history. | H2: COP billions except ratios and shares. 2024A/2025A use explicit pro-forma perimeter notes; no current FX across history.
A4: Metric | B4: 2024A | C4: 2025A | D4: Unit | E4: Source ID | F4: Exact locator / tag | G4: Perimeter / transformation | H4: Quality
A5: Total assets | B5: 372215.38 | C5: 384657.72 | D5: COP bn | E5: BC24/25-ASSETS | F5: 4Q25 6-K statement / ifrs-full:Assets | G5: Pro-forma including Banistmo | H5: Primary filing
A6: Gross loans | B6: 279453.91 | C6: 285207.4 | D6: COP bn | E6: BC24/25-LOANS | F6: 4Q25 6-K loan table | G6: Gross; pro-forma including Banistmo | H6: Primary filing
A7: Customer deposits | B7: 279059.4 | C7: 291707.47 | D7: COP bn | E7: BC24/25-DEPOSITS | F7: 4Q25 6-K statement | G7: Operating funding; not corporate debt | H7: Primary filing
A8: Equity attributable to parent | B8: 43542.468 | C8: 43092.745 | D8: COP bn | E8: BC24/25-EQUITY | F8: 4Q25 6-K statement | G8: Parent attributable; no FX | H8: Primary filing
A9: Adjusted net income | B9: 6267.744 | C9: 7276.23 | D9: COP bn | E9: BC24-NI / BC25-ADJNI | F9: 20-F / 4Q25 6-K discussion | G9: 2025 excludes Banistmo sale goodwill impairment | H9: Primary / adjusted
A10: Reported net income | B10: 6267.744 | C10: 3821 | D10: COP bn | E10: BC24-NI / BC25-REPNI | F10: 20-F / 4Q25 6-K discussion | G10: 2025 includes Banistmo goodwill impairment | H10: Primary filing
A11: Quarterly annualized consolidated NIM | B11: 0.0599 | C11: 0.0616 | D11: % | E11: BC24/25-NIM | F11: 4Q25 6-K NIM table / discussion | G11: Comparable 4Q ratios; not full-year average | H11: Primary filing
A12: Cost of risk | C12: 0.0159 | D12: % | E12: BC25-COR | F12: 4Q25 6-K asset quality discussion | G12: LTM 2025 | H12: Primary filing
A13: 30-day past-due loans / gross loans | B13: 0.0465 | C13: 0.0357 | D13: % | E13: BC24/25-PDL | F13: 4Q25 6-K asset quality table | G13: 2024 ratio derived from reported numerator/denominator | H13: Primary / derived
A14: 30-day PDL coverage | B14: 1.2427 | C14: 1.3441 | D14: % | E14: BC24/25-COVER | F14: 4Q25 6-K / 2025 20-F | G14: Direct ratios | H14: Primary filing
A15: Basic/core solvency | B15: 0.1195 | C15: 0.1222 | D15: % | E15: BC24/25-CORE | F15: 4Q25 6-K solvency table | G15: 2024 pro-forma; 2025 reported | H15: Primary filing
A16: Total solvency | B16: 0.1475 | C16: 0.144 | D16: % | E16: BC24/25-CORE | F16: 4Q25 6-K solvency table | G16: 2024 pro-forma; 2025 reported | H16: Primary filing
A17: Technical equity | C17: 29431.196 | D17: COP bn | E17: BC25-CAP | F17: 4Q25 6-K solvency table | G17: Regulatory capital measure | H17: Primary filing
A18: Implied capital requirement denominator | C18: =C17/C15 -> 240844.48 | D18: COP bn | E18: BC25-CAP | F18: Technical equity / core solvency | G18: Formula-derived denominator for forecast capital roll-forward | H18: Derived
A19: Diluted / equivalent shares | B19: 944.62299 | C19: 944.62299 | D19: mm shares | E19: BC25-SHARES | F19: 2025 20-F Item 5: COP 3,821bn attributable NI / COP 4,045 EPS | G19: 2025 equivalent share count derived from official NI and EPS; held constant for 2024 cross-check | H19: Primary filing / derived

Sheet Assumptions
A1: Assumptions and scenarios | B1: Assumptions and scenarios | C1: Assumptions and scenarios | D1: Assumptions and scenarios | E1: Assumptions and scenarios | F1: Assumptions and scenarios
A2: Blue-font cells are editable inputs. Selector: 1 = Base, 2 = Bull, 3 = Bear. Active results are formula cells, not drivers. | B2: Blue-font cells are editable inputs. Selector: 1 = Base, 2 = Bull, 3 = Bear. Active results are formula cells, not drivers. | C2: Blue-font cells are editable inputs. Selector: 1 = Base, 2 = Bull, 3 = Bear. Active results are formula cells, not drivers. | D2: Blue-font cells are editable inputs. Selector: 1 = Base, 2 = Bull, 3 = Bear. Active results are formula cells, not drivers. | E2: Blue-font cells are editable inputs. Selector: 1 = Base, 2 = Bull, 3 = Bear. Active results are formula cells, not drivers. | F2: Blue-font cells are editable inputs. Selector: 1 = Base, 2 = Bull, 3 = Bear. Active results are formula cells, not drivers.
A3: Scenario selector | B3: 1 | E3: =CHOOSE(B3,"Base","Bull","Bear") -> Base | F3: Return to 1 after perturbation testing
A5: Metric | B5: Base | C5: Bull | D5: Bear | E5: Active | F5: Rationale / source / ownership
A6: Loan growth | B6: 0.06 | C6: 0.08 | D6: 0.03 | E6: =CHOOSE($B$3,B6,C6,D6) -> 0.06 | F6: Model input; anchored to 2025 pro-forma loan growth and 2026 recovery
A7: Deposit growth | B7: 0.07 | C7: 0.09 | D7: 0.04 | E7: =CHOOSE($B$3,B7,C7,D7) -> 0.07 | F7: Model input; preserves deposits as operating funding
A8: Net interest margin | B8: 0.062 | C8: 0.065 | D8: 0.057 | E8: =CHOOSE($B$3,B8,C8,D8) -> 0.062 | F8: Model input; anchored to 4Q25 consolidated NIM 6.16%
A9: Cost of risk | B9: 0.017 | C9: 0.013 | D9: 0.024 | E9: =CHOOSE($B$3,B9,C9,D9) -> 0.017 | F9: Model input; anchored to 2025 LTM 1.59% with downside stress
A10: Fee + other income / avg assets | B10: 0.027 | C10: 0.029 | D10: 0.024 | E10: =CHOOSE($B$3,B10,C10,D10) -> 0.027 | F10: Model input; bank non-interest income proxy
A11: Operating expense / avg assets | B11: 0.034 | C11: 0.032 | D11: 0.037 | E11: =CHOOSE($B$3,B11,C11,D11) -> 0.034 | F11: Model input; explicit operating-efficiency driver
A12: Tax rate | B12: 0.3 | C12: 0.29 | D12: 0.31 | E12: =CHOOSE($B$3,B12,C12,D12) -> 0.3 | F12: Model input; normalized effective tax
A13: Dividend payout target | B13: 0.5 | C13: 0.45 | D13: 0.6 | E13: =CHOOSE($B$3,B13,C13,D13) -> 0.5 | F13: Policy-aware input; 2025 20-F states statutory minimum distribution framework
A14: Core capital eligible / parent equity | B14: 0.683 | C14: 0.683 | D14: 0.683 | E14: =CHOOSE($B$3,B14,C14,D14) -> 0.683 | F14: Derived from 2025 technical equity / parent equity
A15: Minimum core solvency | B15: 0.115 | C15: 0.115 | D15: 0.115 | E15: =CHOOSE($B$3,B15,C15,D15) -> 0.115 | F15: Model governance floor below 2025 reported 12.22%
A16: Cost of equity | B16: 0.13 | C16: 0.12 | D16: 0.145 | E16: =CHOOSE($B$3,B16,C16,D16) -> 0.13 | F16: Valuation input; nominal COP required return
A17: Terminal growth | B17: 0.05 | C17: 0.06 | D17: 0.035 | E17: =CHOOSE($B$3,B17,C17,D17) -> 0.05 | F17: Valuation input; nominal COP long-run growth
... A21: 30-day coverage target | B21: 1.35 | C21: 1.45 | D21: 1.2 | E21: =CHOOSE($B$3,B21,C21,D21) -> 1.35 | F21: Model input; anchored to 2025 reported 134.41%
A23: Scenario ownership: cases change operating drivers, capital/payout mechanics and residual-income valuation through formulas. No scenario changes only the headline valuation. The capital schedule can constrain dividends to protect the visible solvency floor. | B23: Scenario ownership: cases change operating drivers, capital/payout mechanics and residual-income valuation through formulas. No scenario changes only the headline valuation. The capital schedule can constrain dividends to protect the visible solvency floor. | C23: Scenario ownership: cases change operating drivers, capital/payout mechanics and residual-income valuation through formulas. No scenario changes only the headline valuation. The capital schedule can constrain dividends to protect the visible solvency floor. | D23: Scenario ownership: cases change operating drivers, capital/payout mechanics and residual-income valuation through formulas. No scenario changes only the headline valuation. The capital schedule can constrain dividends to protect the visible solvency floor. | E23: Scenario ownership: cases change operating drivers, capital/payout mechanics and residual-income valuation through formulas. No scenario changes only the headline valuation. The capital schedule can constrain dividends to protect the visible solvency floor. | F23: Scenario ownership: cases change operating drivers, capital/payout mechanics and residual-income valuation through formulas. No scenario changes only the headline valuation. The capital schedule can constrain dividends to protect the visible solvency floor.
A24: Scenario ownership: cases change operating drivers, capital/payout mechanics and residual-income valuation through formulas. No scenario changes only the headline valuation. The capital schedule can constrain dividends to protect the visible solvency floor. | B24: Scenario ownership: cases change operating drivers, capital/payout mechanics and residual-income valuation through formulas. No scenario changes only the headline valuation. The capital schedule can constrain dividends to protect the visible solvency floor. | C24: Scenario ownership: cases change operating drivers, capital/payout mechanics and residual-income valuation through formulas. No scenario changes only the headline valuation. The capital schedule can constrain dividends to protect the visible solvency floor. | D24: Scenario ownership: cases change operating drivers, capital/payout mechanics and residual-income valuation through formulas. No scenario changes only the headline valuation. The capital schedule can constrain dividends to protect the visible solvency floor. | E24: Scenario ownership: cases change operating drivers, capital/payout mechanics and residual-income valuation through formulas. No scenario changes only the headline valuation. The capital schedule can constrain dividends to protect the visible solvency floor. | F24: Scenario ownership: cases change operating drivers, capital/payout mechanics and residual-income valuation through formulas. No scenario changes only the headline valuation. The capital schedule can constrain dividends to protect the visible solvency floor.

Sheet Forecast
A1: Forecast summary | B1: Forecast summary | C1: Forecast summary | D1: Forecast summary | E1: Forecast summary | F1: Forecast summary | G1: Forecast summary | H1: Forecast summary
A2: Formula-linked summary of bank driver, earnings, capital and payout schedules. The Sector_KPIs sheet contains the detailed mechanics. | B2: Formula-linked summary of bank driver, earnings, capital and payout schedules. The Sector_KPIs sheet contains the detailed mechanics. | C2: Formula-linked summary of bank driver, earnings, capital and payout schedules. The Sector_KPIs sheet contains the detailed mechanics. | D2: Formula-linked summary of bank driver, earnings, capital and payout schedules. The Sector_KPIs sheet contains the detailed mechanics. | E2: Formula-linked summary of bank driver, earnings, capital and payout schedules. The Sector_KPIs sheet contains the detailed mechanics. | F2: Formula-linked summary of bank driver, earnings, capital and payout schedules. The Sector_KPIs sheet contains the detailed mechanics. | G2: Formula-linked summary of bank driver, earnings, capital and payout schedules. The Sector_KPIs sheet contains the detailed mechanics. | H2: Formula-linked summary of bank driver, earnings, capital and payout schedules. The Sector_KPIs sheet contains the detailed mechanics.
A4: Metric | B4: 2025A | C4: 2026E | D4: 2027E | E4: 2028E | F4: 2029E | G4: 2030E | H4: Decision use
A5: Gross loans | B5: =Sector_KPIs!B5 -> 285207.4 | C5: =Sector_KPIs!C5 -> 302319.84 | D5: =Sector_KPIs!D5 -> 320459.03 | E5: =Sector_KPIs!E5 -> 339686.57 | F5: =Sector_KPIs!F5 -> 360067.77 | G5: =Sector_KPIs!G5 -> 381671.83 | H5: Balance-sheet growth
A6: Loan growth | B6: =Sector_KPIs!B6 -> 0.020588333 | C6: =Sector_KPIs!C6 -> 0.06 | D6: =Sector_KPIs!D6 -> 0.06 | E6: =Sector_KPIs!E6 -> 0.06 | F6: =Sector_KPIs!F6 -> 0.06 | G6: =Sector_KPIs!G6 -> 0.06 | H6: Scenario propagation
A7: Customer deposits | B7: =Sector_KPIs!B7 -> 291707.47 | C7: =Sector_KPIs!C7 -> 312127 | D7: =Sector_KPIs!D7 -> 333975.89 | E7: =Sector_KPIs!E7 -> 357354.2 | F7: =Sector_KPIs!F7 -> 382368.99 | G7: =Sector_KPIs!G7 -> 409134.82 | H7: Operating funding
A8: Deposit growth | B8: =Sector_KPIs!B8 -> 0.045323945 | C8: =Sector_KPIs!C8 -> 0.07 | D8: =Sector_KPIs!D8 -> 0.07 | E8: =Sector_KPIs!E8 -> 0.07 | F8: =Sector_KPIs!F8 -> 0.07 | G8: =Sector_KPIs!G8 -> 0.07 | H8: Funding growth
A9: Net interest income | B9: =Sector_KPIs!B11 -> 17568.776 | C9: =Sector_KPIs!C11 -> 18213.344 | D9: =Sector_KPIs!D11 -> 19306.145 | E9: =Sector_KPIs!E11 -> 20464.514 | F9: =Sector_KPIs!F11 -> 21692.385 | G9: =Sector_KPIs!G11 -> 22993.928 | H9: Core earnings
A10: Credit provisions | B10: =Sector_KPIs!B13 -> 4534.7976 | C10: =Sector_KPIs!C13 -> 4993.9815 | D10: =Sector_KPIs!D13 -> 5293.6204 | E10: =Sector_KPIs!E13 -> 5611.2377 | F10: =Sector_KPIs!F13 -> 5947.9119 | G10: =Sector_KPIs!G13 -> 6304.7866 | H10: Credit cycle
A11: Net income | B11: =Sector_KPIs!B19 -> 7276.23 | C11: =Sector_KPIs!C19 -> 7309.8305 | D11: =Sector_KPIs!D19 -> 7743.561 | E11: =Sector_KPIs!E19 -> 8203.0117 | F11: =Sector_KPIs!F19 -> 8689.7067 | G11: =Sector_KPIs!G19 -> 9205.2605 | H11: Equity return
A12: ROE | B12: =Sector_KPIs!B29 -> 0 | C12: =Sector_KPIs!C29 -> 0.16272924 | D12: =Sector_KPIs!D29 -> 0.15905909 | E12: =Sector_KPIs!E29 -> 0.15574296 | F12: =Sector_KPIs!F29 -> 0.15273671 | G12: =Sector_KPIs!G29 -> 0.15000315 | H12: Profitability
A13: Dividends | B13: =Sector_KPIs!B25 -> 0 | C13: =Sector_KPIs!C25 -> 3654.9152 | D13: =Sector_KPIs!D25 -> 3871.7805 | E13: =Sector_KPIs!E25 -> 4101.5058 | F13: =Sector_KPIs!F25 -> 4344.8533 | G13: =Sector_KPIs!G25 -> 4602.6302 | H13: Payout subject to capital
A14: Ending parent equity | B14: =Sector_KPIs!B26 -> 43092.745 | C14: =Sector_KPIs!C26 -> 46747.66 | D14: =Sector_KPIs!D26 -> 50619.441 | E14: =Sector_KPIs!E26 -> 54720.947 | F14: =Sector_KPIs!F26 -> 59065.8 | G14: =Sector_KPIs!G26 -> 63668.43 | H14: Book value / valuation
A15: Core solvency | B15: =Sector_KPIs!B28 -> 0.1222 | C15: =Sector_KPIs!C28 -> 0.12506564 | D15: =Sector_KPIs!D28 -> 0.12775844 | E15: =Sector_KPIs!E28 -> 0.13029268 | F15: =Sector_KPIs!F28 -> 0.1326773 | G15: =Sector_KPIs!G28 -> 0.13492077 | H15: Capital guardrail
A16: 30-day PDL ratio | B16: =Sector_KPIs!B30 -> 0.0357 | C16: =Sector_KPIs!C30 -> 0.034 | D16: =Sector_KPIs!D30 -> 0.034 | E16: =Sector_KPIs!E30 -> 0.034 | F16: =Sector_KPIs!F30 -> 0.034 | G16: =Sector_KPIs!G30 -> 0.034 | H16: Asset quality

Sheet Valuation
A1: Bank-appropriate equity valuation | B1: Bank-appropriate equity valuation | C1: Bank-appropriate equity valuation | D1: Bank-appropriate equity valuation | E1: Bank-appropriate equity valuation | F1: Bank-appropriate equity valuation | G1: Bank-appropriate equity valuation
A2: Residual income is primary; DDM is a cross-check. No enterprise-value bridge treats deposits as corporate debt. | B2: Residual income is primary; DDM is a cross-check. No enterprise-value bridge treats deposits as corporate debt. | C2: Residual income is primary; DDM is a cross-check. No enterprise-value bridge treats deposits as corporate debt. | D2: Residual income is primary; DDM is a cross-check. No enterprise-value bridge treats deposits as corporate debt. | E2: Residual income is primary; DDM is a cross-check. No enterprise-value bridge treats deposits as corporate debt. | F2: Residual income is primary; DDM is a cross-check. No enterprise-value bridge treats deposits as corporate debt. | G2: Residual income is primary; DDM is a cross-check. No enterprise-value bridge treats deposits as corporate debt.
A4: Residual income | B4: 2026E | C4: 2027E | D4: 2028E | E4: 2029E | F4: 2030E | G4: Output
A5: Beginning book value | B5: =Historical!C8 -> 43092.745 | C5: =Sector_KPIs!C26 -> 46747.66 | D5: =Sector_KPIs!D26 -> 50619.441 | E5: =Sector_KPIs!E26 -> 54720.947 | F5: =Sector_KPIs!F26 -> 59065.8
A6: Net income | B6: =Sector_KPIs!C19 -> 7309.8305 | C6: =Sector_KPIs!D19 -> 7743.561 | D6: =Sector_KPIs!E19 -> 8203.0117 | E6: =Sector_KPIs!F19 -> 8689.7067 | F6: =Sector_KPIs!G19 -> 9205.2605
A7: ROE | B7: =B6/B5 -> 0.16963019 | C7: =C6/C5 -> 0.16564596 | D7: =D6/D5 -> 0.16205259 | E7: =E6/E5 -> 0.15880037 | F7: =F6/F5 -> 0.15584755
A8: Cost of equity | B8: =Assumptions!$E$16 -> 0.13 | C8: =Assumptions!$E$16 -> 0.13 | D8: =Assumptions!$E$16 -> 0.13 | E8: =Assumptions!$E$16 -> 0.13 | F8: =Assumptions!$E$16 -> 0.13
A9: Equity charge | B9: =B5*B8 -> 5602.0569 | C9: =C5*C8 -> 6077.1958 | D9: =D5*D8 -> 6580.5273 | E9: =E5*E8 -> 7113.7231 | F9: =F5*F8 -> 7678.554
A10: Residual income | B10: =B6-B9 -> 1707.7736 | C10: =C6-C9 -> 1666.3652 | D10: =D6-D9 -> 1622.4844 | E10: =E6-E9 -> 1575.9836 | F10: =F6-F9 -> 1526.7065
A11: Discount factor | B11: =1/(1+B8)^1 -> 0.88495575 | C11: =1/(1+C8)^2 -> 0.78314668 | D11: =1/(1+D8)^3 -> 0.69305016 | E11: =1/(1+E8)^4 -> 0.61331873 | F11: =1/(1+F8)^5 -> 0.54275994
A12: PV residual income | B12: =B10*B11 -> 1511.3041 | C12: =C10*C11 -> 1305.0084 | D12: =D10*D11 -> 1124.4631 | E12: =E10*E11 -> 966.58026 | F12: =F10*F11 -> 828.63513
A14: Terminal mechanics
A15: Terminal growth | F15: =Assumptions!E17 -> 0.05
A16: Terminal residual income | F16: =F10*(1+F15) -> 1603.0418
A17: Terminal value / PV | E17: =F16/(F8-F15) -> 20038.023 | F17: =E17*F11 -> 10875.836
A19: Residual-income output | G19: Value
A20: Current book value | G20: =Historical!C8 -> 43092.745
A21: PV explicit residual income | G21: =SUM(B12:F12) -> 5735.9909
A22: PV terminal residual income | G22: =F17 -> 10875.836
A23: Implied equity value | G23: =SUM(G20:G22) -> 59704.572
A24: Equivalent shares (mm) | G24: =Assumptions!E18 -> 944.62299
A25: Implied value per share (COP) | G25: =G23*1000/G24 -> 63204.657
A27: Dividend discount cross-check | B27: 2026E | C27: 2027E | D27: 2028E | E27: 2029E | F27: 2030E | G27: Value
A28: Dividends | B28: =Sector_KPIs!C25 -> 3654.9152 | C28: =Sector_KPIs!D25 -> 3871.7805 | D28: =Sector_KPIs!E25 -> 4101.5058 | E28: =Sector_KPIs!F25 -> 4344.8533 | F28: =Sector_KPIs!G25 -> 4602.6302
A29: PV dividends | B29: =B28*B11 -> 3234.4383 | C29: =C28*C11 -> 3032.1721 | D29: =D28*D11 -> 2842.5493 | E29: =E28*E11 -> 2664.7799 | F29: =F28*F11 -> 2498.1233
A30: Terminal dividend value | F30: =F28*(1+Assumptions!E17)/(Assumptions!E16-Assumptions!E17) -> 60409.522
A31: DDM equity value | G31: =SUM(B29:F29)+F30*F11 -> 47059.931

Sheet Sensitivity
A1: Residual-income sensitivity | B1: Residual-income sensitivity | C1: Residual-income sensitivity | D1: Residual-income sensitivity | E1: Residual-income sensitivity | F1: Residual-income sensitivity
A2: Dynamic equity-value sensitivity to cost of equity and terminal growth. Active-case reconstruction is used by Checks. | B2: Dynamic equity-value sensitivity to cost of equity and terminal growth. Active-case reconstruction is used by Checks. | C2: Dynamic equity-value sensitivity to cost of equity and terminal growth. Active-case reconstruction is used by Checks. | D2: Dynamic equity-value sensitivity to cost of equity and terminal growth. Active-case reconstruction is used by Checks. | E2: Dynamic equity-value sensitivity to cost of equity and terminal growth. Active-case reconstruction is used by Checks. | F2: Dynamic equity-value sensitivity to cost of equity and terminal growth. Active-case reconstruction is used by Checks.
A4: g / CoE | B4: 0.11 | C4: 0.12 | D4: 0.13 | E4: 0.14 | F4: 0.15
A5: 0.03 | B5: =IF(B$4<=$A5,"N/M",Historical!C8+((Sector_KPIs!C19-Historical!C8*B$4)/(1+B$4)^1)+((Sector_KPIs!D19-Sector_KPIs!C26*B$4)/(1+B$4)^2)+((Sector_KPIs!E19-Sector_KPIs!D26*B$4)/(1+B$4)^3)+((Sector_KPIs!F19-Sector_KPIs!E26*B$4)/(1+B$4)^4)+((Sector_KPIs!G19-Sector_KPIs!F26*B$4)/(1+B$4)^5)+(((Sector_KPIs!G19-Sector_KPIs!F26*B$4)*(1+$A5)/(B$4-$A5))/(1+B$4)^5)) -> 73502.916 | C5: =IF(C$4<=$A5,"N/M",Historical!C8+((Sector_KPIs!C19-Historical!C8*C$4)/(1+C$4)^1)+((Sector_KPIs!D19-Sector_KPIs!C26*C$4)/(1+C$4)^2)+((Sector_KPIs!E19-Sector_KPIs!D26*C$4)/(1+C$4)^3)+((Sector_KPIs!F19-Sector_KPIs!E26*C$4)/(1+C$4)^4)+((Sector_KPIs!G19-Sector_KPIs!F26*C$4)/(1+C$4)^5)+(((Sector_KPIs!G19-Sector_KPIs!F26*C$4)*(1+$A5)/(C$4-$A5))/(1+C$4)^5)) -> 64519.236 | D5: =IF(D$4<=$A5,"N/M",Historical!C8+((Sector_KPIs!C19-Historical!C8*D$4)/(1+D$4)^1)+((Sector_KPIs!D19-Sector_KPIs!C26*D$4)/(1+D$4)^2)+((Sector_KPIs!E19-Sector_KPIs!D26*D$4)/(1+D$4)^3)+((Sector_KPIs!F19-Sector_KPIs!E26*D$4)/(1+D$4)^4)+((Sector_KPIs!G19-Sector_KPIs!F26*D$4)/(1+D$4)^5)+(((Sector_KPIs!G19-Sector_KPIs!F26*D$4)*(1+$A5)/(D$4-$A5))/(1+D$4)^5)) -> 57363.678 | E5: =IF(E$4<=$A5,"N/M",Historical!C8+((Sector_KPIs!C19-Historical!C8*E$4)/(1+E$4)^1)+((Sector_KPIs!D19-Sector_KPIs!C26*E$4)/(1+E$4)^2)+((Sector_KPIs!E19-Sector_KPIs!D26*E$4)/(1+E$4)^3)+((Sector_KPIs!F19-Sector_KPIs!E26*E$4)/(1+E$4)^4)+((Sector_KPIs!G19-Sector_KPIs!F26*E$4)/(1+E$4)^5)+(((Sector_KPIs!G19-Sector_KPIs!F26*E$4)*(1+$A5)/(E$4-$A5))/(1+E$4)^5)) -> 51536.198 | F5: =IF(F$4<=$A5,"N/M",Historical!C8+((Sector_KPIs!C19-Historical!C8*F$4)/(1+F$4)^1)+((Sector_KPIs!D19-Sector_KPIs!C26*F$4)/(1+F$4)^2)+((Sector_KPIs!E19-Sector_KPIs!D26*F$4)/(1+F$4)^3)+((Sector_KPIs!F19-Sector_KPIs!E26*F$4)/(1+F$4)^4)+((Sector_KPIs!G19-Sector_KPIs!F26*F$4)/(1+F$4)^5)+(((Sector_KPIs!G19-Sector_KPIs!F26*F$4)*(1+$A5)/(F$4-$A5))/(1+F$4)^5)) -> 46703.514
A6: 0.04 | B6: =IF(B$4<=$A6,"N/M",Historical!C8+((Sector_KPIs!C19-Historical!C8*B$4)/(1+B$4)^1)+((Sector_KPIs!D19-Sector_KPIs!C26*B$4)/(1+B$4)^2)+((Sector_KPIs!E19-Sector_KPIs!D26*B$4)/(1+B$4)^3)+((Sector_KPIs!F19-Sector_KPIs!E26*B$4)/(1+B$4)^4)+((Sector_KPIs!G19-Sector_KPIs!F26*B$4)/(1+B$4)^5)+(((Sector_KPIs!G19-Sector_KPIs!F26*B$4)*(1+$A6)/(B$4-$A6))/(1+B$4)^5)) -> 76688.378 | C6: =IF(C$4<=$A6,"N/M",Historical!C8+((Sector_KPIs!C19-Historical!C8*C$4)/(1+C$4)^1)+((Sector_KPIs!D19-Sector_KPIs!C26*C$4)/(1+C$4)^2)+((Sector_KPIs!E19-Sector_KPIs!D26*C$4)/(1+C$4)^3)+((Sector_KPIs!F19-Sector_KPIs!E26*C$4)/(1+C$4)^4)+((Sector_KPIs!G19-Sector_KPIs!F26*C$4)/(1+C$4)^5)+(((Sector_KPIs!G19-Sector_KPIs!F26*C$4)*(1+$A6)/(C$4-$A6))/(1+C$4)^5)) -> 66388.157 | D6: =IF(D$4<=$A6,"N/M",Historical!C8+((Sector_KPIs!C19-Historical!C8*D$4)/(1+D$4)^1)+((Sector_KPIs!D19-Sector_KPIs!C26*D$4)/(1+D$4)^2)+((Sector_KPIs!E19-Sector_KPIs!D26*D$4)/(1+D$4)^3)+((Sector_KPIs!F19-Sector_KPIs!E26*D$4)/(1+D$4)^4)+((Sector_KPIs!G19-Sector_KPIs!F26*D$4)/(1+D$4)^5)+(((Sector_KPIs!G19-Sector_KPIs!F26*D$4)*(1+$A6)/(D$4-$A6))/(1+D$4)^5)) -> 58404.075 | E6: =IF(E$4<=$A6,"N/M",Historical!C8+((Sector_KPIs!C19-Historical!C8*E$4)/(1+E$4)^1)+((Sector_KPIs!D19-Sector_KPIs!C26*E$4)/(1+E$4)^2)+((Sector_KPIs!E19-Sector_KPIs!D26*E$4)/(1+E$4)^3)+((Sector_KPIs!F19-Sector_KPIs!E26*E$4)/(1+E$4)^4)+((Sector_KPIs!G19-Sector_KPIs!F26*E$4)/(1+E$4)^5)+(((Sector_KPIs!G19-Sector_KPIs!F26*E$4)*(1+$A6)/(E$4-$A6))/(1+E$4)^5)) -> 52040.031 | F6: =IF(F$4<=$A6,"N/M",Historical!C8+((Sector_KPIs!C19-Historical!C8*F$4)/(1+F$4)^1)+((Sector_KPIs!D19-Sector_KPIs!C26*F$4)/(1+F$4)^2)+((Sector_KPIs!E19-Sector_KPIs!D26*F$4)/(1+F$4)^3)+((Sector_KPIs!F19-Sector_KPIs!E26*F$4)/(1+F$4)^4)+((Sector_KPIs!G19-Sector_KPIs!F26*F$4)/(1+F$4)^5)+(((Sector_KPIs!G19-Sector_KPIs!F26*F$4)*(1+$A6)/(F$4-$A6))/(1+F$4)^5)) -> 46853.119
A7: 0.05 | B7: =IF(B$4<=$A7,"N/M",Historical!C8+((Sector_KPIs!C19-Historical!C8*B$4)/(1+B$4)^1)+((Sector_KPIs!D19-Sector_KPIs!C26*B$4)/(1+B$4)^2)+((Sector_KPIs!E19-Sector_KPIs!D26*B$4)/(1+B$4)^3)+((Sector_KPIs!F19-Sector_KPIs!E26*B$4)/(1+B$4)^4)+((Sector_KPIs!G19-Sector_KPIs!F26*B$4)/(1+B$4)^5)+(((Sector_KPIs!G19-Sector_KPIs!F26*B$4)*(1+$A7)/(B$4-$A7))/(1+B$4)^5)) -> 80935.659 | C7: =IF(C$4<=$A7,"N/M",Historical!C8+((Sector_KPIs!C19-Historical!C8*C$4)/(1+C$4)^1)+((Sector_KPIs!D19-Sector_KPIs!C26*C$4)/(1+C$4)^2)+((Sector_KPIs!E19-Sector_KPIs!D26*C$4)/(1+C$4)^3)+((Sector_KPIs!F19-Sector_KPIs!E26*C$4)/(1+C$4)^4)+((Sector_KPIs!G19-Sector_KPIs!F26*C$4)/(1+C$4)^5)+(((Sector_KPIs!G19-Sector_KPIs!F26*C$4)*(1+$A7)/(C$4-$A7))/(1+C$4)^5)) -> 68791.056 | D7: =IF(D$4<=$A7,"N/M",Historical!C8+((Sector_KPIs!C19-Historical!C8*D$4)/(1+D$4)^1)+((Sector_KPIs!D19-Sector_KPIs!C26*D$4)/(1+D$4)^2)+((Sector_KPIs!E19-Sector_KPIs!D26*D$4)/(1+D$4)^3)+((Sector_KPIs!F19-Sector_KPIs!E26*D$4)/(1+D$4)^4)+((Sector_KPIs!G19-Sector_KPIs!F26*D$4)/(1+D$4)^5)+(((Sector_KPIs!G19-Sector_KPIs!F26*D$4)*(1+$A7)/(D$4-$A7))/(1+D$4)^5)) -> 59704.572 | E7: =IF(E$4<=$A7,"N/M",Historical!C8+((Sector_KPIs!C19-Historical!C8*E$4)/(1+E$4)^1)+((Sector_KPIs!D19-Sector_KPIs!C26*E$4)/(1+E$4)^2)+((Sector_KPIs!E19-Sector_KPIs!D26*E$4)/(1+E$4)^3)+((Sector_KPIs!F19-Sector_KPIs!E26*E$4)/(1+E$4)^4)+((Sector_KPIs!G19-Sector_KPIs!F26*E$4)/(1+E$4)^5)+(((Sector_KPIs!G19-Sector_KPIs!F26*E$4)*(1+$A7)/(E$4-$A7))/(1+E$4)^5)) -> 52655.826 | F7: =IF(F$4<=$A7,"N/M",Historical!C8+((Sector_KPIs!C19-Historical!C8*F$4)/(1+F$4)^1)+((Sector_KPIs!D19-Sector_KPIs!C26*F$4)/(1+F$4)^2)+((Sector_KPIs!E19-Sector_KPIs!D26*F$4)/(1+F$4)^3)+((Sector_KPIs!F19-Sector_KPIs!E26*F$4)/(1+F$4)^4)+((Sector_KPIs!G19-Sector_KPIs!F26*F$4)/(1+F$4)^5)+(((Sector_KPIs!G19-Sector_KPIs!F26*F$4)*(1+$A7)/(F$4-$A7))/(1+F$4)^5)) -> 47032.644
A8: 0.06 | B8: =IF(B$4<=$A8,"N/M",Historical!C8+((Sector_KPIs!C19-Historical!C8*B$4)/(1+B$4)^1)+((Sector_KPIs!D19-Sector_KPIs!C26*B$4)/(1+B$4)^2)+((Sector_KPIs!E19-Sector_KPIs!D26*B$4)/(1+B$4)^3)+((Sector_KPIs!F19-Sector_KPIs!E26*B$4)/(1+B$4)^4)+((Sector_KPIs!G19-Sector_KPIs!F26*B$4)/(1+B$4)^5)+(((Sector_KPIs!G19-Sector_KPIs!F26*B$4)*(1+$A8)/(B$4-$A8))/(1+B$4)^5)) -> 86881.854 | C8: =IF(C$4<=$A8,"N/M",Historical!C8+((Sector_KPIs!C19-Historical!C8*C$4)/(1+C$4)^1)+((Sector_KPIs!D19-Sector_KPIs!C26*C$4)/(1+C$4)^2)+((Sector_KPIs!E19-Sector_KPIs!D26*C$4)/(1+C$4)^3)+((Sector_KPIs!F19-Sector_KPIs!E26*C$4)/(1+C$4)^4)+((Sector_KPIs!G19-Sector_KPIs!F26*C$4)/(1+C$4)^5)+(((Sector_KPIs!G19-Sector_KPIs!F26*C$4)*(1+$A8)/(C$4-$A8))/(1+C$4)^5)) -> 71994.921 | D8: =IF(D$4<=$A8,"N/M",Historical!C8+((Sector_KPIs!C19-Historical!C8*D$4)/(1+D$4)^1)+((Sector_KPIs!D19-Sector_KPIs!C26*D$4)/(1+D$4)^2)+((Sector_KPIs!E19-Sector_KPIs!D26*D$4)/(1+D$4)^3)+((Sector_KPIs!F19-Sector_KPIs!E26*D$4)/(1+D$4)^4)+((Sector_KPIs!G19-Sector_KPIs!F26*D$4)/(1+D$4)^5)+(((Sector_KPIs!G19-Sector_KPIs!F26*D$4)*(1+$A8)/(D$4-$A8))/(1+D$4)^5)) -> 61376.639 | E8: =IF(E$4<=$A8,"N/M",Historical!C8+((Sector_KPIs!C19-Historical!C8*E$4)/(1+E$4)^1)+((Sector_KPIs!D19-Sector_KPIs!C26*E$4)/(1+E$4)^2)+((Sector_KPIs!E19-Sector_KPIs!D26*E$4)/(1+E$4)^3)+((Sector_KPIs!F19-Sector_KPIs!E26*E$4)/(1+E$4)^4)+((Sector_KPIs!G19-Sector_KPIs!F26*E$4)/(1+E$4)^5)+(((Sector_KPIs!G19-Sector_KPIs!F26*E$4)*(1+$A8)/(E$4-$A8))/(1+E$4)^5)) -> 53425.57 | F8: =IF(F$4<=$A8,"N/M",Historical!C8+((Sector_KPIs!C19-Historical!C8*F$4)/(1+F$4)^1)+((Sector_KPIs!D19-Sector_KPIs!C26*F$4)/(1+F$4)^2)+((Sector_KPIs!E19-Sector_KPIs!D26*F$4)/(1+F$4)^3)+((Sector_KPIs!F19-Sector_KPIs!E26*F$4)/(1+F$4)^4)+((Sector_KPIs!G19-Sector_KPIs!F26*F$4)/(1+F$4)^5)+(((Sector_KPIs!G19-Sector_KPIs!F26*F$4)*(1+$A8)/(F$4-$A8))/(1+F$4)^5)) -> 47252.065
A9: 0.07 | B9: =IF(B$4<=$A9,"N/M",Historical!C8+((Sector_KPIs!C19-Historical!C8*B$4)/(1+B$4)^1)+((Sector_KPIs!D19-Sector_KPIs!C26*B$4)/(1+B$4)^2)+((Sector_KPIs!E19-Sector_KPIs!D26*B$4)/(1+B$4)^3)+((Sector_KPIs!F19-Sector_KPIs!E26*B$4)/(1+B$4)^4)+((Sector_KPIs!G19-Sector_KPIs!F26*B$4)/(1+B$4)^5)+(((Sector_KPIs!G19-Sector_KPIs!F26*B$4)*(1+$A9)/(B$4-$A9))/(1+B$4)^5)) -> 95801.145 | C9: =IF(C$4<=$A9,"N/M",Historical!C8+((Sector_KPIs!C19-Historical!C8*C$4)/(1+C$4)^1)+((Sector_KPIs!D19-Sector_KPIs!C26*C$4)/(1+C$4)^2)+((Sector_KPIs!E19-Sector_KPIs!D26*C$4)/(1+C$4)^3)+((Sector_KPIs!F19-Sector_KPIs!E26*C$4)/(1+C$4)^4)+((Sector_KPIs!G19-Sector_KPIs!F26*C$4)/(1+C$4)^5)+(((Sector_KPIs!G19-Sector_KPIs!F26*C$4)*(1+$A9)/(C$4-$A9))/(1+C$4)^5)) -> 76480.333 | D9: =IF(D$4<=$A9,"N/M",Historical!C8+((Sector_KPIs!C19-Historical!C8*D$4)/(1+D$4)^1)+((Sector_KPIs!D19-Sector_KPIs!C26*D$4)/(1+D$4)^2)+((Sector_KPIs!E19-Sector_KPIs!D26*D$4)/(1+D$4)^3)+((Sector_KPIs!F19-Sector_KPIs!E26*D$4)/(1+D$4)^4)+((Sector_KPIs!G19-Sector_KPIs!F26*D$4)/(1+D$4)^5)+(((Sector_KPIs!G19-Sector_KPIs!F26*D$4)*(1+$A9)/(D$4-$A9))/(1+D$4)^5)) -> 63606.062 | E9: =IF(E$4<=$A9,"N/M",Historical!C8+((Sector_KPIs!C19-Historical!C8*E$4)/(1+E$4)^1)+((Sector_KPIs!D19-Sector_KPIs!C26*E$4)/(1+E$4)^2)+((Sector_KPIs!E19-Sector_KPIs!D26*E$4)/(1+E$4)^3)+((Sector_KPIs!F19-Sector_KPIs!E26*E$4)/(1+E$4)^4)+((Sector_KPIs!G19-Sector_KPIs!F26*E$4)/(1+E$4)^5)+(((Sector_KPIs!G19-Sector_KPIs!F26*E$4)*(1+$A9)/(E$4-$A9))/(1+E$4)^5)) -> 54415.242 | F9: =IF(F$4<=$A9,"N/M",Historical!C8+((Sector_KPIs!C19-Historical!C8*F$4)/(1+F$4)^1)+((Sector_KPIs!D19-Sector_KPIs!C26*F$4)/(1+F$4)^2)+((Sector_KPIs!E19-Sector_KPIs!D26*F$4)/(1+F$4)^3)+((Sector_KPIs!F19-Sector_KPIs!E26*F$4)/(1+F$4)^4)+((Sector_KPIs!G19-Sector_KPIs!F26*F$4)/(1+F$4)^5)+(((Sector_KPIs!G19-Sector_KPIs!F26*F$4)*(1+$A9)/(F$4-$A9))/(1+F$4)^5)) -> 47526.34
A11: Active-case reconstruction | B11: Value | C11: Valuation output | D11: Difference | E11: Tolerance | F11: Status
A12: Dynamic RI sensitivity reconstruction | B12: =Historical!C8+((Sector_KPIs!C19-Historical!C8*Assumptions!E16)/(1+Assumptions!E16)^1)+((Sector_KPIs!D19-Sector_KPIs!C26*Assumptions!E16)/(1+Assumptions!E16)^2)+((Sector_KPIs!E19-Sector_KPIs!D26*Assumptions!E16)/(1+Assumptions!E16)^3)+((Sector_KPIs!F19-Sector_KPIs!E26*Assumptions!E16)/(1+Assumptions!E16)^4)+((Sector_KPIs!G19-Sector_KPIs!F26*Assumptions!E16)/(1+Assumptions!E16)^5)+(((Sector_KPIs!G19-Sector_KPIs!F26*Assumptions!E16)*(1+Assumptions!E17)/(Assumptions!E16-Assumptions!E17))/(1+Assumptions!E16)^5) -> 59704.572 | C12: =Valuation!G23 -> 59704.572 | D12: =B12-C12 -> 0 | E12: 0.1 | F12: =IF(ABS(D12)<=E12,"PASS","FAIL") -> PASS
A14: Central Base case is CoE 13.0% / g 5.0%. Bull/Bear selector tests also change loans, NII, net income and the valuation output. The active-case reconstruction remains exact under all three cases. | B14: Central Base case is CoE 13.0% / g 5.0%. Bull/Bear selector tests also change loans, NII, net income and the valuation output. The active-case reconstruction remains exact under all three cases. | C14: Central Base case is CoE 13.0% / g 5.0%. Bull/Bear selector tests also change loans, NII, net income and the valuation output. The active-case reconstruction remains exact under all three cases. | D14: Central Base case is CoE 13.0% / g 5.0%. Bull/Bear selector tests also change loans, NII, net income and the valuation output. The active-case reconstruction remains exact under all three cases. | E14: Central Base case is CoE 13.0% / g 5.0%. Bull/Bear selector tests also change loans, NII, net income and the valuation output. The active-case reconstruction remains exact under all three cases. | F14: Central Base case is CoE 13.0% / g 5.0%. Bull/Bear selector tests also change loans, NII, net income and the valuation output. The active-case reconstruction remains exact under all three cases.
A15: Central Base case is CoE 13.0% / g 5.0%. Bull/Bear selector tests also change loans, NII, net income and the valuation output. The active-case reconstruction remains exact under all three cases. | B15: Central Base case is CoE 13.0% / g 5.0%. Bull/Bear selector tests also change loans, NII, net income and the valuation output. The active-case reconstruction remains exact under all three cases. | C15: Central Base case is CoE 13.0% / g 5.0%. Bull/Bear selector tests also change loans, NII, net income and the valuation output. The active-case reconstruction remains exact under all three cases. | D15: Central Base case is CoE 13.0% / g 5.0%. Bull/Bear selector tests also change loans, NII, net income and the valuation output. The active-case reconstruction remains exact under all three cases. | E15: Central Base case is CoE 13.0% / g 5.0%. Bull/Bear selector tests also change loans, NII, net income and the valuation output. The active-case reconstruction remains exact under all three cases. | F15: Central Base case is CoE 13.0% / g 5.0%. Bull/Bear selector tests also change loans, NII, net income and the valuation output. The active-case reconstruction remains exact under all three cases.

Sheet Checks
A1: Formula-driven model checks | B1: Formula-driven model checks | C1: Formula-driven model checks | D1: Formula-driven model checks | E1: Formula-driven model checks | F1: Formula-driven model checks | G1: Formula-driven model checks | H1: Formula-driven model checks
A2: Each assertion exposes Actual, Expected, Difference, Tolerance, Status and a fix location. Overall status aggregates component checks. | B2: Each assertion exposes Actual, Expected, Difference, Tolerance, Status and a fix location. Overall status aggregates component checks. | C2: Each assertion exposes Actual, Expected, Difference, Tolerance, Status and a fix location. Overall status aggregates component checks. | D2: Each assertion exposes Actual, Expected, Difference, Tolerance, Status and a fix location. Overall status aggregates component checks. | E2: Each assertion exposes Actual, Expected, Difference, Tolerance, Status and a fix location. Overall status aggregates component checks. | F2: Each assertion exposes Actual, Expected, Difference, Tolerance, Status and a fix location. Overall status aggregates component checks. | G2: Each assertion exposes Actual, Expected, Difference, Tolerance, Status and a fix location. Overall status aggregates component checks. | H2: Each assertion exposes Actual, Expected, Difference, Tolerance, Status and a fix location. Overall status aggregates component checks.
A4: Check | B4: Actual | C4: Expected | D4: Difference | E4: Tolerance | F4: Status | G4: Severity | H4: Location / fix hint
A5: Source ledger completeness | B5: =Sources!O28 -> 23 | C5: 23 | D5: =B5-C5 -> 0 | E5: 0 | F5: =IF(ABS(D5)<=E5,"PASS","FAIL") -> PASS | G5: Critical | H5: Sources!A4:P28; populate every mandatory field
A6: Gross loans do not exceed total assets | B6: =Historical!C6 -> 285207.4 | C6: =Historical!C5 -> 384657.72 | D6: =C6-B6 -> 99450.32 | E6: 0 | F6: =IF(D6>=E6,"PASS","FAIL") -> PASS | G6: Critical | H6: Historical!C5:C6; verify source units and perimeter
A7: Loan growth formula | B7: =Sector_KPIs!C6 -> 0.06 | C7: =Assumptions!E6 -> 0.06 | D7: =B7-C7 -> 0 | E7: 1e-06 | F7: =IF(ABS(D7)<=E7,"PASS","FAIL") -> PASS | G7: Critical | H7: Sector_KPIs!C5:C6 / Assumptions!E6
A8: Net interest income mechanics | B8: =Sector_KPIs!C11 -> 18213.344 | C8: =Sector_KPIs!C9*Sector_KPIs!C10 -> 18213.344 | D8: =B8-C8 -> 0 | E8: 0.1 | F8: =IF(ABS(D8)<=E8,"PASS","FAIL") -> PASS | G8: Critical | H8: Sector_KPIs!C9:C11
A9: Equity roll-forward | B9: =Sector_KPIs!C26 -> 46747.66 | C9: =Sector_KPIs!B26+Sector_KPIs!C19-Sector_KPIs!C25 -> 46747.66 | D9: =B9-C9 -> 0 | E9: 0.1 | F9: =IF(ABS(D9)<=E9,"PASS","FAIL") -> PASS | G9: Critical | H9: Sector_KPIs!B19:C26
A10: Core solvency above floor | B10: =Sector_KPIs!C28 -> 0.12506564 | C10: =Sector_KPIs!C23 -> 0.115 | D10: =B10-C10 -> 0.010065641 | E10: 0 | F10: =IF(D10>=E10,"PASS","FAIL") -> PASS | G10: Critical | H10: Sector_KPIs!C21:C28 / payout constraint
A11: CoE exceeds terminal growth | B11: =Assumptions!E16 -> 0.13 | C11: =Assumptions!E17 -> 0.05 | D11: =B11-C11 -> 0.08 | E11: 0.01 | F11: =IF(D11>E11,"PASS","FAIL") -> PASS | G11: Critical | H11: Assumptions!E16:E17
A12: Dynamic sensitivity ties valuation | B12: =Sensitivity!B12 -> 59704.572 | C12: =Sensitivity!C12 -> 59704.572 | D12: =B12-C12 -> 0 | E12: =Sensitivity!E12 -> 0.1 | F12: =IF(ABS(D12)<=E12,"PASS","FAIL") -> PASS | G12: Critical | H12: Sensitivity!A11:F12 / Valuation!G23
A13: Scenario selector valid | B13: =Assumptions!B3 -> 1 | C13: 1 | D13: =IF(OR(B13=1,B13=2,B13=3),0,1) -> 0 | E13: 0 | F13: =IF(D13=E13,"PASS","FAIL") -> PASS | G13: Critical | H13: Assumptions!B3; return to Base = 1
A14: No capital-forced negative dividend | B14: =MIN(Sector_KPIs!C25:G25) -> 3654.9152 | C14: 0 | D14: =B14-C14 -> 3654.9152 | E14: 0 | F14: =IF(D14>=E14,"PASS","FAIL") -> PASS | G14: Critical | H14: Sector_KPIs!C24:G25
A15: Overall model status | B15: =IF(COUNTIF(F5:F14,"PASS")=10,"PASS","FAIL") -> PASS | H15: All critical checks must pass

Sheet Sector_KPIs
A1: Bank drivers, credit, capital and payout schedule | B1: Bank drivers, credit, capital and payout schedule | C1: Bank drivers, credit, capital and payout schedule | D1: Bank drivers, credit, capital and payout schedule | E1: Bank drivers, credit, capital and payout schedule | F1: Bank drivers, credit, capital and payout schedule | G1: Bank drivers, credit, capital and payout schedule | H1: Bank drivers, credit, capital and payout schedule
A2: 2025A sourced anchor; 2026E–2030E formula-driven. Deposits remain operating funding. Dividends are constrained by the visible capital floor. | B2: 2025A sourced anchor; 2026E–2030E formula-driven. Deposits remain operating funding. Dividends are constrained by the visible capital floor. | C2: 2025A sourced anchor; 2026E–2030E formula-driven. Deposits remain operating funding. Dividends are constrained by the visible capital floor. | D2: 2025A sourced anchor; 2026E–2030E formula-driven. Deposits remain operating funding. Dividends are constrained by the visible capital floor. | E2: 2025A sourced anchor; 2026E–2030E formula-driven. Deposits remain operating funding. Dividends are constrained by the visible capital floor. | F2: 2025A sourced anchor; 2026E–2030E formula-driven. Deposits remain operating funding. Dividends are constrained by the visible capital floor. | G2: 2025A sourced anchor; 2026E–2030E formula-driven. Deposits remain operating funding. Dividends are constrained by the visible capital floor. | H2: 2025A sourced anchor; 2026E–2030E formula-driven. Deposits remain operating funding. Dividends are constrained by the visible capital floor.
A4: Metric | B4: 2025A | C4: 2026E | D4: 2027E | E4: 2028E | F4: 2029E | G4: 2030E | H4: Unit / note
A5: Gross loans | B5: =Historical!C6 -> 285207.4 | C5: =B5*(1+Assumptions!$E$6) -> 302319.84 | D5: =C5*(1+Assumptions!$E$6) -> 320459.03 | E5: =D5*(1+Assumptions!$E$6) -> 339686.57 | F5: =E5*(1+Assumptions!$E$6) -> 360067.77 | G5: =F5*(1+Assumptions!$E$6) -> 381671.83 | H5: COP bn
A6: Loan growth | B6: =(B5-Historical!B6)/Historical!B6 -> 0.020588333 | C6: =C5/B5-1 -> 0.06 | D6: =D5/C5-1 -> 0.06 | E6: =E5/D5-1 -> 0.06 | F6: =F5/E5-1 -> 0.06 | G6: =G5/F5-1 -> 0.06 | H6: %
A7: Customer deposits | B7: =Historical!C7 -> 291707.47 | C7: =B7*(1+Assumptions!$E$7) -> 312127 | D7: =C7*(1+Assumptions!$E$7) -> 333975.89 | E7: =D7*(1+Assumptions!$E$7) -> 357354.2 | F7: =E7*(1+Assumptions!$E$7) -> 382368.99 | G7: =F7*(1+Assumptions!$E$7) -> 409134.82 | H7: COP bn
A8: Deposit growth | B8: =(B7-Historical!B7)/Historical!B7 -> 0.045323945 | C8: =C7/B7-1 -> 0.07 | D8: =D7/C7-1 -> 0.07 | E8: =E7/D7-1 -> 0.07 | F8: =F7/E7-1 -> 0.07 | G8: =G7/F7-1 -> 0.07 | H8: %
A9: Average loans | B9: =B5 -> 285207.4 | C9: =AVERAGE(B5,C5) -> 293763.62 | D9: =AVERAGE(C5,D5) -> 311389.44 | E9: =AVERAGE(D5,E5) -> 330072.8 | F9: =AVERAGE(E5,F5) -> 349877.17 | G9: =AVERAGE(F5,G5) -> 370869.8 | H9: COP bn
A10: Net interest margin | B10: =Historical!C11 -> 0.0616 | C10: =Assumptions!$E$8 -> 0.062 | D10: =Assumptions!$E$8 -> 0.062 | E10: =Assumptions!$E$8 -> 0.062 | F10: =Assumptions!$E$8 -> 0.062 | G10: =Assumptions!$E$8 -> 0.062 | H10: %
A11: Net interest income | B11: =B9*B10 -> 17568.776 | C11: =C9*C10 -> 18213.344 | D11: =D9*D10 -> 19306.145 | E11: =E9*E10 -> 20464.514 | F11: =F9*F10 -> 21692.385 | G11: =G9*G10 -> 22993.928 | H11: COP bn
A12: Cost of risk | B12: =Historical!C12 -> 0.0159 | C12: =Assumptions!$E$9 -> 0.017 | D12: =Assumptions!$E$9 -> 0.017 | E12: =Assumptions!$E$9 -> 0.017 | F12: =Assumptions!$E$9 -> 0.017 | G12: =Assumptions!$E$9 -> 0.017 | H12: %
A13: Credit provisions | B13: =B9*B12 -> 4534.7976 | C13: =C9*C12 -> 4993.9815 | D13: =D9*D12 -> 5293.6204 | E13: =E9*E12 -> 5611.2377 | F13: =F9*F12 -> 5947.9119 | G13: =G9*G12 -> 6304.7866 | H13: COP bn
A14: Average assets | B14: =Historical!C5 -> 384657.72 | C14: =AVERAGE(B32,C32) -> 396678.27 | D14: =AVERAGE(C32,D32) -> 421470.66 | E14: =AVERAGE(D32,E32) -> 447812.58 | F14: =AVERAGE(E32,F32) -> 475800.87 | G14: =AVERAGE(F32,G32) -> 505538.42 | H14: COP bn
A15: Fee + other income | C15: =C14*Assumptions!$E$10 -> 10710.313 | D15: =D14*Assumptions!$E$10 -> 11379.708 | E15: =E14*Assumptions!$E$10 -> 12090.94 | F15: =F14*Assumptions!$E$10 -> 12846.623 | G15: =G14*Assumptions!$E$10 -> 13649.537 | H15: COP bn
A16: Operating expense | C16: =C14*Assumptions!$E$11 -> 13487.061 | D16: =D14*Assumptions!$E$11 -> 14330.003 | E16: =E14*Assumptions!$E$11 -> 15225.628 | F16: =F14*Assumptions!$E$11 -> 16177.229 | G16: =G14*Assumptions!$E$11 -> 17188.306 | H16: COP bn
A17: Pre-tax income | C17: =C11+C15-C13-C16 -> 10442.615 | D17: =D11+D15-D13-D16 -> 11062.23 | E17: =E11+E15-E13-E16 -> 11718.588 | F17: =F11+F15-F13-F16 -> 12413.867 | G17: =G11+G15-G13-G16 -> 13150.372 | H17: COP bn
A18: Taxes | C18: =MAX(0,C17*Assumptions!$E$12) -> 3132.7845 | D18: =MAX(0,D17*Assumptions!$E$12) -> 3318.669 | E18: =MAX(0,E17*Assumptions!$E$12) -> 3515.5764 | F18: =MAX(0,F17*Assumptions!$E$12) -> 3724.16 | G18: =MAX(0,G17*Assumptions!$E$12) -> 3945.1116 | H18: COP bn
A19: Net income | B19: =Historical!C9 -> 7276.23 | C19: =C17-C18 -> 7309.8305 | D19: =D17-D18 -> 7743.561 | E19: =E17-E18 -> 8203.0117 | F19: =F17-F18 -> 8689.7067 | G19: =G17-G18 -> 9205.2605 | H19: COP bn
A20: Dividend payout target | B20: =Assumptions!E13 -> 0.5 | C20: =Assumptions!$E$13 -> 0.5 | D20: =Assumptions!$E$13 -> 0.5 | E20: =Assumptions!$E$13 -> 0.5 | F20: =Assumptions!$E$13 -> 0.5 | G20: =Assumptions!$E$13 -> 0.5 | H20: %
A21: Core capital eligible factor | B21: =Assumptions!E14 -> 0.683 | C21: =Assumptions!$E$14 -> 0.683 | D21: =Assumptions!$E$14 -> 0.683 | E21: =Assumptions!$E$14 -> 0.683 | F21: =Assumptions!$E$14 -> 0.683 | G21: =Assumptions!$E$14 -> 0.683 | H21: % of parent equity
A22: Capital requirement denominator | B22: =Historical!C18 -> 240844.48 | C22: =B22*(1+C6) -> 255295.15 | D22: =C22*(1+D6) -> 270612.86 | E22: =D22*(1+E6) -> 286849.63 | F22: =E22*(1+F6) -> 304060.61 | G22: =F22*(1+G6) -> 322304.25 | H22: COP bn
A23: Minimum core solvency | B23: =Assumptions!E15 -> 0.115 | C23: =Assumptions!$E$15 -> 0.115 | D23: =Assumptions!$E$15 -> 0.115 | E23: =Assumptions!$E$15 -> 0.115 | F23: =Assumptions!$E$15 -> 0.115 | G23: =Assumptions!$E$15 -> 0.115 | H23: %
A24: Maximum dividends allowed | C24: =MAX(0,B26+C19-C23*C22/C21) -> 7417.3007 | D24: =MAX(0,C26+D19-D23*D22/D21) -> 8926.83 | E24: =MAX(0,D26+E19-E23*E22/E21) -> 10524.198 | F24: =MAX(0,E26+F19-F23*F22/F21) -> 12214.503 | G24: =MAX(0,F26+G19-G23*G22/G21) -> 14003.141 | H24: COP bn
A25: Dividends | C25: =MIN(C19*C20,C24) -> 3654.9152 | D25: =MIN(D19*D20,D24) -> 3871.7805 | E25: =MIN(E19*E20,E24) -> 4101.5058 | F25: =MIN(F19*F20,F24) -> 4344.8533 | G25: =MIN(G19*G20,G24) -> 4602.6302 | H25: COP bn
A26: Ending parent equity | B26: =Historical!C8 -> 43092.745 | C26: =B26+C19-C25 -> 46747.66 | D26: =C26+D19-D25 -> 50619.441 | E26: =D26+E19-E25 -> 54720.947 | F26: =E26+F19-F25 -> 59065.8 | G26: =F26+G19-G25 -> 63668.43 | H26: COP bn
A27: Core eligible capital | B27: =Historical!C17 -> 29431.196 | C27: =C26*C21 -> 31928.652 | D27: =D26*D21 -> 34573.078 | E27: =E26*E21 -> 37374.407 | F27: =F26*F21 -> 40341.941 | G27: =G26*G21 -> 43485.538 | H27: COP bn
A28: Core solvency | B28: =Historical!C15 -> 0.1222 | C28: =C27/C22 -> 0.12506564 | D28: =D27/D22 -> 0.12775844 | E28: =E27/E22 -> 0.13029268 | F28: =F27/F22 -> 0.1326773 | G28: =G27/G22 -> 0.13492077 | H28: %
A29: ROE | B29: =B15/B22 -> 0 | C29: =C19/AVERAGE(B26,C26) -> 0.16272924 | D29: =D19/AVERAGE(C26,D26) -> 0.15905909 | E29: =E19/AVERAGE(D26,E26) -> 0.15574296 | F29: =F19/AVERAGE(E26,F26) -> 0.15273671 | G29: =G19/AVERAGE(F26,G26) -> 0.15000315 | H29: %
A30: 30-day PDL ratio | B30: =Historical!C13 -> 0.0357 | C30: =Assumptions!$E$20 -> 0.034 | D30: =Assumptions!$E$20 -> 0.034 | E30: =Assumptions!$E$20 -> 0.034 | F30: =Assumptions!$E$20 -> 0.034 | G30: =Assumptions!$E$20 -> 0.034 | H30: %
A31: 30-day PDL coverage | B31: =Historical!C14 -> 1.3441 | C31: =Assumptions!$E$21 -> 1.35 | D31: =Assumptions!$E$21 -> 1.35 | E31: =Assumptions!$E$21 -> 1.35 | F31: =Assumptions!$E$21 -> 1.35 | G31: =Assumptions!$E$21 -> 1.35 | H31: %
A32: Total assets | B32: =Historical!C5 -> 384657.72 | C32: =B32*(1+(Assumptions!$E$6*Assumptions!$E$19+Assumptions!$E$7*(1-Assumptions!$E$19))) -> 408698.83 | D32: =C32*(1+(Assumptions!$E$6*Assumptions!$E$19+Assumptions!$E$7*(1-Assumptions!$E$19))) -> 434242.5 | E32: =D32*(1+(Assumptions!$E$6*Assumptions!$E$19+Assumptions!$E$7*(1-Assumptions!$E$19))) -> 461382.66 | F32: =E32*(1+(Assumptions!$E$6*Assumptions!$E$19+Assumptions!$E$7*(1-Assumptions!$E$19))) -> 490219.07 | G32: =F32*(1+(Assumptions!$E$6*Assumptions!$E$19+Assumptions!$E$7*(1-Assumptions!$E$19))) -> 520857.77 | H32: COP bn

Sheet Change_Log
A1: Change log and governance | B1: Change log and governance | C1: Change log and governance | D1: Change log and governance | E1: Change log and governance | F1: Change log and governance
A2: Controlled upgrade record. The original workbook remains untouched. | B2: Controlled upgrade record. The original workbook remains untouched. | C2: Controlled upgrade record. The original workbook remains untouched. | D2: Controlled upgrade record. The original workbook remains untouched. | E2: Controlled upgrade record. The original workbook remains untouched. | F2: Controlled upgrade record. The original workbook remains untouched.
A4: Date | B4: Version | C4: Author / lane | D4: Change | E4: Evidence | F4: Reviewer status
A5: 2026-07-16 | B5: 2.0 | C5: Codex / financial cluster | D5: Replaced broad source anchors with claim-level SEC ledger | E5: Sources!A4:P28 | F5: Owner verified; independent pending
A6: 2026-07-16 | B6: 2.0 | C6: Codex / financial cluster | D6: Removed current-FX normalization; retained COP historical facts | E6: Historical!A1:H19 | F6: Owner verified
A7: 2026-07-16 | B7: 2.0 | C7: Codex / financial cluster | D7: Added bank-specific loans, deposits, NIM, CoR, credit, capital and payout mechanics | E7: Sector_KPIs!A1:H32 | F7: Owner verified
A8: 2026-07-16 | B8: 2.0 | C8: Codex / financial cluster | D8: Added residual-income and DDM valuation plus dynamic sensitivity | E8: Valuation!A1:G31; Sensitivity!A1:F15 | F8: Owner verified
A9: 2026-07-16 | B9: 2.0 | C9: Codex / financial cluster | D9: Replaced hardcoded PASS with formula-driven checks | E9: Checks!A4:H15 | F9: Owner verified
A10: 2026-07-16 | B10: 2.0 | C10: Codex / financial cluster | D10: Added 9/10 evidence gate and explicit predecessor/perimeter governance | E10: Gate_9of10!A1:H20 | F10: Independent review pending
A12: Review-note disposition: the prior PASS label was rejected as non-evidentiary. Known prior defects (generic sources, hardcoded source coverage, blank bank KPI schedule, current-FX history, generic valuation mechanics) are explicitly replaced rather than hidden. | B12: Review-note disposition: the prior PASS label was rejected as non-evidentiary. Known prior defects (generic sources, hardcoded source coverage, blank bank KPI schedule, current-FX history, generic valuation mechanics) are explicitly replaced rather than hidden. | C12: Review-note disposition: the prior PASS label was rejected as non-evidentiary. Known prior defects (generic sources, hardcoded source coverage, blank bank KPI schedule, current-FX history, generic valuation mechanics) are explicitly replaced rather than hidden. | D12: Review-note disposition: the prior PASS label was rejected as non-evidentiary. Known prior defects (generic sources, hardcoded source coverage, blank bank KPI schedule, current-FX history, generic valuation mechanics) are explicitly replaced rather than hidden. | E12: Review-note disposition: the prior PASS label was rejected as non-evidentiary. Known prior defects (generic sources, hardcoded source coverage, blank bank KPI schedule, current-FX history, generic valuation mechanics) are explicitly replaced rather than hidden. | F12: Review-note disposition: the prior PASS label was rejected as non-evidentiary. Known prior defects (generic sources, hardcoded source coverage, blank bank KPI schedule, current-FX history, generic valuation mechanics) are explicitly replaced rather than hidden.
A13: Review-note disposition: the prior PASS label was rejected as non-evidentiary. Known prior defects (generic sources, hardcoded source coverage, blank bank KPI schedule, current-FX history, generic valuation mechanics) are explicitly replaced rather than hidden. | B13: Review-note disposition: the prior PASS label was rejected as non-evidentiary. Known prior defects (generic sources, hardcoded source coverage, blank bank KPI schedule, current-FX history, generic valuation mechanics) are explicitly replaced rather than hidden. | C13: Review-note disposition: the prior PASS label was rejected as non-evidentiary. Known prior defects (generic sources, hardcoded source coverage, blank bank KPI schedule, current-FX history, generic valuation mechanics) are explicitly replaced rather than hidden. | D13: Review-note disposition: the prior PASS label was rejected as non-evidentiary. Known prior defects (generic sources, hardcoded source coverage, blank bank KPI schedule, current-FX history, generic valuation mechanics) are explicitly replaced rather than hidden. | E13: Review-note disposition: the prior PASS label was rejected as non-evidentiary. Known prior defects (generic sources, hardcoded source coverage, blank bank KPI schedule, current-FX history, generic valuation mechanics) are explicitly replaced rather than hidden. | F13: Review-note disposition: the prior PASS label was rejected as non-evidentiary. Known prior defects (generic sources, hardcoded source coverage, blank bank KPI schedule, current-FX history, generic valuation mechanics) are explicitly replaced rather than hidden.
A14: 46224 | B14: v2 IG | C14: Ola 2 elevation: added IS_Hist/BS_Hist/CF_Hist/SCE_Hist (FY2021A-FY2025A, COP mm; full detail FY23-25 from 20-F FY2025 R-files, verified-safe companyfacts tags for FY21-22, gaps disclosed not fabricated), USD_Layer (documented Banrep/filer-tagged FX), Checks_TieOut (tie-outs + 1 disclosed reconciling item: Banistmo held-for-sale cash reclass), Sources_Audited, Forecast (5yr driver-built Base/Bull/Bear off FY2025A continuing ops). Gate_9of10 and legacy scaffold sheets left in place but superseded. Root untouched. Built via Mog SDK only. | D14: Claude (run 24e4a1f1)

Sheet Gate_9of10
A1: Owner 9/10 evidence gate | B1: Owner 9/10 evidence gate | C1: Owner 9/10 evidence gate | D1: Owner 9/10 evidence gate | E1: Owner 9/10 evidence gate | F1: Owner 9/10 evidence gate | G1: Owner 9/10 evidence gate | H1: Owner 9/10 evidence gate
A2: Owner evidence submission only. Independent certification must reproduce every hard gate from the controlled workbook and QA artifacts. | B2: Owner evidence submission only. Independent certification must reproduce every hard gate from the controlled workbook and QA artifacts. | C2: Owner evidence submission only. Independent certification must reproduce every hard gate from the controlled workbook and QA artifacts. | D2: Owner evidence submission only. Independent certification must reproduce every hard gate from the controlled workbook and QA artifacts. | E2: Owner evidence submission only. Independent certification must reproduce every hard gate from the controlled workbook and QA artifacts. | F2: Owner evidence submission only. Independent certification must reproduce every hard gate from the controlled workbook and QA artifacts. | G2: Owner evidence submission only. Independent certification must reproduce every hard gate from the controlled workbook and QA artifacts. | H2: Owner evidence submission only. Independent certification must reproduce every hard gate from the controlled workbook and QA artifacts.
A4: Gate | B4: Weight | C4: Owner status | D4: Blocker class | E4: Exact workbook evidence | F4: External evidence pointer | G4: Reviewer note | H4: Score
A5: H0 Controlled lineage / OOXML | B5: 5 | C5: PASS | D5: None | E5: 00_Cover!A18:B20; Change_Log!A4:F10 | F5: internal QA evidence (not published) | G5: Original and controlled hashes recorded after export | H5: 5
A6: H1 Source fidelity / provenance | B6: 20 | C6: PASS | D6: None | E6: Sources!A4:P28; Historical!A4:H19 | F6: Official SEC URLs in Sources!L5:L27 | G6: 23 claim-level rows including explicit NI/EPS share-count derivation; no current-FX history | H6: 20
A7: H2 Formula and schedule mechanics | B7: 15 | C7: PASS | D7: None | E7: Sector_KPIs!A4:H32; Forecast!A4:H16 | F7: internal QA evidence (not published) | G7: Bank drivers and capital/payout schedule | H7: 15
A8: H3 Scenarios / sensitivity | B8: 10 | C8: PASS | D8: None | E8: Assumptions!A3:F21; Sensitivity!A4:F12 | F8: Perturb-reset log in evidence JSON | G8: Base/Bull/Bear changes loans, NII, NI, valuation | H8: 10
A9: H4 Valuation fit / mechanics | B9: 15 | C9: PASS | D9: None | E9: Valuation!A4:G31; Sensitivity!A4:F12 | F9: internal QA evidence (not published) | G9: Residual income primary; DDM cross-check | H9: 15
A10: H5 Checks / error state | B10: 8 | C10: PASS | D10: None | E10: Checks!A4:H15; Sources!O28:P28 | F10: Post-recalc error scan in evidence JSON | G10: Overall status formula-driven | H10: 8
A11: H6 Native recalculation | B11: 10 | C11: PASS | D11: None | E11: Gate_9of10!A17:H20 | F11: Native recalc log in evidence JSON | G11: LibreOffice native open/save/reopen completed after all source-lineage and visual repairs | H11: 10
A12: H7 Post-recalc visual QA | B12: 7 | C12: PASS | D12: None | E12: All user-facing sheets | F12: internal QA evidence (not published) | G12: All 11 user-facing sheets visually reviewed after native recalculation; final manifest regenerated after gate advancement | H12: 7
A13: H8 Material economic upgrade | B13: 5 | C13: PASS | D13: None | E13: Sector_KPIs!A4:H32; Valuation!A4:G31 | F13: Change_Log!A4:F10 | G13: Substantive bank mechanics replaced generic shell | H13: 5
A14: H9 Governance / handoff | B14: 5 | C14: PASS | D14: None | E14: 00_Cover!A4:B20; Change_Log!A4:F13 | F14: internal QA evidence (not published) | G14: Independent certification pending | H14: 5
A15: Owner score | H15: =SUM(H5:H14) -> 100
A16: Owner decision | C16: =IF(AND(H15>=90,COUNTIF(C5:C14,"PASS")=10),"SUBMITTED FOR INDEPENDENT 9/10 REVIEW","NOT READY") -> SUBMITTED FOR INDEPENDENT 9/10 REVIEW
A18: Native recalculation | B18: Engine | C18: Version | D18: Timestamp | E18: Reopen | F18: Post-recalc errors | G18: Visual manifest | H18: Status
A19: Native open/save/reopen and all-sheet QA completed | B19: LibreOfficeDev | C19: 26.8.0.0.alpha0 2c87e51eeaa2b413ff4ae097b2705eea1995d8e5 | D19: 46220.054 | E19: PASS | F19: 0 matched error tokens; all formula checks PASS | G19: internal QA evidence (not published) | H19: PASS

Sheet IS_Hist
A1: Grupo Cibest S.A. (Bancolombia) — Consolidated Statement of Income (audited, COP millions)
A2: FY2023-2025 full line detail: 20-F FY2025 (CIK 2058897, accn 0002058897-26-000125), R4.htm. FY2021-2022: legacy CIK 1071371 companyfacts.json, verified-safe XBRL tags only (see column note); blank = not independently verified to this presentation, not fabricated.
A4: Line item | B4: FY2021A | C4: FY2022A | D4: FY2023A | E4: FY2024A | F4: FY2025A | G4: Source
A5: Interest income
A6: Total interest income on loans and financial leases | D6: 32825553 | E6: 30330439 | F6: 29236002 | G6: R4
A7: Interest on debt instruments (effective interest method) | D7: 741684 | E7: 728238 | F7: 714677 | G7: R4
A8: Total interest on financial instruments (effective interest method) | D8: 33567237 | E8: 31058677 | F8: 29950679 | G8: R4
A9: Interest income on overnight and market funds | D9: 103145 | E9: 130126 | F9: 100741 | G9: R4
A10: Interest and valuation on financial instruments | D10: 549219 | E10: 1665513 | F10: 1436106 | G10: R4
A11: Total interest and valuation on financial instruments | D11: 34219601 | E11: 32854316 | F11: 31487526 | G11: R4
A12: Interest expenses | D12: -15430183 | E12: -13687660 | F12: -12061226 | G12: R4
A13: Net interest margin before impairment | D13: 18789418 | E13: 19166656 | F13: 19426300 | G13: R4
A14: Credit impairment charges on loans, advances and leases, net | D14: -7210390 | E14: -4964893 | F14: -4437432 | G14: R4
A15: Recovery/(impairment) for other financial instruments | D15: 19305 | E15: -30708 | F15: 7514 | G15: R4
A16: Total credit impairment charges, net | D16: -7191085 | E16: -4995601 | F16: -4429918 | G16: R4
A17: Net interest margin after impairment | D17: 11598333 | E17: 14171055 | F17: 14996382 | G17: R4
A19: Fees and commissions income | B19: 5293804 | C19: 6370526 | D19: 6547953 | E19: 7126512 | F19: 7928554 | G19: R4/CF-tag (validated: FY23 exact match)
A20: Fees and commissions expenses | B20: -1860683 | C20: -2590166 | D20: -2838383 | E20: -3225382 | F20: -3573610 | G20: R4/CF-tag (validated: FY23 exact match)
A21: Total fees and commissions, net | D21: 3709570 | E21: 3901130 | F21: 4354944 | G21: R4
A22: Other operating income | D22: 3942712 | E22: 2976110 | F22: 3572074 | G22: R4
A23: Dividends and net income on equity investments | D23: 196686 | E23: 93099 | F23: 693011 | G23: R4
A24: Total operating income, net | D24: 19447301 | E24: 21141394 | F24: 23616411 | G24: R4
A26: Operating expenses
A27: Salaries and employee benefits | D27: -4899283 | E27: -5224723 | F27: -5760122 | G27: R4
A28: Other administrative and general expenses | D28: -4614987 | E28: -5035023 | F28: -5599360 | G28: R4
A29: Taxes other than income tax | D29: -1393216 | E29: -1402064 | F29: -1481323 | G29: R4
A30: Depreciation, amortization, and impairment | D30: -1017144 | E30: -989336 | F30: -1016301 | G30: R4
A31: Total operating expenses | D31: -11924630 | E31: -12651146 | F31: -13857106 | G31: R4
A32: Profit continued operations before tax | D32: 7522671 | E32: 8490248 | F32: 9759305 | G32: R4
A33: Income tax continued operations | D33: -1820293 | E33: -2379852 | F33: -2810966 | G33: R4
A34: Net income continued operations | D34: 5702378 | E34: 6110396 | F34: 6948339 | G34: R4
A35: (Loss)/gain from discontinued operation, net | D35: 512593 | E35: 255185 | F35: -3006640 | G35: R4 (Banistmo, held-for-sale from 2025-12-18)
A36: Net income | B36: 4207787 | C36: 6996365 | D36: 6214971 | E36: 6365581 | F36: 3941699 | G36: ifrs-full:ProfitLoss (validated exact match all yrs)
A37: Net income attributable to equity holders of the Parent | B37: 4086795 | C37: 6783490 | D37: 6116936 | E37: 6267744 | F37: 3820634 | G37: ifrs-full:ProfitLossAttributableToOwnersOfParent (validated)
A38: Non-controlling interest | B38: 120992 | C38: 212875 | D38: 98035 | E38: 97837 | F38: 121065 | G38: ifrs-full:ProfitLossAttributableToNoncontrollingInterests (validated)
A40: Basic EPS to common shareholders (COP/share) | B40: 4309 | C40: 7113 | D40: 6420 | E40: 6576 | F40: 4045 | G40: ifrs-full:BasicEarningsLossPerShare (validated)
A41: Diluted EPS to common shareholders (COP/share) | B41: 4309 | C41: 7113 | D41: 6420 | E41: 6576 | F41: 4045 | G41: R4 (FY23-25); ifrs-full FY21-22

Sheet BS_Hist
A1: Grupo Cibest S.A. (Bancolombia) — Consolidated Statement of Financial Position (audited, COP millions, as of Dec 31)
A2: FY2024-2025: 20-F FY2025, R3.htm. FY2021-2023: legacy CIK 1071371 companyfacts.json tags, each individually cross-checked against the FY2024 R3 comparative (exact match) before use; failed/unavailable tags excluded and absorbed into an explicit plug row so shown totals still tie to audited Assets/Liabilities/Equity.
A4: Line item | B4: FY2021A | C4: FY2022A | D4: FY2023A | E4: FY2024A | F4: FY2025A | G4: Source
A5: Assets
A6: Cash and cash equivalents | B6: 25329846 | C6: 31645291 | D6: 39799609 | E6: 32844099 | F6: 29916400 | G6: ifrs-full:CashAndCashEquivalents / R3
A7: Financial assets investments | B7: 29289301 | C7: 27940140 | D7: 25674195 | E7: 37570270 | F7: 34317259 | G7: ifrs-full:FinancialAssets / R3
A8: Derivative financial instruments (assets) | B8: 2454005 | C8: 4961237 | D8: 6252270 | E8: 2938142 | F8: 4417863 | G8: ifrs-full:DerivativeFinancialAssets / R3
A9: Loans and advances to customers, net | C9: 254444099 | D9: 237728544 | E9: 263274170 | F9: 243100035 | G9: ifrs-full:LoansAndAdvancesToCustomers / R3
A10: Assets held for sale and inventories, net | E10: 1106399 | F10: 666361 | G10: R3 (not separately tagged FY21-23)
A11: Investment in associates and joint ventures | E11: 2928984 | F11: 3311506 | G11: R3 (companyfacts tag scope differs FY21-23, see note)
A12: Investment properties | B12: 3132220 | C12: 3994058 | D12: 4709911 | E12: 5580109 | F12: 6595407 | G12: ifrs-full:InvestmentProperty / R3
A13: Premises and equipment, net | B13: 5100652 | C13: 6727066 | D13: 6522534 | E13: 5906064 | F13: 5406874 | G13: ifrs-full:PropertyPlantAndEquipment / R3
A14: Right-of-use assets, lease | B14: 1695865 | C14: 1827108 | D14: 1634045 | E14: 1757206 | F14: 1329718 | G14: ifrs-full:RightofuseAssets / R3
A15: Goodwill and intangible assets, net | B15: 8628772 | C15: 10439192 | D15: 8489697 | E15: 9767903 | F15: 2537180 | G15: ifrs-full:Goodwill+IntangibleAssetsOtherThanGoodwill (sum validated) / R3
A16: Deferred tax, net | E16: 763757 | F16: 1750097 | G16: R3 (companyfacts DTA gross, pre IAS12 offset -- excluded FY21-23)
A17: Assets related to investments in subsidiaries held for sale | E17: 0 | F17: 40309257 | G17: R3 (Banistmo, 2025 only)
A18: Other assets, net | B18: 5751658 | C18: 6547866 | D18: 7528036 | E18: 7778279 | F18: 6094423 | G18: ifrs-full:OtherAssets / R3
A19: Unallocated other assets (plug to audited Total, FY21-23 only) | B19: 8472729 | C19: 4429434 | D19: 3589153 | G19: plug = Total Assets - sum(shown lines)
A20: TOTAL ASSETS | B20: 289855048 | C20: 352814733 | D20: 342928809 | E20: 372215382 | F20: 379752380 | G20: ifrs-full:Assets (validated exact match all yrs)
A22: Liabilities
A23: Deposits by customers | B23: 210390848 | C23: 250992323 | D23: 247941180 | E23: 279059401 | F23: 264413956 | G23: ifrs-full:DepositsFromCustomers / R3
A24: Interbank deposits, repos and other similar secured borrowing | E24: 1776965 | F24: 706149 | G24: R3 (companyfacts DepositsFromBanks scope differs, excl. repo -- excluded FY21-23)
A25: Derivative financial instruments (liabilities) | B25: 1961109 | C25: 4737454 | D25: 6710364 | E25: 2679643 | F25: 4514630 | G25: ifrs-full:DerivativeFinancialLiabilities / R3
A26: Borrowings from other financial institutions | B26: 8551558 | C26: 19692638 | D26: 15648606 | E26: 15689532 | F26: 9356428 | G26: ifrs-full:Borrowings (validated) / R3
A27: Debt instruments in issue | E27: 11275216 | F27: 7409693 | G27: R3 (no reliable companyfacts balance tag -- excluded FY21-23)
A28: Lease liabilities | B28: 1819077 | C28: 1900268 | D28: 1773610 | E28: 1889364 | F28: 1325039 | G28: ifrs-full:LeaseLiabilities / R3
A29: Preferred shares | E29: 584204 | F29: 583477 | G29: R3 (no companyfacts tag -- excluded FY21-23)
A30: Current tax | B30: 261653 | C30: 965180 | D30: 164339 | E30: 156162 | F30: 701452 | G30: ifrs-full:CurrentTaxLiabilities / R3
A31: Deferred tax, net | E31: 2578504 | F31: 2903375 | G31: R3 (companyfacts DTL gross, pre IAS12 offset -- excluded FY21-23)
A32: Employee benefit plans | E32: 951555 | F32: 947610 | G32: R3 (no companyfacts tag -- excluded FY21-23)
A33: Liabilities related to investments in subsidiaries held for sale | E33: 0 | F33: 34416684 | G33: R3 (Banistmo, 2025 only)
A34: Other liabilities | B34: 7762724 | C34: 11879211 | D34: 12648581 | E34: 10990561 | F34: 11478253 | G34: ifrs-full:OtherLiabilities / R3
A35: Unallocated other liabilities (plug to audited Total, FY21-23 only) | B35: 25182621 | C35: 23649108 | D35: 19993770 | G35: plug = Total Liabilities - sum(shown lines)
A36: TOTAL LIABILITIES | B36: 255929590 | C36: 312817182 | D36: 303879080 | E36: 327631107 | F36: 338756746 | G36: ifrs-full:Liabilities (validated exact match all yrs)
A38: Equity
A39: Share capital | B39: 480914 | C39: 480914 | D39: 480914 | E39: 480914 | F39: 480914 | G39: ifrs-full:IssuedCapital / R3
A40: Additional paid-in capital | B40: 4857454 | C40: 4857454 | D40: 4857454 | E40: 4857454 | F40: 4857491 | G40: ifrs-full:AdditionalPaidinCapital / R3
A41: Appropriated reserves | B41: 14661007 | C41: 15930665 | D41: 20044769 | E41: 22575837 | F41: 23436138 | G41: ifrs-full:StatutoryReserve / R3
A42: Retained earnings | B42: 3273788 | C42: 3278164 | D42: 2515278 | E42: 2715313 | F42: 3376023 | G42: ifrs-full:RetainedEarnings / R3
A43: Net income attributable to equity holders of the Parent | B43: 4086795 | C43: 6783490 | D43: 6116936 | E43: 6267744 | F43: 3820634 | G43: ifrs-full:ProfitLossAttributableToOwnersOfParent / R3
A44: Accumulated other comprehensive income, net of tax | B44: 4874389 | C44: 7758216 | D44: 4074161 | E44: 6645206 | F44: 3783433 | G44: ifrs-full:AccumulatedOtherComprehensiveIncome / R3
A45: SHAREHOLDERS' EQUITY ATTRIBUTABLE TO OWNERS OF PARENT | B45: 32234347 | C45: 39088903 | D45: 38089512 | E45: 43542468 | F45: 39754633 | G45: ifrs-full:EquityAttributableToOwnersOfParent (validated) / R3
A46: Non-controlling interest | B46: 1691111 | C46: 908648 | D46: 960217 | E46: 1041807 | F46: 1241001 | G46: ifrs-full:NoncontrollingInterests (validated) / R3
A47: TOTAL EQUITY | B47: 33925458 | C47: 39997551 | D47: 39049729 | E47: 44584275 | F47: 40995634 | G47: ifrs-full:Equity (validated exact match all yrs)
A48: TOTAL LIABILITIES AND EQUITY | B48: 289855048 | C48: 352814733 | D48: 342928809 | E48: 372215382 | F48: 379752380 | G48: Total liabilities + Total equity (audited totals)

Sheet CF_Hist
A1: Grupo Cibest S.A. (Bancolombia) — Consolidated Statement of Cash Flows (audited, COP millions)
A2: FY2023-2025 full detail: 20-F FY2025, R9.htm. FY2021-2022: legacy CIK 1071371 companyfacts.json CFO/CFI/CFF/FX summary tags -- validated: CFO+CFI+CFF reproduces ifrs-full:IncreaseDecreaseInCashAndCashEquivalents exactly; +FX reproduces the actual BS cash delta exactly both years (see Checks_TieOut and build log).
A4: Line item | B4: FY2021A | C4: FY2022A | D4: FY2023A | E4: FY2024A | F4: FY2025A | G4: Source
A5: Operating activities (detail FY23-25; summary total FY21-22)
A6: Net income | D6: 6214971 | E6: 6365581 | F6: 3941699 | G6: R9
A7: Depreciation and amortization | D7: 1082838 | E7: 1011455 | F7: 1055991 | G7: R9
A8: Credit impairment charges on loans and advances and leases | D8: 7461479 | E8: 5413652 | F8: 4620893 | G8: R9
A9: Net changes in investment securities at FVPL | D9: -1988166 | E9: -8401726 | F9: -3004255 | G9: R9
A10: Increase in loans and advances to customers | D10: -10554946 | E10: -21622099 | F10: -27306897 | G10: R9
A11: Increase in deposits by customers | D11: 17025357 | E11: 18329816 | F11: 27999206 | G11: R9
A12: Interest received | D12: 34702410 | E12: 33225177 | F12: 31802060 | G12: R9
A13: Interest paid | D13: -15978748 | E13: -14982367 | F13: -13299951 | G13: R9
A14: Income tax paid | D14: -2737511 | E14: -1954871 | F14: -2417279 | G14: R9
A15: Other operating adjustments and working-capital changes (net) | D15: -16074600 | E15: -16948723 | F15: -11132522 | G15: R9 (plug of remaining R9 operating lines)
A16: Net cash provided by operating activities | B16: 6095305 | C16: 6564226 | D16: 19153084 | E16: 435895 | F16: 12258945 | G16: R9 / ifrs-full:CashFlowsFromUsedInOperatingActivities
A18: Investing activities
A19: Net investing cash flow (detail FY23-25 below; total only FY21-22) | G19: R9
A20: Purchases/proceeds of debt & equity instruments (net) | D20: 2418578 | E20: 1271980 | F20: -192891 | G20: R9
A21: Purchases of premises, equipment and investment properties (net) | D21: -2226799 | E21: -1628064 | F21: -1748105 | G21: R9
A22: Purchase of other long-term assets | D22: -351468 | E22: -203112 | F22: -275097 | G22: R9
A23: Other investing flows (net) | D23: 0 | E23: 0 | F23: 0 | G23: R9 (plug: business combinations, JV/associate flows, other)
A24: Net cash used in investing activities | B24: -650486 | C24: -4654502 | D24: -159689 | E24: -559196 | F24: -2216093 | G24: R9 / ifrs-full:CashFlowsFromUsedInInvestingActivities
A26: Financing activities
A27: Increase in repurchase agreements and other similar secured borrowing | D27: 304846 | E27: 550584 | F27: 34012 | G27: R9
A28: Proceeds from borrowings from other financial institutions | D28: 9855033 | E28: 9416739 | F28: 7454602 | G28: R9
A29: Repayment of borrowings from other financial institutions | D29: -9921582 | E29: -10496891 | F29: -10808762 | G29: R9
A30: Payment of lease liability | D30: -182596 | E30: -174818 | F30: -203415 | G30: R9
A31: Placement of debt instruments in issue | D31: 1781728 | E31: 4155253 | F31: 2540893 | G31: R9
A32: Payment of debt instruments in issue | D32: -3928673 | E32: -9276962 | F32: -1618031 | G32: R9
A33: Dividends paid | D33: -3298183 | E33: -3398756 | F33: -5196645 | G33: R9
A34: Buyback of shares | D34: 0 | E34: 0 | F34: -431418 | G34: R9
A35: Transactions with non-controlling interests | D35: -41245 | E35: -19525 | F35: -18086 | G35: R9
A36: Net cash (used)/provided in financing activities | B36: -6809972 | C36: 853436 | D36: -5430672 | E36: -9244376 | F36: -8246850 | G36: R9 / ifrs-full:CashFlowsFromUsedInFinancingActivities
A38: Effect of exchange rate changes on cash and cash equivalents | B38: 2993850 | C38: 3552285 | D38: -5408405 | E38: 2412167 | F38: -1205941 | G38: R9 / ifrs-full:EffectOfExchangeRateChangesOnCashAndCashEquivalents
A39: Net increase/(decrease) in cash and cash equivalents (pre-FX) | B39: -1365153 | C39: 2763160 | D39: 13562723 | E39: -9367677 | F39: 1796002 | G39: CFO+CFI+CFF; published pre-FX subtotal (ifrs tag FY21-22 / R9 FY23-25)
A40: Total change in cash incl. FX effect | B40: 1628697 | C40: 6315445 | D40: 8154318 | E40: -6955510 | F40: 590061 | G40: pre-FX change + FX effect (memo; ties to Begin/End cash below)
A41: Cash and cash equivalents at beginning of year | B41: 23701149 | C41: 25329846 | D41: 31645291 | E41: 39799609 | F41: 32844099 | G41: ifrs-full:CashAndCashEquivalents(t-1) / R9
A42: Cash and cash equivalents at end of year (CF basis) | B42: 25329846 | C42: 31645291 | D42: 39799609 | E42: 32844099 | F42: 33434160 | G42: R9 (FY23-25 incl. Banistmo ops per R9 fn.1; FY21-22 = BS cash)

Sheet SCE_Hist
A1: Grupo Cibest S.A. (Bancolombia) — Consolidated Statement of Changes in Equity (audited, COP millions)
A2: FY2023-2025 roll-forward keyed off R7.htm (dividend/OCI/share-repurchase lines as filed). FY2021-2022 roll uses validated companyfacts totals with an explicit "other movements" plug -- see column note. Full per-reserve-component detail (translation reserve, cash-flow hedge reserve, etc.) is a known gap for FY2021-2022, pending a source package with the FY2022/FY2023 20-F R-files.
A4: Line item | B4: FY2021A | C4: FY2022A | D4: FY2023A | E4: FY2024A | F4: FY2025A | G4: Source
A5: Opening total equity | B5: 28115213 | C5: 33925458 | D5: 39997551 | E5: 39049729 | F5: 44584275 | G5: ifrs-full:Equity(t-1)
A6: Net income (total) | B6: 4207787 | C6: 6996365 | D6: 6214971 | E6: 6365581 | F6: 3941699 | G6: IS_Hist
A7: Other comprehensive income (total) | B7: 1814640 | C7: 2889849 | D7: -3720257 | E7: 2593244 | F7: -2851586 | G7: ifrs-full:OtherComprehensiveIncome / R7
A8: Dividends declared to owners of Parent | B8: -192374 | C8: -2943199 | D8: -3343319 | E8: -3343319 | F8: -4293604 | G8: ifrs-full:DividendsRecognisedAsDistributionsToOwnersOfParent / R7
A9: Share repurchase / buyback | F9: -431418 | G9: R7 (0 pre-2025)
A10: Other equity movements, net (NCI transactions, reserve transfers, other) | B10: -19808 | C10: -870922 | D10: -99217 | E10: -80960 | F10: 46268 | G10: plug = Closing - (Opening+NI+OCI+Div+Buyback)
A11: Closing total equity | B11: 33925458 | C11: 39997551 | D11: 39049729 | E11: 44584275 | F11: 40995634 | G11: ifrs-full:Equity (validated)

Sheet USD_Layer
A1: FX layer -- COP native to USD convenience translation (documented rates, not a hedge or presentation currency change)
A2: Closing (period-end, for BS items) and average (for IS/CF flow items) COP/USD rates. FY2021-2024: ifrs-full:ClosingForeignExchangeRate / AverageForeignExchangeRate as tagged by the filer itself (legacy CIK 1071371 companyfacts.json) -- cross-checked: FY2024 closing 4409.15 matches independent Banco de la República TRM. FY2025: Banco de la República TRM (not in filer XBRL for FY2025 since reorg moved reporting to CIK 2058897 holdco, which only tags dei facts) -- closing 3,757.08 and average 4,052.86 per Banrep TRM, corroborated via actualicese.com/trm-al-31-de-diciembre-de-2025 and actualicese.com/trm-promedio-de-2025.
A4: Rate type | B4: FY2021A | C4: FY2022A | D4: FY2023A | E4: FY2024A | F4: FY2025A
A5: Closing rate (COP/USD) | B5: 3981.16 | C5: 4810.2 | D5: 3822.05 | E5: 4409.15 | F5: 3757.08
A6: Average rate (COP/USD) | B6: 3747.24 | C6: 4257.12 | D6: 4330.14 | E6: 4073.75 | F6: 4052.86
A8: Selected USD mm (BS items @ closing; IS/CF items @ average)
A9: Total assets (USD mm) | B9: =BS_Hist!B20/B5 -> 72806.681 | C9: =BS_Hist!C20/C5 -> 73347.207 | D9: =BS_Hist!D20/D5 -> 89723.789 | E9: =BS_Hist!E20/E5 -> 84418.852 | F9: =BS_Hist!F20/F5 -> 101076.47
A10: Total equity (USD mm) | B10: =BS_Hist!B47/B5 -> 8521.5008 | C10: =BS_Hist!C47/C5 -> 8315.1534 | D10: =BS_Hist!D47/D5 -> 10216.959 | E10: =BS_Hist!E47/E5 -> 10111.762 | F10: =BS_Hist!F47/F5 -> 10911.568
A11: Net income (USD mm) | B11: =IS_Hist!B36/B6 -> 1122.903 | C11: =IS_Hist!C36/C6 -> 1643.4503 | D11: =IS_Hist!D36/D6 -> 1435.2818 | E11: =IS_Hist!E36/E6 -> 1562.5851 | F11: =IS_Hist!F36/F6 -> 972.57221

Sheet Checks_TieOut
A1: Tie-out checks -- Bancolombia / Grupo Cibest statement-grade elevation (COP millions; deltas must be 0 / "n/a")
A3: MASTER | C3: =IF(COUNTIF(H5:H25,"FAIL")=0,"OK - ALL TIE-OUTS PASS (1 disclosed reconciling item, see note row)","FAIL") -> OK - ALL TIE-OUTS PASS (1 disclosed reconciling item, see note row)
A4: Check | B4: FY2021A | C4: FY2022A | D4: FY2023A | E4: FY2024A | F4: FY2025A | H4: Status
A5: BS: Total assets = Total liabilities + Total equity | B5: =BS_Hist!B20-BS_Hist!B36-BS_Hist!B47 -> 0 | C5: =BS_Hist!C20-BS_Hist!C36-BS_Hist!C47 -> 0 | D5: =BS_Hist!D20-BS_Hist!D36-BS_Hist!D47 -> 0 | E5: =BS_Hist!E20-BS_Hist!E36-BS_Hist!E47 -> 0 | F5: =BS_Hist!F20-BS_Hist!F36-BS_Hist!F47 -> 0 | H5: =IF(AND(IF(ISNUMBER(N(B5)),ABS(N(B5))<=1,TRUE),IF(ISNUMBER(N(C5)),ABS(N(C5))<=1,TRUE),IF(ISNUMBER(N(D5)),ABS(N(D5))<=1,TRUE),IF(ISNUMBER(N(E5)),ABS(N(E5))<=1,TRUE),IF(ISNUMBER(N(F5)),ABS(N(F5))<=1,TRUE)),"PASS","FAIL") -> PASS
A6: BS: TL&E memo = TA (audited) | B6: =BS_Hist!B20-BS_Hist!B48 -> 0 | C6: =BS_Hist!C20-BS_Hist!C48 -> 0 | D6: =BS_Hist!D20-BS_Hist!D48 -> 0 | E6: =BS_Hist!E20-BS_Hist!E48 -> 0 | F6: =BS_Hist!F20-BS_Hist!F48 -> 0 | H6: =IF(AND(IF(ISNUMBER(N(B6)),ABS(N(B6))<=1,TRUE),IF(ISNUMBER(N(C6)),ABS(N(C6))<=1,TRUE),IF(ISNUMBER(N(D6)),ABS(N(D6))<=1,TRUE),IF(ISNUMBER(N(E6)),ABS(N(E6))<=1,TRUE),IF(ISNUMBER(N(F6)),ABS(N(F6))<=1,TRUE)),"PASS","FAIL") -> PASS
A7: IS: Net income = parent + NCI | B7: =IS_Hist!B37+IS_Hist!B38-IS_Hist!B36 -> 0 | C7: =IS_Hist!C37+IS_Hist!C38-IS_Hist!C36 -> 0 | D7: =IS_Hist!D37+IS_Hist!D38-IS_Hist!D36 -> 0 | E7: =IS_Hist!E37+IS_Hist!E38-IS_Hist!E36 -> 0 | F7: =IS_Hist!F37+IS_Hist!F38-IS_Hist!F36 -> 0 | H7: =IF(AND(IF(ISNUMBER(N(B7)),ABS(N(B7))<=1,TRUE),IF(ISNUMBER(N(C7)),ABS(N(C7))<=1,TRUE),IF(ISNUMBER(N(D7)),ABS(N(D7))<=1,TRUE),IF(ISNUMBER(N(E7)),ABS(N(E7))<=1,TRUE),IF(ISNUMBER(N(F7)),ABS(N(F7))<=1,TRUE)),"PASS","FAIL") -> PASS
A8: X: BS parent net income = IS parent net income | B8: =BS_Hist!B43-IS_Hist!B37 -> 0 | C8: =BS_Hist!C43-IS_Hist!C37 -> 0 | D8: =BS_Hist!D43-IS_Hist!D37 -> 0 | E8: =BS_Hist!E43-IS_Hist!E37 -> 0 | F8: =BS_Hist!F43-IS_Hist!F37 -> 0 | H8: =IF(AND(IF(ISNUMBER(N(B8)),ABS(N(B8))<=1,TRUE),IF(ISNUMBER(N(C8)),ABS(N(C8))<=1,TRUE),IF(ISNUMBER(N(D8)),ABS(N(D8))<=1,TRUE),IF(ISNUMBER(N(E8)),ABS(N(E8))<=1,TRUE),IF(ISNUMBER(N(F8)),ABS(N(F8))<=1,TRUE)),"PASS","FAIL") -> PASS
A9: X: CF net income = IS net income | B9: =IF(B2="","n/a",N(CF_Hist!B6)-IS_Hist!B36) -> n/a | C9: =IF(C2="","n/a",N(CF_Hist!C6)-IS_Hist!C36) -> n/a | D9: =IF(D2="","n/a",N(CF_Hist!D6)-IS_Hist!D36) -> n/a | E9: =IF(E2="","n/a",N(CF_Hist!E6)-IS_Hist!E36) -> n/a | F9: =IF(F2="","n/a",N(CF_Hist!F6)-IS_Hist!F36) -> n/a | H9: =IF(AND(IF(ISNUMBER(N(B9)),ABS(N(B9))<=1,TRUE),IF(ISNUMBER(N(C9)),ABS(N(C9))<=1,TRUE),IF(ISNUMBER(N(D9)),ABS(N(D9))<=1,TRUE),IF(ISNUMBER(N(E9)),ABS(N(E9))<=1,TRUE),IF(ISNUMBER(N(F9)),ABS(N(F9))<=1,TRUE)),"PASS","FAIL") -> PASS
A10: SCE: Closing equity = BS total equity | B10: =SCE_Hist!B11-BS_Hist!B47 -> 0 | C10: =SCE_Hist!C11-BS_Hist!C47 -> 0 | D10: =SCE_Hist!D11-BS_Hist!D47 -> 0 | E10: =SCE_Hist!E11-BS_Hist!E47 -> 0 | F10: =SCE_Hist!F11-BS_Hist!F47 -> 0 | H10: =IF(AND(IF(ISNUMBER(N(B10)),ABS(N(B10))<=1,TRUE),IF(ISNUMBER(N(C10)),ABS(N(C10))<=1,TRUE),IF(ISNUMBER(N(D10)),ABS(N(D10))<=1,TRUE),IF(ISNUMBER(N(E10)),ABS(N(E10))<=1,TRUE),IF(ISNUMBER(N(F10)),ABS(N(F10))<=1,TRUE)),"PASS","FAIL") -> PASS
A11: SCE: Opening equity = prior-year BS total equity (FY22-25) | C11: =SCE_Hist!C5-BS_Hist!B47 -> 0 | D11: =SCE_Hist!D5-BS_Hist!C47 -> 0 | E11: =SCE_Hist!E5-BS_Hist!D47 -> 0 | F11: =SCE_Hist!F5-BS_Hist!E47 -> 0 | H11: =IF(AND(IF(ISNUMBER(N(C11)),ABS(N(C11))<=1,TRUE),IF(ISNUMBER(N(D11)),ABS(N(D11))<=1,TRUE),IF(ISNUMBER(N(E11)),ABS(N(E11))<=1,TRUE),IF(ISNUMBER(N(F11)),ABS(N(F11))<=1,TRUE)),"PASS","FAIL") -> PASS
A12: SCE: Roll check (Open+NI+OCI+Div+Buyback+Other-Close=0, by construction) | B12: =SCE_Hist!B5+SCE_Hist!B6+SCE_Hist!B7+SCE_Hist!B8+N(SCE_Hist!B9)+SCE_Hist!B10-SCE_Hist!B11 -> 0 | C12: =SCE_Hist!C5+SCE_Hist!C6+SCE_Hist!C7+SCE_Hist!C8+N(SCE_Hist!C9)+SCE_Hist!C10-SCE_Hist!C11 -> 0 | D12: =SCE_Hist!D5+SCE_Hist!D6+SCE_Hist!D7+SCE_Hist!D8+N(SCE_Hist!D9)+SCE_Hist!D10-SCE_Hist!D11 -> 0 | E12: =SCE_Hist!E5+SCE_Hist!E6+SCE_Hist!E7+SCE_Hist!E8+N(SCE_Hist!E9)+SCE_Hist!E10-SCE_Hist!E11 -> 0 | F12: =SCE_Hist!F5+SCE_Hist!F6+SCE_Hist!F7+SCE_Hist!F8+N(SCE_Hist!F9)+SCE_Hist!F10-SCE_Hist!F11 -> 0 | H12: =IF(AND(IF(ISNUMBER(N(B12)),ABS(N(B12))<=1,TRUE),IF(ISNUMBER(N(C12)),ABS(N(C12))<=1,TRUE),IF(ISNUMBER(N(D12)),ABS(N(D12))<=1,TRUE),IF(ISNUMBER(N(E12)),ABS(N(E12))<=1,TRUE),IF(ISNUMBER(N(F12)),ABS(N(F12))<=1,TRUE)),"PASS","FAIL") -> PASS
A13: IS: Net interest margin chain (FY23-25) | D13: =IS_Hist!D11+IS_Hist!D12-IS_Hist!D13 -> 0 | E13: =IS_Hist!E11+IS_Hist!E12-IS_Hist!E13 -> 0 | F13: =IS_Hist!F11+IS_Hist!F12-IS_Hist!F13 -> 0 | H13: =IF(AND(IF(ISNUMBER(N(D13)),ABS(N(D13))<=1,TRUE),IF(ISNUMBER(N(E13)),ABS(N(E13))<=1,TRUE),IF(ISNUMBER(N(F13)),ABS(N(F13))<=1,TRUE)),"PASS","FAIL") -> PASS
A14: IS: Total operating income chain (FY23-25) | D14: =IS_Hist!D17+IS_Hist!D21+IS_Hist!D22+IS_Hist!D23-IS_Hist!D24 -> 0 | E14: =IS_Hist!E17+IS_Hist!E21+IS_Hist!E22+IS_Hist!E23-IS_Hist!E24 -> 0 | F14: =IS_Hist!F17+IS_Hist!F21+IS_Hist!F22+IS_Hist!F23-IS_Hist!F24 -> 0 | H14: =IF(AND(IF(ISNUMBER(N(D14)),ABS(N(D14))<=1,TRUE),IF(ISNUMBER(N(E14)),ABS(N(E14))<=1,TRUE),IF(ISNUMBER(N(F14)),ABS(N(F14))<=1,TRUE)),"PASS","FAIL") -> PASS
A15: IS: PBT = operating income - opex (FY23-25) | D15: =IS_Hist!D24+IS_Hist!D31-IS_Hist!D32 -> 0 | E15: =IS_Hist!E24+IS_Hist!E31-IS_Hist!E32 -> 0 | F15: =IS_Hist!F24+IS_Hist!F31-IS_Hist!F32 -> 0 | H15: =IF(AND(IF(ISNUMBER(N(D15)),ABS(N(D15))<=1,TRUE),IF(ISNUMBER(N(E15)),ABS(N(E15))<=1,TRUE),IF(ISNUMBER(N(F15)),ABS(N(F15))<=1,TRUE)),"PASS","FAIL") -> PASS
A16: IS: Net income = continuing + discontinued (FY23-25) | D16: =IS_Hist!D34+IS_Hist!D35-IS_Hist!D36 -> 0 | E16: =IS_Hist!E34+IS_Hist!E35-IS_Hist!E36 -> 0 | F16: =IS_Hist!F34+IS_Hist!F35-IS_Hist!F36 -> 0 | H16: =IF(AND(IF(ISNUMBER(N(D16)),ABS(N(D16))<=1,TRUE),IF(ISNUMBER(N(E16)),ABS(N(E16))<=1,TRUE),IF(ISNUMBER(N(F16)),ABS(N(F16))<=1,TRUE)),"PASS","FAIL") -> PASS
A17: CF: CFO components sum to reported CFO (FY23-25) | D17: =SUM(CF_Hist!D6:D15)-CF_Hist!D16 -> 0 | E17: =SUM(CF_Hist!E6:E15)-CF_Hist!E16 -> 0 | F17: =SUM(CF_Hist!F6:F15)-CF_Hist!F16 -> 0 | H17: =IF(AND(IF(ISNUMBER(N(D17)),ABS(N(D17))<=1,TRUE),IF(ISNUMBER(N(E17)),ABS(N(E17))<=1,TRUE),IF(ISNUMBER(N(F17)),ABS(N(F17))<=1,TRUE)),"PASS","FAIL") -> PASS
A18: CF: CFI components sum to reported CFI (FY23-25) | D18: =SUM(CF_Hist!D20:D23)-CF_Hist!D24 -> 0 | E18: =SUM(CF_Hist!E20:E23)-CF_Hist!E24 -> 0 | F18: =SUM(CF_Hist!F20:F23)-CF_Hist!F24 -> 0 | H18: =IF(AND(IF(ISNUMBER(N(D18)),ABS(N(D18))<=1,TRUE),IF(ISNUMBER(N(E18)),ABS(N(E18))<=1,TRUE),IF(ISNUMBER(N(F18)),ABS(N(F18))<=1,TRUE)),"PASS","FAIL") -> PASS
A19: CF: CFF components sum to reported CFF (FY23-25) | D19: =SUM(CF_Hist!D27:D35)-CF_Hist!D36 -> 0 | E19: =SUM(CF_Hist!E27:E35)-CF_Hist!E36 -> 0 | F19: =SUM(CF_Hist!F27:F35)-CF_Hist!F36 -> 0 | H19: =IF(AND(IF(ISNUMBER(N(D19)),ABS(N(D19))<=1,TRUE),IF(ISNUMBER(N(E19)),ABS(N(E19))<=1,TRUE),IF(ISNUMBER(N(F19)),ABS(N(F19))<=1,TRUE)),"PASS","FAIL") -> PASS
A20: CF: Pre-FX net change = CFO+CFI+CFF (all 5 yrs) | B20: =CF_Hist!B16+CF_Hist!B24+CF_Hist!B36-CF_Hist!B39 -> 0 | C20: =CF_Hist!C16+CF_Hist!C24+CF_Hist!C36-CF_Hist!C39 -> 0 | D20: =CF_Hist!D16+CF_Hist!D24+CF_Hist!D36-CF_Hist!D39 -> 0 | E20: =CF_Hist!E16+CF_Hist!E24+CF_Hist!E36-CF_Hist!E39 -> 0 | F20: =CF_Hist!F16+CF_Hist!F24+CF_Hist!F36-CF_Hist!F39 -> 0 | H20: =IF(AND(IF(ISNUMBER(N(B20)),ABS(N(B20))<=1,TRUE),IF(ISNUMBER(N(C20)),ABS(N(C20))<=1,TRUE),IF(ISNUMBER(N(D20)),ABS(N(D20))<=1,TRUE),IF(ISNUMBER(N(E20)),ABS(N(E20))<=1,TRUE),IF(ISNUMBER(N(F20)),ABS(N(F20))<=1,TRUE)),"PASS","FAIL") -> PASS
A21: CF: Total change incl. FX = pre-FX change + FX (all 5 yrs) | B21: =CF_Hist!B39+CF_Hist!B38-CF_Hist!B40 -> 0 | C21: =CF_Hist!C39+CF_Hist!C38-CF_Hist!C40 -> 0 | D21: =CF_Hist!D39+CF_Hist!D38-CF_Hist!D40 -> 0 | E21: =CF_Hist!E39+CF_Hist!E38-CF_Hist!E40 -> 0 | F21: =CF_Hist!F39+CF_Hist!F38-CF_Hist!F40 -> 0 | H21: =IF(AND(IF(ISNUMBER(N(B21)),ABS(N(B21))<=1,TRUE),IF(ISNUMBER(N(C21)),ABS(N(C21))<=1,TRUE),IF(ISNUMBER(N(D21)),ABS(N(D21))<=1,TRUE),IF(ISNUMBER(N(E21)),ABS(N(E21))<=1,TRUE),IF(ISNUMBER(N(F21)),ABS(N(F21))<=1,TRUE)),"PASS","FAIL") -> PASS
A22: CF: End cash (CF basis) = Begin cash + total change incl. FX (all 5 yrs) | B22: =CF_Hist!B41+CF_Hist!B40-CF_Hist!B42 -> 0 | C22: =CF_Hist!C41+CF_Hist!C40-CF_Hist!C42 -> 0 | D22: =CF_Hist!D41+CF_Hist!D40-CF_Hist!D42 -> 0 | E22: =CF_Hist!E41+CF_Hist!E40-CF_Hist!E42 -> 0 | F22: =CF_Hist!F41+CF_Hist!F40-CF_Hist!F42 -> 0 | H22: =IF(AND(IF(ISNUMBER(N(B22)),ABS(N(B22))<=1,TRUE),IF(ISNUMBER(N(C22)),ABS(N(C22))<=1,TRUE),IF(ISNUMBER(N(D22)),ABS(N(D22))<=1,TRUE),IF(ISNUMBER(N(E22)),ABS(N(E22))<=1,TRUE),IF(ISNUMBER(N(F22)),ABS(N(F22))<=1,TRUE)),"PASS","FAIL") -> PASS
A23: CF: Beginning cash = prior-year end cash, BS basis (FY22-25) | C23: =CF_Hist!C41-BS_Hist!B6 -> 0 | D23: =CF_Hist!D41-BS_Hist!C6 -> 0 | E23: =CF_Hist!E41-BS_Hist!D6 -> 0 | F23: =CF_Hist!F41-BS_Hist!E6 -> 0 | H23: =IF(AND(IF(ISNUMBER(N(C23)),ABS(N(C23))<=1,TRUE),IF(ISNUMBER(N(D23)),ABS(N(D23))<=1,TRUE),IF(ISNUMBER(N(E23)),ABS(N(E23))<=1,TRUE),IF(ISNUMBER(N(F23)),ABS(N(F23))<=1,TRUE)),"PASS","FAIL") -> PASS
A24: X: CF end cash (FY21-24) = BS cash [FY25 differs by design, see note row below] | B24: =CF_Hist!B42-BS_Hist!B6 -> 0 | C24: =CF_Hist!C42-BS_Hist!C6 -> 0 | D24: =CF_Hist!D42-BS_Hist!D6 -> 0 | E24: =CF_Hist!E42-BS_Hist!E6 -> 0 | H24: =IF(AND(IF(ISNUMBER(N(B24)),ABS(N(B24))<=1,TRUE),IF(ISNUMBER(N(C24)),ABS(N(C24))<=1,TRUE),IF(ISNUMBER(N(D24)),ABS(N(D24))<=1,TRUE),IF(ISNUMBER(N(E24)),ABS(N(E24))<=1,TRUE)),"PASS","FAIL") -> PASS
A25: NOTE: CF FY2025 end cash (33,434,160, incl. Banistmo ops per R9 fn.1) vs BS FY2025 cash (29,916,400, ex-Banistmo, reclassified to held-for-sale) -- delta 3,517,760 is the Banistmo held-for-sale reclassification, not an error. | H25: DISCLOSED

Sheet Sources_Audited
A1: Audited source register -- Grupo Cibest S.A. (Bancolombia), EDGAR
A3: Entity / period | B3: CIK | C3: Filing | D3: Exact citation | E3: Notes
A4: FY2023A-FY2025A (IS, BS FY24-25, CF, SCE, discontinued ops) | B4: 2058897 (Grupo Cibest S.A. -- 2025 holdco reorg) | C4: 20-F FY2025-12-31, filed 2026-04-08, accn 0002058897-26-000125 | D4: R3.htm (BS), R4.htm (IS), R5.htm (Comprehensive income), R7.htm (SCE), R9.htm (CF) -- Financial_Report R-files, $ in COP millions | E4: Banistmo S.A. classified as held-for-sale/discontinued from 2025-12-18 (Note 1, Note 2.D12, Note 31) -- affects FY2025 BS (held-for-sale lines) and IS (discontinued-ops line); FY2023-2024 comparatives in this filing are NOT restated for that reclass.
A5: FY2021A-FY2022A (IS: NI/NCI/EPS/fees only; BS: full line detail; CF: CFO/CFI/CFF/FX summary) | B5: 1071371 (Bancolombia S.A. -- legacy pre-reorg entity) | C5: companyfacts.json (SEC XBRL frames API), as-first-reported facts (fy=2021 / fy=2022, form 20-F) | D5: ifrs-full: tags per column note on IS_Hist/BS_Hist/CF_Hist/SCE_Hist; each tag individually cross-checked against the FY2024 R3/R4/R9 comparative before use (exact match required) | E5: Tags that failed the FY2024 cross-check (scope mismatch or gross-vs-net) were excluded rather than mismapped -- see PARTIAL gaps in build report. cib_-prefixed custom tags were not mined (would require full XBRL instance parse, not just companyfacts frames).
A6: FX rates | B6: n/a | C6: FY2021-2024: ifrs-full:ClosingForeignExchangeRate / AverageForeignExchangeRate, legacy CIK 1071371 companyfacts.json (filer-tagged TRM). FY2025: Banco de la Republica TRM (not in filer XBRL for FY2025 -- 2058897 holdco only tags dei facts) | D6: See USD_Layer sheet | E6: FY2025 closing 3,757.08 / average 4,052.86 per Banrep TRM, corroborated via actualicese.com/trm-al-31-de-diciembre-de-2025 and actualicese.com/trm-promedio-de-2025 (2026-07-21 web check). FY2024 closing (4,409.15) independently cross-checked and matches the filer-tagged value exactly.
A8: Reorg note: SEC EDGAR reassigned the registrant CIK from 1071371 (Bancolombia S.A.) to 2058897 (Grupo Cibest S.A.) for the 2025 holdco reorganization. Historical (pre-2025) XBRL facts live under the legacy CIK; the FY2025 20-F (filed under 2058897) restates none of FY2021-2022 and only the FY2023-2024 R-file comparatives are as originally presented (no Banistmo reclass).
A9: Baseline note: prior workbook state (9of10 baseline) was a 2-year KPI panel with a self-certifying Gate_9of10 sheet; that sheet and the placeholder Sources/Historical/Checks/Sector_KPIs scaffold are left in place but superseded -- real statement-grade content lives in IS_Hist/BS_Hist/CF_Hist/SCE_Hist/USD_Layer/Checks_TieOut/Forecast (this pass).

Sheet Forecast_5yr
A1: Grupo Cibest S.A. (Bancolombia) -- 5-year driver-built forecast (COP millions), continuing operations basis
A2: Anchored to FY2025A continuing-operations net income (6,948,339, IS_Hist) since Banistmo (discontinued, -3,006,640) will not recur once divested. Scenario switch: B6 (1=Base, 2=Bull, 3=Bear).
A4: Scenario switch (1=Base,2=Bull,3=Bear) | B4: 1
A6: Driver | B6: Base | C6: Bull | D6: Bear
A7: Gross loan book growth, % p.a. | B7: 0.09 | C7: 0.13 | D7: 0.04
A8: Net interest margin, % of avg loans (proxy) | B8: 0.075 | C8: 0.082 | D8: 0.065
A9: Cost of risk, % of avg loans | B9: 0.017 | C9: 0.013 | D9: 0.026
A10: Fee income growth, % p.a. | B10: 0.08 | C10: 0.12 | D10: 0.02
A11: Opex growth, % p.a. | B11: 0.07 | C11: 0.06 | D11: 0.09
A12: Effective tax rate, % | B12: 0.3 | C12: 0.28 | D12: 0.33
A13: Dividend payout, % of parent NI | B13: 0.5 | C13: 0.5 | D13: 0.45
A15: Active driver (per scenario switch B4)
A16: Gross loan book growth | B16: =CHOOSE($B$4,B7,C7,D7) -> 0.09
A17: Net interest margin, % of avg loans | B17: =CHOOSE($B$4,B8,C8,D8) -> 0.075
A18: Cost of risk, % of avg loans | B18: =CHOOSE($B$4,B9,C9,D9) -> 0.017
A19: Fee income growth | B19: =CHOOSE($B$4,B10,C10,D10) -> 0.08
A20: Opex growth | B20: =CHOOSE($B$4,B11,C11,D11) -> 0.07
A21: Effective tax rate | B21: =CHOOSE($B$4,B12,C12,D12) -> 0.3
A22: Dividend payout | B22: =CHOOSE($B$4,B13,C13,D13) -> 0.5
A25: Line (COP mm) | C25: FY2026E | D25: FY2027E | E25: FY2028E | F25: FY2029E | G25: FY2030E
A26: Gross loans (avg proxy) | C26: =256353981*(1+B16) -> 2.7942584e+08 | D26: =C26*(1+B16) -> 3.0457416e+08 | E26: =D26*(1+B16) -> 3.3198584e+08 | F26: =E26*(1+B16) -> 3.6186457e+08 | G26: =F26*(1+B16) -> 3.9443238e+08
A27: Net interest income (before impairment) | C27: =C26*B17 -> 20956938 | D27: =D26*B17 -> 22843062 | E27: =E26*B17 -> 24898938 | F27: =F26*B17 -> 27139842 | G27: =G26*B17 -> 29582428
A28: Credit impairment charges, net | C28: =-C26*B18 -> -4750239.3 | D28: =-D26*B18 -> -5177760.8 | E28: =-E26*B18 -> -5643759.3 | F28: =-F26*B18 -> -6151697.6 | G28: =-G26*B18 -> -6705350.4
A29: Fees, other operating income and dividends/equity income (net) | C29: =8620029*(1+B19) -> 9309631.3 | D29: =C29*(1+B19) -> 10054402 | E29: =D29*(1+B19) -> 10858754 | F29: =E29*(1+B19) -> 11727454 | G29: =F29*(1+B19) -> 12665651
A30: Operating expenses | C30: =-13857106*(1+B20) -> -14827103 | D30: =C30*(1+B20) -> -15865001 | E30: =D30*(1+B20) -> -16975551 | F30: =E30*(1+B20) -> -18163839 | G30: =F30*(1+B20) -> -19435308
A31: Profit before tax (continuing ops) | C31: =C27+C28+C29+C30 -> 10689227 | D31: =D27+D28+D29+D30 -> 11854703 | E31: =E27+E28+E29+E30 -> 13138382 | F31: =F27+F28+F29+F30 -> 14551760 | G31: =G27+G28+G29+G30 -> 16107420
A32: Income tax | C32: =-C31*B21 -> -3206768 | D32: =-D31*B21 -> -3556410.8 | E32: =-E31*B21 -> -3941514.6 | F32: =-F31*B21 -> -4365527.9 | G32: =-G31*B21 -> -4832226.1
A33: Net income (continuing ops) | C33: =C31+C32 -> 7482458.6 | D33: =D31+D32 -> 8298291.9 | E33: =E31+E32 -> 9196867.4 | F33: =F31+F32 -> 10186232 | G33: =G31+G32 -> 11275194
A34: Dividends declared | C34: =-C33*B22 -> -3741229.3 | D34: =-D33*B22 -> -4149146 | E34: =-E33*B22 -> -4598433.7 | F34: =-F33*B22 -> -5093115.9 | G34: =-G33*B22 -> -5637597.2
A35: NOTE: opening FY2026E balance uses a gross-loans + allowance-addback proxy off FY2025A (not the audited gross-loan note), and NII/fees/opex bases are FY2025A audited totals; PARTIAL -- a full balance-sheet-driven forecast (funding, capital, RWA) is a next-pass item, not built here.

Sheet Claude Code Log
A1: Turn # | B1: Date | C1: User Request | D1: Action Taken | E1: Details | F1: Outcome
A2: 1 | B2: 46324.359 | C2: Prepare a public model copy | D2: Remove local paths and private build references; preserve financial formulas and inputs | E2: Agent run with MOG as the tool, checked by guard v1. The guard measured every sheet before and after the run. Changed: 00_Cover: 2 cells written, at B19, B20; Gate_9of10: 6 cells written, at F5, F7, F9, F12, F14, G19. Agent: OpenFinmods export | F2: Compare against source and review public copy
