Workbook

Sheet EEFF
A1: Empresa de Distribución Eléctrica Metro-Oeste, S. A.
A2: Estados Financieros Auditados FY24-FY25 (año fiscal al 31 de diciembre)
A3: en B/. sin escala
A5: Años | B5: FY21A | C5: FY22A | D5: FY23A | E5: FY24A | F5: FY25A | G5: FY26E | H5: FY27E | I5: FY28E | J5: FY29E | K5: FY30E
A6: Estado de Resultados
A7: Ingresos por actividades ordinarias | E7: 872479782 | F7: 910833173
A8: Aprovisionamientos | E8: -615692748 | F8: -661106024
A9: Reparaciones y conservación | E9: -21731420 | F9: -19594455
A10: Depreciación y amortización | E10: -48347878 | F10: -53346452
A11: Total de ganancia bruta por actividades ordinarias | E11: 186707736 | F11: 176786242
A12: Gastos de personal | E12: -9105171 | F12: -10322383
A13: Otros gastos | E13: -45818642 | F13: -43618338
A14: Resultado de las actividades de operaciones | E14: 131783923 | F14: 122845521
A15: Gastos financieros | E15: -76941269 | F15: -73951611
A16: Ingresos financieros | E16: 4648031 | F16: 6411378
A17: Pérdida neta en tipos de cambio de moneda extranjera | E17: -318727 | F17: -995436
A18: Utilidad antes del impuesto sobre la renta | E18: 59171958 | F18: 54309852
... A22: Resultados integrales del año | E22: 39807058 | F22: 36942971
A24: Años | B24: FY21A | C24: FY22A | D24: FY23A | E24: FY24A | F24: FY25A | G24: FY26E | H24: FY27E | I24: FY28E | J24: FY29E | K24: FY30E
A25: Balance General
A26: Inmovilizados materiales | E26: 1102383248 | F26: 1229864857
A27: Otros activos no corrientes | E27: 6636716 | F27: 7488557
A28: Activos intangibles | E28: 1435537 | F28: 1231687
A29: Activos por derecho de uso | E29: 310903 | F29: 5557215
A30: Total de activos no corrientes | E30: 1110766404 | F30: 1244142316
A31: Clientes y otras cuentas por cobrar | E31: 295555709 | F31: 247443512
A32: Efectivo | E32: 62979274 | F32: 207018868
A33: Otros activos corrientes | E33: 2493427 | F33: 4814532
A34: Total de activos corrientes | E34: 361028410 | F34: 459276912
A35: Total de activos | E35: 1471794814 | F35: 1703419228
A36: Deuda financiera a largo plazo | E36: 504216550 | F36: 827072790
A37: Bonos por pagar a largo plazo | E37: 0 | F37: 123843760
... A52: Total de pasivos y patrimonio | E52: 1471794814 | F52: 1703419228
A54: Años | B54: FY21A | C54: FY22A | D54: FY23A | E54: FY24A | F54: FY25A | G54: FY26E | H54: FY27E | I54: FY28E | J54: FY29E | K54: FY30E
A55: Estado de Flujos de Efectivo
A56: Utilidad neta | E56: 39800939 | F56: 37173332
A57: Gastos financieros | E57: 76941269 | F57: 73951611
A58: Ingresos financieros | E58: -4648031 | F58: -6411378
A59: Ingresos por subvención de capital | E59: -1778843 | F59: -2663029
A60: Depreciación de inmovilizados materiales | E60: 46727986 | F60: 51526696
A61: Depreciación de activo por derecho de uso | E61: 428415 | F61: 1007377
A62: Amortización de activos intangibles | E62: 1191479 | F62: 812379
A63: Pérdida procedente de inmovilizado material | E63: 62157 | F63: 141306
A64: Estimación para pérdidas crediticias esperadas | E64: 13535038 | F64: 8461227
A65: Adiciones de subvención de capital | E65: 2100335 | F65: 121860
A66: Impuesto sobre la renta | E66: 19371019 | F66: 17136520
A67: Pérdida neta en tipos de cambio de moneda extranjera | E67: -318727 | F67: -995436
... A91: Efectivo y equivalentes de efectivo al final del año | E91: 62979274 | F91: 207018868

Sheet Notas_EEFF
A1: Empresa de Distribución Eléctrica Metro-Oeste, S. A.
A2: Notas a los Estados Financieros
A3: Fuente: informes auditados vía OCR Mistral (verbatim).
A5: Año | B5: Documento fuente | C5: Página OCR | D5: Tabla OCR / sección | E5: Nota # | F5: Título original de la nota | G5: Categoría modelable | H5: Line item EEFF | I5: Sub-line item / detalle | J5: Texto original / disclosure | K5: Monto reportado | L5: Moneda | M5: Unidad / escala | N5: Fecha / venc. / tasa / plazo | O5: Contraparte / contrato / instrumento | P5: Impacto en Supuestos | Q5: Impacto en ModeloFinanciero | R5: Link a celda EEFF | S5: Comentario de extracción | T5: Status
A6: 2025 | B6: INA_EDEMET_2025_0.pdf | C6: page-107 | D6: tbl-83.html | E6: 5 | F6: 5. Saldos y Transacciones con Partes Relacionadas. continuación | G6: Partes relacionadas | J6: [tbl-83.html](tbl-83.html)(tbl-82.html)(tbl-82.html) | T6: OK
A7: 2025 | B7: INA_EDEMET_2025_0.pdf | C7: page-107 | D7: markdown.md | E7: 5 | F7: 5. Saldos y Transacciones con Partes Relacionadas. continuación | G7: Partes relacionadas | J7: Los saldos y transacciones con partes relacionadas incluyen los mantenidos con el Gobierno de Panamá (el “Gobierno”) y entidades autónomas. El Gobierno, accionista de la Compañía en un 47,86% (ver Nota 1), tiene participación e influencia significativa en las entidades de generación y distribución eléctrica mixtas de Panamá. En el caso de la entidad de transmisión, el Gobierno mantiene el 100% de control de las entidades que prestan este servicio, como lo es la Empresa de Transmisión Eléctrica, S. A. (ETESA). Dado a que el Gobierno tiene participación en las tres distribuidoras y en algunas generadoras eléctricas del país, el ingreso por venta de energía por montos importantes es efectuado a dichas entidades. | T7: OK
A8: 2025 | B8: INA_EDEMET_2025_0.pdf | C8: page-107 | D8: markdown.md | E8: 6 | F8: 6. Inmovilizados Materiales | G8: Otros | J8: A continuación, se presenta la composición de los inmovilizados materiales: | T8: OK
A9: 2025 | B9: INA_EDEMET_2025_0.pdf | C9: page-107 | D9: tbl-83.html | E9: 6 | F9: 6. Inmovilizados Materiales | G9: Otros | J9: [tbl-83.html](tbl-83.html) | T9: OK
A10: 2025 | B10: INA_EDEMET_2025_0.pdf | C10: page-108 | D10: markdown.md | E10: 6 | F10: 6. Inmovilizados Materiales | G10: Otros | J10: # **Empresa de Distribución Eléctrica Chiriquí, S. A.** (Entidad 51% Propiedad de Distribuidora Eléctrica del Caribe, S. A.) | T10: OK
A11: 2025 | B11: INA_EDEMET_2025_0.pdf | C11: page-108 | D11: markdown.md | E11: 6 | F11: 6. Inmovilizados Materiales | G11: Otros | J11: # **Notas a los Estados Financieros** | T11: OK
A12: 2025 | B12: INA_EDEMET_2025_0.pdf | C12: page-108 | D12: markdown.md | E12: 6 | F12: 6. Inmovilizados Materiales, continuación | G12: Otros | J12: El movimiento del inmovilizado material en explotación se presenta a continuación: | T12: OK
A13: 2025 | B13: INA_EDEMET_2025_0.pdf | C13: page-108 | D13: tbl-84.html | E13: 6 | F13: 6. Inmovilizados Materiales, continuación | G13: Otros | J13: [tbl-84.html](tbl-84.html)(tbl-84.html) | T13: OK
A14: 2025 | B14: INA_EDEMET_2025_0.pdf | C14: page-109 | D14: markdown.md | E14: 6 | F14: 6. Inmovilizados Materiales, continuación | G14: Otros | J14: # **Notas a los Estados Financieros**--- | T14: OK
A15: 2025 | B15: INA_EDEMET_2025_0.pdf | C15: page-109 | D15: markdown.md | E15: 6 | F15: 6. Inmovilizados Materiales, continuación | G15: Otros | J15: La Compañía tiene formalizadas pólizas de seguros para cubrir los posibles riesgos a que están sujetos los diversos elementos de su inmovilizado material, así como las posibles reclamaciones que se le puedan presentar por el ejercicio de su actividad, entendiendo que dichas pólizas cubren de manera suficiente los riesgos a los que están sometidos. | T15: OK
A16: 2025 | B16: INA_EDEMET_2025_0.pdf | C16: page-109 | D16: markdown.md | E16: 6 | F16: 6. Inmovilizados Materiales, continuación | G16: Otros | J16: Los materiales de almacén de consumo se detallan a continuación: | T16: OK
A17: 2025 | B17: INA_EDEMET_2025_0.pdf | C17: page-109 | D17: tbl-86.html | E17: 6 | F17: 6. Inmovilizados Materiales, continuación | G17: Otros | J17: [tbl-86.html](tbl-86.html)(tbl-85.html)(tbl-85.html) | T17: OK
... A19: 2025 | B19: INA_EDEMET_2025_0.pdf | C19: page-109 | D19: markdown.md | E19: 6 | F19: 6. Inmovilizados Materiales, continuación | G19: Otros | J19: La Compañía ha contratado a operadores logísticos, otorgando así la administración de sus inventarios a terceros, que incluye la recepción, descarga, almacenamiento, control del inventario, siendo de esta forma ellos responsables de todos los materiales pertenecientes a la Compañía y que fueron depositados para su custodia. | T19: OK
A20: 2025 | B20: INA_EDEMET_2025_0.pdf | C20: page-109 | D20: markdown.md | E20: 6 | F20: 6. Inmovilizados Materiales, continuación | G20: Otros | J20: Los costos capitalizados también incluyen los gastos de personal relacionados directamente con las obras en curso. Los importes capitalizados por estos conceptos que se excluyen de la cuenta de resultados ascienden a B/.1,166,699 (2024: B/.1,333,108) (véase Nota 17). | K20: 1166699 | L20: B/. | T20: OK
A21: 2025 | B21: INA_EDEMET_2025_0.pdf | C21: page-109 | D21: markdown.md | E21: 6 | F21: 6. Inmovilizados Materiales, continuación | G21: Otros | J21: Para efectos de conciliación con el estado de flujos de efectivo, las adquisiciones de inmovilizados materiales presentadas como flujos de efectivos de actividades de inversiones se presentan netas del cambio neto de materiales de almacén del año, como se detalla a continuación: | T21: OK
A22: 2025 | B22: INA_EDEMET_2025_0.pdf | C22: page-109 | D22: tbl-86.html | E22: 6 | F22: 6. Inmovilizados Materiales, continuación | G22: Otros | J22: [tbl-86.html](tbl-86.html) | T22: OK
A23: 2025 | B23: INA_EDEMET_2025_0.pdf | C23: page-109 | D23: markdown.md | E23: 6 | F23: 6. Inmovilizados Materiales, continuación | G23: Otros | J23: Al 31 de diciembre de 2025, la Compañía mantiene compromisos para la ejecución de inversiones por un monto de B/.17,537,249, concentrados específicamente en calidad y expansión de la red eléctrica. | K23: 17537249 | L23: B/. | T23: OK
A24: 2025 | B24: INA_EDEMET_2025_0.pdf | C24: page-110 | D24: markdown.md | E24: 7 | F24: 7. Otros Activos | G24: Otros | J24: A continuación, se presenta el detalle de los otros activos: | T24: OK
A25: 2025 | B25: INA_EDEMET_2025_0.pdf | C25: page-110 | D25: tbl-88.html | E25: 7 | F25: 7. Otros Activos | G25: Otros | J25: [tbl-88.html](tbl-88.html)(tbl-87.html)(tbl-87.html) | T25: OK
A26: 2025 | B26: INA_EDEMET_2025_0.pdf | C26: page-110 | D26: markdown.md | E26: 8 | F26: 8. Clientes y Otras Cuentas por Cobrar | G26: Cuentas por cobrar | J26: Los saldos por cobrar a clientes y otras cuentas por cobrar se detallan a continuación: | T26: OK
A27: 2025 | B27: INA_EDEMET_2025_0.pdf | C27: page-110 | D27: tbl-88.html | E27: 8 | F27: 8. Clientes y Otras Cuentas por Cobrar | G27: Cuentas por cobrar | J27: [tbl-88.html](tbl-88.html) | T27: OK
A28: 2025 | B28: INA_EDEMET_2025_0.pdf | C28: page-110 | D28: markdown.md | E28: 8 | F28: 8. Clientes y Otras Cuentas por Cobrar | G28: Cuentas por cobrar | J28: # **Cuentas por Cobrar a Clientes** | T28: OK
A29: 2025 | B29: INA_EDEMET_2025_0.pdf | C29: page-110 | D29: markdown.md | E29: 8 | F29: 8. Clientes y Otras Cuentas por Cobrar | G29: Cuentas por cobrar | J29: Las cuentas por cobrar a clientes comprenden cantidades por cobrar por el monto de la facturación de la energía suministrada. El período promedio de crédito es de 30 días, contados a partir de la fecha de la facturación de energía. | T29: OK
A30: 2025 | B30: INA_EDEMET_2025_0.pdf | C30: page-110 | D30: markdown.md | E30: 8 | F30: 8. Clientes y Otras Cuentas por Cobrar | G30: Cuentas por cobrar | J30: La Compañía mantiene una reserva para pérdidas crediticias esperadas de las cuentas por cobrar comerciales, calculada con un modelo simplificado. El cálculo de esta provisión corresponde a un reconocimiento de las pérdidas crediticias esperadas que proyecta la probabilidad de incumplimiento (no pago) en un lapso de un año. | T30: OK
A31: 2025 | B31: INA_EDEMET_2025_0.pdf | C31: page-111 | D31: markdown.md | E31: 8 | F31: 8. Clientes y Otras Cuentas por Cobrar | G31: Cuentas por cobrar | J31: # **Empresa de Distribución Eléctrica Chiriquí, S. A.** (Entidad 51% Propiedad de Distribuidora Eléctrica del Caribe, S. A.) | T31: OK
A32: 2025 | B32: INA_EDEMET_2025_0.pdf | C32: page-111 | D32: markdown.md | E32: 8 | F32: 8. Clientes y Otras Cuentas por Cobrar | G32: Cuentas por cobrar | J32: # **Notas a los Estados Financieros** | T32: OK
A33: 2025 | B33: INA_EDEMET_2025_0.pdf | C33: page-111 | D33: markdown.md | E33: 8 | F33: 8. Clientes y Otras Cuentas por Cobrar, continuación | G33: Cuentas por cobrar | J33: A cada obligación se le asigna una probabilidad individual de no pago que se calcula a partir de un modelo de probabilidad que involucra variables del producto y de su comportamiento de pago. El modelo calcula un porcentaje de pérdida histórica por tipo de mora, la cual se relaciona con un dato macroeconómico buscando una correlación para proyectar un comportamiento según la mejor estimación del crecimiento económico del país. | T33: OK
A34: 2025 | B34: INA_EDEMET_2025_0.pdf | C34: page-111 | D34: markdown.md | E34: 8 | F34: 8. Clientes y Otras Cuentas por Cobrar, continuación | G34: Cuentas por cobrar | J34: La proyección se aplicará al producto de los promedios de desplazamiento por rango de cartera según la mora histórica, la cual refleja la evolución del comportamiento de los saldos de la cartera de clientes y permite establecer los porcentajes de pérdida sobre hechos históricos. | T34: OK
A35: 2025 | B35: INA_EDEMET_2025_0.pdf | C35: page-111 | D35: markdown.md | E35: 8 | F35: 8. Clientes y Otras Cuentas por Cobrar, continuación | G35: Cuentas por cobrar | J35: El movimiento de la reserva para pérdidas crediticias esperadas se presenta a continuación: | T35: OK
... A45: 2025 | B45: INA_EDEMET_2025_0.pdf | C45: page-113 | D45: markdown.md | E45: 8 | F45: 8. Clientes y Otras Cuentas por Cobrar, continuación | G45: Cuentas por cobrar | J45: Las cuentas por cobrar a gobierno y entidades autónomas incluyen subsidios otorgados por el Gobierno al Fondo de Compensación Energética (FACE), Fondo de Estabilización Tarifaria (FET) y Fondo Tarifario de Occidente (FTO). Los subsidios registrados corresponden a lo acordado en la Ley No.15 de febrero de 2001 que establece el régimen y procedimiento a los que se sujetarán los subsidios destinados a los clientes del servicio público de electricidad, cuyo consumo califica como consumo básico o de subsistencia, y en el cual la administración y aplicación está a cargo de la Compañía, para la cual la Compañía efectúa una retención a algunos clientes y a su vez le concede un descuento a aquellos clientes sujetos al subsidio de acuerdo a lo que define la Ley como clientes de consumo básico o de subsistencias. | T45: OK
A46: 2025 | B46: INA_EDEMET_2025_0.pdf | C46: page-113 | D46: markdown.md | E46: 8 | F46: 8. Clientes y Otras Cuentas por Cobrar, continuación | G46: Cuentas por cobrar | J46: Durante el 2025, la Compañía recibió el pago de subsidios de parte de la Empresa de Transmisión Eléctrica, S.A. por un importe total de B/.83,095,239 (2024: B/.49,571,213). | K46: 83095239 | L46: B/. | T46: OK
A47: 2025 | B47: INA_EDEMET_2025_0.pdf | C47: page-113 | D47: markdown.md | E47: 8 | F47: 8. Clientes y Otras Cuentas por Cobrar, continuación | G47: Cuentas por cobrar | J47: Los saldos correspondientes a los reembolsos tarifarios del FACE y del FET que no hayan sido compensados en su totalidad por el Estado a través de ETESA, podrán ser incorporados en las actualizaciones semestrales, de acuerdo con lo dispuesto en el régimen tarifario vigente y sus modificaciones. | T47: OK
A48: 2025 | B48: INA_EDEMET_2025_0.pdf | C48: page-113 | D48: markdown.md | E48: 8 | F48: 8. Clientes y Otras Cuentas por Cobrar, continuación | G48: Cuentas por cobrar | J48: # **Activos Regulatorios** | T48: OK
A49: 2025 | B49: INA_EDEMET_2025_0.pdf | C49: page-113 | D49: markdown.md | E49: 8 | F49: 8. Clientes y Otras Cuentas por Cobrar, continuación | G49: Cuentas por cobrar | J49: Según se establece en el marco regulatorio vigente y dado que los costos estimados de abastecimientos reconocidos en la tarifa fueron diferentes a los costos reales del año 2025, la Compañía mantiene activos regulatorios por B/.10,797,318 (2024: B/.10,313,941), producto de desvíos tarifarios por B/.14,595,699 (2024: B/.9,772,664), menos recuperaciones en tarifa por B/.14,112,322 (2024: B/.14,190,532), según lo establecido en el régimen tarifario. | K49: 10797318 | L49: B/. | T49: OK
A50: 2025 | B50: INA_EDEMET_2025_0.pdf | C50: page-113 | D50: markdown.md | E50: 8 | F50: 8. Clientes y Otras Cuentas por Cobrar, continuación | G50: Cuentas por cobrar | J50: A continuación, el resumen de los movimientos de los desvíos tarifarios por costos de abastecimiento: | T50: OK
A51: 2025 | B51: INA_EDEMET_2025_0.pdf | C51: page-113 | D51: tbl-92.html | E51: 8 | F51: 8. Clientes y Otras Cuentas por Cobrar, continuación | G51: Cuentas por cobrar | J51: [tbl-92.html](tbl-92.html)(tbl-92.html) | T51: OK
A52: 2025 | B52: INA_EDEMET_2025_0.pdf | C52: page-113 | D52: markdown.md | E52: 8 | F52: 8. Clientes y Otras Cuentas por Cobrar, continuación | G52: Cuentas por cobrar | J52: # **Energía suministrada y no facturada** | T52: OK
A53: 2025 | B53: INA_EDEMET_2025_0.pdf | C53: page-113 | D53: markdown.md | E53: 8 | F53: 8. Clientes y Otras Cuentas por Cobrar, continuación | G53: Cuentas por cobrar | J53: La Compañía registra una estimación de aquellos servicios suministrados que se encontraban pendientes de facturación al 31 de diciembre de 2025, los cuales ascienden a B/.10,123,276 (2024: B/.11,643,580). | K53: 10123276 | L53: B/. | T53: OK
A54: 2025 | B54: INA_EDEMET_2025_0.pdf | C54: page-114 | D54: markdown.md | E54: 9 | F54: 9. Efectivo | G54: Working capital | J54: El efectivo se detalla a continuación: | T54: OK
A55: 2025 | B55: INA_EDEMET_2025_0.pdf | C55: page-114 | D55: tbl-94.html | E55: 9 | F55: 9. Efectivo | G55: Working capital | J55: [tbl-94.html](tbl-94.html)(tbl-93.html)(tbl-93.html) | T55: OK
A56: 2025 | B56: INA_EDEMET_2025_0.pdf | C56: page-114 | D56: markdown.md | E56: 9 | F56: 9. Efectivo | G56: Working capital | J56: Durante el 2025, la Compañía mantuvo excedentes de efectivo, por la utilización de su mayor capacidad de las líneas de crédito disponibles, los cuales fueron depositados en cuentas de overnight con vencimientos diarios y un rendimiento de aproximadamente entre 3% y 3.25% (2024: 0.40%). | T56: OK
A57: 2025 | B57: INA_EDEMET_2025_0.pdf | C57: page-114 | D57: markdown.md | E57: 9 | F57: 9. Efectivo | G57: Working capital | J57: Al 31 de diciembre de 2025 y 2024 no existían restricciones de uso sobre los saldos de efectivo y equivalentes de efectivo. | T57: OK
A58: 2025 | B58: INA_EDEMET_2025_0.pdf | C58: page-114 | D58: markdown.md | E58: 10 | F58: 10. Patrimonio | G58: Capital / patrimonio / dividendos | J58: La composición del patrimonio se resume así: | T58: OK
A59: 2025 | B59: INA_EDEMET_2025_0.pdf | C59: page-114 | D59: tbl-94.html | E59: 10 | F59: 10. Patrimonio | G59: Capital / patrimonio / dividendos | J59: [tbl-94.html](tbl-94.html) | T59: OK
A60: 2025 | B60: INA_EDEMET_2025_0.pdf | C60: page-114 | D60: markdown.md | E60: 10 | F60: 10. Patrimonio | G60: Capital / patrimonio / dividendos | J60: El capital social autorizado, emitido y pagado de la Compañía es de cincuenta millones (50,000,000) de acciones comunes sin valor nominal, las que se encuentran emitidas en su totalidad. | K60: -50000000 | L60: B/. | T60: OK
A61: 2025 | B61: INA_EDEMET_2025_0.pdf | C61: page-115 | D61: markdown.md | E61: 10 | F61: 10. Patrimonio | G61: Capital / patrimonio / dividendos | J61: # **Empresa de Distribución Eléctrica Chiriquí, S. A.** (Entidad 51% Propiedad de Distribuidora Eléctrica del Caribe, S. A.) | T61: OK
A62: 2025 | B62: INA_EDEMET_2025_0.pdf | C62: page-115 | D62: markdown.md | E62: 10 | F62: 10. Patrimonio | G62: Capital / patrimonio / dividendos | J62: # **Notas a los Estados Financieros** | T62: OK
A63: 2025 | B63: INA_EDEMET_2025_0.pdf | C63: page-115 | D63: markdown.md | E63: 10 | F63: 10. Patrimonio, continuación | G63: Capital / patrimonio / dividendos | J63: Hasta el 2009, la Compañía readquirió 198,229 acciones por la suma de B/.188,193. El bloque del 51% de las acciones de la Compañía fue adquirido mediante la Licitación Pública Internacional No.COMVA-001-98 por Distribuidora Eléctrica del Caribe, S. A., que mantiene 25,500,000 acciones; el 49% de las acciones fue retenido por el Estado, de lo cual se reservó el 10% de las acciones para ofrecerlas en venta a los trabajadores permanentes de la Compañía. Un resumen de las disposiciones establecidas por la Comisión de Venta de Acciones (COMVA), relacionadas con las acciones de la Compañía es el siguiente: | K63: 198229 | L63: B/. | T63: OK
A64: 2025 | B64: INA_EDEMET_2025_0.pdf | C64: page-115 | D64: markdown.md | E64: 10 | F64: 10. Patrimonio, continuación | G64: Capital / patrimonio / dividendos | J64: - El comprador del bloque de acciones no podrá vender parcialmente dichas acciones mientras se encuentre vigente el contrato de concesión para la distribución de energía eléctrica, el cual tiene un término de 15 años. - El comprador del bloque del 51% de las acciones de la Compañía, renunció al derecho preferente de compra de las acciones remanentes. Igualmente, existen restricciones aplicables a los compradores de las acciones remanentes. | T64: OK
A65: 2025 | B65: INA_EDEMET_2025_0.pdf | C65: page-115 | D65: markdown.md | E65: 10 | F65: 10. Patrimonio, continuación | G65: Capital / patrimonio / dividendos | J65: El Estado reservó el diez por ciento (10%) del total de las acciones de la Compañía con el propósito de ofrecerlas en venta a los trabajadores permanentes de la Compañía. Dichos trabajadores tenían el derecho de adquirir acciones utilizando el monto equivalente a sus prestaciones laborales, incluyendo la indemnización. Estas acciones se reservaron por el término de un año, contado a partir de la firma del contrato de compra-venta del bloque de acciones y se vendieron en un seis por ciento (6%) de descuento con respecto al precio unitario pagado en la adquisición de ese bloque de acciones. Vencido el término de un año, cesó el derecho de los trabajadores a comprar estas acciones con descuento y el Órgano Ejecutivo podrá venderlas a través de los procedimientos de bolsa de valores o subasta pública con un límite de 5% de estas acciones por comprador. | T65: OK
A66: 2025 | B66: INA_EDEMET_2025_0.pdf | C66: page-115 | D66: markdown.md | E66: 10 | F66: 10. Patrimonio, continuación | G66: Capital / patrimonio / dividendos | J66: La Compañía mantiene una reserva voluntaria de B/.1,599,335 (2024: B/.1,599,335) producto de la compensación de cierre del contrato de compra-venta de las acciones en 1998. | K66: 1599335 | L66: B/. | T66: OK
A67: 2025 | B67: INA_EDEMET_2025_0.pdf | C67: page-115 | D67: markdown.md | E67: 10 | F67: 10. Patrimonio, continuación | G67: Capital / patrimonio / dividendos | J67: Las otras reservas corresponden exclusivamente al efecto de las remediaciones de las obligaciones por beneficios post-empleo. | T67: OK
A68: 2025 | B68: INA_EDEMET_2025_0.pdf | C68: page-115 | D68: markdown.md | E68: 10 | F68: 10. Patrimonio, continuación | G68: Capital / patrimonio / dividendos | J68: Los dividendos decretados y pagados se detallan a continuación: | T68: OK
A69: 2025 | B69: INA_EDEMET_2025_0.pdf | C69: page-115 | D69: tbl-95.html | E69: 10 | F69: 10. Patrimonio, continuación | G69: Capital / patrimonio / dividendos | J69: [tbl-95.html](tbl-95.html)(tbl-95.html) | T69: OK
A70: 2025 | B70: INA_EDEMET_2025_0.pdf | C70: page-115 | D70: markdown.md | E70: 10 | F70: 10. Patrimonio, continuación | G70: Capital / patrimonio / dividendos | J70: Los dividendos decretados en el año 2025 estuvieron sujetos a impuesto de dividendos por un monto de B/.1,222,238. El dividendo bruto por acción fue de B/.0.2447530. | K70: 1222238 | L70: B/. | T70: OK
A71: 2025 | B71: INA_EDEMET_2025_0.pdf | C71: page-116 | D71: markdown.md | E71: 10 | F71: 10. Patrimonio, continuación | G71: Capital / patrimonio / dividendos | J71: **Impuesto complementario** | T71: OK
A72: 2025 | B72: INA_EDEMET_2025_0.pdf | C72: page-116 | D72: markdown.md | E72: 10 | F72: 10. Patrimonio, continuación | G72: Capital / patrimonio / dividendos | J72: El impuesto complementario constituye un anticipo del impuesto de dividendos que la Compañía está obligada a pagar cuando no distribuye utilidades, o bien cuando la distribución realizada es inferior a los porcentajes mínimos exigidos por la legislación vigente. Este impuesto es compensable con el impuesto de dividendos que se devenga en el momento en que se efectúe la distribución de utilidades. El mismo se genera al final del año fiscal sobre las utilidades netas del contribuyente (menos el impuesto sobre la renta pagado) en los siguientes escenarios: | T72: OK
A73: 2025 | B73: INA_EDEMET_2025_0.pdf | C73: page-116 | D73: markdown.md | E73: 10 | F73: 10. Patrimonio, continuación | G73: Capital / patrimonio / dividendos | J73: - Sin distribución de utilidades: Cuando se reconoce utilidades, pero no se distribuyen. - Distribución insuficiente: Cuando se decretan dividendos por una suma inferior al 40% (tasa general) o al 20% (en casos específicos, como rentas de fuente extranjera o exportaciones) de las utilidades netas. | T73: OK
A74: 2025 | B74: INA_EDEMET_2025_0.pdf | C74: page-116 | D74: markdown.md | E74: 10 | F74: 10. Patrimonio, continuación | G74: Capital / patrimonio / dividendos | J74: La tasa aplicable es del 10% sobre la diferencia necesaria para alcanzar el mínimo legal requerido (sea el 40% o el 20%, según corresponda). | T74: OK
A75: 2025 | B75: INA_EDEMET_2025_0.pdf | C75: page-116 | D75: markdown.md | E75: 10 | F75: 10. Patrimonio, continuación | G75: Capital / patrimonio / dividendos | J75: El monto abonado por este concepto se reconoce como un crédito fiscal, lo que implica que, al momento de la distribución efectiva de dividendos, la Compañía podrá deducir lo previamente pagado del impuesto definitivo sobre dividendos | T75: OK
A76: 2025 | B76: INA_EDEMET_2025_0.pdf | C76: page-116 | D76: markdown.md | E76: 11 | F76: 11. Deuda Financiera | G76: Deuda / bonos / préstamos / leases | J76: A continuación, se presenta la composición de la deuda financiera: | T76: OK
A77: 2025 | B77: INA_EDEMET_2025_0.pdf | C77: page-116 | D77: tbl-96.html | E77: 11 | F77: 11. Deuda Financiera | G77: Deuda / bonos / préstamos / leases | J77: [tbl-96.html](tbl-96.html)(tbl-96.html) | T77: OK
A78: 2025 | B78: INA_EDEMET_2025_0.pdf | C78: page-117 | D78: markdown.md | E78: 11 | F78: 11. Deuda Financiera | G78: Deuda / bonos / préstamos / leases | J78: # **Empresa de Distribución Eléctrica Chiriquí, S. A.** (Entidad 51% Propiedad de Distribuidora Eléctrica del Caribe, S. A.) | T78: OK
A79: 2025 | B79: INA_EDEMET_2025_0.pdf | C79: page-117 | D79: markdown.md | E79: 11 | F79: 11. Deuda Financiera | G79: Deuda / bonos / préstamos / leases | J79: # **Notas a los Estados Financieros** | T79: OK
A80: 2025 | B80: INA_EDEMET_2025_0.pdf | C80: page-117 | D80: markdown.md | E80: 11 | F80: 11. Deuda Financiera, continuación | G80: Deuda / bonos / préstamos / leases | J80: A continuación, el movimiento del año de la deuda financiera: | T80: OK
A81: 2025 | B81: INA_EDEMET_2025_0.pdf | C81: page-117 | D81: tbl-98.html | E81: 11 | F81: 11. Deuda Financiera, continuación | G81: Deuda / bonos / préstamos / leases | J81: [tbl-98.html](tbl-98.html)(tbl-97.html)(tbl-97.html) | T81: OK
A82: 2025 | B82: INA_EDEMET_2025_0.pdf | C82: page-117 | D82: markdown.md | E82: 11 | F82: 11. Deuda Financiera, continuación | G82: Deuda / bonos / préstamos / leases | J82: # **Deuda financiera a largo plazo** | T82: OK
... A91: 2025 | B91: INA_EDEMET_2025_0.pdf | C91: page-119 | D91: markdown.md | E91: 11 | F91: 11. Deuda Financiera, continuación | G91: Deuda / bonos / préstamos / leases | J91: Durante el mes de diciembre de 2025, la Compañía contrató un préstamo a largo plazo con el Banco Europeo de Inversión, el cual incluye, entre otras cláusulas, los siguientes ratios financieros que la Compañía se compromete a mantener durante toda la vigencia del financiamiento | T91: OK
A92: 2025 | B92: INA_EDEMET_2025_0.pdf | C92: page-119 | D92: markdown.md | E92: 11 | F92: 11. Deuda Financiera, continuación | G92: Deuda / bonos / préstamos / leases | J92: - La deuda neta total combinada (considerando el monto de la Compañía más el de Empresa de Distribución Eléctrica Metro Oeste, S. A. quien actúa como fiador) a EBITDA no exceda 4.50x. Al 31 de diciembre de 2025 este ratio fue de 4.29x, el cual está dentro del compromiso autorizado. - Cumplir con un nivel de liquidez por un importe mínimo, (i) de ochenta millones de dólares (80,000,000 USD) hasta el 29 de junio de 2026 inclusive; y (ii) de cien millones de dólares (100,000,000 USD) desde el 30 de junio de 2026 en adelante. Se entenderá por liquidez el importe disponible para ser utilizado bajo líneas de crédito comprometidas, y/o en efectivo o equivalentes de efectivo. Al 31 de diciembre de 2025 el ratio de liquidez fue de 334,363,606 USD. | K92: 80000000 | L92: B/. | M92: millones | T92: OK
A93: 2025 | B93: INA_EDEMET_2025_0.pdf | C93: page-119 | D93: markdown.md | E93: 11 | F93: 11. Deuda Financiera, continuación | G93: Deuda / bonos / préstamos / leases | J93: A continuación, se presentan los importes de la deuda financiera según su vencimiento: | T93: OK
A94: 2025 | B94: INA_EDEMET_2025_0.pdf | C94: page-119 | D94: tbl-99.html | E94: 11 | F94: 11. Deuda Financiera, continuación | G94: Deuda / bonos / préstamos / leases | J94: [tbl-99.html](tbl-99.html)(tbl-99.html) | T94: OK
A95: 2025 | B95: INA_EDEMET_2025_0.pdf | C95: page-119 | D95: markdown.md | E95: 11 | F95: 11. Deuda Financiera, continuación | G95: Deuda / bonos / préstamos / leases | J95: Los préstamos fueron contratados a tasas de interés variables, exponiendo a la Compañía a riesgo de interés en los flujos de efectivo. | T95: OK
A96: 2025 | B96: INA_EDEMET_2025_0.pdf | C96: page-120 | D96: markdown.md | E96: 11 | F96: 11. Deuda Financiera, continuación | G96: Deuda / bonos / préstamos / leases | J96: # **Notas a los Estados Financieros**--- | T96: OK
A97: 2025 | B97: INA_EDEMET_2025_0.pdf | C97: page-120 | D97: markdown.md | E97: 11 | F97: 11. Deuda Financiera, continuación | G97: Deuda / bonos / préstamos / leases | J97: # **Deuda financiera a corto plazo** | T97: OK
A98: 2025 | B98: INA_EDEMET_2025_0.pdf | C98: page-120 | D98: markdown.md | E98: 11 | F98: 11. Deuda Financiera, continuación | G98: Deuda / bonos / préstamos / leases | J98: El saldo de la deuda financiera a corto plazo es como sigue: | T98: OK
A99: 2025 | B99: INA_EDEMET_2025_0.pdf | C99: page-120 | D99: tbl-100.html | E99: 11 | F99: 11. Deuda Financiera, continuación | G99: Deuda / bonos / préstamos / leases | J99: [tbl-100.html](tbl-100.html)(tbl-100.html) | T99: OK
A100: 2025 | B100: INA_EDEMET_2025_0.pdf | C100: page-120 | D100: markdown.md | E100: 11 | F100: 11. Deuda Financiera, continuación | G100: Deuda / bonos / préstamos / leases | J100: Al 31 de diciembre de 2025, la Compañía tenía saldo utilizado de B/.63,304,195 (2024: B/.65,100,410) en líneas de crédito. La Compañía mantiene líneas de crédito contratadas por B/.100,000,000 (2024: B/.100,000,000), el monto no utilizado de estas líneas de crédito era B/.36,695,805 (2024: B/.34,899,590). | K100: 63304195 | L100: B/. | T100: OK
A101: 2025 | B101: INA_EDEMET_2025_0.pdf | C101: page-120 | D101: markdown.md | E101: 11 | F101: 11. Deuda Financiera, continuación | G101: Deuda / bonos / préstamos / leases | J101: La deuda financiera a corto plazo está garantizada con fianza cruzada de Empresa de Distribución Eléctrica Metro-Oeste, S. A. (EDEMET). | T101: OK
A102: 2025 | B102: INA_EDEMET_2025_0.pdf | C102: page-120 | D102: markdown.md | E102: 11 | F102: 11. Deuda Financiera, continuación | G102: Deuda / bonos / préstamos / leases | J102: La administración considera que el valor en libros de la deuda financiera corriente se aproxima a su valor razonable, debido a su naturaleza de corto plazo. | T102: OK
A103: 2025 | B103: INA_EDEMET_2025_0.pdf | C103: page-121 | D103: markdown.md | E103: 12 | F103: 12. Conciliación de movimiento de pasivo por actividades de financiamiento | G103: Deuda / bonos / préstamos / leases | J103: A continuación, presentamos la conciliación de movimiento de pasivo por actividades de financiamiento: | T103: OK
A104: 2025 | B104: INA_EDEMET_2025_0.pdf | C104: page-121 | D104: tbl-101.html | E104: 12 | F104: 12. Conciliación de movimiento de pasivo por actividades de financiamiento | G104: Deuda / bonos / préstamos / leases | J104: [tbl-101.html](tbl-101.html)(tbl-101.html) | T104: OK
A105: 2025 | B105: INA_EDEMET_2025_0.pdf | C105: page-122 | D105: markdown.md | E105: 12 | F105: 12. Conciliación de movimiento de pasivo por actividades de financiamiento | G105: Deuda / bonos / préstamos / leases | J105: # **Empresa de Distribución Eléctrica Chiriquí, S. A.** (Entidad 51% Propiedad de Distribuidora Eléctrica del Caribe, S. A.) | T105: OK
A106: 2025 | B106: INA_EDEMET_2025_0.pdf | C106: page-122 | D106: markdown.md | E106: 12 | F106: 12. Conciliación de movimiento de pasivo por actividades de financiamiento | G106: Deuda / bonos / préstamos / leases | J106: # **Notas a los Estados Financieros** | T106: OK
A107: 2025 | B107: INA_EDEMET_2025_0.pdf | C107: page-122 | D107: tbl-102.html | E107: 12 | F107: 12. Conciliación de movimiento de pasivo por actividades de financiamiento, continuación | G107: Deuda / bonos / préstamos / leases | J107: [tbl-102.html](tbl-102.html)(tbl-102.html) | T107: OK
A108: 2025 | B108: INA_EDEMET_2025_0.pdf | C108: page-123 | D108: markdown.md | E108: 13 | F108: 13. Otros Pasivos | G108: Otros | J108: # **Otros pasivos no corrientes** | T108: OK
A109: 2025 | B109: INA_EDEMET_2025_0.pdf | C109: page-123 | D109: markdown.md | E109: 13 | F109: 13. Otros Pasivos | G109: Otros | J109: A continuación, detalle de otros pasivos no corrientes: | T109: OK
A110: 2025 | B110: INA_EDEMET_2025_0.pdf | C110: page-123 | D110: tbl-104.html | E110: 13 | F110: 13. Otros Pasivos | G110: Otros | J110: [tbl-104.html](tbl-104.html)(tbl-103.html)(tbl-103.html) | T110: OK
A111: 2025 | B111: INA_EDEMET_2025_0.pdf | C111: page-123 | D111: markdown.md | E111: 13 | F111: 13. Otros Pasivos | G111: Otros | J111: # (a) Convenio reembolsable | T111: OK
A112: 2025 | B112: INA_EDEMET_2025_0.pdf | C112: page-123 | D112: markdown.md | E112: 13 | F112: 13. Otros Pasivos | G112: Otros | J112: La Compañía mantiene contratos con terceros donde se compromete a distribuir energía para la construcción de infraestructura eléctrica o bien a aportar en efectivo para la construcción de la misma, y paralelamente ambas partes convienen reembolsar la totalidad del aporte efectuado o el importe de la infraestructura establecido en el contrato, siempre que el tercero cumpla con las proyecciones de consumo anuales y demandas mínimas estipuladas en el período de tiempo pactado entre las partes. | T112: OK
... A127: 2025 | B127: INA_EDEMET_2025_0.pdf | C127: page-124 | D127: markdown.md | E127: 13 | F127: 13. Otros Pasivos, continuación | G127: Otros | J127: La Ley No.44 de 12 de agosto de 1995 establece la obligación de los empleadores a constituir un fondo de cesantía para pagar a los empleados la prima de antigüedad y la indemnización por despido injustificado. | T127: OK
A128: 2025 | B128: INA_EDEMET_2025_0.pdf | C128: page-124 | D128: markdown.md | E128: 13 | F128: 13. Otros Pasivos, continuación | G128: Otros | J128: Al 31 de diciembre de 2025, la Compañía mantenía un Fondo de Cesantía con un agente fiduciario por la suma de B/.519,730 (2024: B/.478,243), el cual se presenta en el rubro de otros activos no corrientes del estado de situación financiera (véase Nota 7). | K128: 519730 | L128: B/. | T128: OK
A129: 2025 | B129: INA_EDEMET_2025_0.pdf | C129: page-125 | D129: markdown.md | E129: 13 | F129: 13. Otros Pasivos, continuación | G129: Otros | J129: # **Otros pasivos corrientes** | T129: OK
A130: 2025 | B130: INA_EDEMET_2025_0.pdf | C130: page-125 | D130: markdown.md | E130: 13 | F130: 13. Otros Pasivos, continuación | G130: Otros | J130: A continuación, el detalle de otros pasivos corrientes: | T130: OK
A131: 2025 | B131: INA_EDEMET_2025_0.pdf | C131: page-125 | D131: tbl-108.html | E131: 13 | F131: 13. Otros Pasivos, continuación | G131: Otros | J131: [tbl-108.html](tbl-108.html)(tbl-107.html)(tbl-107.html) | T131: OK
A132: 2025 | B132: INA_EDEMET_2025_0.pdf | C132: page-125 | D132: markdown.md | E132: 13 | F132: 13. Otros Pasivos, continuación | G132: Otros | J132: (*) Con base en el comportamiento histórico de las devoluciones de fianzas y depósitos recibidos, la Compañía presenta como corrientes estos importes. | T132: OK
A133: 2025 | B133: INA_EDEMET_2025_0.pdf | C133: page-125 | D133: markdown.md | E133: 14 | F133: 14. Acreedores Comerciales y Otras Cuentas por Pagar | G133: Cuentas por pagar | J133: A continuación, un detalle de los acreedores comerciales y otras cuentas por pagar: | T133: OK
...

Sheet Supuestos
A1: Empresa de Distribución Eléctrica Metro-Oeste, S. A.
A3: COLOR KEY: Input (azul) · Fórmula (negro) · Link inter-hoja (verde)
A4: Escenario (1=Base, 2=Bull, 3=Bear)
A5: Selector escenario | C5: 1 | M5: caso | N5: NOT_DISCLOSED | Q5: Input de escenario desde fuente citada o NOT_DISCLOSED.
A6: Escenario activo | C6: =CHOOSE($C$5,"Base","Bull","Bear") -> Base | M6: moneda del modelo | N6: NOT_DISCLOSED | Q6: Selector de caso activo C5: Base/Bull/Bear.
A8: Años | B8: FY21A | C8: FY22A | D8: FY23A | E8: FY24A | F8: FY25A | G8: FY26E | H8: FY27E | I8: FY28E | J8: FY29E | K8: FY30E | M8: Unidad | N8: Fuente / nota | Q8: Rationale
A10: A. INGRESOS — CRECIMIENTO (% YoY)
A11: Ingresos por actividades ordinarias — driver activo | G11: =CHOOSE($C$5,G13,G14,G12) -> 0.044 | H11: =CHOOSE($C$5,H13,H14,H12) -> 0.044 | I11: =CHOOSE($C$5,I13,I14,I12) -> 0.044 | J11: =CHOOSE($C$5,J13,J14,J12) -> 0.044 | K11: =CHOOSE($C$5,K13,K14,K12) -> 0.044 | M11: % | N11: EEFF:Ingresos por actividades ordinarias | Q11: Selector de caso activo C5: Base/Bull/Bear.
A12: Bear | G12: 0.024 | H12: 0.024 | I12: 0.024 | J12: 0.024 | K12: 0.024 | M12: % | N12: EEFF:Ingresos por actividades ordinarias | Q12: Escenario driver citado; NOT_DISCLOSED si no hay fuente explícita.
A13: Base | G13: 0.044 | H13: 0.044 | I13: 0.044 | J13: 0.044 | K13: 0.044 | M13: % | N13: EEFF:Ingresos por actividades ordinarias | Q13: Escenario driver citado; NOT_DISCLOSED si no hay fuente explícita.
A14: Bull | G14: 0.064 | H14: 0.064 | I14: 0.064 | J14: 0.064 | K14: 0.064 | M14: % | N14: EEFF:Ingresos por actividades ordinarias | Q14: Escenario driver citado; NOT_DISCLOSED si no hay fuente explícita.
A15: Ingresos por actividades ordinarias (hist, ref EEFF) | E15: =EEFF!E7 -> 872479782 | F15: =EEFF!F7 -> 910833173 | M15: moneda del modelo | N15: EEFF:Ingresos por actividades ordinarias | Q15: Mirror histórico desde fuente citada.
A16: Ingresos por actividades ordinarias YoY histórico (ref EEFF) | F16: =EEFF!F7/EEFF!E7-1 -> 0.04395906 | M16: % | N16: EEFF:Ingresos por actividades ordinarias | Q16: Fórmula viva: año actual / año previo - 1.
A18: B. APROVISIONAMIENTOS (% de ingresos)
A19: Aprovisionamientos — driver activo | G19: =CHOOSE($C$5,G21,G22,G20) -> -0.726 | H19: =CHOOSE($C$5,H21,H22,H20) -> -0.726 | I19: =CHOOSE($C$5,I21,I22,I20) -> -0.726 | J19: =CHOOSE($C$5,J21,J22,J20) -> -0.726 | K19: =CHOOSE($C$5,K21,K22,K20) -> -0.726 | M19: % | N19: EEFF:Aprovisionamientos | Q19: Selector de caso activo C5: Base/Bull/Bear.
A20: Bear | G20: -0.746 | H20: -0.746 | I20: -0.746 | J20: -0.746 | K20: -0.746 | M20: % | N20: EEFF:Aprovisionamientos | Q20: Escenario driver citado; NOT_DISCLOSED si no hay fuente explícita.
A21: Base | G21: -0.726 | H21: -0.726 | I21: -0.726 | J21: -0.726 | K21: -0.726 | M21: % | N21: EEFF:Aprovisionamientos | Q21: Escenario driver citado; NOT_DISCLOSED si no hay fuente explícita.
A22: Bull | G22: -0.706 | H22: -0.706 | I22: -0.706 | J22: -0.706 | K22: -0.706 | M22: % | N22: EEFF:Aprovisionamientos | Q22: Escenario driver citado; NOT_DISCLOSED si no hay fuente explícita.
A23: Aprovisionamientos ÷ Ingresos por actividades ordinarias (hist, ref EEFF) | E23: =IF(EEFF!E7=0,"",EEFF!E8/EEFF!E7) -> -0.70568139 | F23: =IF(EEFF!F7=0,"",EEFF!F8/EEFF!F7) -> -0.72582559 | M23: % | N23: EEFF:Aprovisionamientos / EEFF:Ingresos por actividades ordinarias | Q23: Mirror histórico desde fuente citada.
A25: C. REPARACIONES Y CONSERVACIÓN (% de ingresos)
A26: Reparaciones y conservación — driver activo | G26: =CHOOSE($C$5,G28,G29,G27) -> -0.022 | H26: =CHOOSE($C$5,H28,H29,H27) -> -0.022 | I26: =CHOOSE($C$5,I28,I29,I27) -> -0.022 | J26: =CHOOSE($C$5,J28,J29,J27) -> -0.022 | K26: =CHOOSE($C$5,K28,K29,K27) -> -0.022 | M26: % | N26: EEFF:Reparaciones y conservación | Q26: Selector de caso activo C5: Base/Bull/Bear.
A27: Bear | G27: -0.042 | H27: -0.042 | I27: -0.042 | J27: -0.042 | K27: -0.042 | M27: % | N27: EEFF:Reparaciones y conservación | Q27: Escenario driver citado; NOT_DISCLOSED si no hay fuente explícita.
A28: Base | G28: -0.022 | H28: -0.022 | I28: -0.022 | J28: -0.022 | K28: -0.022 | M28: % | N28: EEFF:Reparaciones y conservación | Q28: Escenario driver citado; NOT_DISCLOSED si no hay fuente explícita.
A29: Bull | G29: -0.002 | H29: -0.002 | I29: -0.002 | J29: -0.002 | K29: -0.002 | M29: % | N29: EEFF:Reparaciones y conservación | Q29: Escenario driver citado; NOT_DISCLOSED si no hay fuente explícita.
A30: Reparaciones y conservación ÷ Ingresos por actividades ordinarias (hist, ref EEFF) | E30: =IF(EEFF!E7=0,"",EEFF!E9/EEFF!E7) -> -0.024907649 | F30: =IF(EEFF!F7=0,"",EEFF!F9/EEFF!F7) -> -0.021512672 | M30: % | N30: EEFF:Reparaciones y conservación / EEFF:Ingresos por actividades ordinarias | Q30: Mirror histórico desde fuente citada.
A32: D. GASTOS DE PERSONAL (% de ingresos)
A33: Gastos de personal — driver activo | G33: =CHOOSE($C$5,G35,G36,G34) -> -0.011 | H33: =CHOOSE($C$5,H35,H36,H34) -> -0.011 | I33: =CHOOSE($C$5,I35,I36,I34) -> -0.011 | J33: =CHOOSE($C$5,J35,J36,J34) -> -0.011 | K33: =CHOOSE($C$5,K35,K36,K34) -> -0.011 | M33: % | N33: EEFF:Gastos de personal | Q33: Selector de caso activo C5: Base/Bull/Bear.
A34: Bear | G34: -0.031 | H34: -0.031 | I34: -0.031 | J34: -0.031 | K34: -0.031 | M34: % | N34: EEFF:Gastos de personal | Q34: Escenario driver citado; NOT_DISCLOSED si no hay fuente explícita.
A35: Base | G35: -0.011 | H35: -0.011 | I35: -0.011 | J35: -0.011 | K35: -0.011 | M35: % | N35: EEFF:Gastos de personal | Q35: Escenario driver citado; NOT_DISCLOSED si no hay fuente explícita.
A36: Bull | G36: 0.009 | H36: 0.009 | I36: 0.009 | J36: 0.009 | K36: 0.009 | M36: % | N36: EEFF:Gastos de personal | Q36: Escenario driver citado; NOT_DISCLOSED si no hay fuente explícita.
A37: Gastos de personal ÷ Ingresos por actividades ordinarias (hist, ref EEFF) | E37: =IF(EEFF!E7=0,"",EEFF!E12/EEFF!E7) -> -0.010435968 | F37: =IF(EEFF!F7=0,"",EEFF!F12/EEFF!F7) -> -0.011332902 | M37: % | N37: EEFF:Gastos de personal / EEFF:Ingresos por actividades ordinarias | Q37: Mirror histórico desde fuente citada.
A39: E. OTROS GASTOS (% de ingresos)
A40: Otros gastos — driver activo | G40: =CHOOSE($C$5,G42,G43,G41) -> -0.048 | H40: =CHOOSE($C$5,H42,H43,H41) -> -0.048 | I40: =CHOOSE($C$5,I42,I43,I41) -> -0.048 | J40: =CHOOSE($C$5,J42,J43,J41) -> -0.048 | K40: =CHOOSE($C$5,K42,K43,K41) -> -0.048 | M40: % | N40: EEFF:Otros gastos | Q40: Selector de caso activo C5: Base/Bull/Bear.
A41: Bear | G41: -0.068 | H41: -0.068 | I41: -0.068 | J41: -0.068 | K41: -0.068 | M41: % | N41: EEFF:Otros gastos | Q41: Escenario driver citado; NOT_DISCLOSED si no hay fuente explícita.
A42: Base | G42: -0.048 | H42: -0.048 | I42: -0.048 | J42: -0.048 | K42: -0.048 | M42: % | N42: EEFF:Otros gastos | Q42: Escenario driver citado; NOT_DISCLOSED si no hay fuente explícita.
A43: Bull | G43: -0.028 | H43: -0.028 | I43: -0.028 | J43: -0.028 | K43: -0.028 | M43: % | N43: EEFF:Otros gastos | Q43: Escenario driver citado; NOT_DISCLOSED si no hay fuente explícita.
A44: Otros gastos ÷ Ingresos por actividades ordinarias (hist, ref EEFF) | E44: =IF(EEFF!E7=0,"",EEFF!E13/EEFF!E7) -> -0.05251542 | F44: =IF(EEFF!F7=0,"",EEFF!F13/EEFF!F7) -> -0.047888394 | M44: % | N44: EEFF:Otros gastos / EEFF:Ingresos por actividades ordinarias | Q44: Mirror histórico desde fuente citada.
A46: F. TASA EFECTIVA DE IMPUESTO (% de UAI)
A47: Impuesto sobre la renta — driver activo | G47: =CHOOSE($C$5,G49,G50,G48) -> -0.316 | H47: =CHOOSE($C$5,H49,H50,H48) -> -0.316 | I47: =CHOOSE($C$5,I49,I50,I48) -> -0.316 | J47: =CHOOSE($C$5,J49,J50,J48) -> -0.316 | K47: =CHOOSE($C$5,K49,K50,K48) -> -0.316 | M47: % | N47: EEFF:Impuesto sobre la renta | Q47: Selector de caso activo C5: Base/Bull/Bear.
A48: Bear | G48: -0.316 | H48: -0.316 | I48: -0.316 | J48: -0.316 | K48: -0.316 | M48: % | N48: EEFF:Impuesto sobre la renta | Q48: Escenario driver citado; NOT_DISCLOSED si no hay fuente explícita.
A49: Base | G49: -0.316 | H49: -0.316 | I49: -0.316 | J49: -0.316 | K49: -0.316 | M49: % | N49: EEFF:Impuesto sobre la renta | Q49: Escenario driver citado; NOT_DISCLOSED si no hay fuente explícita.
A50: Bull | G50: -0.316 | H50: -0.316 | I50: -0.316 | J50: -0.316 | K50: -0.316 | M50: % | N50: EEFF:Impuesto sobre la renta | Q50: Escenario driver citado; NOT_DISCLOSED si no hay fuente explícita.
A51: Impuesto sobre la renta ÷ Utilidad antes del impuesto sobre la renta (hist, ref EEFF) | E51: =IF(EEFF!E18=0,"",EEFF!E19/EEFF!E18) -> -0.32736823 | F51: =IF(EEFF!F18=0,"",EEFF!F19/EEFF!F18) -> -0.31553244 | M51: % | N51: EEFF:Impuesto sobre la renta / EEFF:Utilidad antes del impuesto sobre la renta | Q51: Mirror histórico desde fuente citada.

Sheet ModeloFinanciero
A1: Empresa de Distribución Eléctrica Metro-Oeste, S. A.
A2: Estados Financieros Auditados FY24-FY25 (año fiscal al 31 de diciembre)
A3: en B/. sin escala
A5: Años | B5: FY21A | C5: FY22A | D5: FY23A | E5: FY24A | F5: FY25A | G5: FY26E | H5: FY27E | I5: FY28E | J5: FY29E | K5: FY30E
A6: Estado de Resultados
A7: Ingresos por actividades ordinarias | E7: =EEFF!E7 -> 872479782 | F7: =EEFF!F7 -> 910833173 | G7: =F7*(1+Supuestos!G11) -> 9.5090983e+08 | H7: =G7*(1+Supuestos!H11) -> 9.9274987e+08 | I7: =H7*(1+Supuestos!I11) -> 1.0364309e+09 | J7: =I7*(1+Supuestos!J11) -> 1.0820338e+09 | K7: =J7*(1+Supuestos!K11) -> 1.1296433e+09
A8: Aprovisionamientos | E8: =EEFF!E8 -> -615692748 | F8: =EEFF!F8 -> -661106024 | G8: =G7*Supuestos!G19 -> -6.9036054e+08 | H8: =H7*Supuestos!H19 -> -7.207364e+08 | I8: =I7*Supuestos!I19 -> -7.524488e+08 | J8: =J7*Supuestos!J19 -> -7.8555655e+08 | K8: =K7*Supuestos!K19 -> -8.2012104e+08
A9: Reparaciones y conservación | E9: =EEFF!E9 -> -21731420 | F9: =EEFF!F9 -> -19594455 | G9: =G7*Supuestos!G26 -> -20920016 | H9: =H7*Supuestos!H26 -> -21840497 | I9: =I7*Supuestos!I26 -> -22801479 | J9: =J7*Supuestos!J26 -> -23804744 | K9: =K7*Supuestos!K26 -> -24852153
A10: Depreciación y amortización | E10: =EEFF!E10 -> -48347878 | F10: =EEFF!F10 -> -53346452 | G10: =-(G60+G61+G62) -> -53346452 | H10: =-(H60+H61+H62) -> -53346452 | I10: =-(I60+I61+I62) -> -53346452 | J10: =-(J60+J61+J62) -> -53346452 | K10: =-(K60+K61+K62) -> -53346452
A11: Total de ganancia bruta por actividades ordinarias | E11: =EEFF!E11 -> 186707736 | F11: =EEFF!F11 -> 176786242 | G11: =G7+G8+G9+G10 -> 1.8628283e+08 | H11: =H7+H8+H9+H10 -> 1.9682651e+08 | I11: =I7+I8+I9+I10 -> 2.0783412e+08 | J11: =J7+J8+J9+J10 -> 2.1932607e+08 | K11: =K7+K8+K9+K10 -> 2.3132366e+08
A12: Gastos de personal | E12: =EEFF!E12 -> -9105171 | F12: =EEFF!F12 -> -10322383 | G12: =G7*Supuestos!G33 -> -10460008 | H12: =H7*Supuestos!H33 -> -10920249 | I12: =I7*Supuestos!I33 -> -11400739 | J12: =J7*Supuestos!J33 -> -11902372 | K12: =K7*Supuestos!K33 -> -12426076
A13: Otros gastos | E13: =EEFF!E13 -> -45818642 | F13: =EEFF!F13 -> -43618338 | G13: =G7*Supuestos!G40 -> -45643672 | H13: =H7*Supuestos!H40 -> -47651994 | I13: =I7*Supuestos!I40 -> -49748681 | J13: =J7*Supuestos!J40 -> -51937623 | K13: =K7*Supuestos!K40 -> -54222879
A14: Resultado de las actividades de operaciones | E14: =EEFF!E14 -> 131783923 | F14: =EEFF!F14 -> 122845521 | G14: =G11+G12+G13 -> 1.3017915e+08 | H14: =H11+H12+H13 -> 1.3825427e+08 | I14: =I11+I12+I13 -> 1.466847e+08 | J14: =J11+J12+J13 -> 1.5548607e+08 | K14: =K11+K12+K13 -> 1.6467471e+08
A15: Gastos financieros | E15: =EEFF!E15 -> -76941269 | F15: =EEFF!F15 -> -73951611 | G15: =F15 -> -73951611 | H15: =G15 -> -73951611 | I15: =H15 -> -73951611 | J15: =I15 -> -73951611 | K15: =J15 -> -73951611
A16: Ingresos financieros | E16: =EEFF!E16 -> 4648031 | F16: =EEFF!F16 -> 6411378 | G16: =F16 -> 6411378 | H16: =G16 -> 6411378 | I16: =H16 -> 6411378 | J16: =I16 -> 6411378 | K16: =J16 -> 6411378
A17: Pérdida neta en tipos de cambio de moneda extranjera | E17: =EEFF!E17 -> -318727 | F17: =EEFF!F17 -> -995436 | G17: =F17 -> -995436 | H17: =G17 -> -995436 | I17: =H17 -> -995436 | J17: =I17 -> -995436 | K17: =J17 -> -995436
A18: Utilidad antes del impuesto sobre la renta | E18: =EEFF!E18 -> 59171958 | F18: =EEFF!F18 -> 54309852 | G18: =G14+G15+G16+G17 -> 61643477 | H18: =H14+H15+H16+H17 -> 69718603 | I18: =I14+I15+I16+I17 -> 78149035 | J18: =J14+J15+J16+J17 -> 86950406 | K18: =K14+K15+K16+K17 -> 96139037
A19: Impuesto sobre la renta | E19: =EEFF!E19 -> -19371019 | F19: =EEFF!F19 -> -17136520 | G19: =G18*Supuestos!G47 -> -19479339 | H19: =H18*Supuestos!H47 -> -22031079 | I19: =I18*Supuestos!I47 -> -24695095 | J19: =J18*Supuestos!J47 -> -27476328 | K19: =K18*Supuestos!K47 -> -30379936
A20: Utilidad neta | E20: =EEFF!E20 -> 39800939 | F20: =EEFF!F20 -> 37173332 | G20: =G18+G19 -> 42164138 | H20: =H18+H19 -> 47687524 | I20: =I18+I19 -> 53453940 | J20: =J18+J19 -> 59474078 | K20: =K18+K19 -> 65759101
A21: Ganancia (pérdida) actuarial sobre las obligaciones por beneficios post-empleo | E21: =EEFF!E21 -> 6119 | F21: =EEFF!F21 -> -230361 | G21: =F21 -> -230361 | H21: =G21 -> -230361 | I21: =H21 -> -230361 | J21: =I21 -> -230361 | K21: =J21 -> -230361
A22: Resultados integrales del año | E22: =EEFF!E22 -> 39807058 | F22: =EEFF!F22 -> 36942971 | G22: =G20+G21 -> 41933777 | H22: =H20+H21 -> 47457163 | I22: =I20+I21 -> 53223579 | J22: =J20+J21 -> 59243717 | K22: =K20+K21 -> 65528740
A24: Años | B24: FY21A | C24: FY22A | D24: FY23A | E24: FY24A | F24: FY25A | G24: FY26E | H24: FY27E | I24: FY28E | J24: FY29E | K24: FY30E
A25: Balance General
A26: Inmovilizados materiales | E26: =EEFF!E26 -> 1102383248 | F26: =EEFF!F26 -> 1229864857 | G26: =F26 -> 1229864857 | H26: =G26 -> 1229864857 | I26: =H26 -> 1229864857 | J26: =I26 -> 1229864857 | K26: =J26 -> 1229864857
A27: Otros activos no corrientes | E27: =EEFF!E27 -> 6636716 | F27: =EEFF!F27 -> 7488557 | G27: =F27 -> 7488557 | H27: =G27 -> 7488557 | I27: =H27 -> 7488557 | J27: =I27 -> 7488557 | K27: =J27 -> 7488557
A28: Activos intangibles | E28: =EEFF!E28 -> 1435537 | F28: =EEFF!F28 -> 1231687 | G28: =F28 -> 1231687 | H28: =G28 -> 1231687 | I28: =H28 -> 1231687 | J28: =I28 -> 1231687 | K28: =J28 -> 1231687
A29: Activos por derecho de uso | E29: =EEFF!E29 -> 310903 | F29: =EEFF!F29 -> 5557215 | G29: =F29 -> 5557215 | H29: =G29 -> 5557215 | I29: =H29 -> 5557215 | J29: =I29 -> 5557215 | K29: =J29 -> 5557215
A30: Total de activos no corrientes | E30: =EEFF!E30 -> 1110766404 | F30: =EEFF!F30 -> 1244142316 | G30: =F30 -> 1244142316 | H30: =G30 -> 1244142316 | I30: =H30 -> 1244142316 | J30: =I30 -> 1244142316 | K30: =J30 -> 1244142316
A31: Clientes y otras cuentas por cobrar | E31: =EEFF!E31 -> 295555709 | F31: =EEFF!F31 -> 247443512 | G31: =F31 -> 247443512 | H31: =G31 -> 247443512 | I31: =H31 -> 247443512 | J31: =I31 -> 247443512 | K31: =J31 -> 247443512
A32: Efectivo | E32: =EEFF!E32 -> 62979274 | F32: =EEFF!F32 -> 207018868 | G32: =F32 -> 207018868 | H32: =G32 -> 207018868 | I32: =H32 -> 207018868 | J32: =I32 -> 207018868 | K32: =J32 -> 207018868
A33: Otros activos corrientes | E33: =EEFF!E33 -> 2493427 | F33: =EEFF!F33 -> 4814532 | G33: =F33 -> 4814532 | H33: =G33 -> 4814532 | I33: =H33 -> 4814532 | J33: =I33 -> 4814532 | K33: =J33 -> 4814532
A34: Total de activos corrientes | E34: =EEFF!E34 -> 361028410 | F34: =EEFF!F34 -> 459276912 | G34: =F34 -> 459276912 | H34: =G34 -> 459276912 | I34: =H34 -> 459276912 | J34: =I34 -> 459276912 | K34: =J34 -> 459276912
A35: Total de activos | E35: =EEFF!E35 -> 1471794814 | F35: =EEFF!F35 -> 1703419228 | G35: =F35 -> 1703419228 | H35: =G35 -> 1703419228 | I35: =H35 -> 1703419228 | J35: =I35 -> 1703419228 | K35: =J35 -> 1703419228
A36: Deuda financiera a largo plazo | E36: =EEFF!E36 -> 504216550 | F36: =EEFF!F36 -> 827072790 | G36: =F36 -> 827072790 | H36: =G36 -> 827072790 | I36: =H36 -> 827072790 | J36: =I36 -> 827072790 | K36: =J36 -> 827072790
A37: Bonos por pagar a largo plazo | E37: =EEFF!E37 -> 0 | F37: =EEFF!F37 -> 123843760 | G37: =F37 -> 123843760 | H37: =G37 -> 123843760 | I37: =H37 -> 123843760 | J37: =I37 -> 123843760 | K37: =J37 -> 123843760
... A52: Total de pasivos y patrimonio | E52: =EEFF!E52 -> 1471794814 | F52: =EEFF!F52 -> 1703419228 | G52: =F52 -> 1703419228 | H52: =G52 -> 1703419228 | I52: =H52 -> 1703419228 | J52: =I52 -> 1703419228 | K52: =J52 -> 1703419228
A54: Años | B54: FY21A | C54: FY22A | D54: FY23A | E54: FY24A | F54: FY25A | G54: FY26E | H54: FY27E | I54: FY28E | J54: FY29E | K54: FY30E
A55: Estado de Flujos de Efectivo
A56: Utilidad neta | E56: =EEFF!E56 -> 39800939 | F56: =EEFF!F56 -> 37173332 | G56: =F56 -> 37173332 | H56: =G56 -> 37173332 | I56: =H56 -> 37173332 | J56: =I56 -> 37173332 | K56: =J56 -> 37173332
A57: Gastos financieros | E57: =EEFF!E57 -> 76941269 | F57: =EEFF!F57 -> 73951611 | G57: =F57 -> 73951611 | H57: =G57 -> 73951611 | I57: =H57 -> 73951611 | J57: =I57 -> 73951611 | K57: =J57 -> 73951611
A58: Ingresos financieros | E58: =EEFF!E58 -> -4648031 | F58: =EEFF!F58 -> -6411378 | G58: =F58 -> -6411378 | H58: =G58 -> -6411378 | I58: =H58 -> -6411378 | J58: =I58 -> -6411378 | K58: =J58 -> -6411378
A59: Ingresos por subvención de capital | E59: =EEFF!E59 -> -1778843 | F59: =EEFF!F59 -> -2663029 | G59: =F59 -> -2663029 | H59: =G59 -> -2663029 | I59: =H59 -> -2663029 | J59: =I59 -> -2663029 | K59: =J59 -> -2663029
A60: Depreciación de inmovilizados materiales | E60: =EEFF!E60 -> 46727986 | F60: =EEFF!F60 -> 51526696 | G60: =F60 -> 51526696 | H60: =G60 -> 51526696 | I60: =H60 -> 51526696 | J60: =I60 -> 51526696 | K60: =J60 -> 51526696
A61: Depreciación de activo por derecho de uso | E61: =EEFF!E61 -> 428415 | F61: =EEFF!F61 -> 1007377 | G61: =F61 -> 1007377 | H61: =G61 -> 1007377 | I61: =H61 -> 1007377 | J61: =I61 -> 1007377 | K61: =J61 -> 1007377
A62: Amortización de activos intangibles | E62: =EEFF!E62 -> 1191479 | F62: =EEFF!F62 -> 812379 | G62: =F62 -> 812379 | H62: =G62 -> 812379 | I62: =H62 -> 812379 | J62: =I62 -> 812379 | K62: =J62 -> 812379
A63: Pérdida procedente de inmovilizado material | E63: =EEFF!E63 -> 62157 | F63: =EEFF!F63 -> 141306 | G63: =F63 -> 141306 | H63: =G63 -> 141306 | I63: =H63 -> 141306 | J63: =I63 -> 141306 | K63: =J63 -> 141306
A64: Estimación para pérdidas crediticias esperadas | E64: =EEFF!E64 -> 13535038 | F64: =EEFF!F64 -> 8461227 | G64: =F64 -> 8461227 | H64: =G64 -> 8461227 | I64: =H64 -> 8461227 | J64: =I64 -> 8461227 | K64: =J64 -> 8461227
A65: Adiciones de subvención de capital | E65: =EEFF!E65 -> 2100335 | F65: =EEFF!F65 -> 121860 | G65: =F65 -> 121860 | H65: =G65 -> 121860 | I65: =H65 -> 121860 | J65: =I65 -> 121860 | K65: =J65 -> 121860
A66: Impuesto sobre la renta | E66: =EEFF!E66 -> 19371019 | F66: =EEFF!F66 -> 17136520 | G66: =F66 -> 17136520 | H66: =G66 -> 17136520 | I66: =H66 -> 17136520 | J66: =I66 -> 17136520 | K66: =J66 -> 17136520
A67: Pérdida neta en tipos de cambio de moneda extranjera | E67: =EEFF!E67 -> -318727 | F67: =EEFF!F67 -> -995436 | G67: =F67 -> -995436 | H67: =G67 -> -995436 | I67: =H67 -> -995436 | J67: =I67 -> -995436 | K67: =J67 -> -995436
... A91: Efectivo y equivalentes de efectivo al final del año | E91: =EEFF!E91 -> 62979274 | F91: =EEFF!F91 -> 207018868 | G91: =F91 -> 207018868 | H91: =G91 -> 207018868 | I91: =H91 -> 207018868 | J91: =I91 -> 207018868 | K91: =J91 -> 207018868

Sheet PP&E_Schedule
A1: Empresa de Distribución Eléctrica Metro-Oeste, S. A.
A2: PP&E_Schedule — propiedad, planta y equipo (saldo + capex − depreciación ± bajas, tie EEFF)
A3: Balance: EEFF/ModeloFinanciero (PP&E neto). Movimientos: Estado de Flujos de Efectivo, líneas explícitamente identificadas — sin desglose de notas (nota de PP&E no extraída aún) las líneas no reveladas se marcan NOT_DISCLOSED, nunca se estiman.
A5: Años | B5: FY21A | C5: FY22A | D5: FY23A | E5: FY24A | F5: FY25A | G5: FY26E | H5: FY27E | I5: FY28E | J5: FY29E | K5: FY30E
A7: A. SALDO PP&E, NETO (balance)
A8: PP&E, neto (referencia EEFF/ModeloFinanciero) | B8: =ModeloFinanciero!B26 -> 0 | C8: =ModeloFinanciero!C26 -> 0 | D8: =ModeloFinanciero!D26 -> 0 | E8: =EEFF!E26 -> 1102383248 | F8: =EEFF!F26 -> 1229864857 | G8: =ModeloFinanciero!G26 -> 1229864857 | H8: =ModeloFinanciero!H26 -> 1229864857 | I8: =ModeloFinanciero!I26 -> 1229864857 | J8: =ModeloFinanciero!J26 -> 1229864857 | K8: =ModeloFinanciero!K26 -> 1229864857
A10: B. MOVIMIENTOS (Estado de Flujos de Efectivo)
A11: Saldo inicial (PP&E neto EOP año anterior) | C11: =B8 -> 0 | D11: =C8 -> 0 | E11: =D8 -> 0 | F11: =E8 -> 1102383248 | G11: =F8 -> 1229864857 | H11: =G8 -> 1229864857 | I11: =H8 -> 1229864857 | J11: =I8 -> 1229864857 | K11: =J8 -> 1229864857
A12: (+) Capex / adquisición de PP&E | B12: =ModeloFinanciero!B76 -> 0 | C12: =ModeloFinanciero!C76 -> 0 | D12: =ModeloFinanciero!D76 -> 0 | E12: =EEFF!E76 -> -121066785 | F12: =EEFF!F76 -> -179149611 | G12: =ModeloFinanciero!G76 -> -179149611 | H12: =ModeloFinanciero!H76 -> -179149611 | I12: =ModeloFinanciero!I76 -> -179149611 | J12: =ModeloFinanciero!J76 -> -179149611 | K12: =ModeloFinanciero!K76 -> -179149611
A13: (−) Depreciación de PP&E | B13: =ModeloFinanciero!B60 -> 0 | C13: =ModeloFinanciero!C60 -> 0 | D13: =ModeloFinanciero!D60 -> 0 | E13: =EEFF!E60 -> 46727986 | F13: =EEFF!F60 -> 51526696 | G13: =ModeloFinanciero!G60 -> 51526696 | H13: =ModeloFinanciero!H60 -> 51526696 | I13: =ModeloFinanciero!I60 -> 51526696 | J13: =ModeloFinanciero!J60 -> 51526696 | K13: =ModeloFinanciero!K60 -> 51526696
A15: BAJAS_A_VALOR_EN_LIBROS_NOT_DISCLOSED: el filing no divulga el valor en libros de los activos dados de baja (solo producto de venta / pérdida P&L); el roll-forward no resta bajas — el residual, si existe, absorbe ese componente no divulgado.
A17: Saldo final computado (inicial + capex − depreciación; N/A en el primer año, sin saldo inicial) | C17: =C11-C12-C13 -> 0 | D17: =D11-D12-D13 -> 0 | E17: =E11-E12-E13 -> 74338799 | F17: =F11-F12-F13 -> 1230006163 | G17: =G11-G12-G13 -> 1357487772 | H17: =H11-H12-H13 -> 1357487772 | I17: =I11-I12-I13 -> 1357487772 | J17: =J11-J12-J13 -> 1357487772 | K17: =K11-K12-K13 -> 1357487772
A19: C. TIE-OUT
A20: CHECK Δ saldo final computado − PP&E balance (residual = capex/depreciación/bajas no desglosadas) | C20: =C17-C8 -> 0 | D20: =D17-D8 -> 0 | E20: =E17-E8 -> -1028044449 | F20: =F17-F8 -> 141306 | G20: =G17-G8 -> 127622915 | H20: =H17-H8 -> 127622915 | I20: =I17-I8 -> 127622915 | J20: =J17-J8 -> 127622915 | K20: =K17-K8 -> 127622915

Sheet Intangibles
A1: Empresa de Distribución Eléctrica Metro-Oeste, S. A.
A2: Intangibles — activos intangibles amortizables + plusvalía (memo)
A3: Balance: EEFF/ModeloFinanciero (intangibles neto). Movimientos: Flujo de Efectivo. Plusvalía (si existe) se presenta aparte — no amortiza bajo NIIF, solo deterioro (no computado sin nota).
A5: Años | B5: FY21A | C5: FY22A | D5: FY23A | E5: FY24A | F5: FY25A | G5: FY26E | H5: FY27E | I5: FY28E | J5: FY29E | K5: FY30E
A7: A. INTANGIBLES AMORTIZABLES
A8: Intangibles, neto (referencia EEFF/ModeloFinanciero) | B8: =ModeloFinanciero!B28 -> 0 | C8: =ModeloFinanciero!C28 -> 0 | D8: =ModeloFinanciero!D28 -> 0 | E8: =EEFF!E28 -> 1435537 | F8: =EEFF!F28 -> 1231687 | G8: =ModeloFinanciero!G28 -> 1231687 | H8: =ModeloFinanciero!H28 -> 1231687 | I8: =ModeloFinanciero!I28 -> 1231687 | J8: =ModeloFinanciero!J28 -> 1231687 | K8: =ModeloFinanciero!K28 -> 1231687
A10: Saldo inicial (intangibles neto EOP año anterior) | C10: =B8 -> 0 | D10: =C8 -> 0 | E10: =D8 -> 0 | F10: =E8 -> 1435537 | G10: =F8 -> 1231687 | H10: =G8 -> 1231687 | I10: =H8 -> 1231687 | J10: =I8 -> 1231687 | K10: =J8 -> 1231687
A11: (+) Adquisición de activos intangibles | B11: =ModeloFinanciero!B77 -> 0 | C11: =ModeloFinanciero!C77 -> 0 | D11: =ModeloFinanciero!D77 -> 0 | E11: =EEFF!E77 -> -604998 | F11: =EEFF!F77 -> -608529 | G11: =ModeloFinanciero!G77 -> -608529 | H11: =ModeloFinanciero!H77 -> -608529 | I11: =ModeloFinanciero!I77 -> -608529 | J11: =ModeloFinanciero!J77 -> -608529 | K11: =ModeloFinanciero!K77 -> -608529
A12: (−) Amortización de intangibles | B12: =ModeloFinanciero!B62 -> 0 | C12: =ModeloFinanciero!C62 -> 0 | D12: =ModeloFinanciero!D62 -> 0 | E12: =EEFF!E62 -> 1191479 | F12: =EEFF!F62 -> 812379 | G12: =ModeloFinanciero!G62 -> 812379 | H12: =ModeloFinanciero!H62 -> 812379 | I12: =ModeloFinanciero!I62 -> 812379 | J12: =ModeloFinanciero!J62 -> 812379 | K12: =ModeloFinanciero!K62 -> 812379
A13: Saldo final computado (inicial + adiciones − amortización; N/A en el primer año) | C13: =C10-C11-C12 -> 0 | D13: =D10-D11-D12 -> 0 | E13: =E10-E11-E12 -> -586481 | F13: =F10-F11-F12 -> 1231687 | G13: =G10-G11-G12 -> 1027837 | H13: =H10-H11-H12 -> 1027837 | I13: =I10-I11-I12 -> 1027837 | J13: =J10-J11-J12 -> 1027837 | K13: =K10-K11-K12 -> 1027837
A15: B. TIE-OUT
A16: CHECK Δ saldo final computado − intangibles balance (residual = bajas/otros no desglosados) | C16: =C13-C8 -> 0 | D16: =D13-D8 -> 0 | E16: =E13-E8 -> -2022018 | F16: =F13-F8 -> 0 | G16: =G13-G8 -> -203850 | H16: =H13-H8 -> -203850 | I16: =I13-I8 -> -203850 | J16: =J13-J8 -> -203850 | K16: =K13-K8 -> -203850

Sheet ROU_Lease_Schedule
A1: Empresa de Distribución Eléctrica Metro-Oeste, S. A.
A2: ROU_Lease_Schedule — activo por derecho de uso + pasivo por arrendamiento (NIIF 16)
A3: Balance: EEFF/ModeloFinanciero. Movimientos: Flujo de Efectivo. Nuevos arrendamientos reconocidos (no-cash) NOT_DISCLOSED salvo nota específica — no se estiman.
A5: Años | B5: FY21A | C5: FY22A | D5: FY23A | E5: FY24A | F5: FY25A | G5: FY26E | H5: FY27E | I5: FY28E | J5: FY29E | K5: FY30E
A7: A. ACTIVO POR DERECHO DE USO
A8: Activo por derecho de uso, neto (referencia EEFF/ModeloFinanciero) | B8: =ModeloFinanciero!B29 -> 0 | C8: =ModeloFinanciero!C29 -> 0 | D8: =ModeloFinanciero!D29 -> 0 | E8: =EEFF!E29 -> 310903 | F8: =EEFF!F29 -> 5557215 | G8: =ModeloFinanciero!G29 -> 5557215 | H8: =ModeloFinanciero!H29 -> 5557215 | I8: =ModeloFinanciero!I29 -> 5557215 | J8: =ModeloFinanciero!J29 -> 5557215 | K8: =ModeloFinanciero!K29 -> 5557215
A10: Saldo inicial (ROU neto EOP año anterior) | C10: =B8 -> 0 | D10: =C8 -> 0 | E10: =D8 -> 0 | F10: =E8 -> 310903 | G10: =F8 -> 5557215 | H10: =G8 -> 5557215 | I10: =H8 -> 5557215 | J10: =I8 -> 5557215 | K10: =J8 -> 5557215
A12: NOT_DISCLOSED: nuevos arrendamientos reconocidos (adición no-cash) no identificables en el Flujo de Efectivo.
A13: (−) Depreciación/amortización del activo por derecho de uso | B13: =ModeloFinanciero!B61 -> 0 | C13: =ModeloFinanciero!C61 -> 0 | D13: =ModeloFinanciero!D61 -> 0 | E13: =EEFF!E61 -> 428415 | F13: =EEFF!F61 -> 1007377 | G13: =ModeloFinanciero!G61 -> 1007377 | H13: =ModeloFinanciero!H61 -> 1007377 | I13: =ModeloFinanciero!I61 -> 1007377 | J13: =ModeloFinanciero!J61 -> 1007377 | K13: =ModeloFinanciero!K61 -> 1007377
A14: Saldo final computado (inicial − depreciación − disposiciones; sin adiciones no divulgadas; N/A en el primer año) | C14: =C10-C13 -> 0 | D14: =D10-D13 -> 0 | E14: =E10-E13 -> -428415 | F14: =F10-F13 -> -696474 | G14: =G10-G13 -> 4549838 | H14: =H10-H13 -> 4549838 | I14: =I10-I13 -> 4549838 | J14: =J10-J13 -> 4549838 | K14: =K10-K13 -> 4549838
A15: CHECK Δ ROU computado − ROU balance (residual = adiciones no divulgadas) | C15: =C14-C8 -> 0 | D15: =D14-D8 -> 0 | E15: =E14-E8 -> -739318 | F15: =F14-F8 -> -6253689 | G15: =G14-G8 -> -1007377 | H15: =H14-H8 -> -1007377 | I15: =I14-I8 -> -1007377 | J15: =J14-J8 -> -1007377 | K15: =K14-K8 -> -1007377
A17: B. PASIVO POR ARRENDAMIENTO
A18: Pasivo por arrendamiento — no corriente | B18: =ModeloFinanciero!B40 -> 0 | C18: =ModeloFinanciero!C40 -> 0 | D18: =ModeloFinanciero!D40 -> 0 | E18: =EEFF!E40 -> 153995 | F18: =EEFF!F40 -> 5038023 | G18: =ModeloFinanciero!G40 -> 5038023 | H18: =ModeloFinanciero!H40 -> 5038023 | I18: =ModeloFinanciero!I40 -> 5038023 | J18: =ModeloFinanciero!J40 -> 5038023 | K18: =ModeloFinanciero!K40 -> 5038023
A19: Pasivo por arrendamiento — corriente | B19: =ModeloFinanciero!B48 -> 0 | C19: =ModeloFinanciero!C48 -> 0 | D19: =ModeloFinanciero!D48 -> 0 | E19: =EEFF!E48 -> 254137 | F19: =EEFF!F48 -> 698172 | G19: =ModeloFinanciero!G48 -> 698172 | H19: =ModeloFinanciero!H48 -> 698172 | I19: =ModeloFinanciero!I48 -> 698172 | J19: =ModeloFinanciero!J48 -> 698172 | K19: =ModeloFinanciero!K48 -> 698172
A20: Total pasivo por arrendamiento | B20: =B18+B19 -> 0 | C20: =C18+C19 -> 0 | D20: =D18+D19 -> 0 | E20: =E18+E19 -> 408132 | F20: =F18+F19 -> 5736195 | G20: =G18+G19 -> 5736195 | H20: =H18+H19 -> 5736195 | I20: =I18+I19 -> 5736195 | ... K20: =K18+K19 -> 5736195
A22: Saldo inicial (pasivo total EOP año anterior) | C22: =B20 -> 0 | D22: =C20 -> 0 | E22: =D20 -> 0 | F22: =E20 -> 408132 | G22: =F20 -> 5736195 | H22: =G20 -> 5736195 | I22: =H20 -> 5736195 | J22: =I20 -> 5736195 | K22: =J20 -> 5736195
A24: NOT_DISCLOSED: nuevos arrendamientos reconocidos (adición de pasivo no-cash) no identificables en el Flujo de Efectivo.
A25: NOT_DISCLOSED: sin línea de pago de arrendamientos identificable en el Flujo de Efectivo.
A26: Saldo final computado (inicial − pagos de principal; sin adiciones no divulgadas; N/A en el primer año) | C26: =C22 -> 0 | D26: =D22 -> 0 | E26: =E22 -> 0 | F26: =F22 -> 408132 | G26: =G22 -> 5736195 | H26: =H22 -> 5736195 | I26: =I22 -> 5736195 | J26: =J22 -> 5736195 | K26: =K22 -> 5736195
A27: CHECK Δ pasivo computado − pasivo balance (residual = adiciones no divulgadas) | C27: =C26-C20 -> 0 | D27: =D26-D20 -> 0 | E27: =E26-E20 -> -408132 | F27: =F26-F20 -> -5328063 | G27: =G26-G20 -> 0 | H27: =H26-H20 -> 0 | I27: =I26-I20 -> 0 | J27: =J26-J20 -> 0 | K27: =K26-K20 -> 0
A29: C. MEMO (informativo, no es un CHECK)
A30: Activo ROU − Pasivo por arrendamiento (delta esperado por incentivos/prepagos; no es un error) | B30: =B8-B20 -> 0 | C30: =C8-C20 -> 0 | D30: =D8-D20 -> 0 | E30: =E8-E20 -> -97229 | F30: =F8-F20 -> -178980 | G30: =G8-G20 -> -178980 | H30: =H8-H20 -> -178980 | I30: =I8-I20 -> -178980 | ... K30: =K8-K20 -> -178980

Sheet Debt_Schedule
A1: Empresa de Distribución Eléctrica Metro-Oeste, S. A.
A2: Debt_Schedule — deuda financiera (saldo + draws − amortización; tie balance e intereses P&L)
A3: Balance: EEFF/ModeloFinanciero (deuda corriente + no corriente, excl. arrendamientos → ver ROU_Lease_Schedule). Movimientos e intereses: Flujo de Efectivo / Estado de Resultados.
A5: Años | B5: FY21A | C5: FY22A | D5: FY23A | E5: FY24A | F5: FY25A | G5: FY26E | H5: FY27E | I5: FY28E | J5: FY29E | K5: FY30E
A7: A. SALDO DE DEUDA (balance)
A8: Deuda financiera — no corriente | B8: =SUM(ModeloFinanciero!B36,ModeloFinanciero!B37) -> 0 | C8: =SUM(ModeloFinanciero!C36,ModeloFinanciero!C37) -> 0 | D8: =SUM(ModeloFinanciero!D36,ModeloFinanciero!D37) -> 0 | E8: =SUM(EEFF!E36,EEFF!E37) -> 504216550 | F8: =SUM(EEFF!F36,EEFF!F37) -> 950916550 | G8: =SUM(ModeloFinanciero!G36,ModeloFinanciero!G37) -> 950916550 | H8: =SUM(ModeloFinanciero!H36,ModeloFinanciero!H37) -> 950916550 | I8: =SUM(ModeloFinanciero!I36,ModeloFinanciero!I37) -> 950916550 | J8: =SUM(ModeloFinanciero!J36,ModeloFinanciero!J37) -> 950916550 | K8: =SUM(ModeloFinanciero!K36,ModeloFinanciero!K37) -> 950916550
A9: Deuda financiera — corriente | B9: =SUM(ModeloFinanciero!B42,ModeloFinanciero!B43) -> 0 | C9: =SUM(ModeloFinanciero!C42,ModeloFinanciero!C43) -> 0 | D9: =SUM(ModeloFinanciero!D42,ModeloFinanciero!D43) -> 0 | E9: =SUM(EEFF!E42,EEFF!E43) -> 429069814 | F9: =SUM(EEFF!F42,EEFF!F43) -> 145761703 | G9: =SUM(ModeloFinanciero!G42,ModeloFinanciero!G43) -> 145761703 | H9: =SUM(ModeloFinanciero!H42,ModeloFinanciero!H43) -> 145761703 | I9: =SUM(ModeloFinanciero!I42,ModeloFinanciero!I43) -> 145761703 | J9: =SUM(ModeloFinanciero!J42,ModeloFinanciero!J43) -> 145761703 | K9: =SUM(ModeloFinanciero!K42,ModeloFinanciero!K43) -> 145761703
A10: Total deuda financiera | B10: =B8+B9 -> 0 | C10: =C8+C9 -> 0 | D10: =D8+D9 -> 0 | E10: =E8+E9 -> 933286364 | F10: =F8+F9 -> 1096678253 | G10: =G8+G9 -> 1096678253 | H10: =H8+H9 -> 1096678253 | I10: =I8+I9 -> 1096678253 | ... K10: =K8+K9 -> 1096678253
A12: B. MOVIMIENTOS (Estado de Flujos de Efectivo)
A13: Saldo inicial (deuda total EOP año anterior) | C13: =B10 -> 0 | D13: =C10 -> 0 | E13: =D10 -> 0 | F13: =E10 -> 933286364 | G13: =F10 -> 1096678253 | H13: =G10 -> 1096678253 | I13: =H10 -> 1096678253 | J13: =I10 -> 1096678253 | K13: =J10 -> 1096678253
A14: (+) Desembolsos / producto de nueva deuda | B14: =ModeloFinanciero!B81 -> 0 | C14: =ModeloFinanciero!C81 -> 0 | D14: =ModeloFinanciero!D81 -> 0 | E14: =EEFF!E81 -> 589173940 | F14: =EEFF!F81 -> 535436240 | G14: =ModeloFinanciero!G81 -> 535436240 | H14: =ModeloFinanciero!H81 -> 535436240 | I14: =ModeloFinanciero!I81 -> 535436240 | J14: =ModeloFinanciero!J81 -> 535436240 | K14: =ModeloFinanciero!K81 -> 535436240
A15: (−) Abonos / cancelaciones de deuda | B15: =ModeloFinanciero!B80 -> 0 | C15: =ModeloFinanciero!C80 -> 0 | D15: =ModeloFinanciero!D80 -> 0 | E15: =EEFF!E80 -> -469071611 | F15: =EEFF!F80 -> -495046445 | G15: =ModeloFinanciero!G80 -> -495046445 | H15: =ModeloFinanciero!H80 -> -495046445 | I15: =ModeloFinanciero!I80 -> -495046445 | J15: =ModeloFinanciero!J80 -> -495046445 | K15: =ModeloFinanciero!K80 -> -495046445
A16: Saldo final computado (inicial + desembolsos − abonos; N/A en el primer año) | C16: =C13+C14+C15 -> 0 | D16: =D13+D14+D15 -> 0 | E16: =E13+E14+E15 -> 120102329 | F16: =F13+F14+F15 -> 973676159 | G16: =G13+G14+G15 -> 1137068048 | H16: =H13+H14+H15 -> 1137068048 | I16: =I13+I14+I15 -> 1137068048 | J16: =J13+J14+J15 -> 1137068048 | K16: =K13+K14+K15 -> 1137068048
A18: C. TIE-OUT E INTERESES (P&L)
A19: CHECK Δ deuda computada − deuda balance (residual = costos de emisión/FX/reclasificaciones no desglosadas) | C19: =C16-C10 -> 0 | D19: =D16-D10 -> 0 | E19: =E16-E10 -> -813184035 | F19: =F16-F10 -> -123002094 | G19: =G16-G10 -> 40389795 | H19: =H16-H10 -> 40389795 | I19: =I16-I10 -> 40389795 | J19: =J16-J10 -> 40389795 | K19: =K16-K10 -> 40389795
A20: Intereses financieros del período (ABS, Estado de Resultados) | B20: =ABS(ModeloFinanciero!B15) -> 0 | C20: =ABS(ModeloFinanciero!C15) -> 0 | D20: =ABS(ModeloFinanciero!D15) -> 0 | E20: =ABS(EEFF!E15) -> 76941269 | F20: =ABS(EEFF!F15) -> 73951611 | G20: =ABS(ModeloFinanciero!G15) -> 73951611 | H20: =ABS(ModeloFinanciero!H15) -> 73951611 | I20: =ABS(ModeloFinanciero!I15) -> 73951611 | J20: =ABS(ModeloFinanciero!J15) -> 73951611 | K20: =ABS(ModeloFinanciero!K15) -> 73951611
A21: Tasa de interés efectiva (memo: intereses ÷ deuda promedio BOP/EOP; N/A en el primer año) | C21: =IF((C13+C10)=0,"",C20/((C13+C10)/2)) | D21: =IF((D13+D10)=0,"",D20/((D13+D10)/2)) | E21: =E20/((E13+E10)/2) -> 0.16488245 | F21: =F20/((F13+F10)/2) -> 0.07286 | G21: =G20/((G13+G10)/2) -> 0.067432368 | H21: =H20/((H13+H10)/2) -> 0.067432368 | I21: =I20/((I13+I10)/2) -> 0.067432368 | J21: =J20/((J13+J10)/2) -> 0.067432368 | K21: =K20/((K13+K10)/2) -> 0.067432368

Sheet _CHECKS
A1: Empresa de Distribución Eléctrica Metro-Oeste, S. A.
A2: _CHECKS panel — utility template, live formulas, known residuals signed visible
A3: Status semantics: PASS = zero undocumented hard failures; KNOWN_RESIDUAL = signed G7 residual; SOURCE_GAP = unresolved semantic anchor/schedule.
A4: MASTER_STATUS | B4: MODEL STATUS | C4: =IF(COUNTIF($C$6:$C$32,"FAIL")=0,"PASS","FAIL") -> PASS | G4: Master PASS counts only FAIL rows; KNOWN_RESIDUAL/SOURCE_GAP remain visible but non-blocking.
A5: check_id | B5: description | C5: status | D5: hardness | E5: tolerance | F5: expected | G5: note | H5: FY21A | I5: FY22A | J5: FY23A | K5: FY24A | L5: FY25A | M5: FY26E | N5: FY27E | O5: FY28E | P5: FY29E | Q5: FY30E
A7: UNIVERSAL CHECKS
A8: BS_BALANCE | B8: UNIVERSAL | expected 0; hard fail if ABS(value) > hard_tie_tolerance. Observed: UEPII critical gate <10 for BS/cash; BG hard reconciliation >=1000 because full USD. | source applies_to: all 16 archetypes | C8: =IF(SUMPRODUCT((ABS(H8:Q8)>1000)*1)=0,"PASS","FAIL") -> PASS | D8: hard | E8: 1000 USD | F8: 0 | G8: expected 0; hard fail if ABS(value) > hard_tie_tolerance. Observed: UEPII critical gate <10 for BS/cash; BG hard reconciliation >=1000 because full USD. Default full-USD hard tie threshold is $1,000 unless the workbook declares a tighter scale-aware tolerance. | H8: =ModeloFinanciero!B35-ModeloFinanciero!B52 -> 0 | I8: =ModeloFinanciero!C35-ModeloFinanciero!C52 -> 0 | J8: =ModeloFinanciero!D35-ModeloFinanciero!D52 -> 0 | K8: =ModeloFinanciero!E35-ModeloFinanciero!E52 -> 0 | L8: =ModeloFinanciero!F35-ModeloFinanciero!F52 -> 0 | M8: =ModeloFinanciero!G35-ModeloFinanciero!G52 -> 0 | N8: =ModeloFinanciero!H35-ModeloFinanciero!H52 -> 0 | O8: =ModeloFinanciero!I35-ModeloFinanciero!I52 -> 0 | ... Q8: =ModeloFinanciero!K35-ModeloFinanciero!K52 -> 0
A9: CASH_TIE | B9: UNIVERSAL | expected 0; use hard_tie_tolerance; if cash includes restricted cash/time deposits, define cash_component role explicitly. | source applies_to: all 16 archetypes | C9: =IF(SUMPRODUCT((ABS(H9:Q9)>1000)*1)=0,"PASS","FAIL") -> PASS | D9: hard | E9: 1000 USD | F9: 0 | G9: Observed hard tie threshold for model-to-model cash residuals; define cash-component role when restricted cash/time deposits exist. | H9: =ModeloFinanciero!B91-ModeloFinanciero!B32 -> 0 | I9: =ModeloFinanciero!C91-ModeloFinanciero!C32 -> 0 | J9: =ModeloFinanciero!D91-ModeloFinanciero!D32 -> 0 | K9: =ModeloFinanciero!E91-ModeloFinanciero!E32 -> 0 | L9: =ModeloFinanciero!F91-ModeloFinanciero!F32 -> 0
A10: CF_ROLLFORWARD | B10: UNIVERSAL | expected 0; hard_tie_tolerance; historical rows may be WARN if source CF transcript is incomplete. | source applies_to: all 16 where CF is modeled | C10: =IF(SUMPRODUCT((ABS(H10:Q10)>1000)*1)=0,"PASS","FAIL") -> PASS | D10: hard | E10: 1000 USD | F10: 0 | G10: expected 0; hard_tie_tolerance; historical rows may be WARN if source CF transcript is incomplete. Default full-USD hard tie threshold is $1,000 unless the workbook declares a tighter scale-aware tolerance. | H10: =ModeloFinanciero!B75+ModeloFinanciero!B79+ModeloFinanciero!B88-(ModeloFinanciero!B91-ModeloFinanciero!B90) -> 0 | I10: =ModeloFinanciero!C75+ModeloFinanciero!C79+ModeloFinanciero!C88-(ModeloFinanciero!C91-ModeloFinanciero!C90) -> 0 | J10: =ModeloFinanciero!D75+ModeloFinanciero!D79+ModeloFinanciero!D88-(ModeloFinanciero!D91-ModeloFinanciero!D90) -> 0 | K10: =ModeloFinanciero!E75+ModeloFinanciero!E79+ModeloFinanciero!E88-(ModeloFinanciero!E91-ModeloFinanciero!E90) -> 0 | L10: =ModeloFinanciero!F75+ModeloFinanciero!F79+ModeloFinanciero!F88-(ModeloFinanciero!F91-ModeloFinanciero!F90) -> 0 | M10: =ModeloFinanciero!G75+ModeloFinanciero!G79+ModeloFinanciero!G88-(ModeloFinanciero!G91-ModeloFinanciero!G90) -> 0 | N10: =ModeloFinanciero!H75+ModeloFinanciero!H79+ModeloFinanciero!H88-(ModeloFinanciero!H91-ModeloFinanciero!H90) -> 0 | O10: =ModeloFinanciero!I75+ModeloFinanciero!I79+ModeloFinanciero!I88-(ModeloFinanciero!I91-ModeloFinanciero!I90) -> 0 | ... Q10: =ModeloFinanciero!K75+ModeloFinanciero!K79+ModeloFinanciero!K88-(ModeloFinanciero!K91-ModeloFinanciero!K90) -> 0
A11: NI_TIE_TO_EQUITY | B11: UNIVERSAL | expected 0; hard_tie_tolerance. | source applies_to: all 16 | C11: =IF(SUMPRODUCT((ABS(H11:Q11)>1000)*1)=0,"PASS","FAIL") -> PASS | D11: hard | E11: 1000 USD | F11: 0 | G11: expected 0; hard_tie_tolerance. Default full-USD hard tie threshold is $1,000 unless the workbook declares a tighter scale-aware tolerance. | H11: =ModeloFinanciero!B20-ModeloFinanciero!B56 -> 0 | I11: =ModeloFinanciero!C20-ModeloFinanciero!C56 -> 0 | J11: =ModeloFinanciero!D20-ModeloFinanciero!D56 -> 0 | K11: =ModeloFinanciero!E20-ModeloFinanciero!E56 -> 0 | L11: =ModeloFinanciero!F20-ModeloFinanciero!F56 -> 0
A12: NI_SIGN_SANITY | B12: UNIVERSAL | expected 0; sign convention must be stated in row description. | source applies_to: all 16 | C12: SOURCE_GAP | D12: hard | E12: 1000 USD | F12: 0 | G12: Sign convention diagnostic remains visible; tax-sign taxonomy is not a signed hard-control anchor. | H12: =ModeloFinanciero!B20-(ModeloFinanciero!B18-ABS(ModeloFinanciero!B19)) -> 0 | I12: =ModeloFinanciero!C20-(ModeloFinanciero!C18-ABS(ModeloFinanciero!C19)) -> 0 | J12: =ModeloFinanciero!D20-(ModeloFinanciero!D18-ABS(ModeloFinanciero!D19)) -> 0 | K12: =ModeloFinanciero!E20-(ModeloFinanciero!E18-ABS(ModeloFinanciero!E19)) -> 0 | L12: =ModeloFinanciero!F20-(ModeloFinanciero!F18-ABS(ModeloFinanciero!F19)) -> 0 | M12: =ModeloFinanciero!G20-(ModeloFinanciero!G18-ABS(ModeloFinanciero!G19)) -> 0 | N12: =ModeloFinanciero!H20-(ModeloFinanciero!H18-ABS(ModeloFinanciero!H19)) -> 0 | O12: =ModeloFinanciero!I20-(ModeloFinanciero!I18-ABS(ModeloFinanciero!I19)) -> 0 | ... Q12: =ModeloFinanciero!K20-(ModeloFinanciero!K18-ABS(ModeloFinanciero!K19)) -> 0
A13: RE_ROLLFORWARD | B13: UNIVERSAL | expected 0; hard_tie_tolerance. | source applies_to: all 16 with RE row | C13: SOURCE_GAP | D13: hard | E13: 1000 USD | F13: 0 | G13: No semantic anchors resolved for RE_ROLLFORWARD. | H13: =0 -> 0 | I13: =0 -> 0 | J13: =0 -> 0 | K13: =0 -> 0 | L13: =0 -> 0 | M13: =0 -> 0 | N13: =0 -> 0 | O13: =0 -> 0 | ... Q13: =0 -> 0
A14: EQUITY_TOTAL_TIE | B14: UNIVERSAL | expected 0; hard_tie_tolerance. | source applies_to: all 16 | C14: SOURCE_GAP | D14: hard | E14: 1000 USD | F14: 0 | G14: No semantic anchors resolved for EQUITY_TOTAL_TIE. | H14: =0 -> 0 | I14: =0 -> 0 | J14: =0 -> 0 | K14: =0 -> 0 | L14: =0 -> 0 | M14: =0 -> 0 | N14: =0 -> 0 | O14: =0 -> 0 | ... Q14: =0 -> 0
A15: BS_LINEITEM_SUM_ASSETS | B15: UNIVERSAL | expected 0; hard_tie_tolerance. | source applies_to: all 16 | C15: =IF(SUMPRODUCT((ABS(H15:Q15)>1000)*1)=0,"PASS","FAIL") -> PASS | D15: hard | E15: 1000 USD | F15: 0 | G15: expected 0; hard_tie_tolerance. Default full-USD hard tie threshold is $1,000 unless the workbook declares a tighter scale-aware tolerance. | H15: =SUM(ModeloFinanciero!B30,ModeloFinanciero!B34)-ModeloFinanciero!B35 -> 0 | I15: =SUM(ModeloFinanciero!C30,ModeloFinanciero!C34)-ModeloFinanciero!C35 -> 0 | J15: =SUM(ModeloFinanciero!D30,ModeloFinanciero!D34)-ModeloFinanciero!D35 -> 0 | K15: =SUM(ModeloFinanciero!E30,ModeloFinanciero!E34)-ModeloFinanciero!E35 -> 0 | L15: =SUM(ModeloFinanciero!F30,ModeloFinanciero!F34)-ModeloFinanciero!F35 -> 0 | M15: =SUM(ModeloFinanciero!G30,ModeloFinanciero!G34)-ModeloFinanciero!G35 -> 0 | N15: =SUM(ModeloFinanciero!H30,ModeloFinanciero!H34)-ModeloFinanciero!H35 -> 0 | O15: =SUM(ModeloFinanciero!I30,ModeloFinanciero!I34)-ModeloFinanciero!I35 -> 0 | ... Q15: =SUM(ModeloFinanciero!K30,ModeloFinanciero!K34)-ModeloFinanciero!K35 -> 0
A16: BS_LINEITEM_SUM_LIAB_EQUITY | B16: UNIVERSAL | expected 0; hard_tie_tolerance. | source applies_to: all 16 | C16: SOURCE_GAP | D16: hard | E16: 1000 USD | F16: 0 | G16: No semantic anchors resolved for BS_LINEITEM_SUM_LIAB_EQUITY. | H16: =0 -> 0 | I16: =0 -> 0 | J16: =0 -> 0 | K16: =0 -> 0 | L16: =0 -> 0 | M16: =0 -> 0 | N16: =0 -> 0 | O16: =0 -> 0 | ... Q16: =0 -> 0
A17: SOURCE_TIE_HISTORICAL | B17: UNIVERSAL | expected 0 for audited rows; SOURCE_GAP/WARN allowed only with explicit source-gap note. | source applies_to: all 16 | C17: =IF(SUMPRODUCT((ABS(H17:Q17)>100000)*1)=0,"PASS","FAIL") -> PASS | D17: hard | E17: 100000 USD | F17: 0 | G17: Audited rows tie to 0; only bank ending-cash-vs-EEFF cash rows may use the observed $100,000 hard threshold; SOURCE_GAP/WARN requires explicit source-gap note. | H17: =ModeloFinanciero!B35-EEFF!B35 -> 0 | I17: =ModeloFinanciero!C35-EEFF!C35 -> 0 | J17: =ModeloFinanciero!D35-EEFF!D35 -> 0 | K17: =ModeloFinanciero!E35-EEFF!E35 -> 0 | L17: =ModeloFinanciero!F35-EEFF!F35 -> 0
A18: NO_FORMULA_ERRORS | B18: UNIVERSAL | expected PASS/0; no masking. | source applies_to: all 16 | C18: =IF(SUMPRODUCT((ABS(H18:Q18)>0)*1)=0,"PASS","FAIL") -> PASS | D18: hard | E18: PASS | F18: PASS | G18: expected PASS/0; no masking. | H18: =0 -> 0 | I18: =0 -> 0 | J18: =0 -> 0 | K18: =0 -> 0 | L18: =0 -> 0 | M18: =0 -> 0 | N18: =0 -> 0 | O18: =0 -> 0 | ... Q18: =0 -> 0
A19: NO_CHECKS_MASTER_FAIL | B19: UNIVERSAL | expected PASS; status row should cite included/excluded rows. | source applies_to: all 16 | C19: =IF(SUMPRODUCT((ABS(H19:Q19)>0)*1)=0,"PASS","FAIL") -> PASS | D19: hard | E19: PASS | F19: PASS | G19: expected PASS; status row should cite included/excluded rows. | H19: =COUNTIF($C$6:$C$18,"FAIL")+COUNTIF($C$20:$C$32,"FAIL") -> 0 | I19: =COUNTIF($C$6:$C$18,"FAIL")+COUNTIF($C$20:$C$32,"FAIL") -> 0 | J19: =COUNTIF($C$6:$C$18,"FAIL")+COUNTIF($C$20:$C$32,"FAIL") -> 0 | K19: =COUNTIF($C$6:$C$18,"FAIL")+COUNTIF($C$20:$C$32,"FAIL") -> 0 | L19: =COUNTIF($C$6:$C$18,"FAIL")+COUNTIF($C$20:$C$32,"FAIL") -> 0 | M19: =COUNTIF($C$6:$C$18,"FAIL")+COUNTIF($C$20:$C$32,"FAIL") -> 0 | N19: =COUNTIF($C$6:$C$18,"FAIL")+COUNTIF($C$20:$C$32,"FAIL") -> 0 | O19: =COUNTIF($C$6:$C$18,"FAIL")+COUNTIF($C$20:$C$32,"FAIL") -> 0 | ... Q19: =COUNTIF($C$6:$C$18,"FAIL")+COUNTIF($C$20:$C$32,"FAIL") -> 0
A21: CONDITIONAL CHECKS
A22: PPE_SCHEDULE_TIE | B22: ARCHETYPE/conditional | expected 0; hard_tie_tolerance. | source applies_to: operating-EBITDA, power, utility, downstream fuel, other non-financials | C22: SOURCE_GAP | D22: hard | E22: 1000 USD | F22: 0 | G22: Roll-forward residual is live from PP&E_Schedule; components marked NOT_DISCLOSED keep this report-only until a hard-control policy is signed. | H22: ='PP&E_Schedule'!B20 -> 0 | I22: ='PP&E_Schedule'!C20 -> 0 | J22: ='PP&E_Schedule'!D20 -> 0 | K22: ='PP&E_Schedule'!E20 -> -1028044449 | L22: ='PP&E_Schedule'!F20 -> 141306 | M22: ='PP&E_Schedule'!G20 -> 127622915 | N22: ='PP&E_Schedule'!H20 -> 127622915 | O22: ='PP&E_Schedule'!I20 -> 127622915 | ... Q22: ='PP&E_Schedule'!K20 -> 127622915
A23: LEASE_SCHEDULE_TIE | B23: ARCHETYPE/conditional | expected 0; hard_tie_tolerance. | source applies_to: IFRS-16 issuers | C23: SOURCE_GAP | D23: hard | E23: 1000 USD | F23: 0 | G23: Roll-forward residual is live from ROU_Lease_Schedule; components marked NOT_DISCLOSED keep this report-only until a hard-control policy is signed. | H23: =ROU_Lease_Schedule!B27 -> 0 | I23: =ROU_Lease_Schedule!C27 -> 0 | J23: =ROU_Lease_Schedule!D27 -> 0 | K23: =ROU_Lease_Schedule!E27 -> -408132 | L23: =ROU_Lease_Schedule!F27 -> -5328063 | M23: =ROU_Lease_Schedule!G27 -> 0 | N23: =ROU_Lease_Schedule!H27 -> 0 | O23: =ROU_Lease_Schedule!I27 -> 0 | ... Q23: =ROU_Lease_Schedule!K27 -> 0
A24: DEBT_SCHEDULE_TIE | B24: ARCHETYPE/conditional | expected 0; hard_tie_tolerance; project-finance debt can include accrued interest/unamortized cost roles. | source applies_to: non-bank-lender, power, utility, operating-EBITDA with debt | C24: SOURCE_GAP | D24: hard | E24: 1000 USD | F24: 0 | G24: Roll-forward residual is live from Debt_Schedule; components marked NOT_DISCLOSED keep this report-only until a hard-control policy is signed. | H24: =Debt_Schedule!B19 -> 0 | I24: =Debt_Schedule!C19 -> 0 | J24: =Debt_Schedule!D19 -> 0 | K24: =Debt_Schedule!E19 -> -813184035 | L24: =Debt_Schedule!F19 -> -123002094 | M24: =Debt_Schedule!G19 -> 40389795 | N24: =Debt_Schedule!H19 -> 40389795 | O24: =Debt_Schedule!I19 -> 40389795 | ... Q24: =Debt_Schedule!K19 -> 40389795
A26: UTILITY CHECKS
A27: POWER_REVENUE_BUILD_TIE | B27: ARCHETYPE | expected 0; hard_tie_tolerance. | source applies_to: power, utility | C27: SOURCE_GAP | D27: hard | E27: 1000 USD | F27: 0 | G27: No semantic anchors resolved for POWER_REVENUE_BUILD_TIE. | H27: =0 -> 0 | I27: =0 -> 0 | J27: =0 -> 0 | K27: =0 -> 0 | L27: =0 -> 0 | M27: =0 -> 0 | N27: =0 -> 0 | O27: =0 -> 0 | ... Q27: =0 -> 0
A28: POWER_CHANNEL_VOLUME_TIE | B28: ARCHETYPE | expected 0; observed UEPII uses N/A for years without channel split. | source applies_to: power, utility | C28: SOURCE_GAP | D28: hard | E28: volume_tolerance | F28: 0 | G28: No semantic anchors resolved for POWER_CHANNEL_VOLUME_TIE. | H28: =0 -> 0 | I28: =0 -> 0 | J28: =0 -> 0 | K28: =0 -> 0 | L28: =0 -> 0 | M28: =0 -> 0 | N28: =0 -> 0 | O28: =0 -> 0 | ... Q28: =0 -> 0
A29: POWER_CAPACITY_CEILING | B29: ARCHETYPE | PASS/FAIL or 0/1; threshold from hours-per-year parameter. | source applies_to: power, utility | C29: SOURCE_GAP | D29: hard | E29: PASS | F29: PASS | G29: Installed-capacity ceiling needs an addressable capacity-driver row before the live check can be rendered without hardcoded formula constants. | H29: =0 -> 0 | I29: =0 -> 0 | J29: =0 -> 0 | K29: =0 -> 0 | L29: =0 -> 0 | M29: =0 -> 0 | N29: =0 -> 0 | O29: =0 -> 0 | ... Q29: =0 -> 0
A30: POWER_DSRA_COVERAGE | B30: ARCHETYPE | expected 0; UEPII tail uses <=1 tolerance in U2 rows. | source applies_to: project-finance power/utility | C30: SOURCE_GAP | D30: hard | E30: 1 model currency or ratio residual | F30: 0 | G30: No semantic anchors resolved for POWER_DSRA_COVERAGE. | H30: =0 -> 0 | I30: =0 -> 0 | J30: =0 -> 0 | K30: =0 -> 0 | L30: =0 -> 0 | M30: =0 -> 0 | N30: =0 -> 0 | O30: =0 -> 0 | ... Q30: =0 -> 0
A31: POWER_DSCR_COVENANT | B31: ARCHETYPE | must be >=0 or explicit business-warning text; not always a mechanical blocker. | source applies_to: project-finance power/utility | C31: SOURCE_GAP | D31: soft | E31: 0 cushion | F31: >=0 | G31: No semantic anchors resolved for POWER_DSCR_COVENANT. | H31: =0 -> 0 | I31: =0 -> 0 | J31: =0 -> 0 | K31: =0 -> 0 | L31: =0 -> 0 | M31: =0 -> 0 | N31: =0 -> 0 | O31: =0 -> 0 | ... Q31: =0 -> 0
A32: OPERATING_GP_OR_EBITDA_TIE | B32: ARCHETYPE | expected 0; hard_tie_tolerance. | source applies_to: operating-EBITDA, downstream fuel, power when EBITDA is used | C32: SOURCE_GAP | D32: hard | E32: 1000 USD | F32: 0 | G32: No semantic anchors resolved for OPERATING_GP_OR_EBITDA_TIE. | H32: =0 -> 0 | I32: =0 -> 0 | J32: =0 -> 0 | K32: =0 -> 0 | L32: =0 -> 0 | M32: =0 -> 0 | N32: =0 -> 0 | O32: =0 -> 0 | ... Q32: =0 -> 0

Sheet Source_Register
A1: Empresa de Distribución Eléctrica Metro-Oeste, S. A.
A2: Source_Register — utility archetype. Every row traces to a published filing (OCR text) or to a working file kept by the maintainer.
A3: Status semantics: OK = citation resolved to an existing artifact. SOURCE_GAP = traceability missing (visible, not hidden). NOT_DISCLOSED = no registration/manifest found for this issuer.
A4: source_id | B4: kind | C4: ticker | D4: filing | E4: year | F4: nota | G4: tabla_ocr | H4: feeds_sheet | I4: feeds_anchor | J4: date | K4: status | L4: evidence_count | M4: note
A5: OCR_ROOT:edemet | B5: OCR_ROOT | C5: EDEMET | H5: EEFF; Notas_EEFF | I5: OCR of the published filings | J5: NOT_DISCLOSED | K5: OK | L5: 1 | M5: Annual reports (INA) of edemet
A6: EEFF_FILING:ina_edemet_2025_0 | B6: EEFF_FILING | C6: EDEMET | D6: INA_EDEMET_2025_0.pdf | E6: 2025 | G6: markdown.md | H6: EEFF; Notas_EEFF; MD&A | I6: 00-index.md; 01-eeff.md; 02-notas.md; 03-mda.md; 09-otros.md | J6: FY25 (A) | K6: OK | L6: 152 | M6: markdown.md sha256=ffddf1fad93a54f2...
A7: EEFF_FILING:prospecto_definitivo_programa_rotativo_de_bonos_corporativos_hasta_us_350mm_res_215_25 | B7: EEFF_FILING | C7: EDEMET | D7: PROSPECTO_DEFINITIVO_PROGRAMA_ROTATIVO_DE_BONOS_CORPORATIVOS_HASTA_US_350MM__RES.215-25_.pdf | G7: markdown.md | H7: EEFF; Notas_EEFF; MD&A | I7: 00-index.md; 01-eeff.md; 02-notas.md; 03-mda.md; 09-otros.md | J7: NOT_DISCLOSED | K7: OK | L7: 190 | M7: markdown.md sha256=0b7fbedec37a2407...
A8: EEFF_FILING:350mm_edemet_prospecto_preliminar | B8: EEFF_FILING | C8: EDEMET | D8: _350MM_EDEMET_-_Prospecto__Preliminar_.pdf | G8: markdown.md | H8: EEFF; Notas_EEFF; MD&A | I8: 00-index.md; 01-eeff.md; 02-notas.md; 03-mda.md; 09-otros.md | J8: NOT_DISCLOSED | K8: OK | L8: 298 | M8: markdown.md sha256=6589e64ef2f5ff3e...
A9: NOTA:INA_EDEMET_2025_0.pdf#10 | B9: NOTA | C9: EDEMET | D9: INA_EDEMET_2025_0.pdf | E9: 2025 | F9: 10 | G9: markdown.md; tbl-94.html; tbl-95.html | H9: Notas_EEFF | I9: 10. Patrimonio, continuación | J9: FY25 (A) | K9: OK | L9: 18
A10: NOTA:INA_EDEMET_2025_0.pdf#11 | B10: NOTA | C10: EDEMET | D10: INA_EDEMET_2025_0.pdf | E10: 2025 | F10: 11 | G10: markdown.md; tbl-100.html; tbl-96.html; +2 more | H10: Notas_EEFF | I10: 11. Deuda Financiera, continuación | J10: FY25 (A) | K10: OK | L10: 27
A11: NOTA:INA_EDEMET_2025_0.pdf#12 | B11: NOTA | C11: EDEMET | D11: INA_EDEMET_2025_0.pdf | E11: 2025 | F11: 12 | G11: markdown.md; tbl-101.html; tbl-102.html | H11: Notas_EEFF | I11: 12. Conciliación de movimiento de pasivo por actividades de financiamiento | J11: FY25 (A) | K11: OK | L11: 5
A12: NOTA:INA_EDEMET_2025_0.pdf#13 | B12: NOTA | C12: EDEMET | D12: INA_EDEMET_2025_0.pdf | E12: 2025 | F12: 13 | G12: markdown.md; tbl-104.html; tbl-106.html; +1 more | H12: Notas_EEFF | I12: 13. Otros Pasivos, continuación | J12: FY25 (A) | K12: OK | L12: 25
A13: NOTA:INA_EDEMET_2025_0.pdf#14 | B13: NOTA | C13: EDEMET | D13: INA_EDEMET_2025_0.pdf | E13: 2025 | F13: 14 | G13: markdown.md; tbl-108.html | H13: Notas_EEFF | I13: 14. Acreedores Comerciales y Otras Cuentas por Pagar | J13: FY25 (A) | K13: OK | L13: 7
A14: NOTA:INA_EDEMET_2025_0.pdf#15 | B14: NOTA | C14: EDEMET | D14: INA_EDEMET_2025_0.pdf | E14: 2025 | F14: 15 | G14: markdown.md; tbl-109.html | H14: Notas_EEFF | I14: 15. Ingresos por Actividades Ordinarias | J14: FY25 (A) | K14: OK | L14: 2
A15: NOTA:INA_EDEMET_2025_0.pdf#16 | B15: NOTA | C15: EDEMET | D15: INA_EDEMET_2025_0.pdf | E15: 2025 | F15: 16 | G15: markdown.md; tbl-111.html | H15: Notas_EEFF | I15: 16. Aprovisionamientos | J15: FY25 (A) | K15: OK | L15: 9
A16: NOTA:INA_EDEMET_2025_0.pdf#17 | B16: NOTA | C16: EDEMET | D16: INA_EDEMET_2025_0.pdf | E16: 2025 | F16: 17 | G16: markdown.md; tbl-111.html; tbl-113.html; +1 more | H16: Notas_EEFF | I16: 17. Gastos, continuación | J16: FY25 (A) | K16: OK | L16: 12
A17: NOTA:INA_EDEMET_2025_0.pdf#18 | B17: NOTA | C17: EDEMET | D17: INA_EDEMET_2025_0.pdf | E17: 2025 | F17: 18 | G17: markdown.md; tbl-115.html | H17: Notas_EEFF | I17: 18. Compromisos y Contingencias | J17: FY25 (A) | K17: OK | L17: 8
A18: NOTA:INA_EDEMET_2025_0.pdf#19 | B18: NOTA | C18: EDEMET | D18: INA_EDEMET_2025_0.pdf | E18: 2025 | F18: 19 | G18: markdown.md; tbl-117.html; tbl-119.html | H18: Notas_EEFF | I18: 19. Impuesto sobre la Renta, continuación | J18: FY25 (A) | K18: OK | L18: 19
A19: NOTA:INA_EDEMET_2025_0.pdf#20 | B19: NOTA | C19: EDEMET | D19: INA_EDEMET_2025_0.pdf | E19: 2025 | F19: 20 | G19: markdown.md; tbl-121.html; tbl-122.html | H19: Notas_EEFF | I19: 20. Administración de Riesgos Financieros, continuación | J19: FY25 (A) | K19: OK | L19: 24
A20: NOTA:INA_EDEMET_2025_0.pdf#21 | B20: NOTA | C20: EDEMET | D20: INA_EDEMET_2025_0.pdf | E20: 2025 | F20: 21 | G20: markdown.md; tbl-123.html; tbl-124.html; +2 more | H20: Notas_EEFF | I20: 21. Medición del Valor Razonable, continuación | J20: FY25 (A) | K20: OK | L20: 135
... A25: NOTA:INA_EDEMET_2025_0.pdf#9 | B25: NOTA | C25: EDEMET | D25: INA_EDEMET_2025_0.pdf | E25: 2025 | F25: 9 | G25: markdown.md; tbl-94.html | H25: Notas_EEFF | I25: 9. Efectivo | J25: FY25 (A) | K25: OK | L25: 4
A26: DRIVER:EEFF:Aprovisionamientos | B26: DRIVER_EEFF | C26: EDEMET | H26: Supuestos | I26: Aprovisionamientos — driver activo | J26: NOT_DISCLOSED | K26: OK | L26: 4 | M26: Aprovisionamientos
A27: DRIVER:EEFF:Aprovisionamientos / EEFF:Ingresos por actividades ordinarias | B27: DRIVER_EEFF | C27: EDEMET | H27: Supuestos | I27: Aprovisionamientos ÷ Ingresos por actividades ordinarias (hist, ref EEFF) | J27: NOT_DISCLOSED | K27: OK | L27: 1 | M27: Aprovisionamientos / EEFF:Ingresos por actividades ordinarias
A28: DRIVER:EEFF:Gastos de personal | B28: DRIVER_EEFF | C28: EDEMET | H28: Supuestos | I28: Gastos de personal — driver activo | J28: NOT_DISCLOSED | K28: OK | L28: 4 | M28: Gastos de personal
A29: DRIVER:EEFF:Gastos de personal / EEFF:Ingresos por actividades ordinarias | B29: DRIVER_EEFF | C29: EDEMET | H29: Supuestos | I29: Gastos de personal ÷ Ingresos por actividades ordinarias (hist, ref EEFF) | J29: NOT_DISCLOSED | K29: OK | L29: 1 | M29: Gastos de personal / EEFF:Ingresos por actividades ordinarias
A30: DRIVER:EEFF:Impuesto sobre la renta | B30: DRIVER_EEFF | C30: EDEMET | H30: Supuestos | I30: Impuesto sobre la renta — driver activo | J30: NOT_DISCLOSED | K30: OK | L30: 4 | M30: Impuesto sobre la renta
A31: DRIVER:EEFF:Impuesto sobre la renta / EEFF:Utilidad antes del impuesto sobre la renta | B31: DRIVER_EEFF | C31: EDEMET | H31: Supuestos | I31: Impuesto sobre la renta ÷ Utilidad antes del impuesto sobre la renta (hist, ref EEFF) | J31: NOT_DISCLOSED | K31: OK | L31: 1 | M31: Impuesto sobre la renta / EEFF:Utilidad antes del impuesto sobre la renta
A32: DRIVER:EEFF:Ingresos por actividades ordinarias | B32: DRIVER_EEFF | C32: EDEMET | H32: Supuestos | I32: Ingresos por actividades ordinarias — driver activo | J32: NOT_DISCLOSED | K32: OK | L32: 6 | M32: Ingresos por actividades ordinarias
A33: DRIVER:EEFF:Otros gastos | B33: DRIVER_EEFF | C33: EDEMET | H33: Supuestos | I33: Otros gastos — driver activo | J33: NOT_DISCLOSED | K33: OK | L33: 4 | M33: Otros gastos
A34: DRIVER:EEFF:Otros gastos / EEFF:Ingresos por actividades ordinarias | B34: DRIVER_EEFF | C34: EDEMET | H34: Supuestos | I34: Otros gastos ÷ Ingresos por actividades ordinarias (hist, ref EEFF) | J34: NOT_DISCLOSED | K34: OK | L34: 1 | M34: Otros gastos / EEFF:Ingresos por actividades ordinarias
A35: DRIVER:EEFF:Reparaciones y conservación | B35: DRIVER_EEFF | C35: EDEMET | H35: Supuestos | I35: Reparaciones y conservación — driver activo | J35: NOT_DISCLOSED | K35: OK | L35: 4 | M35: Reparaciones y conservación
A36: DRIVER:EEFF:Reparaciones y conservación / EEFF:Ingresos por actividades ordinarias | B36: DRIVER_EEFF | C36: EDEMET | H36: Supuestos | I36: Reparaciones y conservación ÷ Ingresos por actividades ordinarias (hist, ref EEFF) | J36: NOT_DISCLOSED | K36: OK | L36: 1 | M36: Reparaciones y conservación / EEFF:Ingresos por actividades ordinarias

Sheet _CHANGELOG
A1: Empresa de Distribución Eléctrica Metro-Oeste, S. A.
A2: _CHANGELOG — generation record for edemet.
A3: Internal build history omitted from the public export. Record public changes below.

Sheet Claude Code Log
A1: Turn # | B1: Date | C1: User Request | D1: Action Taken | E1: Details | F1: Outcome
A2: 1 | B2: 46324.359 | C2: Prepare a public model copy | D2: Remove local paths and private build references; preserve financial formulas and inputs | E2: Agent run with MOG as the tool, checked by guard v1. The guard measured every sheet before and after the run. Changed: Notas_EEFF: 1 cell written, at A3; _CHECKS: 1 cell written, at G12; Source_Register: 3 cells written, at A2, I5, M5; _CHANGELOG: data A1:H19 -> A1:A3 (rows 19 -> 3, columns 8 -> 1), 106 cells written, at A2, A3, B3, C3, D3, E3, F3, G3, H3, A4, B4, C4, D4, E4, H4 and 91 more. Other actions: clear x1. Agent: OpenFinmods export | F2: Compare against source and review public copy
