Workbook

Sheet 00_Cover
A1: Cerebras Systems Inc. (Nasdaq: CBRS) | Financial model: statements as filed, backlog-driven forecast 2026E-2035E, valuation and credit
A2: Built 27 Oct 2026 from the final prospectus (424B4, 13 May 2026) and the Q1 and Q2 2026 Forms 10-Q (latest statements: 30 Jun 2026).
A4: What this workbook holds
A5: Every line of the statements: FY2024 and FY2025 (audited, 424B4), six months to 30 June 2025 and 2026 (Q2 10-Q), ten quarters to Q2 2026 (a column waits for Q3 2026).
A6: Revenue by type, timing and region, customers, costs by function, the backlog and its conversion, the cap table with every class and warrant.
A7: Forecast H2 2026E and 2027E-2035E by revenue type (hardware, contracted backlog, renewals, option, other cloud, pass-through); Base, Bull and Bear (switch: Assumptions!C5).
A8: Three statements that balance every year; loan, lease and credit schedule; DCF; value per share against the price of US$119.31 (27 Oct 2026).
A9: How to read it
A10: Units: USD millions (filed thousands / 1,000), except per-share amounts (USD) and share counts (stated on each sheet).
A11: Signs follow the filing. A '—' is the filing's dash and a '*' the filing's 'below 10%': kept as text, read as nil by the model.
A12: Blue numbers are typed from a filing or are inputs. Black numbers are formulas. Green numbers link to another sheet.
A13: Column M on the year sheets is for your comments. Column N shows the source or the derivation.
A14: The thin vertical line separates actual and forecast columns.
A16: Master check (all checks on the Checks sheet) | C16: =Checks!C4 -> OK
A18: Key outputs (active scenario unless stated) | C18: Value
A19: Active scenario | C19: =Assumptions!$C$6 -> Base
A20: Share price, 27 Oct 2026 (USD) | C20: =Market_Package!B10 -> 119.31
A21: DCF value per share, perpetuity (USD) | C21: =DCF!C40 -> 45.940695
A22: Against the price | C22: =DCF!C42 -> -0.61494682
A23: Base value per share (captured, USD) | C23: =Scenario_Summary!D21 -> 45.940695
A24: Bull value per share (captured, USD) | C24: =Scenario_Summary!E21 -> 100.01525
A25: Bear value per share (captured, USD) | C25: =Scenario_Summary!F21 -> 15.52138
A26: Comparables value per share, trailing EV / LTM revenue median (USD) | C26: =Comparables!E27 -> 67.451939
A27: Probability-weighted DCF value, Bear 25% / Base 50% / Bull 25% (USD) | C27: =Valuation!C45 -> 51.854506
A28: Revenue 2026E (USD m) | C28: =Forecast_3Stmt!C13 -> 1193.6715
A29: Revenue 2030E (USD m) | C29: =Forecast_3Stmt!G13 -> 6879.9866
A30: Backlog at 30 Jun 2026 (USD m) | C30: =Backlog!B7 -> 25400
A31: Diluted shares (millions) | C31: =Cap_Table!B30 -> 286.11752
A33: Sheet | B33: What it shows
A34: IS_Hist | B34: Statements of operations as filed, with tie-out checks
A35: CI_Hist | B35: Statements of comprehensive income (loss) as filed
A36: BS_Hist | B36: Balance sheets as filed (31 Dec 2024 and 2025, the 10-Q recast of 31 Dec 2025, 31 Mar 2026, 30 Jun 2026)
A37: CF_Hist | B37: Statements of cash flows as filed
A38: SCE_Hist | B38: Statements of preferred stock and stockholders' equity as filed
A39: Quarterly_Hist | B39: Ten quarters to Q2 2026, stock pay, the IPO catch-up; Q3 2026 column waiting
A40: Revenue_Hist | B40: Revenue by timing and region, customers, depreciation and stock pay by function, costs before them, other income, OpenAI facts
A41: Backlog | B41: Backlog at 30 Jun 2026 and its conversion by the filed windows; renewals; OpenAI option; warrant amortization
A42: Cap_Table | B42: Shares by class, options, RSUs, PRSUs, OpenAI and AWS warrants; diluted count; stock pay of awards in the count
A43: Assumptions | B43: Every forecast input: Base, Bull, Bear and the switch (C5)
A44: Interim_Bridge | B44: 2026E = six months actual + second-half estimate
... A57: Claude Code Log | B57: Log of every scripted write

Sheet IS_Hist
A1: Cerebras Systems Inc. (Nasdaq: CBRS) | Consolidated statements of operations, as filed
A2: USD millions (filed in thousands / 1,000), except per-share amounts (USD) and share counts (thousands). FY2024-FY2025 audited (424B4 p. F-5); six-month periods unaudited (Q2 10-Q p. 7). A '—' is the filing's dash.
A4: Fiscal year ends 31 December | B4: FY2024A | C4: FY2025A | D4: 6M 2025A | E4: 6M 2026A | M4: Comentarios FG | N4: Source / derivation
A6: Revenue
A7: Hardware | B7: 211.965 | C7: 358.44 | D7: 139.969 | E7: 164.712 | N7: 424B4 p. F-5 (FY); Q2 10-Q p. 7 (6M)
A8: Cloud and other services | B8: 78.287 | C8: 151.551 | D8: 62.865 | E8: 208.804 | N8: 424B4 p. F-5 (FY); Q2 10-Q p. 7 (6M)
A9: Total revenue | B9: 290.252 | C9: 509.991 | D9: 202.834 | E9: 373.516 | N9: 424B4 p. F-5 (FY); Q2 10-Q p. 7 (6M)
A11: Cost of revenue
A12: Hardware | B12: 137.31 | C12: 204.746 | D12: 95.059 | E12: 118.072 | N12: 424B4 p. F-5 (FY); Q2 10-Q p. 7 (6M)
A13: Cloud and other services | B13: 30.204 | C13: 106.174 | D13: 34.072 | E13: 143.709 | N13: 424B4 p. F-5 (FY); Q2 10-Q p. 7 (6M)
A14: Total cost of revenue | B14: 167.514 | C14: 310.92 | D14: 129.131 | E14: 261.781 | N14: 424B4 p. F-5 (FY); Q2 10-Q p. 7 (6M)
A15: Gross profit | B15: 122.738 | C15: 199.071 | D15: 73.703 | E15: 111.735 | N15: 424B4 p. F-5 (FY); Q2 10-Q p. 7 (6M)
A17: Operating expenses
A18: Research and development | B18: 158.234 | C18: 243.319 | D18: 113.519 | E18: 395.646 | N18: 424B4 p. F-5 (FY); Q2 10-Q p. 7 (6M)
A19: Sales and marketing | B19: 20.98 | C19: 70.645 | D19: 28.554 | E19: 101.67 | N19: 424B4 p. F-5 (FY); Q2 10-Q p. 7 (6M)
A20: General and administrative | B20: 44.962 | C20: 30.969 | D20: 17.282 | E20: 106.689 | N20: 424B4 p. F-5 (FY); Q2 10-Q p. 7 (6M)
A21: Total operating expenses | B21: 224.176 | C21: 344.933 | D21: 159.355 | E21: 604.005 | N21: 424B4 p. F-5 (FY); Q2 10-Q p. 7 (6M)
A22: Loss from operations | B22: -101.438 | C22: -145.862 | D22: -85.652 | E22: -492.27 | N22: 424B4 p. F-5 (FY); Q2 10-Q p. 7 (6M)
A23: Other income (expense), net | B23: -378.237 | C23: 390.746 | D23: 374.644 | E23: 29.507 | N23: 424B4 p. F-5 (FY); Q2 10-Q p. 7 (6M)
A24: Income (loss) before income taxes | B24: -479.675 | C24: 244.884 | D24: 288.992 | E24: -462.763 | N24: 424B4 p. F-5 (FY); Q2 10-Q p. 7 (6M)
A25: Income tax expense | B25: 1.927 | C25: 7.057 | D25: 3.347 | E25: 1.771 | N25: 424B4 p. F-5 (FY); Q2 10-Q p. 7 (6M)
A26: Net income (loss) | B26: -481.602 | C26: 237.827 | D26: 285.645 | E26: -464.534 | N26: 424B4 p. F-5 (FY); Q2 10-Q p. 7 (6M)
A27: Less: net income attributable to participating securities | B27: — | C27: 149.952 | N27: 424B4 p. F-5 (FY); Q2 10-Q p. 7 (6M); caption not in the filing for 6M 2025A, 6M 2026A (blank)
A28: Less: deemed dividend on issuance of Series F-1 preferred stock | B28: 3.182 | C28: — | N28: 424B4 p. F-5 (FY); Q2 10-Q p. 7 (6M); caption not in the filing for 6M 2025A, 6M 2026A (blank)
A29: Net income (loss) attributable to common shareholders: basic | B29: -484.784 | C29: 87.875 | D29: 110.58 | E29: -464.534 | N29: 424B4 p. F-5 (FY); Q2 10-Q p. 7 (6M)
A30: Net income (loss) attributable to common shareholders: diluted | D30: 285.645 | E30: -464.534 | N30: 424B4 p. F-5 (FY); Q2 10-Q p. 7 (6M); caption not in the filing for FY2024A, FY2025A (blank)
A31: Net income (loss) per share attributable to common shareholders: basic (USD) | B31: -9.9 | C31: 1.64 | D31: 2.11 | E31: -4.34 | N31: 424B4 p. F-5 (FY); Q2 10-Q p. 7 (6M)
A32: Net income (loss) per share attributable to common shareholders: diluted (USD) | B32: -9.9 | C32: 1.38 | D32: 1.76 | E32: -4.34 | N32: 424B4 p. F-5 (FY); Q2 10-Q p. 7 (6M)
A33: Weighted average shares: basic (thousands) | B33: 48972 | C33: 53616 | D33: 52363 | E33: 107132 | N33: 424B4 p. F-5 (FY); Q2 10-Q p. 7 (6M)
A34: Weighted average shares: diluted (thousands) | B34: 48972 | C34: 171821 | D34: 162276 | E34: 107132 | N34: 424B4 p. F-5 (FY); Q2 10-Q p. 7 (6M)
A36: Checks: recomputed less filed (zero passes)
A37: Total revenue | B37: =SUM(B7,B8)-B9 -> 0 | C37: =SUM(C7,C8)-C9 -> 0 | D37: =SUM(D7,D8)-D9 -> 0 | E37: =SUM(E7,E8)-E9 -> 0
A38: Total cost of revenue | B38: =SUM(B12,B13)-B14 -> 0 | C38: =SUM(C12,C13)-C14 -> 0 | D38: =SUM(D12,D13)-D14 -> 0 | E38: =SUM(E12,E13)-E14 -> 0
A39: Gross profit | B39: =B9-B14-B15 -> 0 | C39: =C9-C14-C15 -> 0 | D39: =D9-D14-D15 -> 0 | E39: =E9-E14-E15 -> 0
A40: Total operating expenses | B40: =SUM(B18,B19,B20)-B21 -> 0 | C40: =SUM(C18,C19,C20)-C21 -> 0 | D40: =SUM(D18,D19,D20)-D21 -> 0 | E40: =SUM(E18,E19,E20)-E21 -> 0
A41: Loss from operations | B41: =B15-B21-B22 -> 0 | C41: =C15-C21-C22 -> 0 | D41: =D15-D21-D22 -> 0 | E41: =E15-E21-E22 -> 0
A42: Income (loss) before income taxes | B42: =B22+B23-B24 -> 0 | C42: =C22+C23-C24 -> 0 | D42: =D22+D23-D24 -> 0 | E42: =E22+E23-E24 -> 0
A43: Net income (loss) | B43: =B24-B25-B26 -> 0 | C43: =C24-C25-C26 -> 0 | D43: =D24-D25-D26 -> 0 | E43: =E24-E25-E26 -> 0
A44: Net income attributable to common shareholders, FY | B44: =B26-SUM(B27,B28)-B29 -> 0 | C44: =C26-SUM(C27,C28)-C29 -> 0
A45: Basic earnings per share (rounded to cents) | B45: =ROUND(B29*1000/B33,2)-B31 -> 0 | C45: =ROUND(C29*1000/C33,2)-C31 -> 0 | D45: =ROUND(D29*1000/D33,2)-D31 -> 0 | E45: =ROUND(E29*1000/E33,2)-E31 -> 0

Sheet CI_Hist
A1: Cerebras Systems Inc. (Nasdaq: CBRS) | Consolidated statements of comprehensive income (loss), as filed
A2: USD millions (filed in thousands / 1,000). 424B4 p. F-6 (FY); Q2 10-Q p. 8 (6M).
A4: Fiscal year ends 31 December | B4: FY2024A | C4: FY2025A | D4: 6M 2025A | E4: 6M 2026A | M4: Comentarios FG | N4: Source / derivation
A6: Net income (loss) | B6: -481.602 | C6: 237.827 | D6: 285.645 | E6: -464.534 | N6: 424B4 p. F-6 (FY); Q2 10-Q p. 8 (6M)
A7: Change in foreign currency translation adjustments, net of tax | B7: -0.304 | C7: -0.521 | D7: 0.912 | E7: 0.638 | N7: 424B4 p. F-6 (FY); Q2 10-Q p. 8 (6M)
A9: Available-for-sale investments:
A10: Change in net unrealized gain (loss) on debt securities, net of tax | B10: -0.579 | C10: 1.602 | D10: -0.807 | E10: 3.828 | N10: 424B4 p. F-6 (FY); Q2 10-Q p. 8 (6M)
A11: Comprehensive income (loss) | B11: -482.485 | C11: 238.908 | D11: 285.75 | E11: -460.068 | N11: 424B4 p. F-6 (FY); Q2 10-Q p. 8 (6M)
A13: Checks (zero passes)
A14: Comprehensive income (loss) | B14: =B6+B7+B10-B11 -> 0 | C14: =C6+C7+C10-C11 -> 0 | D14: =D6+D7+D10-D11 -> 0 | E14: =E6+E7+E10-E11 -> 0
A15: Net income equals the statement of operations | B15: =B6-IS_Hist!B26 -> 0 | C15: =C6-IS_Hist!C26 -> 0 | D15: =D6-IS_Hist!D26 -> 0 | E15: =E6-IS_Hist!E26 -> 0

Sheet BS_Hist
A1: Cerebras Systems Inc. (Nasdaq: CBRS) | Consolidated balance sheets, as filed
A2: USD millions (filed in thousands / 1,000). 31 Dec audited (424B4 p. F-4). The Q2 10-Q recasts 31 Dec 2025 (column D): customer warrants, lease and deferred revenue lines split out; totals unchanged. 31 Mar 2026 Q1 10-Q p. 5; 30 Jun 2026 Q2 10-Q p. 6.
A4: Fiscal year ends 31 December | B4: Dec 2024A | C4: Dec 2025A | D4: Dec 2025A recast | E4: Mar 2026A | F4: Jun 2026A | M4: Comentarios FG | N4: Source / derivation
A6: Current assets:
A7: Cash and cash equivalents | B7: 220.208 | C7: 701.706 | D7: 701.706 | E7: 1716.016 | F7: 6742.157 | N7: B-C 424B4 p. F-4; D and F Q2 10-Q p. 6; E Q1 10-Q p. 5
A8: Restricted cash | B8: 361.757 | C8: 228.672 | D8: 228.672 | E8: 1029.098 | F8: 684.68 | N8: B-C 424B4 p. F-4; D and F Q2 10-Q p. 6; E Q1 10-Q p. 5
A9: Investments | B9: 116.943 | C9: 406.531 | D9: 406.531 | E9: 515.605 | F9: 1179.39 | N9: B-C 424B4 p. F-4; D and F Q2 10-Q p. 6; E Q1 10-Q p. 5
A10: Accounts receivable, net | B10: 137.436 | C10: 50.423 | D10: 50.423 | E10: 62.631 | F10: 123.361 | N10: B-C 424B4 p. F-4; D and F Q2 10-Q p. 6; E Q1 10-Q p. 5
A11: Inventories | B11: 174.492 | C11: 63.626 | D11: 63.626 | E11: 89.04 | F11: 32.666 | N11: B-C 424B4 p. F-4; D and F Q2 10-Q p. 6; E Q1 10-Q p. 5
A12: Customer warrants | D12: 60.906 | E12: 90.701 | F12: 167.762 | N12: B-C 424B4 p. F-4; D and F Q2 10-Q p. 6; E Q1 10-Q p. 5; caption not in the filing for Dec 2024A, Dec 2025A (blank)
A13: Prepaid expenses and other current assets | B13: 19.643 | C13: 92.688 | D13: 31.782 | E13: 77.87 | F13: 191.698 | N13: B-C 424B4 p. F-4; D and F Q2 10-Q p. 6; E Q1 10-Q p. 5
A14: Total current assets | B14: 1030.479 | C14: 1543.646 | D14: 1543.646 | E14: 3580.961 | F14: 9121.714 | N14: B-C 424B4 p. F-4; D and F Q2 10-Q p. 6; E Q1 10-Q p. 5
A15: Property and equipment, net | B15: 43.174 | C15: 437.396 | D15: 437.396 | E15: 572.439 | F15: 986.808 | N15: B-C 424B4 p. F-4; D and F Q2 10-Q p. 6; E Q1 10-Q p. 5
A16: Customer warrants, net of current portion | D16: 91.447 | E16: 425.355 | F16: 960.635 | N16: B-C 424B4 p. F-4; D and F Q2 10-Q p. 6; E Q1 10-Q p. 5; caption not in the filing for Dec 2024A, Dec 2025A (blank)
A17: Operating lease right-of-use assets | B17: 36.571 | C17: 248.95 | D17: 248.95 | E17: 353.303 | F17: 528.275 | N17: B-C 424B4 p. F-4; D and F Q2 10-Q p. 6; E Q1 10-Q p. 5
A18: Other non-current assets | B18: 2.514 | C18: 96.045 | D18: 4.598 | E18: 16.32 | F18: 30.44 | N18: B-C 424B4 p. F-4; D and F Q2 10-Q p. 6; E Q1 10-Q p. 5
A19: Total assets | B19: 1112.738 | C19: 2326.037 | D19: 2326.037 | E19: 4948.378 | F19: 11627.872 | N19: B-C 424B4 p. F-4; D and F Q2 10-Q p. 6; E Q1 10-Q p. 5
A21: Current liabilities:
A22: Accounts payable | B22: 25.63 | C22: 48.63 | D22: 48.63 | E22: 50.336 | F22: 88.313 | N22: B-C 424B4 p. F-4; D and F Q2 10-Q p. 6; E Q1 10-Q p. 5
A23: Deferred revenue, current | B23: 38.537 | C23: 131.049 | D23: 131.049 | E23: 149.918 | F23: 173.735 | N23: B-C 424B4 p. F-4; D and F Q2 10-Q p. 6; E Q1 10-Q p. 5
A24: Operating lease liability, current | D24: 45.865 | E24: 66.218 | F24: 88.422 | N24: B-C 424B4 p. F-4; D and F Q2 10-Q p. 6; E Q1 10-Q p. 5; caption not in the filing for Dec 2024A, Dec 2025A (blank)
A25: Customer deposits | B25: 640.317 | C25: 354.46 | D25: 354.46 | E25: 368.426 | F25: 242.672 | N25: B-C 424B4 p. F-4; D and F Q2 10-Q p. 6; E Q1 10-Q p. 5
A26: Forward contract liability | B26: 363.336 | C26: — | N26: B-C 424B4 p. F-4; D and F Q2 10-Q p. 6; E Q1 10-Q p. 5; caption not in the filing for Dec 2025A recast, Mar 2026A, Jun 2026A (blank)
A27: Working capital loan | D27: — | E27: 621.306 | F27: 736.036 | N27: B-C 424B4 p. F-4; D and F Q2 10-Q p. 6; E Q1 10-Q p. 5; caption not in the filing for Dec 2024A, Dec 2025A (blank)
A28: Accrued and other current liabilities | B28: 110.315 | C28: 185.401 | D28: 139.536 | E28: 171.042 | F28: 236.91 | N28: B-C 424B4 p. F-4; D and F Q2 10-Q p. 6; E Q1 10-Q p. 5
A29: Total current liabilities | B29: 1178.135 | C29: 719.54 | D29: 719.54 | E29: 1427.246 | F29: 1566.088 | N29: B-C 424B4 p. F-4; D and F Q2 10-Q p. 6; E Q1 10-Q p. 5
A30: Deferred revenue, net of current portion | D30: 35.847 | E30: 94.344 | F30: 244.529 | N30: B-C 424B4 p. F-4; D and F Q2 10-Q p. 6; E Q1 10-Q p. 5; caption not in the filing for Dec 2024A, Dec 2025A (blank)
A31: Operating lease liability, net of current portion | B31: 27.37 | C31: 215.957 | D31: 215.957 | E31: 312.474 | F31: 480.405 | N31: B-C 424B4 p. F-4; D and F Q2 10-Q p. 6; E Q1 10-Q p. 5
A32: Working capital loan, net of current portion | D32: — | E32: 361.617 | F32: 182.208 | N32: B-C 424B4 p. F-4; D and F Q2 10-Q p. 6; E Q1 10-Q p. 5; caption not in the filing for Dec 2024A, Dec 2025A (blank)
A33: Other non-current liabilities | B33: 23.958 | C33: 35.847 | N33: B-C 424B4 p. F-4; D and F Q2 10-Q p. 6; E Q1 10-Q p. 5; caption not in the filing for Dec 2025A recast, Mar 2026A, Jun 2026A (blank)
A34: Total liabilities | B34: 1229.463 | C34: 971.344 | D34: 971.344 | E34: 2195.681 | F34: 2473.23 | N34: B-C 424B4 p. F-4; D and F Q2 10-Q p. 6; E Q1 10-Q p. 5
A35: Redeemable convertible preferred stock | B35: 850.066 | C35: 1933.348 | D35: 1933.348 | E35: 2947.379 | F35: — | N35: B-C 424B4 p. F-4; D and F Q2 10-Q p. 6; E Q1 10-Q p. 5
A37: Stockholders' equity (deficit)
A38: Class A common stock | B38: 0.001 | C38: 0.001 | D38: 0.001 | E38: 0.001 | F38: 0.001 | N38: B-C 424B4 p. F-4; D and F Q2 10-Q p. 6; E Q1 10-Q p. 5
A39: Class B common stock | F39: 0.001 | N39: B-C 424B4 p. F-4; D and F Q2 10-Q p. 6; E Q1 10-Q p. 5; caption not in the filing for Dec 2024A, Dec 2025A, Dec 2025A recast, Mar 2026A (blank)
A40: Class N common stock | B40: — | C40: — | D40: — | E40: — | F40: — | N40: B-C 424B4 p. F-4; D and F Q2 10-Q p. 6; E Q1 10-Q p. 5
A41: Treasury stock, at cost | B41: -0.088 | C41: -21.456 | D41: -21.456 | E41: -21.456 | F41: -21.456 | N41: B-C 424B4 p. F-4; D and F Q2 10-Q p. 6; E Q1 10-Q p. 5
A42: Additional paid-in capital | B42: 176.233 | C42: 346.829 | D42: 346.829 | E42: 742.713 | F42: 10540.193 | N42: B-C 424B4 p. F-4; D and F Q2 10-Q p. 6; E Q1 10-Q p. 5
A43: Accumulated other comprehensive income | B43: 0.22 | C43: 1.301 | D43: 1.301 | E43: 3.396 | F43: 5.767 | N43: B-C 424B4 p. F-4; D and F Q2 10-Q p. 6; E Q1 10-Q p. 5
A44: Accumulated deficit | B44: -1143.157 | C44: -905.33 | D44: -905.33 | E44: -919.336 | F44: -1369.864 | N44: B-C 424B4 p. F-4; D and F Q2 10-Q p. 6; E Q1 10-Q p. 5
A45: Total stockholders' equity (deficit) | B45: -966.791 | C45: -578.655 | D45: -578.655 | E45: -194.682 | F45: 9154.642 | N45: B-C 424B4 p. F-4; D and F Q2 10-Q p. 6; E Q1 10-Q p. 5
A46: Total liabilities, redeemable convertible preferred stock, and stockholders' equity (deficit) | B46: 1112.738 | C46: 2326.037 | D46: 2326.037 | E46: 4948.378 | F46: 11627.872 | N46: B-C 424B4 p. F-4; D and F Q2 10-Q p. 6; E Q1 10-Q p. 5
A48: Memo: items used by the model
A49: Cash, cash equivalents and restricted cash | B49: =SUM(B7,B8) -> 581.965 | C49: =SUM(C7,C8) -> 930.378 | D49: =SUM(D7,D8) -> 930.378 | E49: =SUM(E7,E8) -> 2745.114 | F49: =SUM(F7,F8) -> 7426.837 | N49: Ties to the cash flow statement.
A50: Cash, cash equivalents and investments (excluding restricted cash) | B50: =SUM(B7,B9) -> 337.151 | C50: =SUM(C7,C9) -> 1108.237 | D50: =SUM(D7,D9) -> 1108.237 | E50: =SUM(E7,E9) -> 2231.621 | F50: =SUM(F7,F9) -> 7921.547
A51: Customer warrants, current and non-current | B51: =SUM(B12,B16) -> 0 | C51: =SUM(C12,C16) -> 0 | D51: =SUM(D12,D16) -> 152.353 | E51: =SUM(E12,E16) -> 516.056 | F51: =SUM(F12,F16) -> 1128.397 | N51: Equity-classified warrants given to OpenAI, G42 and AWS; booked as a reduction of revenue through October 2031 (Q2 10-Q p. 25).
A52: Deferred revenue, current and non-current | B52: =SUM(B23,B30) -> 38.537 | C52: =SUM(C23,C30) -> 131.049 | D52: =SUM(D23,D30) -> 166.896 | E52: =SUM(E23,E30) -> 244.262 | F52: =SUM(F23,F30) -> 418.264
A53: Operating lease liabilities, current and non-current | B53: =SUM(B24,B31) -> 27.37 | C53: =SUM(C24,C31) -> 215.957 | D53: =SUM(D24,D31) -> 261.822 | E53: =SUM(E24,E31) -> 378.692 | F53: =SUM(F24,F31) -> 568.827 | N53: 424B4 columns: the current part sits inside accrued liabilities (not split).
A54: Working Capital Loan (OpenAI), current and non-current | B54: =SUM(B27,B32) -> 0 | C54: =SUM(C27,C32) -> 0 | D54: =SUM(D27,D32) -> 0 | E54: =SUM(E27,E32) -> 982.923 | F54: =SUM(F27,F32) -> 918.244
A56: Checks: recomputed less filed (zero passes)
A57: Total current assets | B57: =SUM(B7,B8,B9,B10,B11,B12,B13)-B14 -> 0 | C57: =SUM(C7,C8,C9,C10,C11,C12,C13)-C14 -> 0 | D57: =SUM(D7,D8,D9,D10,D11,D12,D13)-D14 -> 0 | E57: =SUM(E7,E8,E9,E10,E11,E12,E13)-E14 -> 0 | F57: =SUM(F7,F8,F9,F10,F11,F12,F13)-F14 -> 0
A58: Total assets | B58: =SUM(B14,B15,B16,B17,B18)-B19 -> 0 | C58: =SUM(C14,C15,C16,C17,C18)-C19 -> 0 | D58: =SUM(D14,D15,D16,D17,D18)-D19 -> 0 | E58: =SUM(E14,E15,E16,E17,E18)-E19 -> 0 | F58: =SUM(F14,F15,F16,F17,F18)-F19 -> 0
A59: Total current liabilities | B59: =SUM(B22,B23,B24,B25,B26,B27,B28)-B29 -> 0 | C59: =SUM(C22,C23,C24,C25,C26,C27,C28)-C29 -> 0 | D59: =SUM(D22,D23,D24,D25,D26,D27,D28)-D29 -> 0 | E59: =SUM(E22,E23,E24,E25,E26,E27,E28)-E29 -> 0 | F59: =SUM(F22,F23,F24,F25,F26,F27,F28)-F29 -> 0
A60: Total liabilities | B60: =SUM(B29,B30,B31,B32,B33)-B34 -> 0 | C60: =SUM(C29,C30,C31,C32,C33)-C34 -> 0 | D60: =SUM(D29,D30,D31,D32,D33)-D34 -> 0 | E60: =SUM(E29,E30,E31,E32,E33)-E34 -> 0 | F60: =SUM(F29,F30,F31,F32,F33)-F34 -> 0
A61: Total stockholders' equity (deficit) | B61: =SUM(B38,B39,B40,B41,B42,B43,B44)-B45 -> 0 | C61: =SUM(C38,C39,C40,C41,C42,C43,C44)-C45 -> 0 | D61: =SUM(D38,D39,D40,D41,D42,D43,D44)-D45 -> 0 | E61: =SUM(E38,E39,E40,E41,E42,E43,E44)-E45 -> 0 | F61: =SUM(F38,F39,F40,F41,F42,F43,F44)-F45 -> 0
A62: Liabilities, preferred stock and equity | B62: =SUM(B34,B35,B45)-B46 -> 0 | C62: =SUM(C34,C35,C45)-C46 -> 0 | D62: =SUM(D34,D35,D45)-D46 -> 0 | E62: =SUM(E34,E35,E45)-E46 -> 0 | F62: =SUM(F34,F35,F45)-F46 -> 0
A63: Balance: total assets less the other side | B63: =B19-B46 -> 0 | C63: =C19-C46 -> 0 | D63: =D19-D46 -> 0 | E63: =E19-E46 -> 0 | F63: =F19-F46 -> 0
A64: Recast 31 Dec 2025 totals equal the 424B4 | D64: =D19-C19+D34-C34 -> 0

Sheet CF_Hist
A1: Cerebras Systems Inc. (Nasdaq: CBRS) | Consolidated statements of cash flows, as filed
A2: USD millions (filed in thousands / 1,000). 424B4 p. F-8 (FY, audited); Q2 10-Q p. 11 (6M, unaudited). Cash includes restricted cash.
A4: Fiscal year ends 31 December | B4: FY2024A | C4: FY2025A | D4: 6M 2025A | E4: 6M 2026A | M4: Comentarios FG | N4: Source / derivation
A6: Cash flows from operating activities:
A7: Net income (loss) | B7: -481.602 | C7: 237.827 | D7: 285.645 | E7: -464.534 | N7: 424B4 p. F-8 (FY); Q2 10-Q p. 11 (6M)
A8: Depreciation and amortization | B8: 11.537 | C8: 34.454 | D8: 9.315 | E8: 42.551 | N8: 424B4 p. F-8 (FY); Q2 10-Q p. 11 (6M)
A9: Stock-based compensation | B9: 58.564 | C9: 49.767 | D9: 22.435 | E9: 386.601 | N9: 424B4 p. F-8 (FY); Q2 10-Q p. 11 (6M)
A10: Amortization of customer warrants | D10: — | E10: 46.315 | N10: 424B4 p. F-8 (FY); Q2 10-Q p. 11 (6M); caption not in the filing for FY2024A, FY2025A (blank)
A11: Non-cash lease expense | B11: 7.607 | C11: 22.673 | D11: 5.872 | E11: 39.104 | N11: 424B4 p. F-8 (FY); Q2 10-Q p. 11 (6M)
A12: Non-cash interest expense | D12: — | E12: 38.602 | N12: 424B4 p. F-8 (FY); Q2 10-Q p. 11 (6M); caption not in the filing for FY2024A, FY2025A (blank)
A13: Provision for product warranties | B13: 12.525 | C13: 20.969 | D13: 9 | E13: 8.43 | N13: 424B4 p. F-8 (FY); Q2 10-Q p. 11 (6M)
A14: Change in fair value (extinguishment) of forward contract liability | B14: 401.264 | C14: -363.336 | D14: -363.336 | E14: — | N14: 424B4 p. F-8 (FY); Q2 10-Q p. 11 (6M)
A15: Other | B15: -1.388 | C15: 3.235 | D15: -0.835 | E15: -2.11 | N15: 424B4 p. F-8 (FY); Q2 10-Q p. 11 (6M)
A17: Changes in operating assets and liabilities:
A18: Accounts receivable | B18: -130.672 | C18: 87.012 | D18: 125.508 | E18: -72.938 | N18: 424B4 p. F-8 (FY); Q2 10-Q p. 11 (6M)
A19: Inventories | B19: -144.969 | C19: 63.307 | D19: 74.929 | E19: 31.116 | N19: 424B4 p. F-8 (FY); Q2 10-Q p. 11 (6M)
A20: Prepaid expenses and other assets | B20: -17.051 | C20: -13.867 | D20: -3.003 | E20: -182.311 | N20: 424B4 p. F-8 (FY); Q2 10-Q p. 11 (6M)
A21: Accounts payable | B21: 9.01 | C21: 21.151 | D21: 6.314 | E21: 0.565 | N21: 424B4 p. F-8 (FY); Q2 10-Q p. 11 (6M)
A22: Deferred revenue | B22: 38.196 | C22: 109.474 | D22: 16.525 | E22: 126.44 | N22: 424B4 p. F-8 (FY); Q2 10-Q p. 11 (6M)
A23: Customer deposits | B23: 640.317 | C23: -285.857 | D23: -320.558 | E23: -111.788 | N23: 424B4 p. F-8 (FY); Q2 10-Q p. 11 (6M)
A24: Other liabilities | B24: 48.64 | C24: 3.141 | D24: 8.346 | E24: 66.469 | N24: 424B4 p. F-8 (FY); Q2 10-Q p. 11 (6M)
A25: Net cash flows provided by (used in) operating activities | B25: 451.978 | C25: -10.05 | D25: -123.843 | E25: -47.488 | N25: 424B4 p. F-8 (FY); Q2 10-Q p. 11 (6M)
A27: Cash flows from investing activities:
A28: Purchases of property and equipment | B28: -23.435 | C28: -382.739 | D28: -185.094 | E28: -548.873 | N28: 424B4 p. F-8 (FY); Q2 10-Q p. 11 (6M)
A29: Purchases of investments | B29: -302.898 | C29: -525.414 | D29: -20.175 | E29: -1275.515 | N29: 424B4 p. F-8 (FY); Q2 10-Q p. 11 (6M)
A30: Maturities and sales of investments | B30: 309.548 | C30: 240.577 | D30: 117.973 | E30: 514.455 | N30: 424B4 p. F-8 (FY); Q2 10-Q p. 11 (6M)
A31: Net cash flows used in investing activities | B31: -16.785 | C31: -667.576 | D31: -87.296 | E31: -1309.933 | N31: 424B4 p. F-8 (FY); Q2 10-Q p. 11 (6M)
A33: Cash flows from financing activities:
A34: Proceeds from initial public offering, net of underwriting discounts and commissions | D34: — | E34: 6232.511 | N34: 424B4 p. F-8 (FY); Q2 10-Q p. 11 (6M); caption not in the filing for FY2024A, FY2025A (blank)
A35: Proceeds from sale of shares of redeemable convertible preferred stock (2026: Series H) | B35: 85 | C35: 1100 | D35: — | E35: 1014.249 | N35: 424B4 p. F-8 (FY); Q2 10-Q p. 11 (6M)
A36: Costs incurred in connection with the sale of preferred stock | B36: -0.102 | C36: -16.718 | D36: — | E36: -0.218 | N36: 424B4 p. F-8 (FY); Q2 10-Q p. 11 (6M)
A37: Proceeds from Working Capital Loan | D37: — | E37: 1004.571 | N37: 424B4 p. F-8 (FY); Q2 10-Q p. 11 (6M); caption not in the filing for FY2024A, FY2025A (blank)
A38: Proceeds from exercise of stock options | B38: 27.752 | C38: 17.299 | D38: 5.176 | E38: 20.221 | N38: 424B4 p. F-8 (FY); Q2 10-Q p. 11 (6M)
A39: Proceeds from issuance of shares of Class N common stock | D39: — | E39: 15.036 | N39: 424B4 p. F-8 (FY); Q2 10-Q p. 11 (6M); caption not in the filing for FY2024A, FY2025A (blank)
A40: Fees paid for revolving credit facility | D40: — | E40: -3.801 | N40: 424B4 p. F-8 (FY); Q2 10-Q p. 11 (6M); caption not in the filing for FY2024A, FY2025A (blank)
A41: Repurchases of early exercised stock options | B41: -0.028 | C41: -0.028 | D41: -0.028 | E41: — | N41: 424B4 p. F-8 (FY); Q2 10-Q p. 11 (6M)
A42: Cancellation and settlement of stock options in connection with the Tender Offer | B42: — | C42: -49.32 | N42: 424B4 p. F-8 (FY); Q2 10-Q p. 11 (6M); caption not in the filing for 6M 2025A, 6M 2026A (blank)
A43: Repurchase of common stock | B43: — | C43: -21.368 | N43: 424B4 p. F-8 (FY); Q2 10-Q p. 11 (6M); caption not in the filing for 6M 2025A, 6M 2026A (blank)
A44: Tax withheld related to RSU settlement | B44: — | C44: -2.95 | N44: 424B4 p. F-8 (FY); Q2 10-Q p. 11 (6M); caption not in the filing for 6M 2025A, 6M 2026A (blank)
A45: Tax withholding from tender offer and initial public offering | D45: — | E45: -416.66 | N45: 424B4 p. F-8 (FY); Q2 10-Q p. 11 (6M); caption not in the filing for FY2024A, FY2025A (blank)
A46: Payments of deferred offering costs (2026: and other financing activities) | B46: -0.326 | C46: -0.355 | D46: — | E46: -12.667 | N46: 424B4 p. F-8 (FY); Q2 10-Q p. 11 (6M)
A47: Net cash flows provided by financing activities | B47: 112.296 | C47: 1026.56 | D47: 5.148 | E47: 7853.242 | N47: 424B4 p. F-8 (FY); Q2 10-Q p. 11 (6M)
A48: Effect of exchange rate on cash | B48: -0.304 | C48: -0.521 | D48: 0.912 | E48: 0.638 | N48: 424B4 p. F-8 (FY); Q2 10-Q p. 11 (6M)
A49: Increase (decrease) in cash, cash equivalents, and restricted cash | B49: 547.185 | C49: 348.413 | D49: -205.079 | E49: 6496.459 | N49: 424B4 p. F-8 (FY); Q2 10-Q p. 11 (6M)
A50: Cash, cash equivalents, and restricted cash beginning of period | B50: 34.78 | C50: 581.965 | D50: 581.965 | E50: 930.378 | N50: 424B4 p. F-8 (FY); Q2 10-Q p. 11 (6M)
A51: Cash, cash equivalents, and restricted cash end of period | B51: 581.965 | C51: 930.378 | D51: 376.886 | E51: 7426.837 | N51: 424B4 p. F-8 (FY); Q2 10-Q p. 11 (6M)
A53: Memo: groups used by the model
A54: Other non-cash items (lease, warranty, forward contract, other) | B54: =SUM(B11,B13,B14,B15) -> 420.008 | C54: =SUM(C11,C13,C14,C15) -> -316.459 | D54: =SUM(D11,D13,D14,D15) -> -349.299 | E54: =SUM(E11,E13,E14,E15) -> 45.424
A55: Changes in operating assets and liabilities | B55: =SUM(B18,B19,B20,B21,B22,B23,B24) -> 443.471 | C55: =SUM(C18,C19,C20,C21,C22,C23,C24) -> -15.639 | D55: =SUM(D18,D19,D20,D21,D22,D23,D24) -> -91.939 | E55: =SUM(E18,E19,E20,E21,E22,E23,E24) -> -142.447
A56: Investments bought less matured and sold | B56: =SUM(B29,B30) -> 6.65 | C56: =SUM(C29,C30) -> -284.837 | D56: =SUM(D29,D30) -> 97.798 | E56: =SUM(E29,E30) -> -761.06
A58: Checks: recomputed less filed (zero passes)
A59: Net cash from operating activities | B59: =SUM(B7,B8,B9,B10,B11,B12,B13,B14,B15,B18,B19,B20,B21,B22,B23,B24)-B25 -> 0 | C59: =SUM(C7,C8,C9,C10,C11,C12,C13,C14,C15,C18,C19,C20,C21,C22,C23,C24)-C25 -> 0 | D59: =SUM(D7,D8,D9,D10,D11,D12,D13,D14,D15,D18,D19,D20,D21,D22,D23,D24)-D25 -> 0 | E59: =SUM(E7,E8,E9,E10,E11,E12,E13,E14,E15,E18,E19,E20,E21,E22,E23,E24)-E25 -> 0
A60: Net cash used in investing activities | B60: =SUM(B28,B29,B30)-B31 -> 0 | C60: =SUM(C28,C29,C30)-C31 -> 0 | D60: =SUM(D28,D29,D30)-D31 -> 0 | E60: =SUM(E28,E29,E30)-E31 -> 0
A61: Net cash from financing activities | B61: =SUM(B34,B35,B36,B37,B38,B39,B40,B41,B42,B43,B44,B45,B46)-B47 -> 0 | C61: =SUM(C34,C35,C36,C37,C38,C39,C40,C41,C42,C43,C44,C45,C46)-C47 -> 0 | D61: =SUM(D34,D35,D36,D37,D38,D39,D40,D41,D42,D43,D44,D45,D46)-D47 -> 0 | E61: =SUM(E34,E35,E36,E37,E38,E39,E40,E41,E42,E43,E44,E45,E46)-E47 -> 0
A62: Net change in cash | B62: =B25+B31+B47+B48-B49 -> 0 | C62: =C25+C31+C47+C48-C49 -> 0 | D62: =D25+D31+D47+D48-D49 -> 0 | E62: =E25+E31+E47+E48-E49 -> 0
A63: Beginning cash plus change less ending cash | B63: =B50+B49-B51 -> 0 | C63: =C50+C49-C51 -> 0 | D63: =D50+D49-D51 -> 0 | E63: =E50+E49-E51 -> 0
A64: Net income equals the statement of operations | B64: =B7-IS_Hist!B26 -> 0 | C64: =C7-IS_Hist!C26 -> 0 | D64: =D7-IS_Hist!D26 -> 0 | E64: =E7-IS_Hist!E26 -> 0
A65: Ending cash equals balance sheet cash plus restricted cash | B65: =B51-BS_Hist!B49 -> 0 | C65: =C51-BS_Hist!C49 -> 0 | E65: =E51-BS_Hist!F49 -> 0 | N65: FY2024 and FY2025 against 31 December; 6M 2026 against 30 June 2026. 6M 2025 has no balance sheet here.
A66: Stock pay equals the stock compensation note | C66: =C9-N(Revenue_Hist!C39) -> 0 | E66: =E9-N(Revenue_Hist!E39) -> 0

Sheet SCE_Hist
A1: Cerebras Systems Inc. (Nasdaq: CBRS) | Statements of redeemable convertible preferred stock and stockholders' equity (deficit), as filed
A2: Amounts USD millions (filed thousands / 1,000); share counts in thousands as filed. 2024-2025: 424B4 p. F-7; Q1 and Q2 2026: Q2 10-Q p. 10.
A4: Line | B4: Preferred: shares (k) | C4: Preferred: amount | D4: Common: shares (k) | E4: Common: amount | F4: Additional paid-in capital | G4: Treasury: shares (k) | H4: Treasury: amount | I4: Accumulated other comprehensive income | J4: Accumulated deficit | K4: Total stockholders' equity (deficit) | M4: Comentarios FG | N4: Source / derivation
A6: Fiscal years 2024 and 2025 (audited)
A7: Balance as of December 31, 2023 | B7: 77033 | C7: 722.78 | D7: 45362 | E7: — | F7: 101.578 | G7: -300 | H7: -0.088 | I7: 1.103 | J7: -661.555 | K7: -558.962 | N7: 424B4 p. F-7
A8: Issuance of shares of Series F-1 redeemable convertible preferred stock, net of issuance costs | B8: 5798 | C8: 84.898 | D8: — | E8: — | F8: — | G8: — | H8: — | I8: — | J8: — | K8: — | N8: 424B4 p. F-7
A9: Settlement of Series F-1 redeemable convertible preferred stock forward contract liability | B9: — | C9: 37.928 | D9: — | E9: — | F9: — | G9: — | H9: — | I9: — | J9: — | K9: — | N9: 424B4 p. F-7
A10: Deemed dividend on issuance of Series F-1 redeemable convertible preferred stock | B10: — | C10: 3.182 | D10: — | E10: — | F10: -3.182 | G10: — | H10: — | I10: — | J10: — | K10: -3.182 | N10: 424B4 p. F-7
A11: Issuance of shares of Series E redeemable convertible preferred stock upon exercise of warrant | B11: 68 | C11: 1.278 | D11: — | E11: — | F11: — | G11: — | H11: — | I11: — | J11: — | K11: — | N11: 424B4 p. F-7
A12: Shares issued upon exercise of stock options, net of repurchases of early exercised stock options | B12: — | C12: — | D12: 8011 | E12: 0.001 | F12: 17.667 | G12: — | H12: — | I12: — | J12: — | K12: 17.668 | N12: 424B4 p. F-7
A13: Vesting of early exercised stock options | B13: — | C13: — | D13: — | E13: — | F13: 1.733 | G13: — | H13: — | I13: — | J13: — | K13: 1.733 | N13: 424B4 p. F-7
A14: Stock-based compensation expense | B14: — | C14: — | D14: — | E14: — | F14: 57.525 | G14: — | H14: — | I14: — | J14: — | K14: 57.525 | N14: 424B4 p. F-7
A15: Conversion of stock-based liability classified awards to stock-based equity classified awards | B15: — | C15: — | D15: — | E15: — | F15: 0.912 | G15: — | H15: — | I15: — | J15: — | K15: 0.912 | N15: 424B4 p. F-7
A16: Foreign currency translation adjustments, net of tax | B16: — | C16: — | D16: — | E16: — | F16: — | G16: — | H16: — | I16: -0.304 | J16: — | K16: -0.304 | N16: 424B4 p. F-7
A17: Change in net unrealized loss on debt securities, net of tax | B17: — | C17: — | D17: — | E17: — | F17: — | G17: — | H17: — | I17: -0.579 | J17: — | K17: -0.579 | N17: 424B4 p. F-7
A18: Net loss | B18: — | C18: — | D18: — | E18: — | F18: — | G18: — | H18: — | I18: — | J18: -481.602 | K18: -481.602 | N18: 424B4 p. F-7
A19: Balance as of December 31, 2024 | B19: 82899 | C19: 850.066 | D19: 53373 | E19: 0.001 | F19: 176.233 | G19: -300 | H19: -0.088 | I19: 0.22 | J19: -1143.157 | K19: -966.791 | N19: 424B4 p. F-7
A20: Issuance of shares of Series G redeemable convertible preferred stock, net of issuance costs | B20: 30360 | C20: 1083.282 | D20: — | E20: — | F20: — | G20: — | H20: — | I20: — | J20: — | K20: — | N20: 424B4 p. F-7
A21: Customer warrants issued | B21: — | C21: — | D21: — | E21: — | F21: 152.353 | G21: — | H21: — | I21: — | J21: — | K21: 152.353 | N21: 424B4 p. F-7
A22: Cancellation and settlement of stock options in connection with the Tender Offer | B22: — | C22: — | D22: — | E22: — | F22: -49.32 | G22: — | H22: — | I22: — | J22: — | K22: -49.32 | N22: 424B4 p. F-7
A23: Repurchase of common stock | B23: — | C23: — | D23: — | E23: — | F23: — | G23: -590 | H23: -21.368 | I23: — | J23: — | K23: -21.368 | N23: 424B4 p. F-7
A24: Shares issued upon acceleration of RSUs vesting and exercise of stock options, net of repurchases and withholding taxes | B24: — | C24: — | D24: 4623 | E24: — | F24: 17.169 | G24: — | H24: — | I24: — | J24: — | K24: 17.169 | N24: 424B4 p. F-7
A25: Tax withheld related to RSU settlement | B25: — | C25: — | D25: -89 | E25: — | F25: -2.95 | G25: — | H25: — | I25: — | J25: — | K25: -2.95 | N25: 424B4 p. F-7
A26: Vesting of early exercised stock options | B26: — | C26: — | D26: — | E26: — | F26: 3.449 | G26: — | H26: — | I26: — | J26: — | K26: 3.449 | N26: 424B4 p. F-7
A27: Stock-based compensation expense | B27: — | C27: — | D27: — | E27: — | F27: 48.857 | G27: — | H27: — | I27: — | J27: — | K27: 48.857 | N27: 424B4 p. F-7
A28: Conversion of stock-based liability classified awards to stock-based equity classified awards | B28: — | C28: — | D28: — | E28: — | F28: 1.038 | G28: — | H28: — | I28: — | J28: — | K28: 1.038 | N28: 424B4 p. F-7
A29: Foreign currency translation adjustments, net of tax | B29: — | C29: — | D29: — | E29: — | F29: — | G29: — | H29: — | I29: -0.521 | J29: — | K29: -0.521 | N29: 424B4 p. F-7
A30: Change in net unrealized loss on debt securities, net of tax | B30: — | C30: — | D30: — | E30: — | F30: — | G30: — | H30: — | I30: 1.602 | J30: — | K30: 1.602 | N30: 424B4 p. F-7
A31: Net income | B31: — | C31: — | D31: — | E31: — | F31: — | G31: — | H31: — | I31: — | J31: 237.827 | K31: 237.827 | N31: 424B4 p. F-7
A32: Balance as of December 31, 2025 | B32: 113259 | C32: 1933.348 | D32: 57907 | E32: 0.001 | F32: 346.829 | G32: -890 | H32: -21.456 | I32: 1.301 | J32: -905.33 | K32: -578.655 | N32: 424B4 p. F-7
A34: Six months ended 30 June 2026 (unaudited)
A35: Balance as of December 31, 2025 | B35: 113259 | C35: 1933.348 | D35: 57907 | E35: 0.001 | F35: 346.829 | G35: -890 | H35: -21.456 | I35: 1.301 | J35: -905.33 | K35: -578.655 | N35: Q2 10-Q p. 10
A36: Issuance of shares of Series H redeemable convertible preferred stock, net of issuance costs | B36: 11394 | C36: 1014.031 | D36: — | E36: — | F36: — | G36: — | H36: — | I36: — | J36: — | K36: — | N36: Q2 10-Q p. 10
A37: Customer warrants issued | B37: — | C37: — | D37: — | E37: — | F37: 365.755 | G37: — | H37: — | I37: — | J37: — | K37: 365.755 | N37: Q2 10-Q p. 10
A38: Issuance of shares of Class N common stock | B38: — | C38: — | D38: 2026 | E38: — | F38: 15.019 | G38: — | H38: — | I38: — | J38: — | K38: 15.019 | N38: Q2 10-Q p. 10
A39: Class A common shares issued upon exercise of stock options | B39: — | C39: — | D39: 1085 | E39: — | F39: 5.177 | G39: — | H39: — | I39: — | J39: — | K39: 5.177 | N39: Q2 10-Q p. 10
A40: Tax withholding from tender offer | B40: — | C40: — | D40: — | E40: — | F40: -0.623 | G40: — | H40: — | I40: — | J40: — | K40: -0.623 | N40: Q2 10-Q p. 10
A41: Vesting of early exercised stock options | B41: — | C41: — | D41: — | E41: — | F41: 0.809 | G41: — | H41: — | I41: — | J41: — | K41: 0.809 | N41: Q2 10-Q p. 10
A42: Stock-based compensation expense | B42: — | C42: — | D42: — | E42: — | F42: 9.418 | G42: — | H42: — | I42: — | J42: — | K42: 9.418 | N42: Q2 10-Q p. 10
A43: Conversion of stock-based liability classified awards to stock-based equity classified awards | B43: — | C43: — | D43: — | E43: — | F43: 0.329 | G43: — | H43: — | I43: — | J43: — | K43: 0.329 | N43: Q2 10-Q p. 10
A44: Other comprehensive income | B44: — | C44: — | D44: — | E44: — | F44: — | G44: — | H44: — | I44: 2.095 | J44: — | K44: 2.095 | N44: Q2 10-Q p. 10
A45: Net loss | B45: — | C45: — | D45: — | E45: — | F45: — | G45: — | H45: — | I45: — | J45: -14.006 | K45: -14.006 | N45: Q2 10-Q p. 10
A46: Balance as of March 31, 2026 | B46: 124653 | C46: 2947.379 | D46: 61018 | E46: 0.001 | F46: 742.713 | G46: -890 | H46: -21.456 | I46: 3.396 | J46: -919.336 | K46: -194.682 | N46: Q2 10-Q p. 10
A47: Issuance of common stock in connection with initial public offering, net of underwriting discounts and commissions and offering costs | B47: — | C47: — | D47: 34500 | E47: — | F47: 6217.099 | G47: — | H47: — | I47: — | J47: — | K47: 6217.099 | N47: Q2 10-Q p. 10
A48: Conversion of redeemable convertible preferred stock in connection with initial public offering | B48: -124653 | C48: -2947.379 | D48: 124653 | E48: 0.001 | F48: 2947.378 | G48: — | H48: — | I48: — | J48: — | K48: 2947.379 | N48: Q2 10-Q p. 10
A49: Customer warrants issued | B49: — | C49: — | D49: — | E49: — | F49: 656.604 | G49: — | H49: — | I49: — | J49: — | K49: 656.604 | N49: Q2 10-Q p. 10
A50: Issuance of shares of Class N common stock | B50: — | C50: — | D50: 1656 | E50: — | F50: 0.017 | G50: — | H50: — | I50: — | J50: — | K50: 0.017 | N50: Q2 10-Q p. 10
A51: Issuance of common stock upon settlement of restricted stock units | B51: — | C51: — | D51: 5301 | E51: — | F51: — | G51: — | H51: — | I51: — | J51: — | K51: — | N51: Q2 10-Q p. 10
A52: Class A common shares issued upon exercise of stock options | B52: — | C52: — | D52: 3326 | E52: — | F52: 14.958 | G52: — | H52: — | I52: — | J52: — | K52: 14.958 | N52: Q2 10-Q p. 10
A53: Tax withholdings on settlement of restricted stock units | B53: — | C53: — | D53: -2250 | E53: — | F53: -416.037 | G53: — | H53: — | I53: — | J53: — | K53: -416.037 | N53: Q2 10-Q p. 10
A54: Vesting of early exercised stock options | B54: — | C54: — | D54: — | E54: — | F54: 0.627 | G54: — | H54: — | I54: — | J54: — | K54: 0.627 | N54: Q2 10-Q p. 10
A55: Stock-based compensation expense | B55: — | C55: — | D55: — | E55: — | F55: 376.834 | G55: — | H55: — | I55: — | J55: — | K55: 376.834 | N55: Q2 10-Q p. 10
A56: Other comprehensive income | B56: — | C56: — | D56: — | E56: — | F56: — | G56: — | H56: — | I56: 2.371 | J56: — | K56: 2.371 | N56: Q2 10-Q p. 10
A57: Net loss | B57: — | C57: — | D57: — | E57: — | F57: — | G57: — | H57: — | I57: — | J57: -450.528 | K57: -450.528 | N57: Q2 10-Q p. 10
A58: Balance as of June 30, 2026 | B58: — | C58: — | D58: 228204 | E58: 0.002 | F58: 10540.193 | G58: -890 | H58: -21.456 | I58: 5.767 | J58: -1369.864 | K58: 9154.642 | N58: Q2 10-Q p. 10
A60: Checks (zero passes)
A61: Total = common + APIC + treasury + AOCI + deficit, 31 Dec 2024 | K61: =SUM(E19,F19,H19,I19,J19)-K19 -> 0
A62: Total equals the balance sheet, 31 Dec 2024 | K62: =K19-BS_Hist!B45 -> 0
A63: Preferred amount equals the balance sheet, 31 Dec 2024 | C63: =N(C19)-N(BS_Hist!B35) -> 0
A64: Total = common + APIC + treasury + AOCI + deficit, 31 Dec 2025 | K64: =SUM(E32,F32,H32,I32,J32)-K32 -> 0
A65: Total equals the balance sheet, 31 Dec 2025 | K65: =K32-BS_Hist!C45 -> 0
A66: Preferred amount equals the balance sheet, 31 Dec 2025 | C66: =N(C32)-N(BS_Hist!C35) -> 0
A67: Total = common + APIC + treasury + AOCI + deficit, 31 Mar 2026 | K67: =SUM(E46,F46,H46,I46,J46)-K46 -> 0
A68: Total equals the balance sheet, 31 Mar 2026 | K68: =K46-BS_Hist!E45 -> 0
A69: Preferred amount equals the balance sheet, 31 Mar 2026 | C69: =N(C46)-N(BS_Hist!E35) -> 0
A70: Total = common + APIC + treasury + AOCI + deficit, 30 Jun 2026 | K70: =SUM(E58,F58,H58,I58,J58)-K58 -> 0
A71: Total equals the balance sheet, 30 Jun 2026 | K71: =K58-BS_Hist!F45 -> 0
A72: Preferred amount equals the balance sheet, 30 Jun 2026 | C72: =N(C58)-N(BS_Hist!F35) -> 0
A73: Opening 2026 balance equals the 2025 closing balance | K73: =K35-K32 -> 0

Sheet Quarterly_Hist
A1: Cerebras Systems Inc. (Nasdaq: CBRS) | Quarterly results, as filed
A2: USD millions (filed thousands / 1,000). Unaudited. Q1 2024-Q4 2025: 424B4 p. 104 (operations and stock pay tables). Q1 2025 and Q1 2026: Q1 10-Q p. 6; Q2 2025 and Q2 2026: Q2 10-Q p. 7. Column L waits for the Q3 2026 10-Q (due November 2026).
A4: Three months ended | B4: Q1 2024A | C4: Q2 2024A | D4: Q3 2024A | E4: Q4 2024A | F4: Q1 2025A | G4: Q2 2025A | H4: Q3 2025A | I4: Q4 2025A | J4: Q1 2026A | K4: Q2 2026A | L4: Q3 2026A | M4: Comentarios FG | N4: Source / derivation
A6: Revenue
A7: Hardware | B7: 49.411 | C7: 54.858 | D7: 50.28 | E7: 57.416 | F7: 69.674 | G7: 70.295 | H7: 96.794 | I7: 121.677 | J7: 110.593 | K7: 54.119 | N7: 424B4 p. 104; 2026: Q1 10-Q p. 6, Q2 10-Q p. 7
A8: Cloud and other services | B8: 17.22 | C8: 14.913 | D8: 22.039 | E8: 24.115 | F8: 29.838 | G8: 33.027 | H8: 38.92 | I8: 49.766 | J8: 82.813 | K8: 125.991 | N8: 424B4 p. 104; 2026: Q1 10-Q p. 6, Q2 10-Q p. 7
A9: Total revenue | B9: 66.631 | C9: 69.771 | D9: 72.319 | E9: 81.531 | F9: 99.512 | G9: 103.322 | H9: 135.714 | I9: 171.443 | J9: 193.406 | K9: 180.11 | N9: 424B4 p. 104; 2026: Q1 10-Q p. 6, Q2 10-Q p. 7
A11: Cost of revenue
A12: Hardware | B12: 33.619 | C12: 32.823 | D12: 34.143 | E12: 36.725 | F12: 48.41 | G12: 46.649 | H12: 47.969 | I12: 61.718 | J12: 64.931 | K12: 53.141 | N12: 424B4 p. 104; 2026: Q1 10-Q p. 6, Q2 10-Q p. 7
A13: Cloud and other services | B13: 7.873 | C13: 6.068 | D13: 6.169 | E13: 10.094 | F13: 9.498 | G13: 24.574 | H13: 32.61 | I13: 39.492 | J13: 42.299 | K13: 101.41 | N13: 424B4 p. 104; 2026: Q1 10-Q p. 6, Q2 10-Q p. 7
A14: Total cost of revenue | B14: 41.492 | C14: 38.891 | D14: 40.312 | E14: 46.819 | F14: 57.908 | G14: 71.223 | H14: 80.579 | I14: 101.21 | J14: 107.23 | K14: 154.551 | N14: 424B4 p. 104; 2026: Q1 10-Q p. 6, Q2 10-Q p. 7
A15: Gross profit | B15: 25.139 | C15: 30.88 | D15: 32.007 | E15: 34.712 | F15: 41.604 | G15: 32.099 | H15: 55.135 | I15: 70.233 | J15: 86.176 | K15: 25.559 | N15: 424B4 p. 104; 2026: Q1 10-Q p. 6, Q2 10-Q p. 7
A17: Operating expenses (by function only in the 10-Q quarters; the 424B4 table gives the total)
A18: Research and development | F18: 52.751 | G18: 60.768 | J18: 75.495 | K18: 320.151 | N18: Q1 10-Q p. 6; Q2 10-Q p. 7
A19: Sales and marketing | F19: 10.326 | G19: 18.228 | J19: 14.701 | K19: 86.969 | N19: Q1 10-Q p. 6; Q2 10-Q p. 7
A20: General and administrative | F20: 6.997 | G20: 10.285 | J20: 11.017 | K20: 95.672 | N20: Q1 10-Q p. 6; Q2 10-Q p. 7
A21: Total operating expenses | B21: 43.19 | C21: 54.64 | D21: 51.384 | E21: 74.962 | F21: 70.074 | G21: 89.281 | H21: 81.604 | I21: 103.974 | J21: 101.213 | K21: 502.792 | N21: 424B4 p. 104; 2026: Q1 10-Q p. 6, Q2 10-Q p. 7
A22: Loss from operations | B22: -18.051 | C22: -23.76 | D22: -19.377 | E22: -40.25 | F22: -28.47 | G22: -57.182 | H22: -26.469 | I22: -33.741 | J22: -15.037 | K22: -477.233 | N22: 424B4 p. 104; 2026: Q1 10-Q p. 6, Q2 10-Q p. 7
A23: Other income, net | F23: 6.286 | G23: 368.358 | J23: 2.528 | K23: 26.979 | N23: Q1 10-Q p. 6; Q2 10-Q p. 7
A24: Income (loss) before income taxes | F24: -22.184 | G24: 311.176 | J24: -12.509 | K24: -450.254 | N24: Q1 10-Q p. 6; Q2 10-Q p. 7
A25: Income tax expense | F25: 1.683 | G25: 1.664 | J25: 1.497 | K25: 0.274 | N25: Q1 10-Q p. 6; Q2 10-Q p. 7
A26: Net income (loss) | B26: -15.75 | C26: -50.855 | D26: -309.341 | E26: -105.656 | F26: -23.867 | G26: 309.512 | H26: -22.201 | I26: -25.617 | J26: -14.006 | K26: -450.528 | N26: 424B4 p. 104; 2026: Q1 10-Q p. 6, Q2 10-Q p. 7
A28: Stock-based compensation and depreciation
A29: Stock pay in cost of revenue | B29: 0.189 | C29: 0.231 | D29: 0.237 | E29: 0.264 | F29: 0.326 | G29: 0.187 | H29: 0.161 | I29: 0.153 | J29: 0.95 | K29: 15.353 | N29: 424B4 p. 104; 2026: Q1 10-Q p. 20, Q2 10-Q p. 26
A30: Stock pay in operating expenses | B30: 9.237 | C30: 22.672 | D30: 16.591 | E30: 9.143 | F30: 8.828 | G30: 13.094 | H30: 11.185 | I30: 15.833 | J30: =J31-J29 -> 8.643 | K30: =K31-K29 -> 361.655 | N30: 2026: total less cost of revenue (the 10-Q gives functions, not this subtotal).
A31: Total stock-based compensation | B31: 9.426 | C31: 22.903 | D31: 16.828 | E31: 9.407 | F31: 9.154 | G31: 13.281 | H31: 11.346 | I31: 15.986 | J31: 9.593 | K31: 377.008 | N31: 424B4 p. 104; 2026: Q1 10-Q p. 20, Q2 10-Q p. 26
A32: Depreciation expense | F32: 3.911 | G32: 5.6 | J32: 18.175 | K32: 24.377 | N32: Q1 10-Q p. 17; Q2 10-Q p. 20
A33: of which in cost of revenue | F33: 1.6 | G33: 1.601 | J33: 9.871 | K33: 18.482 | N33: Q1 10-Q p. 17; Q2 10-Q p. 20
A35: The IPO stock pay catch-up in Q2 2026 (the 10-Q does not split it)
A36: Q2 2026: RSU expense | K36: 332.92 | N36: Q2 10-Q p. 26, expense by security type.
A37: Q2 2026: PRSU expense (CEO and CTO) | K37: 34.223 | N37: Q2 10-Q p. 26-27.
A38: Cumulative RSU charge the 424B4 expected at the IPO | K38: 370.9 | N38: 424B4 p. 100: 'we expect to record a cumulative stock-based compensation expense of $370.9 million' in the quarter to 30 Jun 2026.
A39: Q2 2026 stock pay less the 424B4 catch-up estimate (derived) | K39: =K31-K38 -> 6.108 | N39: An estimate of the Q2 run rate. The catch-up actually booked is not disclosed; the forecast run rate is a separate input (Assumptions).
A41: Cash flow by quarter: Q1 as filed in each 10-Q; Q2 = six months less Q1 (derived) | N41: Q1-Q4 2024 and Q3-Q4 2025 cannot be derived: the 424B4 gives annual cash flows only and no 10-Q covers those quarters; only H2 2025 = FY2025 - 6M 2025 (memo).
A42: Net income (loss) | F42: -23.867 | G42: =N(CF_Hist!D7)-N(F42) -> 309.512 | J42: -14.006 | K42: =N(CF_Hist!E7)-N(J42) -> -450.528 | N42: F, J: Q1 10-Q p. 9; G, K: six months (CF_Hist) less Q1
A43: Depreciation and amortization | F43: 3.911 | G43: =N(CF_Hist!D8)-N(F43) -> 5.404 | J43: 18.175 | K43: =N(CF_Hist!E8)-N(J43) -> 24.376 | N43: F, J: Q1 10-Q p. 9; G, K: six months (CF_Hist) less Q1
A44: Stock-based compensation | F44: 9.154 | G44: =N(CF_Hist!D9)-N(F44) -> 13.281 | J44: 9.593 | K44: =N(CF_Hist!E9)-N(J44) -> 377.008 | N44: F, J: Q1 10-Q p. 9; G, K: six months (CF_Hist) less Q1
A45: Amortization of customer warrants | F45: — | G45: =N(CF_Hist!D10)-N(F45) -> 0 | J45: 2.053 | K45: =N(CF_Hist!E10)-N(J45) -> 44.262 | N45: F, J: Q1 10-Q p. 9; G, K: six months (CF_Hist) less Q1
A46: Non-cash interest expense | F46: — | G46: =N(CF_Hist!D12)-N(F46) -> 0 | J46: 18.949 | K46: =N(CF_Hist!E12)-N(J46) -> 19.653 | N46: F, J: Q1 10-Q p. 9; G, K: six months (CF_Hist) less Q1
A47: Non-cash lease expense | F47: 2.912 | G47: =N(CF_Hist!D11)-N(F47) -> 2.96 | J47: 15.775 | K47: =N(CF_Hist!E11)-N(J47) -> 23.329 | N47: F, J: Q1 10-Q p. 9; G, K: six months (CF_Hist) less Q1
A48: Provision for product warranties | F48: 4.5 | G48: =N(CF_Hist!D13)-N(F48) -> 4.5 | J48: 4.59 | K48: =N(CF_Hist!E13)-N(J48) -> 3.84 | N48: F, J: Q1 10-Q p. 9; G, K: six months (CF_Hist) less Q1
A49: Forward contract liability (extinguishment) | G49: =N(CF_Hist!D14)-N(F49) -> -363.336 | K49: =N(CF_Hist!E14)-N(J49) -> 0 | N49: F, J: Q1 10-Q p. 9; G, K: six months (CF_Hist) less Q1
A50: Other | F50: -0.254 | G50: =N(CF_Hist!D15)-N(F50) -> -0.581 | J50: -0.959 | K50: =N(CF_Hist!E15)-N(J50) -> -1.151 | N50: F, J: Q1 10-Q p. 9; G, K: six months (CF_Hist) less Q1
A51: Accounts receivable | F51: 56.787 | G51: =N(CF_Hist!D18)-N(F51) -> 68.721 | J51: -12.208 | K51: =N(CF_Hist!E18)-N(J51) -> -60.73 | N51: F, J: Q1 10-Q p. 9; G, K: six months (CF_Hist) less Q1
A52: Inventories | F52: 53.752 | G52: =N(CF_Hist!D19)-N(F52) -> 21.177 | J52: -21.684 | K52: =N(CF_Hist!E19)-N(J52) -> 52.8 | N52: F, J: Q1 10-Q p. 9; G, K: six months (CF_Hist) less Q1
A53: Prepaid expenses and other assets | F53: 3.688 | G53: =N(CF_Hist!D20)-N(F53) -> -6.691 | J53: -57.603 | K53: =N(CF_Hist!E20)-N(J53) -> -124.708 | N53: F, J: Q1 10-Q p. 9; G, K: six months (CF_Hist) less Q1
A54: Accounts payable | F54: -5.65 | G54: =N(CF_Hist!D21)-N(F54) -> 11.964 | J54: -10.07 | K54: =N(CF_Hist!E21)-N(J54) -> 10.635 | N54: F, J: Q1 10-Q p. 9; G, K: six months (CF_Hist) less Q1
A55: Deferred revenue | F55: 15.055 | G55: =N(CF_Hist!D22)-N(F55) -> 1.47 | J55: 36.769 | K55: =N(CF_Hist!E22)-N(J55) -> 89.671 | N55: F, J: Q1 10-Q p. 9; G, K: six months (CF_Hist) less Q1
A56: Customer deposits | F56: -159.599 | G56: =N(CF_Hist!D23)-N(F56) -> -160.959 | J56: 13.966 | K56: =N(CF_Hist!E23)-N(J56) -> -125.754 | N56: F, J: Q1 10-Q p. 9; G, K: six months (CF_Hist) less Q1
A57: Other liabilities | F57: -15.326 | G57: =N(CF_Hist!D24)-N(F57) -> 23.672 | J57: 8.995 | K57: =N(CF_Hist!E24)-N(J57) -> 57.474 | N57: F, J: Q1 10-Q p. 9; G, K: six months (CF_Hist) less Q1
A58: Net cash from operating activities | F58: -54.937 | G58: =N(CF_Hist!D25)-N(F58) -> -68.906 | J58: 12.335 | K58: =N(CF_Hist!E25)-N(J58) -> -59.823 | N58: F, J: Q1 10-Q p. 9; G, K: six months (CF_Hist) less Q1
A59: Purchases of property and equipment | F59: -98.244 | G59: =N(CF_Hist!D28)-N(F59) -> -86.85 | J59: -131.97 | K59: =N(CF_Hist!E28)-N(J59) -> -416.903 | N59: F, J: Q1 10-Q p. 9; G, K: six months (CF_Hist) less Q1
A60: Purchases of investments | F60: -20.175 | G60: =N(CF_Hist!D29)-N(F60) -> 0 | J60: -308.801 | K60: =N(CF_Hist!E29)-N(J60) -> -966.714 | N60: F, J: Q1 10-Q p. 9; G, K: six months (CF_Hist) less Q1
A61: Maturities and sales of investments | F61: 61.673 | G61: =N(CF_Hist!D30)-N(F61) -> 56.3 | J61: 204.155 | K61: =N(CF_Hist!E30)-N(J61) -> 310.3 | N61: F, J: Q1 10-Q p. 9; G, K: six months (CF_Hist) less Q1
A62: Net cash from financing activities | F62: 1.552 | G62: =N(CF_Hist!D47)-N(F62) -> 3.596 | J62: 2038.106 | K62: =N(CF_Hist!E47)-N(J62) -> 5815.136 | N62: F, J: Q1 10-Q p. 9; G, K: six months (CF_Hist) less Q1
A63: Effect of exchange rates | F63: 0.18 | G63: =N(CF_Hist!D48)-N(F63) -> 0.732 | J63: 0.911 | K63: =N(CF_Hist!E48)-N(J63) -> -0.273 | N63: F, J: Q1 10-Q p. 9; G, K: six months (CF_Hist) less Q1
A64: Net change in cash and restricted cash | F64: -109.951 | G64: =N(CF_Hist!D49)-N(F64) -> -95.128 | J64: 1814.736 | K64: =N(CF_Hist!E49)-N(J64) -> 4681.723 | N64: F, J: Q1 10-Q p. 9; G, K: six months (CF_Hist) less Q1
A65: Cash and restricted cash, end of quarter | F65: 472.014 | G65: =CF_Hist!D51 -> 376.886 | J65: 2745.114 | K65: =CF_Hist!E51 -> 7426.837 | N65: F, J: Q1 10-Q p. 9; G, K: CF_Hist six-month end
A66: Memo: H2 2025 (Q3 + Q4; the split is not filed): operating cash flow | I66: =N(CF_Hist!C25)-N(CF_Hist!D25) -> 113.793 | N66: FY2025 less 6M 2025
A67: Memo: H2 2025 (Q3 + Q4): purchases of property and equipment | I67: =N(CF_Hist!C28)-N(CF_Hist!D28) -> -197.645 | N67: FY2025 less 6M 2025
A69: Ratios (derived)
A70: Gross margin | B70: =B15/B9 -> 0.37728685 | C70: =C15/C9 -> 0.44259076 | D70: =D15/D9 -> 0.44258079 | E70: =E15/E9 -> 0.42575217 | F70: =F15/F9 -> 0.41808023 | G70: =G15/G9 -> 0.31066956 | H70: =H15/H9 -> 0.40625875 | I70: =I15/I9 -> 0.40965802 | ... K70: =K15/K9 -> 0.14190772 | N70: The 424B4 table also prints this ratio; here it is computed.
A71: Cloud and other services: % of revenue | B71: =B8/B9 -> 0.25843826 | C71: =C8/C9 -> 0.2137421 | D71: =D8/D9 -> 0.30474702 | E71: =E8/E9 -> 0.29577707 | F71: =F8/F9 -> 0.29984323 | G71: =G8/G9 -> 0.31965119 | H71: =H8/H9 -> 0.28677955 | I71: =I8/I9 -> 0.29027723 | ... K71: =K8/K9 -> 0.69952251
A72: Operating margin | B72: =B22/B9 -> -0.27090994 | C72: =C22/C9 -> -0.34054263 | D72: =D22/D9 -> -0.26793789 | E72: =E22/E9 -> -0.49367725 | F72: =F22/F9 -> -0.28609615 | G72: =G22/G9 -> -0.55343489 | H72: =H22/H9 -> -0.19503515 | I72: =I22/I9 -> -0.19680594 | ... K72: =K22/K9 -> -2.6496752
A73: Operating margin before stock pay (company's non-GAAP method) | B73: =(B22+B31)/B9 -> -0.12944425 | C73: =(C22+C31)/C9 -> -0.01228304 | D73: =(D22+D31)/D9 -> -0.035246616 | E73: =(E22+E31)/E9 -> -0.37829783 | F73: =(F22+F31)/F9 -> -0.19410724 | G73: =(G22+G31)/G9 -> -0.42489499 | H73: =(H22+H31)/H9 -> -0.11143287 | I73: =(I22+I31)/I9 -> -0.10356212 | ... K73: =(K22+K31)/K9 -> -0.55646549
A75: Checks (zero passes)
A76: Revenue lines add to the total | B76: =SUM(B7,B8)-B9 -> 0 | C76: =SUM(C7,C8)-C9 -> 0 | D76: =SUM(D7,D8)-D9 -> 0 | E76: =SUM(E7,E8)-E9 -> 0 | F76: =SUM(F7,F8)-F9 -> 0 | G76: =SUM(G7,G8)-G9 -> 0 | H76: =SUM(H7,H8)-H9 -> 0 | I76: =SUM(I7,I8)-I9 -> 0 | ... K76: =SUM(K7,K8)-K9 -> 0
A77: Cost lines add to the total | B77: =SUM(B12,B13)-B14 -> 0 | C77: =SUM(C12,C13)-C14 -> 0 | D77: =SUM(D12,D13)-D14 -> 0 | E77: =SUM(E12,E13)-E14 -> 0 | F77: =SUM(F12,F13)-F14 -> 0 | G77: =SUM(G12,G13)-G14 -> 0 | H77: =SUM(H12,H13)-H14 -> 0 | I77: =SUM(I12,I13)-I14 -> 0 | ... K77: =SUM(K12,K13)-K14 -> 0
A78: Gross profit less operating expenses equals the operating loss | B78: =B15-B21-B22 -> 0 | C78: =C15-C21-C22 -> 0 | D78: =D15-D21-D22 -> 0 | E78: =E15-E21-E22 -> 0 | F78: =F15-F21-F22 -> 0 | G78: =G15-G21-G22 -> 0 | H78: =H15-H21-H22 -> 0 | I78: =I15-I21-I22 -> 0 | ... K78: =K15-K21-K22 -> 0
A79: Functions add to operating expenses (10-Q quarters) | F79: =SUM(F18,F19,F20)-F21 -> 0 | G79: =SUM(G18,G19,G20)-G21 -> 0 | J79: =SUM(J18,J19,J20)-J21 -> 0 | K79: =SUM(K18,K19,K20)-K21 -> 0
A80: Cash flow by quarter: lines add to operating cash flow | F80: =SUM(F42,F43,F44,F45,F46,F47,F48,F49,F50,F51,F52,F53,F54,F55,F56,F57)-F58 -> 0 | G80: =SUM(G42,G43,G44,G45,G46,G47,G48,G49,G50,G51,G52,G53,G54,G55,G56,G57)-G58 -> 0 | J80: =SUM(J42,J43,J44,J45,J46,J47,J48,J49,J50,J51,J52,J53,J54,J55,J56,J57)-J58 -> 0 | K80: =SUM(K42,K43,K44,K45,K46,K47,K48,K49,K50,K51,K52,K53,K54,K55,K56,K57)-K58 -> 0
A81: Cash flow by quarter: flows add to the change in cash | F81: =SUM(F58,F59,F60,F61,F62,F63)-F64 -> 0 | G81: =SUM(G58,G59,G60,G61,G62,G63)-G64 -> 0 | J81: =SUM(J58,J59,J60,J61,J62,J63)-J64 -> 0 | K81: =SUM(K58,K59,K60,K61,K62,K63)-K64 -> 0
A82: Cash flow by quarter: opening cash + change = closing cash | F82: =CF_Hist!B51+F64-F65 -> 0 | G82: =F65+G64-G65 -> 0 | J82: =CF_Hist!C51+J64-J65 -> 0 | K82: =J65+K64-K65 -> 0
A83: Q1 2026 closing cash equals the 31 Mar 2026 balance sheet | J83: =J65-BS_Hist!E49 -> 0
A84: Q1 2026 net loss equals the Q1 income statement | J84: =J42-J26 -> 0
A85: Quarters add to the statements: rev | B85: =SUM(B9:E9)-IS_Hist!B9 -> 0 | C85: =SUM(F9:I9)-IS_Hist!C9 -> 0 | D85: =F9+G9-IS_Hist!D9 -> 0 | E85: =J9+K9-IS_Hist!E9 -> 0 | N85: B: Q1-Q4 2024 vs FY2024; C: Q1-Q4 2025 vs FY2025; D: Q1-Q2 2025 vs 6M 2025; E: Q1-Q2 2026 vs 6M 2026.
A86: Quarters add to the statements: cogs | B86: =SUM(B14:E14)-IS_Hist!B14 -> 0 | C86: =SUM(F14:I14)-IS_Hist!C14 -> 0 | D86: =F14+G14-IS_Hist!D14 -> 0 | E86: =J14+K14-IS_Hist!E14 -> 0 | N86: B: Q1-Q4 2024 vs FY2024; C: Q1-Q4 2025 vs FY2025; D: Q1-Q2 2025 vs 6M 2025; E: Q1-Q2 2026 vs 6M 2026.
A87: Quarters add to the statements: opex | B87: =SUM(B21:E21)-IS_Hist!B21 -> 0 | C87: =SUM(F21:I21)-IS_Hist!C21 -> 0 | D87: =F21+G21-IS_Hist!D21 -> 0 | E87: =J21+K21-IS_Hist!E21 -> 0 | N87: B: Q1-Q4 2024 vs FY2024; C: Q1-Q4 2025 vs FY2025; D: Q1-Q2 2025 vs 6M 2025; E: Q1-Q2 2026 vs 6M 2026.
A88: Quarters add to the statements: ni | B88: =SUM(B26:E26)-IS_Hist!B26 -> 0 | C88: =SUM(F26:I26)-IS_Hist!C26 -> 0 | D88: =F26+G26-IS_Hist!D26 -> 0 | E88: =J26+K26-IS_Hist!E26 -> 0 | N88: B: Q1-Q4 2024 vs FY2024; C: Q1-Q4 2025 vs FY2025; D: Q1-Q2 2025 vs 6M 2025; E: Q1-Q2 2026 vs 6M 2026.
A89: Stock pay: quarters add to the year and the half | C89: =SUM(F31:I31)-N(Revenue_Hist!C39) -> 0 | E89: =J31+K31-N(Revenue_Hist!E39) -> 0

Sheet Revenue_Hist
A1: Cerebras Systems Inc. (Nasdaq: CBRS) | Revenue, customers, costs by function and other notes, as filed
A2: USD millions (filed thousands / 1,000) unless stated. 424B4 notes (FY2024, FY2025) and Q2 10-Q notes (6M 2025, 6M 2026).
A4: Fiscal year ends 31 December | B4: FY2024A | C4: FY2025A | D4: 6M 2025A | E4: 6M 2026A | M4: Comentarios FG | N4: Source / derivation
A6: A. Revenue by timing of recognition (424B4 Note 3; Q2 10-Q Note 3)
A7: Hardware revenue recognized at a point in time | B7: 211.965 | C7: 358.44 | D7: 139.969 | E7: 164.712 | N7: 424B4 p. F-18; Q2 10-Q p. 14
A8: Cloud and other services revenue recognized at a point in time | B8: 0.628 | C8: 2.194 | D8: 0.851 | E8: 0.987 | N8: 424B4 p. F-18; Q2 10-Q p. 14
A9: Cloud and other services revenue recognized over time | B9: 77.659 | C9: 149.357 | D9: 62.014 | E9: 207.817 | N9: 424B4 p. F-18; Q2 10-Q p. 14
A10: Total revenue | B10: 290.252 | C10: 509.991 | D10: 202.834 | E10: 373.516 | N10: 424B4 p. F-18; Q2 10-Q p. 14
A12: B. Revenue by billing location of the customer
A13: United States | B13: 282.685 | C13: 187.643 | D13: 105.096 | E13: 154.071 | N13: 424B4 p. F-20; Q2 10-Q p. 16
A14: Europe, Middle East, and Africa | B14: 7.567 | C14: 322.231 | D14: 97.643 | E14: 218.921 | N14: 424B4 p. F-20; Q2 10-Q p. 16
A15: Other | B15: — | C15: 0.117 | D15: 0.095 | E15: 0.524 | N15: 424B4 p. F-20; Q2 10-Q p. 16
A16: Total revenue | B16: 290.252 | C16: 509.991 | D16: 202.834 | E16: 373.516 | N16: 424B4 p. F-20; Q2 10-Q p. 16
A17: Europe, Middle East and Africa: % of revenue | B17: =N(B14)/B16 -> 0.026070449 | C17: =N(C14)/C16 -> 0.63183664 | D17: =N(D14)/D16 -> 0.48139365 | E17: =N(E14)/E16 -> 0.58610876
A19: C. Customers above 10% of revenue ('*' = below 10%, kept as filed; letters change meaning between reports)
A20: Customer A (424B4: MBZUAI; Q2 10-Q: MBZUAI) | B20: * | C20: 0.62 | D20: 0.47 | E20: 0.49 | N20: 424B4 p. F-19 names A as MBZUAI (62% of FY2025); Q2 10-Q p. 15 (34% of Q2 2026, 49% of 6M 2026).
A21: Customer B (424B4: G42) | B21: 0.85 | C21: 0.24 | N21: 424B4 p. F-19: G42 24.0% of FY2025 and 85.0% of FY2024.
A22: Customer B (Q2 10-Q; unnamed) | D22: * | E22: 0.2 | N22: Q2 10-Q p. 15: unnamed. OpenAI revenue was US$56.8m in Q2 2026 = 32% of revenue, so B is probably OpenAI (an inference, not a filed fact).
A23: Customer C (Q2 10-Q; unnamed) | D23: * | E23: * | N23: Q2 10-Q p. 15: 10% of Q2 2026.
A24: Customer D (Q2 10-Q: G42) | D24: 0.41 | E24: 0.1 | N24: Q2 10-Q p. 15: G42 9% of Q2 2026 (below 10%, '*'), 10% of 6M 2026, 41% of 6M 2025.
A25: Q2 2026 alone: A 34%, B 32%, C 10%; G42 9% (Q2 10-Q p. 15)
A27: D. Depreciation by function (424B4 p. F-25; Q2 10-Q p. 20)
A28: Cost of revenue | B28: 3.15 | C28: 12.699 | D28: 3.201 | E28: 28.353 | N28: 424B4 p. F-25
A29: Research and development | B29: 6.536 | C29: 14.513 | D29: 4.55 | E29: 11.568 | N29: 424B4 p. F-25
A30: Sales and marketing | B30: 1.095 | C30: 7.186 | D30: 1.544 | E30: 1.639 | N30: 424B4 p. F-25
A31: General and administrative | B31: 0.756 | C31: 0.056 | D31: 0.02 | E31: 0.991 | N31: 424B4 p. F-25
A32: Total depreciation expense | B32: 11.537 | C32: 34.454 | D32: 9.315 | E32: 42.551 | N32: 424B4 p. F-25
A34: E. Stock-based compensation by function (424B4 p. F-34; Q2 10-Q p. 26)
A35: Cost of revenue | B35: 0.921 | C35: 0.827 | D35: 0.513 | E35: 16.303 | N35: 424B4 p. F-34; Q2 10-Q p. 26
A36: Research and development | B36: 41.397 | C36: 32.154 | D36: 15.013 | E36: 227.846 | N36: 424B4 p. F-34; Q2 10-Q p. 26
A37: Sales and marketing | B37: 8.723 | C37: 9.95 | D37: 3.482 | E37: 72.847 | N37: 424B4 p. F-34; Q2 10-Q p. 26
A38: General and administrative | B38: 7.523 | C38: 6.836 | D38: 3.427 | E38: 69.605 | N38: 424B4 p. F-34; Q2 10-Q p. 26
A39: Total stock-based compensation expense | B39: 58.564 | C39: 49.767 | D39: 22.435 | E39: 386.601 | N39: 424B4 p. F-34; Q2 10-Q p. 26
A41: F. Costs before depreciation and stock pay (derived; feeds the forecast) | N41: Allocation convention (mine): depreciation in cost of revenue goes to cloud (data center systems); stock pay in cost of revenue is split by each line's share of cost of revenue.
A42: Hardware cost of revenue before depreciation and stock pay | B42: =N(IS_Hist!B12)-B35*N(IS_Hist!B12)/N(IS_Hist!B14) -> 136.55506 | C42: =N(IS_Hist!C12)-C35*N(IS_Hist!C12)/N(IS_Hist!C14) -> 204.20141 | D42: =N(IS_Hist!D12)-D35*N(IS_Hist!D12)/N(IS_Hist!D14) -> 94.681358 | E42: =N(IS_Hist!E12)-E35*N(IS_Hist!E12)/N(IS_Hist!E14) -> 110.7188
A43: Cloud cost of revenue before depreciation and stock pay | B43: =N(IS_Hist!B13)-B28-B35*N(IS_Hist!B13)/N(IS_Hist!B14) -> 26.887937 | C43: =N(IS_Hist!C13)-C28-C35*N(IS_Hist!C13)/N(IS_Hist!C14) -> 93.192593 | D43: =N(IS_Hist!D13)-D28-D35*N(IS_Hist!D13)/N(IS_Hist!D14) -> 30.735642 | E43: =N(IS_Hist!E13)-E28-E35*N(IS_Hist!E13)/N(IS_Hist!E14) -> 106.4062
A44: Cost of revenue before depreciation and stock pay | B44: =B42+B43 -> 163.443 | C44: =C42+C43 -> 297.394 | D44: =D42+D43 -> 125.417 | E44: =E42+E43 -> 217.125
A45: Hardware gross margin before depreciation and stock pay | B45: =1-B42/N(IS_Hist!B7) -> 0.35576598 | C45: =1-C42/N(IS_Hist!C7) -> 0.43030519 | D45: =1-D42/N(IS_Hist!D7) -> 0.3235548 | E45: =1-E42/N(IS_Hist!E7) -> 0.32780368
A46: Cloud gross margin before depreciation and stock pay | B46: =1-B43/N(IS_Hist!B8) -> 0.65654659 | C46: =1-C43/N(IS_Hist!C8) -> 0.38507438 | D46: =1-D43/N(IS_Hist!D8) -> 0.51108499 | E46: =1-E43/N(IS_Hist!E8) -> 0.49040153
A47: Gross margin as reported | B47: =N(IS_Hist!B15)/N(IS_Hist!B9) -> 0.42286703 | C47: =N(IS_Hist!C15)/N(IS_Hist!C9) -> 0.39034218 | D47: =N(IS_Hist!D15)/N(IS_Hist!D9) -> 0.3633661 | E47: =N(IS_Hist!E15)/N(IS_Hist!E9) -> 0.29914381
A48: Q2 2026 hardware margin on this basis, with and without the US$28.0m warrant cost | D48: =1-(N(Quarterly_Hist!K12)-N(Quarterly_Hist!K29)*N(Quarterly_Hist!K12)/N(Quarterly_Hist!K14))/N(Quarterly_Hist!K7) -> 0.11561547 | E48: =1-(N(Quarterly_Hist!K12)-N(Quarterly_Hist!K29)*N(Quarterly_Hist!K12)/N(Quarterly_Hist!K14))/(N(Quarterly_Hist!K7)+28.0) -> 0.41716282 | N48: D: as reported; E: revenue before the US$28.0m of warrant amortization (Q2 10-Q p. 35).
A49: Q2 2026 cloud margin on this basis | E49: =1-(N(Quarterly_Hist!K13)-N(Quarterly_Hist!K33)-N(Quarterly_Hist!K29)*N(Quarterly_Hist!K13)/N(Quarterly_Hist!K14))/N(Quarterly_Hist!K8) -> 0.4217524
A50: Research and development before stock pay and depreciation | B50: =N(IS_Hist!B18)-B36-B29 -> 110.301 | C50: =N(IS_Hist!C18)-C36-C29 -> 196.652 | D50: =N(IS_Hist!D18)-D36-D29 -> 93.956 | E50: =N(IS_Hist!E18)-E36-E29 -> 156.232
A51: % of revenue | B51: =B50/N(IS_Hist!B9) -> 0.38001805 | C51: =C50/N(IS_Hist!C9) -> 0.38559896 | D51: =D50/N(IS_Hist!D9) -> 0.46321623 | E51: =E50/N(IS_Hist!E9) -> 0.41827392
A52: Sales and marketing before stock pay and depreciation | B52: =N(IS_Hist!B19)-B37-B30 -> 11.162 | C52: =N(IS_Hist!C19)-C37-C30 -> 53.509 | D52: =N(IS_Hist!D19)-D37-D30 -> 23.528 | E52: =N(IS_Hist!E19)-E37-E30 -> 27.184
A53: % of revenue | B53: =B52/N(IS_Hist!B9) -> 0.038456238 | C53: =C52/N(IS_Hist!C9) -> 0.10492146 | D53: =D52/N(IS_Hist!D9) -> 0.11599633 | E53: =E52/N(IS_Hist!E9) -> 0.072778676
A54: General and administrative before stock pay and depreciation | B54: =N(IS_Hist!B20)-B38-B31 -> 36.683 | C54: =N(IS_Hist!C20)-C38-C31 -> 24.077 | D54: =N(IS_Hist!D20)-D38-D31 -> 13.835 | E54: =N(IS_Hist!E20)-E38-E31 -> 36.093
A55: % of revenue | B55: =B54/N(IS_Hist!B9) -> 0.12638328 | C55: =C54/N(IS_Hist!C9) -> 0.047210637 | D55: =D54/N(IS_Hist!D9) -> 0.068208486 | E55: =E54/N(IS_Hist!E9) -> 0.096630399
A57: G. Other income (424B4 p. F-26; Q2 10-Q p. 20)
A58: Interest and dividend income | B58: 23.228 | C58: 26.802 | D58: 11.833 | E58: 71.571 | N58: 424B4 p. F-26; Q2 10-Q p. 20
A59: Non-cash interest expense (Working Capital Loan) | D59: — | E59: -38.602 | N59: Q2 10-Q p. 20
A60: Forward contract liability: change in fair value and extinguishment | B60: -401.264 | C60: 363.336 | D60: 363.336 | E60: —
A61: Other | B61: -0.201 | C61: 0.608 | D61: -0.525 | E61: -3.462 | N61: 2026: 'Other expense'
A62: Total other income (expense), net | B62: -378.237 | C62: 390.746 | D62: 374.644 | E62: 29.507
A64: H. OpenAI and customer warrants (Q1 and Q2 10-Q)
A65: Revenue from OpenAI, net of warrant amortization | E65: 74.4 | N65: Q2 10-Q p. 15: US$56.8m (Q2) and US$74.4m (6M 2026); Q1 10-Q: US$16.9m.
A66: of which Q2 2026 | E66: 56.8 | N66: Q2 10-Q p. 15
A67: Cloud and other services revenue from customers other than OpenAI (derived) | E67: =N(IS_Hist!E8)-E65 -> 134.404
A68: Customer warrant amortization booked as a reduction of revenue | E68: =N(CF_Hist!E10) -> 46.315 | N68: Q2 10-Q p. 25: US$44.3m (Q2) and US$46.3m (6M 2026); remaining balance through October 2031.
A70: I. Non-GAAP measures (company definitions)
A71: Non-GAAP operating loss (424B4: operating loss + stock pay) | B71: -42.874 | C71: -96.095 | N71: 424B4 p. 20
A72: Core operating loss (10-Q: + stock pay, warrant amortization, IPO payroll tax, less pass-through) | D72: -63.217 | E72: -37.125 | N72: Q2 10-Q p. 39. Different definition from the 424B4 measure.
A73: Employer payroll tax on IPO stock pay (in costs, 6M 2026) | E73: 22.778 | N73: Q2 10-Q p. 39
A75: Checks (zero passes)
A76: Revenue by timing equals the statement | B76: =SUM(B7,B8,B9)-N(IS_Hist!B9) -> 0 | C76: =SUM(C7,C8,C9)-N(IS_Hist!C9) -> 0 | D76: =SUM(D7,D8,D9)-N(IS_Hist!D9) -> 0 | E76: =SUM(E7,E8,E9)-N(IS_Hist!E9) -> 0
A77: Revenue by region equals the statement | B77: =SUM(B13,B14,B15)-N(IS_Hist!B9) -> 0 | C77: =SUM(C13,C14,C15)-N(IS_Hist!C9) -> 0 | D77: =SUM(D13,D14,D15)-N(IS_Hist!D9) -> 0 | E77: =SUM(E13,E14,E15)-N(IS_Hist!E9) -> 0
A78: Hardware revenue equals the point-in-time hardware line | B78: =B7-N(IS_Hist!B7) -> 0 | C78: =C7-N(IS_Hist!C7) -> 0 | D78: =D7-N(IS_Hist!D7) -> 0 | E78: =E7-N(IS_Hist!E7) -> 0
A79: Depreciation by function equals the cash flow statement | B79: =B32-N(CF_Hist!B8) -> 0 | C79: =C32-N(CF_Hist!C8) -> 0 | D79: =D32-N(CF_Hist!D8) -> 0 | E79: =E32-N(CF_Hist!E8) -> 0
A80: Depreciation functions add to the total | B80: =SUM(B28,B29,B30,B31)-B32 -> 0 | C80: =SUM(C28,C29,C30,C31)-C32 -> 0 | D80: =SUM(D28,D29,D30,D31)-D32 -> 0 | E80: =SUM(E28,E29,E30,E31)-E32 -> 0
A81: Stock pay functions add to the total | B81: =SUM(B35,B36,B37,B38)-B39 -> 0 | C81: =SUM(C35,C36,C37,C38)-C39 -> 0 | D81: =SUM(D35,D36,D37,D38)-D39 -> 0 | E81: =SUM(E35,E36,E37,E38)-E39 -> 0
A82: Other income lines add to the total | B82: =SUM(B58,B59,B60,B61)-B62 -> 0 | C82: =SUM(C58,C59,C60,C61)-C62 -> 0 | D82: =SUM(D58,D59,D60,D61)-D62 -> 0 | E82: =SUM(E58,E59,E60,E61)-E62 -> 0
A83: Other income equals the statement | B83: =B62-N(IS_Hist!B23) -> 0 | C83: =C62-N(IS_Hist!C23) -> 0 | D83: =D62-N(IS_Hist!D23) -> 0 | E83: =E62-N(IS_Hist!E23) -> 0
A84: Costs before depreciation and stock pay rebuild total costs | B84: =B44+B28+B35+B50+B52+B54+B32-B28+B39-B35-N(IS_Hist!B14)-N(IS_Hist!B21) -> 0 | C84: =C44+C28+C35+C50+C52+C54+C32-C28+C39-C35-N(IS_Hist!C14)-N(IS_Hist!C21) -> 0 | D84: =D44+D28+D35+D50+D52+D54+D32-D28+D39-D35-N(IS_Hist!D14)-N(IS_Hist!D21) -> 0 | E84: =E44+E28+E35+E50+E52+E54+E32-E28+E39-E35-N(IS_Hist!E14)-N(IS_Hist!E21) -> 0

Sheet Backlog
A1: Cerebras Systems Inc. (Nasdaq: CBRS) | Backlog (remaining performance obligations) and its conversion into revenue
A2: USD millions. Column B = 30 Jun 2026; C = H2 2026E; D-L = fiscal years. The filing gives the share of backlog in three windows; how each window spreads over the years is my convention (blue cells).
B3: Actual | C3: Forecast
A4: Period | B4: Jun 2026A | C4: H2 2026E | D4: 2027E | E4: 2028E | F4: 2029E | G4: 2030E | H4: 2031E | I4: 2032E | J4: 2033E | K4: 2034E | L4: 2035E | M4: Comentarios FG | N4: Source / derivation
A6: A. What the filings say
A7: Backlog (remaining performance obligations), 30 Jun 2026 | B7: 25400 | N7: Q2 10-Q p. 15: 'was $25.4 billion as of June 30, 2026. A significant amount of the balance was attributable to ... the MRA with OpenAI.'
A8: Share recognized in the 24 months to 30 Jun 2028 | B8: 0.22 | N8: Q2 10-Q p. 15: 'approximately 22%'
A9: Share recognized in months 25 to 48 (Jul 2028 - Jun 2030) | B9: 0.43 | N9: Q2 10-Q p. 15: '43% between months 25 and 48'
A10: Share recognized after June 2030 (derived) | B10: =1-B8-B9 -> 0.35 | N10: Q2 10-Q p. 15: "the remaining balance thereafter"
A11: Backlog stated gross of the customer warrant reduction: 1 = gross (used), 2 = net | B11: 1 | N11: The filings do not say. Q2 10-Q p. 15: backlog "includes deferred revenue and amounts that are expected to be invoiced"; 424B4 p. 96: "the gross revenue amount without contra-revenue is what the customer is invoiced and pays in cash"; the warrants are a separate asset recognized "as a reduction of revenue in proportion to the related revenue recognized" (Q2 10-Q p. 24). So gross: reported backlog revenue = schedule less warrant amortization; cash = schedule.
A12: Memo: backlog at 31 Dec 2025 | B12: 24600 | N12: 424B4 p. F-19: US$24.6bn; 15% in the 24 months to Dec 2027, 43% in months 25-48.
A13: Memo: backlog growth in six months (derived) | B13: =B7/B12-1 -> 0.032520325
A14: OpenAI Committed Capacity (MW) | B14: 750 | N14: 424B4 p. 91 and Q2 10-Q p. 15: 750 MW, deployed in tranches 2026-2028; each tranche runs 3-4 years, extendable to 5.
A15: Memo: OpenAI deal value announced ('more than') | B15: 20000 | N15: 424B4 p. v: 'a multi-year deal with OpenAI valued at more than $20 billion dollars'.
A16: OpenAI Additional Capacity option (MW) | B16: 1250 | N16: 424B4 p. 91: option on 1.25 GW more, deployed by the end of 2030 (up to 2.0 GW in total).
A18: B. Conversion schedule (convention: how each filed window spreads over the periods)
A19: Window 1 (22%): share in each period | C19: 0.1 | D19: 0.4 | E19: 0.5 | N19: Ramp: tranches deploy 2026-2028, so H2 2026 is small. Convention.
A20: Window 2 (43%): share in each period | E20: 0.25 | F20: 0.5 | G20: 0.25 | N20: Even over H2 2028, 2029 and H1 2030. Convention.
A21: Window 3 (35%): share in each period | G21: 0.15 | H21: 0.3 | I21: 0.3 | J21: 0.25 | N21: H2 2030 to 2033: the last tranches (deployed by 2028) run up to five years. Convention.
A22: Backlog revenue at full realization | C22: =$B$7*($B$8*N(C19)+$B$9*N(C20)+$B$10*N(C21)) -> 558.8 | D22: =$B$7*($B$8*N(D19)+$B$9*N(D20)+$B$10*N(D21)) -> 2235.2 | E22: =$B$7*($B$8*N(E19)+$B$9*N(E20)+$B$10*N(E21)) -> 5524.5 | F22: =$B$7*($B$8*N(F19)+$B$9*N(F20)+$B$10*N(F21)) -> 5461 | G22: =$B$7*($B$8*N(G19)+$B$9*N(G20)+$B$10*N(G21)) -> 4064 | H22: =$B$7*($B$8*N(H19)+$B$9*N(H20)+$B$10*N(H21)) -> 2667 | I22: =$B$7*($B$8*N(I19)+$B$9*N(I20)+$B$10*N(I21)) -> 2667 | J22: =$B$7*($B$8*N(J19)+$B$9*N(J20)+$B$10*N(J21)) -> 2222.5 | ... L22: =$B$7*($B$8*N(L19)+$B$9*N(L20)+$B$10*N(L21)) -> 0
A23: Revenue from the 30 Jun 2026 backlog (x realization) | C23: =C22*Assumptions!$C$19-IF($B$11=1,C35+C46,0) -> 512.21554 | D23: =D22*Assumptions!$C$19-IF($B$11=1,D35+D46,0) -> 2048.8622 | E23: =E22*Assumptions!$C$19-IF($B$11=1,E35+E46,0) -> 5063.9491 | F23: =F22*Assumptions!$C$19-IF($B$11=1,F35+F46,0) -> 5005.7428 | G23: =G22*Assumptions!$C$19-IF($B$11=1,G35+G46,0) -> 3725.2039 | H23: =H22*Assumptions!$C$19-IF($B$11=1,H35+H46,0) -> 2444.6651 | I23: =I22*Assumptions!$C$19-IF($B$11=1,I35+I46,0) -> 2591.3916 | J23: =J22*Assumptions!$C$19-IF($B$11=1,J35+J46,0) -> 2159.493 | ... L23: =L22*Assumptions!$C$19-IF($B$11=1,L35+L46,0) -> 0 | N23: Reported revenue: schedule x realization, less the warrant amortization when the backlog is gross (row 'basis'). Cash billed = schedule x realization.
A25: C. Renewals and the OpenAI option
A26: Renewals of expired backlog capacity | C26: 0 | D26: =C26*(1+Assumptions!$C$22)+Assumptions!$C$20*MAX(0,C23-D23) -> 0 | E26: =D26*(1+Assumptions!$C$22)+Assumptions!$C$20*MAX(0,D23-E23) -> 0 | F26: =E26*(1+Assumptions!$C$22)+Assumptions!$C$20*MAX(0,E23-F23) -> 46.565049 | G26: =F26*(1+Assumptions!$C$22)+Assumptions!$C$20*MAX(0,F23-G23) -> 1072.3931 | H26: =G26*(1+Assumptions!$C$22)+Assumptions!$C$20*MAX(0,G23-H23) -> 2128.996 | I26: =H26*(1+Assumptions!$C$22)+Assumptions!$C$20*MAX(0,H23-I23) -> 2192.8658 | J26: =I26*(1+Assumptions!$C$22)+Assumptions!$C$20*MAX(0,I23-J23) -> 2604.1707 | K26: =J26*(1+Assumptions!$C$22)+Assumptions!$C$20*MAX(0,J23-K23) -> 4409.8902 | L26: =K26*(1+Assumptions!$C$22)+Assumptions!$C$20*MAX(0,K23-L23) -> 4542.1869 | N26: Each year: renewal rate x the fall in backlog revenue; renewed revenue then grows at the terminal growth rate.
A27: Revenue per GW-year implied by the committed contract (derived) | B27: =B7/(B14/1000)/Assumptions!$C$40 -> 8466.6667 | N27: Backlog / 0.75 GW / average term. A rough price; the backlog also holds other customers.
A28: Option capacity in service (share of the exercised GW) | F28: 0.25 | G28: 0.75 | H28: 1 | I28: 1 | J28: 1 | K28: 1 | L28: 1 | N28: Deployed by the end of 2030 (424B4 p. 91). Convention.
A29: Additional Capacity option: billed revenue (gross) | C29: =$B$16/1000*Assumptions!$C$21*$B$27*N(C28) -> 0 | D29: =$B$16/1000*Assumptions!$C$21*$B$27*N(D28) -> 0 | E29: =$B$16/1000*Assumptions!$C$21*$B$27*N(E28) -> 0 | F29: =$B$16/1000*Assumptions!$C$21*$B$27*N(F28) -> 0 | G29: =$B$16/1000*Assumptions!$C$21*$B$27*N(G28) -> 0 | H29: =$B$16/1000*Assumptions!$C$21*$B$27*N(H28) -> 0 | I29: =$B$16/1000*Assumptions!$C$21*$B$27*N(I28) -> 0 | J29: =$B$16/1000*Assumptions!$C$21*$B$27*N(J28) -> 0 | ... L29: =$B$16/1000*Assumptions!$C$21*$B$27*N(L28) -> 0
A30: Revenue from the Additional Capacity option (reported: gross less its warrant amortization) | C30: =C29-IF($B$11=1,C48,0) -> 0 | D30: =D29-IF($B$11=1,D48,0) -> 0 | E30: =E29-IF($B$11=1,E48,0) -> 0 | F30: =F29-IF($B$11=1,F48,0) -> 0 | G30: =G29-IF($B$11=1,G48,0) -> 0 | H30: =H29-IF($B$11=1,H48,0) -> 0 | I30: =I29-IF($B$11=1,I48,0) -> 0 | J30: =J29-IF($B$11=1,J48,0) -> 0 | ... L30: =L29-IF($B$11=1,L48,0) -> 0
A31: Pass-through data center revenue (at cost) | C31: =C22*Assumptions!$C$19*Assumptions!$C$27 -> 27.94 | D31: =D22*Assumptions!$C$19*Assumptions!$C$27 -> 111.76 | E31: =E22*Assumptions!$C$19*Assumptions!$C$27 -> 276.225 | F31: =F22*Assumptions!$C$19*Assumptions!$C$27 -> 273.05 | G31: =G22*Assumptions!$C$19*Assumptions!$C$27 -> 203.2 | H31: =H22*Assumptions!$C$19*Assumptions!$C$27 -> 133.35 | I31: =I22*Assumptions!$C$19*Assumptions!$C$27 -> 133.35 | J31: =J22*Assumptions!$C$19*Assumptions!$C$27 -> 111.125 | ... L31: =L22*Assumptions!$C$19*Assumptions!$C$27 -> 0
A33: D. Customer warrant asset: amortization as a reduction of revenue (non-cash)
A34: Customer warrant asset, 30 Jun 2026 | B34: =BS_Hist!F51 -> 1128.397 | N34: Q2 10-Q p. 25: amortized 'in proportion to the related revenue' through October 2031.
A35: Amortization (in proportion to backlog revenue, H2 2026E-2031E) | C35: =$B$34*C22/SUM($C$22:$H$22) -> 30.742705 | D35: =$B$34*D22/SUM($C$22:$H$22) -> 122.97082 | E35: =$B$34*E22/SUM($C$22:$H$22) -> 303.93356 | F35: =$B$34*F22/SUM($C$22:$H$22) -> 300.44007 | G35: =$B$34*G22/SUM($C$22:$H$22) -> 223.58331 | H35: =$B$34*H22/SUM($C$22:$H$22) -> 146.72654 | I35: 0 | J35: 0 | K35: 0 | L35: 0 | N35: Inside reported revenue (non-cash). New warrant tranches that vest later are not modelled; their shares are in the diluted count.
A36: Customer warrant asset, end of period | B36: =B34 -> 1128.397 | C36: =B36-C35 -> 1097.6543 | D36: =C36-D35 -> 974.68348 | E36: =D36-E35 -> 670.74992 | F36: =E36-F35 -> 370.30985 | G36: =F36-G35 -> 146.72654 | H36: =G36-H35 -> 0 | I36: =H36-I35 -> 0 | J36: =I36-J35 -> 0 | ... L36: =K36-L35 -> 0
A38: E. Unvested OpenAI warrant tranches (23.4m shares): vesting and contra-revenue
A39: Shares that vest on committed delivery dates of capacity (millions) | B39: 23.411518 | N39: 424B4 p. 86: "23,411,518 shares in the aggregate will vest in multiple tranches on certain committed delivery dates of compute capacity pursuant to the MRA, including ... the Additional Capacity"; full vesting "only if OpenAI exercises all options ... a total of 2GW".
A40: Capacity those shares cover: committed + option (MW) | B40: =B14+B16 -> 2000
A41: Shares per MW (convention: pro rata to capacity; the filing gives no split) | B41: =B39/B40 -> 0.011705759
A42: Shares tied to the Committed Capacity (750 MW) | B42: =B41*B14 -> 8.7793193 | N42: Probable of vesting (Q2 10-Q p. 24): in the diluted count in every scenario.
A43: Shares tied to the Additional Capacity option (1.25 GW) | B43: =B41*B16 -> 14.632199 | N43: Q2 10-Q p. 24: 'not considered probable'; in the count only for the share of the option exercised (Bull 50%).
A44: Grant-date fair value per OpenAI warrant share (USD) | B44: 82.02 | N44: Q2 10-Q p. 24: 'classified as an equity instrument, and the grant date fair value was $82.02 per share'; an asset is booked on vesting (10.03m vested shares = US$822.9m in 6M 2026) and recognized 'as a reduction of revenue in proportion to the related revenue'.
A45: Warrant value of the committed tranches (US$m) | B45: =B42*B44 -> 720.07976
A46: Committed tranches: contra-revenue (in proportion to backlog revenue) | C46: =$B$45*C22/SUM($C$22:$L$22) -> 15.841755 | D46: =$B$45*D22/SUM($C$22:$L$22) -> 63.367019 | E46: =$B$45*E22/SUM($C$22:$L$22) -> 156.61735 | F46: =$B$45*F22/SUM($C$22:$L$22) -> 154.81715 | G46: =$B$45*G22/SUM($C$22:$L$22) -> 115.21276 | H46: =$B$45*H22/SUM($C$22:$L$22) -> 75.608375 | I46: =$B$45*I22/SUM($C$22:$L$22) -> 75.608375 | J46: =$B$45*J22/SUM($C$22:$L$22) -> 63.006979 | ... L46: =$B$45*L22/SUM($C$22:$L$22) -> 0 | N46: Convention: each tranche's asset is booked as it vests and amortized with the revenue it relates to, so booking and amortization fall in the same periods.
A47: Warrant value of the option tranches exercised (US$m) | B47: =B43*Assumptions!$C$21*B44 -> 0
A48: Option tranches: contra-revenue (in proportion to option revenue) | C48: =IF(SUM($C$29:$L$29)=0,0,$B$47*C29/SUM($C$29:$L$29)) -> 0 | D48: =IF(SUM($C$29:$L$29)=0,0,$B$47*D29/SUM($C$29:$L$29)) -> 0 | E48: =IF(SUM($C$29:$L$29)=0,0,$B$47*E29/SUM($C$29:$L$29)) -> 0 | F48: =IF(SUM($C$29:$L$29)=0,0,$B$47*F29/SUM($C$29:$L$29)) -> 0 | G48: =IF(SUM($C$29:$L$29)=0,0,$B$47*G29/SUM($C$29:$L$29)) -> 0 | H48: =IF(SUM($C$29:$L$29)=0,0,$B$47*H29/SUM($C$29:$L$29)) -> 0 | I48: =IF(SUM($C$29:$L$29)=0,0,$B$47*I29/SUM($C$29:$L$29)) -> 0 | J48: =IF(SUM($C$29:$L$29)=0,0,$B$47*J29/SUM($C$29:$L$29)) -> 0 | ... L48: =IF(SUM($C$29:$L$29)=0,0,$B$47*L29/SUM($C$29:$L$29)) -> 0
A49: New warrant assets booked (non-cash; credited to equity) | C49: =C46+C48 -> 15.841755 | D49: =D46+D48 -> 63.367019 | E49: =E46+E48 -> 156.61735 | F49: =F46+F48 -> 154.81715 | G49: =G46+G48 -> 115.21276 | H49: =H46+H48 -> 75.608375 | I49: =I46+I48 -> 75.608375 | J49: =J46+J48 -> 63.006979 | ... L49: =L46+L48 -> 0
A50: All customer warrant amortization inside revenue (existing + new tranches) | C50: =C35+C49 -> 46.584459 | D50: =D35+D49 -> 186.33784 | E50: =E35+E49 -> 460.55091 | F50: =F35+F49 -> 455.25722 | G50: =G35+G49 -> 338.79607 | H50: =H35+H49 -> 222.33492 | I50: =I35+I49 -> 75.608375 | J50: =J35+J49 -> 63.006979 | ... L50: =L35+L49 -> 0
A52: Checks (zero passes)
A53: s1: shares add to 100% | C53: =SUM(C19:L19)-1 -> 0
A54: s2: shares add to 100% | C54: =SUM(C20:L20)-1 -> 0
A55: s3: shares add to 100% | C55: =SUM(C21:L21)-1 -> 0
A56: Scheduled backlog revenue adds to the backlog | C56: =SUM(C22:L22)-B7 -> 0
A57: Window 1 lands by 30 Jun 2028 (H2 2026 + 2027 + half of 2028 schedule from window 1) | C57: =B7*B8*(C19+D19+E19)-B7*B8 -> 0
A58: Warrant amortization adds to the asset | C58: =SUM(C35:L35)-B34 -> 0
A59: Committed tranche amortization adds to its warrant value | C59: =SUM(C46:L46)-B45 -> 0
A60: Option tranche amortization adds to its warrant value | C60: =SUM(C48:L48)-B47 -> 0
A61: Tranche shares add to the 23.4m | B61: =B42+B43-B39 -> 0

Sheet Cap_Table
A1: Cerebras Systems Inc. (Nasdaq: CBRS) | Shares outstanding, dilutive securities and the diluted count (treasury method)
A2: Shares in millions. Basic shares from the Q2 10-Q cover (5 Aug 2026, the latest count). Dilutive securities at 30 Jun 2026 (Q2 10-Q p. 17) unless stated.
A4: Item | B4: Value | C4: Price (USD) | D4: Comentarios FG | E4: Source / derivation
A6: A. Common stock outstanding, 5 Aug 2026 (Q2 10-Q cover, p. 1)
A7: Class A common stock | B7: 112.24711 | E7: 112,247,109 shares
A8: Class B common stock (20 votes a share) | B8: 111.60142 | E8: 111,601,424 shares
A9: Class N common stock (non-voting) | B9: 13.715508 | E9: 13,715,508 shares; includes 10,033,508 OpenAI warrant shares exercised in July 2026
A10: Common shares outstanding | B10: =B7+B8+B9 -> 237.56404
A11: Memo: Class N shares at 30 Jun 2026 (balance sheet caption) | B11: 3.682 | E11: Q2 10-Q p. 6: 3,682,000 shares
A12: OpenAI warrant: shares vested in January 2026 | B12: 4.459337 | E12: Q2 10-Q p. 24
A13: OpenAI warrant: shares vested in June 2026 | B13: 5.574171 | E13: Q2 10-Q p. 24
A14: OpenAI warrant: shares exercised in July 2026 | B14: 10.033508 | E14: Q2 10-Q p. 29
A16: B. Dilutive securities (treasury method at the market price)
A17: Market price used for the treasury method (USD) | C17: =Market_Package!B10 -> 119.31 | E17: Convention: the market price, not the DCF value (avoids a circular count).
A18: Options to purchase common stock (30 Jun 2026) | B18: 23.797 | C18: 4.97 | E18: Count: Q2 10-Q p. 17. Weighted average exercise price US$4.97 at 31 Dec 2025 (424B4 p. F-32), the latest price the filings give.
A19: Options, net shares (treasury method) | B19: =B18*MAX(0,1-C18/C17) -> 22.805708
A20: Unvested RSUs (no exercise price) | B20: 16.532 | E20: Q2 10-Q p. 17
A21: CEO and CTO PRSUs (vest at US$75bn, US$150bn, US$250bn market value) | B21: 9 | E21: Q2 10-Q p. 17, p. 26
A22: Include the PRSUs (1 = yes, 0 = no) | B22: 0 | E22: 0: thresholds far above today's value (about US$28bn basic). Their expense stays a cost in the forecast instead (no double count).
A23: OpenAI warrant: total shares (exercise price US$0.00001) | B23: 33.445026 | E23: Q2 10-Q p. 24; equity-classified.
A24: OpenAI warrant: shares not yet vested (derived) | B24: =B23-B12-B13 -> 23.411518 | E24: Vest with capacity delivered, Additional Capacity bought and value or payment thresholds (Q2 10-Q p. 24).
A25: of which tied to the Committed Capacity: in the count | B25: =Backlog!B42 -> 8.7793193 | E25: Backlog E: pro rata to capacity (convention).
A26: of which tied to the Additional Capacity option: in the count x share exercised | B26: =Backlog!B43*Assumptions!$C$21 -> 0 | E26: Bull 50% exercised; Base and Bear 0%. Changes with the scenario switch.
A27: AWS warrant (exercise price US$100.00) | B27: 2.696678 | C27: 100 | E27: Q2 10-Q p. 25: 269,668 vested at issue; the rest vest on AWS payment thresholds; expires 19 Jun 2033.
A28: AWS warrant, net shares (treasury method) | B28: =B27*MAX(0,1-C27/C17) -> 0.43645002
A29: Memo: early exercised shares subject to repurchase | B29: 0.574 | E29: Q2 10-Q p. 17; already legally issued, so not added.
A30: Diluted shares (millions) | B30: =B10+B19+B20+B21*B22+B25+B26+B28 -> 286.11752 | E30: Method: basic (5 Aug 2026) + options and AWS warrant by the treasury method + RSUs + OpenAI tranches whose trigger occurs in the active scenario.
A32: C. Stock pay of awards already in the diluted count (feeds Schedules E)
A33: Unrecognized RSU expense, 31 Dec 2025 | B33: 343.5 | E33: 424B4 p. F-34 (latest disclosed; the 10-Qs give no total)
A34: Unrecognized option expense, 31 Dec 2025 | B34: 33.2 | E34: 424B4 p. F-33
A35: CEO and CTO RSUs granted in Q1 2026 (grant-date value) | B35: 101.6 | E35: Q2 10-Q p. 26
A36: Less: RSU expense recognized in 6M 2026 | B36: 332.92 | E36: Q2 10-Q p. 26
A37: Less: option expense recognized in 6M 2026 | B37: 18.579 | E37: Q2 10-Q p. 26
A38: Remaining expense of awards in the diluted count, 30 Jun 2026 (estimate) | B38: =MAX(0,B33+B34+B35-B36-B37) -> 126.801 | E38: A floor: RSUs granted to others in 2026 are not disclosed. This part is non-cash in the DCF because its shares are counted.
A39: Amortization period (years) | B39: 2.91 | E39: 424B4 p. F-34: weighted-average period for RSUs
A40: Memo: PRSU grant-date value (expense stays a cost; shares excluded) | B40: 531.2 | E40: Q2 10-Q p. 27; US$34.2m recognized in Q2 2026
A42: D. The IPO (424B4 and Q2 10-Q)
A43: IPO price per Class A share (USD) | C43: 185 | E43: 424B4 cover; completed 15 May 2026 (Q2 10-Q).
A44: Underwriting discount per share (USD) | C44: 4.3475 | E44: 424B4 cover
A45: Shares sold, including the full 4.5m over-allotment | B45: 34.5 | E45: Q2 10-Q: underwriters exercised their option in full
A46: Net proceeds before other offering costs (derived) | B46: =B45*(C43-C44) -> 6232.5113
A48: Checks (zero passes)
A49: Class N rose by the OpenAI exercise between 30 Jun and 5 Aug 2026 | B49: =B9-B11-B14 -> 0
A50: OpenAI shares exercised equal the two vested tranches | B50: =B12+B13-B14 -> 0
A51: OpenAI tranche split adds to the unvested shares | B51: =Backlog!B42+Backlog!B43-B24 -> 0
A52: Securities add to the filed anti-dilutive total (76,011 thousand), rounded to thousands | B52: =ROUND(B18+B20+B21+B24+B27+B29-76.011,3) -> 0 | E52: Contingently issuable warrants 26,108 = unvested OpenAI 23,412 + AWS 2,697 (thousands).
A53: IPO net proceeds equal the cash flow statement | B53: =ROUND(B46-N(CF_Hist!E34),2) -> 0 | E53: Rounded to US$10,000: the filing is in thousands.

Sheet Assumptions
A1: Cerebras Systems Inc. (Nasdaq: CBRS) | Assumptions and scenarios
A2: Blue cells are inputs. Each driver has Base, Bull and Bear rows; the Active row follows the switch in C5. Black cells in section B derive from the filings. USD millions unless stated.
B3: Actual | C3: Forecast
A4: Fiscal year ends 31 December | B4: 2025A | C4: 2026E | D4: 2027E | E4: 2028E | F4: 2029E | G4: 2030E | H4: 2031E | I4: 2032E | J4: 2033E | K4: 2034E | L4: 2035E | M4: Comentarios FG | N4: Source / derivation
A5: Scenario switch: 1 = Base, 2 = Bull, 3 = Bear | C5: 1 | N5: Same convention as the house templates (Supuestos!C5).
A6: Active scenario | C6: =CHOOSE(C5,"Base","Bull","Bear") -> Base
A8: A. Second half of 2026, backlog and valuation inputs (one value per scenario)
C9: Active | D9: Base | E9: Bull | F9: Bear
A10: H2 2026E hardware revenue | C10: =CHOOSE($C$5,D10,E10,F10) -> 130 | D10: 130 | E10: 160 | F10: 100 | N10: H1 2026 164.7 (Q1 110.6, Q2 54.1; Q2 10-Q p. 7). Q2 carries US$28.0m of warrant cost. Analyst input.
A11: H2 2026E other cloud and inference revenue (not in the backlog) | C11: =CHOOSE($C$5,D11,E11,F11) -> 150 | D11: 150 | E11: 180 | F11: 120 | N11: H1 2026 cloud 208.8 less OpenAI 74.4 = 134.4 (Revenue_Hist). Analyst input.
A12: H2 2026E hardware gross margin before depreciation and stock pay | C12: =CHOOSE($C$5,D12,E12,F12) -> 0.36 | D12: 0.36 | E12: 0.4 | F12: 0.3 | N12: H1 2026 32.8%; Q2 2026 41.7% before the warrant cost (Revenue_Hist). Analyst input.
A13: H2 2026E cloud gross margin before depreciation and stock pay | C13: =CHOOSE($C$5,D13,E13,F13) -> 0.4 | D13: 0.4 | E13: 0.45 | F13: 0.33 | N13: H1 2026 49.0%, Q2 2026 42.2%; new data center leases start before their revenue (US$1.5bn signed in Q2, Q2 10-Q p. 28). Analyst input.
A14: H2 2026E research and development, excluding stock pay and depreciation | C14: =CHOOSE($C$5,D14,E14,F14) -> 210 | D14: 210 | E14: 200 | F14: 230 | N14: H1 2026 156.2; Q2 92.9 (Revenue_Hist). Analyst input.
A15: H2 2026E sales and marketing, excluding stock pay and depreciation | C15: =CHOOSE($C$5,D15,E15,F15) -> 40 | D15: 40 | E15: 38 | F15: 45 | N15: H1 2026 27.2 (Revenue_Hist). Analyst input.
A16: H2 2026E general and administrative, excluding stock pay and depreciation | C16: =CHOOSE($C$5,D16,E16,F16) -> 50 | D16: 50 | E16: 48 | F16: 55 | N16: H1 2026 36.1, incl. IPO payroll tax (Revenue_Hist). Analyst input.
A17: H2 2026E stock-based compensation (run rate, no IPO catch-up) | C17: =CHOOSE($C$5,D17,E17,F17) -> 180 | D17: 180 | E17: 160 | F17: 220 | N17: Disclosed balances amortizing: RSUs US$193.0m over 1.56 years and options US$33.2m over 1.78 years (424B4 pp. 100, F-33), PRSUs US$531.2m over 3.4-5.9 years, CEO/CTO RSUs US$101.6m (Q2 10-Q pp. 26-27), plus new grants. Analyst input.
A18: H2 2026E capital expenditures | C18: =CHOOSE($C$5,D18,E18,F18) -> 900 | D18: 900 | E18: 1100 | F18: 700 | N18: H1 2026 548.9 (Q1 132.0, Q2 416.9); construction in progress 604.0 at 30 Jun 2026 (Q2 10-Q). Analyst input.
A19: Backlog realization: share of the 30 Jun 2026 backlog that becomes revenue | C19: =CHOOSE($C$5,D19,E19,F19) -> 1 | D19: 1 | E19: 1 | F19: 0.85 | N19: Contracted, take-or-pay (424B4); Bear allows for slippage or renegotiation with one customer that holds most of it. Analyst input.
A20: Renewal: share of expiring backlog revenue that renews | C20: =CHOOSE($C$5,D20,E20,F20) -> 0.8 | D20: 0.8 | E20: 1 | F20: 0.5 | N20: Tranches run 3-4 years, extendable by OpenAI to 5 (424B4 p. 91); inference demand keeps growing, but OpenAI also buys elsewhere. Analyst input.
A21: OpenAI Additional Capacity (1.25 GW option) exercised | C21: =CHOOSE($C$5,D21,E21,F21) -> 0 | D21: 0 | E21: 0.5 | F21: 0 | N21: Option, not contracted; its warrant tranches are 'not probable' (Q2 10-Q p. 24). Bull only. Analyst input.
... A24: Exit EV / EBITDA multiple (2035E) | C24: =CHOOSE($C$5,D24,E24,F24) -> 12 | D24: 12 | E24: 15 | F24: 9 | N24: Cross-check only; a mature, capital-heavy compute business. Analyst input, no sourced peer multiple.
A26: B. Inputs that do not change with the scenario
A27: Pass-through data center revenue: % of backlog revenue (at cost, zero margin) | C27: 0.05 | N27: Reported gross and outside the backlog (Q2 10-Q p. 15); size not disclosed. Convention.
A28: Depreciation in cost of revenue: share of all depreciation | C28: 0.8 | N28: H1 2026 66.6%, Q2 2026 75.8% (Q2 10-Q p. 20); data center systems dominate the asset base. Analyst input.
A29: Stock pay in cost of revenue: share of all stock pay | C29: 0.04 | N29: H1 2026 4.2% (Q2 10-Q p. 26). Analyst input.
A30: Average life of property and equipment (years) | C30: 4 | N30: Data center and computer equipment 3-5 years (424B4 p. F-16).
A31: Interest yield on cash, restricted cash and investments | C31: 0.0375 | N31: Q2 2026 interest 48.8 x 4 / average balance at 31 Mar and 30 Jun 2026 = 3.8% (Q2 10-Q p. 20). Analyst input.
A32: Working Capital Loan: stated interest rate | C32: 0.06 | N32: Q2 10-Q p. 21: 'bears stated interest at 6% per annum'.
A33: Working Capital Loan repaid through services in H2 2026E: share of the 30 Jun 2026 balance | C33: 0.4 | N33: Current portion 736.0 of 918.2 (80%) falls due within 12 months (Q2 10-Q p. 6): half in H2 2026E. Convention.
A34: Working Capital Loan repaid through services in 2027E: share of the 30 Jun 2026 balance | C34: 0.45 | N34: Rest of the current portion plus part of the long-term portion. Convention.
A35: Working Capital Loan repaid through services in 2028E: share of the 30 Jun 2026 balance | C35: 0.15 | N35: Remainder; matures no later than 31 Dec 2032 (Q2 10-Q p. 21). Convention.
A36: Cash tax rate on taxable income after loss carryforwards | C36: 0.21 | N36: US federal 21%. Convention.
A37: Deferred tax asset for net operating losses, 31 Dec 2025 | C37: 123.49 | N37: 424B4 p. F-37 (fully offset by the valuation allowance).
A38: Share of taxable income that loss carryforwards can offset | C38: 0.8 | N38: US federal limit for losses after 2017.
... A42: Sensitivity: cloud gross margin shift, all years 2027E-2035E (pp) | C42: 0 | N42: Keep at 0. The Sensitivity sheet moves it in the build.
A43: Net operating loss carryforwards, 31 Dec 2025, estimate (derived) | C43: =C37/C36 -> 588.04762 | N43: Deferred tax asset / 21%. Federal and state losses mixed; an estimate.
A44: Accounts receivable: % of annualized revenue (derived, 30 Jun 2026) | C44: =N(BS_Hist!F10)/(2*N(IS_Hist!E9)) -> 0.16513483 | N44: 123.4 / (2 x 6M 2026 revenue 373.5). Applied to annual revenue (and 2 x H2 for 31 Dec 2026E).
A45: Inventories: % of annualized hardware revenue (derived, 30 Jun 2026) | C45: =N(BS_Hist!F11)/(2*N(IS_Hist!E7)) -> 0.09916096
A46: Accounts payable: % of annualized cost of revenue before depreciation and stock pay (derived) | C46: =N(BS_Hist!F22)/(2*N(Revenue_Hist!E44)) -> 0.20336903
A48: C. Drivers by year (Base, Bull, Bear and the active row)
A49: Hardware systems revenue: growth on a year earlier | N49: FY2025 +69% (424B4); H1 2026 +18% but Q2 2026 -23% on Q2 2025, with US$28.0m of warrant cost booked against hardware (Q2 10-Q p. 35). Buyers are few (MBZUAI, G42), and the mix moves to cloud. Analyst input.
A50: Base | D50: 0.05 | E50: 0.05 | F50: 0.05 | G50: 0.04 | H50: 0.04 | I50: 0.03 | J50: 0.03 | K50: 0.03 | L50: 0.03
A51: Bull | D51: 0.15 | E51: 0.12 | F51: 0.1 | G51: 0.08 | H51: 0.06 | I51: 0.05 | J51: 0.04 | K51: 0.04 | L51: 0.04
A52: Bear | D52: -0.15 | E52: -0.05 | F52: 0 | G52: 0 | H52: 0 | I52: 0 | J52: 0 | K52: 0 | L52: 0
A53: Active | D53: =CHOOSE($C$5,D50,D51,D52) -> 0.05 | E53: =CHOOSE($C$5,E50,E51,E52) -> 0.05 | F53: =CHOOSE($C$5,F50,F51,F52) -> 0.05 | G53: =CHOOSE($C$5,G50,G51,G52) -> 0.04 | H53: =CHOOSE($C$5,H50,H51,H52) -> 0.04 | I53: =CHOOSE($C$5,I50,I51,I52) -> 0.03 | J53: =CHOOSE($C$5,J50,J51,J52) -> 0.03 | K53: =CHOOSE($C$5,K50,K51,K52) -> 0.03 | L53: =CHOOSE($C$5,L50,L51,L52) -> 0.03
A54: Other cloud and inference revenue (not in the 30 Jun 2026 backlog): growth | N54: Cloud revenue +281% in Q2 2026 (Q2 10-Q p. 35); on-demand, token bundles and marketplaces (AWS, Microsoft, OpenRouter; 424B4). New contracts after 30 Jun 2026 land here. Analyst input.
A55: Base | D55: 0.9 | E55: 0.55 | F55: 0.4 | G55: 0.3 | H55: 0.22 | I55: 0.18 | J55: 0.14 | K55: 0.11 | L55: 0.09
A56: Bull | D56: 1.2 | E56: 0.75 | F56: 0.5 | G56: 0.38 | H56: 0.28 | I56: 0.22 | J56: 0.17 | K56: 0.13 | L56: 0.1
A57: Bear | D57: 0.45 | E57: 0.3 | F57: 0.22 | G57: 0.17 | H57: 0.13 | I57: 0.1 | J57: 0.08 | K57: 0.06 | L57: 0.05
A58: Active | D58: =CHOOSE($C$5,D55,D56,D57) -> 0.9 | E58: =CHOOSE($C$5,E55,E56,E57) -> 0.55 | F58: =CHOOSE($C$5,F55,F56,F57) -> 0.4 | G58: =CHOOSE($C$5,G55,G56,G57) -> 0.3 | H58: =CHOOSE($C$5,H55,H56,H57) -> 0.22 | I58: =CHOOSE($C$5,I55,I56,I57) -> 0.18 | J58: =CHOOSE($C$5,J55,J56,J57) -> 0.14 | K58: =CHOOSE($C$5,K55,K56,K57) -> 0.11 | L58: =CHOOSE($C$5,L55,L56,L57) -> 0.09
A59: Hardware: gross margin before depreciation and stock pay | N59: FY2025 43.0%, H1 2026 32.8%, Q2 2026 11.6% after US$28.0m of warrant cost in hardware revenue (41.7% without it); Revenue_Hist, allocation convention there. Warrant cost sits in backlog revenue in the forecast. Analyst input.
A60: Base | D60: 0.38 | E60: 0.38 | F60: 0.38 | G60: 0.38 | H60: 0.38 | I60: 0.38 | J60: 0.38 | K60: 0.38 | L60: 0.38
A61: Bull | D61: 0.42 | E61: 0.42 | F61: 0.42 | G61: 0.42 | H61: 0.42 | I61: 0.42 | J61: 0.42 | K61: 0.42 | L61: 0.42
A62: Bear | D62: 0.32 | E62: 0.32 | F62: 0.32 | G62: 0.32 | H62: 0.32 | I62: 0.32 | J62: 0.32 | K62: 0.32 | L62: 0.32
A63: Active | D63: =CHOOSE($C$5,D60,D61,D62) -> 0.38 | E63: =CHOOSE($C$5,E60,E61,E62) -> 0.38 | F63: =CHOOSE($C$5,F60,F61,F62) -> 0.38 | G63: =CHOOSE($C$5,G60,G61,G62) -> 0.38 | H63: =CHOOSE($C$5,H60,H61,H62) -> 0.38 | I63: =CHOOSE($C$5,I60,I61,I62) -> 0.38 | J63: =CHOOSE($C$5,J60,J61,J62) -> 0.38 | K63: =CHOOSE($C$5,K60,K61,K62) -> 0.38 | L63: =CHOOSE($C$5,L60,L61,L62) -> 0.38
A64: Cloud and inference: gross margin before depreciation and stock pay | N64: H1 2026 cloud 49.0%, Q2 2026 42.2% on this basis (Revenue_Hist). The 424B4 (p. 97) warns gross margin will be 'significantly lower' near term from data center costs; leases are opex here (cash cost of revenue). Analyst input.
A65: Base | D65: 0.42 | E65: 0.46 | F65: 0.5 | G65: 0.52 | H65: 0.52 | I65: 0.52 | J65: 0.52 | K65: 0.52 | L65: 0.52
A66: Bull | D66: 0.47 | E66: 0.51 | F66: 0.55 | G66: 0.57 | H66: 0.57 | I66: 0.57 | J66: 0.57 | K66: 0.57 | L66: 0.57
A67: Bear | D67: 0.34 | E67: 0.37 | F67: 0.4 | G67: 0.42 | H67: 0.42 | I67: 0.42 | J67: 0.42 | K67: 0.42 | L67: 0.42
A68: Active | D68: =CHOOSE($C$5,D65,D66,D67) -> 0.42 | E68: =CHOOSE($C$5,E65,E66,E67) -> 0.46 | F68: =CHOOSE($C$5,F65,F66,F67) -> 0.5 | G68: =CHOOSE($C$5,G65,G66,G67) -> 0.52 | H68: =CHOOSE($C$5,H65,H66,H67) -> 0.52 | I68: =CHOOSE($C$5,I65,I66,I67) -> 0.52 | J68: =CHOOSE($C$5,J65,J66,J67) -> 0.52 | K68: =CHOOSE($C$5,K65,K66,K67) -> 0.52 | L68: =CHOOSE($C$5,L65,L66,L67) -> 0.52
A69: Research and development, excluding stock pay and depreciation: % of revenue | N69: H1 2026 41.8% of revenue on this basis (Revenue_Hist); revenue scales with the backlog while chip design costs grow slower. Analyst input.
A70: Base | D70: 0.15 | E70: 0.11 | F70: 0.09 | G70: 0.08 | H70: 0.075 | I70: 0.07 | J70: 0.07 | K70: 0.07 | L70: 0.07
A71: Bull | D71: 0.13 | E71: 0.095 | F71: 0.08 | G71: 0.07 | H71: 0.065 | I71: 0.06 | J71: 0.06 | K71: 0.06 | L71: 0.06
A72: Bear | D72: 0.18 | E72: 0.14 | F72: 0.12 | G72: 0.105 | H72: 0.095 | I72: 0.09 | J72: 0.09 | K72: 0.09 | L72: 0.09
A73: Active | D73: =CHOOSE($C$5,D70,D71,D72) -> 0.15 | E73: =CHOOSE($C$5,E70,E71,E72) -> 0.11 | F73: =CHOOSE($C$5,F70,F71,F72) -> 0.09 | G73: =CHOOSE($C$5,G70,G71,G72) -> 0.08 | H73: =CHOOSE($C$5,H70,H71,H72) -> 0.075 | I73: =CHOOSE($C$5,I70,I71,I72) -> 0.07 | J73: =CHOOSE($C$5,J70,J71,J72) -> 0.07 | K73: =CHOOSE($C$5,K70,K71,K72) -> 0.07 | L73: =CHOOSE($C$5,L70,L71,L72) -> 0.07
A74: Sales and marketing, excluding stock pay and depreciation: % of revenue | N74: H1 2026 7.3% (Revenue_Hist); few large contracts need little selling. Analyst input.
A75: Base | D75: 0.03 | E75: 0.025 | F75: 0.025 | G75: 0.025 | H75: 0.025 | I75: 0.025 | J75: 0.025 | K75: 0.025 | L75: 0.025
A76: Bull | D76: 0.025 | E76: 0.02 | F76: 0.02 | G76: 0.02 | H76: 0.02 | I76: 0.02 | J76: 0.02 | K76: 0.02 | L76: 0.02
A77: Bear | D77: 0.04 | E77: 0.035 | F77: 0.035 | G77: 0.035 | H77: 0.035 | I77: 0.035 | J77: 0.035 | K77: 0.035 | L77: 0.035
A78: Active | D78: =CHOOSE($C$5,D75,D76,D77) -> 0.03 | E78: =CHOOSE($C$5,E75,E76,E77) -> 0.025 | F78: =CHOOSE($C$5,F75,F76,F77) -> 0.025 | G78: =CHOOSE($C$5,G75,G76,G77) -> 0.025 | H78: =CHOOSE($C$5,H75,H76,H77) -> 0.025 | I78: =CHOOSE($C$5,I75,I76,I77) -> 0.025 | J78: =CHOOSE($C$5,J75,J76,J77) -> 0.025 | K78: =CHOOSE($C$5,K75,K76,K77) -> 0.025 | L78: =CHOOSE($C$5,L75,L76,L77) -> 0.025
A79: General and administrative, excluding stock pay and depreciation: % of revenue | N79: H1 2026 9.7% including public-company and IPO payroll costs (Revenue_Hist). Analyst input.
A80: Base | D80: 0.035 | E80: 0.03 | F80: 0.025 | G80: 0.025 | H80: 0.025 | I80: 0.025 | J80: 0.025 | K80: 0.025 | L80: 0.025
A81: Bull | D81: 0.03 | E81: 0.025 | F81: 0.02 | G81: 0.02 | H81: 0.02 | I81: 0.02 | J81: 0.02 | K81: 0.02 | L81: 0.02
A82: Bear | D82: 0.045 | E82: 0.04 | F82: 0.035 | G82: 0.035 | H82: 0.035 | I82: 0.035 | J82: 0.035 | K82: 0.035 | L82: 0.035
A83: Active | D83: =CHOOSE($C$5,D80,D81,D82) -> 0.035 | E83: =CHOOSE($C$5,E80,E81,E82) -> 0.03 | F83: =CHOOSE($C$5,F80,F81,F82) -> 0.025 | G83: =CHOOSE($C$5,G80,G81,G82) -> 0.025 | H83: =CHOOSE($C$5,H80,H81,H82) -> 0.025 | I83: =CHOOSE($C$5,I80,I81,I82) -> 0.025 | J83: =CHOOSE($C$5,J80,J81,J82) -> 0.025 | K83: =CHOOSE($C$5,K80,K81,K82) -> 0.025 | L83: =CHOOSE($C$5,L80,L81,L82) -> 0.025
A84: Stock-based compensation (run rate, all grants): % of revenue | N84: Run rate only; the Q2 2026 IPO catch-up is history (Quarterly_Hist). Includes the CEO/CTO PRSUs (US$531.2m over 3.4-5.9 years, Q2 10-Q p. 27). In the DCF only the part above the existing awards' amortization is a cost (Schedules E). Analyst input.
A85: Base | D85: 0.08 | E85: 0.06 | F85: 0.05 | G85: 0.045 | H85: 0.04 | I85: 0.04 | J85: 0.04 | K85: 0.04 | L85: 0.04
A86: Bull | D86: 0.07 | E86: 0.05 | F86: 0.045 | G86: 0.04 | H86: 0.035 | I86: 0.035 | J86: 0.035 | K86: 0.035 | L86: 0.035
A87: Bear | D87: 0.1 | E87: 0.08 | F87: 0.065 | G87: 0.055 | H87: 0.05 | I87: 0.05 | J87: 0.05 | K87: 0.05 | L87: 0.05
A88: Active | D88: =CHOOSE($C$5,D85,D86,D87) -> 0.08 | E88: =CHOOSE($C$5,E85,E86,E87) -> 0.06 | F88: =CHOOSE($C$5,F85,F86,F87) -> 0.05 | G88: =CHOOSE($C$5,G85,G86,G87) -> 0.045 | H88: =CHOOSE($C$5,H85,H86,H87) -> 0.04 | I88: =CHOOSE($C$5,I85,I86,I87) -> 0.04 | J88: =CHOOSE($C$5,J85,J86,J87) -> 0.04 | K88: =CHOOSE($C$5,K85,K86,K87) -> 0.04 | L88: =CHOOSE($C$5,L85,L86,L87) -> 0.04
A89: Capital expenditures: % of cloud and inference revenue | N89: H1 2026 capex 548.9 = 263% of cloud revenue, 'primarily for systems to deliver Cerebras Cloud' (Q2 10-Q p. 43); construction in progress 604.0 (p. 20). Capacity is built ahead of the 2026-2028 tranches, then maintenance. Bear: more capex per dollar of revenue. Analyst input.
A90: Base | D90: 0.55 | E90: 0.4 | F90: 0.25 | G90: 0.18 | H90: 0.15 | I90: 0.15 | J90: 0.15 | K90: 0.15 | L90: 0.15
A91: Bull | D91: 0.55 | E91: 0.42 | F91: 0.28 | G91: 0.2 | H91: 0.16 | I91: 0.15 | J91: 0.15 | K91: 0.15 | L91: 0.15
A92: Bear | D92: 0.6 | E92: 0.45 | F92: 0.3 | G92: 0.2 | H92: 0.17 | I92: 0.16 | J92: 0.16 | K92: 0.16 | L92: 0.16
A93: Active | D93: =CHOOSE($C$5,D90,D91,D92) -> 0.55 | E93: =CHOOSE($C$5,E90,E91,E92) -> 0.4 | F93: =CHOOSE($C$5,F90,F91,F92) -> 0.25 | G93: =CHOOSE($C$5,G90,G91,G92) -> 0.18 | H93: =CHOOSE($C$5,H90,H91,H92) -> 0.15 | I93: =CHOOSE($C$5,I90,I91,I92) -> 0.15 | J93: =CHOOSE($C$5,J90,J91,J92) -> 0.15 | K93: =CHOOSE($C$5,K90,K91,K92) -> 0.15 | L93: =CHOOSE($C$5,L90,L91,L92) -> 0.15

Sheet Interim_Bridge
A1: Cerebras Systems Inc. (Nasdaq: CBRS) | 2026E bridge: six months actual plus a second-half estimate
A2: 6M columns link to the 10-Q; H2 2026E comes from Assumptions, Backlog and Schedules. Balance sheet: column B = 30 Jun 2026A, column D = 31 Dec 2026E. Costs shown before depreciation and stock pay, which have their own lines. USD millions.
A4: Line | B4: 6M 2026A | C4: H2 2026E | D4: FY2026E | E4: 6M 2025A | F4: H2 2025A | G4: FY2025A | H4: Comentarios FG | I4: Source / derivation
A6: Income statement
A7: Hardware | B7: =N(IS_Hist!E7) -> 164.712 | C7: =Assumptions!$C$10 -> 130 | D7: =B7+C7 -> 294.712 | E7: =N(IS_Hist!D7) -> 139.969 | F7: =G7-E7 -> 218.471 | G7: =N(IS_Hist!C7) -> 358.44
A8: Cloud: contracted backlog (6M 2026A: OpenAI) | B8: =N(Revenue_Hist!E65) -> 74.4 | C8: =Backlog!C23 -> 512.21554 | D8: =B8+C8 -> 586.61554 | E8: 0 | F8: =G8-E8 -> 0 | G8: 0
A9: Cloud: renewals of expired backlog | B9: 0 | C9: =Backlog!C26 -> 0 | D9: =B9+C9 -> 0 | E9: 0 | F9: =G9-E9 -> 0 | G9: 0
A10: Cloud: OpenAI Additional Capacity option | B10: 0 | C10: =Backlog!C30 -> 0 | D10: =B10+C10 -> 0 | E10: 0 | F10: =G10-E10 -> 0 | G10: 0
A11: Cloud: other (not in the backlog; 2025A: all cloud) | B11: =N(Revenue_Hist!E67) -> 134.404 | C11: =Assumptions!$C$11 -> 150 | D11: =B11+C11 -> 284.404 | E11: =N(IS_Hist!D8) -> 62.865 | F11: =G11-E11 -> 88.686 | G11: =N(IS_Hist!C8) -> 151.551
A12: Pass-through data center revenue | B12: 0 | C12: =Backlog!C31 -> 27.94 | D12: =B12+C12 -> 27.94 | E12: 0 | F12: =G12-E12 -> 0 | G12: 0
A13: Total revenue | B13: =B7+(B8+B9+B10+B11)+B12 -> 373.516 | C13: =C7+(C8+C9+C10+C11)+C12 -> 820.15554 | D13: =B13+C13 -> 1193.6715 | E13: =E7+(E8+E9+E10+E11)+E12 -> 202.834 | F13: =G13-E13 -> 307.157 | G13: =G7+(G8+G9+G10+G11)+G12 -> 509.991
A14: Cost of revenue before depreciation and stock pay | B14: =N(Revenue_Hist!E44) -> 217.125 | C14: =C7*(1-Assumptions!$C$12)+(C8+C9+C10+C11)*(1-Assumptions!$C$13)+C12 -> 508.46932 | D14: =B14+C14 -> 725.59432 | E14: =N(Revenue_Hist!D44) -> 125.417 | F14: =G14-E14 -> 171.977 | G14: =N(Revenue_Hist!C44) -> 297.394
A15: Depreciation in cost of revenue | B15: =N(Revenue_Hist!E28) -> 28.353 | C15: =C34*Assumptions!$C$28 -> 143.6808 | D15: =B15+C15 -> 172.0338 | E15: =N(Revenue_Hist!D28) -> 3.201 | F15: =G15-E15 -> 9.498 | G15: =N(Revenue_Hist!C28) -> 12.699
A16: Stock pay in cost of revenue | B16: =N(Revenue_Hist!E35) -> 16.303 | C16: =C35*Assumptions!$C$29 -> 7.2 | D16: =B16+C16 -> 23.503 | E16: =N(Revenue_Hist!D35) -> 0.513 | F16: =G16-E16 -> 0.314 | G16: =N(Revenue_Hist!C35) -> 0.827
A17: Total cost of revenue | B17: =B14+B15+B16 -> 261.781 | C17: =C14+C15+C16 -> 659.35012 | D17: =B17+C17 -> 921.13112 | E17: =E14+E15+E16 -> 129.131 | F17: =G17-E17 -> 181.789 | G17: =G14+G15+G16 -> 310.92
A18: Gross profit | B18: =B13-B17 -> 111.735 | C18: =C13-C17 -> 160.80542 | D18: =B18+C18 -> 272.54042 | E18: =E13-E17 -> 73.703 | F18: =G18-E18 -> 125.368 | G18: =G13-G17 -> 199.071
A19: Research and development before stock pay and depreciation | B19: =N(Revenue_Hist!E50) -> 156.232 | C19: =Assumptions!$C$14 -> 210 | D19: =B19+C19 -> 366.232 | E19: =N(Revenue_Hist!D50) -> 93.956 | F19: =G19-E19 -> 102.696 | G19: =N(Revenue_Hist!C50) -> 196.652
A20: Sales and marketing before stock pay and depreciation | B20: =N(Revenue_Hist!E52) -> 27.184 | C20: =Assumptions!$C$15 -> 40 | D20: =B20+C20 -> 67.184 | E20: =N(Revenue_Hist!D52) -> 23.528 | F20: =G20-E20 -> 29.981 | G20: =N(Revenue_Hist!C52) -> 53.509
A21: General and administrative before stock pay and depreciation | B21: =N(Revenue_Hist!E54) -> 36.093 | C21: =Assumptions!$C$16 -> 50 | D21: =B21+C21 -> 86.093 | E21: =N(Revenue_Hist!D54) -> 13.835 | F21: =G21-E21 -> 10.242 | G21: =N(Revenue_Hist!C54) -> 24.077
A22: Stock pay in operating expenses | B22: =B35-B16 -> 370.298 | C22: =C35-C16 -> 172.8 | D22: =B22+C22 -> 543.098 | E22: =E35-E16 -> 21.922 | F22: =G22-E22 -> 27.018 | G22: =G35-G16 -> 48.94
A23: Depreciation in operating expenses | B23: =B34-B15 -> 14.198 | C23: =C34-C15 -> 35.9202 | D23: =B23+C23 -> 50.1182 | E23: =E34-E15 -> 6.114 | F23: =G23-E23 -> 15.641 | G23: =G34-G15 -> 21.755
A24: Total operating expenses | B24: =B19+B20+B21+B22+B23 -> 604.005 | C24: =C19+C20+C21+C22+C23 -> 508.7202 | D24: =B24+C24 -> 1112.7252 | E24: =E19+E20+E21+E22+E23 -> 159.355 | F24: =G24-E24 -> 185.578 | G24: =G19+G20+G21+G22+G23 -> 344.933
A25: Operating income (loss) | B25: =B18-B24 -> -492.27 | C25: =C18-C24 -> -347.91478 | D25: =B25+C25 -> -840.18478 | E25: =E18-E24 -> -85.652 | F25: =G25-E25 -> -60.21 | G25: =G18-G24 -> -145.862
A26: Interest and dividend income | B26: =N(Revenue_Hist!E58) -> 71.571 | C26: =Assumptions!$C$31*(B58+B59)*0.5 -> 161.36676 | D26: =B26+C26 -> 232.93776 | E26: =N(Revenue_Hist!D58) -> 11.833 | F26: =G26-E26 -> 14.969 | G26: =N(Revenue_Hist!C58) -> 26.802 | I26: H2: yield x cash, restricted cash and investments at 30 Jun 2026 x half a year.
A27: Interest on the Working Capital Loan (non-cash) | B27: =N(Revenue_Hist!E59) -> -38.602 | C27: =-Schedules!C17 -> -22.037856 | D27: =B27+C27 -> -60.639856 | E27: =N(Revenue_Hist!D59) -> 0 | F27: =G27-E27 -> 0 | G27: =N(Revenue_Hist!C59) -> 0
A28: Forward contract and other items | B28: =N(Revenue_Hist!E60)+N(Revenue_Hist!E61) -> -3.462 | C28: 0 | D28: =B28+C28 -> -3.462 | E28: =N(Revenue_Hist!D60)+N(Revenue_Hist!D61) -> 362.811 | F28: =G28-E28 -> 1.133 | G28: =N(Revenue_Hist!C60)+N(Revenue_Hist!C61) -> 363.944
A29: Income (loss) before income taxes | B29: =B25+B26+B27+B28 -> -462.763 | C29: =C25+C26+C27+C28 -> -208.58588 | D29: =B29+C29 -> -671.34888 | E29: =E25+E26+E27+E28 -> 288.992 | F29: =G29-E29 -> -44.108 | G29: =G25+G26+G27+G28 -> 244.884
A30: Income tax expense | B30: =N(IS_Hist!E25) -> 1.771 | C30: =Schedules!C25 -> 2 | D30: =B30+C30 -> 3.771 | E30: =N(IS_Hist!D25) -> 3.347 | F30: =G30-E30 -> 3.71 | G30: =N(IS_Hist!C25) -> 7.057 | I30: H2: Schedules C (loss carryforwards; minimum foreign and state tax).
A31: Net income (loss) | B31: =B29-B30 -> -464.534 | C31: =C29-C30 -> -210.58588 | D31: =B31+C31 -> -675.11988 | E31: =E29-E30 -> 285.645 | F31: =G31-E31 -> -47.818 | G31: =G29-G30 -> 237.827
A33: Memo
A34: Depreciation (all functions) | B34: =N(Revenue_Hist!E32) -> 42.551 | C34: =Schedules!C10 -> 179.601 | D34: =B34+C34 -> 222.152 | E34: =N(Revenue_Hist!D32) -> 9.315 | F34: =G34-E34 -> 25.139 | G34: =N(Revenue_Hist!C32) -> 34.454
A35: Stock-based compensation (all functions) | B35: =N(Revenue_Hist!E39) -> 386.601 | C35: =Assumptions!$C$17 -> 180 | D35: =B35+C35 -> 566.601 | E35: =N(Revenue_Hist!D39) -> 22.435 | F35: =G35-E35 -> 27.332 | G35: =N(Revenue_Hist!C39) -> 49.767 | I35: 6M 2026A includes the IPO catch-up (Quarterly_Hist); H2 is run rate.
A36: Customer warrant amortization inside revenue (non-cash) | B36: =N(CF_Hist!E10) -> 46.315 | C36: =Backlog!C50 -> 46.584459 | D36: =B36+C36 -> 92.899459 | E36: =N(CF_Hist!D10) -> 0 | F36: =G36-E36 -> 0 | G36: 0
A37: New OpenAI warrant assets booked in H2 2026E (non-cash; credited to equity) | C37: =Backlog!C49 -> 15.841755
A39: Cash flow (6M 2026A as filed, grouped; H2 2026E from the rows above and the balance sheet below)
A40: Net income (loss) | B40: =N(CF_Hist!E7) -> -464.534 | C40: =C31 -> -210.58588 | D40: =B40+C40 -> -675.11988
A41: Depreciation and amortization | B41: =N(CF_Hist!E8) -> 42.551 | C41: =C34 -> 179.601 | D41: =B41+C41 -> 222.152
A42: Stock-based compensation | B42: =N(CF_Hist!E9) -> 386.601 | C42: =C35 -> 180 | D42: =B42+C42 -> 566.601
A43: Amortization of customer warrants | B43: =N(CF_Hist!E10) -> 46.315 | C43: =C36 -> 46.584459 | D43: =B43+C43 -> 92.899459
A44: Non-cash interest expense | B44: =N(CF_Hist!E12) -> 38.602 | C44: =-C27 -> 22.037856 | D44: =B44+C44 -> 60.639856
A45: Revenue settled against the Working Capital Loan (non-cash) | B45: 0 | C45: =-Schedules!C15 -> -367.2976 | D45: =B45+C45 -> -367.2976 | I45: OpenAI pays by credits against the loan (US$86.3m to 30 Jun 2026, inside the filed working capital lines).
A46: Other non-cash items | B46: =CF_Hist!E54 -> 45.424 | C46: 0 | D46: =B46+C46 -> 45.424
A47: Changes in operating assets and liabilities | B47: =CF_Hist!E55 -> -142.447 | C47: =-(D60-B60)-(D61-B61)+(D68-B68) -> -22.126512 | D47: =B47+C47 -> -164.57351
A48: Net cash from operating activities | B48: =B40+B41+B42+B43+B44+B45+B46+B47 -> -47.488 | C48: =C40+C41+C42+C43+C44+C45+C46+C47 -> -171.78668 | D48: =B48+C48 -> -219.27468
A49: Purchases of property and equipment | B49: =N(CF_Hist!E28) -> -548.873 | C49: =-Schedules!C7 -> -900 | D49: =B49+C49 -> -1448.873
A50: Investments bought less matured and sold | B50: =CF_Hist!E56 -> -761.06 | C50: 0 | D50: =B50+C50 -> -761.06 | I50: H2: investments held flat.
A51: Net cash from financing activities | B51: =N(CF_Hist!E47) -> 7853.242 | C51: 0 | D51: =B51+C51 -> 7853.242 | I51: 6M 2026A: IPO 6,232.5, Series H 1,014.0, Working Capital Loan 1,004.6, RSU tax withholding -416.7.
A52: Effect of exchange rates | B52: =N(CF_Hist!E48) -> 0.638 | C52: 0 | D52: =B52+C52 -> 0.638
A53: Net change in cash and restricted cash | B53: =B48+B49+B50+B51+B52 -> 6496.459 | C53: =C48+C49+C50+C51+C52 -> -1071.7867 | D53: =B53+C53 -> 5424.6723
A54: Cash and restricted cash, beginning | B54: =BS_Hist!D49 -> 930.378 | C54: =B58 -> 7426.837 | D54: =B54 -> 930.378
A55: Cash and restricted cash, ending | B55: =B54+B53 -> 7426.837 | C55: =C54+C53 -> 6355.0503 | D55: =C55 -> 6355.0503
A57: Balance sheet: 30 Jun 2026A (column B) to 31 Dec 2026E (column D)
A58: Cash, cash equivalents and restricted cash | B58: =BS_Hist!F49 -> 7426.837 | D58: =C55 -> 6355.0503
A59: Investments | B59: =N(BS_Hist!F9) -> 1179.39 | D59: =B59 -> 1179.39 | I59: Held flat.
A60: Accounts receivable | B60: =N(BS_Hist!F10) -> 123.361 | D60: =Assumptions!$C$44*2*C13 -> 270.87249
A61: Inventories | B61: =N(BS_Hist!F11) -> 32.666 | D61: =Assumptions!$C$45*2*C7 -> 25.78185
A62: Customer warrants (current and non-current) | B62: =BS_Hist!F51 -> 1128.397 | D62: =B62+C37-C36 -> 1097.6543
A63: Prepaid expenses and other current assets | B63: =N(BS_Hist!F13) -> 191.698 | D63: =B63 -> 191.698 | I63: Held flat.
A64: Property and equipment, net | B64: =N(BS_Hist!F15) -> 986.808 | D64: =Schedules!C11 -> 1707.207
A65: Operating lease right-of-use assets | B65: =N(BS_Hist!F17) -> 528.275 | D65: =B65 -> 528.275 | I65: New leases add equal assets and liabilities; held flat (no cash or equity effect).
A66: Other non-current assets | B66: =N(BS_Hist!F18) -> 30.44 | D66: =B66 -> 30.44
A67: Total assets | B67: =B58+B59+B60+B61+B62+B63+B64+B65+B66 -> 11627.872 | D67: =D58+D59+D60+D61+D62+D63+D64+D65+D66 -> 11386.369
A68: Accounts payable | B68: =N(BS_Hist!F22) -> 88.313 | D68: =Assumptions!$C$46*2*C14 -> 206.81382
A69: Accrued and other current liabilities | B69: =N(BS_Hist!F28) -> 236.91 | D69: =B69 -> 236.91 | I69: Held flat.
A70: Deferred revenue (current and non-current) | B70: =BS_Hist!F52 -> 418.264 | D70: =B70 -> 418.264 | I70: Held flat.
A71: Customer deposits | B71: =N(BS_Hist!F25) -> 242.672 | D71: =B71 -> 242.672 | I71: Held flat; operating (prepayments for systems), not debt.
A72: Operating lease liabilities | B72: =BS_Hist!F53 -> 568.827 | D72: =B72 -> 568.827
A73: Working Capital Loan (OpenAI) | B73: =BS_Hist!F54 -> 918.244 | D73: =Schedules!C16 -> 550.9464
A74: Total liabilities | B74: =B68+B69+B70+B71+B72+B73 -> 2473.23 | D74: =D68+D69+D70+D71+D72+D73 -> 2224.4332
A75: Stockholders' equity | B75: =N(BS_Hist!F45) -> 9154.642 | D75: =B75+C31+C35-C27+C37 -> 9161.9357 | I75: Adds H2 net income, stock pay and the loan interest deemed paid through services (credited to equity; model convention).
A76: Total liabilities and equity | B76: =B74+B75 -> 11627.872 | D76: =D74+D75 -> 11386.369
A78: Checks (zero passes)
A79: Balance sheet balances | B79: =B67-B76 -> 0 | D79: =D67-D76 -> 0
A80: Total assets at 30 Jun 2026 equal the 10-Q | B80: =B67-N(BS_Hist!F19) -> 0
A81: 6M 2026 revenue, costs and net loss equal the 10-Q | B81: =ABS(B13-N(IS_Hist!E9))+ABS(B17-N(IS_Hist!E14))+ABS(B24-N(IS_Hist!E21))+ABS(B31-N(IS_Hist!E26)) -> 0
A82: 6M 2026 operating cash flow and cash change equal the 10-Q | B82: =ABS(B48-N(CF_Hist!E25))+ABS(B53-N(CF_Hist!E49)) -> 0
A83: 6M 2025 and FY2025: costs and net income equal the filings | E83: =ABS(E17-N(IS_Hist!D14))+ABS(E31-N(IS_Hist!D26)) -> 0 | G83: =ABS(G17-N(IS_Hist!C14))+ABS(G24-N(IS_Hist!C21))+ABS(G31-N(IS_Hist!C26)) -> 0

Sheet Schedules
A1: Cerebras Systems Inc. (Nasdaq: CBRS) | Schedules: capex and depreciation, Working Capital Loan, taxes, working capital, stock pay, unlevered free cash flow
A2: Column B = 30 Jun 2026A (opening balances); C = H2 2026E (the first forecast period); D-L = fiscal years. Every check starts in column C. USD millions.
B3: Actual | C3: Forecast
A4: Period | B4: Jun 2026A | C4: H2 2026E | D4: 2027E | E4: 2028E | F4: 2029E | G4: 2030E | H4: 2031E | I4: 2032E | J4: 2033E | K4: 2034E | L4: 2035E | M4: Comentarios FG | N4: Source / derivation
A6: A. Capital expenditures and property and equipment
A7: Capital expenditures | C7: =Assumptions!$C$18 -> 900 | D7: =Forecast_3Stmt!D15*Assumptions!D93 -> 1424.0764 | E7: =Forecast_3Stmt!E15*Assumptions!E93 -> 2360.6075 | F7: =Forecast_3Stmt!F15*Assumptions!F93 -> 1556.2264 | G7: =Forecast_3Stmt!G15*Assumptions!G93 -> 1137.9553 | H7: =Forecast_3Stmt!H15*Assumptions!H93 -> 965.01015 | I7: =Forecast_3Stmt!I15*Assumptions!I93 -> 1046.8126 | J7: =Forecast_3Stmt!J15*Assumptions!J93 -> 1089.8079 | K7: =Forecast_3Stmt!K15*Assumptions!K93 -> 1078.0203 | L7: =Forecast_3Stmt!L15*Assumptions!L93 -> 1135.3531
A8: % of cloud and inference revenue | C8: =C7/(Interim_Bridge!C8+Interim_Bridge!C9+Interim_Bridge!C10+Interim_Bridge!C11) -> 1.3590741 | D8: =D7/Forecast_3Stmt!D15 -> 0.55 | E8: =E7/Forecast_3Stmt!E15 -> 0.4 | F8: =F7/Forecast_3Stmt!F15 -> 0.25 | G8: =G7/Forecast_3Stmt!G15 -> 0.18 | H8: =H7/Forecast_3Stmt!H15 -> 0.15 | I8: =I7/Forecast_3Stmt!I15 -> 0.15 | J8: =J7/Forecast_3Stmt!J15 -> 0.15 | K8: =K7/Forecast_3Stmt!K15 -> 0.15 | L8: =L7/Forecast_3Stmt!L15 -> 0.15
A9: Property and equipment, beginning | C9: =B11 -> 986.808 | D9: =C11 -> 1707.207 | E9: =D11 -> 2526.4721 | F9: =E11 -> 3960.3857 | G9: =F11 -> 4331.9873 | H9: =G11 -> 4244.7014 | I9: =H11 -> 4027.9099 | J9: =I11 -> 3936.8935 | ... L9: =K11 -> 3872.9567
A10: Depreciation | C10: =(C9+0.5*C7)/Assumptions!$C$30*0.5 -> 179.601 | D10: =(D9+0.5*D7)/Assumptions!$C$30 -> 604.8113 | E10: =(E9+0.5*E7)/Assumptions!$C$30 -> 926.69396 | F10: =(F9+0.5*F7)/Assumptions!$C$30 -> 1184.6247 | G10: =(G9+0.5*G7)/Assumptions!$C$30 -> 1225.2412 | H10: =(H9+0.5*H7)/Assumptions!$C$30 -> 1181.8016 | I10: =(I9+0.5*I7)/Assumptions!$C$30 -> 1137.8291 | J10: =(J9+0.5*J7)/Assumptions!$C$30 -> 1120.4494 | K10: =(K9+0.5*K7)/Assumptions!$C$30 -> 1111.3155 | L10: =(L9+0.5*L7)/Assumptions!$C$30 -> 1110.1583 | N10: (Beginning net PP&E + half the period's capex) / average life; H2 2026E x 0.5. A declining-balance convention.
A11: Property and equipment, ending | B11: =N(BS_Hist!F15) -> 986.808 | C11: =C9+C7-C10 -> 1707.207 | D11: =D9+D7-D10 -> 2526.4721 | E11: =E9+E7-E10 -> 3960.3857 | F11: =F9+F7-F10 -> 4331.9873 | G11: =G9+G7-G10 -> 4244.7014 | H11: =H9+H7-H10 -> 4027.9099 | I11: =I9+I7-I10 -> 3936.8935 | J11: =J9+J7-J10 -> 3906.252 | ... L11: =L9+L7-L10 -> 3898.1515
A13: B. Working Capital Loan (OpenAI; repaid through services; 6% stated)
A14: Balance, beginning | C14: =B16 -> 918.244 | D14: =C16 -> 550.9464 | E14: =D16 -> 137.7366 | F14: =E16 -> 0 | G14: =F16 -> 0 | H14: =G16 -> 0 | I14: =H16 -> 0 | J14: =I16 -> 0 | ... L14: =K16 -> 0
A15: Repaid through services (credits against OpenAI billings) | C15: =MIN(C14,Assumptions!$C$33*$B$16) -> 367.2976 | D15: =MIN(D14,Assumptions!$C$34*$B$16) -> 413.2098 | E15: =MIN(E14,Assumptions!$C$35*$B$16) -> 137.7366 | F15: =0 -> 0 | G15: =0 -> 0 | H15: =0 -> 0 | I15: =0 -> 0 | J15: =0 -> 0 | K15: =0 -> 0 | L15: =0 -> 0
A16: Balance, ending | B16: =BS_Hist!F54 -> 918.244 | C16: =C14-C15 -> 550.9464 | D16: =D14-D15 -> 137.7366 | E16: =E14-E15 -> 0 | F16: =F14-F15 -> 0 | G16: =G14-G15 -> 0 | H16: =H14-H15 -> 0 | I16: =I14-I15 -> 0 | J16: =J14-J15 -> 0 | ... L16: =L14-L15 -> 0
A17: Interest expense (stated rate x average balance; non-cash, deemed paid) | C17: =Assumptions!$C$32*(C14+C16)/2*0.5 -> 22.037856 | D17: =Assumptions!$C$32*(D14+D16)/2 -> 20.66049 | E17: =Assumptions!$C$32*(E14+E16)/2 -> 4.132098 | F17: =Assumptions!$C$32*(F14+F16)/2 -> 0 | G17: =Assumptions!$C$32*(G14+G16)/2 -> 0 | H17: =Assumptions!$C$32*(H14+H16)/2 -> 0 | I17: =Assumptions!$C$32*(I14+I16)/2 -> 0 | J17: =Assumptions!$C$32*(J14+J16)/2 -> 0 | K17: =Assumptions!$C$32*(K14+K16)/2 -> 0 | L17: =Assumptions!$C$32*(L14+L16)/2 -> 0 | N17: Q2 10-Q p. 21: interest on amounts repaid through services is deemed paid. Non-cash; excluded from unlevered free cash flow.
A19: C. Loss carryforwards and taxes
A20: Taxable income before loss carryforwards (operating income + interest income - loan interest) | C20: =Interim_Bridge!C25+Interim_Bridge!C26+Interim_Bridge!C27 -> -208.58588 | D20: =Forecast_3Stmt!D28+Forecast_3Stmt!D30+Forecast_3Stmt!D31 -> -25.942708 | E20: =Forecast_3Stmt!E28+Forecast_3Stmt!E30+Forecast_3Stmt!E31 -> 693.58184 | F20: =Forecast_3Stmt!F28+Forecast_3Stmt!F30+Forecast_3Stmt!F31 -> 997.90866 | G20: =Forecast_3Stmt!G28+Forecast_3Stmt!G30+Forecast_3Stmt!G31 -> 1281.5045 | H20: =Forecast_3Stmt!H28+Forecast_3Stmt!H30+Forecast_3Stmt!H31 -> 1512.0637 | I20: =Forecast_3Stmt!I28+Forecast_3Stmt!I30+Forecast_3Stmt!I31 -> 1860.6862 | J20: =Forecast_3Stmt!J28+Forecast_3Stmt!J30+Forecast_3Stmt!J31 -> 2058.4905 | K20: =Forecast_3Stmt!K28+Forecast_3Stmt!K30+Forecast_3Stmt!K31 -> 2135.0277 | L20: =Forecast_3Stmt!L28+Forecast_3Stmt!L30+Forecast_3Stmt!L31 -> 2352.3075 | N20: Book income as the proxy for taxable income.
A21: Loss carryforwards, beginning | C21: =Assumptions!$C$43+MAX(0,-N(IS_Hist!E24)) -> 1050.8106 | D21: =C24 -> 1259.3965 | E21: =D24 -> 1285.3392 | F21: =E24 -> 730.47374 | G21: =F24 -> 0 | H21: =G24 -> 0 | I21: =H24 -> 0 | J21: =I24 -> 0 | K21: =J24 -> 0 | L21: =K24 -> 0 | N21: H2 2026E: estimate at 31 Dec 2025 plus the 6M 2026 pre-tax loss.
A22: Used | C22: =MIN(C21,MAX(0,C20)*Assumptions!$C$38) -> 0 | D22: =MIN(D21,MAX(0,D20)*Assumptions!$C$38) -> 0 | E22: =MIN(E21,MAX(0,E20)*Assumptions!$C$38) -> 554.86547 | F22: =MIN(F21,MAX(0,F20)*Assumptions!$C$38) -> 730.47374 | G22: =MIN(G21,MAX(0,G20)*Assumptions!$C$38) -> 0 | H22: =MIN(H21,MAX(0,H20)*Assumptions!$C$38) -> 0 | I22: =MIN(I21,MAX(0,I20)*Assumptions!$C$38) -> 0 | J22: =MIN(J21,MAX(0,J20)*Assumptions!$C$38) -> 0 | ... L22: =MIN(L21,MAX(0,L20)*Assumptions!$C$38) -> 0
A23: Added | C23: =MAX(0,-C20) -> 208.58588 | D23: =MAX(0,-D20) -> 25.942708 | E23: =MAX(0,-E20) -> 0 | F23: =MAX(0,-F20) -> 0 | G23: =MAX(0,-G20) -> 0 | H23: =MAX(0,-H20) -> 0 | I23: =MAX(0,-I20) -> 0 | J23: =MAX(0,-J20) -> 0 | ... L23: =MAX(0,-L20) -> 0
A24: Loss carryforwards, ending | C24: =C21-C22+C23 -> 1259.3965 | D24: =D21-D22+D23 -> 1285.3392 | E24: =E21-E22+E23 -> 730.47374 | F24: =F21-F22+F23 -> 0 | G24: =G21-G22+G23 -> 0 | H24: =H21-H22+H23 -> 0 | I24: =I21-I22+I23 -> 0 | J24: =J21-J22+J23 -> 0 | ... L24: =L21-L22+L23 -> 0
A25: Income tax (minimum foreign and state tax, or the tax after carryforwards) | C25: =MAX(Assumptions!$C$39*0.5,MAX(0,C20-C22)*Assumptions!$C$36) -> 2 | D25: =MAX(Assumptions!$C$39,MAX(0,D20-D22)*Assumptions!$C$36) -> 4 | E25: =MAX(Assumptions!$C$39,MAX(0,E20-E22)*Assumptions!$C$36) -> 29.130437 | F25: =MAX(Assumptions!$C$39,MAX(0,F20-F22)*Assumptions!$C$36) -> 56.161333 | G25: =MAX(Assumptions!$C$39,MAX(0,G20-G22)*Assumptions!$C$36) -> 269.11594 | H25: =MAX(Assumptions!$C$39,MAX(0,H20-H22)*Assumptions!$C$36) -> 317.53337 | I25: =MAX(Assumptions!$C$39,MAX(0,I20-I22)*Assumptions!$C$36) -> 390.74411 | J25: =MAX(Assumptions!$C$39,MAX(0,J20-J22)*Assumptions!$C$36) -> 432.28301 | K25: =MAX(Assumptions!$C$39,MAX(0,K20-K22)*Assumptions!$C$36) -> 448.35582 | L25: =MAX(Assumptions!$C$39,MAX(0,L20-L22)*Assumptions!$C$36) -> 493.98458
A27: D. Working capital (receivables + inventories - payables; the other working capital lines are held flat)
A28: Net working capital | B28: =Interim_Bridge!B60+Interim_Bridge!B61-Interim_Bridge!B68 -> 67.714 | C28: =Interim_Bridge!D60+Interim_Bridge!D61-Interim_Bridge!D68 -> 89.840512 | D28: =Forecast_3Stmt!D50+Forecast_3Stmt!D51-Forecast_3Stmt!D58 -> 160.65668 | E28: =Forecast_3Stmt!E50+Forecast_3Stmt!E51-Forecast_3Stmt!E58 -> 360.79075 | F28: =Forecast_3Stmt!F50+Forecast_3Stmt!F51-Forecast_3Stmt!F58 -> 431.68388 | G28: =Forecast_3Stmt!G50+Forecast_3Stmt!G51-Forecast_3Stmt!G58 -> 468.1135 | H28: =Forecast_3Stmt!H50+Forecast_3Stmt!H51-Forecast_3Stmt!H58 -> 480.26895 | I28: =Forecast_3Stmt!I50+Forecast_3Stmt!I51-Forecast_3Stmt!I58 -> 518.61968 | J28: =Forecast_3Stmt!J50+Forecast_3Stmt!J51-Forecast_3Stmt!J58 -> 540.39826 | K28: =Forecast_3Stmt!K50+Forecast_3Stmt!K51-Forecast_3Stmt!K58 -> 540.96437 | L28: =Forecast_3Stmt!L50+Forecast_3Stmt!L51-Forecast_3Stmt!L58 -> 568.44274
A29: Change in working capital (cash effect) | C29: =-(C28-B28) -> -22.126512 | D29: =-(D28-C28) -> -70.816163 | E29: =-(E28-D28) -> -200.13407 | F29: =-(F28-E28) -> -70.893135 | G29: =-(G28-F28) -> -36.42962 | H29: =-(H28-G28) -> -12.155454 | I29: =-(I28-H28) -> -38.350721 | J29: =-(J28-I28) -> -21.778581 | ... L29: =-(L28-K28) -> -27.478371
A31: E. Stock pay: awards already in the diluted count (non-cash in the DCF) and the rest (a cost)
A32: Stock-based compensation (income statement) | C32: =Interim_Bridge!C35 -> 180 | D32: =Forecast_3Stmt!D39 -> 240.83499 | E32: =Forecast_3Stmt!E39 -> 390.15983 | F32: =Forecast_3Stmt!F39 -> 341.95608 | G32: =Forecast_3Stmt!G39 -> 309.5994 | H32: =Forecast_3Stmt!H39 -> 277.43024 | I32: =Forecast_3Stmt!I39 -> 299.68703 | J32: =Forecast_3Stmt!J39 -> 310.71954 | K32: =Forecast_3Stmt!K39 -> 303.60095 | L32: =Forecast_3Stmt!L39 -> 319.37356
A33: Remaining expense of awards in the diluted count, beginning | C33: =Cap_Table!B38 -> 126.801 | D33: =C35 -> 105.01389 | E33: =D35 -> 61.43966 | F33: =E35 -> 17.865433 | G33: =F35 -> 0 | H33: =G35 -> 0 | I33: =H35 -> 0 | J33: =I35 -> 0 | K33: =J35 -> 0 | L33: =K35 -> 0
A34: Amortization of those awards | C34: =MIN(C33,Cap_Table!$B$38/Cap_Table!$B$39*0.5,C32) -> 21.787113 | D34: =MIN(D33,Cap_Table!$B$38/Cap_Table!$B$39,D32) -> 43.574227 | E34: =MIN(E33,Cap_Table!$B$38/Cap_Table!$B$39,E32) -> 43.574227 | F34: =MIN(F33,Cap_Table!$B$38/Cap_Table!$B$39,F32) -> 17.865433 | G34: =MIN(G33,Cap_Table!$B$38/Cap_Table!$B$39,G32) -> 0 | H34: =MIN(H33,Cap_Table!$B$38/Cap_Table!$B$39,H32) -> 0 | I34: =MIN(I33,Cap_Table!$B$38/Cap_Table!$B$39,I32) -> 0 | J34: =MIN(J33,Cap_Table!$B$38/Cap_Table!$B$39,J32) -> 0 | K34: =MIN(K33,Cap_Table!$B$38/Cap_Table!$B$39,K32) -> 0 | L34: =MIN(L33,Cap_Table!$B$38/Cap_Table!$B$39,L32) -> 0
A35: Remaining expense, ending | C35: =C33-C34 -> 105.01389 | D35: =D33-D34 -> 61.43966 | E35: =E33-E34 -> 17.865433 | F35: =F33-F34 -> 0 | G35: =G33-G34 -> 0 | H35: =H33-H34 -> 0 | I35: =I33-I34 -> 0 | J35: =J33-J34 -> 0 | ... L35: =L33-L34 -> 0
A36: Stock pay for new grants and the PRSUs (treated as a cash cost) | C36: =C32-C34 -> 158.21289 | D36: =D32-D34 -> 197.26076 | E36: =E32-E34 -> 346.5856 | F36: =F32-F34 -> 324.09064 | G36: =G32-G34 -> 309.5994 | H36: =H32-H34 -> 277.43024 | I36: =I32-I34 -> 299.68703 | J36: =J32-J34 -> 310.71954 | ... L36: =L32-L34 -> 319.37356 | N36: Method: existing options, RSUs and warrants are in the diluted shares, so their expense is added back; everything else stays a cost. No double count.
A38: F. Unlevered free cash flow (H2 2026E onward)
A39: Operating income | C39: =Interim_Bridge!C25 -> -347.91478 | D39: =Forecast_3Stmt!D28 -> -287.82373 | E39: =Forecast_3Stmt!E28 -> 448.37495 | F39: =Forecast_3Stmt!F28 -> 758.03804 | G39: =Forecast_3Stmt!G28 -> 993.01637 | H39: =Forecast_3Stmt!H28 -> 1159.3891 | I39: =Forecast_3Stmt!I28 -> 1436.8017 | J39: =Forecast_3Stmt!J28 -> 1563.4346 | K39: =Forecast_3Stmt!K28 -> 1564.6419 | L39: =Forecast_3Stmt!L28 -> 1706.0592
A40: Taxes on operating income | C40: =IF(C20>0,C25*MAX(C39,0)/C20,C25) -> 2 | D40: =IF(D20>0,D25*MAX(D39,0)/D20,D25) -> 4 | E40: =IF(E20>0,E25*MAX(E39,0)/E20,E25) -> 18.831748 | F40: =IF(F20>0,F25*MAX(F39,0)/F20,F25) -> 42.661647 | G40: =IF(G20>0,G25*MAX(G39,0)/G20,G25) -> 208.53344 | H40: =IF(H20>0,H25*MAX(H39,0)/H20,H25) -> 243.47171 | I40: =IF(I20>0,I25*MAX(I39,0)/I20,I25) -> 301.72836 | J40: =IF(J20>0,J25*MAX(J39,0)/J20,J25) -> 328.32127 | ... L40: =IF(L20>0,L25*MAX(L39,0)/L20,L25) -> 358.27242 | N40: Tax allocated to operating income; the minimum tax stays in full.
A41: Net operating profit after tax | C41: =C39-C40 -> -349.91478 | D41: =D39-D40 -> -291.82373 | E41: =E39-E40 -> 429.5432 | F41: =F39-F40 -> 715.37639 | G41: =G39-G40 -> 784.48294 | H41: =H39-H40 -> 915.91737 | I41: =I39-I40 -> 1135.0734 | J41: =J39-J40 -> 1235.1134 | ... L41: =L39-L40 -> 1347.7867
A42: Plus: depreciation | C42: =C10 -> 179.601 | D42: =D10 -> 604.8113 | E42: =E10 -> 926.69396 | F42: =F10 -> 1184.6247 | G42: =G10 -> 1225.2412 | H42: =H10 -> 1181.8016 | I42: =I10 -> 1137.8291 | J42: =J10 -> 1120.4494 | ... L42: =L10 -> 1110.1583
A43: Plus: customer warrant amortization (non-cash; warrant shares in the diluted count) | C43: =Backlog!C50 -> 46.584459 | D43: =Backlog!D50 -> 186.33784 | E43: =Backlog!E50 -> 460.55091 | F43: =Backlog!F50 -> 455.25722 | G43: =Backlog!G50 -> 338.79607 | H43: =Backlog!H50 -> 222.33492 | I43: =Backlog!I50 -> 75.608375 | J43: =Backlog!J50 -> 63.006979 | ... L43: =Backlog!L50 -> 0
A44: Plus: amortization of awards in the diluted count | C44: =C34 -> 21.787113 | D44: =D34 -> 43.574227 | E44: =E34 -> 43.574227 | F44: =F34 -> 17.865433 | G44: =G34 -> 0 | H44: =H34 -> 0 | I44: =I34 -> 0 | J44: =J34 -> 0 | ... L44: =L34 -> 0
A45: Less: capital expenditures | C45: =-C7 -> -900 | D45: =-D7 -> -1424.0764 | E45: =-E7 -> -2360.6075 | F45: =-F7 -> -1556.2264 | G45: =-G7 -> -1137.9553 | H45: =-H7 -> -965.01015 | I45: =-I7 -> -1046.8126 | J45: =-J7 -> -1089.8079 | ... L45: =-L7 -> -1135.3531
A46: Change in working capital | C46: =C29 -> -22.126512 | D46: =D29 -> -70.816163 | E46: =E29 -> -200.13407 | F46: =F29 -> -70.893135 | G46: =G29 -> -36.42962 | H46: =H29 -> -12.155454 | I46: =I29 -> -38.350721 | J46: =J29 -> -21.778581 | ... L46: =L29 -> -27.478371
A47: Unlevered free cash flow | C47: =C41+C42+C43+C44+C45+C46 -> -1024.0687 | D47: =D41+D42+D43+D44+D45+D46 -> -951.9929 | E47: =E41+E42+E43+E44+E45+E46 -> -700.37933 | F47: =F41+F42+F43+F44+F45+F46 -> 746.00424 | G47: =G41+G42+G43+G44+G45+G46 -> 1174.1353 | H47: =H41+H42+H43+H44+H45+H46 -> 1342.8883 | I47: =I41+I42+I43+I44+I45+I46 -> 1263.3475 | J47: =J41+J42+J43+J44+J45+J46 -> 1306.9832 | ... L47: =L41+L42+L43+L44+L45+L46 -> 1295.1136 | N47: Operating leases stay in operating costs (cash cost of revenue), so lease liabilities are not debt in the bridge. Loan service credits are debt repayment, not a cost.
A48: % of revenue | C48: =C47/Interim_Bridge!C13 -> -1.2486275 | D48: =D47/Forecast_3Stmt!D13 -> -0.31623076 | E48: =E47/Forecast_3Stmt!E13 -> -0.10770653 | F48: =F47/Forecast_3Stmt!F13 -> 0.10907896 | G48: =G47/Forecast_3Stmt!G13 -> 0.17065953 | H48: =H47/Forecast_3Stmt!H13 -> 0.19361816 | I48: =I47/Forecast_3Stmt!I13 -> 0.16862224 | J48: =J47/Forecast_3Stmt!J13 -> 0.16825247 | K48: =K47/Forecast_3Stmt!K13 -> 0.16716631 | L48: =L47/Forecast_3Stmt!L13 -> 0.16220674
A50: Checks (zero passes; from the first forecast period)
A51: Taxes equal the income statement | C51: =C25-Interim_Bridge!C30 -> 0 | D51: =D25-Forecast_3Stmt!D34 -> 0 | E51: =E25-Forecast_3Stmt!E34 -> 0 | F51: =F25-Forecast_3Stmt!F34 -> 0 | G51: =G25-Forecast_3Stmt!G34 -> 0 | H51: =H25-Forecast_3Stmt!H34 -> 0 | I51: =I25-Forecast_3Stmt!I34 -> 0 | J51: =J25-Forecast_3Stmt!J34 -> 0 | K51: =K25-Forecast_3Stmt!K34 -> 0 | L51: =L25-Forecast_3Stmt!L34 -> 0
A52: Change in working capital equals the cash flow statement | C52: =C29-Interim_Bridge!C47 -> 0 | D52: =D29-Forecast_3Stmt!D77 -> 0 | E52: =E29-Forecast_3Stmt!E77 -> 0 | F52: =F29-Forecast_3Stmt!F77 -> 0 | G52: =G29-Forecast_3Stmt!G77 -> 0 | H52: =H29-Forecast_3Stmt!H77 -> 0 | I52: =I29-Forecast_3Stmt!I77 -> 0 | J52: =J29-Forecast_3Stmt!J77 -> 0 | K52: =K29-Forecast_3Stmt!K77 -> -7.1054274e-14 | L52: =L29-Forecast_3Stmt!L77 -> 0
A53: Property and equipment equal the balance sheet | C53: =C11-Interim_Bridge!D64 -> 0 | D53: =D11-Forecast_3Stmt!D54 -> 0 | E53: =E11-Forecast_3Stmt!E54 -> 0 | F53: =F11-Forecast_3Stmt!F54 -> 0 | G53: =G11-Forecast_3Stmt!G54 -> 0 | H53: =H11-Forecast_3Stmt!H54 -> 0 | I53: =I11-Forecast_3Stmt!I54 -> 0 | J53: =J11-Forecast_3Stmt!J54 -> 0 | K53: =K11-Forecast_3Stmt!K54 -> 0 | L53: =L11-Forecast_3Stmt!L54 -> 0
A54: Loan balance equals the balance sheet | C54: =C16-Interim_Bridge!D73 -> 0 | D54: =D16-Forecast_3Stmt!D63 -> 0 | E54: =E16-Forecast_3Stmt!E63 -> 0 | F54: =F16-Forecast_3Stmt!F63 -> 0 | G54: =G16-Forecast_3Stmt!G63 -> 0 | H54: =H16-Forecast_3Stmt!H63 -> 0 | I54: =I16-Forecast_3Stmt!I63 -> 0 | J54: =J16-Forecast_3Stmt!J63 -> 0 | K54: =K16-Forecast_3Stmt!K63 -> 0 | L54: =L16-Forecast_3Stmt!L63 -> 0
A55: Depreciation equals the income statement | C55: =C10-Interim_Bridge!C34 -> 0 | D55: =D10-Forecast_3Stmt!D40 -> 0 | E55: =E10-Forecast_3Stmt!E40 -> 0 | F55: =F10-Forecast_3Stmt!F40 -> 0 | G55: =G10-Forecast_3Stmt!G40 -> 0 | H55: =H10-Forecast_3Stmt!H40 -> 0 | I55: =I10-Forecast_3Stmt!I40 -> 0 | J55: =J10-Forecast_3Stmt!J40 -> 0 | K55: =K10-Forecast_3Stmt!K40 -> 0 | L55: =L10-Forecast_3Stmt!L40 -> 0

Sheet Forecast_3Stmt
A1: Cerebras Systems Inc. (Nasdaq: CBRS) | Income statement, balance sheet and cash flow, 2025A and 2026E-2035E
A2: 2025A links to the 424B4 (balance sheet: the 31 Dec 2025 recast in the Q2 10-Q); 2026E links to Interim_Bridge; 2027E onward from Assumptions (active scenario), Backlog and Schedules. USD millions.
B3: Actual | C3: Forecast
A4: Fiscal year ends 31 December | B4: 2025A | C4: 2026E | D4: 2027E | E4: 2028E | F4: 2029E | G4: 2030E | H4: 2031E | I4: 2032E | J4: 2033E | K4: 2034E | L4: 2035E | M4: Comentarios FG | N4: Source / derivation
A6: Income statement
A7: Hardware | B7: =N(IS_Hist!C7) -> 358.44 | C7: =Interim_Bridge!D7 -> 294.712 | D7: =C7*(1+Assumptions!D53) -> 309.4476 | E7: =D7*(1+Assumptions!E53) -> 324.91998 | F7: =E7*(1+Assumptions!F53) -> 341.16598 | G7: =F7*(1+Assumptions!G53) -> 354.81262 | H7: =G7*(1+Assumptions!H53) -> 369.00512 | I7: =H7*(1+Assumptions!I53) -> 380.07528 | J7: =I7*(1+Assumptions!J53) -> 391.47753 | K7: =J7*(1+Assumptions!K53) -> 403.22186 | L7: =K7*(1+Assumptions!L53) -> 415.31852
A8: Cloud: contracted backlog (30 Jun 2026) | B8: 0 | C8: =Interim_Bridge!D8 -> 586.61554 | D8: =Backlog!D23 -> 2048.8622 | E8: =Backlog!E23 -> 5063.9491 | F8: =Backlog!F23 -> 5005.7428 | G8: =Backlog!G23 -> 3725.2039 | H8: =Backlog!H23 -> 2444.6651 | I8: =Backlog!I23 -> 2591.3916 | J8: =Backlog!J23 -> 2159.493 | K8: =Backlog!K23 -> 0 | L8: =Backlog!L23 -> 0
A9: Cloud: renewals of expired backlog | B9: 0 | C9: =Interim_Bridge!D9 -> 0 | D9: =Backlog!D26 -> 0 | E9: =Backlog!E26 -> 0 | F9: =Backlog!F26 -> 46.565049 | G9: =Backlog!G26 -> 1072.3931 | H9: =Backlog!H26 -> 2128.996 | I9: =Backlog!I26 -> 2192.8658 | J9: =Backlog!J26 -> 2604.1707 | K9: =Backlog!K26 -> 4409.8902 | L9: =Backlog!L26 -> 4542.1869
A10: Cloud: OpenAI Additional Capacity option | B10: 0 | C10: =Interim_Bridge!D10 -> 0 | D10: =Backlog!D30 -> 0 | E10: =Backlog!E30 -> 0 | F10: =Backlog!F30 -> 0 | G10: =Backlog!G30 -> 0 | H10: =Backlog!H30 -> 0 | I10: =Backlog!I30 -> 0 | J10: =Backlog!J30 -> 0 | K10: =Backlog!K30 -> 0 | L10: =Backlog!L30 -> 0
A11: Cloud: other (not in the backlog; 2025A: all cloud) | B11: =N(IS_Hist!C8) -> 151.551 | C11: =Interim_Bridge!D11 -> 284.404 | D11: =C11*(1+Assumptions!D58+Assumptions!$C$41) -> 540.3676 | E11: =D11*(1+Assumptions!E58+Assumptions!$C$41) -> 837.56978 | F11: =E11*(1+Assumptions!F58+Assumptions!$C$41) -> 1172.5977 | G11: =F11*(1+Assumptions!G58+Assumptions!$C$41) -> 1524.377 | H11: =G11*(1+Assumptions!H58+Assumptions!$C$41) -> 1859.7399 | I11: =H11*(1+Assumptions!I58+Assumptions!$C$41) -> 2194.4931 | J11: =I11*(1+Assumptions!J58+Assumptions!$C$41) -> 2501.7222 | K11: =J11*(1+Assumptions!K58+Assumptions!$C$41) -> 2776.9116 | L11: =K11*(1+Assumptions!L58+Assumptions!$C$41) -> 3026.8336
A12: Pass-through data center revenue | B12: 0 | C12: =Interim_Bridge!D12 -> 27.94 | D12: =Backlog!D31 -> 111.76 | E12: =Backlog!E31 -> 276.225 | F12: =Backlog!F31 -> 273.05 | G12: =Backlog!G31 -> 203.2 | H12: =Backlog!H31 -> 133.35 | I12: =Backlog!I31 -> 133.35 | J12: =Backlog!J31 -> 111.125 | K12: =Backlog!K31 -> 0 | L12: =Backlog!L31 -> 0
A13: Total revenue | B13: =B7+B8+B9+B10+B11+B12 -> 509.991 | C13: =C7+C8+C9+C10+C11+C12 -> 1193.6715 | D13: =D7+D8+D9+D10+D11+D12 -> 3010.4374 | E13: =E7+E8+E9+E10+E11+E12 -> 6502.6639 | F13: =F7+F8+F9+F10+F11+F12 -> 6839.1215 | G13: =G7+G8+G9+G10+G11+G12 -> 6879.9866 | H13: =H7+H8+H9+H10+H11+H12 -> 6935.7561 | I13: =I7+I8+I9+I10+I11+I12 -> 7492.1759 | ... L13: =L7+L8+L9+L10+L11+L12 -> 7984.3391
A14: Growth | C14: =C13/B13-1 -> 1.3405737 | D14: =D13/C13-1 -> 1.5219981 | E14: =E13/D13-1 -> 1.1600396 | F14: =F13/E13-1 -> 0.05174151 | G14: =G13/F13-1 -> 0.0059752013 | H14: =H13/G13-1 -> 0.0081060429 | I14: =I13/H13-1 -> 0.080224817 | J14: =J13/I13-1 -> 0.036813411 | ... L14: =L13/K13-1 -> 0.051951802
A15: Memo: cloud and inference revenue (backlog, renewals, option, other) | B15: =B8+B9+B10+B11 -> 151.551 | C15: =C8+C9+C10+C11 -> 871.01954 | D15: =D8+D9+D10+D11 -> 2589.2298 | E15: =E8+E9+E10+E11 -> 5901.5189 | F15: =F8+F9+F10+F11 -> 6224.9055 | G15: =G8+G9+G10+G11 -> 6321.974 | H15: =H8+H9+H10+H11 -> 6433.401 | I15: =I8+I9+I10+I11 -> 6978.7506 | ... L15: =L8+L9+L10+L11 -> 7569.0206
A16: Cost of revenue before depreciation and stock pay | B16: =N(Revenue_Hist!C44) -> 297.394 | C16: =Interim_Bridge!D14 -> 725.59432 | D16: =D7*(1-Assumptions!D63)+D15*(1-Assumptions!D68-Assumptions!$C$42)+D12 -> 1805.3708 | E16: =E7*(1-Assumptions!E63)+E15*(1-Assumptions!E68-Assumptions!$C$42)+E12 -> 3664.4956 | F16: =F7*(1-Assumptions!F63)+F15*(1-Assumptions!F68-Assumptions!$C$42)+F12 -> 3597.0257 | G16: =G7*(1-Assumptions!G63)+G15*(1-Assumptions!G68-Assumptions!$C$42)+G12 -> 3457.7313 | H16: =H7*(1-Assumptions!H63)+H15*(1-Assumptions!H68-Assumptions!$C$42)+H12 -> 3450.1656 | I16: =I7*(1-Assumptions!I63)+I15*(1-Assumptions!I68-Assumptions!$C$42)+I12 -> 3718.797 | J16: =J7*(1-Assumptions!J63)+J15*(1-Assumptions!J68-Assumptions!$C$42)+J12 -> 3841.2263 | K16: =K7*(1-Assumptions!K63)+K15*(1-Assumptions!K68-Assumptions!$C$42)+K12 -> 3699.6624 | L16: =L7*(1-Assumptions!L63)+L15*(1-Assumptions!L68-Assumptions!$C$42)+L12 -> 3890.6274 | N16: Includes data center lease, power and pass-through costs.
A17: Depreciation in cost of revenue | B17: =N(Revenue_Hist!C28) -> 12.699 | C17: =Interim_Bridge!D15 -> 172.0338 | D17: =D40*Assumptions!$C$28 -> 483.84904 | E17: =E40*Assumptions!$C$28 -> 741.35517 | F17: =F40*Assumptions!$C$28 -> 947.69977 | G17: =G40*Assumptions!$C$28 -> 980.193 | H17: =H40*Assumptions!$C$28 -> 945.4413 | I17: =I40*Assumptions!$C$28 -> 910.26324 | J17: =J40*Assumptions!$C$28 -> 896.35948 | K17: =K40*Assumptions!$C$28 -> 889.05243 | L17: =L40*Assumptions!$C$28 -> 888.12666
A18: Stock pay in cost of revenue | B18: =N(Revenue_Hist!C35) -> 0.827 | C18: =Interim_Bridge!D16 -> 23.503 | D18: =D39*Assumptions!$C$29 -> 9.6333996 | E18: =E39*Assumptions!$C$29 -> 15.606393 | F18: =F39*Assumptions!$C$29 -> 13.678243 | G18: =G39*Assumptions!$C$29 -> 12.383976 | H18: =H39*Assumptions!$C$29 -> 11.09721 | I18: =I39*Assumptions!$C$29 -> 11.987481 | J18: =J39*Assumptions!$C$29 -> 12.428781 | K18: =K39*Assumptions!$C$29 -> 12.144038 | L18: =L39*Assumptions!$C$29 -> 12.774943
A19: Total cost of revenue | B19: =B16+B17+B18 -> 310.92 | C19: =C16+C17+C18 -> 921.13112 | D19: =D16+D17+D18 -> 2298.8532 | E19: =E16+E17+E18 -> 4421.4571 | F19: =F16+F17+F18 -> 4558.4037 | G19: =G16+G17+G18 -> 4450.3083 | H19: =H16+H17+H18 -> 4406.7041 | I19: =I16+I17+I18 -> 4641.0477 | ... L19: =L16+L17+L18 -> 4791.529
A20: Gross profit | B20: =B13-B19 -> 199.071 | C20: =C13-C19 -> 272.54042 | D20: =D13-D19 -> 711.58415 | E20: =E13-E19 -> 2081.2067 | F20: =F13-F19 -> 2280.7178 | G20: =G13-G19 -> 2429.6783 | H20: =H13-H19 -> 2529.0519 | I20: =I13-I19 -> 2851.1282 | ... L20: =L13-L19 -> 3192.8101
A21: Gross margin | B21: =B20/B13 -> 0.39034218 | C21: =C20/C13 -> 0.22832111 | D21: =D20/D13 -> 0.23637235 | E21: =E20/E13 -> 0.32005448 | F21: =F20/F13 -> 0.33348111 | G21: =G20/G13 -> 0.3531516 | H21: =H20/H13 -> 0.36463969 | I21: =I20/I13 -> 0.38054742 | ... L21: =L20/L13 -> 0.39988409
A22: Research and development before stock pay and depreciation | B22: =N(Revenue_Hist!C50) -> 196.652 | C22: =Interim_Bridge!D19 -> 366.232 | D22: =D13*Assumptions!D73 -> 451.5656 | E22: =E13*Assumptions!E73 -> 715.29302 | F22: =F13*Assumptions!F73 -> 615.52094 | G22: =G13*Assumptions!G73 -> 550.39893 | H22: =H13*Assumptions!H73 -> 520.18171 | I22: =I13*Assumptions!I73 -> 524.45231 | J22: =J13*Assumptions!J73 -> 543.75919 | K22: =K13*Assumptions!K73 -> 531.30166 | L22: =L13*Assumptions!L73 -> 558.90374
A23: Sales and marketing before stock pay and depreciation | B23: =N(Revenue_Hist!C52) -> 53.509 | C23: =Interim_Bridge!D20 -> 67.184 | D23: =D13*Assumptions!D78 -> 90.313121 | E23: =E13*Assumptions!E78 -> 162.5666 | F23: =F13*Assumptions!F78 -> 170.97804 | G23: =G13*Assumptions!G78 -> 171.99967 | H23: =H13*Assumptions!H78 -> 173.3939 | I23: =I13*Assumptions!I78 -> 187.3044 | J23: =J13*Assumptions!J78 -> 194.19971 | K23: =K13*Assumptions!K78 -> 189.75059 | L23: =L13*Assumptions!L78 -> 199.60848
A24: General and administrative before stock pay and depreciation | B24: =N(Revenue_Hist!C54) -> 24.077 | C24: =Interim_Bridge!D21 -> 86.093 | D24: =D13*Assumptions!D83 -> 105.36531 | E24: =E13*Assumptions!E83 -> 195.07992 | F24: =F13*Assumptions!F83 -> 170.97804 | G24: =G13*Assumptions!G83 -> 171.99967 | H24: =H13*Assumptions!H83 -> 173.3939 | I24: =I13*Assumptions!I83 -> 187.3044 | J24: =J13*Assumptions!J83 -> 194.19971 | K24: =K13*Assumptions!K83 -> 189.75059 | L24: =L13*Assumptions!L83 -> 199.60848
A25: Stock pay in operating expenses | B25: =B39-B18 -> 48.94 | C25: =C39-C18 -> 543.098 | D25: =D39-D18 -> 231.20159 | E25: =E39-E18 -> 374.55344 | F25: =F39-F18 -> 328.27783 | G25: =G39-G18 -> 297.21542 | H25: =H39-H18 -> 266.33303 | I25: =I39-I18 -> 287.69955 | ... L25: =L39-L18 -> 306.59862
A26: Depreciation in operating expenses | B26: =B40-B17 -> 21.755 | C26: =C40-C17 -> 50.1182 | D26: =D40-D17 -> 120.96226 | E26: =E40-E17 -> 185.33879 | F26: =F40-F17 -> 236.92494 | G26: =G40-G17 -> 245.04825 | H26: =H40-H17 -> 236.36032 | I26: =I40-I17 -> 227.56581 | ... L26: =L40-L17 -> 222.03166
A27: Total operating expenses | B27: =B22+B23+B24+B25+B26 -> 344.933 | C27: =C22+C23+C24+C25+C26 -> 1112.7252 | D27: =D22+D23+D24+D25+D26 -> 999.40788 | E27: =E22+E23+E24+E25+E26 -> 1632.8318 | F27: =F22+F23+F24+F25+F26 -> 1522.6798 | G27: =G22+G23+G24+G25+G26 -> 1436.6619 | H27: =H22+H23+H24+H25+H26 -> 1369.6629 | I27: =I22+I23+I24+I25+I26 -> 1414.3265 | ... L27: =L22+L23+L24+L25+L26 -> 1486.751
A28: Operating income (loss) | B28: =B20-B27 -> -145.862 | C28: =C20-C27 -> -840.18478 | D28: =D20-D27 -> -287.82373 | E28: =E20-E27 -> 448.37495 | F28: =F20-F27 -> 758.03804 | G28: =G20-G27 -> 993.01637 | H28: =H20-H27 -> 1159.3891 | I28: =I20-I27 -> 1436.8017 | ... L28: =L20-L27 -> 1706.0592
A29: Operating margin | B29: =B28/B13 -> -0.28600897 | C29: =C28/C13 -> -0.70386598 | D29: =D28/D13 -> -0.095608609 | E29: =E28/E13 -> 0.068952502 | F29: =F28/F13 -> 0.11083851 | G29: =G28/G13 -> 0.14433406 | H29: =H28/H13 -> 0.16716117 | I29: =I28/I13 -> 0.19177362 | ... L29: =L28/L13 -> 0.21367569
A30: Interest and dividend income | B30: =N(Revenue_Hist!C58) -> 26.802 | C30: =Interim_Bridge!D26 -> 232.93776 | D30: =Assumptions!$C$31*(C48+C49) -> 282.54151 | E30: =Assumptions!$C$31*(D48+D49) -> 249.339 | F30: =Assumptions!$C$31*(E48+E49) -> 239.87062 | G30: =Assumptions!$C$31*(F48+F49) -> 288.48809 | H30: =Assumptions!$C$31*(G48+G49) -> 352.6746 | I30: =Assumptions!$C$31*(H48+H49) -> 423.88453 | J30: =Assumptions!$C$31*(I48+I49) -> 495.0559 | K30: =Assumptions!$C$31*(J48+J49) -> 570.38579 | L30: =Assumptions!$C$31*(K48+K49) -> 646.24836 | N30: Yield x beginning cash, restricted cash and investments. Excluded from unlevered free cash flow.
A31: Interest on the Working Capital Loan (non-cash) | B31: =N(Revenue_Hist!C59) -> 0 | C31: =Interim_Bridge!D27 -> -60.639856 | D31: =-Schedules!D17 -> -20.66049 | E31: =-Schedules!E17 -> -4.132098 | F31: =-Schedules!F17 -> 0 | G31: =-Schedules!G17 -> 0 | H31: =-Schedules!H17 -> 0 | I31: =-Schedules!I17 -> 0 | J31: =-Schedules!J17 -> 0 | K31: =-Schedules!K17 -> 0 | L31: =-Schedules!L17 -> 0
A32: Forward contract and other items | B32: =N(Revenue_Hist!C60)+N(Revenue_Hist!C61) -> 363.944 | C32: =Interim_Bridge!D28 -> -3.462 | D32: =0 -> 0 | E32: =0 -> 0 | F32: =0 -> 0 | G32: =0 -> 0 | H32: =0 -> 0 | I32: =0 -> 0 | J32: =0 -> 0 | K32: =0 -> 0 | L32: =0 -> 0
A33: Income (loss) before income taxes | B33: =B28+B30+B31+B32 -> 244.884 | C33: =C28+C30+C31+C32 -> -671.34888 | D33: =D28+D30+D31+D32 -> -25.942708 | E33: =E28+E30+E31+E32 -> 693.58184 | F33: =F28+F30+F31+F32 -> 997.90866 | G33: =G28+G30+G31+G32 -> 1281.5045 | H33: =H28+H30+H31+H32 -> 1512.0637 | I33: =I28+I30+I31+I32 -> 1860.6862 | ... L33: =L28+L30+L31+L32 -> 2352.3075
A34: Income tax expense | B34: =N(IS_Hist!C25) -> 7.057 | C34: =Interim_Bridge!D30 -> 3.771 | D34: =Schedules!D25 -> 4 | E34: =Schedules!E25 -> 29.130437 | F34: =Schedules!F25 -> 56.161333 | G34: =Schedules!G25 -> 269.11594 | H34: =Schedules!H25 -> 317.53337 | I34: =Schedules!I25 -> 390.74411 | J34: =Schedules!J25 -> 432.28301 | K34: =Schedules!K25 -> 448.35582 | L34: =Schedules!L25 -> 493.98458
A35: Net income (loss) | B35: =B33-B34 -> 237.827 | C35: =C33-C34 -> -675.11988 | D35: =D33-D34 -> -29.942708 | E35: =E33-E34 -> 664.45141 | F35: =F33-F34 -> 941.74732 | G35: =G33-G34 -> 1012.3885 | H35: =H33-H34 -> 1194.5303 | I35: =I33-I34 -> 1469.9421 | ... L35: =L33-L34 -> 1858.3229
A36: Net margin | B36: =B35/B13 -> 0.46633568 | C36: =C35/C13 -> -0.56558263 | D36: =D35/D13 -> -0.0099462983 | E36: =E35/E13 -> 0.10218142 | F36: =F35/F13 -> 0.13770004 | G36: =G35/G13 -> 0.14714978 | H36: =H35/H13 -> 0.17222784 | I36: =I35/I13 -> 0.19619696 | ... L36: =L35/L13 -> 0.23274599
A38: Memo: non-cash items and company-style measures
A39: Stock-based compensation (all functions) | B39: =N(Revenue_Hist!C39) -> 49.767 | C39: =Interim_Bridge!D35 -> 566.601 | D39: =D13*Assumptions!D88 -> 240.83499 | E39: =E13*Assumptions!E88 -> 390.15983 | F39: =F13*Assumptions!F88 -> 341.95608 | G39: =G13*Assumptions!G88 -> 309.5994 | H39: =H13*Assumptions!H88 -> 277.43024 | I39: =I13*Assumptions!I88 -> 299.68703 | J39: =J13*Assumptions!J88 -> 310.71954 | K39: =K13*Assumptions!K88 -> 303.60095 | L39: =L13*Assumptions!L88 -> 319.37356
A40: Depreciation (all functions) | B40: =N(Revenue_Hist!C32) -> 34.454 | C40: =Interim_Bridge!D34 -> 222.152 | D40: =Schedules!D10 -> 604.8113 | E40: =Schedules!E10 -> 926.69396 | F40: =Schedules!F10 -> 1184.6247 | G40: =Schedules!G10 -> 1225.2412 | H40: =Schedules!H10 -> 1181.8016 | I40: =Schedules!I10 -> 1137.8291 | J40: =Schedules!J10 -> 1120.4494 | K40: =Schedules!K10 -> 1111.3155 | L40: =Schedules!L10 -> 1110.1583
A41: Customer warrant amortization inside revenue (non-cash) | B41: =N(CF_Hist!C10) -> 0 | C41: =Interim_Bridge!D36 -> 92.899459 | D41: =Backlog!D50 -> 186.33784 | E41: =Backlog!E50 -> 460.55091 | F41: =Backlog!F50 -> 455.25722 | G41: =Backlog!G50 -> 338.79607 | H41: =Backlog!H50 -> 222.33492 | I41: =Backlog!I50 -> 75.608375 | J41: =Backlog!J50 -> 63.006979 | K41: =Backlog!K50 -> 0 | L41: =Backlog!L50 -> 0
A42: New OpenAI warrant assets booked (non-cash; credited to equity) | B42: 0 | C42: =Interim_Bridge!C37 -> 15.841755 | D42: =Backlog!D49 -> 63.367019 | E42: =Backlog!E49 -> 156.61735 | F42: =Backlog!F49 -> 154.81715 | G42: =Backlog!G49 -> 115.21276 | H42: =Backlog!H49 -> 75.608375 | I42: =Backlog!I49 -> 75.608375 | J42: =Backlog!J49 -> 63.006979 | K42: =Backlog!K49 -> 0 | L42: =Backlog!L49 -> 0
A43: EBITDA (operating income + depreciation) | B43: =B28+B40 -> -111.408 | C43: =C28+C40 -> -618.03278 | D43: =D28+D40 -> 316.98757 | E43: =E28+E40 -> 1375.0689 | F43: =F28+F40 -> 1942.6627 | G43: =G28+G40 -> 2218.2576 | H43: =H28+H40 -> 2341.1907 | I43: =I28+I40 -> 2574.6308 | ... L43: =L28+L40 -> 2816.2175
A44: EBITDA before stock pay and warrant amortization | B44: =B43+B39+B41 -> -61.641 | C44: =C43+C39+C41 -> 41.467676 | D44: =D43+D39+D41 -> 744.16039 | E44: =E43+E39+E41 -> 2225.7796 | F44: =F43+F39+F41 -> 2739.876 | G44: =G43+G39+G41 -> 2866.6531 | H44: =H43+H39+H41 -> 2840.9559 | I44: =I43+I39+I41 -> 2949.9262 | ... L44: =L43+L39+L41 -> 3135.591
A45: % of revenue | B45: =B44/B13 -> -0.12086684 | C45: =C44/C13 -> 0.034739603 | D45: =D44/D13 -> 0.24719345 | E45: =E44/E13 -> 0.34228736 | F45: =F44/F13 -> 0.40061813 | G45: =G44/G13 -> 0.4166655 | H45: =H44/H13 -> 0.40961012 | I45: =I44/I13 -> 0.39373424 | ... L45: =L44/L13 -> 0.39271767
A47: Balance sheet (31 December)
A48: Cash, cash equivalents and restricted cash | B48: =BS_Hist!D49 -> 930.378 | C48: =Interim_Bridge!D58 -> 6355.0503 | D48: =C48+D83 -> 5469.6499 | E48: =D48+E83 -> 5217.1599 | F48: =E48+F83 -> 6513.6257 | G48: =F48+G83 -> 8225.266 | H48: =G48+H83 -> 10124.197 | I48: =H48+I83 -> 12022.101 | J48: =I48+J83 -> 14030.898 | K48: =J48+K83 -> 16053.9 | L48: =K48+L83 -> 18178.923
A49: Investments | B49: =N(BS_Hist!D9) -> 406.531 | C49: =Interim_Bridge!D59 -> 1179.39 | D49: =C49 -> 1179.39 | E49: =D49 -> 1179.39 | F49: =E49 -> 1179.39 | G49: =F49 -> 1179.39 | H49: =G49 -> 1179.39 | I49: =H49 -> 1179.39 | J49: =I49 -> 1179.39 | K49: =J49 -> 1179.39 | L49: =K49 -> 1179.39
A50: Accounts receivable | B50: =N(BS_Hist!D10) -> 50.423 | C50: =Interim_Bridge!D60 -> 270.87249 | D50: =D13*Assumptions!$C$44 -> 497.12805 | E50: =E13*Assumptions!$C$44 -> 1073.8163 | F50: =F13*Assumptions!$C$44 -> 1129.3771 | G50: =G13*Assumptions!$C$44 -> 1136.1254 | H50: =H13*Assumptions!$C$44 -> 1145.3349 | I50: =I13*Assumptions!$C$44 -> 1237.2192 | J50: =J13*Assumptions!$C$44 -> 1282.7654 | K50: =K13*Assumptions!$C$44 -> 1253.3772 | L50: =L13*Assumptions!$C$44 -> 1318.4925
A51: Inventories | B51: =N(BS_Hist!D11) -> 63.626 | C51: =Interim_Bridge!D61 -> 25.78185 | D51: =D7*Assumptions!$C$45 -> 30.685121 | E51: =E7*Assumptions!$C$45 -> 32.219377 | F51: =F7*Assumptions!$C$45 -> 33.830346 | G51: =G7*Assumptions!$C$45 -> 35.18356 | H51: =H7*Assumptions!$C$45 -> 36.590902 | I51: =I7*Assumptions!$C$45 -> 37.688629 | J51: =J7*Assumptions!$C$45 -> 38.819288 | K51: =K7*Assumptions!$C$45 -> 39.983867 | L51: =L7*Assumptions!$C$45 -> 41.183383
A52: Customer warrants (current and non-current) | B52: =BS_Hist!D51 -> 152.353 | C52: =Interim_Bridge!D62 -> 1097.6543 | D52: =C52+D42-D41 -> 974.68348 | E52: =D52+E42-E41 -> 670.74992 | F52: =E52+F42-F41 -> 370.30985 | G52: =F52+G42-G41 -> 146.72654 | H52: =G52+H42-H41 -> 0 | I52: =H52+I42-I41 -> 0 | J52: =I52+J42-J41 -> 0 | K52: =J52+K42-K41 -> 0 | L52: =K52+L42-L41 -> 0
A53: Prepaid expenses and other current assets | B53: =N(BS_Hist!D13) -> 31.782 | C53: =Interim_Bridge!D63 -> 191.698 | D53: =C53 -> 191.698 | E53: =D53 -> 191.698 | F53: =E53 -> 191.698 | G53: =F53 -> 191.698 | H53: =G53 -> 191.698 | I53: =H53 -> 191.698 | J53: =I53 -> 191.698 | K53: =J53 -> 191.698 | L53: =K53 -> 191.698
A54: Property and equipment, net | B54: =N(BS_Hist!D15) -> 437.396 | C54: =Interim_Bridge!D64 -> 1707.207 | D54: =Schedules!D11 -> 2526.4721 | E54: =Schedules!E11 -> 3960.3857 | F54: =Schedules!F11 -> 4331.9873 | G54: =Schedules!G11 -> 4244.7014 | H54: =Schedules!H11 -> 4027.9099 | I54: =Schedules!I11 -> 3936.8935 | J54: =Schedules!J11 -> 3906.252 | K54: =Schedules!K11 -> 3872.9567 | L54: =Schedules!L11 -> 3898.1515
A55: Operating lease right-of-use assets | B55: =N(BS_Hist!D17) -> 248.95 | C55: =Interim_Bridge!D65 -> 528.275 | D55: =C55 -> 528.275 | E55: =D55 -> 528.275 | F55: =E55 -> 528.275 | G55: =F55 -> 528.275 | H55: =G55 -> 528.275 | I55: =H55 -> 528.275 | J55: =I55 -> 528.275 | K55: =J55 -> 528.275 | L55: =K55 -> 528.275
A56: Other non-current assets | B56: =N(BS_Hist!D18) -> 4.598 | C56: =Interim_Bridge!D66 -> 30.44 | D56: =C56 -> 30.44 | E56: =D56 -> 30.44 | F56: =E56 -> 30.44 | G56: =F56 -> 30.44 | H56: =G56 -> 30.44 | I56: =H56 -> 30.44 | J56: =I56 -> 30.44 | K56: =J56 -> 30.44 | L56: =K56 -> 30.44
A57: Total assets | B57: =B48+B49+B50+B51+B52+B53+B54+B55+B56 -> 2326.037 | C57: =C48+C49+C50+C51+C52+C53+C54+C55+C56 -> 11386.369 | D57: =D48+D49+D50+D51+D52+D53+D54+D55+D56 -> 11428.422 | E57: =E48+E49+E50+E51+E52+E53+E54+E55+E56 -> 12884.134 | F57: =F48+F49+F50+F51+F52+F53+F54+F55+F56 -> 14308.933 | G57: =G48+G49+G50+G51+G52+G53+G54+G55+G56 -> 15717.806 | H57: =H48+H49+H50+H51+H52+H53+H54+H55+H56 -> 17263.836 | I57: =I48+I49+I50+I51+I52+I53+I54+I55+I56 -> 19163.705 | ... L57: =L48+L49+L50+L51+L52+L53+L54+L55+L56 -> 25366.553
A58: Accounts payable | B58: =N(BS_Hist!D22) -> 48.63 | C58: =Interim_Bridge!D68 -> 206.81382 | D58: =D16*Assumptions!$C$46 -> 367.1565 | E58: =E16*Assumptions!$C$46 -> 745.2449 | F58: =F16*Assumptions!$C$46 -> 731.52361 | G58: =G16*Assumptions!$C$46 -> 703.19546 | H58: =H16*Assumptions!$C$46 -> 701.65683 | I58: =I16*Assumptions!$C$46 -> 756.28812 | J58: =J16*Assumptions!$C$46 -> 781.18645 | K58: =K16*Assumptions!$C$46 -> 752.39675 | L58: =L16*Assumptions!$C$46 -> 791.2331
A59: Accrued and other current liabilities | B59: =N(BS_Hist!D28) -> 139.536 | C59: =Interim_Bridge!D69 -> 236.91 | D59: =C59 -> 236.91 | E59: =D59 -> 236.91 | F59: =E59 -> 236.91 | G59: =F59 -> 236.91 | H59: =G59 -> 236.91 | I59: =H59 -> 236.91 | J59: =I59 -> 236.91 | K59: =J59 -> 236.91 | L59: =K59 -> 236.91
A60: Deferred revenue (current and non-current) | B60: =BS_Hist!D52 -> 166.896 | C60: =Interim_Bridge!D70 -> 418.264 | D60: =C60 -> 418.264 | E60: =D60 -> 418.264 | F60: =E60 -> 418.264 | G60: =F60 -> 418.264 | H60: =G60 -> 418.264 | I60: =H60 -> 418.264 | J60: =I60 -> 418.264 | K60: =J60 -> 418.264 | L60: =K60 -> 418.264
A61: Customer deposits | B61: =N(BS_Hist!D25) -> 354.46 | C61: =Interim_Bridge!D71 -> 242.672 | D61: =C61 -> 242.672 | E61: =D61 -> 242.672 | F61: =E61 -> 242.672 | G61: =F61 -> 242.672 | H61: =G61 -> 242.672 | I61: =H61 -> 242.672 | J61: =I61 -> 242.672 | K61: =J61 -> 242.672 | L61: =K61 -> 242.672
A62: Operating lease liabilities | B62: =BS_Hist!D53 -> 261.822 | C62: =Interim_Bridge!D72 -> 568.827 | D62: =C62 -> 568.827 | E62: =D62 -> 568.827 | F62: =E62 -> 568.827 | G62: =F62 -> 568.827 | H62: =G62 -> 568.827 | I62: =H62 -> 568.827 | J62: =I62 -> 568.827 | K62: =J62 -> 568.827 | L62: =K62 -> 568.827
A63: Working Capital Loan (OpenAI) | B63: =BS_Hist!D54 -> 0 | C63: =Interim_Bridge!D73 -> 550.9464 | D63: =Schedules!D16 -> 137.7366 | E63: =Schedules!E16 -> 0 | F63: =Schedules!F16 -> 0 | G63: =Schedules!G16 -> 0 | H63: =Schedules!H16 -> 0 | I63: =Schedules!I16 -> 0 | J63: =Schedules!J16 -> 0 | K63: =Schedules!K16 -> 0 | L63: =Schedules!L16 -> 0
A64: Total liabilities | B64: =B58+B59+B60+B61+B62+B63 -> 971.344 | C64: =C58+C59+C60+C61+C62+C63 -> 2224.4332 | D64: =D58+D59+D60+D61+D62+D63 -> 1971.5661 | E64: =E58+E59+E60+E61+E62+E63 -> 2211.9179 | F64: =F58+F59+F60+F61+F62+F63 -> 2198.1966 | G64: =G58+G59+G60+G61+G62+G63 -> 2169.8685 | H64: =H58+H59+H60+H61+H62+H63 -> 2168.3298 | I64: =I58+I59+I60+I61+I62+I63 -> 2222.9611 | ... L64: =L58+L59+L60+L61+L62+L63 -> 2257.9061
A65: Redeemable convertible preferred stock | B65: =N(BS_Hist!D35) -> 1933.348 | C65: =0 -> 0 | D65: =0 -> 0 | E65: =0 -> 0 | F65: =0 -> 0 | G65: =0 -> 0 | H65: =0 -> 0 | I65: =0 -> 0 | J65: =0 -> 0 | ... L65: =0 -> 0 | N65: Converted into common stock at the IPO (Q2 10-Q).
A66: Stockholders' equity (deficit) | B66: =N(BS_Hist!D45) -> -578.655 | C66: =Interim_Bridge!D75 -> 9161.9357 | D66: =C66+D35+D39-D31+D42 -> 9456.8555 | E66: =D66+E35+E39-E31+E42 -> 10672.216 | F66: =E66+F35+F39-F31+F42 -> 12110.737 | G66: =F66+G35+G39-G31+G42 -> 13547.937 | H66: =G66+H35+H39-H31+H42 -> 15095.506 | I66: =H66+I35+I39-I31+I42 -> 16940.744 | J66: =I66+J35+J39-J31+J42 -> 18940.678 | K66: =J66+K35+K39-K31+K42 -> 20930.951 | L66: =K66+L35+L39-L31+L42 -> 23108.647 | N66: Adds net income, stock pay and the loan interest deemed paid through services (model convention). No dividends or buybacks.
A67: Total liabilities, preferred stock and equity | B67: =B64+B65+B66 -> 2326.037 | C67: =C64+C65+C66 -> 11386.369 | D67: =D64+D65+D66 -> 11428.422 | E67: =E64+E65+E66 -> 12884.134 | F67: =F64+F65+F66 -> 14308.933 | G67: =G64+G65+G66 -> 15717.806 | H67: =H64+H65+H66 -> 17263.836 | I67: =I64+I65+I66 -> 19163.705 | ... L67: =L64+L65+L66 -> 25366.553
A69: Cash flow
A70: Net income (loss) | B70: =N(CF_Hist!C7) -> 237.827 | C70: =Interim_Bridge!D40 -> -675.11988 | D70: =D35 -> -29.942708 | E70: =E35 -> 664.45141 | F70: =F35 -> 941.74732 | G70: =G35 -> 1012.3885 | H70: =H35 -> 1194.5303 | I70: =I35 -> 1469.9421 | J70: =J35 -> 1626.2075 | K70: =K35 -> 1686.6719 | L70: =L35 -> 1858.3229
A71: Depreciation and amortization | B71: =N(CF_Hist!C8) -> 34.454 | C71: =Interim_Bridge!D41 -> 222.152 | D71: =D40 -> 604.8113 | E71: =E40 -> 926.69396 | F71: =F40 -> 1184.6247 | G71: =G40 -> 1225.2412 | H71: =H40 -> 1181.8016 | I71: =I40 -> 1137.8291 | J71: =J40 -> 1120.4494 | K71: =K40 -> 1111.3155 | L71: =L40 -> 1110.1583
A72: Stock-based compensation | B72: =N(CF_Hist!C9) -> 49.767 | C72: =Interim_Bridge!D42 -> 566.601 | D72: =D39 -> 240.83499 | E72: =E39 -> 390.15983 | F72: =F39 -> 341.95608 | G72: =G39 -> 309.5994 | H72: =H39 -> 277.43024 | I72: =I39 -> 299.68703 | J72: =J39 -> 310.71954 | K72: =K39 -> 303.60095 | L72: =L39 -> 319.37356
A73: Amortization of customer warrants | B73: =N(CF_Hist!C10) -> 0 | C73: =Interim_Bridge!D43 -> 92.899459 | D73: =D41 -> 186.33784 | E73: =E41 -> 460.55091 | F73: =F41 -> 455.25722 | G73: =G41 -> 338.79607 | H73: =H41 -> 222.33492 | I73: =I41 -> 75.608375 | J73: =J41 -> 63.006979 | K73: =K41 -> 0 | L73: =L41 -> 0
A74: Non-cash interest expense | B74: =N(CF_Hist!C12) -> 0 | C74: =Interim_Bridge!D44 -> 60.639856 | D74: =-D31 -> 20.66049 | E74: =-E31 -> 4.132098 | F74: =-F31 -> 0 | G74: =-G31 -> 0 | H74: =-H31 -> 0 | I74: =-I31 -> 0 | J74: =-J31 -> 0 | K74: =-K31 -> 0 | L74: =-L31 -> 0
A75: Revenue settled against the Working Capital Loan (non-cash) | B75: 0 | C75: =Interim_Bridge!D45 -> -367.2976 | D75: =-Schedules!D15 -> -413.2098 | E75: =-Schedules!E15 -> -137.7366 | F75: =-Schedules!F15 -> 0 | G75: =-Schedules!G15 -> 0 | H75: =-Schedules!H15 -> 0 | I75: =-Schedules!I15 -> 0 | J75: =-Schedules!J15 -> 0 | K75: =-Schedules!K15 -> 0 | L75: =-Schedules!L15 -> 0
A76: Other non-cash items | B76: =CF_Hist!C54 -> -316.459 | C76: =Interim_Bridge!D46 -> 45.424 | D76: =0 -> 0 | E76: =0 -> 0 | F76: =0 -> 0 | G76: =0 -> 0 | H76: =0 -> 0 | I76: =0 -> 0 | J76: =0 -> 0 | K76: =0 -> 0 | L76: =0 -> 0
A77: Changes in operating assets and liabilities | B77: =CF_Hist!C55 -> -15.639 | C77: =Interim_Bridge!D47 -> -164.57351 | D77: =-(D50-C50)-(D51-C51)+(D58-C58) -> -70.816163 | E77: =-(E50-D50)-(E51-D51)+(E58-D58) -> -200.13407 | F77: =-(F50-E50)-(F51-E51)+(F58-E58) -> -70.893135 | G77: =-(G50-F50)-(G51-F51)+(G58-F58) -> -36.42962 | H77: =-(H50-G50)-(H51-G51)+(H58-G58) -> -12.155454 | I77: =-(I50-H50)-(I51-H51)+(I58-H58) -> -38.350721 | J77: =-(J50-I50)-(J51-I51)+(J58-I58) -> -21.778581 | K77: =-(K50-J50)-(K51-J51)+(K58-J58) -> -0.56610995 | L77: =-(L50-K50)-(L51-K51)+(L58-K58) -> -27.478371
A78: Net cash from operating activities | B78: =B70+B71+B72+B73+B74+B75+B76+B77 -> -10.05 | C78: =C70+C71+C72+C73+C74+C75+C76+C77 -> -219.27468 | D78: =D70+D71+D72+D73+D74+D75+D76+D77 -> 538.67594 | E78: =E70+E71+E72+E73+E74+E75+E76+E77 -> 2108.1175 | F78: =F70+F71+F72+F73+F74+F75+F76+F77 -> 2852.6922 | G78: =G70+G71+G72+G73+G74+G75+G76+G77 -> 2849.5956 | H78: =H70+H71+H72+H73+H74+H75+H76+H77 -> 2863.9416 | I78: =I70+I71+I72+I73+I74+I75+I76+I77 -> 2944.7159 | ... L78: =L70+L71+L72+L73+L74+L75+L76+L77 -> 3260.3765
A79: Purchases of property and equipment | B79: =N(CF_Hist!C28) -> -382.739 | C79: =Interim_Bridge!D49 -> -1448.873 | D79: =-Schedules!D7 -> -1424.0764 | E79: =-Schedules!E7 -> -2360.6075 | F79: =-Schedules!F7 -> -1556.2264 | G79: =-Schedules!G7 -> -1137.9553 | H79: =-Schedules!H7 -> -965.01015 | I79: =-Schedules!I7 -> -1046.8126 | J79: =-Schedules!J7 -> -1089.8079 | K79: =-Schedules!K7 -> -1078.0203 | L79: =-Schedules!L7 -> -1135.3531
A80: Investments bought less matured and sold | B80: =CF_Hist!C56 -> -284.837 | C80: =Interim_Bridge!D50 -> -761.06 | D80: =0 -> 0 | E80: =0 -> 0 | F80: =0 -> 0 | G80: =0 -> 0 | H80: =0 -> 0 | I80: =0 -> 0 | J80: =0 -> 0 | K80: =0 -> 0 | L80: =0 -> 0
A81: Net cash from financing activities | B81: =N(CF_Hist!C47) -> 1026.56 | C81: =Interim_Bridge!D51 -> 7853.242 | D81: =0 -> 0 | E81: =0 -> 0 | F81: =0 -> 0 | G81: =0 -> 0 | H81: =0 -> 0 | I81: =0 -> 0 | J81: =0 -> 0 | K81: =0 -> 0 | L81: =0 -> 0 | N81: No new equity or debt after the IPO; the revolver (US$850m) stays undrawn; no dividends or buybacks.
A82: Effect of exchange rates | B82: =N(CF_Hist!C48) -> -0.521 | C82: =Interim_Bridge!D52 -> 0.638 | D82: =0 -> 0 | E82: =0 -> 0 | F82: =0 -> 0 | G82: =0 -> 0 | H82: =0 -> 0 | I82: =0 -> 0 | J82: =0 -> 0 | K82: =0 -> 0 | L82: =0 -> 0
A83: Net change in cash and restricted cash | B83: =B78+B79+B80+B81+B82 -> 348.413 | C83: =C78+C79+C80+C81+C82 -> 5424.6723 | D83: =D78+D79+D80+D81+D82 -> -885.40043 | E83: =E78+E79+E80+E81+E82 -> -252.49002 | F83: =F78+F79+F80+F81+F82 -> 1296.4658 | G83: =G78+G79+G80+G81+G82 -> 1711.6403 | H83: =H78+H79+H80+H81+H82 -> 1898.9315 | I83: =I78+I79+I80+I81+I82 -> 1897.9033 | ... L83: =L78+L79+L80+L81+L82 -> 2125.0234
A84: Free cash flow (operating cash flow less capex) | B84: =B78+B79 -> -392.789 | C84: =C78+C79 -> -1668.1477 | D84: =D78+D79 -> -885.40043 | E84: =E78+E79 -> -252.49002 | F84: =F78+F79 -> 1296.4658 | G84: =G78+G79 -> 1711.6403 | H84: =H78+H79 -> 1898.9315 | I84: =I78+I79 -> 1897.9033 | ... L84: =L78+L79 -> 2125.0234
A85: Free cash flow margin | B85: =B84/B13 -> -0.7701881 | C85: =C84/C13 -> -1.397493 | D85: =D84/D13 -> -0.29411023 | E85: =E84/E13 -> -0.038828705 | F85: =F84/F13 -> 0.18956613 | G85: =G84/G13 -> 0.24878541 | H85: =H84/H13 -> 0.27378868 | I85: =I84/I13 -> 0.25331804 | ... L85: =L84/L13 -> 0.26614894
A87: Checks (zero passes)
A88: Balance sheet balances | B88: =B57-B67 -> 0 | C88: =C57-C67 -> 0 | D88: =D57-D67 -> 0 | E88: =E57-E67 -> 0 | F88: =F57-F67 -> 0 | G88: =G57-G67 -> 0 | H88: =H57-H67 -> 0 | I88: =I57-I67 -> 0 | ... L88: =L57-L67 -> 0
A89: Cash roll-forward | C89: =B48+C83-C48 -> 0 | D89: =C48+D83-D48 -> 0 | E89: =D48+E83-E48 -> 0 | F89: =E48+F83-F48 -> 0 | G89: =F48+G83-G48 -> 0 | H89: =G48+H83-H48 -> 0 | I89: =H48+I83-I48 -> 0 | J89: =I48+J83-J48 -> 0 | ... L89: =K48+L83-L48 -> 0
A90: 2025A revenue, net income and operating cash flow equal the 424B4 | B90: =ABS(B13-N(IS_Hist!C9))+ABS(B35-N(IS_Hist!C26))+ABS(B78-N(CF_Hist!C25)) -> 0
A91: 2025A change in cash equals the 424B4 | B91: =B83-N(CF_Hist!C49) -> 0
A92: 2026E equals six months actual plus H2 (revenue, net income) | C92: =ABS(C13-N(IS_Hist!E9)-Interim_Bridge!C13)+ABS(C35-N(IS_Hist!E26)-Interim_Bridge!C31) -> 0

Sheet Debt_Credit
A1: Cerebras Systems Inc. (Nasdaq: CBRS) | Liquidity, debt, leases, commitments and credit metrics
A2: Balances at 30 Jun 2026 (the latest the filings give) unless stated. Leases are operating leases only (no finance leases in the filings). USD millions.
A4: Item | B4: Jun 2026A | M4: Comentarios FG | N4: Source / derivation
A6: A. Liquidity
A7: Cash and cash equivalents | B7: =N(BS_Hist!F7) -> 6742.157
A8: Investments | B8: =N(BS_Hist!F9) -> 1179.39
A9: Restricted cash (not counted as liquidity) | B9: =N(BS_Hist!F8) -> 684.68 | N9: Q2 10-Q p. 21: the OpenAI loan proceeds "were recorded as restricted cash ... subject to contractual use restrictions and are available to fund permitted uses related to the build-out"; the loan "is secured by a first-priority security interest in the lockbox account". 424B4 p. F-14: also "cash advances received from customers". It backs the loan, so it stays out of the bridge.
A10: Revolving credit facility, undrawn | B10: 850 | N10: Q2 10-Q p. 22: upsized to US$850.0m on 17 Jun 2026; matures 14 Apr 2031; not drawn at 30 Jun 2026; US$150.0m minimum liquidity covenant.
A11: Liquidity (cash + investments + undrawn revolver) | B11: =B7+B8+B10 -> 8771.547
A13: B. Debt and debt-like items (all go into the valuation bridge)
A14: Working Capital Loan (OpenAI), principal outstanding | B14: =BS_Hist!F54 -> 918.244 | N14: Q2 10-Q p. 22: 1,004.6 received in January 2026 less 86.3 credited through services; 6% stated; matures by 31 Dec 2032; repaid in cash or services. Debt.
A15: Total debt and debt-like items | B15: =B14 -> 918.244 | N15: Not included: customer warrants (equity-classified, Q2 10-Q pp. 24-25; their shares are in the diluted count), customer deposits (operating), operating leases (cost in cost of revenue).
A16: Net cash (cash + investments - debt) | B16: =B7+B8-B15 -> 7003.303
A18: C. Operating leases (cost inside operating costs, so not debt in the bridge)
A19: Operating lease liabilities, present value | B19: =BS_Hist!F53 -> 568.827
A20: Lease payments due: 2026 (remaining 6 months) | B20: 58.153 | N20: Q2 10-Q p. 28
A21: Lease payments due: 2027 | B21: 132.394 | N21: Q2 10-Q p. 28
A22: Lease payments due: 2028 | B22: 123.66 | N22: Q2 10-Q p. 28
A23: Lease payments due: 2029 | B23: 126.323 | N23: Q2 10-Q p. 28
A24: Lease payments due: 2030 | B24: 123.261 | N24: Q2 10-Q p. 28
A25: Lease payments due: Thereafter | B25: 126.513 | N25: Q2 10-Q p. 28
A26: Total future lease payments (undiscounted) | B26: =SUM(B20:B25) -> 690.304
A27: Less: imputed interest | B27: -121.477 | N27: Q2 10-Q p. 28
A28: Lease payments less interest equal the lease liability | B28: =B26+B27-B19 -> 0
A29: Leases signed in Q2 2026, not commenced at 30 Jun 2026 (undiscounted) | B29: 1500 | N29: Q2 10-Q p. 28: 'approximately $1.5 billion over the lease term'.
A30: Leases signed in Q3 2026: amount in the notes (subsequent events) | B30: 753.4 | N30: Q2 10-Q p. 29 (Note 17): 'approximately $753.4 million over the lease term'.
A31: Leases signed in Q3 2026: amount in MD&A | B31: 2300 | N31: Q2 10-Q p. 41 (MD&A): 'approximately $2.3 billion over the respective lease term'. Same report, two amounts.
A32: Q3 lease amount used below: 1 = notes (753.4), 2 = MD&A (2,300) | B32: 2 | N32: 2 by default: the larger amount, so the obligations below are not understated. The model's cash costs do not depend on this choice.
A33: Q3 2026 leases used | B33: =CHOOSE(B32,B30,B31) -> 2300
A34: Memo: gap between the two Q3 amounts | B34: =B31-B30 -> 1546.6
A35: All lease payments signed (in use + not commenced), undiscounted | B35: =B26+B29+B33 -> 4490.304
A37: D. Other commitments
A38: Purchase commitments: H2 2026 | B38: 3.6 | N38: Q2 10-Q p. 28 (Note 16)
A39: Purchase commitments: 2027 | B39: 6.2 | N39: Q2 10-Q p. 28
A40: Purchase commitments: 2028 | B40: 0.5 | N40: Q2 10-Q p. 28
A41: Litigation: putative class action (copyright, filed October 2025) | B41: 0 | N41: Q2 10-Q p. 28: no amount accrued or estimated. Not in the bridge.
A43: E. Credit metrics by year (active scenario)
A44: Fiscal year ends 31 December | B44: 2025A | C44: 2026E | D44: 2027E | E44: 2028E | F44: 2029E | G44: 2030E | H44: 2031E | I44: 2032E | J44: 2033E | K44: 2034E | L44: 2035E
A45: EBITDA | B45: =Forecast_3Stmt!B43 -> -111.408 | C45: =Forecast_3Stmt!C43 -> -618.03278 | D45: =Forecast_3Stmt!D43 -> 316.98757 | E45: =Forecast_3Stmt!E43 -> 1375.0689 | F45: =Forecast_3Stmt!F43 -> 1942.6627 | G45: =Forecast_3Stmt!G43 -> 2218.2576 | H45: =Forecast_3Stmt!H43 -> 2341.1907 | I45: =Forecast_3Stmt!I43 -> 2574.6308 | ... L45: =Forecast_3Stmt!L43 -> 2816.2175
A46: Cash, restricted cash and investments | B46: =Forecast_3Stmt!B48+Forecast_3Stmt!B49 -> 1336.909 | C46: =Forecast_3Stmt!C48+Forecast_3Stmt!C49 -> 7534.4403 | D46: =Forecast_3Stmt!D48+Forecast_3Stmt!D49 -> 6649.0399 | E46: =Forecast_3Stmt!E48+Forecast_3Stmt!E49 -> 6396.5499 | F46: =Forecast_3Stmt!F48+Forecast_3Stmt!F49 -> 7693.0157 | G46: =Forecast_3Stmt!G48+Forecast_3Stmt!G49 -> 9404.656 | H46: =Forecast_3Stmt!H48+Forecast_3Stmt!H49 -> 11303.587 | I46: =Forecast_3Stmt!I48+Forecast_3Stmt!I49 -> 13201.491 | ... L46: =Forecast_3Stmt!L48+Forecast_3Stmt!L49 -> 19358.313
A47: Working Capital Loan | B47: =Forecast_3Stmt!B63 -> 0 | C47: =Forecast_3Stmt!C63 -> 550.9464 | D47: =Forecast_3Stmt!D63 -> 137.7366 | E47: =Forecast_3Stmt!E63 -> 0 | F47: =Forecast_3Stmt!F63 -> 0 | G47: =Forecast_3Stmt!G63 -> 0 | H47: =Forecast_3Stmt!H63 -> 0 | I47: =Forecast_3Stmt!I63 -> 0 | ... L47: =Forecast_3Stmt!L63 -> 0
A48: Net cash | B48: =B46-B47 -> 1336.909 | C48: =C46-C47 -> 6983.4939 | D48: =D46-D47 -> 6511.3033 | E48: =E46-E47 -> 6396.5499 | F48: =F46-F47 -> 7693.0157 | G48: =G46-G47 -> 9404.656 | H48: =H46-H47 -> 11303.587 | I48: =I46-I47 -> 13201.491 | ... L48: =L46-L47 -> 19358.313
A49: Debt / EBITDA (x; 0 when EBITDA is negative) | B49: =IF(B45>0,B47/B45,0) -> 0 | C49: =IF(C45>0,C47/C45,0) -> 0 | D49: =IF(D45>0,D47/D45,0) -> 0.43451736 | E49: =IF(E45>0,E47/E45,0) -> 0 | F49: =IF(F45>0,F47/F45,0) -> 0 | G49: =IF(G45>0,G47/G45,0) -> 0 | H49: =IF(H45>0,H47/H45,0) -> 0 | I49: =IF(I45>0,I47/I45,0) -> 0 | ... L49: =IF(L45>0,L47/L45,0) -> 0
A50: Lease liabilities on the balance sheet (memo; held flat in the forecast) | B50: =Forecast_3Stmt!B62 -> 261.822 | C50: =Forecast_3Stmt!C62 -> 568.827 | D50: =Forecast_3Stmt!D62 -> 568.827 | E50: =Forecast_3Stmt!E62 -> 568.827 | F50: =Forecast_3Stmt!F62 -> 568.827 | G50: =Forecast_3Stmt!G62 -> 568.827 | H50: =Forecast_3Stmt!H62 -> 568.827 | I50: =Forecast_3Stmt!I62 -> 568.827 | ... L50: =Forecast_3Stmt!L62 -> 568.827
A51: Free cash flow | B51: =Forecast_3Stmt!B84 -> -392.789 | C51: =Forecast_3Stmt!C84 -> -1668.1477 | D51: =Forecast_3Stmt!D84 -> -885.40043 | E51: =Forecast_3Stmt!E84 -> -252.49002 | F51: =Forecast_3Stmt!F84 -> 1296.4658 | G51: =Forecast_3Stmt!G84 -> 1711.6403 | H51: =Forecast_3Stmt!H84 -> 1898.9315 | I51: =Forecast_3Stmt!I84 -> 1897.9033 | ... L51: =Forecast_3Stmt!L84 -> 2125.0234
A52: Headroom over the US$150m minimum liquidity covenant | B52: =B46-150 -> 1186.909 | C52: =C46-150 -> 7384.4403 | D52: =D46-150 -> 6499.0399 | E52: =E46-150 -> 6246.5499 | F52: =F46-150 -> 7543.0157 | G52: =G46-150 -> 9254.656 | H52: =H46-150 -> 11153.587 | I52: =I46-150 -> 13051.491 | ... L52: =L46-150 -> 19208.313

Sheet Market_Package
A1: Cerebras Systems Inc. (Nasdaq: CBRS) | Market package: price, diluted value, enterprise value and cost of capital
A2: Valuation date 27 Oct 2026; balance sheet date 30 Jun 2026. USD millions unless stated. Peers and trailing multiples: Comparables sheet.
A4: Item | B4: Value | C4: Ticker | D4: Comentarios FG | E4: Source / derivation
A6: A. Dates and price
A7: Valuation date | B7: =DATE(2026,10,27) -> 46322 | E7: Date of the market price.
A8: Balance sheet date | B8: =DATE(2026,6,30) -> 46203 | E8: Latest statements: Q2 10-Q.
A9: Years from the balance sheet date to the valuation date | B9: =(B7-B8)/365 -> 0.3260274
A10: Share price, close of 27 Oct 2026 (USD) | B10: 119.31 | E10: Yahoo Finance daily chart data, close of 27 Oct 2026 (fetched 27 Oct 2026); FMP company profile the same day shows 119.31
A11: Diluted shares (millions) | B11: =Cap_Table!B30 -> 286.11752
A12: Basic shares, 5 Aug 2026 (millions) | B12: =Cap_Table!B10 -> 237.56404
A13: Equity value at the price, diluted | B13: =B10*B11 -> 34136.681
A14: Memo: market value of basic shares | B14: =B10*B12 -> 28343.766
A15: Less: cash, cash equivalents and investments, 30 Jun 2026 | B15: =BS_Hist!F50 -> 7921.547 | E15: Restricted cash excluded (Debt_Credit).
A16: Plus: debt (Working Capital Loan), 30 Jun 2026 | B16: =Debt_Credit!B15 -> 918.244
A17: Enterprise value at the price | B17: =B13-B15+B16 -> 27133.378 | E17: Balances at 30 Jun 2026 against a 27 Oct 2026 price: H2 cash burn is not deducted (the DCF rolls it properly).
A18: Revenue, next twelve months (Nov 2026-Oct 2027: 2/6 x H2 2026E + 10/12 x 2027E) | B18: =2/6*Interim_Bridge!C13+10/12*Forecast_3Stmt!D13 -> 2782.083 | E18: Same forecast path and date as the model; active scenario.
A19: EV / revenue, next twelve months (x) | B19: =B17/B18 -> 9.7529003
A20: EV / revenue 2027E (x) | B20: =B17/Forecast_3Stmt!D13 -> 9.0131017
A21: EV / revenue 2028E (x) | B21: =B17/Forecast_3Stmt!E13 -> 4.1726558
A22: EV / EBITDA 2029E (x) | B22: =IF(Forecast_3Stmt!F43>0,B17/Forecast_3Stmt!F43,0) -> 13.967107
A23: EV / backlog at 30 Jun 2026 (x) | B23: =B17/Backlog!B7 -> 1.0682432
A25: B. Cost of capital
A26: Risk-free rate: 10-year US Treasury | B26: 0.05 | E26: home.treasury.gov daily par yield curve, 10-year, 26 Oct 2026 (as read for the Meta and Anthropic models, dated source snapshot)
A27: Equity risk premium | B27: 0.042 | E27: A. Damodaran implied ERP with adjusted payout, Oct 2026 (same source as the Meta and Anthropic models)
A28: Unlevered beta: median of the four AI chip and compute peers | B28: =Comparables!M10 -> 1.854 | E28: Comparables sheet: 2-year weekly betas against the S&P 500, unlevered at 21% tax (peers file, 27 Oct 2026).
A29: Cerebras debt / market value of equity (basic shares at the price) | B29: =B16/B14 -> 0.032396683 | E29: Debt = Working Capital Loan; no finance leases or borrowings at 30 Jun 2026 (revolver undrawn). Equity = market cap, the basis the peers were unlevered on.
A30: Tax rate for relevering | B30: 0.21 | E30: The rate the peers were unlevered at (Hamada).
A31: Beta used: unlevered x (1 + (1 - tax) x debt / equity) | B31: =B28*(1+(1-B30)*B29) -> 1.9014501
A32: Memo: Cerebras raw beta (about five months of prices; not used) | B32: 1.85 | E32: FMP company profile, 27 Oct 2026
A33: Cost of equity (CAPM) | B33: =B26+B31*B27 -> 0.12986091
A34: Cost of debt (Working Capital Loan stated rate) | B34: =Assumptions!$C$32 -> 0.06
A35: Tax shield on debt | B35: =B30 -> 0.21 | E35: Same 21% as the relevering, for consistency; today's cash shield is nil (loss carryforwards), a small effect at this debt weight.
A36: Debt weight (debt / (debt + market cap)) | B36: =B16/(B16+B14) -> 0.031380073
A37: WACC | B37: =(1-B36)*B33+B36*B34*(1-B35) -> 0.12727328
A39: C. Trading since the listing (memo)
A40: IPO price, 13 May 2026 (USD) | B40: =Cap_Table!C43 -> 185
A41: Low since the listing (USD) | B41: 106.13 | E41: FMP company profile 'range', fetched 27 Oct 2026
A42: High since the listing (USD) | B42: 386.34 | E42: FMP company profile 'range', fetched 27 Oct 2026

Sheet Comparables
A1: Cerebras Systems Inc. (Nasdaq: CBRS) | Trading comparables: AI chips and compute (trailing multiples)
A2: Peers file dated source snapshot (27 Oct 2026): SEC XBRL fundamentals, LTM to each peer's latest quarter; market caps of 27 Oct 2026. USD millions. Trailing only: no forward consensus was available.
A4: Company | B4: Ticker | C4: LTM period | D4: Market cap | E4: Debt | F4: Cash | G4: Enterprise value | H4: LTM revenue | I4: LTM EBITDA | J4: EV / LTM revenue (x) | K4: EV / LTM EBITDA (x) | L4: Revenue growth, LTM | M4: Unlevered beta | N4: Comentarios FG | O4: Source / derivation
A5: NVIDIA CORP | B5: NVDA | C5: LTM to 2026-07-26 | D5: 5252354 | E5: 33370 | F5: 22443 | G5: =D5+E5-F5 -> 5263281 | H5: 302970 | I5: 201266 | J5: =G5/H5 -> 17.372284 | K5: =IF(ISNUMBER(I5),G5/I5,"n.a.") -> 26.15087 | L5: 0.83375903 | M5: 1.853 | O5: SEC XBRL company facts; LTM = fiscal year + YTD - prior YTD (FY2026-01-25+YTD181d-prior); D&A: DepreciationDepletionAndAmortization; debt: LongTermDebt 33,370 (incl. current 1,000), 26 Jul 2026; market cap: FMP batch market cap, 27 Oct 2026; beta: Yahoo Finance weekly adjusted closes vs S&P 500, 2 years to 27 Oct 2026 (104 weeks), OLS slope; unlevered with Hamada at 21% tax, D = debt incl. finance leases, E = market cap
A6: ADVANCED MICRO DEVICES INC | B6: AMD | C6: LTM to 2026-06-27 | D6: 914610 | E6: 3230 | F6: 13111 | G6: =D6+E6-F6 -> 904729 | H6: 41305 | I6: n.a. | J6: =G6/H6 -> 21.903619 | K6: =IF(ISNUMBER(I6),G6/I6,"n.a.") -> n.a. | L6: 0.39543919 | M6: 1.855 | N6: AMD: no current D&A tag, so EBITDA n.a. | O6: SEC XBRL company facts; LTM = fiscal year + YTD - prior YTD (FY2025-12-27+YTD181d-prior); D&A: not reported for the latest period; debt: DebtLongtermAndShorttermCombinedAmount 3,230, 27 Jun 2026; market cap: FMP batch market cap, 27 Oct 2026; beta: Yahoo Finance weekly adjusted closes vs S&P 500, 2 years to 27 Oct 2026 (104 weeks), OLS slope; unlevered with Hamada at 21% tax, D = debt incl. finance leases, E = market cap
A7: Broadcom Inc. | B7: AVGO | C7: LTM to 2026-08-02 | D7: 1634157 | E7: 61080 | F7: 23975 | G7: =D7+E7-F7 -> 1671262 | H7: 89104 | I7: 51440 | J7: =G7/H7 -> 18.756307 | K7: =IF(ISNUMBER(I7),G7/I7,"n.a.") -> 32.489541 | L7: 0.48690051 | M7: 2.23 | O7: SEC XBRL company facts; LTM = fiscal year + YTD - prior YTD (FY2025-11-02+YTD272d-prior); D&A: Depreciation + AmortizationOfIntangibleAssets; debt: DebtLongtermAndShorttermCombinedAmount 61,080, 2 Aug 2026; market cap: Yahoo close 27 Oct 2026 US$342.33 x 4,773.6m shares (10-Q cover, 28 Aug 2026); beta: Yahoo Finance weekly adjusted closes vs S&P 500, 2 years to 27 Oct 2026 (104 weeks), OLS slope; unlevered with Hamada at 21% tax, D = debt incl. finance leases, E = market cap
A8: CoreWeave, Inc. | B8: CRWV | C8: LTM to 2026-06-30 | D8: 32855 | E8: 35770 | F8: 5539 | G8: =D8+E8-F8 -> 63086 | H8: 7590 | I8: 3760 | J8: =G8/H8 -> 8.311726 | K8: =IF(ISNUMBER(I8),G8/I8,"n.a.") -> 16.778191 | L8: 1.1529686 | M8: 1.008 | O8: SEC XBRL company facts; LTM = fiscal year + YTD - prior YTD (FY2025-12-31+YTD180d-prior); D&A: DepreciationDepletionAndAmortization; debt: DebtInstrumentCarryingAmount 35,550 + FinanceLeaseLiability 220, 30 Jun 2026; market cap: FMP profile, 27 Oct 2026 (saved by the SpaceX build); beta: Yahoo Finance weekly adjusted closes vs S&P 500, 2 years to 27 Oct 2026 (83 weeks), OLS slope; unlevered with Hamada at 21% tax, D = debt incl. finance leases, E = market cap
A9: 25th percentile | J9: =_xlfn.QUARTILE.INC($J$5:$J$8,1) -> 15.107145 | L9: =_xlfn.QUARTILE.INC($L$5:$L$8,1) -> 0.46403518 | M9: =_xlfn.QUARTILE.INC($M$5:$M$8,1) -> 1.64175
A10: Median | H10: =MEDIAN($H$5:$H$8) -> 65204.5 | J10: =MEDIAN($J$5:$J$8) -> 18.064296 | K10: =MEDIAN($K$5:$K$8) -> 26.15087 | L10: =MEDIAN($L$5:$L$8) -> 0.66032977 | M10: =MEDIAN($M$5:$M$8) -> 1.854 | O10: EBITDA median from NVDA, AVGO and CRWV (AMD n.a.).
A11: 75th percentile | J11: =_xlfn.QUARTILE.INC($J$5:$J$8,3) -> 19.543135 | L11: =_xlfn.QUARTILE.INC($L$5:$L$8,3) -> 0.91356141 | M11: =_xlfn.QUARTILE.INC($M$5:$M$8,3) -> 1.94875
A12: Cerebras (LTM to 30 Jun 2026: Q3 2025 to Q2 2026) | B12: CBRS | C12: LTM to 2026-06-30 | D12: =Market_Package!B14 -> 28343.766 | E12: =Market_Package!B16 -> 918.244 | F12: =Market_Package!B15 -> 7921.547 | G12: =D12+E12-F12 -> 21340.463 | H12: =N(IS_Hist!C9)-N(IS_Hist!D9)+N(IS_Hist!E9) -> 680.673 | I12: =N(IS_Hist!C22)-N(IS_Hist!D22)+N(IS_Hist!E22)+N(Revenue_Hist!C32)-N(Revenue_Hist!D32)+N(Revenue_Hist!E32) -> -484.79 | J12: =G12/H12 -> 31.352004 | K12: =IF(I12>0,G12/I12,"n.a.") -> n.a. | L12: =H12/SUM(Quarterly_Hist!D9:Quarterly_Hist!G9)-1 -> 0.90833623 | M12: =Market_Package!B28 -> 1.854 | O12: LTM = FY2025 - 6M 2025 + 6M 2026 (IS_Hist); EBITDA = operating loss + depreciation; growth against Q3 2024-Q2 2025 (Quarterly_Hist). Market cap of basic shares at US$119.31.
A14: Scale and profit gap: these multiples are a ceiling-type reference
A15: Cerebras LTM revenue / peer median LTM revenue | D15: =H12/H10 -> 0.010439049 | O15: Peers are tens to hundreds of times larger.
A16: Peer median LTM EBITDA margin (NVDA, AVGO, CRWV) | D16: =MEDIAN(I5/H5,I7/H7,I8/H8) -> 0.57730293
A17: Cerebras LTM EBITDA margin | D17: =I12/H12 -> -0.71222158 | O17: Loss-making: the EBITDA multiple cannot be applied.
A18: Revenue growth, LTM: Cerebras less the peer median (pp) | D18: =L12-L10 -> 0.24800646
A20: Implied value per share (trailing EV / LTM revenue applied to Cerebras LTM revenue; scenario-independent)
A21: Step | D21: 25th percentile | E21: Median | F21: 75th percentile | O21: Source / derivation
A22: EV / LTM revenue (x) | D22: =J9 -> 15.107145 | E22: =J10 -> 18.064296 | F22: =J11 -> 19.543135
A23: Implied enterprise value | D23: =D22*$H$12 -> 10283.026 | E23: =E22*$H$12 -> 12295.878 | F23: =F22*$H$12 -> 13302.485
A24: Plus: cash, cash equivalents and investments, 30 Jun 2026 | D24: =Market_Package!B15 -> 7921.547 | E24: =Market_Package!B15 -> 7921.547 | F24: =Market_Package!B15 -> 7921.547 | O24: Restricted cash excluded: it backs the OpenAI loan (Debt_Credit).
A25: Less: Working Capital Loan | D25: =-Market_Package!B16 -> -918.244 | E25: =-Market_Package!B16 -> -918.244 | F25: =-Market_Package!B16 -> -918.244
A26: Equity value | D26: =D23+D24+D25 -> 17286.329 | E26: =E23+E24+E25 -> 19299.181 | F26: =F23+F24+F25 -> 20305.788
A27: Value per share (USD) | D27: =D26/Market_Package!B11 -> 60.416883 | E27: =E26/Market_Package!B11 -> 67.451939 | F27: =F26/Market_Package!B11 -> 70.970095 | O27: Same bridge and diluted count as the DCF, at 30 Jun 2026 balances (no roll).
A28: Against the price | D28: =D27/Market_Package!B10-1 -> -0.49361426 | E28: =E27/Market_Package!B10-1 -> -0.43464974 | F28: =F27/Market_Package!B10-1 -> -0.40516222
A29: EV / LTM EBITDA (median 26.2x): applied only if Cerebras LTM EBITDA is positive | E29: =IF(I12>0,K10*I12,"n.a.: LTM EBITDA negative") -> n.a.: LTM EBITDA negative
A31: Checks (zero passes)
A32: Median EV / LTM revenue equals the peers file | J32: =ROUND(J10-18.064294192685978,4) -> 0 | O32: To 4 decimals: the file computes its ratios on unrounded revenue; its revenue fields are rounded to US$1m.
A33: Median EV / LTM EBITDA equals the peers file | K33: =ROUND(K10-26.15086999294466,4) -> 0
A34: Median unlevered beta equals the peers file | M34: =ROUND(M10-1.854,6) -> 0
A35: Enterprise values equal the peers file | G35: =ABS(G5-5263281)+ABS(G6-904729)+ABS(G7-1671262)+ABS(G8-63086) -> 0
A36: Cerebras LTM revenue equals the last four quarters | H36: =H12-SUM(Quarterly_Hist!H9:Quarterly_Hist!K9) -> 0

Sheet DCF
A1: Cerebras Systems Inc. (Nasdaq: CBRS) | Discounted cash flow: unlevered free cash flow, perpetuity and exit multiple
A2: Cash flows from 1 Jul 2026, mid-period, discounted to 30 Jun 2026; the perpetuity flows are mid-year too, so the Gordon value carries x(1+WACC)^0.5. Then rolled to 27 Oct 2026. Active scenario. USD millions except per share.
C3: Forecast
A4: Fiscal year ends 31 December | C4: H2 2026E | D4: 2027E | E4: 2028E | F4: 2029E | G4: 2030E | H4: 2031E | I4: 2032E | J4: 2033E | K4: 2034E | L4: 2035E | M4: Comentarios FG | N4: Source / derivation
A5: Revenue | C5: =Interim_Bridge!C13 -> 820.15554 | D5: =Forecast_3Stmt!D13 -> 3010.4374 | E5: =Forecast_3Stmt!E13 -> 6502.6639 | F5: =Forecast_3Stmt!F13 -> 6839.1215 | G5: =Forecast_3Stmt!G13 -> 6879.9866 | H5: =Forecast_3Stmt!H13 -> 6935.7561 | I5: =Forecast_3Stmt!I13 -> 7492.1759 | J5: =Forecast_3Stmt!J13 -> 7767.9884 | K5: =Forecast_3Stmt!K13 -> 7590.0237 | L5: =Forecast_3Stmt!L13 -> 7984.3391
A6: Operating income | C6: =Schedules!C39 -> -347.91478 | D6: =Schedules!D39 -> -287.82373 | E6: =Schedules!E39 -> 448.37495 | F6: =Schedules!F39 -> 758.03804 | G6: =Schedules!G39 -> 993.01637 | H6: =Schedules!H39 -> 1159.3891 | I6: =Schedules!I39 -> 1436.8017 | J6: =Schedules!J39 -> 1563.4346 | ... L6: =Schedules!L39 -> 1706.0592
A7: Less: taxes on operating income | C7: =-Schedules!C40 -> -2 | D7: =-Schedules!D40 -> -4 | E7: =-Schedules!E40 -> -18.831748 | F7: =-Schedules!F40 -> -42.661647 | G7: =-Schedules!G40 -> -208.53344 | H7: =-Schedules!H40 -> -243.47171 | I7: =-Schedules!I40 -> -301.72836 | J7: =-Schedules!J40 -> -328.32127 | ... L7: =-Schedules!L40 -> -358.27242
A8: Net operating profit after tax | C8: =Schedules!C41 -> -349.91478 | D8: =Schedules!D41 -> -291.82373 | E8: =Schedules!E41 -> 429.5432 | F8: =Schedules!F41 -> 715.37639 | G8: =Schedules!G41 -> 784.48294 | H8: =Schedules!H41 -> 915.91737 | I8: =Schedules!I41 -> 1135.0734 | J8: =Schedules!J41 -> 1235.1134 | ... L8: =Schedules!L41 -> 1347.7867
A9: Plus: depreciation | C9: =Schedules!C42 -> 179.601 | D9: =Schedules!D42 -> 604.8113 | E9: =Schedules!E42 -> 926.69396 | F9: =Schedules!F42 -> 1184.6247 | G9: =Schedules!G42 -> 1225.2412 | H9: =Schedules!H42 -> 1181.8016 | I9: =Schedules!I42 -> 1137.8291 | J9: =Schedules!J42 -> 1120.4494 | ... L9: =Schedules!L42 -> 1110.1583
A10: Plus: customer warrant amortization (non-cash) | C10: =Schedules!C43 -> 46.584459 | D10: =Schedules!D43 -> 186.33784 | E10: =Schedules!E43 -> 460.55091 | F10: =Schedules!F43 -> 455.25722 | G10: =Schedules!G43 -> 338.79607 | H10: =Schedules!H43 -> 222.33492 | I10: =Schedules!I43 -> 75.608375 | J10: =Schedules!J43 -> 63.006979 | ... L10: =Schedules!L43 -> 0
A11: Plus: amortization of awards in the diluted count | C11: =Schedules!C44 -> 21.787113 | D11: =Schedules!D44 -> 43.574227 | E11: =Schedules!E44 -> 43.574227 | F11: =Schedules!F44 -> 17.865433 | G11: =Schedules!G44 -> 0 | H11: =Schedules!H44 -> 0 | I11: =Schedules!I44 -> 0 | J11: =Schedules!J44 -> 0 | ... L11: =Schedules!L44 -> 0
A12: Less: capital expenditures | C12: =Schedules!C45 -> -900 | D12: =Schedules!D45 -> -1424.0764 | E12: =Schedules!E45 -> -2360.6075 | F12: =Schedules!F45 -> -1556.2264 | G12: =Schedules!G45 -> -1137.9553 | H12: =Schedules!H45 -> -965.01015 | I12: =Schedules!I45 -> -1046.8126 | J12: =Schedules!J45 -> -1089.8079 | ... L12: =Schedules!L45 -> -1135.3531
A13: Change in working capital | C13: =Schedules!C46 -> -22.126512 | D13: =Schedules!D46 -> -70.816163 | E13: =Schedules!E46 -> -200.13407 | F13: =Schedules!F46 -> -70.893135 | G13: =Schedules!G46 -> -36.42962 | H13: =Schedules!H46 -> -12.155454 | I13: =Schedules!I46 -> -38.350721 | J13: =Schedules!J46 -> -21.778581 | ... L13: =Schedules!L46 -> -27.478371
A14: Unlevered free cash flow | C14: =C8+C9+C10+C11+C12+C13 -> -1024.0687 | D14: =D8+D9+D10+D11+D12+D13 -> -951.9929 | E14: =E8+E9+E10+E11+E12+E13 -> -700.37933 | F14: =F8+F9+F10+F11+F12+F13 -> 746.00424 | G14: =G8+G9+G10+G11+G12+G13 -> 1174.1353 | H14: =H8+H9+H10+H11+H12+H13 -> 1342.8883 | I14: =I8+I9+I10+I11+I12+I13 -> 1263.3475 | J14: =J8+J9+J10+J11+J12+J13 -> 1306.9832 | ... L14: =L8+L9+L10+L11+L12+L13 -> 1295.1136
A15: Years from 30 Jun 2026 to mid-period | C15: 0.25 | D15: 1 | E15: =D15+1 -> 2 | F15: =E15+1 -> 3 | G15: =F15+1 -> 4 | H15: =G15+1 -> 5 | I15: =H15+1 -> 6 | J15: =I15+1 -> 7 | K15: =J15+1 -> 8 | L15: =K15+1 -> 9
A16: Discount factor | C16: =1/(1+$C$21)^C15 -> 0.97049365 | D16: =1/(1+$C$21)^D15 -> 0.88709634 | E16: =1/(1+$C$21)^E15 -> 0.78693992 | F16: =1/(1+$C$21)^F15 -> 0.69809153 | G16: =1/(1+$C$21)^G15 -> 0.61927444 | H16: =1/(1+$C$21)^H15 -> 0.54935609 | I16: =1/(1+$C$21)^I15 -> 0.48733178 | J16: =1/(1+$C$21)^J15 -> 0.43231024 | ... L16: =1/(1+$C$21)^L15 -> 0.34020218
A17: Present value | C17: =C14*C16 -> -993.85219 | D17: =D14*D16 -> -844.50942 | E17: =E14*E16 -> -551.15645 | F17: =F14*F16 -> 520.77924 | G17: =G14*G16 -> 727.11198 | H17: =H14*H16 -> 737.72387 | I17: =I14*I16 -> 615.66937 | J17: =J14*J16 -> 565.02223 | ... L17: =L14*L16 -> 440.60048
A18: Unlevered free cash flow equals Schedules | C18: =C14-Schedules!C47 -> 0 | D18: =D14-Schedules!D47 -> 0 | E18: =E14-Schedules!E47 -> 0 | F18: =F14-Schedules!F47 -> 0 | G18: =G14-Schedules!G47 -> 0 | H18: =H14-Schedules!H47 -> 0 | I18: =I14-Schedules!I47 -> 0 | J18: =J14-Schedules!J47 -> 0 | ... L18: =L14-Schedules!L47 -> 0
A20: Value (perpetuity growth method)
A21: WACC | C21: =Market_Package!B37 -> 0.12727328
A22: Terminal growth | C22: =Assumptions!$C$22 -> 0.03
A23: Terminal return on new invested capital | C23: =Assumptions!$C$23 -> 0.2
A24: Sum of present values, H2 2026E-2035E | C24: =SUM(C17:L17) -> 1703.9735
A25: NOPAT 2036E (2035E x (1 + growth)) | C25: =L8*(1+C22) -> 1388.2203
A26: Reinvestment rate (growth / ROIC) | C26: =C22/C23 -> 0.15
A27: Free cash flow 2036E (NOPAT x (1 - reinvestment)) | C27: =C25*(1-C26) -> 1179.9873
A28: Terminal value at 31 Dec 2035 (mid-year flows: x(1+WACC)^0.5) | C28: =C27/(C21-C22)*(1+C21)^0.5 -> 12879.482 | N28: Same convention as the explicit years: each year's flow arrives mid-year.
A29: Years from 30 Jun 2026 to 31 Dec 2035 | C29: =L15+0.5 -> 9.5
A30: Present value of the terminal value | C30: =C28/(1+C21)^C29 -> 4126.8709
A31: Enterprise value at 30 Jun 2026 | C31: =C24+C30 -> 5830.8444
A32: Plus: cash, cash equivalents and investments, 30 Jun 2026 | C32: =Market_Package!B15 -> 7921.547 | N32: Restricted cash excluded.
A33: Less: Working Capital Loan, 30 Jun 2026 | C33: =-Market_Package!B16 -> -918.244
A34: Equity value at 30 Jun 2026 | C34: =C31+C32+C33 -> 12834.147
A35: Enterprise value rolled to 27 Oct 2026 (x (1+WACC)^years) | C35: =C31*(1+C21)^Market_Package!B9 -> 6063.0954 | N35: H2 2026 flows to 27 Oct are inside the enterprise value; rolling keeps them at their value on the valuation date.
A36: Plus: cash and investments rolled at the interest yield | C36: =C32*(1+Assumptions!$C$31)^Market_Package!B9 -> 8017.1972 | N36: Interest on cash is excluded from unlevered free cash flow and credited here, only to the valuation date; after it, cash is worth its face value.
A37: Less: loan rolled at its 6% stated rate | C37: =C33*(1+Assumptions!$C$32)^Market_Package!B9 -> -935.85487
A38: Equity value at 27 Oct 2026 | C38: =C35+C36+C37 -> 13144.438
A39: Diluted shares (millions) | C39: =Market_Package!B11 -> 286.11752
A40: Value per share (USD) | C40: =C38/C39 -> 45.940695
A41: Share price, 27 Oct 2026 (USD) | C41: =Market_Package!B10 -> 119.31
A42: Value against the price | C42: =C40/C41-1 -> -0.61494682
A43: Terminal value share of enterprise value | C43: =C30/C31 -> 0.70776557
A44: Implied EV / EBITDA 2035E at the terminal value (x) | C44: =IF(Forecast_3Stmt!L43>0,C28/Forecast_3Stmt!L43,0) -> 4.5733264
A46: Why the perpetuity value is a low multiple of 2035E EBITDA (diagnosis; active scenario)
A47: EBITDA 2035E | C47: =Forecast_3Stmt!L43 -> 2816.2175
A48: Depreciation 2035E: share of EBITDA | C48: =Forecast_3Stmt!L40/C47 -> 0.39420191
A49: Taxes: share of operating income 2035E | C49: =-L7/L6 -> 0.21
A50: NOPAT / EBITDA 2035E = (1 - depreciation share) x (1 - tax share) | C50: =L8/C47 -> 0.47858049
A51: Growth factor: (1 + g) x (1 - g / ROIC) | C51: =(1+C22)*(1-C26) -> 0.8755
A52: Spread factor: 1 / (WACC - g) | C52: =1/(C21-C22) -> 10.280316
A53: Mid-year factor: (1 + WACC)^0.5 | C53: =(1+C21)^0.5 -> 1.0617313
A54: Implied EV / EBITDA = NOPAT/EBITDA x growth x spread x mid-year | C54: =C50*C51*C52*C53 -> 4.5733264
A55: Capex / depreciation 2035E (near 1 = depreciation is the maintenance spend) | C55: =-L12/L9 -> 1.0226948
A56: WACC that the exit multiple implies, same NOPAT/EBITDA and growth | C56: =C22+C50*C51*C53/C64 -> 0.06707187 | N56: Approximation: the mid-year factor is held at the model WACC.
A57: Reading: the gap is the value-driver formula working on a capital-heavy business. A peer-style EBITDA multiple ignores depreciation and tax; the perpetuity value pays only for NOPAT.
A58: Depreciation: the 2027-2029 build-out runs through a 4-year life, so depreciation stays a large share of 2035E EBITDA. Capex is close to depreciation in 2035E, so the formula's implicit maintenance spend equals depreciation: no double count.
A59: Taxes: loss carryforwards are used up early; from then on taxes take the statutory 21% of operating income.
A60: WACC: the spread factor 1 / (WACC - g) sets the NOPAT multiple. The exit multiple of 12x is only consistent with the WACC in the row above, far below the model's.
A61: Conclusion: no input is wrong. The exit multiple is a cross-check that assumes a low-capital, peer-like business in 2035; the perpetuity method is the model's value.
A63: Value (exit multiple method, cross-check)
A64: Exit EV / EBITDA 2035E (x) | C64: =Assumptions!$C$24 -> 12
A65: Terminal value at 31 Dec 2035 (a point value; no mid-year factor) | C65: =Forecast_3Stmt!L43*C64 -> 33794.61
A66: Enterprise value rolled to 27 Oct 2026 | C66: =(C24+C65/(1+C21)^C29)*(1+C21)^Market_Package!B9 -> 13031.702
A67: Value per share (USD) | C67: =(C66+C36+C37)/C39 -> 70.296446
A68: Value against the price | C68: =C67/C41-1 -> -0.41080843
A69: Diagnosis rebuilds the implied EV / EBITDA | C69: =C54-C44 -> 0

Sheet Valuation
A1: Cerebras Systems Inc. (Nasdaq: CBRS) | Valuation: DCF by scenario, what the price implies, reverse DCF and football field
A2: Per-share values in USD on the diluted count. Comparables are trailing (no forward consensus available).
A4: A. DCF value per share by scenario (captured by the build) against the price
A5: Scenario | B5: Perpetuity | C5: Exit multiple | D5: Price | E5: Perpetuity vs price | H5: Source / derivation
A6: Base | B6: =Scenario_Summary!D21 -> 45.940695 | C6: =Scenario_Summary!D22 -> 70.296446 | D6: =Market_Package!B10 -> 119.31 | E6: =B6/D6-1 -> -0.61494682 | H6: Scenario_Summary
A7: Bull | B7: =Scenario_Summary!E21 -> 100.01525 | C7: =Scenario_Summary!E22 -> 176.60983 | D7: =Market_Package!B10 -> 119.31 | E7: =B7/D7-1 -> -0.16171945 | H7: Scenario_Summary
A8: Bear | B8: =Scenario_Summary!F21 -> 15.52138 | C8: =Scenario_Summary!F22 -> 23.132492 | D8: =Market_Package!B10 -> 119.31 | E8: =B8/D8-1 -> -0.86990713 | H8: Scenario_Summary
A9: Comparables: trailing EV / LTM revenue, median (same in every scenario) | B9: =Comparables!E27 -> 67.451939 | D9: =Market_Package!B10 -> 119.31 | E9: =B9/D9-1 -> -0.43464974 | H9: Comparables sheet. A ceiling-type reference: peers are far larger and profitable; Cerebras LTM EBITDA is negative, so no EBITDA multiple.
A11: B. What the price implies (active scenario)
A12: Enterprise value at the price | C12: =Market_Package!B17 -> 27133.378
A13: EV / revenue 2027E (x) | C13: =Market_Package!B20 -> 9.0131017
A14: EV / backlog at 30 Jun 2026 (x) | C14: =Market_Package!B23 -> 1.0682432
A16: C. Reverse DCF: growth shift on other cloud revenue (all years 2027E-2035E) against value per share (Base, captured)
A17: Growth shift (pp) | B17: Shift | C17: Value per share | D17: Revenue 2035E | E17: Revenue CAGR 2026E-2035E | H17: Source / derivation
A18: Shift of -20 pp | B18: -0.2 | C18: 38.636213 | D18: 5613.1641 | E18: =(D18/Forecast_3Stmt!C13)^(1/9)-1 -> 0.18768848
A19: Shift of -10 pp | B19: -0.1 | C19: 41.102474 | D19: 6414.0792 | E19: =(D19/Forecast_3Stmt!C13)^(1/9)-1 -> 0.20542122
A20: Shift of +0 pp | B20: 0 | C20: 45.940695 | D20: 7984.3391 | E20: =(D20/Forecast_3Stmt!C13)^(1/9)-1 -> 0.23511107
A21: Shift of +10 pp | B21: 0.1 | C21: 54.922737 | D21: 10903.258 | E21: =(D21/Forecast_3Stmt!C13)^(1/9)-1 -> 0.27861935
A22: Shift of +20 pp | B22: 0.2 | C22: 70.852216 | D22: 16088.591 | E22: =(D22/Forecast_3Stmt!C13)^(1/9)-1 -> 0.33510308
A23: Shift of +30 pp | B23: 0.3 | C23: 98.025311 | D23: 24946.95 | E23: =(D23/Forecast_3Stmt!C13)^(1/9)-1 -> 0.40178498
A24: Shift of +40 pp | B24: 0.4 | C24: 142.8412 | D24: 39573.404 | E24: =(D24/Forecast_3Stmt!C13)^(1/9)-1 -> 0.47552478
A25: Shift of +50 pp | B25: 0.5 | C25: 214.5975 | D25: 63011.417 | E25: =(D25/Forecast_3Stmt!C13)^(1/9)-1 -> 0.55379139
A26: Shift of +60 pp | B26: 0.6 | C26: 326.50973 | D26: 99585.845 | E26: =(D26/Forecast_3Stmt!C13)^(1/9)-1 -> 0.63485484
A27: Captured by the build | B27: MOG build 2026-10-27: Base scenario, margin shift 0
A28: Growth shift the price needs (interpolated) | C28: =IFERROR(INDEX($B$18:$B$26,MATCH(Market_Package!B10,$C$18:$C$26,1))+(Market_Package!B10-INDEX($C$18:$C$26,MATCH(Market_Package!B10,$C$18:$C$26,1)))*(INDEX($B$18:$B$26,MATCH(Market_Package!B10,$C$18:$C$26,1)+1)-INDEX($B$18:$B$26,MATCH(Market_Package!B10,$C$18:$C$26,1)))/(INDEX($C$18:$C$26,MATCH(Market_Package!B10,$C$18:$C$26,1)+1)-INDEX($C$18:$C$26,MATCH(Market_Package!B10,$C$18:$C$26,1))),"outside grid") -> 0.34749362 | H28: Linear interpolation between the two grid points around the price; Base scenario.
A29: Revenue 2035E at that shift (interpolated) | C29: =IFERROR(INDEX($D$18:$D$26,MATCH(Market_Package!B10,$C$18:$C$26,1))+(Market_Package!B10-INDEX($C$18:$C$26,MATCH(Market_Package!B10,$C$18:$C$26,1)))*(INDEX($D$18:$D$26,MATCH(Market_Package!B10,$C$18:$C$26,1)+1)-INDEX($D$18:$D$26,MATCH(Market_Package!B10,$C$18:$C$26,1)))/(INDEX($C$18:$C$26,MATCH(Market_Package!B10,$C$18:$C$26,1)+1)-INDEX($C$18:$C$26,MATCH(Market_Package!B10,$C$18:$C$26,1))),"outside grid") -> 31893.582
A30: Revenue CAGR 2026E-2035E the price needs | C30: =IFERROR((C29/Forecast_3Stmt!C13)^(1/9)-1,"outside grid") -> 0.44057338
A31: Revenue CAGR 2026E-2035E in the active scenario | C31: =(Forecast_3Stmt!L13/Forecast_3Stmt!C13)^(1/9)-1 -> 0.23511107
A33: D. Football field: value per share by method
A34: Method | B34: Low | C34: Mid | D34: High | E34: Low basis | F34: Mid basis | G34: High basis | H34: Source / derivation
A35: DCF, perpetuity growth | B35: =Scenario_Summary!F21 -> 15.52138 | C35: =Scenario_Summary!D21 -> 45.940695 | D35: =Scenario_Summary!E21 -> 100.01525 | E35: Bear | F35: Base | G35: Bull | H35: Scenario_Summary (captured)
A36: DCF, exit multiple | B36: =Scenario_Summary!F22 -> 23.132492 | C36: =Scenario_Summary!D22 -> 70.296446 | D36: =Scenario_Summary!E22 -> 176.60983 | E36: Bear | F36: Base | G36: Bull | H36: Scenario_Summary (captured)
A37: Trading since the listing | B37: =Market_Package!B41 -> 106.13 | C37: =Market_Package!B10 -> 119.31 | D37: =Market_Package!B42 -> 386.34 | E37: Low | F37: Close 27 Oct 2026 | G37: High | H37: FMP profile range; Yahoo close
A38: Comparables, trailing EV / LTM revenue | B38: =Comparables!D27 -> 60.416883 | C38: =Comparables!E27 -> 67.451939 | D38: =Comparables!F27 -> 70.970095 | E38: 25th pct | F38: Median | G38: 75th pct | H38: Comparables sheet; ceiling-type reference
A39: IPO price | B39: =Market_Package!B40 -> 185 | C39: =Market_Package!B40 -> 185 | D39: =Market_Package!B40 -> 185 | E39: IPO | F39: IPO | G39: IPO | H39: 424B4
A41: E. Probability-weighted DCF value (weights are a convention)
A42: Weight: Bear | C42: 0.25
A43: Weight: Base | C43: 0.5
A44: Weight: Bull | C44: 0.25
A45: Weighted value per share | C45: =C42*Scenario_Summary!F21+C43*Scenario_Summary!D21+C44*Scenario_Summary!E21 -> 51.854506
A46: Against the price | C46: =C45/Market_Package!B10-1 -> -0.56538005
A47: Weights add to 100% | C47: =C42+C43+C44-1 -> 0

Sheet Sensitivity
A1: Cerebras Systems Inc. (Nasdaq: CBRS) | Sensitivity of value per share (USD)
A2: Table 1 is live (formulas, active scenario). Table 2 is captured by re-running the model in the build (Base scenario).
A4: Table 1. WACC (rows) against terminal growth (columns); perpetuity method, live
A5: WACC \ terminal growth | B5: =DCF!C22+-0.01 -> 0.02 | C5: =DCF!C22+-0.005 -> 0.025 | D5: =DCF!C22+0.0 -> 0.03 | E5: =DCF!C22+0.005 -> 0.035 | F5: =DCF!C22+0.01 -> 0.04
A6: =DCF!C21+-0.02 -> 0.10727328 | B6: =((DCF!$C$14/(1+$A6)^DCF!$C$15+DCF!$D$14/(1+$A6)^DCF!$D$15+DCF!$E$14/(1+$A6)^DCF!$E$15+DCF!$F$14/(1+$A6)^DCF!$F$15+DCF!$G$14/(1+$A6)^DCF!$G$15+DCF!$H$14/(1+$A6)^DCF!$H$15+DCF!$I$14/(1+$A6)^DCF!$I$15+DCF!$J$14/(1+$A6)^DCF!$J$15+DCF!$K$14/(1+$A6)^DCF!$K$15+DCF!$L$14/(1+$A6)^DCF!$L$15+DCF!$L$8*(1+B$5)*(1-B$5/DCF!$C$23)/($A6-B$5)*(1+$A6)^0.5/(1+$A6)^DCF!$C$29)*(1+$A6)^Market_Package!$B$9+DCF!$C$36+DCF!$C$37)/DCF!$C$39 -> 52.857412 | C6: =((DCF!$C$14/(1+$A6)^DCF!$C$15+DCF!$D$14/(1+$A6)^DCF!$D$15+DCF!$E$14/(1+$A6)^DCF!$E$15+DCF!$F$14/(1+$A6)^DCF!$F$15+DCF!$G$14/(1+$A6)^DCF!$G$15+DCF!$H$14/(1+$A6)^DCF!$H$15+DCF!$I$14/(1+$A6)^DCF!$I$15+DCF!$J$14/(1+$A6)^DCF!$J$15+DCF!$K$14/(1+$A6)^DCF!$K$15+DCF!$L$14/(1+$A6)^DCF!$L$15+DCF!$L$8*(1+C$5)*(1-C$5/DCF!$C$23)/($A6-C$5)*(1+$A6)^0.5/(1+$A6)^DCF!$C$29)*(1+$A6)^Market_Package!$B$9+DCF!$C$36+DCF!$C$37)/DCF!$C$39 -> 53.601848 | D6: =((DCF!$C$14/(1+$A6)^DCF!$C$15+DCF!$D$14/(1+$A6)^DCF!$D$15+DCF!$E$14/(1+$A6)^DCF!$E$15+DCF!$F$14/(1+$A6)^DCF!$F$15+DCF!$G$14/(1+$A6)^DCF!$G$15+DCF!$H$14/(1+$A6)^DCF!$H$15+DCF!$I$14/(1+$A6)^DCF!$I$15+DCF!$J$14/(1+$A6)^DCF!$J$15+DCF!$K$14/(1+$A6)^DCF!$K$15+DCF!$L$14/(1+$A6)^DCF!$L$15+DCF!$L$8*(1+D$5)*(1-D$5/DCF!$C$23)/($A6-D$5)*(1+$A6)^0.5/(1+$A6)^DCF!$C$29)*(1+$A6)^Market_Package!$B$9+DCF!$C$36+DCF!$C$37)/DCF!$C$39 -> 54.436327 | E6: =((DCF!$C$14/(1+$A6)^DCF!$C$15+DCF!$D$14/(1+$A6)^DCF!$D$15+DCF!$E$14/(1+$A6)^DCF!$E$15+DCF!$F$14/(1+$A6)^DCF!$F$15+DCF!$G$14/(1+$A6)^DCF!$G$15+DCF!$H$14/(1+$A6)^DCF!$H$15+DCF!$I$14/(1+$A6)^DCF!$I$15+DCF!$J$14/(1+$A6)^DCF!$J$15+DCF!$K$14/(1+$A6)^DCF!$K$15+DCF!$L$14/(1+$A6)^DCF!$L$15+DCF!$L$8*(1+E$5)*(1-E$5/DCF!$C$23)/($A6-E$5)*(1+$A6)^0.5/(1+$A6)^DCF!$C$29)*(1+$A6)^Market_Package!$B$9+DCF!$C$36+DCF!$C$37)/DCF!$C$39 -> 55.379534 | F6: =((DCF!$C$14/(1+$A6)^DCF!$C$15+DCF!$D$14/(1+$A6)^DCF!$D$15+DCF!$E$14/(1+$A6)^DCF!$E$15+DCF!$F$14/(1+$A6)^DCF!$F$15+DCF!$G$14/(1+$A6)^DCF!$G$15+DCF!$H$14/(1+$A6)^DCF!$H$15+DCF!$I$14/(1+$A6)^DCF!$I$15+DCF!$J$14/(1+$A6)^DCF!$J$15+DCF!$K$14/(1+$A6)^DCF!$K$15+DCF!$L$14/(1+$A6)^DCF!$L$15+DCF!$L$8*(1+F$5)*(1-F$5/DCF!$C$23)/($A6-F$5)*(1+$A6)^0.5/(1+$A6)^DCF!$C$29)*(1+$A6)^Market_Package!$B$9+DCF!$C$36+DCF!$C$37)/DCF!$C$39 -> 56.455713
