Workbook

Sheet 00_Cover
A1: TMUS | 9-of-10 Regated Public-Company Model | B1: TMUS | 9-of-10 Regated Public-Company Model | C1: TMUS | 9-of-10 Regated Public-Company Model | D1: TMUS | 9-of-10 Regated Public-Company Model | E1: TMUS | 9-of-10 Regated Public-Company Model | F1: TMUS | 9-of-10 Regated Public-Company Model | G1: TMUS | 9-of-10 Regated Public-Company Model | H1: TMUS | 9-of-10 Regated Public-Company Model
A2: T-Mobile US, Inc. | Telecommunications | Controlled artifact-tool rebuild; independent certification remains outside owner scope. | B2: T-Mobile US, Inc. | Telecommunications | Controlled artifact-tool rebuild; independent certification remains outside owner scope. | C2: T-Mobile US, Inc. | Telecommunications | Controlled artifact-tool rebuild; independent certification remains outside owner scope. | D2: T-Mobile US, Inc. | Telecommunications | Controlled artifact-tool rebuild; independent certification remains outside owner scope. | E2: T-Mobile US, Inc. | Telecommunications | Controlled artifact-tool rebuild; independent certification remains outside owner scope. | F2: T-Mobile US, Inc. | Telecommunications | Controlled artifact-tool rebuild; independent certification remains outside owner scope. | G2: T-Mobile US, Inc. | Telecommunications | Controlled artifact-tool rebuild; independent certification remains outside owner scope. | H2: T-Mobile US, Inc. | Telecommunications | Controlled artifact-tool rebuild; independent certification remains outside owner scope.
A4: Company | B4: T-Mobile US, Inc.
A5: Ticker | B5: TMUS
A6: Model as of | B6: 2025-12-31
A7: Currency | B7: USD millions unless stated
A8: Forecast horizon | B8: 2026E-2030E
A9: Active case | B9: =Assumptions!B4 -> Base
A10: Overall status | B10: =Checks!B4 -> PASS
A11: Primary valuation | B11: Unlevered FCFF DCF
A12: Market-price comparison | B12: Omitted — no independently refreshed exact-dated quote in this owner lane
A13: Debt definition | B13: LongTermDebt + ShortTermBorrowings + FinanceLeaseLiability; all carrying values, USD mm.
A14: Cash policy | B14: Net debt deducts cash and cash equivalents only; restricted cash and non-operating investments are excluded.
A15: Acquisition / perimeter | B15: 2025 customer/revenue perimeter includes UScellular, Metronet and Lumos acquisitions; 2024 includes Ka'ena. Forecast cases normalize acquisition-heavy growth.
A16: Known limitation | B16: Reported postpaid ARPA is per account while churn is postpaid phone churn; the driver model therefore uses phone customers/ARPU for phone service revenue and treats other postpaid revenue separately.
A19: Investor view: begin with operating drivers and the debt bridge, then assess valuation only after Checks!B4 passes. Gate_9of10 is owner preflight, not independent certification. | B19: Investor view: begin with operating drivers and the debt bridge, then assess valuation only after Checks!B4 passes. Gate_9of10 is owner preflight, not independent certification. | C19: Investor view: begin with operating drivers and the debt bridge, then assess valuation only after Checks!B4 passes. Gate_9of10 is owner preflight, not independent certification. | D19: Investor view: begin with operating drivers and the debt bridge, then assess valuation only after Checks!B4 passes. Gate_9of10 is owner preflight, not independent certification. | E19: Investor view: begin with operating drivers and the debt bridge, then assess valuation only after Checks!B4 passes. Gate_9of10 is owner preflight, not independent certification. | F19: Investor view: begin with operating drivers and the debt bridge, then assess valuation only after Checks!B4 passes. Gate_9of10 is owner preflight, not independent certification. | G19: Investor view: begin with operating drivers and the debt bridge, then assess valuation only after Checks!B4 passes. Gate_9of10 is owner preflight, not independent certification. | H19: Investor view: begin with operating drivers and the debt bridge, then assess valuation only after Checks!B4 passes. Gate_9of10 is owner preflight, not independent certification.

Sheet Sources
A1: TMUS | Source and Transformation Ledger | B1: TMUS | Source and Transformation Ledger | C1: TMUS | Source and Transformation Ledger | D1: TMUS | Source and Transformation Ledger | E1: TMUS | Source and Transformation Ledger | F1: TMUS | Source and Transformation Ledger | G1: TMUS | Source and Transformation Ledger | H1: TMUS | Source and Transformation Ledger | I1: TMUS | Source and Transformation Ledger | J1: TMUS | Source and Transformation Ledger | K1: TMUS | Source and Transformation Ledger | L1: TMUS | Source and Transformation Ledger | M1: TMUS | Source and Transformation Ledger | N1: TMUS | Source and Transformation Ledger | O1: TMUS | Source and Transformation Ledger | P1: TMUS | Source and Transformation Ledger | Q1: TMUS | Source and Transformation Ledger
A2: Every material input identifies target, metric, period, filing metadata, retrieval date, exact URL, scale/sign transform and perimeter note. | B2: Every material input identifies target, metric, period, filing metadata, retrieval date, exact URL, scale/sign transform and perimeter note. | C2: Every material input identifies target, metric, period, filing metadata, retrieval date, exact URL, scale/sign transform and perimeter note. | D2: Every material input identifies target, metric, period, filing metadata, retrieval date, exact URL, scale/sign transform and perimeter note. | E2: Every material input identifies target, metric, period, filing metadata, retrieval date, exact URL, scale/sign transform and perimeter note. | F2: Every material input identifies target, metric, period, filing metadata, retrieval date, exact URL, scale/sign transform and perimeter note. | G2: Every material input identifies target, metric, period, filing metadata, retrieval date, exact URL, scale/sign transform and perimeter note. | H2: Every material input identifies target, metric, period, filing metadata, retrieval date, exact URL, scale/sign transform and perimeter note. | I2: Every material input identifies target, metric, period, filing metadata, retrieval date, exact URL, scale/sign transform and perimeter note. | J2: Every material input identifies target, metric, period, filing metadata, retrieval date, exact URL, scale/sign transform and perimeter note. | K2: Every material input identifies target, metric, period, filing metadata, retrieval date, exact URL, scale/sign transform and perimeter note. | L2: Every material input identifies target, metric, period, filing metadata, retrieval date, exact URL, scale/sign transform and perimeter note. | M2: Every material input identifies target, metric, period, filing metadata, retrieval date, exact URL, scale/sign transform and perimeter note. | N2: Every material input identifies target, metric, period, filing metadata, retrieval date, exact URL, scale/sign transform and perimeter note. | O2: Every material input identifies target, metric, period, filing metadata, retrieval date, exact URL, scale/sign transform and perimeter note. | P2: Every material input identifies target, metric, period, filing metadata, retrieval date, exact URL, scale/sign transform and perimeter note. | Q2: Every material input identifies target, metric, period, filing metadata, retrieval date, exact URL, scale/sign transform and perimeter note.
A4: Source ID | B4: Target | C4: Metric | D4: Value | E4: Units | F4: Period start | G4: Period end / as-of | H4: Taxonomy / tag | I4: Form | J4: Filed | K4: Accession | L4: Source title | M4: Source class | N4: Retrieved | O4: Exact URL | P4: Transform | Q4: Notes / perimeter
A5: SRC-001 | B5: Historical!C5 | C5: Revenue | D5: 78558 | E5: USD mm | F5: 2023-01-01 | G5: 2023-12-31 | H5: us-gaap:RevenueFromContractWithCustomerExcludingAssessedTax | I5: 10-K | J5: 2026-02-11 | K5: 0001283699-26-000010 | L5: T-Mobile US, Inc. Form 10-K / SEC Company Facts | M5: Primary — SEC filed | N5: 2026-07-16 | O5: https://data.sec.gov/api/xbrl/companyfacts/CIK0001283699.json | P5: Filed USD divided by 1,000,000; sign preserved | Q5: 2025 customer/revenue perimeter includes UScellular, Metronet and Lumos acquisitions; 2024 includes Ka'ena. Forecast cases normalize acquisition-heavy growth.
A6: SRC-002 | B6: Historical!D5 | C6: Revenue | D6: 81400 | E6: USD mm | F6: 2024-01-01 | G6: 2024-12-31 | H6: us-gaap:RevenueFromContractWithCustomerExcludingAssessedTax | I6: 10-K | J6: 2026-02-11 | K6: 0001283699-26-000010 | L6: T-Mobile US, Inc. Form 10-K / SEC Company Facts | M6: Primary — SEC filed | N6: 2026-07-16 | O6: https://data.sec.gov/api/xbrl/companyfacts/CIK0001283699.json | P6: Filed USD divided by 1,000,000; sign preserved | Q6: 2025 customer/revenue perimeter includes UScellular, Metronet and Lumos acquisitions; 2024 includes Ka'ena. Forecast cases normalize acquisition-heavy growth.
A7: SRC-003 | B7: Historical!E5 | C7: Revenue | D7: 88309 | E7: USD mm | F7: 2025-01-01 | G7: 2025-12-31 | H7: us-gaap:RevenueFromContractWithCustomerExcludingAssessedTax | I7: 10-K | J7: 2026-02-11 | K7: 0001283699-26-000010 | L7: T-Mobile US, Inc. Form 10-K / SEC Company Facts | M7: Primary — SEC filed | N7: 2026-07-16 | O7: https://data.sec.gov/api/xbrl/companyfacts/CIK0001283699.json | P7: Filed USD divided by 1,000,000; sign preserved | Q7: 2025 customer/revenue perimeter includes UScellular, Metronet and Lumos acquisitions; 2024 includes Ka'ena. Forecast cases normalize acquisition-heavy growth.
A8: SRC-004 | B8: Historical!C6 | C8: Operating income (EBIT) | D8: 14266 | E8: USD mm | F8: 2023-01-01 | G8: 2023-12-31 | H8: us-gaap:OperatingIncomeLoss | I8: 10-K | J8: 2026-02-11 | K8: 0001283699-26-000010 | L8: T-Mobile US, Inc. Form 10-K / SEC Company Facts | M8: Primary — SEC filed | N8: 2026-07-16 | O8: https://data.sec.gov/api/xbrl/companyfacts/CIK0001283699.json | P8: Filed USD divided by 1,000,000; sign preserved | Q8: 2025 customer/revenue perimeter includes UScellular, Metronet and Lumos acquisitions; 2024 includes Ka'ena. Forecast cases normalize acquisition-heavy growth.
A9: SRC-005 | B9: Historical!D6 | C9: Operating income (EBIT) | D9: 18010 | E9: USD mm | F9: 2024-01-01 | G9: 2024-12-31 | H9: us-gaap:OperatingIncomeLoss | I9: 10-K | J9: 2026-02-11 | K9: 0001283699-26-000010 | L9: T-Mobile US, Inc. Form 10-K / SEC Company Facts | M9: Primary — SEC filed | N9: 2026-07-16 | O9: https://data.sec.gov/api/xbrl/companyfacts/CIK0001283699.json | P9: Filed USD divided by 1,000,000; sign preserved | Q9: 2025 customer/revenue perimeter includes UScellular, Metronet and Lumos acquisitions; 2024 includes Ka'ena. Forecast cases normalize acquisition-heavy growth.
A10: SRC-006 | B10: Historical!E6 | C10: Operating income (EBIT) | D10: 18279 | E10: USD mm | F10: 2025-01-01 | G10: 2025-12-31 | H10: us-gaap:OperatingIncomeLoss | I10: 10-K | J10: 2026-02-11 | K10: 0001283699-26-000010 | L10: T-Mobile US, Inc. Form 10-K / SEC Company Facts | M10: Primary — SEC filed | N10: 2026-07-16 | O10: https://data.sec.gov/api/xbrl/companyfacts/CIK0001283699.json | P10: Filed USD divided by 1,000,000; sign preserved | Q10: 2025 customer/revenue perimeter includes UScellular, Metronet and Lumos acquisitions; 2024 includes Ka'ena. Forecast cases normalize acquisition-heavy growth.
A11: SRC-007 | B11: Historical!C7 | C11: Net income | D11: 8317 | E11: USD mm | F11: 2023-01-01 | G11: 2023-12-31 | H11: us-gaap:NetIncomeLoss | I11: 10-K | J11: 2026-02-11 | K11: 0001283699-26-000010 | L11: T-Mobile US, Inc. Form 10-K / SEC Company Facts | M11: Primary — SEC filed | N11: 2026-07-16 | O11: https://data.sec.gov/api/xbrl/companyfacts/CIK0001283699.json | P11: Filed USD divided by 1,000,000; sign preserved | Q11: 2025 customer/revenue perimeter includes UScellular, Metronet and Lumos acquisitions; 2024 includes Ka'ena. Forecast cases normalize acquisition-heavy growth.
A12: SRC-008 | B12: Historical!D7 | C12: Net income | D12: 11339 | E12: USD mm | F12: 2024-01-01 | G12: 2024-12-31 | H12: us-gaap:NetIncomeLoss | I12: 10-K | J12: 2026-02-11 | K12: 0001283699-26-000010 | L12: T-Mobile US, Inc. Form 10-K / SEC Company Facts | M12: Primary — SEC filed | N12: 2026-07-16 | O12: https://data.sec.gov/api/xbrl/companyfacts/CIK0001283699.json | P12: Filed USD divided by 1,000,000; sign preserved | Q12: 2025 customer/revenue perimeter includes UScellular, Metronet and Lumos acquisitions; 2024 includes Ka'ena. Forecast cases normalize acquisition-heavy growth.
A13: SRC-009 | B13: Historical!E7 | C13: Net income | D13: 10992 | E13: USD mm | F13: 2025-01-01 | G13: 2025-12-31 | H13: us-gaap:NetIncomeLoss | I13: 10-K | J13: 2026-02-11 | K13: 0001283699-26-000010 | L13: T-Mobile US, Inc. Form 10-K / SEC Company Facts | M13: Primary — SEC filed | N13: 2026-07-16 | O13: https://data.sec.gov/api/xbrl/companyfacts/CIK0001283699.json | P13: Filed USD divided by 1,000,000; sign preserved | Q13: 2025 customer/revenue perimeter includes UScellular, Metronet and Lumos acquisitions; 2024 includes Ka'ena. Forecast cases normalize acquisition-heavy growth.
A14: SRC-010 | B14: Historical!C8 | C14: Cash from operations | D14: 18559 | E14: USD mm | F14: 2023-01-01 | G14: 2023-12-31 | H14: us-gaap:NetCashProvidedByUsedInOperatingActivities | I14: 10-K | J14: 2026-02-11 | K14: 0001283699-26-000010 | L14: T-Mobile US, Inc. Form 10-K / SEC Company Facts | M14: Primary — SEC filed | N14: 2026-07-16 | O14: https://data.sec.gov/api/xbrl/companyfacts/CIK0001283699.json | P14: Filed USD divided by 1,000,000; sign preserved | Q14: 2025 customer/revenue perimeter includes UScellular, Metronet and Lumos acquisitions; 2024 includes Ka'ena. Forecast cases normalize acquisition-heavy growth.
A15: SRC-011 | B15: Historical!D8 | C15: Cash from operations | D15: 22293 | E15: USD mm | F15: 2024-01-01 | G15: 2024-12-31 | H15: us-gaap:NetCashProvidedByUsedInOperatingActivities | I15: 10-K | J15: 2026-02-11 | K15: 0001283699-26-000010 | L15: T-Mobile US, Inc. Form 10-K / SEC Company Facts | M15: Primary — SEC filed | N15: 2026-07-16 | O15: https://data.sec.gov/api/xbrl/companyfacts/CIK0001283699.json | P15: Filed USD divided by 1,000,000; sign preserved | Q15: 2025 customer/revenue perimeter includes UScellular, Metronet and Lumos acquisitions; 2024 includes Ka'ena. Forecast cases normalize acquisition-heavy growth.
A16: SRC-012 | B16: Historical!E8 | C16: Cash from operations | D16: 27950 | E16: USD mm | F16: 2025-01-01 | G16: 2025-12-31 | H16: us-gaap:NetCashProvidedByUsedInOperatingActivities | I16: 10-K | J16: 2026-02-11 | K16: 0001283699-26-000010 | L16: T-Mobile US, Inc. Form 10-K / SEC Company Facts | M16: Primary — SEC filed | N16: 2026-07-16 | O16: https://data.sec.gov/api/xbrl/companyfacts/CIK0001283699.json | P16: Filed USD divided by 1,000,000; sign preserved | Q16: 2025 customer/revenue perimeter includes UScellular, Metronet and Lumos acquisitions; 2024 includes Ka'ena. Forecast cases normalize acquisition-heavy growth.
... A100: SRC-096 | B100: Sector_KPIs!E18 | C100: Adjusted EBITDA 2025 | D100: 33937 | E100: USD mm | F100: N/A | G100: 2025-12-31 | H100: MD&A — Selected financial data / Non-GAAP Financial Measures — row: Adjusted EBITDA — column 2025 | I100: 10-K | J100: 2026-02-11 | K100: 0001283699-26-000010 | L100: T-Mobile US, Inc. 2025 Form 10-K | M100: Primary — SEC filed | N100: 2026-07-16 | O100: https://www.sec.gov/Archives/edgar/data/1283699/000128369926000010/tmus-20251231.htm | P100: Transcribed from filed table; USD values in millions unless stated | Q100: 2025 customer/revenue perimeter includes UScellular, Metronet and Lumos acquisitions; 2024 includes Ka'ena. Forecast cases normalize acquisition-heavy growth.
A101: SRC-097 | B101: Historical / Valuation | C101: Debt definition | D101: LongTermDebt + ShortTermBorrowings + FinanceLeaseLiability; all carrying values, USD mm. | E101: Policy | F101: N/A | G101: 2025-12-31 | H101: Accounting policy | I101: 10-K | J101: 2026-02-11 | K101: 0001283699-26-000010 | L101: T-Mobile US, Inc. 2025 Form 10-K | M101: Primary — SEC filed | N101: 2026-07-16 | O101: https://www.sec.gov/Archives/edgar/data/1283699/000128369926000010/tmus-20251231.htm | P101: Explicit sum of filed debt components | Q101: Net debt deducts cash and cash equivalents only; restricted cash and non-operating investments are excluded.
A102: SRC-098 | B102: Entire model | C102: Acquisition / perimeter note | D102: 2025 customer/revenue perimeter includes UScellular, Metronet and Lumos acquisitions; 2024 includes Ka'ena. Forecast cases normalize acquisition-heavy growth. | E102: Policy | F102: N/A | G102: 2025-12-31 | H102: Perimeter policy | I102: 10-K | J102: 2026-02-11 | K102: 0001283699-26-000010 | L102: T-Mobile US, Inc. 2025 Form 10-K | M102: Primary — SEC filed | N102: 2026-07-16 | O102: https://www.sec.gov/Archives/edgar/data/1283699/000128369926000010/tmus-20251231.htm | P102: No current-FX restatement; filed values preserved | Q102: Reported postpaid ARPA is per account while churn is postpaid phone churn; the driver model therefore uses phone customers/ARPU for phone service revenue and treats other postpaid revenue separately.

Sheet Historical
A1: TMUS | Historical Financials | B1: TMUS | Historical Financials | C1: TMUS | Historical Financials | D1: TMUS | Historical Financials | E1: TMUS | Historical Financials | F1: TMUS | Historical Financials | G1: TMUS | Historical Financials | H1: TMUS | Historical Financials | I1: TMUS | Historical Financials
A2: Filed values and explicit debt bridge. USD in millions except per-share and share-count data. | B2: Filed values and explicit debt bridge. USD in millions except per-share and share-count data. | C2: Filed values and explicit debt bridge. USD in millions except per-share and share-count data. | D2: Filed values and explicit debt bridge. USD in millions except per-share and share-count data. | E2: Filed values and explicit debt bridge. USD in millions except per-share and share-count data. | F2: Filed values and explicit debt bridge. USD in millions except per-share and share-count data. | G2: Filed values and explicit debt bridge. USD in millions except per-share and share-count data. | H2: Filed values and explicit debt bridge. USD in millions except per-share and share-count data. | I2: Filed values and explicit debt bridge. USD in millions except per-share and share-count data.
A4: Metric | B4: Units | C4: 2023A | D4: 2024A | E4: 2025A | F4: Source definition | G4: Source IDs | H4: Policy / transform | I4: Quality
A5: Revenue | B5: USD mm | C5: 78558 | D5: 81400 | E5: 88309 | F5: SEC Company Facts / filed 10-K; RevenueFromContractWithCustomerExcludingAssessedTax or Revenues or SalesRevenueNet | G5: SRC-001, SRC-002, SRC-003 | H5: Filed USD; no FX restatement; sign preserved. | I5: Filed
A6: Operating income (EBIT) | B6: USD mm | C6: 14266 | D6: 18010 | E6: 18279 | F6: SEC Company Facts / filed 10-K; OperatingIncomeLoss | G6: SRC-004, SRC-005, SRC-006 | H6: Filed USD; no FX restatement; sign preserved. | I6: Filed
A7: Net income | B7: USD mm | C7: 8317 | D7: 11339 | E7: 10992 | F7: SEC Company Facts / filed 10-K; NetIncomeLoss or ProfitLoss | G7: SRC-007, SRC-008, SRC-009 | H7: Filed USD; no FX restatement; sign preserved. | I7: Filed
A8: Cash from operations | B8: USD mm | C8: 18559 | D8: 22293 | E8: 27950 | F8: SEC Company Facts / filed 10-K; NetCashProvidedByUsedInOperatingActivities | G8: SRC-010, SRC-011, SRC-012 | H8: Filed USD; no FX restatement; sign preserved. | I8: Filed
A9: Depreciation & amortization | B9: USD mm | C9: 12818 | D9: 12919 | E9: 13508 | F9: SEC Company Facts / filed 10-K; DepreciationDepletionAndAmortization or DepreciationDepletionAndAmortization or DepreciationAndAmortization | G9: SRC-013, SRC-014, SRC-015 | H9: Filed USD; no FX restatement; sign preserved. | I9: Filed
A10: Cash capex / P&E additions | B10: USD mm | C10: 9801 | D10: 8840 | E10: 9955 | F10: SEC Company Facts / filed 10-K; PaymentsToAcquirePropertyPlantAndEquipment or PaymentsForAdditionsToPropertyPlantAndEquipment | G10: SRC-016, SRC-017, SRC-018 | H10: Filed USD; no FX restatement; sign preserved. | I10: Filed
A11: Total assets | B11: USD mm | C11: 207682 | D11: 208035 | E11: 219237 | F11: SEC Company Facts / filed 10-K; Assets | G11: SRC-019, SRC-020, SRC-021 | H11: Filed USD; no FX restatement; sign preserved. | I11: Filed
A12: Stockholders' equity | B12: USD mm | C12: 64715 | D12: 61741 | E12: 59203 | F12: SEC Company Facts / filed 10-K; StockholdersEquity or StockholdersEquityIncludingPortionAttributableToNoncontrollingInterest | G12: SRC-022, SRC-023, SRC-024 | H12: Filed USD; no FX restatement; sign preserved. | I12: Filed
A13: Cash & cash equivalents | B13: USD mm | C13: 5135 | D13: 5409 | E13: 5598 | F13: SEC Company Facts / filed 10-K; CashAndCashEquivalentsAtCarryingValue or CashCashEquivalentsRestrictedCashAndRestrictedCashEquivalents | G13: SRC-025, SRC-026, SRC-027 | H13: Filed USD; no FX restatement; sign preserved. | I13: Filed
A14: Long-term debt | B14: USD mm | C14: 75018 | D14: 78265 | E14: 86282 | F14: SEC Company Facts / filed 10-K; LongTermDebt or LongTermDebtAndCapitalLeaseObligationsIncludingCurrentMaturities | G14: SRC-028, SRC-029, SRC-030 | H14: LongTermDebt + ShortTermBorrowings + FinanceLeaseLiability; all carrying values, USD mm. | I14: Filed
A15: Short-term borrowings | B15: USD mm | C15: 3619 | D15: 4068 | E15: 5135 | F15: SEC Company Facts / filed 10-K; ShortTermBorrowings or CommercialPaper | G15: SRC-031, SRC-032, SRC-033 | H15: LongTermDebt + ShortTermBorrowings + FinanceLeaseLiability; all carrying values, USD mm. | I15: Filed
A16: Finance lease liability | B16: USD mm | C16: 2496 | D16: 2326 | E16: 2270 | F16: SEC Company Facts / filed 10-K; FinanceLeaseLiability | G16: SRC-034, SRC-035, SRC-036 | H16: LongTermDebt + ShortTermBorrowings + FinanceLeaseLiability; all carrying values, USD mm. | I16: Filed
A17: Diluted weighted-average shares | B17: mm shares | C17: 1200.2863 | D17: 1173.2139 | E17: 1131.0763 | F17: SEC Company Facts / filed 10-K; WeightedAverageNumberOfDilutedSharesOutstanding | G17: SRC-037, SRC-038, SRC-039 | H17: Filed USD; no FX restatement; sign preserved. | I17: Filed
A18: Total debt | B18: USD mm | C18: =C14+C15+C16 -> 81133 | D18: =D14+D15+D16 -> 84659 | E18: =E14+E15+E16 -> 93687 | F18: LongTermDebt + ShortTermBorrowings + FinanceLeaseLiability; all carrying values, USD mm. | G18: Formula | H18: LongTermDebt + ShortTermBorrowings + FinanceLeaseLiability; all carrying values, USD mm. | I18: Modeled
A19: Net debt | B19: USD mm | C19: =C18-C13 -> 75998 | D19: =D18-D13 -> 79250 | E19: =E18-E13 -> 88089 | F19: Total debt less cash and cash equivalents | G19: Formula | H19: Net debt deducts cash and cash equivalents only; restricted cash and non-operating investments are excluded. | I19: Modeled
A21: Debt policy | B21: LongTermDebt + ShortTermBorrowings + FinanceLeaseLiability; all carrying values, USD mm.
A22: Cash policy | B22: Net debt deducts cash and cash equivalents only; restricted cash and non-operating investments are excluded.
A23: Perimeter | B23: 2025 customer/revenue perimeter includes UScellular, Metronet and Lumos acquisitions; 2024 includes Ka'ena. Forecast cases normalize acquisition-heavy growth.

Sheet Assumptions
A1: TMUS | Scenario Assumptions | B1: TMUS | Scenario Assumptions | C1: TMUS | Scenario Assumptions | D1: TMUS | Scenario Assumptions | E1: TMUS | Scenario Assumptions | F1: TMUS | Scenario Assumptions | G1: TMUS | Scenario Assumptions
A2: Blue cells are inputs; green cells are links/formulas. Selector 1=Base, 2=Bull, 3=Bear. | B2: Blue cells are inputs; green cells are links/formulas. Selector 1=Base, 2=Bull, 3=Bear. | C2: Blue cells are inputs; green cells are links/formulas. Selector 1=Base, 2=Bull, 3=Bear. | D2: Blue cells are inputs; green cells are links/formulas. Selector 1=Base, 2=Bull, 3=Bear. | E2: Blue cells are inputs; green cells are links/formulas. Selector 1=Base, 2=Bull, 3=Bear. | F2: Blue cells are inputs; green cells are links/formulas. Selector 1=Base, 2=Bull, 3=Bear. | G2: Blue cells are inputs; green cells are links/formulas. Selector 1=Base, 2=Bull, 3=Bear.
A3: Scenario selector | B3: 1
A4: Active case | B4: =CHOOSE(B3,"Base","Bull","Bear") -> Base
A6: Driver | B6: Units | C6: Bear | D6: Base | E6: Bull | F6: Active | G6: Rationale / calibration
A7: Gross phone adds rate | B7: % / year | C7: 0.11 | D7: 0.135 | E7: 0.16 | F7: =CHOOSE($B$3,D7,E7,C7) -> 0.135 | G7: Gross-add assumption calibrated so churn produces normalized postpaid phone growth after 2025 acquisition effects.
A8: Postpaid phone churn | B8: % / month | C8: 0.0105 | D8: 0.0093 | E8: 0.0085 | F8: =CHOOSE($B$3,D8,E8,C8) -> 0.0093 | G8: 2025 reported churn was 0.93%; cases frame retention risk.
A9: Postpaid phone ARPU growth | B9: % / year | C9: 0 | D9: 0.02 | E9: 0.035 | F9: =CHOOSE($B$3,D9,E9,C9) -> 0.02 | G9: 2025 reported ARPU growth was 2%.
A10: Other postpaid service revenue growth | B10: % / year | C10: -0.01 | D10: 0.02 | E10: 0.04 | F10: =CHOOSE($B$3,D10,E10,C10) -> 0.02 | G10: Captures broadband, connected-device and fee revenue outside the phone ARPU proxy.
A11: Non-postpaid service revenue growth | B11: % / year | C11: -0.02 | D11: 0.01 | E11: 0.03 | F11: =CHOOSE($B$3,D11,E11,C11) -> 0.01 | G11: Prepaid plus wholesale/other service revenue case.
A12: Equipment/other revenue as % service revenue | B12: % | C12: 0.2 | D12: 0.22 | E12: 0.24 | F12: =CHOOSE($B$3,D12,E12,C12) -> 0.22 | G12: Anchored to 2025 equipment revenue and service revenue.
A13: Adjusted EBITDA margin on service revenue | B13: % | C13: 0.45 | D13: 0.48 | E13: 0.5 | F13: =CHOOSE($B$3,D13,E13,C13) -> 0.48 | G13: 2025 reported Adjusted EBITDA margin was 48%.
A14: D&A as % total revenue | B14: % | C14: 0.15 | D14: 0.153 | E14: 0.155 | F14: =CHOOSE($B$3,D14,E14,C14) -> 0.153 | G14: Anchored to 2025 SEC D&A / revenue.
A15: Cash capex as % total revenue | B15: % | C15: 0.13 | D15: 0.113 | E15: 0.105 | F15: =CHOOSE($B$3,D15,E15,C15) -> 0.113 | G15: Anchored to 2025 cash purchases of P&E.
A16: Cash tax rate | B16: % | C16: 0.26 | D16: 0.24 | E16: 0.22 | F16: =CHOOSE($B$3,D16,E16,C16) -> 0.24 | G16: Normalized cash-tax assumption.
A17: NWC investment / change in revenue | B17: % | C17: 0.02 | D17: 0.01 | E17: 0.005 | F17: =CHOOSE($B$3,D17,E17,C17) -> 0.01 | G17: Working-capital sensitivity assumption.
A18: Annual net debt reduction | B18: % | C18: 0.02 | D18: 0.05 | E18: 0.08 | F18: =CHOOSE($B$3,D18,E18,C18) -> 0.05 | G18: Visible leverage-path assumption; no residual cash plug.
... A21: Exit EV / Adjusted EBITDA | B21: x | C21: 6.5 | D21: 7 | E21: 7.5 | F21: =CHOOSE($B$3,D21,E21,C21) -> 7 | G21: Telecom DCF cross-check multiple.
A23: Debt definition | B23: LongTermDebt + ShortTermBorrowings + FinanceLeaseLiability; all carrying values, USD mm.
A24: Cash policy | B24: Net debt deducts cash and cash equivalents only; restricted cash and non-operating investments are excluded.
A25: Known limitation | B25: Reported postpaid ARPA is per account while churn is postpaid phone churn; the driver model therefore uses phone customers/ARPU for phone service revenue and treats other postpaid revenue separately.

Sheet Forecast
A1: TMUS | Integrated Forecast | B1: TMUS | Integrated Forecast | C1: TMUS | Integrated Forecast | D1: TMUS | Integrated Forecast | E1: TMUS | Integrated Forecast | F1: TMUS | Integrated Forecast | G1: TMUS | Integrated Forecast
A2: Operating drivers flow from Sector_KPIs into FCFF and DCF valuation. | B2: Operating drivers flow from Sector_KPIs into FCFF and DCF valuation. | C2: Operating drivers flow from Sector_KPIs into FCFF and DCF valuation. | D2: Operating drivers flow from Sector_KPIs into FCFF and DCF valuation. | E2: Operating drivers flow from Sector_KPIs into FCFF and DCF valuation. | F2: Operating drivers flow from Sector_KPIs into FCFF and DCF valuation. | G2: Operating drivers flow from Sector_KPIs into FCFF and DCF valuation.
A4: Metric | B4: Units | C4: 2026E | D4: 2027E | E4: 2028E | F4: 2029E | G4: 2030E
A5: Revenue | B5: USD mm | C5: =Sector_KPIs!F16 -> 89323.279 | D5: =Sector_KPIs!G16 -> 92499.571 | E5: =Sector_KPIs!H16 -> 95805.938 | F5: =Sector_KPIs!I16 -> 99247.958 | G5: =Sector_KPIs!J16 -> 102831.45
A6: Adjusted EBITDA | B6: USD mm | C6: =Sector_KPIs!F18 -> 35143.585 | D6: =Sector_KPIs!G18 -> 36393.274 | E6: =Sector_KPIs!H18 -> 37694.139 | F6: =Sector_KPIs!I18 -> 39048.377 | G6: =Sector_KPIs!J18 -> 40458.275
A7: Depreciation & amortization | B7: USD mm | C7: =C5*Assumptions!$F$14 -> 13666.462 | D7: =D5*Assumptions!$F$14 -> 14152.434 | E7: =E5*Assumptions!$F$14 -> 14658.308 | F7: =F5*Assumptions!$F$14 -> 15184.938 | G7: =G5*Assumptions!$F$14 -> 15733.212
A8: EBIT | B8: USD mm | C8: =C6-C7 -> 21477.124 | D8: =D6-D7 -> 22240.839 | E8: =E6-E7 -> 23035.831 | F8: =F6-F7 -> 23863.439 | G8: =G6-G7 -> 24725.064
A9: Cash taxes | B9: USD mm | C9: =MAX(0,C8*Assumptions!$F$16) -> 5154.5097 | D9: =MAX(0,D8*Assumptions!$F$16) -> 5337.8014 | E9: =MAX(0,E8*Assumptions!$F$16) -> 5528.5994 | F9: =MAX(0,F8*Assumptions!$F$16) -> 5727.2254 | G9: =MAX(0,G8*Assumptions!$F$16) -> 5934.0153
A10: NOPAT | B10: USD mm | C10: =C8-C9 -> 16322.614 | D10: =D8-D9 -> 16903.038 | E10: =E8-E9 -> 17507.232 | F10: =F8-F9 -> 18136.214 | G10: =G8-G9 -> 18791.048
A11: D&A add-back | B11: USD mm | C11: =C7 -> 13666.462 | D11: =D7 -> 14152.434 | E11: =E7 -> 14658.308 | F11: =F7 -> 15184.938 | G11: =G7 -> 15733.212
A12: Capital expenditures | B12: USD mm | C12: =Sector_KPIs!F19 -> 10093.531 | D12: =Sector_KPIs!G19 -> 10452.451 | E12: =Sector_KPIs!H19 -> 10826.071 | F12: =Sector_KPIs!I19 -> 11215.019 | G12: =Sector_KPIs!J19 -> 11619.954
A13: Change in net working capital | B13: USD mm | C13: =MAX(0,(Sector_KPIs!F16-Sector_KPIs!E16)*Assumptions!$F$17) -> 10.142792 | D13: =MAX(0,(Sector_KPIs!G16-Sector_KPIs!F16)*Assumptions!$F$17) -> 31.762913 | E13: =MAX(0,(Sector_KPIs!H16-Sector_KPIs!G16)*Assumptions!$F$17) -> 33.063673 | F13: =MAX(0,(Sector_KPIs!I16-Sector_KPIs!H16)*Assumptions!$F$17) -> 34.4202 | G13: =MAX(0,(Sector_KPIs!J16-Sector_KPIs!I16)*Assumptions!$F$17) -> 35.834921
A14: FCFF | B14: USD mm | C14: =C10+C11-C12-C13 -> 19885.402 | D14: =D10+D11-D12-D13 -> 20571.258 | E14: =E10+E11-E12-E13 -> 21306.405 | F14: =F10+F11-F12-F13 -> 22071.712 | G14: =G10+G11-G12-G13 -> 22868.471
A15: FCFF margin | B15: % | C15: =IFERROR(C14/C5,0) -> 0.22262284 | D15: =IFERROR(D14/D5,0) -> 0.22239301 | E15: =IFERROR(E14/E5,0) -> 0.22239128 | F15: =IFERROR(F14/F5,0) -> 0.22238958 | G15: =IFERROR(G14/G5,0) -> 0.22238791
A18: FCFF is derived from operating drivers, normalized cash taxes, explicit capex and a revenue-linked NWC assumption. | B18: FCFF is derived from operating drivers, normalized cash taxes, explicit capex and a revenue-linked NWC assumption. | C18: FCFF is derived from operating drivers, normalized cash taxes, explicit capex and a revenue-linked NWC assumption. | D18: FCFF is derived from operating drivers, normalized cash taxes, explicit capex and a revenue-linked NWC assumption. | E18: FCFF is derived from operating drivers, normalized cash taxes, explicit capex and a revenue-linked NWC assumption. | F18: FCFF is derived from operating drivers, normalized cash taxes, explicit capex and a revenue-linked NWC assumption. | G18: FCFF is derived from operating drivers, normalized cash taxes, explicit capex and a revenue-linked NWC assumption.

Sheet Valuation
A1: TMUS | DCF Valuation | B1: TMUS | DCF Valuation | C1: TMUS | DCF Valuation | D1: TMUS | DCF Valuation | E1: TMUS | DCF Valuation | F1: TMUS | DCF Valuation | G1: TMUS | DCF Valuation
A2: Primary method: unlevered FCFF DCF. Exit EV / Adjusted EBITDA is an explicit cross-check. | B2: Primary method: unlevered FCFF DCF. Exit EV / Adjusted EBITDA is an explicit cross-check. | C2: Primary method: unlevered FCFF DCF. Exit EV / Adjusted EBITDA is an explicit cross-check. | D2: Primary method: unlevered FCFF DCF. Exit EV / Adjusted EBITDA is an explicit cross-check. | E2: Primary method: unlevered FCFF DCF. Exit EV / Adjusted EBITDA is an explicit cross-check. | F2: Primary method: unlevered FCFF DCF. Exit EV / Adjusted EBITDA is an explicit cross-check. | G2: Primary method: unlevered FCFF DCF. Exit EV / Adjusted EBITDA is an explicit cross-check.
A4: Metric | B4: Units | C4: 2026E | D4: 2027E | E4: 2028E | F4: 2029E | G4: 2030E
A5: FCFF | B5: USD mm | C5: =Forecast!C14 -> 19885.402 | D5: =Forecast!D14 -> 20571.258 | E5: =Forecast!E14 -> 21306.405 | F5: =Forecast!F14 -> 22071.712 | G5: =Forecast!G14 -> 22868.471
A6: Discount period | B6: years | C6: 1 | D6: 2 | E6: 3 | F6: 4 | G6: 5
A7: Discount factor | B7: x | C7: =1/(1+Assumptions!$F$19)^C6 -> 0.91324201 | D7: =1/(1+Assumptions!$F$19)^D6 -> 0.83401097 | E7: =1/(1+Assumptions!$F$19)^E6 -> 0.76165385 | F7: =1/(1+Assumptions!$F$19)^F6 -> 0.69557429 | G7: =1/(1+Assumptions!$F$19)^G6 -> 0.63522767
A8: PV of FCFF | B8: USD mm | C8: =C5*C7 -> 18160.185 | D8: =D5*D7 -> 17156.655 | E8: =E5*E7 -> 16228.106 | F8: =F5*F7 -> 15352.515 | G8: =G5*G7 -> 14526.686
A11: WACC | B11: =Assumptions!$F$19 -> 0.095
A12: Terminal growth | B12: =Assumptions!$F$20 -> 0.025
A13: Terminal value | B13: =IFERROR(G5*(1+B12)/(B11-B12),0) -> 334859.76
A14: PV of terminal value | B14: =B13*G7 -> 212712.18
A15: Enterprise value | B15: =SUM(C8:G8)+B14 -> 294136.33
A16: Cash & cash equivalents | B16: =Historical!E13 -> 5598
A17: Total debt | B17: =Historical!E18 -> 93687
A18: Equity value | B18: =MAX(0,B15+B16-B17) -> 206047.33
A19: Diluted weighted-average shares | B19: =Historical!E17 -> 1131.0763
A20: DCF value / share | B20: =IFERROR(B18/B19,0) -> 182.16927
A21: Market-price comparison | B21: Omitted
A22: Reason | B22: No independently refreshed exact-dated quote was obtained in the controlled owner lane.
A23: 2030E Adjusted EBITDA | B23: =Sector_KPIs!J18 -> 40458.275
A24: Exit-multiple enterprise value | B24: =B23*Assumptions!$F$21 -> 283207.93
A25: Exit-multiple value / share | B25: =IFERROR(MAX(0,B24+B16-B17)/B19,0) -> 172.50732
A29: Valuation date / horizon | B29: Filed FY2025 actuals with an explicit 2026E-2030E forecast; terminal value is measured at 2030E and discounted to the valuation date.
A30: Debt / cash policy | B30: LongTermDebt + ShortTermBorrowings + FinanceLeaseLiability; all carrying values, USD mm. Net debt deducts cash and cash equivalents only; restricted cash and non-operating investments are excluded.
A31: Share-count basis | B31: Per-share valuation uses FY2025 diluted weighted-average shares; this is a period-average share count, not a point-in-time shares-outstanding quote.

Sheet Sensitivity
A1: TMUS | DCF Sensitivity | B1: TMUS | DCF Sensitivity | C1: TMUS | DCF Sensitivity | D1: TMUS | DCF Sensitivity | E1: TMUS | DCF Sensitivity | F1: TMUS | DCF Sensitivity | G1: TMUS | DCF Sensitivity | H1: TMUS | DCF Sensitivity
A2: Equity value per share across WACC and terminal-growth assumptions. Center cell equals the active DCF case. | B2: Equity value per share across WACC and terminal-growth assumptions. Center cell equals the active DCF case. | C2: Equity value per share across WACC and terminal-growth assumptions. Center cell equals the active DCF case. | D2: Equity value per share across WACC and terminal-growth assumptions. Center cell equals the active DCF case. | E2: Equity value per share across WACC and terminal-growth assumptions. Center cell equals the active DCF case. | F2: Equity value per share across WACC and terminal-growth assumptions. Center cell equals the active DCF case. | G2: Equity value per share across WACC and terminal-growth assumptions. Center cell equals the active DCF case. | H2: Equity value per share across WACC and terminal-growth assumptions. Center cell equals the active DCF case.
A4: Terminal growth → / WACC ↓ | B4: =Assumptions!$F$20+-0.01 -> 0.015 | C4: =Assumptions!$F$20+-0.005 -> 0.02 | D4: =Assumptions!$F$20+0 -> 0.025 | E4: =Assumptions!$F$20+0.005 -> 0.03 | F4: =Assumptions!$F$20+0.01 -> 0.035 | G4: Base DCF / share | H4: =Valuation!B20 -> 182.16927
A5: =Assumptions!$F$19+0.02 -> 0.115 | B5: =IFERROR(MAX(0,Forecast!C14/(1+$A5)+Forecast!D14/(1+$A5)^2+Forecast!E14/(1+$A5)^3+Forecast!F14/(1+$A5)^4+Forecast!G14/(1+$A5)^5+Forecast!G14*(1+B$4)/($A5-B$4)/(1+$A5)^5+Historical!E13-Historical!E18)/Historical!E17,0) -> 109.54217 | C5: =IFERROR(MAX(0,Forecast!C14/(1+$A5)+Forecast!D14/(1+$A5)^2+Forecast!E14/(1+$A5)^3+Forecast!F14/(1+$A5)^4+Forecast!G14/(1+$A5)^5+Forecast!G14*(1+C$4)/($A5-C$4)/(1+$A5)^5+Historical!E13-Historical!E18)/Historical!E17,0) -> 116.42699 | D5: =IFERROR(MAX(0,Forecast!C14/(1+$A5)+Forecast!D14/(1+$A5)^2+Forecast!E14/(1+$A5)^3+Forecast!F14/(1+$A5)^4+Forecast!G14/(1+$A5)^5+Forecast!G14*(1+D$4)/($A5-D$4)/(1+$A5)^5+Historical!E13-Historical!E18)/Historical!E17,0) -> 124.07678 | E5: =IFERROR(MAX(0,Forecast!C14/(1+$A5)+Forecast!D14/(1+$A5)^2+Forecast!E14/(1+$A5)^3+Forecast!F14/(1+$A5)^4+Forecast!G14/(1+$A5)^5+Forecast!G14*(1+E$4)/($A5-E$4)/(1+$A5)^5+Historical!E13-Historical!E18)/Historical!E17,0) -> 132.62655 | F5: =IFERROR(MAX(0,Forecast!C14/(1+$A5)+Forecast!D14/(1+$A5)^2+Forecast!E14/(1+$A5)^3+Forecast!F14/(1+$A5)^4+Forecast!G14/(1+$A5)^5+Forecast!G14*(1+F$4)/($A5-F$4)/(1+$A5)^5+Historical!E13-Historical!E18)/Historical!E17,0) -> 142.24504
A6: =Assumptions!$F$19+0.01 -> 0.105 | B6: =IFERROR(MAX(0,Forecast!C14/(1+$A6)+Forecast!D14/(1+$A6)^2+Forecast!E14/(1+$A6)^3+Forecast!F14/(1+$A6)^4+Forecast!G14/(1+$A6)^5+Forecast!G14*(1+B$4)/($A6-B$4)/(1+$A6)^5+Historical!E13-Historical!E18)/Historical!E17,0) -> 130.65426 | C6: =IFERROR(MAX(0,Forecast!C14/(1+$A6)+Forecast!D14/(1+$A6)^2+Forecast!E14/(1+$A6)^3+Forecast!F14/(1+$A6)^4+Forecast!G14/(1+$A6)^5+Forecast!G14*(1+C$4)/($A6-C$4)/(1+$A6)^5+Historical!E13-Historical!E18)/Historical!E17,0) -> 139.51775 | D6: =IFERROR(MAX(0,Forecast!C14/(1+$A6)+Forecast!D14/(1+$A6)^2+Forecast!E14/(1+$A6)^3+Forecast!F14/(1+$A6)^4+Forecast!G14/(1+$A6)^5+Forecast!G14*(1+D$4)/($A6-D$4)/(1+$A6)^5+Historical!E13-Historical!E18)/Historical!E17,0) -> 149.48917 | E6: =IFERROR(MAX(0,Forecast!C14/(1+$A6)+Forecast!D14/(1+$A6)^2+Forecast!E14/(1+$A6)^3+Forecast!F14/(1+$A6)^4+Forecast!G14/(1+$A6)^5+Forecast!G14*(1+E$4)/($A6-E$4)/(1+$A6)^5+Historical!E13-Historical!E18)/Historical!E17,0) -> 160.79012 | F6: =IFERROR(MAX(0,Forecast!C14/(1+$A6)+Forecast!D14/(1+$A6)^2+Forecast!E14/(1+$A6)^3+Forecast!F14/(1+$A6)^4+Forecast!G14/(1+$A6)^5+Forecast!G14*(1+F$4)/($A6-F$4)/(1+$A6)^5+Historical!E13-Historical!E18)/Historical!E17,0) -> 173.70549
A7: =Assumptions!$F$19+0 -> 0.095 | B7: =IFERROR(MAX(0,Forecast!C14/(1+$A7)+Forecast!D14/(1+$A7)^2+Forecast!E14/(1+$A7)^3+Forecast!F14/(1+$A7)^4+Forecast!G14/(1+$A7)^5+Forecast!G14*(1+B$4)/($A7-B$4)/(1+$A7)^5+Historical!E13-Historical!E18)/Historical!E17,0) -> 157.05614 | C7: =IFERROR(MAX(0,Forecast!C14/(1+$A7)+Forecast!D14/(1+$A7)^2+Forecast!E14/(1+$A7)^3+Forecast!F14/(1+$A7)^4+Forecast!G14/(1+$A7)^5+Forecast!G14*(1+C$4)/($A7-C$4)/(1+$A7)^5+Historical!E13-Historical!E18)/Historical!E17,0) -> 168.7756 | D7: =IFERROR(MAX(0,Forecast!C14/(1+$A7)+Forecast!D14/(1+$A7)^2+Forecast!E14/(1+$A7)^3+Forecast!F14/(1+$A7)^4+Forecast!G14/(1+$A7)^5+Forecast!G14*(1+D$4)/($A7-D$4)/(1+$A7)^5+Historical!E13-Historical!E18)/Historical!E17,0) -> 182.16927 | E7: =IFERROR(MAX(0,Forecast!C14/(1+$A7)+Forecast!D14/(1+$A7)^2+Forecast!E14/(1+$A7)^3+Forecast!F14/(1+$A7)^4+Forecast!G14/(1+$A7)^5+Forecast!G14*(1+E$4)/($A7-E$4)/(1+$A7)^5+Historical!E13-Historical!E18)/Historical!E17,0) -> 197.6235 | F7: =IFERROR(MAX(0,Forecast!C14/(1+$A7)+Forecast!D14/(1+$A7)^2+Forecast!E14/(1+$A7)^3+Forecast!F14/(1+$A7)^4+Forecast!G14/(1+$A7)^5+Forecast!G14*(1+F$4)/($A7-F$4)/(1+$A7)^5+Historical!E13-Historical!E18)/Historical!E17,0) -> 215.65343
A8: =Assumptions!$F$19+-0.01 -> 0.085 | B8: =IFERROR(MAX(0,Forecast!C14/(1+$A8)+Forecast!D14/(1+$A8)^2+Forecast!E14/(1+$A8)^3+Forecast!F14/(1+$A8)^4+Forecast!G14/(1+$A8)^5+Forecast!G14*(1+B$4)/($A8-B$4)/(1+$A8)^5+Historical!E13-Historical!E18)/Historical!E17,0) -> 191.01553 | C8: =IFERROR(MAX(0,Forecast!C14/(1+$A8)+Forecast!D14/(1+$A8)^2+Forecast!E14/(1+$A8)^3+Forecast!F14/(1+$A8)^4+Forecast!G14/(1+$A8)^5+Forecast!G14*(1+C$4)/($A8-C$4)/(1+$A8)^5+Historical!E13-Historical!E18)/Historical!E17,0) -> 207.04743 | D8: =IFERROR(MAX(0,Forecast!C14/(1+$A8)+Forecast!D14/(1+$A8)^2+Forecast!E14/(1+$A8)^3+Forecast!F14/(1+$A8)^4+Forecast!G14/(1+$A8)^5+Forecast!G14*(1+D$4)/($A8-D$4)/(1+$A8)^5+Historical!E13-Historical!E18)/Historical!E17,0) -> 225.75131 | E8: =IFERROR(MAX(0,Forecast!C14/(1+$A8)+Forecast!D14/(1+$A8)^2+Forecast!E14/(1+$A8)^3+Forecast!F14/(1+$A8)^4+Forecast!G14/(1+$A8)^5+Forecast!G14*(1+E$4)/($A8-E$4)/(1+$A8)^5+Historical!E13-Historical!E18)/Historical!E17,0) -> 247.85589 | F8: =IFERROR(MAX(0,Forecast!C14/(1+$A8)+Forecast!D14/(1+$A8)^2+Forecast!E14/(1+$A8)^3+Forecast!F14/(1+$A8)^4+Forecast!G14/(1+$A8)^5+Forecast!G14*(1+F$4)/($A8-F$4)/(1+$A8)^5+Historical!E13-Historical!E18)/Historical!E17,0) -> 274.38139
A9: =Assumptions!$F$19+-0.02 -> 0.075 | B9: =IFERROR(MAX(0,Forecast!C14/(1+$A9)+Forecast!D14/(1+$A9)^2+Forecast!E14/(1+$A9)^3+Forecast!F14/(1+$A9)^4+Forecast!G14/(1+$A9)^5+Forecast!G14*(1+B$4)/($A9-B$4)/(1+$A9)^5+Historical!E13-Historical!E18)/Historical!E17,0) -> 236.31199 | C9: =IFERROR(MAX(0,Forecast!C14/(1+$A9)+Forecast!D14/(1+$A9)^2+Forecast!E14/(1+$A9)^3+Forecast!F14/(1+$A9)^4+Forecast!G14/(1+$A9)^5+Forecast!G14*(1+C$4)/($A9-C$4)/(1+$A9)^5+Historical!E13-Historical!E18)/Historical!E17,0) -> 259.25062 | D9: =IFERROR(MAX(0,Forecast!C14/(1+$A9)+Forecast!D14/(1+$A9)^2+Forecast!E14/(1+$A9)^3+Forecast!F14/(1+$A9)^4+Forecast!G14/(1+$A9)^5+Forecast!G14*(1+D$4)/($A9-D$4)/(1+$A9)^5+Historical!E13-Historical!E18)/Historical!E17,0) -> 286.77697 | E9: =IFERROR(MAX(0,Forecast!C14/(1+$A9)+Forecast!D14/(1+$A9)^2+Forecast!E14/(1+$A9)^3+Forecast!F14/(1+$A9)^4+Forecast!G14/(1+$A9)^5+Forecast!G14*(1+E$4)/($A9-E$4)/(1+$A9)^5+Historical!E13-Historical!E18)/Historical!E17,0) -> 320.4203 | F9: =IFERROR(MAX(0,Forecast!C14/(1+$A9)+Forecast!D14/(1+$A9)^2+Forecast!E14/(1+$A9)^3+Forecast!F14/(1+$A9)^4+Forecast!G14/(1+$A9)^5+Forecast!G14*(1+F$4)/($A9-F$4)/(1+$A9)^5+Historical!E13-Historical!E18)/Historical!E17,0) -> 362.47445

Sheet Checks
A1: TMUS | Formula-Driven Model Checks | B1: TMUS | Formula-Driven Model Checks | C1: TMUS | Formula-Driven Model Checks | D1: TMUS | Formula-Driven Model Checks | E1: TMUS | Formula-Driven Model Checks | F1: TMUS | Formula-Driven Model Checks | G1: TMUS | Formula-Driven Model Checks | H1: TMUS | Formula-Driven Model Checks
A2: Overall status is aggregated from check-row formulas. No check status is hardcoded. | B2: Overall status is aggregated from check-row formulas. No check status is hardcoded. | C2: Overall status is aggregated from check-row formulas. No check status is hardcoded. | D2: Overall status is aggregated from check-row formulas. No check status is hardcoded. | E2: Overall status is aggregated from check-row formulas. No check status is hardcoded. | F2: Overall status is aggregated from check-row formulas. No check status is hardcoded. | G2: Overall status is aggregated from check-row formulas. No check status is hardcoded. | H2: Overall status is aggregated from check-row formulas. No check status is hardcoded.
A3: Model as of | B3: 2025-12-31
A4: Overall model status | B4: =IF(COUNTIF(G7:G16,"<>PASS")=0,"PASS","REMEDIATE") -> PASS
A6: Check ID | B6: Category | C6: Actual | D6: Expected | E6: Difference | F6: Tolerance | G6: Status | H6: Evidence / fix hint
A7: C01 | B7: Source ledger exact URLs | C7: =COUNTBLANK(Sources!O5:O102) -> 0 | D7: 0 | E7: =C7-D7 -> 0 | F7: 0.01 | G7: =IF(ABS(E7)<=F7,"PASS","FAIL") -> PASS | H7: All material rows require an exact URL.
A8: C02 | B8: Source ledger accession field complete | C8: =COUNTBLANK(Sources!K5:K102) -> 0 | D8: 0 | E8: =C8-D8 -> 0 | F8: 0.01 | G8: =IF(ABS(E8)<=F8,"PASS","FAIL") -> PASS | H8: Every source row must carry a filed accession or an explicit N/A.
A9: C03 | B9: Debt bridge | C9: =Historical!E18-SUM(Historical!E14:E16) -> 0 | D9: 0 | E9: =C9-D9 -> 0 | F9: 0.01 | G9: =IF(ABS(E9)<=F9,"PASS","FAIL") -> PASS | H9: LongTermDebt + ShortTermBorrowings + FinanceLeaseLiability; all carrying values, USD mm.
A10: C04 | B10: Net debt bridge | C10: =Historical!E19-(Historical!E18-Historical!E13) -> 0 | D10: 0 | E10: =C10-D10 -> 0 | F10: 0.01 | G10: =IF(ABS(E10)<=F10,"PASS","FAIL") -> PASS | H10: Net debt deducts cash and cash equivalents only; restricted cash and non-operating investments are excluded.
A11: C05 | B11: Operating model historical revenue tie | C11: =Sector_KPIs!E16-Historical!E5 -> 0 | D11: 0 | E11: =C11-D11 -> 0 | F11: 0.01 | G11: =IF(ABS(E11)<=F11,"PASS","FAIL") -> PASS | H11: 2025 operating schedule revenue must equal filed revenue.
A12: C06 | B12: Forecast operating link | C12: =Forecast!C5-Sector_KPIs!F16 -> 0 | D12: 0 | E12: =C12-D12 -> 0 | F12: 0.01 | G12: =IF(ABS(E12)<=F12,"PASS","FAIL") -> PASS | H12: 2026E revenue must flow from the operating model.
A13: C07 | B13: Scenario selector | C13: =IF(AND(Assumptions!B3>=1,Assumptions!B3<=3),1,0) -> 1 | D13: 1 | E13: =C13-D13 -> 0 | F13: 0.01 | G13: =IF(ABS(E13)<=F13,"PASS","FAIL") -> PASS | H13: Selector must be 1, 2 or 3.
A14: C08 | B14: Share count positive | C14: =IF(Historical!E17>0,1,0) -> 1 | D14: 1 | E14: =C14-D14 -> 0 | F14: 0.01 | G14: =IF(ABS(E14)<=F14,"PASS","FAIL") -> PASS | H14: Per-share valuation requires a positive share count.
A15: C09 | B15: Sensitivity center reconciliation | C15: =Sensitivity!D7-Valuation!B20 -> 0 | D15: 0 | E15: =C15-D15 -> 0 | F15: 0.01 | G15: =IF(ABS(E15)<=F15,"PASS","FAIL") -> PASS | H15: Center sensitivity cell must equal the active valuation.
A16: C10 | B16: Valuation finite / non-negative | C16: =IF(AND(ISNUMBER(Valuation!B20),Valuation!B20>=0),1,0) -> 1 | D16: 1 | E16: =C16-D16 -> 0 | F16: 0.01 | G16: =IF(ABS(E16)<=F16,"PASS","FAIL") -> PASS | H16: Primary equity value per share must be finite and non-negative; equity is floored at zero in downside cases.

Sheet Sector_KPIs
A1: TMUS | Subscriber-to-Cash-Flow Operating Model | B1: TMUS | Subscriber-to-Cash-Flow Operating Model | C1: TMUS | Subscriber-to-Cash-Flow Operating Model | D1: TMUS | Subscriber-to-Cash-Flow Operating Model | E1: TMUS | Subscriber-to-Cash-Flow Operating Model | F1: TMUS | Subscriber-to-Cash-Flow Operating Model | G1: TMUS | Subscriber-to-Cash-Flow Operating Model | H1: TMUS | Subscriber-to-Cash-Flow Operating Model | I1: TMUS | Subscriber-to-Cash-Flow Operating Model | J1: TMUS | Subscriber-to-Cash-Flow Operating Model
A2: Phone customers and ARPU drive phone service revenue; other service revenue is modeled separately to avoid ARPA/customer-unit mismatch. | B2: Phone customers and ARPU drive phone service revenue; other service revenue is modeled separately to avoid ARPA/customer-unit mismatch. | C2: Phone customers and ARPU drive phone service revenue; other service revenue is modeled separately to avoid ARPA/customer-unit mismatch. | D2: Phone customers and ARPU drive phone service revenue; other service revenue is modeled separately to avoid ARPA/customer-unit mismatch. | E2: Phone customers and ARPU drive phone service revenue; other service revenue is modeled separately to avoid ARPA/customer-unit mismatch. | F2: Phone customers and ARPU drive phone service revenue; other service revenue is modeled separately to avoid ARPA/customer-unit mismatch. | G2: Phone customers and ARPU drive phone service revenue; other service revenue is modeled separately to avoid ARPA/customer-unit mismatch. | H2: Phone customers and ARPU drive phone service revenue; other service revenue is modeled separately to avoid ARPA/customer-unit mismatch. | I2: Phone customers and ARPU drive phone service revenue; other service revenue is modeled separately to avoid ARPA/customer-unit mismatch. | J2: Phone customers and ARPU drive phone service revenue; other service revenue is modeled separately to avoid ARPA/customer-unit mismatch.
A4: Metric | B4: Units | C4: 2023A | D4: 2024A | E4: 2025A | F4: 2026E | G4: 2027E | H4: 2028E | I4: 2029E | J4: 2030E
A5: Postpaid phone customers | B5: mm | C5: 75.936 | D5: 79.013 | E5: 85.594 | F5: =E5*(1+F8) -> 87.5969 | G5: =F5*(1+G8) -> 89.646667 | H5: =G5*(1+H8) -> 91.744399 | I5: =H5*(1+I8) -> 93.891218 | J5: =I5*(1+J8) -> 96.088272
A6: Gross phone adds rate (modeled) | B6: % / year | F6: =Assumptions!$F$7 -> 0.135 | G6: =Assumptions!$F$7 -> 0.135 | H6: =Assumptions!$F$7 -> 0.135 | I6: =Assumptions!$F$7 -> 0.135 | J6: =Assumptions!$F$7 -> 0.135
A7: Postpaid phone churn | B7: % / month | C7: 0.0087 | D7: 0.0086 | E7: 0.0093 | F7: =Assumptions!$F$8 -> 0.0093 | G7: =Assumptions!$F$8 -> 0.0093 | H7: =Assumptions!$F$8 -> 0.0093 | I7: =Assumptions!$F$8 -> 0.0093 | J7: =Assumptions!$F$8 -> 0.0093
A8: Net phone customer growth | B8: % / year | D8: =IFERROR(D5/C5-1,0) -> 0.040520965 | E8: =IFERROR(E5/D5-1,0) -> 0.083290092 | F8: =F6-F7*12 -> 0.0234 | G8: =G6-G7*12 -> 0.0234 | H8: =H6-H7*12 -> 0.0234 | I8: =I6-I7*12 -> 0.0234 | J8: =J6-J7*12 -> 0.0234
A9: Postpaid phone ARPU | B9: $ / month | C9: 48.83 | D9: 49.35 | E9: 50.37 | F9: =E9*(1+Assumptions!$F$9) -> 51.3774 | G9: =F9*(1+Assumptions!$F$9) -> 52.404948 | H9: =G9*(1+Assumptions!$F$9) -> 53.453047 | I9: =H9*(1+Assumptions!$F$9) -> 54.522108 | J9: =I9*(1+Assumptions!$F$9) -> 55.61255
A10: Phone service revenue proxy | B10: USD mm | C10: =C5*C9*12 -> 44495.459 | D10: =D5*D9*12 -> 46791.499 | E10: =E5*E9*12 -> 51736.437 | F10: =AVERAGE(E5,F5)*F9*12 -> 53388.589 | G10: =AVERAGE(F5,G5)*G9*12 -> 55730.639 | H10: =AVERAGE(G5,H5)*H9*12 -> 58175.431 | I10: =AVERAGE(H5,I5)*I9*12 -> 60727.471 | J10: =AVERAGE(I5,J5)*J9*12 -> 63391.464
A11: Reported postpaid service revenue | B11: USD mm | C11: 48692 | D11: 52340 | E11: 57932 | F11: =F10+F12 -> 59708.063 | G11: =G10+G12 -> 62176.503 | H11: =H10+H12 -> 64750.212 | I11: =I10+I12 -> 67433.747 | J11: =J10+J12 -> 70231.865
A12: Other postpaid service revenue | B12: USD mm | C12: =C11-C10 -> 4196.5414 | D12: =D11-D10 -> 5548.5014 | E12: =E11-E10 -> 6195.5626 | F12: =E12*(1+Assumptions!$F$10) -> 6319.4739 | G12: =F12*(1+Assumptions!$F$10) -> 6445.8634 | H12: =G12*(1+Assumptions!$F$10) -> 6574.7806 | I12: =H12*(1+Assumptions!$F$10) -> 6706.2763 | J12: =I12*(1+Assumptions!$F$10) -> 6840.4018
A13: Prepaid / wholesale / other service revenue | B13: USD mm | C13: =C14-C11 -> 14549 | D13: =D14-D11 -> 13838 | E13: =E14-E11 -> 13374 | F13: =E13*(1+Assumptions!$F$11) -> 13507.74 | G13: =F13*(1+Assumptions!$F$11) -> 13642.817 | H13: =G13*(1+Assumptions!$F$11) -> 13779.246 | I13: =H13*(1+Assumptions!$F$11) -> 13917.038 | J13: =I13*(1+Assumptions!$F$11) -> 14056.208
A14: Total service revenue | B14: USD mm | C14: 63241 | D14: 66178 | E14: 71306 | F14: =F11+F13 -> 73215.803 | G14: =G11+G13 -> 75819.32 | H14: =H11+H13 -> 78529.457 | I14: =I11+I13 -> 81350.785 | J14: =J11+J13 -> 84288.074
A15: Equipment & other revenue | B15: USD mm | C15: 15317 | D15: 15222 | E15: 17003 | F15: =F14*Assumptions!$F$12 -> 16107.477 | G15: =G14*Assumptions!$F$12 -> 16680.25 | H15: =H14*Assumptions!$F$12 -> 17276.481 | I15: =I14*Assumptions!$F$12 -> 17897.173 | J15: =J14*Assumptions!$F$12 -> 18543.376
A16: Total revenue | B16: USD mm | C16: =C14+C15 -> 78558 | D16: =D14+D15 -> 81400 | E16: =E14+E15 -> 88309 | F16: =F14+F15 -> 89323.279 | G16: =G14+G15 -> 92499.571 | H16: =H14+H15 -> 95805.938 | I16: =I14+I15 -> 99247.958 | J16: =J14+J15 -> 102831.45
A17: Adjusted EBITDA margin on service revenue | B17: % | C17: 0.46533104 | D17: 0.48148932 | E17: 0.4759347 | F17: =Assumptions!$F$13 -> 0.48 | G17: =Assumptions!$F$13 -> 0.48 | H17: =Assumptions!$F$13 -> 0.48 | I17: =Assumptions!$F$13 -> 0.48 | J17: =Assumptions!$F$13 -> 0.48
A18: Adjusted EBITDA | B18: USD mm | C18: 29428 | D18: 31864 | E18: 33937 | F18: =F14*F17 -> 35143.585 | G18: =G14*G17 -> 36393.274 | H18: =H14*H17 -> 37694.139 | I18: =I14*I17 -> 39048.377 | J18: =J14*J17 -> 40458.275
A19: Cash capex | B19: USD mm | C19: 9801 | D19: 8840 | E19: 9955 | F19: =F16*Assumptions!$F$15 -> 10093.531 | G19: =G16*Assumptions!$F$15 -> 10452.451 | H19: =H16*Assumptions!$F$15 -> 10826.071 | I19: =I16*Assumptions!$F$15 -> 11215.019 | J19: =J16*Assumptions!$F$15 -> 11619.954
A20: Net debt | B20: USD mm | C20: =Historical!C19 -> 75998 | D20: =Historical!D19 -> 79250 | E20: =Historical!E19 -> 88089 | F20: =E20*(1-Assumptions!$F$18) -> 83684.55 | G20: =F20*(1-Assumptions!$F$18) -> 79500.322 | H20: =G20*(1-Assumptions!$F$18) -> 75525.306 | I20: =H20*(1-Assumptions!$F$18) -> 71749.041 | J20: =I20*(1-Assumptions!$F$18) -> 68161.589
A21: Net leverage | B21: x | C21: =IFERROR(C20/C18,0) -> 2.5825065 | D21: =IFERROR(D20/D18,0) -> 2.4871328 | E21: =IFERROR(E20/E18,0) -> 2.5956626 | F21: =IFERROR(F20/F18,0) -> 2.3812183 | G21: =IFERROR(G20/G18,0) -> 2.1844785 | H21: =IFERROR(H20/H18,0) -> 2.0036352 | I21: =IFERROR(I20/I18,0) -> 1.8374398 | J21: =IFERROR(J20/J18,0) -> 1.6847379
A24: Model limitation: Reported postpaid ARPA is per account while churn is postpaid phone churn; the driver model therefore uses phone customers/ARPU for phone service revenue and treats other postpaid revenue separately. | B24: Model limitation: Reported postpaid ARPA is per account while churn is postpaid phone churn; the driver model therefore uses phone customers/ARPU for phone service revenue and treats other postpaid revenue separately. | C24: Model limitation: Reported postpaid ARPA is per account while churn is postpaid phone churn; the driver model therefore uses phone customers/ARPU for phone service revenue and treats other postpaid revenue separately. | D24: Model limitation: Reported postpaid ARPA is per account while churn is postpaid phone churn; the driver model therefore uses phone customers/ARPU for phone service revenue and treats other postpaid revenue separately. | E24: Model limitation: Reported postpaid ARPA is per account while churn is postpaid phone churn; the driver model therefore uses phone customers/ARPU for phone service revenue and treats other postpaid revenue separately. | F24: Model limitation: Reported postpaid ARPA is per account while churn is postpaid phone churn; the driver model therefore uses phone customers/ARPU for phone service revenue and treats other postpaid revenue separately. | G24: Model limitation: Reported postpaid ARPA is per account while churn is postpaid phone churn; the driver model therefore uses phone customers/ARPU for phone service revenue and treats other postpaid revenue separately. | H24: Model limitation: Reported postpaid ARPA is per account while churn is postpaid phone churn; the driver model therefore uses phone customers/ARPU for phone service revenue and treats other postpaid revenue separately. | I24: Model limitation: Reported postpaid ARPA is per account while churn is postpaid phone churn; the driver model therefore uses phone customers/ARPU for phone service revenue and treats other postpaid revenue separately. | J24: Model limitation: Reported postpaid ARPA is per account while churn is postpaid phone churn; the driver model therefore uses phone customers/ARPU for phone service revenue and treats other postpaid revenue separately.
A27: Year | B27: Revenue | C27: Adj. EBITDA
A28: 2025A | B28: =E16 -> 88309 | C28: =E18 -> 33937
A29: 2026E | B29: =F16 -> 89323.279 | C29: =F18 -> 35143.585
A30: 2027E | B30: =G16 -> 92499.571 | C30: =G18 -> 36393.274
A31: 2028E | B31: =H16 -> 95805.938 | C31: =H18 -> 37694.139
A32: 2029E | B32: =I16 -> 99247.958 | C32: =I18 -> 39048.377
A33: 2030E | B33: =J16 -> 102831.45 | C33: =J18 -> 40458.275

Sheet Change_Log
A1: TMUS | Controlled Change Log | B1: TMUS | Controlled Change Log | C1: TMUS | Controlled Change Log | D1: TMUS | Controlled Change Log | E1: TMUS | Controlled Change Log | F1: TMUS | Controlled Change Log
A2: Prior workbook is preserved. This output is a new artifact with documented source, model, gate and recalculation changes. | B2: Prior workbook is preserved. This output is a new artifact with documented source, model, gate and recalculation changes. | C2: Prior workbook is preserved. This output is a new artifact with documented source, model, gate and recalculation changes. | D2: Prior workbook is preserved. This output is a new artifact with documented source, model, gate and recalculation changes. | E2: Prior workbook is preserved. This output is a new artifact with documented source, model, gate and recalculation changes. | F2: Prior workbook is preserved. This output is a new artifact with documented source, model, gate and recalculation changes.
A4: Timestamp | B4: Version | C4: Area | D4: Change | E4: Evidence | F4: Owner scope
A5: UTC 2026-07-16T22:00:00Z | B5: 9of10-regated | C5: Preservation | D5: Prior workbook preserved without overwrite. | E5: Original SHA-256: 8d802deaaeff11ab5a3c232c176fd64ad6e0a8f2da36fd0c8d33693922f63011 | F5: Controlled rebuild
A6: UTC 2026-07-16T22:00:00Z | B6: 9of10-regated | C6: Sources | D6: Replaced generic source list with exact SEC accession, filing URL, taxonomy/tag, period, unit, transform and target-cell ledger. | E6: Sources!A4:Q* | F6: Owner preflight
A7: UTC 2026-07-16T22:00:00Z | B7: 9of10-regated | C7: Debt / cash / shares | D7: Rebuilt total debt from explicit filed components; documented cash/restricted-cash and share-count policies. | E7: Historical!A13:I19 | F7: Owner preflight
A8: UTC 2026-07-16T22:00:00Z | B8: 9of10-regated | C8: Operating model | D8: Connected phone customers, churn and ARPU to service revenue, EBITDA, FCFF and valuation. | E8: Sector_KPIs | F8: Owner preflight
A9: UTC 2026-07-16T22:00:00Z | B9: 9of10-regated | C9: Valuation | D9: Established formula-driven DCF with exit-multiple cross-check. | E9: Valuation + Sensitivity | F9: Owner preflight
A10: UTC 2026-07-16T22:00:00Z | B10: 9of10-regated | C10: Gate | D10: Added formula-driven Checks and H0-H9 owner-preflight gate; independent certification is explicitly excluded. | E10: Checks + Gate_9of10 | F10: Owner preflight
A11: UTC 2026-07-16T22:00:00Z | B11: 9of10-regated | C11: Output | D11: Authored with artifact-tool; native recalculation and final visual manifest are referenced in Gate_9of10 and support evidence. | E11: T_Mobile_US_9of10_Regated.xlsx | F11: Owner preflight
A12: 46224 | B12: Elevation Ola 2 (statement-grade IG): added audited FY2021-FY2025 statement sheets IS_Hist/BS_Hist/CF_Hist/SCE_Hist (USD mm, published constants; FY2023-25 full line detail from 10-K R-files, FY2021-22 aggregate per companyfacts.json XBRL — gaps documented, not invented), Checks_TieOut (cross-statement + continuity tie-outs), Sources_Audited (exact R-file/accession/tag citations). Existing Historical/Forecast/Valuation/Sensitivity/Checks/Sector_KPIs/Assumptions sheets and their formulas untouched — pre-existing 5-year FY2026E-2030E Base/Bull/Bear driver-built forecast and DCF valuation already satisfied the forecast requirement and were not rebuilt. Root model untouched; v2 saved under the maintainer's archive. Built via Mog SDK only (no openpyxl/LibreOffice). | C12: Claude (run 24e4a1f1)
A13: 46248 | B13: Capa de cobertura Ola 1 de flota (plantilla del piloto Apple post-refutación): se agregaron Drivers_MDA (clientes/adds/ajustes con roll-forward, churn/ARPU/ARPA, ingresos por componente FY2021-25, detalle de opex e intereses FY21-22 que cierra los gaps 1 y 3 de Sources_Audited, no-GAAP reportados con recompute de FCF, espectro, deuda/refi con nota vs XBRL, escalera contractual al 2025-12-31 incl. spectrum leases, leases/torres, empleados, NOT_AVAILABLEs declarados incl. CAC y cohortes, y puente de 9 anclas al motor) y Market_Package (precio/acciones/market cap fechados, puente a EV, CAPM/WACC fechado, múltiplos, memo LTM al 2026-06-30 con el 10-Q Q2 2026 descargado de EDGAR, control de procedencia mecanizado y hallazgos H1-H4). Se agregaron 27 tie-outs (filas 33-59) en Checks_TieOut y se amplió el rango del MASTER de H5:H30 a H5:H59 (endurece; única celda preexistente tocada). HALLAZGOS declarados sin corregir: H1 double-count de la porción corriente de Senior Notes en el puente de deuda del DCF (5,135 FY25); H2 conteo de acciones del DCF vs portada del 10-Q; H3 WACC fechado ~5.5% vs 9.5% de escenario; H4 DCF Base a −0.2% del precio de mercado; y el residual FY23 de IS_Hist!D12 con el gain mal signado (50). NINGUNA hoja histórica ni del DCF fue modificada. Solo Mog SDK. | C13: Claude (Fable 5) — builder de cobertura T-Mobile, Ola 1

Sheet Gate_9of10
A1: TMUS | H0-H9 Owner Preflight Gate | B1: TMUS | H0-H9 Owner Preflight Gate | C1: TMUS | H0-H9 Owner Preflight Gate | D1: TMUS | H0-H9 Owner Preflight Gate | E1: TMUS | H0-H9 Owner Preflight Gate | F1: TMUS | H0-H9 Owner Preflight Gate | G1: TMUS | H0-H9 Owner Preflight Gate
A2: This sheet records owner preflight readiness. Independent certification is still required and is not self-awarded. | B2: This sheet records owner preflight readiness. Independent certification is still required and is not self-awarded. | C2: This sheet records owner preflight readiness. Independent certification is still required and is not self-awarded. | D2: This sheet records owner preflight readiness. Independent certification is still required and is not self-awarded. | E2: This sheet records owner preflight readiness. Independent certification is still required and is not self-awarded. | F2: This sheet records owner preflight readiness. Independent certification is still required and is not self-awarded. | G2: This sheet records owner preflight readiness. Independent certification is still required and is not self-awarded.
A4: Gate | B4: Control objective | C4: Weight | D4: Status | E4: Evidence range | F4: Owner note | G4: Independent certification
A5: H0 | B5: Controlled lineage and package integrity | C5: 5 | D5: =IF(AND(B23<>"",B24<>"",B25<>""),"PASS","FAIL") -> PASS | E5: Gate_9of10!A23:B28; internal QA evidence (not published) | F5: Original/output paths and original hash recorded; final hash and unzip evidence live beside the immutable reviewed file. | G5: Required
A6: H1 | B6: Source fidelity and provenance | C6: 20 | D6: =IF(AND(Checks!G7="PASS",Checks!G8="PASS"),"PASS","FAIL") -> PASS | E6: Sources!A4:Q*; Historical comments; Assumptions comments | F6: SEC tags/periods/units/accessions/retrieval/targets/transforms. Undated inherited market price removed from outputs. | G6: Required
A7: H2 | B7: Historical, formula and schedule mechanics | C7: 15 | D7: =IF(AND(Checks!G9="PASS",Checks!G10="PASS",Checks!G11="PASS",Checks!G12="PASS"),"PASS","FAIL") -> PASS | E7: Historical!A4:I23; Sector_KPIs!A4:J*; Forecast!A4:G15 | F7: Historical hardcodes and forecast formulas trace without cash/debt plugs. | G7: Required
A8: H3 | B8: Scenario and sensitivity integrity | C8: 10 | D8: =IF(AND(Checks!G13="PASS",Checks!G15="PASS"),"PASS","FAIL") -> PASS | E8: Assumptions!A3:G*; Sensitivity!A4:H9 | F8: Editable selector drives Base/Bull/Bear; sensitivity is formula-backed. | G8: Required
A9: H4 | B9: Valuation fit and mechanics | C9: 15 | D9: =IF(AND(Checks!G14="PASS",Checks!G15="PASS",Checks!G16="PASS"),"PASS","FAIL") -> PASS | E9: Valuation!A4:G31; Sensitivity!A4:H9 | F9: DCF with explicit PV/terminal/equity bridge plus exit-multiple cross-check; no stale market-price comparison. | G9: Required
A10: H5 | B10: Model checks and error state | C10: 8 | D10: =IF(Checks!B4="PASS","PASS","FAIL") -> PASS | E10: Checks!A3:H16; post manifest formula_error_scan | F10: Transparent Actual/Expected/Difference/Tolerance/Status checks and post-recalc error scan. | G10: Required
A11: H6 | B11: Native recalculation and reproducibility | C11: 10 | D11: =IF(B21<>"","PASS","FAIL") -> PASS | E11: Gate_9of10!A20:B22; support native log; internal QA evidence (not published) | F11: Opened/recalculated/saved/closed in LibreOfficeDev, then reopened by artifact-tool. | G11: Required
A12: H7 | B12: Visual QA after recalculation | C12: 7 | D12: =IF(B22<>"","PASS","FAIL") -> PASS | E12: internal QA evidence (not published) | F12: Every user-facing sheet rendered after native recalculation and tied to final hash. | G12: Required
A13: H8 | B13: Material economic upgrade | C13: 5 | D13: =IF(AND(COUNTA(Change_Log!A5:A20)>=6,COUNTA(Sector_KPIs!F5:J20)>0),"PASS","FAIL") -> PASS | E13: Change_Log!A4:F*; Sector_KPIs; Valuation; Checks | F13: Source, debt, company-specific operating, scenario, valuation and check mechanics were substantively rebuilt. | G13: Required
A14: H9 | B14: Governance, limitations and reviewer handoff | C14: 5 | D14: =IF(AND('00_Cover'!B4<>"",'00_Cover'!B16<>"",COUNTA(Change_Log!A5:A20)>=6),"PASS","FAIL") -> PASS | E14: 00_Cover!A4:H19; Change_Log!A4:F*; Gate_9of10 | F14: Purpose, version, as-of, units, horizon, case, status, limitations and reviewer handoff are explicit. | G14: Required
A16: Weighted score | B16: =SUMPRODUCT(C5:C14,--(D5:D14="PASS")) -> 100
A17: Owner preflight decision | B17: =IF(AND(B16>=90,COUNTIF(D5:D14,"FAIL")=0),"OWNER PRE-FLIGHT 9/10 READY — INDEPENDENT CERTIFICATION REQUIRED","REMEDIATE BEFORE INDEPENDENT CERTIFICATION") -> OWNER PRE-FLIGHT 9/10 READY — INDEPENDENT CERTIFICATION REQUIRED
A18: Certification status | B18: Independent certification required; not self-certified
A20: Build timestamp | B20: UTC 2026-07-16T22:00:00Z
A21: Native engine | B21: LibreOfficeDev 26.8.0.0.alpha0 (2c87e51eeaa2b413ff4ae097b2705eea1995d8e5)
A22: Visual manifest | B22: internal QA evidence (not published)
A23: Original path | B23: T_Mobile_US_Institutional_Model.xlsx
A24: Original SHA-256 | B24: 8d802deaaeff11ab5a3c232c176fd64ad6e0a8f2da36fd0c8d33693922f63011
A25: Controlled path | B25: T_Mobile_US_9of10_Regated.xlsx
A26: Calculation mode | B26: Automatic; full native recalculation forced during LibreOfficeDev conversion
A27: Evidence ledger | B27: internal QA evidence (not published)
A28: Open blocker ledger | B28: No owner-preflight blocker; independent certification remains required

Sheet IS_Hist
A1: T-Mobile US — Consolidated Statements of Comprehensive Income (audited)
A2: USD millions except per-share/share data. FY2023-2025 = FY2025 10-K R5.htm (accn 0001283699-26-000010). FY2021-2022 = SEC companyfacts.json XBRL aggregate tags (accn 0001283699-22-000018 / 0001283699-23-000016) — detailed expense/other-income line splits not in source package for those two years; presented at aggregate level, memo detail included where the underlying tag exists.
A4: Line item | B4: FY2021A | C4: FY2022A | D4: FY2023A | E4: FY2024A | F4: FY2025A | G4: XBRL tag / source note
A5: Total revenues | B5: 80118 | C5: 79571 | D5: 78558 | E5: 81400 | F5: 88309 | G5: us-gaap:RevenueFromContractWithCustomerExcludingAssessedTax
A6: Operating expenses
A7: Selling, general and administrative | D7: 21311 | E7: 20818 | F7: 23470
A8: Gain on disposal group held for sale | D8: -25 | E8: 0 | F8: 0
A9: Impairment expense | D9: 0 | E9: 0 | F9: 278
A10: Depreciation and amortization | D10: 12818 | E10: 12919 | F10: 13508
A11: Total costs and expenses (aggregate FY21-22; us-gaap:CostsAndExpenses) | B11: 73226 | C11: 73028
A12: Cost of services and cost of equipment sold (aggregate, derived residual = Total opex − SG&A − gain/loss − impairment − D&A; FY23-25 only — not independently tagged in the R5.htm consolidated table) | D12: 30138 | E12: 29653 | F12: 32774
A13: Total operating expenses (FY23-25 filed total) | D13: 64292 | E13: 63390 | F13: 70030
A14: Operating income | B14: 6892 | C14: 6543 | D14: 14266 | E14: 18010 | F14: 18279 | G14: us-gaap:OperatingIncomeLoss
A15: Other income (expense)
A16: Interest expense, net | D16: -3335 | E16: -3411 | F16: -3774
A17: Other (expense) income, net | D17: 68 | E17: 113 | F17: -224
A18: Total other expense, net (FY21-22 implied = PBT − operating income; us-gaap:IncomeLossFromContinuingOperationsBeforeIncomeTaxesExtraordinaryItemsNoncontrollingInterest less OperatingIncomeLoss) | B18: -3541 | C18: -3397 | D18: -3267 | E18: -3298 | F18: -3998
A19: Income before income taxes | B19: 3351 | C19: 3146 | D19: 10999 | E19: 14712 | F19: 14281 | G19: us-gaap:IncomeLossFromContinuingOperationsBeforeIncomeTaxesExtraordinaryItemsNoncontrollingInterest
A20: Income tax expense | B20: -327 | C20: -556 | D20: -2682 | E20: -3373 | F20: -3289 | G20: us-gaap:IncomeTaxExpenseBenefit (sign flipped to expense)
A21: Net income | B21: 3024 | C21: 2590 | D21: 8317 | E21: 11339 | F21: 10992 | G21: us-gaap:NetIncomeLoss
A23: Other comprehensive income, net of tax (FY23-25 only; not decomposed for FY21-22)
A24: Reclassification of loss from cash flow hedges, net of tax | D24: 163 | E24: 176 | F24: 190
A25: (Losses) gains on fair value hedges, net of tax | D25: 0 | E25: 16 | F25: -187
A26: Unrealized (loss) gain on FX translation, net of tax | D26: 9 | E26: 0 | F26: -1
A27: Actuarial gain (loss), net of amortization/reclassification | D27: -90 | E27: -85 | F27: 7
A28: Other comprehensive income | D28: 82 | E28: 107 | F28: 9
A29: Total comprehensive income | D29: 8399 | E29: 11446 | F29: 11001
A31: Earnings per share — basic ($) | B31: 2.42 | C31: 2.07 | D31: 7.02 | E31: 9.7 | F31: 9.75
A32: Earnings per share — diluted ($) | B32: 2.41 | C32: 2.06 | D32: 6.93 | E32: 9.66 | F32: 9.72
A33: Weighted-average shares — basic (mm) | B33: 1247.155 | C33: 1249.7639 | D33: 1185.1216 | E33: 1169.1954 | F33: 1127.9843
A34: Weighted-average shares — diluted (mm) | B34: 1254.7699 | C34: 1255.3768 | D34: 1200.2863 | E34: 1173.2139 | F34: 1131.0763
A36: Memo (FY21-22 only; informational, not additive to subtotals above)
A37: Memo: SG&A (us-gaap:SellingGeneralAndAdministrativeExpense) | B37: 20238 | C37: 21607
A38: Memo: D&A (us-gaap:DepreciationDepletionAndAmortization) | B38: 16383 | C38: 13651
A39: Memo: Restructuring costs (us-gaap:RestructuringCharges) | B39: 215 | C39: 1196
A40: Memo: Asset impairment charges (us-gaap:AssetImpairmentCharges) | B40: 0 | C40: 477

Sheet BS_Hist
A1: T-Mobile US — Consolidated Balance Sheets (audited)
A2: USD millions, as of December 31. FY2024-2025 = FY2025 10-K R3.htm; FY2023 = FY2024 10-K Financial_Report.xlsx comparative column (accn 0001283699-25-000012); FY2021-2022 = companyfacts.json XBRL instant tags — several intangible/liability sub-lines not separately tagged those years and shown as aggregates (flagged in line labels).
A4: Line item | B4: FY2021A | C4: FY2022A | D4: FY2023A | E4: FY2024A | F4: FY2025A | G4: XBRL tag / source note
A5: Current assets
A6: Cash and cash equivalents | B6: 6631 | C6: 4507 | D6: 5135 | E6: 5409 | F6: 5598 | G6: us-gaap:CashAndCashEquivalentsAtCarryingValue
A7: Accounts receivable, net | B7: 4194 | C7: 4445 | D7: 4692 | E7: 4276 | F7: 4874 | G7: us-gaap:AccountsReceivableNetCurrent
A8: Equipment installment plan receivables, net | B8: 4748 | C8: 5123 | D8: 4456 | E8: 4379 | F8: 4997 | G8: FY23-25 filed; FY21-22 derived residual = us-gaap:AssetsCurrent less other captured current-asset lines (no separate EIP-current tag in package for those years)
A9: Inventory | B9: 2567 | C9: 1884 | D9: 1678 | E9: 1607 | F9: 2405 | G9: us-gaap:InventoryNet
A10: Prepaid expenses | B10: 746 | C10: 673 | D10: 702 | E10: 880 | F10: 1215 | G10: us-gaap:PrepaidExpenseCurrent
A11: Other current assets | B11: 2005 | C11: 2435 | D11: 2352 | E11: 1853 | F11: 5372 | G11: us-gaap:OtherAssetsCurrent
A12: Total current assets | B12: 20891 | C12: 19067 | D12: 19015 | E12: 18404 | F12: 24461 | G12: us-gaap:AssetsCurrent
A13: Non-current assets
A14: Property and equipment, net | B14: 39803 | C14: 42086 | D14: 40432 | E14: 38533 | F14: 38333 | G14: us-gaap:PropertyPlantAndEquipmentNet
A15: Operating lease right-of-use assets | B15: 26959 | C15: 28715 | D15: 27135 | E15: 25398 | F15: 25692 | G15: us-gaap:OperatingLeaseRightOfUseAsset
A16: Financing lease right-of-use assets | D16: 3270 | E16: 3091 | F16: 2760
A17: Goodwill | B17: 12188 | C17: 12234 | D17: 12234 | E17: 13005 | F17: 13678 | G17: us-gaap:Goodwill
A18: Spectrum licenses | D18: 96707 | E18: 100558 | F18: 98032
A19: Other intangible assets, net | B19: 4733 | C19: 3508 | D19: 2618 | E19: 2512 | F19: 3843 | G19: us-gaap:FiniteLivedIntangibleAssetsNet (FY21-22); filed line (FY23-25)
A20: Spectrum licenses + other non-current assets (aggregate, FY21-22 only — source gap, see notes) | B20: 101989 | C20: 105728
A21: Equipment installment plan receivables due after one year, net | D21: 2042 | E21: 2209 | F21: 2683
A22: Other assets | D22: 4229 | E22: 4325 | F22: 9755
A23: Total assets | B23: 206563 | C23: 211338 | D23: 207682 | E23: 208035 | F23: 219237 | G23: us-gaap:Assets
A25: Current liabilities
A26: Accounts payable and accrued liabilities | B26: 11405 | C26: 12275 | D26: 10373 | E26: 8463 | F26: 10280 | G26: us-gaap:AccountsPayableAndAccruedLiabilitiesCurrent
A27: Short-term debt | B27: 3378 | C27: 5164 | D27: 3619 | E27: 4068 | F27: 5135 | G27: us-gaap:ShortTermBorrowings
A28: Deferred revenue | D28: 825 | E28: 1222 | F28: 1533
A29: Short-term operating lease liabilities | B29: 3425 | C29: 3512 | D29: 3555 | E29: 3281 | F29: 3814 | G29: us-gaap:OperatingLeaseLiabilityCurrent
A30: Short-term financing lease liabilities | B30: 1120 | C30: 1161 | D30: 1260 | E30: 1175 | F30: 1163 | G30: us-gaap:FinanceLeaseLiabilityCurrent
A31: Other current liabilities | B31: 4171 | C31: 2630 | D31: 1296 | E31: 1965 | F31: 2575 | G31: FY23-25 filed; FY21-22 derived residual = us-gaap:LiabilitiesCurrent less other captured current-liability lines (includes deferred revenue, not separately tagged those years)
A32: Total current liabilities | B32: 23499 | C32: 24742 | D32: 20928 | E32: 20174 | F32: 24500 | G32: us-gaap:LiabilitiesCurrent
A33: Long-term liabilities
A34: Long-term debt | B34: 74193 | C34: 71960 | D34: 71399 | E34: 74197 | F34: 81147 | G34: us-gaap:LongTermDebt
A35: Tower obligations | D35: 3777 | E35: 3664 | F35: 3532
A36: Deferred tax liabilities | D36: 13458 | E36: 16700 | F36: 19583
A37: Operating lease liabilities | B37: 25818 | C37: 29855 | D37: 28240 | E37: 26408 | F37: 26371 | G37: us-gaap:OperatingLeaseLiabilityNoncurrent
A38: Financing lease liabilities | B38: 1455 | C38: 1370 | D38: 1236 | E38: 1151 | F38: 1107 | G38: us-gaap:FinanceLeaseLiabilityNoncurrent
A39: Other long-term liabilities (aggregate incl. tower/deferred tax for FY21-22 — source gap, see notes) | B39: 12496 | C39: 13755 | D39: 3929 | E39: 4000 | F39: 3794 | G39: FY21-22 derived residual = Total LT liabilities less LT debt, op-lease NC and finance-lease NC (all separately tagged)
A40: Total long-term liabilities | B40: 113962 | C40: 116940 | D40: 122039 | E40: 126120 | F40: 135534
A41: Total liabilities (FY21-22 derived = Assets − Equity; FY23-25 = TCL + TLTL) | B41: 137461 | C41: 141682 | D41: 142967 | E41: 146294 | F41: 160034
A43: Stockholders' equity
A44: Common stock | B44: 0 | C44: 0 | D44: 0 | E44: 0 | F44: 0 | G44: us-gaap:CommonStockValue
A45: Additional paid-in capital & treasury stock, net (combined plug, FY21 only — source gap, see notes) | B45: 73279
A46: Additional paid-in capital | C46: 73941 | D46: 67705 | E46: 68798 | F46: 69460
A47: Treasury stock, at cost | C47: -3016 | D47: -9373 | E47: -20584 | F47: -30545
A48: Accumulated other comprehensive loss | B48: -1365 | C48: -1046 | D48: -964 | E48: -857 | F48: -848 | G48: us-gaap:AccumulatedOtherComprehensiveIncomeLossNetOfTax
A49: Retained earnings (accumulated deficit) | B49: -2812 | C49: -223 | D49: 7347 | E49: 14384 | F49: 21136 | G49: us-gaap:RetainedEarningsAccumulatedDeficit
A50: Total stockholders' equity | B50: 69102 | C50: 69656 | D50: 64715 | E50: 61741 | F50: 59203 | G50: us-gaap:StockholdersEquity
A51: Total liabilities and stockholders' equity | B51: 206563 | C51: 211338 | D51: 207682 | E51: 208035 | F51: 219237 | G51: us-gaap:LiabilitiesAndStockholdersEquity

Sheet CF_Hist
A1: T-Mobile US — Consolidated Statements of Cash Flows (audited)
A2: USD millions. FY2023-2025 = FY2025 10-K R7.htm. FY2021-2022 = companyfacts.json XBRL aggregate tags (CFO/CFI/CFF totals only; line-item detail not in source package). Cash basis = including restricted cash throughout, matching the filed CF presentation.
A4: Line item | B4: FY2021A | C4: FY2022A | D4: FY2023A | E4: FY2024A | F4: FY2025A | G4: XBRL tag / source note
A5: Operating activities
A6: Net income | B6: 3024 | C6: 2590 | D6: 8317 | E6: 11339 | F6: 10992
A7: Adjustments and working-capital changes (aggregate FY21-22; not decomposed — source gap)
A8: Depreciation and amortization | D8: 12818 | E8: 12919 | F8: 13508
A9: Stock-based compensation expense | D9: 667 | E9: 649 | F9: 829
A10: Deferred income tax expense | D10: 2600 | E10: 3120 | F10: 2864
A11: Bad debt expense | D11: 898 | E11: 1192 | F11: 1370
A12: Losses from sales of receivables | D12: 165 | E12: 62 | F12: 58
A13: Impairment expense | D13: 0 | E13: 0 | F13: 278
A14: Loss on remeasurement of disposal group held for sale | D14: 9 | E14: 0 | F14: 0
A15: Accounts receivable | D15: -5038 | E15: -3088 | F15: -755
A16: Equipment installment plan receivables | D16: 170 | E16: -523 | F16: -877
A17: Inventory | D17: 197 | E17: 131 | F17: -615
A18: Operating lease right-of-use assets | D18: 3721 | E18: 3480 | F18: 3635
A19: Other current and long-term assets | D19: -358 | E19: -411 | F19: -1488
... A23: Other, net (operating) | D23: 143 | E23: 21 | F23: 445
A24: Adjustments + WC changes, net (FY21-22 aggregate plug = CFO − NI) | B24: 10893 | C24: 14191
A25: Net cash provided by operating activities | B25: 13917 | C25: 16781 | D25: 18559 | E25: 22293 | F25: 27950 | G25: us-gaap:NetCashProvidedByUsedInOperatingActivities
A27: Investing activities (FY21-22 aggregate only — source gap)
A28: Purchases of property and equipment | D28: -9801 | E28: -8840 | F28: -9955
A29: Purchases of spectrum licenses and other intangible assets | D29: -1010 | E29: -3471 | F29: -2568
A30: Proceeds from sale of property, equipment and intangible assets | D30: 153 | E30: 99 | F30: 2168
A31: Proceeds from sales of tower sites | D31: 12 | E31: 0 | F31: 0
A32: Proceeds related to beneficial interests in securitization transactions | D32: 4816 | E32: 3579 | F32: 0
A33: Acquisition of companies, net of cash acquired | D33: 0 | E33: -373 | F33: -3523
A34: Investments in unconsolidated affiliates, net | D34: -7 | E34: -18 | F34: -4056
A35: Other, net (investing) | D35: 8 | E35: -48 | F35: 327
A36: Net cash used in investing activities | B36: -19386 | C36: -12359 | D36: -5829 | E36: -9072 | F36: -17607 | G36: us-gaap:NetCashProvidedByUsedInInvestingActivities
A38: Financing activities (FY21-22 aggregate only — source gap)
A39: Proceeds from issuance of long-term debt, net | D39: 8446 | E39: 8587 | F39: 12010
A40: Repayments of financing lease obligations | D40: -1227 | E40: -1367 | F40: -1252
A41: Repayments of long-term debt | D41: -5051 | E41: -5073 | F41: -6199
A42: Repurchases of common stock | D42: -13074 | E42: -11228 | F42: -9974
A43: Dividends on common stock | D43: -747 | E43: -3300 | F43: -4121
A44: Tax withholdings on share-based awards | D44: -297 | E44: -269 | F44: -434
A45: Other, net (financing) | D45: -147 | E45: -165 | F45: -111
A46: Net cash used in (provided by) financing activities | B46: 1709 | C46: -6451 | D46: -12097 | E46: -12815 | F46: -10081 | G46: us-gaap:NetCashProvidedByUsedInFinancingActivities
A48: Effect of exchange rate changes on cash, incl. restricted cash | B48: 0 | C48: 0 | D48: 0 | E48: 0 | F48: 1
A49: Change in cash, cash equivalents and restricted cash | B49: -3760 | C49: -2029 | D49: 633 | E49: 406 | F49: 263
A50: Cash, cash equivalents and restricted cash
A51: Beginning of period | B51: 10463 | C51: 6703 | D51: 4674 | E51: 5307 | F51: 5713 | G51: us-gaap:CashCashEquivalentsRestrictedCashAndRestrictedCashEquivalents
A52: End of period | B52: 6703 | C52: 4674 | D52: 5307 | E52: 5713 | F52: 5976 | G52: us-gaap:CashCashEquivalentsRestrictedCashAndRestrictedCashEquivalents

Sheet SCE_Hist
A1: T-Mobile US — Consolidated Statement of Stockholders' Equity (audited)
A2: USD millions. FY2023-2025 roll-forward = FY2025 10-K R9.htm (accn 0001283699-26-000010), including the audited Dec 31, 2022 opening balance. FY2021 roll-forward is not in the source package (no FY2022 10-K included) and is not fabricated; FY2021/2022 period-end equity levels are in BS_Hist instead.
A4: Line item | B4: FY2021A | C4: FY2022A | D4: FY2023A | E4: FY2024A | F4: FY2025A | G4: XBRL tag / source note
A5: Balance at Dec 31, 2022 (audited anchor; FY2021 roll-forward not in source package) | C5: 69656
A7: FY2023 activity
A8: Net income | D8: 8317
A9: Dividends declared | D9: -747
A10: Other comprehensive income | D10: 82
A11: Stock-based compensation | D11: 687
A12: Stock issued — employee stock purchase plan | D12: 210
A13: Shares withheld — net share settlement | D13: -297
A14: Repurchases of common stock | D14: -13255
A15: SoftBank contingent shares settlement | D15: 52
A16: Other, net | D16: 10
A17: Balance at Dec 31, 2023 | D17: 64715
A19: FY2024 activity
A20: Net income | E20: 11339
A21: Dividends declared | E21: -4302
A22: Other comprehensive income | E22: 107
A23: Stock-based compensation | E23: 619
A24: Stock issued — employee stock purchase plan | E24: 191
A25: Shares withheld — net share settlement | E25: -269
A26: Repurchases of common stock | E26: -11206
A27: Ka'ena Acquisition upfront consideration | E27: 536
A28: Other, net | E28: 11
A29: Balance at Dec 31, 2024 | E29: 61741
A31: FY2025 activity
A32: Net income | F32: 10992
A33: Dividends declared | F33: -4240
A34: Other comprehensive income | F34: 9
A35: Stock-based compensation | F35: 829
A36: Stock issued — employee stock purchase plan | F36: 214
A37: Shares withheld — net share settlement | F37: -434
A38: Repurchases of common stock | F38: -9957
A39: Other, net | F39: 49
A40: Balance at Dec 31, 2025 | F40: 59203

Sheet Checks_TieOut
A1: Tie-out checks — audited historical statements (all deltas must be 0 within tolerance; USD millions)
A2: MASTER | B2: =IF(COUNTIF(H5:H59,"FAIL")=0,"OK — ALL TIE-OUTS PASS (INFO rows are memo reconciling items, not failures)","FAIL") -> FAIL
A3: Conteo mecanizado | B3: =COUNTIF(H5:H59,"PASS")&" PASS / "&(COUNTIF(H5:H59,"PASS")+COUNTIF(H5:H59,"FAIL"))&" checks computables (la fila 28 es INFO, fuera del conteo)" -> 51 PASS / 52 checks computables (la fila 28 es INFO, fuera del conteo)
A4: Check | B4: FY2021A | C4: FY2022A | D4: FY2023A | E4: FY2024A | F4: FY2025A | H4: Status
A5: IS: Op income = Revenue − Total costs (FY21-22) | B5: =IS_Hist!B5-IS_Hist!B11-IS_Hist!B14 -> 0 | C5: =IS_Hist!C5-IS_Hist!C11-IS_Hist!C14 -> 0 | H5: =IF(AND(ABS(N(B5))<=1,ABS(N(C5))<=1),"PASS","FAIL") -> PASS
A6: IS: PBT = Op income + Other expense net (FY21-22) | B6: =IS_Hist!B14+IS_Hist!B18-IS_Hist!B19 -> 0 | C6: =IS_Hist!C14+IS_Hist!C18-IS_Hist!C19 -> 0 | H6: =IF(AND(ABS(N(B6))<=1,ABS(N(C6))<=1),"PASS","FAIL") -> PASS
A7: IS: NI = PBT + tax (tax stored as signed expense) (FY21-25) | B7: =IS_Hist!B19+IS_Hist!B20-IS_Hist!B21 -> 0 | C7: =IS_Hist!C19+IS_Hist!C20-IS_Hist!C21 -> 0 | D7: =IS_Hist!D19+IS_Hist!D20-IS_Hist!D21 -> 0 | E7: =IS_Hist!E19+IS_Hist!E20-IS_Hist!E21 -> 0 | F7: =IS_Hist!F19+IS_Hist!F20-IS_Hist!F21 -> 0 | H7: =IF(AND(ABS(N(B7))<=1,ABS(N(C7))<=1,ABS(N(D7))<=1,ABS(N(E7))<=1,ABS(N(F7))<=1),"PASS","FAIL") -> PASS
A8: IS: Total opex = SG&A + gain/loss + impairment + D&A + Cost of svcs/equip residual (FY23-25) | D8: =IS_Hist!D7-IS_Hist!D8+IS_Hist!D9+IS_Hist!D10+IS_Hist!D12-IS_Hist!D13 -> 0 | E8: =IS_Hist!E7-IS_Hist!E8+IS_Hist!E9+IS_Hist!E10+IS_Hist!E12-IS_Hist!E13 -> 0 | F8: =IS_Hist!F7-IS_Hist!F8+IS_Hist!F9+IS_Hist!F10+IS_Hist!F12-IS_Hist!F13 -> 0 | H8: =IF(AND(ABS(N(D8))<=1,ABS(N(E8))<=1,ABS(N(F8))<=1),"PASS","FAIL") -> PASS
A9: IS: Op income = Revenue − Total opex (FY23-25) | D9: =IS_Hist!D5-IS_Hist!D13-IS_Hist!D14 -> 0 | E9: =IS_Hist!E5-IS_Hist!E13-IS_Hist!E14 -> 0 | F9: =IS_Hist!F5-IS_Hist!F13-IS_Hist!F14 -> 0 | H9: =IF(AND(ABS(N(D9))<=1,ABS(N(E9))<=1,ABS(N(F9))<=1),"PASS","FAIL") -> PASS
A10: IS: PBT = Op income + Interest exp net + Other net (FY23-25) | D10: =IS_Hist!D14+IS_Hist!D16+IS_Hist!D17-IS_Hist!D19 -> 0 | E10: =IS_Hist!E14+IS_Hist!E16+IS_Hist!E17-IS_Hist!E19 -> 0 | F10: =IS_Hist!F14+IS_Hist!F16+IS_Hist!F17-IS_Hist!F19 -> 0 | H10: =IF(AND(ABS(N(D10))<=1,ABS(N(E10))<=1,ABS(N(F10))<=1),"PASS","FAIL") -> PASS
A11: IS: TCI = NI + OCI (FY23-25) | D11: =IS_Hist!D21+IS_Hist!D28-IS_Hist!D29 -> 0 | E11: =IS_Hist!E21+IS_Hist!E28-IS_Hist!E29 -> 0 | F11: =IS_Hist!F21+IS_Hist!F28-IS_Hist!F29 -> 0 | H11: =IF(AND(ABS(N(D11))<=1,ABS(N(E11))<=1,ABS(N(F11))<=1),"PASS","FAIL") -> PASS
A12: BS: Total current assets sum (FY21-25) | B12: =SUM(BS_Hist!B6:B11)-BS_Hist!B12 -> 0 | C12: =SUM(BS_Hist!C6:C11)-BS_Hist!C12 -> 0 | D12: =SUM(BS_Hist!D6:D11)-BS_Hist!D12 -> 0 | E12: =SUM(BS_Hist!E6:E11)-BS_Hist!E12 -> 0 | F12: =SUM(BS_Hist!F6:F11)-BS_Hist!F12 -> 0 | H12: =IF(AND(ABS(N(B12))<=1,ABS(N(C12))<=1,ABS(N(D12))<=1,ABS(N(E12))<=1,ABS(N(F12))<=1),"PASS","FAIL") -> PASS
A13: BS: Total assets = CA + NCA (FY21-25) | B13: =BS_Hist!B12+SUM(BS_Hist!B14:B22)-BS_Hist!B23 -> 0 | C13: =BS_Hist!C12+SUM(BS_Hist!C14:C22)-BS_Hist!C23 -> 0 | D13: =BS_Hist!D12+SUM(BS_Hist!D14:D22)-BS_Hist!D23 -> 0 | E13: =BS_Hist!E12+SUM(BS_Hist!E14:E22)-BS_Hist!E23 -> 0 | F13: =BS_Hist!F12+SUM(BS_Hist!F14:F22)-BS_Hist!F23 -> 0 | H13: =IF(AND(ABS(N(B13))<=1,ABS(N(C13))<=1,ABS(N(D13))<=1,ABS(N(E13))<=1,ABS(N(F13))<=1),"PASS","FAIL") -> PASS
A14: BS: Total current liabilities sum (FY21-25) | B14: =SUM(BS_Hist!B26:B31)-BS_Hist!B32 -> 0 | C14: =SUM(BS_Hist!C26:C31)-BS_Hist!C32 -> 0 | D14: =SUM(BS_Hist!D26:D31)-BS_Hist!D32 -> 0 | E14: =SUM(BS_Hist!E26:E31)-BS_Hist!E32 -> 0 | F14: =SUM(BS_Hist!F26:F31)-BS_Hist!F32 -> 0 | H14: =IF(AND(ABS(N(B14))<=1,ABS(N(C14))<=1,ABS(N(D14))<=1,ABS(N(E14))<=1,ABS(N(F14))<=1),"PASS","FAIL") -> PASS
A15: BS: Total long-term liabilities sum (FY21-25) | B15: =SUM(BS_Hist!B34:B39)-BS_Hist!B40 -> 0 | C15: =SUM(BS_Hist!C34:C39)-BS_Hist!C40 -> 0 | D15: =SUM(BS_Hist!D34:D39)-BS_Hist!D40 -> 0 | E15: =SUM(BS_Hist!E34:E39)-BS_Hist!E40 -> 0 | F15: =SUM(BS_Hist!F34:F39)-BS_Hist!F40 -> 0 | H15: =IF(AND(ABS(N(B15))<=1,ABS(N(C15))<=1,ABS(N(D15))<=1,ABS(N(E15))<=1,ABS(N(F15))<=1),"PASS","FAIL") -> PASS
A16: BS: Total liabilities = TCL + TLTL (FY21-25) | B16: =BS_Hist!B32+BS_Hist!B40-BS_Hist!B41 -> 0 | C16: =BS_Hist!C32+BS_Hist!C40-BS_Hist!C41 -> 0 | D16: =BS_Hist!D32+BS_Hist!D40-BS_Hist!D41 -> 0 | E16: =BS_Hist!E32+BS_Hist!E40-BS_Hist!E41 -> 0 | F16: =BS_Hist!F32+BS_Hist!F40-BS_Hist!F41 -> 0 | H16: =IF(AND(ABS(N(B16))<=1,ABS(N(C16))<=1,ABS(N(D16))<=1,ABS(N(E16))<=1,ABS(N(F16))<=1),"PASS","FAIL") -> PASS
A17: BS: Total equity components sum (FY22-25; FY21 uses combined plug) | C17: =BS_Hist!C44+N(BS_Hist!C46)+N(BS_Hist!C47)+BS_Hist!C48+BS_Hist!C49-BS_Hist!C50 -> 0 | D17: =BS_Hist!D44+N(BS_Hist!D46)+N(BS_Hist!D47)+BS_Hist!D48+BS_Hist!D49-BS_Hist!D50 -> 0 | E17: =BS_Hist!E44+N(BS_Hist!E46)+N(BS_Hist!E47)+BS_Hist!E48+BS_Hist!E49-BS_Hist!E50 -> 0 | F17: =BS_Hist!F44+N(BS_Hist!F46)+N(BS_Hist!F47)+BS_Hist!F48+BS_Hist!F49-BS_Hist!F50 -> 0 | H17: =IF(AND(ABS(N(C17))<=1,ABS(N(D17))<=1,ABS(N(E17))<=1,ABS(N(F17))<=1),"PASS","FAIL") -> PASS
A18: BS: Total equity components sum (FY21 combined plug) | B18: =BS_Hist!B44+BS_Hist!B45+BS_Hist!B48+BS_Hist!B49-BS_Hist!B50 -> 0 | H18: =IF(AND(ABS(N(B18))<=1),"PASS","FAIL") -> PASS
A19: BS: TL&E = Total liabilities + Total equity (FY21-25) | B19: =BS_Hist!B41+BS_Hist!B50-BS_Hist!B51 -> 0 | C19: =BS_Hist!C41+BS_Hist!C50-BS_Hist!C51 -> 0 | D19: =BS_Hist!D41+BS_Hist!D50-BS_Hist!D51 -> 0 | E19: =BS_Hist!E41+BS_Hist!E50-BS_Hist!E51 -> 0 | F19: =BS_Hist!F41+BS_Hist!F50-BS_Hist!F51 -> 0 | H19: =IF(AND(ABS(N(B19))<=1,ABS(N(C19))<=1,ABS(N(D19))<=1,ABS(N(E19))<=1,ABS(N(F19))<=1),"PASS","FAIL") -> PASS
A20: BS: Balance (Total assets − TL&E) (FY21-25) | B20: =BS_Hist!B23-BS_Hist!B51 -> 0 | C20: =BS_Hist!C23-BS_Hist!C51 -> 0 | D20: =BS_Hist!D23-BS_Hist!D51 -> 0 | E20: =BS_Hist!E23-BS_Hist!E51 -> 0 | F20: =BS_Hist!F23-BS_Hist!F51 -> 0 | H20: =IF(AND(ABS(N(B20))<=1,ABS(N(C20))<=1,ABS(N(D20))<=1,ABS(N(E20))<=1,ABS(N(F20))<=1),"PASS","FAIL") -> PASS
A21: CF: CFO = NI + adjustments/WC (FY21-22 plug) | B21: =CF_Hist!B6+CF_Hist!B24-CF_Hist!B25 -> 0 | C21: =CF_Hist!C6+CF_Hist!C24-CF_Hist!C25 -> 0 | H21: =IF(AND(ABS(N(B21))<=1,ABS(N(C21))<=1),"PASS","FAIL") -> PASS
A22: CF: CFO detail sum = reported CFO (FY23-25) | D22: =SUM(CF_Hist!D6:D23)-CF_Hist!D25 -> 0 | E22: =SUM(CF_Hist!E6:E23)-CF_Hist!E25 -> 0 | F22: =SUM(CF_Hist!F6:F23)-CF_Hist!F25 -> 0 | H22: =IF(AND(ABS(N(D22))<=1,ABS(N(E22))<=1,ABS(N(F22))<=1),"PASS","FAIL") -> PASS
A23: CF: CFI detail sum = reported CFI (FY23-25) | D23: =SUM(CF_Hist!D28:D35)-CF_Hist!D36 -> 0 | E23: =SUM(CF_Hist!E28:E35)-CF_Hist!E36 -> 0 | F23: =SUM(CF_Hist!F28:F35)-CF_Hist!F36 -> 0 | H23: =IF(AND(ABS(N(D23))<=1,ABS(N(E23))<=1,ABS(N(F23))<=1),"PASS","FAIL") -> PASS
A24: CF: CFF detail sum = reported CFF (FY23-25) | D24: =SUM(CF_Hist!D39:D45)-CF_Hist!D46 -> 0 | E24: =SUM(CF_Hist!E39:E45)-CF_Hist!E46 -> 0 | F24: =SUM(CF_Hist!F39:F45)-CF_Hist!F46 -> 0 | H24: =IF(AND(ABS(N(D24))<=1,ABS(N(E24))<=1,ABS(N(F24))<=1),"PASS","FAIL") -> PASS
A25: CF: Net change = CFO+CFI+CFF+FX (FY21-25) | B25: =CF_Hist!B25+CF_Hist!B36+CF_Hist!B46+CF_Hist!B48-CF_Hist!B49 -> 0 | C25: =CF_Hist!C25+CF_Hist!C36+CF_Hist!C46+CF_Hist!C48-CF_Hist!C49 -> 0 | D25: =CF_Hist!D25+CF_Hist!D36+CF_Hist!D46+CF_Hist!D48-CF_Hist!D49 -> 0 | E25: =CF_Hist!E25+CF_Hist!E36+CF_Hist!E46+CF_Hist!E48-CF_Hist!E49 -> 0 | F25: =CF_Hist!F25+CF_Hist!F36+CF_Hist!F46+CF_Hist!F48-CF_Hist!F49 -> 0 | H25: =IF(AND(ABS(N(B25))<=1,ABS(N(C25))<=1,ABS(N(D25))<=1,ABS(N(E25))<=1,ABS(N(F25))<=1),"PASS","FAIL") -> PASS
A26: CF: End cash = Begin + change (FY21-25) | B26: =CF_Hist!B51+CF_Hist!B49-CF_Hist!B52 -> 0 | C26: =CF_Hist!C51+CF_Hist!C49-CF_Hist!C52 -> 0 | D26: =CF_Hist!D51+CF_Hist!D49-CF_Hist!D52 -> 0 | E26: =CF_Hist!E51+CF_Hist!E49-CF_Hist!E52 -> 0 | F26: =CF_Hist!F51+CF_Hist!F49-CF_Hist!F52 -> 0 | H26: =IF(AND(ABS(N(B26))<=1,ABS(N(C26))<=1,ABS(N(D26))<=1,ABS(N(E26))<=1,ABS(N(F26))<=1),"PASS","FAIL") -> PASS
A27: CF: Beginning cash = prior-year end cash (FY22-25) | C27: =CF_Hist!C51-CF_Hist!B52 -> 0 | D27: =CF_Hist!D51-CF_Hist!C52 -> 0 | E27: =CF_Hist!E51-CF_Hist!D52 -> 0 | F27: =CF_Hist!F51-CF_Hist!E52 -> 0 | H27: =IF(AND(ABS(N(C27))<=1,ABS(N(D27))<=1,ABS(N(E27))<=1,ABS(N(F27))<=1),"PASS","FAIL") -> PASS
A28: X: CF end cash (incl. restricted) vs BS cash (FY21-25; informational — restricted cash sits outside BS cash line, expected non-zero) | B28: =CF_Hist!B52-BS_Hist!B6 -> 72 | C28: =CF_Hist!C52-BS_Hist!C6 -> 167 | D28: =CF_Hist!D52-BS_Hist!D6 -> 172 | E28: =CF_Hist!E52-BS_Hist!E6 -> 304 | F28: =CF_Hist!F52-BS_Hist!F6 -> 378 | H28: =IF(AND(ABS(N(B28))<=500,ABS(N(C28))<=500,ABS(N(D28))<=500,ABS(N(E28))<=500,ABS(N(F28))<=500),"INFO","INFO") -> INFO
A29: X: CF net income = IS net income (FY21-25) | B29: =CF_Hist!B6-IS_Hist!B21 -> 0 | C29: =CF_Hist!C6-IS_Hist!C21 -> 0 | D29: =CF_Hist!D6-IS_Hist!D21 -> 0 | E29: =CF_Hist!E6-IS_Hist!E21 -> 0 | F29: =CF_Hist!F6-IS_Hist!F21 -> 0 | H29: =IF(AND(ABS(N(B29))<=1,ABS(N(C29))<=1,ABS(N(D29))<=1,ABS(N(E29))<=1,ABS(N(F29))<=1),"PASS","FAIL") -> PASS
A30: X: BS total equity = SCE ending balance (FY23-25) | D30: =SCE_Hist!D17-BS_Hist!D50 -> 0 | E30: =SCE_Hist!E29-BS_Hist!E50 -> 0 | F30: =SCE_Hist!F40-BS_Hist!F50 -> 0 | H30: =IF(AND(ABS(N(D30))<=1,ABS(N(E30))<=1,ABS(N(F30))<=1),"PASS","FAIL") -> PASS
A32: COBERTURA — drivers de negocio (Drivers_MDA) y paquete de mercado (Market_Package), agregados 2026-08-14. Patrón del piloto Apple post-refutación: cero tautologías; cada check amarra contra celdas INDEPENDIENTES (otra hoja, otra fuente u otro vintage) y PUEDE fallar.
A33: DRV: clientes postpaid phone + other = total postpaid (tabla publicada, constantes) | B33: =Drivers_MDA!B12 -> 0 | C33: =Drivers_MDA!C12 -> 0 | D33: =Drivers_MDA!D12 -> 0 | E33: =Drivers_MDA!E12 -> 0 | F33: =Drivers_MDA!F12 -> 0 | H33: =IF(AND(ABS(N(B33))<=0.5,ABS(N(C33))<=0.5,ABS(N(D33))<=0.5,ABS(N(E33))<=0.5,ABS(N(F33))<=0.5),"PASS","FAIL") -> PASS | I33: B,C,D,E,F
A34: DRV: total postpaid + prepaid = total customers | B34: =Drivers_MDA!B13 -> 0 | C34: =Drivers_MDA!C13 -> 0 | D34: =Drivers_MDA!D13 -> 0 | E34: =Drivers_MDA!E13 -> 0 | F34: =Drivers_MDA!F13 -> 0 | H34: =IF(AND(ABS(N(B34))<=0.5,ABS(N(C34))<=0.5,ABS(N(D34))<=0.5,ABS(N(E34))<=0.5,ABS(N(F34))<=0.5),"PASS","FAIL") -> PASS | I34: B,C,D,E,F
A35: DRV: roll-forward de la base (fin = inicio + adds netos + ajustes, FY22-25) — continuidad entre tablas de años consecutivos | C35: =Drivers_MDA!C26 -> 0 | D35: =Drivers_MDA!D26 -> 0 | E35: =Drivers_MDA!E26 -> 0 | F35: =Drivers_MDA!F26 -> 0 | H35: =IF(AND(ABS(N(C35))<=0.5,ABS(N(D35))<=0.5,ABS(N(E35))<=0.5,ABS(N(F35))<=0.5),"PASS","FAIL") -> PASS | I35: C,D,E,F
A36: DRV: componentes de adds netos = total reportado | B36: =Drivers_MDA!B25 -> 0 | C36: =Drivers_MDA!C25 -> 0 | D36: =Drivers_MDA!D25 -> 0 | E36: =Drivers_MDA!E25 -> 0 | F36: =Drivers_MDA!F25 -> 0 | H36: =IF(AND(ABS(N(B36))<=0.5,ABS(N(C36))<=0.5,ABS(N(D36))<=0.5,ABS(N(E36))<=0.5,ABS(N(F36))<=0.5),"PASS","FAIL") -> PASS | I36: B,C,D,E,F
A37: DRV: componentes de servicio = total service revenues | B37: =Drivers_MDA!B46 -> 0 | C37: =Drivers_MDA!C46 -> 0 | D37: =Drivers_MDA!D46 -> 0 | E37: =Drivers_MDA!E46 -> 0 | F37: =Drivers_MDA!F46 -> 0 | H37: =IF(AND(ABS(N(B37))<=0.5,ABS(N(C37))<=0.5,ABS(N(D37))<=0.5,ABS(N(E37))<=0.5,ABS(N(F37))<=0.5),"PASS","FAIL") -> PASS | I37: B,C,D,E,F
A38: DRV: servicio + equipo + otros = total revenues | B38: =Drivers_MDA!B47 -> 0 | C38: =Drivers_MDA!C47 -> 0 | D38: =Drivers_MDA!D47 -> 0 | E38: =Drivers_MDA!E47 -> 0 | F38: =Drivers_MDA!F47 -> 0 | H38: =IF(AND(ABS(N(B38))<=0.5,ABS(N(C38))<=0.5,ABS(N(D38))<=0.5,ABS(N(E38))<=0.5,ABS(N(F38))<=0.5),"PASS","FAIL") -> PASS | I38: B,C,D,E,F
A39: DRV: total revenues del MD&A = IS_Hist (dos rutas de fuente; cierra la brecha del split FY21-22) | B39: =Drivers_MDA!B48 -> 0 | C39: =Drivers_MDA!C48 -> 0 | D39: =Drivers_MDA!D48 -> 0 | E39: =Drivers_MDA!E48 -> 0 | F39: =Drivers_MDA!F48 -> 0 | H39: =IF(AND(ABS(N(B39))<=0.5,ABS(N(C39))<=0.5,ABS(N(D39))<=0.5,ABS(N(E39))<=0.5,ABS(N(F39))<=0.5),"PASS","FAIL") -> PASS | I39: B,C,D,E,F
A40: DRV: detalle de opex del PDF = IS_Hist (FY21-22 agregado XBRL, FY23-25 total filed; cierra el gap 1) | B40: =Drivers_MDA!B62 -> 0 | C40: =Drivers_MDA!C62 -> 0 | D40: =Drivers_MDA!D62 -> 0 | E40: =Drivers_MDA!E62 -> 0 | F40: =Drivers_MDA!F62 -> 0 | H40: =IF(AND(ABS(N(B40))<=0.5,ABS(N(C40))<=0.5,ABS(N(D40))<=0.5,ABS(N(E40))<=0.5,ABS(N(F40))<=0.5),"PASS","FAIL") -> PASS | I40: B,C,D,E,F
A41: DRV: intereses + otros FY21-22 del PDF = plug agregado de IS_Hist (cierra el gap 1) | B41: =Drivers_MDA!B66 -> 0 | C41: =Drivers_MDA!C66 -> 0 | H41: =IF(AND(ABS(N(B41))<=0.5,ABS(N(C41))<=0.5),"PASS","FAIL") -> PASS | I41: B,C
A42: DRV: Sector_KPIs FY23-25 = Drivers_MDA en clientes phone, churn y ARPU (entrada de Ola 1 vs extracción nueva del filing) | D42: =ABS(Drivers_MDA!D14)+ABS(Drivers_MDA!D34)+ABS(Drivers_MDA!D35) -> 0 | E42: =ABS(Drivers_MDA!E14)+ABS(Drivers_MDA!E34)+ABS(Drivers_MDA!E35) -> 0 | F42: =ABS(Drivers_MDA!F14)+ABS(Drivers_MDA!F34)+ABS(Drivers_MDA!F35) -> 0 | H42: =IF(AND(ABS(N(D42))<=0.001,ABS(N(E42))<=0.001,ABS(N(F42))<=0.001),"PASS","FAIL") -> PASS | I42: D,E,F
A43: DRV: Sector_KPIs FY23-25 = Drivers_MDA en ingresos (postpaid svc, total svc, equipo+otros) y Adjusted EBITDA | D43: =ABS(Drivers_MDA!D49)+ABS(Drivers_MDA!D72) -> 0 | E43: =ABS(Drivers_MDA!E49)+ABS(Drivers_MDA!E72) -> 0 | F43: =ABS(Drivers_MDA!F49)+ABS(Drivers_MDA!F72) -> 0 | H43: =IF(AND(ABS(N(D43))<=0.5,ABS(N(E43))<=0.5,ABS(N(F43))<=0.5),"PASS","FAIL") -> PASS | I43: D,E,F
A44: DRV: Free Cash Flow reportado en el MD&A = recompute desde las líneas de CF_Hist (FY23-25) | D44: =Drivers_MDA!D75 -> 0 | E44: =Drivers_MDA!E75 -> 0 | F44: =Drivers_MDA!F75 -> 0 | H44: =IF(AND(ABS(N(D44))<=0.5,ABS(N(E44))<=0.5,ABS(N(F44))<=0.5),"PASS","FAIL") -> PASS | I44: D,E,F
A45: DRV: spectrum — balance del PDF = BS_Hist y purchases del PDF = CF_Hist (FY23-25) | D45: =ABS(Drivers_MDA!D81)+ABS(Drivers_MDA!D84) -> 0 | E45: =ABS(Drivers_MDA!E81)+ABS(Drivers_MDA!E84) -> 0 | F45: =ABS(Drivers_MDA!F81)+ABS(Drivers_MDA!F84) -> 0 | H45: =IF(AND(ABS(N(D45))<=0.5,ABS(N(E45))<=0.5,ABS(N(F45))<=0.5),"PASS","FAIL") -> PASS | I45: D,E,F
A46: DRV: nota de deuda — consistencia interna (total = corriente + LT), nota vs XBRL (Historical!C14:E14) y terceros + afiliadas = total LT (FY24-25) | D46: =ABS(Drivers_MDA!D94)+ABS(Drivers_MDA!D95) -> 0 | E46: =ABS(Drivers_MDA!E94)+ABS(Drivers_MDA!E95)+ABS(Drivers_MDA!E96) -> 0 | F46: =ABS(Drivers_MDA!F94)+ABS(Drivers_MDA!F95)+ABS(Drivers_MDA!F96) -> 0 | H46: =IF(AND(ABS(N(D46))<=0.5,ABS(N(E46))<=0.5,ABS(N(F46))<=0.5),"PASS","FAIL") -> PASS | I46: D,E,F
A47: DRV: emisiones y repagos de deuda LP del PDF = CF_Hist (FY23-25) | D47: =ABS(Drivers_MDA!D103)+ABS(Drivers_MDA!D105) -> 0 | E47: =ABS(Drivers_MDA!E103)+ABS(Drivers_MDA!E105) -> 0 | F47: =ABS(Drivers_MDA!F103)+ABS(Drivers_MDA!F105) -> 0 | H47: =IF(AND(ABS(N(D47))<=0.5,ABS(N(E47))<=0.5,ABS(N(F47))<=0.5),"PASS","FAIL") -> PASS | I47: D,E,F
A48: DRV: escalera contractual — buckets suman al total por fila (9 filas) y filas suman al total por columna (5 columnas), todo constantes publicadas | F48: =ABS(Drivers_MDA!B120)+ABS(Drivers_MDA!C120) -> 0 | H48: =IF(ABS(N(F48))<=0.5,"PASS","FAIL") -> PASS | I48: F
A49: DRV: tres fuentes de deuda — principal de la escalera (Item 7) + prima − descuento − costos (Nota 9) = carrying XBRL (Historical!E14) | F49: =ABS(Drivers_MDA!B121) -> 0 | H49: =IF(ABS(N(F49))<=0.5,"PASS","FAIL") -> PASS | I49: F
A50: DRV: finance leases del balance (BS_Hist) = us-gaap:FinanceLeaseLiability (Historical) FY23-25 — dos rutas de fuente | D50: =Drivers_MDA!D129 -> 0 | E50: =Drivers_MDA!E129 -> 0 | F50: =Drivers_MDA!F129 -> 0 | H50: =IF(AND(ABS(N(D50))<=0.5,ABS(N(E50))<=0.5,ABS(N(F50))<=0.5),"PASS","FAIL") -> PASS | I50: D,E,F
A51: FCST: las 9 anclas FY2025A del motor (Sector_KPIs col E: clientes, churn, ARPU, ingresos x4, EBITDA, capex) = Drivers_MDA | F51: =ABS(Drivers_MDA!F148)+ABS(Drivers_MDA!F149)+ABS(Drivers_MDA!F150)+ABS(Drivers_MDA!F151)+ABS(Drivers_MDA!F152)+ABS(Drivers_MDA!F153)+ABS(Drivers_MDA!F154)+ABS(Drivers_MDA!F155)+ABS(Drivers_MDA!F156) -> 0 | H51: =IF(ABS(N(F51))<=0.001,"PASS","FAIL") -> PASS | I51: F
A52: MKT: enterprise value — tie EXACTO contra el ancla de vintage distinto (precio x acciones + deuda − caja de la columna comparativa del 10-Q Q2 2026, constantes independientes de BS_Hist), EV positivo, y banda de ±25% contra el EV con balance al 2026-06-30 (deriva real −0.4%). F es el conteo de incumplimientos | F52: =IF(ABS(Market_Package!B23-(Market_Package!B7*Market_Package!B8+Market_Package!B28-Market_Package!B27))>0.5,1,0)+IF(Market_Package!B23<=0,1,0)+IF(ABS(Market_Package!B23/Market_Package!B92-1)>0.25,1,0) -> 0 | H52: =IF(N(F52)=0,"PASS","FAIL") -> PASS | I52: F
A53: MKT: caja del paquete — tie EXACTO contra el ancla de vintage distinto (10-Q comparativa, B27), positiva, y tie EXACTO contra la caja XBRL del DCF (Historical!E13, tercera ruta). Sin banda contra la caja al 2026-06-30: se movió −49.5% en 6 meses por razones reales (declarado en B90). F es el conteo de incumplimientos | F53: =IF(ABS(Market_Package!B14-Market_Package!B27)>0.5,1,0)+IF(Market_Package!B14<=0,1,0)+IF(ABS(Market_Package!B14-Historical!E13)>0.5,1,0) -> 0 | H53: =IF(N(F53)=0,"PASS","FAIL") -> PASS | I53: F
A54: MKT: deuda del paquete — (1) la brecha contra la deuda del DCF debe ser EXACTAMENTE la porción corriente de Senior Notes (BS_Hist!F27): mecaniza el hallazgo H1 del double-count; (2) tie EXACTO contra el ancla de vintage distinto (B28); (3) banda de ±25% contra la deuda al 2026-06-30 (deriva real −1.8%). F es el conteo de incumplimientos | F54: =IF(ABS((Market_Package!B20-Market_Package!B19)-BS_Hist!F27)>0.5,1,0)+IF(ABS(Market_Package!B19-Market_Package!B28)>0.5,1,0)+IF(ABS(Market_Package!B19/Market_Package!B91-1)>0.25,1,0) -> 0 | H54: =IF(N(F54)=0,"PASS","FAIL") -> PASS | I54: F
A55: MKT: costo de capital — guardia del enlace vivo de la tasa efectiva (B37 debe ser exactamente −IS_Hist!F20/IS_Hist!F19: una tasa en duro cae) más bandas de plausibilidad: Rf [0.5%,12%], beta [0.1x,2.5x], Kd [1%,15%], WACC [3%,20%]. Una cifra plausible y equivocada dentro de banda pasa — limitación declarada (patrón del check 54 del piloto). F es el conteo de incumplimientos | F55: =IF(ABS(Market_Package!B37-(-IS_Hist!F20/IS_Hist!F19))>0.0000001,1,0)+IF(OR(Market_Package!B31<0.005,Market_Package!B31>0.12),1,0)+IF(OR(Market_Package!B33<0.1,Market_Package!B33>2.5),1,0)+IF(OR(Market_Package!B35<0.01,Market_Package!B35>0.15),1,0)+IF(OR(Market_Package!B45<0.03,Market_Package!B45>0.2),1,0) -> 0 | H55: =IF(N(F55)=0,"PASS","FAIL") -> PASS | I55: F
A56: MKT: precio, acciones y capitalización — cableado (B11 = B7 x B8), precio dentro de banda absoluta [50,600] USD (caza errores de unidad/magnitud; un precio plausible y equivocado pasa — limitación declarada; el libro no tiene otro precio contra el cual anclar porque la política omitía la comparación de mercado), y acciones dentro de ±8% del promedio diluido FY2025A (Historical!E17; deriva real por buybacks −5.2%). F es el conteo de incumplimientos | F56: =IF(ABS(Market_Package!B11-Market_Package!B7*Market_Package!B8)>0.5,1,0)+IF(OR(Market_Package!B7<50,Market_Package!B7>600),1,0)+IF(ABS(Market_Package!B8/Historical!E17-1)>0.08,1,0) -> 0 | H56: =IF(N(F56)=0,"PASS","FAIL") -> PASS | I56: F
A57: MKT: procedencia de los inputs de mercado — fuente presente, fecha con serial válido, desfase relativo ≤5 días entre precio/Rf/Kd y frescura absoluta de 10 días contra HOY() al recalcular (el libro caduca solo: es diseño). 0 significa completo | F57: =Market_Package!B97+Market_Package!B98+Market_Package!B99 -> 1 | H57: =IF(N(F57)=0,"PASS","FAIL") -> FAIL | I57: F
A58: XREF: calibración declarada de Assumptions contra lo reportado — churn Base (D8) = churn FY2025A reportado, crecimiento de ARPU Base (D9) ≈ crecimiento FY2025A reportado (±0.5pp), margen Adjusted EBITDA Base (D13) ≈ margen FY2025A reportado (±1pp). Mecaniza las afirmaciones de la columna G de Assumptions (lección M3 del piloto). F es el conteo de incumplimientos | F58: =IF(ABS(Assumptions!D8-Drivers_MDA!F29)>0.0005,1,0)+IF(ABS(Assumptions!D9-(Drivers_MDA!F31/Drivers_MDA!E31-1))>0.005,1,0)+IF(ABS(Assumptions!D13-Drivers_MDA!F71)>0.01,1,0) -> 0 | H58: =IF(N(F58)=0,"PASS","FAIL") -> PASS | I58: F
A59: DRV: bandas de plausibilidad para constantes reportadas SIN tie posible — churn FY25 (0,5%], ARPU FY25 [20,80], ARPA FY25 [100,250], prepaid ARPU FY25 [20,60], empleados FY25 [30k,120k], FCF FY21 (0,30000], tasa efectiva de interés FY25 [2%,9%]. Caza corrupción gruesa, no un dígito plausible equivocado (patrón del check 61 del piloto). F es el conteo de incumplimientos | F59: =IF(OR(Drivers_MDA!F29<=0,Drivers_MDA!F29>0.05),1,0)+IF(OR(Drivers_MDA!F31<20,Drivers_MDA!F31>80),1,0)+IF(OR(Drivers_MDA!F33<100,Drivers_MDA!F33>250),1,0)+IF(OR(Drivers_MDA!F32<20,Drivers_MDA!F32>60),1,0)+IF(OR(Drivers_MDA!F134<30000,Drivers_MDA!F134>120000),1,0)+IF(OR(Drivers_MDA!B73<=0,Drivers_MDA!B73>30000),1,0)+IF(OR(Drivers_MDA!F99<0.02,Drivers_MDA!F99>0.09),1,0) -> 0 | H59: =IF(N(F59)=0,"PASS","FAIL") -> PASS | I59: F

Sheet Sources_Audited
A1: Audited source register — T-Mobile US consolidated statements (SEC EDGAR, CIK 0001283699)
A3: Model years | B3: Primary source | C3: Accession / file | D3: Detail level
A4: FY2023A-FY2025A | B4: FY2025 Form 10-K (filed 2026-02-11) — Consolidated Balance Sheets (R3.htm), Statements of Comprehensive Income (R5.htm), Cash Flows (R7.htm), Stockholders' Equity (R9.htm) | C4: 0001283699-26-000010; 10-K_2025-12-31 R-files {R3,R5,R7,R9}.htm | D4: Full line-item detail, filed constants
A5: FY2023A/FY2024A cross-check | B5: FY2024 Form 10-K (filed 2025-01-31) — Consolidated Balance Sheets sheet | C5: 0001283699-25-000012; .../10-K_2024-12-31_Financial_Report.xlsx, sheet "Consolidated Balance Sheets" | D5: Cross-check only; FY2025 10-K comparative column used as primary
A6: FY2021A/FY2022A | B6: SEC XBRL Company Facts API (aggregate history by us-gaap tag; no FY2021/FY2022 10-K R-files or Financial_Report.xlsx in source package) | C6: https://data.sec.gov/api/xbrl/companyfacts/CIK0001283699.json — accn 0001283699-22-000018 (FY2021 10-K) and 0001283699-23-000016 (FY2022 10-K), per individual tag | D6: Aggregate/summary level only, per line — see IS_Hist/BS_Hist/CF_Hist notes for exact tags and gaps
A8: Known gaps (honest, not filled with invented figures):
A9: 1) FY2021/FY2022 IS expense detail (SG&A/D&A/interest split, other income/expense split) — only aggregate CostsAndExpenses and an implied "other expense net" plug are available; component memo lines shown where a specific XBRL tag exists.
A10: 2) FY2021/FY2022 BS: Spectrum licenses vs. other non-current assets not separately tagged; combined into one aggregate line. Tower obligations / deferred tax liabilities (non-current) not separately tagged; folded into "Other long-term liabilities (aggregate)". FY2021 APIC vs. treasury stock split not available; shown as one combined plug (FY2022 has the exact split via the FY2023 10-K SCE opening balance).
A11: 3) FY2021/FY2022 CF: only CFO/CFI/CFF/FX totals from XBRL; no line-item detail (no 10-K R7 in package for those years).
A12: 4) FY2021 Stockholders' Equity roll-forward (SCE) not in source package (only FY2022 10-K forward has FY2022 activity, and it is not included either) — FY2021/FY2022 period-end balances are carried in BS_Hist; the audited SCE roll-forward starts at the Dec 31, 2022 opening balance per the FY2025 10-K R9.htm.
A14: Scale/units: all statement sheets are USD millions (as filed, "$ in Millions" per R-file headers), consistent with the 00_Cover/Historical/Sector_KPIs USD mm convention already in this workbook — no /1000 or unit-scale mismatch introduced.
A15: Currency: native reporting currency is USD; no FX/USD conversion layer required (rule 4 — FX layer only applies to non-USD-native models).
A17: ACTUALIZACIÓN 2026-08-14 — capa de cobertura agregada | B17: Drivers_MDA y Market_Package son hojas nuevas, aditivas y no destructivas. Drivers_MDA contiene constantes publicadas de los cinco 10-K locales (PDF, pdftotext -layout), enlaces vivos a las hojas históricas y cálculos; lo que T-Mobile no divulga queda NOT_AVAILABLE con razón, sin inventar ceros. Checks_TieOut pasó de 26 a 53 filas de status computables (27 nuevas, filas 33-59); el MASTER B2 amplió su rango (única celda preexistente modificada en el libro).
A18: ACTUALIZACIÓN 2026-08-14 — gap 1 (detalle IS FY21-22) parcialmente CERRADO | B18: El 10-K FY2022 (accn 0001283699-23-000016, PDF local tmus-20221231.pdf) SÍ trae el detalle FY2021-22: cost of services/equipment, SG&A, impairment, loss on disposal, D&A (suman exactamente al CostsAndExpenses agregado de IS_Hist!B11:C11) e Interest expense net / Other expense net (suman exactamente al plug de IS_Hist!B18:C18). Cargado en Drivers_MDA filas 54-66 con ties (checks 40-41). IS_Hist NO se modificó: la brecha se cierra en la capa de cobertura.
A19: ACTUALIZACIÓN 2026-08-14 — gaps 2 y 3 (BS/CF FY21-22) parcialmente CERRADOS | B19: Del mismo 10-K FY2022: spectrum licenses FY21-22 (92,606 / 95,798 — deja el residual de "otros activos no corrientes" del agregado BS_Hist!B20:C20 en 9,383 / 9,930), cash capex incl. interés capitalizado (12,326 / 13,970), purchases de spectrum (9,366 / 3,331), emisiones/repagos de deuda LP (14,727 / −11,100 y 3,714 / −5,556) y repagos de finance leases (−1,111 / −1,239). Todo en Drivers_MDA (filas 76, 80-84, 102-105, 131); BS_Hist y CF_Hist intactas. Sigue NO disponible: el roll-forward SCE FY2021 y el detalle línea a línea completo del CF FY21-22.
A20: ACTUALIZACIÓN 2026-08-14 — 10-Q Q2 2026 descargado directo de EDGAR | B20: Accn 0001283699-26-000101 (filed 2026-07-23, periodo 2026-06-30), tmus-20260630.htm — NO estaba en el paquete local (pull 2026-07-20/21). Solo alimenta Market_Package: acciones en circulación al 2026-07-17 (portada), 6M 2026/2025 para el memo LTM, balance al 2026-06-30 y las anclas de vintage distinto de la columna comparativa al 2025-12-31 (checks 52-54). NO entra en la historia auditada FY2021A-FY2025A.
A21: Datos de mercado fechados 2026-08-13 / 2026-08-14 | B21: Precio (stockanalysis.com, 2026-08-14), Rf (Tesoro EE.UU. CSV primario, 2026-08-13 — pin de flota de la corrida), ERP (Damodaran ene-2026), beta (stockanalysis 0.33; cross-checks Yahoo 0.33, investing.com 0.44), Kd (FRED BAMLC0A4CBBBEY BBB, 2026-08-13). Cada uno con fuente y fecha propias en Market_Package columnas D/E; control mecanizado en Market_Package!B97:B100 y check 57.

Sheet Drivers_MDA
A1: T-Mobile US — Drivers de negocio del MD&A y disclosures (FY2021A-FY2025A)
A2: USD millones salvo indicación. CAPA DE COBERTURA ADITIVA: no altera ninguna hoja histórica ni el DCF. Todo dato 'Reportado' es una constante publicada; todo 'Calculado' es fórmula viva; los 'Tie' deben ser 0. FY2021-22 se cubre desde los PDF locales de los 10-K (el paquete XBRL solo traía agregados — brechas de Sources_Audited cerradas aquí, no reescribiendo historia).
A4: Métrica | B4: FY2021A | C4: FY2022A | D4: FY2023A | E4: FY2024A | F4: FY2025A | G4: Unidad | H4: Fuente (documento - sección - accession) | I4: Estado
A6: 1. CLIENTES (fin de periodo, miles)
A7: Postpaid phone customers | B7: 70262 | C7: 72834 | D7: 75936 | E7: 79013 | F7: 85594 | G7: miles | H7: FY21-22: 10-K FY2022 (accn 0001283699-23-000016) Item 7 MD&A (FY2021 confirmado en 10-K FY2021, accn 0001283699-22-000018) | FY23-25: 10-K FY2025 (accn 0001283699-26-000010) Item 7 MD&A — tabla 'ending customers'. FY25 incluye 3,287k adquiridos de UScellular (Q3'25) | I7: Reportado
A8: Postpaid other customers | B8: 17401 | C8: 19398 | D8: 22116 | E8: 25105 | F8: 30851 | G8: miles | H8: FY21-22: 10-K FY2022 (accn 0001283699-23-000016) Item 7 MD&A (FY2021 confirmado en 10-K FY2021, accn 0001283699-22-000018) | FY23-25: 10-K FY2025 (accn 0001283699-26-000010) Item 7 MD&A — FY25 incluye 390k de UScellular, 755k fibra Metronet, 97k Lumos | I8: Reportado
A9: Total postpaid customers (reportado) | B9: 87663 | C9: 92232 | D9: 98052 | E9: 104118 | F9: 116445 | G9: miles | H9: FY21-22: 10-K FY2022 (accn 0001283699-23-000016) Item 7 MD&A (FY2021 confirmado en 10-K FY2021, accn 0001283699-22-000018) | FY23-25: 10-K FY2025 (accn 0001283699-26-000010) Item 7 MD&A | I9: Reportado
A10: Prepaid customers | B10: 21056 | C10: 21366 | D10: 21648 | E10: 25410 | F10: 25943 | G10: miles | H10: FY21-22: 10-K FY2022 (accn 0001283699-23-000016) Item 7 MD&A (FY2021 confirmado en 10-K FY2021, accn 0001283699-22-000018) | FY23-25: 10-K FY2025 (accn 0001283699-26-000010) Item 7 MD&A — FY24 incluye 3,504k de la Ka'ena Acquisition | I10: Reportado
A11: Total customers (reportado) | B11: 108719 | C11: 113598 | D11: 119700 | E11: 129528 | F11: 142388 | G11: miles | H11: FY21-22: 10-K FY2022 (accn 0001283699-23-000016) Item 7 MD&A (FY2021 confirmado en 10-K FY2021, accn 0001283699-22-000018) | FY23-25: 10-K FY2025 (accn 0001283699-26-000010) Item 7 MD&A | I11: Reportado
A12: Tie: phone + other − total postpaid | B12: =B7+B8-B9 -> 0 | C12: =C7+C8-C9 -> 0 | D12: =D7+D8-D9 -> 0 | E12: =E7+E8-E9 -> 0 | F12: =F7+F8-F9 -> 0 | G12: miles | H12: Aditividad de la tabla publicada (constantes independientes) | I12: Tie (debe ser 0)
A13: Tie: postpaid + prepaid − total customers | B13: =B9+B10-B11 -> 0 | C13: =C9+C10-C11 -> 0 | D13: =D9+D10-D11 -> 0 | E13: =E9+E10-E11 -> 0 | F13: =F9+F10-F11 -> 0 | G13: miles | H13: Aditividad de la tabla publicada | I13: Tie (debe ser 0)
A14: Tie: postpaid phone (mm) − Sector_KPIs FY23-25 | D14: =D7/1000-Sector_KPIs!C5 -> 0 | E14: =E7/1000-Sector_KPIs!D5 -> 0 | F14: =F7/1000-Sector_KPIs!E5 -> 0 | G14: mm | H14: Sector_KPIs!C5:E5 (constantes de la Ola 1, entrada independiente) | I14: Tie (debe ser 0)
A15: Memo: clientes 5G broadband dentro de postpaid other | E15: 5742 | F15: 7602 | G15: miles | H15: 10-K FY2025 (accn 0001283699-26-000010) Item 7 — solo divulgado FY2024-25 | I15: Reportado (solo FY24-25)
A16: Memo: clientes de fibra dentro de postpaid other | F16: 997 | G16: miles | H16: 10-K FY2025 (accn 0001283699-26-000010) Item 7 — solo FY2025 | I16: Reportado (solo FY25)
A18: Adiciones netas y ajustes a la base (miles)
A19: Postpaid phone net customer additions | B19: 2917 | C19: 3093 | D19: 3082 | E19: 3077 | F19: 3294 | G19: miles | H19: FY21-22: 10-K FY2022 (accn 0001283699-23-000016) Item 7 MD&A (FY2021 confirmado en 10-K FY2021, accn 0001283699-22-000018) | FY23-25: 10-K FY2025 (accn 0001283699-26-000010) Item 7 MD&A — tabla 'net customer additions' | I19: Reportado
A20: Postpaid other net customer additions | B20: 2578 | C20: 3326 | D20: 2568 | E20: 2989 | F20: 4504 | G20: miles | H20: FY21-22: 10-K FY2022 (accn 0001283699-23-000016) Item 7 MD&A (FY2021 confirmado en 10-K FY2021, accn 0001283699-22-000018) | FY23-25: 10-K FY2025 (accn 0001283699-26-000010) Item 7 MD&A | I20: Reportado
A21: Total postpaid net additions (reportado) | B21: 5495 | C21: 6419 | D21: 5650 | E21: 6066 | F21: 7798 | G21: miles | H21: FY21-22: 10-K FY2022 (accn 0001283699-23-000016) Item 7 MD&A (FY2021 confirmado en 10-K FY2021, accn 0001283699-22-000018) | FY23-25: 10-K FY2025 (accn 0001283699-26-000010) Item 7 MD&A | I21: Reportado
A22: Prepaid net customer additions | B22: 342 | C22: 338 | D22: 282 | E22: 258 | F22: 184 | G22: miles | H22: FY21-22: 10-K FY2022 (accn 0001283699-23-000016) Item 7 MD&A (FY2021 confirmado en 10-K FY2021, accn 0001283699-22-000018) | FY23-25: 10-K FY2025 (accn 0001283699-26-000010) Item 7 MD&A | I22: Reportado
A23: Total net customer additions (reportado) | B23: 5837 | C23: 6757 | D23: 5932 | E23: 6324 | F23: 7982 | G23: miles | H23: FY21-22: 10-K FY2022 (accn 0001283699-23-000016) Item 7 MD&A (FY2021 confirmado en 10-K FY2021, accn 0001283699-22-000018) | FY23-25: 10-K FY2025 (accn 0001283699-26-000010) Item 7 MD&A | I23: Reportado
A24: Ajustes a la base (adquisiciones / base adjustments) | B24: 818 | C24: -1878 | D24: 170 | E24: 3504 | F24: 4878 | G24: miles | H24: FY21-22: 10-K FY2022 (accn 0001283699-23-000016) Item 7 MD&A (FY2021 confirmado en 10-K FY2021, accn 0001283699-22-000018) | FY23-25: 10-K FY2025 (accn 0001283699-26-000010) Item 7 MD&A — fila 'Adjustments to customers' (FY22 negativo por decomisionar redes legacy Sprint; FY24 Ka'ena; FY25 UScellular/Metronet/Lumos) | I24: Reportado
A25: Tie: componentes − total net additions | B25: =B19+B20+B22-B23 -> 0 | C25: =C19+C20+C22-C23 -> 0 | D25: =D19+D20+D22-D23 -> 0 | E25: =E19+E20+E22-E23 -> 0 | F25: =F19+F20+F22-F23 -> 0 | G25: miles | H25: Aditividad de la tabla publicada | I25: Tie (debe ser 0)
A26: Tie: roll-forward de la base (fin = inicio + adds netos + ajustes) | C26: =B11+C23+C24-C11 -> 0 | D26: =C11+D23+D24-D11 -> 0 | E26: =D11+E23+E24-E11 -> 0 | F26: =E11+F23+F24-F11 -> 0 | G26: miles | H26: Continuidad entre tablas publicadas de años consecutivos — todo constantes | I26: Tie (debe ser 0)
A28: 2. CHURN, ARPU Y ARPA
A29: Postpaid phone churn | B29: 0.0098 | C29: 0.0088 | D29: 0.0087 | E29: 0.0086 | F29: 0.0093 | G29: % / mes | H29: FY21-22: 10-K FY2022 (accn 0001283699-23-000016) Item 7 MD&A (FY2021 confirmado en 10-K FY2021, accn 0001283699-22-000018) | FY23-25: 10-K FY2025 (accn 0001283699-26-000010) Item 7 MD&A — tabla 'churn' | I29: Reportado
A30: Prepaid churn | B30: 0.0283 | C30: 0.0277 | D30: 0.0276 | E30: 0.0273 | F30: 0.0272 | G30: % / mes | H30: FY21-22: 10-K FY2022 (accn 0001283699-23-000016) Item 7 MD&A (FY2021 confirmado en 10-K FY2021, accn 0001283699-22-000018) | FY23-25: 10-K FY2025 (accn 0001283699-26-000010) Item 7 MD&A | I30: Reportado
A31: Postpaid phone ARPU | B31: 47.75 | C31: 48.78 | D31: 48.83 | E31: 49.35 | F31: 50.37 | G31: USD / mes | H31: FY21-22: 10-K FY2022 (accn 0001283699-23-000016) Item 7 MD&A (FY2021 confirmado en 10-K FY2021, accn 0001283699-22-000018) | FY23-25: 10-K FY2025 (accn 0001283699-26-000010) Item 7 MD&A — tabla 'ARPU' | I31: Reportado
A32: Prepaid ARPU | B32: 38.79 | C32: 38.76 | D32: 37.92 | E32: 36.06 | F32: 34.14 | G32: USD / mes | H32: FY21-22: 10-K FY2022 (accn 0001283699-23-000016) Item 7 MD&A (FY2021 confirmado en 10-K FY2021, accn 0001283699-22-000018) | FY23-25: 10-K FY2025 (accn 0001283699-26-000010) Item 7 MD&A | I32: Reportado
A33: Postpaid ARPA (por cuenta) | B33: 134.03 | C33: 137.43 | D33: 139.27 | E33: 143.85 | F33: 148.97 | G33: USD / mes | H33: FY21-22: 10-K FY2022 (accn 0001283699-23-000016) Item 7 MD&A (FY2021 confirmado en 10-K FY2021, accn 0001283699-22-000018) | FY23-25: 10-K FY2025 (accn 0001283699-26-000010) Item 7 MD&A — tabla 'ARPA'. OJO: ARPA es por CUENTA; churn y ARPU son de postpaid phone (limitación declarada en 00_Cover!B16) | I33: Reportado
A34: Tie: churn postpaid phone − Sector_KPIs FY23-25 | D34: =D29-Sector_KPIs!C7 -> 0 | E34: =E29-Sector_KPIs!D7 -> 0 | F34: =F29-Sector_KPIs!E7 -> 0 | G34: % / mes | H34: Sector_KPIs!C7:E7 | I34: Tie (debe ser 0)
A35: Tie: ARPU postpaid phone − Sector_KPIs FY23-25 | D35: =D31-Sector_KPIs!C9 -> 0 | E35: =E31-Sector_KPIs!D9 -> 0 | F35: =F31-Sector_KPIs!E9 -> 0 | G35: USD / mes | H35: Sector_KPIs!C9:E9 | I35: Tie (debe ser 0)
A36: Cuentas postpaid implícitas (ingresos postpaid / ARPA / 12) | B36: =B39/(B33*12) -> 26.462981 | C36: =C39/(C33*12) -> 27.843872 | D36: =D39/(D33*12) -> 29.135253 | E36: =E39/(E33*12) -> 30.320936 | F36: =F39/(F33*12) -> 32.406972 | G36: mm cuentas | H36: Derivación del analista: T-Mobile no tabula el conteo de cuentas en el 10-K FY2025 | I36: Calculado (implícito)
A38: 3. INGRESOS POR COMPONENTE (USD mm)
A39: Postpaid revenues | B39: 42562 | C39: 45919 | D39: 48692 | E39: 52340 | F39: 57932 | G39: USD m | H39: FY21-22: 10-K FY2022 (accn 0001283699-23-000016) Item 7 MD&A (FY2021 confirmado en 10-K FY2021, accn 0001283699-22-000018) | FY23-25: 10-K FY2025 (accn 0001283699-26-000010) Item 7 MD&A — 'Results of Operations', estado de resultados por componente | I39: Reportado
A40: Prepaid revenues | B40: 9733 | C40: 9857 | D40: 9767 | E40: 10399 | F40: 10497 | G40: USD m | H40: FY21-22: 10-K FY2022 (accn 0001283699-23-000016) Item 7 MD&A (FY2021 confirmado en 10-K FY2021, accn 0001283699-22-000018) | FY23-25: 10-K FY2025 (accn 0001283699-26-000010) Item 7 MD&A | I40: Reportado
A41: Wholesale and other service revenues | B41: 6074 | C41: 5547 | D41: 4782 | E41: 3439 | F41: 2877 | G41: USD m | H41: FY21-22: 10-K FY2022 (accn 0001283699-23-000016) Item 7 MD&A (FY2021 confirmado en 10-K FY2021, accn 0001283699-22-000018) | FY23-25: 10-K FY2025 (accn 0001283699-26-000010) Item 7 MD&A | I41: Reportado
A42: Total service revenues (reportado) | B42: 58369 | C42: 61323 | D42: 63241 | E42: 66178 | F42: 71306 | G42: USD m | H42: FY21-22: 10-K FY2022 (accn 0001283699-23-000016) Item 7 MD&A (FY2021 confirmado en 10-K FY2021, accn 0001283699-22-000018) | FY23-25: 10-K FY2025 (accn 0001283699-26-000010) Item 7 MD&A | I42: Reportado
A43: Equipment revenues | B43: 20727 | C43: 17130 | D43: 14138 | E43: 14263 | F43: 15972 | G43: USD m | H43: FY21-22: 10-K FY2022 (accn 0001283699-23-000016) Item 7 MD&A (FY2021 confirmado en 10-K FY2021, accn 0001283699-22-000018) | FY23-25: 10-K FY2025 (accn 0001283699-26-000010) Item 7 MD&A | I43: Reportado
A44: Other revenues | B44: 1022 | C44: 1118 | D44: 1179 | E44: 959 | F44: 1031 | G44: USD m | H44: FY21-22: 10-K FY2022 (accn 0001283699-23-000016) Item 7 MD&A (FY2021 confirmado en 10-K FY2021, accn 0001283699-22-000018) | FY23-25: 10-K FY2025 (accn 0001283699-26-000010) Item 7 MD&A | I44: Reportado
A45: Total revenues (reportado) | B45: 80118 | C45: 79571 | D45: 78558 | E45: 81400 | F45: 88309 | G45: USD m | H45: FY21-22: 10-K FY2022 (accn 0001283699-23-000016) Item 7 MD&A (FY2021 confirmado en 10-K FY2021, accn 0001283699-22-000018) | FY23-25: 10-K FY2025 (accn 0001283699-26-000010) Item 7 MD&A | I45: Reportado
A46: Tie: componentes de servicio − total service revenues | B46: =B39+B40+B41-B42 -> 0 | C46: =C39+C40+C41-C42 -> 0 | D46: =D39+D40+D41-D42 -> 0 | E46: =E39+E40+E41-E42 -> 0 | F46: =F39+F40+F41-F42 -> 0 | G46: USD m | H46: Aditividad del estado publicado | I46: Tie (debe ser 0)
A47: Tie: servicio + equipo + otros − total revenues | B47: =B42+B43+B44-B45 -> 0 | C47: =C42+C43+C44-C45 -> 0 | D47: =D42+D43+D44-D45 -> 0 | E47: =E42+E43+E44-E45 -> 0 | F47: =F42+F43+F44-F45 -> 0 | G47: USD m | H47: Aditividad del estado publicado | I47: Tie (debe ser 0)
A48: Tie: total revenues − IS_Hist (CIERRE DE BRECHA: el split FY21-22 no estaba en el paquete XBRL) | B48: =B45-IS_Hist!B5 -> 0 | C48: =C45-IS_Hist!C5 -> 0 | D48: =D45-IS_Hist!D5 -> 0 | E48: =E45-IS_Hist!E5 -> 0 | F48: =F45-IS_Hist!F5 -> 0 | G48: USD m | H48: IS_Hist!B5:F5 (XBRL / R5.htm) vs constantes del 10-K FY2022 PDF — dos rutas de fuente | I48: Tie (debe ser 0)
A49: Tie: ingresos FY23-25 − Sector_KPIs (postpaid svc, total svc, equipo+otros) | D49: =ABS(D39-Sector_KPIs!C11)+ABS(D42-Sector_KPIs!C14)+ABS(D43+D44-Sector_KPIs!C15) -> 0 | E49: =ABS(E39-Sector_KPIs!D11)+ABS(E42-Sector_KPIs!D14)+ABS(E43+E44-Sector_KPIs!D15) -> 0 | F49: =ABS(F39-Sector_KPIs!E11)+ABS(F42-Sector_KPIs!E14)+ABS(F43+F44-Sector_KPIs!E15) -> 0 | G49: USD m | H49: Sector_KPIs!C11:E11, C14:E14, C15:E15 | I49: Tie (debe ser 0)
A50: Mix: servicio / total | B50: =B42/B45 -> 0.72853791 | C50: =C42/C45 -> 0.77067022 | D50: =D42/D45 -> 0.80502304 | E50: =E42/E45 -> 0.81299754 | F50: =F42/F45 -> 0.80746017 | G50: % | I50: Calculado
A51: YoY ingresos totales | B51: n.a. | C51: =C45/B45-1 -> -0.0068274295 | D51: =D45/C45-1 -> -0.012730769 | E51: =E45/D45-1 -> 0.036177092 | F51: =F45/E45-1 -> 0.08487715 | G51: % | I51: Calculado
A52: YoY ingresos de servicio | B52: n.a. | C52: =C42/B42-1 -> 0.050609056 | D52: =D42/C42-1 -> 0.031277009 | E52: =E42/D42-1 -> 0.046441391 | F52: =F42/E42-1 -> 0.077487987 | G52: % | I52: Calculado
A54: 4. DETALLE DE OPEX E INTERESES (cierre parcial de los gaps 1 y 3 de Sources_Audited — capa de cobertura; IS_Hist intacta)
A55: Cost of services (excl. D&A) | B55: 13934 | C55: 14666 | D55: 11655 | E55: 10771 | F55: 11497 | G55: USD m | H55: FY21-22: 10-K FY2022 (accn 0001283699-23-000016) Item 7 MD&A (FY2021 confirmado en 10-K FY2021, accn 0001283699-22-000018) | FY23-25: 10-K FY2025 (accn 0001283699-26-000010) Item 7 MD&A — estado de resultados | I55: Reportado
A56: Cost of equipment sales (excl. D&A) | B56: 22671 | C56: 21540 | D56: 18533 | E56: 18882 | F56: 21277 | G56: USD m | H56: FY21-22: 10-K FY2022 (accn 0001283699-23-000016) Item 7 MD&A (FY2021 confirmado en 10-K FY2021, accn 0001283699-22-000018) | FY23-25: 10-K FY2025 (accn 0001283699-26-000010) Item 7 MD&A | I56: Reportado
A57: Selling, general and administrative | B57: 20238 | C57: 21607 | D57: =IS_Hist!D7 -> 21311 | E57: =IS_Hist!E7 -> 20818 | F57: =IS_Hist!F7 -> 23470 | G57: USD m | H57: FY21-22: 10-K FY2022 (accn 0001283699-23-000016); FY23-25: enlace vivo a IS_Hist!D7:F7 | I57: Reportado FY21-22 / Enlace vivo FY23-25
A58: Impairment expense | B58: 0 | C58: 477 | D58: 0 | E58: 0 | F58: 278 | G58: USD m | H58: FY21-22: 10-K FY2022 (accn 0001283699-23-000016) Item 7 MD&A (FY2021 confirmado en 10-K FY2021, accn 0001283699-22-000018) | FY23-25: 10-K FY2025 (accn 0001283699-26-000010) Item 7 MD&A | I58: Reportado
A59: (Gain) / loss on disposal group held for sale | B59: 0 | C59: 1087 | D59: -25 | E59: 0 | F59: 0 | G59: USD m | H59: FY21-22: 10-K FY2022 (accn 0001283699-23-000016) Item 7 MD&A (FY2021 confirmado en 10-K FY2021, accn 0001283699-22-000018) | FY23-25: 10-K FY2025 (accn 0001283699-26-000010) Item 7 MD&A — FY22 loss 1,087 (wireline); FY23 gain (25) | I59: Reportado
A60: Depreciation and amortization | B60: 16383 | C60: 13651 | D60: 12818 | E60: 12919 | F60: 13508 | G60: USD m | H60: FY21-22: 10-K FY2022 (accn 0001283699-23-000016) Item 7 MD&A (FY2021 confirmado en 10-K FY2021, accn 0001283699-22-000018) | FY23-25: 10-K FY2025 (accn 0001283699-26-000010) Item 7 MD&A | I60: Reportado
A61: Total opex (calc) | B61: =SUM(B55:B60) -> 73226 | C61: =SUM(C55:C60) -> 73028 | D61: =SUM(D55:D60) -> 64292 | E61: =SUM(E55:E60) -> 63390 | F61: =SUM(F55:F60) -> 70030 | G61: USD m | I61: Calculado
A62: Tie: opex detalle − IS_Hist (FY21-22 vs agregado CostsAndExpenses; FY23-25 vs total filed) | B62: =B61-IS_Hist!B11 -> 0 | C62: =C61-IS_Hist!C11 -> 0 | D62: =D61-IS_Hist!D13 -> 0 | E62: =E61-IS_Hist!E13 -> 0 | F62: =F61-IS_Hist!F13 -> 0 | G62: USD m | H62: IS_Hist!B11:C11 (XBRL agregado) y D13:F13 (filed) — constantes del PDF vs dos rutas de fuente | I62: Tie (debe ser 0)
A63: HALLAZGO: IS_Hist!D12 (residual FY23) difiere del costo real de servicios+equipo en 50 (resta el gain de -25 con signo invertido); FY24-25 cuadran | D63: =D55+D56-IS_Hist!D12 -> 50 | E63: =E55+E56-IS_Hist!E12 -> 0 | F63: =F55+F56-IS_Hist!F12 -> 0 | G63: USD m | H63: 10-K FY2025 estado de resultados (11,655+18,533=30,188) vs IS_Hist!D12 (30,138). Declarado, NO corregido: IS_Hist es historia gateada | I63: Calculado — HALLAZGO declarado
A64: Interest expense, net | B64: -3342 | C64: -3364 | D64: =IS_Hist!D16 -> -3335 | E64: =IS_Hist!E16 -> -3411 | F64: =IS_Hist!F16 -> -3774 | G64: USD m | H64: FY21-22: 10-K FY2022 (accn 0001283699-23-000016) estado de resultados; FY23-25: enlace vivo | I64: Reportado FY21-22 / Enlace vivo FY23-25
A65: Other (expense) income, net | B65: -199 | C65: -33 | D65: =IS_Hist!D17 -> 68 | E65: =IS_Hist!E17 -> 113 | F65: =IS_Hist!F17 -> -224 | G65: USD m | H65: Igual que la fila 64 | I65: Reportado FY21-22 / Enlace vivo FY23-25
A66: Tie FY21-22: intereses + otros − agregado IS_Hist (cierra el plug "other expense net") | B66: =B64+B65-IS_Hist!B18 -> 0 | C66: =C64+C65-IS_Hist!C18 -> 0 | G66: USD m | H66: IS_Hist!B18:C18 (plug implícito del XBRL) vs detalle del PDF | I66: Tie (debe ser 0)
A68: 5. NO-GAAP REPORTADOS EN EL MD&A: ADJUSTED EBITDA, CORE ADJUSTED EBITDA, FREE CASH FLOW
A69: Adjusted EBITDA (reportado) | B69: 26924 | C69: 27821 | D69: 29428 | E69: 31864 | F69: 33937 | G69: USD m | H69: FY21-22: 10-K FY2022 (accn 0001283699-23-000016) Item 7 MD&A (FY2021 confirmado en 10-K FY2021, accn 0001283699-22-000018) | FY23-25: 10-K FY2025 (accn 0001283699-26-000010) Item 7 MD&A — reconciliación a Net income | I69: Reportado
A70: Core Adjusted EBITDA (reportado) | B70: 23576 | C70: 26391 | D70: 29116 | E70: 31771 | F70: 33924 | G70: USD m | H70: FY21-22: 10-K FY2022 (accn 0001283699-23-000016) Item 7 MD&A (FY2021 confirmado en 10-K FY2021, accn 0001283699-22-000018) | FY23-25: 10-K FY2025 (accn 0001283699-26-000010) Item 7 MD&A — Adjusted EBITDA menos lease revenues | I70: Reportado
A71: Margen Adjusted EBITDA / service revenues (calc) | B71: =B69/B42 -> 0.46127225 | C71: =C69/C42 -> 0.4536797 | D71: =D69/D42 -> 0.46533104 | E71: =E69/E42 -> 0.48148932 | F71: =F69/F42 -> 0.4759347 | G71: % | I71: Calculado
A72: Tie: Adjusted EBITDA − Sector_KPIs FY23-25 | D72: =D69-Sector_KPIs!C18 -> 0 | E72: =E69-Sector_KPIs!D18 -> 0 | F72: =F69-Sector_KPIs!E18 -> 0 | G72: USD m | H72: Sector_KPIs!C18:E18 | I72: Tie (debe ser 0)
A73: Free Cash Flow reportado (definición del año: FY21-22 "Free Cash Flow"; FY23-25 "Adjusted Free Cash Flow") | B73: 5646 | C73: 7656 | D73: 13586 | E73: 17032 | F73: 17995 | G73: USD m | H73: FY21-22: 10-K FY2022 (accn 0001283699-23-000016) — resta ademas debt prepayment costs (FY21 -116); FY23-25: 10-K FY2025 (accn 0001283699-26-000010) | I73: Reportado
A74: Recompute FCF FY23-25 desde CF_Hist (CFO − capex + torres + securitización) | D74: =CF_Hist!D25+CF_Hist!D28+N(CF_Hist!D31)+N(CF_Hist!D32) -> 13586 | E74: =CF_Hist!E25+CF_Hist!E28+N(CF_Hist!E31)+N(CF_Hist!E32) -> 17032 | F74: =CF_Hist!F25+CF_Hist!F28+N(CF_Hist!F31)+N(CF_Hist!F32) -> 17995 | G74: USD m | H74: CF_Hist filas 25/28/31/32 — líneas del estado auditado | I74: Calculado
A75: Tie: FCF reportado − recompute (FY23-25) | D75: =D73-D74 -> 0 | E75: =E73-E74 -> 0 | F75: =F73-F74 -> 0 | G75: USD m | H75: Tabla del MD&A vs líneas del CF auditado — dos tablas del filing | I75: Tie (debe ser 0)
A76: Cash capex, incl. interés capitalizado | B76: 12326 | C76: 13970 | D76: =-CF_Hist!D28 -> 9801 | E76: =-CF_Hist!E28 -> 8840 | F76: =-CF_Hist!F28 -> 9955 | G76: USD m | H76: FY21-22: 10-K FY2022 (accn 0001283699-23-000016) tabla FCF (cierra parte del gap 3); FY23-25: enlace vivo (salida con signo invertido) | I76: Reportado FY21-22 / Enlace vivo FY23-25
A77: Capex / ingresos totales | B77: =B76/B45 -> 0.15384807 | C77: =C76/C45 -> 0.17556648 | D77: =D76/D45 -> 0.12476132 | E77: =E76/E45 -> 0.10859951 | F77: =F76/F45 -> 0.11272917 | G77: % | I77: Calculado
A79: 6. ESPECTRO (licencias y leases)
A80: Spectrum licenses (balance) | B80: 92606 | C80: 95798 | D80: 96707 | E80: 100558 | F80: 98032 | G80: USD m | H80: FY21-22: 10-K FY2022 (accn 0001283699-23-000016) balance; FY23: 10-K FY2024 (accn 0001283699-25-000012) balance; FY24-25: 10-K FY2025 (accn 0001283699-26-000010) balance — constantes del PDF | I80: Reportado
A81: Tie: spectrum FY23-25 − BS_Hist | D81: =D80-BS_Hist!D18 -> 0 | E81: =E80-BS_Hist!E18 -> 0 | F81: =F80-BS_Hist!F18 -> 0 | G81: USD m | H81: BS_Hist!D18:F18 (R3/Financial_Report) vs PDF — dos rutas | I81: Tie (debe ser 0)
A82: Memo: residual "otros activos no corrientes" FY21-22 (cierra parte del gap 2) | B82: =BS_Hist!B20-B80 -> 9383 | C82: =BS_Hist!C20-C80 -> 9930 | G82: USD m | H82: BS_Hist!B20:C20 (agregado spectrum+otros) menos el spectrum ahora conocido: 9,383 / 9,930 | I82: Calculado
A83: Purchases of spectrum licenses and other intangibles (CF, salida en positivo) | B83: 9366 | C83: 3331 | D83: 1010 | E83: 3471 | F83: 2568 | G83: USD m | H83: FY21-22: 10-K FY2022 (accn 0001283699-23-000016) CF (FY21 incluye C-band Auction 107); FY23-25: 10-K FY2025 (accn 0001283699-26-000010) CF | I83: Reportado
A84: Tie: purchases FY23-25 + CF_Hist (línea negativa) | D84: =D83+CF_Hist!D29 -> 0 | E84: =E83+CF_Hist!E29 -> 0 | F84: =F83+CF_Hist!F29 -> 0 | G84: USD m | H84: CF_Hist!D29:F29 | I84: Tie (debe ser 0)
A85: Memo: favorable spectrum leases (intangible, neto FY25) | F85: 380 | G85: USD m | H85: 10-K FY2025 (accn 0001283699-26-000010) nota de intangibles — hasta 27 años | I85: Reportado (solo FY25)
A87: 7. DEUDA Y REFINANCIAMIENTO
A88: Nota de deuda (carrying, USD mm) — FY2023 del 10-K FY2024; FY2024-25 del 10-K FY2025:
A89: Total debt (nota de deuda) | D89: 75018 | E89: 78265 | F89: 86282 | G89: USD m | H89: FY23: 10-K FY2024 (accn 0001283699-25-000012) Nota de deuda; FY24-25: 10-K FY2025 (accn 0001283699-26-000010) Nota 9 'Debt' | I89: Reportado
A90: Porción corriente de Senior Notes | D90: 3619 | E90: 4068 | F90: 5135 | G90: USD m | H90: Misma nota: "Less: Current portion of Senior Notes" | I90: Reportado
A91: Total long-term debt (nota) | D91: 71399 | E91: 74197 | F91: 81147 | G91: USD m | H91: Misma nota | I91: Reportado
A92: Long-term debt a terceros | E92: 72700 | F92: 79649 | G92: USD m | H92: 10-K FY2025 (accn 0001283699-26-000010) Nota 9 — clasificación del LT debt | I92: Reportado (FY24-25)
A93: Long-term debt a afiliadas (Deutsche Telekom) | E93: 1497 | F93: 1498 | G93: USD m | H93: Misma nota. Redimidas a la par el 2026-02-01 (evento posterior) | I93: Reportado (FY24-25)
A94: Tie: total − corriente − LT (nota internamente) | D94: =D89-D90-D91 -> 0 | E94: =E89-E90-E91 -> 0 | F94: =F89-F90-F91 -> 0 | G94: USD m | I94: Tie (debe ser 0)
A95: Tie: total de la nota − Historical (XBRL us-gaap:LongTermDebt) | D95: =D89-Historical!C14 -> 0 | E95: =E89-Historical!D14 -> 0 | F95: =F89-Historical!E14 -> 0 | G95: USD m | H95: Historical!C14:E14 — la nota del PDF y el tag XBRL deben coincidir | I95: Tie (debe ser 0)
A96: Tie: terceros + afiliadas − total LT (FY24-25) | E96: =E92+E93-E91 -> 0 | F96: =F92+F93-F91 -> 0 | G96: USD m | I96: Tie (debe ser 0)
A97: HALLAZGO (verificación): ShortTermBorrowings del modelo ES la porción corriente de la nota | D97: =Historical!C15-D90 -> 0 | E97: =Historical!D15-E90 -> 0 | F97: =Historical!E15-F90 -> 0 | G97: USD m | H97: Historical!C15:E15 vs fila 90 — cero en los tres años: son la MISMA cifra | I97: Calculado — evidencia del hallazgo
A98: HALLAZGO cuantificado: exceso del puente de deuda del DCF (double-count de la porción corriente) | D98: =Historical!C18-(D89+Historical!C16) -> 3619 | E98: =Historical!D18-(E89+Historical!D16) -> 4068 | F98: =Historical!E18-(F89+Historical!E16) -> 5135 | G98: USD m | H98: Historical!E18 (=LongTermDebt+ShortTermBorrowings+FinanceLease) vs total de la nota + finance leases. FY23 3,619 / FY24 4,068 / FY25 5,135. Detalle y efecto en Market_Package (H1) | I98: Calculado — HALLAZGO declarado
A99: Tasa de interés efectiva aprox. (excl. derivados e interés capitalizado) | E99: 0.041 | F99: 0.042 | G99: % | H99: 10-K FY2025 (accn 0001283699-26-000010) Nota 9 | I99: Reportado (FY24-25)
A100: Deuda promedio ponderada del año | E100: 78.3 | F100: 83 | G100: USD bn | H100: Misma nota | I100: Reportado (FY24-25)
A101: Deuda denominada en EUR | F101: 4.8 | G101: EUR bn | H101: 10-K FY2025 (accn 0001283699-26-000010) Item 7A — exposición FX declarada | I101: Reportado (solo FY25)
A102: Proceeds from issuance of long-term debt, net (CF) | B102: 14727 | C102: 3714 | D102: 8446 | E102: 8587 | F102: 12010 | G102: USD m | H102: FY21-22: 10-K FY2022 (accn 0001283699-23-000016) CF; FY23-25: 10-K FY2025 (accn 0001283699-26-000010) CF | I102: Reportado
A103: Tie: emisiones FY23-25 − CF_Hist | D103: =D102-CF_Hist!D39 -> 0 | E103: =E102-CF_Hist!E39 -> 0 | F103: =F102-CF_Hist!F39 -> 0 | G103: USD m | I103: Tie (debe ser 0)
A104: Repayments of long-term debt (CF) | B104: -11100 | C104: -5556 | D104: -5051 | E104: -5073 | F104: -6199 | G104: USD m | H104: Mismas fuentes que la fila 102 | I104: Reportado
A105: Tie: repagos FY23-25 − CF_Hist | D105: =D104-CF_Hist!D41 -> 0 | E105: =E104-CF_Hist!E41 -> 0 | F105: =F104-CF_Hist!F41 -> 0 | G105: USD m | I105: Tie (debe ser 0)
A106: Refi FY2025: emitió USD 12.0 bn de deuda LP neta (incl. dos ECA facilities por ~2.0 bn) y redimió/repagó USD 6.2 bn de principal agregado | H106: 10-K FY2025 (accn 0001283699-26-000010) MD&A Liquidity y Nota 9 | I106: Reportado (narrativa)
A107: Refi posterior al cierre: 2026-02-01 redimió a la par las Senior Notes 4.750% a afiliadas due 2028; 2026-02-05 tomó USD 1.0 bn bajo un master receivables financing agreement con vencimiento 2027-02-05 | H107: 10-K FY2025 (accn 0001283699-26-000010) Nota 9 / eventos posteriores | I107: Reportado (narrativa)
A109: 8. ESCALERA CONTRACTUAL AL 2025-12-31 — OJO: columnas = buckets de vencimiento, NO años fiscales
A110: (USD mm) | B110: < 1 año | C110: 1-3 años | D110: 3-5 años | E110: > 5 años | F110: Total | H110: 10-K FY2025 (accn 0001283699-26-000010) Item 7 MD&A — 'material contractual obligations and borrowings'
...

Sheet Market_Package
A1: T-Mobile US — Paquete de mercado fechado y costo de capital
A2: Cada input de mercado lleva su fuente y su FECHA. Los enlaces al balance y a resultados son fórmulas vivas contra las hojas auditadas (que esta hoja NO modifica). El libro omitía la comparación de mercado por política de carril; esta hoja la aporta fechada, sin cablearla al DCF.
A4: Concepto | B4: Valor | C4: Unidad | D4: Fecha del dato (as-of) | E4: Fuente | F4: Nota / método
A6: 1. PRECIO Y ACCIONES
A7: Precio de la acción (cierre) | B7: 182.61 | C7: USD/acción | D7: 46248 | E7: stockanalysis.com/stocks/TMUS/ — cierre diario | F7: Recuperado 2026-08-14 tras la campana. Cruce interno: market cap del proveedor 195.88 bn = 182.61 x 1,072.67 mm acciones del 10-Q, consistente
A8: Acciones en circulación | B8: 1072.6716 | C8: millones de acciones | D8: 46220 | E8: SEC Form 10-Q Q2 2026, portada (accn 0001283699-26-000101) — "Shares Outstanding as of July 17, 2026" | F8: 1,072,671,613 acciones. Filing descargado directo de EDGAR el 2026-08-14 (filed 2026-07-23; no estaba en el paquete local, pull 2026-07-20/21)
A9: Memo — acciones diluidas promedio FY2025A | B9: =Historical!E17 -> 1131.0763 | C9: millones de acciones | D9: 46022 | E9: Historical!E17 (enlace vivo) | F9: Es la base por acción de Valuation!B19:B20
A10: Memo — brecha de conteo (portada 10-Q − promedio diluido FY25) | B10: =B8-B9 -> -58.404638 | C10: millones de acciones | E10: Calculado | F10: HALLAZGO H2: los buybacks ya retiraron ~5.2% del conteo FY2025A; el DCF por acción usa el promedio diluido FY2025A
A11: Capitalización de mercado | B11: =B7*B8 -> 195880.56 | C11: USD m | D11: =D7 -> 46248 | E11: Calculado: precio x acciones en circulación
A13: 2. PUENTE A ENTERPRISE VALUE (balance FY2025A del propio modelo)
A14: Caja y equivalentes | B14: =BS_Hist!F6 -> 5598 | C14: USD m | D14: 46022 | E14: BS_Hist!F6 — 10-K FY2025, balance auditado (enlace vivo)
A15: Deuda de corto plazo (incl. porción corriente de Senior Notes) | B15: =BS_Hist!F27 -> 5135 | C15: USD m | D15: 46022 | E15: BS_Hist!F27 (enlace vivo)
A16: Deuda de largo plazo (incl. afiliadas 1,498) | B16: =BS_Hist!F34 -> 81147 | C16: USD m | D16: 46022 | E16: BS_Hist!F34 (enlace vivo)
A17: Finance lease liabilities — corriente | B17: =BS_Hist!F30 -> 1163 | C17: USD m | D17: 46022 | E17: BS_Hist!F30 (enlace vivo)
A18: Finance lease liabilities — no corriente | B18: =BS_Hist!F38 -> 1107 | C18: USD m | D18: 46022 | E18: BS_Hist!F38 (enlace vivo)
A19: Deuda bruta (balance, SIN doble conteo) | B19: =SUM(B15:B18) -> 88552 | C19: USD m | D19: 46022 | E19: Calculado | F19: 5,135 + 81,147 + 1,163 + 1,107 = 88,552
A20: Memo — deuda usada hoy en el DCF (Valuation!B17) | B20: =Historical!E18 -> 93687 | C20: USD m | D20: 46022 | E20: Historical!E18 (enlace vivo) | F20: = LongTermDebt + ShortTermBorrowings + FinanceLeaseLiability (XBRL)
A21: HALLAZGO H1 — diferencia (deuda del DCF − deuda del balance) | B21: =B20-B19 -> 5135 | C21: USD m | E21: Calculado | F21: Es EXACTAMENTE la porción corriente de Senior Notes contada dos veces: us-gaap:LongTermDebt (86,282) YA la incluye y ShortTermBorrowings (5,135) la vuelve a sumar. Nota 9 del 10-K FY2025: Total debt 86,282 − current 5,135 = LT 81,147. Evidencia mecanizada: Drivers_MDA filas 97-98 y check 54
A22: Deuda neta (definición de esta hoja) | B22: =B19-B14 -> 82954 | C22: USD m | D22: 46022 | E22: Calculado
A23: Enterprise value (deuda del balance) | B23: =B11+B19-B14 -> 278834.56 | C23: USD m | D23: =D7 -> 46248 | E23: Calculado: cap. de mercado + deuda bruta BS − caja | F23: Precio del 2026-08-14 contra balance del 2025-12-31
A24: Memo — EV con la deuda del DCF | B24: =B11+B20-B14 -> 283969.56 | C24: USD m | E24: Calculado | F24: 5,135 más alto que B23 por el double-count (H1)
A25: Memo — tower obligations (no corriente), FUERA de la definición de deuda del modelo | B25: =BS_Hist!F35 -> 3532 | C25: USD m | D25: 46022 | E25: BS_Hist!F35 (enlace vivo) | F25: Política declarada en 00_Cover!B13; se expone, no se recategoriza
A26: Memo — operating lease liabilities (corriente + no corriente), FUERA de la definición de deuda | B26: =BS_Hist!F29+BS_Hist!F37 -> 30185 | C26: USD m | D26: 46022 | E26: BS_Hist!F29 + F37 (enlace vivo) | F26: 30,185. Un EV con leases operativos capitalizados sería ~11% más alto; queda como memo, no como definición
A27: Ancla de vintage distinto — caja al 2025-12-31 (10-Q Q2 2026, columna comparativa) | B27: 5598 | C27: USD m | D27: 46022 | E27: 10-Q Q2 2026 (accn 0001283699-26-000101), balance condensado, columna "December 31, 2025" — constante tecleada del filing, independiente de BS_Hist | F27: El check 53 exige tie exacto contra B14
A28: Ancla de vintage distinto — deuda del balance al 2025-12-31 (10-Q Q2 2026, columna comparativa) | B28: 88552 | C28: USD m | D28: 46022 | E28: 10-Q Q2 2026 (accn 0001283699-26-000101), balance condensado: 5,135 + 79,649 + 1,498 + 1,163 + 1,107 | F28: El check 54 exige tie exacto contra B19
A30: 3. COSTO DE CAPITAL
A31: Tasa libre de riesgo (UST 10 años, par yield) | B31: 0.0463 | C31: % | D31: 46247 | E31: home.treasury.gov — Daily Treasury Par Yield Curve Rates, columna "10 Yr" (CSV primario descargado 2026-08-14) | F31: Pin de flota de la corrida (mismo Rf del piloto Apple). Misma fecha: 20Y 5.20%, 30Y 5.21%. El 2026-08-14 publicó 4.68% tras el cierre del paquete — desfase de un día declarado en L2
A32: Prima de riesgo de mercado (ERP implícita, S&P 500) | B32: 0.0423 | C32: % | D32: 46023 | E32: A. Damodaran (NYU Stern), "Implied Equity Risk Premiums — United States" (histimpl.html), actualización de enero 2026 | F32: Misma ERP de flota que el piloto Apple (verificada en su auditoría)
A33: Beta (5 años, mensual, vs S&P 500) | B33: 0.33 | C33: x | D33: 46248 | E33: stockanalysis.com/stocks/TMUS/statistics/ | F33: Cross-checks el mismo día: Yahoo Finance 0.33; investing.com 0.44 (ventana distinta). Beta defensivo de telecom — sensibilidad en L1
A34: Costo del capital propio (CAPM) | B34: =B31+B33*B32 -> 0.060259 | C34: % | D34: =D31 -> 46247 | E34: Calculado: Rf + beta x ERP
A35: Costo de deuda antes de impuestos (benchmark BBB) | B35: 0.0553 | C35: % | D35: 46247 | E35: FRED — serie primaria BAMLC0A4CBBBEY, ICE BofA BBB US Corporate Index Effective Yield (CSV fredgraph descargado 2026-08-14) | F35: TMUS es emisor grado de inversión (área BBB/Baa). Es el costo MARGINAL de mercado, no el cupón promedio de la deuda viva (memo B36)
A36: Memo — costo efectivo de la deuda propia | B36: 4.2% FY2025 (FY2024: 4.1%) | C36: % | D36: 46022 | E36: 10-K FY2025 (accn 0001283699-26-000010) Nota 9 — excl. derivados e interés capitalizado, sobre deuda promedio de USD 83.0 bn
A37: Tasa efectiva de impuestos (FY2025A del modelo) | B37: =-IS_Hist!F20/IS_Hist!F19 -> 0.230306 | C37: % | D37: 46022 | E37: −IS_Hist!F20 / IS_Hist!F19 (enlace vivo; el impuesto está almacenado con signo) | F37: 23.0% FY2025. Assumptions usa 24% normalizado (check 58 vigila la calibración de los drivers)
A38: Memo — tasa estatutaria federal de EE.UU. | B38: 0.21 | C38: % | E38: Referencia para una versión marginal del escudo fiscal
A39: Costo de deuda después de impuestos | B39: =B35*(1-B37) -> 0.042564078 | C39: % | D39: =D35 -> 46247 | E39: Calculado: Kd x (1 − t)
A40: Valor de mercado del capital (E) | B40: =B11 -> 195880.56 | C40: USD m | D40: =D7 -> 46248 | E40: Calculado
A41: Deuda bruta (D — definición del balance de esta hoja) | B41: =B19 -> 88552 | C41: USD m | D41: 46022 | E41: Calculado | F41: Con la deuda del DCF (B20) el WACC apenas se mueve: memo B48
A42: Capital total (D+E) | B42: =B40+B41 -> 284432.56 | C42: USD m | E42: Calculado
A43: Peso del capital propio (We) | B43: =B40/B42 -> 0.68867137 | C43: % | E43: Calculado
A44: Peso de la deuda (Wd) | B44: =B41/B42 -> 0.31132863 | C44: % | E44: Calculado
A45: WACC (fechado) | B45: =B43*B34+B44*B39 -> 0.054750064 | C45: % | D45: =D7 -> 46248 | E45: Calculado: We x Ke + Wd x Kd x (1 − t) | F45: Fórmula viva: mover B31, B32, B33 o B35 mueve el WACC
A46: Memo — WACC usado hoy en el DCF (escenario activo) | B46: =Assumptions!F19 -> 0.095 | C46: % | E46: Assumptions!F19 (enlace vivo)
A47: Memo — diferencia (este paquete − modelo) | B47: =B45-B46 -> -0.040249936 | C47: % | E47: Calculado | F47: HALLAZGO H3: −4.0pp. El 9.5% del modelo es un supuesto normalizado de escenario; el CAPM fechado con beta 0.33 da ~5.5%. No se cablea: ver H3
A48: Memo — WACC con la deuda del DCF (D = Historical!E18) | B48: =(B40/(B40+B20))*B34+(B20/(B40+B20))*B39 -> 0.054533966 | C48: % | E48: Calculado | F48: Sensibilidad del WACC a la definición de deuda: ~2pb
A50: 4. MÚLTIPLOS IMPLÍCITOS vs FY2025A DEL MODELO
A51: Ingresos totales FY2025A | B51: =IS_Hist!F5 -> 88309 | C51: USD m | D51: 46022 | E51: IS_Hist!F5 (enlace vivo)
A52: Ingresos de servicio FY2025A | B52: =Sector_KPIs!E14 -> 71306 | C52: USD m | D52: 46022 | E52: Sector_KPIs!E14 (enlace vivo)
A53: Adjusted EBITDA FY2025A (no-GAAP reportado) | B53: =Sector_KPIs!E18 -> 33937 | C53: USD m | D53: 46022 | E53: Sector_KPIs!E18 (enlace vivo) | F53: No-GAAP de la compañía; amarrado al MD&A vía Drivers_MDA fila 72 (check 43)
A54: EBITDA GAAP (calc: utilidad operativa + D&A) | B54: =IS_Hist!F14+IS_Hist!F10 -> 31787 | C54: USD m | D54: 46022 | E54: IS_Hist!F14 + F10 (enlace vivo) | F54: Construcción del analista: 18,279 + 13,508 = 31,787
A55: Utilidad neta FY2025A | B55: =IS_Hist!F21 -> 10992 | C55: USD m | D55: 46022 | E55: IS_Hist!F21 (enlace vivo)
A56: UPA diluida FY2025A | B56: =IS_Hist!F32 -> 9.72 | C56: USD/acción | D56: 46022 | E56: IS_Hist!F32 (enlace vivo)
A57: CFO FY2025A | B57: =CF_Hist!F25 -> 27950 | C57: USD m | D57: 46022 | E57: CF_Hist!F25 (enlace vivo)
A58: Capex FY2025A (cash, incl. interés capitalizado) | B58: =-CF_Hist!F28 -> 9955 | C58: USD m | D58: 46022 | E58: CF_Hist!F28 con signo invertido (enlace vivo)
A59: Adjusted Free Cash Flow FY2025A (reportado) | B59: =Drivers_MDA!F73 -> 17995 | C59: USD m | D59: 46022 | E59: Drivers_MDA!F73 (constante del MD&A, con tie contra CF_Hist en el check 44)
A60: P/E (cap. de mercado / utilidad neta) | B60: =B11/B55 -> 17.820284 | C60: x | D60: =D7 -> 46248 | E60: Calculado
A61: P/E (precio / UPA diluida) | B61: =B7/B56 -> 18.787037 | C61: x | D61: =D7 -> 46248 | E61: Calculado | F61: Difiere del anterior por la base de acciones (en circulación vs diluidas promedio)
A62: EV / Ingresos totales | B62: =B23/B51 -> 3.1574875 | C62: x | D62: =D7 -> 46248 | E62: Calculado
A63: EV / Ingresos de servicio | B63: =B23/B52 -> 3.9103941 | C63: x | D63: =D7 -> 46248 | E63: Calculado | F63: El múltiplo de servicio es el estándar del sector para operadores
A64: EV / Adjusted EBITDA | B64: =B23/B53 -> 8.2162408 | C64: x | D64: =D7 -> 46248 | E64: Calculado
A65: EV / EBITDA GAAP (calc) | B65: =B23/B54 -> 8.7719685 | C65: x | D65: =D7 -> 46248 | E65: Calculado
A66: Memo — EV (deuda del DCF) / Adjusted EBITDA | B66: =B24/B53 -> 8.3675506 | C66: x | E66: Calculado | F66: Sensibilidad del múltiplo al hallazgo H1: +0.15x
A67: Adjusted FCF yield | B67: =B59/B11 -> 0.091867206 | C67: % | D67: =D7 -> 46248 | E67: Calculado
A68: Dividend yield (dividendos pagados FY2025A) | B68: =-CF_Hist!F43/B11 -> 0.02103833 | C68: % | D68: =D7 -> 46248 | E68: CF_Hist!F43 (enlace vivo) | F68: Sobre dividendos efectivamente pagados (4,121), no el declarado corriente
A69: Buyback yield (recompras FY2025A) | B69: =-CF_Hist!F42/B11 -> 0.050918784 | C69: % | D69: =D7 -> 46248 | E69: CF_Hist!F42 (enlace vivo)
A70: Retorno total al accionista (FY2025A / cap. actual) | B70: =B68+B69 -> 0.071957114 | C70: % | D70: =D7 -> 46248 | E70: Calculado
A71: Memo — DCF Base por acción vs precio de mercado | B71: =Valuation!B20-B7 -> -0.44073489 | C71: USD/acción | D71: =D7 -> 46248 | E71: Valuation!B20 (enlace vivo) − B7 | F71: HALLAZGO H4: el DCF Base (182.17) está a −0.2% del precio (182.61). El libro omitía la comparación por política de carril; esta hoja la aporta fechada, SIN cablearla a Valuation
A72: Memo — lo mismo en % | B72: =B71/B7 -> -0.002413531 | C72: % | E72: Calculado
A74: 5. MEMO LTM — al 2026-06-30 (10-Q Q2 2026). FUERA del perímetro auditado FY2021A-FY2025A del modelo.
A75: Ingresos totales 6M 2026 | B75: 45898 | C75: USD m | D75: 46203 | E75: 10-Q Q2 2026 (accn 0001283699-26-000101), estado condensado de resultados
A76: Ingresos totales 6M 2025 | B76: 42018 | C76: USD m | D76: 45838 | E76: 10-Q Q2 2026, columna comparativa
A77: Ingresos totales LTM | B77: =IS_Hist!F5-B76+B75 -> 92189 | C77: USD m | D77: 46203 | E77: Calculado: FY2025A − 6M 2025 + 6M 2026
A78: Utilidad operativa 6M 2026 | B78: 9987 | C78: USD m | D78: 46203 | E78: 10-Q Q2 2026
A79: Utilidad operativa 6M 2025 | B79: 10013 | C79: USD m | D79: 45838 | E79: 10-Q Q2 2026, columna comparativa
A80: Utilidad operativa LTM | B80: =IS_Hist!F14-B79+B78 -> 18253 | C80: USD m | D80: 46203 | E80: Calculado
A81: Utilidad neta 6M 2026 | B81: 5743 | C81: USD m | D81: 46203 | E81: 10-Q Q2 2026
A82: Utilidad neta 6M 2025 | B82: 6175 | C82: USD m | D82: 45838 | E82: 10-Q Q2 2026, columna comparativa
A83: Utilidad neta LTM | B83: =IS_Hist!F21-B82+B81 -> 10560 | C83: USD m | D83: 46203 | E83: Calculado
A84: Ingresos de servicio 6M 2026 | B84: 37814 | C84: USD m | D84: 46203 | E84: 10-Q Q2 2026
A85: Ingresos de servicio 6M 2025 | B85: 34363 | C85: USD m | D85: 45838 | E85: 10-Q Q2 2026, columna comparativa
A86: Ingresos de servicio LTM | B86: =B52-B85+B84 -> 74757 | C86: USD m | D86: 46203 | E86: Calculado
A87: P/E LTM | B87: =B11/B83 -> 18.549296 | C87: x | D87: =D7 -> 46248 | E87: Calculado
A88: EV / Ingresos LTM | B88: =B23/B77 -> 3.0245969 | C88: x | D88: =D7 -> 46248 | E88: Calculado | F88: Usa el EV construido con el balance FY2025A
A89: EV / EBIT LTM | B89: =B23/B80 -> 15.276095 | C89: x | D89: =D7 -> 46248 | E89: Calculado
A90: Caja al 2026-06-30 | B90: 2825 | C90: USD m | D90: 46203 | E90: 10-Q Q2 2026 (accn 0001283699-26-000101), balance condensado | F90: Ancla de vintage distinto: la caja se movió −49.5% en 6 meses (dividendos, buybacks, capex) — por eso el check 53 usa tie exacto de vintage y no una banda sobre esta cifra
A91: Deuda del balance al 2026-06-30 | B91: 86920 | C91: USD m | D91: 46203 | E91: 10-Q Q2 2026, balance condensado: 6,117 + 78,504 + 0 (afiliadas redimidas) + 1,178 + 1,121 | F91: Ancla de vintage distinto: deriva real vs FY2025A = −1.8%; el check 54 usa banda de ±25%
A92: EV con el balance al 2026-06-30 | B92: =B11+B91-B90 -> 279975.56 | C92: USD m | D92: =D7 -> 46248 | E92: Calculado | F92: Referencia: no se usa en los múltiplos de arriba para no mezclar perímetros
A93: Memo — diferencia vs el EV con balance FY2025A | B93: =B92-B23 -> 1141 | C93: USD m | E93: Calculado
A95: 6. CONTROL DE PROCEDENCIA (todo input de mercado debe traer fuente y fecha con serial válido)
A96: Inputs de mercado sujetos a control | B96: 6 | C96: conteo | E96: B7 precio, B8 acciones, B31 Rf, B32 ERP, B33 beta, B35 Kd | F96: Los demás valores de la hoja son enlaces vivos, constantes de filing con accession, o cálculos
A97: Inputs sin fuente | B97: =IF(LEN(E7)=0,1,0)+IF(LEN(E8)=0,1,0)+IF(LEN(E31)=0,1,0)+IF(LEN(E32)=0,1,0)+IF(LEN(E33)=0,1,0)+IF(LEN(E35)=0,1,0) -> 0 | C97: conteo | E97: Calculado | F97: Debe ser 0
A98: Inputs sin fecha válida (ausente o texto en vez de serial) | B98: =IF(OR(LEN(D7)=0,NOT(ISNUMBER(D7))),1,0)+IF(OR(LEN(D8)=0,NOT(ISNUMBER(D8))),1,0)+IF(OR(LEN(D31)=0,NOT(ISNUMBER(D31))),1,0)+IF(OR(LEN(D32)=0,NOT(ISNUMBER(D32))),1,0)+IF(OR(LEN(D33)=0,NOT(ISNUMBER(D33))),1,0)+IF(OR(LEN(D35)=0,NOT(ISNUMBER(D35))),1,0) -> 0 | C98: conteo | E98: Calculado | F98: Debe ser 0. Una fecha escrita como texto cuenta como inválida (lección M2 del piloto)
A99: Inputs de cotización diaria desfasados entre sí (>5 días) o paquete obsoleto (>10 días vs HOY() al recalcular) | B99: =IF(D7<MAX(D7,D31,D35)-5,1,0)+IF(D31<MAX(D7,D31,D35)-5,1,0)+IF(D35<MAX(D7,D31,D35)-5,1,0)+IF(MAX(D7,D31,D35)<TODAY()-10,1,0) -> 1 | C99: conteo | E99: Calculado | F99: Debe ser 0. Cubre precio (D7), Rf (D31) y Kd (D35) entre sí, más frescura ABSOLUTA: el libro caduca solo a los 10 días — es diseño, no defecto. Excluye a propósito la ERP (serie anual) y las acciones (del 10-Q): baja frecuencia, desfase declarado en L2
A100: Estado de procedencia | B100: =IF(AND(B97=0,B98=0,B99=0),"PASS","FAIL") -> FAIL | C100: estado | E100: Calculado
A102: 7. LIMITACIONES, HALLAZGOS Y CABLEADO PENDIENTE
A103: H1 — El puente de deuda del DCF (Historical!E18 → Valuation!B17) cuenta DOS veces la porción corriente de Senior Notes: us-gaap:LongTermDebt ya la incluye y ShortTermBorrowings la vuelve a sumar (B21 = 5,135; FY23 3,619; FY24 4,068 — Drivers_MDA fila 98). El DCF resta 5,135 de deuda de más: corregirlo subiría el equity value ~5,135 USD mm (~USD 4.5/acción, +2.5%). NO se corrige aquí: Historical y Valuation son outputs gateados. Mecanizado en el check 54.
A104: H2 — Valuation!B19 usa el promedio diluido FY2025A (1,131.1 mm); en circulación hoy hay 1,072.7 mm (portada del 10-Q, B8). Con el conteo actual, el mismo equity value daría ~5.4% más por acción. Para refrescar bastaría apuntar Valuation!B19 a B8; se deja sin cablear para no mover outputs gateados.
A105: H3 — El WACC fechado de esta hoja (B45, ~5.5%) está 4.0pp por debajo del 9.5% del escenario Base (Assumptions!D19). El driver es el beta defensivo de TMUS (0.33). El 9.5% del modelo es un supuesto normalizado de largo plazo; cablear B45 a Assumptions rompería el diseño Base/Bull/Bear. Queda como contraste declarado, patrón H3 del piloto.
A106: H4 — El DCF Base (Valuation!B20 = 182.17) está a −0.2% del precio de mercado fechado (182.61, B7). El libro omitía la comparación por política de carril (00_Cover!B12); esta hoja la aporta con fuente y fecha, sin modificar esa política.
A107: L1 — La beta es de proveedor (stockanalysis.com 0.33; Yahoo 0.33; investing.com 0.44, ventana distinta). Con 0.44 el Ke sube a 6.49% y el WACC de esta hoja a ~5.8%: la conclusión de H3 no cambia. No hay serie local de precios para estimar una beta propia.
A108: L2 — Fechas mezcladas a propósito y declaradas: ERP de enero 2026 (serie anual), Rf pin de flota del 2026-08-13 (el 10Y del 08-14, 4.68%, publicó tras el cierre del paquete), Kd del 2026-08-13, precio del 2026-08-14, acciones del 2026-07-17 (10-Q).
...

Sheet Claude Code Log
A1: Turn # | B1: Date | C1: User Request | D1: Action Taken | E1: Details | F1: Outcome
A2: 1 | B2: 46324.359 | C2: Prepare a public model copy | D2: Remove local paths and private build references; preserve financial formulas and inputs | E2: Agent run with MOG as the tool, checked by guard v1. The guard measured every sheet before and after the run. Changed: Change_Log: 2 cells written, at E11, B12; Gate_9of10: 7 cells written, at E5, E11, E12, B22, B23, B25, B27; Sources_Audited: 1 cell written, at C4. Agent: OpenFinmods export | F2: Compare against source and review public copy
