Workbook

Sheet EEFF
A1: Corporación de Finanzas del País, S.A. (PANACREDIT) y Subsidiarias
A2: Estados Financieros Consolidados Auditados FY21-FY25
A3: en B/. (a la par con US$), sin escala
A5: Años | B5: FY21A | C5: FY22A | D5: FY23A | E5: FY24A | F5: FY25A | G5: FY26E | H5: FY27E | I5: FY28E | J5: FY29E | K5: FY30E
A6: Estado Consolidado de Resultados
A7: Intereses ganados | B7: 19760933 | C7: 24013816 | D7: 31354516 | E7: 36993609 | F7: 41706437
A8: Comisiones ganadas | B8: 7681190 | C8: 9366601 | D8: 12465658 | E8: 13927593 | F8: 12923349
A9: Total de ingresos por intereses y comisiones | D9: 43820174 | E9: 50921202 | F9: 54629786
A10: Gastos por intereses | B10: 13459518 | C10: 14950862 | D10: 19286748 | E10: 24742945 | F10: 27201007
A11: Total de gastos por intereses | D11: 19286748 | E11: 24742945 | F11: 27201007
A12: Total de ingresos por intereses y comisiones, neto | D12: 24533426 | E12: 26178257 | F12: 27428779
A13: Provisión para pérdidas en préstamos | B13: 3675000 | C13: 3910000 | D13: 4847500 | E13: 5995466 | F13: 6437000
A14: (Reversión de) provisión para pérdidas en inversiones a costo amortizado | D14: 0 | E14: 17849 | F14: -6344
A15: Provisión para bienes adjudicados | B15: 370000 | C15: 350000 | D15: 390000 | E15: 420000 | F15: 60000
A16: Ingreso neto por intereses, después de provisiones | D16: 19295926 | E16: 19744942 | F16: 20938123
A17: Ganancia en valuación de inversiones | B17: -20000 | C17: -490000 | D17: -600000 | E17: 849397 | F17: 440739
A18: Otros ingresos | B18: 1654019 | C18: 2676655 | D18: 2971728 | E18: 3527350 | F18: 2917037
A19: Total de otros ingresos, neto | D19: 2371728 | E19: 4376747 | F19: 3357776
A20: Salarios y otros gastos de personal | B20: 2702111 | C20: 4150613 | D20: 5339952 | E20: 6663071 | F20: 6791234
A21: Impuestos varios | D21: 450020 | E21: 502974 | F21: 497149
A22: Depreciación y amortización | B22: 592499 | C22: 691158 | D22: 967602 | E22: 1039519 | F22: 1073936
A23: Publicidad y mercadeo | D23: 512348 | E23: 551309 | F23: 482250
A24: Arrendamientos por activos de bajo valor | D24: 553995 | E24: 661195 | F24: 755718
A25: Servicio de electricidad, agua y comunicaciones | D25: 328341 | E25: 414413 | F25: 417694
A26: Reparación y mantenimiento | D26: 345922 | E26: 357513 | F26: 395065
A27: Honorarios y servicios profesionales | D27: 685363 | E27: 843843 | F27: 976597
A28: Otros | D28: 2605570 | E28: 2829287 | F28: 2876235
A29: Total de gastos generales y administrativos | B29: 6940231 | C29: 8703073 | D29: 11789113 | E29: 13863124 | F29: 14265878
A30: Utilidad antes de impuesto sobre la renta | B30: 4665645 | C30: 7653137 | D30: 9878541 | E30: 10258565 | F30: 10030021
A31: Impuesto sobre la renta, neto | B31: 42161 | C31: -478846 | D31: -730485 | E31: -803240 | F31: -957116
A32: Utilidad neta | B32: 4707806 | C32: 7174291 | D32: 9148056 | E32: 9455325 | F32: 9072905
A34: Años | B34: FY21A | C34: FY22A | D34: FY23A | E34: FY24A | F34: FY25A | G34: FY26E | H34: FY27E | I34: FY28E | J34: FY29E | K34: FY30E
A35: Estado Consolidado de Situación Financiera
A36: Efectivo y depósitos en bancos | B36: 51019770 | C36: 59336554 | D36: 50672297 | E36: 50373962 | F36: 54042975
A37: Inversiones a valor razonable con cambios en resultados | B37: 11874112 | C37: 12019089 | D37: 24940576 | E37: 31751384 | F37: 30841061
A38: Inversiones a valor razonable con cambios en otras utilidades integrales | E38: 0 | F38: 2443224
A39: Inversiones a costo amortizado | B39: 4813611 | C39: 15087171 | D39: 17787629 | E39: 14615074 | F39: 13731942
A40: Préstamos por cobrar a costo amortizado, neto | B40: 169258759 | C40: 201123133 | D40: 249844714 | E40: 293697141 | F40: 330675937
A41: Propiedades, mobiliario, equipo y mejoras, neto | B41: 635534 | C41: 964183 | D41: 1713722 | E41: 1698467 | F41: 2078441
A42: Activos por derecho de uso, neto | B42: 1388986 | C42: 1333232 | D42: 911230 | E42: 411245 | F42: 174042
A43: Impuesto sobre la renta diferido | B43: 1296186 | C43: 1794598 | D43: 2203644 | E43: 2706141 | F43: 3235826
A44: Plusvalía | C44: 0 | D44: 311843 | E44: 311843 | F44: 311843
A45: Activos intangibles | B45: 423552 | C45: 429752 | D45: 538906 | E45: 547852 | F45: 945826
A46: Otros activos | B46: 4326380 | C46: 2973555 | D46: 4315151 | E46: 5546572 | F46: 6304812
A47: Total de activos | B47: 245036890 | C47: 295061267 | D47: 353239712 | E47: 401659681 | F47: 444785929
A48: Financiamientos recibidos | B48: 16699995 | C48: 24753401 | D48: 39175942 | E48: 39379317 | F48: 30544893
A49: Valores comerciales negociables | B49: 35068408 | C49: 27321218 | D49: 48388455 | E49: 54284121 | F49: 60442410
A50: Bonos corporativos por pagar | B50: 138133557 | C50: 178307351 | D50: 189967478 | E50: 225902195 | F50: 261842525
A51: Bonos perpetuos | B51: 5500000 | C51: 5500000 | D51: 5500000 | E51: 2417000 | F51: 2417000
A52: Documentos por pagar | B52: 12917773 | C52: 12605818 | D52: 16886634 | E52: 18509756 | F52: 21024789
A53: Obligaciones bursátiles | E53: 0 | F53: 1429160
A54: Pasivo por impuesto corriente | B54: 380158 | C54: 427118 | D54: 49582 | E54: 101302 | F54: 251066
A55: Pasivos por arrendamientos | B55: 1427412 | C55: 1351485 | D55: 901713 | E55: 367169 | F55: 70535
A56: Provisión para prestaciones laborales | B56: 453505 | C56: 579411
A57: Otros pasivos | B57: 2978091 | C57: 4859086 | D57: 5850501 | E57: 4883025 | F57: 4786974
A58: Total de pasivos | B58: 213558899 | C58: 255704888 | D58: 306720305 | E58: 345843885 | F58: 382809352
A59: Acciones comunes | B59: 5500000 | C59: 5500000 | D59: 5500000 | E59: 5500000 | F59: 5500000
A60: Acciones preferidas | B60: 10000000 | C60: 12732000 | D60: 13752000 | E60: 17320000 | F60: 18803000
A61: Reservas de capital voluntario | B61: 2061947 | C61: 2982207 | D61: 4314591 | E61: 4619789 | F61: 5476767
A62: Reserva de inversiones en valores | E62: 0 | F62: -353970
A63: Impuesto complementario | B63: -459195 | C63: -544629
A64: Utilidades no distribuidas | B64: 14375239 | C64: 18686801 | D64: 22952816 | E64: 28376007 | F64: 32550780
A65: Total de patrimonio | B65: 31477991 | C65: 39356379 | D65: 46519407 | E65: 55815796 | F65: 61976577
A66: Total de pasivos y patrimonio | B66: 245036890 | C66: 295061267 | D66: 353239712 | E66: 401659681 | F66: 444785929
A68: Años | B68: FY21A | C68: FY22A | D68: FY23A | E68: FY24A | F68: FY25A | G68: FY26E | H68: FY27E | I68: FY28E | J68: FY29E | K68: FY30E
A69: Estado Consolidado de Flujos de Efectivo
A70: Utilidad neta | B70: 4707806 | C70: 7174291 | D70: 9148056 | E70: 9455325 | F70: 9072905
A71: Depreciación y amortización | B71: 592499 | C71: 691157 | D71: 967602 | E71: 1039518 | F71: 1073936
A72: Provisión para pérdidas en préstamos | B72: 3675000 | C72: 3910000 | D72: 4847500 | E72: 5995466 | F72: 6437000
A73: Provisión para bienes adjudicados | B73: 370000 | C73: 350000 | D73: 390000 | E73: 420000 | F73: 60000
A74: (Reversión de) provisión para pérdidas de inversiones | D74: 0 | E74: 17849 | F74: -6344
A75: Ganancia en venta de mobiliarios y equipos | B75: -862 | C75: 24000 | D75: 6305 | E75: -4000 | F75: -9775
A76: Ganancia en venta de inversiones a VRCR | E76: -44449 | F76: -94965
A77: Ganancia en valuación de inversiones a VRCR | B77: 20000 | C77: 490000 | D77: 600000 | E77: -849397 | F77: -440739
A78: Impuesto sobre la renta | B78: -42161 | C78: 478846 | D78: 730484 | E78: 803240 | F78: 957116
A79: Ingreso por intereses y comisiones, neto | B79: -6301415 | C79: -9062954 | D79: -24533426 | E79: -26178257 | F79: -27428989
A80: Inversiones en valores | B80: -4321008 | C80: -3992575 | D80: -13521487 | E80: -6762146 | F80: -88938
A81: Depósitos a plazo mayor a 90 días | B81: -5200000 | C81: 3150000 | D81: -2517658 | E81: -2850000 | F81: -10950000
A82: Préstamos | B82: -35605377 | C82: -33700178 | D82: -52434388 | E82: -50117533 | F82: -43262802
A83: Otros activos | B83: -1483218 | C83: -679491 | D83: -675084 | E83: -823975 | F83: -1106323
A84: Otros pasivos | B84: 36797 | C84: 2006901 | D84: 374872 | E84: -915756 | F84: -96052
A85: Intereses pagados | B85: -12876453 | C85: -14665029 | D85: -18797986 | E85: -24715926 | F85: -27200797
A86: Intereses y comisiones cobrados | B86: 16758617 | C86: 22640255 | D86: 44044102 | E86: 51204698 | F86: 54629786
A87: Impuesto sobre la renta pagado | B87: -314589 | C87: -929058 | D87: -1517066 | E87: -1307002 | F87: -1082751
A88: Flujos de efectivo de las actividades de operación | B88: -34784364 | C88: -22113835 | D88: -52888174 | E88: -45632345 | F88: -39537732
A89: Adquisición de subsidiaria, neto del efectivo adquirido | D89: -2066231 | E89: 0
A90: Adquisición de equipo, mobiliario, y mejoras | B90: -108540 | C90: -561210 | D90: -1082639 | E90: -424004 | F90: -875517
A91: Venta de mobiliario y equipo | E91: 2760 | F91: 102381
A92: Adquisición de activos intangibles | B92: -30353 | C92: -61237 | D92: -193531 | E92: -111982 | F92: -515594
A93: Adquisición de inversiones en valores | B93: -1050000 | C93: -22450000 | D93: -58835789 | E93: -7150000 | F93: -55052975
A94: Redención y venta de inversiones en valores | B94: 4351089 | C94: 15616150 | D94: 56217996 | E94: 10291566 | F94: 54244850
A95: Flujos de efectivo de las actividades de inversión | B95: -1453641 | C95: -6488417 | D95: -5960194 | E95: 2608340 | F95: -2096855
A96: Pagos a financiamientos recibidos y emisiones de deuda | D96: -111124902 | E96: -208063672 | F96: -197649897
A97: Nuevos financiamientos recibidos y emisiones de deuda | D97: 161382743 | E97: 248632822 | F97: 234858285
A98: Pagos de pasivos por arrendamientos | B98: -314350 | C98: -447733 | D98: -606360 | E98: -534544 | F98: -296634
A99: Dividendos pagados de acciones comunes y preferidas | B99: -902262 | C99: -1942469 | D99: -3033828 | E99: -3688255 | F99: -4028047
A100: Emisión de acciones preferidas | B100: 2990000 | C100: 2732000 | D100: 1020000 | E100: 3568000 | F100: 1483000
A101: Impuesto complementario | B101: 0 | C101: -85434 | D101: 28800 | E101: -38681 | F101: -13107
A102: Flujos de efectivo de las actividades de financiamiento | B102: 43186007 | C102: 40138586 | D102: 47666453 | E102: 39875670 | F102: 34353600
A103: Disminución neta en efectivo y equivalentes de efectivo | B103: 6948002 | C103: 11536334 | D103: -11181915 | E103: -3148335 | F103: -7280987
...

Sheet Notas_EEFF
A1: Corporación de Finanzas del País, S.A. (PANACREDIT) y Subsidiarias
A2: Notas a los Estados Financieros
A3: Fuente: informes auditados vía OCR Mistral (verbatim).
A5: Año | B5: Documento fuente | C5: Página OCR | D5: Tabla OCR / sección | E5: Nota # | F5: Título original de la nota | G5: Categoría modelable | H5: Line item EEFF | I5: Sub-line item / detalle | J5: Texto original / disclosure | K5: Monto reportado | L5: Moneda | M5: Unidad / escala | N5: Fecha / venc. / tasa / plazo | O5: Contraparte / contrato / instrumento | P5: Impacto en Supuestos | Q5: Impacto en ModeloFinanciero | R5: Link a celda EEFF | S5: Comentario de extracción | T5: Status
A6: 2022 | B6: INA_CFPAIS_2022_0.pdf | C6: page-41 | D6: markdown.md | E6: 1 | F6: 1. Información general | G6: Otros | J6: Corporación de Finanzas del País, S.A. (PANACREDIT) (la “Compañía”) es una sociedad anónima registrada en la República de Panamá. Las oficinas principales de la Compañía están ubicadas en el edificio Panacredit en calle 50, ciudad de Panamá, y cuenta con 17 sucursales y oficinas ubicadas en distintos puntos estratégicos en Ciudad de Panamá y en el interior del país, ubicadas en Penonomé, Chitré, Santiago y David. Los estados financieros consolidados comprenden la información financiera de la Compañía y su subsidiaria. | T6: OK
A7: 2022 | B7: INA_CFPAIS_2022_0.pdf | C7: page-41 | D7: markdown.md | E7: 1 | F7: 1. Información general | G7: Otros | J7: La Compañía inició operaciones a partir del 1 de abril de 2008, y dentro del giro principal del negocio están el otorgamiento de créditos de consumo, principalmente préstamos personales por descuento directo, préstamos con garantía hipotecaria, préstamos de autos, financiamiento comercial, fundamentalmente a pequeñas y medianas empresas; operaciones de factoring o descuentos de facturas locales y leasing, principalmente a través de su nombre comercial “Panacredit”. | T7: OK
A8: 2022 | B8: INA_CFPAIS_2022_0.pdf | C8: page-41 | D8: markdown.md | E8: 1 | F8: 1. Información general | G8: Otros | J8: Su subsidiaria Argentia RE Cell C. inició operaciones a partir del 19 de octubre de 2018, y su principal actividad es la de asumir reaseguros de compañías de seguros cedentes. La subsidiaria está ubicada en St. James, Barbados. | T8: OK
A9: 2022 | B9: INA_CFPAIS_2022_0.pdf | C9: page-41 | D9: markdown.md | E9: 1 | F9: 1. Información general | G9: Otros | J9: ## Aspectos regulatorios: | T9: OK
A10: 2022 | B10: INA_CFPAIS_2022_0.pdf | C10: page-41 | D10: markdown.md | E10: 1 | F10: 1. Información general | G10: Otros | J10: La Compañía cuenta con licencia No.164 de 20 de diciembre de 2007 para operar como empresa financiera e inscrita en el Registro de Empresas Financieras del Ministerio de Comercio e Industrias de Panamá (MICI). | T10: OK
A11: 2022 | B11: INA_CFPAIS_2022_0.pdf | C11: page-41 | D11: markdown.md | E11: 1 | F11: 1. Información general | G11: Otros | J11: La Compañía está sujeto a la supervisión de la Dirección General de Empresas Financieras del Ministerio de Comercio e Industrias de Panamá (MICI) por su calidad de empresas financieras en Panamá, y a través de la Superintendencia del Mercado de Valores de Panamá por ser un emisor activo por medio de Valores Comerciales Negociables (VCNs), Bonos Corporativos, Bonos Perpetuos y Acciones Preferidas. | T11: OK
A12: 2022 | B12: INA_CFPAIS_2022_0.pdf | C12: page-41 | D12: markdown.md | E12: 1 | F12: 1. Información general | G12: Otros | J12: A partir del 2015 es regulada por la Superintendencia de Bancos de Panamá, en relación a blanqueo de capitales de acuerdo a la Ley No.23 del 27 de abril de 2015. | T12: OK
A13: 2022 | B13: INA_CFPAIS_2022_0.pdf | C13: page-41 | D13: markdown.md | E13: 1 | F13: 1. Información general | G13: Otros | J13: ## Aprobación de los estados financieros consolidados: | T13: OK
A14: 2022 | B14: INA_CFPAIS_2022_0.pdf | C14: page-41 | D14: markdown.md | E14: 1 | F14: 1. Información general | G14: Otros | J14: Los estados financieros consolidados de la Compañía fueron aprobados para su emisión por la Junta Directiva el 2 de marzo de 2023. | T14: OK
A15: 2022 | B15: INA_CFPAIS_2022_0.pdf | C15: page-41 | D15: markdown.md | E15: 1 | F15: 1. Información general | G15: Otros | J15: - 5 - | T15: OK
A16: 2022 | B16: INA_CFPAIS_2022_0.pdf | C16: page-42 | D16: markdown.md | E16: 2 | F16: 2. Base de preparación | G16: Políticas contables | J16: ### Declaración de cumplimiento | T16: OK
A17: 2022 | B17: INA_CFPAIS_2022_0.pdf | C17: page-42 | D17: markdown.md | E17: 2 | F17: 2. Base de preparación | G17: Políticas contables | J17: Los estados financieros consolidados de la Compañía han sido preparados de conformidad con las Normas Internacionales de Información Financiera (NIIF), tal como han sido emitidos por el Consejo de Normas Internacionales de Contabilidad. Así también, han sido preparados bajo la hipótesis de que la Compañía opera sobre la base de un negocio en marcha. | T17: OK
... A166: 2022 | B166: INA_CFPAIS_2022_0.pdf | C166: page-56 | D166: markdown.md | E166: 3 | F166: 3. Políticas de contables significativas | G166: Políticas contables | J166: De acuerdo con las disposiciones fiscales vigentes en la República de Panamá, las ganancias obtenidas por la Compañía por operaciones locales están sujetas al pago del impuesto sobre la renta. Adicionalmente, las ganancias obtenidas por operaciones internacionales y aquellas obtenidas por depósitos a plazo e intereses devengados de la inversión en obligaciones emitidas por el gobierno de la República de Panamá y operaciones en la Bolsa Latinoamericana de Valores están exentas del pago del impuesto sobre la renta. | T166: OK
A167: 2022 | B167: INA_CFPAIS_2022_0.pdf | C167: page-56 | D167: markdown.md | E167: 3 | F167: 3. Políticas de contables significativas | G167: Políticas contables | J167: La Ley No.8 del 15 de marzo de 2010 refiere que la tasa fiscal para las entidades financieras es de 25% sobre la renta neta gravable, o sobre el total de ingresos superior a B/.1,500,000 determinen como base imponible el 25% de tasa fiscal sobre el 4.67% del total de ingresos. La Compañía considera el mayor para registrar el impuesto corriente, excepto cuando tenga la aprobación de la autoridad fiscal de no aplicación del cálculo alterno. | K167: 1500000 | L167: B/. | T167: OK
A168: 2022 | B168: INA_CFPAIS_2022_0.pdf | C168: page-56 | D168: markdown.md | E168: 3 | F168: 3. Políticas de contables significativas | G168: Políticas contables | J168: De acuerdo a las regulaciones fiscales vigentes, las declaraciones de impuesto sobre la renta están sujetas a revisión por la autoridad fiscal por los tres últimos años, incluyendo el año terminado al 31 de diciembre de 2022. | T168: OK
A169: 2022 | B169: INA_CFPAIS_2022_0.pdf | C169: page-56 | D169: markdown.md | E169: 3 | F169: 3. Políticas de contables significativas | G169: Políticas contables | J169: Durante el año 2022, la Compañía realizó reclasificaciones en la presentación de sus ingresos y gastos que afectaban las cifras presentadas en el estado de ganancia o pérdida comparativos de 2021. | T169: OK
A170: 2022 | B170: INA_CFPAIS_2022_0.pdf | C170: page-56 | D170: markdown.md | E170: 4 | F170: 4. Administración de los riesgos financieros | G170: Riesgo financiero | J170: ### Introducción y revisión general: | T170: OK
A171: 2022 | B171: INA_CFPAIS_2022_0.pdf | C171: page-56 | D171: markdown.md | E171: 4 | F171: 4. Administración de los riesgos financieros | G171: Riesgo financiero | J171: La Compañía está expuesta a los siguientes riesgos de instrumentos financieros: | T171: OK
A172: 2022 | B172: INA_CFPAIS_2022_0.pdf | C172: page-56 | D172: markdown.md | E172: 4 | F172: 4. Administración de los riesgos financieros | G172: Riesgo financiero | J172: - riesgo crediticio; - riesgo de liquidez; - riesgos de mercado; y - riesgo operacional. | T172: OK
A173: 2022 | B173: INA_CFPAIS_2022_0.pdf | C173: page-56 | D173: markdown.md | E173: 4 | F173: 4. Administración de los riesgos financieros | G173: Riesgo financiero | J173: Esta nota presenta información sobre los objetivos, políticas y procesos de la Compañía para medir y administrar el riesgo. | T173: OK
A174: 2022 | B174: INA_CFPAIS_2022_0.pdf | C174: page-56 | D174: markdown.md | E174: 4 | F174: 4. Administración de los riesgos financieros | G174: Riesgo financiero | J174: ### Marco de información general sobre la administración del riesgo: | T174: OK
A175: 2022 | B175: INA_CFPAIS_2022_0.pdf | C175: page-56 | D175: markdown.md | E175: 4 | F175: 4. Administración de los riesgos financieros | G175: Riesgo financiero | J175: La Junta Directiva de la Compañía tiene la responsabilidad general del establecimiento y la supervisión del marco de administración de riesgos de la Compañía. La administración ha creado una serie de comités integrales, quienes son responsables de aprobar y supervisar las políticas de administración de riesgos de la Compañía. | T175: OK
A176: 2022 | B176: INA_CFPAIS_2022_0.pdf | C176: page-56 | D176: markdown.md | E176: 4 | F176: 4. Administración de los riesgos financieros | G176: Riesgo financiero | J176: - 20 - | T176: OK
A177: 2022 | B177: INA_CFPAIS_2022_0.pdf | C177: page-57 | D177: markdown.md | E177: 4 | F177: 4. Administración de los riesgos financieros | G177: Riesgo financiero | J177: Las políticas de administración de riesgos de la Compañía se establecen para identificar y analizar los riesgos que enfrenta la Compañía, para establecer límites y controles de riesgo adecuados, y para monitorear los riesgos y el cumplimiento de los límites. Las políticas y los sistemas de administración de riesgos se revisan periódicamente para reflejar los cambios en las condiciones del mercado y las actividades de la Compañía. La Compañía, a través de sus normas y procedimientos de formación y administración, tiene como objetivo desarrollar un entorno de control disciplinado y constructivo en el que todos los empleados comprendan sus funciones y obligaciones. | T177: OK
A178: 2022 | B178: INA_CFPAIS_2022_0.pdf | C178: page-57 | D178: markdown.md | E178: 4 | F178: 4. Administración de los riesgos financieros | G178: Riesgo financiero | J178: El departamento de auditoría interna supervisa cómo la administración supervisa el cumplimiento de las políticas y procedimientos de administración de riesgos de la Compañía y revisa la idoneidad del marco de administración de riesgos en relación con los riesgos que enfrenta la Compañía. Así también lleva a cabo revisiones periódicas de controles y procedimientos de administración de riesgos y se informan a la Junta Directiva. | T178: OK
A179: 2022 | B179: INA_CFPAIS_2022_0.pdf | C179: page-57 | D179: markdown.md | E179: 4 | F179: 4. Administración de los riesgos financieros | G179: Riesgo financiero | J179: El "riesgo de crédito" es el riesgo de pérdida financiera para la Compañía si un cliente o contraparte de un instrumento financiero no cumple con sus obligaciones contractuales y surge principalmente de los préstamos de la Compañía a clientes. A los efectos de la presentación de informes de administración de riesgos, la Compañía considera y consolida todos los elementos de la exposición al riesgo de crédito. | T179: OK
... A210: 2022 | B210: INA_CFPAIS_2022_0.pdf | C210: page-60 | D210: markdown.md | E210: 5 | F210: 5. Revisión de los riesgos financieros | G210: Riesgo financiero | J210: #### Efectivo y depósitos en bancos: | T210: OK
A211: 2022 | B211: INA_CFPAIS_2022_0.pdf | C211: page-60 | D211: markdown.md | E211: 5 | F211: 5. Revisión de los riesgos financieros | G211: Riesgo financiero | J211: La Compañía mantenía depósitos en bancos al 31 de diciembre de 2022 por B/.59,335,404 (2021: B/.51,018,720). Los depósitos en bancos están colocados en instituciones financieras, los cuales cuentan con calificaciones de riesgo en los rangos de A+ y BB+ principalmente, basado en las agencias Standard &amp; Poor’s, Moody’s y Fitch Ratings. | K211: 59335404 | L211: B/. | T211: OK
A212: 2022 | B212: INA_CFPAIS_2022_0.pdf | C212: page-60 | D212: markdown.md | E212: 5 | F212: 5. Revisión de los riesgos financieros | G212: Riesgo financiero | J212: - 24 - | T212: OK
A213: 2022 | B213: INA_CFPAIS_2022_0.pdf | C213: page-61 | D213: markdown.md | E213: 5 | F213: 5. Revisión de los riesgos financieros | G213: Riesgo financiero | J213: Préstamos a clientes – medidos al costo amortizado: | T213: OK
A214: 2022 | B214: INA_CFPAIS_2022_0.pdf | C214: page-61 | D214: markdown.md | E214: 5 | F214: 5. Revisión de los riesgos financieros | G214: Riesgo financiero | J214: El cuadro a continuación presenta la información acerca de los riesgos por categoría basado en el tipo de producto ofrecido, saldos por cobrar y riesgo: | T214: OK
A215: 2022 | B215: INA_CFPAIS_2022_0.pdf | C215: page-61 | D215: tbl-17.html | E215: 5 | F215: 5. Revisión de los riesgos financieros | G215: Riesgo financiero | J215: [tbl-17.html](tbl-17.html) | T215: OK
A216: 2022 | B216: INA_CFPAIS_2022_0.pdf | C216: page-61 | D216: markdown.md | E216: 5 | F216: 5. Revisión de los riesgos financieros | G216: Riesgo financiero | J216: Colaterales y otras mejoras de crédito: | T216: OK
A217: 2022 | B217: INA_CFPAIS_2022_0.pdf | C217: page-61 | D217: markdown.md | E217: 5 | F217: 5. Revisión de los riesgos financieros | G217: Riesgo financiero | J217: La Compañía mantiene garantías y otras mejoras de crédito contra algunas de sus exposiciones crediticias. La siguiente tabla muestra los principales tipos de garantías mantenidas contra diferentes tipos de activos financieros: | T217: OK
A218: 2022 | B218: INA_CFPAIS_2022_0.pdf | C218: page-61 | D218: tbl-18.html | E218: 5 | F218: 5. Revisión de los riesgos financieros | G218: Riesgo financiero | J218: [tbl-18.html](tbl-18.html) | T218: OK
A219: 2022 | B219: INA_CFPAIS_2022_0.pdf | C219: page-62 | D219: markdown.md | E219: 5 | F219: 5. Revisión de los riesgos financieros | G219: Riesgo financiero | J219: Activos obtenidos mediante la posesión del colateral: | T219: OK
A220: 2022 | B220: INA_CFPAIS_2022_0.pdf | C220: page-62 | D220: markdown.md | E220: 5 | F220: 5. Revisión de los riesgos financieros | G220: Riesgo financiero | J220: El detalle de los activos financieros y no financieros obtenidos por la Compañía durante el año producto de los colaterales mantenidos como seguridad ante los préstamos a clientes se presentan a continuación: | T220: OK
A221: 2022 | B221: INA_CFPAIS_2022_0.pdf | C221: page-62 | D221: tbl-19.html | E221: 5 | F221: 5. Revisión de los riesgos financieros | G221: Riesgo financiero | J221: [tbl-19.html](tbl-19.html) | T221: OK
A222: 2022 | B222: INA_CFPAIS_2022_0.pdf | C222: page-62 | D222: markdown.md | E222: 5 | F222: 5. Revisión de los riesgos financieros | G222: Riesgo financiero | J222: La política de la Compañía es la realización prontamente del colateral de una manera ordenada, de la Compañía usualmente no utiliza los colaterales para sus operaciones. | T222: OK
A223: 2022 | B223: INA_CFPAIS_2022_0.pdf | C223: page-62 | D223: markdown.md | E223: 5 | F223: 5. Revisión de los riesgos financieros | G223: Riesgo financiero | J223: Montos producto de la Pérdida de Crédito Esperada (PCE): | T223: OK
... A328: 2022 | B328: INA_CFPAIS_2022_0.pdf | C328: page-75 | D328: tbl-32.html | E328: 12 | F328: 12. Préstamos a clientes | G328: Deuda / bonos / préstamos / leases | J328: [tbl-32.html](tbl-32.html) | T328: OK
A329: 2022 | B329: INA_CFPAIS_2022_0.pdf | C329: page-75 | D329: markdown.md | E329: 12 | F329: 12. Préstamos a clientes | G329: Deuda / bonos / préstamos / leases | J329: Los préstamos a clientes incluyen créditos por B/.9,106,469 (2021: B/.16,781,505) que mantienen pagarés que han sido endosados y transferidos a un fideicomiso de garantía como colaterales en la emisión de los bonos Serie AW y AZ. | K329: 9106469 | L329: B/. | T329: OK
A330: 2022 | B330: INA_CFPAIS_2022_0.pdf | C330: page-75 | D330: markdown.md | E330: 12 | F330: 12. Préstamos a clientes | G330: Deuda / bonos / préstamos / leases | J330: A continuación se presentan los préstamos por fecha de vencimiento: | T330: OK
A331: 2022 | B331: INA_CFPAIS_2022_0.pdf | C331: page-75 | D331: tbl-33.html | E331: 12 | F331: 12. Préstamos a clientes | G331: Deuda / bonos / préstamos / leases | J331: [tbl-33.html](tbl-33.html) | T331: OK
A332: 2022 | B332: INA_CFPAIS_2022_0.pdf | C332: page-75 | D332: markdown.md | E332: 12 | F332: 12. Préstamos a clientes | G332: Deuda / bonos / préstamos / leases | J332: La morosidad de los préstamos por cobrar es la siguiente: | T332: OK
A333: 2022 | B333: INA_CFPAIS_2022_0.pdf | C333: page-75 | D333: tbl-34.html | E333: 12 | F333: 12. Préstamos a clientes | G333: Deuda / bonos / préstamos / leases | J333: [tbl-34.html](tbl-34.html) | T333: OK
A334: 2022 | B334: INA_CFPAIS_2022_0.pdf | C334: page-75 | D334: markdown.md | E334: 12 | F334: 12. Préstamos a clientes | G334: Deuda / bonos / préstamos / leases | J334: - 39 - | T334: OK
A335: 2022 | B335: INA_CFPAIS_2022_0.pdf | C335: page-76 | D335: markdown.md | E335: 13 | F335: 13. Financiamientos recibidos | G335: Deuda / bonos / préstamos / leases | J335: Los financiamientos recibidos se detallan a continuación: | T335: OK
A336: 2022 | B336: INA_CFPAIS_2022_0.pdf | C336: page-76 | D336: tbl-35.html | E336: 13 | F336: 13. Financiamientos recibidos | G336: Deuda / bonos / préstamos / leases | J336: [tbl-35.html](tbl-35.html) | T336: OK
A337: 2022 | B337: INA_CFPAIS_2022_0.pdf | C337: page-76 | D337: markdown.md | E337: 13 | F337: 13. Financiamientos recibidos | G337: Deuda / bonos / préstamos / leases | J337: Los financiamientos recibidos están medidos a costo amortizado. Estas obligaciones están respaldadas con crédito general de la Compañía y fianza solidaria. | T337: OK
A338: 2022 | B338: INA_CFPAIS_2022_0.pdf | C338: page-76 | D338: markdown.md | E338: 14 | F338: 14. Documentos por pagar | G338: Otros | J338: Los documentos por pagar ascienden a B/.12,605,818 (2021: B/.12,917,773) y consisten en pagarés negociado a una tasa de interés entre 4.25% y 8.00% (2021: 3.4% y 8.0%) con vencimiento entre 2023 a 2027. | K338: 12605818 | L338: B/. | T338: OK
A339: 2022 | B339: INA_CFPAIS_2022_0.pdf | C339: page-76 | D339: markdown.md | E339: 15 | F339: 15. Valores comerciales negociables | G339: Otros | J339: Los valores comerciales negociables se presentan a continuación: | T339: OK
A340: 2022 | B340: INA_CFPAIS_2022_0.pdf | C340: page-76 | D340: tbl-36.html | E340: 15 | F340: 15. Valores comerciales negociables | G340: Otros | J340: [tbl-36.html](tbl-36.html) | T340: OK
A341: 2022 | B341: INA_CFPAIS_2022_0.pdf | C341: page-76 | D341: markdown.md | E341: 15 | F341: 15. Valores comerciales negociables | G341: Otros | J341: - 40 - | T341: OK
A342: 2022 | B342: INA_CFPAIS_2022_0.pdf | C342: page-77 | D342: markdown.md | E342: 15 | F342: 15. Valores comerciales negociables | G342: Otros | J342: El detalle por cantidad de series emitidas es el siguiente: | T342: OK
A343: 2022 | B343: INA_CFPAIS_2022_0.pdf | C343: page-77 | D343: tbl-37.html | E343: 15 | F343: 15. Valores comerciales negociables | G343: Otros | J343: [tbl-37.html](tbl-37.html) | T343: OK
A344: 2022 | B344: INA_CFPAIS_2022_0.pdf | C344: page-77 | D344: markdown.md | E344: 15 | F344: 15. Valores comerciales negociables | G344: Otros | J344: Los términos y condiciones de los valores comerciales negociables es el siguiente: | T344: OK
A345: 2022 | B345: INA_CFPAIS_2022_0.pdf | C345: page-77 | D345: tbl-38.html | E345: 15 | F345: 15. Valores comerciales negociables | G345: Otros | J345: [tbl-38.html](tbl-38.html) | T345: OK
A346: 2022 | B346: INA_CFPAIS_2022_0.pdf | C346: page-77 | D346: markdown.md | E346: 16 | F346: 16. Bonos corporativos | G346: Deuda / bonos / préstamos / leases | J346: Los bonos corporativos se presentan a continuación: | T346: OK
A347: 2022 | B347: INA_CFPAIS_2022_0.pdf | C347: page-77 | D347: tbl-39.html | E347: 16 | F347: 16. Bonos corporativos | G347: Deuda / bonos / préstamos / leases | J347: [tbl-39.html](tbl-39.html) | T347: OK
A348: 2022 | B348: INA_CFPAIS_2022_0.pdf | C348: page-77 | D348: markdown.md | E348: 16 | F348: 16. Bonos corporativos | G348: Deuda / bonos / préstamos / leases | J348: - 41 - | T348: OK
A349: 2022 | B349: INA_CFPAIS_2022_0.pdf | C349: page-78 | D349: markdown.md | E349: 16 | F349: 16. Bonos corporativos | G349: Deuda / bonos / préstamos / leases | J349: El detalle por cantidad de series emitidas es el siguiente: | T349: OK
A350: 2022 | B350: INA_CFPAIS_2022_0.pdf | C350: page-78 | D350: tbl-40.html | E350: 16 | F350: 16. Bonos corporativos | G350: Deuda / bonos / préstamos / leases | J350: [tbl-40.html](tbl-40.html) | T350: OK
... A372: 2022 | B372: INA_CFPAIS_2022_0.pdf | C372: page-81 | D372: tbl-49.html | E372: 18 | F372: 18. Patrimonio | G372: Capital / patrimonio / dividendos | J372: [tbl-49.html](tbl-49.html) | T372: OK
A373: 2022 | B373: INA_CFPAIS_2022_0.pdf | C373: page-81 | D373: markdown.md | E373: 18 | F373: 18. Patrimonio | G373: Capital / patrimonio / dividendos | J373: Al 31 de diciembre, la Junta Directiva aprobó a través de actas el aumento de la reserva de capital voluntario por B/.920,260 (2021: no hubo). | K373: 920260 | L373: B/. | T373: OK
A374: 2022 | B374: INA_CFPAIS_2022_0.pdf | C374: page-81 | D374: markdown.md | E374: 18 | F374: 18. Patrimonio | G374: Capital / patrimonio / dividendos | J374: - 45 - | T374: OK
A375: 2022 | B375: INA_CFPAIS_2022_0.pdf | C375: page-82 | D375: markdown.md | E375: 18 | F375: 18. Patrimonio | G375: Capital / patrimonio / dividendos | J375: ## Ganancia básica por acción: | T375: OK
A376: 2022 | B376: INA_CFPAIS_2022_0.pdf | C376: page-82 | D376: markdown.md | E376: 18 | F376: 18. Patrimonio | G376: Capital / patrimonio / dividendos | J376: La ganancia básica por acción mide el desempeño de la Compañía sobre el período reportado y la misma se calcula dividiendo la utilidad neta atribuible a los accionistas entre el número promedio ponderado de acciones en circulación durante el período. | T376: OK
A377: 2022 | B377: INA_CFPAIS_2022_0.pdf | C377: page-82 | D377: markdown.md | E377: 18 | F377: 18. Patrimonio | G377: Capital / patrimonio / dividendos | J377: El cálculo de la ganancia básica por acción se presenta a continuación: | T377: OK
A378: 2022 | B378: INA_CFPAIS_2022_0.pdf | C378: page-82 | D378: tbl-50.html | E378: 18 | F378: 18. Patrimonio | G378: Capital / patrimonio / dividendos | J378: [tbl-50.html](tbl-50.html) | T378: OK
A379: 2022 | B379: INA_CFPAIS_2022_0.pdf | C379: page-82 | D379: markdown.md | E379: 19 | F379: 19. Gastos de personal | G379: Costos / gastos | J379: Los gastos de personal se detallan a continuación: | T379: OK
A380: 2022 | B380: INA_CFPAIS_2022_0.pdf | C380: page-82 | D380: tbl-51.html | E380: 19 | F380: 19. Gastos de personal | G380: Costos / gastos | J380: [tbl-51.html](tbl-51.html) | T380: OK
A381: 2022 | B381: INA_CFPAIS_2022_0.pdf | C381: page-82 | D381: markdown.md | E381: 20 | F381: 20. Gastos generales y administrativos | G381: Costos / gastos | J381: Los gastos generales y administrativos se detallan a continuación: | T381: OK
A382: 2022 | B382: INA_CFPAIS_2022_0.pdf | C382: page-82 | D382: tbl-52.html | E382: 20 | F382: 20. Gastos generales y administrativos | G382: Costos / gastos | J382: [tbl-52.html](tbl-52.html) | T382: OK
A383: 2022 | B383: INA_CFPAIS_2022_0.pdf | C383: page-82 | D383: markdown.md | E383: 20 | F383: 20. Gastos generales y administrativos | G383: Costos / gastos | J383: - 46 - | T383: OK
A384: 2022 | B384: INA_CFPAIS_2022_0.pdf | C384: page-83 | D384: markdown.md | E384: 21 | F384: 21. Gasto de impuesto sobre la renta | G384: Impuestos | J384: El gasto de impuesto sobre la renta se detalla a continuación: | T384: OK
A385: 2022 | B385: INA_CFPAIS_2022_0.pdf | C385: page-83 | D385: tbl-53.html | E385: 21 | F385: 21. Gasto de impuesto sobre la renta | G385: Impuestos | J385: [tbl-53.html](tbl-53.html) | T385: OK
... A437: 2022 | B437: INA_CFPAIS_2022_0.pdf | C437: page-93 | D437: markdown.md | E437: 1 | F437: 1. Información general | G437: Otros | J437: Los Fideicomisos Corporación de Finanzas del País (el "Fideicomiso") están conformados por dos (2) fideicomisos irrevocables constituidos conforme al Contrato de Fideicomiso de fecha del 19 de enero de 2016 y 1 de octubre de 2019 (los "Contratos de Fideicomisos") celebrado entre Corporación de Finanzas del País, S. A. como Fideicomitente y MMG Bank Corporation como Fiduciario. El Fiduciario es sociedad anónima incorporada en Panamá y está autorizada para dedicarse a la Administración de fideicomisos en o desde la República de Panamá de acuerdo con Resolución Fiduciaria No.SBP-FID.0009-2013 de 14 de junio de 2013. La oficina principal del Fiduciario está ubicada en el piso 22 del Edificio MMG Tower en Avenida Paseo del Mar en Costa del Este, en Ciudad de Panamá. | T437: OK
A438: 2022 | B438: INA_CFPAIS_2022_0.pdf | C438: page-93 | D438: markdown.md | E438: 1 | F438: 1. Información general | G438: Otros | J438: El objetivo general de los Fideicomisos es garantizar con los bienes en fideicomiso el cumplimiento de las obligaciones del "Fideicomitente" a favor de los tenedores, derivadas de los bonos corporativos de hasta B/.50,000,000, correspondiente a las Series AW y AZ emitidas y en circulación y de los bonos corporativos hasta B/.100,000,000, que la fecha no mantiene series de bonos emitidas y en circulación, cuyo registro y oferta pública ha sido autorizada por la Superintendencia del Mercado de Valores de Panamá mediante resolución SMV No.20-16 de 19 de enero de 2016 y SMV No.387-19 de 27 de septiembre de 2019. El Fideicomiso está vigente hasta la fecha que todas las obligaciones garantizadas se extingan. | K438: 50000000 | L438: B/. | T438: OK
A439: 2022 | B439: INA_CFPAIS_2022_0.pdf | C439: page-93 | D439: markdown.md | E439: 1 | F439: 1. Información general | G439: Otros | J439: El Fideicomitente mediante resolución SMV No.331-22 de 5 de octubre de 2022 autorizada por la Superintendencia del Mercado de Valores de Panamá dio por terminado el Registro de Bonos Corporativos de hasta B/.10,000,000, correspondiente a la Serie T autorizado mediante resolución CNV No.386-08 del 3 de diciembre de 2008. | K439: 10000000 | L439: B/. | T439: OK
A440: 2022 | B440: INA_CFPAIS_2022_0.pdf | C440: page-93 | D440: markdown.md | E440: 1 | F440: 1. Información general | G440: Otros | J440: El negocio de fideicomiso en Panamá está regulado mediante la Ley No.1 del 5 de enero de 1984 como ha sido modificada por la Ley No.21 del 10 de mayo de 2017, así como resoluciones y acuerdos de la Superintendencia de Bancos de Panamá. | T440: OK
A441: 2022 | B441: INA_CFPAIS_2022_0.pdf | C441: page-93 | D441: markdown.md | E441: 1 | F441: 1. Información general | G441: Otros | J441: El Fiduciario tendrá las siguientes obligaciones: | T441: OK
A442: 2022 | B442: INA_CFPAIS_2022_0.pdf | C442: page-93 | D442: markdown.md | E442: 1 | F442: 1. Información general | G442: Otros | J442: - Notificar por escrito a la Fideicomitente, al agente de pago y transferencia y a la Superintendencia de Mercado de Valores de Panamá tan pronto la Fideicomitente incumpla con su obligación de dar y mantener en fideicomiso el porcentaje mínimo de créditos a que se refiere obligaciones de la Fideicomitente. - Distribuir los bienes de los Fideicomisos a los beneficiarios por intermedio del agente de pago, registro y transferencia, para pagar las sumas adeudadas por la Fideicomitente derivadas de los bonos registrados. - Devolver al Fideicomitente los bienes del Fideicomiso al haberse pagado todas las sumas de dinero derivadas de los bonos. - Observar y cumplir las demás obligaciones que como Fiduciario se le imponen según la ley de Fideicomisos. | T442: OK
A443: 2022 | B443: INA_CFPAIS_2022_0.pdf | C443: page-94 | D443: markdown.md | E443: 1 | F443: 1. Información general | G443: Otros | J443: ## Notas a los Estados Financieros Combinados Por el año terminado el 31 de diciembre de 2022 (Cifras en balboas) | T443: OK
A444: 2022 | B444: INA_CFPAIS_2022_0.pdf | C444: page-94 | D444: markdown.md | E444: 1 | F444: 1. Información general | G444: Otros | J444: El Fiduciario tendrá las siguientes facultades: | T444: OK
A445: 2022 | B445: INA_CFPAIS_2022_0.pdf | C445: page-94 | D445: markdown.md | E445: 1 | F445: 1. Información general | G445: Otros | J445: - Ejecutar todas las medidas que estimen pertinentes y convenientes para la conservación de los bienes en Fideicomiso. - Deducir de los bienes de los Fideicomiso las sumas debidas a su favor por los servicios prestados en ocasión y en ejercicio de sus funciones como Fiduciario del Fideicomiso, así como en concepto de gastos, costos, y tributos causados por la celebración y ejecución del mismo. - Designar a uno o más Fiduciarios sustitutos en caso de que la Fideicomitente no lo nombre el plazo acordado. - Contratar la prestación de servicios profesionales que sean requeridos para el ejercicio de los derechos y obligaciones que adquiere bajo los Fideicomisos, incluyendo a manera de ejemplo, servicios legales, de contabilidad y auditoría, de común acuerdo con la Fideicomitente. | T445: OK
A446: 2022 | B446: INA_CFPAIS_2022_0.pdf | C446: page-94 | D446: markdown.md | E446: 1 | F446: 1. Información general | G446: Otros | J446: El Fideicomitente tiene como obligación sustituir los documentos por cobrar con una morosidad mayor a 90 días por otros que se encuentren al día y que sumados a los existentes en los Fideicomisos cumplan con la cobertura, así como sustituir las garantías que requieran ser reemplazadas. | T446: OK
A447: 2022 | B447: INA_CFPAIS_2022_0.pdf | C447: page-94 | D447: markdown.md | E447: 1 | F447: 1. Información general | G447: Otros | J447: ### Aprobación de estados financieros combinados | T447: OK
A448: 2022 | B448: INA_CFPAIS_2022_0.pdf | C448: page-94 | D448: markdown.md | E448: 1 | F448: 1. Información general | G448: Otros | J448: Los estados financieros combinados por el año terminado al 31 de diciembre de 2022 fueron aprobados por la Administración del Fideicomiso el 14 de marzo de 2023. | T448: OK
A449: 2022 | B449: INA_CFPAIS_2022_0.pdf | C449: page-94 | D449: markdown.md | E449: 2 | F449: 2. Base de preparación | G449: Políticas contables | J449: Los estados financieros combinados han sido preparados de conformidad con las Normas Internacionales de Información Financiera (NIIF) emitidas por el Consejo de Normas Internacionales de Contabilidad (IASB). Asimismo, han sido preparados bajo la presunción de que el Fideicomiso opera sobre una base de negocio en marcha. | T449: OK
A450: 2022 | B450: INA_CFPAIS_2022_0.pdf | C450: page-94 | D450: markdown.md | E450: 2 | F450: 2. Base de preparación | G450: Políticas contables | J450: ### Moneda funcional y de presentación | T450: OK
A451: 2022 | B451: INA_CFPAIS_2022_0.pdf | C451: page-94 | D451: markdown.md | E451: 2 | F451: 2. Base de preparación | G451: Políticas contables | J451: Los estados financieros combinados están expresados en Balboas (B/.), la unidad monetaria de la República de Panamá, la cual está a la par y es de libre cambio con el dólar (USD) de los Estados Unidos de América. La República de Panamá no emite papel moneda propio y, en su lugar, el dólar (USD) de los Estados Unidos de América es utilizado como moneda de curso legal y moneda funcional. | T451: OK
... A518: 2022 | B518: INA_CFPAIS_2022_0.pdf | C518: page-102 | D518: markdown.md | E518: 8 | F518: 8. Eventos posteriores a la fecha sobre el que se informa | G518: Otros | J518: No se ha presentado ningún evento significativo que requiera algún ajuste o que no requiriéndolo, deba revelarse, entre la fecha sobre el que se informa y la fecha de autorización. | T518: OK
A519: 2022 | B519: INA_CFPAIS_2022_0.pdf | C519: page-103 | D519: markdown.md | E519: 8 | F519: 8. Eventos posteriores a la fecha sobre el que se informa | G519: Otros | J519: # CERTIFICACIÓN ## CORPORACIÓN DE FINANZAS DEL PAÍS, S.A. ### MMG BANK CORPORATION FIDBI-011 #### BONOS CORPORATIVOS ##### US$ 50.000,000.00 | K519: 50 | L519: B/. | T519: OK
A520: 2022 | B520: INA_CFPAIS_2022_0.pdf | C520: page-103 | D520: markdown.md | E520: 8 | F520: 8. Eventos posteriores a la fecha sobre el que se informa | G520: Otros | J520: En nuestra condición de agente fiduciario del fideicomiso de garantía constituido por CORPORACIÓN DE FINANZAS DEL PAÍS, S.A. (en adelante la “Emisora”) para garantizar el cumplimiento de las obligaciones de ésta, derivadas de los bonos corporativos de hasta Cincuenta Millones de Dólares con 00/100 (US$50.000,000.00), cuyo registro y oferta pública ha sido autorizada por la Superintendencia del Mercado de Valores mediante Resolución SMV No. 20-16 de 19 de enero de 2016, (en adelante los “Bonos”); por este medio certificamos que al 31 de diciembre de 2022: | K520: 50 | L520: B/. | T520: OK
A521: 2022 | B521: INA_CFPAIS_2022_0.pdf | C521: page-103 | D521: markdown.md | E521: 8 | F521: 8. Eventos posteriores a la fecha sobre el que se informa | G521: Otros | J521: 1. El saldo a capital de Bonos Serie AW y AZ emitidos y en circulación, garantizados por el fideicomiso de garantía, asciende a siete millones quinientos mil dólares con 00/100 (US$7,500,000.00). | K521: -7500000 | L521: B/. | T521: OK
...

Sheet Supuestos
A1: Corporación de Finanzas del País, S.A. (PANACREDIT) y Subsidiarias
A3: COLOR KEY: Input (azul) · Fórmula (negro) · Link inter-hoja (verde)
A4: Escenario (1=Base, 2=Bull, 3=Bear)
A5: Selector escenario | C5: 1 | M5: caso | N5: NOT_DISCLOSED | Q5: Derivación mecánica declarada por el plan.
A6: Escenario activo | C6: =CHOOSE($C$5,"Base","Bull","Bear") -> Base | M6: moneda del modelo | N6: NOT_DISCLOSED | Q6: Selector de caso activo C5: Base/Bull/Bear.
A8: Años | B8: FY21A | C8: FY22A | D8: FY23A | E8: FY24A | F8: FY25A | G8: FY26E | H8: FY27E | I8: FY28E | J8: FY29E | K8: FY30E | M8: Unidad | N8: Fuente / nota | Q8: Rationale
A10: A. INGRESO POR INTERESES — CRECIMIENTO (% YoY)
A11: Total de ingresos por intereses y comisiones — driver activo | G11: =CHOOSE($C$5,G13,G14,G12) -> 0.073 | H11: =CHOOSE($C$5,H13,H14,H12) -> 0.073 | I11: =CHOOSE($C$5,I13,I14,I12) -> 0.073 | J11: =CHOOSE($C$5,J13,J14,J12) -> 0.073 | K11: =CHOOSE($C$5,K13,K14,K12) -> 0.073 | M11: moneda del modelo | N11: NOT_DISCLOSED | Q11: Selector de caso activo C5: Base/Bull/Bear.
A12: Bear | G12: 0.053 | H12: 0.053 | I12: 0.053 | J12: 0.053 | K12: 0.053 | M12: moneda del modelo | N12: NOT_DISCLOSED | Q12: Escenario driver citado; NOT_DISCLOSED si no hay fuente explícita.
A13: Base | G13: 0.073 | H13: 0.073 | I13: 0.073 | J13: 0.073 | K13: 0.073 | M13: moneda del modelo | N13: NOT_DISCLOSED | Q13: Escenario driver citado; NOT_DISCLOSED si no hay fuente explícita.
A14: Bull | G14: 0.093 | H14: 0.093 | I14: 0.093 | J14: 0.093 | K14: 0.093 | M14: moneda del modelo | N14: NOT_DISCLOSED | Q14: Escenario driver citado; NOT_DISCLOSED si no hay fuente explícita.
A15: Total de ingresos por intereses y comisiones (hist, ref EEFF) | B15: =EEFF!B9 -> 0 | C15: =EEFF!C9 -> 0 | D15: =EEFF!D9 -> 43820174 | E15: =EEFF!E9 -> 50921202 | F15: =EEFF!F9 -> 54629786 | M15: moneda del modelo | N15: EEFF (citado por fórmula viva) | Q15: Mirror histórico desde fuente citada.
A17: B. GASTO POR INTERESES (% de ingreso x int.)
A18: Gastos por intereses — driver activo | G18: =CHOOSE($C$5,G20,G21,G19) -> 0.498 | H18: =CHOOSE($C$5,H20,H21,H19) -> 0.498 | I18: =CHOOSE($C$5,I20,I21,I19) -> 0.498 | J18: =CHOOSE($C$5,J20,J21,J19) -> 0.498 | K18: =CHOOSE($C$5,K20,K21,K19) -> 0.498 | M18: moneda del modelo | N18: NOT_DISCLOSED | Q18: Selector de caso activo C5: Base/Bull/Bear.
A19: Bear | G19: 0.478 | H19: 0.478 | I19: 0.478 | J19: 0.478 | K19: 0.478 | M19: moneda del modelo | N19: NOT_DISCLOSED | Q19: Escenario driver citado; NOT_DISCLOSED si no hay fuente explícita.
A20: Base | G20: 0.498 | H20: 0.498 | I20: 0.498 | J20: 0.498 | K20: 0.498 | M20: moneda del modelo | N20: NOT_DISCLOSED | Q20: Escenario driver citado; NOT_DISCLOSED si no hay fuente explícita.
A21: Bull | G21: 0.518 | H21: 0.518 | I21: 0.518 | J21: 0.518 | K21: 0.518 | M21: moneda del modelo | N21: NOT_DISCLOSED | Q21: Escenario driver citado; NOT_DISCLOSED si no hay fuente explícita.
A22: Gastos por intereses ÷ ingresos (hist, ref EEFF) | B22: =IF(EEFF!B9=0,"",EEFF!B10/EEFF!B9) | C22: =IF(EEFF!C9=0,"",EEFF!C10/EEFF!C9) | D22: =IF(EEFF!D9=0,"",EEFF!D10/EEFF!D9) -> 0.44013399 | E22: =IF(EEFF!E9=0,"",EEFF!E10/EEFF!E9) -> 0.48590654 | F22: =IF(EEFF!F9=0,"",EEFF!F10/EEFF!F9) -> 0.49791531 | M22: % | N22: EEFF (citado por fórmula viva) | Q22: Mirror histórico desde fuente citada.
A24: C. GASTOS GENERALES (% de ingreso x int.)
A25: Total de gastos generales y administrativos — driver activo | G25: =CHOOSE($C$5,G27,G28,G26) -> 0.261 | H25: =CHOOSE($C$5,H27,H28,H26) -> 0.261 | I25: =CHOOSE($C$5,I27,I28,I26) -> 0.261 | J25: =CHOOSE($C$5,J27,J28,J26) -> 0.261 | K25: =CHOOSE($C$5,K27,K28,K26) -> 0.261 | M25: moneda del modelo | N25: NOT_DISCLOSED | Q25: Selector de caso activo C5: Base/Bull/Bear.
A26: Bear | G26: 0.241 | H26: 0.241 | I26: 0.241 | J26: 0.241 | K26: 0.241 | M26: moneda del modelo | N26: NOT_DISCLOSED | Q26: Escenario driver citado; NOT_DISCLOSED si no hay fuente explícita.
A27: Base | G27: 0.261 | H27: 0.261 | I27: 0.261 | J27: 0.261 | K27: 0.261 | M27: moneda del modelo | N27: NOT_DISCLOSED | Q27: Escenario driver citado; NOT_DISCLOSED si no hay fuente explícita.
A28: Bull | G28: 0.281 | H28: 0.281 | I28: 0.281 | J28: 0.281 | K28: 0.281 | M28: moneda del modelo | N28: NOT_DISCLOSED | Q28: Escenario driver citado; NOT_DISCLOSED si no hay fuente explícita.
A29: Total de gastos generales y administrativos ÷ ingresos (hist, ref EEFF) | B29: =IF(EEFF!B9=0,"",EEFF!B29/EEFF!B9) | C29: =IF(EEFF!C9=0,"",EEFF!C29/EEFF!C9) | D29: =IF(EEFF!D9=0,"",EEFF!D29/EEFF!D9) -> 0.26903392 | E29: =IF(EEFF!E9=0,"",EEFF!E29/EEFF!E9) -> 0.2722466 | F29: =IF(EEFF!F9=0,"",EEFF!F29/EEFF!F9) -> 0.26113736 | M29: % | N29: EEFF (citado por fórmula viva) | Q29: Mirror histórico desde fuente citada.
A32: D. CARTERA / YIELD / NIM / RIESGO
A33: Prestamos netos - crecimiento activo | G33: =CHOOSE($C$5,G35,G36,G34) -> 0.105 | H33: =CHOOSE($C$5,H35,H36,H34) -> 0.1 | I33: =CHOOSE($C$5,I35,I36,I34) -> 0.095 | J33: =CHOOSE($C$5,J35,J36,J34) -> 0.09 | K33: =CHOOSE($C$5,K35,K36,K34) -> 0.085 | M33: % | N33: NOT_DISCLOSED | Q33: Selector de caso activo C5: Base/Bull/Bear.
A34: Bear | G34: 0.075 | H34: 0.07 | I34: 0.065 | J34: 0.06 | K34: 0.06 | M34: moneda del modelo | N34: NOT_DISCLOSED | Q34: Escenario driver citado; NOT_DISCLOSED si no hay fuente explícita.
A35: Base | G35: 0.105 | H35: 0.1 | I35: 0.095 | J35: 0.09 | K35: 0.085 | M35: moneda del modelo | N35: NOT_DISCLOSED | Q35: Escenario driver citado; NOT_DISCLOSED si no hay fuente explícita.
A36: Bull | G36: 0.13 | H36: 0.125 | I36: 0.12 | J36: 0.115 | K36: 0.11 | M36: moneda del modelo | N36: NOT_DISCLOSED | Q36: Escenario driver citado; NOT_DISCLOSED si no hay fuente explícita.
A37: Prestamos netos (hist, ref EEFF) | B37: =EEFF!B40 -> 169258759 | C37: =EEFF!C40 -> 201123133 | D37: =EEFF!D40 -> 249844714 | E37: =EEFF!E40 -> 293697141 | F37: =EEFF!F40 -> 330675937 | M37: moneda del modelo | N37: EEFF (citado por fórmula viva) | Q37: Mirror histórico desde fuente citada.
A38: Portfolio yield - driver activo | G38: =CHOOSE($C$5,G40,G41,G39) -> 0.134 | H38: =CHOOSE($C$5,H40,H41,H39) -> 0.133 | I38: =CHOOSE($C$5,I40,I41,I39) -> 0.132 | J38: =CHOOSE($C$5,J40,J41,J39) -> 0.131 | K38: =CHOOSE($C$5,K40,K41,K39) -> 0.13 | M38: % | N38: NOT_DISCLOSED | Q38: Selector de caso activo C5: Base/Bull/Bear.
A39: Bear | G39: 0.125 | H39: 0.123 | I39: 0.121 | J39: 0.12 | K39: 0.12 | M39: moneda del modelo | N39: NOT_DISCLOSED | Q39: Escenario driver citado; NOT_DISCLOSED si no hay fuente explícita.
A40: Base | G40: 0.134 | H40: 0.133 | I40: 0.132 | J40: 0.131 | K40: 0.13 | M40: moneda del modelo | N40: NOT_DISCLOSED | Q40: Escenario driver citado; NOT_DISCLOSED si no hay fuente explícita.
A41: Bull | G41: 0.142 | H41: 0.141 | I41: 0.14 | J41: 0.139 | K41: 0.138 | M41: moneda del modelo | N41: NOT_DISCLOSED | Q41: Escenario driver citado; NOT_DISCLOSED si no hay fuente explícita.
A42: Comisiones yield - driver activo | G42: =CHOOSE($C$5,G44,G45,G43) -> 0.039 | H42: =CHOOSE($C$5,H44,H45,H43) -> 0.038 | I42: =CHOOSE($C$5,I44,I45,I43) -> 0.038 | J42: =CHOOSE($C$5,J44,J45,J43) -> 0.037 | K42: =CHOOSE($C$5,K44,K45,K43) -> 0.037 | M42: % | N42: NOT_DISCLOSED | Q42: Selector de caso activo C5: Base/Bull/Bear.
A43: Bear | G43: 0.035 | H43: 0.034 | I43: 0.034 | J43: 0.033 | K43: 0.033 | M43: moneda del modelo | N43: NOT_DISCLOSED | Q43: Escenario driver citado; NOT_DISCLOSED si no hay fuente explícita.
A44: Base | G44: 0.039 | H44: 0.038 | I44: 0.038 | J44: 0.037 | K44: 0.037 | M44: moneda del modelo | N44: NOT_DISCLOSED | Q44: Escenario driver citado; NOT_DISCLOSED si no hay fuente explícita.
A45: Bull | G45: 0.043 | H45: 0.042 | I45: 0.041 | J45: 0.041 | K45: 0.04 | M45: moneda del modelo | N45: NOT_DISCLOSED | Q45: Escenario driver citado; NOT_DISCLOSED si no hay fuente explícita.
A46: Costo de fondos - driver activo | G46: =CHOOSE($C$5,G48,G49,G47) -> 0.073 | H46: =CHOOSE($C$5,H48,H49,H47) -> 0.073 | I46: =CHOOSE($C$5,I48,I49,I47) -> 0.074 | J46: =CHOOSE($C$5,J48,J49,J47) -> 0.074 | K46: =CHOOSE($C$5,K48,K49,K47) -> 0.074 | M46: moneda del modelo | N46: NOT_DISCLOSED | Q46: Selector de caso activo C5: Base/Bull/Bear.
A47: Bear | G47: 0.08 | H47: 0.081 | I47: 0.082 | J47: 0.083 | K47: 0.083 | M47: moneda del modelo | N47: NOT_DISCLOSED | Q47: Escenario driver citado; NOT_DISCLOSED si no hay fuente explícita.
A48: Base | G48: 0.073 | H48: 0.073 | I48: 0.074 | J48: 0.074 | K48: 0.074 | M48: moneda del modelo | N48: NOT_DISCLOSED | Q48: Escenario driver citado; NOT_DISCLOSED si no hay fuente explícita.
A49: Bull | G49: 0.068 | H49: 0.068 | I49: 0.069 | J49: 0.069 | K49: 0.069 | M49: moneda del modelo | N49: NOT_DISCLOSED | Q49: Escenario driver citado; NOT_DISCLOSED si no hay fuente explícita.
A50: Costo de riesgo / provision - driver activo | G50: =CHOOSE($C$5,G52,G53,G51) -> 0.02 | H50: =CHOOSE($C$5,H52,H53,H51) -> 0.02 | I50: =CHOOSE($C$5,I52,I53,I51) -> 0.02 | J50: =CHOOSE($C$5,J52,J53,J51) -> 0.019 | K50: =CHOOSE($C$5,K52,K53,K51) -> 0.019 | M50: moneda del modelo | N50: NOT_DISCLOSED | Q50: Selector de caso activo C5: Base/Bull/Bear.
A51: Bear | G51: 0.024 | H51: 0.024 | I51: 0.023 | J51: 0.023 | K51: 0.023 | M51: moneda del modelo | N51: NOT_DISCLOSED | Q51: Escenario driver citado; NOT_DISCLOSED si no hay fuente explícita.
A52: Base | G52: 0.02 | H52: 0.02 | I52: 0.02 | J52: 0.019 | K52: 0.019 | M52: moneda del modelo | N52: NOT_DISCLOSED | Q52: Escenario driver citado; NOT_DISCLOSED si no hay fuente explícita.
A53: Bull | G53: 0.017 | H53: 0.017 | I53: 0.016 | J53: 0.016 | K53: 0.016 | M53: moneda del modelo | N53: NOT_DISCLOSED | Q53: Escenario driver citado; NOT_DISCLOSED si no hay fuente explícita.
A54: G&A / ingresos - eficiencia activa | G54: =CHOOSE($C$5,G56,G57,G55) -> 0.261 | H54: =CHOOSE($C$5,H56,H57,H55) -> 0.258 | I54: =CHOOSE($C$5,I56,I57,I55) -> 0.255 | J54: =CHOOSE($C$5,J56,J57,J55) -> 0.252 | K54: =CHOOSE($C$5,K56,K57,K55) -> 0.25 | M54: moneda del modelo | N54: NOT_DISCLOSED | Q54: Selector de caso activo C5: Base/Bull/Bear.
A55: Bear | G55: 0.285 | H55: 0.285 | I55: 0.285 | J55: 0.285 | K55: 0.285 | M55: moneda del modelo | N55: NOT_DISCLOSED | Q55: Escenario driver citado; NOT_DISCLOSED si no hay fuente explícita.
A56: Base | G56: 0.261 | H56: 0.258 | I56: 0.255 | J56: 0.252 | K56: 0.25 | M56: moneda del modelo | N56: NOT_DISCLOSED | Q56: Escenario driver citado; NOT_DISCLOSED si no hay fuente explícita.
A57: Bull | G57: 0.245 | H57: 0.242 | I57: 0.24 | J57: 0.238 | K57: 0.236 | M57: moneda del modelo | N57: NOT_DISCLOSED | Q57: Escenario driver citado; NOT_DISCLOSED si no hay fuente explícita.

Sheet ModeloFinanciero
A1: Corporación de Finanzas del País, S.A. (PANACREDIT) y Subsidiarias
A2: Estados Financieros Consolidados Auditados FY21-FY25
A3: en B/. (a la par con US$), sin escala
A5: Años | B5: FY21A | C5: FY22A | D5: FY23A | E5: FY24A | F5: FY25A | G5: FY26E | H5: FY27E | I5: FY28E | J5: FY29E | K5: FY30E
A6: Estado Consolidado de Resultados
A7: Intereses ganados | B7: =EEFF!B7 -> 19760933 | C7: =EEFF!C7 -> 24013816 | D7: =EEFF!D7 -> 31354516 | E7: =EEFF!E7 -> 36993609 | F7: =EEFF!F7 -> 41706437 | G7: =F7*(1+Supuestos!G33) -> 46085613 | H7: =G7*(1+Supuestos!H33) -> 50694174 | I7: =H7*(1+Supuestos!I33) -> 55510121 | J7: =I7*(1+Supuestos!J33) -> 60506032 | K7: =J7*(1+Supuestos!K33) -> 65649044
A8: Comisiones ganadas | B8: =EEFF!B8 -> 7681190 | C8: =EEFF!C8 -> 9366601 | D8: =EEFF!D8 -> 12465658 | E8: =EEFF!E8 -> 13927593 | F8: =EEFF!F8 -> 12923349 | G8: =AVERAGE(F40,G40)*Supuestos!G42 -> 12896362 | H8: =AVERAGE(G40,H40)*Supuestos!H42 -> 12565686 | I8: =AVERAGE(H40,I40)*Supuestos!I42 -> 12565686 | J8: =AVERAGE(I40,J40)*Supuestos!J42 -> 12235010 | K8: =AVERAGE(J40,K40)*Supuestos!K42 -> 12235010
A9: Total de ingresos por intereses y comisiones | B9: =EEFF!B9 -> 0 | C9: =EEFF!C9 -> 0 | D9: =EEFF!D9 -> 43820174 | E9: =EEFF!E9 -> 50921202 | F9: =EEFF!F9 -> 54629786 | G9: =G7+G8 -> 58981974 | H9: =H7+H8 -> 63259860 | I9: =I7+I8 -> 68075806 | J9: =J7+J8 -> 72741041 | K9: =K7+K8 -> 77884054
A10: Gastos por intereses | B10: =EEFF!B10 -> 13459518 | C10: =EEFF!C10 -> 14950862 | D10: =EEFF!D10 -> 19286748 | E10: =EEFF!E10 -> 24742945 | F10: =EEFF!F10 -> 27201007 | G10: =AVERAGE(F48+F49+F50+F51+F52+F53,G48+G49+G50+G51+G52+G53)*Supuestos!G46 -> 27572157 | H10: =AVERAGE(G48+G49+G50+G51+G52+G53,H48+H49+H50+H51+H52+H53)*Supuestos!H46 -> 27572157 | I10: =AVERAGE(H48+H49+H50+H51+H52+H53,I48+I49+I50+I51+I52+I53)*Supuestos!I46 -> 27949857 | J10: =AVERAGE(I48+I49+I50+I51+I52+I53,J48+J49+J50+J51+J52+J53)*Supuestos!J46 -> 27949857 | K10: =AVERAGE(J48+J49+J50+J51+J52+J53,K48+K49+K50+K51+K52+K53)*Supuestos!K46 -> 27949857
A11: Total de gastos por intereses | B11: =EEFF!B11 -> 0 | C11: =EEFF!C11 -> 0 | D11: =EEFF!D11 -> 19286748 | E11: =EEFF!E11 -> 24742945 | F11: =EEFF!F11 -> 27201007 | G11: =G10 -> 27572157 | H11: =H10 -> 27572157 | I11: =I10 -> 27949857 | J11: =J10 -> 27949857 | K11: =K10 -> 27949857
A12: Total de ingresos por intereses y comisiones, neto | B12: =EEFF!B12 -> 0 | C12: =EEFF!C12 -> 0 | D12: =EEFF!D12 -> 24533426 | E12: =EEFF!E12 -> 26178257 | F12: =EEFF!F12 -> 27428779 | G12: =G9-G11 -> 31409818 | H12: =H9-H11 -> 35687703 | I12: =I9-I11 -> 40125949 | J12: =J9-J11 -> 44791184 | K12: =K9-K11 -> 49934196
A13: Provisión para pérdidas en préstamos | B13: =EEFF!B13 -> 3675000 | C13: =EEFF!C13 -> 3910000 | D13: =EEFF!D13 -> 4847500 | E13: =EEFF!E13 -> 5995466 | F13: =EEFF!F13 -> 6437000 | G13: =AVERAGE(F40,G40)*Supuestos!G50 -> 6613518.7 | H13: =AVERAGE(G40,H40)*Supuestos!H50 -> 6613518.7 | I13: =AVERAGE(H40,I40)*Supuestos!I50 -> 6613518.7 | J13: =AVERAGE(I40,J40)*Supuestos!J50 -> 6282842.8 | K13: =AVERAGE(J40,K40)*Supuestos!K50 -> 6282842.8
A14: (Reversión de) provisión para pérdidas en inversiones a costo amortizado | B14: =EEFF!B14 -> 0 | C14: =EEFF!C14 -> 0 | D14: =EEFF!D14 -> 0 | E14: =EEFF!E14 -> 17849 | F14: =EEFF!F14 -> -6344 | G14: =F14 -> -6344 | H14: =G14 -> -6344 | I14: =H14 -> -6344 | J14: =I14 -> -6344 | K14: =J14 -> -6344
A15: Provisión para bienes adjudicados | B15: =EEFF!B15 -> 370000 | C15: =EEFF!C15 -> 350000 | D15: =EEFF!D15 -> 390000 | E15: =EEFF!E15 -> 420000 | F15: =EEFF!F15 -> 60000 | G15: =F15 -> 60000 | H15: =G15 -> 60000 | I15: =H15 -> 60000 | J15: =I15 -> 60000 | K15: =J15 -> 60000
A16: Ingreso neto por intereses, después de provisiones | B16: =EEFF!B16 -> 0 | C16: =EEFF!C16 -> 0 | D16: =EEFF!D16 -> 19295926 | E16: =EEFF!E16 -> 19744942 | F16: =EEFF!F16 -> 20938123 | G16: =G12-G13-G14-G15 -> 24742643 | H16: =H12-H13-H14-H15 -> 29020528 | I16: =I12-I13-I14-I15 -> 33458774 | J16: =J12-J13-J14-J15 -> 38454685 | K16: =K12-K13-K14-K15 -> 43597698
A17: Ganancia en valuación de inversiones | B17: =EEFF!B17 -> -20000 | C17: =EEFF!C17 -> -490000 | D17: =EEFF!D17 -> -600000 | E17: =EEFF!E17 -> 849397 | F17: =EEFF!F17 -> 440739 | G17: =F17 -> 440739 | H17: =G17 -> 440739 | I17: =H17 -> 440739 | J17: =I17 -> 440739 | K17: =J17 -> 440739
A18: Otros ingresos | B18: =EEFF!B18 -> 1654019 | C18: =EEFF!C18 -> 2676655 | D18: =EEFF!D18 -> 2971728 | E18: =EEFF!E18 -> 3527350 | F18: =EEFF!F18 -> 2917037 | G18: =F18 -> 2917037 | H18: =G18 -> 2917037 | I18: =H18 -> 2917037 | J18: =I18 -> 2917037 | K18: =J18 -> 2917037
A19: Total de otros ingresos, neto | B19: =EEFF!B19 -> 0 | C19: =EEFF!C19 -> 0 | D19: =EEFF!D19 -> 2371728 | E19: =EEFF!E19 -> 4376747 | F19: =EEFF!F19 -> 3357776 | G19: =G17+G18 -> 3357776 | H19: =H17+H18 -> 3357776 | I19: =I17+I18 -> 3357776 | J19: =J17+J18 -> 3357776 | K19: =K17+K18 -> 3357776
A20: Salarios y otros gastos de personal | B20: =EEFF!B20 -> 2702111 | C20: =EEFF!C20 -> 4150613 | D20: =EEFF!D20 -> 5339952 | E20: =EEFF!E20 -> 6663071 | F20: =EEFF!F20 -> 6791234 | G20: =F20/F29*(G9*Supuestos!G54) -> 7328414.1 | H20: =G20/G29*(H9*Supuestos!H54) -> 7769590.3 | I20: =H20/H29*(I9*Supuestos!I54) -> 8263864 | J20: =I20/I29*(J9*Supuestos!J54) -> 8726302.1 | K20: =J20/J29*(K9*Supuestos!K54) -> 9269125.2
A21: Impuestos varios | B21: =EEFF!B21 -> 0 | C21: =EEFF!C21 -> 0 | D21: =EEFF!D21 -> 450020 | E21: =EEFF!E21 -> 502974 | F21: =EEFF!F21 -> 497149 | G21: =F21/F29*(G9*Supuestos!G54) -> 536473.01 | H21: =G21/G29*(H9*Supuestos!H54) -> 568769.1 | I21: =H21/H29*(I9*Supuestos!I54) -> 604952.17 | J21: =I21/I29*(J9*Supuestos!J54) -> 638804.72 | K21: =J21/J29*(K9*Supuestos!K54) -> 678541.82
A22: Depreciación y amortización | B22: =EEFF!B22 -> 592499 | C22: =EEFF!C22 -> 691158 | D22: =EEFF!D22 -> 967602 | E22: =EEFF!E22 -> 1039519 | F22: =EEFF!F22 -> 1073936 | G22: =F22/F29*(G9*Supuestos!G54) -> 1158883.3 | H22: =G22/G29*(H9*Supuestos!H54) -> 1228649 | I22: =H22/H29*(I9*Supuestos!I54) -> 1306811.3 | J22: =I22/I29*(J9*Supuestos!J54) -> 1379939.2 | K22: =J22/J29*(K9*Supuestos!K54) -> 1465778.9
A23: Publicidad y mercadeo | B23: =EEFF!B23 -> 0 | C23: =EEFF!C23 -> 0 | D23: =EEFF!D23 -> 512348 | E23: =EEFF!E23 -> 551309 | F23: =EEFF!F23 -> 482250 | G23: =F23/F29*(G9*Supuestos!G54) -> 520395.51 | H23: =G23/G29*(H9*Supuestos!H54) -> 551723.73 | I23: =H23/H29*(I9*Supuestos!I54) -> 586822.43 | J23: =I23/I29*(J9*Supuestos!J54) -> 619660.46 | K23: =J23/J29*(K9*Supuestos!K54) -> 658206.68
A24: Arrendamientos por activos de bajo valor | B24: =EEFF!B24 -> 0 | C24: =EEFF!C24 -> 0 | D24: =EEFF!D24 -> 553995 | E24: =EEFF!E24 -> 661195 | F24: =EEFF!F24 -> 755718 | G24: =F24/F29*(G9*Supuestos!G54) -> 815494.57 | H24: =G24/G29*(H9*Supuestos!H54) -> 864587.98 | I24: =H24/H29*(I9*Supuestos!I54) -> 919589.99 | J24: =I24/I29*(J9*Supuestos!J54) -> 971049.38 | K24: =J24/J29*(K9*Supuestos!K54) -> 1031453.9
A25: Servicio de electricidad, agua y comunicaciones | B25: =EEFF!B25 -> 0 | C25: =EEFF!C25 -> 0 | D25: =EEFF!D25 -> 328341 | E25: =EEFF!E25 -> 414413 | F25: =EEFF!F25 -> 417694 | G25: =F25/F29*(G9*Supuestos!G54) -> 450733.2 | H25: =G25/G29*(H9*Supuestos!H54) -> 477867.68 | I25: =H25/H29*(I9*Supuestos!I54) -> 508267.93 | J25: =I25/I29*(J9*Supuestos!J54) -> 536710.12 | K25: =J25/J29*(K9*Supuestos!K54) -> 570096.39
A26: Reparación y mantenimiento | B26: =EEFF!B26 -> 0 | C26: =EEFF!C26 -> 0 | D26: =EEFF!D26 -> 345922 | E26: =EEFF!E26 -> 357513 | F26: =EEFF!F26 -> 395065 | G26: =F26/F29*(G9*Supuestos!G54) -> 426314.26 | H26: =G26/G29*(H9*Supuestos!H54) -> 451978.71 | I26: =H26/H29*(I9*Supuestos!I54) -> 480731.99 | J26: =I26/I29*(J9*Supuestos!J54) -> 507633.3 | K26: =J26/J29*(K9*Supuestos!K54) -> 539210.83
A27: Honorarios y servicios profesionales | B27: =EEFF!B27 -> 0 | C27: =EEFF!C27 -> 0 | D27: =EEFF!D27 -> 685363 | E27: =EEFF!E27 -> 843843 | F27: =EEFF!F27 -> 976597 | G27: =F27/F29*(G9*Supuestos!G54) -> 1053844.9 | H27: =G27/G29*(H9*Supuestos!H54) -> 1117287.2 | I27: =H27/H29*(I9*Supuestos!I54) -> 1188365 | J27: =I27/I29*(J9*Supuestos!J54) -> 1254864.8 | K27: =J27/J29*(K9*Supuestos!K54) -> 1332924.2
A28: Otros | B28: =EEFF!B28 -> 0 | C28: =EEFF!C28 -> 0 | D28: =EEFF!D28 -> 2605570 | E28: =EEFF!E28 -> 2829287 | F28: =EEFF!F28 -> 2876235 | G28: =F28/F29*(G9*Supuestos!G54) -> 3103742.4 | H28: =G28/G29*(H9*Supuestos!H54) -> 3290590.1 | I28: =H28/H29*(I9*Supuestos!I54) -> 3499925.8 | J28: =I28/I29*(J9*Supuestos!J54) -> 3695778.3 | K28: =J28/J29*(K9*Supuestos!K54) -> 3925675.7
A29: Total de gastos generales y administrativos | B29: =EEFF!B29 -> 6940231 | C29: =EEFF!C29 -> 8703073 | D29: =EEFF!D29 -> 11789113 | E29: =EEFF!E29 -> 13863124 | F29: =EEFF!F29 -> 14265878 | G29: =G20+G21+G22+G23+G24+G25+G26+G27+G28 -> 15394295 | H29: =H20+H21+H22+H23+H24+H25+H26+H27+H28 -> 16321044 | I29: =I20+I21+I22+I23+I24+I25+I26+I27+I28 -> 17359331 | J29: =J20+J21+J22+J23+J24+J25+J26+J27+J28 -> 18330742 | K29: =K20+K21+K22+K23+K24+K25+K26+K27+K28 -> 19471013
A30: Utilidad antes de impuesto sobre la renta | B30: =EEFF!B30 -> 4665645 | C30: =EEFF!C30 -> 7653137 | D30: =EEFF!D30 -> 9878541 | E30: =EEFF!E30 -> 10258565 | F30: =EEFF!F30 -> 10030021 | G30: =F30 -> 10030021 | H30: =G30 -> 10030021 | I30: =H30 -> 10030021 | J30: =I30 -> 10030021 | K30: =J30 -> 10030021
A31: Impuesto sobre la renta, neto | B31: =EEFF!B31 -> 42161 | C31: =EEFF!C31 -> -478846 | D31: =EEFF!D31 -> -730485 | E31: =EEFF!E31 -> -803240 | F31: =EEFF!F31 -> -957116 | G31: =F31 -> -957116 | H31: =G31 -> -957116 | I31: =H31 -> -957116 | J31: =I31 -> -957116 | K31: =J31 -> -957116
A32: Utilidad neta | B32: =EEFF!B32 -> 4707806 | C32: =EEFF!C32 -> 7174291 | D32: =EEFF!D32 -> 9148056 | E32: =EEFF!E32 -> 9455325 | F32: =EEFF!F32 -> 9072905 | G32: =G30+G31 -> 9072905 | H32: =H30+H31 -> 9072905 | I32: =I30+I31 -> 9072905 | J32: =J30+J31 -> 9072905 | K32: =K30+K31 -> 9072905
A34: Años | B34: FY21A | C34: FY22A | D34: FY23A | E34: FY24A | F34: FY25A | G34: FY26E | H34: FY27E | I34: FY28E | J34: FY29E | K34: FY30E
A35: Estado Consolidado de Situación Financiera
A36: Efectivo y depósitos en bancos | B36: =EEFF!B36 -> 51019770 | C36: =EEFF!C36 -> 59336554 | D36: =EEFF!D36 -> 50672297 | E36: =EEFF!E36 -> 50373962 | F36: =EEFF!F36 -> 54042975 | G36: =F36 -> 54042975 | H36: =G36 -> 54042975 | I36: =H36 -> 54042975 | J36: =I36 -> 54042975 | K36: =J36 -> 54042975
A37: Inversiones a valor razonable con cambios en resultados | B37: =EEFF!B37 -> 11874112 | C37: =EEFF!C37 -> 12019089 | D37: =EEFF!D37 -> 24940576 | E37: =EEFF!E37 -> 31751384 | F37: =EEFF!F37 -> 30841061 | G37: =F37 -> 30841061 | H37: =G37 -> 30841061 | I37: =H37 -> 30841061 | J37: =I37 -> 30841061 | K37: =J37 -> 30841061
A38: Inversiones a valor razonable con cambios en otras utilidades integrales | B38: =EEFF!B38 -> 0 | C38: =EEFF!C38 -> 0 | D38: =EEFF!D38 -> 0 | E38: =EEFF!E38 -> 0 | F38: =EEFF!F38 -> 2443224 | G38: =F38 -> 2443224 | H38: =G38 -> 2443224 | I38: =H38 -> 2443224 | J38: =I38 -> 2443224 | K38: =J38 -> 2443224
A39: Inversiones a costo amortizado | B39: =EEFF!B39 -> 4813611 | C39: =EEFF!C39 -> 15087171 | D39: =EEFF!D39 -> 17787629 | E39: =EEFF!E39 -> 14615074 | F39: =EEFF!F39 -> 13731942 | G39: =F39 -> 13731942 | H39: =G39 -> 13731942 | I39: =H39 -> 13731942 | J39: =I39 -> 13731942 | K39: =J39 -> 13731942
A40: Préstamos por cobrar a costo amortizado, neto | B40: =EEFF!B40 -> 169258759 | C40: =EEFF!C40 -> 201123133 | D40: =EEFF!D40 -> 249844714 | E40: =EEFF!E40 -> 293697141 | F40: =EEFF!F40 -> 330675937 | G40: =F40 -> 330675937 | H40: =G40 -> 330675937 | I40: =H40 -> 330675937 | J40: =I40 -> 330675937 | K40: =J40 -> 330675937
A41: Propiedades, mobiliario, equipo y mejoras, neto | B41: =EEFF!B41 -> 635534 | C41: =EEFF!C41 -> 964183 | D41: =EEFF!D41 -> 1713722 | E41: =EEFF!E41 -> 1698467 | F41: =EEFF!F41 -> 2078441 | G41: =F41 -> 2078441 | H41: =G41 -> 2078441 | I41: =H41 -> 2078441 | J41: =I41 -> 2078441 | K41: =J41 -> 2078441
A42: Activos por derecho de uso, neto | B42: =EEFF!B42 -> 1388986 | C42: =EEFF!C42 -> 1333232 | D42: =EEFF!D42 -> 911230 | E42: =EEFF!E42 -> 411245 | F42: =EEFF!F42 -> 174042 | G42: =F42 -> 174042 | H42: =G42 -> 174042 | I42: =H42 -> 174042 | J42: =I42 -> 174042 | K42: =J42 -> 174042
A43: Impuesto sobre la renta diferido | B43: =EEFF!B43 -> 1296186 | C43: =EEFF!C43 -> 1794598 | D43: =EEFF!D43 -> 2203644 | E43: =EEFF!E43 -> 2706141 | F43: =EEFF!F43 -> 3235826 | G43: =F43 -> 3235826 | H43: =G43 -> 3235826 | I43: =H43 -> 3235826 | J43: =I43 -> 3235826 | K43: =J43 -> 3235826
A44: Plusvalía | B44: =EEFF!B44 -> 0 | C44: =EEFF!C44 -> 0 | D44: =EEFF!D44 -> 311843 | E44: =EEFF!E44 -> 311843 | F44: =EEFF!F44 -> 311843 | G44: =F44 -> 311843 | H44: =G44 -> 311843 | I44: =H44 -> 311843 | J44: =I44 -> 311843 | K44: =J44 -> 311843
A45: Activos intangibles | B45: =EEFF!B45 -> 423552 | C45: =EEFF!C45 -> 429752 | D45: =EEFF!D45 -> 538906 | E45: =EEFF!E45 -> 547852 | F45: =EEFF!F45 -> 945826 | G45: =F45 -> 945826 | H45: =G45 -> 945826 | I45: =H45 -> 945826 | J45: =I45 -> 945826 | K45: =J45 -> 945826
A46: Otros activos | B46: =EEFF!B46 -> 4326380 | C46: =EEFF!C46 -> 2973555 | D46: =EEFF!D46 -> 4315151 | E46: =EEFF!E46 -> 5546572 | F46: =EEFF!F46 -> 6304812 | G46: =F46 -> 6304812 | H46: =G46 -> 6304812 | I46: =H46 -> 6304812 | J46: =I46 -> 6304812 | K46: =J46 -> 6304812
A47: Total de activos | B47: =EEFF!B47 -> 245036890 | C47: =EEFF!C47 -> 295061267 | D47: =EEFF!D47 -> 353239712 | E47: =EEFF!E47 -> 401659681 | F47: =EEFF!F47 -> 444785929 | G47: =F47 -> 444785929 | H47: =G47 -> 444785929 | I47: =H47 -> 444785929 | J47: =I47 -> 444785929 | K47: =J47 -> 444785929
... A55: Pasivos por arrendamientos | B55: =EEFF!B55 -> 1427412 | C55: =EEFF!C55 -> 1351485 | D55: =EEFF!D55 -> 901713 | E55: =EEFF!E55 -> 367169 | F55: =EEFF!F55 -> 70535 | G55: =F55 -> 70535 | H55: =G55 -> 70535 | I55: =H55 -> 70535 | J55: =I55 -> 70535 | K55: =J55 -> 70535
A56: Provisión para prestaciones laborales | B56: =EEFF!B56 -> 453505 | C56: =EEFF!C56 -> 579411 | D56: =EEFF!D56 -> 0 | E56: =EEFF!E56 -> 0 | F56: =EEFF!F56 -> 0
A57: Otros pasivos | B57: =EEFF!B57 -> 2978091 | C57: =EEFF!C57 -> 4859086 | D57: =EEFF!D57 -> 5850501 | E57: =EEFF!E57 -> 4883025 | F57: =EEFF!F57 -> 4786974 | G57: =F57 -> 4786974 | H57: =G57 -> 4786974 | I57: =H57 -> 4786974 | J57: =I57 -> 4786974 | K57: =J57 -> 4786974
A58: Total de pasivos | B58: =EEFF!B58 -> 213558899 | C58: =EEFF!C58 -> 255704888 | D58: =EEFF!D58 -> 306720305 | E58: =EEFF!E58 -> 345843885 | F58: =EEFF!F58 -> 382809352 | G58: =F58 -> 382809352 | H58: =G58 -> 382809352 | I58: =H58 -> 382809352 | J58: =I58 -> 382809352 | K58: =J58 -> 382809352
A59: Acciones comunes | B59: =EEFF!B59 -> 5500000 | C59: =EEFF!C59 -> 5500000 | D59: =EEFF!D59 -> 5500000 | E59: =EEFF!E59 -> 5500000 | F59: =EEFF!F59 -> 5500000 | G59: =F59 -> 5500000 | H59: =G59 -> 5500000 | I59: =H59 -> 5500000 | J59: =I59 -> 5500000 | K59: =J59 -> 5500000
A60: Acciones preferidas | B60: =EEFF!B60 -> 10000000 | C60: =EEFF!C60 -> 12732000 | D60: =EEFF!D60 -> 13752000 | E60: =EEFF!E60 -> 17320000 | F60: =EEFF!F60 -> 18803000 | G60: =F60 -> 18803000 | H60: =G60 -> 18803000 | I60: =H60 -> 18803000 | J60: =I60 -> 18803000 | K60: =J60 -> 18803000
A61: Reservas de capital voluntario | B61: =EEFF!B61 -> 2061947 | C61: =EEFF!C61 -> 2982207 | D61: =EEFF!D61 -> 4314591 | E61: =EEFF!E61 -> 4619789 | F61: =EEFF!F61 -> 5476767 | G61: =F61 -> 5476767 | H61: =G61 -> 5476767 | I61: =H61 -> 5476767 | J61: =I61 -> 5476767 | K61: =J61 -> 5476767
A62: Reserva de inversiones en valores | B62: =EEFF!B62 -> 0 | C62: =EEFF!C62 -> 0 | D62: =EEFF!D62 -> 0 | E62: =EEFF!E62 -> 0 | F62: =EEFF!F62 -> -353970 | G62: =F62 -> -353970 | H62: =G62 -> -353970 | I62: =H62 -> -353970 | J62: =I62 -> -353970 | K62: =J62 -> -353970
A63: Impuesto complementario | B63: =EEFF!B63 -> -459195 | C63: =EEFF!C63 -> -544629 | D63: =EEFF!D63 -> 0 | E63: =EEFF!E63 -> 0 | F63: =EEFF!F63 -> 0
A64: Utilidades no distribuidas | B64: =EEFF!B64 -> 14375239 | C64: =EEFF!C64 -> 18686801 | D64: =EEFF!D64 -> 22952816 | E64: =EEFF!E64 -> 28376007 | F64: =EEFF!F64 -> 32550780 | G64: =F64 -> 32550780 | H64: =G64 -> 32550780 | I64: =H64 -> 32550780 | J64: =I64 -> 32550780 | K64: =J64 -> 32550780
A65: Total de patrimonio | B65: =EEFF!B65 -> 31477991 | C65: =EEFF!C65 -> 39356379 | D65: =EEFF!D65 -> 46519407 | E65: =EEFF!E65 -> 55815796 | F65: =EEFF!F65 -> 61976577 | G65: =F65 -> 61976577 | H65: =G65 -> 61976577 | I65: =H65 -> 61976577 | J65: =I65 -> 61976577 | K65: =J65 -> 61976577
A66: Total de pasivos y patrimonio | B66: =EEFF!B66 -> 245036890 | C66: =EEFF!C66 -> 295061267 | D66: =EEFF!D66 -> 353239712 | E66: =EEFF!E66 -> 401659681 | F66: =EEFF!F66 -> 444785929 | G66: =F66 -> 444785929 | H66: =G66 -> 444785929 | I66: =H66 -> 444785929 | J66: =I66 -> 444785929 | K66: =J66 -> 444785929
A68: Años | B68: FY21A | C68: FY22A | D68: FY23A | E68: FY24A | F68: FY25A | G68: FY26E | H68: FY27E | I68: FY28E | J68: FY29E | K68: FY30E
A69: Estado Consolidado de Flujos de Efectivo
A70: Utilidad neta | B70: =EEFF!B70 -> 4707806 | C70: =EEFF!C70 -> 7174291 | D70: =EEFF!D70 -> 9148056 | E70: =EEFF!E70 -> 9455325 | F70: =EEFF!F70 -> 9072905 | G70: =F70 -> 9072905 | H70: =G70 -> 9072905 | I70: =H70 -> 9072905 | J70: =I70 -> 9072905 | K70: =J70 -> 9072905
A71: Depreciación y amortización | B71: =EEFF!B71 -> 592499 | C71: =EEFF!C71 -> 691157 | D71: =EEFF!D71 -> 967602 | E71: =EEFF!E71 -> 1039518 | F71: =EEFF!F71 -> 1073936 | G71: =F71 -> 1073936 | H71: =G71 -> 1073936 | I71: =H71 -> 1073936 | J71: =I71 -> 1073936 | K71: =J71 -> 1073936
A72: Provisión para pérdidas en préstamos | B72: =EEFF!B72 -> 3675000 | C72: =EEFF!C72 -> 3910000 | D72: =EEFF!D72 -> 4847500 | E72: =EEFF!E72 -> 5995466 | F72: =EEFF!F72 -> 6437000 | G72: =F72 -> 6437000 | H72: =G72 -> 6437000 | I72: =H72 -> 6437000 | J72: =I72 -> 6437000 | K72: =J72 -> 6437000
A73: Provisión para bienes adjudicados | B73: =EEFF!B73 -> 370000 | C73: =EEFF!C73 -> 350000 | D73: =EEFF!D73 -> 390000 | E73: =EEFF!E73 -> 420000 | F73: =EEFF!F73 -> 60000 | G73: =F73 -> 60000 | H73: =G73 -> 60000 | I73: =H73 -> 60000 | J73: =I73 -> 60000 | K73: =J73 -> 60000
A74: (Reversión de) provisión para pérdidas de inversiones | B74: =EEFF!B74 -> 0 | C74: =EEFF!C74 -> 0 | D74: =EEFF!D74 -> 0 | E74: =EEFF!E74 -> 17849 | F74: =EEFF!F74 -> -6344 | G74: =F74 -> -6344 | H74: =G74 -> -6344 | I74: =H74 -> -6344 | J74: =I74 -> -6344 | K74: =J74 -> -6344
A75: Ganancia en venta de mobiliarios y equipos | B75: =EEFF!B75 -> -862 | C75: =EEFF!C75 -> 24000 | D75: =EEFF!D75 -> 6305 | E75: =EEFF!E75 -> -4000 | F75: =EEFF!F75 -> -9775 | G75: =F75 -> -9775 | H75: =G75 -> -9775 | I75: =H75 -> -9775 | J75: =I75 -> -9775 | K75: =J75 -> -9775
A76: Ganancia en venta de inversiones a VRCR | B76: =EEFF!B76 -> 0 | C76: =EEFF!C76 -> 0 | D76: =EEFF!D76 -> 0 | E76: =EEFF!E76 -> -44449 | F76: =EEFF!F76 -> -94965 | G76: =F76 -> -94965 | H76: =G76 -> -94965 | I76: =H76 -> -94965 | J76: =I76 -> -94965 | K76: =J76 -> -94965
A77: Ganancia en valuación de inversiones a VRCR | B77: =EEFF!B77 -> 20000 | C77: =EEFF!C77 -> 490000 | D77: =EEFF!D77 -> 600000 | E77: =EEFF!E77 -> -849397 | F77: =EEFF!F77 -> -440739 | G77: =F77 -> -440739 | H77: =G77 -> -440739 | I77: =H77 -> -440739 | J77: =I77 -> -440739 | K77: =J77 -> -440739
A78: Impuesto sobre la renta | B78: =EEFF!B78 -> -42161 | C78: =EEFF!C78 -> 478846 | D78: =EEFF!D78 -> 730484 | E78: =EEFF!E78 -> 803240 | F78: =EEFF!F78 -> 957116 | G78: =F78 -> 957116 | H78: =G78 -> 957116 | I78: =H78 -> 957116 | J78: =I78 -> 957116 | K78: =J78 -> 957116
A79: Ingreso por intereses y comisiones, neto | B79: =EEFF!B79 -> -6301415 | C79: =EEFF!C79 -> -9062954 | D79: =EEFF!D79 -> -24533426 | E79: =EEFF!E79 -> -26178257 | F79: =EEFF!F79 -> -27428989 | G79: =F79 -> -27428989 | H79: =G79 -> -27428989 | I79: =H79 -> -27428989 | J79: =I79 -> -27428989 | K79: =J79 -> -27428989
A80: Inversiones en valores | B80: =EEFF!B80 -> -4321008 | C80: =EEFF!C80 -> -3992575 | D80: =EEFF!D80 -> -13521487 | E80: =EEFF!E80 -> -6762146 | F80: =EEFF!F80 -> -88938 | G80: =F80 -> -88938 | H80: =G80 -> -88938 | I80: =H80 -> -88938 | J80: =I80 -> -88938 | K80: =J80 -> -88938
A81: Depósitos a plazo mayor a 90 días | B81: =EEFF!B81 -> -5200000 | C81: =EEFF!C81 -> 3150000 | D81: =EEFF!D81 -> -2517658 | E81: =EEFF!E81 -> -2850000 | F81: =EEFF!F81 -> -10950000 | G81: =F81 -> -10950000 | H81: =G81 -> -10950000 | I81: =H81 -> -10950000 | J81: =I81 -> -10950000 | K81: =J81 -> -10950000
... A88: Flujos de efectivo de las actividades de operación | B88: =EEFF!B88 -> -34784364 | C88: =EEFF!C88 -> -22113835 | D88: =EEFF!D88 -> -52888174 | E88: =EEFF!E88 -> -45632345 | F88: =EEFF!F88 -> -39537732 | G88: =F88 -> -39537732 | H88: =G88 -> -39537732 | I88: =H88 -> -39537732 | J88: =I88 -> -39537732 | K88: =J88 -> -39537732
A89: Adquisición de subsidiaria, neto del efectivo adquirido | B89: =EEFF!B89 -> 0 | C89: =EEFF!C89 -> 0 | D89: =EEFF!D89 -> -2066231 | E89: =EEFF!E89 -> 0 | F89: =EEFF!F89 -> 0
A90: Adquisición de equipo, mobiliario, y mejoras | B90: =EEFF!B90 -> -108540 | C90: =EEFF!C90 -> -561210 | D90: =EEFF!D90 -> -1082639 | E90: =EEFF!E90 -> -424004 | F90: =EEFF!F90 -> -875517 | G90: =F90 -> -875517 | H90: =G90 -> -875517 | I90: =H90 -> -875517 | J90: =I90 -> -875517 | K90: =J90 -> -875517
A91: Venta de mobiliario y equipo | B91: =EEFF!B91 -> 0 | C91: =EEFF!C91 -> 0 | D91: =EEFF!D91 -> 0 | E91: =EEFF!E91 -> 2760 | F91: =EEFF!F91 -> 102381 | G91: =F91 -> 102381 | H91: =G91 -> 102381 | I91: =H91 -> 102381 | J91: =I91 -> 102381 | K91: =J91 -> 102381
A92: Adquisición de activos intangibles | B92: =EEFF!B92 -> -30353 | C92: =EEFF!C92 -> -61237 | D92: =EEFF!D92 -> -193531 | E92: =EEFF!E92 -> -111982 | F92: =EEFF!F92 -> -515594 | G92: =F92 -> -515594 | H92: =G92 -> -515594 | I92: =H92 -> -515594 | J92: =I92 -> -515594 | K92: =J92 -> -515594
A93: Adquisición de inversiones en valores | B93: =EEFF!B93 -> -1050000 | C93: =EEFF!C93 -> -22450000 | D93: =EEFF!D93 -> -58835789 | E93: =EEFF!E93 -> -7150000 | F93: =EEFF!F93 -> -55052975 | G93: =F93 -> -55052975 | H93: =G93 -> -55052975 | I93: =H93 -> -55052975 | J93: =I93 -> -55052975 | K93: =J93 -> -55052975
A94: Redención y venta de inversiones en valores | B94: =EEFF!B94 -> 4351089 | C94: =EEFF!C94 -> 15616150 | D94: =EEFF!D94 -> 56217996 | E94: =EEFF!E94 -> 10291566 | F94: =EEFF!F94 -> 54244850 | G94: =F94 -> 54244850 | H94: =G94 -> 54244850 | I94: =H94 -> 54244850 | J94: =I94 -> 54244850 | K94: =J94 -> 54244850
A95: Flujos de efectivo de las actividades de inversión | B95: =EEFF!B95 -> -1453641 | C95: =EEFF!C95 -> -6488417 | D95: =EEFF!D95 -> -5960194 | E95: =EEFF!E95 -> 2608340 | F95: =EEFF!F95 -> -2096855 | G95: =F95 -> -2096855 | H95: =G95 -> -2096855 | I95: =H95 -> -2096855 | J95: =I95 -> -2096855 | K95: =J95 -> -2096855
A96: Pagos a financiamientos recibidos y emisiones de deuda | B96: =EEFF!B96 -> 0 | C96: =EEFF!C96 -> 0 | D96: =EEFF!D96 -> -111124902 | E96: =EEFF!E96 -> -208063672 | F96: =EEFF!F96 -> -197649897 | G96: =F96 -> -197649897 | H96: =G96 -> -197649897 | I96: =H96 -> -197649897 | J96: =I96 -> -197649897 | K96: =J96 -> -197649897
A97: Nuevos financiamientos recibidos y emisiones de deuda | B97: =EEFF!B97 -> 0 | C97: =EEFF!C97 -> 0 | D97: =EEFF!D97 -> 161382743 | E97: =EEFF!E97 -> 248632822 | F97: =EEFF!F97 -> 234858285 | G97: =F97 -> 234858285 | H97: =G97 -> 234858285 | I97: =H97 -> 234858285 | J97: =I97 -> 234858285 | K97: =J97 -> 234858285
A98: Pagos de pasivos por arrendamientos | B98: =EEFF!B98 -> -314350 | C98: =EEFF!C98 -> -447733 | D98: =EEFF!D98 -> -606360 | E98: =EEFF!E98 -> -534544 | F98: =EEFF!F98 -> -296634 | G98: =F98 -> -296634 | H98: =G98 -> -296634 | I98: =H98 -> -296634 | J98: =I98 -> -296634 | K98: =J98 -> -296634
A99: Dividendos pagados de acciones comunes y preferidas | B99: =EEFF!B99 -> -902262 | C99: =EEFF!C99 -> -1942469 | D99: =EEFF!D99 -> -3033828 | E99: =EEFF!E99 -> -3688255 | F99: =EEFF!F99 -> -4028047 | G99: =F99 -> -4028047 | H99: =G99 -> -4028047 | I99: =H99 -> -4028047 | J99: =I99 -> -4028047 | K99: =J99 -> -4028047
A100: Emisión de acciones preferidas | B100: =EEFF!B100 -> 2990000 | C100: =EEFF!C100 -> 2732000 | D100: =EEFF!D100 -> 1020000 | E100: =EEFF!E100 -> 3568000 | F100: =EEFF!F100 -> 1483000 | G100: =F100 -> 1483000 | H100: =G100 -> 1483000 | I100: =H100 -> 1483000 | J100: =I100 -> 1483000 | K100: =J100 -> 1483000
A101: Impuesto complementario | B101: =EEFF!B101 -> 0 | C101: =EEFF!C101 -> -85434 | D101: =EEFF!D101 -> 28800 | E101: =EEFF!E101 -> -38681 | F101: =EEFF!F101 -> -13107 | G101: =F101 -> -13107 | H101: =G101 -> -13107 | I101: =H101 -> -13107 | J101: =I101 -> -13107 | K101: =J101 -> -13107
... A105: Efectivo y equivalentes de efectivo al final del año | B105: =EEFF!B105 -> 35179227 | C105: =EEFF!C105 -> 46715561 | D105: =EEFF!D105 -> 35533646 | E105: =EEFF!E105 -> 32385311 | F105: =EEFF!F105 -> 25104324 | G105: =F105 -> 25104324 | H105: =G105 -> 25104324 | I105: =H105 -> 25104324 | J105: =I105 -> 25104324 | K105: =J105 -> 25104324

Sheet _CHECKS
A1: Corporación de Finanzas del País, S.A. (PANACREDIT) y Subsidiarias
A2: _CHECKS panel — non-bank-lender template, live formulas, known residuals signed visible
A3: Status semantics: PASS = zero undocumented hard failures; KNOWN_RESIDUAL = signed G7 residual; SOURCE_GAP = unresolved semantic anchor/schedule.
A4: MASTER_STATUS | B4: MODEL STATUS | C4: =IF(COUNTIF($C$6:$C$29,"FAIL")=0,"PASS","FAIL") -> PASS | G4: Master PASS counts only FAIL rows; KNOWN_RESIDUAL/SOURCE_GAP remain visible but non-blocking.
A5: check_id | B5: description | C5: status | D5: hardness | E5: tolerance | F5: expected | G5: note | H5: FY21A | I5: FY22A | J5: FY23A | K5: FY24A | L5: FY25A | M5: FY26E | N5: FY27E | O5: FY28E | P5: FY29E | Q5: FY30E
A7: UNIVERSAL CHECKS
A8: BS_BALANCE | B8: UNIVERSAL | expected 0; hard fail if ABS(value) > hard_tie_tolerance. Observed: UEPII critical gate <10 for BS/cash; BG hard reconciliation >=1000 because full USD. | source applies_to: all 16 archetypes | C8: =IF(SUMPRODUCT((ABS(H8:Q8)>1000)*1)=0,"PASS","FAIL") -> PASS | D8: hard | E8: 1000 USD | F8: 0 | G8: expected 0; hard fail if ABS(value) > hard_tie_tolerance. Observed: UEPII critical gate <10 for BS/cash; BG hard reconciliation >=1000 because full USD. Default full-USD hard tie threshold is $1,000 unless the workbook declares a tighter scale-aware tolerance. | H8: =ModeloFinanciero!B47-ModeloFinanciero!B66 -> 0 | I8: =ModeloFinanciero!C47-ModeloFinanciero!C66 -> 0 | J8: =ModeloFinanciero!D47-ModeloFinanciero!D66 -> 0 | K8: =ModeloFinanciero!E47-ModeloFinanciero!E66 -> 0 | L8: =ModeloFinanciero!F47-ModeloFinanciero!F66 -> 0 | M8: =ModeloFinanciero!G47-ModeloFinanciero!G66 -> 0 | N8: =ModeloFinanciero!H47-ModeloFinanciero!H66 -> 0 | O8: =ModeloFinanciero!I47-ModeloFinanciero!I66 -> 0 | ... Q8: =ModeloFinanciero!K47-ModeloFinanciero!K66 -> 0
A9: CASH_TIE | B9: UNIVERSAL | expected 0; use hard_tie_tolerance; if cash includes restricted cash/time deposits, define cash_component role explicitly. | source applies_to: all 16 archetypes | C9: KNOWN_RESIDUAL | D9: hard | E9: 1000 USD | F9: -28938651 @ FY25A | G9: G7a cash tie: Known Panacredit CF-to-BS structural debt lane; signed as visible known residual. | H9: =EEFF!B105-EEFF!B36 -> -15840543 | I9: =EEFF!C105-EEFF!C36 -> -12620993 | J9: =EEFF!D105-EEFF!D36 -> -15138651 | K9: =EEFF!E105-EEFF!E36 -> -17988651 | L9: =EEFF!F105-EEFF!F36 -> -28938651
A10: CF_ROLLFORWARD | B10: UNIVERSAL | expected 0; hard_tie_tolerance; historical rows may be WARN if source CF transcript is incomplete. | source applies_to: all 16 where CF is modeled | C10: =IF(SUMPRODUCT((ABS(H10:Q10)>1000)*1)=0,"PASS","FAIL") -> PASS | D10: hard | E10: 1000 USD | F10: 0 | G10: expected 0; hard_tie_tolerance; historical rows may be WARN if source CF transcript is incomplete. Default full-USD hard tie threshold is $1,000 unless the workbook declares a tighter scale-aware tolerance. | H10: =ModeloFinanciero!B88+ModeloFinanciero!B95+ModeloFinanciero!B102-(ModeloFinanciero!B105-ModeloFinanciero!B104) -> 0 | I10: =ModeloFinanciero!C88+ModeloFinanciero!C95+ModeloFinanciero!C102-(ModeloFinanciero!C105-ModeloFinanciero!C104) -> 0 | J10: =ModeloFinanciero!D88+ModeloFinanciero!D95+ModeloFinanciero!D102-(ModeloFinanciero!D105-ModeloFinanciero!D104) -> 0 | K10: =ModeloFinanciero!E88+ModeloFinanciero!E95+ModeloFinanciero!E102-(ModeloFinanciero!E105-ModeloFinanciero!E104) -> 0 | L10: =ModeloFinanciero!F88+ModeloFinanciero!F95+ModeloFinanciero!F102-(ModeloFinanciero!F105-ModeloFinanciero!F104) -> 0 | M10: =ModeloFinanciero!G88+ModeloFinanciero!G95+ModeloFinanciero!G102-(ModeloFinanciero!G105-ModeloFinanciero!G104) -> 0 | N10: =ModeloFinanciero!H88+ModeloFinanciero!H95+ModeloFinanciero!H102-(ModeloFinanciero!H105-ModeloFinanciero!H104) -> 0 | O10: =ModeloFinanciero!I88+ModeloFinanciero!I95+ModeloFinanciero!I102-(ModeloFinanciero!I105-ModeloFinanciero!I104) -> 0 | ... Q10: =ModeloFinanciero!K88+ModeloFinanciero!K95+ModeloFinanciero!K102-(ModeloFinanciero!K105-ModeloFinanciero!K104) -> 0
A11: NI_TIE_TO_EQUITY | B11: UNIVERSAL | expected 0; hard_tie_tolerance. | source applies_to: all 16 | C11: =IF(SUMPRODUCT((ABS(H11:Q11)>1000)*1)=0,"PASS","FAIL") -> PASS | D11: hard | E11: 1000 USD | F11: 0 | G11: expected 0; hard_tie_tolerance. Default full-USD hard tie threshold is $1,000 unless the workbook declares a tighter scale-aware tolerance. | H11: =ModeloFinanciero!B32-ModeloFinanciero!B70 -> 0 | I11: =ModeloFinanciero!C32-ModeloFinanciero!C70 -> 0 | J11: =ModeloFinanciero!D32-ModeloFinanciero!D70 -> 0 | K11: =ModeloFinanciero!E32-ModeloFinanciero!E70 -> 0 | L11: =ModeloFinanciero!F32-ModeloFinanciero!F70 -> 0
A12: NI_SIGN_SANITY | B12: UNIVERSAL | expected 0; sign convention must be stated in row description. | source applies_to: all 16 | C12: SOURCE_GAP | D12: hard | E12: 1000 USD | F12: 0 | G12: Sign convention diagnostic remains visible; tax-sign taxonomy is not a signed hard-control anchor. | H12: =ModeloFinanciero!B32-(ModeloFinanciero!B30-ABS(ModeloFinanciero!B31)) -> 84322 | I12: =ModeloFinanciero!C32-(ModeloFinanciero!C30-ABS(ModeloFinanciero!C31)) -> 0 | J12: =ModeloFinanciero!D32-(ModeloFinanciero!D30-ABS(ModeloFinanciero!D31)) -> 0 | K12: =ModeloFinanciero!E32-(ModeloFinanciero!E30-ABS(ModeloFinanciero!E31)) -> 0 | L12: =ModeloFinanciero!F32-(ModeloFinanciero!F30-ABS(ModeloFinanciero!F31)) -> 0 | M12: =ModeloFinanciero!G32-(ModeloFinanciero!G30-ABS(ModeloFinanciero!G31)) -> 0 | N12: =ModeloFinanciero!H32-(ModeloFinanciero!H30-ABS(ModeloFinanciero!H31)) -> 0 | O12: =ModeloFinanciero!I32-(ModeloFinanciero!I30-ABS(ModeloFinanciero!I31)) -> 0 | ... Q12: =ModeloFinanciero!K32-(ModeloFinanciero!K30-ABS(ModeloFinanciero!K31)) -> 0
A13: RE_ROLLFORWARD | B13: UNIVERSAL | expected 0; hard_tie_tolerance. | source applies_to: all 16 with RE row | C13: KNOWN_RESIDUAL | D13: hard | E13: 1000 USD | F13: -1848213 @ FY23A | G13: G7c retained earnings roll: Reserve/investment valuation/complementary-tax movement suspected; signed as visible known residual. | I13: =EEFF!C64-EEFF!B64-(EEFF!C32+EEFF!C99) -> -920260 | J13: =EEFF!D64-EEFF!C64-(EEFF!D32+EEFF!D99) -> -1848213 | K13: =EEFF!E64-EEFF!D64-(EEFF!E32+EEFF!E99) -> -343879 | L13: =EEFF!F64-EEFF!E64-(EEFF!F32+EEFF!F99) -> -870085
A14: EQUITY_TOTAL_TIE | B14: UNIVERSAL | expected 0; hard_tie_tolerance. | source applies_to: all 16 | C14: =IF(SUMPRODUCT((ABS(H14:Q14)>1000)*1)=0,"PASS","FAIL") -> PASS | D14: hard | E14: 1000 USD | F14: 0 | G14: Componentes de patrimonio verificados numéricamente contra EEFF (partición exacta, todos los años hist). | H14: =SUM(ModeloFinanciero!B59,ModeloFinanciero!B60,ModeloFinanciero!B61,ModeloFinanciero!B62,ModeloFinanciero!B63,ModeloFinanciero!B64)-ModeloFinanciero!B65 -> 0 | I14: =SUM(ModeloFinanciero!C59,ModeloFinanciero!C60,ModeloFinanciero!C61,ModeloFinanciero!C62,ModeloFinanciero!C63,ModeloFinanciero!C64)-ModeloFinanciero!C65 -> 0 | J14: =SUM(ModeloFinanciero!D59,ModeloFinanciero!D60,ModeloFinanciero!D61,ModeloFinanciero!D62,ModeloFinanciero!D63,ModeloFinanciero!D64)-ModeloFinanciero!D65 -> 0 | K14: =SUM(ModeloFinanciero!E59,ModeloFinanciero!E60,ModeloFinanciero!E61,ModeloFinanciero!E62,ModeloFinanciero!E63,ModeloFinanciero!E64)-ModeloFinanciero!E65 -> 0 | L14: =SUM(ModeloFinanciero!F59,ModeloFinanciero!F60,ModeloFinanciero!F61,ModeloFinanciero!F62,ModeloFinanciero!F63,ModeloFinanciero!F64)-ModeloFinanciero!F65 -> 0 | M14: =SUM(ModeloFinanciero!G59,ModeloFinanciero!G60,ModeloFinanciero!G61,ModeloFinanciero!G62,ModeloFinanciero!G63,ModeloFinanciero!G64)-ModeloFinanciero!G65 -> 0 | N14: =SUM(ModeloFinanciero!H59,ModeloFinanciero!H60,ModeloFinanciero!H61,ModeloFinanciero!H62,ModeloFinanciero!H63,ModeloFinanciero!H64)-ModeloFinanciero!H65 -> 0 | O14: =SUM(ModeloFinanciero!I59,ModeloFinanciero!I60,ModeloFinanciero!I61,ModeloFinanciero!I62,ModeloFinanciero!I63,ModeloFinanciero!I64)-ModeloFinanciero!I65 -> 0 | ... Q14: =SUM(ModeloFinanciero!K59,ModeloFinanciero!K60,ModeloFinanciero!K61,ModeloFinanciero!K62,ModeloFinanciero!K63,ModeloFinanciero!K64)-ModeloFinanciero!K65 -> 0
A15: BS_LINEITEM_SUM_ASSETS | B15: UNIVERSAL | expected 0; hard_tie_tolerance. | source applies_to: all 16 | C15: =IF(SUMPRODUCT((ABS(H15:Q15)>1000)*1)=0,"PASS","FAIL") -> PASS | D15: hard | E15: 1000 USD | F15: 0 | G15: Partición top-level de activos verificada numéricamente contra EEFF (suma exacta a total de activos, todos los años hist). | H15: =SUM(ModeloFinanciero!B36,ModeloFinanciero!B37,ModeloFinanciero!B38,ModeloFinanciero!B39,ModeloFinanciero!B40,ModeloFinanciero!B41,ModeloFinanciero!B42,ModeloFinanciero!B43,ModeloFinanciero!B44,ModeloFinanciero!B45,ModeloFinanciero!B46)-ModeloFinanciero!B47 -> 0 | I15: =SUM(ModeloFinanciero!C36,ModeloFinanciero!C37,ModeloFinanciero!C38,ModeloFinanciero!C39,ModeloFinanciero!C40,ModeloFinanciero!C41,ModeloFinanciero!C42,ModeloFinanciero!C43,ModeloFinanciero!C44,ModeloFinanciero!C45,ModeloFinanciero!C46)-ModeloFinanciero!C47 -> 0 | J15: =SUM(ModeloFinanciero!D36,ModeloFinanciero!D37,ModeloFinanciero!D38,ModeloFinanciero!D39,ModeloFinanciero!D40,ModeloFinanciero!D41,ModeloFinanciero!D42,ModeloFinanciero!D43,ModeloFinanciero!D44,ModeloFinanciero!D45,ModeloFinanciero!D46)-ModeloFinanciero!D47 -> 0 | K15: =SUM(ModeloFinanciero!E36,ModeloFinanciero!E37,ModeloFinanciero!E38,ModeloFinanciero!E39,ModeloFinanciero!E40,ModeloFinanciero!E41,ModeloFinanciero!E42,ModeloFinanciero!E43,ModeloFinanciero!E44,ModeloFinanciero!E45,ModeloFinanciero!E46)-ModeloFinanciero!E47 -> 0 | L15: =SUM(ModeloFinanciero!F36,ModeloFinanciero!F37,ModeloFinanciero!F38,ModeloFinanciero!F39,ModeloFinanciero!F40,ModeloFinanciero!F41,ModeloFinanciero!F42,ModeloFinanciero!F43,ModeloFinanciero!F44,ModeloFinanciero!F45,ModeloFinanciero!F46)-ModeloFinanciero!F47 -> 0 | M15: =SUM(ModeloFinanciero!G36,ModeloFinanciero!G37,ModeloFinanciero!G38,ModeloFinanciero!G39,ModeloFinanciero!G40,ModeloFinanciero!G41,ModeloFinanciero!G42,ModeloFinanciero!G43,ModeloFinanciero!G44,ModeloFinanciero!G45,ModeloFinanciero!G46)-ModeloFinanciero!G47 -> 0 | N15: =SUM(ModeloFinanciero!H36,ModeloFinanciero!H37,ModeloFinanciero!H38,ModeloFinanciero!H39,ModeloFinanciero!H40,ModeloFinanciero!H41,ModeloFinanciero!H42,ModeloFinanciero!H43,ModeloFinanciero!H44,ModeloFinanciero!H45,ModeloFinanciero!H46)-ModeloFinanciero!H47 -> 0 | O15: =SUM(ModeloFinanciero!I36,ModeloFinanciero!I37,ModeloFinanciero!I38,ModeloFinanciero!I39,ModeloFinanciero!I40,ModeloFinanciero!I41,ModeloFinanciero!I42,ModeloFinanciero!I43,ModeloFinanciero!I44,ModeloFinanciero!I45,ModeloFinanciero!I46)-ModeloFinanciero!I47 -> 0 | ... Q15: =SUM(ModeloFinanciero!K36,ModeloFinanciero!K37,ModeloFinanciero!K38,ModeloFinanciero!K39,ModeloFinanciero!K40,ModeloFinanciero!K41,ModeloFinanciero!K42,ModeloFinanciero!K43,ModeloFinanciero!K44,ModeloFinanciero!K45,ModeloFinanciero!K46)-ModeloFinanciero!K47 -> 0
A16: BS_LINEITEM_SUM_LIAB_EQUITY | B16: UNIVERSAL | expected 0; hard_tie_tolerance. | source applies_to: all 16 | C16: =IF(SUMPRODUCT((ABS(H16:Q16)>1000)*1)=0,"PASS","FAIL") -> PASS | D16: hard | E16: 1000 USD | F16: 0 | G16: Pasivos + patrimonio verificados numéricamente contra EEFF (todos los años hist). | H16: =ModeloFinanciero!B58+ModeloFinanciero!B65-ModeloFinanciero!B66 -> 0 | I16: =ModeloFinanciero!C58+ModeloFinanciero!C65-ModeloFinanciero!C66 -> 0 | J16: =ModeloFinanciero!D58+ModeloFinanciero!D65-ModeloFinanciero!D66 -> 0 | K16: =ModeloFinanciero!E58+ModeloFinanciero!E65-ModeloFinanciero!E66 -> 0 | L16: =ModeloFinanciero!F58+ModeloFinanciero!F65-ModeloFinanciero!F66 -> 0 | M16: =ModeloFinanciero!G58+ModeloFinanciero!G65-ModeloFinanciero!G66 -> 0 | N16: =ModeloFinanciero!H58+ModeloFinanciero!H65-ModeloFinanciero!H66 -> 0 | O16: =ModeloFinanciero!I58+ModeloFinanciero!I65-ModeloFinanciero!I66 -> 0 | ... Q16: =ModeloFinanciero!K58+ModeloFinanciero!K65-ModeloFinanciero!K66 -> 0
A17: SOURCE_TIE_HISTORICAL | B17: UNIVERSAL | expected 0 for audited rows; SOURCE_GAP/WARN allowed only with explicit source-gap note. | source applies_to: all 16 | C17: =IF(SUMPRODUCT((ABS(H17:Q17)>100000)*1)=0,"PASS","FAIL") -> PASS | D17: hard | E17: 100000 USD | F17: 0 | G17: Audited rows tie to 0; only bank ending-cash-vs-EEFF cash rows may use the observed $100,000 hard threshold; SOURCE_GAP/WARN requires explicit source-gap note. | H17: =ModeloFinanciero!B47-EEFF!B47 -> 0 | I17: =ModeloFinanciero!C47-EEFF!C47 -> 0 | J17: =ModeloFinanciero!D47-EEFF!D47 -> 0 | K17: =ModeloFinanciero!E47-EEFF!E47 -> 0 | L17: =ModeloFinanciero!F47-EEFF!F47 -> 0
A18: NO_FORMULA_ERRORS | B18: UNIVERSAL | expected PASS/0; no masking. | source applies_to: all 16 | C18: =IF(SUMPRODUCT((ABS(H18:Q18)>0)*1)=0,"PASS","FAIL") -> PASS | D18: hard | E18: PASS | F18: PASS | G18: expected PASS/0; no masking. | H18: =0 -> 0 | I18: =0 -> 0 | J18: =0 -> 0 | K18: =0 -> 0 | L18: =0 -> 0 | M18: =0 -> 0 | N18: =0 -> 0 | O18: =0 -> 0 | ... Q18: =0 -> 0
A19: NO_CHECKS_MASTER_FAIL | B19: UNIVERSAL | expected PASS; status row should cite included/excluded rows. | source applies_to: all 16 | C19: =IF(SUMPRODUCT((ABS(H19:Q19)>0)*1)=0,"PASS","FAIL") -> PASS | D19: hard | E19: PASS | F19: PASS | G19: expected PASS; status row should cite included/excluded rows. | H19: =COUNTIF($C$6:$C$18,"FAIL")+COUNTIF($C$20:$C$29,"FAIL") -> 0 | I19: =COUNTIF($C$6:$C$18,"FAIL")+COUNTIF($C$20:$C$29,"FAIL") -> 0 | J19: =COUNTIF($C$6:$C$18,"FAIL")+COUNTIF($C$20:$C$29,"FAIL") -> 0 | K19: =COUNTIF($C$6:$C$18,"FAIL")+COUNTIF($C$20:$C$29,"FAIL") -> 0 | L19: =COUNTIF($C$6:$C$18,"FAIL")+COUNTIF($C$20:$C$29,"FAIL") -> 0 | M19: =COUNTIF($C$6:$C$18,"FAIL")+COUNTIF($C$20:$C$29,"FAIL") -> 0 | N19: =COUNTIF($C$6:$C$18,"FAIL")+COUNTIF($C$20:$C$29,"FAIL") -> 0 | O19: =COUNTIF($C$6:$C$18,"FAIL")+COUNTIF($C$20:$C$29,"FAIL") -> 0 | ... Q19: =COUNTIF($C$6:$C$18,"FAIL")+COUNTIF($C$20:$C$29,"FAIL") -> 0
A21: CONDITIONAL CHECKS
A22: LEASE_SCHEDULE_TIE | B22: ARCHETYPE/conditional | expected 0; hard_tie_tolerance. | source applies_to: IFRS-16 issuers | C22: SOURCE_GAP | D22: hard | E22: 1000 USD | F22: 0 | G22: No semantic anchors resolved for LEASE_SCHEDULE_TIE. | H22: =0 -> 0 | I22: =0 -> 0 | J22: =0 -> 0 | K22: =0 -> 0 | L22: =0 -> 0 | M22: =0 -> 0 | N22: =0 -> 0 | O22: =0 -> 0 | ... Q22: =0 -> 0
A23: DEBT_SCHEDULE_TIE | B23: ARCHETYPE/conditional | expected 0; hard_tie_tolerance; project-finance debt can include accrued interest/unamortized cost roles. | source applies_to: non-bank-lender, power, utility, operating-EBITDA with debt | C23: SOURCE_GAP | D23: hard | E23: 1000 USD | F23: 0 | G23: No semantic anchors resolved for DEBT_SCHEDULE_TIE. | H23: =0 -> 0 | I23: =0 -> 0 | J23: =0 -> 0 | K23: =0 -> 0 | L23: =0 -> 0 | M23: =0 -> 0 | N23: =0 -> 0 | O23: =0 -> 0 | ... Q23: =0 -> 0
A25: NON-BANK-LENDER CHECKS
A26: BANK_NET_LOANS | B26: ARCHETYPE | expected 0; hard_tie_tolerance. | source applies_to: bank, non-bank-lender with loan book | C26: SOURCE_GAP | D26: hard | E26: 1000 USD | F26: 0 | G26: No semantic anchors resolved for BANK_NET_LOANS. | H26: =0 -> 0 | I26: =0 -> 0 | J26: =0 -> 0 | K26: =0 -> 0 | L26: =0 -> 0 | M26: =0 -> 0 | N26: =0 -> 0 | O26: =0 -> 0 | ... Q26: =0 -> 0
A27: BANK_ALLOWANCE | B27: ARCHETYPE | expected 0 under observed sign convention. | source applies_to: bank, non-bank-lender | C27: SOURCE_GAP | D27: hard | E27: 1000 USD | F27: 0 | G27: No semantic anchors resolved for BANK_ALLOWANCE. | H27: =0 -> 0 | I27: =0 -> 0 | J27: =0 -> 0 | K27: =0 -> 0 | L27: =0 -> 0 | M27: =0 -> 0 | N27: =0 -> 0 | O27: =0 -> 0 | ... Q27: =0 -> 0
A28: BANK_NII_TIE | B28: ARCHETYPE | expected 0; hard_tie_tolerance. | source applies_to: bank, non-bank-lender where NIM build exists | C28: SOURCE_GAP | D28: hard | E28: 1000 USD | F28: 0 | G28: No semantic anchors resolved for BANK_NII_TIE. | H28: =0 -> 0 | I28: =0 -> 0 | J28: =0 -> 0 | K28: =0 -> 0 | L28: =0 -> 0 | M28: =0 -> 0 | N28: =0 -> 0 | O28: =0 -> 0 | ... Q28: =0 -> 0
A29: BANK_NPL_COVERAGE | B29: ARCHETYPE | must be >=0. | source applies_to: bank, non-bank-lender where NPL coverage is material | C29: SOURCE_GAP | D29: hard | E29: 0 cushion | F29: >=0 | G29: No semantic anchors resolved for BANK_NPL_COVERAGE. | H29: =0 -> 0 | I29: =0 -> 0 | J29: =0 -> 0 | K29: =0 -> 0 | L29: =0 -> 0 | M29: =0 -> 0 | N29: =0 -> 0 | O29: =0 -> 0 | ... Q29: =0 -> 0

Sheet Source_Register
A1: Corporación de Finanzas del País, S.A. (PANACREDIT) y Subsidiarias
A2: Source_Register — non-bank-lender archetype. Every row traces to a published filing (OCR text) or to a working file kept by the maintainer.
A3: Status semantics: OK = citation resolved to an existing artifact. SOURCE_GAP = traceability missing (visible, not hidden). NOT_DISCLOSED = no registration/manifest found for this issuer.
A4: source_id | B4: kind | C4: ticker | D4: filing | E4: year | F4: nota | G4: tabla_ocr | H4: feeds_sheet | I4: feeds_anchor | J4: date | K4: status | L4: evidence_count | M4: note
A5: OCR_ROOT:panacredit | B5: OCR_ROOT | C5: CFPAIS | H5: EEFF; Notas_EEFF | I5: OCR of the published filings; OCR of the published filings | J5: NOT_DISCLOSED | K5: OK | L5: 2 | M5: Annual reports (INA) of panacredit
A6: EEFF_FILING:ina_cfpais_2022_0 | B6: EEFF_FILING | C6: CFPAIS | D6: INA_CFPAIS_2022_0.pdf | E6: 2022 | G6: markdown.md | H6: EEFF; Notas_EEFF; MD&A | I6: 00-index.md; 01-eeff.md; 02-notas.md; 03-mda.md; 09-otros.md | J6: FY22 (A) | K6: OK | L6: 108 | M6: markdown.md sha256=6e31d3375f7e9ace...
A7: EEFF_FILING:ina_cfpais_2023_0 | B7: EEFF_FILING | C7: CFPAIS | D7: INA_CFPAIS_2023_0.pdf | E7: 2023 | G7: markdown.md | H7: EEFF; Notas_EEFF; MD&A | I7: 00-index.md; 01-eeff.md; 02-notas.md; 03-mda.md; 09-otros.md | J7: FY23 (A) | K7: OK | L7: 106 | M7: markdown.md sha256=8c31407000317145...
A8: EEFF_FILING:ina_cfpais_2024_0 | B8: EEFF_FILING | C8: CFPAIS | D8: INA_CFPAIS_2024_0.pdf | E8: 2024 | G8: markdown.md | H8: EEFF; Notas_EEFF; MD&A | I8: 00-index.md; 01-eeff.md; 02-notas.md; 03-mda.md; 09-otros.md | J8: FY24 (A) | K8: OK | L8: 102 | M8: markdown.md sha256=91f473de33cbfbf9...
A9: EEFF_FILING:ina_cfpais_2025_0 | B9: EEFF_FILING | C9: CFPAIS | D9: INA_CFPAIS_2025_0.pdf | E9: 2025 | G9: markdown.md | H9: EEFF; Notas_EEFF; MD&A | I9: 00-index.md; 01-eeff.md; 02-notas.md; 03-mda.md; 09-otros.md | J9: FY25 (A) | K9: OK | L9: 112 | M9: markdown.md sha256=9cef84601c972bf9...
A10: EEFF_FILING:prospecto_definitivo_bonos_50mm_smv332_24 | B10: EEFF_FILING | C10: CFPAIS | D10: Prospecto Definitivo Bonos 50MM SMV332-24.pdf | G10: markdown.md | H10: EEFF; Notas_EEFF; MD&A | I10: markdown.md | J10: NOT_DISCLOSED | K10: OK | L10: 80 | M10: markdown.md sha256=30717f9fe0311aab...
A11: NOTA:INA_CFPAIS_2022_0.pdf#1 | B11: NOTA | C11: CFPAIS | D11: INA_CFPAIS_2022_0.pdf | E11: 2022 | F11: 1 | G11: markdown.md | H11: Notas_EEFF | I11: 1. Información general | J11: FY22 (A) | K11: OK | L11: 22
A12: NOTA:INA_CFPAIS_2022_0.pdf#10 | B12: NOTA | C12: CFPAIS | D12: INA_CFPAIS_2022_0.pdf | E12: 2022 | F12: 10 | G12: markdown.md; tbl-30.html | H12: Notas_EEFF | I12: 10. Inversiones en valores medidas a valor razonable con cambios en resultados | J12: FY22 (A) | K12: OK | L12: 2
A13: NOTA:INA_CFPAIS_2022_0.pdf#11 | B13: NOTA | C13: CFPAIS | D13: INA_CFPAIS_2022_0.pdf | E13: 2022 | F13: 11 | G13: markdown.md; tbl-31.html | H13: Notas_EEFF | I13: 11. Inversiones en valores medidas a costo amortizado | J13: FY22 (A) | K13: OK | L13: 3
A14: NOTA:INA_CFPAIS_2022_0.pdf#12 | B14: NOTA | C14: CFPAIS | D14: INA_CFPAIS_2022_0.pdf | E14: 2022 | F14: 12 | G14: markdown.md; tbl-32.html; tbl-33.html; +1 more | H14: Notas_EEFF | I14: 12. Préstamos a clientes | J14: FY22 (A) | K14: OK | L14: 8
A15: NOTA:INA_CFPAIS_2022_0.pdf#13 | B15: NOTA | C15: CFPAIS | D15: INA_CFPAIS_2022_0.pdf | E15: 2022 | F15: 13 | G15: markdown.md; tbl-35.html | H15: Notas_EEFF | I15: 13. Financiamientos recibidos | J15: FY22 (A) | K15: OK | L15: 3
A16: NOTA:INA_CFPAIS_2022_0.pdf#14 | B16: NOTA | C16: CFPAIS | D16: INA_CFPAIS_2022_0.pdf | E16: 2022 | F16: 14 | G16: markdown.md | H16: Notas_EEFF | I16: 14. Documentos por pagar | J16: FY22 (A) | K16: OK | L16: 1
A17: NOTA:INA_CFPAIS_2022_0.pdf#15 | B17: NOTA | C17: CFPAIS | D17: INA_CFPAIS_2022_0.pdf | E17: 2022 | F17: 15 | G17: markdown.md; tbl-36.html; tbl-37.html; +1 more | H17: Notas_EEFF | I17: 15. Valores comerciales negociables | J17: FY22 (A) | K17: OK | L17: 7
A18: NOTA:INA_CFPAIS_2022_0.pdf#16 | B18: NOTA | C18: CFPAIS | D18: INA_CFPAIS_2022_0.pdf | E18: 2022 | F18: 16 | G18: markdown.md; tbl-39.html; tbl-40.html; +1 more | H18: Notas_EEFF | I18: 16. Bonos corporativos | J18: FY22 (A) | K18: OK | L18: 8
A19: NOTA:INA_CFPAIS_2022_0.pdf#17 | B19: NOTA | C19: CFPAIS | D19: INA_CFPAIS_2022_0.pdf | E19: 2022 | F19: 17 | G19: markdown.md; tbl-42.html; tbl-43.html | H19: Notas_EEFF | I19: 17. Bonos perpetuos | J19: FY22 (A) | K19: OK | L19: 5
A20: NOTA:INA_CFPAIS_2022_0.pdf#18 | B20: NOTA | C20: CFPAIS | D20: INA_CFPAIS_2022_0.pdf | E20: 2022 | F20: 18 | G20: markdown.md; tbl-44.html; tbl-45.html; +5 more | H20: Notas_EEFF | I20: 18. Patrimonio | J20: FY22 (A) | K20: OK | L20: 20
A21: NOTA:INA_CFPAIS_2022_0.pdf#19 | B21: NOTA | C21: CFPAIS | D21: INA_CFPAIS_2022_0.pdf | E21: 2022 | F21: 19 | G21: markdown.md; tbl-51.html | H21: Notas_EEFF | I21: 19. Gastos de personal | J21: FY22 (A) | K21: OK | L21: 2
A22: NOTA:INA_CFPAIS_2022_0.pdf#2 | B22: NOTA | C22: CFPAIS | D22: INA_CFPAIS_2022_0.pdf | E22: 2022 | F22: 2 | G22: markdown.md | H22: Notas_EEFF | I22: 2. Base de preparación | J22: FY22 (A) | K22: OK | L22: 24
... A65: NOTA:INA_CFPAIS_2025_0.pdf#4 | B65: NOTA | C65: CFPAIS | D65: INA_CFPAIS_2025_0.pdf | E65: 2025 | F65: 4 | G65: markdown.md; tbl-22.html; tbl-23.html; +16 more | H65: Notas_EEFF | I65: 4. Administración de Riesgo Financieros, continuación | J65: FY25 (A) | K65: OK | L65: 102
A66: DRIVER:EEFF (citado por fórmula viva) | B66: DRIVER_OTHER | C66: CFPAIS | H66: Supuestos | I66: Total de ingresos por intereses y comisiones (hist, ref EEFF) | J66: NOT_DISCLOSED | K66: SOURCE_GAP | L66: 4 | M66: Unclassified _source citation shape: EEFF (citado por fórmula viva)
A67: DRIVER:NOT_DISCLOSED | B67: DRIVER_OTHER | C67: CFPAIS | H67: Supuestos | I67: Selector escenario | J67: NOT_DISCLOSED | K67: SOURCE_GAP | L67: 38 | M67: Unclassified _source citation shape: NOT_DISCLOSED

Sheet _CHANGELOG
A1: Corporación de Finanzas del País, S.A. (PANACREDIT) y Subsidiarias
A2: _CHANGELOG — generation record for panacredit.
A3: Internal build history omitted from the public export. Record public changes below.

Sheet MD&A
A1: Corporación de Finanzas del País, S.A. (PANACREDIT) y Subsidiarias
A2: MD&A — Informe de Actualización INA_CFPAIS_2025_0 (índice verbatim del mirror OCR; la narrativa completa vive en el mirror)
A3: Fuente: mirror OCR INA_CFPAIS_2025_0, sección MD&A · sha256=e50a67131278bfbe… · linaje completo en Source_Register.
A5: A. ÍNDICE DE SECCIONES DEL MD&A (verbatim, con página del filing)
A6: · Panacredit (pág. 1)
A7: · INFORME DE ACTUALIZACIÓN ANUAL IN-A (pág. 2)
A8: · PRIMERA PARTE (pág. 13)
A9: · I. INFORMACION FINANCIERA DEL EMISOR (pág. 13)
A10: · II. ANALISIS DE RESULTADOS FINANCIEROS Y OPERATIVOS (pág. 13)
A11: · III. DIRECTORES, DIGNATARIOS, EJECUTIVOS, ADMINISTRADORES, ASESORES Y EMPLEADOS (pág. 13)
A12: · IV. ACCIONISTAS PRINCIPALES (pág. 13)
A13: · V. PARTES RELACIONADAS, VINCULOS Y AFILIACIONES (pág. 13)
... A57: Doctrina: hoja índice/verbatim — sin narrativa inventada; cifras solo del filing (NOT_DISCLOSED donde no hay dato).

Sheet Claude Code Log
A1: Turn # | B1: Date | C1: User Request | D1: Action Taken | E1: Details | F1: Outcome
A2: 1 | B2: 46324.359 | C2: Prepare a public model copy | D2: Remove local paths and private build references; preserve financial formulas and inputs | E2: Agent run with MOG as the tool, checked by guard v1. The guard measured every sheet before and after the run. Changed: Notas_EEFF: 1 cell written, at A3; _CHECKS: 1 cell written, at G12; Source_Register: 3 cells written, at A2, I5, M5; _CHANGELOG: data A1:H33 -> A1:A3 (rows 33 -> 3, columns 8 -> 1), 205 cells written, at A2, A3, B3, C3, D3, E3, F3, G3, H3, A4, B4, C4, D4, E4, F4 and 190 more. Other actions: clear x1. Agent: OpenFinmods export | F2: Compare against source and review public copy
