Workbook

Sheet 00_Cover
A1: adidas AG — Controlled Institutional Financial Model
A2: Consumer cyclical / apparel | EUR millions unless per-share | Controlled version 2.0 | As of 2026-07-16
A4: Model field | B4: Value
A5: Legal entity / identifier | B5: XETRA: ADS
A6: Model archetype | B6: Operating company / FCFF DCF
A7: Model status | B7: ='9_10_Blockers'!$B$16 -> PENDING INDEPENDENT 9/10 REVIEW
A8: Reporting currency | B8: EUR
A9: Model units | B9: EUR millions unless per-share
A10: Valuation date | B10: 2025-12-31
A11: Active case | B11: =CHOOSE(Assumptions!$B$3,"Base","Bull","Bear") -> Base
A12: Primary source route | B12: https://report.adidas-group.com/2025/en/services/downloads.html
A13: Purpose | B13: Source-backed operating model and FCFF DCF; independent certification pending
A14: Decision use | B14: Owner review-ready; no owner certification claim
A15: Key limitation | B15: Revenue is now product-built; product growth, post-2026 margins, WACC and terminal growth remain model-owned and require independent review.
A16: Controlled lineage | B16: Adidas_Institutional_Model.xlsx | SHA-256 30cbb37f94bb55224c9f1fb4ddb86532568199a2f3ccc0dbf2c86c0a5c86ffb8
A18: Owner evidence only. The controlled workbook does not self-certify a 9/10 result. Independent review must reproduce sources, formulas, scenarios, valuation mechanics, native recalculation and visual QA.

Sheet Sources
A1: Source ledger and claim-level data lineage
A2: Every material historical and valuation input is classified as Reported, Inferred, Assumption, Document identity only, or Not disclosed. Status is formula-driven.
A4: Source ID | B4: Metric / line item | C4: Period / as-of | D4: Value | E4: Units / currency | F4: Source title | G4: Source class | H4: Exact URL / allowed local locator | I4: Page / table / row / section | J4: Retrieved | K4: Workbook destination | L4: Transformation / normalization | M4: Classification | N4: Notes / limitation | O4: Material? | P4: Mapping status
A5: AD-2021-REVENUE | B5: Revenue | C5: FY2021 | D5: 21234 | E5: EUR millions | F5: adidas Annual Report 2022 — Financial Highlights 2022 (IFRS) | G5: Primary — issuer annual report | H5: https://report.adidas-group.com/2022/en/at-a-glance/financial-highlights-2022.html | I5: Financial Highlights table; Net sales row; 2021 column | J5: 2026-07-16 | K5: Historical!B5 | L5: No FX conversion; reported EUR millions | M5: Reported | N5: Mapped to the exact annual-report table row and period column. | O5: Yes | P5: =IF(O5<>"Yes","N/A",IF(M5="Not disclosed","BLOCKED",IF(AND(H5<>"",I5<>"",K5<>"",M5<>""),"MAPPED","MISSING"))) -> MAPPED
A6: AD-2022-REVENUE | B6: Revenue | C6: FY2022 | D6: 22511 | E6: EUR millions | F6: adidas Annual Report 2022 — Financial Highlights 2022 (IFRS) | G6: Primary — issuer annual report | H6: https://report.adidas-group.com/2022/en/at-a-glance/financial-highlights-2022.html | I6: Financial Highlights table; Net sales row; 2022 column | J6: 2026-07-16 | K6: Historical!C5 | L6: No FX conversion; reported EUR millions | M6: Reported | N6: Mapped to the exact annual-report table row and period column. | O6: Yes | P6: =IF(O6<>"Yes","N/A",IF(M6="Not disclosed","BLOCKED",IF(AND(H6<>"",I6<>"",K6<>"",M6<>""),"MAPPED","MISSING"))) -> MAPPED
A7: AD-2023-REVENUE | B7: Revenue | C7: FY2023 | D7: 21427 | E7: EUR millions | F7: adidas Annual Report 2024 — Financial Highlights 2024 (IFRS) | G7: Primary — issuer annual report | H7: https://report.adidas-group.com/2024/en/at-a-glance/financial-highlights-2024.html | I7: Financial Highlights table; Net sales row; 2023 column | J7: 2026-07-16 | K7: Historical!D5 | L7: No FX conversion; reported EUR millions | M7: Reported | N7: Mapped to the exact annual-report table row and period column. | O7: Yes | P7: =IF(O7<>"Yes","N/A",IF(M7="Not disclosed","BLOCKED",IF(AND(H7<>"",I7<>"",K7<>"",M7<>""),"MAPPED","MISSING"))) -> MAPPED
A8: AD-2024-REVENUE | B8: Revenue | C8: FY2024 | D8: 23683 | E8: EUR millions | F8: adidas Annual Report 2025 — Financial Highlights 2025 (IFRS) | G8: Primary — issuer annual report | H8: https://report.adidas-group.com/2025/en/at-a-glance/financial-highlights-2025.html | I8: Financial Highlights table; Net sales row; 2024 column | J8: 2026-07-16 | K8: Historical!E5 | L8: No FX conversion; reported EUR millions | M8: Reported | N8: Mapped to the exact annual-report table row and period column. | O8: Yes | P8: =IF(O8<>"Yes","N/A",IF(M8="Not disclosed","BLOCKED",IF(AND(H8<>"",I8<>"",K8<>"",M8<>""),"MAPPED","MISSING"))) -> MAPPED
A9: AD-2025-REVENUE | B9: Revenue | C9: FY2025 | D9: 24811 | E9: EUR millions | F9: adidas Annual Report 2025 — Financial Highlights 2025 (IFRS) | G9: Primary — issuer annual report | H9: https://report.adidas-group.com/2025/en/at-a-glance/financial-highlights-2025.html | I9: Financial Highlights table; Net sales row; 2025 column | J9: 2026-07-16 | K9: Historical!F5 | L9: No FX conversion; reported EUR millions | M9: Reported | N9: Mapped to the exact annual-report table row and period column. | O9: Yes | P9: =IF(O9<>"Yes","N/A",IF(M9="Not disclosed","BLOCKED",IF(AND(H9<>"",I9<>"",K9<>"",M9<>""),"MAPPED","MISSING"))) -> MAPPED
A10: AD-2021-GROSS-PROFIT | B10: Gross profit | C10: FY2021 | D10: 10765 | E10: EUR millions | F10: adidas Annual Report 2022 — Financial Highlights 2022 (IFRS) | G10: Primary — issuer annual report | H10: https://report.adidas-group.com/2022/en/at-a-glance/financial-highlights-2022.html | I10: Financial Highlights table; Gross profit row; 2021 column | J10: 2026-07-16 | K10: Historical!B6 | L10: No FX conversion; reported EUR millions | M10: Reported | N10: Mapped to the exact annual-report table row and period column. | O10: Yes | P10: =IF(O10<>"Yes","N/A",IF(M10="Not disclosed","BLOCKED",IF(AND(H10<>"",I10<>"",K10<>"",M10<>""),"MAPPED","MISSING"))) -> MAPPED
A11: AD-2022-GROSS-PROFIT | B11: Gross profit | C11: FY2022 | D11: 10644 | E11: EUR millions | F11: adidas Annual Report 2022 — Financial Highlights 2022 (IFRS) | G11: Primary — issuer annual report | H11: https://report.adidas-group.com/2022/en/at-a-glance/financial-highlights-2022.html | I11: Financial Highlights table; Gross profit row; 2022 column | J11: 2026-07-16 | K11: Historical!C6 | L11: No FX conversion; reported EUR millions | M11: Reported | N11: Mapped to the exact annual-report table row and period column. | O11: Yes | P11: =IF(O11<>"Yes","N/A",IF(M11="Not disclosed","BLOCKED",IF(AND(H11<>"",I11<>"",K11<>"",M11<>""),"MAPPED","MISSING"))) -> MAPPED
A12: AD-2023-GROSS-PROFIT | B12: Gross profit | C12: FY2023 | D12: 10184 | E12: EUR millions | F12: adidas Annual Report 2024 — Financial Highlights 2024 (IFRS) | G12: Primary — issuer annual report | H12: https://report.adidas-group.com/2024/en/at-a-glance/financial-highlights-2024.html | I12: Financial Highlights table; Gross profit row; 2023 column | J12: 2026-07-16 | K12: Historical!D6 | L12: No FX conversion; reported EUR millions | M12: Reported | N12: Mapped to the exact annual-report table row and period column. | O12: Yes | P12: =IF(O12<>"Yes","N/A",IF(M12="Not disclosed","BLOCKED",IF(AND(H12<>"",I12<>"",K12<>"",M12<>""),"MAPPED","MISSING"))) -> MAPPED
A13: AD-2024-GROSS-PROFIT | B13: Gross profit | C13: FY2024 | D13: 12026 | E13: EUR millions | F13: adidas Annual Report 2025 — Financial Highlights 2025 (IFRS) | G13: Primary — issuer annual report | H13: https://report.adidas-group.com/2025/en/at-a-glance/financial-highlights-2025.html | I13: Financial Highlights table; Gross profit row; 2024 column | J13: 2026-07-16 | K13: Historical!E6 | L13: No FX conversion; reported EUR millions | M13: Reported | N13: Mapped to the exact annual-report table row and period column. | O13: Yes | P13: =IF(O13<>"Yes","N/A",IF(M13="Not disclosed","BLOCKED",IF(AND(H13<>"",I13<>"",K13<>"",M13<>""),"MAPPED","MISSING"))) -> MAPPED
A14: AD-2025-GROSS-PROFIT | B14: Gross profit | C14: FY2025 | D14: 12804 | E14: EUR millions | F14: adidas Annual Report 2025 — Financial Highlights 2025 (IFRS) | G14: Primary — issuer annual report | H14: https://report.adidas-group.com/2025/en/at-a-glance/financial-highlights-2025.html | I14: Financial Highlights table; Gross profit row; 2025 column | J14: 2026-07-16 | K14: Historical!F6 | L14: No FX conversion; reported EUR millions | M14: Reported | N14: Mapped to the exact annual-report table row and period column. | O14: Yes | P14: =IF(O14<>"Yes","N/A",IF(M14="Not disclosed","BLOCKED",IF(AND(H14<>"",I14<>"",K14<>"",M14<>""),"MAPPED","MISSING"))) -> MAPPED
A15: AD-2021-OPERATING-PROFIT-EBIT | B15: Operating profit / EBIT | C15: FY2021 | D15: 1986 | E15: EUR millions | F15: adidas Annual Report 2022 — Financial Highlights 2022 (IFRS) | G15: Primary — issuer annual report | H15: https://report.adidas-group.com/2022/en/at-a-glance/financial-highlights-2022.html | I15: Financial Highlights table; Operating profit row; 2021 column | J15: 2026-07-16 | K15: Historical!B7 | L15: No FX conversion; reported EUR millions | M15: Reported | N15: Mapped to the exact annual-report table row and period column. | O15: Yes | P15: =IF(O15<>"Yes","N/A",IF(M15="Not disclosed","BLOCKED",IF(AND(H15<>"",I15<>"",K15<>"",M15<>""),"MAPPED","MISSING"))) -> MAPPED
A16: AD-2022-OPERATING-PROFIT-EBIT | B16: Operating profit / EBIT | C16: FY2022 | D16: 669 | E16: EUR millions | F16: adidas Annual Report 2022 — Financial Highlights 2022 (IFRS) | G16: Primary — issuer annual report | H16: https://report.adidas-group.com/2022/en/at-a-glance/financial-highlights-2022.html | I16: Financial Highlights table; Operating profit row; 2022 column | J16: 2026-07-16 | K16: Historical!C7 | L16: No FX conversion; reported EUR millions | M16: Reported | N16: Mapped to the exact annual-report table row and period column. | O16: Yes | P16: =IF(O16<>"Yes","N/A",IF(M16="Not disclosed","BLOCKED",IF(AND(H16<>"",I16<>"",K16<>"",M16<>""),"MAPPED","MISSING"))) -> MAPPED
... A53: AD-2025-SHARES-OUTSTANDING-MM- | B53: Shares outstanding (mm) | C53: FY2025 | D53: 178.66502 | E53: million shares | F53: adidas Annual Report 2025 — Financial Highlights 2025 (IFRS) | G53: Primary — issuer annual report | H53: https://report.adidas-group.com/2025/en/at-a-glance/financial-highlights-2025.html | I53: Financial Highlights table; Number of shares outstanding row; 2025 column | J53: 2026-07-16 | K53: Historical!F16 | L53: Reported shares divided by 1,000,000 | M53: Reported | N53: Mapped to the exact annual-report table row and period column. | O53: Yes | P53: =IF(O53<>"Yes","N/A",IF(M53="Not disclosed","BLOCKED",IF(AND(H53<>"",I53<>"",K53<>"",M53<>""),"MAPPED","MISSING"))) -> MAPPED
A54: AD-2021-LIABILITIES-INFERRED | B54: Total liabilities | C54: FY2021 | E54: EUR millions | F54: adidas Annual Report 2022 — Financial Highlights 2022 (IFRS) | G54: Primary inputs; workbook inference | H54: https://report.adidas-group.com/2022/en/at-a-glance/financial-highlights-2022.html | I54: Financial Highlights table; Total assets and Shareholders' equity rows; 2021 column | J54: 2026-07-16 | K54: Historical!B12 | L54: Formula: Total assets less Shareholders' equity | M54: Inferred | N54: Derived transparently from two reported totals; not represented as a reported line item. | O54: Yes | P54: =IF(O54<>"Yes","N/A",IF(M54="Not disclosed","BLOCKED",IF(AND(H54<>"",I54<>"",K54<>"",M54<>""),"MAPPED","MISSING"))) -> MAPPED
A55: AD-2022-LIABILITIES-INFERRED | B55: Total liabilities | C55: FY2022 | E55: EUR millions | F55: adidas Annual Report 2022 — Financial Highlights 2022 (IFRS) | G55: Primary inputs; workbook inference | H55: https://report.adidas-group.com/2022/en/at-a-glance/financial-highlights-2022.html | I55: Financial Highlights table; Total assets and Shareholders' equity rows; 2022 column | J55: 2026-07-16 | K55: Historical!C12 | L55: Formula: Total assets less Shareholders' equity | M55: Inferred | N55: Derived transparently from two reported totals; not represented as a reported line item. | O55: Yes | P55: =IF(O55<>"Yes","N/A",IF(M55="Not disclosed","BLOCKED",IF(AND(H55<>"",I55<>"",K55<>"",M55<>""),"MAPPED","MISSING"))) -> MAPPED
A56: AD-2023-LIABILITIES-INFERRED | B56: Total liabilities | C56: FY2023 | E56: EUR millions | F56: adidas Annual Report 2024 — Financial Highlights 2024 (IFRS) | G56: Primary inputs; workbook inference | H56: https://report.adidas-group.com/2024/en/at-a-glance/financial-highlights-2024.html | I56: Financial Highlights table; Total assets and Shareholders' equity rows; 2023 column | J56: 2026-07-16 | K56: Historical!D12 | L56: Formula: Total assets less Shareholders' equity | M56: Inferred | N56: Derived transparently from two reported totals; not represented as a reported line item. | O56: Yes | P56: =IF(O56<>"Yes","N/A",IF(M56="Not disclosed","BLOCKED",IF(AND(H56<>"",I56<>"",K56<>"",M56<>""),"MAPPED","MISSING"))) -> MAPPED
A57: AD-2024-LIABILITIES-INFERRED | B57: Total liabilities | C57: FY2024 | E57: EUR millions | F57: adidas Annual Report 2025 — Financial Highlights 2025 (IFRS) | G57: Primary inputs; workbook inference | H57: https://report.adidas-group.com/2025/en/at-a-glance/financial-highlights-2025.html | I57: Financial Highlights table; Total assets and Shareholders' equity rows; 2024 column | J57: 2026-07-16 | K57: Historical!E12 | L57: Formula: Total assets less Shareholders' equity | M57: Inferred | N57: Derived transparently from two reported totals; not represented as a reported line item. | O57: Yes | P57: =IF(O57<>"Yes","N/A",IF(M57="Not disclosed","BLOCKED",IF(AND(H57<>"",I57<>"",K57<>"",M57<>""),"MAPPED","MISSING"))) -> MAPPED
A58: AD-2025-LIABILITIES-INFERRED | B58: Total liabilities | C58: FY2025 | E58: EUR millions | F58: adidas Annual Report 2025 — Financial Highlights 2025 (IFRS) | G58: Primary inputs; workbook inference | H58: https://report.adidas-group.com/2025/en/at-a-glance/financial-highlights-2025.html | I58: Financial Highlights table; Total assets and Shareholders' equity rows; 2025 column | J58: 2026-07-16 | K58: Historical!F12 | L58: Formula: Total assets less Shareholders' equity | M58: Inferred | N58: Derived transparently from two reported totals; not represented as a reported line item. | O58: Yes | P58: =IF(O58<>"Yes","N/A",IF(M58="Not disclosed","BLOCKED",IF(AND(H58<>"",I58<>"",K58<>"",M58<>""),"MAPPED","MISSING"))) -> MAPPED
A59: AD-A-REV26 | B59: 2026 revenue growth | C59: FY2026E | D59: 0.08 | E59: % | F59: adidas Annual Report 2025 — Outlook | G59: Primary guidance anchored model assumption | H59: https://report.adidas-group.com/2025/en/group-management-report-financial-review/outlook.html | I59: 2026 Outlook table; Net sales; high-single-digit currency-neutral growth | J59: 2026-07-16 | K59: Assumptions!B5:E5 | L59: Base interprets high-single-digit as 8%; Bear/Base/Bull bracket 5%/8%/11% | M59: Assumption | N59: Management guidance is qualitative; numeric midpoint is explicitly model-owned. | O59: Yes | P59: =IF(O59<>"Yes","N/A",IF(M59="Not disclosed","BLOCKED",IF(AND(H59<>"",I59<>"",K59<>"",M59<>""),"MAPPED","MISSING"))) -> MAPPED
A60: AD-A-EBIT26 | B60: 2026 EBIT margin | C60: FY2026E | D60: 0.085834091 | E60: % | F60: adidas Annual Report 2025 — Outlook | G60: Primary guidance anchored model assumption | H60: https://report.adidas-group.com/2025/en/group-management-report-financial-review/outlook.html | I60: 2026 Outlook table; Operating profit around EUR 2.3bn | J60: 2026-07-16 | K60: Assumptions!B6:E6 | L60: Base margin = EUR 2.3bn / modeled Base revenue | M60: Assumption | N60: Bear and Bull are model scenarios; only the Base operating-profit anchor is management guidance. | O60: Yes | P60: =IF(O60<>"Yes","N/A",IF(M60="Not disclosed","BLOCKED",IF(AND(H60<>"",I60<>"",K60<>"",M60<>""),"MAPPED","MISSING"))) -> MAPPED
A61: AD-A-CAPEX26 | B61: 2026 capital expenditure | C61: FY2026E | D61: 500 | E61: EUR millions | F61: adidas Annual Report 2025 — Outlook | G61: Primary guidance anchored model assumption | H61: https://report.adidas-group.com/2025/en/group-management-report-financial-review/outlook.html | I61: 2026 Outlook table; Capital expenditure around EUR 500m | J61: 2026-07-16 | K61: Assumptions!B11:E11 | L61: Base uses disclosed approximate amount; Bear/Bull are scenarios | M61: Assumption | N61: Management guidance is approximate. | O61: Yes | P61: =IF(O61<>"Yes","N/A",IF(M61="Not disclosed","BLOCKED",IF(AND(H61<>"",I61<>"",K61<>"",M61<>""),"MAPPED","MISSING"))) -> MAPPED
A62: AD-A-OWC26 | B62: Operating working capital / revenue | C62: FY2026E | D62: 0.225 | E62: % | F62: adidas Annual Report 2025 — Outlook | G62: Primary guidance anchored model assumption | H62: https://report.adidas-group.com/2025/en/group-management-report-financial-review/outlook.html | I62: 2026 Outlook table; Average operating working capital between 22% and 23% of sales | J62: 2026-07-16 | K62: Assumptions!B13:E13 | L62: Base uses midpoint 22.5% | M62: Assumption | N62: Used as a simplified end-period working-capital driver; management guidance is average OWC. | O62: Yes | P62: =IF(O62<>"Yes","N/A",IF(M62="Not disclosed","BLOCKED",IF(AND(H62<>"",I62<>"",K62<>"",M62<>""),"MAPPED","MISSING"))) -> MAPPED
A63: AD-A-TAX | B63: Cash tax rate | C63: FY2026E-FY2030E | D63: 0.243 | E63: % | F63: adidas Annual Report 2025 — Financial Highlights | G63: Primary historical anchor; model assumption | H63: https://report.adidas-group.com/2025/en/at-a-glance/financial-highlights-2025.html | I63: Key Ratios; Effective tax rate; 2025 column | J63: 2026-07-16 | K63: Assumptions!B9:E9 | L63: Base uses FY2025 effective tax rate as cash-tax proxy | M63: Assumption | N63: Cash taxes can differ from the accounting effective tax rate. | O63: Yes | P63: =IF(O63<>"Yes","N/A",IF(M63="Not disclosed","BLOCKED",IF(AND(H63<>"",I63<>"",K63<>"",M63<>""),"MAPPED","MISSING"))) -> MAPPED
A64: AD-A-DA | B64: D&A / revenue | C64: FY2026E-FY2030E | D64: 0.019426867 | E64: % | F64: adidas Annual Report 2025 — Statement of Financial Position and Cash Flows | G64: Primary historical anchor; model assumption | H64: https://report.adidas-group.com/2025/en/group-management-report-financial-review/business-performance/statement-of-financial-position-and-statement-of-cash-flows.html | I64: Investment analysis; depreciation and amortization EUR 482m; 2025 net sales EUR 24,811m | J64: 2026-07-16 | K64: Assumptions!B10:E10 | L64: Base = 482 / 24,811 | M64: Assumption | N64: Excludes impairment losses and reversals as disclosed. | O64: Yes | P64: =IF(O64<>"Yes","N/A",IF(M64="Not disclosed","BLOCKED",IF(AND(H64<>"",I64<>"",K64<>"",M64<>""),"MAPPED","MISSING"))) -> MAPPED
A65: AD-A-GROWTH-LT | B65: 2027-2030 revenue growth | C65: FY2027E-FY2030E | D65: 0.04 | E65: % | F65: Model-owned assumption | G65: Model assumption | H65: Assumptions sheet | I65: Revenue growth scenario row | J65: 2026-07-16 | K65: Assumptions!B7:E7 | L65: Bear/Base/Bull = 2%/4%/6% | M65: Assumption | N65: No issuer guidance beyond FY2026. | O65: Yes | P65: =IF(O65<>"Yes","N/A",IF(M65="Not disclosed","BLOCKED",IF(AND(H65<>"",I65<>"",K65<>"",M65<>""),"MAPPED","MISSING"))) -> MAPPED
A66: AD-A-MARGIN-LT | B66: 2027-2030 EBIT margin | C66: FY2027E-FY2030E | D66: 0.09 | E66: % | F66: Model-owned assumption | G66: Model assumption | H66: Assumptions sheet | I66: EBIT margin scenario row | J66: 2026-07-16 | K66: Assumptions!B8:E8 | L66: Bear/Base/Bull = 8%/9%/10% | M66: Assumption | N66: No issuer guidance beyond FY2026. | O66: Yes | P66: =IF(O66<>"Yes","N/A",IF(M66="Not disclosed","BLOCKED",IF(AND(H66<>"",I66<>"",K66<>"",M66<>""),"MAPPED","MISSING"))) -> MAPPED
A67: AD-A-CAPEX-LT | B67: 2027-2030 capex / revenue | C67: FY2027E-FY2030E | D67: 0.02 | E67: % | F67: Model-owned assumption | G67: Model assumption | H67: Assumptions sheet | I67: Capex intensity scenario row | J67: 2026-07-16 | K67: Assumptions!B12:E12 | L67: Bear/Base/Bull = 2.2%/2.0%/1.8% | M67: Assumption | N67: No issuer guidance beyond FY2026. | O67: Yes | P67: =IF(O67<>"Yes","N/A",IF(M67="Not disclosed","BLOCKED",IF(AND(H67<>"",I67<>"",K67<>"",M67<>""),"MAPPED","MISSING"))) -> MAPPED
A68: AD-A-WACC | B68: WACC | C68: Valuation date 2025-12-31 | D68: 0.085 | E68: % | F68: Model-owned valuation assumption | G68: Model assumption | H68: Assumptions sheet | I68: WACC scenario row | J68: 2026-07-16 | K68: Assumptions!B14:E14 | L68: Bear/Base/Bull = 9.5%/8.5%/7.5% | M68: Assumption | N68: Not issuer-reported; must be independently reviewed. | O68: Yes | P68: =IF(O68<>"Yes","N/A",IF(M68="Not disclosed","BLOCKED",IF(AND(H68<>"",I68<>"",K68<>"",M68<>""),"MAPPED","MISSING"))) -> MAPPED
A69: AD-A-TG | B69: Terminal growth | C69: Terminal period | D69: 0.025 | E69: % | F69: Model-owned valuation assumption | G69: Model assumption | H69: Assumptions sheet | I69: Terminal growth scenario row | J69: 2026-07-16 | K69: Assumptions!B15:E15 | L69: Bear/Base/Bull = 2.0%/2.5%/3.0% | M69: Assumption | N69: Not issuer-reported; must be independently reviewed. | O69: Yes | P69: =IF(O69<>"Yes","N/A",IF(M69="Not disclosed","BLOCKED",IF(AND(H69<>"",I69<>"",K69<>"",M69<>""),"MAPPED","MISSING"))) -> MAPPED
A70: AD-MARKET | B70: Share price at end of period | C70: 2025-12-31 | D70: 169.05 | E70: EUR/share | F70: adidas Annual Report 2025 — Financial Highlights | G70: Primary — issuer annual report | H70: https://report.adidas-group.com/2025/en/at-a-glance/financial-highlights-2025.html | I70: Per Share of Common Stock; Share price at end of period; 2025 column | J70: 2026-07-16 | K70: Valuation!B19 | L70: No transformation | M70: Reported | N70: Historical year-end comparison only; not a live market price. | O70: Yes | P70: =IF(O70<>"Yes","N/A",IF(M70="Not disclosed","BLOCKED",IF(AND(H70<>"",I70<>"",K70<>"",M70<>""),"MAPPED","MISSING"))) -> MAPPED
A221: AD-2025-PRODUCT-FOOTWEAR | B221: Footwear revenue | C221: FY2025 | D221: 14232 | E221: EUR millions | F221: adidas Annual Report 2025 — Income Statement | G221: Primary — issuer annual report | H221: https://report.adidas-group.com/2025/en/group-management-report-financial-review/business-performance/income-statement.html | I221: Net sales by product division; Footwear; 2025 | J221: 2026-07-16 | K221: Sector_KPIs!C5 | L221: No transformation | M221: Reported | N221: Bottom-up revenue anchor | O221: Yes | P221: MAPPED
A222: AD-2025-PRODUCT-APPAREL | B222: Apparel revenue | C222: FY2025 | D222: 8764 | E222: EUR millions | F222: adidas Annual Report 2025 — Income Statement | G222: Primary — issuer annual report | H222: https://report.adidas-group.com/2025/en/group-management-report-financial-review/business-performance/income-statement.html | I222: Net sales by product division; Apparel; 2025 | J222: 2026-07-16 | K222: Sector_KPIs!C6 | L222: No transformation | M222: Reported | N222: Bottom-up revenue anchor | O222: Yes | P222: MAPPED
A223: AD-2025-PRODUCT-ACCESSORIES | B223: Accessories revenue | C223: FY2025 | D223: 1815 | E223: EUR millions | F223: adidas Annual Report 2025 — Income Statement | G223: Primary — issuer annual report | H223: https://report.adidas-group.com/2025/en/group-management-report-financial-review/business-performance/income-statement.html | I223: Net sales by product division; Accessories; 2025 | J223: 2026-07-16 | K223: Sector_KPIs!C7 | L223: No transformation | M223: Reported | N223: Bottom-up revenue anchor | O223: Yes | P223: MAPPED
A224: AD-2025-CHANNEL-WHOLESALE | B224: Wholesale revenue | C224: FY2025 | D224: 14833 | E224: EUR millions | F224: adidas Annual Report 2025 — Income Statement | G224: Primary — issuer annual report | H224: https://report.adidas-group.com/2025/en/group-management-report-financial-review/business-performance/income-statement.html | I224: Net sales by channel; Wholesale; 2025 | J224: 2026-07-16 | K224: Sector_KPIs!C23 | L224: No transformation | M224: Reported | N224: Diagnostic only | O224: No | P224: MAPPED
A225: AD-2025-CHANNEL-DTC | B225: Direct-to-consumer revenue | C225: FY2025 | D225: 9931 | E225: EUR millions | F225: adidas Annual Report 2025 — Income Statement | G225: Primary — issuer annual report | H225: https://report.adidas-group.com/2025/en/group-management-report-financial-review/business-performance/income-statement.html | I225: Net sales by channel; DTC; 2025 | J225: 2026-07-16 | K225: Sector_KPIs!C24 | L225: No transformation | M225: Reported | N225: Diagnostic only | O225: No | P225: MAPPED
A226: AD-2025-SHARES-BRIDGE | B226: Ordinary shares outstanding | C226: FY2025 | D226: 178.66502 | E226: million shares | F226: adidas Annual Report 2025 — Financial Highlights | G226: Primary — issuer annual report | H226: https://report.adidas-group.com/2025/en/at-a-glance/financial-highlights-2025.html | I226: Number of shares row; 2025 | J226: 2026-07-16 | K226: Sector_KPIs!B30 | L226: Reported shares divided by 1,000,000 | M226: Reported | N226: Single-class denominator | O226: Yes | P226: MAPPED
A227: AD-FORECAST-PRODUCT-GROWTH | B227: Product-division forecast growth | C227: FY2026E-FY2030E | E227: percent | F227: Controlled model assumption | G227: Model-owned assumption | H227: Sector_KPIs!B14:E19 | I227: Scenario table | J227: 2026-07-16 | K227: Forecast!C5:G5 | L227: Formula-driven product build | M227: Assumption | N227: Not issuer guidance by product | O227: Yes | P227: MAPPED

Sheet Historical
A1: Historical financials
A2: EUR millions unless per-share. Blanks are intentional when no claim-level primary-source mapping was available.
A4: Metric | B4: 2021A | C4: 2022A | D4: 2023A | E4: 2024A | F4: 2025A | G4: Source mapping | H4: Classification
A5: Revenue | B5: 21234 | C5: 22511 | D5: 21427 | E5: 23683 | F5: 24811 | G5: Sources ledger | H5: =IF(COUNT(B5:F5)=0,"Not disclosed","Reported; see Sources") -> Reported; see Sources
A6: Gross profit | B6: 10765 | C6: 10644 | D6: 10184 | E6: 12026 | F6: 12804 | G6: Sources ledger | H6: =IF(COUNT(B6:F6)=0,"Not disclosed","Reported; see Sources") -> Reported; see Sources
A7: Operating profit / EBIT | B7: 1986 | C7: 669 | D7: 268 | E7: 1337 | F7: 2056 | G7: Sources ledger | H7: =IF(COUNT(B7:F7)=0,"Not disclosed","Reported; see Sources") -> Reported; see Sources
A8: Net income attributable | B8: 2116 | C8: 612 | D8: -75 | E8: 764 | F8: 1340 | G8: Sources ledger | H8: =IF(COUNT(B8:F8)=0,"Not disclosed","Reported; see Sources") -> Reported; see Sources
A9: Cash from operations | B9: 2873 | C9: -458 | D9: 2550 | E9: 2910 | F9: 751 | G9: Sources ledger | H9: =IF(COUNT(B9:F9)=0,"Not disclosed","Reported; see Sources") -> Reported; see Sources
A10: Capital expenditure | B10: 667 | C10: 695 | D10: 504 | E10: 540 | F10: 477 | G10: Sources ledger | H10: =IF(COUNT(B10:F10)=0,"Not disclosed","Reported; see Sources") -> Reported; see Sources
A11: Total assets | B11: 22137 | C11: 20296 | D11: 18020 | E11: 20655 | F11: 20262 | G11: Sources ledger | H11: =IF(COUNT(B11:F11)=0,"Not disclosed","Reported; see Sources") -> Reported; see Sources
A12: Total liabilities | B12: =IF(AND(B11<>"",B13<>""),B11-B13,"") -> 14618 | C12: =IF(AND(C11<>"",C13<>""),C11-C13,"") -> 15305 | D12: =IF(AND(D11<>"",D13<>""),D11-D13,"") -> 13440 | E12: =IF(AND(E11<>"",E13<>""),E11-E13,"") -> 15179 | F12: =IF(AND(F11<>"",F13<>""),F11-F13,"") -> 14486 | G12: Assets less equity | H12: Inferred where inputs exist
A13: Shareholders' equity | B13: 7519 | C13: 4991 | D13: 4580 | E13: 5476 | F13: 5776 | G13: Sources ledger | H13: =IF(COUNT(B13:F13)=0,"Not disclosed","Reported; see Sources") -> Reported; see Sources
A14: Adjusted net borrowings | E14: 3622 | F14: 4331 | G14: Sources ledger | H14: =IF(COUNT(B14:F14)=0,"Not disclosed","Reported; see Sources") -> Reported; see Sources
A15: Cash and cash equivalents | E15: 2455 | F15: 1617 | G15: Sources ledger | H15: =IF(COUNT(B15:F15)=0,"Not disclosed","Reported; see Sources") -> Reported; see Sources
A16: Shares outstanding (mm) | B16: 191.59485 | C16: 178.5372 | D16: 178.54908 | E16: 178.54908 | F16: 178.66502 | G16: Sources ledger | H16: =IF(COUNT(B16:F16)=0,"Not disclosed","Reported; see Sources") -> Reported; see Sources

Sheet Assumptions
A1: Assumptions and scenarios
A2: Blue-font cells are model inputs. Selector: 1 = Base, 2 = Bull, 3 = Bear. Active results are formulas and are not editable drivers.
A3: Scenario selector | B3: 1
A4: Metric | B4: Bear | C4: Base | D4: Bull | E4: Active | F4: Rationale / source
A5: 2026 revenue growth | B5: 0.05 | C5: 0.08 | D5: 0.11 | E5: =CHOOSE($B$3,C5,D5,B5) -> 0.08 | F5: 2026 guidance: high-single-digit currency-neutral growth; numeric scenario interpretation
A6: 2026 EBIT margin | B6: 0.078 | C6: 0.085834091 | D6: 0.092 | E6: =CHOOSE($B$3,C6,D6,B6) -> 0.085834091 | F6: Base derived from ~EUR 2.3bn operating-profit guidance
A7: 2027-2030 revenue growth | B7: 0.02 | C7: 0.04 | D7: 0.06 | E7: =CHOOSE($B$3,C7,D7,B7) -> 0.04 | F7: Model-owned post-guidance assumption
A8: 2027-2030 EBIT margin | B8: 0.08 | C8: 0.09 | D8: 0.1 | E8: =CHOOSE($B$3,C8,D8,B8) -> 0.09 | F8: Model-owned post-guidance assumption
A9: Cash tax rate | B9: 0.26 | C9: 0.243 | D9: 0.22 | E9: =CHOOSE($B$3,C9,D9,B9) -> 0.243 | F9: Base anchored to FY2025 effective tax rate
A10: D&A / revenue | B10: 0.017 | C10: 0.019426867 | D10: 0.021 | E10: =CHOOSE($B$3,C10,D10,B10) -> 0.019426867 | F10: Base anchored to FY2025 D&A excluding impairment / revenue
A11: 2026 capital expenditure | B11: 550 | C11: 500 | D11: 450 | E11: =CHOOSE($B$3,C11,D11,B11) -> 500 | F11: Base anchored to management guidance around EUR 500m
A12: 2027-2030 capex / revenue | B12: 0.022 | C12: 0.02 | D12: 0.018 | E12: =CHOOSE($B$3,C12,D12,B12) -> 0.02 | F12: Model-owned post-guidance assumption
A13: Operating working capital / revenue | B13: 0.23 | C13: 0.225 | D13: 0.22 | E13: =CHOOSE($B$3,C13,D13,B13) -> 0.225 | F13: Base midpoint of 22%-23% 2026 management outlook
A14: WACC | B14: 0.095 | C14: 0.085 | D14: 0.075 | E14: =CHOOSE($B$3,C14,D14,B14) -> 0.085 | F14: Model-owned EUR discount-rate assumption
A15: Terminal growth | B15: 0.02 | C15: 0.025 | D15: 0.03 | E15: =CHOOSE($B$3,C15,D15,B15) -> 0.025 | F15: Model-owned long-run nominal EUR growth assumption
A17: Guidance-anchored inputs are separated from post-2026 and valuation assumptions. Bull/Bear cases use the same model architecture and must be reset to Base after testing.

Sheet Forecast
A1: Forecast model
A2: EUR millions unless per-share. Forecast outputs are formula-driven and guarded by source readiness.
A4: Metric | B4: 2025A | C4: 2026E | D4: 2027E | E4: 2028E | F4: 2029E | G4: 2030E
A5: Revenue | B5: 24811 | C5: =Sector_KPIs!D9 -> 26916.71 | D5: =Sector_KPIs!E9 -> 28070.725 | E5: =Sector_KPIs!F9 -> 29275.149 | F5: =Sector_KPIs!G9 -> 30532.222 | G5: =Sector_KPIs!H9 -> 31844.286
A6: Growth | C6: =C5/B5-1 -> 0.084870017 | D6: =D5/C5-1 -> 0.04287355 | E6: =E5/D5-1 -> 0.042906764 | F6: =F5/E5-1 -> 0.042939944 | G6: =G5/F5-1 -> 0.04297309
A7: EBIT margin | B7: 0.082866471 | C7: =Assumptions!$E$6 -> 0.085834091 | D7: =Assumptions!$E$8 -> 0.09 | E7: =Assumptions!$E$8 -> 0.09 | F7: =Assumptions!$E$8 -> 0.09 | G7: =Assumptions!$E$8 -> 0.09
A8: EBIT | B8: 2056 | C8: =C5*C7 -> 2310.3713 | D8: =D5*D7 -> 2526.3652 | E8: =E5*E7 -> 2634.7634 | F8: =F5*F7 -> 2747.9 | G8: =G5*G7 -> 2865.9857
A9: Cash tax rate | C9: =Assumptions!$E$9 -> 0.243 | D9: =Assumptions!$E$9 -> 0.243 | E9: =Assumptions!$E$9 -> 0.243 | F9: =Assumptions!$E$9 -> 0.243 | G9: =Assumptions!$E$9 -> 0.243
A10: NOPAT | C10: =C8*(1-C9) -> 1748.9511 | D10: =D8*(1-D9) -> 1912.4585 | E10: =E8*(1-E9) -> 1994.5159 | F10: =F8*(1-F9) -> 2080.1603 | G10: =G8*(1-G9) -> 2169.5512
A11: D&A | C11: =C5*Assumptions!$E$10 -> 522.90735 | D11: =D5*Assumptions!$E$10 -> 545.32624 | E11: =E5*Assumptions!$E$10 -> 568.72443 | F11: =F5*Assumptions!$E$10 -> 593.14542 | G11: =G5*Assumptions!$E$10 -> 618.63471
A12: Capital expenditure | C12: =-Assumptions!$E$11 -> -500 | D12: =-D5*Assumptions!$E$12 -> -561.4145 | E12: =-E5*Assumptions!$E$12 -> -585.50298 | F12: =-F5*Assumptions!$E$12 -> -610.64444 | G12: =-G5*Assumptions!$E$12 -> -636.88572
A13: Operating working capital | B13: 5556 | C13: =C5*Assumptions!$E$13 -> 6056.2598 | D13: =D5*Assumptions!$E$13 -> 6315.9131 | E13: =E5*Assumptions!$E$13 -> 6586.9085 | F13: =F5*Assumptions!$E$13 -> 6869.75 | G13: =G5*Assumptions!$E$13 -> 7164.9644
A14: Change in NWC | C14: =-(C13-B13) -> -500.25975 | D14: =-(D13-C13) -> -259.65335 | E14: =-(E13-D13) -> -270.99539 | F14: =-(F13-E13) -> -282.84148 | G14: =-(G13-F13) -> -295.21438
A15: FCFF | C15: =C10+C11+C12+C14 -> 1271.5987 | D15: =D10+D11+D12+D14 -> 1636.7169 | E15: =E10+E11+E12+E14 -> 1706.7419 | F15: =F10+F11+F12+F14 -> 1779.8198 | G15: =G10+G11+G12+G14 -> 1856.0858
A16: Adjusted net borrowings | B16: 4331 | C16: =$B$16 -> 4331 | D16: =$B$16 -> 4331 | E16: =$B$16 -> 4331 | F16: =$B$16 -> 4331 | G16: =$B$16 -> 4331
A17: Shares outstanding (mm) | B17: 178.66502 | C17: =$B$17 -> 178.66502 | D17: =$B$17 -> 178.66502 | E17: =$B$17 -> 178.66502 | F17: =$B$17 -> 178.66502 | G17: =$B$17 -> 178.66502
A19: Revenue forecast is now built bottom-up from Footwear, Apparel and Accessories. Product growth assumptions are model-owned; official channel data remains a diagnostic cross-check.

Sheet Valuation
A1: Discounted cash flow valuation
A2: FCFF DCF in EUR millions; Gordon-growth terminal value; year-end discounting; 2025-12-31 valuation date.
A4: Metric | B4: Year 1 | C4: Year 2 | D4: Year 3 | E4: Year 4 | F4: Year 5 | G4: Output
A5: FCFF | B5: =Forecast!C15 -> 1271.5987 | C5: =Forecast!D15 -> 1636.7169 | D5: =Forecast!E15 -> 1706.7419 | E5: =Forecast!F15 -> 1779.8198 | F5: =Forecast!G15 -> 1856.0858
A6: Discount factor | B6: =1/(1+Assumptions!$E$14)^1 -> 0.92165899 | C6: =1/(1+Assumptions!$E$14)^2 -> 0.84945529 | D6: =1/(1+Assumptions!$E$14)^3 -> 0.7829081 | E6: =1/(1+Assumptions!$E$14)^4 -> 0.72157428 | F6: =1/(1+Assumptions!$E$14)^5 -> 0.66504542
A7: PV FCFF | B7: =B5*B6 -> 1171.9804 | C7: =C5*C6 -> 1390.3178 | D7: =D5*D6 -> 1336.2221 | E7: =E5*E6 -> 1284.2722 | F7: =F5*F6 -> 1234.3814
A9: Output | B9: Value
A10: PV explicit FCFF | B10: =SUM(B7:F7) -> 6417.1738
A11: Terminal-year FCFF | B11: =F5*(1+Assumptions!$E$15) -> 1902.488
A12: Terminal value | B12: =IF(Assumptions!$E$14>Assumptions!$E$15,B11/(Assumptions!$E$14-Assumptions!$E$15),"") -> 31708.133
A13: PV terminal value | B13: =B12*F6 -> 21087.349
A14: Enterprise value | B14: =B10+B13 -> 27504.522
A15: Adjusted net borrowings | B15: =Forecast!B16 -> 4331
A16: Equity value | B16: =B14-B15 -> 23173.522
A17: Shares outstanding (mm) | B17: =Forecast!B17 -> 178.66502
A18: Implied value / share | B18: =IF(B17>0,B16/B17,"") -> 129.70375
A19: Share price at 2025-12-31 | B19: 169.05
A20: Upside / (downside) | B20: =IF(B19>0,B18/B19-1,"") -> -0.2327492
A21: Valuation readiness | B21: =IF(AND(COUNT(B5:F7)=15,B17>0,Assumptions!$E$14>Assumptions!$E$15),"READY FOR INDEPENDENT REVIEW","NOT DECISION-READY") -> READY FOR INDEPENDENT REVIEW
A22: Method | B22: FCFF DCF / Gordon growth
A23: Valuation fit: FCFF DCF is appropriate for a non-financial operating company with audited statements. Net debt uses adidas' adjusted net borrowings definition. WACC and terminal growth are model-owned assumptions, not issuer-reported facts.

Sheet Sensitivity
A1: Valuation sensitivity
A2: Implied EUR/share sensitivity to WACC and terminal growth. Every cell recalculates the underlying DCF.
A4: WACC / terminal g | B4: =Assumptions!$E$14-1% -> 0.075 | C4: =Assumptions!$E$14-0.5% -> 0.08 | D4: =Assumptions!$E$14 -> 0.085 | E4: =Assumptions!$E$14+0.5% -> 0.09 | F4: =Assumptions!$E$14+1% -> 0.095
A5: =Assumptions!$E$15-1% -> 0.015 | B5: =(SUMPRODUCT(Valuation!$B$5:$F$5,1/(1+B$4)^{1,2,3,4,5})+IF(B$4>$A5,Valuation!$F$5*(1+$A5)/(B$4-$A5)/(1+B$4)^5,0)-Valuation!$B$15)/Valuation!$B$17 -> 135.10616 | C5: =(SUMPRODUCT(Valuation!$B$5:$F$5,1/(1+C$4)^{1,2,3,4,5})+IF(C$4>$A5,Valuation!$F$5*(1+$A5)/(C$4-$A5)/(1+C$4)^5,0)-Valuation!$B$15)/Valuation!$B$17 -> 122.58479 | D5: =(SUMPRODUCT(Valuation!$B$5:$F$5,1/(1+D$4)^{1,2,3,4,5})+IF(D$4>$A5,Valuation!$F$5*(1+$A5)/(D$4-$A5)/(1+D$4)^5,0)-Valuation!$B$15)/Valuation!$B$17 -> 111.85572 | E5: =(SUMPRODUCT(Valuation!$B$5:$F$5,1/(1+E$4)^{1,2,3,4,5})+IF(E$4>$A5,Valuation!$F$5*(1+$A5)/(E$4-$A5)/(1+E$4)^5,0)-Valuation!$B$15)/Valuation!$B$17 -> 102.5604 | F5: =(SUMPRODUCT(Valuation!$B$5:$F$5,1/(1+F$4)^{1,2,3,4,5})+IF(F$4>$A5,Valuation!$F$5*(1+$A5)/(F$4-$A5)/(1+F$4)^5,0)-Valuation!$B$15)/Valuation!$B$17 -> 94.42996
A6: =Assumptions!$E$15-0.5% -> 0.02 | B6: =(SUMPRODUCT(Valuation!$B$5:$F$5,1/(1+B$4)^{1,2,3,4,5})+IF(B$4>$A6,Valuation!$F$5*(1+$A6)/(B$4-$A6)/(1+B$4)^5,0)-Valuation!$B$15)/Valuation!$B$17 -> 146.89255 | C6: =(SUMPRODUCT(Valuation!$B$5:$F$5,1/(1+C$4)^{1,2,3,4,5})+IF(C$4>$A6,Valuation!$F$5*(1+$A6)/(C$4-$A6)/(1+C$4)^5,0)-Valuation!$B$15)/Valuation!$B$17 -> 132.37448 | D6: =(SUMPRODUCT(Valuation!$B$5:$F$5,1/(1+D$4)^{1,2,3,4,5})+IF(D$4>$A6,Valuation!$F$5*(1+$A6)/(D$4-$A6)/(1+D$4)^5,0)-Valuation!$B$15)/Valuation!$B$17 -> 120.09327 | E6: =(SUMPRODUCT(Valuation!$B$5:$F$5,1/(1+E$4)^{1,2,3,4,5})+IF(E$4>$A6,Valuation!$F$5*(1+$A6)/(E$4-$A6)/(1+E$4)^5,0)-Valuation!$B$15)/Valuation!$B$17 -> 109.56952 | F6: =(SUMPRODUCT(Valuation!$B$5:$F$5,1/(1+F$4)^{1,2,3,4,5})+IF(F$4>$A6,Valuation!$F$5*(1+$A6)/(F$4-$A6)/(1+F$4)^5,0)-Valuation!$B$15)/Valuation!$B$17 -> 100.45168
A7: =Assumptions!$E$15 -> 0.025 | B7: =(SUMPRODUCT(Valuation!$B$5:$F$5,1/(1+B$4)^{1,2,3,4,5})+IF(B$4>$A7,Valuation!$F$5*(1+$A7)/(B$4-$A7)/(1+B$4)^5,0)-Valuation!$B$15)/Valuation!$B$17 -> 161.03621 | C7: =(SUMPRODUCT(Valuation!$B$5:$F$5,1/(1+C$4)^{1,2,3,4,5})+IF(C$4>$A7,Valuation!$F$5*(1+$A7)/(C$4-$A7)/(1+C$4)^5,0)-Valuation!$B$15)/Valuation!$B$17 -> 143.94412 | D7: =(SUMPRODUCT(Valuation!$B$5:$F$5,1/(1+D$4)^{1,2,3,4,5})+IF(D$4>$A7,Valuation!$F$5*(1+$A7)/(D$4-$A7)/(1+D$4)^5,0)-Valuation!$B$15)/Valuation!$B$17 -> 129.70375 | E7: =(SUMPRODUCT(Valuation!$B$5:$F$5,1/(1+E$4)^{1,2,3,4,5})+IF(E$4>$A7,Valuation!$F$5*(1+$A7)/(E$4-$A7)/(1+E$4)^5,0)-Valuation!$B$15)/Valuation!$B$17 -> 117.65696 | F7: =(SUMPRODUCT(Valuation!$B$5:$F$5,1/(1+F$4)^{1,2,3,4,5})+IF(F$4>$A7,Valuation!$F$5*(1+$A7)/(F$4-$A7)/(1+F$4)^5,0)-Valuation!$B$15)/Valuation!$B$17 -> 107.33365
A8: =Assumptions!$E$15+0.5% -> 0.03 | B8: =(SUMPRODUCT(Valuation!$B$5:$F$5,1/(1+B$4)^{1,2,3,4,5})+IF(B$4>$A8,Valuation!$F$5*(1+$A8)/(B$4-$A8)/(1+B$4)^5,0)-Valuation!$B$15)/Valuation!$B$17 -> 178.32292 | C8: =(SUMPRODUCT(Valuation!$B$5:$F$5,1/(1+C$4)^{1,2,3,4,5})+IF(C$4>$A8,Valuation!$F$5*(1+$A8)/(C$4-$A8)/(1+C$4)^5,0)-Valuation!$B$15)/Valuation!$B$17 -> 157.82767 | D8: =(SUMPRODUCT(Valuation!$B$5:$F$5,1/(1+D$4)^{1,2,3,4,5})+IF(D$4>$A8,Valuation!$F$5*(1+$A8)/(D$4-$A8)/(1+D$4)^5,0)-Valuation!$B$15)/Valuation!$B$17 -> 141.06158 | E8: =(SUMPRODUCT(Valuation!$B$5:$F$5,1/(1+E$4)^{1,2,3,4,5})+IF(E$4>$A8,Valuation!$F$5*(1+$A8)/(E$4-$A8)/(1+E$4)^5,0)-Valuation!$B$15)/Valuation!$B$17 -> 127.09231 | F8: =(SUMPRODUCT(Valuation!$B$5:$F$5,1/(1+F$4)^{1,2,3,4,5})+IF(F$4>$A8,Valuation!$F$5*(1+$A8)/(F$4-$A8)/(1+F$4)^5,0)-Valuation!$B$15)/Valuation!$B$17 -> 115.27439
A9: =Assumptions!$E$15+1% -> 0.035 | B9: =(SUMPRODUCT(Valuation!$B$5:$F$5,1/(1+B$4)^{1,2,3,4,5})+IF(B$4>$A9,Valuation!$F$5*(1+$A9)/(B$4-$A9)/(1+B$4)^5,0)-Valuation!$B$15)/Valuation!$B$17 -> 199.93129 | C9: =(SUMPRODUCT(Valuation!$B$5:$F$5,1/(1+C$4)^{1,2,3,4,5})+IF(C$4>$A9,Valuation!$F$5*(1+$A9)/(C$4-$A9)/(1+C$4)^5,0)-Valuation!$B$15)/Valuation!$B$17 -> 174.79647 | D9: =(SUMPRODUCT(Valuation!$B$5:$F$5,1/(1+D$4)^{1,2,3,4,5})+IF(D$4>$A9,Valuation!$F$5*(1+$A9)/(D$4-$A9)/(1+D$4)^5,0)-Valuation!$B$15)/Valuation!$B$17 -> 154.69099 | E9: =(SUMPRODUCT(Valuation!$B$5:$F$5,1/(1+E$4)^{1,2,3,4,5})+IF(E$4>$A9,Valuation!$F$5*(1+$A9)/(E$4-$A9)/(1+E$4)^5,0)-Valuation!$B$15)/Valuation!$B$17 -> 138.24318 | F9: =(SUMPRODUCT(Valuation!$B$5:$F$5,1/(1+F$4)^{1,2,3,4,5})+IF(F$4>$A9,Valuation!$F$5*(1+$A9)/(F$4-$A9)/(1+F$4)^5,0)-Valuation!$B$15)/Valuation!$B$17 -> 124.53858
A11: Center cell D7 uses Base WACC 8.5% and Base terminal growth 2.5%; Checks compares it with the Valuation implied share price.

Sheet Checks
A1: Model checks and decision-use gate
A2: Each assertion shows Actual, Expected, Difference, Tolerance, formula-driven Status and a fix hint.
A4: Check | B4: Actual | C4: Expected | D4: Difference | E4: Tolerance | F4: Status | G4: Location / fix hint
A5: Material source mappings | B5: =COUNTIF(Sources!$P$5:$P$70,"MAPPED") -> 66 | C5: =COUNTIF(Sources!$O$5:$O$70,"Yes") -> 66 | D5: =B5-C5 -> 0 | E5: 0 | F5: =IF(COUNTIF(Sources!$P$5:$P$70,"MISSING")>0,"FAIL",IF(COUNTIF(Sources!$P$5:$P$70,"BLOCKED")>0,"BLOCKED",IF(ABS(D5)<=E5,"PASS","FAIL"))) -> PASS | G5: Sources!O:P; map every required field or retain BLOCKED
A6: FY2025 revenue tie | B6: =IF(Historical!F5="",0,Historical!F5) -> 24811 | C6: =IF(Sources!D9="",0,Sources!D9) -> 24811 | D6: =B6-C6 -> 0 | E6: 0.1 | F6: =IF(ABS(D6)<=E6,IF(B6=0,"BLOCKED","PASS"),"FAIL") -> PASS | G6: Historical!F5 vs claim-level Sources value
A7: FY2025 EBIT tie | B7: =IF(Historical!F7="",0,Historical!F7) -> 2056 | C7: =IF(Sources!D19="",0,Sources!D19) -> 2056 | D7: =B7-C7 -> 0 | E7: 0.1 | F7: =IF(AND(B7=0,C7=0),"BLOCKED",IF(ABS(D7)<=E7,"PASS","FAIL")) -> PASS | G7: Historical!F7 vs claim-level Sources value
A8: Liabilities bridge | B8: =IF(Historical!F12="",0,Historical!F12) -> 14486 | C8: =IF(AND(Historical!F11<>"",Historical!F13<>""),Historical!F11-Historical!F13,0) -> 14486 | D8: =B8-C8 -> 0 | E8: 0.1 | F8: =IF(AND(B8=0,C8=0),"BLOCKED",IF(ABS(D8)<=E8,"PASS","FAIL")) -> PASS | G8: Historical!F12 = assets - equity
A9: Forecast revenue populated | B9: =COUNT(Forecast!C5:G5) -> 5 | C9: 5 | D9: =B9-C9 -> 0 | E9: 0 | F9: =IF(ABS(D9)<=E9,"PASS","BLOCKED") -> PASS | G9: Forecast!C5:G5
A10: FCFF populated | B10: =COUNT(Forecast!C15:G15) -> 5 | C10: 5 | D10: =B10-C10 -> 0 | E10: 0 | F10: =IF(ABS(D10)<=E10,"PASS","BLOCKED") -> PASS | G10: Forecast!C15:G15
A11: WACC exceeds terminal growth | B11: =IF(AND(Assumptions!E14<>"",Assumptions!E15<>"",Assumptions!E14>Assumptions!E15),1,0) -> 1 | C11: 1 | D11: =B11-C11 -> 0 | E11: 0 | F11: =IF(ABS(D11)<=E11,"PASS","BLOCKED") -> PASS | G11: Assumptions!E14:E15
A12: DCF enterprise-value bridge | B12: =Valuation!B14 -> 27504.522 | C12: =Valuation!B10+Valuation!B13 -> 27504.522 | D12: =B12-C12 -> 0 | E12: 0.1 | F12: =IF(ABS(D12)<=E12,"PASS","FAIL") -> PASS | G12: Valuation!B14 = PV explicit + PV terminal
A13: Equity-value bridge | B13: =Valuation!B16 -> 23173.522 | C13: =Valuation!B14-Valuation!B15 -> 23173.522 | D13: =B13-C13 -> 0 | E13: 0.1 | F13: =IF(ABS(D13)<=E13,"PASS","FAIL") -> PASS | G13: Valuation!B16 = EV - adjusted net borrowings
A14: Sensitivity center tie | B14: =Sensitivity!D7 -> 129.70375 | C14: =Valuation!B18 -> 129.70375 | D14: =B14-C14 -> 0 | E14: 0.01 | F14: =IF(ABS(D14)<=E14,"PASS","FAIL") -> PASS | G14: Sensitivity!D7 = Valuation!B18
A15: Headline valuation suppression | B15: =IF(ISNUMBER(Valuation!B18),1,0) -> 1 | C15: 1 | D15: =B15-C15 -> 0 | E15: 0 | F15: =IF(ABS(D15)<=E15,"PASS","FAIL") -> PASS | G15: Valuation!B18 must be numeric
A16: Scenario selector valid | B16: =IF(AND(Assumptions!B3>=1,Assumptions!B3<=3),1,0) -> 1 | C16: 1 | D16: =B16-C16 -> 0 | E16: 0 | F16: =IF(ABS(D16)<=E16,"PASS","FAIL") -> PASS | G16: Assumptions!B3 must be 1, 2 or 3
A18: Overall gate | F18: =IF(AND(COUNTIF(F5:F16,"PASS")=12,COUNTIF(F20:F22,"PASS")=3),"REVIEW-READY — INDEPENDENT CERTIFICATION PENDING","BLOCKER — CHECKS FAILED") -> REVIEW-READY — INDEPENDENT CERTIFICATION PENDING
A19: Decision use | B19: Owner review-ready; no owner certification claim
A20: Product-driver revenue tie 2030 | B20: =Sector_KPIs!H9 -> 31844.286 | C20: =Forecast!G5 -> 31844.286 | D20: =B20-C20 -> 0 | E20: 0.1 | F20: =IF(ABS(D20)<=E20,"PASS","FAIL") -> PASS | G20: Sector_KPIs!H10
A21: FY2025 product total tie | B21: =Sector_KPIs!C9 -> 24811 | C21: 24811 | D21: =B21-C21 -> 0 | E21: 0.1 | F21: =IF(ABS(D21)<=E21,"PASS","FAIL") -> PASS | G21: Sector_KPIs!C9 / Historical!F5
A22: Share denominator tie | B22: =Sector_KPIs!B33 -> 178.66502 | C22: =Historical!F16 -> 178.66502 | D22: =B22-C22 -> 0 | E22: 1e-06 | F22: =IF(ABS(D22)<=E22,"PASS","FAIL") -> PASS | G22: Sector_KPIs!B33 / Historical!F16

Sheet Sector_KPIs
A1: Product and channel operating drivers
A2: Reported FY2024–FY2025 product/channel revenue; FY2026E–FY2030E product growth is explicitly model-owned and scenario-controlled. EUR millions.
A4: Product division | B4: 2024A | C4: 2025A | D4: 2026E | E4: 2027E | F4: 2028E | G4: 2029E | H4: 2030E
A5: Footwear | B5: 13977 | C5: 14232 | D5: =C5*(1+$E$14) -> 15370.56 | E5: =D5*(1+$E$17) -> 15985.382 | F5: =E5*(1+$E$17) -> 16624.798 | G5: =F5*(1+$E$17) -> 17289.79 | H5: =G5*(1+$E$17) -> 17981.381
A6: Apparel | B6: 7937 | C6: 8764 | D6: =C6*(1+$E$15) -> 9640.4 | E6: =D6*(1+$E$18) -> 10122.42 | F6: =E6*(1+$E$18) -> 10628.541 | G6: =F6*(1+$E$18) -> 11159.968 | H6: =G6*(1+$E$18) -> 11717.966
A7: Accessories | B7: 1779 | C7: 1815 | D7: =C7*(1+$E$16) -> 1905.75 | E7: =D7*(1+$E$19) -> 1962.9225 | F7: =E7*(1+$E$19) -> 2021.8102 | G7: =F7*(1+$E$19) -> 2082.4645 | H7: =G7*(1+$E$19) -> 2144.9384
A8: Other / rounding | B8: -10 | C8: 0 | D8: 0 | E8: 0 | F8: 0 | G8: 0 | H8: 0
A9: Total revenue | B9: 23683 | C9: 24811 | D9: =SUM(D5:D8) -> 26916.71 | E9: =SUM(E5:E8) -> 28070.725 | F9: =SUM(F5:F8) -> 29275.149 | G9: =SUM(G5:G8) -> 30532.222 | H9: =SUM(H5:H8) -> 31844.286
A10: Tie to reported / Forecast | B10: 0 | C10: 0 | D10: =D9-Forecast!C5 -> 0 | E10: =E9-Forecast!D5 -> 0 | F10: =F9-Forecast!E5 -> 0 | G10: =G9-Forecast!F5 -> 0 | H10: =H9-Forecast!G5 -> 0
A12: Scenario assumption | B12: Bear | C12: Base | D12: Bull | E12: Active | F12: Classification
A13: Selector mapping | B13: 3 | C13: 1 | D13: 2 | F13: 1=Base, 2=Bull, 3=Bear
A14: Footwear growth — 2026 | B14: 0.05 | C14: 0.08 | D14: 0.11 | E14: =CHOOSE(Assumptions!$B$3,C14,D14,B14) -> 0.08 | F14: Model-owned; anchored to official product revenue
A15: Apparel growth — 2026 | B15: 0.06 | C15: 0.1 | D15: 0.14 | E15: =CHOOSE(Assumptions!$B$3,C15,D15,B15) -> 0.1 | F15: Model-owned; anchored to official product revenue
A16: Accessories growth — 2026 | B16: 0.02 | C16: 0.05 | D16: 0.08 | E16: =CHOOSE(Assumptions!$B$3,C16,D16,B16) -> 0.05 | F16: Model-owned; anchored to official product revenue
A17: Footwear growth — 2027-2030 | B17: 0.02 | C17: 0.04 | D17: 0.06 | E17: =CHOOSE(Assumptions!$B$3,C17,D17,B17) -> 0.04 | F17: Model-owned
A18: Apparel growth — 2027-2030 | B18: 0.03 | C18: 0.05 | D18: 0.07 | E18: =CHOOSE(Assumptions!$B$3,C18,D18,B18) -> 0.05 | F18: Model-owned
A19: Accessories growth — 2027-2030 | B19: 0.01 | C19: 0.03 | D19: 0.05 | E19: =CHOOSE(Assumptions!$B$3,C19,D19,B19) -> 0.03 | F19: Model-owned
A22: Channel diagnostic | B22: 2024A | C22: 2025A | D22: Currency-neutral growth | F22: Source / locator
A23: Wholesale | B23: 14172 | C23: 14833 | D23: 0.12 | F23: adidas FY2025 Annual Report — Income Statement, net sales by product division and channel
A24: Direct-to-consumer | B24: 9490 | C24: 9931 | D24: 0.14 | F24: https://report.adidas-group.com/2025/en/group-management-report-financial-review/business-performance/income-statement.html
A25: Total channel revenue | B25: 23662 | C25: 24764 | F25: Channel totals can differ from consolidated total due to segment presentation / rounding; diagnostic only.
A28: Share-class and valuation denominator bridge
A29: Bridge item | B29: Shares (mm) | C29: Valuation treatment | D29: Evidence / limitation
A30: Ordinary shares outstanding — FY2025 | B30: 178.66502 | C30: Included 1:1 | D30: adidas FY2025 Annual Report, financial highlights / number of shares
A31: Preferred / class shares | B31: 0 | C31: None | D31: No separate preferred class in the controlled valuation denominator
A32: Treasury shares | C32: Excluded from outstanding denominator | D32: Not separately extracted; outstanding count used directly
A33: Total valuation denominator | B33: =SUM(B30:B31) -> 178.66502 | C33: Equity value divided by this line | D33: Formula
A34: DCF equity value | B34: =Valuation!B16 -> 23173.522 | C34: EUR mm | D34: Valuation!B16
A35: Implied value per ordinary share | B35: =B34/B33 -> 129.70375 | C35: EUR/share | D35: Valuation!B18
A36: Share price at valuation date | B36: =Valuation!B19 -> 169.05 | C36: EUR/share | D36: Valuation!B19
A37: Bridge status | B37: =IF(ABS(B33-Historical!F16)<0.000001,"PASS","FAIL") -> PASS | C37: PASS if denominator ties | D37: Formula

Sheet Change_Log
A1: Change log and governance
A2: Controlled version history, scope, evidence and reviewer disposition.
A4: Date | B4: Version | C4: Author / lane | D4: Change | E4: Changed sheets / ranges | F4: Evidence | G4: Reviewer status
A5: 2026-07-15 | B5: 1.0 | C5: Codex baseline | D5: Initial generic institutional model shell | E5: All baseline sheets | F5: Adidas_Institutional_Model.xlsx | G5: Superseded by controlled copy; original preserved
A6: 2026-07-16 | B6: 2.0 | C6: limited-company / consumer-agri cluster | D6: Rebuilt EUR history, guidance-anchored FCFF model, dynamic DCF/sensitivity, formula-driven checks and H0-H9 ledger | E6: 00_Cover; Sources; Historical; Assumptions; Forecast; Valuation; Sensitivity; Checks; Sector_KPIs; Change_Log; added 9_10_Blockers | F6: Companion QA, recalc and evidence package | G6: Independent review pending
A7: 2026-07-16 | B7: 2.0 | C7: limited-company / consumer-agri cluster | D7: Preserved baseline lineage and source boundary | E7: No original workbook edits; no raw Latinex companies/objects/OCR access | F7: Original SHA-256 30cbb37f94bb55224c9f1fb4ddb86532568199a2f3ccc0dbf2c86c0a5c86ffb8 | G7: Owner verified; independent package review pending
A8: 2026-07-16 | B8: 2.0 | C8: limited-company / consumer-agri cluster | D8: Native recalculation required after export | E8: All formulas | F8: See companion recalc log and render manifest tied to controlled SHA-256 | G8: Pending until post-export evidence is frozen
A9: 2026-07-16 | B9: 2.1 | C9: /root/limited_near_finish_high | D9: Added official product/channel anchors, bottom-up revenue drivers and single-class share bridge; linked forecast and checks. | E9: Sector_KPIs, Sources 221:227, Checks 20:22 | F9: Owner mechanics prepared; native/visual QA pending | G9: PENDING — reviewer only
A10: 46224 | B10: Elevation to statement-grade IG (Ola 2, run 24e4a1f1): added audited FY2021-FY2025 statement sheets IS_Hist/CI_Hist/BS_Hist/CF_Hist/SCE_Hist (EUR mm, published constants from adidas AG standalone Consolidated Financial Statements PDFs, physical-page cited per year), Checks_TieOut (28 cross-statement tie-outs), Sources_Audited, Source_Register pointer, and Forecast_IG (5-yr Base/Bull/Bear driver scaffold, PARTIAL/assumption-based, anchored to FY2025A). Root Ola-1 sheets (Historical, Sources, Assumptions, Forecast, Valuation, Sensitivity, Checks, Sector_KPIs, 9_10_Blockers) left untouched. Root workbook untouched; v2 saved under the maintainer's archive. Built via Mog SDK only. | C10: Claude (run 24e4a1f1)

Sheet 9_10_Blockers
A1: Independent 9/10 hard-gate ledger
A2: Owner evidence status only. Independent reviewer results remain pending; no owner self-certification.
A4: Gate | B4: Points | C4: Owner evidence status | D4: Evidence location | E4: Blocker / resolution | F4: Independent result
A5: H0 | B5: 5 | C5: OWNER EVIDENCE COMPLETE | D5: Controlled path, original hash, package integrity and lineage evidence | E5: Independent identity/package reproduction pending | F5: PENDING
A6: H1 | B6: 20 | C6: OWNER EVIDENCE COMPLETE | D6: Sources!A:P claim-level ledger and formula-driven mapping status | E6: Independent source sampling pending | F6: PENDING
A7: H2 | B7: 15 | C7: OWNER EVIDENCE COMPLETE | D7: Historical; Forecast; Checks | E7: Independent formula tracing pending | F7: PENDING
A8: H3 | B8: 10 | C8: OWNER EVIDENCE COMPLETE | D8: Assumptions selector; Forecast outputs; Sensitivity | E8: Independent scenario toggle/reset pending | F8: PENDING
A9: H4 | B9: 15 | C9: OWNER EVIDENCE COMPLETE | D9: Valuation; Sensitivity; Checks | E9: Independent DCF reproduction pending | F9: PENDING
A10: H5 | B10: 8 | C10: OWNER EVIDENCE COMPLETE | D10: Checks with Actual/Expected/Difference/Tolerance/Status/Fix hint | E10: Post-native-recalc error scan evidence required | F10: PENDING
A11: H6 | B11: 10 | C11: OWNER EVIDENCE PREPARED | D11: Companion isolated LibreOffice open/save/reopen log | E11: Independent native-recalc reproduction pending | F11: PENDING
A12: H7 | B12: 7 | C12: OWNER EVIDENCE PREPARED | D12: Companion render manifest for every user-facing sheet | E12: Independent visual review pending | F12: PENDING
A13: H8 | B13: 5 | C13: OWNER EVIDENCE COMPLETE | D13: Source mapping, model mechanics, formula gates and valuation readiness were materially changed | E13: Not a visual-only upgrade | F13: PENDING
A14: H9 | B14: 5 | C14: OWNER EVIDENCE COMPLETE | D14: 00_Cover; Change_Log; this ledger | E14: Independent governance review pending | F14: PENDING
A16: Owner package status | B16: =IF(COUNTIF(C5:C14,"BLOCKED*")>0,"NOT CERTIFIED — source/disclosure blocker","PENDING INDEPENDENT 9/10 REVIEW") -> PENDING INDEPENDENT 9/10 REVIEW
A18: Resolved owner criteria: audited source availability, line-item mapping, EUR-unit history, guidance-anchored model, Base/Bull/Bear propagation, FCFF DCF, dynamic WACC/g sensitivity and formula-driven checks. Certification remains an independent-review decision.

Sheet IS_Hist
A1: adidas AG — Consolidated Income Statement (audited, IFRS)
A2: EUR millions. Each FY sourced from that FY’s own Consolidated Financial Statements PDF (see Sources_Audited for exact file + physical page); cross-checked vs following-year comparative column.
A4: Line item | B4: FY2021A | C4: FY2022A | D4: FY2023A | E4: FY2024A | F4: FY2025A | G4: Note ref
A5: Net sales | B5: 21234 | C5: 22511 | D5: 21427 | E5: 23683 | F5: 24811 | G5: 36
A6: Cost of sales | B6: 10469 | C6: 11867 | D6: 11244 | E6: 11658 | F6: 12006
A7: Gross profit | B7: 10765 | C7: 10644 | D7: 10184 | E7: 12026 | F7: 12804
A8: Royalty and commission income | B8: 86 | C8: 112 | D8: 83 | E8: 81 | F8: 81
A9: Other operating income | B9: 28 | C9: 173 | D9: 71 | E9: 174 | F9: 41 | G9: 29
A10: Other operating expenses | B10: 8892 | C10: 10260 | D10: 10070 | E10: 10945 | F10: 10871 | G10: 09,12,30,31
A12: Of which:
A13: Marketing and point-of-sale expenses | B13: 2547 | C13: 2763 | D13: 2528 | E13: 2841 | F13: 3079
A14: Distribution and selling expenses | B14: 4782 | C14: 5601 | D14: 5547 | E14: 5936 | F14: 5877
A15: General and administration expenses | B15: 1481 | C15: 1651 | D15: 1839 | E15: 2138 | F15: 1885
A16: Sundry expenses | B16: 76 | C16: 182 | D16: 137 | E16: 44 | F16: 23
A17: Impairment losses/(gains), net, on accounts receivable and contract assets | B17: 6 | C17: 63 | D17: 19 | E17: -15 | F17: 7
A19: Operating profit | B19: 1986 | C19: 669 | D19: 268 | E19: 1337 | F19: 2056
A20: Financial income | B20: 19 | C20: 39 | D20: 79 | E20: 101 | F20: 74 | G20: 32
A21: Financial expenses | B21: 153 | C21: 320 | D21: 282 | E21: 317 | F21: 310 | G21: 32
A22: Income before taxes | B22: 1852 | C22: 388 | D22: 65 | E22: 1121 | F22: 1820
A23: Income taxes | B23: 360 | C23: 134 | D23: 124 | E23: 297 | F23: 443 | G23: 34
A24: Net income from continuing operations | B24: 1492 | C24: 254 | D24: -58 | E24: 824 | F24: 1377
A25: Gain from discontinued operations, net of tax | B25: 666 | C25: 384 | D25: 44 | E25: 8 | F25: 8 | G25: 03
A26: Net income | B26: 2158 | C26: 638 | D26: -14 | E26: 832 | F26: 1385
A28: Attributable to:
A29: Net income attributable to shareholders | B29: 2116 | C29: 612 | D29: -75 | E29: 764 | F29: 1340
A30: Net income attributable to non-controlling interests | B30: 42 | C30: 26 | D30: 61 | E30: 68 | F30: 45
A32: Basic EPS, continuing operations (EUR) | B32: 7.47 | C32: 1.25 | D32: -0.67 | E32: 4.24 | F32: 7.46 | G32: 35
A33: Diluted EPS, continuing operations (EUR) | B33: 7.47 | C33: 1.25 | D33: -0.67 | E33: 4.24 | F33: 7.46 | G33: 35
A34: Basic EPS, continuing + discontinued (EUR) | B34: 10.9 | C34: 3.34 | D34: -0.42 | E34: 4.28 | F34: 7.51 | G34: 35
A35: Diluted EPS, continuing + discontinued (EUR) | B35: 10.9 | C35: 3.34 | D35: -0.42 | E35: 4.28 | F35: 7.51 | G35: 35

Sheet CI_Hist
A1: adidas AG — Consolidated Statement of Comprehensive Income (audited, IFRS)
A2: EUR millions. Same source basis as IS_Hist.
A4: Line item | B4: FY2021A | C4: FY2022A | D4: FY2023A | E4: FY2024A | F4: FY2025A | G4: Note ref
A5: Net income | B5: 2158 | C5: 638 | D5: -14 | E5: 832 | F5: 1385
A6: Items that will not be reclassified subsequently to profit or loss:
A7: Remeasurements of defined benefit plans (IAS 19), net of tax | B7: 50 | C7: 131 | D7: -5 | E7: -2 | F7: 22 | G7: 23
A8: Net gain/(loss) on other equity investments (IFRS 9), net of tax | B8: 1 | C8: 0 | D8: -5 | E8: 1 | F8: -60 | G8: 28
A9: Subtotal — items not reclassified | B9: 52 | C9: 131 | D9: -10 | E9: -2 | F9: -38
A10: Items that may be reclassified to profit or loss:
A11: Net gain/(loss) on cash flow hedges and net foreign investment hedges, net of tax | B11: 186 | C11: -25 | D11: -126 | E11: 156 | F11: -320 | G11: 28
A12: Net gain/(loss) on cost of hedging reserve — options, net of tax | B12: -6 | C12: -1 | D12: 7 | E12: 1 | F12: -1 | G12: 28
A13: Net gain/(loss) on cost of hedging reserve — forward contracts, net of tax | B13: 11 | C13: -36 | D13: 46 | E13: 11 | F13: 12 | G13: 28
A14: Reclassification of currency translation differences (disposal of foreign operations) | C14: -228
A15: Currency translation differences | B15: 330 | C15: 177 | D15: -155 | E15: 117 | F15: -391
A16: Subtotal — items that may be reclassified | B16: 521 | C16: -113 | D16: -228 | E16: 285 | F16: -700
A18: Other comprehensive income | B18: 573 | C18: 18 | D18: -238 | E18: 283 | F18: -738
A19: Total comprehensive income | B19: 2731 | C19: 656 | D19: -252 | E19: 1115 | F19: 647
A21: Attributable to:
A22: Attributable to shareholders of adidas AG | B22: 2650 | C22: 610 | D22: -300 | E22: 1023 | F22: 648
A23: Attributable to non-controlling interests | B23: 81 | C23: 47 | D23: 48 | E23: 92 | F23: -1

Sheet BS_Hist
A1: adidas AG — Consolidated Statement of Financial Position (audited, IFRS)
A2: EUR millions, as of December 31. Same source basis as IS_Hist. Blank = line not presented / nil that year (e.g. Short-term financial assets introduced FY2023, Assets/Liabilities held-for-sale only FY2021 Reebok disposal group).
A4: Line item | B4: FY2021A | C4: FY2022A | D4: FY2023A | E4: FY2024A | F4: FY2025A | G4: Note ref
A5: Assets
A6: Current assets
A7: Cash and cash equivalents | B7: 3828 | C7: 798 | D7: 1431 | E7: 2455 | F7: 1617 | G7: 04
A8: Accounts receivable | B8: 2175 | C8: 2529 | D8: 1906 | E8: 2413 | F8: 2634 | G8: 05
A9: Other current financial assets | B9: 745 | C9: 1014 | D9: 755 | E9: 950 | F9: 518 | G9: 06
A10: Short-term financial assets | D10: 34 | E10: 0
A11: Inventories | B11: 4009 | C11: 5973 | D11: 4525 | E11: 4989 | F11: 5832 | G11: 07
A12: Income tax receivables | B12: 91 | C12: 102 | D12: 156 | E12: 101 | F12: 167 | G12: 34
A13: Other current assets | B13: 1062 | C13: 1316 | D13: 1003 | E13: 997 | F13: 1208 | G13: 08
A14: Assets classified as held for sale | B14: 2033 | G14: 03
A15: Total current assets | B15: 13944 | C15: 11732 | D15: 9809 | E15: 11904 | F15: 11977
A16: Non-current assets
A17: Property, plant, and equipment | B17: 2256 | C17: 2279 | D17: 2157 | E17: 2133 | F17: 1973 | G17: 09
A18: Right-of-use assets | B18: 2569 | C18: 2665 | D18: 2247 | E18: 2779 | F18: 2605 | G18: 10
A19: Goodwill | B19: 1228 | C19: 1260 | D19: 1238 | E19: 1275 | F19: 1203 | G19: 11
A20: Trademarks / Other intangible assets | B20: 352 | C20: 429 | D20: 442 | E20: 426 | F20: 443 | G20: 12
A21: Long-term financial assets | B21: 290 | C21: 301 | D21: 301 | E21: 340 | F21: 353 | G21: 13
A22: Other non-current financial assets | B22: 160 | C22: 336 | D22: 418 | E22: 234 | F22: 217 | G22: 14
A23: Deferred tax assets | B23: 1263 | C23: 1216 | D23: 1358 | E23: 1272 | F23: 1077 | G23: 34
A24: Other non-current assets | B24: 74 | C24: 76 | D24: 49 | E24: 291 | F24: 415 | G24: 15
A25: Total non-current assets | B25: 8193 | C25: 8563 | D25: 8211 | E25: 8751 | F25: 8285
A27: Total assets | B27: 22137 | C27: 20296 | D27: 18020 | E27: 20655 | F27: 20262
A29: Liabilities
A30: Current liabilities
A31: Short-term borrowings | B31: 29 | C31: 527 | D31: 549 | E31: 570 | F31: 645 | G31: 16
A32: Accounts payable | B32: 2294 | C32: 2908 | D32: 2276 | E32: 3096 | F32: 2910
A33: Current lease liabilities | B33: 573 | C33: 643 | D33: 545 | E33: 607 | F33: 603 | G33: 19
A34: Other current financial liabilities | B34: 363 | C34: 424 | D34: 266 | E34: 191 | F34: 335 | G34: 17
A35: Income taxes | B35: 536 | C35: 302 | D35: 323 | E35: 334 | F35: 357 | G35: 34
A36: Other current provisions | B36: 1458 | C36: 1589 | D36: 1323 | E36: 1538 | F36: 1208 | G36: 18
A37: Current accrued liabilities | B37: 2684 | C37: 2412 | D37: 2273 | E37: 2659 | F37: 2383 | G37: 20
A38: Other current liabilities | B38: 434 | C38: 452 | D38: 488 | E38: 598 | F38: 652 | G38: 21
A39: Liabilities classified as held for sale | B39: 594 | G39: 03
A40: Total current liabilities | B40: 8965 | C40: 9257 | D40: 8043 | E40: 9593 | F40: 9094
A41: Non-current liabilities
A42: Long-term borrowings | B42: 2466 | C42: 2946 | D42: 2430 | E42: 1915 | F42: 1996 | G42: 16
A43: Non-current lease liabilities | B43: 2263 | C43: 2343 | D43: 2039 | E43: 2495 | F43: 2310 | G43: 19
A44: Other non-current financial liabilities | B44: 51 | C44: 44 | D44: 6 | E44: 1 | F44: 7 | G44: 22
A45: Pensions and similar obligations | B45: 267 | C45: 118 | D45: 139 | E45: 144 | F45: 106 | G45: 23
A46: Deferred tax liabilities | B46: 122 | C46: 135 | D46: 147 | E46: 133 | F46: 45 | G46: 34
A47: Other non-current provisions | B47: 149 | C47: 88 | D47: 188 | E47: 353 | F47: 436 | G47: 18
A48: Non-current accrued liabilities | B48: 8 | C48: 7 | G48: 20
A49: Other non-current liabilities | B49: 9 | C49: 6 | D49: 103 | E49: 154 | F49: 143 | G49: 24
A50: Total non-current liabilities | B50: 5334 | C50: 5688 | D50: 5052 | E50: 5194 | F50: 5043
A52: Total liabilities | B52: 14299 | C52: 14945 | D52: 13095 | E52: 14787 | F52: 14137
A54: Equity
A55: Share capital | B55: 192 | C55: 179 | D55: 179 | E55: 179 | F55: 179
A56: Reserves | B56: 69 | C56: 466 | D56: 257 | E56: 522 | F56: -161
A57: Retained earnings | B57: 7259 | C57: 4347 | D57: 4145 | E57: 4775 | F57: 5758
A58: Shareholders’ equity | B58: 7519 | C58: 4991 | D58: 4580 | E58: 5476 | F58: 5776 | G58: 25
A59: Non-controlling interests | B59: 318 | C59: 360 | D59: 345 | E59: 392 | F59: 349 | G59: 27
A60: Total equity | B60: 7837 | C60: 5351 | D60: 4925 | E60: 5867 | F60: 6125
A62: Total liabilities and equity | B62: 22137 | C62: 20296 | D62: 18020 | E62: 20655 | F62: 20262

Sheet CF_Hist
A1: adidas AG — Consolidated Statement of Cash Flows (audited, IFRS)
A2: EUR millions. Same source basis as IS_Hist. Signs as published (outflows negative). FY2021-22 reported a continuing/discontinued-operations split; FY2023-25 do not — folded into the "discontinued operations / hyperinflation" and "-- discontinued operations" lines so each subtotal ties to the as-published total.
A4: Line item | B4: FY2021A | C4: FY2022A | D4: FY2023A | E4: FY2024A | F4: FY2025A | G4: Note ref
A5: Operating activities
A6: Income before taxes (continuing operations) | B6: 1852 | C6: 388 | D6: 65 | E6: 1121 | F6: 1820
A7: Depreciation, amortization, and impairment losses | B7: 1149 | C7: 1375 | D7: 1212 | E7: 1208 | F7: 1154 | G7: 11,12,30
A8: Reversals of impairment losses | B8: -34 | C8: -4 | D8: -42 | E8: -28 | F8: -19 | G8: 29/09,10,30
A9: Interest income | B9: -13 | C9: -23 | D9: -39 | E9: -57 | F9: -58 | G9: 32
A10: Interest expense | B10: 111 | C10: 138 | D10: 162 | E10: 221 | F10: 227 | G10: 32
A11: Unrealized foreign exchange losses/(gains), net | B11: 51 | C11: 85 | D11: 144 | E11: -19 | F11: 24
A12: Losses on sale of PP&E and intangible assets, net | B12: 13 | C12: 16 | D12: 20 | E12: 17 | F12: 20
A13: Other non-cash effects from operating activities | B13: 6 | C13: -8 | D13: -8 | E13: -10 | F13: 22 | G13: 29/30
A14: Operating profit before working capital changes | B14: 3135 | C14: 1966 | D14: 1514 | E14: 2453 | F14: 3190
A15: Change in receivables and other assets | B15: -170 | C15: -820 | D15: 995 | E15: -839 | F15: -562
A16: Change in inventories | B16: 125 | C16: -1901 | D16: 1297 | E16: -500 | F16: -1104
A17: Change in accounts payable and other liabilities | B17: 226 | C17: 721 | D17: -868 | E17: 2024 | F17: -377
A18: Cash generated from operations before taxes | B18: 3316 | C18: -34 | D18: 2938 | E18: 3138 | F18: 1147
A19: Income taxes paid | B19: -444 | C19: -424 | D19: -307 | E19: -236 | F19: -399
A20: Discontinued operations / hyperinflation adj. (net cash effect) | B20: 320 | C20: -85 | D20: 0 | E20: 9 | F20: 3
A21: Cash flows from operating activities | B21: 3192 | C21: -543 | D21: 2630 | E21: 2910 | F21: 751
A23: Investing activities
A24: Purchase of trademarks / other intangible assets | B24: -173 | C24: -191 | D24: -141 | E24: -121 | F24: -114 | G24: 12
A25: Proceeds from sale of intangible assets | B25: 1 | C25: 1 | D25: 1 | E25: 0 | F25: 0
A26: Purchase of property, plant, and equipment | B26: -494 | C26: -504 | D26: -363 | E26: -419 | F26: -363 | G26: 09
A27: Proceeds from sale of property, plant, and equipment | B27: 1 | C27: 1 | D27: 10 | E27: 49 | F27: 4
A28: Proceeds from sale of a disposal group | B28: 12 | C28: 12 | D28: 0 | E28: 100 | F28: 100 | G28: 03
A29: Proceeds from (reimbursement of) disposal of discontinued operations | B29: 177 | C29: 1165 | D29: -19 | E29: 0 | F29: 0 | G29: 03
A30: Change in short-term financial assets | B30: 0 | C30: 0 | D30: -34 | E30: 28 | F30: 0
A31: Change in investments and other long-term assets | B31: 49 | C31: -13 | D31: 57 | E31: -50 | F31: -88
A32: Interest received | B32: 13 | C32: 23 | D32: 39 | E32: 57 | F32: 58
A33: Cash flows from investing activities — discontinued operations | B33: -9 | C33: 0
A34: Cash flows from investing activities | B34: -424 | C34: 495 | D34: -450 | E34: -356 | F34: -404
A36: Financing activities
A37: Repayment of eurobonds | B37: -600 | C37: 0 | D37: -500 | E37: -500 | F37: -500 | G37: 16
A38: Proceeds from issuance of bonds | B38: 0 | C38: 994 | D38: 0 | E38: 0 | F38: 498 | G38: 16
A39: Interest paid | B39: -111 | C39: -140 | D39: -163 | E39: -217 | F39: -220
A40: Repayments of lease liabilities | B40: -572 | C40: -631 | D40: -603 | E40: -656 | F40: -643 | G40: 19
A41: Dividend paid to shareholders of adidas AG | B41: -585 | C41: -610 | D41: -125 | E41: -125 | F41: -357 | G41: 25
A42: Dividend paid to non-controlling interest shareholders | B42: 0 | C42: -22 | D42: -33 | E42: -40 | F42: -42 | G42: 27
A43: Repurchase of treasury shares (incl. share-based payment) | B43: -1032 | C43: -2530 | D43: -29 | E43: -35 | F43: -43 | G43: 25/26
A44: Proceeds from reissuance of treasury shares (share-based payment) | B44: 27 | C44: 25 | D44: 25 | E44: 24 | F44: 39 | G44: 26
A45: Change in short-term borrowings | B45: -79 | C45: -18 | D45: 3 | E45: 3 | F45: 166 | G45: 16
A46: Acquisition of non-controlling interests | B46: 0 | C46: -27 | D46: 0 | E46: -12 | F46: 0 | G46: 27
A47: Cash flows from financing activities — discontinued operations | B47: -39 | C47: -6
A48: Cash flows from financing activities | B48: -2991 | C48: -2963 | D48: -1425 | E48: -1559 | F48: -1103
A50: Effect of exchange rates on cash | B50: 57 | C50: -19 | D50: -40 | E50: 29 | F50: -82
A51: IAS 29 hyperinflation effects / other | D51: -82 | G51: 37
A52: Change in cash and cash equivalents | B52: -165 | C52: -3031 | D52: 633 | E52: 1024 | F52: -838
A53: Cash and cash equivalents at beginning of year | B53: 3994 | C53: 3828 | D53: 798 | E53: 1431 | F53: 2455 | G53: 04
A54: Cash and cash equivalents at end of period | B54: 3828 | C54: 798 | D54: 1431 | E54: 2455 | F54: 1617 | G54: 04

Sheet SCE_Hist
A1: adidas AG — Consolidated Statement of Changes in Equity (summary reconciliation)
A2: EUR millions. Opening/closing balances and TCI are audited constants from the SCE (see Sources_Audited). "Other equity transactions" is the residual of all remaining SCE line items (mainly NCI acquisitions, share cancellations, minor reclassifications) not individually itemized here — see the cited SCE page for the full line-by-line breakdown.
A4: Line item | B4: FY2021A | C4: FY2022A | D4: FY2023A | E4: FY2024A | F4: FY2025A
A5: Total equity, beginning of year | B5: 6691 | C5: 7837 | D5: 5351 | E5: 4925 | F5: 5867
A6: Net income | B6: 2158 | C6: 638 | D6: -14 | E6: 832 | F6: 1385
A7: Other comprehensive income | B7: 573 | C7: 18 | D7: -238 | E7: 283 | F7: -738
A8: Total comprehensive income | B8: =B6+B7 -> 2731 | C8: =C6+C7 -> 656 | D8: =D6+D7 -> -252 | E8: =E6+E7 -> 1115 | F8: =F6+F7 -> 647
A9: Dividends paid (shareholders + non-controlling interests) | B9: -585 | C9: -632 | D9: -158 | E9: -165 | F9: -399
A10: Treasury shares: repurchases, reissuances, cancellations (net) | B10: -1001 | C10: -2481 | D10: 0 | E10: 0 | F10: 0
A11: Equity-settled share-based payment | B11: 1 | C11: -4 | D11: 15 | E11: 5 | F11: 9
A12: Other equity transactions, net (NCI acquisitions/disposals, reclassifications — see SCE PDF page for detail) | B12: 0 | C12: -25 | D12: -31 | E12: -13 | F12: 1
A13: Total equity, end of year (computed) | B13: =B5+B8+B9+B10+B11+B12 -> 7837 | C13: =C5+C8+C9+C10+C11+C12 -> 5351 | D13: =D5+D8+D9+D10+D11+D12 -> 4925 | E13: =E5+E8+E9+E10+E11+E12 -> 5867 | F13: =F5+F8+F9+F10+F11+F12 -> 6125
A14: Total equity, end of year (audited, per Balance Sheet) | B14: 7837 | C14: 5351 | D14: 4925 | E14: 5867 | F14: 6125

Sheet Checks_TieOut
A1: Tie-out checks — audited historical statements (all deltas must be 0 within EUR 1m tolerance for rounding)
A2: MASTER | B2: =IF(COUNTIF(H5:H37,"FAIL")=0,"OK — ALL TIE-OUTS PASS","FAIL") -> OK — ALL TIE-OUTS PASS
A4: Check | B4: FY2021A | C4: FY2022A | D4: FY2023A | E4: FY2024A | F4: FY2025A | H4: Status
A5: IS: Gross profit = Net sales - Cost of sales | B5: =IS_Hist!B5-IS_Hist!B6-IS_Hist!B7 -> 0 | C5: =IS_Hist!C5-IS_Hist!C6-IS_Hist!C7 -> 0 | D5: =IS_Hist!D5-IS_Hist!D6-IS_Hist!D7 -> -1 | E5: =IS_Hist!E5-IS_Hist!E6-IS_Hist!E7 -> -1 | F5: =IS_Hist!F5-IS_Hist!F6-IS_Hist!F7 -> 1 | H5: =IF(AND(ABS(N(B5))<=1,ABS(N(C5))<=1,ABS(N(D5))<=1,ABS(N(E5))<=1,ABS(N(F5))<=1),"PASS","FAIL") -> PASS
A6: IS: Operating profit chain | B6: =IS_Hist!B7+IS_Hist!B8+IS_Hist!B9-IS_Hist!B10-IS_Hist!B19 -> 1 | C6: =IS_Hist!C7+IS_Hist!C8+IS_Hist!C9-IS_Hist!C10-IS_Hist!C19 -> 0 | D6: =IS_Hist!D7+IS_Hist!D8+IS_Hist!D9-IS_Hist!D10-IS_Hist!D19 -> 0 | E6: =IS_Hist!E7+IS_Hist!E8+IS_Hist!E9-IS_Hist!E10-IS_Hist!E19 -> -1 | F6: =IS_Hist!F7+IS_Hist!F8+IS_Hist!F9-IS_Hist!F10-IS_Hist!F19 -> -1 | H6: =IF(AND(ABS(N(B6))<=1,ABS(N(C6))<=1,ABS(N(D6))<=1,ABS(N(E6))<=1,ABS(N(F6))<=1),"PASS","FAIL") -> PASS
A7: IS: Other operating expenses = sum of sub-lines | B7: =SUM(IS_Hist!B13:B17)-IS_Hist!B10 -> 0 | C7: =SUM(IS_Hist!C13:C17)-IS_Hist!C10 -> 0 | D7: =SUM(IS_Hist!D13:D17)-IS_Hist!D10 -> 0 | E7: =SUM(IS_Hist!E13:E17)-IS_Hist!E10 -> -1 | F7: =SUM(IS_Hist!F13:F17)-IS_Hist!F10 -> 0 | H7: =IF(AND(ABS(N(B7))<=1,ABS(N(C7))<=1,ABS(N(D7))<=1,ABS(N(E7))<=1,ABS(N(F7))<=1),"PASS","FAIL") -> PASS
A8: IS: Income before taxes = OP + fin income - fin exp | B8: =IS_Hist!B19+IS_Hist!B20-IS_Hist!B21-IS_Hist!B22 -> 0 | C8: =IS_Hist!C19+IS_Hist!C20-IS_Hist!C21-IS_Hist!C22 -> 0 | D8: =IS_Hist!D19+IS_Hist!D20-IS_Hist!D21-IS_Hist!D22 -> 0 | E8: =IS_Hist!E19+IS_Hist!E20-IS_Hist!E21-IS_Hist!E22 -> 0 | F8: =IS_Hist!F19+IS_Hist!F20-IS_Hist!F21-IS_Hist!F22 -> 0 | H8: =IF(AND(ABS(N(B8))<=1,ABS(N(C8))<=1,ABS(N(D8))<=1,ABS(N(E8))<=1,ABS(N(F8))<=1),"PASS","FAIL") -> PASS
A9: IS: Net income (continuing) = PBT - tax | B9: =IS_Hist!B22-IS_Hist!B23-IS_Hist!B24 -> 0 | C9: =IS_Hist!C22-IS_Hist!C23-IS_Hist!C24 -> 0 | D9: =IS_Hist!D22-IS_Hist!D23-IS_Hist!D24 -> -1 | E9: =IS_Hist!E22-IS_Hist!E23-IS_Hist!E24 -> 0 | F9: =IS_Hist!F22-IS_Hist!F23-IS_Hist!F24 -> 0 | H9: =IF(AND(ABS(N(B9))<=1,ABS(N(C9))<=1,ABS(N(D9))<=1,ABS(N(E9))<=1,ABS(N(F9))<=1),"PASS","FAIL") -> PASS
A10: IS: Net income = continuing + discontinued | B10: =IS_Hist!B24+IS_Hist!B25-IS_Hist!B26 -> 0 | C10: =IS_Hist!C24+IS_Hist!C25-IS_Hist!C26 -> 0 | D10: =IS_Hist!D24+IS_Hist!D25-IS_Hist!D26 -> 0 | E10: =IS_Hist!E24+IS_Hist!E25-IS_Hist!E26 -> 0 | F10: =IS_Hist!F24+IS_Hist!F25-IS_Hist!F26 -> 0 | H10: =IF(AND(ABS(N(B10))<=1,ABS(N(C10))<=1,ABS(N(D10))<=1,ABS(N(E10))<=1,ABS(N(F10))<=1),"PASS","FAIL") -> PASS
A11: IS: Net income = shareholders + NCI | B11: =IS_Hist!B29+IS_Hist!B30-IS_Hist!B26 -> 0 | C11: =IS_Hist!C29+IS_Hist!C30-IS_Hist!C26 -> 0 | D11: =IS_Hist!D29+IS_Hist!D30-IS_Hist!D26 -> 0 | E11: =IS_Hist!E29+IS_Hist!E30-IS_Hist!E26 -> 0 | F11: =IS_Hist!F29+IS_Hist!F30-IS_Hist!F26 -> 0 | H11: =IF(AND(ABS(N(B11))<=1,ABS(N(C11))<=1,ABS(N(D11))<=1,ABS(N(E11))<=1,ABS(N(F11))<=1),"PASS","FAIL") -> PASS
A12: CI: OCI = subtotal(not reclass.) + subtotal(may reclass.) | B12: =CI_Hist!B9+CI_Hist!B16-CI_Hist!B18 -> 0 | C12: =CI_Hist!C9+CI_Hist!C16-CI_Hist!C18 -> 0 | D12: =CI_Hist!D9+CI_Hist!D16-CI_Hist!D18 -> 0 | E12: =CI_Hist!E9+CI_Hist!E16-CI_Hist!E18 -> 0 | F12: =CI_Hist!F9+CI_Hist!F16-CI_Hist!F18 -> 0 | H12: =IF(AND(ABS(N(B12))<=1,ABS(N(C12))<=1,ABS(N(D12))<=1,ABS(N(E12))<=1,ABS(N(F12))<=1),"PASS","FAIL") -> PASS
A13: CI: TCI = NI + OCI | B13: =CI_Hist!B5+CI_Hist!B18-CI_Hist!B19 -> 0 | C13: =CI_Hist!C5+CI_Hist!C18-CI_Hist!C19 -> 0 | D13: =CI_Hist!D5+CI_Hist!D18-CI_Hist!D19 -> 0 | E13: =CI_Hist!E5+CI_Hist!E18-CI_Hist!E19 -> 0 | F13: =CI_Hist!F5+CI_Hist!F18-CI_Hist!F19 -> 0 | H13: =IF(AND(ABS(N(B13))<=1,ABS(N(C13))<=1,ABS(N(D13))<=1,ABS(N(E13))<=1,ABS(N(F13))<=1),"PASS","FAIL") -> PASS
A14: CI: TCI = shareholders + NCI | B14: =CI_Hist!B22+CI_Hist!B23-CI_Hist!B19 -> 0 | C14: =CI_Hist!C22+CI_Hist!C23-CI_Hist!C19 -> 1 | D14: =CI_Hist!D22+CI_Hist!D23-CI_Hist!D19 -> 0 | E14: =CI_Hist!E22+CI_Hist!E23-CI_Hist!E19 -> 0 | F14: =CI_Hist!F22+CI_Hist!F23-CI_Hist!F19 -> 0 | H14: =IF(AND(ABS(N(B14))<=1,ABS(N(C14))<=1,ABS(N(D14))<=1,ABS(N(E14))<=1,ABS(N(F14))<=1),"PASS","FAIL") -> PASS
A15: X: CI net income = IS net income | B15: =CI_Hist!B5-IS_Hist!B26 -> 0 | C15: =CI_Hist!C5-IS_Hist!C26 -> 0 | D15: =CI_Hist!D5-IS_Hist!D26 -> 0 | E15: =CI_Hist!E5-IS_Hist!E26 -> 0 | F15: =CI_Hist!F5-IS_Hist!F26 -> 0 | H15: =IF(AND(ABS(N(B15))<=1,ABS(N(C15))<=1,ABS(N(D15))<=1,ABS(N(E15))<=1,ABS(N(F15))<=1),"PASS","FAIL") -> PASS
A16: BS: Total current assets = sum of components | B16: =SUM(BS_Hist!B7:B14)-BS_Hist!B15 -> -1 | C16: =SUM(BS_Hist!C7:C14)-BS_Hist!C15 -> 0 | D16: =SUM(BS_Hist!D7:D14)-BS_Hist!D15 -> 1 | E16: =SUM(BS_Hist!E7:E14)-BS_Hist!E15 -> 1 | F16: =SUM(BS_Hist!F7:F14)-BS_Hist!F15 -> -1 | H16: =IF(AND(ABS(N(B16))<=1,ABS(N(C16))<=1,ABS(N(D16))<=1,ABS(N(E16))<=1,ABS(N(F16))<=1),"PASS","FAIL") -> PASS
A17: BS: Total non-current assets = sum of components | B17: =SUM(BS_Hist!B17:B24)-BS_Hist!B25 -> -1 | C17: =SUM(BS_Hist!C17:C24)-BS_Hist!C25 -> -1 | D17: =SUM(BS_Hist!D17:D24)-BS_Hist!D25 -> -1 | E17: =SUM(BS_Hist!E17:E24)-BS_Hist!E25 -> -1 | F17: =SUM(BS_Hist!F17:F24)-BS_Hist!F25 -> 1 | H17: =IF(AND(ABS(N(B17))<=1,ABS(N(C17))<=1,ABS(N(D17))<=1,ABS(N(E17))<=1,ABS(N(F17))<=1),"PASS","FAIL") -> PASS
A18: BS: Total assets = CA + NCA | B18: =BS_Hist!B15+BS_Hist!B25-BS_Hist!B27 -> 0 | C18: =BS_Hist!C15+BS_Hist!C25-BS_Hist!C27 -> -1 | D18: =BS_Hist!D15+BS_Hist!D25-BS_Hist!D27 -> 0 | E18: =BS_Hist!E15+BS_Hist!E25-BS_Hist!E27 -> 0 | F18: =BS_Hist!F15+BS_Hist!F25-BS_Hist!F27 -> 0 | H18: =IF(AND(ABS(N(B18))<=1,ABS(N(C18))<=1,ABS(N(D18))<=1,ABS(N(E18))<=1,ABS(N(F18))<=1),"PASS","FAIL") -> PASS
A19: BS: Total current liabilities = sum of components | B19: =SUM(BS_Hist!B31:B39)-BS_Hist!B40 -> 0 | C19: =SUM(BS_Hist!C31:C39)-BS_Hist!C40 -> 0 | D19: =SUM(BS_Hist!D31:D39)-BS_Hist!D40 -> 0 | E19: =SUM(BS_Hist!E31:E39)-BS_Hist!E40 -> 0 | F19: =SUM(BS_Hist!F31:F39)-BS_Hist!F40 -> -1 | H19: =IF(AND(ABS(N(B19))<=1,ABS(N(C19))<=1,ABS(N(D19))<=1,ABS(N(E19))<=1,ABS(N(F19))<=1),"PASS","FAIL") -> PASS
A20: BS: Total non-current liabilities = sum of components | B20: =SUM(BS_Hist!B42:B49)-BS_Hist!B50 -> 1 | C20: =SUM(BS_Hist!C42:C49)-BS_Hist!C50 -> -1 | D20: =SUM(BS_Hist!D42:D49)-BS_Hist!D50 -> 0 | E20: =SUM(BS_Hist!E42:E49)-BS_Hist!E50 -> 1 | F20: =SUM(BS_Hist!F42:F49)-BS_Hist!F50 -> 0 | H20: =IF(AND(ABS(N(B20))<=1,ABS(N(C20))<=1,ABS(N(D20))<=1,ABS(N(E20))<=1,ABS(N(F20))<=1),"PASS","FAIL") -> PASS
A21: BS: Total liabilities = CL + NCL | B21: =BS_Hist!B40+BS_Hist!B50-BS_Hist!B52 -> 0 | C21: =BS_Hist!C40+BS_Hist!C50-BS_Hist!C52 -> 0 | D21: =BS_Hist!D40+BS_Hist!D50-BS_Hist!D52 -> 0 | E21: =BS_Hist!E40+BS_Hist!E50-BS_Hist!E52 -> 0 | F21: =BS_Hist!F40+BS_Hist!F50-BS_Hist!F52 -> 0 | H21: =IF(AND(ABS(N(B21))<=1,ABS(N(C21))<=1,ABS(N(D21))<=1,ABS(N(E21))<=1,ABS(N(F21))<=1),"PASS","FAIL") -> PASS
A22: BS: Shareholders’ equity = sum of components | B22: =SUM(BS_Hist!B55:B57)-BS_Hist!B58 -> 1 | C22: =SUM(BS_Hist!C55:C57)-BS_Hist!C58 -> 1 | D22: =SUM(BS_Hist!D55:D57)-BS_Hist!D58 -> 1 | E22: =SUM(BS_Hist!E55:E57)-BS_Hist!E58 -> 0 | F22: =SUM(BS_Hist!F55:F57)-BS_Hist!F58 -> 0 | H22: =IF(AND(ABS(N(B22))<=1,ABS(N(C22))<=1,ABS(N(D22))<=1,ABS(N(E22))<=1,ABS(N(F22))<=1),"PASS","FAIL") -> PASS
A23: BS: Total equity = shareholders’ equity + NCI | B23: =BS_Hist!B58+BS_Hist!B59-BS_Hist!B60 -> 0 | C23: =BS_Hist!C58+BS_Hist!C59-BS_Hist!C60 -> 0 | D23: =BS_Hist!D58+BS_Hist!D59-BS_Hist!D60 -> 0 | E23: =BS_Hist!E58+BS_Hist!E59-BS_Hist!E60 -> 1 | F23: =BS_Hist!F58+BS_Hist!F59-BS_Hist!F60 -> 0 | H23: =IF(AND(ABS(N(B23))<=1,ABS(N(C23))<=1,ABS(N(D23))<=1,ABS(N(E23))<=1,ABS(N(F23))<=1),"PASS","FAIL") -> PASS
A24: BS: Total liabilities and equity = TL + TE | B24: =BS_Hist!B52+BS_Hist!B60-BS_Hist!B62 -> -1 | C24: =BS_Hist!C52+BS_Hist!C60-BS_Hist!C62 -> 0 | D24: =BS_Hist!D52+BS_Hist!D60-BS_Hist!D62 -> 0 | E24: =BS_Hist!E52+BS_Hist!E60-BS_Hist!E62 -> -1 | F24: =BS_Hist!F52+BS_Hist!F60-BS_Hist!F62 -> 0 | H24: =IF(AND(ABS(N(B24))<=1,ABS(N(C24))<=1,ABS(N(D24))<=1,ABS(N(E24))<=1,ABS(N(F24))<=1),"PASS","FAIL") -> PASS
A25: BS: Balance sheet balances (TA - TL&E) | B25: =BS_Hist!B27-BS_Hist!B62 -> 0 | C25: =BS_Hist!C27-BS_Hist!C62 -> 0 | D25: =BS_Hist!D27-BS_Hist!D62 -> 0 | E25: =BS_Hist!E27-BS_Hist!E62 -> 0 | F25: =BS_Hist!F27-BS_Hist!F62 -> 0 | H25: =IF(AND(ABS(N(B25))<=1,ABS(N(C25))<=1,ABS(N(D25))<=1,ABS(N(E25))<=1,ABS(N(F25))<=1),"PASS","FAIL") -> PASS
A26: CF: Operating profit before WC changes = sum of adjustments | B26: =SUM(CF_Hist!B6:B13)-CF_Hist!B14 -> 0 | C26: =SUM(CF_Hist!C6:C13)-CF_Hist!C14 -> 1 | D26: =SUM(CF_Hist!D6:D13)-CF_Hist!D14 -> 0 | E26: =SUM(CF_Hist!E6:E13)-CF_Hist!E14 -> 0 | F26: =SUM(CF_Hist!F6:F13)-CF_Hist!F14 -> 0 | H26: =IF(AND(ABS(N(B26))<=1,ABS(N(C26))<=1,ABS(N(D26))<=1,ABS(N(E26))<=1,ABS(N(F26))<=1),"PASS","FAIL") -> PASS
A27: CF: Cash generated before taxes = OP before WC + WC changes | B27: =CF_Hist!B14+SUM(CF_Hist!B15:B17)-CF_Hist!B18 -> 0 | C27: =CF_Hist!C14+SUM(CF_Hist!C15:C17)-CF_Hist!C18 -> 0 | D27: =CF_Hist!D14+SUM(CF_Hist!D15:D17)-CF_Hist!D18 -> 0 | E27: =CF_Hist!E14+SUM(CF_Hist!E15:E17)-CF_Hist!E18 -> 0 | F27: =CF_Hist!F14+SUM(CF_Hist!F15:F17)-CF_Hist!F18 -> 0 | H27: =IF(AND(ABS(N(B27))<=1,ABS(N(C27))<=1,ABS(N(D27))<=1,ABS(N(E27))<=1,ABS(N(F27))<=1),"PASS","FAIL") -> PASS
A28: CF: CFO = pre-tax cash + tax paid + discontinued/hyperinflation adj. | B28: =CF_Hist!B18+CF_Hist!B19+CF_Hist!B20-CF_Hist!B21 -> 0 | C28: =CF_Hist!C18+CF_Hist!C19+CF_Hist!C20-CF_Hist!C21 -> 0 | D28: =CF_Hist!D18+CF_Hist!D19+CF_Hist!D20-CF_Hist!D21 -> 1 | E28: =CF_Hist!E18+CF_Hist!E19+CF_Hist!E20-CF_Hist!E21 -> 1 | F28: =CF_Hist!F18+CF_Hist!F19+CF_Hist!F20-CF_Hist!F21 -> 0 | H28: =IF(AND(ABS(N(B28))<=1,ABS(N(C28))<=1,ABS(N(D28))<=1,ABS(N(E28))<=1,ABS(N(F28))<=1),"PASS","FAIL") -> PASS
A29: CF: CFI = sum of investing lines (tol. ±2m — multi-line IFRS rounding) | B29: =SUM(CF_Hist!B24:B33)-CF_Hist!B34 -> 1 | C29: =SUM(CF_Hist!C24:C33)-CF_Hist!C34 -> -1 | D29: =SUM(CF_Hist!D24:D33)-CF_Hist!D34 -> 0 | E29: =SUM(CF_Hist!E24:E33)-CF_Hist!E34 -> 0 | F29: =SUM(CF_Hist!F24:F33)-CF_Hist!F34 -> 1 | H29: =IF(AND(ABS(N(B29))<=2,ABS(N(C29))<=2,ABS(N(D29))<=2,ABS(N(E29))<=2,ABS(N(F29))<=2),"PASS","FAIL") -> PASS
A30: CF: CFF = sum of financing lines (tol. ±2m — multi-line IFRS rounding) | B30: =SUM(CF_Hist!B37:B47)-CF_Hist!B48 -> 0 | C30: =SUM(CF_Hist!C37:C47)-CF_Hist!C48 -> -2 | D30: =SUM(CF_Hist!D37:D47)-CF_Hist!D48 -> 0 | E30: =SUM(CF_Hist!E37:E47)-CF_Hist!E48 -> 1 | F30: =SUM(CF_Hist!F37:F47)-CF_Hist!F48 -> 1 | H30: =IF(AND(ABS(N(B30))<=2,ABS(N(C30))<=2,ABS(N(D30))<=2,ABS(N(E30))<=2,ABS(N(F30))<=2),"PASS","FAIL") -> PASS
A31: CF: Change in cash = CFO + CFI + CFF + FX + other | B31: =CF_Hist!B21+CF_Hist!B34+CF_Hist!B48+CF_Hist!B50+N(CF_Hist!B51)-CF_Hist!B52 -> -1 | C31: =CF_Hist!C21+CF_Hist!C34+CF_Hist!C48+CF_Hist!C50+N(CF_Hist!C51)-CF_Hist!C52 -> 1 | D31: =CF_Hist!D21+CF_Hist!D34+CF_Hist!D48+CF_Hist!D50+N(CF_Hist!D51)-CF_Hist!D52 -> 0 | E31: =CF_Hist!E21+CF_Hist!E34+CF_Hist!E48+CF_Hist!E50+N(CF_Hist!E51)-CF_Hist!E52 -> 0 | F31: =CF_Hist!F21+CF_Hist!F34+CF_Hist!F48+CF_Hist!F50+N(CF_Hist!F51)-CF_Hist!F52 -> 0 | H31: =IF(AND(ABS(N(B31))<=1,ABS(N(C31))<=1,ABS(N(D31))<=1,ABS(N(E31))<=1,ABS(N(F31))<=1),"PASS","FAIL") -> PASS
A32: CF: End cash = beginning + change | B32: =CF_Hist!B53+CF_Hist!B52-CF_Hist!B54 -> 1 | C32: =CF_Hist!C53+CF_Hist!C52-CF_Hist!C54 -> -1 | D32: =CF_Hist!D53+CF_Hist!D52-CF_Hist!D54 -> 0 | E32: =CF_Hist!E53+CF_Hist!E52-CF_Hist!E54 -> 0 | F32: =CF_Hist!F53+CF_Hist!F52-CF_Hist!F54 -> 0 | H32: =IF(AND(ABS(N(B32))<=1,ABS(N(C32))<=1,ABS(N(D32))<=1,ABS(N(E32))<=1,ABS(N(F32))<=1),"PASS","FAIL") -> PASS
A33: X: CF end cash = BS cash | B33: =CF_Hist!B54-BS_Hist!B7 -> 0 | C33: =CF_Hist!C54-BS_Hist!C7 -> 0 | D33: =CF_Hist!D54-BS_Hist!D7 -> 0 | E33: =CF_Hist!E54-BS_Hist!E7 -> 0 | F33: =CF_Hist!F54-BS_Hist!F7 -> 0 | H33: =IF(AND(ABS(N(B33))<=1,ABS(N(C33))<=1,ABS(N(D33))<=1,ABS(N(E33))<=1,ABS(N(F33))<=1),"PASS","FAIL") -> PASS
A34: X: SCE closing equity (computed) = audited closing equity | B34: =SCE_Hist!B13-SCE_Hist!B14 -> 0 | C34: =SCE_Hist!C13-SCE_Hist!C14 -> 0 | D34: =SCE_Hist!D13-SCE_Hist!D14 -> 0 | E34: =SCE_Hist!E13-SCE_Hist!E14 -> 0 | F34: =SCE_Hist!F13-SCE_Hist!F14 -> 0 | H34: =IF(AND(ABS(N(B34))<=1,ABS(N(C34))<=1,ABS(N(D34))<=1,ABS(N(E34))<=1,ABS(N(F34))<=1),"PASS","FAIL") -> PASS
A35: X: SCE closing equity (audited) = BS total equity | B35: =SCE_Hist!B14-BS_Hist!B60 -> 0 | C35: =SCE_Hist!C14-BS_Hist!C60 -> 0 | D35: =SCE_Hist!D14-BS_Hist!D60 -> 0 | E35: =SCE_Hist!E14-BS_Hist!E60 -> 0 | F35: =SCE_Hist!F14-BS_Hist!F60 -> 0 | H35: =IF(AND(ABS(N(B35))<=1,ABS(N(C35))<=1,ABS(N(D35))<=1,ABS(N(E35))<=1,ABS(N(F35))<=1),"PASS","FAIL") -> PASS
A36: X: SCE net income = IS net income | B36: =SCE_Hist!B6-IS_Hist!B26 -> 0 | C36: =SCE_Hist!C6-IS_Hist!C26 -> 0 | D36: =SCE_Hist!D6-IS_Hist!D26 -> 0 | E36: =SCE_Hist!E6-IS_Hist!E26 -> 0 | F36: =SCE_Hist!F6-IS_Hist!F26 -> 0 | H36: =IF(AND(ABS(N(B36))<=1,ABS(N(C36))<=1,ABS(N(D36))<=1,ABS(N(E36))<=1,ABS(N(F36))<=1),"PASS","FAIL") -> PASS
A37: CF: Beginning cash = prior-year end cash (FY22-FY25) | C37: =CF_Hist!C53-CF_Hist!B54 -> 0 | D37: =CF_Hist!D53-CF_Hist!C54 -> 0 | E37: =CF_Hist!E53-CF_Hist!D54 -> 0 | F37: =CF_Hist!F53-CF_Hist!E54 -> 0 | H37: =IF(AND(ABS(N(C37))<=1,ABS(N(D37))<=1,ABS(N(E37))<=1,ABS(N(F37))<=1),"PASS","FAIL") -> PASS

Sheet Sources_Audited
A1: Audited source register — adidas AG consolidated financial statements (report.adidas-group.com annual-report PDFs, downloaded 2026-07-21)
A3: Model year | B3: Source file (local copy kept by the maintainer) | C3: BS phys. pg. | D3: IS phys. pg. | E3: CI phys. pg. | F3: SCE phys. pg. | G3: CF phys. pg. | H3: Notes
A4: FY2021A | B4: FY2021_cons-financial-statements-adidas-ar21.pdf | C4: 2-3 | D4: 4 | E4: 5 | F4: 6 | G4: 7-8
A5: FY2022A | B5: FY2022_cons-financial-statements-adidas-ar22.pdf | C5: 2-3 | D5: 4-5 | E5: 6 | F5: 7-8 | G5: 9-10
A6: FY2023A | B6: FY2023_cons-financial-statements-adidas-ar23.pdf | C6: 2-3 | D6: 4 | E6: 5 | F6: 6-7 | G6: 8-9
A7: FY2024A | B7: FY2024_cons-financial-statements-adidas-ar24.pdf | C7: 2-3 | D7: 4 | E7: 5 | F7: 6 | G7: 7-8
A8: FY2025A | B8: FY2025_cons-financial-statements-adidas-ar25.pdf | C8: 2-3 | D8: 4 | E8: 5 | F8: 6 | G8: 7
A10: Physical PDF page = page order counted from page 1 of the standalone PDF file (verified via pdftotext form-feed page breaks + printed page-footer cross-check), NOT the printed running page number in the header/footer (Ola-1 lesson).
A11: Each year’s figures are the CURRENT-year column from that year’s own report (as originally published for that fiscal year), cross-checked against the following year’s comparative column. Where the two disagree the discrepancy is a documented restatement, not a transcription error — see notes below.
A12: Known restatement: FY2022 cash flow from operating activities is EUR (458)m (continuing) / (543)m (incl. discontinued) per adidas’ own FY2022 report; the FY2023 report’s FY2022 comparative column instead shows (394)m / (479)m. This workbook uses the FY2022-report figure (-458/-543, i.e. total -543 as reported "Cash flows from operating activities") for consistency (each year sourced from its own report).
A13: Known restatement: FY2023 cash flow from operating activities is EUR 2,630m per adidas’ own FY2023 report; the FY2024 report’s FY2023 comparative shows EUR 2,550m, both footnoted "Prior year adjusted due to Hyperinflation accounting" (IAS 29, hyperinflationary economies e.g. Ghana/Argentina/Turkey reclassification). This workbook uses the FY2023-report figure (2,630) for CF_Hist. NOTE: the pre-existing Ola-1 Historical!D9 tab uses the later-restated 2,550 figure sourced from adidas’ Financial Highlights page — both are legitimately adidas-published numbers on different bases; this is a documented basis difference, not an error in either sheet.
A14: BS lines "Short-term financial assets" and "Assets/Liabilities classified as held for sale" are blank in years where adidas did not present them (introduced FY2023; Reebok disposal group only FY2021) — blanks are intentional, not missing data.
A15: SCE_Hist is a summary reconciliation (opening/closing/TCI = audited constants; dividends, treasury-share transactions, and share-based payment = audited constants; "Other equity transactions, net" is the computed residual of all remaining SCE line items, mainly NCI acquisitions/disposals — full line-by-line detail is in the cited SCE PDF pages, not reproduced here.
A16: Notes PDFs (FYxxxx_notes-adidas-arYY.pdf) were reviewed for segment/geography detail (Sector_KPIs) but were not required for primary-statement figures, which are fully covered by the standalone Consolidated Financial Statements PDFs cited above.

Sheet Source_Register
A1: Source_Register — pointer
A3: Primary audited source detail for the statement-grade elevation (Ola 2, run 24e4a1f1) lives in the Sources_Audited sheet (per-year file + physical-page citations for BS/IS/CI/SCE/CF). The pre-existing Sources tab (Ola 1, financial-highlights-page citations) is preserved unmodified.

Sheet Forecast_IG
A1: adidas AG — 5-year driver-built forecast (Base/Bull/Bear), anchored to FY2025A
A2: EUR millions unless noted. ASSUMPTION-driven (not published); scenario select in B4 (1=Base, 2=Bull, 3=Bear). Rationale: Base assumes continuation of the FY2023-25 margin-recovery trend (gross margin recovered from 47.5% FY23 to 51.6% FY25 post-Yeezy-inventory unwind) at a decelerating mid-single-digit revenue growth rate consistent with adidas’ multi-year guidance cadence; Bull/Bear flex growth +/-3pp and gross margin +/-1.5pp vs Base. This is a forecast scaffold, not a published fact — treat as PARTIAL/indicative pending management-guidance-anchored refresh.
A4: Scenario (1=Base,2=Bull,3=Bear) | B4: 1
A6: Driver | B6: FY2026E | C6: FY2027E | D6: FY2028E | E6: FY2029E | F6: FY2030E
A7: Revenue growth % — Base | B7: 0.07 | C7: 0.06 | D7: 0.055 | E7: 0.05 | F7: 0.045
A8: Revenue growth % — Bull | B8: 0.1 | C8: 0.09 | D8: 0.08 | E8: 0.07 | F8: 0.065
A9: Revenue growth % — Bear | B9: 0.03 | C9: 0.02 | D9: 0.02 | E9: 0.015 | F9: 0.015
A10: Gross margin % — Base | B10: 0.52 | C10: 0.523 | D10: 0.526 | E10: 0.528 | F10: 0.53
A11: Gross margin % — Bull | B11: 0.53 | C11: 0.535 | D11: 0.538 | E11: 0.54 | F11: 0.542
A12: Gross margin % — Bear | B12: 0.505 | C12: 0.5 | D12: 0.498 | E12: 0.495 | F12: 0.493
A13: OpEx (royalty/other inc net of other opex) % of sales — Base | B13: 0.435 | C13: 0.43 | D13: 0.425 | E13: 0.42 | F13: 0.418
A14: OpEx % of sales — Bull | B14: 0.42 | C14: 0.412 | D14: 0.405 | E14: 0.4 | F14: 0.397
A15: OpEx % of sales — Bear | B15: 0.45 | C15: 0.448 | D15: 0.445 | E15: 0.443 | F15: 0.44
A16: Net financial expense % of sales (all scenarios) | B16: 0.01 | C16: 0.009 | D16: 0.008 | E16: 0.008 | F16: 0.007
A17: Effective tax rate (all scenarios) | B17: 0.25 | C17: 0.25 | D17: 0.25 | E17: 0.25 | F17: 0.25
A18: Capex % of sales (all scenarios) | B18: 0.02 | C18: 0.02 | D18: 0.02 | E18: 0.02 | F18: 0.02
A19: D&A % of sales (all scenarios) | B19: 0.048 | C19: 0.047 | D19: 0.046 | E19: 0.045 | F19: 0.045
A22: Projection (selected scenario) | B22: FY2026E | C22: FY2027E | D22: FY2028E | E22: FY2029E | F22: FY2030E
A23: Revenue | B23: =IS_Hist!F5*(1+CHOOSE($B$4,B7,B8,B9)) -> 26547.77 | C23: =B23*(1+CHOOSE($B$4,C7,C8,C9)) -> 28140.636 | D23: =C23*(1+CHOOSE($B$4,D7,D8,D9)) -> 29688.371 | E23: =D23*(1+CHOOSE($B$4,E7,E8,E9)) -> 31172.79 | F23: =E23*(1+CHOOSE($B$4,F7,F8,F9)) -> 32575.565
A24: Gross profit | B24: =B23*CHOOSE($B$4,B10,B11,B12) -> 13804.84 | C24: =C23*CHOOSE($B$4,C10,C11,C12) -> 14717.553 | D24: =D23*CHOOSE($B$4,D10,D11,D12) -> 15616.083 | E24: =E23*CHOOSE($B$4,E10,E11,E12) -> 16459.233 | F24: =F23*CHOOSE($B$4,F10,F11,F12) -> 17265.05
A25: Operating profit (proxy: GP - OpEx) | B25: =B23*(CHOOSE($B$4,B10,B11,B12)-CHOOSE($B$4,B13,B14,B15)) -> 2256.5605 | C25: =C23*(CHOOSE($B$4,C10,C11,C12)-CHOOSE($B$4,C13,C14,C15)) -> 2617.0792 | D25: =D23*(CHOOSE($B$4,D10,D11,D12)-CHOOSE($B$4,D13,D14,D15)) -> 2998.5255 | E25: =E23*(CHOOSE($B$4,E10,E11,E12)-CHOOSE($B$4,E13,E14,E15)) -> 3366.6613 | F25: =F23*(CHOOSE($B$4,F10,F11,F12)-CHOOSE($B$4,F13,F14,F15)) -> 3648.4633
A26: Net financial expense | B26: =B23*B16 -> 265.4777 | C26: =C23*C16 -> 253.26573 | D26: =D23*D16 -> 237.50697 | E26: =E23*E16 -> 249.38232 | F26: =F23*F16 -> 228.02896
A27: Income before taxes | B27: =B25-B26 -> 1991.0828 | C27: =C25-C26 -> 2363.8134 | D27: =D25-D26 -> 2761.0185 | E27: =E25-E26 -> 3117.279 | F27: =F25-F26 -> 3420.4344
A28: Income taxes | B28: =B27*B17 -> 497.77069 | C28: =C27*C17 -> 590.95336 | D28: =D27*D17 -> 690.25463 | E28: =E27*E17 -> 779.31974 | F28: =F27*F17 -> 855.10859
A29: Net income (proxy) | B29: =B27-B28 -> 1493.3121 | C29: =C27-C28 -> 1772.8601 | D29: =D27-D28 -> 2070.7639 | E29: =E27-E28 -> 2337.9592 | F29: =F27-F28 -> 2565.3258
A30: D&A | B30: =B23*B19 -> 1274.293 | C30: =C23*C19 -> 1322.6099 | D30: =D23*D19 -> 1365.6651 | E30: =E23*E19 -> 1402.7755 | F30: =F23*F19 -> 1465.9004
A31: Capex | B31: =B23*B18 -> 530.9554 | C31: =C23*C18 -> 562.81272 | D31: =D23*D18 -> 593.76742 | E31: =E23*E18 -> 623.4558 | F31: =F23*F18 -> 651.51131
A32: Unlevered FCF proxy (NI + D&A - Capex) | B32: =B29+B30-B31 -> 2236.6496 | C32: =C29+C30-C31 -> 2532.6573 | D32: =D29+D30-D31 -> 2842.6615 | E32: =E29+E30-E31 -> 3117.279 | F32: =F29+F30-F31 -> 3379.7149

Sheet Claude Code Log
A1: Turn # | B1: Date | C1: User Request | D1: Action Taken | E1: Details | F1: Outcome
A2: 1 | B2: 46324.359 | C2: Prepare a public model copy | D2: Remove local paths and private build references; preserve financial formulas and inputs | E2: Agent run with MOG as the tool, checked by guard v1. The guard measured every sheet before and after the run. Changed: 00_Cover: 1 cell written, at B16; Change_Log: 2 cells written, at F5, B10; Sources_Audited: 1 cell written, at B3. Agent: OpenFinmods export | F2: Compare against source and review public copy
