Workbook

Sheet 00_Cover
A1: Anthropic, PBC | Financial model: statements as filed in the Form S-1, forecast 2026E-2035E, valuation and credit
A2: Built 27 Oct 2026 from the Form S-1 filed with the SEC on 26 Oct 2026 (CIK 0002130357, accession 0001628280-26-067168).
A4: What this workbook holds
A5: Every line of the statements in the S-1: fiscal 2023 to 2025 (audited) and the six months to 30 June 2025 and 2026 (unaudited).
A6: Quarterly results, revenue by pricing model and region, costs by function, non-GAAP measures and the capital structure.
A7: Forecast 2026E-2035E with Base, Bull and Bear (switch: Assumptions!C5); valuation (DCF, comparables, funding marks, reverse DCF); credit view.
A8: Reference price: the Series H price in the S-1, US$589.0095 per preferred share = US$58.90 per common share. No IPO price exists yet.
A9: How to read it
A10: Units: USD millions, except per-share amounts (USD) and share counts (stated on each sheet).
A11: Signs follow the filing. A number in parentheses in the filing is negative here.
A12: Blue numbers are typed from the S-1 or are inputs. Black numbers are formulas. Green numbers link to another sheet.
A13: Column M on the year sheets is for your comments. Column N shows the source or the derivation.
A14: The thin vertical line separates actual and forecast columns.
A16: Master check (all checks on the Checks sheet) | C16: =Checks!C4 -> OK
A18: Key outputs (active scenario unless stated) | C18: Value
A19: Active scenario | C19: =Assumptions!$C$6 -> Base
A20: Series H price per common share (USD) | C20: =Market_Package!B10 -> 58.90095
A21: DCF value per share, perpetuity (USD) | C21: =DCF!C33 -> 80.416348
A22: Against the Series H price | C22: =DCF!C35 -> 0.365281
A23: Probability-weighted DCF value, Bear 25% / Base 50% / Bull 25% (USD) | C23: =Valuation!C52 -> 82.499139
A24: Revenue CAGR 2026E-2035E the Series H price needs (Base) | C24: =Valuation!C36 -> 0.24482088
A25: Revenue 2026E (USD m) | C25: =Forecast_3Stmt!C7 -> 54786
A26: Revenue 2030E (USD m) | C26: =Forecast_3Stmt!G7 -> 322620.29
A27: Fully diluted shares (millions) | C27: =Cap_Table!B47 -> 16281.166
A29: Sheet | B29: What it shows
A30: IS_Hist | B30: Statements of operations as filed, with tie-out checks
A31: CI_Hist | B31: Statements of comprehensive loss as filed
A32: BS_Hist | B32: Balance sheets as filed (31 Dec 2024, 31 Dec 2025, 30 Jun 2026)
A33: CF_Hist | B33: Statements of cash flows as filed
A34: SCE_Hist | B34: Statements of preferred stock and stockholders' deficit as filed
A35: Quarterly_Hist | B35: Six quarters to Q2 2026 and adjusted operating income
A36: Revenue_Hist | B36: Revenue by pricing model and region, customers, costs by function, non-GAAP, key metrics, the Q3 2026 floor
A37: Cap_Table | B37: Shares outstanding, preferred as converted, options, RSUs, notes; fully diluted count; Series H price
A38: Assumptions | B38: Every forecast input: Base, Bull, Bear and the switch (C5)
A39: Interim_Bridge | B39: 2026E = six months actual + second-half estimate; IPO conversion
A40: Schedules | B40: Capex and depreciation, loss carryforwards and taxes, working capital, unlevered free cash flow
... A51: Claude Code Log | B51: Log of every scripted write

Sheet IS_Hist
A1: Anthropic, PBC | Consolidated statements of operations, as filed in the Form S-1
A2: USD millions, except per-share amounts (USD) and share counts (thousands). Fiscal years audited; six-month periods unaudited. Source: Form S-1, 26 Oct 2026, page F-7.
A4: Fiscal year ends 31 December | B4: 2023A | C4: 2024A | D4: 2025A | E4: 6M 2025A | F4: 6M 2026A | M4: Comentarios FG | N4: Source / derivation
A6: Revenue | B6: 41 | C6: 386 | D6: 4585 | E6: 1163 | F6: 16286 | N6: S-1 page F-7
A8: Operating expenses:
A9: Compute and infrastructure | B9: 433 | C9: 2522 | D9: 7326 | E9: 2334 | F9: 8945 | N9: S-1 page F-7
A10: Personnel | B10: 95 | C10: 454 | D10: 1839 | E10: 538 | F10: 3152 | N10: S-1 page F-7
A11: Bartz settlement | B11: 0 | C11: 0 | D11: 1500 | E11: 0 | F11: 0 | N11: S-1 page F-7
A12: Sales, marketing, and partnerships | B12: 2 | C12: 43 | D12: 568 | E12: 120 | F12: 3168 | N12: S-1 page F-7
A13: Other operating and administrative | B13: 62 | C13: 347 | D13: 1412 | E13: 306 | F13: 1714 | N13: S-1 page F-7
A14: Total operating expenses | B14: 592 | C14: 3366 | D14: 12645 | E14: 3298 | F14: 16979 | N14: S-1 page F-7
A15: Operating loss | B15: -551 | C15: -2980 | D15: -8060 | E15: -2135 | F15: -693 | N15: S-1 page F-7
A16: Interest income | B16: 69 | C16: 106 | D16: 431 | E16: 115 | F16: 1111 | N16: S-1 page F-7
A17: Change in fair value of convertible notes, derivative liabilities, and SAFEs | B17: -1045 | C17: -5434 | D17: -34308 | E17: -10942 | F17: -72388 | N17: S-1 page F-7
A18: Other income (expense), net | B18: -2 | C18: 0 | D18: -8 | E18: 0 | F18: -8757 | N18: S-1 page F-7
A19: Total other income (expense), net | B19: -978 | C19: -5328 | D19: -33885 | E19: -10827 | F19: -80034 | N19: S-1 page F-7
A20: Loss before provision for income taxes | B20: -1529 | C20: -8308 | D20: -41945 | E20: -12962 | F20: -80727 | N20: S-1 page F-7
... A24: Weighted-average shares outstanding, basic and diluted | B24: 1076881 | C24: 1528995 | D24: 1821085 | E24: 1788731 | F24: 2024973 | N24: S-1 page F-7
A26: Checks: recomputed less filed (zero passes)
A27: Total operating expenses | B27: =B9+B10+B11+B12+B13-B14 -> 0 | C27: =C9+C10+C11+C12+C13-C14 -> 0 | D27: =D9+D10+D11+D12+D13-D14 -> 0 | E27: =E9+E10+E11+E12+E13-E14 -> 0 | F27: =F9+F10+F11+F12+F13-F14 -> 0
A28: Operating loss | B28: =B6-B14-B15 -> 0 | C28: =C6-C14-C15 -> 0 | D28: =D6-D14-D15 -> 0 | E28: =E6-E14-E15 -> 0 | F28: =F6-F14-F15 -> 0
A29: Total other income (expense), net | B29: =B16+B17+B18-B19 -> 0 | C29: =C16+C17+C18-C19 -> 0 | D29: =D16+D17+D18-D19 -> 0 | E29: =E16+E17+E18-E19 -> 0 | F29: =F16+F17+F18-F19 -> 0
A30: Loss before provision for income taxes | B30: =B15+B19-B20 -> 0 | C30: =C15+C19-C20 -> 0 | D30: =D15+D19-D20 -> 0 | E30: =E15+E19-E20 -> 0 | F30: =F15+F19-F20 -> 0
A31: Net loss | B31: =B20-B21-B22 -> 0 | C31: =C20-C21-C22 -> 0 | D31: =D20-D21-D22 -> 0 | E31: =E20-E21-E22 -> 0 | F31: =F20-F21-F22 -> 0
A32: Net loss per share (rounded to cents) | B32: =ROUND(B22*1000/B24,2)-B23 -> 0 | C32: =ROUND(C22*1000/C24,2)-C23 -> 0 | D32: =ROUND(D22*1000/D24,2)-D23 -> 0 | E32: =ROUND(E22*1000/E24,2)-E23 -> 0 | F32: =ROUND(F22*1000/F24,2)-F23 -> 0

Sheet CI_Hist
A1: Anthropic, PBC | Consolidated statements of comprehensive loss, as filed in the Form S-1
A2: USD millions. Source: Form S-1, 26 Oct 2026, page F-8.
A4: Fiscal year ends 31 December | B4: 2023A | C4: 2024A | D4: 2025A | E4: 6M 2025A | F4: 6M 2026A | M4: Comentarios FG | N4: Source / derivation
A6: Net loss | B6: -1531 | C6: -8309 | D6: -41965 | E6: -12969 | F6: -80748 | N6: S-1 page F-8
A8: Other comprehensive income (loss):
A9: Net unrealized gain (loss) on available-for-sale securities, net of tax | B9: 0 | C9: 0 | D9: 4 | E9: 0 | F9: -49 | N9: S-1 page F-8
A10: Foreign currency translation adjustments | B10: 0 | C10: 0 | D10: 1 | E10: 1 | F10: -9 | N10: S-1 page F-8
A11: Other comprehensive income (loss) | B11: 0 | C11: 0 | D11: 5 | E11: 1 | F11: -58 | N11: S-1 page F-8
A12: Comprehensive loss | B12: -1531 | C12: -8309 | D12: -41960 | E12: -12968 | F12: -80806 | N12: S-1 page F-8
A14: Checks: recomputed less filed (zero passes)
A15: Other comprehensive income (loss) | B15: =B9+B10-B11 -> 0 | C15: =C9+C10-C11 -> 0 | D15: =D9+D10-D11 -> 0 | E15: =E9+E10-E11 -> 0 | F15: =F9+F10-F11 -> 0
A16: Comprehensive loss | B16: =B6+B11-B12 -> 0 | C16: =C6+C11-C12 -> 0 | D16: =D6+D11-D12 -> 0 | E16: =E6+E11-E12 -> 0 | F16: =F6+F11-F12 -> 0
A17: Net loss equals the statement of operations | B17: =B6-IS_Hist!B22 -> 0 | C17: =C6-IS_Hist!C22 -> 0 | D17: =D6-IS_Hist!D22 -> 0 | E17: =E6-IS_Hist!E22 -> 0 | F17: =F6-IS_Hist!F22 -> 0

Sheet BS_Hist
A1: Anthropic, PBC | Consolidated balance sheets, as filed in the Form S-1
A2: USD millions. 31 December audited; 30 June 2026 unaudited. Source: Form S-1, 26 Oct 2026, pages F-5 and F-6.
A4: Fiscal year ends 31 December | B4: 31 Dec 2024A | C4: 31 Dec 2025A | D4: 30 Jun 2026A | M4: Comentarios FG | N4: Source / derivation
A6: Assets
A8: Current assets:
A9: Cash and cash equivalents | B9: 3141 | C9: 17388 | D9: 112389 | N9: S-1 pages F-5 and F-6
A10: Short-term investments | B10: 0 | C10: 2889 | D10: 19262 | N10: S-1 pages F-5 and F-6
A11: Accounts receivable, net | B11: 95 | C11: 909 | D11: 5833 | N11: S-1 pages F-5 and F-6
A12: Prepaid expenses and other current assets | B12: 2076 | C12: 2560 | D12: 496 | N12: S-1 pages F-5 and F-6
A13: Total current assets | B13: 5312 | C13: 23746 | D13: 137980 | N13: S-1 pages F-5 and F-6
A14: Restricted cash | B14: 13 | C14: 13 | D14: 2529 | N14: S-1 pages F-5 and F-6
A15: Property and equipment, net | B15: 19 | C15: 146 | D15: 1187 | N15: S-1 pages F-5 and F-6
A16: Operating lease right-of-use assets | B16: 35 | C16: 126 | D16: 1157 | N16: S-1 pages F-5 and F-6
A17: Goodwill | B17: 0 | C17: 154 | D17: 576 | N17: S-1 pages F-5 and F-6
A18: Other assets, noncurrent | B18: 2373 | C18: 476 | D18: 3929 | N18: S-1 pages F-5 and F-6
A19: Total assets | B19: 7752 | C19: 24661 | D19: 147358 | N19: S-1 pages F-5 and F-6
A20: Liabilities, Redeemable Convertible Preferred Stock, and Stockholders’ Deficit
A22: Current liabilities:
A23: Accounts payable, accrued expenses, and other current liabilities | B23: 333 | C23: 2511 | D23: 5422 | N23: S-1 pages F-5 and F-6
A24: Operating lease liabilities, current | B24: 13 | C24: 37 | D24: 148 | N24: S-1 pages F-5 and F-6
A25: Deferred revenue | B25: 28 | C25: 269 | D25: 1650 | N25: S-1 pages F-5 and F-6
A26: Total current liabilities | B26: 374 | C26: 2817 | D26: 7220 | N26: S-1 pages F-5 and F-6
A27: Operating lease liabilities, noncurrent | B27: 39 | C27: 80 | D27: 931 | N27: S-1 pages F-5 and F-6
A28: Convertible notes payable | B28: 14116 | C28: 41677 | D28: 108566 | N28: S-1 pages F-5 and F-6
A29: Other noncurrent liabilities | B29: 150 | C29: 823 | D29: 750 | N29: S-1 pages F-5 and F-6
A30: Total liabilities | B30: 14679 | C30: 45397 | D30: 117467 | N30: S-1 pages F-5 and F-6
A31: Commitments and contingencies (Note 13)
A32: Redeemable convertible preferred stock | B32: 2874 | C32: 29769 | D32: 157510 | N32: Caption as filed: Redeemable convertible preferred stock, $0.00001 par value; 360,995, 728,289, and 1,040,441 shares authorized as of December 31, 2024 and 2025 and June 30, 2026 (unaudited), respectively; 220,219, 544,322, and 853,394 shares issued and outstanding as of December 31, 2024 and 2025 and June 30, 2026 (unaudited), respectively; aggregate liquidation preference of $2,874, $24,646, and $136,286 as of December 31, 2024 and 2025 and June 30, 2026 (unaudited), respectively
A34: Stockholders’ deficit:
A35: Class A common stock | B35: 0 | C35: 0 | D35: 0 | N35: Caption as filed: Class A common stock, $0.00001 par value; 6,319,705, 8,162,757, and 10,991,000 shares authorized as of December 31, 2024 and 2025 and June 30, 2026 (unaudited), respectively; 1,779,060, 1,901,267, and 2,157,398 shares issued and outstanding as of December 31, 2024 and 2025 and June 30, 2026 (unaudited), respectively
A36: Class N common stock | B36: 0 | C36: 0 | D36: 0 | N36: Caption as filed: Class N common stock, $0.00001 par value; 2,148,900, 5,547,243, and 7,044,000 shares authorized as of December 31, 2024 and 2025 and June 30, 2026 (unaudited), respectively; no shares issued and outstanding as of December 31, 2024 and 2025, and 30,643 shares issued and outstanding as of June 30, 2026 (unaudited)
A37: Class T common stock | B37: 0 | C37: 0 | D37: 0 | N37: Caption as filed: Class T common stock, $0.00001 par value; 0 shares authorized and issued as of December 31, 2024 and 2025 and June 30, 2026 (unaudited)
A38: Additional paid-in capital | B38: 239 | C38: 1644 | D38: 5336 | N38: S-1 pages F-5 and F-6
A39: Accumulated other comprehensive income (loss) | B39: 0 | C39: 5 | D39: -53 | N39: S-1 pages F-5 and F-6
A40: Accumulated deficit | B40: -10040 | C40: -52154 | D40: -132902 | N40: S-1 pages F-5 and F-6
A41: Total stockholders’ deficit | B41: -9801 | C41: -50505 | D41: -127619 | N41: S-1 pages F-5 and F-6
A42: Total liabilities, redeemable convertible preferred stock, and stockholders’ deficit | B42: 7752 | C42: 24661 | D42: 147358 | N42: S-1 pages F-5 and F-6
A44: Memo: items used by the model
A45: Cash, cash equivalents and short-term investments | B45: =B9+B10 -> 3141 | C45: =C9+C10 -> 20277 | D45: =D9+D10 -> 131651
A46: Finance lease liabilities (inside other liabilities) | B46: 0 | C46: 0 | D46: 443 | N46: S-1 Note 7: total finance lease liabilities 443 at 30 Jun 2026; none at 31 Dec 2025.
A47: Lease liabilities: operating (current and noncurrent) and finance | B47: =B24+B27+B46 -> 52 | C47: =C24+C27+C46 -> 117 | D47: =D24+D27+D46 -> 1522
A49: Checks: recomputed less filed (zero passes)
A50: Total current assets | B50: =B9+B10+B11+B12-B13 -> 0 | C50: =C9+C10+C11+C12-C13 -> 0 | D50: =D9+D10+D11+D12-D13 -> 0
A51: Total assets | B51: =B13+B14+B15+B16+B17+B18-B19 -> 0 | C51: =C13+C14+C15+C16+C17+C18-C19 -> 0 | D51: =D13+D14+D15+D16+D17+D18-D19 -> 0
A52: Total current liabilities | B52: =B23+B24+B25-B26 -> 0 | C52: =C23+C24+C25-C26 -> 0 | D52: =D23+D24+D25-D26 -> 0
A53: Total liabilities | B53: =B26+B27+B28+B29-B30 -> 0 | C53: =C26+C27+C28+C29-C30 -> 0 | D53: =D26+D27+D28+D29-D30 -> 0
A54: Total stockholders' deficit | B54: =B35+B36+B37+B38+B39+B40-B41 -> 0 | C54: =C35+C36+C37+C38+C39+C40-C41 -> 0 | D54: =D35+D36+D37+D38+D39+D40-D41 -> 0
A55: Liabilities, preferred stock and deficit | B55: =B30+B32+B41-B42 -> 0 | C55: =C30+C32+C41-C42 -> 0 | D55: =D30+D32+D41-D42 -> 0
A56: Balance: total assets less the other side | B56: =B19-B42 -> 0 | C56: =C19-C42 -> 0 | D56: =D19-D42 -> 0

Sheet CF_Hist
A1: Anthropic, PBC | Consolidated statements of cash flows, as filed in the Form S-1
A2: USD millions. Fiscal years audited; six-month periods unaudited. Source: Form S-1, 26 Oct 2026, pages F-12 and F-13.
A4: Fiscal year ends 31 December | B4: 2023A | C4: 2024A | D4: 2025A | E4: 6M 2025A | F4: 6M 2026A | M4: Comentarios FG | N4: Source / derivation
A6: Cash flows from operating activities:
A7: Net loss | B7: -1531 | C7: -8309 | D7: -41965 | E7: -12969 | F7: -80748 | N7: S-1 pages F-12 and F-13
A9: Adjustments to reconcile net loss to net cash provided by (used in) operating activities:
A10: Stock-based compensation expense | B10: 29 | C10: 192 | D10: 1158 | E10: 279 | F10: 2185 | N10: S-1 pages F-12 and F-13
A11: Depreciation and amortization | B11: 3 | C11: 21 | D11: 40 | E11: 14 | F11: 97 | N11: S-1 pages F-12 and F-13
A12: Change in fair value of convertible notes, derivative liabilities, and SAFEs | B12: 1045 | C12: 5434 | D12: 34308 | E12: 10942 | F12: 72388 | N12: S-1 pages F-12 and F-13
A13: Donation matching program liability | B13: 0 | C13: 0 | D13: 541 | E13: 0 | F13: 126 | N13: S-1 pages F-12 and F-13
A14: Recognition and change in fair value of other financial instruments | B14: 0 | C14: 0 | D14: 0 | E14: 0 | F14: 8720 | N14: S-1 pages F-12 and F-13
A15: Other | B15: 0 | C15: 7 | D15: 11 | E15: 5 | F15: -7 | N15: S-1 pages F-12 and F-13
A17: Changes in operating assets and liabilities:
A18: Accounts receivable, net | B18: -10 | C18: -90 | D18: -834 | E18: -384 | F18: -4982 | N18: S-1 pages F-12 and F-13
A19: Prepaid expenses and other assets | B19: -1253 | C19: -3190 | D19: 1771 | E19: 212 | F19: 2094 | N19: S-1 pages F-12 and F-13
A20: Accounts payable, accrued expenses, and other liabilities | B20: 84 | C20: 222 | D20: 2079 | E20: 257 | F20: 2679 | N20: S-1 pages F-12 and F-13
A21: Lease liabilities | B21: -1 | C21: 0 | D21: 13 | E21: 7 | F21: -3 | N21: S-1 pages F-12 and F-13
A22: Deferred revenue | B22: 7 | C22: 21 | D22: 241 | E22: 124 | F22: 1380 | N22: S-1 pages F-12 and F-13
A23: Net cash provided by (used in) operating activities | B23: -1627 | C23: -5692 | D23: -2637 | E23: -1513 | F23: 3929 | N23: S-1 pages F-12 and F-13
A25: Cash flows from investing activities:
A26: Purchases of property and equipment | B26: -2 | C26: -15 | D26: -131 | E26: -18 | F26: -482 | N26: S-1 pages F-12 and F-13
A27: Purchases of short-term investments | B27: 0 | C27: 0 | D27: -3082 | E27: 0 | F27: -18972 | N27: S-1 pages F-12 and F-13
A28: Sales and maturities of short-term investments | B28: 0 | C28: 0 | D28: 213 | E28: 0 | F28: 2610 | N28: S-1 pages F-12 and F-13
A29: Other investing activities | B29: 0 | C29: -7 | D29: -77 | E29: -31 | F29: -337 | N29: S-1 pages F-12 and F-13
A30: Net cash used in investing activities | B30: -2 | C30: -22 | D30: -3077 | E30: -49 | F30: -17181 | N30: S-1 pages F-12 and F-13
A32: Cash flows from financing activities:
A33: Proceeds from issuance of redeemable convertible preferred stock, net of issuance costs | B33: 445 | C33: 1188 | D33: 16548 | E33: 3549 | F33: 110432 | N33: S-1 pages F-12 and F-13
A34: Principal payments for finance leases | B34: 0 | C34: 0 | D34: 0 | E34: 0 | F34: -4 | N34: S-1 pages F-12 and F-13
A35: Issuance of convertible notes for cash | B35: 1750 | C35: 6050 | D35: 3450 | E35: 1300 | F35: 0 | N35: S-1 pages F-12 and F-13
A36: Proceeds from issuance of common stock | B36: 3 | C36: 10 | D36: 111 | E36: 49 | F36: 355 | N36: S-1 pages F-12 and F-13
A37: Repurchase of common stock | B37: 0 | C37: 0 | D37: -149 | E37: -149 | F37: 0 | N37: S-1 pages F-12 and F-13
A38: Issuance of SAFEs for cash | B38: 122 | C38: 0 | D38: 0 | E38: 0 | F38: 0 | N38: S-1 pages F-12 and F-13
A39: Payment of deferred offering costs | B39: 0 | C39: 0 | D39: 0 | E39: 0 | F39: -9 | N39: S-1 pages F-12 and F-13
A40: Net cash provided by financing activities | B40: 2320 | C40: 7248 | D40: 19960 | E40: 4749 | F40: 110774 | N40: S-1 pages F-12 and F-13
A41: Effect of exchange rate changes on cash, cash equivalents, and restricted cash | B41: 0 | C41: 0 | D41: 1 | E41: 1 | F41: -5 | N41: S-1 pages F-12 and F-13
A42: Net increase in cash, cash equivalents, and restricted cash | B42: 691 | C42: 1534 | D42: 14247 | E42: 3188 | F42: 97517 | N42: S-1 pages F-12 and F-13
A43: Cash, cash equivalents, and restricted cash at beginning of period | B43: 929 | C43: 1620 | D43: 3154 | E43: 3154 | F43: 17401 | N43: S-1 pages F-12 and F-13
A44: Cash, cash equivalents, and restricted cash at end of period | B44: 1620 | C44: 3154 | D44: 17401 | E44: 6342 | F44: 114918 | N44: S-1 pages F-12 and F-13
A46: Checks: recomputed less filed (zero passes)
A47: Net cash from operating activities | B47: =B7+B10+B11+B12+B13+B14+B15+B18+B19+B20+B21+B22-B23 -> 0 | C47: =C7+C10+C11+C12+C13+C14+C15+C18+C19+C20+C21+C22-C23 -> 0 | D47: =D7+D10+D11+D12+D13+D14+D15+D18+D19+D20+D21+D22-D23 -> 0 | E47: =E7+E10+E11+E12+E13+E14+E15+E18+E19+E20+E21+E22-E23 -> 0 | F47: =F7+F10+F11+F12+F13+F14+F15+F18+F19+F20+F21+F22-F23 -> 0
A48: Net cash used in investing activities | B48: =B26+B27+B28+B29-B30 -> 0 | C48: =C26+C27+C28+C29-C30 -> 0 | D48: =D26+D27+D28+D29-D30 -> 0 | E48: =E26+E27+E28+E29-E30 -> 0 | F48: =F26+F27+F28+F29-F30 -> 0
A49: Net cash from financing activities | B49: =B33+B34+B35+B36+B37+B38+B39-B40 -> 0 | C49: =C33+C34+C35+C36+C37+C38+C39-C40 -> 0 | D49: =D33+D34+D35+D36+D37+D38+D39-D40 -> 0 | E49: =E33+E34+E35+E36+E37+E38+E39-E40 -> 0 | F49: =F33+F34+F35+F36+F37+F38+F39-F40 -> 0
A50: Net increase in cash | B50: =B23+B30+B40+B41-B42 -> 0 | C50: =C23+C30+C40+C41-C42 -> 0 | D50: =D23+D30+D40+D41-D42 -> 0 | E50: =E23+E30+E40+E41-E42 -> 0 | F50: =F23+F30+F40+F41-F42 -> 0
A51: Beginning cash plus increase less ending cash | B51: =B43+B42-B44 -> 0 | C51: =C43+C42-C44 -> 0 | D51: =D43+D42-D44 -> 0 | E51: =E43+E42-E44 -> 0 | F51: =F43+F42-F44 -> 0
A52: Net loss equals the statement of operations | B52: =B7-IS_Hist!B22 -> 0 | C52: =C7-IS_Hist!C22 -> 0 | D52: =D7-IS_Hist!D22 -> 0 | E52: =E7-IS_Hist!E22 -> 0 | F52: =F7-IS_Hist!F22 -> 0
A53: Ending cash equals balance sheet cash plus restricted cash | C53: =C44-BS_Hist!B9-BS_Hist!B14 -> 0 | D53: =D44-BS_Hist!C9-BS_Hist!C14 -> 0 | F53: =F44-BS_Hist!D9-BS_Hist!D14 -> 0 | N53: 2024A and 2025A against 31 December; 6M 2026A against 30 June 2026.

Sheet SCE_Hist
A1: Anthropic, PBC | Statements of redeemable convertible preferred stock and stockholders' deficit, as filed
A2: USD millions; share counts in thousands (after the 10-for-1 split of 17 Sep 2026). Source: Form S-1, 26 Oct 2026, pages F-9 to F-11.
A4: Line | B4: Preferred shares (k) | C4: Preferred amount | D4: Class A shares (k) | E4: Class A amount | F4: Class N shares (k) | G4: Class N amount | H4: Class T shares (k) | I4: Class T amount | J4: Additional paid-in capital | K4: AOCI | L4: Accumulated deficit | M4: Total stockholders' deficit | N4: Comentarios FG | O4: Source / derivation
A6: Fiscal years 2023 to 2025 (audited)
A7: Balance as of December 31, 2022 | B7: 136005 | C7: 1106 | D7: 1738823 | E7: 0 | F7: 0 | G7: 0 | H7: 0 | I7: 0 | J7: 5 | K7: 0 | L7: -200 | M7: -195 | O7: S-1 pages F-9 to F-11
A8: Issuance of redeemable convertible preferred stock, net of issuance costs | B8: 39670 | C8: 445 | D8: 0 | E8: 0 | F8: 0 | G8: 0 | H8: 0 | I8: 0 | J8: 0 | K8: 0 | L8: 0 | M8: 0 | O8: S-1 pages F-9 to F-11
A9: Conversion of SAFE note into redeemable convertible preferred stock | B9: 89 | C9: 1 | D9: 0 | E9: 0 | F9: 0 | G9: 0 | H9: 0 | I9: 0 | J9: 0 | K9: 0 | L9: 0 | M9: 0 | O9: S-1 pages F-9 to F-11
A10: Issuance of Class T common stock | B10: 0 | C10: 0 | D10: 0 | E10: 0 | F10: 0 | G10: 0 | H10: 0 | I10: 0 | J10: 0 | K10: 0 | L10: 0 | M10: 0 | O10: S-1 pages F-9 to F-11
A11: Issuance of Class A common stock upon exercise of stock options | B11: 0 | C11: 0 | D11: 15330 | E11: 0 | F11: 0 | G11: 0 | H11: 0 | I11: 0 | J11: 3 | K11: 0 | L11: 0 | M11: 3 | O11: S-1 pages F-9 to F-11
A12: Stock-based compensation expense | B12: 0 | C12: 0 | D12: 0 | E12: 0 | F12: 0 | G12: 0 | H12: 0 | I12: 0 | J12: 29 | K12: 0 | L12: 0 | M12: 29 | O12: S-1 pages F-9 to F-11
A13: Net loss | B13: 0 | C13: 0 | D13: 0 | E13: 0 | F13: 0 | G13: 0 | H13: 0 | I13: 0 | J13: 0 | K13: 0 | L13: -1531 | M13: -1531 | O13: S-1 pages F-9 to F-11
A14: Balance as of December 31, 2023 | B14: 175764 | C14: 1552 | D14: 1754153 | E14: 0 | F14: 0 | G14: 0 | H14: 0 | I14: 0 | J14: 37 | K14: 0 | L14: -1731 | M14: -1694 | O14: S-1 pages F-9 to F-11
A15: Issuance of redeemable convertible preferred stock, net of issuance costs | B15: 39979 | C15: 1188 | D15: 0 | E15: 0 | F15: 0 | G15: 0 | H15: 0 | I15: 0 | J15: 0 | K15: 0 | L15: 0 | M15: 0 | O15: S-1 pages F-9 to F-11
A16: Conversion of SAFE notes into redeemable convertible preferred stock | B16: 4476 | C16: 134 | D16: 0 | E16: 0 | F16: 0 | G16: 0 | H16: 0 | I16: 0 | J16: 0 | K16: 0 | L16: 0 | M16: 0 | O16: S-1 pages F-9 to F-11
A17: Issuance of Class A common stock upon exercise of stock options | B17: 0 | C17: 0 | D17: 24907 | E17: 0 | F17: 0 | G17: 0 | H17: 0 | I17: 0 | J17: 10 | K17: 0 | L17: 0 | M17: 10 | O17: S-1 pages F-9 to F-11
A18: Stock-based compensation expense | B18: 0 | C18: 0 | D18: 0 | E18: 0 | F18: 0 | G18: 0 | H18: 0 | I18: 0 | J18: 192 | K18: 0 | L18: 0 | M18: 192 | O18: S-1 pages F-9 to F-11
... A30: Balance as of December 31, 2025 | B30: 544322 | C30: 29769 | D30: 1901267 | E30: 0 | F30: 0 | G30: 0 | H30: 0 | I30: 0 | J30: 1644 | K30: 5 | L30: -52154 | M30: -50505 | O30: S-1 pages F-9 to F-11
A32: Six months ended 30 June 2025 (unaudited)
A33: Balance as of December 31, 2024 | B33: 220219 | C33: 2874 | D33: 1779060 | E33: 0 | F33: 0 | G33: 0 | H33: 0 | I33: 0 | J33: 239 | K33: 0 | L33: -10040 | M33: -9801 | O33: S-1 pages F-9 to F-11
A34: Issuance of redeemable convertible preferred stock, net of issuance costs (unaudited) | B34: 63610 | C34: 3549 | D34: 0 | E34: 0 | F34: 0 | G34: 0 | H34: 0 | I34: 0 | J34: 0 | K34: 0 | L34: 0 | M34: 0 | O34: S-1 pages F-9 to F-11
A35: Conversion of convertible notes into redeemable convertible preferred stock (unaudited) | B35: 147533 | C35: 8168 | D35: 0 | E35: 0 | F35: 0 | G35: 0 | H35: 0 | I35: 0 | J35: 0 | K35: 0 | L35: 0 | M35: 0 | O35: S-1 pages F-9 to F-11
A36: Issuance of Class A common stock upon exercise of stock options and grants of restricted stock (unaudited) | B36: 0 | C36: 0 | D36: 83704 | E36: 0 | F36: 0 | G36: 0 | H36: 0 | I36: 0 | J36: 49 | K36: 0 | L36: 0 | M36: 49 | O36: S-1 pages F-9 to F-11
A37: Repurchase of outstanding common stock (unaudited) | B37: 0 | C37: 0 | D37: -27942 | E37: 0 | F37: 0 | G37: 0 | H37: 0 | I37: 0 | J37: 0 | K37: 0 | L37: -149 | M37: -149 | O37: S-1 pages F-9 to F-11
A38: Stock-based compensation expense (unaudited) | B38: 0 | C38: 0 | D38: 0 | E38: 0 | F38: 0 | G38: 0 | H38: 0 | I38: 0 | J38: 279 | K38: 0 | L38: 0 | M38: 279 | O38: S-1 pages F-9 to F-11
A39: Foreign currency translation adjustments (unaudited) | B39: 0 | C39: 0 | D39: 0 | E39: 0 | F39: 0 | G39: 0 | H39: 0 | I39: 0 | J39: 0 | K39: 1 | L39: 0 | M39: 1 | O39: S-1 pages F-9 to F-11
A40: Net loss (unaudited) | B40: 0 | C40: 0 | D40: 0 | E40: 0 | F40: 0 | G40: 0 | H40: 0 | I40: 0 | J40: 0 | K40: 0 | L40: -12969 | M40: -12969 | O40: S-1 pages F-9 to F-11
A41: Balance as of June 30, 2025 (unaudited) | B41: 431362 | C41: 14591 | D41: 1834822 | E41: 0 | F41: 0 | G41: 0 | H41: 0 | I41: 0 | J41: 567 | K41: 1 | L41: -23158 | M41: -22590 | O41: S-1 pages F-9 to F-11
A43: Six months ended 30 June 2026 (unaudited)
A44: Balance as of December 31, 2025 | B44: 544322 | C44: 29769 | D44: 1901267 | E44: 0 | F44: 0 | G44: 0 | H44: 0 | I44: 0 | J44: 1644 | K44: 5 | L44: -52154 | M44: -50505 | O44: S-1 pages F-9 to F-11
A45: Issuance of redeemable convertible preferred stock, net of issuance costs (unaudited) | B45: 285187 | C45: 122242 | D45: 0 | E45: 0 | F45: 0 | G45: 0 | H45: 0 | I45: 0 | J45: 0 | K45: 0 | L45: 0 | M45: 0 | O45: S-1 pages F-9 to F-11
A46: Conversion of convertible notes into redeemable convertible preferred stock (unaudited) | B46: 23885 | C46: 5499 | D46: 0 | E46: 0 | F46: 0 | G46: 0 | H46: 0 | I46: 0 | J46: 0 | K46: 0 | L46: 0 | M46: 0 | O46: S-1 pages F-9 to F-11
A47: Issuance of Class A common stock upon exercise of stock options, grants of restricted stock, and sales of common stock for cash (unaudited) | B47: 0 | C47: 0 | D47: 229818 | E47: 0 | F47: 0 | G47: 0 | H47: 0 | I47: 0 | J47: 355 | K47: 0 | L47: 0 | M47: 355 | O47: S-1 pages F-9 to F-11
A48: Issuance of Class A common stock in connection with acquisitions (unaudited) | B48: 0 | C48: 0 | D48: 26313 | E48: 0 | F48: 0 | G48: 0 | H48: 0 | I48: 0 | J48: 534 | K48: 0 | L48: 0 | M48: 534 | O48: S-1 pages F-9 to F-11
A49: Issuance of Class N common stock upon settlement of donation matching program liability (unaudited) | B49: 0 | C49: 0 | D49: 0 | E49: 0 | F49: 30643 | G49: 0 | H49: 0 | I49: 0 | J49: 667 | K49: 0 | L49: 0 | M49: 667 | O49: S-1 pages F-9 to F-11
A50: Stock-based compensation expense (unaudited) | B50: 0 | C50: 0 | D50: 0 | E50: 0 | F50: 0 | G50: 0 | H50: 0 | I50: 0 | J50: 2185 | K50: 0 | L50: 0 | M50: 2185 | O50: S-1 pages F-9 to F-11
A51: Foreign currency translation adjustments (unaudited) | B51: 0 | C51: 0 | D51: 0 | E51: 0 | F51: 0 | G51: 0 | H51: 0 | I51: 0 | J51: 0 | K51: -9 | L51: 0 | M51: -9 | O51: S-1 pages F-9 to F-11
A52: Net unrealized loss on available-for-sale securities (unaudited) | B52: 0 | C52: 0 | D52: 0 | E52: 0 | F52: 0 | G52: 0 | H52: 0 | I52: 0 | J52: 0 | K52: -49 | L52: 0 | M52: -49 | O52: S-1 pages F-9 to F-11
A53: Net loss (unaudited) | B53: 0 | C53: 0 | D53: 0 | E53: 0 | F53: 0 | G53: 0 | H53: 0 | I53: 0 | J53: 0 | K53: 0 | L53: -80748 | M53: -80748 | O53: S-1 pages F-9 to F-11
A54: Other (unaudited) | B54: 0 | C54: 0 | D54: 0 | E54: 0 | F54: 0 | G54: 0 | H54: 0 | I54: 0 | J54: -49 | K54: 0 | L54: 0 | M54: -49 | O54: S-1 pages F-9 to F-11
A55: Balance as of June 30, 2026 (unaudited) | B55: 853394 | C55: 157510 | D55: 2157398 | E55: 0 | F55: 30643 | G55: 0 | H55: 0 | I55: 0 | J55: 5336 | K55: -53 | L55: -132902 | M55: -127619 | O55: S-1 pages F-9 to F-11
A57: Checks (zero passes)
A58: Total deficit = APIC + AOCI + accumulated deficit, 31 Dec 2024 | M58: =J20+K20+L20-M20 -> 0
A59: Preferred amount equals the balance sheet, 31 Dec 2024 | C59: =C20-BS_Hist!B32 -> 0
A60: Total deficit equals the balance sheet, 31 Dec 2024 | M60: =M20-BS_Hist!B41 -> 0
A61: Total deficit = APIC + AOCI + accumulated deficit, 31 Dec 2025 | M61: =J30+K30+L30-M30 -> 0
A62: Preferred amount equals the balance sheet, 31 Dec 2025 | C62: =C30-BS_Hist!C32 -> 0
A63: Total deficit equals the balance sheet, 31 Dec 2025 | M63: =M30-BS_Hist!C41 -> 0
A64: Total deficit = APIC + AOCI + accumulated deficit, 30 Jun 2026 | M64: =J55+K55+L55-M55 -> 0
A65: Preferred amount equals the balance sheet, 30 Jun 2026 | C65: =C55-BS_Hist!D32 -> 0
A66: Total deficit equals the balance sheet, 30 Jun 2026 | M66: =M55-BS_Hist!D41 -> 0

Sheet Quarterly_Hist
A1: Anthropic, PBC | Quarterly statements of operations and adjusted operating income, as filed
A2: USD millions. Unaudited. Source: Form S-1, 26 Oct 2026, MD&A 'Quarterly Results of Operations'.
A4: Three months ended | B4: Q1 2025A | C4: Q2 2025A | D4: Q3 2025A | E4: Q4 2025A | F4: Q1 2026A | G4: Q2 2026A | M4: Comentarios FG | N4: Source / derivation
A6: Revenue | B6: 376 | C6: 787 | D6: 1382 | E6: 2040 | F6: 4731 | G6: 11555 | N6: S-1 MD&A, quarterly table
A7: Operating expenses:
A8: Compute and infrastructure | B8: 944 | C8: 1390 | D8: 2047 | E8: 2945 | F8: 3387 | G8: 5558 | N8: S-1 MD&A, quarterly table
A9: Personnel | B9: 218 | C9: 320 | D9: 489 | E9: 812 | F9: 1295 | G9: 1857 | N9: S-1 MD&A, quarterly table
A10: Bartz settlement | B10: 0 | C10: 0 | D10: 1500 | E10: 0 | F10: 0 | G10: 0 | N10: S-1 MD&A, quarterly table
A11: Sales, marketing, and partnerships | B11: 24 | C11: 96 | D11: 202 | E11: 246 | F11: 1033 | G11: 2135 | N11: S-1 MD&A, quarterly table
A12: Other operating and administrative | B12: 125 | C12: 181 | D12: 233 | E12: 873 | F12: 683 | G12: 1031 | N12: S-1 MD&A, quarterly table
A13: Total operating expenses | B13: 1311 | C13: 1987 | D13: 4471 | E13: 4876 | F13: 6398 | G13: 10581 | N13: S-1 MD&A, quarterly table
A14: Operating income (loss) | B14: -935 | C14: -1200 | D14: -3089 | E14: -2836 | F14: -1667 | G14: 974 | N14: S-1 MD&A, quarterly table
A15: Interest income | B15: 51 | C15: 64 | D15: 124 | E15: 192 | F15: 349 | G15: 762 | N15: S-1 MD&A, quarterly table
A16: Change in fair value of convertible notes, derivative liabilities, and SAFEs | B16: -5701 | C16: -5241 | D16: -9165 | E16: -14201 | F16: -12791 | G16: -59597 | N16: S-1 MD&A, quarterly table
A17: Other income (expense), net | B17: 0 | C17: 0 | D17: -3 | E17: -5 | F17: -309 | G17: -8448 | N17: S-1 MD&A, quarterly table
A18: Total other income (expense), net | B18: -5650 | C18: -5177 | D18: -9044 | E18: -14014 | F18: -12751 | G18: -67283 | N18: S-1 MD&A, quarterly table
A19: Loss before provision for income taxes | B19: -6585 | C19: -6377 | D19: -12133 | E19: -16850 | F19: -14418 | G19: -66309 | N19: S-1 MD&A, quarterly table
... A21: Net loss | B21: -6592 | C21: -6377 | D21: -12138 | E21: -16858 | F21: -14439 | G21: -66309 | N21: S-1 MD&A, quarterly table
A23: Adjusted operating income (company definition, non-GAAP)
A24: Stock-based compensation expense | B24: 105 | C24: 181 | D24: 305 | E24: 574 | F24: 924 | G24: 1261 | N24: S-1 MD&A, quarterly non-GAAP table
A25: Non-cash charitable contributions | B25: 0 | C25: 0 | D25: 0 | E25: 541 | F25: 126 | G25: 0 | N25: S-1 MD&A, quarterly non-GAAP table
A26: Bartz settlement | B26: 0 | C26: 0 | D26: 1500 | E26: 0 | F26: 0 | G26: 0 | N26: S-1 MD&A, quarterly non-GAAP table
A27: Adjusted Operating Income (Loss) | B27: -830 | C27: -1019 | D27: -1284 | E27: -1721 | F27: -617 | G27: 2235 | N27: S-1 MD&A, quarterly non-GAAP table
A29: Ratios (derived)
A30: Revenue: growth on the prior quarter | C30: =C6/B6-1 -> 1.0930851 | D30: =D6/C6-1 -> 0.75603558 | E30: =E6/D6-1 -> 0.47612156 | F30: =F6/E6-1 -> 1.3191176 | G30: =G6/F6-1 -> 1.4424012
A31: Compute and infrastructure: % of revenue | B31: =B8/B6 -> 2.5106383 | C31: =C8/C6 -> 1.7662008 | D31: =D8/D6 -> 1.4811867 | E31: =E8/E6 -> 1.4436275 | F31: =F8/F6 -> 0.7159163 | G31: =G8/G6 -> 0.48100389
A32: Personnel: % of revenue | B32: =B9/B6 -> 0.57978723 | C32: =C9/C6 -> 0.40660737 | D32: =D9/D6 -> 0.35383502 | E32: =E9/E6 -> 0.39803922 | F32: =F9/F6 -> 0.27372648 | G32: =G9/G6 -> 0.16070965
A33: Sales, marketing and partnerships: % of revenue | B33: =B11/B6 -> 0.063829787 | C33: =C11/C6 -> 0.12198221 | D33: =D11/D6 -> 0.14616498 | E33: =E11/E6 -> 0.12058824 | F33: =F11/F6 -> 0.21834707 | G33: =G11/G6 -> 0.1847685
A34: Other operating and administrative: % of revenue | B34: =B12/B6 -> 0.33244681 | C34: =C12/C6 -> 0.22998729 | D34: =D12/D6 -> 0.16859624 | E34: =E12/E6 -> 0.42794118 | F34: =F12/F6 -> 0.14436694 | G34: =G12/G6 -> 0.089225444
A35: Personnel excluding stock-based compensation: % of revenue | B35: =(B9-B24)/B6 -> 0.30053191 | C35: =(C9-C24)/C6 -> 0.17662008 | D35: =(D9-D24)/D6 -> 0.13314038 | E35: =(E9-E24)/E6 -> 0.11666667 | F35: =(F9-F24)/F6 -> 0.078418939 | G35: =(G9-G24)/G6 -> 0.051579403
A36: Operating margin | B36: =B14/B6 -> -2.4867021 | C36: =C14/C6 -> -1.5247776 | D36: =D14/D6 -> -2.2351664 | E36: =E14/E6 -> -1.3901961 | F36: =F14/F6 -> -0.3523568 | G36: =G14/G6 -> 0.084292514
A37: Adjusted operating margin (company definition) | B37: =B27/B6 -> -2.2074468 | C37: =C27/C6 -> -1.2947903 | D37: =D27/D6 -> -0.92908828 | E37: =E27/E6 -> -0.84362745 | F37: =F27/F6 -> -0.1304164 | G37: =G27/G6 -> 0.19342276
A39: Checks (zero passes)
A40: Total operating expenses | B40: =B8+B9+B10+B11+B12-B13 -> 0 | C40: =C8+C9+C10+C11+C12-C13 -> 0 | D40: =D8+D9+D10+D11+D12-D13 -> 0 | E40: =E8+E9+E10+E11+E12-E13 -> 0 | F40: =F8+F9+F10+F11+F12-F13 -> 0 | G40: =G8+G9+G10+G11+G12-G13 -> 0
A41: Net loss | B41: =B14+B18-B20-B21 -> 0 | C41: =C14+C18-C20-C21 -> 0 | D41: =D14+D18-D20-D21 -> 0 | E41: =E14+E18-E20-E21 -> 0 | F41: =F14+F18-F20-F21 -> 0 | G41: =G14+G18-G20-G21 -> 0
A42: Adjusted operating income | B42: =B14+B24+B25+B26-B27 -> 0 | C42: =C14+C24+C25+C26-C27 -> 0 | D42: =D14+D24+D25+D26-D27 -> 0 | E42: =E14+E24+E25+E26-E27 -> 0 | F42: =F14+F24+F25+F26-F27 -> 0 | G42: =G14+G24+G25+G26-G27 -> 0
A43: Quarters add up to the statements: rev | B43: =SUM(B6:E6)-IS_Hist!D6 -> 0 | C43: =B6+C6-IS_Hist!E6 -> 0 | D43: =F6+G6-IS_Hist!F6 -> 0 | N43: B: Q1-Q4 2025 against FY2025; C: Q1-Q2 2025 against 6M 2025; D: Q1-Q2 2026 against 6M 2026.
A44: Quarters add up to the statements: comp | B44: =SUM(B8:E8)-IS_Hist!D9 -> 0 | C44: =B8+C8-IS_Hist!E9 -> 0 | D44: =F8+G8-IS_Hist!F9 -> 0 | N44: B: Q1-Q4 2025 against FY2025; C: Q1-Q2 2025 against 6M 2025; D: Q1-Q2 2026 against 6M 2026.
A45: Quarters add up to the statements: topex | B45: =SUM(B13:E13)-IS_Hist!D14 -> 0 | C45: =B13+C13-IS_Hist!E14 -> 0 | D45: =F13+G13-IS_Hist!F14 -> 0 | N45: B: Q1-Q4 2025 against FY2025; C: Q1-Q2 2025 against 6M 2025; D: Q1-Q2 2026 against 6M 2026.
A46: Quarters add up to the statements: nl | B46: =SUM(B21:E21)-IS_Hist!D22 -> 0 | C46: =B21+C21-IS_Hist!E22 -> 0 | D46: =F21+G21-IS_Hist!F22 -> 0 | N46: B: Q1-Q4 2025 against FY2025; C: Q1-Q2 2025 against 6M 2025; D: Q1-Q2 2026 against 6M 2026.

Sheet Revenue_Hist
A1: Anthropic, PBC | Revenue, customers, costs by function and non-GAAP measures, as filed
A2: USD millions unless stated. Source: Form S-1, 26 Oct 2026: notes 2 and 3, the MD&A and the business section.
A4: Fiscal year ends 31 December | B4: 2023A | C4: 2024A | D4: 2025A | E4: 6M 2025A | F4: 6M 2026A | M4: Comentarios FG | N4: Source / derivation
A6: Revenue by pricing model (S-1 Note 3)
A7: Consumption-based | B7: 39 | C7: 288 | D7: 3796 | E7: 983 | F7: 13064 | N7: S-1 Note 3
A8: Subscription-based | B8: 2 | C8: 98 | D8: 789 | E8: 180 | F8: 3222 | N8: S-1 Note 3
A9: Total | B9: 41 | C9: 386 | D9: 4585 | E9: 1163 | F9: 16286 | N9: S-1 Note 3
A10: Subscription-based: % of revenue | B10: =B8/B9 -> 0.048780488 | C10: =C8/C9 -> 0.25388601 | D10: =D8/D9 -> 0.17208288 | E10: =E8/E9 -> 0.15477214 | F10: =F8/F9 -> 0.19783863
A12: Revenue by region, billing address of the customer (S-1 Note 3)
A13: United States | B13: 34 | C13: 263 | D13: 3362 | E13: 820 | F13: 11763 | N13: S-1 Note 3
A14: International | B14: 7 | C14: 123 | D14: 1223 | E14: 343 | F14: 4523 | N14: S-1 Note 3
A15: Total | B15: 41 | C15: 386 | D15: 4585 | E15: 1163 | F15: 16286 | N15: S-1 Note 3
A16: International: % of revenue | B16: =B14/B15 -> 0.17073171 | C16: =C14/C15 -> 0.31865285 | D16: =D14/D15 -> 0.26673937 | E16: =E14/E15 -> 0.29492691 | F16: =F14/F15 -> 0.2777232
A18: Customers above 10% of revenue (S-1 Note 2; a dash means below 10%)
A19: Customer A | B19: 0 | C19: 0 | D19: 0.12 | E19: 0 | F19: 0 | N19: S-1 Note 2, concentration of revenue
A20: Customer B | B20: 0 | C20: 0 | D20: 0.12 | E20: 0.18 | F20: 0 | N20: S-1 Note 2, concentration of revenue
A21: Customer C | B21: 0.43 | C21: 0 | D21: 0 | E21: 0 | F21: 0.11 | N21: S-1 Note 2, concentration of revenue
A22: Customer D | B22: 0.11 | C22: 0 | D22: 0 | E22: 0 | F22: 0 | N22: S-1 Note 2, concentration of revenue
A24: Operating expenses by function (S-1 Note 2)
A25: Cost of revenue | B25: 26 | C25: 752 | D25: 2773 | E25: 1019 | F25: 2380 | N25: S-1 Note 2, expenses by function
A26: Research and development | B26: 422 | C26: 2275 | D26: 6338 | E26: 1850 | F26: 9741 | N26: S-1 Note 2, expenses by function
A27: Sales and marketing | B27: 76 | C27: 163 | D27: 911 | E27: 239 | F27: 3808 | N27: S-1 Note 2, expenses by function
A28: Bartz settlement | B28: 0 | C28: 0 | D28: 1500 | E28: 0 | F28: 0 | N28: S-1 Note 2, expenses by function
A29: General and administrative | B29: 68 | C29: 176 | D29: 1123 | E29: 190 | F29: 1050 | N29: S-1 Note 2, expenses by function
A30: Total operating expenses | B30: 592 | C30: 3366 | D30: 12645 | E30: 3298 | F30: 16979 | N30: S-1 Note 2, expenses by function
A31: Gross margin: 1 - cost of revenue / revenue (derived) | B31: =1-B25/IS_Hist!B6 -> 0.36585366 | C31: =1-C25/IS_Hist!C6 -> -0.94818653 | D31: =1-D25/IS_Hist!D6 -> 0.39520174 | E31: =1-E25/IS_Hist!E6 -> 0.12381771 | F31: =1-F25/IS_Hist!F6 -> 0.85386221
A32: Research and development: % of revenue (derived) | B32: =B26/IS_Hist!B6 -> 10.292683 | C32: =C26/IS_Hist!C6 -> 5.8937824 | D32: =D26/IS_Hist!D6 -> 1.3823337 | E32: =E26/IS_Hist!E6 -> 1.5907137 | F32: =F26/IS_Hist!F6 -> 0.59812109
A34: Adjusted operating income and adjusted net income (company definitions, non-GAAP; S-1 MD&A)
A35: Operating loss | B35: -551 | C35: -2980 | D35: -8060 | E35: -2135 | F35: -693 | N35: S-1 MD&A, non-GAAP reconciliation
A36: Stock-based compensation expense | B36: 29 | C36: 192 | D36: 1165 | E36: 286 | F36: 2185 | N36: S-1 MD&A, non-GAAP reconciliation
A37: Non-cash charitable contributions | B37: 0 | C37: 0 | D37: 541 | E37: 0 | F37: 126 | N37: S-1 MD&A, non-GAAP reconciliation
A38: Bartz settlement | B38: 0 | C38: 0 | D38: 1500 | E38: 0 | F38: 0 | N38: S-1 MD&A, non-GAAP reconciliation
A39: Adjusted Operating Income (Loss) | B39: -522 | C39: -2788 | D39: -4854 | E39: -1849 | F39: 1618 | N39: S-1 MD&A, non-GAAP reconciliation
A40: Adjusted operating margin | B40: =B39/IS_Hist!B6 -> -12.731707 | C40: =C39/IS_Hist!C6 -> -7.2227979 | D40: =D39/IS_Hist!D6 -> -1.0586696 | E40: =E39/IS_Hist!E6 -> -1.5898538 | F40: =F39/IS_Hist!F6 -> 0.099349134
A41: Change in fair value of convertible notes, derivative liabilities, and SAFEs | B41: 1045 | C41: 5434 | D41: 34308 | E41: 10942 | F41: 72388 | N41: S-1 MD&A, adjusted net income reconciliation
A42: Change in fair value of certain mark-to-market financial instruments | B42: 0 | C42: 0 | D42: 3 | E42: 0 | F42: 8720 | N42: S-1 MD&A, adjusted net income reconciliation
A43: Adjusted Net Income (Loss) | B43: -457 | C43: -2683 | D43: -4448 | E43: -1741 | F43: 2671 | N43: S-1 MD&A, adjusted net income reconciliation
A45: Key metrics stated in the S-1 prose (as of 30 Sep 2026 unless stated)
B46: Value | C46: A year earlier
A47: Customers with US$100,000 or more of TTM revenue | B47: 11900 | C47: 950 | N47: S-1: We had more than 11,900 customers with $100,000 or more of revenue on a TTM basis as of September 30, 2026, up from more than 950 as of September 30, 2025
A48: Customers with US$1 million or more of TTM revenue | B48: 1900 | N48: S-1: we had more than 1,900 customers with $1 million or more of revenue on a TTM basis
A49: Customers with US$10 million or more of TTM revenue (approximately) | B49: 250 | N49: S-1: approximately 250 customers with $10 million or more of reve nue
A50: Customers above US$100,000 using Claude Platform and an application | B50: 0.5 | C50: 0.3 | N50: S-1: over 50% of our customers with $100,000 or more of revenue on a TTM basis used Claude Platform and at least one of our first-party applications, up from approximately 30%
A51: Net revenue retention (approximately) | B51: 9 | N51: S-1: Net Revenue Retention of approximately 900% as of September 30, 2026
A52: Employees (approximately) | B52: 5300 | N52: S-1: As of September 30, 2026, with approximately 5,300 employees, our TTM revenue per employee was over $6.6 million
A53: TTM revenue per employee, 'over' (USD m) | B53: 6.6 | N53: S-1: As of September 30, 2026, with approximately 5,300 employees, our TTM revenue per employee was over $6.6 million
A55: Third-quarter 2026 revenue: the floor the S-1 implies (derived)
A56: TTM revenue to 30 Sep 2026, lower bound (employees x revenue per employee) | B56: =B52*B53 -> 34980 | N56: 5,300 x US$6.6m. Both figures are 'approximately' and 'over' in the S-1, so this is an estimate of a floor.
A57: Q3 2026 revenue, lower bound | B57: =B56-Quarterly_Hist!E6-Quarterly_Hist!F6-Quarterly_Hist!G6 -> 16654 | N57: TTM floor less Q4 2025, Q1 2026 and Q2 2026 revenue (Quarterly_Hist). The S-1 leaves Q3 revenue blank.
A59: Deferred revenue roll-forward (S-1 Note 3)
A60: Balance as of December 31, 2023 | B60: 7 | N60: S-1 Note 3
A61: Revenue recognized from deferred revenue at the beginning of the period | B61: -7 | N61: S-1 Note 3
A62: Amounts billed or received in advance and not recognized as revenue and other | B62: 28 | N62: S-1 Note 3
A63: Balance as of December 31, 2024 | B63: 28 | N63: S-1 Note 3
A64: Revenue recognized from deferred revenue at the beginning of the period | B64: -28 | N64: S-1 Note 3
A65: Amounts billed or received in advance and not recognized as revenue and other | B65: 269 | N65: S-1 Note 3
A66: Balance as of December 31, 2025 | B66: 269 | N66: S-1 Note 3
A67: Revenue recognized from deferred revenue at the beginning of the period (unaudited) | B67: -196 | N67: S-1 Note 3
A68: Amounts billed or received in advance and not recognized as revenue and other (unaudited) | B68: 1577 | N68: S-1 Note 3
A69: Balance as of June 30, 2026 (unaudited) | B69: 1650 | N69: S-1 Note 3
A71: Checks (zero passes)
A72: Revenue by pricing model adds to total | B72: =B7+B8-B9 -> 0 | C72: =C7+C8-C9 -> 0 | D72: =D7+D8-D9 -> 0 | E72: =E7+E8-E9 -> 0 | F72: =F7+F8-F9 -> 0
A73: Revenue by pricing model equals the statement | B73: =B9-IS_Hist!B6 -> 0 | C73: =C9-IS_Hist!C6 -> 0 | D73: =D9-IS_Hist!D6 -> 0 | E73: =E9-IS_Hist!E6 -> 0 | F73: =F9-IS_Hist!F6 -> 0
A74: Revenue by region equals the statement | B74: =B13+B14-IS_Hist!B6 -> 0 | C74: =C13+C14-IS_Hist!C6 -> 0 | D74: =D13+D14-IS_Hist!D6 -> 0 | E74: =E13+E14-IS_Hist!E6 -> 0 | F74: =F13+F14-IS_Hist!F6 -> 0
A75: Expenses by function equal total operating expenses | B75: =B25+B26+B27+B28+B29-IS_Hist!B14 -> 0 | C75: =C25+C26+C27+C28+C29-IS_Hist!C14 -> 0 | D75: =D25+D26+D27+D28+D29-IS_Hist!D14 -> 0 | E75: =E25+E26+E27+E28+E29-IS_Hist!E14 -> 0 | F75: =F25+F26+F27+F28+F29-IS_Hist!F14 -> 0
A76: Adjusted operating income recomputed | B76: =B35+B36+B37+B38-B39 -> 0 | C76: =C35+C36+C37+C38-C39 -> 0 | D76: =D35+D36+D37+D38-D39 -> 0 | E76: =E35+E36+E37+E38-E39 -> 0 | F76: =F35+F36+F37+F38-F39 -> 0
A77: Operating loss equals the statement | B77: =B35-IS_Hist!B15 -> 0 | C77: =C35-IS_Hist!C15 -> 0 | D77: =D35-IS_Hist!D15 -> 0 | E77: =E35-IS_Hist!E15 -> 0 | F77: =F35-IS_Hist!F15 -> 0

Sheet Cap_Table
A1: Anthropic, PBC | Capital structure, fully diluted shares and the Series H reference price
A2: Shares in thousands unless stated, after the 10-for-1 split of common stock on 17 Sep 2026. Source: Form S-1, 26 Oct 2026 (balance sheet captions, Notes 10 and 11).
A4: Item | B4: Value | C4: Price (USD) | D4: Comentarios FG | E4: Source / derivation
A6: A. Common stock outstanding, 30 Jun 2026
A7: Class A common stock | B7: 2157398 | E7: Balance sheet caption: 2,157,398 thousand issued and outstanding
A8: Class N common stock (non-voting) | B8: 30643 | E8: Balance sheet caption: 30,643 thousand
A9: Common shares outstanding | B9: =B7+B8 -> 2188041
A11: B. Redeemable convertible preferred stock, as converted into common (Note 10)
A12: Series A | B12: 485744 | E12: Note 10: common stock reserved, as-if converted, 30 Jun 2026
A13: Series B | B13: 874304 | E13: Note 10: common stock reserved, as-if converted, 30 Jun 2026
A14: Series C-1 | B14: 263972 | E14: Note 10: common stock reserved, as-if converted, 30 Jun 2026
A15: Series C-2 | B15: 133617 | E15: Note 10: common stock reserved, as-if converted, 30 Jun 2026
A16: Series D-1 | B16: 370299 | E16: Note 10: common stock reserved, as-if converted, 30 Jun 2026
A17: Series D-2 | B17: 46314 | E17: Note 10: common stock reserved, as-if converted, 30 Jun 2026
A18: Series D-3 | B18: 52873 | E18: Note 10: common stock reserved, as-if converted, 30 Jun 2026
A19: Series E-1 | B19: 636101 | E19: Note 10: common stock reserved, as-if converted, 30 Jun 2026
A20: Series E-2 | B20: 952819 | E20: Note 10: common stock reserved, as-if converted, 30 Jun 2026
A21: Series E-3 | B21: 126646 | E21: Note 10: common stock reserved, as-if converted, 30 Jun 2026
A22: Series E-4 | B22: 153429 | E22: Note 10: common stock reserved, as-if converted, 30 Jun 2026
A23: Series E-5 | B23: 242436 | E23: Note 10: common stock reserved, as-if converted, 30 Jun 2026
... A35: Series H-4 | B35: 0 | E35: Note 10: common stock reserved, as-if converted, 30 Jun 2026
A36: Preferred stock as converted | B36: =SUM(B12:B35) -> 8558869 | E36: Conversion ratio 10:1, Series D about 10.4-10.6:1 after anti-dilution adjustments (Note 10).
A38: C. Other dilutive securities, 30 Jun 2026
A39: Convertible notes (Amazon): Class N shares issuable on conversion | B39: 1840445 | E39: MD&A table: 1,840,444,962 shares at conversion prices US$2.0928 and US$5.0478; principal US$6,203m.
A40: Stock options outstanding | B40: 1797066 | C40: 2.89 | E40: Note 11: weighted-average exercise price US$2.89.
A41: Stock options, net shares by the treasury method at the Series H price | B41: =B40*(1-C40/C52) -> 1708892.2 | E41: Options x (1 - exercise price / reference price).
A42: Restricted stock units outstanding | B42: 1049631 | E42: Note 11: vest at the IPO for the service already given.
A43: Holdback shares (acquisitions) | B43: 1590 | E43: Note 12 anti-dilutive table.
A44: Shares available under the donation matching plan | B44: 933698 | E44: Note 10: reserved for the employee donation matching program; issued as donations are matched.
A45: Include the donation matching reserve (1 = yes, 0 = no) | B45: 1 | E45: Analyst choice. With it, the count matches the US$965bn Series H post-money within about 1%.
A46: Fully diluted shares (thousands) | B46: =B9+B36+B39+B41+B42+B43+B44*B45 -> 16281166
A47: Fully diluted shares (millions) | B47: =B46/1000 -> 16281.166
A49: D. Reference price: the Series H round (S-1)
A50: Series H-1 and H-2 price per preferred share (USD) | C50: 589.0095 | E50: S-1 Note 10: 'at a price of $589.0095 per share, for aggregate gross proceeds of $65.2 billion' (second quarter of 2026).
A51: Common shares per preferred share | B51: 10 | E51: Conversion ratio 10:1 after the split (Note 10).
A52: Series H price per common share (USD) | C52: =C50/B51 -> 58.90095
A53: Equity value at the Series H price (USD m) | B53: =B47*C52 -> 958976.16
A54: Memo: Series H post-money announced by the company (USD m) | B54: 965000 | E54: Company blog and Reuters, 28 May 2026: Series H at US$965bn post-money. Not in the S-1; memo check of the share count only
A55: Share count check: equity at the Series H price / post-money - 1 | B55: =B53/B54-1 -> -0.0062423253
A57: E. Original issue price by series (Note 10, 30 Jun 2026)
B58: Shares out (k) | C58: Price per preferred | E58: Per common share = price / 10
A59: Series A | B59: 48574 | C59: 2.57 | E59: Carrying value US$125m; liquidation preference US$125m.
A60: Series B | B60: 87430 | C60: 11.23 | E60: Carrying value US$982m; liquidation preference US$982m.
A61: Series C-1 | B61: 26397 | C61: 11.23 | E61: Carrying value US$296m; liquidation preference US$296m.
A62: Series C-2 | B62: 13362 | C62: 11.23 | E62: Carrying value US$150m; liquidation preference US$150m.
A63: Series D-1 | B63: 35013 | C63: 30 | E63: Carrying value US$1,042m; liquidation preference US$1,051m.
A64: Series D-2 | B64: 4444 | C64: 27 | E64: Carrying value US$133m; liquidation preference US$120m.
A65: Series D-3 | B65: 4999 | C65: 30 | E65: Carrying value US$146m; liquidation preference US$150m.
A66: Series E-1 | B66: 63610 | C66: 56.09 | E66: Carrying value US$3,549m; liquidation preference US$3,568m.
A67: Series E-2 | B67: 95282 | C67: 20.93 | E67: Carrying value US$4,728m; liquidation preference US$1,994m.
A68: Series E-3 | B68: 12664 | C68: 56.09 | E68: Carrying value US$856m; liquidation preference US$710m.
A69: Series E-4 | B69: 15343 | C69: 50.48 | E69: Carrying value US$986m; liquidation preference US$774m.
A70: Series E-5 | B70: 24244 | C70: 53.28 | E70: Carrying value US$1,598m; liquidation preference US$1,292m.
... A78: Series H-2 | B78: 33110 | C78: 589.01 | E78: Carrying value US$19,502m; liquidation preference US$19,502m.
A80: F. Fair value of common stock used for option grants (Note 11)
B81: Low (USD) | C81: High (USD)
A82: 2023 | B82: 0.51 | C82: 1.08 | E82: Note 11, weighted-average assumptions table
A83: 2024 | B83: 1.3 | C83: 2.23 | E83: Note 11, weighted-average assumptions table
A84: 2025 | B84: 3.45 | C84: 16.69 | E84: Note 11, weighted-average assumptions table
A85: Six months to 30 Jun 2026 | B85: 21.56 | C85: 57.14 | E85: Note 11, weighted-average assumptions table
A86: RSUs granted in the six months to 30 Jun 2026: grant-date fair value (USD) | C86: 46.48 | E86: Note 11, RSU activity table
A88: Checks (zero passes)
A89: Preferred as converted equals the anti-dilutive table (8,558,869) | B89: =B36-8558869 -> 0
A90: Class A and N shares equal the equity statement | B90: =B7-SCE_Hist!D55+B8-SCE_Hist!F55 -> 0

Sheet Assumptions
A1: Anthropic, PBC | Assumptions and scenarios
A2: Blue cells are inputs. Each driver has Base, Bull and Bear rows; the Active row follows the switch in C5. USD millions unless stated.
B3: Actual | C3: Forecast
A4: Fiscal year ends 31 December | B4: 2025A | C4: 2026E | D4: 2027E | E4: 2028E | F4: 2029E | G4: 2030E | H4: 2031E | I4: 2032E | J4: 2033E | K4: 2034E | L4: 2035E | M4: Comentarios FG | N4: Source / derivation
A5: Scenario switch: 1 = Base, 2 = Bull, 3 = Bear | C5: 1 | N5: Same convention as the house templates (Supuestos!C5).
A6: Active scenario | C6: =CHOOSE(C5,"Base","Bull","Bear") -> Base
A8: A. Second half of 2026 and valuation inputs (one value per scenario)
C9: Active | D9: Base | E9: Bull | F9: Bear
A10: Q3 2026E revenue (USD m) | C10: =CHOOSE($C$5,D10,E10,F10) -> 17500 | D10: 17500 | E10: 19000 | F10: 16700 | N10: S-1 floor: TTM revenue per employee 'over $6.6 million' x about 5,300 employees = TTM revenue above US$34,980m, so Q3 2026 is above US$16,654m (Revenue_Hist). Bear = the floor. Press: July 2026 run-rate above US$65bn (Reuters, 17 Aug 2026; not in the S-1).
A11: Q4 2026E revenue (USD m) | C11: =CHOOSE($C$5,D11,E11,F11) -> 21000 | D11: 21000 | E11: 25000 | F11: 17500 | N11: Base +20% on Q3 2026E; Bull +32%; Bear +5%. Q2 2026 grew 144% on Q1 (S-1). Analyst input.
A12: H2 2026E compute and infrastructure: % of revenue | C12: =CHOOSE($C$5,D12,E12,F12) -> 0.5 | D12: 0.5 | E12: 0.47 | F12: 0.54 | N12: Q2 2026 48.1% (S-1); the S-1 expects more short-term compute in the near term. Analyst input.
A13: H2 2026E personnel, cash part: % of revenue | C13: =CHOOSE($C$5,D13,E13,F13) -> 0.05 | D13: 0.05 | E13: 0.05 | F13: 0.055 | N13: Q2 2026 5.2% (S-1). Analyst input.
A14: H2 2026E sales, marketing and partnerships: % of revenue | C14: =CHOOSE($C$5,D14,E14,F14) -> 0.18 | D14: 0.18 | E14: 0.17 | F14: 0.19 | N14: Q2 2026 18.5% (S-1). Analyst input.
A15: H2 2026E other operating and administrative: % of revenue | C15: =CHOOSE($C$5,D15,E15,F15) -> 0.085 | D15: 0.085 | E15: 0.08 | F15: 0.09 | N15: Q2 2026 8.9% (S-1). Analyst input.
A16: Terminal growth (after 2035E) | C16: =CHOOSE($C$5,D16,E16,F16) -> 0.03 | D16: 0.03 | E16: 0.035 | F16: 0.025 | N16: Below the 10-year Treasury yield (5.00%); near long-run nominal GDP. Analyst input.
A17: Terminal return on new invested capital | C17: =CHOOSE($C$5,D17,E17,F17) -> 0.25 | D17: 0.25 | E17: 0.35 | F17: 0.15 | N17: Reinvestment = growth / ROIC (Damodaran). Mature software and platform returns 20%-40%. Analyst input.
A18: Exit EV / EBITDA multiple (2035E) | C18: =CHOOSE($C$5,D18,E18,F18) -> 15 | D18: 15 | E18: 18 | F18: 12 | N18: Cross-check only. AI platform peers today: Microsoft 20.6x, Alphabet 21.7x, Meta 14.2x LTM EV/EBITDA (stockanalysis.com, 26 Oct 2026). A 2035 exit sees lower growth. Analyst input.
A20: B. Inputs that do not change with the scenario
A21: H2 2026E stock-based compensation before the IPO catch-up (USD m) | C21: 2600 | N21: Q2 2026 1,261 (S-1), about 1,300 a quarter.
A22: Q4 2026E one-off RSU charge at the IPO (USD m) | C22: 2900 | N22: S-1: of US$26.6bn unrecognized RSU cost at 30 Jun 2026, 'US$2.9 billion relates to RSUs for which the service-based vesting condition had been satisfied or partially satisfied'; recorded when the S-1 becomes effective. Assumes an IPO before 31 Dec 2026.
A23: H2 2026E capital expenditures incl. finance-lease principal (USD m) | C23: 1500 | N23: 6M 2026 482 plus 148 accrued, unpaid (S-1). Anthropic Direct ramps. Analyst input.
A24: H2 2026E change in fair value of notes and other financial items (USD m) | C24: 0 | N24: Non-cash; stops when the notes convert at the IPO. The S-1 gives no estimate. Set to zero (no effect on cash or value).
A25: IPO primary proceeds to the company (USD m) | C25: 0 | N25: Price range and share count blank in the S-1. Kept at zero: new shares sold near fair value change value per share very little.
A26: Interest income yield on cash and short-term investments | C26: 0.035 | N26: 6M 2026 realized about 2.9% on average balances (S-1); 3-month bill 4.22% (Treasury, 26 Oct 2026). Analyst input.
A27: Cash tax rate on taxable income after loss carryforwards | C27: 0.21 | N27: US federal 21%; state taxes offset by research credits (S-1 tax note: R&D credit deferred tax asset 656). Analyst input.
A28: Deferred tax asset for net operating losses, 31 Dec 2025 (USD m) | C28: 2007 | N28: S-1 income tax note (fully reserved by the valuation allowance).
A29: Share of taxable income that loss carryforwards can offset | C29: 0.8 | N29: US federal limit for losses arising after 2017.
A30: Accounts receivable: % of revenue | C30: 0.18 | N30: 30 Jun 2026: 5,833 / (2 x 6M revenue 16,286) = 17.9% (S-1).
A31: Prepaid expenses and other current assets: % of revenue | C31: 0.015 | N31: 30 Jun 2026: 496 / 32,572 = 1.5% (S-1).
A32: Deferred revenue: % of revenue | C32: 0.05 | N32: 30 Jun 2026: 1,650 / 32,572 = 5.1% (S-1).
... A36: Sensitivity: compute cost shift, all years 2027E-2035E (pp of revenue) | C36: 0 | N36: Keep at 0. The Sensitivity sheet moves it.
A37: Net operating loss carryforwards, 31 Dec 2025, estimate (USD m) | C37: =C28/C27 -> 9557.1429 | N37: Deferred tax asset / 21%. The S-1 gives the tax asset, not the gross loss; mixed federal and state rates make this an estimate.
A39: C. Drivers by year (Base, Bull, Bear and the active row)
A40: Revenue: growth on a year earlier | N40: 2025A +1,088%; 6M 2026 +1,300% (S-1). The S-1 says growth will decline, possibly fast. Base 2027E: Q4 2026E run-rate (US$84bn) plus about 35% growth over 2027. Base 2028E (US$182bn) sits below the US$190-200bn the company reportedly gave investors (Reuters, 15 Aug 2026; not in the S-1); Bull reaches it. Analyst input.
A41: Base | D41: 1.1 | E41: 0.6 | F41: 0.38 | G41: 0.27 | H41: 0.2 | I41: 0.15 | J41: 0.12 | K41: 0.1 | L41: 0.08
A42: Bull | D42: 1.25 | E42: 0.7 | F42: 0.45 | G42: 0.32 | H42: 0.24 | I42: 0.18 | J42: 0.14 | K42: 0.11 | L42: 0.09
A43: Bear | D43: 0.7 | E43: 0.35 | F43: 0.22 | G43: 0.15 | H43: 0.11 | I43: 0.09 | J43: 0.07 | K43: 0.06 | L43: 0.05
A44: Active | D44: =CHOOSE($C$5,D41,D42,D43) -> 1.1 | E44: =CHOOSE($C$5,E41,E42,E43) -> 0.6 | F44: =CHOOSE($C$5,F41,F42,F43) -> 0.38 | G44: =CHOOSE($C$5,G41,G42,G43) -> 0.27 | H44: =CHOOSE($C$5,H41,H42,H43) -> 0.2 | I44: =CHOOSE($C$5,I41,I42,I43) -> 0.15 | J44: =CHOOSE($C$5,J41,J42,J43) -> 0.12 | K44: =CHOOSE($C$5,K41,K42,K43) -> 0.1 | L44: =CHOOSE($C$5,L41,L42,L43) -> 0.08
A45: Compute and infrastructure: % of revenue | N45: 2025A 159.8%; 6M 2026 54.9%; Q2 2026 48.1% (S-1). The S-1 warns that margins may compress as new compute comes online and as short-term compute rises. Includes CSP fees and all depreciation of owned infrastructure. Analyst input.
A46: Base | D46: 0.5 | E46: 0.48 | F46: 0.46 | G46: 0.44 | H46: 0.42 | I46: 0.41 | J46: 0.4 | K46: 0.4 | L46: 0.4
A47: Bull | D47: 0.47 | E47: 0.44 | F47: 0.41 | G47: 0.39 | H47: 0.37 | I47: 0.36 | J47: 0.35 | K47: 0.35 | L47: 0.35
A48: Bear | D48: 0.56 | E48: 0.55 | F48: 0.53 | G48: 0.51 | H48: 0.5 | I48: 0.49 | J48: 0.48 | K48: 0.48 | L48: 0.48
A49: Active | D49: =CHOOSE($C$5,D46,D47,D48) -> 0.5 | E49: =CHOOSE($C$5,E46,E47,E48) -> 0.48 | F49: =CHOOSE($C$5,F46,F47,F48) -> 0.46 | G49: =CHOOSE($C$5,G46,G47,G48) -> 0.44 | H49: =CHOOSE($C$5,H46,H47,H48) -> 0.42 | I49: =CHOOSE($C$5,I46,I47,I48) -> 0.41 | J49: =CHOOSE($C$5,J46,J47,J48) -> 0.4 | K49: =CHOOSE($C$5,K46,K47,K48) -> 0.4 | L49: =CHOOSE($C$5,L46,L47,L48) -> 0.4
A50: Personnel, cash part (excluding stock-based compensation): % of revenue | N50: Q2 2026: personnel 1,857 less stock-based compensation 1,261 = 596, or 5.2% of revenue (S-1 quarterly tables). About 5,300 employees at 30 Sep 2026 (S-1). Analyst input.
A51: Base | D51: 0.05 | E51: 0.05 | F51: 0.045 | G51: 0.045 | H51: 0.045 | I51: 0.04 | J51: 0.04 | K51: 0.04 | L51: 0.04
A52: Bull | D52: 0.045 | E52: 0.045 | F52: 0.04 | G52: 0.04 | H52: 0.04 | I52: 0.035 | J52: 0.035 | K52: 0.035 | L52: 0.035
A53: Bear | D53: 0.055 | E53: 0.055 | F53: 0.05 | G53: 0.05 | H53: 0.05 | I53: 0.045 | J53: 0.045 | K53: 0.045 | L53: 0.045
A54: Active | D54: =CHOOSE($C$5,D51,D52,D53) -> 0.05 | E54: =CHOOSE($C$5,E51,E52,E53) -> 0.05 | F54: =CHOOSE($C$5,F51,F52,F53) -> 0.045 | G54: =CHOOSE($C$5,G51,G52,G53) -> 0.045 | H54: =CHOOSE($C$5,H51,H52,H53) -> 0.045 | I54: =CHOOSE($C$5,I51,I52,I53) -> 0.04 | J54: =CHOOSE($C$5,J51,J52,J53) -> 0.04 | K54: =CHOOSE($C$5,K51,K52,K53) -> 0.04 | L54: =CHOOSE($C$5,L51,L52,L53) -> 0.04
A55: Stock-based compensation: % of revenue | N55: 6M 2026 13.4%. Unrecognized at 30 Jun 2026: RSUs US$26.6bn, options US$2.8bn (S-1); RSU expense starts at the IPO. Base 2027E = US$11.4bn. Treated as a real cost in the DCF (not added back). Analyst input.
A56: Base | D56: 0.1 | E56: 0.08 | F56: 0.07 | G56: 0.06 | H56: 0.055 | I56: 0.05 | J56: 0.05 | K56: 0.045 | L56: 0.045
A57: Bull | D57: 0.09 | E57: 0.07 | F57: 0.06 | G57: 0.055 | H57: 0.05 | I57: 0.045 | J57: 0.045 | K57: 0.04 | L57: 0.04
A58: Bear | D58: 0.12 | E58: 0.1 | F58: 0.09 | G58: 0.08 | H58: 0.07 | I58: 0.065 | J58: 0.06 | K58: 0.06 | L58: 0.06
A59: Active | D59: =CHOOSE($C$5,D56,D57,D58) -> 0.1 | E59: =CHOOSE($C$5,E56,E57,E58) -> 0.08 | F59: =CHOOSE($C$5,F56,F57,F58) -> 0.07 | G59: =CHOOSE($C$5,G56,G57,G58) -> 0.06 | H59: =CHOOSE($C$5,H56,H57,H58) -> 0.055 | I59: =CHOOSE($C$5,I56,I57,I58) -> 0.05 | J59: =CHOOSE($C$5,J56,J57,J58) -> 0.05 | K59: =CHOOSE($C$5,K56,K57,K58) -> 0.045 | L59: =CHOOSE($C$5,L56,L57,L58) -> 0.045
A60: Sales, marketing and partnerships: % of revenue | N60: 6M 2026 19% (S-1: 'sales, marketing, and partnerships expenses representing 19% of revenue'); Q2 2026 18.5%. Includes fees paid to cloud partners. Analyst input.
A61: Base | D61: 0.16 | E61: 0.14 | F61: 0.12 | G61: 0.11 | H61: 0.1 | I61: 0.09 | J61: 0.09 | K61: 0.08 | L61: 0.08
A62: Bull | D62: 0.15 | E62: 0.12 | F62: 0.1 | G62: 0.09 | H62: 0.08 | I62: 0.08 | J62: 0.07 | K62: 0.07 | L62: 0.07
A63: Bear | D63: 0.18 | E63: 0.17 | F63: 0.16 | G63: 0.15 | H63: 0.14 | I63: 0.13 | J63: 0.12 | K63: 0.12 | L63: 0.12
A64: Active | D64: =CHOOSE($C$5,D61,D62,D63) -> 0.16 | E64: =CHOOSE($C$5,E61,E62,E63) -> 0.14 | F64: =CHOOSE($C$5,F61,F62,F63) -> 0.12 | G64: =CHOOSE($C$5,G61,G62,G63) -> 0.11 | H64: =CHOOSE($C$5,H61,H62,H63) -> 0.1 | I64: =CHOOSE($C$5,I61,I62,I63) -> 0.09 | J64: =CHOOSE($C$5,J61,J62,J63) -> 0.09 | K64: =CHOOSE($C$5,K61,K62,K63) -> 0.08 | L64: =CHOOSE($C$5,L61,L62,L63) -> 0.08
A65: Other operating and administrative: % of revenue | N65: 6M 2026 10.5%; Q2 2026 8.9% (S-1). Includes non-cash charitable contributions (donation matching). Analyst input.
A66: Base | D66: 0.075 | E66: 0.065 | F66: 0.06 | G66: 0.055 | H66: 0.05 | I66: 0.05 | J66: 0.045 | K66: 0.045 | L66: 0.045
A67: Bull | D67: 0.07 | E67: 0.06 | F67: 0.055 | G67: 0.05 | H67: 0.045 | I67: 0.045 | J67: 0.04 | K67: 0.04 | L67: 0.04
A68: Bear | D68: 0.085 | E68: 0.08 | F68: 0.075 | G68: 0.07 | H68: 0.065 | I68: 0.065 | J68: 0.065 | K68: 0.065 | L68: 0.065
A69: Active | D69: =CHOOSE($C$5,D66,D67,D68) -> 0.075 | E69: =CHOOSE($C$5,E66,E67,E68) -> 0.065 | F69: =CHOOSE($C$5,F66,F67,F68) -> 0.06 | G69: =CHOOSE($C$5,G66,G67,G68) -> 0.055 | H69: =CHOOSE($C$5,H66,H67,H68) -> 0.05 | I69: =CHOOSE($C$5,I66,I67,I68) -> 0.05 | J69: =CHOOSE($C$5,J66,J67,J68) -> 0.045 | K69: =CHOOSE($C$5,K66,K67,K68) -> 0.045 | L69: =CHOOSE($C$5,L66,L67,L68) -> 0.045
A70: Capital expenditures incl. finance-lease principal: % of revenue | N70: 6M 2026 3.0% (purchases of property and equipment 482, S-1). Anthropic Direct (leased chips in dedicated facilities, S-1) raises owned and finance-leased infrastructure. Bear: commitments are fixed 12-18 months ahead (S-1), so spend falls slower than revenue. Analyst input.
A71: Base | D71: 0.06 | E71: 0.08 | F71: 0.08 | G71: 0.07 | H71: 0.06 | I71: 0.06 | J71: 0.05 | K71: 0.05 | L71: 0.05
A72: Bull | D72: 0.06 | E72: 0.08 | F72: 0.08 | G72: 0.07 | H72: 0.06 | I72: 0.06 | J72: 0.05 | K72: 0.05 | L72: 0.05
A73: Bear | D73: 0.08 | E73: 0.1 | F73: 0.1 | G73: 0.09 | H73: 0.08 | I73: 0.07 | J73: 0.06 | K73: 0.06 | L73: 0.06
A74: Active | D74: =CHOOSE($C$5,D71,D72,D73) -> 0.06 | E74: =CHOOSE($C$5,E71,E72,E73) -> 0.08 | F74: =CHOOSE($C$5,F71,F72,F73) -> 0.08 | G74: =CHOOSE($C$5,G71,G72,G73) -> 0.07 | H74: =CHOOSE($C$5,H71,H72,H73) -> 0.06 | I74: =CHOOSE($C$5,I71,I72,I73) -> 0.06 | J74: =CHOOSE($C$5,J71,J72,J73) -> 0.05 | K74: =CHOOSE($C$5,K71,K72,K73) -> 0.05 | L74: =CHOOSE($C$5,L71,L72,L73) -> 0.05

Sheet Interim_Bridge
A1: Anthropic, PBC | 2026E bridge: six months actual plus a second-half estimate
A2: 6M columns link to the S-1 statements; H2 2026E comes from the inputs on Assumptions. Balance sheet rows: 6M 2026A = 30 Jun 2026, FY2026E = 31 Dec 2026E. USD millions.
A4: Line | B4: 6M 2026A | C4: H2 2026E | D4: FY2026E | E4: 6M 2025A | F4: H2 2025A | G4: FY2025A | H4: Comentarios FG | I4: Source / derivation
A6: Income statement
A7: Revenue | B7: =IS_Hist!F6 -> 16286 | C7: =C8+C9 -> 38500 | D7: =B7+C7 -> 54786 | E7: =IS_Hist!E6 -> 1163 | F7: =G7-E7 -> 3422 | G7: =IS_Hist!D6 -> 4585
A8: Q3 2026E revenue | C8: =Assumptions!$C$10 -> 17500
A9: Q4 2026E revenue | C9: =Assumptions!$C$11 -> 21000
A10: Compute and infrastructure | B10: =IS_Hist!F9 -> 8945 | C10: =C7*Assumptions!$C$12 -> 19250 | D10: =B10+C10 -> 28195 | E10: =IS_Hist!E9 -> 2334 | F10: =G10-E10 -> 4992 | G10: =IS_Hist!D9 -> 7326
A11: Stock-based compensation (memo; inside personnel) | B11: =CF_Hist!F10 -> 2185 | C11: =Assumptions!$C$21+Assumptions!$C$22 -> 5500 | D11: =B11+C11 -> 7685 | E11: =CF_Hist!E10 -> 279 | F11: =G11-E11 -> 879 | G11: =CF_Hist!D10 -> 1158 | I11: H2 2026E includes the one-off RSU charge at the IPO.
A12: Personnel, cash part (memo) | B12: =IS_Hist!F10-B11 -> 967 | C12: =C7*Assumptions!$C$13 -> 1925 | D12: =B12+C12 -> 2892 | E12: =IS_Hist!E10-E11 -> 259 | F12: =G12-E12 -> 422 | G12: =IS_Hist!D10-G11 -> 681
A13: Personnel | B13: =IS_Hist!F10 -> 3152 | C13: =C12+C11 -> 7425 | D13: =B13+C13 -> 10577 | E13: =IS_Hist!E10 -> 538 | F13: =G13-E13 -> 1301 | G13: =IS_Hist!D10 -> 1839
A14: Bartz settlement | B14: =IS_Hist!F11 -> 0 | C14: 0 | D14: =B14+C14 -> 0 | E14: =IS_Hist!E11 -> 0 | F14: =G14-E14 -> 1500 | G14: =IS_Hist!D11 -> 1500
A15: Sales, marketing, and partnerships | B15: =IS_Hist!F12 -> 3168 | C15: =C7*Assumptions!$C$14 -> 6930 | D15: =B15+C15 -> 10098 | E15: =IS_Hist!E12 -> 120 | F15: =G15-E15 -> 448 | G15: =IS_Hist!D12 -> 568
A16: Other operating and administrative | B16: =IS_Hist!F13 -> 1714 | C16: =C7*Assumptions!$C$15 -> 3272.5 | D16: =B16+C16 -> 4986.5 | E16: =IS_Hist!E13 -> 306 | F16: =G16-E16 -> 1106 | G16: =IS_Hist!D13 -> 1412
A17: Total operating expenses | B17: =B10+B13+B14+B15+B16 -> 16979 | C17: =C10+C13+C14+C15+C16 -> 36877.5 | D17: =B17+C17 -> 53856.5 | E17: =E10+E13+E14+E15+E16 -> 3298 | F17: =G17-E17 -> 9347 | G17: =G10+G13+G14+G15+G16 -> 12645
A18: Operating income (loss) | B18: =B7-B17 -> -693 | C18: =C7-C17 -> 1622.5 | D18: =B18+C18 -> 929.5 | E18: =E7-E17 -> -2135 | F18: =G18-E18 -> -5925 | G18: =G7-G17 -> -8060
A19: Depreciation and amortization (memo; inside the costs above) | B19: =CF_Hist!F11 -> 97 | C19: =(BS_Hist!D15+0.5*Assumptions!$C$23)/Assumptions!$C$34*0.5 -> 193.7 | D19: =B19+C19 -> 290.7 | E19: =CF_Hist!E11 -> 14 | F19: =G19-E19 -> 26 | G19: =CF_Hist!D11 -> 40 | I19: H2 2026E: (PP&E at 30 Jun 2026 + half the H2 capex) / average life x half a year.
A20: Non-cash charitable contributions (memo) | B20: =Revenue_Hist!F37 -> 126 | C20: 0 | D20: =B20+C20 -> 126 | E20: =Revenue_Hist!E37 -> 0 | F20: =G20-E20 -> 541 | G20: =Revenue_Hist!D37 -> 541
A21: Adjusted operating income (company definition) | B21: =B18+B11+B20+B14 -> 1618 | C21: =C18+C11+C20+C14 -> 7122.5 | D21: =B21+C21 -> 8740.5 | E21: =E18+E11+E20+E14 -> -1856 | F21: =G21-E21 -> -3005 | G21: =G18+G11+G20+G14 -> -4861
A22: Interest income | B22: =IS_Hist!F16 -> 1111 | C22: =Assumptions!$C$26*B44*0.5 -> 2303.8925 | D22: =B22+C22 -> 3414.8925 | E22: =IS_Hist!E16 -> 115 | F22: =G22-E22 -> 316 | G22: =IS_Hist!D16 -> 431
A23: Change in fair value of notes and other items | B23: =IS_Hist!F17+IS_Hist!F18 -> -81145 | C23: =Assumptions!$C$24 -> 0 | D23: =B23+C23 -> -81145 | E23: =IS_Hist!E17+IS_Hist!E18 -> -10942 | F23: =G23-E23 -> -23374 | G23: =IS_Hist!D17+IS_Hist!D18 -> -34316
A24: Income (loss) before income taxes | B24: =B18+B22+B23 -> -80727 | C24: =C18+C22+C23 -> 3926.3925 | D24: =B24+C24 -> -76800.607 | E24: =E18+E22+E23 -> -12962 | F24: =G24-E24 -> -28983 | G24: =G18+G22+G23 -> -41945
A25: Provision for income taxes | B25: =IS_Hist!F21 -> 21 | C25: =MAX(0,Schedules!C20-B25) -> 161.46448 | D25: =B25+C25 -> 182.46448 | E25: =IS_Hist!E21 -> 7 | F25: =G25-E25 -> 13 | G25: =IS_Hist!D21 -> 20 | I25: FY2026E tax from the loss-carryforward schedule (Schedules) less the six-month actual.
A26: Net income (loss) | B26: =B24-B25 -> -80748 | C26: =C24-C25 -> 3764.928 | D26: =B26+C26 -> -76983.072 | E26: =E24-E25 -> -12969 | F26: =G26-E26 -> -28996 | G26: =G24-G25 -> -41965
A28: Cash flow (6M 2026A as filed; H2 2026E from the rows above and the balance sheet below)
A29: Net income (loss) | B29: =CF_Hist!F7 -> -80748 | C29: =C26 -> 3764.928 | D29: =B29+C29 -> -76983.072
A30: Depreciation and amortization | B30: =CF_Hist!F11 -> 97 | C30: =C19 -> 193.7 | D30: =B30+C30 -> 290.7
A31: Stock-based compensation | B31: =CF_Hist!F10 -> 2185 | C31: =C11 -> 5500 | D31: =B31+C31 -> 7685
A32: Fair value changes and other non-cash items | B32: =CF_Hist!F12+CF_Hist!F13+CF_Hist!F14+CF_Hist!F15 -> 81227 | C32: =-C23 -> 0 | D32: =B32+C32 -> 81227
A33: Changes in operating assets and liabilities | B33: =CF_Hist!F18+CF_Hist!F19+CF_Hist!F20+CF_Hist!F21+CF_Hist!F22 -> 1168 | C33: =-(D45-B45)-(D46-B46)+(D50-B50)+(D51-B51) -> -228.47 | D33: =B33+C33 -> 939.53
A34: Net cash from operating activities | B34: =B29+B30+B31+B32+B33 -> 3929 | C34: =C29+C30+C31+C32+C33 -> 9230.158 | D34: =B34+C34 -> 13159.158
A35: Capital expenditures | B35: =CF_Hist!F26 -> -482 | C35: =-Assumptions!$C$23 -> -1500 | D35: =B35+C35 -> -1982
A36: Other investing (excluding short-term investment flows) | B36: =CF_Hist!F29 -> -337 | C36: 0 | D36: =B36+C36 -> -337
A37: Net cash from financing activities | B37: =CF_Hist!F40 -> 110774 | C37: =Assumptions!$C$25 -> 0 | D37: =B37+C37 -> 110774 | I37: 6M 2026A: Series G and H proceeds US$110.4bn. H2 2026E: IPO primary proceeds input (zero).
A38: Restricted cash, exchange rates and investment marks (balancing item) | B38: =B44-B40-(B34+B35+B36+B37) -> -2510 | C38: 0 | D38: =B38+C38 -> -2510 | I38: 6M 2026A: restricted cash rose 2,516 (Broadcom and lease deposits), FX -5, investment marks 11.
A39: Net change in cash and short-term investments | B39: =B34+B35+B36+B37+B38 -> 111374 | C39: =C34+C35+C36+C37+C38 -> 7730.158 | D39: =B39+C39 -> 119104.16
A40: Cash and short-term investments, beginning | B40: =BS_Hist!C45 -> 20277 | C40: =B44 -> 131651 | D40: =B40 -> 20277
A41: Cash and short-term investments, ending | B41: =B40+B39 -> 131651 | C41: =C40+C39 -> 139381.16 | D41: =C41 -> 139381.16
A43: Balance sheet: 30 Jun 2026A (column B) to 31 Dec 2026E (column D)
A44: Cash and short-term investments | B44: =BS_Hist!D45 -> 131651 | D44: =C41 -> 139381.16
A45: Accounts receivable | B45: =BS_Hist!D11 -> 5833 | D45: =D7*Assumptions!$C$30 -> 9861.48
A46: Prepaid expenses and other current assets | B46: =BS_Hist!D12 -> 496 | D46: =D7*Assumptions!$C$31 -> 821.79
A47: Property and equipment, net | B47: =BS_Hist!D15 -> 1187 | D47: =B47+Assumptions!$C$23-C19 -> 2493.3
A48: Restricted cash, lease assets, goodwill and other assets | B48: =BS_Hist!D14+BS_Hist!D16+BS_Hist!D17+BS_Hist!D18 -> 8191 | D48: =B48 -> 8191 | I48: Held flat.
A49: Total assets | B49: =B44+B45+B46+B47+B48 -> 147358 | D49: =D44+D45+D46+D47+D48 -> 160748.73
A50: Accounts payable, accrued and other current liabilities | B50: =BS_Hist!D23 -> 5422 | D50: =D10*Assumptions!$C$33 -> 8458.5
A51: Deferred revenue | B51: =BS_Hist!D25 -> 1650 | D51: =D7*Assumptions!$C$32 -> 2739.3
A52: Operating lease and other noncurrent liabilities | B52: =BS_Hist!D24+BS_Hist!D27+BS_Hist!D29 -> 1829 | D52: =B52 -> 1829 | I52: Held flat.
A53: Convertible notes payable | B53: =BS_Hist!D28 -> 108566 | D53: 0 | I53: Convert into 1,840m Class N shares at the IPO (S-1), assumed before 31 Dec 2026.
A54: Total liabilities | B54: =B50+B51+B52+B53 -> 117467 | D54: =D50+D51+D52+D53 -> 13026.8
A55: Redeemable convertible preferred stock | B55: =BS_Hist!D32 -> 157510 | D55: 0 | I55: Converts into common stock at the IPO (S-1).
A56: Stockholders' equity (deficit) | B56: =BS_Hist!D41 -> -127619 | D56: =B56+C26+C11+(B53-C23)+B55+C37 -> 147721.93 | I56: Adds H2 net income, stock-based compensation, the notes at conversion value and the preferred stock.
A57: Total liabilities, preferred stock and equity | B57: =B54+B55+B56 -> 147358 | D57: =D54+D55+D56 -> 160748.73
A59: Checks (zero passes)
A60: Balance sheet balances | B60: =B49-B57 -> 0 | D60: =D49-D57 -> 0
A61: 46203 | B61: =B49-BS_Hist!D19 -> 0
A62: 6M 2026 operating cash flow equals the S-1 | B62: =B34-CF_Hist!F23 -> 0
A63: 6M 2026 net loss equals the S-1 | B63: =B26-IS_Hist!F22 -> 0
A64: 6M 2025 net loss equals the S-1 | E64: =E26-IS_Hist!E22 -> 0 | G64: =G26-IS_Hist!D22 -> 0

Sheet Schedules
A1: Anthropic, PBC | Schedules: capex and depreciation, loss carryforwards and taxes, working capital, unlevered free cash flow
A2: 2026E is the full year (six months actual plus the H2 estimate). USD millions.
B3: Actual | C3: Forecast
A4: Fiscal year ends 31 December | B4: 2025A | C4: 2026E | D4: 2027E | E4: 2028E | F4: 2029E | G4: 2030E | H4: 2031E | I4: 2032E | J4: 2033E | K4: 2034E | L4: 2035E | M4: Comentarios FG | N4: Source / derivation
A6: A. Capital expenditures and property and equipment
A7: Capital expenditures | B7: =-CF_Hist!D26 -> 131 | C7: =-CF_Hist!F26+Assumptions!$C$23 -> 1982 | D7: =Forecast_3Stmt!D7*Assumptions!D74 -> 6903.036 | E7: =Forecast_3Stmt!E7*Assumptions!E74 -> 14726.477 | F7: =Forecast_3Stmt!F7*Assumptions!F74 -> 20322.538 | G7: =Forecast_3Stmt!G7*Assumptions!G74 -> 22583.42 | H7: =Forecast_3Stmt!H7*Assumptions!H74 -> 23228.661 | I7: =Forecast_3Stmt!I7*Assumptions!I74 -> 26712.96 | J7: =Forecast_3Stmt!J7*Assumptions!J74 -> 24932.096 | K7: =Forecast_3Stmt!K7*Assumptions!K74 -> 27425.306 | L7: =Forecast_3Stmt!L7*Assumptions!L74 -> 29619.33
A8: % of revenue | B8: =B7/Forecast_3Stmt!B7 -> 0.028571429 | C8: =C7/Forecast_3Stmt!C7 -> 0.036177126 | D8: =D7/Forecast_3Stmt!D7 -> 0.06 | E8: =E7/Forecast_3Stmt!E7 -> 0.08 | F8: =F7/Forecast_3Stmt!F7 -> 0.08 | G8: =G7/Forecast_3Stmt!G7 -> 0.07 | H8: =H7/Forecast_3Stmt!H7 -> 0.06 | I8: =I7/Forecast_3Stmt!I7 -> 0.06 | ... L8: =L7/Forecast_3Stmt!L7 -> 0.05
A9: Property and equipment, beginning | C9: =B12 -> 146 | D9: =C12 -> 2493.3 | E9: =D12 -> 8207.3724 | F9: =E12 -> 19819.727 | G9: =F12 -> 34146.066 | H9: =G12 -> 47641.931 | I9: =H12 -> 59019.34 | J9: =I12 -> 71257.136 | ... L9: =K12 -> 88238.451
A10: Depreciation and amortization | B10: =CF_Hist!D11 -> 40 | C10: =Interim_Bridge!D19 -> 290.7 | D10: =(D9+0.5*D7)/Assumptions!$C$34 -> 1188.9636 | E10: =(E9+0.5*E7)/Assumptions!$C$34 -> 3114.1222 | F10: =(F9+0.5*F7)/Assumptions!$C$34 -> 5996.1992 | G10: =(G9+0.5*G7)/Assumptions!$C$34 -> 9087.5552 | H10: =(H9+0.5*H7)/Assumptions!$C$34 -> 11851.252 | I10: =(I9+0.5*I7)/Assumptions!$C$34 -> 14475.164 | J10: =(J9+0.5*J7)/Assumptions!$C$34 -> 16744.637 | K10: =(K9+0.5*K7)/Assumptions!$C$34 -> 18631.45 | L10: =(L9+0.5*L7)/Assumptions!$C$34 -> 20609.623 | N10: (Beginning PP&E + half the year's capex) / average life.
A11: Other additions (finance-lease assets, acquisitions, accrued capex) | C11: =C12-C9-C7+C10 -> 656 | D11: =0 -> 0 | E11: =0 -> 0 | F11: =0 -> 0 | G11: =0 -> 0 | H11: =0 -> 0 | I11: =0 -> 0 | J11: =0 -> 0 | K11: =0 -> 0 | L11: =0 -> 0 | N11: 2026E: balancing item to the 31 Dec 2026E balance (6M 2026: finance-lease assets 445, accrued capex 148).
A12: Property and equipment, ending | B12: =BS_Hist!C15 -> 146 | C12: =Interim_Bridge!D47 -> 2493.3 | D12: =D9+D7+D11-D10 -> 8207.3724 | E12: =E9+E7+E11-E10 -> 19819.727 | F12: =F9+F7+F11-F10 -> 34146.066 | G12: =G9+G7+G11-G10 -> 47641.931 | H12: =H9+H7+H11-H10 -> 59019.34 | I12: =I9+I7+I11-I10 -> 71257.136 | J12: =J9+J7+J11-J10 -> 79444.595 | K12: =K9+K7+K11-K10 -> 88238.451 | L12: =L9+L7+L11-L10 -> 97248.158
A14: B. Loss carryforwards and cash taxes
A15: Taxable income before loss carryforwards (operating income + interest income) | C15: =Forecast_3Stmt!C17+Forecast_3Stmt!C19 -> 4344.3925 | D15: =Forecast_3Stmt!D17+Forecast_3Stmt!D19 -> 18109.16 | E15: =Forecast_3Stmt!E17+Forecast_3Stmt!E19 -> 39683.546 | F15: =Forecast_3Stmt!F17+Forecast_3Stmt!F19 -> 69046.009 | G15: =Forecast_3Stmt!G17+Forecast_3Stmt!G19 -> 102342.4 | H15: =Forecast_3Stmt!H17+Forecast_3Stmt!H19 -> 139490.51 | I15: =Forecast_3Stmt!I17+Forecast_3Stmt!I19 -> 176103.94 | J15: =Forecast_3Stmt!J17+Forecast_3Stmt!J19 -> 207951.61 | ... L15: =Forecast_3Stmt!L17+Forecast_3Stmt!L19 -> 265413.56 | N15: Fair value changes on the notes are treated as neither taxable nor deductible.
A16: Loss carryforwards, beginning | C16: =Assumptions!$C$37 -> 9557.1429 | D16: =C19 -> 6081.6289 | E16: =D19 -> 0 | F16: =E19 -> 0 | G16: =F19 -> 0 | H16: =G19 -> 0 | I16: =H19 -> 0 | J16: =I19 -> 0 | K16: =J19 -> 0 | L16: =K19 -> 0
A17: Used | C17: =MIN(C16,MAX(0,C15)*Assumptions!$C$29) -> 3475.514 | D17: =MIN(D16,MAX(0,D15)*Assumptions!$C$29) -> 6081.6289 | E17: =MIN(E16,MAX(0,E15)*Assumptions!$C$29) -> 0 | F17: =MIN(F16,MAX(0,F15)*Assumptions!$C$29) -> 0 | G17: =MIN(G16,MAX(0,G15)*Assumptions!$C$29) -> 0 | H17: =MIN(H16,MAX(0,H15)*Assumptions!$C$29) -> 0 | I17: =MIN(I16,MAX(0,I15)*Assumptions!$C$29) -> 0 | J17: =MIN(J16,MAX(0,J15)*Assumptions!$C$29) -> 0 | ... L17: =MIN(L16,MAX(0,L15)*Assumptions!$C$29) -> 0
A18: Added | C18: =MAX(0,-C15) -> 0 | D18: =MAX(0,-D15) -> 0 | E18: =MAX(0,-E15) -> 0 | F18: =MAX(0,-F15) -> 0 | G18: =MAX(0,-G15) -> 0 | H18: =MAX(0,-H15) -> 0 | I18: =MAX(0,-I15) -> 0 | J18: =MAX(0,-J15) -> 0 | ... L18: =MAX(0,-L15) -> 0
A19: Loss carryforwards, ending | C19: =C16-C17+C18 -> 6081.6289 | D19: =D16-D17+D18 -> 0 | E19: =E16-E17+E18 -> 0 | F19: =F16-F17+F18 -> 0 | G19: =G16-G17+G18 -> 0 | H19: =H16-H17+H18 -> 0 | I19: =I16-I17+I18 -> 0 | J19: =J16-J17+J18 -> 0 | ... L19: =L16-L17+L18 -> 0
A20: Cash taxes | C20: =MAX(0,C15-C17)*Assumptions!$C$27 -> 182.46448 | D20: =MAX(0,D15-D17)*Assumptions!$C$27 -> 2525.7814 | E20: =MAX(0,E15-E17)*Assumptions!$C$27 -> 8333.5447 | F20: =MAX(0,F15-F17)*Assumptions!$C$27 -> 14499.662 | G20: =MAX(0,G15-G17)*Assumptions!$C$27 -> 21491.905 | H20: =MAX(0,H15-H17)*Assumptions!$C$27 -> 29293.008 | I20: =MAX(0,I15-I17)*Assumptions!$C$27 -> 36981.827 | J20: =MAX(0,J15-J17)*Assumptions!$C$27 -> 43669.838 | ... L20: =MAX(0,L15-L17)*Assumptions!$C$27 -> 55736.848
A21: Taxes / income before taxes | C21: =IF(Forecast_3Stmt!C21>0,Forecast_3Stmt!C22/Forecast_3Stmt!C21,0) -> 0 | D21: =IF(Forecast_3Stmt!D21>0,Forecast_3Stmt!D22/Forecast_3Stmt!D21,0) -> 0.13947535 | E21: =IF(Forecast_3Stmt!E21>0,Forecast_3Stmt!E22/Forecast_3Stmt!E21,0) -> 0.21 | F21: =IF(Forecast_3Stmt!F21>0,Forecast_3Stmt!F22/Forecast_3Stmt!F21,0) -> 0.21 | G21: =IF(Forecast_3Stmt!G21>0,Forecast_3Stmt!G22/Forecast_3Stmt!G21,0) -> 0.21 | H21: =IF(Forecast_3Stmt!H21>0,Forecast_3Stmt!H22/Forecast_3Stmt!H21,0) -> 0.21 | I21: =IF(Forecast_3Stmt!I21>0,Forecast_3Stmt!I22/Forecast_3Stmt!I21,0) -> 0.21 | J21: =IF(Forecast_3Stmt!J21>0,Forecast_3Stmt!J22/Forecast_3Stmt!J21,0) -> 0.21 | ... L21: =IF(Forecast_3Stmt!L21>0,Forecast_3Stmt!L22/Forecast_3Stmt!L21,0) -> 0.21
A23: C. Working capital
A24: Net working capital (receivables + prepaid - payables - deferred revenue) | B24: =Forecast_3Stmt!B34+Forecast_3Stmt!B35-Forecast_3Stmt!B39-Forecast_3Stmt!B40 -> 689 | C24: =Forecast_3Stmt!C34+Forecast_3Stmt!C35-Forecast_3Stmt!C39-Forecast_3Stmt!C40 -> -514.53 | D24: =Forecast_3Stmt!D34+Forecast_3Stmt!D35-Forecast_3Stmt!D39-Forecast_3Stmt!D40 -> -575.253 | E24: =Forecast_3Stmt!E34+Forecast_3Stmt!E35-Forecast_3Stmt!E39-Forecast_3Stmt!E40 -> 184.08096 | F24: =Forecast_3Stmt!F34+Forecast_3Stmt!F35-Forecast_3Stmt!F39-Forecast_3Stmt!F40 -> 1778.2221 | G24: =Forecast_3Stmt!G34+Forecast_3Stmt!G35-Forecast_3Stmt!G39-Forecast_3Stmt!G40 -> 4194.0638 | H24: =Forecast_3Stmt!H34+Forecast_3Stmt!H35-Forecast_3Stmt!H39-Forecast_3Stmt!H40 -> 7355.7426 | I24: =Forecast_3Stmt!I34+Forecast_3Stmt!I35-Forecast_3Stmt!I39-Forecast_3Stmt!I40 -> 9794.752 | ... L24: =Forecast_3Stmt!L34+Forecast_3Stmt!L35-Forecast_3Stmt!L39-Forecast_3Stmt!L40 -> 14809.665
A25: Increase in net working capital | C25: =C24-B24 -> -1203.53 | D25: =D24-C24 -> -60.723 | E25: =E24-D24 -> 759.33396 | F25: =F24-E24 -> 1594.1411 | G25: =G24-F24 -> 2415.8417 | H25: =H24-G24 -> 3161.6788 | I25: =I24-H24 -> 2439.0094 | J25: =J24-I24 -> 2671.296 | ... L25: =L24-K24 -> 1097.0122
A27: D. Unlevered free cash flow (stock-based compensation treated as a cash cost)
A28: Operating income | C28: =Forecast_3Stmt!C17 -> 929.5 | D28: =Forecast_3Stmt!D17 -> 13230.819 | E28: =Forecast_3Stmt!E17 -> 34054.978 | F28: =Forecast_3Stmt!F17 -> 62237.773 | G28: =Forecast_3Stmt!G17 -> 93559.884 | H28: =Forecast_3Stmt!H17 -> 127757.64 | I28: =Forecast_3Stmt!I17 -> 160277.76 | J28: =Forecast_3Stmt!J17 -> 186990.72 | ... L28: =Forecast_3Stmt!L17 -> 231030.77
A29: Taxes on operating income | C29: =IF(C15>0,C20*MAX(C28,0)/C15,0) -> 39.039 | D29: =IF(D15>0,D20*MAX(D28,0)/D15,0) -> 1845.3732 | E29: =IF(E15>0,E20*MAX(E28,0)/E15,0) -> 7151.5453 | F29: =IF(F15>0,F20*MAX(F28,0)/F15,0) -> 13069.932 | G29: =IF(G15>0,G20*MAX(G28,0)/G15,0) -> 19647.576 | H29: =IF(H15>0,H20*MAX(H28,0)/H15,0) -> 26829.103 | I29: =IF(I15>0,I20*MAX(I28,0)/I15,0) -> 33658.33 | J29: =IF(J15>0,J20*MAX(J28,0)/J15,0) -> 39268.051 | ... L29: =IF(L15>0,L20*MAX(L28,0)/L15,0) -> 48516.463 | N29: Cash taxes allocated between operating and interest income.
A30: Net operating profit after tax | C30: =C28-C29 -> 890.461 | D30: =D28-D29 -> 11385.446 | E30: =E28-E29 -> 26903.432 | F30: =F28-F29 -> 49167.84 | G30: =G28-G29 -> 73912.309 | H30: =H28-H29 -> 100928.53 | I30: =I28-I29 -> 126619.43 | J30: =J28-J29 -> 147722.67 | ... L30: =L28-L29 -> 182514.31
A31: Depreciation and amortization | C31: =C10 -> 290.7 | D31: =D10 -> 1188.9636 | E31: =E10 -> 3114.1222 | F31: =F10 -> 5996.1992 | G31: =G10 -> 9087.5552 | H31: =H10 -> 11851.252 | I31: =I10 -> 14475.164 | J31: =J10 -> 16744.637 | ... L31: =L10 -> 20609.623
A32: Capital expenditures | C32: =-C7 -> -1982 | D32: =-D7 -> -6903.036 | E32: =-E7 -> -14726.477 | F32: =-F7 -> -20322.538 | G32: =-G7 -> -22583.42 | H32: =-H7 -> -23228.661 | I32: =-I7 -> -26712.96 | J32: =-J7 -> -24932.096 | ... L32: =-L7 -> -29619.33
A33: Change in working capital | C33: =-C25 -> 1203.53 | D33: =-D25 -> 60.723 | E33: =-E25 -> -759.33396 | F33: =-F25 -> -1594.1411 | G33: =-G25 -> -2415.8417 | H33: =-H25 -> -3161.6788 | I33: =-I25 -> -2439.0094 | J33: =-J25 -> -2671.296 | ... L33: =-L25 -> -1097.0122
A34: Unlevered free cash flow | C34: =C30+C31+C32+C33 -> 402.691 | D34: =D30+D31+D32+D33 -> 5732.0964 | E34: =E30+E31+E32+E33 -> 14531.744 | F34: =F30+F31+F32+F33 -> 33247.36 | G34: =G30+G31+G32+G33 -> 58000.602 | H34: =H30+H31+H32+H33 -> 86389.444 | I34: =I30+I31+I32+I33 -> 111942.63 | J34: =J30+J31+J32+J33 -> 136863.91 | ... L34: =L30+L31+L32+L33 -> 172407.59
A35: % of revenue | C35: =C34/Forecast_3Stmt!C7 -> 0.0073502537 | D35: =D34/Forecast_3Stmt!D7 -> 0.049822395 | E35: =E34/Forecast_3Stmt!E7 -> 0.078942133 | F35: =F34/Forecast_3Stmt!F7 -> 0.13087877 | G35: =G34/Forecast_3Stmt!G7 -> 0.17977977 | H35: =H34/Forecast_3Stmt!H7 -> 0.22314531 | I35: =I34/Forecast_3Stmt!I7 -> 0.25143442 | J35: =J34/Forecast_3Stmt!J7 -> 0.27447334 | ... L35: =L34/Forecast_3Stmt!L7 -> 0.29103898
A37: Checks (zero passes)
A38: Taxes equal the income statement (2027E onward) | D38: =D20-Forecast_3Stmt!D22 -> 0 | E38: =E20-Forecast_3Stmt!E22 -> 0 | F38: =F20-Forecast_3Stmt!F22 -> 0 | G38: =G20-Forecast_3Stmt!G22 -> 0 | H38: =H20-Forecast_3Stmt!H22 -> 0 | I38: =I20-Forecast_3Stmt!I22 -> 0 | J38: =J20-Forecast_3Stmt!J22 -> 0 | K38: =K20-Forecast_3Stmt!K22 -> 0 | L38: =L20-Forecast_3Stmt!L22 -> 0
A39: Change in working capital equals the cash flow statement | D39: =D33-Forecast_3Stmt!D53 -> 0 | E39: =E33-Forecast_3Stmt!E53 -> 0 | F39: =F33-Forecast_3Stmt!F53 -> 0 | G39: =G33-Forecast_3Stmt!G53 -> 0 | H39: =H33-Forecast_3Stmt!H53 -> 0 | I39: =I33-Forecast_3Stmt!I53 -> 0 | J39: =J33-Forecast_3Stmt!J53 -> 0 | K39: =K33-Forecast_3Stmt!K53 -> 0 | L39: =L33-Forecast_3Stmt!L53 -> 0

Sheet Forecast_3Stmt
A1: Anthropic, PBC | Income statement, balance sheet and cash flow, 2025A and 2026E-2035E
A2: 2025A links to the S-1; 2026E links to Interim_Bridge; 2027E onward from Assumptions (active scenario). USD millions.
B3: Actual | C3: Forecast
A4: Fiscal year ends 31 December | B4: 2025A | C4: 2026E | D4: 2027E | E4: 2028E | F4: 2029E | G4: 2030E | H4: 2031E | I4: 2032E | J4: 2033E | K4: 2034E | L4: 2035E | M4: Comentarios FG | N4: Source / derivation
A6: Income statement
A7: Revenue | B7: =IS_Hist!D6 -> 4585 | C7: =Interim_Bridge!D7 -> 54786 | D7: =C7*(1+Assumptions!D44+Assumptions!$C$35) -> 115050.6 | E7: =D7*(1+Assumptions!E44+Assumptions!$C$35) -> 184080.96 | F7: =E7*(1+Assumptions!F44+Assumptions!$C$35) -> 254031.72 | G7: =F7*(1+Assumptions!G44+Assumptions!$C$35) -> 322620.29 | H7: =G7*(1+Assumptions!H44+Assumptions!$C$35) -> 387144.35 | I7: =H7*(1+Assumptions!I44+Assumptions!$C$35) -> 445216 | J7: =I7*(1+Assumptions!J44+Assumptions!$C$35) -> 498641.92 | K7: =J7*(1+Assumptions!K44+Assumptions!$C$35) -> 548506.11 | L7: =K7*(1+Assumptions!L44+Assumptions!$C$35) -> 592386.6
A8: Growth | C8: =C7/B7-1 -> 10.948964 | D8: =D7/C7-1 -> 1.1 | E8: =E7/D7-1 -> 0.6 | F8: =F7/E7-1 -> 0.38 | G8: =G7/F7-1 -> 0.27 | H8: =H7/G7-1 -> 0.2 | I8: =I7/H7-1 -> 0.15 | J8: =J7/I7-1 -> 0.12 | ... L8: =L7/K7-1 -> 0.08
A9: Compute and infrastructure | B9: =IS_Hist!D9 -> 7326 | C9: =Interim_Bridge!D10 -> 28195 | D9: =D7*(Assumptions!D49+Assumptions!$C$36) -> 57525.3 | E9: =E7*(Assumptions!E49+Assumptions!$C$36) -> 88358.861 | F9: =F7*(Assumptions!F49+Assumptions!$C$36) -> 116854.59 | G9: =G7*(Assumptions!G49+Assumptions!$C$36) -> 141952.93 | H9: =H7*(Assumptions!H49+Assumptions!$C$36) -> 162600.63 | I9: =I7*(Assumptions!I49+Assumptions!$C$36) -> 182538.56 | J9: =J7*(Assumptions!J49+Assumptions!$C$36) -> 199456.77 | K9: =K7*(Assumptions!K49+Assumptions!$C$36) -> 219402.45 | L9: =L7*(Assumptions!L49+Assumptions!$C$36) -> 236954.64
A10: Personnel, cash part (memo) | B10: =Interim_Bridge!G12 -> 681 | C10: =Interim_Bridge!D12 -> 2892 | D10: =D7*Assumptions!D54 -> 5752.53 | E10: =E7*Assumptions!E54 -> 9204.048 | F10: =F7*Assumptions!F54 -> 11431.428 | G10: =G7*Assumptions!G54 -> 14517.913 | H10: =H7*Assumptions!H54 -> 17421.496 | I10: =I7*Assumptions!I54 -> 17808.64 | J10: =J7*Assumptions!J54 -> 19945.677 | K10: =K7*Assumptions!K54 -> 21940.245 | L10: =L7*Assumptions!L54 -> 23695.464
A11: Stock-based compensation (memo) | B11: =Interim_Bridge!G11 -> 1158 | C11: =Interim_Bridge!D11 -> 7685 | D11: =D7*Assumptions!D59 -> 11505.06 | E11: =E7*Assumptions!E59 -> 14726.477 | F11: =F7*Assumptions!F59 -> 17782.221 | G11: =G7*Assumptions!G59 -> 19357.217 | H11: =H7*Assumptions!H59 -> 21292.939 | I11: =I7*Assumptions!I59 -> 22260.8 | J11: =J7*Assumptions!J59 -> 24932.096 | K11: =K7*Assumptions!K59 -> 24682.775 | L11: =L7*Assumptions!L59 -> 26657.397
A12: Personnel | B12: =IS_Hist!D10 -> 1839 | C12: =Interim_Bridge!D13 -> 10577 | D12: =D10+D11 -> 17257.59 | E12: =E10+E11 -> 23930.525 | F12: =F10+F11 -> 29213.648 | G12: =G10+G11 -> 33875.131 | H12: =H10+H11 -> 38714.435 | I12: =I10+I11 -> 40069.44 | J12: =J10+J11 -> 44877.773 | K12: =K10+K11 -> 46623.02 | L12: =L10+L11 -> 50352.861
A13: Bartz settlement | B13: =IS_Hist!D11 -> 1500 | C13: =Interim_Bridge!D14 -> 0 | D13: =0 -> 0 | E13: =0 -> 0 | F13: =0 -> 0 | G13: =0 -> 0 | H13: =0 -> 0 | I13: =0 -> 0 | J13: =0 -> 0 | K13: =0 -> 0 | L13: =0 -> 0
A14: Sales, marketing, and partnerships | B14: =IS_Hist!D12 -> 568 | C14: =Interim_Bridge!D15 -> 10098 | D14: =D7*Assumptions!D64 -> 18408.096 | E14: =E7*Assumptions!E64 -> 25771.334 | F14: =F7*Assumptions!F64 -> 30483.807 | G14: =G7*Assumptions!G64 -> 35488.232 | H14: =H7*Assumptions!H64 -> 38714.435 | I14: =I7*Assumptions!I64 -> 40069.44 | J14: =J7*Assumptions!J64 -> 44877.773 | K14: =K7*Assumptions!K64 -> 43880.489 | L14: =L7*Assumptions!L64 -> 47390.928
A15: Other operating and administrative | B15: =IS_Hist!D13 -> 1412 | C15: =Interim_Bridge!D16 -> 4986.5 | D15: =D7*Assumptions!D69 -> 8628.795 | E15: =E7*Assumptions!E69 -> 11965.262 | F15: =F7*Assumptions!F69 -> 15241.903 | G15: =G7*Assumptions!G69 -> 17744.116 | H15: =H7*Assumptions!H69 -> 19357.217 | I15: =I7*Assumptions!I69 -> 22260.8 | J15: =J7*Assumptions!J69 -> 22438.886 | K15: =K7*Assumptions!K69 -> 24682.775 | L15: =L7*Assumptions!L69 -> 26657.397
A16: Total operating expenses | B16: =B9+B12+B13+B14+B15 -> 12645 | C16: =C9+C12+C13+C14+C15 -> 53856.5 | D16: =D9+D12+D13+D14+D15 -> 101819.78 | E16: =E9+E12+E13+E14+E15 -> 150025.98 | F16: =F9+F12+F13+F14+F15 -> 191793.95 | G16: =G9+G12+G13+G14+G15 -> 229060.41 | H16: =H9+H12+H13+H14+H15 -> 259386.71 | I16: =I9+I12+I13+I14+I15 -> 284938.24 | ... L16: =L9+L12+L13+L14+L15 -> 361355.83
A17: Operating income (loss) | B17: =B7-B16 -> -8060 | C17: =C7-C16 -> 929.5 | D17: =D7-D16 -> 13230.819 | E17: =E7-E16 -> 34054.978 | F17: =F7-F16 -> 62237.773 | G17: =G7-G16 -> 93559.884 | H17: =H7-H16 -> 127757.64 | I17: =I7-I16 -> 160277.76 | ... L17: =L7-L16 -> 231030.77
A18: Operating margin | B18: =B17/B7 -> -1.7579062 | C18: =C17/C7 -> 0.016966013 | D18: =D17/D7 -> 0.115 | E18: =E17/E7 -> 0.185 | F18: =F17/F7 -> 0.245 | G18: =G17/G7 -> 0.29 | H18: =H17/H7 -> 0.33 | I18: =I17/I7 -> 0.36 | ... L18: =L17/L7 -> 0.39
A19: Interest income | B19: =IS_Hist!D16 -> 431 | C19: =Interim_Bridge!D22 -> 3414.8925 | D19: =Assumptions!$C$26*C33 -> 4878.3405 | E19: =Assumptions!$C$26*D33 -> 5628.5686 | F19: =Assumptions!$C$26*E33 -> 6808.2363 | G19: =Assumptions!$C$26*F33 -> 8782.5193 | H19: =Assumptions!$C$26*G33 -> 11732.88 | I19: =Assumptions!$C$26*H33 -> 15826.177 | J19: =Assumptions!$C$26*I33 -> 20960.891 | K19: =Assumptions!$C$26*J33 -> 27203.32 | L19: =Assumptions!$C$26*K33 -> 34382.788 | N19: Yield x beginning cash and short-term investments.
A20: Change in fair value of notes and other items | B20: =IS_Hist!D17+IS_Hist!D18 -> -34316 | C20: =Interim_Bridge!D23 -> -81145 | D20: =0 -> 0 | E20: =0 -> 0 | F20: =0 -> 0 | G20: =0 -> 0 | H20: =0 -> 0 | I20: =0 -> 0 | J20: =0 -> 0 | K20: =0 -> 0 | L20: =0 -> 0 | N20: Stops after the notes convert at the IPO.
A21: Income (loss) before income taxes | B21: =B17+B19+B20 -> -41945 | C21: =C17+C19+C20 -> -76800.607 | D21: =D17+D19+D20 -> 18109.16 | E21: =E17+E19+E20 -> 39683.546 | F21: =F17+F19+F20 -> 69046.009 | G21: =G17+G19+G20 -> 102342.4 | H21: =H17+H19+H20 -> 139490.51 | I21: =I17+I19+I20 -> 176103.94 | ... L21: =L17+L19+L20 -> 265413.56
A22: Provision for income taxes | B22: =IS_Hist!D21 -> 20 | C22: =Interim_Bridge!D25 -> 182.46448 | D22: =Schedules!D20 -> 2525.7814 | E22: =Schedules!E20 -> 8333.5447 | F22: =Schedules!F20 -> 14499.662 | G22: =Schedules!G20 -> 21491.905 | H22: =Schedules!H20 -> 29293.008 | I22: =Schedules!I20 -> 36981.827 | J22: =Schedules!J20 -> 43669.838 | K22: =Schedules!K20 -> 50635.348 | L22: =Schedules!L20 -> 55736.848
A23: Net income (loss) | B23: =B21-B22 -> -41965 | C23: =C21-C22 -> -76983.072 | D23: =D21-D22 -> 15583.378 | E23: =E21-E22 -> 31350.002 | F23: =F21-F22 -> 54546.347 | G23: =G21-G22 -> 80850.499 | H23: =H21-H22 -> 110197.51 | I23: =I21-I22 -> 139122.11 | ... L23: =L21-L22 -> 209676.71
A24: Net margin | B24: =B23/B7 -> -9.1526718 | C24: =C23/C7 -> -1.4051596 | D24: =D23/D7 -> 0.13544804 | E24: =E23/E7 -> 0.17030551 | F24: =F23/F7 -> 0.21472258 | G24: =G23/G7 -> 0.25060575 | H24: =H23/H7 -> 0.28464191 | I24: =I23/I7 -> 0.31248228 | ... L24: =L23/L7 -> 0.35395249
A26: Memo: non-cash costs and company measures
A27: Depreciation and amortization (inside the costs above) | B27: =CF_Hist!D11 -> 40 | C27: =Schedules!C10 -> 290.7 | D27: =Schedules!D10 -> 1188.9636 | E27: =Schedules!E10 -> 3114.1222 | F27: =Schedules!F10 -> 5996.1992 | G27: =Schedules!G10 -> 9087.5552 | H27: =Schedules!H10 -> 11851.252 | I27: =Schedules!I10 -> 14475.164 | J27: =Schedules!J10 -> 16744.637 | ... L27: =Schedules!L10 -> 20609.623
A28: EBITDA (operating income + D&A) | B28: =B17+B27 -> -8020 | C28: =C17+C27 -> 1220.2 | D28: =D17+D27 -> 14419.783 | E28: =E17+E27 -> 37169.1 | F28: =F17+F27 -> 68233.972 | G28: =G17+G27 -> 102647.44 | H28: =H17+H27 -> 139608.89 | I28: =I17+I27 -> 174752.92 | ... L28: =L17+L27 -> 251640.4
A29: Adjusted operating income (company definition: + stock-based compensation and one-offs) | B29: =Revenue_Hist!D39 -> -4854 | C29: =Interim_Bridge!D21 -> 8740.5 | D29: =D17+D11 -> 24735.879 | E29: =E17+E11 -> 48781.454 | F29: =F17+F11 -> 80019.993 | G29: =G17+G11 -> 112917.1 | H29: =H17+H11 -> 149050.57 | I29: =I17+I11 -> 182538.56 | J29: =J17+J11 -> 211922.82 | K29: =K17+K11 -> 238600.16 | L29: =L17+L11 -> 257688.17
A30: Adjusted operating margin | B30: =B29/B7 -> -1.0586696 | C30: =C29/C7 -> 0.15953893 | D30: =D29/D7 -> 0.215 | E30: =E29/E7 -> 0.265 | F30: =F29/F7 -> 0.315 | G30: =G29/G7 -> 0.35 | H30: =H29/H7 -> 0.385 | I30: =I29/I7 -> 0.41 | ... L30: =L29/L7 -> 0.435
A32: Balance sheet (31 December)
A33: Cash and short-term investments | B33: =BS_Hist!C45 -> 20277 | C33: =Interim_Bridge!D44 -> 139381.16 | D33: =C33+D59 -> 160816.25 | E33: =D33+E59 -> 194521.04 | F33: =E33+F59 -> 250929.12 | G33: =F33+G59 -> 335225.13 | H33: =G33+H59 -> 452176.49 | I33: =H33+I59 -> 598882.6 | J33: =I33+J59 -> 777237.71 | K33: =J33+K59 -> 982365.38 | L33: =K33+L59 -> 1208592.8
A34: Accounts receivable | B34: =BS_Hist!C11 -> 909 | C34: =Interim_Bridge!D45 -> 9861.48 | D34: =D7*Assumptions!$C$30 -> 20709.108 | E34: =E7*Assumptions!$C$30 -> 33134.573 | F34: =F7*Assumptions!$C$30 -> 45725.71 | G34: =G7*Assumptions!$C$30 -> 58071.652 | H34: =H7*Assumptions!$C$30 -> 69685.983 | I34: =I7*Assumptions!$C$30 -> 80138.88 | J34: =J7*Assumptions!$C$30 -> 89755.546 | K34: =K7*Assumptions!$C$30 -> 98731.1 | L34: =L7*Assumptions!$C$30 -> 106629.59
A35: Prepaid expenses and other current assets | B35: =BS_Hist!C12 -> 2560 | C35: =Interim_Bridge!D46 -> 821.79 | D35: =D7*Assumptions!$C$31 -> 1725.759 | E35: =E7*Assumptions!$C$31 -> 2761.2144 | F35: =F7*Assumptions!$C$31 -> 3810.4759 | G35: =G7*Assumptions!$C$31 -> 4839.3044 | H35: =H7*Assumptions!$C$31 -> 5807.1652 | I35: =I7*Assumptions!$C$31 -> 6678.24 | J35: =J7*Assumptions!$C$31 -> 7479.6288 | K35: =K7*Assumptions!$C$31 -> 8227.5917 | L35: =L7*Assumptions!$C$31 -> 8885.799
A36: Property and equipment, net | B36: =BS_Hist!C15 -> 146 | C36: =Interim_Bridge!D47 -> 2493.3 | D36: =Schedules!D12 -> 8207.3724 | E36: =Schedules!E12 -> 19819.727 | F36: =Schedules!F12 -> 34146.066 | G36: =Schedules!G12 -> 47641.931 | H36: =Schedules!H12 -> 59019.34 | I36: =Schedules!I12 -> 71257.136 | J36: =Schedules!J12 -> 79444.595 | K36: =Schedules!K12 -> 88238.451 | L36: =Schedules!L12 -> 97248.158
A37: Restricted cash, lease assets, goodwill and other assets | B37: =BS_Hist!C14+BS_Hist!C16+BS_Hist!C17+BS_Hist!C18 -> 769 | C37: =Interim_Bridge!D48 -> 8191 | D37: =C37 -> 8191 | E37: =D37 -> 8191 | F37: =E37 -> 8191 | G37: =F37 -> 8191 | H37: =G37 -> 8191 | I37: =H37 -> 8191 | J37: =I37 -> 8191 | K37: =J37 -> 8191 | L37: =K37 -> 8191
A38: Total assets | B38: =B33+B34+B35+B36+B37 -> 24661 | C38: =C33+C34+C35+C36+C37 -> 160748.73 | D38: =D33+D34+D35+D36+D37 -> 199649.49 | E38: =E33+E34+E35+E36+E37 -> 258427.55 | F38: =F33+F34+F35+F36+F37 -> 342802.38 | G38: =G33+G34+G35+G36+G37 -> 453969.02 | H38: =H33+H34+H35+H36+H37 -> 594879.98 | I38: =I33+I34+I35+I36+I37 -> 765147.85 | ... L38: =L33+L34+L35+L36+L37 -> 1429547.3
A39: Accounts payable, accrued and other current liabilities | B39: =BS_Hist!C23 -> 2511 | C39: =Interim_Bridge!D50 -> 8458.5 | D39: =D9*Assumptions!$C$33 -> 17257.59 | E39: =E9*Assumptions!$C$33 -> 26507.658 | F39: =F9*Assumptions!$C$33 -> 35056.378 | G39: =G9*Assumptions!$C$33 -> 42585.878 | H39: =H9*Assumptions!$C$33 -> 48780.188 | I39: =I9*Assumptions!$C$33 -> 54761.568 | J39: =J9*Assumptions!$C$33 -> 59837.031 | K39: =K9*Assumptions!$C$33 -> 65820.734 | L39: =L9*Assumptions!$C$33 -> 71086.392
A40: Deferred revenue | B40: =BS_Hist!C25 -> 269 | C40: =Interim_Bridge!D51 -> 2739.3 | D40: =D7*Assumptions!$C$32 -> 5752.53 | E40: =E7*Assumptions!$C$32 -> 9204.048 | F40: =F7*Assumptions!$C$32 -> 12701.586 | G40: =G7*Assumptions!$C$32 -> 16131.015 | H40: =H7*Assumptions!$C$32 -> 19357.217 | I40: =I7*Assumptions!$C$32 -> 22260.8 | J40: =J7*Assumptions!$C$32 -> 24932.096 | K40: =K7*Assumptions!$C$32 -> 27425.306 | L40: =L7*Assumptions!$C$32 -> 29619.33
A41: Operating lease and other noncurrent liabilities | B41: =BS_Hist!C24+BS_Hist!C27+BS_Hist!C29 -> 940 | C41: =Interim_Bridge!D52 -> 1829 | D41: =C41 -> 1829 | E41: =D41 -> 1829 | F41: =E41 -> 1829 | G41: =F41 -> 1829 | H41: =G41 -> 1829 | I41: =H41 -> 1829 | J41: =I41 -> 1829 | K41: =J41 -> 1829 | L41: =K41 -> 1829
A42: Convertible notes payable | B42: =BS_Hist!C28 -> 41677 | C42: =Interim_Bridge!D53 -> 0 | D42: =0 -> 0 | E42: =0 -> 0 | F42: =0 -> 0 | G42: =0 -> 0 | H42: =0 -> 0 | I42: =0 -> 0 | J42: =0 -> 0 | K42: =0 -> 0 | L42: =0 -> 0
A43: Total liabilities | B43: =B39+B40+B41+B42 -> 45397 | C43: =C39+C40+C41+C42 -> 13026.8 | D43: =D39+D40+D41+D42 -> 24839.12 | E43: =E39+E40+E41+E42 -> 37540.706 | F43: =F39+F40+F41+F42 -> 49586.964 | G43: =G39+G40+G41+G42 -> 60545.893 | H43: =H39+H40+H41+H42 -> 69966.405 | I43: =I39+I40+I41+I42 -> 78851.368 | ... L43: =L39+L40+L41+L42 -> 102534.72
A44: Redeemable convertible preferred stock | B44: =BS_Hist!C32 -> 29769 | C44: =Interim_Bridge!D55 -> 0 | D44: =0 -> 0 | E44: =0 -> 0 | F44: =0 -> 0 | G44: =0 -> 0 | H44: =0 -> 0 | I44: =0 -> 0 | J44: =0 -> 0 | K44: =0 -> 0 | L44: =0 -> 0
A45: Stockholders' equity (deficit) | B45: =BS_Hist!C41 -> -50505 | C45: =Interim_Bridge!D56 -> 147721.93 | D45: =C45+D23+D11+D57 -> 174810.37 | E45: =D45+E23+E11+E57 -> 220886.84 | F45: =E45+F23+F11+F57 -> 293215.41 | G45: =F45+G23+G11+G57 -> 393423.13 | H45: =G45+H23+H11+H57 -> 524913.57 | I45: =H45+I23+I11+I57 -> 686296.48 | J45: =I45+J23+J11+J57 -> 875510.35 | K45: =J45+K23+K11+K57 -> 1090678.5 | L45: =K45+L23+L11+L57 -> 1327012.6
A46: Total liabilities, preferred stock and equity | B46: =B43+B44+B45 -> 24661 | C46: =C43+C44+C45 -> 160748.73 | D46: =D43+D44+D45 -> 199649.49 | E46: =E43+E44+E45 -> 258427.55 | F46: =F43+F44+F45 -> 342802.38 | G46: =G43+G44+G45 -> 453969.02 | H46: =H43+H44+H45 -> 594879.98 | I46: =I43+I44+I45 -> 765147.85 | ... L46: =L43+L44+L45 -> 1429547.3
A48: Cash flow
A49: Net income (loss) | B49: =CF_Hist!D7 -> -41965 | C49: =Interim_Bridge!D29 -> -76983.072 | D49: =D23 -> 15583.378 | E49: =E23 -> 31350.002 | F49: =F23 -> 54546.347 | G49: =G23 -> 80850.499 | H49: =H23 -> 110197.51 | I49: =I23 -> 139122.11 | J49: =J23 -> 164281.77 | K49: =K23 -> 190485.36 | L49: =L23 -> 209676.71
A50: Depreciation and amortization | B50: =CF_Hist!D11 -> 40 | C50: =Interim_Bridge!D30 -> 290.7 | D50: =D27 -> 1188.9636 | E50: =E27 -> 3114.1222 | F50: =F27 -> 5996.1992 | G50: =G27 -> 9087.5552 | H50: =H27 -> 11851.252 | I50: =I27 -> 14475.164 | J50: =J27 -> 16744.637 | K50: =K27 -> 18631.45 | L50: =L27 -> 20609.623
A51: Stock-based compensation | B51: =CF_Hist!D10 -> 1158 | C51: =Interim_Bridge!D31 -> 7685 | D51: =D11 -> 11505.06 | E51: =E11 -> 14726.477 | F51: =F11 -> 17782.221 | G51: =G11 -> 19357.217 | H51: =H11 -> 21292.939 | I51: =I11 -> 22260.8 | J51: =J11 -> 24932.096 | K51: =K11 -> 24682.775 | L51: =L11 -> 26657.397
A52: Fair value changes and other non-cash items | B52: =CF_Hist!D12+CF_Hist!D13+CF_Hist!D14+CF_Hist!D15 -> 34860 | C52: =Interim_Bridge!D32 -> 81227 | D52: =0 -> 0 | E52: =0 -> 0 | F52: =0 -> 0 | G52: =0 -> 0 | H52: =0 -> 0 | I52: =0 -> 0 | J52: =0 -> 0 | K52: =0 -> 0 | L52: =0 -> 0
A53: Changes in operating assets and liabilities | B53: =CF_Hist!D18+CF_Hist!D19+CF_Hist!D20+CF_Hist!D21+CF_Hist!D22 -> 3270 | C53: =Interim_Bridge!D33 -> 939.53 | D53: =-(D34-C34)-(D35-C35)+(D39-C39)+(D40-C40) -> 60.723 | E53: =-(E34-D34)-(E35-D35)+(E39-D39)+(E40-D40) -> -759.33396 | F53: =-(F34-E34)-(F35-E35)+(F39-E39)+(F40-E40) -> -1594.1411 | G53: =-(G34-F34)-(G35-F35)+(G39-F39)+(G40-F40) -> -2415.8417 | H53: =-(H34-G34)-(H35-G35)+(H39-G39)+(H40-G40) -> -3161.6788 | I53: =-(I34-H34)-(I35-H35)+(I39-H39)+(I40-H40) -> -2439.0094 | J53: =-(J34-I34)-(J35-I35)+(J39-I39)+(J40-I40) -> -2671.296 | K53: =-(K34-J34)-(K35-J35)+(K39-J39)+(K40-J40) -> -1246.6048 | L53: =-(L34-K34)-(L35-K35)+(L39-K39)+(L40-K40) -> -1097.0122
A54: Net cash from operating activities | B54: =B49+B50+B51+B52+B53 -> -2637 | C54: =C49+C50+C51+C52+C53 -> 13159.158 | D54: =D49+D50+D51+D52+D53 -> 28338.125 | E54: =E49+E50+E51+E52+E53 -> 48431.267 | F54: =F49+F50+F51+F52+F53 -> 76730.626 | G54: =G49+G50+G51+G52+G53 -> 106879.43 | H54: =H49+H50+H51+H52+H53 -> 140180.02 | I54: =I49+I50+I51+I52+I53 -> 173419.07 | ... L54: =L49+L50+L51+L52+L53 -> 255846.72
A55: Capital expenditures | B55: =CF_Hist!D26 -> -131 | C55: =Interim_Bridge!D35 -> -1982 | D55: =-Schedules!D7 -> -6903.036 | E55: =-Schedules!E7 -> -14726.477 | F55: =-Schedules!F7 -> -20322.538 | G55: =-Schedules!G7 -> -22583.42 | H55: =-Schedules!H7 -> -23228.661 | I55: =-Schedules!I7 -> -26712.96 | J55: =-Schedules!J7 -> -24932.096 | K55: =-Schedules!K7 -> -27425.306 | L55: =-Schedules!L7 -> -29619.33
A56: Other investing (excluding short-term investment flows) | B56: =CF_Hist!D29 -> -77 | C56: =Interim_Bridge!D36 -> -337 | D56: =0 -> 0 | E56: =0 -> 0 | F56: =0 -> 0 | G56: =0 -> 0 | H56: =0 -> 0 | I56: =0 -> 0 | J56: =0 -> 0 | K56: =0 -> 0 | L56: =0 -> 0
A57: Net cash from financing activities | B57: =CF_Hist!D40 -> 19960 | C57: =Interim_Bridge!D37 -> 110774 | D57: =0 -> 0 | E57: =0 -> 0 | F57: =0 -> 0 | G57: =0 -> 0 | H57: =0 -> 0 | I57: =0 -> 0 | J57: =0 -> 0 | K57: =0 -> 0 | L57: =0 -> 0 | N57: No new equity or debt after the IPO in the forecast; no dividends or buybacks.
A58: Restricted cash, exchange rates and investment marks | B58: =B33-BS_Hist!B45-(B54+B55+B56+B57) -> 21 | C58: =Interim_Bridge!D38 -> -2510 | D58: =0 -> 0 | E58: =0 -> 0 | F58: =0 -> 0 | G58: =0 -> 0 | H58: =0 -> 0 | I58: =0 -> 0 | J58: =0 -> 0 | K58: =0 -> 0 | L58: =0 -> 0 | N58: Balancing item in actual periods.
A59: Net change in cash and short-term investments | B59: =B54+B55+B56+B57+B58 -> 17136 | C59: =C54+C55+C56+C57+C58 -> 119104.16 | D59: =D54+D55+D56+D57+D58 -> 21435.089 | E59: =E54+E55+E56+E57+E58 -> 33704.79 | F59: =F54+F55+F56+F57+F58 -> 56408.088 | G59: =G54+G55+G56+G57+G58 -> 84296.009 | H59: =H54+H55+H56+H57+H58 -> 116951.36 | I59: =I54+I55+I56+I57+I58 -> 146706.11 | ... L59: =L54+L55+L56+L57+L58 -> 226227.39
A60: Free cash flow (operating cash flow less capex) | B60: =B54+B55 -> -2768 | C60: =C54+C55 -> 11177.158 | D60: =D54+D55 -> 21435.089 | E60: =E54+E55 -> 33704.79 | F60: =F54+F55 -> 56408.088 | G60: =G54+G55 -> 84296.009 | H60: =H54+H55 -> 116951.36 | I60: =I54+I55 -> 146706.11 | ... L60: =L54+L55 -> 226227.39
A61: Free cash flow margin | B61: =B60/B7 -> -0.60370774 | C61: =C60/C7 -> 0.20401486 | D61: =D60/D7 -> 0.1863101 | E61: =E60/E7 -> 0.18309764 | F61: =F60/F7 -> 0.22205135 | G61: =G60/G7 -> 0.26128552 | H61: =H60/H7 -> 0.30208722 | I61: =I60/I7 -> 0.3295167 | ... L61: =L60/L7 -> 0.38189147
A63: Checks (zero passes)
A64: Balance sheet balances | B64: =B38-B46 -> 0 | C64: =C38-C46 -> 0 | D64: =D38-D46 -> 0 | E64: =E38-E46 -> 0 | F64: =F38-F46 -> 0 | G64: =G38-G46 -> 0 | H64: =H38-H46 -> 0 | I64: =I38-I46 -> 0 | ... L64: =L38-L46 -> 0
A65: Cash roll-forward | C65: =B33+C59-C33 -> 0 | D65: =C33+D59-D33 -> 0 | E65: =D33+E59-E33 -> 0 | F65: =E33+F59-F33 -> 0 | G65: =F33+G59-G33 -> 0 | H65: =G33+H59-H33 -> 0 | I65: =H33+I59-I33 -> 0 | J65: =I33+J59-J33 -> 0 | ... L65: =K33+L59-L33 -> 0
A66: 2025A net income equals the S-1 | B66: =B23-IS_Hist!D22 -> 0
A67: 2025A operating cash flow equals the S-1 | B67: =B54-CF_Hist!D23 -> 0

Sheet Debt_Credit
A1: Anthropic, PBC | Liquidity, obligations and credit metrics
A2: No financial debt after the IPO: the convertible notes and preferred stock convert into common stock. USD millions.
A4: Item | B4: 30 Jun 2026A | C4: Comentarios FG | D4: Source / derivation
A6: A. Liquidity
A7: Cash and cash equivalents | B7: =BS_Hist!D9 -> 112389
A8: Short-term investments | B8: =BS_Hist!D10 -> 19262
A9: Revolving credit facility (A&R, September 2026), undrawn | B9: 15000 | D9: S-1: 'a $15 billion senior secured revolving credit facility'; matures 4 Sep 2031; one financial covenant; in compliance at 30 Jun 2026.
A10: Liquidity | B10: =B7+B8+B9 -> 146651
A11: Memo: Google 2026 note purchase agreement, available | B11: 20000 | D11: S-1 MD&A table; draw period to December 2030.
A12: Memo: Amazon 2026 note purchase agreement, available | B12: 15000 | D12: S-1 MD&A table.
A13: Memo: Infrastructure partner (Broadcom) 2026 agreement, available | B13: 42000 | D13: S-1 MD&A table; finances infrastructure.
A14: Memo: strategic financing capacity, total | B14: =B11+B12+B13 -> 77000
A16: B. Debt and debt-like items
A17: Convertible notes payable (fair value) | B17: =BS_Hist!D28 -> 108566 | D17: Principal US$6,203m; converts into 1,840m Class N shares at the IPO; counted in the fully diluted shares, not as debt.
A18: Lease liabilities (operating and finance) | B18: =BS_Hist!D47 -> 1522
A19: Financial debt after the IPO | B19: 0 | D19: Revolver undrawn; notes convert.
A20: Net cash after the IPO (cash + short-term investments - leases - debt) | B20: =B7+B8-B18-B19 -> 130129
A22: C. Signed commitments, 31 Dec 2025 (S-1 Note 13; the 30 Sep 2026 total is blank in the S-1)
A23: 2026 | B23: 7059 | D23: Non-cancelable contractual commitments, mostly compute
A24: 2027 | B24: 11128 | D24: Non-cancelable contractual commitments, mostly compute
A25: 2028 | B25: 10832 | D25: Non-cancelable contractual commitments, mostly compute
A26: 2029 | B26: 8304 | D26: Non-cancelable contractual commitments, mostly compute
A27: 2030 | B27: 5428 | D27: Non-cancelable contractual commitments, mostly compute
A28: Thereafter | B28: 11808 | D28: Non-cancelable contractual commitments, mostly compute
A29: Total non-cancelable commitments | B29: =SUM(B23:B28) -> 54559
A30: Commitments add to the S-1 total (54,559) | B30: =B29-54559 -> 0
A31: Operating lease payments, undiscounted, 30 Jun 2026 | B31: 1601 | D31: S-1 Note 7 maturity table.
A32: Finance lease payments, undiscounted, 30 Jun 2026 | B32: 523 | D32: S-1 Note 7 maturity table.
A33: Cash and short-term investments / commitments due in 2026 and 2027 (x) | B33: =(B7+B8)/(B23+B24) -> 7.238742 | D33: Commitments signed after 31 Dec 2025 are not in this number.
A35: D. Credit metrics by year (active scenario)
A36: Fiscal year ends 31 December | B36: 2025A | C36: 2026E | D36: 2027E | E36: 2028E | F36: 2029E | G36: 2030E | H36: 2031E | I36: 2032E | J36: 2033E | K36: 2034E | L36: 2035E
A37: EBITDA | B37: =Forecast_3Stmt!B28 -> -8020 | C37: =Forecast_3Stmt!C28 -> 1220.2 | D37: =Forecast_3Stmt!D28 -> 14419.783 | E37: =Forecast_3Stmt!E28 -> 37169.1 | F37: =Forecast_3Stmt!F28 -> 68233.972 | G37: =Forecast_3Stmt!G28 -> 102647.44 | H37: =Forecast_3Stmt!H28 -> 139608.89 | I37: =Forecast_3Stmt!I28 -> 174752.92 | ... L37: =Forecast_3Stmt!L28 -> 251640.4
A38: Cash and short-term investments | B38: =Forecast_3Stmt!B33 -> 20277 | C38: =Forecast_3Stmt!C33 -> 139381.16 | D38: =Forecast_3Stmt!D33 -> 160816.25 | E38: =Forecast_3Stmt!E33 -> 194521.04 | F38: =Forecast_3Stmt!F33 -> 250929.12 | G38: =Forecast_3Stmt!G33 -> 335225.13 | H38: =Forecast_3Stmt!H33 -> 452176.49 | I38: =Forecast_3Stmt!I33 -> 598882.6 | ... L38: =Forecast_3Stmt!L33 -> 1208592.8
A39: Lease and other noncurrent liabilities | B39: =Forecast_3Stmt!B41 -> 940 | C39: =Forecast_3Stmt!C41 -> 1829 | D39: =Forecast_3Stmt!D41 -> 1829 | E39: =Forecast_3Stmt!E41 -> 1829 | F39: =Forecast_3Stmt!F41 -> 1829 | G39: =Forecast_3Stmt!G41 -> 1829 | H39: =Forecast_3Stmt!H41 -> 1829 | I39: =Forecast_3Stmt!I41 -> 1829 | ... L39: =Forecast_3Stmt!L41 -> 1829
A40: Convertible notes payable | B40: =Forecast_3Stmt!B42 -> 41677 | C40: =Forecast_3Stmt!C42 -> 0 | D40: =Forecast_3Stmt!D42 -> 0 | E40: =Forecast_3Stmt!E42 -> 0 | F40: =Forecast_3Stmt!F42 -> 0 | G40: =Forecast_3Stmt!G42 -> 0 | H40: =Forecast_3Stmt!H42 -> 0 | I40: =Forecast_3Stmt!I42 -> 0 | ... L40: =Forecast_3Stmt!L42 -> 0
A41: Net cash (cash - leases and other - notes) | B41: =B38-B39-B40 -> -22340 | C41: =C38-C39-C40 -> 137552.16 | D41: =D38-D39-D40 -> 158987.25 | E41: =E38-E39-E40 -> 192692.04 | F41: =F38-F39-F40 -> 249100.12 | G41: =G38-G39-G40 -> 333396.13 | H41: =H38-H39-H40 -> 450347.49 | I41: =I38-I39-I40 -> 597053.6 | ... L41: =L38-L39-L40 -> 1206763.8
A42: Net cash / revenue | B42: =B41/Forecast_3Stmt!B7 -> -4.87241 | C42: =C41/Forecast_3Stmt!C7 -> 2.5107173 | D42: =D41/Forecast_3Stmt!D7 -> 1.3818898 | E42: =E41/Forecast_3Stmt!E7 -> 1.0467787 | F42: =F41/Forecast_3Stmt!F7 -> 0.98058667 | G42: =G41/Forecast_3Stmt!G7 -> 1.033401 | H42: =H41/Forecast_3Stmt!H7 -> 1.1632547 | I42: =I41/Forecast_3Stmt!I7 -> 1.3410425 | ... L42: =L41/Forecast_3Stmt!L7 -> 2.037122
A43: Free cash flow | B43: =Forecast_3Stmt!B60 -> -2768 | C43: =Forecast_3Stmt!C60 -> 11177.158 | D43: =Forecast_3Stmt!D60 -> 21435.089 | E43: =Forecast_3Stmt!E60 -> 33704.79 | F43: =Forecast_3Stmt!F60 -> 56408.088 | G43: =Forecast_3Stmt!G60 -> 84296.009 | H43: =Forecast_3Stmt!H60 -> 116951.36 | I43: =Forecast_3Stmt!I60 -> 146706.11 | ... L43: =Forecast_3Stmt!L60 -> 226227.39
A44: Operating cash flow / capex (x) | B44: =IF(Forecast_3Stmt!B55<0,-Forecast_3Stmt!B54/Forecast_3Stmt!B55,0) -> -20.129771 | C44: =IF(Forecast_3Stmt!C55<0,-Forecast_3Stmt!C54/Forecast_3Stmt!C55,0) -> 6.639333 | D44: =IF(Forecast_3Stmt!D55<0,-Forecast_3Stmt!D54/Forecast_3Stmt!D55,0) -> 4.1051683 | E44: =IF(Forecast_3Stmt!E55<0,-Forecast_3Stmt!E54/Forecast_3Stmt!E55,0) -> 3.2887205 | F44: =IF(Forecast_3Stmt!F55<0,-Forecast_3Stmt!F54/Forecast_3Stmt!F55,0) -> 3.7756419 | G44: =IF(Forecast_3Stmt!G55<0,-Forecast_3Stmt!G54/Forecast_3Stmt!G55,0) -> 4.7326502 | H44: =IF(Forecast_3Stmt!H55<0,-Forecast_3Stmt!H54/Forecast_3Stmt!H55,0) -> 6.0347869 | I44: =IF(Forecast_3Stmt!I55<0,-Forecast_3Stmt!I54/Forecast_3Stmt!I55,0) -> 6.4919449 | ... L44: =IF(Forecast_3Stmt!L55<0,-Forecast_3Stmt!L54/Forecast_3Stmt!L55,0) -> 8.6378295
A45: Debt / EBITDA after the IPO (x) | C45: =IF(C37>0,0/C37,0) -> 0 | D45: =IF(D37>0,0/D37,0) -> 0 | E45: =IF(E37>0,0/E37,0) -> 0 | F45: =IF(F37>0,0/F37,0) -> 0 | G45: =IF(G37>0,0/G37,0) -> 0 | H45: =IF(H37>0,0/H37,0) -> 0 | I45: =IF(I37>0,0/I37,0) -> 0 | J45: =IF(J37>0,0/J37,0) -> 0 | ... L45: =IF(L37>0,0/L37,0) -> 0
A47: E. Credit view
A48: No funded debt after the IPO. Liquidity at 30 Jun 2026 was about US$147bn including the undrawn US$15bn revolver.
A49: The real fixed obligation is compute: US$54.6bn of signed commitments at 31 Dec 2025, procured 12 to 18 months ahead (S-1), and more signed since (the S-1 leaves the 30 Sep 2026 total blank).
A50: Customer concentration: two customers were 12% of 2025 revenue each; one was 11% of 6M 2026 revenue (S-1 Note 2).
A51: No credit rating found. The revolver is senior secured with a financial covenant (S-1).

Sheet Market_Package
A1: Anthropic, PBC | Market package: reference price, fully diluted value, cost of capital and peers
A2: Valuation date 27 Oct 2026; balance sheet date 30 Jun 2026. Peer data: stockanalysis.com, close of 26 Oct 2026 (saved pages in evidence/market). USD millions unless stated.
A4: Item | B4: Value | C4: Comentarios FG | D4: Source / derivation
A6: A. Dates and reference price
A7: Valuation date | B7: =DATE(2026,10,27) -> 46322 | D7: Day after the S-1 filing.
A8: Balance sheet date | B8: =DATE(2026,6,30) -> 46203 | D8: Latest balance sheet in the S-1.
A9: Years from the balance sheet date to the valuation date | B9: =(B7-B8)/365 -> 0.3260274
A10: Reference price: Series H price per common share (USD) | B10: =Cap_Table!C52 -> 58.90095 | D10: US$589.0095 per preferred share / 10 (S-1). No IPO price range yet.
A11: Fully diluted shares (millions) | B11: =Cap_Table!B47 -> 16281.166
A12: Equity value at the reference price | B12: =B10*B11 -> 958976.16
A13: Less: cash and short-term investments, 30 Jun 2026 | B13: =BS_Hist!D45 -> 131651
A14: Plus: lease liabilities, 30 Jun 2026 | B14: =BS_Hist!D47 -> 1522
A15: Enterprise value at the reference price | B15: =B12-B13+B14 -> 828847.16
A16: Revenue, next twelve months (Q4 2026E + 0.75 x 2027E) | B16: =Interim_Bridge!C9+0.75*Forecast_3Stmt!D7 -> 107287.95 | D16: From the valuation date; active scenario.
A17: EV / revenue 2026E (x) | B17: =B15/Forecast_3Stmt!C7 -> 15.128813
A18: EV / revenue, next twelve months (x) | B18: =B15/B16 -> 7.725445
A19: EV / revenue 2027E (x) | B19: =B15/Forecast_3Stmt!D7 -> 7.2041967
A20: EV / EBITDA 2028E (x) | B20: =IF(Forecast_3Stmt!E28>0,B15/Forecast_3Stmt!E28,0) -> 22.299361
A21: EV / EBITDA 2030E (x) | B21: =IF(Forecast_3Stmt!G28>0,B15/Forecast_3Stmt!G28,0) -> 8.0746988
A23: B. Cost of capital
A24: Risk-free rate: 10-year US Treasury | B24: 0.05 | D24: home.treasury.gov, daily par yield curve, 10-year, 26 Oct 2026 (as read for the Meta model, dated source snapshot)
A25: Equity risk premium | B25: 0.042 | D25: A. Damodaran implied ERP with adjusted payout, Oct 2026, as quoted by yxinsights.com (same source as the Meta model). Alternative 3.70% (A. Damodaran implied ERP, blog, Oct 2026 (same source as the Meta model)).
A26: Beta: median of the 11 peers below | B26: =MEDIAN(G33:G43) -> 1.456 | D26: No trading history for Anthropic. 5-year betas from stockanalysis.com.
A27: Cost of equity (CAPM) | B27: =B24+B26*B25 -> 0.111152
A28: Debt weight | B28: 0 | D28: No financial debt after the IPO; leases are small.
A29: WACC | B29: =B27*(1-B28) -> 0.111152
A31: C. Peers (close of 26 Oct 2026)
A32: Company | B32: Ticker | C32: Market cap | D32: Enterprise value | E32: Forward P/S (x) | F32: EV / NTM revenue (x) | G32: Beta (5Y) | H32: Revenue growth, 3Y forecast | I32: Forward P/E (x) | J32: Group | K32: Source
A33: Microsoft | B33: MSFT | C33: 3955314.9 | D33: 4007284.9 | E33: 10.11 | F33: =E33*D33/C33 -> 10.242838 | G33: 1.099 | H33: 0.1977 | I33: 26.954 | J33: AI platforms | K33: stockanalysis_msft_statistics_2026-10-27.html
A34: Alphabet | B34: GOOGL | C34: 3874464 | D34: 3752781 | E34: 6.972 | F34: =E34*D34/C34 -> 6.7530345 | G34: 1.211 | H34: 0.2328 | I34: 23.682 | J34: AI platforms | K34: stockanalysis_googl_statistics_2026-10-27.html
A35: Amazon | B35: AMZN | C35: 2686762.8 | D35: 2815409.8 | E35: 3.035 | F35: =E35*D35/C35 -> 3.1803212 | G35: 1.456 | H35: 0.154 | I35: 26.813 | J35: AI platforms | K35: stockanalysis_amzn_statistics_2026-10-27.html
A36: Meta Platforms | B36: META | C36: 1611863.5 | D36: 1644256.5 | E36: 5.452 | F36: =E36*D36/C36 -> 5.5615667 | G36: 1.185 | H36: 0.228 | I36: 19.174 | J36: AI platforms | K36: stockanalysis_meta_statistics_2026-10-27.html
A37: NVIDIA | B37: NVDA | C37: 5215752 | D37: 5192143 | E37: 9.689 | F37: =E37*D37/C37 -> 9.6451429 | G37: 2.216 | H37: 0.6112 | I37: 17.859 | J37: AI platforms | K37: stockanalysis_nvda_statistics_2026-10-27.html
A38: Oracle | B38: ORCL | C38: 382151.03 | D38: 514217.03 | E38: 3.872 | F38: =E38*D38/C38 -> 5.2101085 | G38: 1.77 | H38: 0.3974 | I38: 14.804 | J38: AI platforms | K38: stockanalysis_orcl_statistics_2026-10-27.html
A39: Palantir | B39: PLTR | C39: 477824.15 | D39: 468626.45 | E39: 46.886 | F39: =E39*D39/C39 -> 45.983485 | G39: 1.602 | H39: 0.5852 | I39: 104.94 | J39: High-growth software | K39: stockanalysis_pltr_statistics_2026-10-27.html
A40: Cloudflare | B40: NET | C40: 118168.61 | D40: 117535.17 | E40: 36.248 | F40: =E40*D40/C40 -> 36.053691 | G40: 1.646 | H40: 0.2972 | I40: 224.048 | J40: High-growth software | K40: stockanalysis_net_statistics_2026-10-27.html
A41: Snowflake | B41: SNOW | C41: 118054.8 | D41: 116481.94 | E41: 16.47 | F41: =E41*D41/C41 -> 16.250568 | G41: 1.351 | H41: 0.3051 | I41: 132.848 | J41: High-growth software | K41: stockanalysis_snow_statistics_2026-10-27.html
A42: CrowdStrike | B42: CRWD | C42: 268671.58 | D42: 264477.91 | E42: 40.379 | F42: =E42*D42/C42 -> 39.748728 | G42: 1.197 | H42: 0.233 | I42: 185.34 | J42: High-growth software | K42: stockanalysis_crwd_statistics_2026-10-27.html
A43: Datadog | B43: DDOG | C43: 100627.18 | D43: 96919.548 | E43: 20.373 | F43: =E43*D43/C43 -> 19.622351 | G43: 1.512 | H43: 0.2559 | I43: 105.727 | J43: High-growth software | K43: stockanalysis_ddog_statistics_2026-10-27.html

Sheet DCF
A1: Anthropic, PBC | Discounted cash flow: unlevered free cash flow, perpetuity and exit multiple
A2: Cash flows from 1 Jul 2026, discounted to 30 Jun 2026 at mid-period, then rolled to the valuation date. Active scenario. USD millions except per share.
C3: Forecast
A4: Fiscal year ends 31 December | C4: H2 2026E | D4: 2027E | E4: 2028E | F4: 2029E | G4: 2030E | H4: 2031E | I4: 2032E | J4: 2033E | K4: 2034E | L4: 2035E | M4: Comentarios FG | N4: Source / derivation
A5: Revenue | C5: =Interim_Bridge!C7 -> 38500 | D5: =Forecast_3Stmt!D7 -> 115050.6 | E5: =Forecast_3Stmt!E7 -> 184080.96 | F5: =Forecast_3Stmt!F7 -> 254031.72 | G5: =Forecast_3Stmt!G7 -> 322620.29 | H5: =Forecast_3Stmt!H7 -> 387144.35 | I5: =Forecast_3Stmt!I7 -> 445216 | J5: =Forecast_3Stmt!J7 -> 498641.92 | K5: =Forecast_3Stmt!K7 -> 548506.11 | L5: =Forecast_3Stmt!L7 -> 592386.6
A6: Operating income | C6: =Interim_Bridge!C18 -> 1622.5 | D6: =Schedules!D28 -> 13230.819 | E6: =Schedules!E28 -> 34054.978 | F6: =Schedules!F28 -> 62237.773 | G6: =Schedules!G28 -> 93559.884 | H6: =Schedules!H28 -> 127757.64 | I6: =Schedules!I28 -> 160277.76 | J6: =Schedules!J28 -> 186990.72 | K6: =Schedules!K28 -> 213917.38 | L6: =Schedules!L28 -> 231030.77
A7: Taxes on operating income | C7: =-Interim_Bridge!C25*MAX(Interim_Bridge!C18,0)/MAX(Interim_Bridge!C18+Interim_Bridge!C22,1) -> -66.721839 | D7: =-Schedules!D29 -> -1845.3732 | E7: =-Schedules!E29 -> -7151.5453 | F7: =-Schedules!F29 -> -13069.932 | G7: =-Schedules!G29 -> -19647.576 | H7: =-Schedules!H29 -> -26829.103 | I7: =-Schedules!I29 -> -33658.33 | J7: =-Schedules!J29 -> -39268.051 | K7: =-Schedules!K29 -> -44922.651 | L7: =-Schedules!L29 -> -48516.463
A8: Net operating profit after tax | C8: =C6+C7 -> 1555.7782 | D8: =D6+D7 -> 11385.446 | E8: =E6+E7 -> 26903.432 | F8: =F6+F7 -> 49167.84 | G8: =G6+G7 -> 73912.309 | H8: =H6+H7 -> 100928.53 | I8: =I6+I7 -> 126619.43 | J8: =J6+J7 -> 147722.67 | ... L8: =L6+L7 -> 182514.31
A9: Depreciation and amortization | C9: =Interim_Bridge!C19 -> 193.7 | D9: =Schedules!D31 -> 1188.9636 | E9: =Schedules!E31 -> 3114.1222 | F9: =Schedules!F31 -> 5996.1992 | G9: =Schedules!G31 -> 9087.5552 | H9: =Schedules!H31 -> 11851.252 | I9: =Schedules!I31 -> 14475.164 | J9: =Schedules!J31 -> 16744.637 | K9: =Schedules!K31 -> 18631.45 | L9: =Schedules!L31 -> 20609.623
A10: Capital expenditures | C10: =Interim_Bridge!C35 -> -1500 | D10: =Schedules!D32 -> -6903.036 | E10: =Schedules!E32 -> -14726.477 | F10: =Schedules!F32 -> -20322.538 | G10: =Schedules!G32 -> -22583.42 | H10: =Schedules!H32 -> -23228.661 | I10: =Schedules!I32 -> -26712.96 | J10: =Schedules!J32 -> -24932.096 | K10: =Schedules!K32 -> -27425.306 | L10: =Schedules!L32 -> -29619.33
A11: Change in working capital | C11: =Interim_Bridge!C33 -> -228.47 | D11: =Schedules!D33 -> 60.723 | E11: =Schedules!E33 -> -759.33396 | F11: =Schedules!F33 -> -1594.1411 | G11: =Schedules!G33 -> -2415.8417 | H11: =Schedules!H33 -> -3161.6788 | I11: =Schedules!I33 -> -2439.0094 | J11: =Schedules!J33 -> -2671.296 | K11: =Schedules!K33 -> -1246.6048 | L11: =Schedules!L33 -> -1097.0122
A12: Unlevered free cash flow | C12: =C8+C9+C10+C11 -> 21.008161 | D12: =D8+D9+D10+D11 -> 5732.0964 | E12: =E8+E9+E10+E11 -> 14531.744 | F12: =F8+F9+F10+F11 -> 33247.36 | G12: =G8+G9+G10+G11 -> 58000.602 | H12: =H8+H9+H10+H11 -> 86389.444 | I12: =I8+I9+I10+I11 -> 111942.63 | J12: =J8+J9+J10+J11 -> 136863.91 | ... L12: =L8+L9+L10+L11 -> 172407.59
A13: Years from 30 Jun 2026 to mid-period | C13: 0.25 | D13: 1 | E13: =D13+1 -> 2 | F13: =E13+1 -> 3 | G13: =F13+1 -> 4 | H13: =G13+1 -> 5 | I13: =H13+1 -> 6 | J13: =I13+1 -> 7 | K13: =J13+1 -> 8 | L13: =K13+1 -> 9
A14: Discount factor | C14: =1/(1+$C$18)^C13 -> 0.97399479 | D14: =1/(1+$C$18)^D13 -> 0.89996688 | E14: =1/(1+$C$18)^E13 -> 0.80994039 | F14: =1/(1+$C$18)^F13 -> 0.72891952 | G14: =1/(1+$C$18)^G13 -> 0.65600343 | H14: =1/(1+$C$18)^H13 -> 0.59038136 | I14: =1/(1+$C$18)^I13 -> 0.53132367 | J14: =1/(1+$C$18)^J13 -> 0.47817371 | ... L14: =1/(1+$C$18)^L13 -> 0.3872922
A15: Present value | C15: =C12*C14 -> 20.46184 | D15: =D12*D14 -> 5158.6969 | E15: =E12*E14 -> 11769.846 | F15: =F12*F14 -> 24234.65 | G15: =G12*G14 -> 38048.594 | H15: =H12*H14 -> 51002.718 | I15: =I12*I14 -> 59477.767 | J15: =J12*J14 -> 65444.725 | ... L15: =L12*L14 -> 66772.116
A17: Value (perpetuity growth method)
A18: WACC | C18: =Market_Package!B29 -> 0.111152
A19: Terminal growth | C19: =Assumptions!$C$16 -> 0.03
A20: Terminal return on new invested capital | C20: =Assumptions!$C$17 -> 0.25
A21: Sum of present values, H2 2026E-2035E | C21: =SUM(C15:L15) -> 390334.04
A22: NOPAT 2036E (2035E x (1 + growth)) | C22: =L8*(1+C19) -> 187989.74
A23: Reinvestment rate (growth / ROIC) | C23: =C19/C20 -> 0.12
A24: Terminal value at 31 Dec 2035 | C24: =C22*(1-C23)/(C18-C19) -> 2038532.3
A25: Years from 30 Jun 2026 to 31 Dec 2035 | C25: =L13+0.5 -> 9.5
A26: Present value of the terminal value | C26: =C24/(1+C18)^C25 -> 748978.94
A27: Enterprise value at 30 Jun 2026 | C27: =C21+C26 -> 1139313
A28: Enterprise value at the valuation date | C28: =C27*(1+C18)^Market_Package!B9 -> 1179142.9
A29: Plus: cash and short-term investments, 30 Jun 2026 | C29: =Market_Package!B13 -> 131651
A30: Less: lease liabilities | C30: =-Market_Package!B14 -> -1522
A31: Equity value | C31: =C28+C29+C30 -> 1309271.9
A32: Fully diluted shares (millions) | C32: =Market_Package!B11 -> 16281.166
A33: Value per share (USD) | C33: =C31/C32 -> 80.416348
A34: Series H price per common share (USD) | C34: =Market_Package!B10 -> 58.90095
A35: Value against the Series H price | C35: =C33/C34-1 -> 0.365281
A36: Terminal value share of enterprise value | C36: =C26/C27 -> 0.65739525
A37: Implied EV / EBITDA 2035E at the terminal value (x) | C37: =C24/Forecast_3Stmt!L28 -> 8.1009739
A39: Value (exit multiple method, cross-check)
A40: Exit EV / EBITDA 2035E (x) | C40: =Assumptions!$C$18 -> 15
A41: Terminal value at 31 Dec 2035 | C41: =Forecast_3Stmt!L28*C40 -> 3774606
A42: Enterprise value at the valuation date | C42: =(C21+C41/(1+C18)^C25)*(1+C18)^Market_Package!B9 -> 1839294.4
A43: Value per share (USD) | C43: =(C42+C29+C30)/C32 -> 120.96329
A44: Value against the Series H price | C44: =C43/C34-1 -> 1.0536729

Sheet Valuation
A1: Anthropic, PBC | Valuation: trading comparables, funding marks, reverse DCF and football field
A2: Per-share values in USD on the fully diluted count. Active scenario unless stated.
A4: A. Trading comparables: EV / revenue for the next twelve months
A5: Peer group | B5: 25th percentile | C5: Median | D5: 75th percentile | H5: Source / derivation
A6: AI platforms: EV / NTM revenue (x) | B6: =_xlfn.QUARTILE.INC(Market_Package!$F$33:$F$38,1) -> 5.2979731 | C6: =MEDIAN(Market_Package!$F$33:$F$38) -> 6.1573006 | D6: =_xlfn.QUARTILE.INC(Market_Package!$F$33:$F$38,3) -> 8.9221158
A7: Implied enterprise value | B7: =B6*Market_Package!B16 -> 568408.67 | C7: =C6*Market_Package!B16 -> 660604.16 | D7: =D6*Market_Package!B16 -> 957235.52
A8: Value per share | B8: =(B7+Market_Package!B13-Market_Package!B14)/Market_Package!B11 -> 42.904646 | C8: =(C7+Market_Package!B13-Market_Package!B14)/Market_Package!B11 -> 48.567354 | D8: =(D7+Market_Package!B13-Market_Package!B14)/Market_Package!B11 -> 66.786648
A9: High-growth software: EV / NTM revenue (x) | B9: =_xlfn.QUARTILE.INC(Market_Package!$F$39:$F$43,1) -> 19.622351 | C9: =MEDIAN(Market_Package!$F$39:$F$43) -> 36.053691 | D9: =_xlfn.QUARTILE.INC(Market_Package!$F$39:$F$43,3) -> 39.748728
A10: Implied enterprise value | B10: =B9*Market_Package!B16 -> 2105241.8 | C10: =C9*Market_Package!B16 -> 3868126.6 | D10: =D9*Market_Package!B16 -> 4264559.6
A11: Value per share | B11: =(B10+Market_Package!B13-Market_Package!B14)/Market_Package!B11 -> 137.29795 | C11: =(C10+Market_Package!B13-Market_Package!B14)/Market_Package!B11 -> 245.5755 | D11: =(D10+Market_Package!B13-Market_Package!B14)/Market_Package!B11 -> 269.92468
A12: Memo: Anthropic revenue growth, 2027E on 2026E | C12: =Forecast_3Stmt!D8 -> 1.1 | H12: Peers' 3-year revenue growth forecasts run 15%-61% (Market_Package); multiples of slower peers understate a company growing faster.
A14: B. Funding rounds and fair value marks per common share (S-1)
A15: Series F-1 price / 10 (2025) | C15: =Cap_Table!C71/10 -> 14.097
A16: Series G-1 price / 10 (first quarter of 2026) | C16: =Cap_Table!C73/10 -> 25.914
A17: Series H-1 price / 10 (second quarter of 2026) | C17: =Cap_Table!C77/10 -> 58.901
A18: Common stock fair value for option grants, 6M 2026: low | C18: =Cap_Table!B85 -> 21.56
A19: Common stock fair value for option grants, 6M 2026: high | C19: =Cap_Table!C85 -> 57.14
A20: RSU grant-date fair value, 6M 2026 | C20: =Cap_Table!C86 -> 46.48
A22: C. Reverse DCF: revenue growth shift (all years 2027E-2035E) against value per share
A23: Growth shift (pp) | B23: Shift | C23: Value per share | D23: Revenue 2035E | E23: Revenue CAGR 2026E-2035E | H23: Source / derivation
A24: Shift of -10.0 pp | B24: -0.1 | C24: 46.813656 | D24: 284180.92 | E24: =(D24/Forecast_3Stmt!C7)^(1/9)-1 -> 0.20070452
A25: Shift of -7.5 pp | B25: -0.075 | C25: 53.432048 | D25: 343486.83 | E25: =(D25/Forecast_3Stmt!C7)^(1/9)-1 -> 0.2262592
A26: Shift of -5.0 pp | B26: -0.05 | C26: 61.130786 | D26: 413492.32 | E26: =(D26/Forecast_3Stmt!C7)^(1/9)-1 -> 0.25179466
A27: Shift of -2.5 pp | B27: -0.025 | C27: 70.066776 | D27: 495840.88 | E27: =(D27/Forecast_3Stmt!C7)^(1/9)-1 -> 0.27731194
A28: Shift of +0.0 pp | B28: 0 | C28: 80.416348 | D28: 592386.6 | E28: =(D28/Forecast_3Stmt!C7)^(1/9)-1 -> 0.30281196
A29: Shift of +2.5 pp | B29: 0.025 | C29: 92.377235 | D29: 705216.12 | E29: =(D29/Forecast_3Stmt!C7)^(1/9)-1 -> 0.32829561
A30: Shift of +5.0 pp | B30: 0.05 | C30: 106.1707 | D30: 836672.26 | E30: =(D30/Forecast_3Stmt!C7)^(1/9)-1 -> 0.3537637
A31: Shift of +7.5 pp | B31: 0.075 | C31: 122.04384 | D31: 989379.65 | E31: =(D31/Forecast_3Stmt!C7)^(1/9)-1 -> 0.37921699
A32: Shift of +10.0 pp | B32: 0.1 | C32: 140.27205 | D32: 1166272.2 | E32: =(D32/Forecast_3Stmt!C7)^(1/9)-1 -> 0.40465619
A33: Captured by the build | B33: MOG build 2026-10-27: Base scenario, compute shift 0
A34: Growth shift the Series H price needs (interpolated) | C34: =IFERROR(INDEX($B$24:$B$32,MATCH(Market_Package!B10,$C$24:$C$32,1))+(Market_Package!B10-INDEX($C$24:$C$32,MATCH(Market_Package!B10,$C$24:$C$32,1)))*(INDEX($B$24:$B$32,MATCH(Market_Package!B10,$C$24:$C$32,1)+1)-INDEX($B$24:$B$32,MATCH(Market_Package!B10,$C$24:$C$32,1)))/(INDEX($C$24:$C$32,MATCH(Market_Package!B10,$C$24:$C$32,1)+1)-INDEX($C$24:$C$32,MATCH(Market_Package!B10,$C$24:$C$32,1))),"outside grid") -> -0.057240915 | H34: Linear interpolation between the two grid points around the Series H price; Base scenario.
A35: Revenue 2035E at that shift (interpolated) | C35: =IFERROR(INDEX($D$24:$D$32,MATCH(Market_Package!B10,$C$24:$C$32,1))+(Market_Package!B10-INDEX($C$24:$C$32,MATCH(Market_Package!B10,$C$24:$C$32,1)))*(INDEX($D$24:$D$32,MATCH(Market_Package!B10,$C$24:$C$32,1)+1)-INDEX($D$24:$D$32,MATCH(Market_Package!B10,$C$24:$C$32,1)))/(INDEX($C$24:$C$32,MATCH(Market_Package!B10,$C$24:$C$32,1)+1)-INDEX($C$24:$C$32,MATCH(Market_Package!B10,$C$24:$C$32,1))),"outside grid") -> 393216.17
A36: Revenue CAGR 2026E-2035E the price needs | C36: =IFERROR((C35/Forecast_3Stmt!C7)^(1/9)-1,"outside grid") -> 0.24482088
A37: Revenue CAGR 2026E-2035E in the active scenario | C37: =(Forecast_3Stmt!L7/Forecast_3Stmt!C7)^(1/9)-1 -> 0.30281196
A39: D. Football field: value per share by method
A40: Method | B40: Low | C40: Mid | D40: High | E40: Low basis | F40: Mid basis | G40: High basis | H40: Source / derivation
A41: DCF, perpetuity growth | B41: =Scenario_Summary!F21 -> 22.36499 | C41: =Scenario_Summary!D21 -> 80.416348 | D41: =Scenario_Summary!E21 -> 146.79887 | E41: Bear | F41: Base | G41: Bull | H41: Scenario_Summary (captured by the build)
A42: DCF, exit multiple | B42: =Scenario_Summary!F22 -> 30.789908 | C42: =Scenario_Summary!D22 -> 120.96329 | D42: =Scenario_Summary!E22 -> 239.93712 | E42: Bear | F42: Base | G42: Bull | H42: Scenario_Summary (captured by the build)
A43: Comparables, AI platforms | B43: =B8 -> 42.904646 | C43: =C8 -> 48.567354 | D43: =D8 -> 66.786648 | E43: 25th pct | F43: Median | G43: 75th pct
A44: Comparables, high-growth software | B44: =B11 -> 137.29795 | C44: =C11 -> 245.5755 | D44: =D11 -> 269.92468 | E44: 25th pct | F44: Median | G44: 75th pct
A45: Last two funding rounds | B45: =C16 -> 25.914 | C45: =C17 -> 58.901 | D45: =C17 -> 58.901 | E45: Series G | F45: Series H | G45: Series H
A46: Common stock fair value, 6M 2026 | B46: =C18 -> 21.56 | C46: =C20 -> 46.48 | D46: =C19 -> 57.14 | E46: Option low | F46: RSU grants | G46: Option high
A48: E. Probability-weighted DCF value (weights are a convention)
A49: Weight: Bear | C49: 0.25
A50: Weight: Base | C50: 0.5
A51: Weight: Bull | C51: 0.25
A52: Weighted value per share | C52: =C49*Scenario_Summary!F21+C50*Scenario_Summary!D21+C51*Scenario_Summary!E21 -> 82.499139
A53: Against the Series H price | C53: =C52/Market_Package!B10-1 -> 0.40064191
A54: Weights add to 100% | C54: =C49+C50+C51-1 -> 0

Sheet Sensitivity
A1: Anthropic, PBC | Sensitivity of value per share (USD)
A2: Table 1 is live (formulas, active scenario). Table 2 is captured by re-running the model in the build (Base scenario).
A4: Table 1. WACC (rows) against terminal growth (columns); perpetuity method, live
A5: WACC \ terminal growth | B5: =DCF!C19+-0.01 -> 0.02 | C5: =DCF!C19+-0.005 -> 0.025 | D5: =DCF!C19+0 -> 0.03 | E5: =DCF!C19+0.005 -> 0.035 | F5: =DCF!C19+0.01 -> 0.04
A6: =DCF!C18+-0.02 -> 0.091152 | B6: =((SUMPRODUCT(DCF!$C$12:$L$12,1/(1+$A6)^DCF!$C$13:$L$13)+DCF!$L$8*(1+B$5)*(1-B$5/DCF!$C$20)/($A6-B$5)/(1+$A6)^DCF!$C$25)*(1+$A6)^Market_Package!$B$9+DCF!$C$29+DCF!$C$30)/DCF!$C$32 -> 102.09766 | C6: =((SUMPRODUCT(DCF!$C$12:$L$12,1/(1+$A6)^DCF!$C$13:$L$13)+DCF!$L$8*(1+C$5)*(1-C$5/DCF!$C$20)/($A6-C$5)/(1+$A6)^DCF!$C$25)*(1+$A6)^Market_Package!$B$9+DCF!$C$29+DCF!$C$30)/DCF!$C$32 -> 105.90706 | D6: =((SUMPRODUCT(DCF!$C$12:$L$12,1/(1+$A6)^DCF!$C$13:$L$13)+DCF!$L$8*(1+D$5)*(1-D$5/DCF!$C$20)/($A6-D$5)/(1+$A6)^DCF!$C$25)*(1+$A6)^Market_Package!$B$9+DCF!$C$29+DCF!$C$30)/DCF!$C$32 -> 110.32293 | E6: =((SUMPRODUCT(DCF!$C$12:$L$12,1/(1+$A6)^DCF!$C$13:$L$13)+DCF!$L$8*(1+E$5)*(1-E$5/DCF!$C$20)/($A6-E$5)/(1+$A6)^DCF!$C$25)*(1+$A6)^Market_Package!$B$9+DCF!$C$29+DCF!$C$30)/DCF!$C$32 -> 115.50727 | F6: =((SUMPRODUCT(DCF!$C$12:$L$12,1/(1+$A6)^DCF!$C$13:$L$13)+DCF!$L$8*(1+F$5)*(1-F$5/DCF!$C$20)/($A6-F$5)/(1+$A6)^DCF!$C$25)*(1+$A6)^Market_Package!$B$9+DCF!$C$29+DCF!$C$30)/DCF!$C$32 -> 121.68545
A7: =DCF!C18+-0.01 -> 0.101152 | B7: =((SUMPRODUCT(DCF!$C$12:$L$12,1/(1+$A7)^DCF!$C$13:$L$13)+DCF!$L$8*(1+B$5)*(1-B$5/DCF!$C$20)/($A7-B$5)/(1+$A7)^DCF!$C$25)*(1+$A7)^Market_Package!$B$9+DCF!$C$29+DCF!$C$30)/DCF!$C$32 -> 87.748715 | C7: =((SUMPRODUCT(DCF!$C$12:$L$12,1/(1+$A7)^DCF!$C$13:$L$13)+DCF!$L$8*(1+C$5)*(1-C$5/DCF!$C$20)/($A7-C$5)/(1+$A7)^DCF!$C$25)*(1+$A7)^Market_Package!$B$9+DCF!$C$29+DCF!$C$30)/DCF!$C$32 -> 90.298004 | D7: =((SUMPRODUCT(DCF!$C$12:$L$12,1/(1+$A7)^DCF!$C$13:$L$13)+DCF!$L$8*(1+D$5)*(1-D$5/DCF!$C$20)/($A7-D$5)/(1+$A7)^DCF!$C$25)*(1+$A7)^Market_Package!$B$9+DCF!$C$29+DCF!$C$30)/DCF!$C$32 -> 93.192562 | E7: =((SUMPRODUCT(DCF!$C$12:$L$12,1/(1+$A7)^DCF!$C$13:$L$13)+DCF!$L$8*(1+E$5)*(1-E$5/DCF!$C$20)/($A7-E$5)/(1+$A7)^DCF!$C$25)*(1+$A7)^Market_Package!$B$9+DCF!$C$29+DCF!$C$30)/DCF!$C$32 -> 96.51068 | F7: =((SUMPRODUCT(DCF!$C$12:$L$12,1/(1+$A7)^DCF!$C$13:$L$13)+DCF!$L$8*(1+F$5)*(1-F$5/DCF!$C$20)/($A7-F$5)/(1+$A7)^DCF!$C$25)*(1+$A7)^Market_Package!$B$9+DCF!$C$29+DCF!$C$30)/DCF!$C$32 -> 100.35625
A8: =DCF!C18+0 -> 0.111152 | B8: =((SUMPRODUCT(DCF!$C$12:$L$12,1/(1+$A8)^DCF!$C$13:$L$13)+DCF!$L$8*(1+B$5)*(1-B$5/DCF!$C$20)/($A8-B$5)/(1+$A8)^DCF!$C$25)*(1+$A8)^Market_Package!$B$9+DCF!$C$29+DCF!$C$30)/DCF!$C$32 -> 76.689571 | C8: =((SUMPRODUCT(DCF!$C$12:$L$12,1/(1+$A8)^DCF!$C$13:$L$13)+DCF!$L$8*(1+C$5)*(1-C$5/DCF!$C$20)/($A8-C$5)/(1+$A8)^DCF!$C$25)*(1+$A8)^Market_Package!$B$9+DCF!$C$29+DCF!$C$30)/DCF!$C$32 -> 78.449762 | D8: =((SUMPRODUCT(DCF!$C$12:$L$12,1/(1+$A8)^DCF!$C$13:$L$13)+DCF!$L$8*(1+D$5)*(1-D$5/DCF!$C$20)/($A8-D$5)/(1+$A8)^DCF!$C$25)*(1+$A8)^Market_Package!$B$9+DCF!$C$29+DCF!$C$30)/DCF!$C$32 -> 80.416348 | E8: =((SUMPRODUCT(DCF!$C$12:$L$12,1/(1+$A8)^DCF!$C$13:$L$13)+DCF!$L$8*(1+E$5)*(1-E$5/DCF!$C$20)/($A8-E$5)/(1+$A8)^DCF!$C$25)*(1+$A8)^Market_Package!$B$9+DCF!$C$29+DCF!$C$30)/DCF!$C$32 -> 82.629984 | F8: =((SUMPRODUCT(DCF!$C$12:$L$12,1/(1+$A8)^DCF!$C$13:$L$13)+DCF!$L$8*(1+F$5)*(1-F$5/DCF!$C$20)/($A8-F$5)/(1+$A8)^DCF!$C$25)*(1+$A8)^Market_Package!$B$9+DCF!$C$29+DCF!$C$30)/DCF!$C$32 -> 85.142751
A9: =DCF!C18+0.01 -> 0.121152 | B9: =((SUMPRODUCT(DCF!$C$12:$L$12,1/(1+$A9)^DCF!$C$13:$L$13)+DCF!$L$8*(1+B$5)*(1-B$5/DCF!$C$20)/($A9-B$5)/(1+$A9)^DCF!$C$25)*(1+$A9)^Market_Package!$B$9+DCF!$C$29+DCF!$C$30)/DCF!$C$32 -> 67.9347 | C9: =((SUMPRODUCT(DCF!$C$12:$L$12,1/(1+$A9)^DCF!$C$13:$L$13)+DCF!$L$8*(1+C$5)*(1-C$5/DCF!$C$20)/($A9-C$5)/(1+$A9)^DCF!$C$25)*(1+$A9)^Market_Package!$B$9+DCF!$C$29+DCF!$C$30)/DCF!$C$32 -> 69.17958 | D9: =((SUMPRODUCT(DCF!$C$12:$L$12,1/(1+$A9)^DCF!$C$13:$L$13)+DCF!$L$8*(1+D$5)*(1-D$5/DCF!$C$20)/($A9-D$5)/(1+$A9)^DCF!$C$25)*(1+$A9)^Market_Package!$B$9+DCF!$C$29+DCF!$C$30)/DCF!$C$32 -> 70.552417 | E9: =((SUMPRODUCT(DCF!$C$12:$L$12,1/(1+$A9)^DCF!$C$13:$L$13)+DCF!$L$8*(1+E$5)*(1-E$5/DCF!$C$20)/($A9-E$5)/(1+$A9)^DCF!$C$25)*(1+$A9)^Market_Package!$B$9+DCF!$C$29+DCF!$C$30)/DCF!$C$32 -> 72.07549 | F9: =((SUMPRODUCT(DCF!$C$12:$L$12,1/(1+$A9)^DCF!$C$13:$L$13)+DCF!$L$8*(1+F$5)*(1-F$5/DCF!$C$20)/($A9-F$5)/(1+$A9)^DCF!$C$25)*(1+$A9)^Market_Package!$B$9+DCF!$C$29+DCF!$C$30)/DCF!$C$32 -> 73.776568
A10: =DCF!C18+0.02 -> 0.131152 | B10: =((SUMPRODUCT(DCF!$C$12:$L$12,1/(1+$A10)^DCF!$C$13:$L$13)+DCF!$L$8*(1+B$5)*(1-B$5/DCF!$C$20)/($A10-B$5)/(1+$A10)^DCF!$C$25)*(1+$A10)^Market_Package!$B$9+DCF!$C$29+DCF!$C$30)/DCF!$C$32 -> 60.854072 | C10: =((SUMPRODUCT(DCF!$C$12:$L$12,1/(1+$A10)^DCF!$C$13:$L$13)+DCF!$L$8*(1+C$5)*(1-C$5/DCF!$C$20)/($A10-C$5)/(1+$A10)^DCF!$C$25)*(1+$A10)^Market_Package!$B$9+DCF!$C$29+DCF!$C$30)/DCF!$C$32 -> 61.751181 | D10: =((SUMPRODUCT(DCF!$C$12:$L$12,1/(1+$A10)^DCF!$C$13:$L$13)+DCF!$L$8*(1+D$5)*(1-D$5/DCF!$C$20)/($A10-D$5)/(1+$A10)^DCF!$C$25)*(1+$A10)^Market_Package!$B$9+DCF!$C$29+DCF!$C$30)/DCF!$C$32 -> 62.729822 | E10: =((SUMPRODUCT(DCF!$C$12:$L$12,1/(1+$A10)^DCF!$C$13:$L$13)+DCF!$L$8*(1+E$5)*(1-E$5/DCF!$C$20)/($A10-E$5)/(1+$A10)^DCF!$C$25)*(1+$A10)^Market_Package!$B$9+DCF!$C$29+DCF!$C$30)/DCF!$C$32 -> 63.802716 | F10: =((SUMPRODUCT(DCF!$C$12:$L$12,1/(1+$A10)^DCF!$C$13:$L$13)+DCF!$L$8*(1+F$5)*(1-F$5/DCF!$C$20)/($A10-F$5)/(1+$A10)^DCF!$C$25)*(1+$A10)^Market_Package!$B$9+DCF!$C$29+DCF!$C$30)/DCF!$C$32 -> 64.985373
A11: Centre cell equals the DCF value per share | D11: =D8-DCF!C33 -> 0
A13: Table 2. Revenue growth shift, all years 2027E-2035E (rows) against compute cost shift (columns); Base, captured
A14: Growth shift \ compute shift (pp of revenue) | B14: -0.05 | C14: -0.025 | D14: 0 | E14: 0.025 | F14: 0.05
A15: -0.1 | B15: 52.625744 | C15: 49.72003 | D15: 46.813656 | E15: 43.906255 | F15: 40.997125
A16: -0.05 | B16: 68.866412 | C16: 64.998926 | D16: 61.130786 | E16: 57.261623 | F16: 53.39073
A17: 0 | B17: 90.720795 | C17: 85.568897 | D17: 80.416348 | E17: 75.262781 | F17: 70.107484
A18: 0.05 | B18: 119.88173 | C18: 113.02654 | D18: 106.1707 | E18: 99.31385 | F18: 92.45527
A19: 0.1 | B19: 158.46808 | C19: 149.37039 | D19: 140.27205 | E19: 131.1727 | F19: 122.07162
A20: Captured by the build | B20: MOG build 2026-10-27: Base scenario, all other inputs as saved
A21: Table 2 centre equals the Base DCF value (captured) | D21: =D17-Scenario_Summary!D21 -> 0

Sheet Scenario_Summary
A1: Anthropic, PBC | Scenario summary: Base, Bull and Bear
A2: Column C is live (active scenario). Columns D to F were captured by the build, running the switch 1, 2, 3 with the sensitivity shifts at zero.
A4: Output | C4: Live | D4: Base | E4: Bull | F4: Bear | G4: Source / derivation
A5: Revenue 2026E | C5: =Forecast_3Stmt!C7 -> 54786 | D5: 54786 | E5: 60286 | F5: 50486
A6: Revenue 2027E | C6: =Forecast_3Stmt!D7 -> 115050.6 | D6: 115050.6 | E6: 135643.5 | F6: 85826.2
A7: Revenue 2028E | C7: =Forecast_3Stmt!E7 -> 184080.96 | D7: 184080.96 | E7: 230593.95 | F7: 115865.37
A8: Revenue 2030E | C8: =Forecast_3Stmt!G7 -> 322620.29 | D8: 322620.29 | E8: 441356.82 | F8: 162559.11
A9: Revenue 2035E | C9: =Forecast_3Stmt!L7 -> 592386.6 | D9: 592386.6 | E9: 890733.66 | F9: 234228.5
A10: Revenue CAGR 2026E-2035E | C10: =(Forecast_3Stmt!L7/Forecast_3Stmt!C7)^(1/9)-1 -> 0.30281196 | D10: 0.30281196 | E10: 0.34880117 | F10: 0.18591097
A11: Operating margin 2026E | C11: =Forecast_3Stmt!C18 -> 0.016966013 | D11: 0.016966013 | E11: 0.065139502 | F11: -0.03799073
A12: Operating margin 2027E | C12: =Forecast_3Stmt!D18 -> 0.115 | D12: 0.115 | E12: 0.175 | F12: 0
A13: Operating margin 2030E | C13: =Forecast_3Stmt!G18 -> 0.29 | D13: 0.29 | E13: 0.375 | F13: 0.14
A14: Operating margin 2035E | C14: =Forecast_3Stmt!L18 -> 0.39 | D14: 0.39 | E14: 0.465 | F14: 0.23
A15: Net income 2027E | C15: =Forecast_3Stmt!D23 -> 15583.378 | D15: 15583.378 | E15: 23449.376 | F15: 4595.0234
A16: Free cash flow 2027E | C16: =Forecast_3Stmt!D60 -> 21435.089 | D16: 21435.089 | E16: 28142.598 | F16: 10283.914
A17: Unlevered free cash flow, 2027E-2030E total | C17: =SUM(Schedules!D34:'Schedules'!G34) -> 111511.8 | D17: 111511.8 | E17: 214435.24 | F17: 1870.735
A18: Cash and short-term investments 2030E | C18: =Forecast_3Stmt!G33 -> 335225.13 | D18: 335225.13 | E18: 452555.33 | F18: 204992.12
A19: Enterprise value, perpetuity method | C19: =DCF!C28 -> 1179142.9 | D19: 1179142.9 | E19: 2259927.8 | F19: 233999.12
A20: Terminal value share of enterprise value | C20: =DCF!C36 -> 0.65739525 | D20: 0.65739525 | E20: 0.67345767 | F20: 0.68569838
A21: DCF value per share, perpetuity (USD) | C21: =DCF!C33 -> 80.416348 | D21: 80.416348 | E21: 146.79887 | F21: 22.36499
A22: DCF value per share, exit multiple (USD) | C22: =DCF!C43 -> 120.96329 | D22: 120.96329 | E22: 239.93712 | F22: 30.789908
A23: Perpetuity value against the Series H price | C23: =DCF!C35 -> 0.365281 | D23: 0.365281 | E23: 1.4923006 | F23: -0.62029492
A24: Captured by the build | D24: MOG build 2026-10-27: switch 1, 2, 3 with sensitivity shifts at 0
A25: With the switch on Base, live equals the captured Base | C25: =IF(Assumptions!$C$5=1,SUMPRODUCT((C5:C23-D5:D23)^2),0) -> 0

Sheet Limitations
A1: Anthropic, PBC | Limitations of this model
A2: Read before using any number.
A4: # | B4: Limitation | D4: Comentarios FG | E4: Effect
A5: 1 | B5: The S-1 is a preliminary prospectus. The price range, the shares offered, the 30 Sep 2026 liquidity and the compute commitments after 31 Dec 2025 are blank. | E5: The share count and the cash after the IPO can change.
A6: 2 | B6: The latest statements are for the six months to 30 Jun 2026 (unaudited). Q3 2026 revenue is not given; the model uses a floor derived from the S-1 (revenue per employee) and an estimate above it. | E6: 2026E depends on two quarterly inputs.
A7: 3 | B7: Most of the 2023-2026 net loss is the change in fair value of convertible notes and other financial items (US$80.0bn of the US$80.7bn 6M 2026 loss). These stop when the notes convert. | E7: Net loss history says little about the business; the model uses operating income.
A8: 4 | B8: Stock-based compensation is a real cost in the DCF (not added back). Existing options and RSUs are in the fully diluted count. The RSU charge at the IPO (US$2.9bn) is in Q4 2026E. | E8: Adding back stock-based compensation would raise the value.
A9: 5 | B9: The fully diluted count (about 16.3bn shares) is built from S-1 Notes 10 to 12 and includes the 934m-share donation matching reserve; it matches the US$965bn Series H post-money within about 1%. | E9: Switch the reserve off in Cap_Table to see the effect.
A10: 6 | B10: The reference price is the Series H price (US$58.90 per common share, second quarter of 2026), a private round with preferred rights. It is not a public market price. | E10: The IPO price may differ.
A11: 7 | B11: Forecast drivers (growth, cost ratios, capex) are analyst inputs, not company guidance. The company's reported 2028 revenue projection (US$190-200bn) comes from press reports, not the S-1. | E11: Scenario and sensitivity tables show the range.
A12: 8 | B12: Compute is bought through cloud contracts, leases and, more and more, owned or leased infrastructure (Anthropic Direct). The model keeps all of it in one cost line plus a capex ratio. | E12: A shift from cloud to owned capacity moves cost from operating expense to capex and depreciation.
A13: 9 | B13: Loss carryforwards are estimated from the deferred tax asset (US$2,007m / 21%). Tax law changes and state taxes are not modelled. | E13: Small effect on value.
A14: 10 | B14: Comparables trade on different growth and margins. The multiples of slower peers understate a company growing faster; the high-growth software group is closer but much smaller. | E14: Treat comparables as a range, not a point.
A15: 11 | B15: Peer prices and the risk-free rate are as of 26 Oct 2026; the equity risk premium is Damodaran's October 2026 estimate. | E15: Values move with markets.

Sheet Checks
A1: Anthropic, PBC | Checks
A2: Every check on every sheet, linked here. Column C shows the largest absolute difference in the check row; zero passes. The master passes below 0.5.
A4: Master check (all checks below) | C4: =IF(MAX(MAX(C7:C69),-MIN(C7:C69))<0.5,"OK","ERROR") -> OK
A6: Check | B6: Sheet | C6: Value (0 = pass) | D6: Range
A7: Total operating expenses | B7: IS_Hist | C7: =MAX(MAX(IS_Hist!B27:F27),-MIN(IS_Hist!B27:F27)) -> 0 | D7: B27:F27
A8: Operating loss | B8: IS_Hist | C8: =MAX(MAX(IS_Hist!B28:F28),-MIN(IS_Hist!B28:F28)) -> 0 | D8: B28:F28
A9: Total other income (expense), net | B9: IS_Hist | C9: =MAX(MAX(IS_Hist!B29:F29),-MIN(IS_Hist!B29:F29)) -> 0 | D9: B29:F29
A10: Loss before provision for income taxes | B10: IS_Hist | C10: =MAX(MAX(IS_Hist!B30:F30),-MIN(IS_Hist!B30:F30)) -> 0 | D10: B30:F30
A11: Net loss | B11: IS_Hist | C11: =MAX(MAX(IS_Hist!B31:F31),-MIN(IS_Hist!B31:F31)) -> 0 | D11: B31:F31
A12: Net loss per share (rounded to cents) | B12: IS_Hist | C12: =MAX(MAX(IS_Hist!B32:F32),-MIN(IS_Hist!B32:F32)) -> 0 | D12: B32:F32
A13: Other comprehensive income (loss) | B13: CI_Hist | C13: =MAX(MAX(CI_Hist!B15:F15),-MIN(CI_Hist!B15:F15)) -> 0 | D13: B15:F15
A14: Comprehensive loss | B14: CI_Hist | C14: =MAX(MAX(CI_Hist!B16:F16),-MIN(CI_Hist!B16:F16)) -> 0 | D14: B16:F16
A15: Net loss equals the statement of operations | B15: CI_Hist | C15: =MAX(MAX(CI_Hist!B17:F17),-MIN(CI_Hist!B17:F17)) -> 0 | D15: B17:F17
A16: Total current assets | B16: BS_Hist | C16: =MAX(MAX(BS_Hist!B50:D50),-MIN(BS_Hist!B50:D50)) -> 0 | D16: B50:D50
A17: Total assets | B17: BS_Hist | C17: =MAX(MAX(BS_Hist!B51:D51),-MIN(BS_Hist!B51:D51)) -> 0 | D17: B51:D51
A18: Total current liabilities | B18: BS_Hist | C18: =MAX(MAX(BS_Hist!B52:D52),-MIN(BS_Hist!B52:D52)) -> 0 | D18: B52:D52
A19: Total liabilities | B19: BS_Hist | C19: =MAX(MAX(BS_Hist!B53:D53),-MIN(BS_Hist!B53:D53)) -> 0 | D19: B53:D53
A20: Total stockholders' deficit | B20: BS_Hist | C20: =MAX(MAX(BS_Hist!B54:D54),-MIN(BS_Hist!B54:D54)) -> 0 | D20: B54:D54
A21: Liabilities, preferred stock and deficit | B21: BS_Hist | C21: =MAX(MAX(BS_Hist!B55:D55),-MIN(BS_Hist!B55:D55)) -> 0 | D21: B55:D55
A22: Balance: total assets less the other side | B22: BS_Hist | C22: =MAX(MAX(BS_Hist!B56:D56),-MIN(BS_Hist!B56:D56)) -> 0 | D22: B56:D56
A23: Net cash from operating activities | B23: CF_Hist | C23: =MAX(MAX(CF_Hist!B47:F47),-MIN(CF_Hist!B47:F47)) -> 0 | D23: B47:F47
A24: Net cash used in investing activities | B24: CF_Hist | C24: =MAX(MAX(CF_Hist!B48:F48),-MIN(CF_Hist!B48:F48)) -> 0 | D24: B48:F48
A25: Net cash from financing activities | B25: CF_Hist | C25: =MAX(MAX(CF_Hist!B49:F49),-MIN(CF_Hist!B49:F49)) -> 0 | D25: B49:F49
A26: Net increase in cash | B26: CF_Hist | C26: =MAX(MAX(CF_Hist!B50:F50),-MIN(CF_Hist!B50:F50)) -> 0 | D26: B50:F50
A27: Beginning cash plus increase less ending cash | B27: CF_Hist | C27: =MAX(MAX(CF_Hist!B51:F51),-MIN(CF_Hist!B51:F51)) -> 0 | D27: B51:F51
A28: Net loss equals the statement of operations | B28: CF_Hist | C28: =MAX(MAX(CF_Hist!B52:F52),-MIN(CF_Hist!B52:F52)) -> 0 | D28: B52:F52
A29: Ending cash equals balance sheet cash plus restricted cash | B29: CF_Hist | C29: =MAX(MAX(CF_Hist!C53:F53),-MIN(CF_Hist!C53:F53)) -> 0 | D29: C53:F53
A30: Total deficit = APIC + AOCI + accumulated deficit, 31 Dec 2024 | B30: SCE_Hist | C30: =MAX(MAX(SCE_Hist!M58:M58),-MIN(SCE_Hist!M58:M58)) -> 0 | D30: M58:M58
A31: Preferred amount equals the balance sheet, 31 Dec 2024 | B31: SCE_Hist | C31: =MAX(MAX(SCE_Hist!C59:C59),-MIN(SCE_Hist!C59:C59)) -> 0 | D31: C59:C59
A32: Total deficit equals the balance sheet, 31 Dec 2024 | B32: SCE_Hist | C32: =MAX(MAX(SCE_Hist!M60:M60),-MIN(SCE_Hist!M60:M60)) -> 0 | D32: M60:M60
A33: Total deficit = APIC + AOCI + accumulated deficit, 31 Dec 2025 | B33: SCE_Hist | C33: =MAX(MAX(SCE_Hist!M61:M61),-MIN(SCE_Hist!M61:M61)) -> 0 | D33: M61:M61
A34: Preferred amount equals the balance sheet, 31 Dec 2025 | B34: SCE_Hist | C34: =MAX(MAX(SCE_Hist!C62:C62),-MIN(SCE_Hist!C62:C62)) -> 0 | D34: C62:C62
A35: Total deficit equals the balance sheet, 31 Dec 2025 | B35: SCE_Hist | C35: =MAX(MAX(SCE_Hist!M63:M63),-MIN(SCE_Hist!M63:M63)) -> 0 | D35: M63:M63
A36: Total deficit = APIC + AOCI + accumulated deficit, 30 Jun 2026 | B36: SCE_Hist | C36: =MAX(MAX(SCE_Hist!M64:M64),-MIN(SCE_Hist!M64:M64)) -> 0 | D36: M64:M64
A37: Preferred amount equals the balance sheet, 30 Jun 2026 | B37: SCE_Hist | C37: =MAX(MAX(SCE_Hist!C65:C65),-MIN(SCE_Hist!C65:C65)) -> 0 | D37: C65:C65
A38: Total deficit equals the balance sheet, 30 Jun 2026 | B38: SCE_Hist | C38: =MAX(MAX(SCE_Hist!M66:M66),-MIN(SCE_Hist!M66:M66)) -> 0 | D38: M66:M66
A39: Total operating expenses | B39: Quarterly_Hist | C39: =MAX(MAX(Quarterly_Hist!B40:G40),-MIN(Quarterly_Hist!B40:G40)) -> 0 | D39: B40:G40
A40: Net loss | B40: Quarterly_Hist | C40: =MAX(MAX(Quarterly_Hist!B41:G41),-MIN(Quarterly_Hist!B41:G41)) -> 0 | D40: B41:G41
A41: Adjusted operating income | B41: Quarterly_Hist | C41: =MAX(MAX(Quarterly_Hist!B42:G42),-MIN(Quarterly_Hist!B42:G42)) -> 0 | D41: B42:G42
A42: Quarters add up to the statements: rev | B42: Quarterly_Hist | C42: =MAX(MAX(Quarterly_Hist!B43:D43),-MIN(Quarterly_Hist!B43:D43)) -> 0 | D42: B43:D43
A43: Quarters add up to the statements: comp | B43: Quarterly_Hist | C43: =MAX(MAX(Quarterly_Hist!B44:D44),-MIN(Quarterly_Hist!B44:D44)) -> 0 | D43: B44:D44
A44: Quarters add up to the statements: topex | B44: Quarterly_Hist | C44: =MAX(MAX(Quarterly_Hist!B45:D45),-MIN(Quarterly_Hist!B45:D45)) -> 0 | D44: B45:D45
A45: Quarters add up to the statements: nl | B45: Quarterly_Hist | C45: =MAX(MAX(Quarterly_Hist!B46:D46),-MIN(Quarterly_Hist!B46:D46)) -> 0 | D45: B46:D46
A46: Revenue by pricing model adds to total | B46: Revenue_Hist | C46: =MAX(MAX(Revenue_Hist!B72:F72),-MIN(Revenue_Hist!B72:F72)) -> 0 | D46: B72:F72
A47: Revenue by pricing model equals the statement | B47: Revenue_Hist | C47: =MAX(MAX(Revenue_Hist!B73:F73),-MIN(Revenue_Hist!B73:F73)) -> 0 | D47: B73:F73
A48: Revenue by region equals the statement | B48: Revenue_Hist | C48: =MAX(MAX(Revenue_Hist!B74:F74),-MIN(Revenue_Hist!B74:F74)) -> 0 | D48: B74:F74
A49: Expenses by function equal total operating expenses | B49: Revenue_Hist | C49: =MAX(MAX(Revenue_Hist!B75:F75),-MIN(Revenue_Hist!B75:F75)) -> 0 | D49: B75:F75
A50: Adjusted operating income recomputed | B50: Revenue_Hist | C50: =MAX(MAX(Revenue_Hist!B76:F76),-MIN(Revenue_Hist!B76:F76)) -> 0 | D50: B76:F76
A51: Operating loss equals the statement | B51: Revenue_Hist | C51: =MAX(MAX(Revenue_Hist!B77:F77),-MIN(Revenue_Hist!B77:F77)) -> 0 | D51: B77:F77
A52: Preferred as converted equals the anti-dilutive table (8,558,869) | B52: Cap_Table | C52: =MAX(MAX(Cap_Table!B89:B89),-MIN(Cap_Table!B89:B89)) -> 0 | D52: B89:B89
A53: Class A and N shares equal the equity statement | B53: Cap_Table | C53: =MAX(MAX(Cap_Table!B90:B90),-MIN(Cap_Table!B90:B90)) -> 0 | D53: B90:B90
A54: Balance sheet balances | B54: Interim_Bridge | C54: =MAX(MAX(Interim_Bridge!B60:D60),-MIN(Interim_Bridge!B60:D60)) -> 0 | D54: B60:D60
A55: 46203 | B55: Interim_Bridge | C55: =MAX(MAX(Interim_Bridge!B61:B61),-MIN(Interim_Bridge!B61:B61)) -> 0 | D55: B61:B61
A56: 6M 2026 operating cash flow equals the S-1 | B56: Interim_Bridge | C56: =MAX(MAX(Interim_Bridge!B62:B62),-MIN(Interim_Bridge!B62:B62)) -> 0 | D56: B62:B62
A57: 6M 2026 net loss equals the S-1 | B57: Interim_Bridge | C57: =MAX(MAX(Interim_Bridge!B63:B63),-MIN(Interim_Bridge!B63:B63)) -> 0 | D57: B63:B63
A58: 6M 2025 net loss equals the S-1 | B58: Interim_Bridge | C58: =MAX(MAX(Interim_Bridge!E64:G64),-MIN(Interim_Bridge!E64:G64)) -> 0 | D58: E64:G64
A59: Taxes equal the income statement (2027E onward) | B59: Schedules | C59: =MAX(MAX(Schedules!D38:L38),-MIN(Schedules!D38:L38)) -> 0 | D59: D38:L38
A60: Change in working capital equals the cash flow statement | B60: Schedules | C60: =MAX(MAX(Schedules!D39:L39),-MIN(Schedules!D39:L39)) -> 0 | D60: D39:L39
A61: Balance sheet balances | B61: Forecast_3Stmt | C61: =MAX(MAX(Forecast_3Stmt!B64:L64),-MIN(Forecast_3Stmt!B64:L64)) -> 0 | D61: B64:L64
A62: Cash roll-forward | B62: Forecast_3Stmt | C62: =MAX(MAX(Forecast_3Stmt!C65:L65),-MIN(Forecast_3Stmt!C65:L65)) -> 0 | D62: C65:L65
A63: 2025A net income equals the S-1 | B63: Forecast_3Stmt | C63: =MAX(MAX(Forecast_3Stmt!B66:B66),-MIN(Forecast_3Stmt!B66:B66)) -> 0 | D63: B66:B66
A64: 2025A operating cash flow equals the S-1 | B64: Forecast_3Stmt | C64: =MAX(MAX(Forecast_3Stmt!B67:B67),-MIN(Forecast_3Stmt!B67:B67)) -> 0 | D64: B67:B67
A65: Commitments add to the S-1 total (54,559) | B65: Debt_Credit | C65: =MAX(MAX(Debt_Credit!B30:B30),-MIN(Debt_Credit!B30:B30)) -> 0 | D65: B30:B30
A66: Weights add to 100% | B66: Valuation | C66: =MAX(MAX(Valuation!C54:C54),-MIN(Valuation!C54:C54)) -> 0 | D66: C54:C54
A67: Centre cell equals the DCF value per share | B67: Sensitivity | C67: =MAX(MAX(Sensitivity!D11:D11),-MIN(Sensitivity!D11:D11)) -> 0 | D67: D11:D11
A68: Table 2 centre equals the Base DCF value (captured) | B68: Sensitivity | C68: =MAX(MAX(Sensitivity!D21:D21),-MIN(Sensitivity!D21:D21)) -> 0 | D68: D21:D21
A69: With the switch on Base, live equals the captured Base | B69: Scenario_Summary | C69: =MAX(MAX(Scenario_Summary!C25:C25),-MIN(Scenario_Summary!C25:C25)) -> 0 | D69: C25:C25

Sheet FormatRules
A1: Anthropic, PBC | Format rules (OpenFinmods palette)
A2: Colours from the OpenFinmods public palette, as in meta.xlsx. The number colour code does not change: blue typed, black formula, green link to another sheet.
A4: Role | B4: Applies to | C4: Hex | D4: Pigment | E4: Note | F4: Swatch
A5: Sheet title | B5: Row 1 title of every sheet (Arial 10 bold) | C5: #5A2331 | D5: Borgona | E5: Text colour only.
A6: Year band, label and actual years | B6: Header row over the label column and the actual years | C6: #F6F3EC | D6: Crema
A7: Year band, forecast years | B7: Header row over the forecast years | C7: #EAE2DD | D7: Borgona 8% on crema
A8: Notes columns header | B8: Header of column M (Comentarios FG) and the source columns | C8: #D3D2CF | D8: Navy 15% on crema
A9: Input and scenario rows | B9: Fill of input cells (Assumptions, switches, weights) | C9: #EBDDC8 | D9: Ocre 20% on crema | E9: Blue on it: 5.41:1.
A10: Detail rows fill | B10: Breakdown rows (none in this workbook) | C10: #EDEAE4 | D10: Navy 4% on crema
A11: Detail rows font | B11: Breakdown rows (none in this workbook) | C11: #6A7689 | D11: Gris
A12: Tab, cover and checks | B12: 00_Cover, Checks, FormatRules | C12: #0E1A2B | D12: Navy
A13: Tab, source sheets | B13: S-1 statements and notes, Cap_Table, Limitations | C13: #6A7689 | D13: Gris
A14: Tab, model sheets | B14: Assumptions to Debt_Credit | C14: #5A2331 | D14: Borgona
A15: Tab, output sheets | B15: Market_Package, DCF, Valuation, Sensitivity, Scenario_Summary | C15: #C0873A | D15: Ocre
A16: Typed number (code, unchanged) | B16: Hard-coded inputs and filed numbers | C16: #0432FF | D16: Standard financial-model number colours | E16: Blue = typed.
A17: Formula and text (code, unchanged) | B17: Formulas and labels | C17: #000000 | D17: Standard financial-model number colours | E17: Black = formula.
A18: Link to another sheet (code, unchanged) | B18: References to other sheets | C18: #00703C | D18: Standard financial-model number colours | E18: Green = link.
A19: Link to another workbook (code, unchanged) | B19: External links (none) | C19: #7030A0 | D19: Standard financial-model number colours | E19: Purple.
A20: Check (code, unchanged) | B20: Check rows, through the number format [Red] | C20: #FF0000 | D20: Standard financial-model number colours

Sheet Claude Code Log
A1: Turn # | B1: Date | C1: User Request | D1: Action Taken | E1: Details | F1: Outcome
A2: 1 | B2: 46324.359 | C2: Prepare a public model copy | D2: Remove local paths and private build references; preserve financial formulas and inputs | E2: Agent run with MOG as the tool, checked by guard v1. The guard measured every sheet before and after the run. Changed: 00_Cover: 1 cell written, at B50; Market_Package: 1 cell written, at D24; FormatRules: 7 cells written, at A1, A2, D16, D17, D18, D19, D20. Other actions: clear x1. Agent: OpenFinmods export | F2: Compare against source and review public copy
