Workbook

Sheet EEFF
A1: Group Energy Gas Panamá, S. de R.L. and Subsidiary
A2: Consolidated Audited Financial Statements — December 31, 2025, 2024 and 2023 (issuer = Generadora de Gatún, S.A.)
A3: (All amounts in US$ unless otherwise stated)
A5: Años | B5: FY21A | C5: FY22A | D5: FY23A | E5: FY24A | F5: FY25A | G5: FY26E | H5: FY27E | I5: FY28E | J5: FY29E | K5: FY30E
A6: Consolidated Statement of Comprehensive Income (Loss)
A7: Electricity sales | D7: 0 | E7: 71148608 | F7: 321681090
A8: Operating costs and expenses
A9: Electricity purchases | D9: 0 | E9: -23505670 | F9: -45494652
A10: Fuel costs | D10: 0 | E10: -27262804 | F10: -151394592
A11: Depreciation and amortization | D11: 0 | E11: -9073154 | F11: -41820657
A12: Operating, maintenance, and transmission costs | D12: 0 | E12: -1007849 | F12: -16140520
A13: General and administrative expenses | D13: -212127 | E13: -1553970 | F13: -9882798
A14: Total operating costs and expenses | D14: -212127 | E14: -62403447 | F14: -264733219
A15: Operating income (loss) | D15: -212127 | E15: 8745161 | F15: 56947871
A16: Other (expenses) income
A17: Finance cost, net | D17: -6942984 | E17: -14420444 | F17: -69197853
A18: Other income, net | D18: 0 | E18: 723940 | F18: 9178382
A19: Total other expenses, net | D19: -6942984 | E19: -13696504 | F19: -60019471
A20: Net loss before tax | D20: -7155111 | E20: -4951343 | F20: -3071600
A21: Income tax | D21: 0 | E21: -1440939 | F21: -5576826
A22: Net loss | D22: -7155111 | E22: -6392282 | F22: -8648426
A23: Other comprehensive income (loss)
A24: Items that may be reclassified to profit or loss
A25: Cash flow hedge reserve | D25: -7412348 | E25: 16195629 | F25: -14972862
A26: Total other comprehensive (loss) income | D26: -14567459 | E26: 9803347 | F26: -23621288
A28: Años | B28: FY21A | C28: FY22A | D28: FY23A | E28: FY24A | F28: FY25A | G28: FY26E | H28: FY27E | I28: FY28E | J28: FY29E | K28: FY30E
A29: Consolidated Balance Sheet
A30: Assets
A31: Current assets
A32: Cash | D32: 730289 | E32: 35690715 | F32: 34127110
A33: Restricted cash | D33: 9484768 | E33: 71344482 | F33: 25061346
A34: Accounts receivable | D34: 0 | E34: 47076358 | F34: 52989225
A35: Accounts receivable related parties | D35: 0 | E35: 216976 | F35: 1565841
A36: Inventories | D36: 0 | E36: 12567893 | F36: 12635537
A37: Prepaid expenses and other assets | D37: 0 | E37: 18443 | F37: 8044029
A38: Total current assets | D38: 10215057 | E38: 166914867 | F38: 134423088
A39: Non-current assets
A40: Property, plant and equipment | D40: 4405052 | E40: 573263125 | F40: 760443619
A41: Construction in progress | D41: 568305169 | E41: 170183780 | F41: 0
A42: Intangible asset | D42: 232073438 | E42: 229172520 | F42: 217568848
A43: Right-of-use assets | D43: 9194053 | E43: 6262558 | F43: 5921376
A44: Guarantee deposit | D44: 71922 | E44: 31038 | F44: 32028
A45: Derivative financial instruments | D45: 89302665 | E45: 104809005 | F45: 89498950
A46: Severance fund | D46: 0 | E46: 57766 | F46: 115685
A47: Deferred tax asset | D47: 0 | E47: 0 | F47: 421174
A48: Total non-current assets | D48: 903352299 | E48: 1083779792 | F48: 1074001680
A49: Total assets | D49: 913567356 | E49: 1250694659 | F49: 1208424768
A50: Liabilities
A51: Current liabilities
A52: Accounts payable | D52: 812820 | E52: 39939411 | F52: 9326557
A53: Loans payable, short term | D53: 0 | E53: 20477182 | F53: 6387577
A54: Accounts payable sellers | D54: 19423030 | E54: 19626508 | F54: 46374534
A55: Accounts payable related parties | D55: 0 | E55: 8894863 | F55: 2705118
A56: Lease liabilities, short-term | D56: 72912 | E56: 240776 | F56: 299722
A57: Income tax payable | D57: 0 | E57: 1440939 | F57: 4557061
A58: Accrued expenses and other liabilities | D58: 137467 | E58: 270020 | F58: 366843
A59: Total current liabilities | D59: 20446229 | E59: 90889699 | F59: 70017412
A60: Non-current liabilities
A61: Account payable sellers | D61: 84309211 | E61: 85192442 | F61: 43657337
A62: Loans payable, long term | D62: 575680720 | E62: 704207379 | F62: 841707434
A63: Lease liabilities, long-term | D63: 10421780 | E63: 7561463 | F63: 7306348
A64: Seniority premium | D64: 0 | E64: 65223 | F64: 124106
A65: Total non-current liabilities | D65: 670411711 | E65: 797026507 | F65: 892795225
A66: Total liabilities | D66: 690857940 | E66: 887916206 | F66: 962812637
A67: Equity
A68: Quotes of participation | D68: 158568190 | E68: 288833880 | F68: 195288846
A69: Accumulated deficit | D69: -23111594 | E69: -29503876 | F69: -38152302
A70: Cash flow hedge reserve | D70: 87252820 | E70: 103448449 | F70: 88475587
A71: Total equity | D71: 222709416 | E71: 362778453 | F71: 245612131
A72: Total liabilities and equity | D72: 913567356 | E72: 1250694659 | F72: 1208424768
A74: Años | B74: FY21A | C74: FY22A | D74: FY23A | E74: FY24A | F74: FY25A | G74: FY26E | H74: FY27E | I74: FY28E | J74: FY29E | K74: FY30E
A75: Consolidated Statement of Cash Flows
A76: Cash flows from operating activities
A77: Net loss before tax | D77: -7155111 | E77: -4951343 | F77: -3071600
A78: Adjustments to reconcile net loss before tax to net cash provided by operating activities:
A79: Depreciation of property, plant and equipment | D79: 0 | E79: 6060088 | F79: 29746572
A80: Amortization of intangible assets | D80: 0 | E80: 2900918 | F80: 11603672
A81: Amortization of right of use asset | D81: 0 | E81: 112148 | F81: 470414
A82: Interest on accounts payable sellers | D82: 6982133 | E82: 1086710 | F82: 5232921
A83: Finance cost | D83: 0 | E83: 14055900 | F83: 63186268
A84: Finance income | D84: 0 | E84: -3377644 | F84: -13262202
A85: Other expenses | D85: 0 | E85: 0 | F85: -71280
A86: Amortization of deferred financing costs | D86: 0 | E86: 1466734 | F86: 10712475
A87: Cash flows before working capital movements | D87: -172978 | E87: 17353511 | F87: 104547240
A88: Net changes in assets and liabilities:
A89: Accounts receivable | D89: 0 | E89: -47076360 | F89: -5912867
A90: Accounts receivable related parties | D90: 0 | E90: 3911236 | F90: -1348865
A91: Inventories | D91: 0 | E91: -12567893 | F91: -67644
A92: Prepaid expenses and other assets | D92: 0 | E92: -18435 | F92: -8025588
A93: Severance fund | D93: 0 | E93: -57766 | F93: -57919
A94: Guarantee deposit | D94: -40684 | E94: 40884 | F94: -990
A95: Account payable | D95: -2378846 | E95: 37941625 | F95: -4371652
A96: Account payable to related party | D96: -46661 | E96: 4766651 | F96: -6189745
A97: Accrued expenses and other liabilities | D97: 76131 | E97: 132552 | F97: 96823
A98: Seniority premium | D98: 0 | E98: 65223 | F98: 58883
A99: Income tax paid | D99: 0 | E99: 0 | F99: -2881878
A100: Net cash provided by (used in) operating activities | D100: -2563038 | E100: 4491228 | F100: 75845798
A101: Cash flows from investing activities
A102: Construction in progress | D102: -256069301 | E102: -105937007 | F102: -47361449
A103: Property, plant and equipment | D103: 0 | E103: -8223531 | F103: -4768660
...

Sheet Notas_EEFF
A1: Group Energy Gas Panamá, S. de R.L. and Subsidiary
A2: Notas a los Estados Financieros
A3: Fuente: informes auditados vía OCR Mistral (verbatim).
A5: Año | B5: Documento fuente | C5: Página OCR | D5: Tabla OCR / sección | E5: Nota # | F5: Título original de la nota | G5: Categoría modelable | H5: Line item EEFF | I5: Sub-line item / detalle | J5: Texto original / disclosure | K5: Monto reportado | L5: Moneda | M5: Unidad / escala | N5: Fecha / venc. / tasa / plazo | O5: Contraparte / contrato / instrumento | P5: Impacto en Supuestos | Q5: Impacto en ModeloFinanciero | R5: Link a celda EEFF | S5: Comentario de extracción | T5: Status
B6: NOT_DISCLOSED | E6: N/A | F6: Notas a los EEFF — OCR no localizó la sección de notas | G6: Otros | J6: NOT_DISCLOSED: revisión OCR manual requerida. | S6: roots=0 docs=0 | T6: NOT_DISCLOSED

Sheet Supuestos
A1: Group Energy Gas Panamá, S. de R.L. and Subsidiary
A3: COLOR KEY: Input (azul) · Fórmula (negro) · Link inter-hoja (verde)
A4: Escenario (1=Base, 2=Bull, 3=Bear)
A5: Selector escenario | C5: 1 | M5: caso | N5: NOT_DISCLOSED | Q5: Derivación mecánica declarada por el plan.
A6: Escenario activo | C6: =CHOOSE($C$5,"Base","Bull","Bear") -> Base | M6: moneda del modelo | N6: NOT_DISCLOSED | Q6: Selector de caso activo C5: Base/Bull/Bear.
A8: Años | B8: FY21A | C8: FY22A | D8: FY23A | E8: FY24A | F8: FY25A | G8: FY26E | H8: FY27E | I8: FY28E | J8: FY29E | K8: FY30E | M8: Unidad | N8: Fuente / nota | Q8: Rationale
A10: A. ELECTRICITY SALES — PxQ (MWh × $/MWh)
A11: Net contracted energy sold (MWh) | D11: 0 | E11: 119181 | F11: 2178568 | G11: 2226250 | H11: 2226250 | I11: 2226250 | J11: 3146630 | K11: 3146630 | M11: MWh | N11: NOT_DISCLOSED | Q11: Derivación mecánica declarada por el plan.
A12: Realized contracted electricity price ($/MWh) | E12: =E13/E11 -> 596.97945 | F12: =F13/F11 -> 147.65713 | G12: =((400*1000*18.89*12)+(G11*89))/G11 -> 129.72858 | H12: =((400*1000*18.89*12)+(H11*89))/H11 -> 129.72858 | I12: =((400*1000*18.89*12)+(I11*89))/I11 -> 129.72858 | J12: =((550*1000*18.89*12)+(J11*89))/J11 -> 128.62144 | K12: =((550*1000*18.89*12)+(K11*89))/K11 -> 128.62144 | M12: MWh | N12: NOT_DISCLOSED | Q12: Derivación mecánica por fórmula viva.
A13: Electricity sales | D13: =D14 -> 0 | E13: =E14 -> 71148608 | F13: =F14 -> 321681090 | G13: =G11*G12 -> 288808250 | H13: =H11*H12 -> 288808250 | I13: =I11*I12 -> 288808250 | J13: =J11*J12 -> 404724070 | K13: =K11*K12 -> 404724070 | M13: moneda del modelo | N13: NOT_DISCLOSED | Q13: Derivación mecánica por fórmula viva.
A14: Electricity sales (hist, ref EEFF) | D14: =EEFF!D7 -> 0 | E14: =EEFF!E7 -> 71148608 | F14: =EEFF!F7 -> 321681090 | M14: moneda del modelo | N14: EEFF (citado por fórmula viva) | Q14: Mirror histórico desde fuente citada.
A17: B. COSTO DE VENTAS (% de ingresos)
A18: Fuel costs — driver activo | G18: =CHOOSE($C$5,G20,G21,G19) -> -0.471 | H18: =CHOOSE($C$5,H20,H21,H19) -> -0.471 | I18: =CHOOSE($C$5,I20,I21,I19) -> -0.471 | J18: =CHOOSE($C$5,J20,J21,J19) -> -0.471 | K18: =CHOOSE($C$5,K20,K21,K19) -> -0.471 | M18: moneda del modelo | N18: NOT_DISCLOSED | Q18: Selector de caso activo C5: Base/Bull/Bear.
A19: Bear | G19: -0.491 | H19: -0.491 | I19: -0.491 | J19: -0.491 | K19: -0.491 | M19: moneda del modelo | N19: NOT_DISCLOSED | Q19: Escenario driver citado; NOT_DISCLOSED si no hay fuente explícita.
A20: Base | G20: -0.471 | H20: -0.471 | I20: -0.471 | J20: -0.471 | K20: -0.471 | M20: moneda del modelo | N20: NOT_DISCLOSED | Q20: Escenario driver citado; NOT_DISCLOSED si no hay fuente explícita.
A21: Bull | G21: -0.451 | H21: -0.451 | I21: -0.451 | J21: -0.451 | K21: -0.451 | M21: moneda del modelo | N21: NOT_DISCLOSED | Q21: Escenario driver citado; NOT_DISCLOSED si no hay fuente explícita.
A22: Fuel costs ÷ ingresos (hist, ref EEFF) | D22: =IF(EEFF!D7=0,"",EEFF!D10/EEFF!D7) | E22: =IF(EEFF!E7=0,"",EEFF!E10/EEFF!E7) -> -0.38318113 | F22: =IF(EEFF!F7=0,"",EEFF!F10/EEFF!F7) -> -0.47063566 | M22: % | N22: EEFF (citado por fórmula viva) | Q22: Mirror histórico desde fuente citada.
A24: C. GASTOS OPERATIVOS (% de ingresos)
A25: General and administrative expenses — driver activo | G25: =CHOOSE($C$5,G27,G28,G26) -> -0.031 | H25: =CHOOSE($C$5,H27,H28,H26) -> -0.031 | I25: =CHOOSE($C$5,I27,I28,I26) -> -0.031 | J25: =CHOOSE($C$5,J27,J28,J26) -> -0.031 | K25: =CHOOSE($C$5,K27,K28,K26) -> -0.031 | M25: moneda del modelo | N25: NOT_DISCLOSED | Q25: Selector de caso activo C5: Base/Bull/Bear.
A26: Bear | G26: -0.051 | H26: -0.051 | I26: -0.051 | J26: -0.051 | K26: -0.051 | M26: moneda del modelo | N26: NOT_DISCLOSED | Q26: Escenario driver citado; NOT_DISCLOSED si no hay fuente explícita.
A27: Base | G27: -0.031 | H27: -0.031 | I27: -0.031 | J27: -0.031 | K27: -0.031 | M27: moneda del modelo | N27: NOT_DISCLOSED | Q27: Escenario driver citado; NOT_DISCLOSED si no hay fuente explícita.
A28: Bull | G28: -0.011 | H28: -0.011 | I28: -0.011 | J28: -0.011 | K28: -0.011 | M28: moneda del modelo | N28: NOT_DISCLOSED | Q28: Escenario driver citado; NOT_DISCLOSED si no hay fuente explícita.
A29: General and administrative expenses ÷ ingresos (hist, ref EEFF) | D29: =IF(EEFF!D7=0,"",EEFF!D13/EEFF!D7) | E29: =IF(EEFF!E7=0,"",EEFF!E13/EEFF!E7) -> -0.021841186 | F29: =IF(EEFF!F7=0,"",EEFF!F13/EEFF!F7) -> -0.030722347 | M29: % | N29: EEFF (citado por fórmula viva) | Q29: Mirror histórico desde fuente citada.

Sheet ModeloFinanciero
A1: Group Energy Gas Panamá, S. de R.L. and Subsidiary
A2: Consolidated Audited Financial Statements — December 31, 2025, 2024 and 2023 (issuer = Generadora de Gatún, S.A.)
A3: (All amounts in US$ unless otherwise stated)
A5: Años | B5: FY21A | C5: FY22A | D5: FY23A | E5: FY24A | F5: FY25A | G5: FY26E | H5: FY27E | I5: FY28E | J5: FY29E | K5: FY30E
A6: Consolidated Statement of Comprehensive Income (Loss)
A7: Electricity sales | D7: =EEFF!D7 -> 0 | E7: =EEFF!E7 -> 71148608 | F7: =EEFF!F7 -> 321681090 | G7: =Supuestos!G13 -> 288808250 | H7: =Supuestos!H13 -> 288808250 | I7: =Supuestos!I13 -> 288808250 | J7: =Supuestos!J13 -> 404724070 | K7: =Supuestos!K13 -> 404724070
A9: Operating costs and expenses
A10: Electricity purchases | D10: =EEFF!D9 -> 0 | E10: =EEFF!E9 -> -23505670 | F10: =EEFF!F9 -> -45494652 | G10: =F10 -> -45494652 | H10: =G10 -> -45494652 | I10: =H10 -> -45494652 | J10: =I10 -> -45494652 | K10: =J10 -> -45494652
A11: Fuel costs | D11: =EEFF!D10 -> 0 | E11: =EEFF!E10 -> -27262804 | F11: =EEFF!F10 -> -151394592 | G11: =G7*Supuestos!G18 -> -1.3602869e+08 | H11: =H7*Supuestos!H18 -> -1.3602869e+08 | I11: =I7*Supuestos!I18 -> -1.3602869e+08 | J11: =J7*Supuestos!J18 -> -1.9062504e+08 | K11: =K7*Supuestos!K18 -> -1.9062504e+08
A12: Depreciation and amortization | D12: =EEFF!D11 -> 0 | E12: =EEFF!E11 -> -9073154 | F12: =EEFF!F11 -> -41820657 | G12: =F12 -> -41820657 | H12: =G12 -> -41820657 | I12: =H12 -> -41820657 | J12: =I12 -> -41820657 | K12: =J12 -> -41820657
A13: Operating, maintenance, and transmission costs | D13: =EEFF!D12 -> 0 | E13: =EEFF!E12 -> -1007849 | F13: =EEFF!F12 -> -16140520 | G13: =F13 -> -16140520 | H13: =G13 -> -16140520 | I13: =H13 -> -16140520 | J13: =I13 -> -16140520 | K13: =J13 -> -16140520
A14: General and administrative expenses | D14: =EEFF!D13 -> -212127 | E14: =EEFF!E13 -> -1553970 | F14: =EEFF!F13 -> -9882798 | G14: =G7*Supuestos!G25 -> -8953055.8 | H14: =H7*Supuestos!H25 -> -8953055.8 | I14: =I7*Supuestos!I25 -> -8953055.8 | J14: =J7*Supuestos!J25 -> -12546446 | K14: =K7*Supuestos!K25 -> -12546446
A15: Total operating costs and expenses | D15: =EEFF!D14 -> -212127 | E15: =EEFF!E14 -> -62403447 | F15: =EEFF!F14 -> -264733219 | G15: =G10+G11+G12+G13+G14 -> -2.4843757e+08 | H15: =H10+H11+H12+H13+H14 -> -2.4843757e+08 | I15: =I10+I11+I12+I13+I14 -> -2.4843757e+08 | J15: =J10+J11+J12+J13+J14 -> -3.0662731e+08 | K15: =K10+K11+K12+K13+K14 -> -3.0662731e+08
A16: Operating income (loss) | D16: =EEFF!D15 -> -212127 | E16: =EEFF!E15 -> 8745161 | F16: =EEFF!F15 -> 56947871 | G16: =G7+G15 -> 40370680 | H16: =H7+H15 -> 40370680 | I16: =I7+I15 -> 40370680 | J16: =J7+J15 -> 98096758 | K16: =K7+K15 -> 98096758
A18: Other (expenses) income
A19: Finance cost, net | D19: =EEFF!D17 -> -6942984 | E19: =EEFF!E17 -> -14420444 | F19: =EEFF!F17 -> -69197853 | G19: =F19 -> -69197853 | H19: =G19 -> -69197853 | I19: =H19 -> -69197853 | J19: =I19 -> -69197853 | K19: =J19 -> -69197853
A20: Other income, net | D20: =EEFF!D18 -> 0 | E20: =EEFF!E18 -> 723940 | F20: =EEFF!F18 -> 9178382 | G20: =F20 -> 9178382 | H20: =G20 -> 9178382 | I20: =H20 -> 9178382 | J20: =I20 -> 9178382 | K20: =J20 -> 9178382
A21: Total other expenses, net | D21: =EEFF!D19 -> -6942984 | E21: =EEFF!E19 -> -13696504 | F21: =EEFF!F19 -> -60019471 | G21: =G19+G20 -> -60019471 | H21: =H19+H20 -> -60019471 | I21: =I19+I20 -> -60019471 | J21: =J19+J20 -> -60019471 | K21: =K19+K20 -> -60019471
A22: Net loss before tax | D22: =EEFF!D20 -> -7155111 | E22: =EEFF!E20 -> -4951343 | F22: =EEFF!F20 -> -3071600 | G22: =G16+G21 -> -19648792 | H22: =H16+H21 -> -19648792 | I22: =I16+I21 -> -19648792 | J22: =J16+J21 -> 38077287 | K22: =K16+K21 -> 38077287
A23: Income tax | D23: =EEFF!D21 -> 0 | E23: =EEFF!E21 -> -1440939 | F23: =EEFF!F21 -> -5576826 | G23: =F23 -> -5576826 | H23: =G23 -> -5576826 | I23: =H23 -> -5576826 | J23: =I23 -> -5576826 | K23: =J23 -> -5576826
A24: Net loss | D24: =EEFF!D22 -> -7155111 | E24: =EEFF!E22 -> -6392282 | F24: =EEFF!F22 -> -8648426 | G24: =G22+G23 -> -25225618 | H24: =H22+H23 -> -25225618 | I24: =I22+I23 -> -25225618 | J24: =J22+J23 -> 32500461 | K24: =K22+K23 -> 32500461
A26: Other comprehensive income (loss)
A27: Items that may be reclassified to profit or loss
A28: Cash flow hedge reserve | D28: =EEFF!D25 -> -7412348 | E28: =EEFF!E25 -> 16195629 | F28: =EEFF!F25 -> -14972862 | G28: =F28 -> -14972862 | H28: =G28 -> -14972862 | I28: =H28 -> -14972862 | J28: =I28 -> -14972862 | K28: =J28 -> -14972862
A29: Total other comprehensive (loss) income | D29: =EEFF!D26 -> -14567459 | E29: =EEFF!E26 -> 9803347 | F29: =EEFF!F26 -> -23621288 | G29: =G24+G28 -> -40198480 | H29: =H24+H28 -> -40198480 | I29: =I24+I28 -> -40198480 | J29: =J24+J28 -> 17527599 | K29: =K24+K28 -> 17527599
A31: Años | B31: FY21A | C31: FY22A | D31: FY23A | E31: FY24A | F31: FY25A | G31: FY26E | H31: FY27E | I31: FY28E | J31: FY29E | K31: FY30E
A32: Consolidated Balance Sheet
A33: Assets
A34: Current assets
A35: Cash | D35: =EEFF!D32 -> 730289 | E35: =EEFF!E32 -> 35690715 | F35: =EEFF!F32 -> 34127110 | G35: =F35 -> 34127110 | H35: =G35 -> 34127110 | I35: =H35 -> 34127110 | J35: =I35 -> 34127110 | K35: =J35 -> 34127110
A36: Restricted cash | D36: =EEFF!D33 -> 9484768 | E36: =EEFF!E33 -> 71344482 | F36: =EEFF!F33 -> 25061346 | G36: =F36 -> 25061346 | H36: =G36 -> 25061346 | I36: =H36 -> 25061346 | J36: =I36 -> 25061346 | K36: =J36 -> 25061346
A37: Accounts receivable | D37: =EEFF!D34 -> 0 | E37: =EEFF!E34 -> 47076358 | F37: =EEFF!F34 -> 52989225 | G37: =F37 -> 52989225 | H37: =G37 -> 52989225 | I37: =H37 -> 52989225 | J37: =I37 -> 52989225 | K37: =J37 -> 52989225
A38: Accounts receivable related parties | D38: =EEFF!D35 -> 0 | E38: =EEFF!E35 -> 216976 | F38: =EEFF!F35 -> 1565841 | G38: =F38 -> 1565841 | H38: =G38 -> 1565841 | I38: =H38 -> 1565841 | J38: =I38 -> 1565841 | K38: =J38 -> 1565841
A39: Inventories | D39: =EEFF!D36 -> 0 | E39: =EEFF!E36 -> 12567893 | F39: =EEFF!F36 -> 12635537 | G39: =F39 -> 12635537 | H39: =G39 -> 12635537 | I39: =H39 -> 12635537 | J39: =I39 -> 12635537 | K39: =J39 -> 12635537
A40: Prepaid expenses and other assets | D40: =EEFF!D37 -> 0 | E40: =EEFF!E37 -> 18443 | F40: =EEFF!F37 -> 8044029 | G40: =F40 -> 8044029 | H40: =G40 -> 8044029 | I40: =H40 -> 8044029 | J40: =I40 -> 8044029 | K40: =J40 -> 8044029
A41: Total current assets | D41: =EEFF!D38 -> 10215057 | E41: =EEFF!E38 -> 166914867 | F41: =EEFF!F38 -> 134423088 | G41: =F41 -> 134423088 | H41: =G41 -> 134423088 | I41: =H41 -> 134423088 | J41: =I41 -> 134423088 | K41: =J41 -> 134423088
A43: Non-current assets
A44: Property, plant and equipment | D44: =EEFF!D40 -> 4405052 | E44: =EEFF!E40 -> 573263125 | F44: =EEFF!F40 -> 760443619 | G44: =F44 -> 760443619 | H44: =G44 -> 760443619 | I44: =H44 -> 760443619 | J44: =I44 -> 760443619 | K44: =J44 -> 760443619
A45: Construction in progress | D45: =EEFF!D41 -> 568305169 | E45: =EEFF!E41 -> 170183780 | F45: =EEFF!F41 -> 0 | G45: =F45 -> 0 | H45: =G45 -> 0 | I45: =H45 -> 0 | J45: =I45 -> 0 | K45: =J45 -> 0
A46: Intangible asset | D46: =EEFF!D42 -> 232073438 | E46: =EEFF!E42 -> 229172520 | F46: =EEFF!F42 -> 217568848 | G46: =F46 -> 217568848 | H46: =G46 -> 217568848 | I46: =H46 -> 217568848 | J46: =I46 -> 217568848 | K46: =J46 -> 217568848
A47: Right-of-use assets | D47: =EEFF!D43 -> 9194053 | E47: =EEFF!E43 -> 6262558 | F47: =EEFF!F43 -> 5921376 | G47: =F47 -> 5921376 | H47: =G47 -> 5921376 | I47: =H47 -> 5921376 | J47: =I47 -> 5921376 | K47: =J47 -> 5921376
A48: Guarantee deposit | D48: =EEFF!D44 -> 71922 | E48: =EEFF!E44 -> 31038 | F48: =EEFF!F44 -> 32028 | G48: =F48 -> 32028 | H48: =G48 -> 32028 | I48: =H48 -> 32028 | J48: =I48 -> 32028 | K48: =J48 -> 32028
A49: Derivative financial instruments | D49: =EEFF!D45 -> 89302665 | E49: =EEFF!E45 -> 104809005 | F49: =EEFF!F45 -> 89498950 | G49: =F49 -> 89498950 | H49: =G49 -> 89498950 | I49: =H49 -> 89498950 | J49: =I49 -> 89498950 | K49: =J49 -> 89498950
A50: Severance fund | D50: =EEFF!D46 -> 0 | E50: =EEFF!E46 -> 57766 | F50: =EEFF!F46 -> 115685 | G50: =F50 -> 115685 | H50: =G50 -> 115685 | I50: =H50 -> 115685 | J50: =I50 -> 115685 | K50: =J50 -> 115685
A51: Deferred tax asset | D51: =EEFF!D47 -> 0 | E51: =EEFF!E47 -> 0 | F51: =EEFF!F47 -> 421174 | G51: =F51 -> 421174 | H51: =G51 -> 421174 | I51: =H51 -> 421174 | J51: =I51 -> 421174 | K51: =J51 -> 421174
A52: Total non-current assets | D52: =EEFF!D48 -> 903352299 | E52: =EEFF!E48 -> 1083779792 | F52: =EEFF!F48 -> 1074001680 | G52: =F52 -> 1074001680 | H52: =G52 -> 1074001680 | I52: =H52 -> 1074001680 | J52: =I52 -> 1074001680 | K52: =J52 -> 1074001680
A53: Total assets | D53: =EEFF!D49 -> 913567356 | E53: =EEFF!E49 -> 1250694659 | F53: =EEFF!F49 -> 1208424768 | G53: =F53 -> 1208424768 | H53: =G53 -> 1208424768 | I53: =H53 -> 1208424768 | J53: =I53 -> 1208424768 | K53: =J53 -> 1208424768
A55: Liabilities
A56: Current liabilities
A57: Accounts payable | D57: =EEFF!D52 -> 812820 | E57: =EEFF!E52 -> 39939411 | F57: =EEFF!F52 -> 9326557 | G57: =F57 -> 9326557 | H57: =G57 -> 9326557 | I57: =H57 -> 9326557 | J57: =I57 -> 9326557 | K57: =J57 -> 9326557
A58: Loans payable, short term | D58: =EEFF!D53 -> 0 | E58: =EEFF!E53 -> 20477182 | F58: =EEFF!F53 -> 6387577 | G58: =F58 -> 6387577 | H58: =G58 -> 6387577 | I58: =H58 -> 6387577 | J58: =I58 -> 6387577 | K58: =J58 -> 6387577
A59: Accounts payable sellers | D59: =EEFF!D54 -> 19423030 | E59: =EEFF!E54 -> 19626508 | F59: =EEFF!F54 -> 46374534 | G59: =F59 -> 46374534 | H59: =G59 -> 46374534 | I59: =H59 -> 46374534 | J59: =I59 -> 46374534 | K59: =J59 -> 46374534
A60: Accounts payable related parties | D60: =EEFF!D55 -> 0 | E60: =EEFF!E55 -> 8894863 | F60: =EEFF!F55 -> 2705118 | G60: =F60 -> 2705118 | H60: =G60 -> 2705118 | I60: =H60 -> 2705118 | J60: =I60 -> 2705118 | K60: =J60 -> 2705118
A61: Lease liabilities, short-term | D61: =EEFF!D56 -> 72912 | E61: =EEFF!E56 -> 240776 | F61: =EEFF!F56 -> 299722 | G61: =F61 -> 299722 | H61: =G61 -> 299722 | I61: =H61 -> 299722 | J61: =I61 -> 299722 | K61: =J61 -> 299722
A62: Income tax payable | D62: =EEFF!D57 -> 0 | E62: =EEFF!E57 -> 1440939 | F62: =EEFF!F57 -> 4557061 | G62: =F62 -> 4557061 | H62: =G62 -> 4557061 | I62: =H62 -> 4557061 | J62: =I62 -> 4557061 | K62: =J62 -> 4557061
A63: Accrued expenses and other liabilities | D63: =EEFF!D58 -> 137467 | E63: =EEFF!E58 -> 270020 | F63: =EEFF!F58 -> 366843 | G63: =F63 -> 366843 | H63: =G63 -> 366843 | I63: =H63 -> 366843 | J63: =I63 -> 366843 | K63: =J63 -> 366843
A64: Total current liabilities | D64: =EEFF!D59 -> 20446229 | E64: =EEFF!E59 -> 90889699 | F64: =EEFF!F59 -> 70017412 | G64: =F64 -> 70017412 | H64: =G64 -> 70017412 | I64: =H64 -> 70017412 | J64: =I64 -> 70017412 | K64: =J64 -> 70017412
A66: Non-current liabilities
A67: Account payable sellers | D67: =EEFF!D61 -> 84309211 | E67: =EEFF!E61 -> 85192442 | F67: =EEFF!F61 -> 43657337 | G67: =F67 -> 43657337 | H67: =G67 -> 43657337 | I67: =H67 -> 43657337 | J67: =I67 -> 43657337 | K67: =J67 -> 43657337
A68: Loans payable, long term | D68: =EEFF!D62 -> 575680720 | E68: =EEFF!E62 -> 704207379 | F68: =EEFF!F62 -> 841707434 | G68: =F68 -> 841707434 | H68: =G68 -> 841707434 | I68: =H68 -> 841707434 | J68: =I68 -> 841707434 | K68: =J68 -> 841707434
A69: Lease liabilities, long-term | D69: =EEFF!D63 -> 10421780 | E69: =EEFF!E63 -> 7561463 | F69: =EEFF!F63 -> 7306348 | G69: =F69 -> 7306348 | H69: =G69 -> 7306348 | I69: =H69 -> 7306348 | J69: =I69 -> 7306348 | K69: =J69 -> 7306348
A70: Seniority premium | D70: =EEFF!D64 -> 0 | E70: =EEFF!E64 -> 65223 | F70: =EEFF!F64 -> 124106 | G70: =F70 -> 124106 | H70: =G70 -> 124106 | I70: =H70 -> 124106 | J70: =I70 -> 124106 | K70: =J70 -> 124106
A71: Total non-current liabilities | D71: =EEFF!D65 -> 670411711 | E71: =EEFF!E65 -> 797026507 | F71: =EEFF!F65 -> 892795225 | G71: =F71 -> 892795225 | H71: =G71 -> 892795225 | I71: =H71 -> 892795225 | J71: =I71 -> 892795225 | K71: =J71 -> 892795225
A72: Total liabilities | D72: =EEFF!D66 -> 690857940 | E72: =EEFF!E66 -> 887916206 | F72: =EEFF!F66 -> 962812637 | G72: =F72 -> 962812637 | H72: =G72 -> 962812637 | I72: =H72 -> 962812637 | J72: =I72 -> 962812637 | K72: =J72 -> 962812637
A74: Equity
A75: Quotes of participation | D75: =EEFF!D68 -> 158568190 | E75: =EEFF!E68 -> 288833880 | F75: =EEFF!F68 -> 195288846 | G75: =F75 -> 195288846 | H75: =G75 -> 195288846 | I75: =H75 -> 195288846 | J75: =I75 -> 195288846 | K75: =J75 -> 195288846
A76: Accumulated deficit | D76: =EEFF!D69 -> -23111594 | E76: =EEFF!E69 -> -29503876 | F76: =EEFF!F69 -> -38152302 | G76: =F76 -> -38152302 | H76: =G76 -> -38152302 | I76: =H76 -> -38152302 | J76: =I76 -> -38152302 | K76: =J76 -> -38152302
A77: Cash flow hedge reserve | D77: =EEFF!D70 -> 87252820 | E77: =EEFF!E70 -> 103448449 | F77: =EEFF!F70 -> 88475587 | G77: =F77 -> 88475587 | H77: =G77 -> 88475587 | I77: =H77 -> 88475587 | J77: =I77 -> 88475587 | K77: =J77 -> 88475587
A78: Total equity | D78: =EEFF!D71 -> 222709416 | E78: =EEFF!E71 -> 362778453 | F78: =EEFF!F71 -> 245612131 | G78: =F78 -> 245612131 | H78: =G78 -> 245612131 | I78: =H78 -> 245612131 | J78: =I78 -> 245612131 | K78: =J78 -> 245612131
A79: Total liabilities and equity | D79: =EEFF!D72 -> 913567356 | E79: =EEFF!E72 -> 1250694659 | F79: =EEFF!F72 -> 1208424768 | G79: =F79 -> 1208424768 | H79: =G79 -> 1208424768 | I79: =H79 -> 1208424768 | J79: =I79 -> 1208424768 | K79: =J79 -> 1208424768
A81: Años | B81: FY21A | C81: FY22A | D81: FY23A | E81: FY24A | F81: FY25A | G81: FY26E | H81: FY27E | I81: FY28E | J81: FY29E | K81: FY30E
A82: Consolidated Statement of Cash Flows
A83: Cash flows from operating activities
A84: Net loss before tax | D84: =EEFF!D77 -> -7155111 | E84: =EEFF!E77 -> -4951343 | F84: =EEFF!F77 -> -3071600 | G84: =F84 -> -3071600 | H84: =G84 -> -3071600 | I84: =H84 -> -3071600 | J84: =I84 -> -3071600 | K84: =J84 -> -3071600
A86: Adjustments to reconcile net loss before tax to net cash provided by operating activities:
A87: Depreciation of property, plant and equipment | D87: =EEFF!D79 -> 0 | E87: =EEFF!E79 -> 6060088 | F87: =EEFF!F79 -> 29746572 | G87: =F87 -> 29746572 | H87: =G87 -> 29746572 | I87: =H87 -> 29746572 | J87: =I87 -> 29746572 | K87: =J87 -> 29746572
A88: Amortization of intangible assets | D88: =EEFF!D80 -> 0 | E88: =EEFF!E80 -> 2900918 | F88: =EEFF!F80 -> 11603672 | G88: =F88 -> 11603672 | H88: =G88 -> 11603672 | I88: =H88 -> 11603672 | J88: =I88 -> 11603672 | K88: =J88 -> 11603672
A89: Amortization of right of use asset | D89: =EEFF!D81 -> 0 | E89: =EEFF!E81 -> 112148 | F89: =EEFF!F81 -> 470414 | G89: =F89 -> 470414 | H89: =G89 -> 470414 | I89: =H89 -> 470414 | J89: =I89 -> 470414 | K89: =J89 -> 470414
A90: Interest on accounts payable sellers | D90: =EEFF!D82 -> 6982133 | E90: =EEFF!E82 -> 1086710 | F90: =EEFF!F82 -> 5232921 | G90: =F90 -> 5232921 | H90: =G90 -> 5232921 | I90: =H90 -> 5232921 | J90: =I90 -> 5232921 | K90: =J90 -> 5232921
A91: Finance cost | D91: =EEFF!D83 -> 0 | E91: =EEFF!E83 -> 14055900 | F91: =EEFF!F83 -> 63186268 | G91: =F91 -> 63186268 | H91: =G91 -> 63186268 | I91: =H91 -> 63186268 | J91: =I91 -> 63186268 | K91: =J91 -> 63186268
A92: Finance income | D92: =EEFF!D84 -> 0 | E92: =EEFF!E84 -> -3377644 | F92: =EEFF!F84 -> -13262202 | G92: =F92 -> -13262202 | H92: =G92 -> -13262202 | I92: =H92 -> -13262202 | J92: =I92 -> -13262202 | K92: =J92 -> -13262202
A93: Other expenses | D93: =EEFF!D85 -> 0 | E93: =EEFF!E85 -> 0 | F93: =EEFF!F85 -> -71280 | G93: =F93 -> -71280 | H93: =G93 -> -71280 | I93: =H93 -> -71280 | J93: =I93 -> -71280 | K93: =J93 -> -71280
A94: Amortization of deferred financing costs | D94: =EEFF!D86 -> 0 | E94: =EEFF!E86 -> 1466734 | F94: =EEFF!F86 -> 10712475 | G94: =F94 -> 10712475 | H94: =G94 -> 10712475 | I94: =H94 -> 10712475 | J94: =I94 -> 10712475 | K94: =J94 -> 10712475
A95: Cash flows before working capital movements | D95: =EEFF!D87 -> -172978 | E95: =EEFF!E87 -> 17353511 | F95: =EEFF!F87 -> 104547240 | G95: =F95 -> 104547240 | H95: =G95 -> 104547240 | I95: =H95 -> 104547240 | J95: =I95 -> 104547240 | K95: =J95 -> 104547240
A97: Net changes in assets and liabilities:
A98: Accounts receivable | D98: =EEFF!D89 -> 0 | E98: =EEFF!E89 -> -47076360 | F98: =EEFF!F89 -> -5912867 | G98: =F98 -> -5912867 | H98: =G98 -> -5912867 | I98: =H98 -> -5912867 | J98: =I98 -> -5912867 | K98: =J98 -> -5912867
A99: Accounts receivable related parties | D99: =EEFF!D90 -> 0 | E99: =EEFF!E90 -> 3911236 | F99: =EEFF!F90 -> -1348865 | G99: =F99 -> -1348865 | H99: =G99 -> -1348865 | I99: =H99 -> -1348865 | J99: =I99 -> -1348865 | K99: =J99 -> -1348865
A100: Inventories | D100: =EEFF!D91 -> 0 | E100: =EEFF!E91 -> -12567893 | F100: =EEFF!F91 -> -67644 | G100: =F100 -> -67644 | H100: =G100 -> -67644 | I100: =H100 -> -67644 | J100: =I100 -> -67644 | K100: =J100 -> -67644
A101: Prepaid expenses and other assets | D101: =EEFF!D92 -> 0 | E101: =EEFF!E92 -> -18435 | F101: =EEFF!F92 -> -8025588 | G101: =F101 -> -8025588 | H101: =G101 -> -8025588 | I101: =H101 -> -8025588 | J101: =I101 -> -8025588 | K101: =J101 -> -8025588
A102: Severance fund | D102: =EEFF!D93 -> 0 | E102: =EEFF!E93 -> -57766 | F102: =EEFF!F93 -> -57919 | G102: =F102 -> -57919 | H102: =G102 -> -57919 | I102: =H102 -> -57919 | J102: =I102 -> -57919 | K102: =J102 -> -57919
A103: Guarantee deposit | D103: =EEFF!D94 -> -40684 | E103: =EEFF!E94 -> 40884 | F103: =EEFF!F94 -> -990 | G103: =F103 -> -990 | H103: =G103 -> -990 | I103: =H103 -> -990 | J103: =I103 -> -990 | K103: =J103 -> -990
A104: Account payable | D104: =EEFF!D95 -> -2378846 | E104: =EEFF!E95 -> 37941625 | F104: =EEFF!F95 -> -4371652 | G104: =F104 -> -4371652 | H104: =G104 -> -4371652 | I104: =H104 -> -4371652 | J104: =I104 -> -4371652 | K104: =J104 -> -4371652
A105: Account payable to related party | D105: =EEFF!D96 -> -46661 | E105: =EEFF!E96 -> 4766651 | F105: =EEFF!F96 -> -6189745 | G105: =F105 -> -6189745 | H105: =G105 -> -6189745 | I105: =H105 -> -6189745 | J105: =I105 -> -6189745 | K105: =J105 -> -6189745
A106: Accrued expenses and other liabilities | D106: =EEFF!D97 -> 76131 | E106: =EEFF!E97 -> 132552 | F106: =EEFF!F97 -> 96823 | G106: =F106 -> 96823 | H106: =G106 -> 96823 | I106: =H106 -> 96823 | J106: =I106 -> 96823 | K106: =J106 -> 96823
A107: Seniority premium | D107: =EEFF!D98 -> 0 | E107: =EEFF!E98 -> 65223 | F107: =EEFF!F98 -> 58883 | G107: =F107 -> 58883 | H107: =G107 -> 58883 | I107: =H107 -> 58883 | J107: =I107 -> 58883 | K107: =J107 -> 58883
A108: Income tax paid | D108: =EEFF!D99 -> 0 | E108: =EEFF!E99 -> 0 | F108: =EEFF!F99 -> -2881878 | G108: =F108 -> -2881878 | H108: =G108 -> -2881878 | I108: =H108 -> -2881878 | J108: =I108 -> -2881878 | K108: =J108 -> -2881878
A109: Net cash provided by (used in) operating activities | D109: =EEFF!D100 -> -2563038 | E109: =EEFF!E100 -> 4491228 | F109: =EEFF!F100 -> 75845798 | G109: =F109 -> 75845798 | H109: =G109 -> 75845798 | I109: =H109 -> 75845798 | J109: =I109 -> 75845798 | K109: =J109 -> 75845798
A111: Cash flows from investing activities
A112: Construction in progress | D112: =EEFF!D102 -> -256069301 | E112: =EEFF!E102 -> -105937007 | F112: =EEFF!F102 -> -47361449 | G112: =F112 -> -47361449 | H112: =G112 -> -47361449 | I112: =H112 -> -47361449 | J112: =I112 -> -47361449 | K112: =J112 -> -47361449
A113: Property, plant and equipment | D113: =EEFF!D103 -> 0 | E113: =EEFF!E103 -> -8223531 | F113: =EEFF!F103 -> -4768660 | G113: =F113 -> -4768660 | H113: =G113 -> -4768660 | I113: =H113 -> -4768660 | J113: =I113 -> -4768660 | K113: =J113 -> -4768660
...

Sheet _CHECKS
A1: Group Energy Gas Panamá, S. de R.L. and Subsidiary
A2: _CHECKS panel — power template, live formulas, known residuals signed visible
A3: Status semantics: PASS = zero undocumented hard failures; KNOWN_RESIDUAL = signed G7 residual; SOURCE_GAP = unresolved semantic anchor/schedule.
A4: MASTER_STATUS | B4: MODEL STATUS | C4: =IF(COUNTIF($C$6:$C$33,"FAIL")=0,"PASS","FAIL") -> PASS | G4: Master PASS counts only FAIL rows; KNOWN_RESIDUAL/SOURCE_GAP remain visible but non-blocking.
A5: check_id | B5: description | C5: status | D5: hardness | E5: tolerance | F5: expected | G5: note | H5: FY21A | I5: FY22A | J5: FY23A | K5: FY24A | L5: FY25A | M5: FY26E | N5: FY27E | O5: FY28E | P5: FY29E | Q5: FY30E
A7: UNIVERSAL CHECKS
A8: BS_BALANCE | B8: UNIVERSAL | expected 0; hard fail if ABS(value) > hard_tie_tolerance. Observed: UEPII critical gate <10 for BS/cash; BG hard reconciliation >=1000 because full USD. | source applies_to: all 16 archetypes | C8: =IF(SUMPRODUCT((ABS(H8:Q8)>1000)*1)=0,"PASS","FAIL") -> PASS | D8: hard | E8: 1000 USD | F8: 0 | G8: expected 0; hard fail if ABS(value) > hard_tie_tolerance. Observed: UEPII critical gate <10 for BS/cash; BG hard reconciliation >=1000 because full USD. Default full-USD hard tie threshold is $1,000 unless the workbook declares a tighter scale-aware tolerance. | H8: =ModeloFinanciero!B53-ModeloFinanciero!B79 -> 0 | I8: =ModeloFinanciero!C53-ModeloFinanciero!C79 -> 0 | J8: =ModeloFinanciero!D53-ModeloFinanciero!D79 -> 0 | K8: =ModeloFinanciero!E53-ModeloFinanciero!E79 -> 0 | L8: =ModeloFinanciero!F53-ModeloFinanciero!F79 -> 0 | M8: =ModeloFinanciero!G53-ModeloFinanciero!G79 -> 0 | N8: =ModeloFinanciero!H53-ModeloFinanciero!H79 -> 0 | O8: =ModeloFinanciero!I53-ModeloFinanciero!I79 -> 0 | ... Q8: =ModeloFinanciero!K53-ModeloFinanciero!K79 -> 0
A9: CASH_TIE | B9: UNIVERSAL | expected 0; use hard_tie_tolerance; if cash includes restricted cash/time deposits, define cash_component role explicitly. | source applies_to: all 16 archetypes | C9: SOURCE_GAP | D9: hard | E9: 1000 USD | F9: 0 | G9: No semantic anchors resolved for CASH_TIE. | H9: =0 -> 0 | I9: =0 -> 0 | J9: =0 -> 0 | K9: =0 -> 0 | L9: =0 -> 0 | M9: =0 -> 0 | N9: =0 -> 0 | O9: =0 -> 0 | ... Q9: =0 -> 0
A10: CF_ROLLFORWARD | B10: UNIVERSAL | expected 0; hard_tie_tolerance; historical rows may be WARN if source CF transcript is incomplete. | source applies_to: all 16 where CF is modeled | C10: =IF(SUMPRODUCT((ABS(H10:Q10)>1000)*1)=0,"PASS","FAIL") -> PASS | D10: hard | E10: 1000 USD | F10: 0 | G10: expected 0; hard_tie_tolerance; historical rows may be WARN if source CF transcript is incomplete. Default full-USD hard tie threshold is $1,000 unless the workbook declares a tighter scale-aware tolerance. | H10: =ModeloFinanciero!B109+ModeloFinanciero!B117+ModeloFinanciero!B127-ModeloFinanciero!B128 -> 0 | I10: =ModeloFinanciero!C109+ModeloFinanciero!C117+ModeloFinanciero!C127-ModeloFinanciero!C128 -> 0 | J10: =ModeloFinanciero!D109+ModeloFinanciero!D117+ModeloFinanciero!D127-ModeloFinanciero!D128 -> 0 | K10: =ModeloFinanciero!E109+ModeloFinanciero!E117+ModeloFinanciero!E127-ModeloFinanciero!E128 -> 0 | L10: =ModeloFinanciero!F109+ModeloFinanciero!F117+ModeloFinanciero!F127-ModeloFinanciero!F128 -> 0 | M10: =ModeloFinanciero!G109+ModeloFinanciero!G117+ModeloFinanciero!G127-ModeloFinanciero!G128 -> 0 | N10: =ModeloFinanciero!H109+ModeloFinanciero!H117+ModeloFinanciero!H127-ModeloFinanciero!H128 -> 0 | O10: =ModeloFinanciero!I109+ModeloFinanciero!I117+ModeloFinanciero!I127-ModeloFinanciero!I128 -> 0 | ... Q10: =ModeloFinanciero!K109+ModeloFinanciero!K117+ModeloFinanciero!K127-ModeloFinanciero!K128 -> 0
A11: NI_TIE_TO_EQUITY | B11: UNIVERSAL | expected 0; hard_tie_tolerance. | source applies_to: all 16 | C11: SOURCE_GAP | D11: hard | E11: 1000 USD | F11: 0 | G11: No semantic anchors resolved for NI_TIE_TO_EQUITY. | H11: =0 -> 0 | I11: =0 -> 0 | J11: =0 -> 0 | K11: =0 -> 0 | L11: =0 -> 0 | M11: =0 -> 0 | N11: =0 -> 0 | O11: =0 -> 0 | ... Q11: =0 -> 0
A12: NI_SIGN_SANITY | B12: UNIVERSAL | expected 0; sign convention must be stated in row description. | source applies_to: all 16 | C12: SOURCE_GAP | D12: hard | E12: 1000 USD | F12: 0 | G12: No semantic anchors resolved for NI_SIGN_SANITY. | H12: =0 -> 0 | I12: =0 -> 0 | J12: =0 -> 0 | K12: =0 -> 0 | L12: =0 -> 0 | M12: =0 -> 0 | N12: =0 -> 0 | O12: =0 -> 0 | ... Q12: =0 -> 0
A13: RE_ROLLFORWARD | B13: UNIVERSAL | expected 0; hard_tie_tolerance. | source applies_to: all 16 with RE row | C13: SOURCE_GAP | D13: hard | E13: 1000 USD | F13: 0 | G13: No semantic anchors resolved for RE_ROLLFORWARD. | H13: =0 -> 0 | I13: =0 -> 0 | J13: =0 -> 0 | K13: =0 -> 0 | L13: =0 -> 0 | M13: =0 -> 0 | N13: =0 -> 0 | O13: =0 -> 0 | ... Q13: =0 -> 0
A14: EQUITY_TOTAL_TIE | B14: UNIVERSAL | expected 0; hard_tie_tolerance. | source applies_to: all 16 | C14: =IF(SUMPRODUCT((ABS(H14:Q14)>1000)*1)=0,"PASS","FAIL") -> PASS | D14: hard | E14: 1000 USD | F14: 0 | G14: expected 0; hard_tie_tolerance. Default full-USD hard tie threshold is $1,000 unless the workbook declares a tighter scale-aware tolerance. | H14: =SUM(ModeloFinanciero!B75,ModeloFinanciero!B76,ModeloFinanciero!B77)-ModeloFinanciero!B78 -> 0 | I14: =SUM(ModeloFinanciero!C75,ModeloFinanciero!C76,ModeloFinanciero!C77)-ModeloFinanciero!C78 -> 0 | J14: =SUM(ModeloFinanciero!D75,ModeloFinanciero!D76,ModeloFinanciero!D77)-ModeloFinanciero!D78 -> 0 | K14: =SUM(ModeloFinanciero!E75,ModeloFinanciero!E76,ModeloFinanciero!E77)-ModeloFinanciero!E78 -> 0 | L14: =SUM(ModeloFinanciero!F75,ModeloFinanciero!F76,ModeloFinanciero!F77)-ModeloFinanciero!F78 -> 0 | M14: =SUM(ModeloFinanciero!G75,ModeloFinanciero!G76,ModeloFinanciero!G77)-ModeloFinanciero!G78 -> 0 | N14: =SUM(ModeloFinanciero!H75,ModeloFinanciero!H76,ModeloFinanciero!H77)-ModeloFinanciero!H78 -> 0 | O14: =SUM(ModeloFinanciero!I75,ModeloFinanciero!I76,ModeloFinanciero!I77)-ModeloFinanciero!I78 -> 0 | ... Q14: =SUM(ModeloFinanciero!K75,ModeloFinanciero!K76,ModeloFinanciero!K77)-ModeloFinanciero!K78 -> 0
A15: BS_LINEITEM_SUM_ASSETS | B15: UNIVERSAL | expected 0; hard_tie_tolerance. | source applies_to: all 16 | C15: =IF(SUMPRODUCT((ABS(H15:Q15)>1000)*1)=0,"PASS","FAIL") -> PASS | D15: hard | E15: 1000 USD | F15: 0 | G15: expected 0; hard_tie_tolerance. Default full-USD hard tie threshold is $1,000 unless the workbook declares a tighter scale-aware tolerance. | H15: =SUM(ModeloFinanciero!B41,ModeloFinanciero!B52)-ModeloFinanciero!B53 -> 0 | I15: =SUM(ModeloFinanciero!C41,ModeloFinanciero!C52)-ModeloFinanciero!C53 -> 0 | J15: =SUM(ModeloFinanciero!D41,ModeloFinanciero!D52)-ModeloFinanciero!D53 -> 0 | K15: =SUM(ModeloFinanciero!E41,ModeloFinanciero!E52)-ModeloFinanciero!E53 -> 0 | L15: =SUM(ModeloFinanciero!F41,ModeloFinanciero!F52)-ModeloFinanciero!F53 -> 0 | M15: =SUM(ModeloFinanciero!G41,ModeloFinanciero!G52)-ModeloFinanciero!G53 -> 0 | N15: =SUM(ModeloFinanciero!H41,ModeloFinanciero!H52)-ModeloFinanciero!H53 -> 0 | O15: =SUM(ModeloFinanciero!I41,ModeloFinanciero!I52)-ModeloFinanciero!I53 -> 0 | ... Q15: =SUM(ModeloFinanciero!K41,ModeloFinanciero!K52)-ModeloFinanciero!K53 -> 0
A16: BS_LINEITEM_SUM_LIAB_EQUITY | B16: UNIVERSAL | expected 0; hard_tie_tolerance. | source applies_to: all 16 | C16: =IF(SUMPRODUCT((ABS(H16:Q16)>1000)*1)=0,"PASS","FAIL") -> PASS | D16: hard | E16: 1000 USD | F16: 0 | G16: expected 0; hard_tie_tolerance. Default full-USD hard tie threshold is $1,000 unless the workbook declares a tighter scale-aware tolerance. | H16: =ModeloFinanciero!B72+ModeloFinanciero!B78-ModeloFinanciero!B79 -> 0 | I16: =ModeloFinanciero!C72+ModeloFinanciero!C78-ModeloFinanciero!C79 -> 0 | J16: =ModeloFinanciero!D72+ModeloFinanciero!D78-ModeloFinanciero!D79 -> 0 | K16: =ModeloFinanciero!E72+ModeloFinanciero!E78-ModeloFinanciero!E79 -> 0 | L16: =ModeloFinanciero!F72+ModeloFinanciero!F78-ModeloFinanciero!F79 -> 0 | M16: =ModeloFinanciero!G72+ModeloFinanciero!G78-ModeloFinanciero!G79 -> 0 | N16: =ModeloFinanciero!H72+ModeloFinanciero!H78-ModeloFinanciero!H79 -> 0 | O16: =ModeloFinanciero!I72+ModeloFinanciero!I78-ModeloFinanciero!I79 -> 0 | ... Q16: =ModeloFinanciero!K72+ModeloFinanciero!K78-ModeloFinanciero!K79 -> 0
A17: SOURCE_TIE_HISTORICAL | B17: UNIVERSAL | expected 0 for audited rows; SOURCE_GAP/WARN allowed only with explicit source-gap note. | source applies_to: all 16 | C17: =IF(SUMPRODUCT((ABS(H17:Q17)>100000)*1)=0,"PASS","FAIL") -> PASS | D17: hard | E17: 100000 USD | F17: 0 | G17: Audited rows tie to 0; only bank ending-cash-vs-EEFF cash rows may use the observed $100,000 hard threshold; SOURCE_GAP/WARN requires explicit source-gap note. | H17: =ModeloFinanciero!B53-EEFF!B49 -> 0 | I17: =ModeloFinanciero!C53-EEFF!C49 -> 0 | J17: =ModeloFinanciero!D53-EEFF!D49 -> 0 | K17: =ModeloFinanciero!E53-EEFF!E49 -> 0 | L17: =ModeloFinanciero!F53-EEFF!F49 -> 0
A18: NO_FORMULA_ERRORS | B18: UNIVERSAL | expected PASS/0; no masking. | source applies_to: all 16 | C18: =IF(SUMPRODUCT((ABS(H18:Q18)>0)*1)=0,"PASS","FAIL") -> PASS | D18: hard | E18: PASS | F18: PASS | G18: expected PASS/0; no masking. | H18: =0 -> 0 | I18: =0 -> 0 | J18: =0 -> 0 | K18: =0 -> 0 | L18: =0 -> 0 | M18: =0 -> 0 | N18: =0 -> 0 | O18: =0 -> 0 | ... Q18: =0 -> 0
A19: NO_CHECKS_MASTER_FAIL | B19: UNIVERSAL | expected PASS; status row should cite included/excluded rows. | source applies_to: all 16 | C19: =IF(SUMPRODUCT((ABS(H19:Q19)>0)*1)=0,"PASS","FAIL") -> PASS | D19: hard | E19: PASS | F19: PASS | G19: expected PASS; status row should cite included/excluded rows. | H19: =COUNTIF($C$6:$C$18,"FAIL")+COUNTIF($C$20:$C$33,"FAIL") -> 0 | I19: =COUNTIF($C$6:$C$18,"FAIL")+COUNTIF($C$20:$C$33,"FAIL") -> 0 | J19: =COUNTIF($C$6:$C$18,"FAIL")+COUNTIF($C$20:$C$33,"FAIL") -> 0 | K19: =COUNTIF($C$6:$C$18,"FAIL")+COUNTIF($C$20:$C$33,"FAIL") -> 0 | L19: =COUNTIF($C$6:$C$18,"FAIL")+COUNTIF($C$20:$C$33,"FAIL") -> 0 | M19: =COUNTIF($C$6:$C$18,"FAIL")+COUNTIF($C$20:$C$33,"FAIL") -> 0 | N19: =COUNTIF($C$6:$C$18,"FAIL")+COUNTIF($C$20:$C$33,"FAIL") -> 0 | O19: =COUNTIF($C$6:$C$18,"FAIL")+COUNTIF($C$20:$C$33,"FAIL") -> 0 | ... Q19: =COUNTIF($C$6:$C$18,"FAIL")+COUNTIF($C$20:$C$33,"FAIL") -> 0
A21: CONDITIONAL CHECKS
A22: PPE_SCHEDULE_TIE | B22: ARCHETYPE/conditional | expected 0; hard_tie_tolerance. | source applies_to: operating-EBITDA, power, utility, downstream fuel, other non-financials | C22: SOURCE_GAP | D22: hard | E22: 1000 USD | F22: 0 | G22: No semantic anchors resolved for PPE_SCHEDULE_TIE. | H22: =0 -> 0 | I22: =0 -> 0 | J22: =0 -> 0 | K22: =0 -> 0 | L22: =0 -> 0 | M22: =0 -> 0 | N22: =0 -> 0 | O22: =0 -> 0 | ... Q22: =0 -> 0
A23: LEASE_SCHEDULE_TIE | B23: ARCHETYPE/conditional | expected 0; hard_tie_tolerance. | source applies_to: IFRS-16 issuers | C23: SOURCE_GAP | D23: hard | E23: 1000 USD | F23: 0 | G23: No semantic anchors resolved for LEASE_SCHEDULE_TIE. | H23: =0 -> 0 | I23: =0 -> 0 | J23: =0 -> 0 | K23: =0 -> 0 | L23: =0 -> 0 | M23: =0 -> 0 | N23: =0 -> 0 | O23: =0 -> 0 | ... Q23: =0 -> 0
A24: DEBT_SCHEDULE_TIE | B24: ARCHETYPE/conditional | expected 0; hard_tie_tolerance; project-finance debt can include accrued interest/unamortized cost roles. | source applies_to: non-bank-lender, power, utility, operating-EBITDA with debt | C24: SOURCE_GAP | D24: hard | E24: 1000 USD | F24: 0 | G24: No semantic anchors resolved for DEBT_SCHEDULE_TIE. | H24: =0 -> 0 | I24: =0 -> 0 | J24: =0 -> 0 | K24: =0 -> 0 | L24: =0 -> 0 | M24: =0 -> 0 | N24: =0 -> 0 | O24: =0 -> 0 | ... Q24: =0 -> 0
A26: POWER CHECKS
A27: POWER_REVENUE_BUILD_TIE | B27: ARCHETYPE | expected 0; hard_tie_tolerance. | source applies_to: power, utility | C27: SOURCE_GAP | D27: hard | E27: 1000 USD | F27: 0 | G27: No semantic anchors resolved for POWER_REVENUE_BUILD_TIE. | H27: =0 -> 0 | I27: =0 -> 0 | J27: =0 -> 0 | K27: =0 -> 0 | L27: =0 -> 0 | M27: =0 -> 0 | N27: =0 -> 0 | O27: =0 -> 0 | ... Q27: =0 -> 0
A28: POWER_CHANNEL_VOLUME_TIE | B28: ARCHETYPE | expected 0; observed UEPII uses N/A for years without channel split. | source applies_to: power, utility | C28: SOURCE_GAP | D28: hard | E28: volume_tolerance | F28: 0 | G28: No semantic anchors resolved for POWER_CHANNEL_VOLUME_TIE. | H28: =0 -> 0 | I28: =0 -> 0 | J28: =0 -> 0 | K28: =0 -> 0 | L28: =0 -> 0 | M28: =0 -> 0 | N28: =0 -> 0 | O28: =0 -> 0 | ... Q28: =0 -> 0
A29: POWER_CAPACITY_CEILING | B29: ARCHETYPE | PASS/FAIL or 0/1; threshold from hours-per-year parameter. | source applies_to: power, utility | C29: SOURCE_GAP | D29: hard | E29: PASS | F29: PASS | G29: Installed-capacity ceiling needs an addressable capacity-driver row before the live check can be rendered without hardcoded formula constants. | H29: =0 -> 0 | I29: =0 -> 0 | J29: =0 -> 0 | K29: =0 -> 0 | L29: =0 -> 0 | M29: =0 -> 0 | N29: =0 -> 0 | O29: =0 -> 0 | ... Q29: =0 -> 0
A30: POWER_DSRA_COVERAGE | B30: ARCHETYPE | expected 0; UEPII tail uses <=1 tolerance in U2 rows. | source applies_to: project-finance power/utility | C30: SOURCE_GAP | D30: hard | E30: 1 model currency or ratio residual | F30: 0 | G30: No semantic anchors resolved for POWER_DSRA_COVERAGE. | H30: =0 -> 0 | I30: =0 -> 0 | J30: =0 -> 0 | K30: =0 -> 0 | L30: =0 -> 0 | M30: =0 -> 0 | N30: =0 -> 0 | O30: =0 -> 0 | ... Q30: =0 -> 0
A31: POWER_DSCR_COVENANT | B31: ARCHETYPE | must be >=0 or explicit business-warning text; not always a mechanical blocker. | source applies_to: project-finance power/utility | C31: SOURCE_GAP | D31: soft | E31: 0 cushion | F31: >=0 | G31: No semantic anchors resolved for POWER_DSCR_COVENANT. | H31: =0 -> 0 | I31: =0 -> 0 | J31: =0 -> 0 | K31: =0 -> 0 | L31: =0 -> 0 | M31: =0 -> 0 | N31: =0 -> 0 | O31: =0 -> 0 | ... Q31: =0 -> 0
A32: POWER_DEBT_FACE_ZERO | B32: ARCHETYPE | PASS/FAIL; tail-life projects. | source applies_to: finite-life project finance | C32: SOURCE_GAP | D32: hard | E32: PASS | F32: PASS | G32: No semantic anchors resolved for POWER_DEBT_FACE_ZERO. | H32: =0 -> 0 | I32: =0 -> 0 | J32: =0 -> 0 | K32: =0 -> 0 | L32: =0 -> 0 | M32: =0 -> 0 | N32: =0 -> 0 | O32: =0 -> 0 | ... Q32: =0 -> 0
A33: OPERATING_GP_OR_EBITDA_TIE | B33: ARCHETYPE | expected 0; hard_tie_tolerance. | source applies_to: operating-EBITDA, downstream fuel, power when EBITDA is used | C33: SOURCE_GAP | D33: hard | E33: 1000 USD | F33: 0 | G33: No semantic anchors resolved for OPERATING_GP_OR_EBITDA_TIE. | H33: =0 -> 0 | I33: =0 -> 0 | J33: =0 -> 0 | K33: =0 -> 0 | L33: =0 -> 0 | M33: =0 -> 0 | N33: =0 -> 0 | O33: =0 -> 0 | ... Q33: =0 -> 0

Sheet Source_Register
A1: Group Energy Gas Panamá, S. de R.L. and Subsidiary
A2: Source_Register — power archetype. Every row traces to a published filing (OCR text) or to a working file kept by the maintainer.
A3: Status semantics: OK = citation resolved to an existing artifact. SOURCE_GAP = traceability missing (visible, not hidden). NOT_DISCLOSED = no registration/manifest found for this issuer.
A4: source_id | B4: kind | C4: ticker | D4: filing | E4: year | F4: nota | G4: tabla_ocr | H4: feeds_sheet | I4: feeds_anchor | J4: date | K4: status | L4: evidence_count | M4: note
A5: OCR_ROOT:gana-gatun | B5: OCR_ROOT | H5: EEFF; Notas_EEFF | I5: OCR of the published filings | J5: NOT_DISCLOSED | K5: OK | L5: 1 | M5: Published filings of gana-gatun
A6: EEFF_FILING:gatun_final_offering_memorandum_ratings_letter | B6: EEFF_FILING | D6: Gatun - Final Offering Memorandum & Ratings Letter.pdf | G6: markdown.md | H6: EEFF; Notas_EEFF; MD&A | I6: markdown.md | J6: NOT_DISCLOSED | K6: OK | L6: 602 | M6: markdown.md sha256=1c0060ae3a96104e...
A7: EEFF_FILING:gatun_preliminary_offering_memorandum_ered_93 | B7: EEFF_FILING | D7: Gatun - Preliminary Offering Memorandum (eRed)[93].pdf | G7: markdown.md | H7: EEFF; Notas_EEFF; MD&A | I7: markdown.md | J7: NOT_DISCLOSED | K7: OK | L7: 592 | M7: markdown.md sha256=66a3f3b08fb4607b...
A8: NOTA:Gatun - Final Offering Memorandum & Ratings Letter.pdf#1 | B8: NOTA | D8: Gatun - Final Offering Memorandum & Ratings Letter.pdf | F8: 1 | G8: markdown.md | H8: Notas_EEFF | I8: 1. MAIN ASSUMPTIONS | J8: NOT_DISCLOSED | K8: OK | L8: 186
A9: NOTA:Gatun - Final Offering Memorandum & Ratings Letter.pdf#10 | B9: NOTA | D9: Gatun - Final Offering Memorandum & Ratings Letter.pdf | F9: 10 | G9: markdown.md | H9: Notas_EEFF | I9: 10. Construction in Progress | J9: NOT_DISCLOSED | K9: OK | L9: 15
A10: NOTA:Gatun - Final Offering Memorandum & Ratings Letter.pdf#11 | B10: NOTA | D10: Gatun - Final Offering Memorandum & Ratings Letter.pdf | F10: 11 | G10: markdown.md | H10: Notas_EEFF | I10: 11. Lease | J10: NOT_DISCLOSED | K10: OK | L10: 19
A11: NOTA:Gatun - Final Offering Memorandum & Ratings Letter.pdf#12 | B11: NOTA | D11: Gatun - Final Offering Memorandum & Ratings Letter.pdf | F11: 12 | G11: markdown.md | H11: Notas_EEFF | I11: 12. Loans Payable (Continued) | J11: NOT_DISCLOSED | K11: OK | L11: 44
A12: NOTA:Gatun - Final Offering Memorandum & Ratings Letter.pdf#13 | B12: NOTA | D12: Gatun - Final Offering Memorandum & Ratings Letter.pdf | F12: 13 | G12: markdown.md | H12: Notas_EEFF | I12: 13. Hedge Accounting Applicable to Senior Credit Agreement (Continued) | J12: NOT_DISCLOSED | K12: OK | L12: 48
A13: NOTA:Gatun - Final Offering Memorandum & Ratings Letter.pdf#14 | B13: NOTA | D13: Gatun - Final Offering Memorandum & Ratings Letter.pdf | F13: 14 | G13: markdown.md | H13: Notas_EEFF | I13: 14. Accounts Payable | J13: NOT_DISCLOSED | K13: OK | L13: 2
A14: NOTA:Gatun - Final Offering Memorandum & Ratings Letter.pdf#15 | B14: NOTA | D14: Gatun - Final Offering Memorandum & Ratings Letter.pdf | F14: 15 | G14: markdown.md | H14: Notas_EEFF | I14: 15. Balances and Transactions with Related Parties (Continued) | J14: NOT_DISCLOSED | K14: OK | L14: 27
A15: NOTA:Gatun - Final Offering Memorandum & Ratings Letter.pdf#16 | B15: NOTA | D15: Gatun - Final Offering Memorandum & Ratings Letter.pdf | F15: 16 | G15: markdown.md | H15: Notas_EEFF | I15: 16. Prepaid Expenses and Other Assets | J15: NOT_DISCLOSED | K15: OK | L15: 2
A16: NOTA:Gatun - Final Offering Memorandum & Ratings Letter.pdf#17 | B16: NOTA | D16: Gatun - Final Offering Memorandum & Ratings Letter.pdf | F16: 17 | G16: markdown.md | H16: Notas_EEFF | I16: 17. Shareholders’ Equity (Continued) | J16: NOT_DISCLOSED | K16: OK | L16: 18
A17: NOTA:Gatun - Final Offering Memorandum & Ratings Letter.pdf#18 | B17: NOTA | D17: Gatun - Final Offering Memorandum & Ratings Letter.pdf | F17: 18 | G17: markdown.md | H17: Notas_EEFF | I17: 18. Intangible Assets | J17: NOT_DISCLOSED | K17: OK | L17: 11
A18: NOTA:Gatun - Final Offering Memorandum & Ratings Letter.pdf#19 | B18: NOTA | D18: Gatun - Final Offering Memorandum & Ratings Letter.pdf | F18: 19 | G18: markdown.md | H18: Notas_EEFF | I18: 19. Electricity Sales | J18: NOT_DISCLOSED | K18: OK | L18: 12
A19: NOTA:Gatun - Final Offering Memorandum & Ratings Letter.pdf#2 | B19: NOTA | D19: Gatun - Final Offering Memorandum & Ratings Letter.pdf | F19: 2 | G19: markdown.md | H19: Notas_EEFF | I19: 2. SIMULATION RESULTS | J19: NOT_DISCLOSED | K19: OK | L19: 332
... A35: NOTA:Gatun - Final Offering Memorandum & Ratings Letter.pdf#9 | B35: NOTA | D35: Gatun - Final Offering Memorandum & Ratings Letter.pdf | F35: 9 | G35: markdown.md | H35: Notas_EEFF | I35: 9. Property, Plant and Equipment (Continued) | J35: NOT_DISCLOSED | K35: OK | L35: 4
A36: DRIVER:EEFF (citado por fórmula viva) | B36: DRIVER_OTHER | H36: Supuestos | I36: Electricity sales (hist, ref EEFF) | J36: NOT_DISCLOSED | K36: SOURCE_GAP | L36: 3 | M36: Unclassified _source citation shape: EEFF (citado por fórmula viva)
A37: DRIVER:NOT_DISCLOSED | B37: DRIVER_OTHER | H37: Supuestos | I37: Selector escenario | J37: NOT_DISCLOSED | K37: SOURCE_GAP | L37: 13 | M37: Unclassified _source citation shape: NOT_DISCLOSED

Sheet _CHANGELOG
A1: Group Energy Gas Panamá, S. de R.L. and Subsidiary
A2: _CHANGELOG — generation record for gana-gatun.
A3: Internal build history omitted from the public export. Record public changes below.

Sheet Claude Code Log
A1: Turn # | B1: Date | C1: User Request | D1: Action Taken | E1: Details | F1: Outcome
A2: 1 | B2: 46324.359 | C2: Prepare a public model copy | D2: Remove local paths and private build references; preserve financial formulas and inputs | E2: Agent run with MOG as the tool, checked by guard v1. The guard measured every sheet before and after the run. Changed: Notas_EEFF: 1 cell written, at A3; Source_Register: 3 cells written, at A2, I5, M5; _CHANGELOG: data A1:H33 -> A1:A3 (rows 33 -> 3, columns 8 -> 1), 205 cells written, at A2, A3, B3, C3, D3, E3, F3, G3, H3, A4, B4, C4, D4, E4, F4 and 190 more. Other actions: clear x1. Agent: OpenFinmods export | F2: Compare against source and review public copy
