Workbook

Sheet EEFF
A1: Grupo Melo, S.A. y Subsidiarias
A2: Estados Financieros Consolidados Auditados FY21-FY25
A3: en B/. sin escala
A5: Años | B5: FY21A | C5: FY22A | D5: FY23A | E5: FY24A | F5: FY25A | G5: FY26E | H5: FY27E | I5: FY28E | J5: FY29E | K5: FY30E
A6: Estado Consolidado de Resultados y Otros Resultados Integrales
A7: Ingresos de actividades ordinarias | B7: 446526908 | C7: 475476377 | D7: 460436761 | E7: 471286765 | F7: 477606859
A8: Otros ingresos | B8: 4324870 | C8: 3967649 | D8: 10430308 | E8: 3049990 | F8: 3273534
A9: Cambios en el inventario de mercancía, productos terminados, en proceso y otros | B9: -151521675 | C9: -187725448 | D9: -172601924 | E9: -172621803 | F9: -184583589
A10: Consumo de materia prima y materiales usados | B10: -101910296 | C10: -91798432 | D10: -85551297 | E10: -86117863 | F10: -78107263
A11: Gastos de personal | B11: -78191068 | C11: -82630079 | D11: -84367143 | E11: -90003575 | F11: -92534638
A12: Depreciación y amortización | B12: -14499892 | C12: -13788592 | D12: -14598107 | E12: -15421420 | F12: -15968601
A13: Depreciación activos derecho de uso | B13: -4281088 | C13: -4141096 | D13: -3853656 | E13: -4881754 | F13: -5584457
A14: Pérdida crediticia esperada | B14: -926879 | C14: -767688 | D14: -1432537 | E14: -1418031 | F14: -455297
A15: Otros gastos | B15: -67772425 | C15: -73044128 | D15: -84424966 | E15: -81815270 | F15: -80604183
A16: Ganancia operativa | B16: 31748455 | C16: 25548563 | D16: 24037439 | E16: 22057039 | F16: 23042365
A17: Intereses y dividendos ganados | B17: 1827169 | C17: 2203898 | D17: 1911252 | E17: 2201801 | F17: 2520005
A18: Gastos de intereses pasivos por arrendamiento | B18: -1003513 | C18: -925031 | D18: -830555 | E18: -1006351 | F18: -1199370
... A27: Total de resultados integrales | B27: 21120595 | C27: 18112643 | D27: 18414037 | E27: 14554108 | F27: 15961582
A29: Años | B29: FY21A | C29: FY22A | D29: FY23A | E29: FY24A | F29: FY25A | G29: FY26E | H29: FY27E | I29: FY28E | J29: FY29E | K29: FY30E
A30: Estado Consolidado de Situación Financiera
A31: Efectivo y equivalentes de efectivo | B31: 14137059 | C31: 10248083 | D31: 13933186 | E31: 14627619 | F31: 21421098
A32: Documentos y cuentas por cobrar, neto | B32: 55987713 | C32: 55396562 | D32: 50598758 | E32: 48881564 | F32: 47635856
A33: Inventarios | B33: 88215721 | C33: 105854774 | D33: 106547752 | E33: 98584841 | F33: 86537964
A34: Inventario de materiales, piezas y repuestos | B34: 4368953 | C34: 5522228 | D34: 5650193 | E34: 7019946 | F34: 7379445
A35: Lotes disponibles para la venta | B35: 7437127 | C35: 6714577 | D35: 8088976 | E35: 6759518 | F35: 5876049
A36: Activos biológicos | B36: 9533860 | C36: 10662082 | D36: 9971872 | E36: 7465217 | F36: 8437671
A37: Adelantos para compras de inventarios y granos | B37: 6253970 | C37: 4940077 | D37: 11953319 | E37: 15363019 | F37: 20196108
A38: Gastos pagados por adelantado | B38: 3881243 | C38: 9409729 | D38: 2059074 | E38: 1651119 | F38: 1545541
A39: Impuesto sobre la renta pagado por adelantado | B39: 683093 | C39: 2940162 | D39: 3768331 | E39: 828999 | F39: 1992042
A40: Otros activos | B40: 339020 | C40: 312728 | D40: 123508 | E40: 228031 | F40: 239863
A41: Total de activos corrientes | B41: 190837759 | C41: 212001002 | D41: 212694969 | E41: 201409873 | F41: 201261637
A42: Efectivo y equivalentes de efectivo (no corriente) | D42: 0 | E42: 1400000 | F42: 0
A43: Documentos por cobrar, neto | B43: 12370463 | C43: 11827693 | D43: 11670843 | E43: 11965641 | F43: 11635096
A44: Inventario de materiales, piezas y repuestos (no corriente) | B44: 394833 | C44: 435601 | D44: 364529 | E44: 958317 | F44: 936271
A45: Inmuebles, mobiliarios, equipos y mejoras, neto | B45: 122024120 | C45: 121738941 | D45: 123764215 | E45: 117719141 | F45: 119820020
A46: Activo Intangible, neto | D46: 0 | E46: 7437220 | F46: 6646648
A47: Equipo para arrendamiento, neto | B47: 2092260 | C47: 2003420 | D47: 3633937 | E47: 3477575 | F47: 2378222
A48: Activos por derecho de uso | B48: 16299265 | C48: 15847890 | D48: 14989169 | E48: 17883482 | F48: 18860730
A49: Propiedades de inversión | B49: 9805509 | C49: 9967013 | D49: 7548656 | E49: 7555934 | F49: 7439753
A50: Otras inversiones | B50: 615566 | C50: 615566 | D50: 615566 | E50: 615566 | F50: 615566
A51: Inversión en asociadas | B51: 4864483 | C51: 5436683 | D51: 6419403 | E51: 6760369 | F51: 7176666
A52: Activos biológicos (no corriente) | B52: 8125114 | C52: 7741648 | D52: 9201413 | E52: 9128819 | F52: 9133839
A53: Fondo de cesantía | B53: 9075419 | C53: 10207260 | D53: 10640387 | E53: 11667330 | F53: 12349530
A54: Impuesto sobre la renta diferido | B54: 1084512 | C54: 1088903 | D54: 1094422 | E54: 421341 | F54: 420911
A55: Otros activos (no corriente) | B55: 578136 | C55: 600216 | D55: 643053 | E55: 663877 | F55: 676023
A56: Total de activos no corrientes | B56: 187329680 | C56: 187510834 | D56: 190585593 | E56: 197654612 | F56: 198089275
A57: Total de activos | B57: 378167439 | C57: 399511836 | D57: 403280562 | E57: 399064485 | F57: 399350912
A58: Préstamos por pagar | B58: 12760000 | C58: 14000000 | D58: 13819186 | E58: 8000000 | F58: 6900000
... A63: Cuentas por pagar compañías relacionadas | B63: 15200 | C63: 248703 | D63: 68927 | E63: 0 | F63: 42296
A64: Impuesto sobre la renta por pagar | B64: 2908783 | C64: 0
A65: Gastos acumulados y otros pasivos | B65: 7121789 | C65: 7040115 | D65: 7090627 | E65: 7903342 | F65: 7308891
A66: Total de pasivos corrientes | B66: 90409174 | C66: 86465847 | D66: 81870978 | E66: 71191745 | F66: 70600588
A67: Préstamos por pagar (no corriente) | D67: 0 | E67: 2124600 | F67: 2124600
A68: Bonos por pagar | B68: 52466986 | C68: 67427589 | D68: 67388899 | E68: 62350209 | F68: 52311519
A69: Pasivos por arrendamiento (no corriente) | B69: 14331670 | C69: 14277496 | D69: 13594963 | E69: 15912188 | F69: 15961760
A70: Provisión para prima de antigüedad | B70: 9477255 | C70: 10127829 | D70: 10407453 | E70: 10739857 | F70: 10998227
A71: Total de pasivos no corrientes | B71: 76275911 | C71: 91832914 | D71: 91391315 | E71: 91126854 | F71: 81396106
A72: Total de pasivos | B72: 166685085 | C72: 178298761 | D72: 173262293 | E72: 162318599 | F72: 151996694
A73: Capital emitido: acciones comunes, sin valor nominal | B73: 45813813 | C73: 45813813 | D73: 45077843 | E73: 44725993 | F73: 44553868
A74: Utilidades no distribuidas | B74: 165176872 | C74: 174803519 | D74: 183969668 | E74: 190907552 | F74: 201717520
A75: Otros resultados integrales | B75: 216328 | C75: 324037 | D75: 645130 | E75: 724767 | F75: 739584
A76: Total de patrimonio atribuible a los propietarios | B76: 211207013 | C76: 220941369 | D76: 229692641 | E76: 236358312 | F76: 247010972
A77: Participación no controladora | B77: 275341 | C77: 271706 | D77: 325628 | E77: 387574 | F77: 343246
A78: Total de patrimonio | B78: 211482354 | C78: 221213075 | D78: 230018269 | E78: 236745886 | F78: 247354218
A79: Total de pasivos y patrimonio | B79: 378167439 | C79: 399511836 | D79: 403280562 | E79: 399064485 | F79: 399350912
A81: Años | B81: FY21A | C81: FY22A | D81: FY23A | E81: FY24A | F81: FY25A | G81: FY26E | H81: FY27E | I81: FY28E | J81: FY29E | K81: FY30E
A82: Estado Consolidado de Flujos de Efectivo
A83: Utilidad neta | B83: 21205300 | C83: 18004934 | D83: 18092944 | E83: 14474471 | F83: 15946765
A84: Participación en resultado de asociadas | B84: -1026225 | C84: -1366177 | D84: -1650460 | E84: -1225747 | F84: -1203147
A85: Depreciación y amortización de propiedad, equipo y mejoras | B85: 13407970 | C85: 12908124 | D85: 13628603 | E85: 13965491 | F85: 14006514
A86: Amortización de activo intangible | D86: 0 | E86: 191146 | F86: 798172
A87: Depreciación de equipo para arrendamiento | B87: 1091922 | C87: 880468 | D87: 973473 | E87: 1264783 | F87: 1163915
A88: Depreciación de derecho de uso | B88: 4281088 | C88: 4141096 | D88: 3853656 | E88: 4881754 | F88: 5084457
A89: Pérdida en venta de activo fijo | B89: 111753 | C89: 78722 | D89: -221006 | E89: 7413 | F89: 84328
A90: Ganancia por cancelación o acuerdos en derecho de uso | B90: -720416 | C90: -726549 | D90: -45930 | E90: -15073
A91: Pérdida en disposición de propiedad de inversión | E91: 0 | F91: 8000
A92: Ganancia en venta de valores | D92: -6443146 | E92: 0
A93: Provisión para prima de antigüedad | B93: 1717272 | C93: 2015167 | D93: 1194818 | E93: 1254843 | F93: 1277252
A94: Pérdida crediticia esperada | D94: 1432537 | E94: 1418031 | F94: 455297
A95: Costos financieros, neto | B95: 4253458 | C95: 2306216 | D95: 3577343 | E95: 3746352 | F95: 3157485
A96: Impuesto sobre la renta | B96: 7315922 | C96: 6603590 | D96: 4017612 | E96: 5061963 | F96: 5141262
A97: Documentos y cuentas por cobrar | B97: -4692774 | C97: 1133921 | D97: 5956108 | E97: 4365 | F97: 1120956
A98: Inventarios | B98: -12146830 | C98: -17465207 | D98: -1051273 | E98: 8766185 | F98: 13354407
A99: Inventario de materiales, piezas y repuestos | B99: -33995 | C99: -1194043 | D99: -56893 | E99: -1963541 | F99: -337453
A100: Lotes disponibles para la venta | B100: 816657 | C100: 722550 | D100: 1098461 | E100: 1329458 | F100: 883469
A101: Activos biológicos | B101: -2230832 | C101: -561778 | D101: -162083 | E101: 2512854 | F101: -977474
A102: Adelanto a compra de inventarios y granos | B102: -2308440 | C102: 1313893 | D102: -7013242 | E102: -3409700 | F102: -4833089
A103: Gastos pagados por adelantado | B103: -3086910 | C103: -5528486 | D103: 7350655 | E103: 407955 | F103: 105578
A104: Otros activos | B104: 502522 | C104: 4211 | D104: 146383 | E104: -125347 | F104: -23978
A105: Cuentas por pagar proveedores y compañías relacionadas | B105: 18812266 | C105: 5177883 | D105: -6679279 | E105: -4033223 | F105: -3313445
A106: Adelantos recibidos de clientes | B106: 2365978 | C106: -2301924 | D106: 1888489 | E106: 646426 | F106: 319248
... A117: Adquisición de equipo de arrendamiento | B117: -310772 | C117: -965474 | D117: -2850922 | E117: -1511496 | F117: -612571
A118: Adquisición de activos intangibles | E118: 0 | F118: -7600
A119: Producto de la disposición de propiedades de inversión | E119: 0 | F119: 105000
A120: Dividendos recibidos de inversión en asociadas | B120: 1395523 | C120: 793977 | D120: 667740 | E120: 817297 | F120: 795946
A121: Costos incurridos en activo biológico - plantación forestal | B121: -165254 | C121: -182978
A122: Producto de la venta de subsidiaria | D122: 4009155 | E122: 0
A123: Plazo fijo | D123: 0 | E123: -3400000 | F123: -4606000
A124: Mejoras a propiedades de inversión | B124: -14988 | C124: -161504 | D124: -54503 | E124: -7278 | F124: 3181
A125: Efectivo neto usado en las actividades de inversión | B125: -5802718 | C125: -12145588 | D125: -12919247 | E125: -18814011 | F125: -19429480
...

Sheet Notas_EEFF
A1: Grupo Melo, S.A. y Subsidiarias
A2: Notas a los Estados Financieros
A3: Fuente: informes auditados vía OCR Mistral (verbatim).
A5: Año | B5: Documento fuente | C5: Página OCR | D5: Tabla OCR / sección | E5: Nota # | F5: Título original de la nota | G5: Categoría modelable | H5: Line item EEFF | I5: Sub-line item / detalle | J5: Texto original / disclosure | K5: Monto reportado | L5: Moneda | M5: Unidad / escala | N5: Fecha / venc. / tasa / plazo | O5: Contraparte / contrato / instrumento | P5: Impacto en Supuestos | Q5: Impacto en ModeloFinanciero | R5: Link a celda EEFF | S5: Comentario de extracción | T5: Status
A6: 2022 | B6: INA_GRMELO_2022_0.pdf | C6: page-34 | D6: markdown.md | E6: 1 | F6: 1. Información general | G6: Otros | J6: Empresas Melo, S.A., (en adelante, el "Fideicomitente Emisor") y MMG Bank Corporation como Agente Fiduciario (FIDBI-006), constituyeron el Fideicomiso de Garantía mediante Escritura Pública No.19,704 del 17 de diciembre de 2009, de la Notaría Cuarta del Circuito de Panamá. | T6: OK
A7: 2022 | B7: INA_GRMELO_2022_0.pdf | C7: page-34 | D7: markdown.md | E7: 1 | F7: 1. Información general | G7: Otros | J7: El objetivo general del Fideicomiso es garantizar con los bienes que mantienen, el cumplimiento de las obligaciones adquiridas por parte del Fideicomitente. Las obligaciones por parte del Fideicomitente son derivadas de: a) la emisión de bonos corporativos rotativos de hasta B/.50,000.000, cuyo registro y oferta pública fue autorizada por la Superintendencia de Mercado de Valores de Panamá mediante Resolución CNV No.358-09 de 20 de noviembre de 2009, modificada mediante Resolución SMV-552-14 del 13 de noviembre de 2014. | K7: 50000 | L7: B/. | T7: OK
A8: 2022 | B8: INA_GRMELO_2022_0.pdf | C8: page-34 | D8: markdown.md | E8: 1 | F8: 1. Información general | G8: Otros | J8: El Fiduciario es MMG Bank Corporation ("Agente Fiduciario") es una sociedad anónima organizada y de conformidad con las leyes de la República de Panamá, autorizada para ejercer el negocio Fiduciario en o desde la República de Panamá mediante Resolución Fiduciaria No.SBP-FID.0009-2013 de 14 de junio de 2013. | T8: OK
A9: 2022 | B9: INA_GRMELO_2022_0.pdf | C9: page-34 | D9: markdown.md | E9: 1 | F9: 1. Información general | G9: Otros | J9: El negocio de Fideicomiso en Panamá está regulado mediante la ley No.1 del 5 de enero de 1984, y la Ley No.21 del 10 de mayo de 2017, así como resoluciones y acuerdos de la Superintendencia de Bancos de Panamá. | T9: OK
A10: 2022 | B10: INA_GRMELO_2022_0.pdf | C10: page-34 | D10: markdown.md | E10: 1 | F10: 1. Información general | G10: Otros | J10: Los bienes del Fideicomiso de garantía están compuestos por: | T10: OK
A11: 2022 | B11: INA_GRMELO_2022_0.pdf | C11: page-34 | D11: markdown.md | E11: 1 | F11: 1. Información general | G11: Otros | J11: - Los derechos reales derivados de la Primera Hipoteca y Anticresis que se constituye a favor del Fiduciario, sobre ciertos bienes inmuebles propiedad del Fideicomitente y/o el Garante Hipotecario y cuyo valor de mercado, según avalúo por un evaluador aceptable al Fiduciario deberá cubrir al menos un 120% del saldo insoluto a capital de los Bonos emitidos y en circulación (Ver Nota No.4). | T11: OK
A12: 2022 | B12: INA_GRMELO_2022_0.pdf | C12: page-34 | D12: markdown.md | E12: 1 | F12: 1. Información general | G12: Otros | J12: - Cesión de las pólizas de seguro contra incendios de las fincas hipotecadas a favor del Fiduciario. | T12: OK
A13: 2022 | B13: INA_GRMELO_2022_0.pdf | C13: page-34 | D13: markdown.md | E13: 1 | F13: 1. Información general | G13: Otros | J13: El total del Patrimonio del Fideicomiso es de B/.66,200,381 (2021: B/.67,125,350) de los cuales la suma de B/.66,200,381 (2021: B/.67,125,350) están conformados por el derecho real de hipoteca a favor del Fiduciario detallados en la Nota No.4. | K13: 66200381 | L13: B/. | T13: OK
A14: 2022 | B14: INA_GRMELO_2022_0.pdf | C14: page-34 | D14: markdown.md | E14: 1 | F14: 1. Información general | G14: Otros | J14: Al 31 de diciembre de 2022, la Cobertura de Garantía representa el 195%, la cual resulta de dividir el valor de mercado de los bienes inmuebles hipotecados entre el saldo insoluto a capital de los Bonos emitidos y en circulación. | T14: OK
A15: 2022 | B15: INA_GRMELO_2022_0.pdf | C15: page-34 | D15: markdown.md | E15: 1 | F15: 1. Información general | G15: Otros | J15: El Fideicomiso estará vigente hasta la fecha en que todas las obligaciones garantizadas se extingan. | T15: OK
A16: 2022 | B16: INA_GRMELO_2022_0.pdf | C16: page-34 | D16: markdown.md | E16: 1 | F16: 1. Información general | G16: Otros | J16: La oficina principal de la Fiduciaria está localizada en Costa del Este, Avenida Paseo del Mar, Edificio MMG Tower, Piso 22, Ciudad de Panamá República de Panamá. | T16: OK
A17: 2022 | B17: INA_GRMELO_2022_0.pdf | C17: page-35 | D17: markdown.md | E17: 1 | F17: 1. Información general | G17: Otros | J17: Notas a los Estados Financieros Por el año terminado el 31 de diciembre de 2022 (Cifras en balboas) | T17: OK
A18: 2022 | B18: INA_GRMELO_2022_0.pdf | C18: page-35 | D18: markdown.md | E18: 2 | F18: 2. Bases para la preparación de los estados financieros | G18: Otros | J18: ### 2.1. Base de medición | T18: OK
A19: 2022 | B19: INA_GRMELO_2022_0.pdf | C19: page-35 | D19: markdown.md | E19: 2 | F19: 2. Bases para la preparación de los estados financieros | G19: Otros | J19: Los estados financieros del Fideicomiso de Garantía Empresas Melo S.A. (FIDBI-006) (MMG Bank Corporation como Agente Fiduciario al 31 de diciembre de 2022, fueron preparados sobre la base de costo o costo amortizado. | T19: OK
A20: 2022 | B20: INA_GRMELO_2022_0.pdf | C20: page-35 | D20: markdown.md | E20: 2 | F20: 2. Bases para la preparación de los estados financieros | G20: Otros | J20: ### 2.2. Moneda funcional y de presentación | T20: OK
A21: 2022 | B21: INA_GRMELO_2022_0.pdf | C21: page-35 | D21: markdown.md | E21: 2 | F21: 2. Bases para la preparación de los estados financieros | G21: Otros | J21: Los estados financieros están expresados en balboas (B/.), que es la moneda funcional del Fideicomiso y la unidad monetaria de la República de Panamá, la cual está a la par y es de libre cambio con el dólar (US$) de los Estados Unidos de América. La República de Panamá no emite papel moneda propio y en su lugar, el dólar (US$) de los Estados Unidos de América es utilizado como moneda de curso legal. | T21: OK
A22: 2022 | B22: INA_GRMELO_2022_0.pdf | C22: page-35 | D22: markdown.md | E22: 3 | F22: 3. Resumen de las principales políticas contables | G22: Políticas contables | J22: ### 3.1. Estimaciones y juicios realizados | T22: OK
A23: 2022 | B23: INA_GRMELO_2022_0.pdf | C23: page-35 | D23: markdown.md | E23: 3 | F23: 3. Resumen de las principales políticas contables | G23: Políticas contables | J23: La preparación de los estados financieros del Fideicomiso requiere que se realicen estimaciones y juicios contables que son evaluados de manera continua y se basan en experiencia pasadas y ciertos factores aplicables al sector, mismos que son razonables bajo las circunstancias actuales y las expectativas de sucesos futuros. | T23: OK
A24: 2022 | B24: INA_GRMELO_2022_0.pdf | C24: page-35 | D24: markdown.md | E24: 3 | F24: 3. Resumen de las principales políticas contables | G24: Políticas contables | J24: Al 31 de diciembre de 2022, el Fideicomiso no ha requerido estimaciones contables significativas. | T24: OK
A25: 2022 | B25: INA_GRMELO_2022_0.pdf | C25: page-35 | D25: markdown.md | E25: 3 | F25: 3. Resumen de las principales políticas contables | G25: Políticas contables | J25: ### 3.2. Derecho real de hipoteca | T25: OK
... A31: 2022 | B31: INA_GRMELO_2022_0.pdf | C31: page-36 | D31: markdown.md | E31: 3 | F31: 3. Resumen de las principales políticas contables | G31: Políticas contables | J31: Corresponden a desembolsos o retiros de derecho real de hipoteca que debe efectuar la administradora del Fideicomiso de conformidad y en cumplimiento con el Contrato de Fideicomiso, los cuales se reconocen como retiros al Patrimonio del Fideicomiso. | T31: OK
A32: 2022 | B32: INA_GRMELO_2022_0.pdf | C32: page-36 | D32: markdown.md | E32: 4 | F32: 4. Derecho real de hipoteca | G32: Otros | J32: Los derechos hipotecarios y anticréticos corresponden a la primera hipoteca constituida a favor del Fiduciario MMG Bank Corporation, sobre bienes inmuebles del Fideicomitente y/o del Garante Hipotecario Inmobiliaria los Libertadores, S.A., por un valor de B/.61,077,310. | K32: 61077310 | L32: B/. | T32: OK
A33: 2022 | B33: INA_GRMELO_2022_0.pdf | C33: page-36 | D33: markdown.md | E33: 4 | F33: 4. Derecho real de hipoteca | G33: Otros | J33: Los bienes inmuebles en garantía tienen un valor de mercado de B/.66,200,381 (2021: B/.67,125,350) según informe del Avaluador Panamericana de Avalúos, S.A. de fecha 30 de diciembre 2022, (2021: según informe del Avaluador Panamericana de Avalúos, S.A. de fecha diciembre 2021). | K33: 66200381 | L33: B/. | T33: OK
A34: 2022 | B34: INA_GRMELO_2022_0.pdf | C34: page-36 | D34: tbl-28.html | E34: 4 | F34: 4. Derecho real de hipoteca | G34: Otros | J34: [tbl-28.html](tbl-28.html) | T34: OK
A35: 2022 | B35: INA_GRMELO_2022_0.pdf | C35: page-36 | D35: markdown.md | E35: 5 | F35: 5. Impuesto sobre la renta | G35: Impuestos | J35: - El Decreto Ejecutivo No.170 del 27 de octubre de 1993, establece en el artículo 81 que se consideran contribuyentes el Fideicomiso constituido conforme a la Ley que generan rentas gravables. El Fideicomiso constituido de acuerdo con la Ley No.1 del 5 de enero de 1984, se considera contribuyente al Fiduciario, quien determinará el impuesto de acuerdo con las reglas generales aplicables a las personas jurídicas o naturales según sea su naturaleza. | T35: OK
A36: 2022 | B36: INA_GRMELO_2022_0.pdf | C36: page-36 | D36: markdown.md | E36: 5 | F36: 5. Impuesto sobre la renta | G36: Impuestos | J36: - De acuerdo con la legislación fiscal vigente, la renta proveniente de los intereses ganados sobre depósitos en bancos locales, están exentos del pago del impuesto sobre la renta. | T36: OK
A37: 2022 | B37: INA_GRMELO_2022_0.pdf | C37: page-36 | D37: markdown.md | E37: 5 | F37: 5. Impuesto sobre la renta | G37: Impuestos | J37: - Al 31 de diciembre de 2022, el Fideicomiso no generó renta gravable. | T37: OK
A38: 2022 | B38: INA_GRMELO_2022_0.pdf | C38: page-37 | D38: markdown.md | E38: 5 | F38: 5. Impuesto sobre la renta | G38: Impuestos | J38: Notas a los Estados Financieros Por el año terminado el 31 de diciembre de 2022 (Cifras en balboas) | T38: OK
A39: 2023 | B39: INA_GRMELO_2023_0.pdf | C39: page-35 | D39: markdown.md | E39: 1 | F39: 1. Información general | G39: Otros | J39: Empresas Melo, S.A., (en adelante, el "Fideicomitente Emisor") y MMG Bank Corporation como Agente Fiduciario (FIDBI-006), constituyeron el Fideicomiso de Garantía mediante Escritura Pública No.19,704 del 17 de diciembre de 2009, de la Notaría Cuarta del Circuito de Panamá. | T39: OK
A40: 2023 | B40: INA_GRMELO_2023_0.pdf | C40: page-35 | D40: markdown.md | E40: 1 | F40: 1. Información general | G40: Otros | J40: El objetivo general del Fideicomiso es garantizar con los bienes que mantienen, el cumplimiento de las obligaciones adquiridas por parte del Fideicomitente. Las obligaciones por parte del Fideicomitente son derivadas de: a) la emisión de bonos corporativos rotativos de hasta B/.50,000.000, cuyo registro y oferta pública fue autorizada por la Superintendencia de Mercado de Valores de Panamá mediante Resolución CNV No.358-09 de 20 de noviembre de 2009. | K40: 50000 | L40: B/. | T40: OK
A41: 2023 | B41: INA_GRMELO_2023_0.pdf | C41: page-35 | D41: markdown.md | E41: 1 | F41: 1. Información general | G41: Otros | J41: El Fiduciario es MMG Bank Corporation ("Agente Fiduciario") es una sociedad anónima organizada y de conformidad con las leyes de la República de Panamá, autorizada para ejercer el negocio Fiduciario en o desde la República de Panamá mediante Resolución Fiduciaria No.SBP-FID.0009-2013 de 14 de junio de 2013. | T41: OK
A42: 2023 | B42: INA_GRMELO_2023_0.pdf | C42: page-35 | D42: markdown.md | E42: 1 | F42: 1. Información general | G42: Otros | J42: El negocio de Fideicomiso en Panamá está regulado mediante la ley No.1 del 5 de enero de 1984, y la Ley No.21 del 10 de mayo de 2017, así como resoluciones y acuerdos de la Superintendencia de Bancos de Panamá. | T42: OK
A43: 2023 | B43: INA_GRMELO_2023_0.pdf | C43: page-35 | D43: markdown.md | E43: 1 | F43: 1. Información general | G43: Otros | J43: Los bienes del Fideicomiso de garantía están compuestos por: | T43: OK
A44: 2023 | B44: INA_GRMELO_2023_0.pdf | C44: page-35 | D44: markdown.md | E44: 1 | F44: 1. Información general | G44: Otros | J44: - Los derechos reales derivados de la Primera Hipoteca y Anticresis que se constituye a favor del Fiduciario, sobre ciertos bienes inmuebles propiedad del Fideicomitente y/o el Garante Hipotecario y cuyo valor de mercado, según avalúo por un evaluador aceptable al Fiduciario deberá cubrir al menos un 120% del saldo insoluto a capital de los Bonos emitidos y en circulación (Ver Nota No.4). | T44: OK
A45: 2023 | B45: INA_GRMELO_2023_0.pdf | C45: page-35 | D45: markdown.md | E45: 1 | F45: 1. Información general | G45: Otros | J45: - Cesión de las pólizas de seguro contra incendios de las fincas hipotecadas a favor del Fiduciario. | T45: OK
A46: 2023 | B46: INA_GRMELO_2023_0.pdf | C46: page-35 | D46: markdown.md | E46: 1 | F46: 1. Información general | G46: Otros | J46: El total del Patrimonio del Fideicomiso es de B/.57,200,381 (2022: B/.66,200,381) de los cuales la suma de B/.57,200,381 (2022: B/.66,200,381) están conformados por el derecho real de hipoteca a favor del Fiduciario detallados en la Nota No.4. | K46: 57200381 | L46: B/. | T46: OK
A47: 2023 | B47: INA_GRMELO_2023_0.pdf | C47: page-35 | D47: markdown.md | E47: 1 | F47: 1. Información general | G47: Otros | J47: Al 31 de diciembre de 2023, la Cobertura de Garantía representa el 168% (2022: 195%), la cual resulta de dividir el valor de mercado de los bienes inmuebles hipotecados entre el saldo insoluto a capital de los Bonos emitidos y en circulación. | T47: OK
A48: 2023 | B48: INA_GRMELO_2023_0.pdf | C48: page-35 | D48: markdown.md | E48: 1 | F48: 1. Información general | G48: Otros | J48: El Fideicomiso estará vigente hasta la fecha en que todas las obligaciones garantizadas se extingan. | T48: OK
A49: 2023 | B49: INA_GRMELO_2023_0.pdf | C49: page-35 | D49: markdown.md | E49: 1 | F49: 1. Información general | G49: Otros | J49: La oficina principal de la Fiduciaria está localizada en Costa del Este, Avenida Paseo del Mar, Edificio MMG Tower, Piso 22, Ciudad de Panamá República de Panamá. | T49: OK
A50: 2023 | B50: INA_GRMELO_2023_0.pdf | C50: page-36 | D50: markdown.md | E50: 2 | F50: 2. Bases para la preparación de los estados financieros | G50: Otros | J50: ### 2.1. Base de medición | T50: OK
A51: 2023 | B51: INA_GRMELO_2023_0.pdf | C51: page-36 | D51: markdown.md | E51: 2 | F51: 2. Bases para la preparación de los estados financieros | G51: Otros | J51: Los estados financieros del Fideicomiso de Garantía Empresas Melo S.A. (FIDBI-006) (MMG Bank Corporation como Agente Fiduciario al 31 de diciembre de 2023, fueron preparados sobre la base de costo o costo amortizado. | T51: OK
A52: 2023 | B52: INA_GRMELO_2023_0.pdf | C52: page-36 | D52: markdown.md | E52: 2 | F52: 2. Bases para la preparación de los estados financieros | G52: Otros | J52: ### 2.2. Moneda funcional y de presentación | T52: OK
A53: 2023 | B53: INA_GRMELO_2023_0.pdf | C53: page-36 | D53: markdown.md | E53: 2 | F53: 2. Bases para la preparación de los estados financieros | G53: Otros | J53: Los estados financieros están expresados en balboas (B/.), que es la moneda funcional del Fideicomiso y la unidad monetaria de la República de Panamá, la cual está a la par y es de libre cambio con el dólar (US$) de los Estados Unidos de América. La República de Panamá no emite papel moneda propio y en su lugar, el dólar (US$) de los Estados Unidos de América es utilizado como moneda de curso legal. | T53: OK
A54: 2023 | B54: INA_GRMELO_2023_0.pdf | C54: page-36 | D54: markdown.md | E54: 3 | F54: 3. Resumen de las principales políticas contables | G54: Políticas contables | J54: ### 3.1. Estimaciones y juicios realizados | T54: OK
A55: 2023 | B55: INA_GRMELO_2023_0.pdf | C55: page-36 | D55: markdown.md | E55: 3 | F55: 3. Resumen de las principales políticas contables | G55: Políticas contables | J55: La preparación de los estados financieros del Fideicomiso requiere que se realicen estimaciones y juicios contables que son evaluados de manera continua y se basan en experiencia pasadas y ciertos factores aplicables al sector, mismos que son razonables bajo las circunstancias actuales y las expectativas de sucesos futuros. | T55: OK
A56: 2023 | B56: INA_GRMELO_2023_0.pdf | C56: page-36 | D56: markdown.md | E56: 3 | F56: 3. Resumen de las principales políticas contables | G56: Políticas contables | J56: Al 31 de diciembre de 2023 y 2022, el Fideicomiso no ha requerido estimaciones contables significativas. | T56: OK
A57: 2023 | B57: INA_GRMELO_2023_0.pdf | C57: page-36 | D57: markdown.md | E57: 3 | F57: 3. Resumen de las principales políticas contables | G57: Políticas contables | J57: ### 3.2. Derecho real de hipoteca | T57: OK
A58: 2023 | B58: INA_GRMELO_2023_0.pdf | C58: page-36 | D58: markdown.md | E58: 3 | F58: 3. Resumen de las principales políticas contables | G58: Políticas contables | J58: El derecho real de hipoteca sobre bienes inmuebles se reconoce como activos dentro del estado de situación financiera de acuerdo con las políticas contables de la Fiduciaria, por el monto o valor de mercado de las hipotecas constituidas a favor del Fiduciario según indica en la Escritura Pública donde consta la primera hipoteca y anticresis. | T58: OK
... A62: 2023 | B62: INA_GRMELO_2023_0.pdf | C62: page-37 | D62: markdown.md | E62: 3 | F62: 3. Resumen de las principales políticas contables | G62: Políticas contables | J62: Corresponden a desembolsos o retiros de derecho real de hipoteca que debe efectuar la administradora del Fideicomiso de conformidad y en cumplimiento con el Contrato de Fideicomiso, los cuales se reconocen como retiros al Patrimonio del Fideicomiso. | T62: OK
A63: 2023 | B63: INA_GRMELO_2023_0.pdf | C63: page-37 | D63: markdown.md | E63: 4 | F63: 4. Derecho real de hipoteca | G63: Otros | J63: Los derechos hipotecarios y anticréticos corresponden a la primera hipoteca constituida a favor del Fiduciario MMG Bank Corporation, sobre bienes inmuebles del Fideicomitente y/o del Garante Hipotecario Inmobiliaria los Libertadores, S.A., por un valor de B/.61,077,310. | K63: 61077310 | L63: B/. | T63: OK
A64: 2023 | B64: INA_GRMELO_2023_0.pdf | C64: page-37 | D64: markdown.md | E64: 4 | F64: 4. Derecho real de hipoteca | G64: Otros | J64: Mediante Escritura Pública No.2,620 de 15 de marzo de 2023, el Fiduciario otorga consentimiento para cancelar parcialmente gravámenes hipotecarios y anticréticos que pesaban sobre 8 fincas de propiedad de Empresas Melo. | T64: OK
A65: 2023 | B65: INA_GRMELO_2023_0.pdf | C65: page-37 | D65: markdown.md | E65: 4 | F65: 4. Derecho real de hipoteca | G65: Otros | J65: Los bienes inmuebles en garantía tienen un valor de mercado de B/.57,200,381 (2022: B/.66,200,381) según informe del Avaluador Panamericana de Avalúos, S.A. de fecha 28 de septiembre 2023 (2022: según informe del Avaluador Panamericana de Avalúos, S.A. de fecha 30 de diciembre 2022). | K65: 57200381 | L65: B/. | T65: OK
A66: 2023 | B66: INA_GRMELO_2023_0.pdf | C66: page-37 | D66: tbl-20.html | E66: 4 | F66: 4. Derecho real de hipoteca | G66: Otros | J66: [tbl-20.html](tbl-20.html) | T66: OK
A67: 2023 | B67: INA_GRMELO_2023_0.pdf | C67: page-37 | D67: markdown.md | E67: 5 | F67: 5. Impuesto sobre la renta | G67: Impuestos | J67: - El Decreto Ejecutivo No.170 del 27 de octubre de 1993, establece en el artículo 81 que se consideran contribuyentes el Fideicomiso constituido conforme a la Ley que generan rentas gravables. El Fideicomiso constituido de acuerdo con la Ley No.1 del 5 de enero de 1984, se considera contribuyente al Fiduciario, quien determinará el impuesto de acuerdo con las reglas generales aplicables a las personas jurídicas o naturales según sea su naturaleza. | T67: OK
A68: 2023 | B68: INA_GRMELO_2023_0.pdf | C68: page-37 | D68: markdown.md | E68: 5 | F68: 5. Impuesto sobre la renta | G68: Impuestos | J68: - De acuerdo con la legislación fiscal vigente, la renta proveniente de los intereses ganados sobre depósitos en bancos locales, están exentos del pago del impuesto sobre la renta. | T68: OK
A69: 2023 | B69: INA_GRMELO_2023_0.pdf | C69: page-37 | D69: markdown.md | E69: 5 | F69: 5. Impuesto sobre la renta | G69: Impuestos | J69: - Al 31 de diciembre de 2023 y 2022, el Fideicomiso no generó renta gravable. | T69: OK
A70: 2023 | B70: INA_GRMELO_2023_0.pdf | C70: page-38 | D70: markdown.md | E70: 5 | F70: 5. Impuesto sobre la renta | G70: Impuestos | J70: Notas a los Estados Financieros Por el año terminado el 31 de diciembre de 2023 (Cifras en balboas) | T70: OK
A71: 2024 | B71: INA_GRMELO_2024_0.pdf | C71: page-32 | D71: markdown.md | E71: 1 | F71: 1. Información general | G71: Otros | J71: Empresas Melo, S.A., (en adelante, el "Fideicomitente Emisor") y MMG Bank Corporation como Agente Fiduciario (FIDBI-006), constituyeron el Fideicomiso de Garantía mediante Escritura Pública No.19,704 del 17 de diciembre de 2009, de la Notaría Cuarta del Circuito de Panamá. | T71: OK
A72: 2024 | B72: INA_GRMELO_2024_0.pdf | C72: page-32 | D72: markdown.md | E72: 1 | F72: 1. Información general | G72: Otros | J72: El objetivo general del Fideicomiso es garantizar con los bienes que mantienen, el cumplimiento de las obligaciones adquiridas por parte del Fideicomitente. Las obligaciones por parte del Fideicomitente son derivadas de: a) la emisión de bonos corporativos rotativos de hasta B/.50,000.000, cuyo registro y oferta pública fue autorizada por la Superintendencia de Mercado de Valores de Panamá mediante Resolución CNV No.358-09 de 20 de noviembre de 2009. | K72: 50000 | L72: B/. | T72: OK
A73: 2024 | B73: INA_GRMELO_2024_0.pdf | C73: page-32 | D73: markdown.md | E73: 1 | F73: 1. Información general | G73: Otros | J73: El Fiduciario es MMG Bank Corporation ("Agente Fiduciario") es una sociedad anónima organizada y de conformidad con las leyes de la República de Panamá, autorizada para ejercer el negocio Fiduciario en o desde la República de Panamá mediante Resolución Fiduciaria No.SBP-FID.0009-2013 de 14 de junio de 2013. | T73: OK
A74: 2024 | B74: INA_GRMELO_2024_0.pdf | C74: page-32 | D74: markdown.md | E74: 1 | F74: 1. Información general | G74: Otros | J74: El negocio de Fideicomiso en Panamá está regulado mediante la ley No.1 del 5 de enero de 1984, y la Ley No.21 del 10 de mayo de 2017, así como resoluciones y acuerdos de la Superintendencia de Bancos de Panamá. | T74: OK
A75: 2024 | B75: INA_GRMELO_2024_0.pdf | C75: page-32 | D75: markdown.md | E75: 1 | F75: 1. Información general | G75: Otros | J75: Los bienes del Fideicomiso de garantía están compuestos por: | T75: OK
A76: 2024 | B76: INA_GRMELO_2024_0.pdf | C76: page-32 | D76: markdown.md | E76: 1 | F76: 1. Información general | G76: Otros | J76: - Los derechos reales derivados de la Primera Hipoteca y Anticresis que se constituye a favor del Fiduciario, sobre ciertos bienes inmuebles propiedad del Fideicomitente y/o el Garante Hipotecario y cuyo valor de mercado, según avalúo por un evaluador aceptable al Fiduciario deberá cubrir al menos un 120% del saldo insoluto a capital de los Bonos emitidos y en circulación (Ver Nota No.4). | T76: OK
A77: 2024 | B77: INA_GRMELO_2024_0.pdf | C77: page-32 | D77: markdown.md | E77: 1 | F77: 1. Información general | G77: Otros | J77: - Cesión de las pólizas de seguro contra incendios de las fincas hipotecadas a favor del Fiduciario. | T77: OK
A78: 2024 | B78: INA_GRMELO_2024_0.pdf | C78: page-32 | D78: markdown.md | E78: 1 | F78: 1. Información general | G78: Otros | J78: El total del Patrimonio del Fideicomiso es de B/.66,274,750 (2023: B/.57,200,381) de los cuales la suma de B/.66,274,750 (2023: B/.57,200,381) están conformados por el derecho real de hipoteca a favor del Fiduciario detallados en la Nota No.4. | K78: 66274750 | L78: B/. | T78: OK
A79: 2024 | B79: INA_GRMELO_2024_0.pdf | C79: page-32 | D79: markdown.md | E79: 1 | F79: 1. Información general | G79: Otros | J79: Al 31 de diciembre de 2024, la Cobertura de Garantía representa el 195% (2023: 168%), la cual resulta de dividir el valor de mercado de los bienes inmuebles hipotecados entre el saldo insoluto a capital de los Bonos emitidos y en circulación. | T79: OK
A80: 2024 | B80: INA_GRMELO_2024_0.pdf | C80: page-32 | D80: markdown.md | E80: 1 | F80: 1. Información general | G80: Otros | J80: El Fideicomiso estará vigente hasta la fecha en que todas las obligaciones garantizadas se extingan. | T80: OK
A81: 2024 | B81: INA_GRMELO_2024_0.pdf | C81: page-32 | D81: markdown.md | E81: 1 | F81: 1. Información general | G81: Otros | J81: La oficina principal de la Fiduciaria está localizada en Costa del Este, Avenida Paseo del Mar, Edificio MMG Tower, Piso 22, Ciudad de Panamá República de Panamá. | T81: OK
A82: 2024 | B82: INA_GRMELO_2024_0.pdf | C82: page-33 | D82: markdown.md | E82: 2 | F82: 2. Bases para la preparación de los estados financieros | G82: Otros | J82: ### 2.1. Base de medición | T82: OK
A83: 2024 | B83: INA_GRMELO_2024_0.pdf | C83: page-33 | D83: markdown.md | E83: 2 | F83: 2. Bases para la preparación de los estados financieros | G83: Otros | J83: Los estados financieros del Fideicomiso de Garantía Empresas Melo S.A. (FIDBI-006) (MMG Bank Corporation como Agente Fiduciario al 31 de diciembre de 2024, fueron preparados sobre la base de costo o costo amortizado. | T83: OK
A84: 2024 | B84: INA_GRMELO_2024_0.pdf | C84: page-33 | D84: markdown.md | E84: 2 | F84: 2. Bases para la preparación de los estados financieros | G84: Otros | J84: ### 2.2. Moneda funcional y de presentación | T84: OK
A85: 2024 | B85: INA_GRMELO_2024_0.pdf | C85: page-33 | D85: markdown.md | E85: 2 | F85: 2. Bases para la preparación de los estados financieros | G85: Otros | J85: Los estados financieros están expresados en balboas (B/.), que es la moneda funcional del Fideicomiso y la unidad monetaria de la República de Panamá, la cual está a la par y es de libre cambio con el dólar (US$) de los Estados Unidos de América. La República de Panamá no emite papel moneda propio y en su lugar, el dólar (US$) de los Estados Unidos de América es utilizado como moneda de curso legal. | T85: OK
A86: 2024 | B86: INA_GRMELO_2024_0.pdf | C86: page-33 | D86: markdown.md | E86: 3 | F86: 3. Resumen de las principales políticas contables | G86: Políticas contables | J86: ### 3.1. Estimaciones y juicios realizados | T86: OK
A87: 2024 | B87: INA_GRMELO_2024_0.pdf | C87: page-33 | D87: markdown.md | E87: 3 | F87: 3. Resumen de las principales políticas contables | G87: Políticas contables | J87: La preparación de los estados financieros del Fideicomiso requiere que se realicen estimaciones y juicios contables que son evaluados de manera continua y se basan en experiencia pasadas y ciertos factores aplicables al sector, mismos que son razonables bajo las circunstancias actuales y las expectativas de sucesos futuros. | T87: OK
A88: 2024 | B88: INA_GRMELO_2024_0.pdf | C88: page-33 | D88: markdown.md | E88: 3 | F88: 3. Resumen de las principales políticas contables | G88: Políticas contables | J88: Al 31 de diciembre de 2024 y 2023, el Fideicomiso no ha requerido estimaciones contables significativas. | T88: OK
A89: 2024 | B89: INA_GRMELO_2024_0.pdf | C89: page-33 | D89: markdown.md | E89: 3 | F89: 3. Resumen de las principales políticas contables | G89: Políticas contables | J89: ### 3.2. Derecho real de hipoteca | T89: OK
A90: 2024 | B90: INA_GRMELO_2024_0.pdf | C90: page-33 | D90: markdown.md | E90: 3 | F90: 3. Resumen de las principales políticas contables | G90: Políticas contables | J90: El derecho real de hipoteca sobre bienes inmuebles se reconoce como activos dentro del estado de situación financiera de acuerdo con las políticas contables de la Fiduciaria, por el monto o valor de mercado de las hipotecas constituidas a favor del Fiduciario según indica en la Escritura Pública donde consta la primera hipoteca y anticresis. | T90: OK
... A94: 2024 | B94: INA_GRMELO_2024_0.pdf | C94: page-34 | D94: markdown.md | E94: 3 | F94: 3. Resumen de las principales políticas contables | G94: Políticas contables | J94: Corresponden a desembolsos o retiros de derecho real de hipoteca que debe efectuar la administradora del Fideicomiso de conformidad y en cumplimiento con el Contrato de Fideicomiso, los cuales se reconocen como retiros al Patrimonio del Fideicomiso. | T94: OK
A95: 2024 | B95: INA_GRMELO_2024_0.pdf | C95: page-34 | D95: markdown.md | E95: 4 | F95: 4. Derecho real de hipoteca | G95: Otros | J95: Los derechos hipotecarios y anticréticos corresponden a la primera hipoteca constituida a favor del Fiduciario MMG Bank Corporation, sobre bienes inmuebles del Fideicomitente y/o del Garante Hipotecario Inmobiliaria los Libertadores, S.A., por un valor de B/.61,077,310. | K95: 61077310 | L95: B/. | T95: OK
A96: 2024 | B96: INA_GRMELO_2024_0.pdf | C96: page-34 | D96: markdown.md | E96: 4 | F96: 4. Derecho real de hipoteca | G96: Otros | J96: Mediante Escritura Pública No.2,620 de 15 de marzo de 2023, el Fiduciario otorga consentimiento para cancelar parcialmente gravámenes hipotecarios y anticréticos que pesaban sobre 8 fincas de propiedad de Empresas Melo. | T96: OK
A97: 2024 | B97: INA_GRMELO_2024_0.pdf | C97: page-34 | D97: markdown.md | E97: 4 | F97: 4. Derecho real de hipoteca | G97: Otros | J97: Los bienes inmuebles en garantía tienen un valor de mercado de B/.66,274,750 (2023: B/.57,200,381) según informe del Avaluador Panamericana de Avalúos, S.A., de fecha de diciembre 2024 (2023: según informe del Avaluador Panamericana de Avalúos, S.A. de fecha 28 de septiembre 2023). | K97: 66274750 | L97: B/. | T97: OK
A98: 2024 | B98: INA_GRMELO_2024_0.pdf | C98: page-34 | D98: tbl-27.html | E98: 4 | F98: 4. Derecho real de hipoteca | G98: Otros | J98: [tbl-27.html](tbl-27.html) | T98: OK
A99: 2024 | B99: INA_GRMELO_2024_0.pdf | C99: page-34 | D99: markdown.md | E99: 5 | F99: 5. Impuesto sobre la renta | G99: Impuestos | J99: - El Decreto Ejecutivo No.170 del 27 de octubre de 1993, establece en el artículo 81 que se consideran contribuyentes el Fideicomiso constituido conforme a la Ley que generan rentas gravables. El Fideicomiso constituido de acuerdo con la Ley No.1 del 5 de enero de 1984, se considera contribuyente al Fiduciario, quien determinará el impuesto de acuerdo con las reglas generales aplicables a las personas jurídicas o naturales según sea su naturaleza. - De acuerdo con la legislación fiscal vigente, la renta proveniente de los intereses ganados sobre depósitos en bancos locales, están exentos del pago del impuesto sobre la renta. - Al 31 de diciembre de 2024 y 2023, el Fideicomiso no generó renta gravable. | T99: OK
A100: 2024 | B100: INA_GRMELO_2024_0.pdf | C100: page-35 | D100: markdown.md | E100: 5 | F100: 5. Impuesto sobre la renta | G100: Impuestos | J100: Notas a los Estados Financieros Por el año terminado el 31 de diciembre de 2024 (Cifras en balboas) | T100: OK
A101: 2025 | B101: INA_GRMELO_2025_0.pdf | C101: page-43 | D101: markdown.md | E101: 1 | F101: 1. Información general | G101: Otros | J101: Empresas Melo, S.A., (en adelante, el "Fideicomitente Emisor") y MMG Bank Corporation como Agente Fiduciario (FIDBI-006), constituyeron el Fideicomiso de Garantía mediante Escritura Pública No.19,704 del 17 de diciembre de 2009, de la Notaría Cuarta del Circuito de Panamá. | T101: OK
A102: 2025 | B102: INA_GRMELO_2025_0.pdf | C102: page-43 | D102: markdown.md | E102: 1 | F102: 1. Información general | G102: Otros | J102: El objetivo general del Fideicomiso es garantizar con los bienes que mantienen, el cumplimiento de las obligaciones adquiridas por parte del Fideicomitente. Las obligaciones por parte del Fideicomitente son derivadas de la emisión de bonos corporativos rotativos de hasta B/.50,000.000, cuyo registro y oferta pública fue autorizada por la Superintendencia de Mercado de Valores de Panamá mediante Resolución CNV No.358-09 de 20 de noviembre de 2009. | K102: 50000 | L102: B/. | T102: OK
A103: 2025 | B103: INA_GRMELO_2025_0.pdf | C103: page-43 | D103: markdown.md | E103: 1 | F103: 1. Información general | G103: Otros | J103: El Fiduciario es MMG Bank Corporation ("Agente Fiduciario") es una sociedad anónima organizada y de conformidad con las leyes de la República de Panamá, autorizada para ejercer el negocio Fiduciario en o desde la República de Panamá mediante Resolución Fiduciaria No.SBP-FID.0009-2013 de 14 de junio de 2013. | T103: OK
A104: 2025 | B104: INA_GRMELO_2025_0.pdf | C104: page-43 | D104: markdown.md | E104: 1 | F104: 1. Información general | G104: Otros | J104: El negocio de Fideicomiso en Panamá está regulado mediante la ley No.1 del 5 de enero de 1984, y la Ley No.21 del 10 de mayo de 2017, así como resoluciones y acuerdos de la Superintendencia de Bancos de Panamá. | T104: OK
A105: 2025 | B105: INA_GRMELO_2025_0.pdf | C105: page-43 | D105: markdown.md | E105: 1 | F105: 1. Información general | G105: Otros | J105: Los bienes del Fideicomiso de garantía están compuestos por: | T105: OK
A106: 2025 | B106: INA_GRMELO_2025_0.pdf | C106: page-43 | D106: markdown.md | E106: 1 | F106: 1. Información general | G106: Otros | J106: - Los derechos reales derivados de la Primera Hipoteca y Anticresis que se constituye a favor del Fiduciario, sobre ciertos bienes inmuebles propiedad del Fideicomitente y/o el Garante Hipotecario y cuyo valor de mercado, según avalúo por un evaluador aceptable al Fiduciario deberá cubrir al menos un 120% del saldo insoluto a capital de los Bonos emitidos y en circulación (Ver Nota No.4). | T106: OK
A107: 2025 | B107: INA_GRMELO_2025_0.pdf | C107: page-43 | D107: markdown.md | E107: 1 | F107: 1. Información general | G107: Otros | J107: - Cesión de las pólizas de seguro contra incendios de las fincas hipotecadas a favor del Fiduciario. | T107: OK
A108: 2025 | B108: INA_GRMELO_2025_0.pdf | C108: page-43 | D108: markdown.md | E108: 1 | F108: 1. Información general | G108: Otros | J108: El total del Patrimonio del Fideicomiso es de B/.66,274,750 (2024: B/.66,274,750) de los cuales la suma de B/.66,274,750 (2024: B/.66,274,750) están conformados por el derecho real de hipoteca a favor del Fiduciario detallados en la Nota No.4. | K108: 66274750 | L108: B/. | T108: OK
A109: 2025 | B109: INA_GRMELO_2025_0.pdf | C109: page-43 | D109: markdown.md | E109: 1 | F109: 1. Información general | G109: Otros | J109: Al 31 de diciembre de 2025, la Cobertura de Garantía representa el 195% (2024: 195%), la cual resulta de dividir el valor de mercado de los bienes inmuebles hipotecados entre el saldo insoluto a capital de los Bonos emitidos y en circulación. | T109: OK
A110: 2025 | B110: INA_GRMELO_2025_0.pdf | C110: page-43 | D110: markdown.md | E110: 1 | F110: 1. Información general | G110: Otros | J110: El Fideicomiso estará vigente hasta la fecha en que todas las obligaciones garantizadas se extingan. | T110: OK
A111: 2025 | B111: INA_GRMELO_2025_0.pdf | C111: page-43 | D111: markdown.md | E111: 1 | F111: 1. Información general | G111: Otros | J111: La oficina principal de la Fiduciaria está localizada en Costa del Este, Avenida Paseo del Mar, PH MMG Tower, Piso 22, Ciudad de Panamá República de Panamá. | T111: OK
A112: 2025 | B112: INA_GRMELO_2025_0.pdf | C112: page-44 | D112: markdown.md | E112: 2 | F112: 2. Bases para la preparación de los estados financieros | G112: Otros | J112: ### 2.1. Base de medición | T112: OK
...

Sheet Supuestos
A1: Grupo Melo, S.A. y Subsidiarias
A3: COLOR KEY: Input (azul) · Fórmula (negro) · Link inter-hoja (verde)
A4: Escenario (1=Base, 2=Bull, 3=Bear)
A5: Selector escenario | C5: 1 | M5: caso | N5: NOT_DISCLOSED | Q5: Derivación mecánica declarada por el plan.
A6: Escenario activo | C6: =CHOOSE($C$5,"Base","Bull","Bear") -> Base | M6: moneda del modelo | N6: NOT_DISCLOSED | Q6: Selector de caso activo C5: Base/Bull/Bear.
A8: Años | B8: FY21A | C8: FY22A | D8: FY23A | E8: FY24A | F8: FY25A | G8: FY26E | H8: FY27E | I8: FY28E | J8: FY29E | K8: FY30E | M8: Unidad | N8: Fuente / nota | Q8: Rationale
A10: A. INGRESOS POR SEGMENTO — Nota 29 / Nota 7 (revenue_by_division.csv)
A11: Avícola / Alimentos — crecimiento activo | G11: =CHOOSE($C$5,G13,G14,G12) -> 0.007 | H11: =CHOOSE($C$5,H13,H14,H12) -> 0.007 | I11: =CHOOSE($C$5,I13,I14,I12) -> 0.007 | J11: =CHOOSE($C$5,J13,J14,J12) -> 0.007 | K11: =CHOOSE($C$5,K13,K14,K12) -> 0.007 | M11: % | N11: NOT_DISCLOSED | Q11: Selector de caso activo C5: Base/Bull/Bear.
A12: Bear | G12: -0.013 | H12: -0.013 | I12: -0.013 | J12: -0.013 | K12: -0.013 | M12: moneda del modelo | N12: NOT_DISCLOSED | Q12: Escenario driver citado; NOT_DISCLOSED si no hay fuente explícita.
A13: Base | G13: 0.007 | H13: 0.007 | I13: 0.007 | J13: 0.007 | K13: 0.007 | M13: moneda del modelo | N13: NOT_DISCLOSED | Q13: Escenario driver citado; NOT_DISCLOSED si no hay fuente explícita.
A14: Bull | G14: 0.027 | H14: 0.027 | I14: 0.027 | J14: 0.027 | K14: 0.027 | M14: moneda del modelo | N14: NOT_DISCLOSED | Q14: Escenario driver citado; NOT_DISCLOSED si no hay fuente explícita.
A15: Avícola / Alimentos — ingresos | B15: 173093792 | C15: 187726127 | D15: 187720897 | E15: 179519684 | F15: 180784387 | G15: =F15*(1+G11) -> 1.8204988e+08 | H15: =G15*(1+H11) -> 1.8332423e+08 | I15: =H15*(1+I11) -> 1.846075e+08 | J15: =I15*(1+J11) -> 1.8589975e+08 | K15: =J15*(1+K11) -> 1.8720105e+08 | M15: moneda del modelo | N15: NOT_DISCLOSED | Q15: Derivación mecánica por fórmula viva.
A16: Almacenes — crecimiento activo | G16: =CHOOSE($C$5,G18,G19,G17) -> 0.009 | H16: =CHOOSE($C$5,H18,H19,H17) -> 0.009 | I16: =CHOOSE($C$5,I18,I19,I17) -> 0.009 | J16: =CHOOSE($C$5,J18,J19,J17) -> 0.009 | K16: =CHOOSE($C$5,K18,K19,K17) -> 0.009 | M16: % | N16: NOT_DISCLOSED | Q16: Selector de caso activo C5: Base/Bull/Bear.
A17: Bear | G17: -0.011 | H17: -0.011 | I17: -0.011 | J17: -0.011 | K17: -0.011 | M17: moneda del modelo | N17: NOT_DISCLOSED | Q17: Escenario driver citado; NOT_DISCLOSED si no hay fuente explícita.
A18: Base | G18: 0.009 | H18: 0.009 | I18: 0.009 | J18: 0.009 | K18: 0.009 | M18: moneda del modelo | N18: NOT_DISCLOSED | Q18: Escenario driver citado; NOT_DISCLOSED si no hay fuente explícita.
A19: Bull | G19: 0.029 | H19: 0.029 | I19: 0.029 | J19: 0.029 | K19: 0.029 | M19: moneda del modelo | N19: NOT_DISCLOSED | Q19: Escenario driver citado; NOT_DISCLOSED si no hay fuente explícita.
A20: Almacenes — ingresos | B20: 175999106 | C20: 167727756 | D20: 146014874 | E20: 143014423 | F20: 144232867 | G20: =F20*(1+G16) -> 1.4553096e+08 | H20: =G20*(1+H16) -> 1.4684074e+08 | I20: =H20*(1+I16) -> 1.4816231e+08 | J20: =I20*(1+J16) -> 1.4949577e+08 | K20: =J20*(1+K16) -> 1.5084123e+08 | M20: moneda del modelo | N20: NOT_DISCLOSED | Q20: Derivación mecánica por fórmula viva.
A21: Maquinaria / Motors — crecimiento activo | G21: =CHOOSE($C$5,G23,G24,G22) -> 0.056 | H21: =CHOOSE($C$5,H23,H24,H22) -> 0.056 | I21: =CHOOSE($C$5,I23,I24,I22) -> 0.056 | J21: =CHOOSE($C$5,J23,J24,J22) -> 0.056 | K21: =CHOOSE($C$5,K23,K24,K22) -> 0.056 | M21: % | N21: NOT_DISCLOSED | Q21: Selector de caso activo C5: Base/Bull/Bear.
A22: Bear | G22: 0.036 | H22: 0.036 | I22: 0.036 | J22: 0.036 | K22: 0.036 | M22: moneda del modelo | N22: NOT_DISCLOSED | Q22: Escenario driver citado; NOT_DISCLOSED si no hay fuente explícita.
A23: Base | G23: 0.056 | H23: 0.056 | I23: 0.056 | J23: 0.056 | K23: 0.056 | M23: moneda del modelo | N23: NOT_DISCLOSED | Q23: Escenario driver citado; NOT_DISCLOSED si no hay fuente explícita.
A24: Bull | G24: 0.076 | H24: 0.076 | I24: 0.076 | J24: 0.076 | K24: 0.076 | M24: moneda del modelo | N24: NOT_DISCLOSED | Q24: Escenario driver citado; NOT_DISCLOSED si no hay fuente explícita.
A25: Maquinaria / Motors — ingresos | B25: 61483016 | C25: 76982373 | D25: 76432292 | E25: 90672130 | F25: 95723653 | G25: =F25*(1+G21) -> 1.0108418e+08 | H25: =G25*(1+H21) -> 1.0674489e+08 | I25: =H25*(1+I21) -> 1.1272261e+08 | J25: =I25*(1+J21) -> 1.1903507e+08 | K25: =J25*(1+K21) -> 1.2570104e+08 | M25: moneda del modelo | N25: NOT_DISCLOSED | Q25: Derivación mecánica por fórmula viva.
A26: Restaurantes — crecimiento activo | G26: =CHOOSE($C$5,G28,G29,G27) -> 0.019 | H26: =CHOOSE($C$5,H28,H29,H27) -> 0.019 | I26: =CHOOSE($C$5,I28,I29,I27) -> 0.019 | J26: =CHOOSE($C$5,J28,J29,J27) -> 0.019 | K26: =CHOOSE($C$5,K28,K29,K27) -> 0.019 | M26: % | N26: NOT_DISCLOSED | Q26: Selector de caso activo C5: Base/Bull/Bear.
A27: Bear | G27: -0.001 | H27: -0.001 | I27: -0.001 | J27: -0.001 | K27: -0.001 | M27: moneda del modelo | N27: NOT_DISCLOSED | Q27: Escenario driver citado; NOT_DISCLOSED si no hay fuente explícita.
A28: Base | G28: 0.019 | H28: 0.019 | I28: 0.019 | J28: 0.019 | K28: 0.019 | M28: moneda del modelo | N28: NOT_DISCLOSED | Q28: Escenario driver citado; NOT_DISCLOSED si no hay fuente explícita.
A29: Bull | G29: 0.039 | H29: 0.039 | I29: 0.039 | J29: 0.039 | K29: 0.039 | M29: moneda del modelo | N29: NOT_DISCLOSED | Q29: Escenario driver citado; NOT_DISCLOSED si no hay fuente explícita.
A30: Restaurantes — ingresos | B30: 29184102 | C30: 36401877 | D30: 43117879 | E30: 50683919 | F30: 51627691 | G30: =F30*(1+G26) -> 52608617 | H30: =G30*(1+H26) -> 53608181 | I30: =H30*(1+I26) -> 54626736 | J30: =I30*(1+J26) -> 55664644 | K30: =J30*(1+K26) -> 56722273 | M30: moneda del modelo | N30: NOT_DISCLOSED | Q30: Derivación mecánica por fórmula viva.
A31: Bienes Raíces — crecimiento activo | G31: =CHOOSE($C$5,G33,G34,G32) -> -0.265 | H31: =CHOOSE($C$5,H33,H34,H32) -> -0.265 | I31: =CHOOSE($C$5,I33,I34,I32) -> -0.265 | J31: =CHOOSE($C$5,J33,J34,J32) -> -0.265 | K31: =CHOOSE($C$5,K33,K34,K32) -> -0.265 | M31: % | N31: NOT_DISCLOSED | Q31: Selector de caso activo C5: Base/Bull/Bear.
A32: Bear | G32: -0.285 | H32: -0.285 | I32: -0.285 | J32: -0.285 | K32: -0.285 | M32: moneda del modelo | N32: NOT_DISCLOSED | Q32: Escenario driver citado; NOT_DISCLOSED si no hay fuente explícita.
A33: Base | G33: -0.265 | H33: -0.265 | I33: -0.265 | J33: -0.265 | K33: -0.265 | M33: moneda del modelo | N33: NOT_DISCLOSED | Q33: Escenario driver citado; NOT_DISCLOSED si no hay fuente explícita.
A34: Bull | G34: -0.245 | H34: -0.245 | I34: -0.245 | J34: -0.245 | K34: -0.245 | M34: moneda del modelo | N34: NOT_DISCLOSED | Q34: Escenario driver citado; NOT_DISCLOSED si no hay fuente explícita.
A35: Bienes Raíces — ingresos | B35: 6269641 | C35: 6102917 | D35: 6708500 | E35: 7126152 | F35: 5238261 | G35: =F35*(1+G31) -> 3850121.8 | H35: =G35*(1+H31) -> 2829839.5 | I35: =H35*(1+I31) -> 2079932.1 | J35: =I35*(1+J31) -> 1528750.1 | K35: =J35*(1+K31) -> 1123631.3 | M35: moneda del modelo | N35: NOT_DISCLOSED | Q35: Derivación mecánica por fórmula viva.
A36: Servicios — ingresos externos | B36: 497251 | C36: 535327 | D36: 442319 | E36: 270457 | F36: 0 | G36: 0 | H36: 0 | I36: 0 | J36: 0 | K36: 0 | M36: moneda del modelo | N36: NOT_DISCLOSED | Q36: Derivación mecánica declarada por el plan.
A37: Ingresos consolidados — suma segmentos | B37: =B15+B20+B25+B30+B35+B36 -> 446526908 | C37: =C15+C20+C25+C30+C35+C36 -> 475476377 | D37: =D15+D20+D25+D30+D35+D36 -> 460436761 | E37: =E15+E20+E25+E30+E35+E36 -> 471286765 | F37: =F15+F20+F25+F30+F35+F36 -> 477606859 | G37: =G15+G20+G25+G30+G35+G36 -> 4.8512376e+08 | H37: =H15+H20+H25+H30+H35+H36 -> 4.9334788e+08 | I37: =I15+I20+I25+I30+I35+I36 -> 5.0219908e+08 | ... K37: =K15+K20+K25+K30+K35+K36 -> 5.2158922e+08 | M37: moneda del modelo | N37: NOT_DISCLOSED | Q37: Suma mecánica del bloque.
A39: B. COSTOS E IMPUESTOS — ratios activos sobre FY25 auditado
A40: Cambio inventario / ingresos — driver activo | G40: =CHOOSE($C$5,G42,G43,G41) -> -0.3865 | H40: =CHOOSE($C$5,H42,H43,H41) -> -0.3865 | I40: =CHOOSE($C$5,I42,I43,I41) -> -0.3865 | J40: =CHOOSE($C$5,J42,J43,J41) -> -0.3865 | K40: =CHOOSE($C$5,K42,K43,K41) -> -0.3865 | M40: moneda del modelo | N40: NOT_DISCLOSED | Q40: Selector de caso activo C5: Base/Bull/Bear.
A41: Bear | G41: -0.3965 | H41: -0.3965 | I41: -0.3965 | J41: -0.3965 | K41: -0.3965 | M41: moneda del modelo | N41: NOT_DISCLOSED | Q41: Escenario driver citado; NOT_DISCLOSED si no hay fuente explícita.
A42: Base | G42: -0.3865 | H42: -0.3865 | I42: -0.3865 | J42: -0.3865 | K42: -0.3865 | M42: moneda del modelo | N42: NOT_DISCLOSED | Q42: Escenario driver citado; NOT_DISCLOSED si no hay fuente explícita.
A43: Bull | G43: -0.3765 | H43: -0.3765 | I43: -0.3765 | J43: -0.3765 | K43: -0.3765 | M43: moneda del modelo | N43: NOT_DISCLOSED | Q43: Escenario driver citado; NOT_DISCLOSED si no hay fuente explícita.
A44: Materia prima / ingresos — driver activo | G44: =CHOOSE($C$5,G46,G47,G45) -> -0.1635 | H44: =CHOOSE($C$5,H46,H47,H45) -> -0.1635 | I44: =CHOOSE($C$5,I46,I47,I45) -> -0.1635 | J44: =CHOOSE($C$5,J46,J47,J45) -> -0.1635 | K44: =CHOOSE($C$5,K46,K47,K45) -> -0.1635 | M44: moneda del modelo | N44: NOT_DISCLOSED | Q44: Selector de caso activo C5: Base/Bull/Bear.
A45: Bear | G45: -0.1735 | H45: -0.1735 | I45: -0.1735 | J45: -0.1735 | K45: -0.1735 | M45: moneda del modelo | N45: NOT_DISCLOSED | Q45: Escenario driver citado; NOT_DISCLOSED si no hay fuente explícita.
A46: Base | G46: -0.1635 | H46: -0.1635 | I46: -0.1635 | J46: -0.1635 | K46: -0.1635 | M46: moneda del modelo | N46: NOT_DISCLOSED | Q46: Escenario driver citado; NOT_DISCLOSED si no hay fuente explícita.
A47: Bull | G47: -0.1535 | H47: -0.1535 | I47: -0.1535 | J47: -0.1535 | K47: -0.1535 | M47: moneda del modelo | N47: NOT_DISCLOSED | Q47: Escenario driver citado; NOT_DISCLOSED si no hay fuente explícita.
A48: Personal / ingresos — driver activo | G48: =CHOOSE($C$5,G50,G51,G49) -> -0.1937 | H48: =CHOOSE($C$5,H50,H51,H49) -> -0.1937 | I48: =CHOOSE($C$5,I50,I51,I49) -> -0.1937 | J48: =CHOOSE($C$5,J50,J51,J49) -> -0.1937 | K48: =CHOOSE($C$5,K50,K51,K49) -> -0.1937 | M48: moneda del modelo | N48: NOT_DISCLOSED | Q48: Selector de caso activo C5: Base/Bull/Bear.
A49: Bear | G49: -0.2037 | H49: -0.2037 | I49: -0.2037 | J49: -0.2037 | K49: -0.2037 | M49: moneda del modelo | N49: NOT_DISCLOSED | Q49: Escenario driver citado; NOT_DISCLOSED si no hay fuente explícita.
A50: Base | G50: -0.1937 | H50: -0.1937 | I50: -0.1937 | J50: -0.1937 | K50: -0.1937 | M50: moneda del modelo | N50: NOT_DISCLOSED | Q50: Escenario driver citado; NOT_DISCLOSED si no hay fuente explícita.
A51: Bull | G51: -0.1837 | H51: -0.1837 | I51: -0.1837 | J51: -0.1837 | K51: -0.1837 | M51: moneda del modelo | N51: NOT_DISCLOSED | Q51: Escenario driver citado; NOT_DISCLOSED si no hay fuente explícita.
A52: D&A PP&E / ingresos — driver activo | G52: =CHOOSE($C$5,G54,G55,G53) -> -0.0334 | H52: =CHOOSE($C$5,H54,H55,H53) -> -0.0334 | I52: =CHOOSE($C$5,I54,I55,I53) -> -0.0334 | J52: =CHOOSE($C$5,J54,J55,J53) -> -0.0334 | K52: =CHOOSE($C$5,K54,K55,K53) -> -0.0334 | M52: moneda del modelo | N52: NOT_DISCLOSED | Q52: Selector de caso activo C5: Base/Bull/Bear.
A53: Bear | G53: -0.0434 | H53: -0.0434 | I53: -0.0434 | J53: -0.0434 | K53: -0.0434 | M53: moneda del modelo | N53: NOT_DISCLOSED | Q53: Escenario driver citado; NOT_DISCLOSED si no hay fuente explícita.
A54: Base | G54: -0.0334 | H54: -0.0334 | I54: -0.0334 | J54: -0.0334 | K54: -0.0334 | M54: moneda del modelo | N54: NOT_DISCLOSED | Q54: Escenario driver citado; NOT_DISCLOSED si no hay fuente explícita.
A55: Bull | G55: -0.0234 | H55: -0.0234 | I55: -0.0234 | J55: -0.0234 | K55: -0.0234 | M55: moneda del modelo | N55: NOT_DISCLOSED | Q55: Escenario driver citado; NOT_DISCLOSED si no hay fuente explícita.
A56: D&A derecho de uso / ingresos — driver activo | G56: =CHOOSE($C$5,G58,G59,G57) -> -0.0117 | H56: =CHOOSE($C$5,H58,H59,H57) -> -0.0117 | I56: =CHOOSE($C$5,I58,I59,I57) -> -0.0117 | J56: =CHOOSE($C$5,J58,J59,J57) -> -0.0117 | K56: =CHOOSE($C$5,K58,K59,K57) -> -0.0117 | M56: moneda del modelo | N56: NOT_DISCLOSED | Q56: Selector de caso activo C5: Base/Bull/Bear.
A57: Bear | G57: -0.0217 | H57: -0.0217 | I57: -0.0217 | J57: -0.0217 | K57: -0.0217 | M57: moneda del modelo | N57: NOT_DISCLOSED | Q57: Escenario driver citado; NOT_DISCLOSED si no hay fuente explícita.
A58: Base | G58: -0.0117 | H58: -0.0117 | I58: -0.0117 | J58: -0.0117 | K58: -0.0117 | M58: moneda del modelo | N58: NOT_DISCLOSED | Q58: Escenario driver citado; NOT_DISCLOSED si no hay fuente explícita.
A59: Bull | G59: -0.0017 | H59: -0.0017 | I59: -0.0017 | J59: -0.0017 | K59: -0.0017 | M59: moneda del modelo | N59: NOT_DISCLOSED | Q59: Escenario driver citado; NOT_DISCLOSED si no hay fuente explícita.
A60: Otros gastos / ingresos — driver activo | G60: =CHOOSE($C$5,G62,G63,G61) -> -0.1688 | H60: =CHOOSE($C$5,H62,H63,H61) -> -0.1688 | I60: =CHOOSE($C$5,I62,I63,I61) -> -0.1688 | J60: =CHOOSE($C$5,J62,J63,J61) -> -0.1688 | K60: =CHOOSE($C$5,K62,K63,K61) -> -0.1688 | M60: moneda del modelo | N60: NOT_DISCLOSED | Q60: Selector de caso activo C5: Base/Bull/Bear.
A61: Bear | G61: -0.1788 | H61: -0.1788 | I61: -0.1788 | J61: -0.1788 | K61: -0.1788 | M61: moneda del modelo | N61: NOT_DISCLOSED | Q61: Escenario driver citado; NOT_DISCLOSED si no hay fuente explícita.
A62: Base | G62: -0.1688 | H62: -0.1688 | I62: -0.1688 | J62: -0.1688 | K62: -0.1688 | M62: moneda del modelo | N62: NOT_DISCLOSED | Q62: Escenario driver citado; NOT_DISCLOSED si no hay fuente explícita.
A63: Bull | G63: -0.1588 | H63: -0.1588 | I63: -0.1588 | J63: -0.1588 | K63: -0.1588 | M63: moneda del modelo | N63: NOT_DISCLOSED | Q63: Escenario driver citado; NOT_DISCLOSED si no hay fuente explícita.
A64: Tasa efectiva de impuesto — driver activo | G64: =CHOOSE($C$5,G66,G67,G65) -> -0.2438 | H64: =CHOOSE($C$5,H66,H67,H65) -> -0.2438 | I64: =CHOOSE($C$5,I66,I67,I65) -> -0.2438 | J64: =CHOOSE($C$5,J66,J67,J65) -> -0.2438 | K64: =CHOOSE($C$5,K66,K67,K65) -> -0.2438 | M64: % | N64: NOT_DISCLOSED | Q64: Selector de caso activo C5: Base/Bull/Bear.
A65: Bear | G65: -0.2538 | H65: -0.2538 | I65: -0.2538 | J65: -0.2538 | K65: -0.2538 | M65: moneda del modelo | N65: NOT_DISCLOSED | Q65: Escenario driver citado; NOT_DISCLOSED si no hay fuente explícita.
A66: Base | G66: -0.2438 | H66: -0.2438 | I66: -0.2438 | J66: -0.2438 | K66: -0.2438 | M66: moneda del modelo | N66: NOT_DISCLOSED | Q66: Escenario driver citado; NOT_DISCLOSED si no hay fuente explícita.
A67: Bull | G67: -0.2338 | H67: -0.2338 | I67: -0.2338 | J67: -0.2338 | K67: -0.2338 | M67: moneda del modelo | N67: NOT_DISCLOSED | Q67: Escenario driver citado; NOT_DISCLOSED si no hay fuente explícita.

Sheet ModeloFinanciero
A1: Grupo Melo, S.A. y Subsidiarias
A2: Estados Financieros Consolidados Auditados FY21-FY25
A3: en B/. sin escala
A5: Años | B5: FY21A | C5: FY22A | D5: FY23A | E5: FY24A | F5: FY25A | G5: FY26E | H5: FY27E | I5: FY28E | J5: FY29E | K5: FY30E
A6: Estado Consolidado de Resultados y Otros Resultados Integrales
A7: Ingresos de actividades ordinarias | B7: =EEFF!B7 -> 446526908 | C7: =EEFF!C7 -> 475476377 | D7: =EEFF!D7 -> 460436761 | E7: =EEFF!E7 -> 471286765 | F7: =EEFF!F7 -> 477606859 | G7: =Supuestos!G37 -> 4.8512376e+08 | H7: =Supuestos!H37 -> 4.9334788e+08 | I7: =Supuestos!I37 -> 5.0219908e+08 | J7: =Supuestos!J37 -> 5.1162398e+08 | K7: =Supuestos!K37 -> 5.2158922e+08
A8: Otros ingresos | B8: =EEFF!B8 -> 4324870 | C8: =EEFF!C8 -> 3967649 | D8: =EEFF!D8 -> 10430308 | E8: =EEFF!E8 -> 3049990 | F8: =EEFF!F8 -> 3273534 | G8: =F8 -> 3273534 | H8: =G8 -> 3273534 | I8: =H8 -> 3273534 | J8: =I8 -> 3273534 | K8: =J8 -> 3273534
A9: Cambios en el inventario de mercancía, productos terminados, en proceso y otros | B9: =EEFF!B9 -> -151521675 | C9: =EEFF!C9 -> -187725448 | D9: =EEFF!D9 -> -172601924 | E9: =EEFF!E9 -> -172621803 | F9: =EEFF!F9 -> -184583589 | G9: =G7*Supuestos!G40 -> -1.8750033e+08 | H9: =H7*Supuestos!H40 -> -1.9067896e+08 | I9: =I7*Supuestos!I40 -> -1.9409994e+08 | J9: =J7*Supuestos!J40 -> -1.9774267e+08 | K9: =K7*Supuestos!K40 -> -2.0159423e+08
A10: Consumo de materia prima y materiales usados | B10: =EEFF!B10 -> -101910296 | C10: =EEFF!C10 -> -91798432 | D10: =EEFF!D10 -> -85551297 | E10: =EEFF!E10 -> -86117863 | F10: =EEFF!F10 -> -78107263 | G10: =G7*Supuestos!G44 -> -79317734 | H10: =H7*Supuestos!H44 -> -80662378 | I10: =I7*Supuestos!I44 -> -82109549 | J10: =J7*Supuestos!J44 -> -83650521 | K10: =K7*Supuestos!K44 -> -85279837
A11: Gastos de personal | B11: =EEFF!B11 -> -78191068 | C11: =EEFF!C11 -> -82630079 | D11: =EEFF!D11 -> -84367143 | E11: =EEFF!E11 -> -90003575 | F11: =EEFF!F11 -> -92534638 | G11: =G7*Supuestos!G48 -> -93968472 | H11: =H7*Supuestos!H48 -> -95561484 | I11: =I7*Supuestos!I48 -> -97275961 | J11: =J7*Supuestos!J48 -> -99101566 | K11: =K7*Supuestos!K48 -> -1.0103183e+08
A12: Depreciación y amortización | B12: =EEFF!B12 -> -14499892 | C12: =EEFF!C12 -> -13788592 | D12: =EEFF!D12 -> -14598107 | E12: =EEFF!E12 -> -15421420 | F12: =EEFF!F12 -> -15968601 | G12: =G7*Supuestos!G52 -> -16203133 | H12: =H7*Supuestos!H52 -> -16477819 | I12: =I7*Supuestos!I52 -> -16773449 | J12: =J7*Supuestos!J52 -> -17088241 | K12: =K7*Supuestos!K52 -> -17421080
A13: Depreciación activos derecho de uso | B13: =EEFF!B13 -> -4281088 | C13: =EEFF!C13 -> -4141096 | D13: =EEFF!D13 -> -3853656 | E13: =EEFF!E13 -> -4881754 | F13: =EEFF!F13 -> -5584457 | G13: =G7*Supuestos!G56 -> -5675948 | H13: =H7*Supuestos!H56 -> -5772170.2 | I13: =I7*Supuestos!I56 -> -5875729.2 | J13: =J7*Supuestos!J56 -> -5986000.6 | K13: =K7*Supuestos!K56 -> -6102593.8
A14: Pérdida crediticia esperada | B14: =EEFF!B14 -> -926879 | C14: =EEFF!C14 -> -767688 | D14: =EEFF!D14 -> -1432537 | E14: =EEFF!E14 -> -1418031 | F14: =EEFF!F14 -> -455297 | G14: =F14 -> -455297 | H14: =G14 -> -455297 | I14: =H14 -> -455297 | J14: =I14 -> -455297 | K14: =J14 -> -455297
A15: Otros gastos | B15: =EEFF!B15 -> -67772425 | C15: =EEFF!C15 -> -73044128 | D15: =EEFF!D15 -> -84424966 | E15: =EEFF!E15 -> -81815270 | F15: =EEFF!F15 -> -80604183 | G15: =G7*Supuestos!G60 -> -81888890 | H15: =H7*Supuestos!H60 -> -83277122 | I15: =I7*Supuestos!I60 -> -84771204 | J15: =J7*Supuestos!J60 -> -86362128 | K15: =K7*Supuestos!K60 -> -88044260
A16: Ganancia operativa | B16: =EEFF!B16 -> 31748455 | C16: =EEFF!C16 -> 25548563 | D16: =EEFF!D16 -> 24037439 | E16: =EEFF!E16 -> 22057039 | F16: =EEFF!F16 -> 23042365 | G16: =G7+G8+G9+G10+G11+G12+G13+G14+G15 -> 23387484 | H16: =H7+H8+H9+H10+H11+H12+H13+H14+H15 -> 23736187 | I16: =I7+I8+I9+I10+I11+I12+I13+I14+I15 -> 24111478 | J16: =J7+J8+J9+J10+J11+J12+J13+J14+J15 -> 24511094 | K16: =K7+K8+K9+K10+K11+K12+K13+K14+K15 -> 24933620
A17: Intereses y dividendos ganados | B17: =EEFF!B17 -> 1827169 | C17: =EEFF!C17 -> 2203898 | D17: =EEFF!D17 -> 1911252 | E17: =EEFF!E17 -> 2201801 | F17: =EEFF!F17 -> 2520005 | G17: =F17 -> 2520005 | H17: =G17 -> 2520005 | I17: =H17 -> 2520005 | J17: =I17 -> 2520005 | K17: =J17 -> 2520005
A18: Gastos de intereses pasivos por arrendamiento | B18: =EEFF!B18 -> -1003513 | C18: =EEFF!C18 -> -925031 | D18: =EEFF!D18 -> -830555 | E18: =EEFF!E18 -> -1006351 | F18: =EEFF!F18 -> -1199370 | G18: =F18 -> -1199370 | H18: =G18 -> -1199370 | I18: =H18 -> -1199370 | J18: =I18 -> -1199370 | K18: =J18 -> -1199370
A19: Gasto de intereses | B19: =EEFF!B19 -> -5077114 | C19: =EEFF!C19 -> -3585083 | D19: =EEFF!D19 -> -4658040 | E19: =EEFF!E19 -> -4941802 | F19: =EEFF!F19 -> -4478120 | G19: =F19 -> -4478120 | H19: =G19 -> -4478120 | I19: =H19 -> -4478120 | J19: =I19 -> -4478120 | K19: =J19 -> -4478120
A20: Costos financieros, neto | B20: =EEFF!B20 -> -4253458 | C20: =EEFF!C20 -> -2306216 | D20: =EEFF!D20 -> -3577343 | E20: =EEFF!E20 -> -3746352 | F20: =EEFF!F20 -> -3157485 | G20: =G17+G18+G19 -> -3157485 | H20: =H17+H18+H19 -> -3157485 | I20: =I17+I18+I19 -> -3157485 | J20: =J17+J18+J19 -> -3157485 | K20: =K17+K18+K19 -> -3157485
A21: Participación en resultados de asociadas | B21: =EEFF!B21 -> 1026225 | C21: =EEFF!C21 -> 1366177 | D21: =EEFF!D21 -> 1650460 | E21: =EEFF!E21 -> 1225747 | F21: =EEFF!F21 -> 1203147 | G21: =F21 -> 1203147 | H21: =G21 -> 1203147 | I21: =H21 -> 1203147 | J21: =I21 -> 1203147 | K21: =J21 -> 1203147
A22: Utilidad antes del impuesto sobre la renta | B22: =EEFF!B22 -> 28521222 | C22: =EEFF!C22 -> 24608524 | D22: =EEFF!D22 -> 22110556 | E22: =EEFF!E22 -> 19536434 | F22: =EEFF!F22 -> 21088027 | G22: =G16+G20+G21 -> 21433146 | H22: =H16+H20+H21 -> 21781849 | I22: =I16+I20+I21 -> 22157140 | J22: =J16+J20+J21 -> 22556756 | K22: =K16+K20+K21 -> 22979282
A23: Impuesto sobre la renta | B23: =EEFF!B23 -> -7315922 | C23: =EEFF!C23 -> -6603590 | D23: =EEFF!D23 -> -4017612 | E23: =EEFF!E23 -> -5061963 | F23: =EEFF!F23 -> -5141262 | G23: =G22*Supuestos!G64 -> -5225401.1 | H23: =H22*Supuestos!H64 -> -5310414.8 | I23: =I22*Supuestos!I64 -> -5401910.7 | J23: =J22*Supuestos!J64 -> -5499337.1 | K23: =K22*Supuestos!K64 -> -5602348.9
A24: Utilidad neta | B24: =EEFF!B24 -> 21205300 | C24: =EEFF!C24 -> 18004934 | D24: =EEFF!D24 -> 18092944 | E24: =EEFF!E24 -> 14474471 | F24: =EEFF!F24 -> 15946765 | G24: =G22+G23 -> 16207745 | H24: =H22+H23 -> 16471434 | I24: =I22+I23 -> 16755229 | J24: =J22+J23 -> 17057419 | K24: =K22+K23 -> 17376933
A25: Reserva para conversión de moneda extranjera | B25: =EEFF!B25 -> -84705 | C25: =EEFF!C25 -> 107709 | D25: =EEFF!D25 -> 321093 | E25: =EEFF!E25 -> 79637 | F25: =EEFF!F25 -> 14817 | G25: =F25 -> 14817 | H25: =G25 -> 14817 | I25: =H25 -> 14817 | J25: =I25 -> 14817 | K25: =J25 -> 14817
A26: Total de otros resultados integrales | B26: =EEFF!B26 -> -84705 | C26: =EEFF!C26 -> 107709 | D26: =EEFF!D26 -> 321093 | E26: =EEFF!E26 -> 79637 | F26: =EEFF!F26 -> 14817 | G26: =G25 -> 14817 | H26: =H25 -> 14817 | I26: =I25 -> 14817 | J26: =J25 -> 14817 | K26: =K25 -> 14817
A27: Total de resultados integrales | B27: =EEFF!B27 -> 21120595 | C27: =EEFF!C27 -> 18112643 | D27: =EEFF!D27 -> 18414037 | E27: =EEFF!E27 -> 14554108 | F27: =EEFF!F27 -> 15961582 | G27: =G24+G26 -> 16222562 | H27: =H24+H26 -> 16486251 | I27: =I24+I26 -> 16770046 | J27: =J24+J26 -> 17072236 | K27: =K24+K26 -> 17391750
A29: Años | B29: FY21A | C29: FY22A | D29: FY23A | E29: FY24A | F29: FY25A | G29: FY26E | H29: FY27E | I29: FY28E | J29: FY29E | K29: FY30E
A30: Estado Consolidado de Situación Financiera
A31: Efectivo conciliado (puente conciliación: efectivo BS - plazo fijo) | B31: =B33 -> 14137059 | C31: =C33 -> 10248083 | D31: =D33 -> 13933186 | E31: =E33-E32 -> 12627619 | F31: =F33-F32 -> 13421098 | G31: =G33-G32 -> 13421098 | H31: =H33-H32 -> 13421098 | I31: =I33-I32 -> 13421098 | J31: =J33-J32 -> 13421098 | K31: =K33-K32 -> 13421098
A32: Depósitos a plazo fijo incluidos en efectivo BS (saldo corriente; fuente Nota 8: GRMELO_2024 lines 5193-5199; GRMELO_2025 lines 5311-5317; parsed EEFF BS rows 61/73/91, CF rows 180/240) | E32: =2000000 -> 2000000 | F32: =8000000 -> 8000000 | G32: =F32 -> 8000000 | H32: =G32 -> 8000000 | I32: =H32 -> 8000000 | J32: =I32 -> 8000000 | K32: =J32 -> 8000000
A33: Efectivo y equivalentes de efectivo | B33: =EEFF!B31 -> 14137059 | C33: =EEFF!C31 -> 10248083 | D33: =EEFF!D31 -> 13933186 | E33: =EEFF!E31 -> 14627619 | F33: =EEFF!F31 -> 21421098 | G33: =F33 -> 21421098 | H33: =G33 -> 21421098 | I33: =H33 -> 21421098 | J33: =I33 -> 21421098 | K33: =J33 -> 21421098
A34: Documentos y cuentas por cobrar, neto | B34: =EEFF!B32 -> 55987713 | C34: =EEFF!C32 -> 55396562 | D34: =EEFF!D32 -> 50598758 | E34: =EEFF!E32 -> 48881564 | F34: =EEFF!F32 -> 47635856 | G34: =F34 -> 47635856 | H34: =G34 -> 47635856 | I34: =H34 -> 47635856 | J34: =I34 -> 47635856 | K34: =J34 -> 47635856
A35: Inventarios | B35: =EEFF!B33 -> 88215721 | C35: =EEFF!C33 -> 105854774 | D35: =EEFF!D33 -> 106547752 | E35: =EEFF!E33 -> 98584841 | F35: =EEFF!F33 -> 86537964 | G35: =F35 -> 86537964 | H35: =G35 -> 86537964 | I35: =H35 -> 86537964 | J35: =I35 -> 86537964 | K35: =J35 -> 86537964
A36: Inventario de materiales, piezas y repuestos | B36: =EEFF!B34 -> 4368953 | C36: =EEFF!C34 -> 5522228 | D36: =EEFF!D34 -> 5650193 | E36: =EEFF!E34 -> 7019946 | F36: =EEFF!F34 -> 7379445 | G36: =F36 -> 7379445 | H36: =G36 -> 7379445 | I36: =H36 -> 7379445 | J36: =I36 -> 7379445 | K36: =J36 -> 7379445
A37: Lotes disponibles para la venta | B37: =EEFF!B35 -> 7437127 | C37: =EEFF!C35 -> 6714577 | D37: =EEFF!D35 -> 8088976 | E37: =EEFF!E35 -> 6759518 | F37: =EEFF!F35 -> 5876049 | G37: =F37 -> 5876049 | H37: =G37 -> 5876049 | I37: =H37 -> 5876049 | J37: =I37 -> 5876049 | K37: =J37 -> 5876049
A38: Activos biológicos | B38: =EEFF!B36 -> 9533860 | C38: =EEFF!C36 -> 10662082 | D38: =EEFF!D36 -> 9971872 | E38: =EEFF!E36 -> 7465217 | F38: =EEFF!F36 -> 8437671 | G38: =F38 -> 8437671 | H38: =G38 -> 8437671 | I38: =H38 -> 8437671 | J38: =I38 -> 8437671 | K38: =J38 -> 8437671
A39: Adelantos para compras de inventarios y granos | B39: =EEFF!B37 -> 6253970 | C39: =EEFF!C37 -> 4940077 | D39: =EEFF!D37 -> 11953319 | E39: =EEFF!E37 -> 15363019 | F39: =EEFF!F37 -> 20196108 | G39: =F39 -> 20196108 | H39: =G39 -> 20196108 | I39: =H39 -> 20196108 | J39: =I39 -> 20196108 | K39: =J39 -> 20196108
A40: Gastos pagados por adelantado | B40: =EEFF!B38 -> 3881243 | C40: =EEFF!C38 -> 9409729 | D40: =EEFF!D38 -> 2059074 | E40: =EEFF!E38 -> 1651119 | F40: =EEFF!F38 -> 1545541 | G40: =F40 -> 1545541 | H40: =G40 -> 1545541 | I40: =H40 -> 1545541 | J40: =I40 -> 1545541 | K40: =J40 -> 1545541
A41: Impuesto sobre la renta pagado por adelantado | B41: =EEFF!B39 -> 683093 | C41: =EEFF!C39 -> 2940162 | D41: =EEFF!D39 -> 3768331 | E41: =EEFF!E39 -> 828999 | F41: =EEFF!F39 -> 1992042 | G41: =F41 -> 1992042 | H41: =G41 -> 1992042 | I41: =H41 -> 1992042 | J41: =I41 -> 1992042 | K41: =J41 -> 1992042
A42: Otros activos | B42: =EEFF!B40 -> 339020 | C42: =EEFF!C40 -> 312728 | D42: =EEFF!D40 -> 123508 | E42: =EEFF!E40 -> 228031 | F42: =EEFF!F40 -> 239863 | G42: =F42 -> 239863 | H42: =G42 -> 239863 | I42: =H42 -> 239863 | J42: =I42 -> 239863 | K42: =J42 -> 239863
A43: Total de activos corrientes | B43: =EEFF!B41 -> 190837759 | C43: =EEFF!C41 -> 212001002 | D43: =EEFF!D41 -> 212694969 | E43: =EEFF!E41 -> 201409873 | F43: =EEFF!F41 -> 201261637 | G43: =F43 -> 201261637 | H43: =G43 -> 201261637 | I43: =H43 -> 201261637 | J43: =I43 -> 201261637 | K43: =J43 -> 201261637
A44: Efectivo y equivalentes de efectivo (no corriente) | B44: =EEFF!B42 -> 0 | C44: =EEFF!C42 -> 0 | D44: =EEFF!D42 -> 0 | E44: =EEFF!E42 -> 1400000 | F44: =EEFF!F42 -> 0 | G44: =F44 -> 0 | H44: =G44 -> 0 | I44: =H44 -> 0 | J44: =I44 -> 0 | K44: =J44 -> 0
... A65: Cuentas por pagar compañías relacionadas | B65: =EEFF!B63 -> 15200 | C65: =EEFF!C63 -> 248703 | D65: =EEFF!D63 -> 68927 | E65: =EEFF!E63 -> 0 | F65: =EEFF!F63 -> 42296 | G65: =F65 -> 42296 | H65: =G65 -> 42296 | I65: =H65 -> 42296 | J65: =I65 -> 42296 | K65: =J65 -> 42296
A66: Impuesto sobre la renta por pagar | B66: =EEFF!B64 -> 2908783 | C66: =EEFF!C64 -> 0 | D66: =EEFF!D64 -> 0 | E66: =EEFF!E64 -> 0 | F66: =EEFF!F64 -> 0
A67: Gastos acumulados y otros pasivos | B67: =EEFF!B65 -> 7121789 | C67: =EEFF!C65 -> 7040115 | D67: =EEFF!D65 -> 7090627 | E67: =EEFF!E65 -> 7903342 | F67: =EEFF!F65 -> 7308891 | G67: =F67 -> 7308891 | H67: =G67 -> 7308891 | I67: =H67 -> 7308891 | J67: =I67 -> 7308891 | K67: =J67 -> 7308891
A68: Total de pasivos corrientes | B68: =EEFF!B66 -> 90409174 | C68: =EEFF!C66 -> 86465847 | D68: =EEFF!D66 -> 81870978 | E68: =EEFF!E66 -> 71191745 | F68: =EEFF!F66 -> 70600588 | G68: =F68 -> 70600588 | H68: =G68 -> 70600588 | I68: =H68 -> 70600588 | J68: =I68 -> 70600588 | K68: =J68 -> 70600588
A69: Préstamos por pagar (no corriente) | B69: =EEFF!B67 -> 0 | C69: =EEFF!C67 -> 0 | D69: =EEFF!D67 -> 0 | E69: =EEFF!E67 -> 2124600 | F69: =EEFF!F67 -> 2124600 | G69: =F69 -> 2124600 | H69: =G69 -> 2124600 | I69: =H69 -> 2124600 | J69: =I69 -> 2124600 | K69: =J69 -> 2124600
A70: Bonos por pagar | B70: =EEFF!B68 -> 52466986 | C70: =EEFF!C68 -> 67427589 | D70: =EEFF!D68 -> 67388899 | E70: =EEFF!E68 -> 62350209 | F70: =EEFF!F68 -> 52311519 | G70: =F70 -> 52311519 | H70: =G70 -> 52311519 | I70: =H70 -> 52311519 | J70: =I70 -> 52311519 | K70: =J70 -> 52311519
A71: Pasivos por arrendamiento (no corriente) | B71: =EEFF!B69 -> 14331670 | C71: =EEFF!C69 -> 14277496 | D71: =EEFF!D69 -> 13594963 | E71: =EEFF!E69 -> 15912188 | F71: =EEFF!F69 -> 15961760 | G71: =F71 -> 15961760 | H71: =G71 -> 15961760 | I71: =H71 -> 15961760 | J71: =I71 -> 15961760 | K71: =J71 -> 15961760
A72: Provisión para prima de antigüedad | B72: =EEFF!B70 -> 9477255 | C72: =EEFF!C70 -> 10127829 | D72: =EEFF!D70 -> 10407453 | E72: =EEFF!E70 -> 10739857 | F72: =EEFF!F70 -> 10998227 | G72: =F72 -> 10998227 | H72: =G72 -> 10998227 | I72: =H72 -> 10998227 | J72: =I72 -> 10998227 | K72: =J72 -> 10998227
A73: Total de pasivos no corrientes | B73: =EEFF!B71 -> 76275911 | C73: =EEFF!C71 -> 91832914 | D73: =EEFF!D71 -> 91391315 | E73: =EEFF!E71 -> 91126854 | F73: =EEFF!F71 -> 81396106 | G73: =F73 -> 81396106 | H73: =G73 -> 81396106 | I73: =H73 -> 81396106 | J73: =I73 -> 81396106 | K73: =J73 -> 81396106
A74: Total de pasivos | B74: =EEFF!B72 -> 166685085 | C74: =EEFF!C72 -> 178298761 | D74: =EEFF!D72 -> 173262293 | E74: =EEFF!E72 -> 162318599 | F74: =EEFF!F72 -> 151996694 | G74: =F74 -> 151996694 | H74: =G74 -> 151996694 | I74: =H74 -> 151996694 | J74: =I74 -> 151996694 | K74: =J74 -> 151996694
A75: Capital emitido: acciones comunes, sin valor nominal | B75: =EEFF!B73 -> 45813813 | C75: =EEFF!C73 -> 45813813 | D75: =EEFF!D73 -> 45077843 | E75: =EEFF!E73 -> 44725993 | F75: =EEFF!F73 -> 44553868 | G75: =F75 -> 44553868 | H75: =G75 -> 44553868 | I75: =H75 -> 44553868 | J75: =I75 -> 44553868 | K75: =J75 -> 44553868
A76: Utilidades no distribuidas | B76: =EEFF!B74 -> 165176872 | C76: =EEFF!C74 -> 174803519 | D76: =EEFF!D74 -> 183969668 | E76: =EEFF!E74 -> 190907552 | F76: =EEFF!F74 -> 201717520 | G76: =F76 -> 201717520 | H76: =G76 -> 201717520 | I76: =H76 -> 201717520 | J76: =I76 -> 201717520 | K76: =J76 -> 201717520
A77: Otros resultados integrales | B77: =EEFF!B75 -> 216328 | C77: =EEFF!C75 -> 324037 | D77: =EEFF!D75 -> 645130 | E77: =EEFF!E75 -> 724767 | F77: =EEFF!F75 -> 739584 | G77: =F77 -> 739584 | H77: =G77 -> 739584 | I77: =H77 -> 739584 | J77: =I77 -> 739584 | K77: =J77 -> 739584
A78: Total de patrimonio atribuible a los propietarios | B78: =EEFF!B76 -> 211207013 | C78: =EEFF!C76 -> 220941369 | D78: =EEFF!D76 -> 229692641 | E78: =EEFF!E76 -> 236358312 | F78: =EEFF!F76 -> 247010972 | G78: =F78 -> 247010972 | H78: =G78 -> 247010972 | I78: =H78 -> 247010972 | J78: =I78 -> 247010972 | K78: =J78 -> 247010972
... A81: Total de pasivos y patrimonio | B81: =EEFF!B79 -> 378167439 | C81: =EEFF!C79 -> 399511836 | D81: =EEFF!D79 -> 403280562 | E81: =EEFF!E79 -> 399064485 | F81: =EEFF!F79 -> 399350912 | G81: =F81 -> 399350912 | H81: =G81 -> 399350912 | I81: =H81 -> 399350912 | J81: =I81 -> 399350912 | K81: =J81 -> 399350912
A83: Años | B83: FY21A | C83: FY22A | D83: FY23A | E83: FY24A | F83: FY25A | G83: FY26E | H83: FY27E | I83: FY28E | J83: FY29E | K83: FY30E
A84: Estado Consolidado de Flujos de Efectivo
A85: Utilidad neta | B85: =EEFF!B83 -> 21205300 | C85: =EEFF!C83 -> 18004934 | D85: =EEFF!D83 -> 18092944 | E85: =EEFF!E83 -> 14474471 | F85: =EEFF!F83 -> 15946765 | G85: =F85 -> 15946765 | H85: =G85 -> 15946765 | I85: =H85 -> 15946765 | J85: =I85 -> 15946765 | K85: =J85 -> 15946765
A86: Participación en resultado de asociadas | B86: =EEFF!B84 -> -1026225 | C86: =EEFF!C84 -> -1366177 | D86: =EEFF!D84 -> -1650460 | E86: =EEFF!E84 -> -1225747 | F86: =EEFF!F84 -> -1203147 | G86: =F86 -> -1203147 | H86: =G86 -> -1203147 | I86: =H86 -> -1203147 | J86: =I86 -> -1203147 | K86: =J86 -> -1203147
A87: Depreciación y amortización de propiedad, equipo y mejoras | B87: =EEFF!B85 -> 13407970 | C87: =EEFF!C85 -> 12908124 | D87: =EEFF!D85 -> 13628603 | E87: =EEFF!E85 -> 13965491 | F87: =EEFF!F85 -> 14006514 | G87: =F87 -> 14006514 | H87: =G87 -> 14006514 | I87: =H87 -> 14006514 | J87: =I87 -> 14006514 | K87: =J87 -> 14006514
A88: Amortización de activo intangible | B88: =EEFF!B86 -> 0 | C88: =EEFF!C86 -> 0 | D88: =EEFF!D86 -> 0 | E88: =EEFF!E86 -> 191146 | F88: =EEFF!F86 -> 798172 | G88: =F88 -> 798172 | H88: =G88 -> 798172 | I88: =H88 -> 798172 | J88: =I88 -> 798172 | K88: =J88 -> 798172
A89: Depreciación de equipo para arrendamiento | B89: =EEFF!B87 -> 1091922 | C89: =EEFF!C87 -> 880468 | D89: =EEFF!D87 -> 973473 | E89: =EEFF!E87 -> 1264783 | F89: =EEFF!F87 -> 1163915 | G89: =F89 -> 1163915 | H89: =G89 -> 1163915 | I89: =H89 -> 1163915 | J89: =I89 -> 1163915 | K89: =J89 -> 1163915
A90: Depreciación de derecho de uso | B90: =EEFF!B88 -> 4281088 | C90: =EEFF!C88 -> 4141096 | D90: =EEFF!D88 -> 3853656 | E90: =EEFF!E88 -> 4881754 | F90: =EEFF!F88 -> 5084457 | G90: =F90 -> 5084457 | H90: =G90 -> 5084457 | I90: =H90 -> 5084457 | J90: =I90 -> 5084457 | K90: =J90 -> 5084457
A91: Pérdida en venta de activo fijo | B91: =EEFF!B89 -> 111753 | C91: =EEFF!C89 -> 78722 | D91: =EEFF!D89 -> -221006 | E91: =EEFF!E89 -> 7413 | F91: =EEFF!F89 -> 84328 | G91: =F91 -> 84328 | H91: =G91 -> 84328 | I91: =H91 -> 84328 | J91: =I91 -> 84328 | K91: =J91 -> 84328
A92: Ganancia por cancelación o acuerdos en derecho de uso | B92: =EEFF!B90 -> -720416 | C92: =EEFF!C90 -> -726549 | D92: =EEFF!D90 -> -45930 | E92: =EEFF!E90 -> -15073 | F92: =EEFF!F90 -> 0
A93: Pérdida en disposición de propiedad de inversión | B93: =EEFF!B91 -> 0 | C93: =EEFF!C91 -> 0 | D93: =EEFF!D91 -> 0 | E93: =EEFF!E91 -> 0 | F93: =EEFF!F91 -> 8000 | G93: =F93 -> 8000 | H93: =G93 -> 8000 | I93: =H93 -> 8000 | J93: =I93 -> 8000 | K93: =J93 -> 8000
A94: Ganancia en venta de valores | B94: =EEFF!B92 -> 0 | C94: =EEFF!C92 -> 0 | D94: =EEFF!D92 -> -6443146 | E94: =EEFF!E92 -> 0 | F94: =EEFF!F92 -> 0
A95: Provisión para prima de antigüedad | B95: =EEFF!B93 -> 1717272 | C95: =EEFF!C93 -> 2015167 | D95: =EEFF!D93 -> 1194818 | E95: =EEFF!E93 -> 1254843 | F95: =EEFF!F93 -> 1277252 | G95: =F95 -> 1277252 | H95: =G95 -> 1277252 | I95: =H95 -> 1277252 | J95: =I95 -> 1277252 | K95: =J95 -> 1277252
A96: Pérdida crediticia esperada | B96: =EEFF!B94 -> 0 | C96: =EEFF!C94 -> 0 | D96: =EEFF!D94 -> 1432537 | E96: =EEFF!E94 -> 1418031 | F96: =EEFF!F94 -> 455297 | G96: =F96 -> 455297 | H96: =G96 -> 455297 | I96: =H96 -> 455297 | J96: =I96 -> 455297 | K96: =J96 -> 455297
A97: Costos financieros, neto | B97: =EEFF!B95 -> 4253458 | C97: =EEFF!C95 -> 2306216 | D97: =EEFF!D95 -> 3577343 | E97: =EEFF!E95 -> 3746352 | F97: =EEFF!F95 -> 3157485 | G97: =F97 -> 3157485 | H97: =G97 -> 3157485 | I97: =H97 -> 3157485 | J97: =I97 -> 3157485 | K97: =J97 -> 3157485
A98: Impuesto sobre la renta | B98: =EEFF!B96 -> 7315922 | C98: =EEFF!C96 -> 6603590 | D98: =EEFF!D96 -> 4017612 | E98: =EEFF!E96 -> 5061963 | F98: =EEFF!F96 -> 5141262 | G98: =F98 -> 5141262 | H98: =G98 -> 5141262 | I98: =H98 -> 5141262 | J98: =I98 -> 5141262 | K98: =J98 -> 5141262
A99: Documentos y cuentas por cobrar | B99: =EEFF!B97 -> -4692774 | C99: =EEFF!C97 -> 1133921 | D99: =EEFF!D97 -> 5956108 | E99: =EEFF!E97 -> 4365 | F99: =EEFF!F97 -> 1120956 | G99: =F99 -> 1120956 | H99: =G99 -> 1120956 | I99: =H99 -> 1120956 | J99: =I99 -> 1120956 | K99: =J99 -> 1120956
A100: Inventarios | B100: =EEFF!B98 -> -12146830 | C100: =EEFF!C98 -> -17465207 | D100: =EEFF!D98 -> -1051273 | E100: =EEFF!E98 -> 8766185 | F100: =EEFF!F98 -> 13354407 | G100: =F100 -> 13354407 | H100: =G100 -> 13354407 | I100: =H100 -> 13354407 | J100: =I100 -> 13354407 | K100: =J100 -> 13354407
A101: Inventario de materiales, piezas y repuestos | B101: =EEFF!B99 -> -33995 | C101: =EEFF!C99 -> -1194043 | D101: =EEFF!D99 -> -56893 | E101: =EEFF!E99 -> -1963541 | F101: =EEFF!F99 -> -337453 | G101: =F101 -> -337453 | H101: =G101 -> -337453 | I101: =H101 -> -337453 | J101: =I101 -> -337453 | K101: =J101 -> -337453
A102: Lotes disponibles para la venta | B102: =EEFF!B100 -> 816657 | C102: =EEFF!C100 -> 722550 | D102: =EEFF!D100 -> 1098461 | E102: =EEFF!E100 -> 1329458 | F102: =EEFF!F100 -> 883469 | G102: =F102 -> 883469 | H102: =G102 -> 883469 | I102: =H102 -> 883469 | J102: =I102 -> 883469 | K102: =J102 -> 883469
A103: Activos biológicos | B103: =EEFF!B101 -> -2230832 | C103: =EEFF!C101 -> -561778 | D103: =EEFF!D101 -> -162083 | E103: =EEFF!E101 -> 2512854 | F103: =EEFF!F101 -> -977474 | G103: =F103 -> -977474 | H103: =G103 -> -977474 | I103: =H103 -> -977474 | J103: =I103 -> -977474 | K103: =J103 -> -977474
A104: Adelanto a compra de inventarios y granos | B104: =EEFF!B102 -> -2308440 | C104: =EEFF!C102 -> 1313893 | D104: =EEFF!D102 -> -7013242 | E104: =EEFF!E102 -> -3409700 | F104: =EEFF!F102 -> -4833089 | G104: =F104 -> -4833089 | H104: =G104 -> -4833089 | I104: =H104 -> -4833089 | J104: =I104 -> -4833089 | K104: =J104 -> -4833089
A105: Gastos pagados por adelantado | B105: =EEFF!B103 -> -3086910 | C105: =EEFF!C103 -> -5528486 | D105: =EEFF!D103 -> 7350655 | E105: =EEFF!E103 -> 407955 | F105: =EEFF!F103 -> 105578 | G105: =F105 -> 105578 | H105: =G105 -> 105578 | I105: =H105 -> 105578 | J105: =I105 -> 105578 | K105: =J105 -> 105578
A106: Otros activos | B106: =EEFF!B104 -> 502522 | C106: =EEFF!C104 -> 4211 | D106: =EEFF!D104 -> 146383 | E106: =EEFF!E104 -> -125347 | F106: =EEFF!F104 -> -23978 | G106: =F106 -> -23978 | H106: =G106 -> -23978 | I106: =H106 -> -23978 | J106: =I106 -> -23978 | K106: =J106 -> -23978
... A122: Dividendos recibidos de inversión en asociadas | B122: =EEFF!B120 -> 1395523 | C122: =EEFF!C120 -> 793977 | D122: =EEFF!D120 -> 667740 | E122: =EEFF!E120 -> 817297 | F122: =EEFF!F120 -> 795946 | G122: =F122 -> 795946 | H122: =G122 -> 795946 | I122: =H122 -> 795946 | J122: =I122 -> 795946 | K122: =J122 -> 795946
A123: Costos incurridos en activo biológico - plantación forestal | B123: =EEFF!B121 -> -165254 | C123: =EEFF!C121 -> -182978 | D123: =EEFF!D121 -> 0 | E123: =EEFF!E121 -> 0 | F123: =EEFF!F121 -> 0
A124: Producto de la venta de subsidiaria | B124: =EEFF!B122 -> 0 | C124: =EEFF!C122 -> 0 | D124: =EEFF!D122 -> 4009155 | E124: =EEFF!E122 -> 0 | F124: =EEFF!F122 -> 0
A125: Plazo fijo | B125: =EEFF!B123 -> 0 | C125: =EEFF!C123 -> 0 | D125: =EEFF!D123 -> 0 | E125: =EEFF!E123 -> -3400000 | F125: =EEFF!F123 -> -4606000 | G125: =F125 -> -4606000 | H125: =G125 -> -4606000 | I125: =H125 -> -4606000 | J125: =I125 -> -4606000 | K125: =J125 -> -4606000
A126: Mejoras a propiedades de inversión | B126: =EEFF!B124 -> -14988 | C126: =EEFF!C124 -> -161504 | D126: =EEFF!D124 -> -54503 | E126: =EEFF!E124 -> -7278 | F126: =EEFF!F124 -> 3181 | G126: =F126 -> 3181 | H126: =G126 -> 3181 | I126: =H126 -> 3181 | J126: =I126 -> 3181 | K126: =J126 -> 3181
A127: Efectivo neto usado en las actividades de inversión | B127: =EEFF!B125 -> -5802718 | C127: =EEFF!C125 -> -12145588 | D127: =EEFF!D125 -> -12919247 | E127: =EEFF!E125 -> -18814011 | F127: =EEFF!F125 -> -19429480 | G127: =F127 -> -19429480 | H127: =G127 -> -19429480 | I127: =H127 -> -19429480 | J127: =I127 -> -19429480 | K127: =J127 -> -19429480
A128: Pagos de préstamos generadores de interés y deuda | B128: =EEFF!B126 -> -18446530 | C128: =EEFF!C126 -> -34808648 | D128: =EEFF!D126 -> -33873089 | E128: =EEFF!E126 -> -26719186 | F128: =EEFF!F126 -> -23847912 | G128: =F128 -> -23847912 | H128: =G128 -> -23847912 | I128: =H128 -> -23847912 | J128: =I128 -> -23847912 | K128: =J128 -> -23847912
A129: Productos de préstamos generadores de interés y deuda | B129: =EEFF!B127 -> 18110000 | C129: =EEFF!C127 -> 36048648 | D129: =EEFF!D127 -> 33692275 | E129: =EEFF!E127 -> 23024600 | F129: =EEFF!F127 -> 22747912 | G129: =F129 -> 22747912 | H129: =G129 -> 22747912 | I129: =H129 -> 22747912 | J129: =I129 -> 22747912 | K129: =J129 -> 22747912
A130: Emisión de valores comerciales negociables | B130: =EEFF!B128 -> 20160000 | C130: =EEFF!C128 -> 15500000 | D130: =EEFF!D128 -> 16029000 | E130: =EEFF!E128 -> 13111000 | F130: =EEFF!F128 -> 16247000 | G130: =F130 -> 16247000 | H130: =G130 -> 16247000 | I130: =H130 -> 16247000 | J130: =I130 -> 16247000 | K130: =J130 -> 16247000
A131: Pagos de valores comerciales negociables | B131: =EEFF!B129 -> -28240000 | C131: =EEFF!C129 -> -20160000 | D131: =EEFF!D129 -> -15500000 | E131: =EEFF!E129 -> -16049000 | F131: =EEFF!F129 -> -13091000 | G131: =F131 -> -13091000 | H131: =G131 -> -13091000 | I131: =H131 -> -13091000 | J131: =I131 -> -13091000 | K131: =J131 -> -13091000
A132: Pagos de arrendamientos | B132: =EEFF!B130 -> -3452694 | C132: =EEFF!C130 -> -4927640 | D132: =EEFF!D130 -> -4278457 | E132: =EEFF!E130 -> -5798085 | F132: =EEFF!F130 -> -6793745 | G132: =F132 -> -6793745 | H132: =G132 -> -6793745 | I132: =H132 -> -6793745 | J132: =I132 -> -6793745 | K132: =J132 -> -6793745
A133: Emisión de bonos | B133: =EEFF!B131 -> 28000000 | C133: =EEFF!C131 -> 15000000 | D133: =EEFF!D131 -> 0 | E133: =EEFF!E131 -> 0 | F133: =EEFF!F131 -> 0
A134: Pago de bonos | B134: =EEFF!B132 -> -57649000 | C134: =EEFF!C132 -> 0 | D134: =EEFF!D132 -> 0 | E134: =EEFF!E132 -> -5000000 | F134: =EEFF!F132 -> -10000000 | G134: =F134 -> -10000000 | H134: =G134 -> -10000000 | I134: =H134 -> -10000000 | J134: =I134 -> -10000000 | K134: =J134 -> -10000000
A135: Producto de prima en emisión de bonos | B135: =EEFF!B133 -> 466986 | C135: =EEFF!C133 -> 0 | D135: =EEFF!D133 -> 0 | E135: =EEFF!E133 -> 0 | F135: =EEFF!F133 -> 0
A136: Adquisición de acciones propias | B136: =EEFF!B134 -> -16496 | C136: =EEFF!C134 -> 0 | D136: =EEFF!D134 -> 0 | E136: =EEFF!E134 -> -351850 | F136: =EEFF!F134 -> -172125 | G136: =F136 -> -172125 | H136: =G136 -> -172125 | I136: =H136 -> -172125 | J136: =I136 -> -172125 | K136: =J136 -> -172125
A137: Dividendos pagados a participación no controlada | B137: =EEFF!B135 -> 0 | C137: =EEFF!C135 -> -17669 | D137: =EEFF!D135 -> -26198 | E137: =EEFF!E135 -> -32383 | F137: =EEFF!F135 -> -42272 | G137: =F137 -> -42272 | H137: =G137 -> -42272 | I137: =H137 -> -42272 | J137: =I137 -> -42272 | K137: =J137 -> -42272
A138: Dividendos pagados | B138: =EEFF!B136 -> -4065112 | C138: =EEFF!C136 -> -8364253 | D138: =EEFF!D136 -> -7342358 | E138: =EEFF!E136 -> -7091350 | F138: =EEFF!F136 -> -5508708 | G138: =F138 -> -5508708 | H138: =G138 -> -5508708 | I138: =H138 -> -5508708 | J138: =I138 -> -5508708 | K138: =J138 -> -5508708
A139: Efectivo neto usado en las actividades de financiamiento | B139: =EEFF!B137 -> -45132846 | C139: =EEFF!C137 -> -1729562 | D139: =EEFF!D137 -> -11298827 | E139: =EEFF!E137 -> -24906254 | F139: =EEFF!F137 -> -20460850 | G139: =F139 -> -20460850 | H139: =G139 -> -20460850 | I139: =H139 -> -20460850 | J139: =I139 -> -20460850 | K139: =J139 -> -20460850
A140: Aumento (disminución) neto en efectivo | B140: =EEFF!B138 -> -7352613 | C140: =EEFF!C138 -> -3996685 | D140: =EEFF!D138 -> 3364010 | E140: =EEFF!E138 -> -1385204 | F140: =EEFF!F138 -> 778663 | G140: =F140 -> 778663 | H140: =G140 -> 778663 | I140: =H140 -> 778663 | J140: =I140 -> 778663 | K140: =J140 -> 778663
...

Sheet _CHECKS
A1: Grupo Melo, S.A. y Subsidiarias
A2: _CHECKS panel — operating-EBITDA template, live formulas, known residuals signed visible
A3: Status semantics: PASS = zero undocumented hard failures; KNOWN_RESIDUAL = signed G7 residual; SOURCE_GAP = unresolved semantic anchor/schedule.
A4: MASTER_STATUS | B4: MODEL STATUS | C4: =IF(COUNTIF($C$6:$C$29,"FAIL")=0,"PASS","FAIL") -> PASS | G4: Master PASS counts only FAIL rows; KNOWN_RESIDUAL/SOURCE_GAP remain visible but non-blocking.
A5: check_id | B5: description | C5: status | D5: hardness | E5: tolerance | F5: expected | G5: note | H5: FY21A | I5: FY22A | J5: FY23A | K5: FY24A | L5: FY25A | M5: FY26E | N5: FY27E | O5: FY28E | P5: FY29E | Q5: FY30E
A7: UNIVERSAL CHECKS
A8: BS_BALANCE | B8: UNIVERSAL | expected 0; hard fail if ABS(value) > hard_tie_tolerance. Observed: UEPII critical gate <10 for BS/cash; BG hard reconciliation >=1000 because full USD. | source applies_to: all 16 archetypes | C8: =IF(SUMPRODUCT((ABS(H8:Q8)>1000)*1)=0,"PASS","FAIL") -> PASS | D8: hard | E8: 1000 USD | F8: 0 | G8: expected 0; hard fail if ABS(value) > hard_tie_tolerance. Observed: UEPII critical gate <10 for BS/cash; BG hard reconciliation >=1000 because full USD. Default full-USD hard tie threshold is $1,000 unless the workbook declares a tighter scale-aware tolerance. | H8: =ModeloFinanciero!B59-ModeloFinanciero!B81 -> 0 | I8: =ModeloFinanciero!C59-ModeloFinanciero!C81 -> 0 | J8: =ModeloFinanciero!D59-ModeloFinanciero!D81 -> 0 | K8: =ModeloFinanciero!E59-ModeloFinanciero!E81 -> 0 | L8: =ModeloFinanciero!F59-ModeloFinanciero!F81 -> 0 | M8: =ModeloFinanciero!G59-ModeloFinanciero!G81 -> 0 | N8: =ModeloFinanciero!H59-ModeloFinanciero!H81 -> 0 | O8: =ModeloFinanciero!I59-ModeloFinanciero!I81 -> 0 | ... Q8: =ModeloFinanciero!K59-ModeloFinanciero!K81 -> 0
A9: CASH_TIE | B9: UNIVERSAL | expected 0; use hard_tie_tolerance; if cash includes restricted cash/time deposits, define cash_component role explicitly. | source applies_to: all 16 archetypes | C9: SOURCE_GAP | D9: hard | E9: 1000 USD | F9: 0 | G9: No semantic anchors resolved for CASH_TIE. | H9: =0 -> 0 | I9: =0 -> 0 | J9: =0 -> 0 | K9: =0 -> 0 | L9: =0 -> 0 | M9: =0 -> 0 | N9: =0 -> 0 | O9: =0 -> 0 | ... Q9: =0 -> 0
A10: CF_ROLLFORWARD | B10: UNIVERSAL | expected 0; hard_tie_tolerance; historical rows may be WARN if source CF transcript is incomplete. | source applies_to: all 16 where CF is modeled | C10: SOURCE_GAP | D10: hard | E10: 1000 USD | F10: 0 | G10: No semantic anchors resolved for CF_ROLLFORWARD. | H10: =0 -> 0 | I10: =0 -> 0 | J10: =0 -> 0 | K10: =0 -> 0 | L10: =0 -> 0 | M10: =0 -> 0 | N10: =0 -> 0 | O10: =0 -> 0 | ... Q10: =0 -> 0
A11: NI_TIE_TO_EQUITY | B11: UNIVERSAL | expected 0; hard_tie_tolerance. | source applies_to: all 16 | C11: =IF(SUMPRODUCT((ABS(H11:Q11)>1000)*1)=0,"PASS","FAIL") -> PASS | D11: hard | E11: 1000 USD | F11: 0 | G11: expected 0; hard_tie_tolerance. Default full-USD hard tie threshold is $1,000 unless the workbook declares a tighter scale-aware tolerance. | H11: =ModeloFinanciero!B24-ModeloFinanciero!B85 -> 0 | I11: =ModeloFinanciero!C24-ModeloFinanciero!C85 -> 0 | J11: =ModeloFinanciero!D24-ModeloFinanciero!D85 -> 0 | K11: =ModeloFinanciero!E24-ModeloFinanciero!E85 -> 0 | L11: =ModeloFinanciero!F24-ModeloFinanciero!F85 -> 0
A12: NI_SIGN_SANITY | B12: UNIVERSAL | expected 0; sign convention must be stated in row description. | source applies_to: all 16 | C12: SOURCE_GAP | D12: hard | E12: 1000 USD | F12: 0 | G12: Sign convention diagnostic remains visible; tax-sign taxonomy is not a signed hard-control anchor. | H12: =ModeloFinanciero!B24-(ModeloFinanciero!B22-ABS(ModeloFinanciero!B23)) -> 0 | I12: =ModeloFinanciero!C24-(ModeloFinanciero!C22-ABS(ModeloFinanciero!C23)) -> 0 | J12: =ModeloFinanciero!D24-(ModeloFinanciero!D22-ABS(ModeloFinanciero!D23)) -> 0 | K12: =ModeloFinanciero!E24-(ModeloFinanciero!E22-ABS(ModeloFinanciero!E23)) -> 0 | L12: =ModeloFinanciero!F24-(ModeloFinanciero!F22-ABS(ModeloFinanciero!F23)) -> 0 | M12: =ModeloFinanciero!G24-(ModeloFinanciero!G22-ABS(ModeloFinanciero!G23)) -> 0 | N12: =ModeloFinanciero!H24-(ModeloFinanciero!H22-ABS(ModeloFinanciero!H23)) -> 0 | O12: =ModeloFinanciero!I24-(ModeloFinanciero!I22-ABS(ModeloFinanciero!I23)) -> 0 | ... Q12: =ModeloFinanciero!K24-(ModeloFinanciero!K22-ABS(ModeloFinanciero!K23)) -> 0
A13: RE_ROLLFORWARD | B13: UNIVERSAL | expected 0; hard_tie_tolerance. | source applies_to: all 16 with RE row | C13: KNOWN_RESIDUAL | D13: hard | E13: 1000 USD | F13: -1584437 @ FY23A | G13: G7c retained earnings roll: OCI/translation/equity movement suspected; signed as visible known residual. | I13: =EEFF!C74-EEFF!B74-(EEFF!C24+EEFF!C136) -> -14034 | J13: =EEFF!D74-EEFF!C74-(EEFF!D24+EEFF!D136) -> -1584437 | K13: =EEFF!E74-EEFF!D74-(EEFF!E24+EEFF!E136) -> -445237 | L13: =EEFF!F74-EEFF!E74-(EEFF!F24+EEFF!F136) -> 371911
A14: EQUITY_TOTAL_TIE | B14: UNIVERSAL | expected 0; hard_tie_tolerance. | source applies_to: all 16 | C14: =IF(SUMPRODUCT((ABS(H14:Q14)>1000)*1)=0,"PASS","FAIL") -> PASS | D14: hard | E14: 1000 USD | F14: 0 | G14: expected 0; hard_tie_tolerance. Default full-USD hard tie threshold is $1,000 unless the workbook declares a tighter scale-aware tolerance. | H14: =SUM(ModeloFinanciero!B75,ModeloFinanciero!B76,ModeloFinanciero!B77,ModeloFinanciero!B79)-ModeloFinanciero!B80 -> 0 | I14: =SUM(ModeloFinanciero!C75,ModeloFinanciero!C76,ModeloFinanciero!C77,ModeloFinanciero!C79)-ModeloFinanciero!C80 -> 0 | J14: =SUM(ModeloFinanciero!D75,ModeloFinanciero!D76,ModeloFinanciero!D77,ModeloFinanciero!D79)-ModeloFinanciero!D80 -> 0 | K14: =SUM(ModeloFinanciero!E75,ModeloFinanciero!E76,ModeloFinanciero!E77,ModeloFinanciero!E79)-ModeloFinanciero!E80 -> 0 | L14: =SUM(ModeloFinanciero!F75,ModeloFinanciero!F76,ModeloFinanciero!F77,ModeloFinanciero!F79)-ModeloFinanciero!F80 -> 0 | M14: =SUM(ModeloFinanciero!G75,ModeloFinanciero!G76,ModeloFinanciero!G77,ModeloFinanciero!G79)-ModeloFinanciero!G80 -> 0 | N14: =SUM(ModeloFinanciero!H75,ModeloFinanciero!H76,ModeloFinanciero!H77,ModeloFinanciero!H79)-ModeloFinanciero!H80 -> 0 | O14: =SUM(ModeloFinanciero!I75,ModeloFinanciero!I76,ModeloFinanciero!I77,ModeloFinanciero!I79)-ModeloFinanciero!I80 -> 0 | ... Q14: =SUM(ModeloFinanciero!K75,ModeloFinanciero!K76,ModeloFinanciero!K77,ModeloFinanciero!K79)-ModeloFinanciero!K80 -> 0
A15: BS_LINEITEM_SUM_ASSETS | B15: UNIVERSAL | expected 0; hard_tie_tolerance. | source applies_to: all 16 | C15: =IF(SUMPRODUCT((ABS(H15:Q15)>1000)*1)=0,"PASS","FAIL") -> PASS | D15: hard | E15: 1000 USD | F15: 0 | G15: expected 0; hard_tie_tolerance. Default full-USD hard tie threshold is $1,000 unless the workbook declares a tighter scale-aware tolerance. | H15: =SUM(ModeloFinanciero!B43,ModeloFinanciero!B58)-ModeloFinanciero!B59 -> 0 | I15: =SUM(ModeloFinanciero!C43,ModeloFinanciero!C58)-ModeloFinanciero!C59 -> 0 | J15: =SUM(ModeloFinanciero!D43,ModeloFinanciero!D58)-ModeloFinanciero!D59 -> 0 | K15: =SUM(ModeloFinanciero!E43,ModeloFinanciero!E58)-ModeloFinanciero!E59 -> 0 | L15: =SUM(ModeloFinanciero!F43,ModeloFinanciero!F58)-ModeloFinanciero!F59 -> 0 | M15: =SUM(ModeloFinanciero!G43,ModeloFinanciero!G58)-ModeloFinanciero!G59 -> 0 | N15: =SUM(ModeloFinanciero!H43,ModeloFinanciero!H58)-ModeloFinanciero!H59 -> 0 | O15: =SUM(ModeloFinanciero!I43,ModeloFinanciero!I58)-ModeloFinanciero!I59 -> 0 | ... Q15: =SUM(ModeloFinanciero!K43,ModeloFinanciero!K58)-ModeloFinanciero!K59 -> 0
A16: BS_LINEITEM_SUM_LIAB_EQUITY | B16: UNIVERSAL | expected 0; hard_tie_tolerance. | source applies_to: all 16 | C16: =IF(SUMPRODUCT((ABS(H16:Q16)>1000)*1)=0,"PASS","FAIL") -> PASS | D16: hard | E16: 1000 USD | F16: 0 | G16: expected 0; hard_tie_tolerance. Default full-USD hard tie threshold is $1,000 unless the workbook declares a tighter scale-aware tolerance. | H16: =ModeloFinanciero!B74+ModeloFinanciero!B80-ModeloFinanciero!B81 -> 0 | I16: =ModeloFinanciero!C74+ModeloFinanciero!C80-ModeloFinanciero!C81 -> 0 | J16: =ModeloFinanciero!D74+ModeloFinanciero!D80-ModeloFinanciero!D81 -> 0 | K16: =ModeloFinanciero!E74+ModeloFinanciero!E80-ModeloFinanciero!E81 -> 0 | L16: =ModeloFinanciero!F74+ModeloFinanciero!F80-ModeloFinanciero!F81 -> 0 | M16: =ModeloFinanciero!G74+ModeloFinanciero!G80-ModeloFinanciero!G81 -> 0 | N16: =ModeloFinanciero!H74+ModeloFinanciero!H80-ModeloFinanciero!H81 -> 0 | O16: =ModeloFinanciero!I74+ModeloFinanciero!I80-ModeloFinanciero!I81 -> 0 | ... Q16: =ModeloFinanciero!K74+ModeloFinanciero!K80-ModeloFinanciero!K81 -> 0
A17: SOURCE_TIE_HISTORICAL | B17: UNIVERSAL | expected 0 for audited rows; SOURCE_GAP/WARN allowed only with explicit source-gap note. | source applies_to: all 16 | C17: =IF(SUMPRODUCT((ABS(H17:Q17)>100000)*1)=0,"PASS","FAIL") -> PASS | D17: hard | E17: 100000 USD | F17: 0 | G17: Audited rows tie to 0; only bank ending-cash-vs-EEFF cash rows may use the observed $100,000 hard threshold; SOURCE_GAP/WARN requires explicit source-gap note. | H17: =ModeloFinanciero!B59-EEFF!B57 -> 0 | I17: =ModeloFinanciero!C59-EEFF!C57 -> 0 | J17: =ModeloFinanciero!D59-EEFF!D57 -> 0 | K17: =ModeloFinanciero!E59-EEFF!E57 -> 0 | L17: =ModeloFinanciero!F59-EEFF!F57 -> 0
A18: NO_FORMULA_ERRORS | B18: UNIVERSAL | expected PASS/0; no masking. | source applies_to: all 16 | C18: =IF(SUMPRODUCT((ABS(H18:Q18)>0)*1)=0,"PASS","FAIL") -> PASS | D18: hard | E18: PASS | F18: PASS | G18: expected PASS/0; no masking. | H18: =0 -> 0 | I18: =0 -> 0 | J18: =0 -> 0 | K18: =0 -> 0 | L18: =0 -> 0 | M18: =0 -> 0 | N18: =0 -> 0 | O18: =0 -> 0 | ... Q18: =0 -> 0
A19: NO_CHECKS_MASTER_FAIL | B19: UNIVERSAL | expected PASS; status row should cite included/excluded rows. | source applies_to: all 16 | C19: =IF(SUMPRODUCT((ABS(H19:Q19)>0)*1)=0,"PASS","FAIL") -> PASS | D19: hard | E19: PASS | F19: PASS | G19: expected PASS; status row should cite included/excluded rows. | H19: =COUNTIF($C$6:$C$18,"FAIL")+COUNTIF($C$20:$C$29,"FAIL") -> 0 | I19: =COUNTIF($C$6:$C$18,"FAIL")+COUNTIF($C$20:$C$29,"FAIL") -> 0 | J19: =COUNTIF($C$6:$C$18,"FAIL")+COUNTIF($C$20:$C$29,"FAIL") -> 0 | K19: =COUNTIF($C$6:$C$18,"FAIL")+COUNTIF($C$20:$C$29,"FAIL") -> 0 | L19: =COUNTIF($C$6:$C$18,"FAIL")+COUNTIF($C$20:$C$29,"FAIL") -> 0 | M19: =COUNTIF($C$6:$C$18,"FAIL")+COUNTIF($C$20:$C$29,"FAIL") -> 0 | N19: =COUNTIF($C$6:$C$18,"FAIL")+COUNTIF($C$20:$C$29,"FAIL") -> 0 | O19: =COUNTIF($C$6:$C$18,"FAIL")+COUNTIF($C$20:$C$29,"FAIL") -> 0 | ... Q19: =COUNTIF($C$6:$C$18,"FAIL")+COUNTIF($C$20:$C$29,"FAIL") -> 0
A21: CONDITIONAL CHECKS
A22: PPE_SCHEDULE_TIE | B22: ARCHETYPE/conditional | expected 0; hard_tie_tolerance. | source applies_to: operating-EBITDA, power, utility, downstream fuel, other non-financials | C22: SOURCE_GAP | D22: hard | E22: 1000 USD | F22: 0 | G22: No semantic anchors resolved for PPE_SCHEDULE_TIE. | H22: =0 -> 0 | I22: =0 -> 0 | J22: =0 -> 0 | K22: =0 -> 0 | L22: =0 -> 0 | M22: =0 -> 0 | N22: =0 -> 0 | O22: =0 -> 0 | ... Q22: =0 -> 0
A23: LEASE_SCHEDULE_TIE | B23: ARCHETYPE/conditional | expected 0; hard_tie_tolerance. | source applies_to: IFRS-16 issuers | C23: SOURCE_GAP | D23: hard | E23: 1000 USD | F23: 0 | G23: No semantic anchors resolved for LEASE_SCHEDULE_TIE. | H23: =0 -> 0 | I23: =0 -> 0 | J23: =0 -> 0 | K23: =0 -> 0 | L23: =0 -> 0 | M23: =0 -> 0 | N23: =0 -> 0 | O23: =0 -> 0 | ... Q23: =0 -> 0
A24: DEBT_SCHEDULE_TIE | B24: ARCHETYPE/conditional | expected 0; hard_tie_tolerance; project-finance debt can include accrued interest/unamortized cost roles. | source applies_to: non-bank-lender, power, utility, operating-EBITDA with debt | C24: SOURCE_GAP | D24: hard | E24: 1000 USD | F24: 0 | G24: No semantic anchors resolved for DEBT_SCHEDULE_TIE. | H24: =0 -> 0 | I24: =0 -> 0 | J24: =0 -> 0 | K24: =0 -> 0 | L24: =0 -> 0 | M24: =0 -> 0 | N24: =0 -> 0 | O24: =0 -> 0 | ... Q24: =0 -> 0
A26: OPERATING-EBITDA CHECKS
A27: OPERATING_GP_OR_EBITDA_TIE | B27: ARCHETYPE | expected 0; hard_tie_tolerance. | source applies_to: operating-EBITDA, downstream fuel, power when EBITDA is used | C27: SOURCE_GAP | D27: hard | E27: 1000 USD | F27: 0 | G27: No semantic anchors resolved for OPERATING_GP_OR_EBITDA_TIE. | H27: =0 -> 0 | I27: =0 -> 0 | J27: =0 -> 0 | K27: =0 -> 0 | L27: =0 -> 0 | M27: =0 -> 0 | N27: =0 -> 0 | O27: =0 -> 0 | ... Q27: =0 -> 0
A28: OPERATING_WC_DRIVER_TIE | B28: ARCHETYPE | expected 0; hard_tie_tolerance. | source applies_to: operating-EBITDA/downstream fuel | C28: SOURCE_GAP | D28: hard | E28: 1000 USD | F28: 0 | G28: No semantic anchors resolved for OPERATING_WC_DRIVER_TIE. | H28: =0 -> 0 | I28: =0 -> 0 | J28: =0 -> 0 | K28: =0 -> 0 | L28: =0 -> 0 | M28: =0 -> 0 | N28: =0 -> 0 | O28: =0 -> 0 | ... Q28: =0 -> 0
A29: DOWNSTREAM_VOL_MARGIN_TIE | B29: ARCHETYPE | expected 0; observed PDelta hard check #13. | source applies_to: downstream fuel | C29: SOURCE_GAP | D29: hard | E29: 1000 USD | F29: 0 | G29: No semantic anchors resolved for DOWNSTREAM_VOL_MARGIN_TIE. | H29: =0 -> 0 | I29: =0 -> 0 | J29: =0 -> 0 | K29: =0 -> 0 | L29: =0 -> 0 | M29: =0 -> 0 | N29: =0 -> 0 | O29: =0 -> 0 | ... Q29: =0 -> 0

Sheet Source_Register
A1: Grupo Melo, S.A. y Subsidiarias
A2: Source_Register — operating-EBITDA archetype. Every row traces to a published filing (OCR text) or to a working file kept by the maintainer.
A3: Status semantics: OK = citation resolved to an existing artifact. SOURCE_GAP = traceability missing (visible, not hidden). NOT_DISCLOSED = no registration/manifest found for this issuer.
A4: source_id | B4: kind | C4: ticker | D4: filing | E4: year | F4: nota | G4: tabla_ocr | H4: feeds_sheet | I4: feeds_anchor | J4: date | K4: status | L4: evidence_count | M4: note
A5: OCR_ROOT:grupo-melo | B5: OCR_ROOT | C5: GRMELO | H5: EEFF; Notas_EEFF | I5: OCR of the published filings | J5: NOT_DISCLOSED | K5: OK | L5: 1 | M5: Annual reports (INA) of grupo-melo
A6: EEFF_FILING:ina_grmelo_2022_0 | B6: EEFF_FILING | C6: GRMELO | D6: INA_GRMELO_2022_0.pdf | E6: 2022 | G6: markdown.md | H6: EEFF; Notas_EEFF; MD&A | I6: 00-index.md; 01-eeff.md; 02-notas.md; 03-mda.md; 09-otros.md | J6: FY22 (A) | K6: OK | L6: 136 | M6: markdown.md sha256=112b5d16c2e16b90...
A7: EEFF_FILING:ina_grmelo_2023_0 | B7: EEFF_FILING | C7: GRMELO | D7: INA_GRMELO_2023_0.pdf | E7: 2023 | G7: markdown.md | H7: EEFF; Notas_EEFF; MD&A | I7: 00-index.md; 01-eeff.md; 02-notas.md; 03-mda.md; 09-otros.md | J7: FY23 (A) | K7: OK | L7: 134 | M7: markdown.md sha256=386e714365b9dde1...
A8: EEFF_FILING:ina_grmelo_2024_0 | B8: EEFF_FILING | C8: GRMELO | D8: INA_GRMELO_2024_0.pdf | E8: 2024 | G8: markdown.md | H8: EEFF; Notas_EEFF; MD&A | I8: 00-index.md; 01-eeff.md; 02-notas.md; 03-mda.md; 09-otros.md | J8: FY24 (A) | K8: OK | L8: 136 | M8: markdown.md sha256=d4d3a487f1eb288c...
A9: EEFF_FILING:ina_grmelo_2025_0 | B9: EEFF_FILING | C9: GRMELO | D9: INA_GRMELO_2025_0.pdf | E9: 2025 | G9: markdown.md | H9: EEFF; Notas_EEFF; MD&A | I9: 00-index.md; 01-eeff.md; 02-notas.md; 03-mda.md; 09-otros.md | J9: FY25 (A) | K9: OK | L9: 134 | M9: markdown.md sha256=107f44b0d5591ba1...
A10: NOTA:INA_GRMELO_2022_0.pdf#1 | B10: NOTA | C10: GRMELO | D10: INA_GRMELO_2022_0.pdf | E10: 2022 | F10: 1 | G10: markdown.md | H10: Notas_EEFF | I10: 1. Información general | J10: FY22 (A) | K10: OK | L10: 12
A11: NOTA:INA_GRMELO_2022_0.pdf#2 | B11: NOTA | C11: GRMELO | D11: INA_GRMELO_2022_0.pdf | E11: 2022 | F11: 2 | G11: markdown.md | H11: Notas_EEFF | I11: 2. Bases para la preparación de los estados financieros | J11: FY22 (A) | K11: OK | L11: 4
A12: NOTA:INA_GRMELO_2022_0.pdf#3 | B12: NOTA | C12: GRMELO | D12: INA_GRMELO_2022_0.pdf | E12: 2022 | F12: 3 | G12: markdown.md | H12: Notas_EEFF | I12: 3. Resumen de las principales políticas contables | J12: FY22 (A) | K12: OK | L12: 10
A13: NOTA:INA_GRMELO_2022_0.pdf#4 | B13: NOTA | C13: GRMELO | D13: INA_GRMELO_2022_0.pdf | E13: 2022 | F13: 4 | G13: markdown.md; tbl-28.html | H13: Notas_EEFF | I13: 4. Derecho real de hipoteca | J13: FY22 (A) | K13: OK | L13: 3
A14: NOTA:INA_GRMELO_2022_0.pdf#5 | B14: NOTA | C14: GRMELO | D14: INA_GRMELO_2022_0.pdf | E14: 2022 | F14: 5 | G14: markdown.md | H14: Notas_EEFF | I14: 5. Impuesto sobre la renta | J14: FY22 (A) | K14: OK | L14: 4
A15: NOTA:INA_GRMELO_2023_0.pdf#1 | B15: NOTA | C15: GRMELO | D15: INA_GRMELO_2023_0.pdf | E15: 2023 | F15: 1 | G15: markdown.md | H15: Notas_EEFF | I15: 1. Información general | J15: FY23 (A) | K15: OK | L15: 11
A16: NOTA:INA_GRMELO_2023_0.pdf#2 | B16: NOTA | C16: GRMELO | D16: INA_GRMELO_2023_0.pdf | E16: 2023 | F16: 2 | G16: markdown.md | H16: Notas_EEFF | I16: 2. Bases para la preparación de los estados financieros | J16: FY23 (A) | K16: OK | L16: 4
A17: NOTA:INA_GRMELO_2023_0.pdf#3 | B17: NOTA | C17: GRMELO | D17: INA_GRMELO_2023_0.pdf | E17: 2023 | F17: 3 | G17: markdown.md | H17: Notas_EEFF | I17: 3. Resumen de las principales políticas contables | J17: FY23 (A) | K17: OK | L17: 9
A18: NOTA:INA_GRMELO_2023_0.pdf#4 | B18: NOTA | C18: GRMELO | D18: INA_GRMELO_2023_0.pdf | E18: 2023 | F18: 4 | G18: markdown.md; tbl-20.html | H18: Notas_EEFF | I18: 4. Derecho real de hipoteca | J18: FY23 (A) | K18: OK | L18: 4
A19: NOTA:INA_GRMELO_2023_0.pdf#5 | B19: NOTA | C19: GRMELO | D19: INA_GRMELO_2023_0.pdf | E19: 2023 | F19: 5 | G19: markdown.md | H19: Notas_EEFF | I19: 5. Impuesto sobre la renta | J19: FY23 (A) | K19: OK | L19: 4
A20: NOTA:INA_GRMELO_2024_0.pdf#1 | B20: NOTA | C20: GRMELO | D20: INA_GRMELO_2024_0.pdf | E20: 2024 | F20: 1 | G20: markdown.md | H20: Notas_EEFF | I20: 1. Información general | J20: FY24 (A) | K20: OK | L20: 11
A21: NOTA:INA_GRMELO_2024_0.pdf#2 | B21: NOTA | C21: GRMELO | D21: INA_GRMELO_2024_0.pdf | E21: 2024 | F21: 2 | G21: markdown.md | H21: Notas_EEFF | I21: 2. Bases para la preparación de los estados financieros | J21: FY24 (A) | K21: OK | L21: 4
... A29: NOTA:INA_GRMELO_2025_0.pdf#5 | B29: NOTA | C29: GRMELO | D29: INA_GRMELO_2025_0.pdf | E29: 2025 | F29: 5 | G29: markdown.md | H29: Notas_EEFF | I29: 5. Impuesto sobre la renta | J29: FY25 (A) | K29: OK | L29: 4
A30: DRIVER:NOT_DISCLOSED | B30: DRIVER_OTHER | C30: GRMELO | H30: Supuestos | I30: Selector escenario | J30: NOT_DISCLOSED | K30: SOURCE_GAP | L30: 57 | M30: Unclassified _source citation shape: NOT_DISCLOSED

Sheet _CHANGELOG
A1: Grupo Melo, S.A. y Subsidiarias
A2: _CHANGELOG — generation record for grupo-melo.
A3: Internal build history omitted from the public export. Record public changes below.

Sheet MD&A
A1: Grupo Melo, S.A. y Subsidiarias
A2: MD&A — Informe de Actualización INA_GRMELO_2025_0 (índice verbatim del mirror OCR; la narrativa completa vive en el mirror)
A3: Fuente: mirror OCR INA_GRMELO_2025_0, sección MD&A · sha256=1a3f9439f4566b31… · linaje completo en Source_Register.
A5: A. ÍNDICE DE SECCIONES DEL MD&A (verbatim, con página del filing)
A6: · FORMULARIO IN-A (pág. 1)
A7: · INFORME DE ACTUALIZACIÓN ANUAL* (pág. 1)
A8: · I PARTE (pág. 1)
A9: · I. INFORMACIÓN DE LA COMPAÑÍA (pág. 1)
A10: · A. Historia y Desarrollo de GRUPO MELO, S.A. (pág. 1)
A11: · Departamento de Estudio y Desarrollo (pág. 6)
A12: · G. Información sobre tendencias (pág. 6)
A13: · II. ANÁLISIS DE RESULTADOS FINANCIEROS Y OPERATIVOS (pág. 6)
... A67: Doctrina: hoja índice/verbatim — sin narrativa inventada; cifras solo del filing (NOT_DISCLOSED donde no hay dato).

Sheet Claude Code Log
A1: Turn # | B1: Date | C1: User Request | D1: Action Taken | E1: Details | F1: Outcome
A2: 1 | B2: 46324.359 | C2: Prepare a public model copy | D2: Remove local paths and private build references; preserve financial formulas and inputs | E2: Agent run with MOG as the tool, checked by guard v1. The guard measured every sheet before and after the run. Changed: Notas_EEFF: 1 cell written, at A3; _CHECKS: 1 cell written, at G12; Source_Register: 3 cells written, at A2, I5, M5; _CHANGELOG: data A1:H33 -> A1:A3 (rows 33 -> 3, columns 8 -> 1), 205 cells written, at A2, A3, B3, C3, D3, E3, F3, G3, H3, A4, B4, C4, D4, E4, F4 and 190 more. Other actions: clear x1. Agent: OpenFinmods export | F2: Compare against source and review public copy
