Workbook

Sheet 00_Cover
A1: Space Exploration Technologies Corp. (SpaceX) | Financial model: statements as filed, segment forecast 2026E-2035E, valuation and credit
A2: Built 27 Oct 2026 from the 424B4 of 11 Jun 2026, the 10-Qs for Q2 and Q3 2026 and the 8-Ks of 20 and 26 Oct 2026. Nasdaq: SPCX. Includes xAI and X (from Feb 2026) and Cursor (from 14 Aug 2026).
A4: What this workbook holds
A5: Every line of the statements: fiscal 2023 to 2025 (audited) and the nine months to 30 September 2025 and 2026 (unaudited); seven quarters to Q3 2026.
A6: Segments (Space, Connectivity, SI), revenue by type, operating data (subscribers, ARPU, launches, GW of compute), customers, backlog, debt and commitments.
A7: Forecast by segment, Q4 2026E stub then 2027E-2035E, with Base, Bull and Bear (switch: Assumptions!C5); Apollo GPU lease from 2027; EchoStar spectrum at closing.
A8: Valuation: DCF (perpetuity and exit multiple), sum of the parts at trailing peer multiples, reverse DCF on revenue per GW, sensitivity, scenario summary; credit metrics.
A9: How to read it
A10: Units: USD millions, except per-share amounts (USD) and share counts (millions).
A11: Signs follow the filing. Interest expense is negative, as filed. A cell the filing shows as — is blank, with a note in column N.
A12: Blue numbers are typed from a filing or are inputs. Black numbers are formulas. Green numbers link to another sheet.
A13: Column M on the year sheets is for your comments. Column N shows the source or the derivation.
A14: The thin vertical line separates actual and forecast columns.
A16: Master check (all checks on the Checks sheet) | C16: =Checks!C4 -> OK
A18: Key outputs (active scenario unless stated) | C18: Value
A19: Active scenario | C19: =Assumptions!$C$6 -> Base
A20: SPCX price, 27 Oct 2026 (USD) | C20: =Market_Package!B10 -> 148.58
A21: DCF value per share, perpetuity (USD) | C21: =DCF!C37 -> 31.894477
A22: Against the price | C22: =DCF!C40 -> -0.78533802
A23: Base / Bull / Bear value per share (captured, USD): Base | C23: =Scenario_Summary!D23 -> 31.894477
A24: Bull | C24: =Scenario_Summary!E23 -> 67.790591
A25: Bear | C25: =Scenario_Summary!F23 -> 3.4085009
A26: DCF value per share with the Musk performance shares counted the other way (USD) | C26: =DCF!C38 -> 35.054485
A27: Sum of the parts at trailing peer multiples, average of the two bases (USD) | C27: =Valuation!C42 -> 29.7058
A28: Probability-weighted DCF value, Bear 25% / Base 50% / Bull 25% (USD) | C28: =Valuation!C49 -> 33.747011
A29: Shift on SI revenue per GW the price needs (Base) | C29: =Valuation!C35 -> 2.6335686
A30: Revenue 2026E (USD m) | C30: =Forecast_3Stmt!C10 -> 44225.754
A31: Revenue 2030E (USD m) | C31: =Forecast_3Stmt!G10 -> 178794.88
A32: WACC | C32: =Market_Package!B59 -> 0.10294983
A33: Diluted shares (millions) | C33: =Cap_Table!B56 -> 14444.097
A35: Sheet | B35: What it shows
A36: IS_Hist | B36: Statements of operations as filed, with tie-out checks
A37: CI_Hist | B37: Statements of comprehensive income (loss) as filed
A38: BS_Hist | B38: Balance sheets as filed (31 Dec 2024, 31 Dec 2025, 30 Sep 2026)
A39: CF_Hist | B39: Statements of cash flows as filed
A40: SCE_Hist | B40: Statements of preferred stock and shareholders' equity as filed
A41: Quarterly_Hist | B41: Seven quarters to Q3 2026 (Q4 2025 derived)
A42: Segments_Hist | B42: Segments, revenue by type, operating data, customers, backlog, derived Q3 2026 rates
A43: Cap_Table | B43: Shares outstanding, Musk performance-share tranches, options, RSUs, EchoStar shares; diluted count; market price
A44: Assumptions | B44: Every forecast input with its reason: Base, Bull, Bear and the switch (C5)
A45: Interim_Bridge | B45: 2026E = nine months filed + Q4 2026E by segment; 31 Dec 2026E balance sheet
A46: Segments_Fcst | B46: Segment drivers: launches, subscribers x ARPU, GW x revenue per GW, Cursor, X; EBITDA and capex
... A58: Claude Code Log | B58: Log of every scripted write

Sheet IS_Hist
A1: Space Exploration Technologies Corp. (SpaceX) | Consolidated statements of operations, as filed
A2: USD millions, except per-share amounts (USD) and shares (millions). FY2023-FY2025 audited (424B4 of 11 Jun 2026); nine months unaudited (10-Q Q3 2026).
A4: Fiscal year ends 31 December | B4: FY2023A | C4: FY2024A | D4: FY2025A | E4: 9M 2025A | F4: 9M 2026A | M4: Comentarios FG | N4: Source / derivation
A6: Revenue | B6: 10387 | C6: 14015 | D6: 18674 | E6: 13714 | F6: 27083 | N6: FY: 424B4 p. F-5; 9M: 10-Q Q3 2026 p. 4
A7: Costs and expenses
A8: Cost of revenue | B8: 6110 | C8: 7996 | D8: 9451 | E8: 6949 | F8: 11361 | N8: FY: 424B4 p. F-5; 9M: 10-Q Q3 2026 p. 4
A9: Research and development | B9: 2105 | C9: 3464 | D9: 8643 | E9: 5806 | F9: 11658 | N9: FY: 424B4 p. F-5; 9M: 10-Q Q3 2026 p. 4
A10: Selling, general, and administrative | B10: 1665 | C10: 1813 | D10: 2644 | E10: 1674 | F10: 3365 | N10: FY: 424B4 p. F-5; 9M: 10-Q Q3 2026 p. 4
A11: Restructuring charges (credits) | B11: 237 | C11: 213 | D11: 487 | E11: 472 | F11: -6 | N11: FY: 424B4 p. F-5; 9M: 10-Q Q3 2026 p. 4
A12: Impairment | B12: 3775 | C12: 63 | D12: 38 | E12: 29 | N12: FY: 424B4 p. F-5; 9M: 10-Q Q3 2026 p. 4. Filing shows — (nil) in 9M 2026A: left blank
A13: Total costs and expenses | B13: 13892 | C13: 13549 | D13: 21263 | E13: 14930 | F13: 26378 | N13: FY: 424B4 p. F-5; 9M: 10-Q Q3 2026 p. 4
A14: Income (loss) from operations | B14: -3505 | C14: 466 | D14: -2589 | E14: -1216 | F14: 705 | N14: FY: 424B4 p. F-5; 9M: 10-Q Q3 2026 p. 4
A15: Interest expense | B15: -1693 | C15: -1580 | D15: -1945 | E15: -1372 | F15: -1968 | N15: FY: 424B4 p. F-5; 9M: 10-Q Q3 2026 p. 4
A16: Interest income | B16: 249 | C16: 371 | D16: 492 | E16: 370 | F16: 1426 | N16: FY: 424B4 p. F-5; 9M: 10-Q Q3 2026 p. 4
A17: Other income (expense), net | B17: -42 | C17: 985 | D17: -177 | E17: 342 | F17: -937 | N17: FY: 424B4 p. F-5; 9M: 10-Q Q3 2026 p. 4
A18: Income (loss) before income taxes | B18: -4991 | C18: 242 | D18: -4219 | E18: -1876 | F18: -774 | N18: FY: 424B4 p. F-5; 9M: 10-Q Q3 2026 p. 4
A19: Provision for (benefit from) income taxes | B19: -363 | C19: -549 | D19: 718 | E19: 714 | F19: -361 | N19: FY: 424B4 p. F-5; 9M: 10-Q Q3 2026 p. 4
A20: Net income (loss) | B20: -4628 | C20: 791 | D20: -4937 | E20: -2590 | F20: -413 | N20: FY: 424B4 p. F-5; 9M: 10-Q Q3 2026 p. 4
A21: Net income (loss) attributable to shareholders, basic | B21: -4628 | C21: 18 | D21: -4937 | E21: -2590 | F21: -1084 | N21: FY: 424B4 p. F-5; 9M: 10-Q Q3 2026 p. 4
A22: Net income (loss) attributable to shareholders, diluted | B22: -4628 | C22: 21 | D22: -4937 | E22: =E21 -> -2590 | F22: =F21 -> -1084 | N22: FY: 424B4 p. F-5; 9M: 10-Q Q3 2026 p. 4. The 10-Q gives one line 'basic and diluted' for the nine months, so E and F link to the basic line
A24: Per share and share counts
A25: Net income (loss) per share, basic (USD) | B25: -1.68 | C25: 0.01 | D25: -1.69 | E25: -0.89 | F25: -0.15 | N25: FY: 424B4 p. F-5; 9M: 10-Q Q3 2026 p. 4
A26: Net income (loss) per share, diluted (USD) | B26: -1.68 | C26: 0 | D26: -1.69 | E26: -0.89 | F26: -0.15 | N26: FY: 424B4 p. F-5; 9M: 10-Q Q3 2026 p. 4
A27: Weighted average shares, basic (millions) | B27: 2759 | C27: 2848 | D27: 2926 | E27: 2915 | F27: 7274 | N27: FY: 424B4 p. F-5; 9M: 10-Q Q3 2026 p. 4
A28: Weighted average shares, diluted (millions) | B28: 2759 | C28: 9956 | D28: 2926 | E28: 2915 | F28: 7274 | N28: FY: 424B4 p. F-5; 9M: 10-Q Q3 2026 p. 4
A30: Checks: recomputed less filed (zero passes)
A31: Total costs and expenses | B31: =B8+B9+B10+B11+B12-B13 -> 0 | C31: =C8+C9+C10+C11+C12-C13 -> 0 | D31: =D8+D9+D10+D11+D12-D13 -> 0 | E31: =E8+E9+E10+E11+E12-E13 -> 0 | F31: =F8+F9+F10+F11+F12-F13 -> 0
A32: Income (loss) from operations | B32: =B6-B13-B14 -> 0 | C32: =C6-C13-C14 -> 0 | D32: =D6-D13-D14 -> 0 | E32: =E6-E13-E14 -> 0 | F32: =F6-F13-F14 -> 0
A33: Income (loss) before income taxes | B33: =B14+B15+B16+B17-B18 -> 0 | C33: =C14+C15+C16+C17-C18 -> 0 | D33: =D14+D15+D16+D17-D18 -> 0 | E33: =E14+E15+E16+E17-E18 -> 0 | F33: =F14+F15+F16+F17-F18 -> 0
A34: Net income (loss) | B34: =B18-B19-B20 -> 0 | C34: =C18-C19-C20 -> 0 | D34: =D18-D19-D20 -> 0 | E34: =E18-E19-E20 -> 0 | F34: =F18-F19-F20 -> 0
A35: Basic EPS (rounded to cents) | B35: =ROUND(B21/B27,2)-B25 -> 0 | C35: =ROUND(C21/C27,2)-C25 -> 0 | D35: =ROUND(D21/D27,2)-D25 -> 0 | E35: =ROUND(E21/E27,2)-E25 -> 0 | F35: =ROUND(F21/F27,2)-F25 -> 0
A36: Diluted EPS (rounded to cents) | B36: =ROUND(B22/B28,2)-B26 -> 0 | C36: =ROUND(C22/C28,2)-C26 -> 0 | D36: =ROUND(D22/D28,2)-D26 -> 0 | E36: =ROUND(E22/E28,2)-E26 -> 0 | F36: =ROUND(F22/F28,2)-F26 -> 0

Sheet CI_Hist
A1: Space Exploration Technologies Corp. (SpaceX) | Consolidated statements of comprehensive income (loss), as filed
A2: USD millions. FY: 424B4 p. F-6; 9M: 10-Q Q3 2026 p. 6.
A4: Fiscal year ends 31 December | B4: FY2023A | C4: FY2024A | D4: FY2025A | E4: 9M 2025A | F4: 9M 2026A | M4: Comentarios FG | N4: Source / derivation
A6: Net income (loss) | B6: -4628 | C6: 791 | D6: -4937 | E6: -2590 | F6: -413 | N6: FY: 424B4 p. F-6; 9M: 10-Q Q3 2026 p. 6
A7: Change in foreign currency translation adjustments, net of tax | B7: 222 | C7: -391 | D7: 805 | E7: 792 | F7: -207 | N7: FY: 424B4 p. F-6; 9M: 10-Q Q3 2026 p. 6
A8: Unrealized gains (losses) on marketable securities, net of tax | B8: 1 | C8: -1 | D8: 0 | F8: -27 | N8: FY: 424B4 p. F-6; 9M: 10-Q Q3 2026 p. 6. Filing shows — (nil) in 9M 2025A: left blank
A9: Other comprehensive income (loss) | B9: 223 | C9: -392 | D9: 805 | E9: 792 | F9: -234 | N9: FY: 424B4 p. F-6; 9M: 10-Q Q3 2026 p. 6
A10: Comprehensive income (loss) | B10: -4405 | C10: 399 | D10: -4132 | E10: -1798 | F10: -647 | N10: FY: 424B4 p. F-6; 9M: 10-Q Q3 2026 p. 6
A12: Checks: recomputed less filed (zero passes)
A13: Other comprehensive income (loss) | B13: =B7+B8-B9 -> 0 | C13: =C7+C8-C9 -> 0 | D13: =D7+D8-D9 -> 0 | E13: =E7+E8-E9 -> 0 | F13: =F7+F8-F9 -> 0
A14: Comprehensive income (loss) | B14: =B6+B9-B10 -> 0 | C14: =C6+C9-C10 -> 0 | D14: =D6+D9-D10 -> 0 | E14: =E6+E9-E10 -> 0 | F14: =F6+F9-F10 -> 0
A15: Net income equals the statement of operations | B15: =B6-IS_Hist!B20 -> 0 | C15: =C6-IS_Hist!C20 -> 0 | D15: =D6-IS_Hist!D20 -> 0 | E15: =E6-IS_Hist!E20 -> 0 | F15: =F6-IS_Hist!F20 -> 0

Sheet BS_Hist
A1: Space Exploration Technologies Corp. (SpaceX) | Consolidated balance sheets, as filed
A2: USD millions. 31 December audited (424B4); 30 September 2026 unaudited (10-Q Q3 2026).
A4: Fiscal year ends 31 December | B4: 31 Dec 2024A | C4: 31 Dec 2025A | D4: 30 Sep 2026A | M4: Comentarios FG | N4: Source / derivation
A6: Current assets
A7: Cash and cash equivalents | B7: 11385 | C7: 24747 | D7: 51294 | N7: 31 Dec: 424B4 p. F-4; 30 Sep 2026: 10-Q Q3 2026 p. 4
A8: Marketable securities | B8: 800 | D8: 38561 | N8: 31 Dec: 424B4 p. F-4; 30 Sep 2026: 10-Q Q3 2026 p. 4. Filing shows — (nil) in 31 Dec 2025A: left blank
A9: Accounts receivable, net | B9: 1052 | C9: 1579 | D9: 4772 | N9: 31 Dec: 424B4 p. F-4; 30 Sep 2026: 10-Q Q3 2026 p. 4
A10: Inventory | B10: 2003 | C10: 2416 | D10: 2891 | N10: 31 Dec: 424B4 p. F-4; 30 Sep 2026: 10-Q Q3 2026 p. 4
A11: Prepaid expenses and other current assets | B11: 868 | C11: 2210 | D11: 3457 | N11: 31 Dec: 424B4 p. F-4; 30 Sep 2026: 10-Q Q3 2026 p. 4
A12: Total current assets | B12: 16108 | C12: 30952 | D12: 100975 | N12: 31 Dec: 424B4 p. F-4; 30 Sep 2026: 10-Q Q3 2026 p. 4
A13: Noncurrent assets
A14: Property, plant, and equipment, net | B14: 21147 | C14: 42602 | D14: 89483 | N14: 31 Dec: 424B4 p. F-4; 30 Sep 2026: 10-Q Q3 2026 p. 4
A15: Finance lease right-of-use assets | B15: 1686 | C15: 1260 | D15: 1040 | N15: 31 Dec: 424B4 p. F-4; 30 Sep 2026: 10-Q Q3 2026 p. 4
A16: Intangible assets, net | B16: 2211 | C16: 1548 | D16: 6354 | N16: 31 Dec: 424B4 p. F-4; 30 Sep 2026: 10-Q Q3 2026 p. 4
A17: Digital assets | B17: 1749 | C17: 1637 | D17: 1573 | N17: 31 Dec: 424B4 p. F-4; 30 Sep 2026: 10-Q Q3 2026 p. 4
A18: Goodwill | B18: 11129 | C18: 11809 | D18: 48423 | N18: 31 Dec: 424B4 p. F-4; 30 Sep 2026: 10-Q Q3 2026 p. 4
A19: Deferred tax assets | B19: 696 | C19: 141 | D19: 388 | N19: 31 Dec: 424B4 p. F-4; 30 Sep 2026: 10-Q Q3 2026 p. 4
A20: Other assets | B20: 2336 | C20: 2130 | D20: 5809 | N20: 31 Dec: 424B4 p. F-4; 30 Sep 2026: 10-Q Q3 2026 p. 4
A21: Total assets | B21: 57062 | C21: 92079 | D21: 254045 | N21: 31 Dec: 424B4 p. F-4; 30 Sep 2026: 10-Q Q3 2026 p. 4
A22: Current liabilities
A23: Accounts payable | B23: 4413 | C23: 11792 | D23: 13259 | N23: 31 Dec: 424B4 p. F-4; 30 Sep 2026: 10-Q Q3 2026 p. 4
A24: Deferred revenue, current | B24: 5498 | C24: 6111 | D24: 10784 | N24: 31 Dec: 424B4 p. F-4; 30 Sep 2026: 10-Q Q3 2026 p. 4
A25: Debt and finance leases, current | B25: 372 | C25: 928 | D25: 2698 | N25: 31 Dec: 424B4 p. F-4; 30 Sep 2026: 10-Q Q3 2026 p. 4
A26: Accrued expenses and other current liabilities | B26: 1508 | C26: 2569 | D26: 5997 | N26: 31 Dec: 424B4 p. F-4; 30 Sep 2026: 10-Q Q3 2026 p. 4
A27: Total current liabilities | B27: 11791 | C27: 21400 | D27: 32738 | N27: 31 Dec: 424B4 p. F-4; 30 Sep 2026: 10-Q Q3 2026 p. 4
A28: Long-term liabilities
A29: Deferred revenue, net of current | B29: 4681 | C29: 6005 | D29: 6736 | N29: 31 Dec: 424B4 p. F-4; 30 Sep 2026: 10-Q Q3 2026 p. 4
A30: Debt and finance leases, net of current | B30: 13421 | C30: 21968 | D30: 36146 | N30: 31 Dec: 424B4 p. F-4; 30 Sep 2026: 10-Q Q3 2026 p. 4
A31: Other liabilities | B31: 1365 | C31: 1381 | D31: 1657 | N31: 31 Dec: 424B4 p. F-4; 30 Sep 2026: 10-Q Q3 2026 p. 4
A32: Total liabilities | B32: 31258 | C32: 50754 | D32: 77277 | N32: 31 Dec: 424B4 p. F-4; 30 Sep 2026: 10-Q Q3 2026 p. 4
A33: Redeemable convertible preferred stock
A34: Redeemable convertible preferred stock | B34: 20941 | C34: 38752 | N34: 31 Dec: 424B4 p. F-4; 30 Sep 2026: 10-Q Q3 2026 p. 4. Filing shows — (nil) in 30 Sep 2026A: left blank
A35: Shareholders' equity
A36: Class A common stock | B36: 2 | C36: 3 | D36: 8 | N36: 31 Dec: 424B4 p. F-4; 30 Sep 2026: 10-Q Q3 2026 p. 4
A37: Class B common stock | B37: 1 | C37: 1 | D37: 5 | N37: 31 Dec: 424B4 p. F-4; 30 Sep 2026: 10-Q Q3 2026 p. 4
A38: Class C common stock | B38: 0 | C38: 0 | N38: 31 Dec: 424B4 p. F-4; 30 Sep 2026: 10-Q Q3 2026 p. 4. Filing shows — (nil) in 30 Sep 2026A: left blank
A39: Additional paid-in capital | B39: 35865 | C39: 37706 | D39: 212539 | N39: 31 Dec: 424B4 p. F-4; 30 Sep 2026: 10-Q Q3 2026 p. 4
A40: Accumulated deficit | B40: -32098 | C40: -37035 | D40: -37448 | N40: 31 Dec: 424B4 p. F-4; 30 Sep 2026: 10-Q Q3 2026 p. 4
A41: Accumulated other comprehensive income | B41: 1093 | C41: 1898 | D41: 1664 | N41: 31 Dec: 424B4 p. F-4; 30 Sep 2026: 10-Q Q3 2026 p. 4
A42: Total shareholders' equity | B42: 4863 | C42: 2573 | D42: 176768 | N42: 31 Dec: 424B4 p. F-4; 30 Sep 2026: 10-Q Q3 2026 p. 4
A43: Total liabilities, redeemable convertible preferred stock, and shareholders' equity | B43: 57062 | C43: 92079 | D43: 254045 | N43: 31 Dec: 424B4 p. F-4; 30 Sep 2026: 10-Q Q3 2026 p. 4
A45: Memo: items used by the model
A46: Cash, cash equivalents and marketable securities | B46: =B7+B8 -> 12185 | C46: =C7+C8 -> 24747 | D46: =D7+D8 -> 89855
A47: Deferred revenue, current and noncurrent | B47: =B24+B29 -> 10179 | C47: =C24+C29 -> 12116 | D47: =D24+D29 -> 17520
A48: Debt and finance leases, current and noncurrent (carrying) | B48: =B25+B30 -> 13793 | C48: =C25+C30 -> 22896 | D48: =D25+D30 -> 38844
A49: Restricted cash inside prepaid expenses and other current assets | B49: 23 | C49: 182 | D49: 555 | N49: 424B4 p. F-12; 10-Q Q3 2026 p. 11
A50: Restricted cash inside other assets | B50: 93 | C50: 195 | D50: 1537 | N50: 424B4 p. F-12; 10-Q Q3 2026 p. 11
A51: Total assets, 31 Dec 2025, as shown in the 10-Q Q3 comparative column | C51: 92079 | N51: 10-Q Q3 2026 p. 4
A52: Total liabilities, 31 Dec 2025, as shown in the 10-Q Q3 comparative column | C52: 50754 | N52: 10-Q Q3 2026 p. 4
A53: Total shareholders' equity, 31 Dec 2025, as shown in the 10-Q Q3 comparative column | C53: 2573 | N53: 10-Q Q3 2026 p. 4
A54: Cash and cash equivalents, 31 Dec 2025, as shown in the 10-Q Q3 comparative column | C54: 24747 | N54: 10-Q Q3 2026 p. 4
A56: Checks: recomputed less filed (zero passes)
A57: Total current assets | B57: =B7+B8+B9+B10+B11-B12 -> 0 | C57: =C7+C8+C9+C10+C11-C12 -> 0 | D57: =D7+D8+D9+D10+D11-D12 -> 0
A58: Total assets | B58: =B12+B14+B15+B16+B17+B18+B19+B20-B21 -> 0 | C58: =C12+C14+C15+C16+C17+C18+C19+C20-C21 -> 0 | D58: =D12+D14+D15+D16+D17+D18+D19+D20-D21 -> 0
A59: Total current liabilities | B59: =B23+B24+B25+B26-B27 -> 0 | C59: =C23+C24+C25+C26-C27 -> 0 | D59: =D23+D24+D25+D26-D27 -> 0
A60: Total liabilities | B60: =B27+B29+B30+B31-B32 -> 0 | C60: =C27+C29+C30+C31-C32 -> 0 | D60: =D27+D29+D30+D31-D32 -> 0
A61: Total shareholders' equity | B61: =B36+B37+B38+B39+B40+B41-B42 -> 0 | C61: =C36+C37+C38+C39+C40+C41-C42 -> 0 | D61: =D36+D37+D38+D39+D40+D41-D42 -> 0
A62: Liabilities, preferred stock and equity | B62: =B32+B34+B42-B43 -> 0 | C62: =C32+C34+C42-C43 -> 0 | D62: =D32+D34+D42-D43 -> 0
A63: Balance: total assets less the other side | B63: =B21-B43 -> 0 | C63: =C21-C43 -> 0 | D63: =D21-D43 -> 0
A64: 31 Dec 2025 in the 10-Q equals the 424B4 | C64: =ABS(C51-C21)+ABS(C52-C32)+ABS(C53-C42)+ABS(C54-C7) -> 0

Sheet CF_Hist
A1: Space Exploration Technologies Corp. (SpaceX) | Consolidated statements of cash flows, as filed
A2: USD millions. FY: 424B4 p. F-8 and F-9; 9M: 10-Q Q3 2026 p. 9. A blank with 'No such line' means the filing has no such row for that period.
A4: Fiscal year ends 31 December | B4: FY2023A | C4: FY2024A | D4: FY2025A | E4: 9M 2025A | F4: 9M 2026A | M4: Comentarios FG | N4: Source / derivation
A6: Cash flows from operating activities
A7: Net income (loss) | B7: -4628 | C7: 791 | D7: -4937 | E7: -2590 | F7: -413 | N7: FY: 424B4 p. F-8-F-9; 9M: 10-Q Q3 2026 p. 9
A8: Depreciation and amortization | B8: 2635 | C8: 3824 | D8: 6701 | E8: 4784 | F8: 8934 | N8: FY: 424B4 p. F-8-F-9; 9M: 10-Q Q3 2026 p. 9
A9: Share-based compensation | B9: 679 | C9: 784 | D9: 1947 | E9: 1044 | F9: 3833 | N9: FY: 424B4 p. F-8-F-9; 9M: 10-Q Q3 2026 p. 9
A10: Intangible asset impairment | B10: 3775 | N10: FY: 424B4 p. F-8-F-9; 9M: 10-Q Q3 2026 p. 9. Filing shows — (nil) in FY2024A, FY2025A: left blank. No such line in 9M 2025A, 9M 2026A
A11: Deferred income taxes | B11: -409 | C11: -675 | D11: 626 | E11: 623 | F11: -455 | N11: FY: 424B4 p. F-8-F-9; 9M: 10-Q Q3 2026 p. 9
A12: Unrealized (gain) loss on digital assets | C12: -955 | D12: 112 | E12: -389 | F12: 64 | N12: FY: 424B4 p. F-8-F-9; 9M: 10-Q Q3 2026 p. 9. Filing shows — (nil) in FY2023A: left blank
A13: Unrealized gain on investments in unconsolidated affiliates, net | F13: -532 | N13: FY: 424B4 p. F-8-F-9; 9M: 10-Q Q3 2026 p. 9. Filing shows — (nil) in 9M 2025A: left blank. No such line in FY2023A, FY2024A, FY2025A
A14: Impairment and loss on disposal of fixed assets, net | B14: 36 | C14: 135 | D14: 88 | N14: FY: 424B4 p. F-8-F-9; 9M: 10-Q Q3 2026 p. 9. No such line in 9M 2025A, 9M 2026A
A15: Amortization of debt discount and issuance costs | B15: 212 | C15: 84 | D15: 93 | N15: FY: 424B4 p. F-8-F-9; 9M: 10-Q Q3 2026 p. 9. No such line in 9M 2025A, 9M 2026A
A16: Loss on debt extinguishment | F16: 1545 | N16: FY: 424B4 p. F-8-F-9; 9M: 10-Q Q3 2026 p. 9. Filing shows — (nil) in 9M 2025A: left blank. No such line in FY2023A, FY2024A, FY2025A
A17: Other | B17: 214 | C17: 115 | D17: 66 | E17: 193 | F17: -254 | N17: FY: 424B4 p. F-8-F-9; 9M: 10-Q Q3 2026 p. 9
A19: Changes in operating assets and liabilities
A20: Accounts receivable | B20: 345 | C20: -347 | D20: -543 | E20: -934 | F20: -2882 | N20: FY: 424B4 p. F-8-F-9; 9M: 10-Q Q3 2026 p. 9
A21: Inventory | B21: -72 | C21: -309 | D21: -413 | E21: -378 | F21: -1381 | N21: FY: 424B4 p. F-8-F-9; 9M: 10-Q Q3 2026 p. 9
A22: Prepaid expenses and other assets | B22: 41 | C22: -328 | D22: -673 | E22: -427 | F22: -1305 | N22: FY: 424B4 p. F-8-F-9; 9M: 10-Q Q3 2026 p. 9
A23: Accounts payable | B23: 220 | C23: 472 | D23: 709 | E23: 668 | F23: -970 | N23: FY: 424B4 p. F-8-F-9; 9M: 10-Q Q3 2026 p. 9
A24: Deferred revenue | B24: 1695 | C24: 1876 | D24: 1929 | E24: 404 | F24: 4922 | N24: FY: 424B4 p. F-8-F-9; 9M: 10-Q Q3 2026 p. 9
A25: Operating lease liabilities, net | B25: -15 | C25: -37 | D25: -56 | N25: FY: 424B4 p. F-8-F-9; 9M: 10-Q Q3 2026 p. 9. No such line in 9M 2025A, 9M 2026A
A26: Other liabilities (9M: other liabilities, net) | B26: -208 | C26: 346 | D26: 1136 | E26: 1122 | F26: 1991 | N26: FY: 424B4 p. F-8-F-9; 9M: 10-Q Q3 2026 p. 9
A27: Net cash provided by operating activities | B27: 4520 | C27: 5776 | D27: 6785 | E27: 4120 | F27: 13097 | N27: FY: 424B4 p. F-8-F-9; 9M: 10-Q Q3 2026 p. 9
A29: Cash flows from investing activities
A30: Purchases of property, plant, and equipment | B30: -4415 | C30: -11163 | D30: -20737 | E30: -13846 | F30: -48069 | N30: FY: 424B4 p. F-8-F-9; 9M: 10-Q Q3 2026 p. 9
A31: Capitalized interest | D31: -169 | E31: -96 | F31: -20 | N31: FY: 424B4 p. F-8-F-9; 9M: 10-Q Q3 2026 p. 9. Filing shows — (nil) in FY2023A, FY2024A: left blank
A32: Proceeds from product rebates | D32: 118 | F32: 1372 | N32: FY: 424B4 p. F-8-F-9; 9M: 10-Q Q3 2026 p. 9. Filing shows — (nil) in FY2023A, FY2024A, 9M 2025A: left blank
A33: Purchases of marketable securities | B33: -3535 | C33: -3542 | D33: -611 | E33: -601 | F33: -46834 | N33: FY: 424B4 p. F-8-F-9; 9M: 10-Q Q3 2026 p. 9
A34: Maturities of marketable securities | B34: 2731 | C34: 3712 | D34: 548 | E34: 548 | F34: 9158 | N34: FY: 424B4 p. F-8-F-9; 9M: 10-Q Q3 2026 p. 9
A35: Proceeds from sales of marketable securities | B35: 333 | C35: 193 | D35: 1457 | E35: 1173 | F35: 77 | N35: FY: 424B4 p. F-8-F-9; 9M: 10-Q Q3 2026 p. 9
A36: Payments for intangible assets | F36: -866 | N36: FY: 424B4 p. F-8-F-9; 9M: 10-Q Q3 2026 p. 9. Filing shows — (nil) in 9M 2025A: left blank. No such line in FY2023A, FY2024A, FY2025A
A37: Cash received from acquisition of businesses | F37: 514 | N37: FY: 424B4 p. F-8-F-9; 9M: 10-Q Q3 2026 p. 9. Filing shows — (nil) in 9M 2025A: left blank. No such line in FY2023A, FY2024A, FY2025A
A38: Investments in unconsolidated affiliates | D38: -86 | N38: FY: 424B4 p. F-8-F-9; 9M: 10-Q Q3 2026 p. 9. Filing shows — (nil) in FY2023A, FY2024A: left blank. No such line in 9M 2025A, 9M 2026A
A39: Other investing activities, net | B39: 19 | C39: 4 | D39: -95 | E39: -175 | F39: 57 | N39: FY: 424B4 p. F-8-F-9; 9M: 10-Q Q3 2026 p. 9
A40: Net cash used in investing activities | B40: -4867 | C40: -10796 | D40: -19575 | E40: -12997 | F40: -84611 | N40: FY: 424B4 p. F-8-F-9; 9M: 10-Q Q3 2026 p. 9
A42: Cash flows from financing activities
A43: Principal repayments on finance leases | C43: -154 | D43: -295 | E43: -213 | F43: -270 | N43: FY: 424B4 p. F-8-F-9; 9M: 10-Q Q3 2026 p. 9. Filing shows — (nil) in FY2023A: left blank
A44: Proceeds from debt and other financing obligations | D44: 16055 | E44: 10947 | F44: 51834 | N44: FY: 424B4 p. F-8-F-9; 9M: 10-Q Q3 2026 p. 9. Filing shows — (nil) in FY2023A, FY2024A: left blank
A45: Payment of debt issuance costs | D45: -66 | E45: -66 | F45: -124 | N45: FY: 424B4 p. F-8-F-9; 9M: 10-Q Q3 2026 p. 9. Filing shows — (nil) in FY2023A, FY2024A: left blank
A46: Repayments on debt and other financing obligations | B46: -112 | C46: -77 | D46: -6858 | E46: -6014 | F46: -39845 | N46: FY: 424B4 p. F-8-F-9; 9M: 10-Q Q3 2026 p. 9
A47: Payment of debt extinguishment premium | F47: -1153 | N47: FY: 424B4 p. F-8-F-9; 9M: 10-Q Q3 2026 p. 9. Filing shows — (nil) in 9M 2025A: left blank. No such line in FY2023A, FY2024A, FY2025A
A48: Proceeds from issuance of capital stock, net of issuance costs | B48: 774 | C48: 13101 | D48: 18807 | E48: 5299 | F48: 8319 | N48: FY: 424B4 p. F-8-F-9; 9M: 10-Q Q3 2026 p. 9
A49: Proceeds from employee equity award plans | B49: 141 | C49: 224 | D49: 328 | E49: 206 | F49: 368 | N49: FY: 424B4 p. F-8-F-9; 9M: 10-Q Q3 2026 p. 9
A50: Payments for repurchase of common and redeemable convertible preferred stock | B50: -170 | C50: -1021 | D50: -1125 | E50: -525 | F50: -4426 | N50: FY: 424B4 p. F-8-F-9; 9M: 10-Q Q3 2026 p. 9
A51: Taxes paid related to net share settlement of equity awards | B51: -211 | C51: -243 | D51: -496 | E51: -194 | F51: -559 | N51: FY: 424B4 p. F-8-F-9; 9M: 10-Q Q3 2026 p. 9
A52: Proceeds from IPO, net of underwriting commissions and offering costs | F52: 85675 | N52: FY: 424B4 p. F-8-F-9; 9M: 10-Q Q3 2026 p. 9. Filing shows — (nil) in 9M 2025A: left blank. No such line in FY2023A, FY2024A, FY2025A
A53: Net cash provided by financing activities | B53: 422 | C53: 11830 | D53: 26350 | E53: 9440 | F53: 99819 | N53: FY: 424B4 p. F-8-F-9; 9M: 10-Q Q3 2026 p. 9
A54: Effect of exchange rate changes on cash and cash equivalents | B54: -2 | C54: 1 | D54: 63 | E54: 69 | F54: -43 | N54: FY: 424B4 p. F-8-F-9; 9M: 10-Q Q3 2026 p. 9
A55: Net change in cash and cash equivalents and restricted cash | B55: 73 | C55: 6811 | D55: 13623 | E55: 632 | F55: 28262 | N55: FY: 424B4 p. F-8-F-9; 9M: 10-Q Q3 2026 p. 9
A56: Cash and cash equivalents and restricted cash, beginning of period | B56: 4617 | C56: 4690 | D56: 11501 | E56: 11501 | F56: 25124 | N56: FY: 424B4 p. F-8-F-9; 9M: 10-Q Q3 2026 p. 9
A57: Cash and cash equivalents and restricted cash, end of period | B57: 4690 | C57: 11501 | D57: 25124 | E57: 12133 | F57: 53386 | N57: FY: 424B4 p. F-8-F-9; 9M: 10-Q Q3 2026 p. 9
A59: Supplemental disclosures
A60: Cash paid for interest, net of interest capitalized | B60: 1365 | C60: 1500 | D60: 1476 | E60: 695 | F60: 2078 | N60: FY: 424B4 p. F-8-F-9; 9M: 10-Q Q3 2026 p. 9
A61: Cash paid for income taxes, net | B61: 45 | C61: 134 | D61: 154 | E61: 56 | F61: 66 | N61: FY: 424B4 p. F-8-F-9; 9M: 10-Q Q3 2026 p. 9
A62: Purchases of PP&E included in accounts payable and accrued expenses | B62: 505 | C62: 2481 | D62: 7088 | E62: 3573 | F62: 11827 | N62: FY: 424B4 p. F-8-F-9; 9M: 10-Q Q3 2026 p. 9
A63: Purchases of PP&E financed by other financings | F63: 3921 | N63: FY: 424B4 p. F-8-F-9; 9M: 10-Q Q3 2026 p. 9. Filing shows — (nil) in 9M 2025A: left blank. No such line in FY2023A, FY2024A, FY2025A
A64: Share-based compensation capitalized in PP&E | B64: 108 | C64: 132 | D64: 154 | E64: 114 | F64: 160 | N64: FY: 424B4 p. F-8-F-9; 9M: 10-Q Q3 2026 p. 9
A65: Acquisition of businesses through issuance of shares | F65: 42723 | N65: FY: 424B4 p. F-8-F-9; 9M: 10-Q Q3 2026 p. 9. Filing shows — (nil) in 9M 2025A: left blank. No such line in FY2023A, FY2024A, FY2025A
A67: Checks: recomputed less filed (zero passes)
A68: Net cash provided by operating activities | B68: =B7+B8+B9+B10+B11+B12+B13+B14+B15+B16+B17+B20+B21+B22+B23+B24+B25+B26-B27 -> 0 | C68: =C7+C8+C9+C10+C11+C12+C13+C14+C15+C16+C17+C20+C21+C22+C23+C24+C25+C26-C27 -> 0 | D68: =D7+D8+D9+D10+D11+D12+D13+D14+D15+D16+D17+D20+D21+D22+D23+D24+D25+D26-D27 -> 0 | E68: =E7+E8+E9+E10+E11+E12+E13+E14+E15+E16+E17+E20+E21+E22+E23+E24+E25+E26-E27 -> 0 | F68: =F7+F8+F9+F10+F11+F12+F13+F14+F15+F16+F17+F20+F21+F22+F23+F24+F25+F26-F27 -> 0
A69: Net cash used in investing activities | B69: =B30+B31+B32+B33+B34+B35+B36+B37+B38+B39-B40 -> 0 | C69: =C30+C31+C32+C33+C34+C35+C36+C37+C38+C39-C40 -> 0 | D69: =D30+D31+D32+D33+D34+D35+D36+D37+D38+D39-D40 -> 0 | E69: =E30+E31+E32+E33+E34+E35+E36+E37+E38+E39-E40 -> 0 | F69: =F30+F31+F32+F33+F34+F35+F36+F37+F38+F39-F40 -> 0
A70: Net cash provided by financing activities | B70: =B43+B44+B45+B46+B47+B48+B49+B50+B51+B52-B53 -> 0 | C70: =C43+C44+C45+C46+C47+C48+C49+C50+C51+C52-C53 -> 0 | D70: =D43+D44+D45+D46+D47+D48+D49+D50+D51+D52-D53 -> 0 | E70: =E43+E44+E45+E46+E47+E48+E49+E50+E51+E52-E53 -> 0 | F70: =F43+F44+F45+F46+F47+F48+F49+F50+F51+F52-F53 -> 0
A71: Net change in cash | B71: =B27+B40+B53+B54-B55 -> 0 | C71: =C27+C40+C53+C54-C55 -> 0 | D71: =D27+D40+D53+D54-D55 -> 0 | E71: =E27+E40+E53+E54-E55 -> 0 | F71: =F27+F40+F53+F54-F55 -> 0
A72: Beginning cash plus change less ending cash | B72: =B56+B55-B57 -> 0 | C72: =C56+C55-C57 -> 0 | D72: =D56+D55-D57 -> 0 | E72: =E56+E55-E57 -> 0 | F72: =F56+F55-F57 -> 0
A73: Net income equals the statement of operations | B73: =B7-IS_Hist!B20 -> 0 | C73: =C7-IS_Hist!C20 -> 0 | D73: =D7-IS_Hist!D20 -> 0 | E73: =E7-IS_Hist!E20 -> 0 | F73: =F7-IS_Hist!F20 -> 0
A74: Ending cash equals balance sheet cash plus restricted cash | C74: =C57-BS_Hist!B7-BS_Hist!B49-BS_Hist!B50 -> 0 | D74: =D57-BS_Hist!C7-BS_Hist!C49-BS_Hist!C50 -> 0 | F74: =F57-BS_Hist!D7-BS_Hist!D49-BS_Hist!D50 -> 0 | N74: FY2024A against 31 Dec 2024, FY2025A against 31 Dec 2025, 9M 2026A against 30 Sep 2026; no balance sheet at 30 Sep 2025 in these filings.
A75: Beginning cash of each period equals the prior year end | C75: =C56-B57 -> 0 | D75: =D56-C57 -> 0 | E75: =E56-C57 -> 0 | F75: =F56-D57 -> 0

Sheet SCE_Hist
A1: Space Exploration Technologies Corp. (SpaceX) | Statements of redeemable convertible preferred stock and shareholders' equity, as filed
A2: USD millions; shares in millions. FY2023-FY2025: 424B4 p. F-7; nine months: 10-Q Q3 2026 p. 7 and 8. Cells the filing shows as — are blank.
A4: Line | B4: Preferred shares | C4: Preferred amount | D4: Common shares | E4: Common amount | F4: Additional paid-in capital | G4: Accumulated deficit | H4: AOCI | I4: Total shareholders' equity | J4: Comentarios FG | K4: Source / derivation
A6: Fiscal years 2023 to 2025 (audited)
A7: Balances at December 31, 2022 | B7: 136 | C7: 7239 | D7: 2742 | E7: 3 | F7: 35275 | G7: -28757 | H7: 1262 | I7: 7783 | K7: 424B4 p. F-7
A8: Share-based compensation | C8: 3 | F8: 784 | I8: 784 | K8: 424B4 p. F-7. Filing shows — (nil) in Preferred shares, Common shares, Common amount, Accumulated deficit, AOCI: left blank
A9: Issuance of redeemable convertible preferred stock | B9: 750 | C9: 750 | K9: 424B4 p. F-7. Filing shows — (nil) in Common shares, Common amount, Additional paid-in capital, Accumulated deficit, AOCI, Total shareholders' equity: left blank
A10: Common stock issued, net of tax withholding | D10: 249 | E10: 0 | F10: -41 | I10: -41 | K10: 424B4 p. F-7. Filing shows — (nil) in Preferred shares, Preferred amount, Accumulated deficit, AOCI: left blank
A11: Repurchase of common stock | D11: -11 | E11: 0 | F11: -170 | I11: -170 | K11: 424B4 p. F-7. Filing shows — (nil) in Preferred shares, Preferred amount, Accumulated deficit, AOCI: left blank
A12: Net loss | G12: -4628 | I12: -4628 | K12: 424B4 p. F-7. Filing shows — (nil) in Preferred shares, Preferred amount, Common shares, Common amount, Additional paid-in capital, AOCI: left blank
A13: Other comprehensive income (loss) | H13: 223 | I13: 223 | K13: 424B4 p. F-7. Filing shows — (nil) in Preferred shares, Preferred amount, Common shares, Common amount, Additional paid-in capital, Accumulated deficit: left blank
A14: Balances at December 31, 2023 | B14: 886 | C14: 7992 | D14: 2980 | E14: 3 | F14: 35848 | G14: -33385 | H14: 1485 | I14: 3951 | K14: 424B4 p. F-7
A15: Roll-forward to December 31, 2023: opening + movements - closing | B15: =B7+SUM(B8:B13)-B14 -> 0 | C15: =C7+SUM(C8:C13)-C14 -> 0 | D15: =D7+SUM(D8:D13)-D14 -> 0 | E15: =E7+SUM(E8:E13)-E14 -> 0 | F15: =F7+SUM(F8:F13)-F14 -> 0 | G15: =G7+SUM(G8:G13)-G14 -> 0 | H15: =H7+SUM(H8:H13)-H14 -> 0 | I15: =I7+SUM(I8:I13)-I14 -> 0
A16: Adjustment for prior periods from adoption of ASU 2023-08 | G16: 496 | I16: 496 | K16: 424B4 p. F-7. Filing shows — (nil) in Preferred shares, Preferred amount, Common shares, Common amount, Additional paid-in capital, AOCI: left blank
A17: Share-based compensation | F17: 914 | I17: 914 | K17: 424B4 p. F-7. Filing shows — (nil) in Preferred shares, Preferred amount, Common shares, Common amount, Accumulated deficit, AOCI: left blank
A18: Issuance of redeemable convertible preferred stock | B18: 862 | C18: 13001 | K18: 424B4 p. F-7. Filing shows — (nil) in Common shares, Common amount, Additional paid-in capital, Accumulated deficit, AOCI, Total shareholders' equity: left blank
A19: Common stock issued, net of tax withholding | D19: 75 | E19: 0 | F19: 72 | I19: 72 | K19: 424B4 p. F-7. Filing shows — (nil) in Preferred shares, Preferred amount, Accumulated deficit, AOCI: left blank
A20: Repurchase of common and redeemable convertible preferred stock | B20: 0 | C20: -21 | D20: -46 | E20: 0 | F20: -1000 | I20: -1000 | K20: 424B4 p. F-7. Filing shows — (nil) in Accumulated deficit, AOCI: left blank
A21: Conversion of redeemable convertible preferred stock to common stock | B21: 0 | C21: -31 | D21: 14 | E21: 0 | F21: 31 | I21: 31 | K21: 424B4 p. F-7. Filing shows — (nil) in Accumulated deficit, AOCI: left blank
A22: Net income | G22: 791 | I22: 791 | K22: 424B4 p. F-7. Filing shows — (nil) in Preferred shares, Preferred amount, Common shares, Common amount, Additional paid-in capital, AOCI: left blank
A23: Other comprehensive income (loss) | H23: -392 | I23: -392 | K23: 424B4 p. F-7. Filing shows — (nil) in Preferred shares, Preferred amount, Common shares, Common amount, Additional paid-in capital, Accumulated deficit: left blank
A24: Balances at December 31, 2024 | B24: 1748 | C24: 20941 | D24: 3023 | E24: 3 | F24: 35865 | G24: -32098 | H24: 1093 | I24: 4863 | K24: 424B4 p. F-7
A25: Roll-forward to December 31, 2024: opening + movements - closing | B25: =B14+SUM(B16:B23)-B24 -> 0 | C25: =C14+SUM(C16:C23)-C24 -> 0 | D25: =D14+SUM(D16:D23)-D24 -> 0 | E25: =E14+SUM(E16:E23)-E24 -> 0 | F25: =F14+SUM(F16:F23)-F24 -> 0 | G25: =G14+SUM(G16:G23)-G24 -> 0 | H25: =H14+SUM(H16:H23)-H24 -> 0 | I25: =I14+SUM(I16:I23)-I24 -> 0
A26: Share-based compensation | F26: 2087 | I26: 2087 | K26: 424B4 p. F-7. Filing shows — (nil) in Preferred shares, Preferred amount, Common shares, Common amount, Accumulated deficit, AOCI: left blank
A27: Issuance of redeemable convertible preferred stock | B27: 299 | C27: 17898 | K27: 424B4 p. F-7. Filing shows — (nil) in Common shares, Common amount, Additional paid-in capital, Accumulated deficit, AOCI, Total shareholders' equity: left blank
A28: Common stock issued, net of tax withholding | D28: 97 | E28: 1 | F28: 740 | I28: 741 | K28: 424B4 p. F-7. Filing shows — (nil) in Preferred shares, Preferred amount, Accumulated deficit, AOCI: left blank
A29: Repurchase of common stock | D29: -69 | E29: 0 | F29: -1125 | I29: -1125 | K29: 424B4 p. F-7. Filing shows — (nil) in Preferred shares, Preferred amount, Accumulated deficit, AOCI: left blank
A30: Conversion of redeemable convertible preferred stock to common stock | B30: -1 | C30: -87 | D30: 28 | E30: 0 | F30: 87 | I30: 87 | K30: 424B4 p. F-7. Filing shows — (nil) in Accumulated deficit, AOCI: left blank
A31: Transfer of equity in business combination | D31: 0 | E31: 0 | F31: 52 | I31: 52 | K31: 424B4 p. F-7. Filing shows — (nil) in Preferred shares, Preferred amount, Accumulated deficit, AOCI: left blank
A32: Net loss | G32: -4937 | I32: -4937 | K32: 424B4 p. F-7. Filing shows — (nil) in Preferred shares, Preferred amount, Common shares, Common amount, Additional paid-in capital, AOCI: left blank
A33: Other comprehensive income (loss) | H33: 805 | I33: 805 | K33: 424B4 p. F-7. Filing shows — (nil) in Preferred shares, Preferred amount, Common shares, Common amount, Additional paid-in capital, Accumulated deficit: left blank
A34: Balances at December 31, 2025 | B34: 2046 | C34: 38752 | D34: 3079 | E34: 4 | F34: 37706 | G34: -37035 | H34: 1898 | I34: 2573 | K34: 424B4 p. F-7
A35: Roll-forward to December 31, 2025: opening + movements - closing | B35: =B24+SUM(B26:B33)-B34 -> 0 | C35: =C24+SUM(C26:C33)-C34 -> 0 | D35: =D24+SUM(D26:D33)-D34 -> 0 | E35: =E24+SUM(E26:E33)-E34 -> 0 | F35: =F24+SUM(F26:F33)-F34 -> 0 | G35: =G24+SUM(G26:G33)-G34 -> 0 | H35: =H24+SUM(H26:H33)-H34 -> 0 | I35: =I24+SUM(I26:I33)-I34 -> 0
A37: Nine months ended 30 September 2025 (unaudited)
A38: Balances at December 31, 2024 | B38: 1748 | C38: 20941 | D38: 3023 | E38: 3 | F38: 35865 | G38: -32098 | H38: 1093 | I38: 4863 | K38: 10-Q Q3 2026 p. 8
A39: Share-based compensation | F39: 1150 | I39: 1150 | K39: 10-Q Q3 2026 p. 8. Filing shows — (nil) in Preferred shares, Preferred amount, Common shares, Common amount, Accumulated deficit, AOCI: left blank
A40: Issuance of redeemable convertible preferred stock | B40: 145 | C40: 4388 | K40: 10-Q Q3 2026 p. 8. Filing shows — (nil) in Common shares, Common amount, Additional paid-in capital, Accumulated deficit, AOCI, Total shareholders' equity: left blank
A41: Common stock issued, net of tax withholding | D41: 62 | E41: 1 | F41: 922 | I41: 923 | K41: 10-Q Q3 2026 p. 8. Filing shows — (nil) in Preferred shares, Preferred amount, Accumulated deficit, AOCI: left blank
A42: Conversion of redeemable convertible preferred stock to common stock | B42: 0 | C42: -1 | D42: 2 | E42: 0 | F42: 1 | I42: 1 | K42: 10-Q Q3 2026 p. 8. Filing shows — (nil) in Accumulated deficit, AOCI: left blank
A43: Repurchase of common stock | D43: -47 | E43: 0 | F43: -523 | I43: -523 | K43: 10-Q Q3 2026 p. 8. Filing shows — (nil) in Preferred shares, Preferred amount, Accumulated deficit, AOCI: left blank
A44: Transfer of equity in business combination | D44: 1 | E44: 0 | F44: 39 | I44: 39 | K44: 10-Q Q3 2026 p. 8. Filing shows — (nil) in Preferred shares, Preferred amount, Accumulated deficit, AOCI: left blank
A45: Net loss | G45: -2590 | I45: -2590 | K45: 10-Q Q3 2026 p. 8. Filing shows — (nil) in Preferred shares, Preferred amount, Common shares, Common amount, Additional paid-in capital, AOCI: left blank
A46: Other comprehensive income | H46: 792 | I46: 792 | K46: 10-Q Q3 2026 p. 8. Filing shows — (nil) in Preferred shares, Preferred amount, Common shares, Common amount, Additional paid-in capital, Accumulated deficit: left blank
A47: Balances at September 30, 2025 | B47: 1893 | C47: 25328 | D47: 3041 | E47: 4 | F47: 37454 | G47: -34688 | H47: 1885 | I47: 4655 | K47: 10-Q Q3 2026 p. 8
A48: Roll-forward to September 30, 2025: opening + movements - closing | B48: =B38+SUM(B39:B46)-B47 -> 0 | C48: =C38+SUM(C39:C46)-C47 -> 0 | D48: =D38+SUM(D39:D46)-D47 -> 0 | E48: =E38+SUM(E39:E46)-E47 -> 0 | F48: =F38+SUM(F39:F46)-F47 -> 0 | G48: =G38+SUM(G39:G46)-G47 -> 0 | H48: =H38+SUM(H39:H46)-H47 -> 0 | I48: =I38+SUM(I39:I46)-I47 -> 0
A50: Nine months ended 30 September 2026 (unaudited)
A51: Balances at December 31, 2025 | B51: 2046 | C51: 38752 | D51: 3079 | E51: 4 | F51: 37706 | G51: -37035 | H51: 1898 | I51: 2573 | K51: 10-Q Q3 2026 p. 7
A52: Share-based compensation | F52: 3991 | I52: 3991 | K52: 10-Q Q3 2026 p. 7. Filing shows — (nil) in Preferred shares, Preferred amount, Common shares, Common amount, Accumulated deficit, AOCI: left blank
A53: Issuance of common stock in connection with IPO, net of underwriting commissions and offering costs | D53: 639 | E53: 1 | F53: 85674 | I53: 85675 | K53: 10-Q Q3 2026 p. 7. Filing shows — (nil) in Preferred shares, Preferred amount, Accumulated deficit, AOCI: left blank
A54: Issuance of redeemable convertible preferred stock | B54: 78 | C54: 5869 | K54: 10-Q Q3 2026 p. 7. Filing shows — (nil) in Common shares, Common amount, Additional paid-in capital, Accumulated deficit, AOCI, Total shareholders' equity: left blank
A55: Common stock issued, net of tax withholding | D55: 1381 | E55: 1 | F55: 2258 | I55: 2259 | K55: 10-Q Q3 2026 p. 7. Filing shows — (nil) in Preferred shares, Preferred amount, Accumulated deficit, AOCI: left blank
A56: Conversion of redeemable convertible preferred stock pursuant to xAI Merger | B56: -1987 | C56: -37476 | D56: 1424 | E56: 1 | F56: 37474 | I56: 37475 | K56: 10-Q Q3 2026 p. 7. Filing shows — (nil) in Accumulated deficit, AOCI: left blank
A57: Repurchase of common stock pursuant to xAI Merger | D57: -25 | E57: 0 | F57: -2413 | I57: -2413 | K57: 10-Q Q3 2026 p. 7. Filing shows — (nil) in Preferred shares, Preferred amount, Accumulated deficit, AOCI: left blank
A58: Conversion of redeemable convertible preferred stock to common stock | B58: -135 | C58: -7076 | D58: 6728 | E58: 6 | F58: 7070 | I58: 7076 | K58: 10-Q Q3 2026 p. 7. Filing shows — (nil) in Accumulated deficit, AOCI: left blank
A59: Repurchase of common and redeemable convertible preferred stock | B59: -2 | C59: -69 | D59: -41 | E59: 0 | F59: -1944 | I59: -1944 | K59: 10-Q Q3 2026 p. 7. Filing shows — (nil) in Accumulated deficit, AOCI: left blank
A60: Transfer of equity in business combinations | D60: 394 | F60: 42723 | I60: 42723 | K60: 10-Q Q3 2026 p. 7. Filing shows — (nil) in Preferred shares, Preferred amount, Common amount, Accumulated deficit, AOCI: left blank
A61: Net loss | G61: -413 | I61: -413 | K61: 10-Q Q3 2026 p. 7. Filing shows — (nil) in Preferred shares, Preferred amount, Common shares, Common amount, Additional paid-in capital, AOCI: left blank
A62: Other comprehensive loss | H62: -234 | I62: -234 | K62: 10-Q Q3 2026 p. 7. Filing shows — (nil) in Preferred shares, Preferred amount, Common shares, Common amount, Additional paid-in capital, Accumulated deficit: left blank
A63: Balances at September 30, 2026 | D63: 13579 | E63: 13 | F63: 212539 | G63: -37448 | H63: 1664 | I63: 176768 | K63: 10-Q Q3 2026 p. 7. Filing shows — (nil) in Preferred shares, Preferred amount: left blank
A64: Roll-forward to September 30, 2026: opening + movements - closing | B64: =B51+SUM(B52:B62)-B63 -> 0 | C64: =C51+SUM(C52:C62)-C63 -> 0 | D64: =D51+SUM(D52:D62)-D63 -> 0 | E64: =E51+SUM(E52:E62)-E63 -> 0 | F64: =F51+SUM(F52:F62)-F63 -> 0 | G64: =G51+SUM(G52:G62)-G63 -> 0 | H64: =H51+SUM(H52:H62)-H63 -> 0 | I64: =I51+SUM(I52:I62)-I63 -> 0
A66: Checks (zero passes)
A67: Total = common + APIC + deficit + AOCI: bal_fy_dec2022 | I67: =E7+F7+G7+H7-I7 -> 0
A68: Total = common + APIC + deficit + AOCI: bal_fy_dec2023 | I68: =E14+F14+G14+H14-I14 -> 0
A69: Total = common + APIC + deficit + AOCI: bal_fy_dec2024 | I69: =E24+F24+G24+H24-I24 -> 0
A70: Total = common + APIC + deficit + AOCI: bal_fy_dec2025 | I70: =E34+F34+G34+H34-I34 -> 0
A71: Total = common + APIC + deficit + AOCI: bal_q3_9m25_dec2024 | I71: =E38+F38+G38+H38-I38 -> 0
A72: Total = common + APIC + deficit + AOCI: bal_q3_9m25_sep2025 | I72: =E47+F47+G47+H47-I47 -> 0
A73: Total = common + APIC + deficit + AOCI: bal_q3_9m26_dec2025 | I73: =E51+F51+G51+H51-I51 -> 0
A74: Total = common + APIC + deficit + AOCI: bal_q3_9m26_sep2026 | I74: =E63+F63+G63+H63-I63 -> 0
A75: Equity and preferred equal the balance sheet: bal_fy_dec2024 | I75: =ABS(I24-BS_Hist!B42)+ABS(C24-N(BS_Hist!B34)) -> 0
A76: Equity and preferred equal the balance sheet: bal_fy_dec2025 | I76: =ABS(I34-BS_Hist!C42)+ABS(C34-N(BS_Hist!C34)) -> 0
A77: Equity and preferred equal the balance sheet: bal_q3_9m26_sep2026 | I77: =ABS(I63-BS_Hist!D42)+ABS(C63-N(BS_Hist!D34)) -> 0

Sheet Quarterly_Hist
A1: Space Exploration Technologies Corp. (SpaceX) | Quarterly statements of operations, Q1 2025 to Q3 2026
A2: USD millions, unaudited. Q1: 424B4 (Q1 2025 and Q1 2026 columns); Q2: 10-Q Q2 2026; Q3: 10-Q Q3 2026. Q4 2025A is derived: FY2025 less nine months 2025 (formula).
A4: Three months ended | B4: Q1 2025A | C4: Q2 2025A | D4: Q3 2025A | E4: Q4 2025A | F4: Q1 2026A | G4: Q2 2026A | H4: Q3 2026A | M4: Comentarios FG | N4: Source / derivation
A6: Revenue | B6: 4067 | C6: 4071 | D6: 5576 | E6: =IS_Hist!D6-IS_Hist!E6 -> 4960 | F6: 4694 | G6: 7814 | H6: 14575 | N6: Q1: 424B4 p. F-64; Q2: 10-Q Q2 2026 p. 4; Q3: 10-Q Q3 2026 p. 4; Q4 2025A: IS_Hist FY2025 less 9M 2025
A7: Cost of revenue | B7: 1962 | C7: 2282 | D7: 2705 | E7: =IS_Hist!D8-IS_Hist!E8 -> 2502 | F7: 2388 | G7: 3495 | H7: 5478 | N7: Q1: 424B4 p. F-64; Q2: 10-Q Q2 2026 p. 4; Q3: 10-Q Q3 2026 p. 4; Q4 2025A: IS_Hist FY2025 less 9M 2025
A8: Research and development | B8: 1557 | C8: 1958 | D8: 2291 | E8: =IS_Hist!D9-IS_Hist!E9 -> 2837 | F8: 3514 | G8: 3548 | H8: 4596 | N8: Q1: 424B4 p. F-64; Q2: 10-Q Q2 2026 p. 4; Q3: 10-Q Q3 2026 p. 4; Q4 2025A: IS_Hist FY2025 less 9M 2025
A9: Selling, general, and administrative | B9: 493 | C9: 606 | D9: 575 | E9: =IS_Hist!D10-IS_Hist!E10 -> 970 | F9: 746 | G9: 912 | H9: 1707 | N9: Q1: 424B4 p. F-64; Q2: 10-Q Q2 2026 p. 4; Q3: 10-Q Q3 2026 p. 4; Q4 2025A: IS_Hist FY2025 less 9M 2025
A10: Restructuring charges (credits) | B10: 4 | C10: 190 | D10: 278 | E10: =IS_Hist!D11-IS_Hist!E11 -> 15 | F10: -11 | G10: 2 | H10: 3 | N10: Q1: 424B4 p. F-64; Q2: 10-Q Q2 2026 p. 4; Q3: 10-Q Q3 2026 p. 4; Q4 2025A: IS_Hist FY2025 less 9M 2025
A11: Impairment | B11: 24 | C11: 5 | E11: =IS_Hist!D12-IS_Hist!E12 -> 9 | N11: Q1: 424B4 p. F-64; Q2: 10-Q Q2 2026 p. 4; Q3: 10-Q Q3 2026 p. 4; Q4 2025A: IS_Hist FY2025 less 9M 2025. Filing shows — (nil) in Q3 2025A, Q1 2026A, Q2 2026A, Q3 2026A: left blank
A12: Total costs and expenses | B12: 4040 | C12: 5041 | D12: 5849 | E12: =IS_Hist!D13-IS_Hist!E13 -> 6333 | F12: 6637 | G12: 7957 | H12: 11784 | N12: Q1: 424B4 p. F-64; Q2: 10-Q Q2 2026 p. 4; Q3: 10-Q Q3 2026 p. 4; Q4 2025A: IS_Hist FY2025 less 9M 2025
A13: Income (loss) from operations | B13: 27 | C13: -970 | D13: -273 | E13: =IS_Hist!D14-IS_Hist!E14 -> -1373 | F13: -1943 | G13: -143 | H13: 2791 | N13: Q1: 424B4 p. F-64; Q2: 10-Q Q2 2026 p. 4; Q3: 10-Q Q3 2026 p. 4; Q4 2025A: IS_Hist FY2025 less 9M 2025
A14: Interest expense | B14: -447 | C14: -411 | D14: -514 | E14: =IS_Hist!D15-IS_Hist!E15 -> -573 | F14: -664 | G14: -629 | H14: -675 | N14: Q1: 424B4 p. F-64; Q2: 10-Q Q2 2026 p. 4; Q3: 10-Q Q3 2026 p. 4; Q4 2025A: IS_Hist FY2025 less 9M 2025
A15: Interest income | B15: 117 | C15: 98 | D15: 155 | E15: =IS_Hist!D16-IS_Hist!E16 -> 122 | F15: 213 | G15: 340 | H15: 873 | N15: Q1: 424B4 p. F-64; Q2: 10-Q Q2 2026 p. 4; Q3: 10-Q Q3 2026 p. 4; Q4 2025A: IS_Hist FY2025 less 9M 2025
A16: Other income (expense), net | B16: -211 | C16: 413 | D16: 140 | E16: =IS_Hist!D17-IS_Hist!E17 -> -519 | F16: -1876 | G16: -86 | H16: 1025 | N16: Q1: 424B4 p. F-64; Q2: 10-Q Q2 2026 p. 4; Q3: 10-Q Q3 2026 p. 4; Q4 2025A: IS_Hist FY2025 less 9M 2025
A17: Income (loss) before income taxes | B17: -514 | C17: -870 | D17: -492 | E17: =IS_Hist!D18-IS_Hist!E18 -> -2343 | F17: -4270 | G17: -518 | H17: 4014 | N17: Q1: 424B4 p. F-64; Q2: 10-Q Q2 2026 p. 4; Q3: 10-Q Q3 2026 p. 4; Q4 2025A: IS_Hist FY2025 less 9M 2025
A18: Provision for (benefit from) income taxes | B18: 14 | C18: 138 | D18: 562 | E18: =IS_Hist!D19-IS_Hist!E19 -> 4 | F18: 6 | G18: 23 | H18: -390 | N18: Q1: 424B4 p. F-64; Q2: 10-Q Q2 2026 p. 4; Q3: 10-Q Q3 2026 p. 4; Q4 2025A: IS_Hist FY2025 less 9M 2025
A19: Net income (loss) | B19: -528 | C19: -1008 | D19: -1054 | E19: =IS_Hist!D20-IS_Hist!E20 -> -2347 | F19: -4276 | G19: -541 | H19: 4404 | N19: Q1: 424B4 p. F-64; Q2: 10-Q Q2 2026 p. 4; Q3: 10-Q Q3 2026 p. 4; Q4 2025A: IS_Hist FY2025 less 9M 2025
A20: Depreciation and amortization (memo) | B20: 1443 | C20: =SUM(Segments_Hist!C117:Segments_Hist!C119) -> 1526 | D20: =SUM(Segments_Hist!D117:Segments_Hist!D119) -> 1814 | E20: =CF_Hist!D8-CF_Hist!E8 -> 1917 | F20: 2442 | G20: =SUM(Segments_Hist!G117:Segments_Hist!G119) -> 2848 | H20: =SUM(Segments_Hist!H117:Segments_Hist!H119) -> 3644 | N20: Q1: 424B4 p. 119 (adjusted EBITDA reconciliation); Q2, Q3: sum of segment D&A (Segments_Hist); Q4 2025A: cash flow FY less 9M
A21: Segment adjusted EBITDA, total (memo) | B21: =SUM(Segments_Hist!B107:Segments_Hist!B109) -> 1730 | C21: =SUM(Segments_Hist!C107:Segments_Hist!C109) -> 1214 | D21: =SUM(Segments_Hist!D107:Segments_Hist!D109) -> 2169 | E21: =SUM(Segments_Hist!E107:Segments_Hist!E109) -> 1471 | F21: =SUM(Segments_Hist!F107:Segments_Hist!F109) -> 1127 | G21: =SUM(Segments_Hist!G107:Segments_Hist!G109) -> 3538 | H21: =SUM(Segments_Hist!H107:Segments_Hist!H109) -> 8809 | N21: Segments_Hist
A23: Ratios (derived)
A24: Revenue: growth on the prior quarter | C24: =C6/B6-1 -> 0.00098352594 | D24: =D6/C6-1 -> 0.36968804 | E24: =E6/D6-1 -> -0.11047346 | F24: =F6/E6-1 -> -0.053629032 | G24: =G6/F6-1 -> 0.66467831 | H24: =H6/G6-1 -> 0.86524187
A25: Operating margin | B25: =B13/B6 -> 0.0066388001 | C25: =C13/C6 -> -0.2382707 | D25: =D13/D6 -> -0.048959828 | E25: =E13/E6 -> -0.27681452 | F25: =F13/F6 -> -0.41393268 | G25: =G13/G6 -> -0.018300486 | H25: =H13/H6 -> 0.19149228
A26: Segment adjusted EBITDA margin | B26: =B21/B6 -> 0.42537497 | C26: =C21/C6 -> 0.29820683 | D26: =D21/D6 -> 0.38898852 | E26: =E21/E6 -> 0.29657258 | F26: =F21/F6 -> 0.24009374 | G26: =G21/G6 -> 0.45277707 | H26: =H21/H6 -> 0.60439108
A28: Checks (zero passes)
A29: Total costs and expenses | B29: =B7+B8+B9+B10+B11-B12 -> 0 | C29: =C7+C8+C9+C10+C11-C12 -> 0 | D29: =D7+D8+D9+D10+D11-D12 -> 0 | E29: =E7+E8+E9+E10+E11-E12 -> 0 | F29: =F7+F8+F9+F10+F11-F12 -> 0 | G29: =G7+G8+G9+G10+G11-G12 -> 0 | H29: =H7+H8+H9+H10+H11-H12 -> 0
A30: Operating result | B30: =B6-B12-B13 -> 0 | C30: =C6-C12-C13 -> 0 | D30: =D6-D12-D13 -> 0 | E30: =E6-E12-E13 -> 0 | F30: =F6-F12-F13 -> 0 | G30: =G6-G12-G13 -> 0 | H30: =H6-H12-H13 -> 0
A31: Net income (loss) | B31: =B13+B14+B15+B16-B18-B19 -> 0 | C31: =C13+C14+C15+C16-C18-C19 -> 0 | D31: =D13+D14+D15+D16-D18-D19 -> 0 | E31: =E13+E14+E15+E16-E18-E19 -> 0 | F31: =F13+F14+F15+F16-F18-F19 -> 0 | G31: =G13+G14+G15+G16-G18-G19 -> 0 | H31: =H13+H14+H15+H16-H18-H19 -> 0
A32: Quarters add up to nine months: revenue | B32: =SUM(B6:D6)-IS_Hist!E6 -> 0 | F32: =SUM(F6:H6)-IS_Hist!F6 -> 0 | N32: B: Q1-Q3 2025 against 9M 2025; F: Q1-Q3 2026 against 9M 2026. Q4 2025 is derived, so FY2025 adds up by construction.
A33: Quarters add up to nine months: total costs and expenses | B33: =SUM(B12:D12)-IS_Hist!E13 -> 0 | F33: =SUM(F12:H12)-IS_Hist!F13 -> 0 | N33: B: Q1-Q3 2025 against 9M 2025; F: Q1-Q3 2026 against 9M 2026. Q4 2025 is derived, so FY2025 adds up by construction.
A34: Quarters add up to nine months: income (loss) from operations | B34: =SUM(B13:D13)-IS_Hist!E14 -> 0 | F34: =SUM(F13:H13)-IS_Hist!F14 -> 0 | N34: B: Q1-Q3 2025 against 9M 2025; F: Q1-Q3 2026 against 9M 2026. Q4 2025 is derived, so FY2025 adds up by construction.
A35: Quarters add up to nine months: net income (loss) | B35: =SUM(B19:D19)-IS_Hist!E20 -> 0 | F35: =SUM(F19:H19)-IS_Hist!F20 -> 0 | N35: B: Q1-Q3 2025 against 9M 2025; F: Q1-Q3 2026 against 9M 2026. Q4 2025 is derived, so FY2025 adds up by construction.

Sheet Segments_Hist
A1: Space Exploration Technologies Corp. (SpaceX) | Segments, revenue by type, operating data and customers, as filed
A2: USD millions unless stated. The AI segment is called SI (Super Intelligence) from Q3 2026; same segment. Block A: years and nine months; block B: quarters.
A4: Fiscal year ends 31 December | B4: FY2023A | C4: FY2024A | D4: FY2025A | E4: 9M 2025A | F4: 9M 2026A | M4: Comentarios FG | N4: Source / derivation
A6: A1. Revenue by type and segment
A7: Launch Services | B7: 1964 | C7: 2584 | D7: 2576 | E7: 2056 | F7: 2108 | N7: FY: 424B4 p. F-22; 9M: 10-Q Q3 2026 p. 13
A8: Launch & Development | B8: 1593 | C8: 1212 | D8: 1510 | E8: 1221 | F8: 1240 | N8: FY: 424B4 p. F-22; 9M: 10-Q Q3 2026 p. 13
A9: Space | B9: 3557 | C9: 3796 | D9: 4086 | E9: 3277 | F9: 3348 | N9: FY: 424B4 p. F-22; 9M: 10-Q Q3 2026 p. 13
A10: Consumer | B10: 2817 | C10: 4830 | D10: 7208 | E10: 5198 | F10: 7754 | N10: FY: 424B4 p. F-22; 9M: 10-Q Q3 2026 p. 13
A11: Enterprise & Government | B11: 1052 | C11: 2769 | D11: 4179 | E11: 2961 | F11: 5042 | N11: FY: 424B4 p. F-22; 9M: 10-Q Q3 2026 p. 13
A12: Connectivity | B12: 3869 | C12: 7599 | D12: 11387 | E12: 8159 | F12: 12796 | N12: FY: 424B4 p. F-22; 9M: 10-Q Q3 2026 p. 13
A13: Advertising | B13: 2323 | C13: 1728 | D13: 1844 | E13: 1323 | F13: 1248 | N13: FY: 424B4 p. F-22; 9M: 10-Q Q3 2026 p. 13
A14: SI (AI) solutions & infrastructure | B14: 638 | C14: 892 | D14: 1357 | E14: 955 | F14: 9691 | N14: FY: 424B4 p. F-22; 9M: 10-Q Q3 2026 p. 13
A15: SI (AI) | B15: 2961 | C15: 2620 | D15: 3201 | E15: 2278 | F15: 10939 | N15: FY: 424B4 p. F-22; 9M: 10-Q Q3 2026 p. 13
A16: Total revenues | B16: 10387 | C16: 14015 | D16: 18674 | E16: 13714 | F16: 27083 | N16: FY: 424B4 p. F-22; 9M: 10-Q Q3 2026 p. 13
A18: A. Segment income (loss) from operations
A19: Space | B19: -1 | C19: 21 | D19: -657 | E19: -181 | F19: -1211 | N19: FY: 424B4 p. F-57-F-58 and 24; 9M: 10-Q Q3 2026 p. 33, 34
A20: Connectivity | B20: 469 | C20: 2006 | D20: 4423 | E20: 3147 | F20: 5211 | N20: FY: 424B4 p. F-57-F-58 and 24; 9M: 10-Q Q3 2026 p. 33, 34
A21: SI (formerly AI) | B21: -3973 | C21: -1561 | D21: -6355 | E21: -4182 | F21: -3295 | N21: FY: 424B4 p. F-57-F-58 and 24; 9M: 10-Q Q3 2026 p. 33, 34
A23: A. Depreciation and amortization
A24: Space | B24: 571 | C24: 637 | D24: 757 | E24: 572 | F24: 509 | N24: FY: 424B4 p. F-57-F-58 and 24; 9M: 10-Q Q3 2026 p. 33, 34
A25: Connectivity | B25: 884 | C25: 1508 | D25: 2376 | E25: 1706 | F25: 2574 | N25: FY: 424B4 p. F-57-F-58 and 24; 9M: 10-Q Q3 2026 p. 33, 34
A26: SI (formerly AI) | B26: 1180 | C26: 1679 | D26: 3568 | E26: 2506 | F26: 5851 | N26: FY: 424B4 p. F-57-F-58 and 24; 9M: 10-Q Q3 2026 p. 33, 34
A28: A. Share-based compensation (excluding acquisition awards)
A29: Space | B29: 427 | C29: 472 | D29: 515 | E29: 383 | F29: 503 | N29: FY: 424B4 p. F-57-F-58 and 24; 9M: 10-Q Q3 2026 p. 33, 34
A30: Connectivity | B30: 249 | C30: 296 | D30: 369 | E30: 270 | F30: 398 | N30: FY: 424B4 p. F-57-F-58 and 24; 9M: 10-Q Q3 2026 p. 33, 34
A31: SI (formerly AI) | B31: 3 | C31: 16 | D31: 1063 | E31: 391 | F31: 1715 | N31: FY: 424B4 p. F-57-F-58 and 24; 9M: 10-Q Q3 2026 p. 33, 34
A33: A. Share-based compensation related to acquisitions
A34: Space | N34: FY: 424B4 p. F-57-F-58 and 24; 9M: 10-Q Q3 2026 p. 33, 34. Filing shows — (nil) in 9M 2026A: left blank. No such line in FY2023A, FY2024A, FY2025A, 9M 2025A
A35: Connectivity | N35: FY: 424B4 p. F-57-F-58 and 24; 9M: 10-Q Q3 2026 p. 33, 34. Filing shows — (nil) in 9M 2026A: left blank. No such line in FY2023A, FY2024A, FY2025A, 9M 2025A
A36: SI (formerly AI) | F36: 1217 | N36: FY: 424B4 p. F-57-F-58 and 24; 9M: 10-Q Q3 2026 p. 33, 34. No such line in FY2023A, FY2024A, FY2025A, 9M 2025A
A38: A. Acquisition-related costs
A39: Space | N39: FY: 424B4 p. F-57-F-58 and 24; 9M: 10-Q Q3 2026 p. 33, 34. Filing shows — (nil) in 9M 2026A: left blank. No such line in FY2023A, FY2024A, FY2025A, 9M 2025A
A40: Connectivity | N40: FY: 424B4 p. F-57-F-58 and 24; 9M: 10-Q Q3 2026 p. 33, 34. Filing shows — (nil) in 9M 2026A: left blank. No such line in FY2023A, FY2024A, FY2025A, 9M 2025A
A41: SI (formerly AI) | F41: 8 | N41: FY: 424B4 p. F-57-F-58 and 24; 9M: 10-Q Q3 2026 p. 33, 34. No such line in FY2023A, FY2024A, FY2025A, 9M 2025A
A43: A. Restructuring charges (credits)
A44: Space | N44: FY: 424B4 p. F-57-F-58 and 24; 9M: 10-Q Q3 2026 p. 33, 34. Filing shows — (nil) in FY2023A, FY2024A, FY2025A, 9M 2025A, 9M 2026A: left blank
A45: Connectivity | N45: FY: 424B4 p. F-57-F-58 and 24; 9M: 10-Q Q3 2026 p. 33, 34. Filing shows — (nil) in FY2023A, FY2024A, FY2025A, 9M 2025A, 9M 2026A: left blank
A46: SI (formerly AI) | B46: 237 | C46: 213 | D46: 487 | E46: 472 | F46: -6 | N46: FY: 424B4 p. F-57-F-58 and 24; 9M: 10-Q Q3 2026 p. 33, 34
A48: A. Impairment
A49: Space | C49: 24 | D49: 38 | E49: 29 | N49: FY: 424B4 p. F-57-F-58 and 24; 9M: 10-Q Q3 2026 p. 33, 34. Filing shows — (nil) in FY2023A: left blank. No such line in 9M 2026A
A50: Connectivity | C50: 39 | N50: FY: 424B4 p. F-57-F-58 and 24; 9M: 10-Q Q3 2026 p. 33, 34. Filing shows — (nil) in FY2023A, FY2025A, 9M 2025A: left blank. No such line in 9M 2026A
A51: SI (formerly AI) | B51: 3775 | N51: FY: 424B4 p. F-57-F-58 and 24; 9M: 10-Q Q3 2026 p. 33, 34. Filing shows — (nil) in FY2024A, FY2025A, 9M 2025A: left blank. No such line in 9M 2026A
A53: A. Segment adjusted EBITDA (company measure, non-GAAP)
A54: Space | B54: 997 | C54: 1154 | D54: 653 | E54: 803 | F54: -199 | N54: FY: 424B4 p. F-57-F-58 and 24; 9M: 10-Q Q3 2026 p. 33, 34
A55: Connectivity | B55: 1602 | C55: 3849 | D55: 7168 | E55: 5123 | F55: 8183 | N55: FY: 424B4 p. F-57-F-58 and 24; 9M: 10-Q Q3 2026 p. 33, 34
A56: SI (formerly AI) | B56: 1222 | C56: 347 | D56: -1237 | E56: -813 | F56: 5490 | N56: FY: 424B4 p. F-57-F-58 and 24; 9M: 10-Q Q3 2026 p. 33, 34
A58: A. Capital expenditures
A59: Space | B59: 1497 | C59: 2032 | D59: 3832 | E59: 2818 | F59: 3832 | N59: FY: 424B4 p. F-57-F-58 and 24; 9M: 10-Q Q3 2026 p. 33, 34
A60: Connectivity | B60: 2455 | C60: 3498 | D60: 4178 | E60: 2951 | F60: 4242 | N60: FY: 424B4 p. F-57-F-58 and 24; 9M: 10-Q Q3 2026 p. 33, 34
A61: SI (formerly AI) | B61: 463 | C61: 5633 | D61: 12727 | E61: 8077 | F61: 39995 | N61: FY: 424B4 p. F-57-F-58 and 24; 9M: 10-Q Q3 2026 p. 33, 34
A63: A. Operating data (year end or period end; per year or nine months)
A64: Starlink consumer subscribers, period end (millions) | B64: 2.3 | C64: 4.4 | D64: 8.9 | E64: 7.2 | F64: 13.6 | N64: 424B4 p. 24; 10-Q Q3 2026 p. 40. Renamed 'consumer subscribers' in Q3 2026; same measure
A65: Starlink consumer ARPU (USD per month) | B65: 99 | C65: 91 | D65: 81 | E65: 84 | F65: 67 | N65: 424B4 p. 24; 10-Q Q3 2026 p. 40
A66: SI nameplate compute, period end (GW) | B66: 0 | C66: 0.3 | D66: 0.8 | E66: 0.6 | F66: 1.7 | N66: 424B4 p. 24; 10-Q Q3 2026 p. 40 ('Nameplate compute 1.7 0.6')
A67: Launches, Falcon and Starship | B67: 98 | C67: 138 | D67: 170 | E67: =124+4 -> 128 | F67: =110+3 -> 113 | N67: 424B4 p. 24; 9M: Falcon + Starship, 10-Q Q3 2026 p. 39
A68: Customer launches | B68: 33 | C68: 45 | D68: 43 | E68: 36 | F68: 29 | N68: FY: 424B4 p. 87 ('customer launches totaled 33, 45, and 43'); 9M: Falcon customer launches, 10-Q Q3 2026 p. 39; Starship launches are all internal
A69: Mass to orbit (metric tons) | B69: 1210 | C69: 1699 | D69: 2213 | E69: 1627 | F69: 1517 | N69: 424B4 p. 24; 10-Q Q3 2026 p. 39
A71: A. Customers above 10% of revenue (unnamed in the filings; '*' = below 10%)
A72: Customer A: % of revenue | B72: 0.252 | C72: 0.242 | D72: 0.209 | E72: 0.216 | F72: 0.173 | N72: 424B4 p. F-23; 10-Q Q3 2026 p. 13
A73: Customer B: % of revenue | E73: * | F73: 0.242 | N73: 10-Q Q3 2026 p. 13: '*' in 9M 2025 means below 10%, kept as text; not disclosed for the years. 10-Q Q3 2026 p. 13
A75: A. Checks (zero passes)
A76: Revenue types add to the segments | B76: =ABS(B7+B8-B9)+ABS(B10+B11-B12)+ABS(B13+B14-B15) -> 0 | C76: =ABS(C7+C8-C9)+ABS(C10+C11-C12)+ABS(C13+C14-C15) -> 0 | D76: =ABS(D7+D8-D9)+ABS(D10+D11-D12)+ABS(D13+D14-D15) -> 0 | E76: =ABS(E7+E8-E9)+ABS(E10+E11-E12)+ABS(E13+E14-E15) -> 0 | F76: =ABS(F7+F8-F9)+ABS(F10+F11-F12)+ABS(F13+F14-F15) -> 0
A77: Segments add to total revenue and to the statement | B77: =ABS(B9+B12+B15-B16)+ABS(B16-IS_Hist!B6) -> 0 | C77: =ABS(C9+C12+C15-C16)+ABS(C16-IS_Hist!C6) -> 0 | D77: =ABS(D9+D12+D15-D16)+ABS(D16-IS_Hist!D6) -> 0 | E77: =ABS(E9+E12+E15-E16)+ABS(E16-IS_Hist!E6) -> 0 | F77: =ABS(F9+F12+F15-F16)+ABS(F16-IS_Hist!F6) -> 0
A78: Segment operating results add to the statement | B78: =B19+B20+B21-IS_Hist!B14 -> 0 | C78: =C19+C20+C21-IS_Hist!C14 -> 0 | D78: =D19+D20+D21-IS_Hist!D14 -> 0 | E78: =E19+E20+E21-IS_Hist!E14 -> 0 | F78: =F19+F20+F21-IS_Hist!F14 -> 0
A79: Segment D&A adds to the cash flow statement | B79: =B24+B25+B26-CF_Hist!B8 -> 0 | C79: =C24+C25+C26-CF_Hist!C8 -> 0 | D79: =D24+D25+D26-CF_Hist!D8 -> 0 | E79: =E24+E25+E26-CF_Hist!E8 -> 0 | F79: =F24+F25+F26-CF_Hist!F8 -> 0
A80: Segment SBC (incl. acquisition awards) adds to the cash flow statement | B80: =B29+B30+B31+B36-CF_Hist!B9 -> 0 | C80: =C29+C30+C31+C36-CF_Hist!C9 -> 0 | D80: =D29+D30+D31+D36-CF_Hist!D9 -> 0 | E80: =E29+E30+E31+E36-CF_Hist!E9 -> 0 | F80: =F29+F30+F31+F36-CF_Hist!F9 -> 0
A81: Segment capex adds to purchases of PP&E | B81: =B59+B60+B61+CF_Hist!B30 -> 0 | C81: =C59+C60+C61+CF_Hist!C30 -> 0 | D81: =D59+D60+D61+CF_Hist!D30 -> 0 | E81: =E59+E60+E61+CF_Hist!E30 -> 0 | F81: =F59+F60+F61+CF_Hist!F30 -> 0
A82: Adjusted EBITDA reconciliation, Space: result + D&A + SBC + acquisition items + restructuring + impairment - EBITDA | B82: =B19+B24+B29+B34+B39+B44+B49-B54 -> 0 | C82: =C19+C24+C29+C34+C39+C44+C49-C54 -> 0 | D82: =D19+D24+D29+D34+D39+D44+D49-D54 -> 0 | E82: =E19+E24+E29+E34+E39+E44+E49-E54 -> 0 | F82: =F19+F24+F29+F34+F39+F44+F49-F54 -> 0
A83: Adjusted EBITDA reconciliation, Connectivity: result + D&A + SBC + acquisition items + restructuring + impairment - EBITDA | B83: =B20+B25+B30+B35+B40+B45+B50-B55 -> 0 | C83: =C20+C25+C30+C35+C40+C45+C50-C55 -> 0 | D83: =D20+D25+D30+D35+D40+D45+D50-D55 -> 0 | E83: =E20+E25+E30+E35+E40+E45+E50-E55 -> 0 | F83: =F20+F25+F30+F35+F40+F45+F50-F55 -> 0
A84: Adjusted EBITDA reconciliation, SI (formerly AI): result + D&A + SBC + acquisition items + restructuring + impairment - EBITDA | B84: =B21+B26+B31+B36+B41+B46+B51-B56 -> 0 | C84: =C21+C26+C31+C36+C41+C46+C51-C56 -> 0 | D84: =D21+D26+D31+D36+D41+D46+D51-D56 -> 0 | E84: =E21+E26+E31+E36+E41+E46+E51-E56 -> 0 | F84: =F21+F26+F31+F36+F41+F46+F51-F56 -> 0
A87: Three months ended | B87: Q1 2025A | C87: Q2 2025A | D87: Q3 2025A | E87: Q4 2025A | F87: Q1 2026A | G87: Q2 2026A | H87: Q3 2026A | M87: Comentarios FG | N87: Source / derivation
A89: B1. Revenue by type and segment
A90: Launch Services | B90: 566 | C90: 490 | D90: 1000 | E90: =D7-E7 -> 520 | F90: 330 | G90: 648 | H90: 1130 | N90: Q1: 424B4 p. F-71, 24, 23; Q2: 10-Q Q2 2026 p. 13, 30; Q3: 10-Q Q3 2026 p. 13, 32; Q4 2025A: block A FY2025 less 9M 2025
A91: Launch & Development | B91: 299 | C91: 256 | D91: 666 | E91: =D8-E8 -> 289 | F91: 289 | G91: 314 | H91: 637 | N91: Q1: 424B4 p. F-71, 24, 23; Q2: 10-Q Q2 2026 p. 13, 30; Q3: 10-Q Q3 2026 p. 13, 32; Q4 2025A: block A FY2025 less 9M 2025
A92: Space | B92: 865 | C92: 746 | D92: 1666 | E92: =D9-E9 -> 809 | F92: 619 | G92: 962 | H92: 1767 | N92: Q1: 424B4 p. F-71, 24, 23; Q2: 10-Q Q2 2026 p. 13, 30; Q3: 10-Q Q3 2026 p. 13, 32; Q4 2025A: block A FY2025 less 9M 2025
A93: Consumer | B93: 1492 | C93: 1721 | D93: 1986 | E93: =D10-E10 -> 2010 | F93: 2148 | G93: 2485 | H93: 3121 | N93: Q1: 424B4 p. F-71, 24, 23; Q2: 10-Q Q2 2026 p. 13, 30; Q3: 10-Q Q3 2026 p. 13, 32; Q4 2025A: block A FY2025 less 9M 2025
A94: Enterprise & Government | B94: 983 | C94: 867 | D94: 1111 | E94: =D11-E11 -> 1218 | F94: 1109 | G94: 1806 | H94: 2127 | N94: Q1: 424B4 p. F-71, 24, 23; Q2: 10-Q Q2 2026 p. 13, 30; Q3: 10-Q Q3 2026 p. 13, 32; Q4 2025A: block A FY2025 less 9M 2025
A95: Connectivity | B95: 2475 | C95: 2588 | D95: 3097 | E95: =D12-E12 -> 3228 | F95: 3257 | G95: 4291 | H95: 5248 | N95: Q1: 424B4 p. F-71, 24, 23; Q2: 10-Q Q2 2026 p. 13, 30; Q3: 10-Q Q3 2026 p. 13, 32; Q4 2025A: block A FY2025 less 9M 2025
A96: Advertising | B96: 443 | C96: 426 | D96: 454 | E96: =D13-E13 -> 521 | F96: 343 | G96: 367 | H96: 538 | N96: Q1: 424B4 p. F-71, 24, 23; Q2: 10-Q Q2 2026 p. 13, 30; Q3: 10-Q Q3 2026 p. 13, 32; Q4 2025A: block A FY2025 less 9M 2025
A97: SI (AI) solutions & infrastructure | B97: 284 | C97: 311 | D97: 359 | E97: =D14-E14 -> 402 | F97: 475 | G97: 2194 | H97: 7022 | N97: Q1: 424B4 p. F-71, 24, 23; Q2: 10-Q Q2 2026 p. 13, 30; Q3: 10-Q Q3 2026 p. 13, 32; Q4 2025A: block A FY2025 less 9M 2025
A98: SI (AI) | B98: 727 | C98: 737 | D98: 813 | E98: =D15-E15 -> 923 | F98: 818 | G98: 2561 | H98: 7560 | N98: Q1: 424B4 p. F-71, 24, 23; Q2: 10-Q Q2 2026 p. 13, 30; Q3: 10-Q Q3 2026 p. 13, 32; Q4 2025A: block A FY2025 less 9M 2025
A99: Total revenues | B99: 4067 | C99: 4071 | D99: 5576 | E99: =D16-E16 -> 4960 | F99: 4694 | G99: 7814 | H99: 14575 | N99: Q1: 424B4 p. F-71, 24, 23; Q2: 10-Q Q2 2026 p. 13, 30; Q3: 10-Q Q3 2026 p. 13, 32; Q4 2025A: block A FY2025 less 9M 2025
A101: B. Segment income (loss) from operations
A102: Space | B102: -70 | C102: -369 | D102: 259 | E102: =D19-E19 -> -476 | F102: -662 | G102: -542 | H102: -7 | N102: Q1: 424B4 p. F-71, 24, 23; Q2: 10-Q Q2 2026 p. 13, 30; Q3: 10-Q Q3 2026 p. 13, 32; Q4 2025A: block A FY2025 less 9M 2025
A103: Connectivity | B103: 1033 | C103: 923 | D103: 1190 | E103: =D20-E20 -> 1276 | F103: 1188 | G103: 1656 | H103: 2367 | N103: Q1: 424B4 p. F-71, 24, 23; Q2: 10-Q Q2 2026 p. 13, 30; Q3: 10-Q Q3 2026 p. 13, 32; Q4 2025A: block A FY2025 less 9M 2025
A104: SI (formerly AI) | B104: -936 | C104: -1524 | D104: -1722 | E104: =D21-E21 -> -2173 | F104: -2469 | G104: -1257 | H104: 431 | N104: Q1: 424B4 p. F-71, 24, 23; Q2: 10-Q Q2 2026 p. 13, 30; Q3: 10-Q Q3 2026 p. 13, 32; Q4 2025A: block A FY2025 less 9M 2025
A106: B. Segment adjusted EBITDA
A107: Space | B107: 224 | C107: -93 | D107: 674 | E107: =D54-E54 -> -150 | F107: -351 | G107: -205 | H107: 357 | N107: Q1: 424B4 p. F-71, 24, 23; Q2: 10-Q Q2 2026 p. 13, 30; Q3: 10-Q Q3 2026 p. 13, 32; Q4 2025A: block A FY2025 less 9M 2025
A108: Connectivity | B108: 1618 | C108: 1583 | D108: 1923 | E108: =D55-E55 -> 2045 | F108: 2087 | G108: 2597 | H108: 3499 | N108: Q1: 424B4 p. F-71, 24, 23; Q2: 10-Q Q2 2026 p. 13, 30; Q3: 10-Q Q3 2026 p. 13, 32; Q4 2025A: block A FY2025 less 9M 2025
A109: SI (formerly AI) | B109: -112 | C109: -276 | D109: -428 | E109: =D56-E56 -> -424 | F109: -609 | G109: 1146 | H109: 4953 | N109: Q1: 424B4 p. F-71, 24, 23; Q2: 10-Q Q2 2026 p. 13, 30; Q3: 10-Q Q3 2026 p. 13, 32; Q4 2025A: block A FY2025 less 9M 2025
A111: B. Capital expenditures
A112: Space | B112: 759 | C112: 946 | D112: 1113 | E112: =D59-E59 -> 1014 | F112: 1052 | G112: 1174 | H112: 1606 | N112: Q1: 424B4 p. F-71, 24, 23; Q2: 10-Q Q2 2026 p. 13, 30; Q3: 10-Q Q3 2026 p. 13, 32; Q4 2025A: block A FY2025 less 9M 2025
A113: Connectivity | B113: 814 | C113: 1130 | D113: 1007 | E113: =D60-E60 -> 1227 | F113: 1332 | G113: 1367 | H113: 1543 | N113: Q1: 424B4 p. F-71, 24, 23; Q2: 10-Q Q2 2026 p. 13, 30; Q3: 10-Q Q3 2026 p. 13, 32; Q4 2025A: block A FY2025 less 9M 2025
A114: SI (formerly AI) | B114: 2567 | C114: 749 | D114: 4760 | E114: =D61-E61 -> 4650 | F114: 7723 | G114: 15828 | H114: 16444 | N114: Q1: 424B4 p. F-71, 24, 23; Q2: 10-Q Q2 2026 p. 13, 30; Q3: 10-Q Q3 2026 p. 13, 32; Q4 2025A: block A FY2025 less 9M 2025
A116: B. Depreciation and amortization
A117: Space | C117: 146 | D117: 264 | E117: =D24-E24 -> 185 | G117: 158 | H117: 185 | N117: Q1: 424B4 p. F-71, 24, 23; Q2: 10-Q Q2 2026 p. 13, 30; Q3: 10-Q Q3 2026 p. 13, 32; Q4 2025A: block A FY2025 less 9M 2025. No such line in Q1 2025A, Q1 2026A
A118: Connectivity | C118: 569 | D118: 628 | E118: =D25-E25 -> 670 | G118: 805 | H118: 986 | N118: Q1: 424B4 p. F-71, 24, 23; Q2: 10-Q Q2 2026 p. 13, 30; Q3: 10-Q Q3 2026 p. 13, 32; Q4 2025A: block A FY2025 less 9M 2025. No such line in Q1 2025A, Q1 2026A
A119: SI (formerly AI) | C119: 811 | D119: 922 | E119: =D26-E26 -> 1062 | G119: 1885 | H119: 2473 | N119: Q1: 424B4 p. F-71, 24, 23; Q2: 10-Q Q2 2026 p. 13, 30; Q3: 10-Q Q3 2026 p. 13, 32; Q4 2025A: block A FY2025 less 9M 2025. No such line in Q1 2025A, Q1 2026A
A121: B. Operating data
A122: Starlink consumer subscribers, quarter end (millions) | B122: 5 | C122: 6 | D122: 7.2 | E122: =D64 -> 8.9 | F122: 10.3 | G122: 12 | H122: 13.6 | N122: 424B4 p. 24; 10-Q Q2 2026 p. 35; 10-Q Q3 2026 p. 40; Q4 2025A = 31 Dec 2025 (filed)
...

Sheet Cap_Table
A1: Space Exploration Technologies Corp. (SpaceX) | Shares outstanding, dilutive securities and the diluted count at the market price
A2: Shares in millions. Treasury-stock method at the SPCX close of 27 Oct 2026. Sources: 10-Q Q3 2026 cover and Note 12-13; 424B4 (option prices, Musk awards, EchoStar shares).
A4: Item | B4: Value | C4: Price (USD) | D4: Comentarios FG | E4: Source / derivation
A6: A. Common stock outstanding, 15 Oct 2026 (10-Q cover)
A7: Class A common stock | B7: 8246.5412 | E7: 10-Q Q3 2026, cover page
A8: Class B common stock (10 votes per share) | B8: 5334.5225 | E8: 10-Q Q3 2026, cover page
A9: Shares outstanding | B9: =B7+B8 -> 13581.064
A10: Memo: Class A at 30 Sep 2026 (balance sheet caption) | B10: 8240 | E10: 10-Q Q3 2026 p. 4
A11: Memo: Class B at 30 Sep 2026 (balance sheet caption) | B11: 5339 | E11: 10-Q Q3 2026 p. 4
A13: B. Performance-based restricted Class B shares held by Mr. Musk (issued, outstanding and voted; not vested)
A14: SpaceX CEO Award, 13 Jan 2026: 15 tranches, market-cap milestones US$0.5tn to US$7.5tn, plus a permanent Mars colony of at least one million people | B14: 1000 | E14: 424B4 p. 235; tranche table 424B4 pp. 235-236; F-89
A15: AI CEO Award, 23 Mar 2026 (replaced the xAI award): 12 equal tranches, US$1.065tn to US$6.565tn, plus non-Earth data centers delivering 100 TW of compute a year | B15: 302.07229 | E15: 424B4 p. 236; F-89
A16: Performance-based restricted shares | B16: =B14+B15 -> 1302.0723 | E16: Inside the cover count (9M 2026 equity note: 1,306m Class B issued). Both awards require continued employment; Mr. Musk votes all of them. The 10-Q excludes 1,333m such awards from diluted EPS: 10-Q Q3 2026 p. 27
A17: Market capitalisation for the milestones: shares outstanding x price (USD bn) | B17: =B9*C61/1000 -> 2017.8744 | E17: Shares outstanding at 15 Oct 2026 x the 27 Oct 2026 close. The award's own definition (averaging period) is not reproduced; indicative.
A18: Tranche | B18: Shares (m) | C18: Milestone (USD bn) | D18: Market cap met (1 = yes) | E18: Second condition (both must be met to vest)
A19: SpaceX CEO Award, tranche 1 | B19: 66.666665 | C19: 500 | D19: =IF($B$17>=C19,1,0) -> 1 | E19: Mars colony of at least one million inhabitants: not met
A20: SpaceX CEO Award, tranche 2 | B20: 66.666665 | C20: 1000 | D20: =IF($B$17>=C20,1,0) -> 1 | E20: Mars colony of at least one million inhabitants: not met
A21: SpaceX CEO Award, tranche 3 | B21: 66.666665 | C21: 1500 | D21: =IF($B$17>=C21,1,0) -> 1 | E21: Mars colony of at least one million inhabitants: not met
A22: SpaceX CEO Award, tranche 4 | B22: 66.666665 | C22: 2000 | D22: =IF($B$17>=C22,1,0) -> 1 | E22: Mars colony of at least one million inhabitants: not met
A23: SpaceX CEO Award, tranche 5 | B23: 66.666665 | C23: 2500 | D23: =IF($B$17>=C23,1,0) -> 0 | E23: Mars colony of at least one million inhabitants: not met
A24: SpaceX CEO Award, tranche 6 | B24: 66.666665 | C24: 3000 | D24: =IF($B$17>=C24,1,0) -> 0 | E24: Mars colony of at least one million inhabitants: not met
A25: SpaceX CEO Award, tranche 7 | B25: 66.666665 | C25: 3500 | D25: =IF($B$17>=C25,1,0) -> 0 | E25: Mars colony of at least one million inhabitants: not met
A26: SpaceX CEO Award, tranche 8 | B26: 66.666665 | C26: 4000 | D26: =IF($B$17>=C26,1,0) -> 0 | E26: Mars colony of at least one million inhabitants: not met
A27: SpaceX CEO Award, tranche 9 | B27: 66.666665 | C27: 4500 | D27: =IF($B$17>=C27,1,0) -> 0 | E27: Mars colony of at least one million inhabitants: not met
A28: SpaceX CEO Award, tranche 10 | B28: 66.666665 | C28: 5000 | D28: =IF($B$17>=C28,1,0) -> 0 | E28: Mars colony of at least one million inhabitants: not met
A29: SpaceX CEO Award, tranche 11 | B29: 66.66667 | C29: 5500 | D29: =IF($B$17>=C29,1,0) -> 0 | E29: Mars colony of at least one million inhabitants: not met
A30: SpaceX CEO Award, tranche 12 | B30: 66.66667 | C30: 6000 | D30: =IF($B$17>=C30,1,0) -> 0 | E30: Mars colony of at least one million inhabitants: not met
... A33: SpaceX CEO Award, tranche 15 | B33: 66.66667 | C33: 7500 | D33: =IF($B$17>=C33,1,0) -> 0 | E33: Mars colony of at least one million inhabitants: not met
A34: AI CEO Award, tranche 1 | B34: =$B$15/12 -> 25.17269 | C34: 1065 | D34: =IF($B$17>=C34,1,0) -> 1 | E34: Non-Earth data centers delivering 100 TW of compute a year: not met
A35: AI CEO Award, tranche 2 | B35: =$B$15/12 -> 25.17269 | C35: 1565 | D35: =IF($B$17>=C35,1,0) -> 1 | E35: Non-Earth data centers delivering 100 TW of compute a year: not met
A36: AI CEO Award, tranche 3 | B36: =$B$15/12 -> 25.17269 | C36: 2065 | D36: =IF($B$17>=C36,1,0) -> 0 | E36: Non-Earth data centers delivering 100 TW of compute a year: not met
A37: AI CEO Award, tranche 4 | B37: =$B$15/12 -> 25.17269 | C37: 2565 | D37: =IF($B$17>=C37,1,0) -> 0 | E37: Non-Earth data centers delivering 100 TW of compute a year: not met
A38: AI CEO Award, tranche 5 | B38: =$B$15/12 -> 25.17269 | C38: 3065 | D38: =IF($B$17>=C38,1,0) -> 0 | E38: Non-Earth data centers delivering 100 TW of compute a year: not met
A39: AI CEO Award, tranche 6 | B39: =$B$15/12 -> 25.17269 | C39: 3565 | D39: =IF($B$17>=C39,1,0) -> 0 | E39: Non-Earth data centers delivering 100 TW of compute a year: not met
A40: AI CEO Award, tranche 7 | B40: =$B$15/12 -> 25.17269 | C40: 4065 | D40: =IF($B$17>=C40,1,0) -> 0 | E40: Non-Earth data centers delivering 100 TW of compute a year: not met
A41: AI CEO Award, tranche 8 | B41: =$B$15/12 -> 25.17269 | C41: 4565 | D41: =IF($B$17>=C41,1,0) -> 0 | E41: Non-Earth data centers delivering 100 TW of compute a year: not met
A42: AI CEO Award, tranche 9 | B42: =$B$15/12 -> 25.17269 | C42: 5065 | D42: =IF($B$17>=C42,1,0) -> 0 | E42: Non-Earth data centers delivering 100 TW of compute a year: not met
A43: AI CEO Award, tranche 10 | B43: =$B$15/12 -> 25.17269 | C43: 5565 | D43: =IF($B$17>=C43,1,0) -> 0 | E43: Non-Earth data centers delivering 100 TW of compute a year: not met
A44: AI CEO Award, tranche 11 | B44: =$B$15/12 -> 25.17269 | C44: 6065 | D44: =IF($B$17>=C44,1,0) -> 0 | E44: Non-Earth data centers delivering 100 TW of compute a year: not met
A45: AI CEO Award, tranche 12 | B45: =$B$15/12 -> 25.17269 | C45: 6565 | D45: =IF($B$17>=C45,1,0) -> 0 | E45: Non-Earth data centers delivering 100 TW of compute a year: not met
A46: Shares in tranches whose market-cap milestone is met at 27 Oct 2026 | B46: =SUMPRODUCT(B19:B45,D19:D45) -> 317.01204 | E46: None of them vests: the second condition of every tranche is far off. The company deems both conditions improbable and records no expense for these awards (424B4 p. F-89; grant-date fair value US$90.40 to US$95.92 a share).
A47: Count the 1,302m performance shares in the diluted shares (1 = yes, 0 = no) | B47: 1 | E47: Default 1: the shares are issued, outstanding and voted, and counting them is the conservative choice. Set 0 to see the value per share without them (also shown live on DCF). No expense for them is charged in the forecast.
A49: C. Dilutive securities (Note 12 reserve table, 30 Sep 2026)
A50: Class A stock options outstanding | B50: 158 | C50: 27.65 | E50: 10-Q Q3 2026 p. 26; exercise price: weighted average at 31 Mar 2026, 424B4 p. 19 (latest stated; convention)
A51: Class B stock options outstanding (mostly Mr. Musk's 2018-2021 options) | B51: 350 | C51: 8.22 | E51: 10-Q Q3 2026 p. 26; exercise price at 31 Mar 2026, 424B4 p. 19
A52: Class A options, net shares by the treasury-stock method | B52: =MAX(0,B50*(1-C50/C61)) -> 128.59698 | E52: Options x (1 - exercise price / market price): the exercise cash buys back shares at the market price.
A53: Class B options, net shares by the treasury-stock method | B53: =MAX(0,B51*(1-C51/C61)) -> 330.63669
A54: Restricted stock units outstanding | B54: 142 | E54: 10-Q Q3 2026 p. 26; unvested RSAs (Cursor and others) are already inside the cover count
A55: EchoStar spectrum: Class A shares to be issued at closing (about Nov 2027) | B55: =Assumptions!$C$37 -> 261.8 | E55: Committed consideration at a fixed US$42.40; counted now so that the DCF does not also deduct the stock part as cash.
A56: Diluted shares for valuation | B56: =B9-B16*(1-B47)+B52+B53+B54+B55 -> 14444.097 | E56: Method: shares outstanding (Musk performance shares in or out by the switch), plus options by the treasury method, all RSUs (including Cursor awards) and the EchoStar shares.
A57: Diluted shares at the other setting of the switch | B57: =B56+B16*(1-2*B47) -> 13142.025
A58: Memo: weighted diluted shares in Q3 2026 EPS (company calculation) | B58: 12475 | E58: 10-Q Q3 2026 p. 4: basic 11,942 + options 457 + RSUs 75 + ESPP 1
A60: D. Market price
A61: SPCX closing price, 27 Oct 2026 (USD) | C61: 148.58 | E61: SPCX close on 27 Oct 2026, Yahoo Finance daily chart data, fetched 27 Oct 2026; FMP profile shows the same price.
A62: Market capitalisation on the diluted count (USD m) | B62: =B56*C61 -> 2146104
A63: Market capitalisation on the shares outstanding (USD m) | B63: =B9*C61 -> 2017874.4
A64: Memo: FMP market capitalisation (USD m) | B64: 2057923 | E64: FMP profile market capitalisation, 27 Oct 2026 (USD m); FMP's share count is not stated.
A66: Checks (zero passes)
A67: Class A and B at 30 Sep 2026 equal the equity statement (13,579) | B67: =B10+B11-SCE_Hist!D63 -> 0

Sheet Assumptions
A1: Space Exploration Technologies Corp. (SpaceX) | Assumptions and scenarios
A2: Blue cells are inputs. Each driver has Base, Bull and Bear rows; the Active row follows the switch in C5. USD millions unless stated.
B3: Actual | C3: Forecast
A4: Fiscal year ends 31 December | B4: 2025A | C4: 2026E | D4: 2027E | E4: 2028E | F4: 2029E | G4: 2030E | H4: 2031E | I4: 2032E | J4: 2033E | K4: 2034E | L4: 2035E | M4: Comentarios FG | N4: Source / derivation
A5: Scenario switch: 1 = Base, 2 = Bull, 3 = Bear | C5: 1 | N5: Same convention as the house templates (Supuestos!C5).
A6: Active scenario | C6: =CHOOSE(C5,"Base","Bull","Bear") -> Base
A8: A. Q4 2026E stub and valuation inputs (one value per scenario)
C9: Active | D9: Base | E9: Bull | F9: Bear
A10: Q4 2026E: Starlink consumer subscribers at 31 Dec 2026 (millions) | C10: =CHOOSE($C$5,D10,E10,F10) -> 15.2 | D10: 15.2 | E10: 15.5 | F10: 14.8 | N10: 13.6m at 30 Sep 2026, +1.6m in Q3 and +1.7m in Q2 (10-Q). Base repeats the Q3 addition; Bull a little faster; Bear slower.
A11: Q4 2026E: Starlink consumer ARPU (USD per month) | C11: =CHOOSE($C$5,D11,E11,F11) -> 69 | D11: 69 | E11: 70 | F11: 67 | N11: US$69 in Q3 2026, US$66 in Q1 and Q2 (10-Q). Base holds Q3; Bear returns towards the 9M average of US$67.
A12: Q4 2026E: Enterprise & Government revenue growth on Q3 2026 | C12: =CHOOSE($C$5,D12,E12,F12) -> 0.08 | D12: 0.08 | E12: 0.12 | F12: 0.02 | N12: Q3 2026 +18% on Q2, +91% on Q3 2025 (10-Q). Base slows to +8% a quarter.
A13: Q4 2026E: customer launches (Falcon and Starship) | C13: =CHOOSE($C$5,D13,E13,F13) -> 13 | D13: 13 | E13: 15 | F13: 10 | N13: 12 in Q3 2026, 29 in 9M 2026; 43 in FY2025 (424B4, 10-Q). Base 13 brings 2026E to 42, close to 2025.
A14: Q4 2026E: Launch & Development revenue growth on Q3 2026 | C14: =CHOOSE($C$5,D14,E14,F14) -> 0 | D14: 0 | E14: 0.05 | F14: -0.1 | N14: Q3 2026 US$637m, Q2 US$314m: lumpy milestone revenue (10-Q). Base holds Q3.
A15: Q4 2026E: SI nameplate compute at 31 Dec 2026 (GW) | C15: =CHOOSE($C$5,D15,E15,F15) -> 2.1 | D15: 2.1 | E15: 2.3 | F15: 1.9 | N15: 1.0 GW at 31 Mar, 1.4 at 30 Jun, 1.7 at 30 Sep 2026 (424B4, 10-Q): +0.3 to +0.4 GW a quarter. Base +0.4 GW.
A16: Q4 2026E: change in SI compute revenue per average GW on Q3 2026 | C16: =CHOOSE($C$5,D16,E16,F16) -> 0 | D16: 0 | E16: 0.03 | F16: -0.08 | N16: Q3 2026 rate is a formula on Segments_Hist (SI solutions less Cursor, per average GW). Bear: new capacity comes on line before it earns.
A17: Q4 2026E: Cursor revenue growth on the Q3 daily run-rate | C17: =CHOOSE($C$5,D17,E17,F17) -> 0.1 | D17: 0.1 | E17: 0.2 | F17: 0 | N17: Q3 2026 Cursor revenue US$608m for the 47 days after the 14 Aug close (10-Q). Base +10% on that daily rate.
A18: Q4 2026E: advertising revenue growth on Q3 2026 | C18: =CHOOSE($C$5,D18,E18,F18) -> 0.08 | D18: 0.08 | E18: 0.15 | F18: -0.05 | N18: Q3 2026 US$538m, Q2 US$367m (10-Q); Q4 is the strongest ad quarter. Analyst input.
A19: Q4 2026E: Space segment adjusted EBITDA margin | C19: =CHOOSE($C$5,D19,E19,F19) -> 0.15 | D19: 0.15 | E19: 0.2 | F19: 0.05 | N19: Q3 2026 20.2%, 9M 2026 -5.9%, FY2025 16.0% (formulas on Segments_Hist). Base near FY2025.
A20: Q4 2026E: Connectivity segment adjusted EBITDA margin | C20: =CHOOSE($C$5,D20,E20,F20) -> 0.65 | D20: 0.65 | E20: 0.67 | F20: 0.62 | N20: Q3 2026 66.7%, 9M 2026 63.9% (Segments_Hist).
A21: Q4 2026E: SI segment adjusted EBITDA margin | C21: =CHOOSE($C$5,D21,E21,F21) -> 0.6 | D21: 0.6 | E21: 0.64 | F21: 0.5 | N21: Q3 2026 65.5%, the first quarter of large compute revenue; 9M 2026 50.2% (Segments_Hist).
... A29: Apollo GPU finance lease closes (1 = yes, 0 = no) | C29: =CHOOSE($C$5,D29,E29,F29) -> 1 | D29: 1 | E29: 1 | F29: 0 | N29: Binding commitment of 24 Oct 2026, subject to closing conditions, expected before year end (8-K 26 Oct 2026). Bear: it does not close and SI capex is paid in cash.
A31: B. Inputs that do not change with the scenario
A32: Apollo lease: aggregate principal (financed cost) | C32: 40000 | N32: 8-K 26 Oct 2026: 'aggregate principal payments ... approximately $40 billion'.
A33: Apollo lease: quarter of 2027 in which the schedules start (1 to 4) | C33: 2 | N33: 8-K: schedules 'commence during the first half of 2027'; Base takes Q2, one tranche for all. Convention.
A34: Apollo lease: fixed interest rate | C34: 0.065 | N34: Not disclosed: 'the fixed rate will be determined at pricing' (8-K 26 Oct 2026). Derivation: the June 2026 SpaceX Notes average 5.855% (10-Q Q3 Note 9); press reports put their coupons at about 5.35%-6.65%, and AI credit spreads have widened since June (FT and CNBC coverage, Oct 2026, as researched for this build, not re-read here). 6.5% sits at the top of the notes' range for a secured equipment lease. Convention. The FT described the package as about US$10bn of bank loans plus US$30bn of investment-grade debt; the model follows the 8-K's finance lease.
A35: EchoStar spectrum: year of the acquisition closing | C35: 2027 | N35: 424B4 p. 124: expected closing 30 Nov 2027; no later than 30 Nov 2028.
A36: EchoStar spectrum: cash at closing (payoff of EchoStar debt) | C36: 8500 | N36: 424B4 p. 123: 'up to $8.5 billion related to the payoff of designated EchoStar debt'.
A37: EchoStar spectrum: Class A shares issued at closing (millions) | C37: 261.8 | N37: 424B4 p. 123: 'approximately 261.8 million shares' at a fixed US$42.40.
A38: EchoStar spectrum: fixed value per share (USD) | C38: 42.4 | N38: 424B4 p. 123.
A39: EchoStar spectrum: Spectrum Credit Agreement payments in 2026 | C39: 1241 | N39: 424B4 p. 124.
A40: EchoStar spectrum: paid to the Trust by 30 Sep 2026 | C40: 856 | N40: 10-Q Q3 Note 6.
A41: EchoStar spectrum: payments in 2027 (closing 30 Nov 2027) | C41: 828 | N41: 424B4 p. 124.
A42: EchoStar spectrum: extra payments if closing slips to 30 Nov 2028 | C42: 827 | N42: 424B4 p. 124.
A43: Tax rate: US federal | C43: 0.21 | N43: US federal statutory rate 21% (10-Q Q3 Note 15).
... A66: Sensitivity: shift on revenue per GW, all years (0 = none) | C66: 0 | N66: Used by the captured tables and the reverse DCF; keep at 0.
A67: Tax rate, federal plus state (used for the terminal year and the WACC) | C67: =$C$43+$C$44 -> 0.23
A69: C. Drivers by year (Base, Bull, Bear and the active row)
A70: Connectivity: Starlink consumer subscribers at year end (millions) | N70: 8.9m end-2025, 13.6m at 30 Sep 2026 (+89% in a year; 10-Q). Base adds 6-7m a year to 2029 (direct-to-cell service on the EchoStar and 800 MHz spectrum helps), then slows. Bull keeps adding faster; Bear slows at once.
A71: Base | D71: 21 | E71: 28 | F71: 35 | G71: 41 | H71: 47 | I71: 52 | J71: 56 | K71: 60 | L71: 63
A72: Bull | D72: 23 | E72: 32 | F72: 42 | G72: 52 | H72: 62 | I72: 70 | J72: 77 | K72: 83 | L72: 88
A73: Bear | D73: 19 | E73: 23 | F73: 26 | G73: 29 | H73: 31 | I73: 33 | J73: 35 | K73: 36 | L73: 37
A74: Active | D74: =CHOOSE($C$5,D71,D72,D73) -> 21 | E74: =CHOOSE($C$5,E71,E72,E73) -> 28 | F74: =CHOOSE($C$5,F71,F72,F73) -> 35 | G74: =CHOOSE($C$5,G71,G72,G73) -> 41 | H74: =CHOOSE($C$5,H71,H72,H73) -> 47 | I74: =CHOOSE($C$5,I71,I72,I73) -> 52 | J74: =CHOOSE($C$5,J71,J72,J73) -> 56 | K74: =CHOOSE($C$5,K71,K72,K73) -> 60 | L74: =CHOOSE($C$5,L71,L72,L73) -> 63
A75: Connectivity: consumer ARPU (USD per month) | N75: US$99 in 2023, US$81 in 2025, US$67 in 9M 2026: lower-priced plans and new countries (424B4, 10-Q). Base keeps falling slowly.
A76: Base | D76: 66 | E76: 64 | F76: 62 | G76: 61 | H76: 60 | I76: 60 | J76: 60 | K76: 60 | L76: 60
A77: Bull | D77: 68 | E77: 67 | F77: 66 | G77: 66 | H77: 66 | I77: 66 | J77: 66 | K77: 66 | L77: 66
A78: Bear | D78: 63 | E78: 60 | F78: 57 | G78: 55 | H78: 54 | I78: 53 | J78: 52 | K78: 52 | L78: 52
A79: Active | D79: =CHOOSE($C$5,D76,D77,D78) -> 66 | E79: =CHOOSE($C$5,E76,E77,E78) -> 64 | F79: =CHOOSE($C$5,F76,F77,F78) -> 62 | G79: =CHOOSE($C$5,G76,G77,G78) -> 61 | H79: =CHOOSE($C$5,H76,H77,H78) -> 60 | I79: =CHOOSE($C$5,I76,I77,I78) -> 60 | J79: =CHOOSE($C$5,J76,J77,J78) -> 60 | K79: =CHOOSE($C$5,K76,K77,K78) -> 60 | L79: =CHOOSE($C$5,L76,L77,L78) -> 60
A80: Connectivity: Enterprise & Government revenue growth | N80: +70% in 9M 2026, +51% in 2025 (filings): aviation, maritime, government (Starshield). Analyst input.
A81: Base | D81: 0.45 | E81: 0.35 | F81: 0.3 | G81: 0.25 | H81: 0.2 | I81: 0.15 | J81: 0.12 | K81: 0.1 | L81: 0.08
A82: Bull | D82: 0.6 | E82: 0.45 | F82: 0.38 | G82: 0.3 | H82: 0.25 | I82: 0.2 | J82: 0.15 | K82: 0.12 | L82: 0.1
A83: Bear | D83: 0.25 | E83: 0.18 | F83: 0.14 | G83: 0.11 | H83: 0.09 | I83: 0.07 | J83: 0.06 | K83: 0.05 | L83: 0.04
A84: Active | D84: =CHOOSE($C$5,D81,D82,D83) -> 0.45 | E84: =CHOOSE($C$5,E81,E82,E83) -> 0.35 | F84: =CHOOSE($C$5,F81,F82,F83) -> 0.3 | G84: =CHOOSE($C$5,G81,G82,G83) -> 0.25 | H84: =CHOOSE($C$5,H81,H82,H83) -> 0.2 | I84: =CHOOSE($C$5,I81,I82,I83) -> 0.15 | J84: =CHOOSE($C$5,J81,J82,J83) -> 0.12 | K84: =CHOOSE($C$5,K81,K82,K83) -> 0.1 | L84: =CHOOSE($C$5,L81,L82,L83) -> 0.08
A85: Connectivity: segment adjusted EBITDA margin | N85: 62.9% in 2025, 63.9% in 9M 2026, 66.7% in Q3 2026 (Segments_Hist).
A86: Base | D86: 0.64 | E86: 0.65 | F86: 0.65 | G86: 0.66 | H86: 0.66 | I86: 0.66 | J86: 0.66 | K86: 0.66 | L86: 0.66
A87: Bull | D87: 0.66 | E87: 0.67 | F87: 0.68 | G87: 0.69 | H87: 0.69 | I87: 0.69 | J87: 0.69 | K87: 0.69 | L87: 0.69
A88: Bear | D88: 0.6 | E88: 0.6 | F88: 0.6 | G88: 0.6 | H88: 0.6 | I88: 0.6 | J88: 0.6 | K88: 0.6 | L88: 0.6
A89: Active | D89: =CHOOSE($C$5,D86,D87,D88) -> 0.64 | E89: =CHOOSE($C$5,E86,E87,E88) -> 0.65 | F89: =CHOOSE($C$5,F86,F87,F88) -> 0.65 | G89: =CHOOSE($C$5,G86,G87,G88) -> 0.66 | H89: =CHOOSE($C$5,H86,H87,H88) -> 0.66 | I89: =CHOOSE($C$5,I86,I87,I88) -> 0.66 | J89: =CHOOSE($C$5,J86,J87,J88) -> 0.66 | K89: =CHOOSE($C$5,K86,K87,K88) -> 0.66 | L89: =CHOOSE($C$5,L86,L87,L88) -> 0.66
A90: Connectivity: capex, % of segment revenue | N90: 36.7% in 2025, 33.2% in 9M 2026 (Segments_Hist). Starship lowers the cost per satellite; the constellation must still be replaced every five years.
A91: Base | D91: 0.28 | E91: 0.25 | F91: 0.22 | G91: 0.2 | H91: 0.18 | I91: 0.17 | J91: 0.16 | K91: 0.15 | L91: 0.15
A92: Bull | D92: 0.27 | E92: 0.24 | F92: 0.21 | G92: 0.19 | H92: 0.17 | I92: 0.16 | J92: 0.15 | K92: 0.14 | L92: 0.14
A93: Bear | D93: 0.32 | E93: 0.3 | F93: 0.28 | G93: 0.26 | H93: 0.24 | I93: 0.22 | J93: 0.2 | K93: 0.2 | L93: 0.2
A94: Active | D94: =CHOOSE($C$5,D91,D92,D93) -> 0.28 | E94: =CHOOSE($C$5,E91,E92,E93) -> 0.25 | F94: =CHOOSE($C$5,F91,F92,F93) -> 0.22 | G94: =CHOOSE($C$5,G91,G92,G93) -> 0.2 | H94: =CHOOSE($C$5,H91,H92,H93) -> 0.18 | I94: =CHOOSE($C$5,I91,I92,I93) -> 0.17 | J94: =CHOOSE($C$5,J91,J92,J93) -> 0.16 | K94: =CHOOSE($C$5,K91,K92,K93) -> 0.15 | L94: =CHOOSE($C$5,L91,L92,L93) -> 0.15
A95: Space: customer launches per year | N95: 33, 45 and 43 customer launches in 2023-2025 (424B4); 29 in 9M 2026. The Q3 release adds 18 NSSL and 3 NASA crew missions to the pipeline.
A96: Base | D96: 48 | E96: 52 | F96: 56 | G96: 60 | H96: 63 | I96: 66 | J96: 68 | K96: 70 | L96: 72
A97: Bull | D97: 52 | E97: 60 | F97: 68 | G97: 76 | H97: 84 | I97: 90 | J97: 95 | K97: 100 | L97: 105
A98: Bear | D98: 42 | E98: 44 | F98: 46 | G98: 48 | H98: 50 | I98: 51 | J98: 52 | K98: 53 | L98: 54
A99: Active | D99: =CHOOSE($C$5,D96,D97,D98) -> 48 | E99: =CHOOSE($C$5,E96,E97,E98) -> 52 | F99: =CHOOSE($C$5,F96,F97,F98) -> 56 | G99: =CHOOSE($C$5,G96,G97,G98) -> 60 | H99: =CHOOSE($C$5,H96,H97,H98) -> 63 | I99: =CHOOSE($C$5,I96,I97,I98) -> 66 | J99: =CHOOSE($C$5,J96,J97,J98) -> 68 | K99: =CHOOSE($C$5,K96,K97,K98) -> 70 | L99: =CHOOSE($C$5,L96,L97,L98) -> 72
A100: Space: growth in revenue per customer launch | N100: 2026E rate is a formula (launch services revenue / customer launches). Bull: Starship heavy-lift missions price higher.
A101: Base | D101: 0.03 | E101: 0.03 | F101: 0.03 | G101: 0.03 | H101: 0.03 | I101: 0.03 | J101: 0.03 | K101: 0.03 | L101: 0.03
A102: Bull | D102: 0.06 | E102: 0.06 | F102: 0.05 | G102: 0.05 | H102: 0.05 | I102: 0.04 | J102: 0.04 | K102: 0.04 | L102: 0.04
A103: Bear | D103: 0 | E103: 0 | F103: 0 | G103: 0 | H103: 0 | I103: 0 | J103: 0 | K103: 0 | L103: 0
A104: Active | D104: =CHOOSE($C$5,D101,D102,D103) -> 0.03 | E104: =CHOOSE($C$5,E101,E102,E103) -> 0.03 | F104: =CHOOSE($C$5,F101,F102,F103) -> 0.03 | G104: =CHOOSE($C$5,G101,G102,G103) -> 0.03 | H104: =CHOOSE($C$5,H101,H102,H103) -> 0.03 | I104: =CHOOSE($C$5,I101,I102,I103) -> 0.03 | J104: =CHOOSE($C$5,J101,J102,J103) -> 0.03 | K104: =CHOOSE($C$5,K101,K102,K103) -> 0.03 | L104: =CHOOSE($C$5,L101,L102,L103) -> 0.03
A105: Space: Launch & Development revenue growth | N105: US$1,510m in 2025; NASA lunar lander and crew contracts, recognised over time (424B4). Analyst input.
A106: Base | D106: 0.08 | E106: 0.08 | F106: 0.08 | G106: 0.06 | H106: 0.06 | I106: 0.05 | J106: 0.05 | K106: 0.04 | L106: 0.04
A107: Bull | D107: 0.15 | E107: 0.15 | F107: 0.12 | G107: 0.1 | H107: 0.08 | I107: 0.06 | J107: 0.06 | K107: 0.05 | L107: 0.05
A108: Bear | D108: -0.05 | E108: 0 | F108: 0 | G108: 0 | H108: 0 | I108: 0 | J108: 0 | K108: 0 | L108: 0
A109: Active | D109: =CHOOSE($C$5,D106,D107,D108) -> 0.08 | E109: =CHOOSE($C$5,E106,E107,E108) -> 0.08 | F109: =CHOOSE($C$5,F106,F107,F108) -> 0.08 | G109: =CHOOSE($C$5,G106,G107,G108) -> 0.06 | H109: =CHOOSE($C$5,H106,H107,H108) -> 0.06 | I109: =CHOOSE($C$5,I106,I107,I108) -> 0.05 | J109: =CHOOSE($C$5,J106,J107,J108) -> 0.05 | K109: =CHOOSE($C$5,K106,K107,K108) -> 0.04 | L109: =CHOOSE($C$5,L106,L107,L108) -> 0.04
A110: Space: segment adjusted EBITDA margin | N110: 16.0% in 2025, 30.4% in 2024, -5.9% in 9M 2026 (Starship development in R&D). Base returns towards 2024-2025 levels.
A111: Base | D111: 0.15 | E111: 0.18 | F111: 0.2 | G111: 0.22 | H111: 0.24 | I111: 0.25 | J111: 0.25 | K111: 0.25 | L111: 0.25
A112: Bull | D112: 0.2 | E112: 0.25 | F112: 0.28 | G112: 0.3 | H112: 0.32 | I112: 0.33 | J112: 0.33 | K112: 0.33 | L112: 0.33
A113: Bear | D113: 0.05 | E113: 0.08 | F113: 0.1 | G113: 0.12 | H113: 0.12 | I113: 0.12 | J113: 0.12 | K113: 0.12 | L113: 0.12
A114: Active | D114: =CHOOSE($C$5,D111,D112,D113) -> 0.15 | E114: =CHOOSE($C$5,E111,E112,E113) -> 0.18 | F114: =CHOOSE($C$5,F111,F112,F113) -> 0.2 | G114: =CHOOSE($C$5,G111,G112,G113) -> 0.22 | H114: =CHOOSE($C$5,H111,H112,H113) -> 0.24 | I114: =CHOOSE($C$5,I111,I112,I113) -> 0.25 | J114: =CHOOSE($C$5,J111,J112,J113) -> 0.25 | K114: =CHOOSE($C$5,K111,K112,K113) -> 0.25 | L114: =CHOOSE($C$5,L111,L112,L113) -> 0.25
A115: Space: capex | N115: US$3,832m in 2025 and in 9M 2026 (Segments_Hist): Starship factories and pads. Base stays high to 2028.
A116: Base | D116: 5500 | E116: 5500 | F116: 5000 | G116: 4500 | H116: 4000 | I116: 4000 | J116: 4000 | K116: 4000 | L116: 4000
A117: Bull | D117: 5500 | E117: 5500 | F117: 5000 | G117: 4500 | H117: 4000 | I117: 4000 | J117: 4000 | K117: 4000 | L117: 4000
A118: Bear | D118: 6000 | E118: 6000 | F118: 5500 | G118: 5000 | H118: 4500 | I118: 4500 | J118: 4500 | K118: 4500 | L118: 4500
A119: Active | D119: =CHOOSE($C$5,D116,D117,D118) -> 5500 | E119: =CHOOSE($C$5,E116,E117,E118) -> 5500 | F119: =CHOOSE($C$5,F116,F117,F118) -> 5000 | G119: =CHOOSE($C$5,G116,G117,G118) -> 4500 | H119: =CHOOSE($C$5,H116,H117,H118) -> 4000 | I119: =CHOOSE($C$5,I116,I117,I118) -> 4000 | J119: =CHOOSE($C$5,J116,J117,J118) -> 4000 | K119: =CHOOSE($C$5,K116,K117,K118) -> 4000 | L119: =CHOOSE($C$5,L116,L117,L118) -> 4000
A120: SI: nameplate compute at year end (GW) | N120: 0.8 GW end-2025, 1.7 GW at 30 Sep 2026 (filings). Bear stops adding capacity once returns fall below cost. Base 2027E +1.5 GW includes the GPUs from the Apollo lease (US$40bn) and US$25.6bn of purchase commitments due in 2027 (10-Q Note 16).
A121: Base | D121: 3.6 | E121: 5.2 | F121: 6.8 | G121: 8.4 | H121: 9.8 | I121: 11 | J121: 12 | K121: 12.8 | L121: 13.5
A122: Bull | D122: 4.2 | E122: 6.5 | F122: 9 | G122: 11.5 | H122: 14 | I122: 16 | J122: 17.5 | K122: 18.5 | L122: 19.5
A123: Bear | D123: 2.8 | E123: 3.4 | F123: 3.9 | G123: 4.3 | H123: 4.6 | I123: 4.9 | J123: 5.1 | K123: 5.3 | L123: 5.5
A124: Active | D124: =CHOOSE($C$5,D121,D122,D123) -> 3.6 | E124: =CHOOSE($C$5,E121,E122,E123) -> 5.2 | F124: =CHOOSE($C$5,F121,F122,F123) -> 6.8 | G124: =CHOOSE($C$5,G121,G122,G123) -> 8.4 | H124: =CHOOSE($C$5,H121,H122,H123) -> 9.8 | I124: =CHOOSE($C$5,I121,I122,I123) -> 11 | J124: =CHOOSE($C$5,J121,J122,J123) -> 12 | K124: =CHOOSE($C$5,K121,K122,K123) -> 12.8 | L124: =CHOOSE($C$5,L121,L122,L123) -> 13.5
A125: SI: compute revenue per average GW (USD bn a year) | N125: Q3 2026: about US$16.6bn per average GW a year (formula on Segments_Hist). One customer pays US$1.25bn a month to May 2029 (424B4). Price per GW falls as new chips arrive.
A126: Base | D126: 15.5 | E126: 14.9 | F126: 14.4 | G126: 14 | H126: 13.7 | I126: 13.4 | J126: 13.2 | K126: 13 | L126: 12.8
A127: Bull | D127: 16.5 | E127: 16 | F127: 15.6 | G127: 15.3 | H127: 15 | I127: 14.8 | J127: 14.6 | K127: 14.5 | L127: 14.4
A128: Bear | D128: 13.5 | E128: 12.3 | F128: 11.4 | G128: 10.8 | H128: 10.3 | I128: 9.9 | J128: 9.6 | K128: 9.4 | L128: 9.2
A129: Active | D129: =CHOOSE($C$5,D126,D127,D128) -> 15.5 | E129: =CHOOSE($C$5,E126,E127,E128) -> 14.9 | F129: =CHOOSE($C$5,F126,F127,F128) -> 14.4 | G129: =CHOOSE($C$5,G126,G127,G128) -> 14 | H129: =CHOOSE($C$5,H126,H127,H128) -> 13.7 | I129: =CHOOSE($C$5,I126,I127,I128) -> 13.4 | J129: =CHOOSE($C$5,J126,J127,J128) -> 13.2 | K129: =CHOOSE($C$5,K126,K127,K128) -> 13 | L129: =CHOOSE($C$5,L126,L127,L128) -> 12.8
A130: SI: capex per GW added or replaced (USD bn) | N130: 9M 2026: US$40.0bn of SI capex for +0.9 GW (formula on Segments_Hist, about US$44bn per GW, part of it for capacity not yet live). Chip prices fall in every scenario; that is also why revenue per GW falls. Analyst input.
A131: Base | D131: 42 | E131: 40 | F131: 37 | G131: 35 | H131: 33 | I131: 31 | J131: 29 | K131: 28 | L131: 27
A132: Bull | D132: 40 | E132: 37 | F132: 34 | G132: 32 | H132: 30 | I132: 28 | J132: 27 | K132: 26 | L132: 25
...

Sheet Interim_Bridge
A1: Space Exploration Technologies Corp. (SpaceX) | 2026E bridge: nine months filed plus a Q4 2026E estimate by segment
A2: 9M columns link to the filings; Q4 2026E comes from the inputs on Assumptions (Section A). Balance sheet: column B = 30 Sep 2026A, column D = 31 Dec 2026E. USD millions.
A4: Line | B4: 9M 2026A | C4: Q4 2026E | D4: FY2026E | E4: 9M 2025A | F4: Q4 2025A | G4: FY2025A | H4: Comentarios FG | I4: Source / derivation
A6: Revenue by segment
A7: Space: customer launches | B7: =Segments_Hist!F68 -> 29 | C7: =Assumptions!$C$13 -> 13 | D7: =B7+C7 -> 42 | E7: =Segments_Hist!E68 -> 36 | F7: =G7-E7 -> 7 | G7: =Segments_Hist!D68 -> 43
A8: Space: Launch Services revenue per customer launch (USD m) | B8: =B9/B7 -> 72.689655 | C8: =B8 -> 72.689655 | D8: =D9/D7 -> 72.689655 | E8: =E9/E7 -> 57.111111 | F8: =F9/F7 -> 74.285714 | G8: =G9/G7 -> 59.906977 | I8: Q4 2026E holds the 9M 2026 rate (formula).
A9: Space: Launch Services | B9: =Segments_Hist!F7 -> 2108 | C9: =C7*C8 -> 944.96552 | D9: =B9+C9 -> 3052.9655 | E9: =Segments_Hist!E7 -> 2056 | F9: =G9-E9 -> 520 | G9: =Segments_Hist!D7 -> 2576
A10: Space: Launch & Development | B10: =Segments_Hist!F8 -> 1240 | C10: =Segments_Hist!H91*(1+Assumptions!$C$14) -> 637 | D10: =B10+C10 -> 1877 | E10: =Segments_Hist!E8 -> 1221 | F10: =G10-E10 -> 289 | G10: =Segments_Hist!D8 -> 1510 | I10: Q4 2026E = Q3 2026 x (1 + input).
A11: Space | B11: =B9+B10 -> 3348 | C11: =C9+C10 -> 1581.9655 | D11: =B11+C11 -> 4929.9655 | E11: =E9+E10 -> 3277 | F11: =G11-E11 -> 809 | G11: =G9+G10 -> 4086
A12: Connectivity: consumer subscribers, period end (millions) | B12: =Segments_Hist!H122 -> 13.6 | C12: =Assumptions!$C$10 -> 15.2 | D12: =C12 -> 15.2 | E12: =Segments_Hist!D122 -> 7.2 | F12: =G12 -> 8.9 | G12: =Segments_Hist!E122 -> 8.9 | I12: B: 30 Sep 2026; C and D: 31 Dec 2026E.
A13: Connectivity: consumer ARPU (USD per month) | B13: =Segments_Hist!F65 -> 67 | C13: =Assumptions!$C$11 -> 69 | E13: =Segments_Hist!E65 -> 84 | G13: =Segments_Hist!D65 -> 81
A14: Consumer subscription revenue, Q4 2026E (ARPU x average subscribers x 3) | C14: =C13*(B12+C12)/2*3 -> 2980.8
A15: Kits and other above subscription revenue (Q3 2026 rate) | C15: =Segments_Hist!H133 -> 0.17791365
A16: Connectivity: Consumer | B16: =Segments_Hist!F10 -> 7754 | C16: =C14*(1+C15) -> 3511.125 | D16: =B16+C16 -> 11265.125 | E16: =Segments_Hist!E10 -> 5198 | F16: =G16-E16 -> 2010 | G16: =Segments_Hist!D10 -> 7208
A17: Connectivity: Enterprise & Government | B17: =Segments_Hist!F11 -> 5042 | C17: =Segments_Hist!H94*(1+Assumptions!$C$12) -> 2297.16 | D17: =B17+C17 -> 7339.16 | E17: =Segments_Hist!E11 -> 2961 | F17: =G17-E17 -> 1218 | G17: =Segments_Hist!D11 -> 4179 | I17: Q4 2026E = Q3 2026 x (1 + input).
A18: Connectivity | B18: =B16+B17 -> 12796 | C18: =C16+C17 -> 5808.285 | D18: =B18+C18 -> 18604.285 | E18: =E16+E17 -> 8159 | F18: =G18-E18 -> 3228 | G18: =G16+G17 -> 11387
A19: SI: nameplate compute, period end (GW) | B19: =Segments_Hist!H124 -> 1.7 | C19: =Assumptions!$C$15 -> 2.1 | D19: =C19 -> 2.1 | E19: =Segments_Hist!E66 -> 0.6 | F19: =G19 -> 0.8 | G19: =Segments_Hist!D66 -> 0.8
A20: SI compute revenue per average GW, annualised (USD bn) | B20: =Segments_Hist!H135 -> 16.552258 | C20: =B20*(1+Assumptions!$C$16) -> 16.552258 | I20: B: Q3 2026 rate (Segments_Hist); C = B x (1 + input).
A21: SI: compute and AI services | B21: =Segments_Hist!F14-B22 -> 9083 | C21: =(B19+C19)/2*C20*1000/4 -> 7862.3226 | D21: =B21+C21 -> 16945.323 | E21: =Segments_Hist!E14 -> 955 | F21: =G21-E21 -> 402 | G21: =Segments_Hist!D14 -> 1357
A22: SI: Cursor | B22: =Segments_Hist!H129 -> 608 | C22: =B22/47*92*(1+Assumptions!$C$17) -> 1309.1404 | D22: =B22+C22 -> 1917.1404 | E22: 0 | F22: =G22-E22 -> 0 | G22: 0 | I22: Q4 2026E = Q3 Cursor revenue / 47 days (14 Aug to 30 Sep) x 92 days x (1 + input). No Cursor revenue before 14 Aug 2026.
A23: SI: Advertising (X) | B23: =Segments_Hist!F13 -> 1248 | C23: =Segments_Hist!H96*(1+Assumptions!$C$18) -> 581.04 | D23: =B23+C23 -> 1829.04 | E23: =Segments_Hist!E13 -> 1323 | F23: =G23-E23 -> 521 | G23: =Segments_Hist!D13 -> 1844
A24: SI | B24: =B21+B22+B23 -> 10939 | C24: =C21+C22+C23 -> 9752.503 | D24: =B24+C24 -> 20691.503 | E24: =E21+E22+E23 -> 2278 | F24: =G24-E24 -> 923 | G24: =G21+G22+G23 -> 3201
A25: Revenue | B25: =B11+B18+B24 -> 27083 | C25: =C11+C18+C24 -> 17142.754 | D25: =B25+C25 -> 44225.754 | E25: =E11+E18+E24 -> 13714 | F25: =G25-E25 -> 4960 | G25: =G11+G18+G24 -> 18674
A27: Income statement
A28: Segment adjusted EBITDA: Space | B28: =Segments_Hist!F54 -> -199 | C28: =C11*Assumptions!$C$19 -> 237.29483 | D28: =B28+C28 -> 38.294828 | E28: =Segments_Hist!E54 -> 803 | F28: =G28-E28 -> -150 | G28: =Segments_Hist!D54 -> 653
A29: Segment adjusted EBITDA: Connectivity | B29: =Segments_Hist!F55 -> 8183 | C29: =C18*Assumptions!$C$20 -> 3775.3852 | D29: =B29+C29 -> 11958.385 | E29: =Segments_Hist!E55 -> 5123 | F29: =G29-E29 -> 2045 | G29: =Segments_Hist!D55 -> 7168
A30: Segment adjusted EBITDA: SI | B30: =Segments_Hist!F56 -> 5490 | C30: =C24*Assumptions!$C$21 -> 5851.5018 | D30: =B30+C30 -> 11341.502 | E30: =Segments_Hist!E56 -> -813 | F30: =G30-E30 -> -424 | G30: =Segments_Hist!D56 -> -1237
A31: Segment adjusted EBITDA, total | B31: =B28+B29+B30 -> 13474 | C31: =C28+C29+C30 -> 9864.1819 | D31: =B31+C31 -> 23338.182 | E31: =E28+E29+E30 -> 5113 | F31: =G31-E31 -> 1471 | G31: =G28+G29+G30 -> 6584
A32: Depreciation and amortization | B32: =CF_Hist!F8 -> 8934 | C32: =C50+C51+C52 -> 3746.8125 | D32: =B32+C32 -> 12680.812 | E32: =CF_Hist!E8 -> 4784 | F32: =G32-E32 -> 1917 | G32: =CF_Hist!D8 -> 6701 | I32: Q4 2026E: existing PP&E, finance-lease assets and intangibles (memo below); Q4 capex starts depreciating on 1 Jan 2027.
A33: Share-based compensation | B33: =CF_Hist!F9 -> 3833 | C33: =Schedules!C98 -> 2956.7598 | D33: =B33+C33 -> 6789.7598 | E33: =CF_Hist!E9 -> 1044 | F33: =G33-E33 -> 903 | G33: =CF_Hist!D9 -> 1947 | I33: Q4 2026E: existing awards (filed amounts) plus future grants (Schedules section H).
A34: Restructuring, impairment and acquisition costs | B34: =Segments_Hist!F44+Segments_Hist!F45+Segments_Hist!F46+Segments_Hist!F49+Segments_Hist!F50+Segments_Hist!F51+Segments_Hist!F39+Segments_Hist!F40+Segments_Hist!F41 -> 2 | C34: 0 | D34: =B34+C34 -> 2 | E34: =Segments_Hist!E44+Segments_Hist!E45+Segments_Hist!E46+Segments_Hist!E49+Segments_Hist!E50+Segments_Hist!E51+Segments_Hist!E39+Segments_Hist!E40+Segments_Hist!E41 -> 501 | F34: =G34-E34 -> 24 | G34: =Segments_Hist!D44+Segments_Hist!D45+Segments_Hist!D46+Segments_Hist!D49+Segments_Hist!D50+Segments_Hist!D51+Segments_Hist!D39+Segments_Hist!D40+Segments_Hist!D41 -> 525
A35: Income (loss) from operations | B35: =B31-B32-B33-B34 -> 705 | C35: =C31-C32-C33-C34 -> 3160.6096 | D35: =B35+C35 -> 3865.6096 | E35: =E31-E32-E33-E34 -> -1216 | F35: =G35-E35 -> -1373 | G35: =G31-G32-G33-G34 -> -2589
A36: Interest expense | B36: =IS_Hist!F15 -> -1968 | C36: =-B53*B94/4 -> -675 | D36: =B36+C36 -> -2643 | E36: =IS_Hist!E15 -> -1372 | F36: =G36-E36 -> -573 | G36: =IS_Hist!D15 -> -1945 | I36: Q4 2026E: blended rate (memo) x debt and finance leases at 30 Sep 2026 / 4.
A37: Interest income | B37: =IS_Hist!F16 -> 1426 | C37: =Assumptions!$C$53*B81/4 -> 947.97025 | D37: =B37+C37 -> 2373.9703 | E37: =IS_Hist!E16 -> 370 | F37: =G37-E37 -> 122 | G37: =IS_Hist!D16 -> 492 | I37: Q4 2026E: yield x cash and securities at 30 Sep 2026 / 4.
A38: Other income (expense), net | B38: =IS_Hist!F17 -> -937 | C38: 0 | D38: =B38+C38 -> -937 | E38: =IS_Hist!E17 -> 342 | F38: =G38-E38 -> -519 | G38: =IS_Hist!D17 -> -177 | I38: Not forecast (marks on digital assets and investments).
A39: Income (loss) before income taxes | B39: =B35+B36+B37+B38 -> -774 | C39: =C35+C36+C37+C38 -> 3433.5799 | D39: =B39+C39 -> 2659.5799 | E39: =E35+E36+E37+E38 -> -1876 | F39: =G39-E39 -> -2343 | G39: =G35+G36+G37+G38 -> -4219
A40: Provision for (benefit from) income taxes | B40: =IS_Hist!F19 -> -361 | C40: =MAX(0,C39)*Assumptions!$C$25 -> 171.67899 | D40: =B40+C40 -> -189.32101 | E40: =IS_Hist!E19 -> 714 | F40: =G40-E40 -> 4 | G40: =IS_Hist!D19 -> 718
A41: Net income (loss) | B41: =B39-B40 -> -413 | C41: =C39-C40 -> 3261.9009 | D41: =B41+C41 -> 2848.9009 | E41: =E39-E40 -> -2590 | F41: =G41-E41 -> -2347 | G41: =G39-G40 -> -4937
A43: Memo: depreciation base at 30 Sep 2026 (derived from the filings)
A44: Q3 2026 depreciation and amortization | B44: =Quarterly_Hist!H20 -> 3644
A45: Q3 2026 amortization of intangibles | B45: 293 | I45: 10-Q Q3 2026 p. 15: 'Amortization expense ... $293 million' (Note 6)
A46: Q3 2026 amortization of finance-lease assets | B46: 79 | I46: 10-Q Q3 2026 p. 22
A47: Q3 2026 depreciation of PP&E (derived) | B47: =B44-B45-B46 -> 3272
A48: Remaining life of PP&E at 30 Sep 2026 (years, derived) | B48: =BS_Hist!D14/(B47*4) -> 6.8370263 | I48: PP&E / annualised Q3 depreciation. Construction in progress makes the true life longer; convention.
A49: Finite-lived intangibles, net, 30 Sep 2026 | B49: 6333 | I49: 10-Q Q3 2026 p. 15: total net carrying value US$6,333m; indefinite-lived US$21m
A50: PP&E depreciation, Q4 2026E | C50: =BS_Hist!D14/B48/4 -> 3272
A51: Finance-lease asset amortization, Q4 2026E | C51: =MIN(BS_Hist!D15,B46) -> 79
A52: Intangible amortization, Q4 2026E | C52: =B49/Assumptions!$C$63/4 -> 395.8125
A53: Blended rate on debt and finance leases (derived) | B53: =-Quarterly_Hist!H14*4/BS_Hist!D48 -> 0.069508804 | I53: Q3 2026 interest expense x 4 / debt and finance leases at 30 Sep 2026. Includes Valor financings (related-party interest US$351m in Q3).
A55: Capex and spectrum
A56: Capex: Space | B56: =Segments_Hist!F59 -> 3832 | C56: =Assumptions!$C$22 -> 1600 | D56: =B56+C56 -> 5432 | E56: =Segments_Hist!E59 -> 2818 | F56: =G56-E56 -> 1014 | G56: =Segments_Hist!D59 -> 3832
A57: Capex: Connectivity | B57: =Segments_Hist!F60 -> 4242 | C57: =Assumptions!$C$23 -> 1600 | D57: =B57+C57 -> 5842 | E57: =Segments_Hist!E60 -> 2951 | F57: =G57-E57 -> 1227 | G57: =Segments_Hist!D60 -> 4178
A58: Capex: SI | B58: =Segments_Hist!F61 -> 39995 | C58: =Assumptions!$C$24 -> 20000 | D58: =B58+C58 -> 59995 | E58: =Segments_Hist!E61 -> 8077 | F58: =G58-E58 -> 4650 | G58: =Segments_Hist!D61 -> 12727
A59: Capex, total | B59: =B56+B57+B58 -> 48069 | C59: =C56+C57+C58 -> 23200 | D59: =B59+C59 -> 71269 | E59: =E56+E57+E58 -> 13846 | F59: =G59-E59 -> 6891 | G59: =G56+G57+G58 -> 20737
A60: EchoStar spectrum: Spectrum Credit Agreement payments | C60: =Assumptions!$C$39-Assumptions!$C$40 -> 385 | D60: =C60 -> 385 | I60: Q4 2026E = 2026 payments (424B4 p. 124) less the US$856m paid by 30 Sep (10-Q). Paid to the Trust; the 9M payments sit in other assets.
A62: Cash flow (9M 2026A as filed; Q4 2026E from the rows above and the balance sheet below)
A63: Net income (loss) | B63: =CF_Hist!F7 -> -413 | C63: =C41 -> 3261.9009 | D63: =B63+C63 -> 2848.9009
A64: Depreciation and amortization | B64: =CF_Hist!F8 -> 8934 | C64: =C32 -> 3746.8125 | D64: =B64+C64 -> 12680.812
A65: Share-based compensation | B65: =CF_Hist!F9 -> 3833 | C65: =C33 -> 2956.7598 | D65: =B65+C65 -> 6789.7598
A66: Other non-cash items (deferred tax, marks, loss on debt extinguishment, other) | B66: =CF_Hist!F11+CF_Hist!F12+CF_Hist!F13+CF_Hist!F16+CF_Hist!F17 -> 368 | C66: 0 | D66: =B66+C66 -> 368
A67: Changes in operating assets and liabilities | B67: =CF_Hist!F20+CF_Hist!F21+CF_Hist!F22+CF_Hist!F23+CF_Hist!F24+CF_Hist!F26 -> 375 | C67: =-(D82-B82)-(D83-B83)-(D84-B84)+(D91-B91)+(D92-B92)+(D93-B93) -> 4860.8214 | D67: =B67+C67 -> 5235.8214
A68: Net cash provided by operating activities | B68: =B63+B64+B65+B66+B67 -> 13097 | C68: =C63+C64+C65+C66+C67 -> 14826.295 | D68: =B68+C68 -> 27923.295
A69: Purchases of property, plant, and equipment | B69: =CF_Hist!F30 -> -48069 | C69: =-C59 -> -23200 | D69: =B69+C69 -> -71269
A70: EchoStar spectrum payments | B70: 0 | C70: =-C60 -> -385 | D70: =B70+C70 -> -385
A71: Other investing (rebates, intangibles, acquisitions, other) | B71: =CF_Hist!F31+CF_Hist!F32+CF_Hist!F36+CF_Hist!F37+CF_Hist!F39 -> 1057 | C71: 0 | D71: =B71+C71 -> 1057
A72: Add back: marketable securities bought less matured or sold (inside the model's cash) | B72: =-(CF_Hist!F33+CF_Hist!F34+CF_Hist!F35) -> 37599 | C72: 0 | D72: =B72+C72 -> 37599 | I72: The model's cash is cash plus marketable securities, so buying securities is not an outflow.
A73: Debt and finance leases, net | B73: =CF_Hist!F43+CF_Hist!F44+CF_Hist!F45+CF_Hist!F46+CF_Hist!F47 -> 10442 | C73: =-Debt_Credit!B30-C51 -> -574 | D73: =B73+C73 -> 9868 | I73: Q4 2026E: scheduled maturities (US$495m, 10-Q Note 9) and finance-lease principal (taken equal to the asset amortization).
A74: Equity: IPO, stock issued and repurchased | B74: =CF_Hist!F48+CF_Hist!F49+CF_Hist!F50+CF_Hist!F51+CF_Hist!F52 -> 89377 | C74: 0 | D74: =B74+C74 -> 89377
A75: Restricted cash, exchange rates and security marks (balancing item) | B75: =B81-B77-(B68+B69+B70+B71+B72+B73+B74) -> -38395 | C75: 0 | D75: =B75+C75 -> -38395 | I75: 9M 2026: restricted cash rose US$1,715m (Note 2 table), FX -43, unrealised marks on securities.
A76: Net change in cash and marketable securities | B76: =B68+B69+B70+B71+B72+B73+B74+B75 -> 65108 | C76: =C68+C69+C70+C71+C72+C73+C74+C75 -> -9332.7054 | D76: =B76+C76 -> 55775.295
A77: Cash and marketable securities, beginning | B77: =BS_Hist!C46 -> 24747 | C77: =B81 -> 89855 | D77: =B77 -> 24747
A78: Cash and marketable securities, ending | B78: =B77+B76 -> 89855 | C78: =C77+C76 -> 80522.295 | D78: =C78 -> 80522.295
A80: Balance sheet: 30 Sep 2026A (column B) to 31 Dec 2026E (column D)
A81: Cash and marketable securities | B81: =BS_Hist!D46 -> 89855 | D81: =C78 -> 80522.295
A82: Accounts receivable | B82: =BS_Hist!D9 -> 4772 | D82: =B82*C25/Quarterly_Hist!H6 -> 5612.708 | I82: Scaled by Q4 2026E revenue / Q3 2026 revenue.
A83: Inventory | B83: =BS_Hist!D10 -> 2891 | D83: =B83*C25/Quarterly_Hist!H6 -> 3400.3225
A84: Prepaid expenses and other current assets | B84: =BS_Hist!D11 -> 3457 | D84: =B84*C25/Quarterly_Hist!H6 -> 4066.0377
A85: Property, plant, and equipment, net | B85: =BS_Hist!D14 -> 89483 | D85: =B85+C59-C50 -> 109411
A86: Finance lease right-of-use assets | B86: =BS_Hist!D15 -> 1040 | D86: =B86-C51 -> 961
A87: Intangible assets, net | B87: =BS_Hist!D16 -> 6354 | D87: =B87-C52 -> 5958.1875
A88: EchoStar spectrum (payments to the Trust from Q4 2026) | B88: 0 | D88: =B88+C60 -> 385
A89: Goodwill, digital assets, deferred tax and other assets | B89: =BS_Hist!D18+BS_Hist!D17+BS_Hist!D19+BS_Hist!D20 -> 56193 | D89: =B89 -> 56193 | I89: Held flat.
A90: Total assets | B90: =B81+B82+B83+B84+B85+B86+B87+B88+B89 -> 254045 | D90: =D81+D82+D83+D84+D85+D86+D87+D88+D89 -> 266509.55
A91: Accounts payable | B91: =BS_Hist!D23 -> 13259 | D91: =B91*(C59+C25-C31)/(SUM(Segments_Hist!H112:Segments_Hist!H114)+Quarterly_Hist!H6-Quarterly_Hist!H21) -> 15935.777 | I91: Scaled by capex plus cash operating costs, Q4 2026E against Q3 2026 (most payables are for PP&E: US$11,827m at 30 Sep).
A92: Deferred revenue, current and noncurrent | B92: =BS_Hist!D47 -> 17520 | D92: =B92*C25/Quarterly_Hist!H6 -> 20606.589
A93: Accrued expenses and other current liabilities | B93: =BS_Hist!D26 -> 5997 | D93: =B93*C25/Quarterly_Hist!H6 -> 7053.5227
A94: Debt and finance leases (carrying) | B94: =BS_Hist!D48 -> 38844 | D94: =B94+C73 -> 38270
A95: Other liabilities | B95: =BS_Hist!D31 -> 1657 | D95: =B95 -> 1657 | I95: Held flat.
A96: Total liabilities | B96: =B91+B92+B93+B94+B95 -> 77277 | D96: =D91+D92+D93+D94+D95 -> 83522.89
A97: Shareholders' equity | B97: =BS_Hist!D42 -> 176768 | D97: =B97+C41+C33 -> 182986.66
A98: Total liabilities and equity | B98: =B96+B97 -> 254045 | D98: =D96+D97 -> 266509.55
A99: Memo: net working capital (receivables + inventory + prepaid - payables - deferred revenue - accrued) | B99: =B82+B83+B84-B91-B92-B93 -> -25656 | D99: =D82+D83+D84-D91-D92-D93 -> -30516.821
A101: Q4 2026E unlevered free cash flow (feeds the DCF)
A102: Income from operations | C102: =C35 -> 3160.6096
A103: Taxes on operating income | C103: =-MAX(0,C35)*Assumptions!$C$25 -> -158.03048
A104: Depreciation and amortization | C104: =C32 -> 3746.8125
A105: Add back: expense of existing awards (shares already in the diluted count) | C105: =Schedules!C96 -> 2356.7634
A106: Capex | C106: =-C59 -> -23200
A107: EchoStar spectrum payments | C107: =-C60 -> -385
A108: Change in working capital | C108: =C67 -> 4860.8214
...

Sheet Segments_Fcst
A1: Space Exploration Technologies Corp. (SpaceX) | Segment build: drivers, revenue, adjusted EBITDA and capex, 2025A and 2026E-2035E
A2: 2025A links to Segments_Hist; 2026E to Interim_Bridge; 2027E onward from Assumptions (active scenario). USD millions unless stated.
B3: Actual | C3: Forecast
A4: Fiscal year ends 31 December | B4: 2025A | C4: 2026E | D4: 2027E | E4: 2028E | F4: 2029E | G4: 2030E | H4: 2031E | I4: 2032E | J4: 2033E | K4: 2034E | L4: 2035E | M4: Comentarios FG | N4: Source / derivation
A6: Space
A7: Customer launches | B7: =Segments_Hist!D68 -> 43 | C7: =Interim_Bridge!D7 -> 42 | D7: =Assumptions!D99 -> 48 | E7: =Assumptions!E99 -> 52 | F7: =Assumptions!F99 -> 56 | G7: =Assumptions!G99 -> 60 | H7: =Assumptions!H99 -> 63 | I7: =Assumptions!I99 -> 66 | J7: =Assumptions!J99 -> 68 | K7: =Assumptions!K99 -> 70 | L7: =Assumptions!L99 -> 72
A8: Launch Services revenue per customer launch (USD m) | B8: =B9/B7 -> 59.906977 | C8: =Interim_Bridge!D8 -> 72.689655 | D8: =C8*(1+Assumptions!D104) -> 74.870345 | E8: =D8*(1+Assumptions!E104) -> 77.116455 | F8: =E8*(1+Assumptions!F104) -> 79.429949 | G8: =F8*(1+Assumptions!G104) -> 81.812847 | H8: =G8*(1+Assumptions!H104) -> 84.267233 | I8: =H8*(1+Assumptions!I104) -> 86.79525 | J8: =I8*(1+Assumptions!J104) -> 89.399107 | K8: =J8*(1+Assumptions!K104) -> 92.08108 | L8: =K8*(1+Assumptions!L104) -> 94.843513
A9: Launch Services | B9: =Segments_Hist!D7 -> 2576 | C9: =Interim_Bridge!D9 -> 3052.9655 | D9: =D7*D8 -> 3593.7766 | E9: =E7*E8 -> 4010.0557 | F9: =F7*F8 -> 4448.0771 | G9: =G7*G8 -> 4908.7708 | H9: =H7*H8 -> 5308.8357 | I9: =I7*I8 -> 5728.4865 | J9: =J7*J8 -> 6079.1393 | K9: =K7*K8 -> 6445.6756 | L9: =L7*L8 -> 6828.7329
A10: Launch & Development | B10: =Segments_Hist!D8 -> 1510 | C10: =Interim_Bridge!D10 -> 1877 | D10: =C10*(1+Assumptions!D109) -> 2027.16 | E10: =D10*(1+Assumptions!E109) -> 2189.3328 | F10: =E10*(1+Assumptions!F109) -> 2364.4794 | G10: =F10*(1+Assumptions!G109) -> 2506.3482 | H10: =G10*(1+Assumptions!H109) -> 2656.7291 | I10: =H10*(1+Assumptions!I109) -> 2789.5655 | J10: =I10*(1+Assumptions!J109) -> 2929.0438 | K10: =J10*(1+Assumptions!K109) -> 3046.2056 | L10: =K10*(1+Assumptions!L109) -> 3168.0538
A11: Space revenue | B11: =B9+B10 -> 4086 | C11: =C9+C10 -> 4929.9655 | D11: =D9+D10 -> 5620.9366 | E11: =E9+E10 -> 6199.3885 | F11: =F9+F10 -> 6812.5566 | G11: =G9+G10 -> 7415.119 | H11: =H9+H10 -> 7965.5647 | I11: =I9+I10 -> 8518.052 | ... L11: =L9+L10 -> 9996.7867
A12: Space adjusted EBITDA | B12: =Segments_Hist!D54 -> 653 | C12: =Interim_Bridge!D28 -> 38.294828 | D12: =D11*Assumptions!D114 -> 843.14048 | E12: =E11*Assumptions!E114 -> 1115.8899 | F12: =F11*Assumptions!F114 -> 1362.5113 | G12: =G11*Assumptions!G114 -> 1631.3262 | H12: =H11*Assumptions!H114 -> 1911.7355 | I12: =I11*Assumptions!I114 -> 2129.513 | J12: =J11*Assumptions!J114 -> 2252.0458 | K12: =K11*Assumptions!K114 -> 2372.9703 | L12: =L11*Assumptions!L114 -> 2499.1967
A13: Margin | B13: =B12/B11 -> 0.159814 | C13: =C12/C11 -> 0.0077677678 | D13: =D12/D11 -> 0.15 | E13: =E12/E11 -> 0.18 | F13: =F12/F11 -> 0.2 | G13: =G12/G11 -> 0.22 | H13: =H12/H11 -> 0.24 | I13: =I12/I11 -> 0.25 | ... L13: =L12/L11 -> 0.25
A14: Space capex | B14: =Segments_Hist!D59 -> 3832 | C14: =Interim_Bridge!D56 -> 5432 | D14: =Assumptions!D119 -> 5500 | E14: =Assumptions!E119 -> 5500 | F14: =Assumptions!F119 -> 5000 | G14: =Assumptions!G119 -> 4500 | H14: =Assumptions!H119 -> 4000 | I14: =Assumptions!I119 -> 4000 | J14: =Assumptions!J119 -> 4000 | K14: =Assumptions!K119 -> 4000 | L14: =Assumptions!L119 -> 4000
A16: Connectivity
A17: Consumer subscribers, year end (millions) | B17: =Segments_Hist!D64 -> 8.9 | C17: =Interim_Bridge!D12 -> 15.2 | D17: =Assumptions!D74 -> 21 | E17: =Assumptions!E74 -> 28 | F17: =Assumptions!F74 -> 35 | G17: =Assumptions!G74 -> 41 | H17: =Assumptions!H74 -> 47 | I17: =Assumptions!I74 -> 52 | J17: =Assumptions!J74 -> 56 | K17: =Assumptions!K74 -> 60 | L17: =Assumptions!L74 -> 63
A18: Consumer ARPU (USD per month) | B18: =Segments_Hist!D65 -> 81 | C18: =Interim_Bridge!C13 -> 69 | D18: =Assumptions!D79 -> 66 | E18: =Assumptions!E79 -> 64 | F18: =Assumptions!F79 -> 62 | G18: =Assumptions!G79 -> 61 | H18: =Assumptions!H79 -> 60 | I18: =Assumptions!I79 -> 60 | J18: =Assumptions!J79 -> 60 | K18: =Assumptions!K79 -> 60 | L18: =Assumptions!L79 -> 60 | N18: 2026E column shows the Q4 2026E input.
A19: Consumer subscription revenue (ARPU x average subscribers x 12) | D19: =D18*(C17+D17)/2*12 -> 14335.2 | E19: =E18*(D17+E17)/2*12 -> 18816 | F19: =F18*(E17+F17)/2*12 -> 23436 | G19: =G18*(F17+G17)/2*12 -> 27816 | H19: =H18*(G17+H17)/2*12 -> 31680 | I19: =I18*(H17+I17)/2*12 -> 35640 | J19: =J18*(I17+J17)/2*12 -> 38880 | K19: =K18*(J17+K17)/2*12 -> 41760 | L19: =L18*(K17+L17)/2*12 -> 44280
A20: Consumer revenue (subscription x (1 + kits and other, Q3 2026 rate)) | B20: =Segments_Hist!D10 -> 7208 | C20: =Interim_Bridge!D16 -> 11265.125 | D20: =D19*(1+Interim_Bridge!$C$15) -> 16885.628 | E20: =E19*(1+Interim_Bridge!$C$15) -> 22163.623 | F20: =F19*(1+Interim_Bridge!$C$15) -> 27605.584 | G20: =G19*(1+Interim_Bridge!$C$15) -> 32764.846 | H20: =H19*(1+Interim_Bridge!$C$15) -> 37316.304 | I20: =I19*(1+Interim_Bridge!$C$15) -> 41980.842 | J20: =J19*(1+Interim_Bridge!$C$15) -> 45797.283 | K20: =K19*(1+Interim_Bridge!$C$15) -> 49189.674 | L20: =L19*(1+Interim_Bridge!$C$15) -> 52158.016
A21: Enterprise & Government | B21: =Segments_Hist!D11 -> 4179 | C21: =Interim_Bridge!D17 -> 7339.16 | D21: =C21*(1+Assumptions!D84) -> 10641.782 | E21: =D21*(1+Assumptions!E84) -> 14366.406 | F21: =E21*(1+Assumptions!F84) -> 18676.327 | G21: =F21*(1+Assumptions!G84) -> 23345.409 | H21: =G21*(1+Assumptions!H84) -> 28014.491 | I21: =H21*(1+Assumptions!I84) -> 32216.665 | J21: =I21*(1+Assumptions!J84) -> 36082.665 | K21: =J21*(1+Assumptions!K84) -> 39690.931 | L21: =K21*(1+Assumptions!L84) -> 42866.205
A22: Connectivity revenue | B22: =B20+B21 -> 11387 | C22: =C20+C21 -> 18604.285 | D22: =D20+D21 -> 27527.41 | E22: =E20+E21 -> 36530.029 | F22: =F20+F21 -> 46281.912 | G22: =G20+G21 -> 56110.255 | H22: =H20+H21 -> 65330.795 | I22: =I20+I21 -> 74197.507 | ... L22: =L20+L21 -> 95024.222
A23: Connectivity adjusted EBITDA | B23: =Segments_Hist!D55 -> 7168 | C23: =Interim_Bridge!D29 -> 11958.385 | D23: =D22*Assumptions!D89 -> 17617.542 | E23: =E22*Assumptions!E89 -> 23744.519 | F23: =F22*Assumptions!F89 -> 30083.243 | G23: =G22*Assumptions!G89 -> 37032.768 | H23: =H22*Assumptions!H89 -> 43118.325 | I23: =I22*Assumptions!I89 -> 48970.355 | J23: =J22*Assumptions!J89 -> 54040.765 | K23: =K22*Assumptions!K89 -> 58661.199 | L23: =L22*Assumptions!L89 -> 62715.986
A24: Margin | B24: =B23/B22 -> 0.62948977 | C24: =C23/C22 -> 0.64277586 | D24: =D23/D22 -> 0.64 | E24: =E23/E22 -> 0.65 | F24: =F23/F22 -> 0.65 | G24: =G23/G22 -> 0.66 | H24: =H23/H22 -> 0.66 | I24: =I23/I22 -> 0.66 | ... L24: =L23/L22 -> 0.66
A25: Connectivity capex | B25: =Segments_Hist!D60 -> 4178 | C25: =Interim_Bridge!D57 -> 5842 | D25: =D22*Assumptions!D94 -> 7707.6747 | E25: =E22*Assumptions!E94 -> 9132.5072 | F25: =F22*Assumptions!F94 -> 10182.021 | G25: =G22*Assumptions!G94 -> 11222.051 | H25: =H22*Assumptions!H94 -> 11759.543 | I25: =I22*Assumptions!I94 -> 12613.576 | J25: =J22*Assumptions!J94 -> 13100.792 | K25: =K22*Assumptions!K94 -> 13332.091 | L25: =L22*Assumptions!L94 -> 14253.633
A27: SI (Super Intelligence: compute, Grok, Cursor, X advertising)
A28: Nameplate compute, year end (GW) | B28: =Segments_Hist!D66 -> 0.8 | C28: =Interim_Bridge!D19 -> 2.1 | D28: =C28+(Assumptions!D124-Assumptions!$C$15)*(1+Assumptions!$C$65) -> 3.6 | E28: =D28+(Assumptions!E124-Assumptions!D124)*(1+Assumptions!$C$65) -> 5.2 | F28: =E28+(Assumptions!F124-Assumptions!E124)*(1+Assumptions!$C$65) -> 6.8 | G28: =F28+(Assumptions!G124-Assumptions!F124)*(1+Assumptions!$C$65) -> 8.4 | H28: =G28+(Assumptions!H124-Assumptions!G124)*(1+Assumptions!$C$65) -> 9.8 | I28: =H28+(Assumptions!I124-Assumptions!H124)*(1+Assumptions!$C$65) -> 11 | J28: =I28+(Assumptions!J124-Assumptions!I124)*(1+Assumptions!$C$65) -> 12 | K28: =J28+(Assumptions!K124-Assumptions!J124)*(1+Assumptions!$C$65) -> 12.8 | L28: =K28+(Assumptions!L124-Assumptions!K124)*(1+Assumptions!$C$65) -> 13.5 | N28: 2027E onward: prior year + the input addition x (1 + the sensitivity shift on GW additions).
A29: GW added in the year | B29: =Segments_Hist!D66-Segments_Hist!C66 -> 0.5 | C29: =C28-B28 -> 1.3 | D29: =D28-C28 -> 1.5 | E29: =E28-D28 -> 1.6 | F29: =F28-E28 -> 1.6 | G29: =G28-F28 -> 1.6 | H29: =H28-G28 -> 1.4 | I29: =I28-H28 -> 1.2 | J29: =J28-I28 -> 1 | ... L29: =L28-K28 -> 0.7
A30: Year | B30: 2025 | C30: 2026 | D30: 2027 | E30: 2028 | F30: 2029 | G30: 2030 | H30: 2031 | I30: 2032 | J30: 2033 | K30: 2034 | L30: 2035
A31: GW replaced: capacity added 'useful life' years earlier | D31: =SUMPRODUCT(($B$30:$L$30=D30-Assumptions!$C$62)*$B$29:$L$29)+IF(D30-Assumptions!$C$62=2024,Segments_Hist!C66-Segments_Hist!B66,0) -> 0 | E31: =SUMPRODUCT(($B$30:$L$30=E30-Assumptions!$C$62)*$B$29:$L$29)+IF(E30-Assumptions!$C$62=2024,Segments_Hist!C66-Segments_Hist!B66,0) -> 0 | F31: =SUMPRODUCT(($B$30:$L$30=F30-Assumptions!$C$62)*$B$29:$L$29)+IF(F30-Assumptions!$C$62=2024,Segments_Hist!C66-Segments_Hist!B66,0) -> 0 | G31: =SUMPRODUCT(($B$30:$L$30=G30-Assumptions!$C$62)*$B$29:$L$29)+IF(G30-Assumptions!$C$62=2024,Segments_Hist!C66-Segments_Hist!B66,0) -> 0 | H31: =SUMPRODUCT(($B$30:$L$30=H30-Assumptions!$C$62)*$B$29:$L$29)+IF(H30-Assumptions!$C$62=2024,Segments_Hist!C66-Segments_Hist!B66,0) -> 0.3 | I31: =SUMPRODUCT(($B$30:$L$30=I30-Assumptions!$C$62)*$B$29:$L$29)+IF(I30-Assumptions!$C$62=2024,Segments_Hist!C66-Segments_Hist!B66,0) -> 0.5 | J31: =SUMPRODUCT(($B$30:$L$30=J30-Assumptions!$C$62)*$B$29:$L$29)+IF(J30-Assumptions!$C$62=2024,Segments_Hist!C66-Segments_Hist!B66,0) -> 1.3 | K31: =SUMPRODUCT(($B$30:$L$30=K30-Assumptions!$C$62)*$B$29:$L$29)+IF(K30-Assumptions!$C$62=2024,Segments_Hist!C66-Segments_Hist!B66,0) -> 1.5 | L31: =SUMPRODUCT(($B$30:$L$30=L30-Assumptions!$C$62)*$B$29:$L$29)+IF(L30-Assumptions!$C$62=2024,Segments_Hist!C66-Segments_Hist!B66,0) -> 1.6 | N31: Replacement of chips and equipment at the end of their life; 2024 additions from Segments_Hist.
A32: Compute revenue per average GW (USD bn a year) | C32: =Interim_Bridge!C20 -> 16.552258 | D32: =Assumptions!D129*(1+Assumptions!$C$66) -> 15.5 | E32: =Assumptions!E129*(1+Assumptions!$C$66) -> 14.9 | F32: =Assumptions!F129*(1+Assumptions!$C$66) -> 14.4 | G32: =Assumptions!G129*(1+Assumptions!$C$66) -> 14 | H32: =Assumptions!H129*(1+Assumptions!$C$66) -> 13.7 | I32: =Assumptions!I129*(1+Assumptions!$C$66) -> 13.4 | J32: =Assumptions!J129*(1+Assumptions!$C$66) -> 13.2 | K32: =Assumptions!K129*(1+Assumptions!$C$66) -> 13 | L32: =Assumptions!L129*(1+Assumptions!$C$66) -> 12.8 | N32: 2026E column shows the Q4 2026E rate. 2027E onward: input x (1 + sensitivity shift).
A33: Compute and AI services revenue (average GW x revenue per GW) | B33: =Segments_Hist!D14 -> 1357 | C33: =Interim_Bridge!D21 -> 16945.323 | D33: =(C28+D28)/2*D32*1000 -> 44175 | E33: =(D28+E28)/2*E32*1000 -> 65560 | F33: =(E28+F28)/2*F32*1000 -> 86400 | G33: =(F28+G28)/2*G32*1000 -> 106400 | H33: =(G28+H28)/2*H32*1000 -> 124670 | I33: =(H28+I28)/2*I32*1000 -> 139360 | J33: =(I28+J28)/2*J32*1000 -> 151800 | K33: =(J28+K28)/2*K32*1000 -> 161200 | L33: =(K28+L28)/2*L32*1000 -> 168320
A34: Cursor | B34: 0 | C34: =Interim_Bridge!D22 -> 1917.1404 | D34: =C34*(1+Assumptions!D139) -> 3067.4247 | E34: =D34*(1+Assumptions!E139) -> 4294.3946 | F34: =E34*(1+Assumptions!F139) -> 5582.7129 | G34: =F34*(1+Assumptions!G139) -> 6810.9098 | H34: =G34*(1+Assumptions!H139) -> 7900.6553 | I34: =H34*(1+Assumptions!I139) -> 8848.734 | J34: =I34*(1+Assumptions!J139) -> 9733.6074 | K34: =J34*(1+Assumptions!K139) -> 10512.296 | L34: =K34*(1+Assumptions!L139) -> 11143.034
A35: Advertising (X) | B35: =Segments_Hist!D13 -> 1844 | C35: =Interim_Bridge!D23 -> 1829.04 | D35: =C35*(1+Assumptions!D144) -> 1883.9112 | E35: =D35*(1+Assumptions!E144) -> 1940.4285 | F35: =E35*(1+Assumptions!F144) -> 1998.6414 | G35: =F35*(1+Assumptions!G144) -> 2058.6006 | H35: =G35*(1+Assumptions!H144) -> 2120.3587 | I35: =H35*(1+Assumptions!I144) -> 2183.9694 | J35: =I35*(1+Assumptions!J144) -> 2249.4885 | K35: =J35*(1+Assumptions!K144) -> 2316.9731 | L35: =K35*(1+Assumptions!L144) -> 2386.4823
A36: SI revenue | B36: =B33+B34+B35 -> 3201 | C36: =C33+C34+C35 -> 20691.503 | D36: =D33+D34+D35 -> 49126.336 | E36: =E33+E34+E35 -> 71794.823 | F36: =F33+F34+F35 -> 93981.354 | G36: =G33+G34+G35 -> 115269.51 | H36: =H33+H34+H35 -> 134691.01 | I36: =I33+I34+I35 -> 150392.7 | ... L36: =L33+L34+L35 -> 181849.52
A37: SI adjusted EBITDA | B37: =Segments_Hist!D56 -> -1237 | C37: =Interim_Bridge!D30 -> 11341.502 | D37: =D36*Assumptions!D149 -> 29475.802 | E37: =E36*Assumptions!E149 -> 43076.894 | F37: =F36*Assumptions!F149 -> 56388.813 | G37: =G36*Assumptions!G149 -> 69161.706 | H37: =H36*Assumptions!H149 -> 80814.608 | I37: =I36*Assumptions!I149 -> 90235.622 | J37: =J36*Assumptions!J149 -> 98269.858 | K37: =K36*Assumptions!K149 -> 104417.56 | L37: =L36*Assumptions!L149 -> 109109.71
A38: Margin | B38: =B37/B36 -> -0.38644174 | C38: =C37/C36 -> 0.54812363 | D38: =D37/D36 -> 0.6 | E38: =E37/E36 -> 0.6 | F38: =F37/F36 -> 0.6 | G38: =G37/G36 -> 0.6 | H38: =H37/H36 -> 0.6 | I38: =I37/I36 -> 0.6 | ... L38: =L37/L36 -> 0.6
A39: Capacity cost: (GW added + GW replaced) x capex per GW | D39: =(D29+D31)*Assumptions!D134*1000 -> 63000 | E39: =(E29+E31)*Assumptions!E134*1000 -> 64000 | F39: =(F29+F31)*Assumptions!F134*1000 -> 59200 | G39: =(G29+G31)*Assumptions!G134*1000 -> 56000 | H39: =(H29+H31)*Assumptions!H134*1000 -> 56100 | I39: =(I29+I31)*Assumptions!I134*1000 -> 52700 | J39: =(J29+J31)*Assumptions!J134*1000 -> 66700 | K39: =(K29+K31)*Assumptions!K134*1000 -> 64400 | L39: =(L29+L31)*Assumptions!L134*1000 -> 62100
A40: Of which GPUs financed by the Apollo lease (non-cash) | D40: =Schedules!D27 -> 40000 | E40: =Schedules!E27 -> 0 | F40: =Schedules!F27 -> 0 | G40: =Schedules!G27 -> 0 | H40: =Schedules!H27 -> 0 | I40: =Schedules!I27 -> 0 | J40: =Schedules!J27 -> 0 | K40: =Schedules!K27 -> 0 | L40: =Schedules!L27 -> 0
A41: SI capex, gross (cash and leased) | B41: =Segments_Hist!D61 -> 12727 | C41: =Interim_Bridge!D58 -> 59995 | D41: =MAX(D39,D40) -> 63000 | E41: =MAX(E39,E40) -> 64000 | F41: =MAX(F39,F40) -> 59200 | G41: =MAX(G39,G40) -> 56000 | H41: =MAX(H39,H40) -> 56100 | I41: =MAX(I39,I40) -> 52700 | J41: =MAX(J39,J40) -> 66700 | K41: =MAX(K39,K40) -> 64400 | L41: =MAX(L39,L40) -> 62100
A43: Total
A44: Revenue | B44: =B11+B22+B36 -> 18674 | C44: =C11+C22+C36 -> 44225.754 | D44: =D11+D22+D36 -> 82274.682 | E44: =E11+E22+E36 -> 114524.24 | F44: =F11+F22+F36 -> 147075.82 | G44: =G11+G22+G36 -> 178794.88 | H44: =H11+H22+H36 -> 207987.37 | I44: =I11+I22+I36 -> 233108.26 | ... L44: =L11+L22+L36 -> 286870.52
A45: Growth | C45: =C44/B44-1 -> 1.3683064 | D45: =D44/C44-1 -> 0.86033421 | E45: =E44/D44-1 -> 0.39197427 | F45: =F44/E44-1 -> 0.28423312 | G45: =G44/F44-1 -> 0.21566469 | H45: =H44/G44-1 -> 0.16327363 | I45: =I44/H44-1 -> 0.12078083 | J45: =J44/I44-1 -> 0.092501927 | ... L45: =L44/K44-1 -> 0.053115551
A46: Segment adjusted EBITDA | B46: =B12+B23+B37 -> 6584 | C46: =C12+C23+C37 -> 23338.182 | D46: =D12+D23+D37 -> 47936.484 | E46: =E12+E23+E37 -> 67937.303 | F46: =F12+F23+F37 -> 87834.566 | G46: =G12+G23+G37 -> 107825.8 | H46: =H12+H23+H37 -> 125844.67 | I46: =I12+I23+I37 -> 141335.49 | ... L46: =L12+L23+L37 -> 174324.89
A47: Margin | B47: =B46/B44 -> 0.35257577 | C47: =C46/C44 -> 0.52770569 | D47: =D46/D44 -> 0.58263956 | E47: =E46/E44 -> 0.5932133 | F47: =F46/F44 -> 0.59720602 | G47: =G46/G44 -> 0.60306983 | H47: =H46/H44 -> 0.60505917 | I47: =I46/I44 -> 0.60630837 | ... L47: =L46/L44 -> 0.60767795
A48: Capex, gross (including leased GPUs) | B48: =B14+B25+B41 -> 20737 | C48: =C14+C25+C41 -> 71269 | D48: =D14+D25+D41 -> 76207.675 | E48: =E14+E25+E41 -> 78632.507 | F48: =F14+F25+F41 -> 74382.021 | G48: =G14+G25+G41 -> 71722.051 | H48: =H14+H25+H41 -> 71859.543 | I48: =I14+I25+I41 -> 69313.576 | ... L48: =L14+L25+L41 -> 80353.633
A49: Capex paid in cash | B49: =B48 -> 20737 | C49: =C48 -> 71269 | D49: =D48-D40 -> 36207.675 | E49: =E48-E40 -> 78632.507 | F49: =F48-F40 -> 74382.021 | G49: =G48-G40 -> 71722.051 | H49: =H48-H40 -> 71859.543 | I49: =I48-I40 -> 69313.576 | J49: =J48-J40 -> 83800.792 | K49: =K48-K40 -> 81732.091 | L49: =L48-L40 -> 80353.633
A50: Gross capex, % of revenue | B50: =B48/B44 -> 1.1104745 | C50: =C48/C44 -> 1.6114819 | D50: =D48/D44 -> 0.92625912 | E50: =E48/E44 -> 0.68660143 | F50: =F48/F44 -> 0.50573928 | G50: =G48/G44 -> 0.40114152 | H50: =H48/H44 -> 0.34549955 | I50: =I48/I44 -> 0.297345 | ... L50: =L48/L44 -> 0.28010418
A51: SI share of revenue | B51: =B36/B44 -> 0.1714148 | C51: =C36/C44 -> 0.46786095 | D51: =D36/D44 -> 0.5971015 | E51: =E36/E44 -> 0.6268963 | F51: =F36/F44 -> 0.63899935 | G51: =G36/G44 -> 0.64470251 | H51: =H36/H44 -> 0.64759226 | I51: =I36/I44 -> 0.64516247 | ... L51: =L36/L44 -> 0.63390798
A52: Memo: 2027E revenue covered by the backlog due within a year | D52: =Segments_Hist!H145/D44 -> 0.51270365 | N52: US$42.2bn of backlog falls due by 30 Sep 2027 (10-Q); compare with 2027E revenue.
A54: Checks (zero passes)
A55: 2025A revenue equals the statement | B55: =B44-IS_Hist!D6 -> 0
A56: 2026E revenue equals the bridge | C56: =C44-Interim_Bridge!D25 -> 0
A57: Revenue by segment adds up (from the first forecast year) | C57: =C11+C22+C36-Forecast_3Stmt!C10 -> 0 | D57: =D11+D22+D36-Forecast_3Stmt!D10 -> 0 | E57: =E11+E22+E36-Forecast_3Stmt!E10 -> 0 | F57: =F11+F22+F36-Forecast_3Stmt!F10 -> 0 | G57: =G11+G22+G36-Forecast_3Stmt!G10 -> 0 | H57: =H11+H22+H36-Forecast_3Stmt!H10 -> 0 | I57: =I11+I22+I36-Forecast_3Stmt!I10 -> 0 | J57: =J11+J22+J36-Forecast_3Stmt!J10 -> 0 | ... L57: =L11+L22+L36-Forecast_3Stmt!L10 -> 0

Sheet Schedules
A1: Space Exploration Technologies Corp. (SpaceX) | Schedules: depreciation by vintage, Apollo lease, EchoStar, debt and interest, taxes, working capital, unlevered free cash flow
A2: 2026E is the full year (nine months filed plus the Q4 estimate). USD millions.
B3: Actual | C3: Forecast
A4: Fiscal year ends 31 December | B4: 2025A | C4: 2026E | D4: 2027E | E4: 2028E | F4: 2029E | G4: 2030E | H4: 2031E | I4: 2032E | J4: 2033E | K4: 2034E | L4: 2035E | M4: Comentarios FG | N4: Source / derivation
A5: Year | B5: 2025 | C5: 2026 | D5: 2027 | E5: 2028 | F5: 2029 | G5: 2030 | H5: 2031 | I5: 2032 | J5: 2033 | K5: 2034 | L5: 2035
A7: A. Depreciation and amortization
A8: Existing PP&E (30 Sep 2026 pool), beginning | D8: =C10 -> 86211 | E8: =D10 -> 73123 | F8: =E10 -> 60035 | G8: =F10 -> 46947 | H8: =G10 -> 33859 | I8: =H10 -> 20771 | J8: =I10 -> 7683 | K8: =J10 -> 0 | L8: =K10 -> 0
A9: Depreciation of the existing pool | C9: =Interim_Bridge!C50 -> 3272 | D9: =MIN(D8,BS_Hist!D14/Interim_Bridge!B48) -> 13088 | E9: =MIN(E8,BS_Hist!D14/Interim_Bridge!B48) -> 13088 | F9: =MIN(F8,BS_Hist!D14/Interim_Bridge!B48) -> 13088 | G9: =MIN(G8,BS_Hist!D14/Interim_Bridge!B48) -> 13088 | H9: =MIN(H8,BS_Hist!D14/Interim_Bridge!B48) -> 13088 | I9: =MIN(I8,BS_Hist!D14/Interim_Bridge!B48) -> 13088 | J9: =MIN(J8,BS_Hist!D14/Interim_Bridge!B48) -> 7683 | K9: =MIN(K8,BS_Hist!D14/Interim_Bridge!B48) -> 0 | L9: =MIN(L8,BS_Hist!D14/Interim_Bridge!B48) -> 0 | N9: 2026E: Q4 only. Straight line over the derived remaining life (Interim_Bridge).
A10: Existing PP&E pool, ending | C10: =BS_Hist!D14-C9 -> 86211 | D10: =D8-D9 -> 73123 | E10: =E8-E9 -> 60035 | F10: =F8-F9 -> 46947 | G10: =G8-G9 -> 33859 | H10: =H8-H9 -> 20771 | I10: =I8-I9 -> 7683 | J10: =J8-J9 -> 0 | K10: =K8-K9 -> 0 | L10: =L8-L9 -> 0
A11: New capex vintages: Space | C11: =Interim_Bridge!C56 -> 1600 | D11: =Segments_Fcst!D14 -> 5500 | E11: =Segments_Fcst!E14 -> 5500 | F11: =Segments_Fcst!F14 -> 5000 | G11: =Segments_Fcst!G14 -> 4500 | H11: =Segments_Fcst!H14 -> 4000 | I11: =Segments_Fcst!I14 -> 4000 | J11: =Segments_Fcst!J14 -> 4000 | K11: =Segments_Fcst!K14 -> 4000 | L11: =Segments_Fcst!L14 -> 4000 | N11: 2026E vintage = Q4 2026E capex only (the nine months are in the 30 Sep 2026 pool).
A12: New capex vintages: Connectivity | C12: =Interim_Bridge!C57 -> 1600 | D12: =Segments_Fcst!D25 -> 7707.6747 | E12: =Segments_Fcst!E25 -> 9132.5072 | F12: =Segments_Fcst!F25 -> 10182.021 | G12: =Segments_Fcst!G25 -> 11222.051 | H12: =Segments_Fcst!H25 -> 11759.543 | I12: =Segments_Fcst!I25 -> 12613.576 | J12: =Segments_Fcst!J25 -> 13100.792 | K12: =Segments_Fcst!K25 -> 13332.091 | L12: =Segments_Fcst!L25 -> 14253.633 | N12: 2026E vintage = Q4 2026E capex only (the nine months are in the 30 Sep 2026 pool).
A13: New capex vintages: SI (incl. leased GPUs) | C13: =Interim_Bridge!C58 -> 20000 | D13: =Segments_Fcst!D41 -> 63000 | E13: =Segments_Fcst!E41 -> 64000 | F13: =Segments_Fcst!F41 -> 59200 | G13: =Segments_Fcst!G41 -> 56000 | H13: =Segments_Fcst!H41 -> 56100 | I13: =Segments_Fcst!I41 -> 52700 | J13: =Segments_Fcst!J41 -> 66700 | K13: =Segments_Fcst!K41 -> 64400 | L13: =Segments_Fcst!L41 -> 62100 | N13: 2026E vintage = Q4 2026E capex only (the nine months are in the 30 Sep 2026 pool).
A14: Depreciation of new capex: Space | D14: =SUMPRODUCT($C$11:$L$11,((D5-$C$5:$L$5)=0)*0.5+((D5-$C$5:$L$5)>=1)*((D5-$C$5:$L$5)<=Assumptions!$C$60-1)+((D5-$C$5:$L$5)=Assumptions!$C$60)*0.5)/Assumptions!$C$60 -> 435 | E14: =SUMPRODUCT($C$11:$L$11,((E5-$C$5:$L$5)=0)*0.5+((E5-$C$5:$L$5)>=1)*((E5-$C$5:$L$5)<=Assumptions!$C$60-1)+((E5-$C$5:$L$5)=Assumptions!$C$60)*0.5)/Assumptions!$C$60 -> 985 | F14: =SUMPRODUCT($C$11:$L$11,((F5-$C$5:$L$5)=0)*0.5+((F5-$C$5:$L$5)>=1)*((F5-$C$5:$L$5)<=Assumptions!$C$60-1)+((F5-$C$5:$L$5)=Assumptions!$C$60)*0.5)/Assumptions!$C$60 -> 1510 | G14: =SUMPRODUCT($C$11:$L$11,((G5-$C$5:$L$5)=0)*0.5+((G5-$C$5:$L$5)>=1)*((G5-$C$5:$L$5)<=Assumptions!$C$60-1)+((G5-$C$5:$L$5)=Assumptions!$C$60)*0.5)/Assumptions!$C$60 -> 1985 | H14: =SUMPRODUCT($C$11:$L$11,((H5-$C$5:$L$5)=0)*0.5+((H5-$C$5:$L$5)>=1)*((H5-$C$5:$L$5)<=Assumptions!$C$60-1)+((H5-$C$5:$L$5)=Assumptions!$C$60)*0.5)/Assumptions!$C$60 -> 2410 | I14: =SUMPRODUCT($C$11:$L$11,((I5-$C$5:$L$5)=0)*0.5+((I5-$C$5:$L$5)>=1)*((I5-$C$5:$L$5)<=Assumptions!$C$60-1)+((I5-$C$5:$L$5)=Assumptions!$C$60)*0.5)/Assumptions!$C$60 -> 2810 | J14: =SUMPRODUCT($C$11:$L$11,((J5-$C$5:$L$5)=0)*0.5+((J5-$C$5:$L$5)>=1)*((J5-$C$5:$L$5)<=Assumptions!$C$60-1)+((J5-$C$5:$L$5)=Assumptions!$C$60)*0.5)/Assumptions!$C$60 -> 3210 | K14: =SUMPRODUCT($C$11:$L$11,((K5-$C$5:$L$5)=0)*0.5+((K5-$C$5:$L$5)>=1)*((K5-$C$5:$L$5)<=Assumptions!$C$60-1)+((K5-$C$5:$L$5)=Assumptions!$C$60)*0.5)/Assumptions!$C$60 -> 3610 | L14: =SUMPRODUCT($C$11:$L$11,((L5-$C$5:$L$5)=0)*0.5+((L5-$C$5:$L$5)>=1)*((L5-$C$5:$L$5)<=Assumptions!$C$60-1)+((L5-$C$5:$L$5)=Assumptions!$C$60)*0.5)/Assumptions!$C$60 -> 4010 | N14: Each vintage: half a year in its first year, full years after, half a year at the end of its life (straight line).
A15: Depreciation of new capex: Connectivity | D15: =SUMPRODUCT($C$12:$L$12,((D5-$C$5:$L$5)=0)*0.5+((D5-$C$5:$L$5)>=1)*((D5-$C$5:$L$5)<=Assumptions!$C$61-1)+((D5-$C$5:$L$5)=Assumptions!$C$61)*0.5)/Assumptions!$C$61 -> 1090.7675 | E15: =SUMPRODUCT($C$12:$L$12,((E5-$C$5:$L$5)=0)*0.5+((E5-$C$5:$L$5)>=1)*((E5-$C$5:$L$5)<=Assumptions!$C$61-1)+((E5-$C$5:$L$5)=Assumptions!$C$61)*0.5)/Assumptions!$C$61 -> 2774.7857 | F15: =SUMPRODUCT($C$12:$L$12,((F5-$C$5:$L$5)=0)*0.5+((F5-$C$5:$L$5)>=1)*((F5-$C$5:$L$5)<=Assumptions!$C$61-1)+((F5-$C$5:$L$5)=Assumptions!$C$61)*0.5)/Assumptions!$C$61 -> 4706.2384 | G15: =SUMPRODUCT($C$12:$L$12,((G5-$C$5:$L$5)=0)*0.5+((G5-$C$5:$L$5)>=1)*((G5-$C$5:$L$5)<=Assumptions!$C$61-1)+((G5-$C$5:$L$5)=Assumptions!$C$61)*0.5)/Assumptions!$C$61 -> 6846.6456 | H15: =SUMPRODUCT($C$12:$L$12,((H5-$C$5:$L$5)=0)*0.5+((H5-$C$5:$L$5)>=1)*((H5-$C$5:$L$5)<=Assumptions!$C$61-1)+((H5-$C$5:$L$5)=Assumptions!$C$61)*0.5)/Assumptions!$C$61 -> 8984.805 | I15: =SUMPRODUCT($C$12:$L$12,((I5-$C$5:$L$5)=0)*0.5+((I5-$C$5:$L$5)>=1)*((I5-$C$5:$L$5)<=Assumptions!$C$61-1)+((I5-$C$5:$L$5)=Assumptions!$C$61)*0.5)/Assumptions!$C$61 -> 10491.349 | J15: =SUMPRODUCT($C$12:$L$12,((J5-$C$5:$L$5)=0)*0.5+((J5-$C$5:$L$5)>=1)*((J5-$C$5:$L$5)<=Assumptions!$C$61-1)+((J5-$C$5:$L$5)=Assumptions!$C$61)*0.5)/Assumptions!$C$61 -> 11378.768 | K15: =SUMPRODUCT($C$12:$L$12,((K5-$C$5:$L$5)=0)*0.5+((K5-$C$5:$L$5)>=1)*((K5-$C$5:$L$5)<=Assumptions!$C$61-1)+((K5-$C$5:$L$5)=Assumptions!$C$61)*0.5)/Assumptions!$C$61 -> 12090.604 | L15: =SUMPRODUCT($C$12:$L$12,((L5-$C$5:$L$5)=0)*0.5+((L5-$C$5:$L$5)>=1)*((L5-$C$5:$L$5)<=Assumptions!$C$61-1)+((L5-$C$5:$L$5)=Assumptions!$C$61)*0.5)/Assumptions!$C$61 -> 12708.769 | N15: Each vintage: half a year in its first year, full years after, half a year at the end of its life (straight line).
A16: Depreciation of new capex: SI | D16: =SUMPRODUCT($C$13:$L$13,((D5-$C$5:$L$5)=0)*0.5+((D5-$C$5:$L$5)>=1)*((D5-$C$5:$L$5)<=Assumptions!$C$62-1)+((D5-$C$5:$L$5)=Assumptions!$C$62)*0.5)/Assumptions!$C$62 -> 7357.1429 | E16: =SUMPRODUCT($C$13:$L$13,((E5-$C$5:$L$5)=0)*0.5+((E5-$C$5:$L$5)>=1)*((E5-$C$5:$L$5)<=Assumptions!$C$62-1)+((E5-$C$5:$L$5)=Assumptions!$C$62)*0.5)/Assumptions!$C$62 -> 16428.571 | F16: =SUMPRODUCT($C$13:$L$13,((F5-$C$5:$L$5)=0)*0.5+((F5-$C$5:$L$5)>=1)*((F5-$C$5:$L$5)<=Assumptions!$C$62-1)+((F5-$C$5:$L$5)=Assumptions!$C$62)*0.5)/Assumptions!$C$62 -> 25228.571 | G16: =SUMPRODUCT($C$13:$L$13,((G5-$C$5:$L$5)=0)*0.5+((G5-$C$5:$L$5)>=1)*((G5-$C$5:$L$5)<=Assumptions!$C$62-1)+((G5-$C$5:$L$5)=Assumptions!$C$62)*0.5)/Assumptions!$C$62 -> 33457.143 | H16: =SUMPRODUCT($C$13:$L$13,((H5-$C$5:$L$5)=0)*0.5+((H5-$C$5:$L$5)>=1)*((H5-$C$5:$L$5)<=Assumptions!$C$62-1)+((H5-$C$5:$L$5)=Assumptions!$C$62)*0.5)/Assumptions!$C$62 -> 41464.286 | I16: =SUMPRODUCT($C$13:$L$13,((I5-$C$5:$L$5)=0)*0.5+((I5-$C$5:$L$5)>=1)*((I5-$C$5:$L$5)<=Assumptions!$C$62-1)+((I5-$C$5:$L$5)=Assumptions!$C$62)*0.5)/Assumptions!$C$62 -> 49235.714 | J16: =SUMPRODUCT($C$13:$L$13,((J5-$C$5:$L$5)=0)*0.5+((J5-$C$5:$L$5)>=1)*((J5-$C$5:$L$5)<=Assumptions!$C$62-1)+((J5-$C$5:$L$5)=Assumptions!$C$62)*0.5)/Assumptions!$C$62 -> 56335.714 | K16: =SUMPRODUCT($C$13:$L$13,((K5-$C$5:$L$5)=0)*0.5+((K5-$C$5:$L$5)>=1)*((K5-$C$5:$L$5)<=Assumptions!$C$62-1)+((K5-$C$5:$L$5)=Assumptions!$C$62)*0.5)/Assumptions!$C$62 -> 59771.429 | L16: =SUMPRODUCT($C$13:$L$13,((L5-$C$5:$L$5)=0)*0.5+((L5-$C$5:$L$5)>=1)*((L5-$C$5:$L$5)<=Assumptions!$C$62-1)+((L5-$C$5:$L$5)=Assumptions!$C$62)*0.5)/Assumptions!$C$62 -> 59735.714 | N16: Each vintage: half a year in its first year, full years after, half a year at the end of its life (straight line).
A17: Finance-lease assets (existing), beginning | D17: =C19 -> 961 | E17: =D19 -> 645 | F17: =E19 -> 329 | G17: =F19 -> 13 | H17: =G19 -> 0 | I17: =H19 -> 0 | J17: =I19 -> 0 | K17: =J19 -> 0 | L17: =K19 -> 0
A18: Amortization of finance-lease assets | C18: =Interim_Bridge!C51 -> 79 | D18: =MIN(D17,Interim_Bridge!B46*4) -> 316 | E18: =MIN(E17,Interim_Bridge!B46*4) -> 316 | F18: =MIN(F17,Interim_Bridge!B46*4) -> 316 | G18: =MIN(G17,Interim_Bridge!B46*4) -> 13 | H18: =MIN(H17,Interim_Bridge!B46*4) -> 0 | I18: =MIN(I17,Interim_Bridge!B46*4) -> 0 | J18: =MIN(J17,Interim_Bridge!B46*4) -> 0 | K18: =MIN(K17,Interim_Bridge!B46*4) -> 0 | L18: =MIN(L17,Interim_Bridge!B46*4) -> 0
A19: Finance-lease assets (existing), ending | B19: =BS_Hist!C15 -> 1260 | C19: =Interim_Bridge!D86 -> 961 | D19: =D17-D18 -> 645 | E19: =E17-E18 -> 329 | F19: =F17-F18 -> 13 | G19: =G17-G18 -> 0 | H19: =H17-H18 -> 0 | I19: =I17-I18 -> 0 | J19: =J17-J18 -> 0 | K19: =K17-K18 -> 0 | L19: =L17-L18 -> 0
A20: Intangible assets, beginning | D20: =C22 -> 5958.1875 | E20: =D22 -> 4374.9375 | F20: =E22 -> 2791.6875 | G20: =F22 -> 1208.4375 | H20: =G22 -> 21 | I20: =H22 -> 21 | J20: =I22 -> 21 | K20: =J22 -> 21 | L20: =K22 -> 21
A21: Amortization of intangibles | C21: =Interim_Bridge!C52 -> 395.8125 | D21: =MAX(0,MIN(D20-(BS_Hist!D16-Interim_Bridge!B49),Interim_Bridge!B49/Assumptions!$C$63)) -> 1583.25 | E21: =MAX(0,MIN(E20-(BS_Hist!D16-Interim_Bridge!B49),Interim_Bridge!B49/Assumptions!$C$63)) -> 1583.25 | F21: =MAX(0,MIN(F20-(BS_Hist!D16-Interim_Bridge!B49),Interim_Bridge!B49/Assumptions!$C$63)) -> 1583.25 | G21: =MAX(0,MIN(G20-(BS_Hist!D16-Interim_Bridge!B49),Interim_Bridge!B49/Assumptions!$C$63)) -> 1187.4375 | H21: =MAX(0,MIN(H20-(BS_Hist!D16-Interim_Bridge!B49),Interim_Bridge!B49/Assumptions!$C$63)) -> 0 | I21: =MAX(0,MIN(I20-(BS_Hist!D16-Interim_Bridge!B49),Interim_Bridge!B49/Assumptions!$C$63)) -> 0 | J21: =MAX(0,MIN(J20-(BS_Hist!D16-Interim_Bridge!B49),Interim_Bridge!B49/Assumptions!$C$63)) -> 0 | K21: =MAX(0,MIN(K20-(BS_Hist!D16-Interim_Bridge!B49),Interim_Bridge!B49/Assumptions!$C$63)) -> 0 | L21: =MAX(0,MIN(L20-(BS_Hist!D16-Interim_Bridge!B49),Interim_Bridge!B49/Assumptions!$C$63)) -> 0 | N21: Finite-lived only; the US$21m indefinite-lived stays.
A22: Intangible assets, ending | B22: =BS_Hist!C16 -> 1548 | C22: =Interim_Bridge!D87 -> 5958.1875 | D22: =D20-D21 -> 4374.9375 | E22: =E20-E21 -> 2791.6875 | F22: =F20-F21 -> 1208.4375 | G22: =G20-G21 -> 21 | H22: =H20-H21 -> 21 | I22: =I20-I21 -> 21 | J22: =J20-J21 -> 21 | K22: =K20-K21 -> 21 | L22: =L20-L21 -> 21
A23: Depreciation and amortization, total | B23: =CF_Hist!D8 -> 6701 | C23: =Interim_Bridge!D32 -> 12680.812 | D23: =D9+D14+D15+D16+D18+D21 -> 23870.16 | E23: =E9+E14+E15+E16+E18+E21 -> 35175.607 | F23: =F9+F14+F15+F16+F18+F21 -> 46432.06 | G23: =G9+G14+G15+G16+G18+G21 -> 56577.226 | H23: =H9+H14+H15+H16+H18+H21 -> 65947.091 | I23: =I9+I14+I15+I16+I18+I21 -> 75625.064 | J23: =J9+J14+J15+J16+J18+J21 -> 78607.482 | K23: =K9+K14+K15+K16+K18+K21 -> 75472.032 | L23: =L9+L14+L15+L16+L18+L21 -> 76454.483
A24: PP&E, net, ending (including leased GPUs) | B24: =BS_Hist!C14 -> 42602 | C24: =Interim_Bridge!D85 -> 109411 | D24: =C24+Segments_Fcst!D48-D9-D14-D15-D16 -> 163647.76 | E24: =D24+Segments_Fcst!E48-E9-E14-E15-E16 -> 209003.91 | F24: =E24+Segments_Fcst!F48-F9-F14-F15-F16 -> 238853.13 | G24: =F24+Segments_Fcst!G48-G9-G14-G15-G16 -> 255198.39 | H24: =G24+Segments_Fcst!H48-H9-H14-H15-H16 -> 261110.84 | I24: =H24+Segments_Fcst!I48-I9-I14-I15-I16 -> 254799.35 | J24: =I24+Segments_Fcst!J48-J9-J14-J15-J16 -> 259992.66 | K24: =J24+Segments_Fcst!K48-K9-K14-K15-K16 -> 266252.72 | L24: =K24+Segments_Fcst!L48-L9-L14-L15-L16 -> 270151.87
A26: B. Apollo GPU finance lease (8-K of 26 Oct 2026) | N26: Rent quarterly in advance = 1/20 of the financed cost + fixed-rate interest; terms 5 to 5.25 years; one tranche assumed.
A27: Leased GPUs delivered (PP&E and lease liability added) | D27: =IF(D5=2027,Assumptions!$C$32*Assumptions!$C$29,0) -> 40000 | E27: =IF(E5=2027,Assumptions!$C$32*Assumptions!$C$29,0) -> 0 | F27: =IF(F5=2027,Assumptions!$C$32*Assumptions!$C$29,0) -> 0 | G27: =IF(G5=2027,Assumptions!$C$32*Assumptions!$C$29,0) -> 0 | H27: =IF(H5=2027,Assumptions!$C$32*Assumptions!$C$29,0) -> 0 | I27: =IF(I5=2027,Assumptions!$C$32*Assumptions!$C$29,0) -> 0 | J27: =IF(J5=2027,Assumptions!$C$32*Assumptions!$C$29,0) -> 0 | K27: =IF(K5=2027,Assumptions!$C$32*Assumptions!$C$29,0) -> 0 | L27: =IF(L5=2027,Assumptions!$C$32*Assumptions!$C$29,0) -> 0
A28: Share of principal repaid by year end | D28: =IF(Assumptions!$C$29=1,MIN(1,MAX(0,(5-Assumptions!$C$33)+4*(D5-2027))/20),0) -> 0.15 | E28: =IF(Assumptions!$C$29=1,MIN(1,MAX(0,(5-Assumptions!$C$33)+4*(E5-2027))/20),0) -> 0.35 | F28: =IF(Assumptions!$C$29=1,MIN(1,MAX(0,(5-Assumptions!$C$33)+4*(F5-2027))/20),0) -> 0.55 | G28: =IF(Assumptions!$C$29=1,MIN(1,MAX(0,(5-Assumptions!$C$33)+4*(G5-2027))/20),0) -> 0.75 | H28: =IF(Assumptions!$C$29=1,MIN(1,MAX(0,(5-Assumptions!$C$33)+4*(H5-2027))/20),0) -> 0.95 | I28: =IF(Assumptions!$C$29=1,MIN(1,MAX(0,(5-Assumptions!$C$33)+4*(I5-2027))/20),0) -> 1 | J28: =IF(Assumptions!$C$29=1,MIN(1,MAX(0,(5-Assumptions!$C$33)+4*(J5-2027))/20),0) -> 1 | K28: =IF(Assumptions!$C$29=1,MIN(1,MAX(0,(5-Assumptions!$C$33)+4*(K5-2027))/20),0) -> 1 | L28: =IF(Assumptions!$C$29=1,MIN(1,MAX(0,(5-Assumptions!$C$33)+4*(L5-2027))/20),0) -> 1 | N28: First rent at commencement (in advance): a Q2 start pays 3 quarters in 2027, then 4 a year.
A29: Principal repaid | D29: =Assumptions!$C$32*(D28-0) -> 6000 | E29: =Assumptions!$C$32*(E28-D28) -> 8000 | F29: =Assumptions!$C$32*(F28-E28) -> 8000 | G29: =Assumptions!$C$32*(G28-F28) -> 8000 | H29: =Assumptions!$C$32*(H28-G28) -> 8000 | I29: =Assumptions!$C$32*(I28-H28) -> 2000 | J29: =Assumptions!$C$32*(J28-I28) -> 0 | K29: =Assumptions!$C$32*(K28-J28) -> 0 | L29: =Assumptions!$C$32*(L28-K28) -> 0
A30: Lease liability, ending | C30: 0 | D30: =C30+D27-D29 -> 34000 | E30: =D30+E27-E29 -> 26000 | F30: =E30+F27-F29 -> 18000 | G30: =F30+G27-G29 -> 10000 | H30: =G30+H27-H29 -> 2000 | I30: =H30+I27-I29 -> 0 | J30: =I30+J27-J29 -> 0 | K30: =J30+K27-K29 -> 0 | L30: =K30+L27-L29 -> 0
A31: Lease interest | D31: =Assumptions!$C$34*(C30+D27+D30)/2*IF(D5=2027,(5-Assumptions!$C$33)/4,1) -> 1803.75 | E31: =Assumptions!$C$34*(D30+E27+E30)/2*IF(E5=2027,(5-Assumptions!$C$33)/4,1) -> 1950 | F31: =Assumptions!$C$34*(E30+F27+F30)/2*IF(F5=2027,(5-Assumptions!$C$33)/4,1) -> 1430 | G31: =Assumptions!$C$34*(F30+G27+G30)/2*IF(G5=2027,(5-Assumptions!$C$33)/4,1) -> 910 | H31: =Assumptions!$C$34*(G30+H27+H30)/2*IF(H5=2027,(5-Assumptions!$C$33)/4,1) -> 390 | I31: =Assumptions!$C$34*(H30+I27+I30)/2*IF(I5=2027,(5-Assumptions!$C$33)/4,1) -> 65 | J31: =Assumptions!$C$34*(I30+J27+J30)/2*IF(J5=2027,(5-Assumptions!$C$33)/4,1) -> 0 | K31: =Assumptions!$C$34*(J30+K27+K30)/2*IF(K5=2027,(5-Assumptions!$C$33)/4,1) -> 0 | L31: =Assumptions!$C$34*(K30+L27+L30)/2*IF(L5=2027,(5-Assumptions!$C$33)/4,1) -> 0 | N31: Average balance x rate; in 2027 only for the quarters after commencement.
A33: C. Spectrum: EchoStar and 800 MHz | N33: EchoStar (424B4 pp. 123-124): about US$19.6bn = 261.8m Class A shares at US$42.40 + up to US$8.5bn cash; interest-only payments until closing.
A34: EchoStar: cash paid (credit-agreement payments and the closing payment) | C34: =Interim_Bridge!C60 -> 385 | D34: =IF(D5=2027,Assumptions!$C$41,0)+IF(AND(D5=2028,Assumptions!$C$35=2028),Assumptions!$C$42,0)+IF(D5=Assumptions!$C$35,Assumptions!$C$36,0) -> 9328 | E34: =IF(E5=2027,Assumptions!$C$41,0)+IF(AND(E5=2028,Assumptions!$C$35=2028),Assumptions!$C$42,0)+IF(E5=Assumptions!$C$35,Assumptions!$C$36,0) -> 0 | F34: =IF(F5=2027,Assumptions!$C$41,0)+IF(AND(F5=2028,Assumptions!$C$35=2028),Assumptions!$C$42,0)+IF(F5=Assumptions!$C$35,Assumptions!$C$36,0) -> 0 | G34: =IF(G5=2027,Assumptions!$C$41,0)+IF(AND(G5=2028,Assumptions!$C$35=2028),Assumptions!$C$42,0)+IF(G5=Assumptions!$C$35,Assumptions!$C$36,0) -> 0 | H34: =IF(H5=2027,Assumptions!$C$41,0)+IF(AND(H5=2028,Assumptions!$C$35=2028),Assumptions!$C$42,0)+IF(H5=Assumptions!$C$35,Assumptions!$C$36,0) -> 0 | I34: =IF(I5=2027,Assumptions!$C$41,0)+IF(AND(I5=2028,Assumptions!$C$35=2028),Assumptions!$C$42,0)+IF(I5=Assumptions!$C$35,Assumptions!$C$36,0) -> 0 | J34: =IF(J5=2027,Assumptions!$C$41,0)+IF(AND(J5=2028,Assumptions!$C$35=2028),Assumptions!$C$42,0)+IF(J5=Assumptions!$C$35,Assumptions!$C$36,0) -> 0 | K34: =IF(K5=2027,Assumptions!$C$41,0)+IF(AND(K5=2028,Assumptions!$C$35=2028),Assumptions!$C$42,0)+IF(K5=Assumptions!$C$35,Assumptions!$C$36,0) -> 0 | L34: =IF(L5=2027,Assumptions!$C$41,0)+IF(AND(L5=2028,Assumptions!$C$35=2028),Assumptions!$C$42,0)+IF(L5=Assumptions!$C$35,Assumptions!$C$36,0) -> 0
A35: 800 MHz spectrum from Grain Management: cash at closing (30 Jun 2027) | C35: 0 | D35: =IF(D5=Assumptions!$C$48,Assumptions!$C$47,0) -> 8000 | E35: =IF(E5=Assumptions!$C$48,Assumptions!$C$47,0) -> 0 | F35: =IF(F5=Assumptions!$C$48,Assumptions!$C$47,0) -> 0 | G35: =IF(G5=Assumptions!$C$48,Assumptions!$C$47,0) -> 0 | H35: =IF(H5=Assumptions!$C$48,Assumptions!$C$47,0) -> 0 | I35: =IF(I5=Assumptions!$C$48,Assumptions!$C$47,0) -> 0 | J35: =IF(J5=Assumptions!$C$48,Assumptions!$C$47,0) -> 0 | K35: =IF(K5=Assumptions!$C$48,Assumptions!$C$47,0) -> 0 | L35: =IF(L5=Assumptions!$C$48,Assumptions!$C$47,0) -> 0 | N35: Signed 8 Oct 2026 (8-K 20 Oct 2026); price from press reports (Assumptions). FCC approval pending. No separate revenue line: Starlink Mobile revenue sits inside the Connectivity drivers (subscribers, ARPU, Enterprise & Government).
A36: Spectrum cash paid, total | C36: =C34+C35 -> 385 | D36: =D34+D35 -> 17328 | E36: =E34+E35 -> 0 | F36: =F34+F35 -> 0 | G36: =G34+G35 -> 0 | H36: =H34+H35 -> 0 | I36: =I34+I35 -> 0 | J36: =J34+J35 -> 0 | ... L36: =L34+L35 -> 0
A37: Class A shares issued at closing (value at the fixed US$42.40) | D37: =IF(D5=Assumptions!$C$35,Assumptions!$C$37*Assumptions!$C$38,0) -> 11100.32 | E37: =IF(E5=Assumptions!$C$35,Assumptions!$C$37*Assumptions!$C$38,0) -> 0 | F37: =IF(F5=Assumptions!$C$35,Assumptions!$C$37*Assumptions!$C$38,0) -> 0 | G37: =IF(G5=Assumptions!$C$35,Assumptions!$C$37*Assumptions!$C$38,0) -> 0 | H37: =IF(H5=Assumptions!$C$35,Assumptions!$C$37*Assumptions!$C$38,0) -> 0 | I37: =IF(I5=Assumptions!$C$35,Assumptions!$C$37*Assumptions!$C$38,0) -> 0 | J37: =IF(J5=Assumptions!$C$35,Assumptions!$C$37*Assumptions!$C$38,0) -> 0 | K37: =IF(K5=Assumptions!$C$35,Assumptions!$C$37*Assumptions!$C$38,0) -> 0 | L37: =IF(L5=Assumptions!$C$35,Assumptions!$C$37*Assumptions!$C$38,0) -> 0 | N37: Non-cash; the shares are already in the diluted count (Cap_Table).
A38: Spectrum licences, ending (EchoStar and 800 MHz) | C38: =Interim_Bridge!D88 -> 385 | D38: =C38+D36+D37 -> 28813.32 | E38: =D38+E36+E37 -> 28813.32 | F38: =E38+F36+F37 -> 28813.32 | G38: =F38+G36+G37 -> 28813.32 | H38: =G38+H36+H37 -> 28813.32 | I38: =H38+I36+I37 -> 28813.32 | J38: =I38+J36+J37 -> 28813.32 | K38: =J38+K36+K37 -> 28813.32 | L38: =K38+L36+L37 -> 28813.32 | N38: Indefinite-lived licences: not amortised. The US$856m paid to the EchoStar Trust by 30 Sep 2026 stays in other assets.
A40: D. Existing debt and finance leases (10-Q Q3 Note 9 maturities)
A41: Debt and finance leases, beginning (carrying) | D41: =C43 -> 38270 | E41: =D43 -> 35529 | F41: =E43 -> 32346 | G41: =F43 -> 28608 | H41: =G43 -> 24998 | I41: =H43 -> 24998 | J41: =I43 -> 24998 | K41: =J43 -> 24998 | L41: =K43 -> 24998
A42: Scheduled repayments and finance-lease principal | C42: =-Interim_Bridge!C73 -> 574 | D42: =MIN(D41,Debt_Credit!B31+D18) -> 2741 | E42: =MIN(E41,Debt_Credit!B32+E18) -> 3183 | F42: =MIN(F41,Debt_Credit!B33+F18) -> 3738 | G42: =MIN(G41,Debt_Credit!B34+G18) -> 3610 | H42: =MIN(H41,H18) -> 0 | I42: =MIN(I41,I18) -> 0 | J42: =MIN(J41,J18) -> 0 | K42: =MIN(K41,K18) -> 0 | L42: =MIN(L41,L18) -> 0 | N42: Maturities after 2030 (US$25.2bn, SpaceX Notes 2031-2056) are assumed refinanced. Finance-lease principal taken equal to the asset amortization.
A43: Debt and finance leases, ending (carrying) | B43: =BS_Hist!C48 -> 22896 | C43: =Interim_Bridge!D94 -> 38270 | D43: =D41-D42 -> 35529 | E43: =E41-E42 -> 32346 | F43: =F41-F42 -> 28608 | G43: =G41-G42 -> 24998 | H43: =H41-H42 -> 24998 | I43: =I41-I42 -> 24998 | J43: =J41-J42 -> 24998 | K43: =K41-K42 -> 24998 | L43: =L41-L42 -> 24998
A45: E. Interest
A46: Interest on existing debt (blended rate x beginning balance) | D46: =Interim_Bridge!B53*D41 -> 2660.1019 | E46: =Interim_Bridge!B53*E41 -> 2469.5783 | F46: =Interim_Bridge!B53*F41 -> 2248.3318 | G46: =Interim_Bridge!B53*G41 -> 1988.5079 | H46: =Interim_Bridge!B53*H41 -> 1737.5811 | I46: =Interim_Bridge!B53*I41 -> 1737.5811 | J46: =Interim_Bridge!B53*J41 -> 1737.5811 | K46: =Interim_Bridge!B53*K41 -> 1737.5811 | L46: =Interim_Bridge!B53*L41 -> 1737.5811
A47: Interest on the Apollo lease | D47: =D31 -> 1803.75 | E47: =E31 -> 1950 | F47: =F31 -> 1430 | G47: =G31 -> 910 | H47: =H31 -> 390 | I47: =I31 -> 65 | J47: =J31 -> 0 | K47: =K31 -> 0 | L47: =L31 -> 0
A48: Interest on new borrowing (blended rate x beginning balance) | D48: =Interim_Bridge!B53*Forecast_3Stmt!C43 -> 0 | E48: =Interim_Bridge!B53*Forecast_3Stmt!D43 -> 0 | F48: =Interim_Bridge!B53*Forecast_3Stmt!E43 -> 0 | G48: =Interim_Bridge!B53*Forecast_3Stmt!F43 -> 0 | H48: =Interim_Bridge!B53*Forecast_3Stmt!G43 -> 0 | I48: =Interim_Bridge!B53*Forecast_3Stmt!H43 -> 0 | J48: =Interim_Bridge!B53*Forecast_3Stmt!I43 -> 0 | K48: =Interim_Bridge!B53*Forecast_3Stmt!J43 -> 0 | L48: =Interim_Bridge!B53*Forecast_3Stmt!K43 -> 0
A49: Interest expense | D49: =-(D46+D47+D48) -> -4463.8519 | E49: =-(E46+E47+E48) -> -4419.5783 | F49: =-(F46+F47+F48) -> -3678.3318 | G49: =-(G46+G47+G48) -> -2898.5079 | H49: =-(H46+H47+H48) -> -2127.5811 | I49: =-(I46+I47+I48) -> -1802.5811 | J49: =-(J46+J47+J48) -> -1737.5811 | K49: =-(K46+K47+K48) -> -1737.5811 | L49: =-(L46+L47+L48) -> -1737.5811
A50: Interest income (yield x beginning cash and securities) | D50: =Assumptions!$C$53*Forecast_3Stmt!C28 -> 3398.0408 | E50: =Assumptions!$C$53*Forecast_3Stmt!D28 -> 2438.4035 | F50: =Assumptions!$C$53*Forecast_3Stmt!E28 -> 1731.9699 | G50: =Assumptions!$C$53*Forecast_3Stmt!F28 -> 1506.7502 | H50: =Assumptions!$C$53*Forecast_3Stmt!G28 -> 2121.8982 | I50: =Assumptions!$C$53*Forecast_3Stmt!H28 -> 3565.9023 | J50: =Assumptions!$C$53*Forecast_3Stmt!I28 -> 6124.4656 | K50: =Assumptions!$C$53*Forecast_3Stmt!J28 -> 8784.884 | L50: =Assumptions!$C$53*Forecast_3Stmt!K28 -> 11838.855
A52: F. Loss carryforwards, credits and taxes (federal and state)
A53: Taxable income before loss carryforwards (income before taxes) | C53: =Forecast_3Stmt!C21 -> 2659.5799 | D53: =Forecast_3Stmt!D21 -> 10693.845 | E53: =Forecast_3Stmt!E21 -> 17345.119 | F53: =Forecast_3Stmt!F21 -> 29653.205 | G53: =Forecast_3Stmt!G21 -> 43598.996 | H53: =Forecast_3Stmt!H21 -> 52612.337 | I53: =Forecast_3Stmt!I21 -> 59314.958 | J53: =Forecast_3Stmt!J21 -> 71428.578 | ... L53: =Forecast_3Stmt!L21 -> 97931.215 | N53: Book income taken as taxable income; timing differences are not modelled. Stock compensation taken as deductible.
A54: Federal loss carryforwards, beginning | C54: =Assumptions!$C$49 -> 9728 | D54: =C57 -> 7600.3361 | E54: =D57 -> 0 | F54: =E57 -> 0 | G54: =F57 -> 0 | H54: =G57 -> 0 | I54: =H57 -> 0 | J54: =I57 -> 0 | K54: =J57 -> 0 | L54: =K57 -> 0
A55: Used | C55: =MIN(C54,MAX(0,C53)*Assumptions!$C$50) -> 2127.6639 | D55: =MIN(D54,MAX(0,D53)*Assumptions!$C$50) -> 7600.3361 | E55: =MIN(E54,MAX(0,E53)*Assumptions!$C$50) -> 0 | F55: =MIN(F54,MAX(0,F53)*Assumptions!$C$50) -> 0 | G55: =MIN(G54,MAX(0,G53)*Assumptions!$C$50) -> 0 | H55: =MIN(H54,MAX(0,H53)*Assumptions!$C$50) -> 0 | I55: =MIN(I54,MAX(0,I53)*Assumptions!$C$50) -> 0 | J55: =MIN(J54,MAX(0,J53)*Assumptions!$C$50) -> 0 | ... L55: =MIN(L54,MAX(0,L53)*Assumptions!$C$50) -> 0
A56: Added | C56: =MAX(0,-C53) -> 0 | D56: =MAX(0,-D53) -> 0 | E56: =MAX(0,-E53) -> 0 | F56: =MAX(0,-F53) -> 0 | G56: =MAX(0,-G53) -> 0 | H56: =MAX(0,-H53) -> 0 | I56: =MAX(0,-I53) -> 0 | J56: =MAX(0,-J53) -> 0 | ... L56: =MAX(0,-L53) -> 0
A57: Federal loss carryforwards, ending | C57: =C54-C55+C56 -> 7600.3361 | D57: =D54-D55+D56 -> 0 | E57: =E54-E55+E56 -> 0 | F57: =F54-F55+F56 -> 0 | G57: =G54-G55+G56 -> 0 | H57: =H54-H55+H56 -> 0 | I57: =I54-I55+I56 -> 0 | J57: =J54-J55+J56 -> 0 | ... L57: =L54-L55+L56 -> 0
A58: Federal tax before credits | C58: =MAX(0,C53-C55)*Assumptions!$C$43 -> 111.70235 | D58: =MAX(0,D53-D55)*Assumptions!$C$43 -> 649.63694 | E58: =MAX(0,E53-E55)*Assumptions!$C$43 -> 3642.4749 | F58: =MAX(0,F53-F55)*Assumptions!$C$43 -> 6227.1731 | G58: =MAX(0,G53-G55)*Assumptions!$C$43 -> 9155.7892 | H58: =MAX(0,H53-H55)*Assumptions!$C$43 -> 11048.591 | I58: =MAX(0,I53-I55)*Assumptions!$C$43 -> 12456.141 | J58: =MAX(0,J53-J55)*Assumptions!$C$43 -> 15000.001 | ... L58: =MAX(0,L53-L55)*Assumptions!$C$43 -> 20565.555
A59: Federal tax credits, beginning | C59: =Assumptions!$C$51 -> 3586 | D59: =C61 -> 3502.2232 | E59: =D61 -> 3014.9955 | F59: =E61 -> 283.13934 | G59: =F61 -> 0 | H59: =G61 -> 0 | I59: =H61 -> 0 | J59: =I61 -> 0 | K59: =J61 -> 0 | L59: =K61 -> 0
A60: Credits used | C60: =MIN(C59,C58*Assumptions!$C$52) -> 83.776766 | D60: =MIN(D59,D58*Assumptions!$C$52) -> 487.2277 | E60: =MIN(E59,E58*Assumptions!$C$52) -> 2731.8562 | F60: =MIN(F59,F58*Assumptions!$C$52) -> 283.13934 | G60: =MIN(G59,G58*Assumptions!$C$52) -> 0 | H60: =MIN(H59,H58*Assumptions!$C$52) -> 0 | I60: =MIN(I59,I58*Assumptions!$C$52) -> 0 | J60: =MIN(J59,J58*Assumptions!$C$52) -> 0 | ... L60: =MIN(L59,L58*Assumptions!$C$52) -> 0
A61: Federal tax credits, ending | C61: =C59-C60 -> 3502.2232 | D61: =D59-D60 -> 3014.9955 | E61: =E59-E60 -> 283.13934 | F61: =F59-F60 -> 0 | G61: =G59-G60 -> 0 | H61: =H59-H60 -> 0 | I61: =I59-I60 -> 0 | J61: =J59-J60 -> 0 | ... L61: =L59-L60 -> 0
A62: State loss carryforwards, beginning | C62: =Assumptions!$C$45 -> 5234 | D62: =C65 -> 3106.3361 | E62: =D65 -> 0 | F62: =E65 -> 0 | G62: =F65 -> 0 | H62: =G65 -> 0 | I62: =H65 -> 0 | J62: =I65 -> 0 | K62: =J65 -> 0 | L62: =K65 -> 0
A63: Used | C63: =MIN(C62,MAX(0,C53)*Assumptions!$C$50) -> 2127.6639 | D63: =MIN(D62,MAX(0,D53)*Assumptions!$C$50) -> 3106.3361 | E63: =MIN(E62,MAX(0,E53)*Assumptions!$C$50) -> 0 | F63: =MIN(F62,MAX(0,F53)*Assumptions!$C$50) -> 0 | G63: =MIN(G62,MAX(0,G53)*Assumptions!$C$50) -> 0 | H63: =MIN(H62,MAX(0,H53)*Assumptions!$C$50) -> 0 | I63: =MIN(I62,MAX(0,I53)*Assumptions!$C$50) -> 0 | J63: =MIN(J62,MAX(0,J53)*Assumptions!$C$50) -> 0 | ... L63: =MIN(L62,MAX(0,L53)*Assumptions!$C$50) -> 0
A64: Added | C64: =MAX(0,-C53) -> 0 | D64: =MAX(0,-D53) -> 0 | E64: =MAX(0,-E53) -> 0 | F64: =MAX(0,-F53) -> 0 | G64: =MAX(0,-G53) -> 0 | H64: =MAX(0,-H53) -> 0 | I64: =MAX(0,-I53) -> 0 | J64: =MAX(0,-J53) -> 0 | ... L64: =MAX(0,-L53) -> 0
A65: State loss carryforwards, ending | C65: =C62-C63+C64 -> 3106.3361 | D65: =D62-D63+D64 -> 0 | E65: =E62-E63+E64 -> 0 | F65: =F62-F63+F64 -> 0 | G65: =G62-G63+G64 -> 0 | H65: =H62-H63+H64 -> 0 | I65: =I62-I63+I64 -> 0 | J65: =J62-J63+J64 -> 0 | ... L65: =L62-L63+L64 -> 0
A66: State tax before credits | C66: =MAX(0,C53-C63)*Assumptions!$C$44 -> 10.638319 | D66: =MAX(0,D53-D63)*Assumptions!$C$44 -> 151.75018 | E66: =MAX(0,E53-E63)*Assumptions!$C$44 -> 346.90237 | F66: =MAX(0,F53-F63)*Assumptions!$C$44 -> 593.0641 | G66: =MAX(0,G53-G63)*Assumptions!$C$44 -> 871.97993 | H66: =MAX(0,H53-H63)*Assumptions!$C$44 -> 1052.2467 | I66: =MAX(0,I53-I63)*Assumptions!$C$44 -> 1186.2992 | J66: =MAX(0,J53-J63)*Assumptions!$C$44 -> 1428.5716 | ... L66: =MAX(0,L53-L63)*Assumptions!$C$44 -> 1958.6243
A67: State tax credits, beginning | C67: =Assumptions!$C$46 -> 2104 | D67: =C69 -> 2096.0213 | E67: =D69 -> 1982.2086 | F67: =E69 -> 1722.0318 | G67: =F69 -> 1277.2338 | H67: =G69 -> 623.24882 | I67: =H69 -> 0 | J67: =I69 -> 0 | K67: =J69 -> 0 | L67: =K69 -> 0
A68: Credits used | C68: =MIN(C67,C66*Assumptions!$C$52) -> 7.9787396 | D68: =MIN(D67,D66*Assumptions!$C$52) -> 113.81264 | E68: =MIN(E67,E66*Assumptions!$C$52) -> 260.17678 | F68: =MIN(F67,F66*Assumptions!$C$52) -> 444.79808 | G68: =MIN(G67,G66*Assumptions!$C$52) -> 653.98494 | H68: =MIN(H67,H66*Assumptions!$C$52) -> 623.24882 | I68: =MIN(I67,I66*Assumptions!$C$52) -> 0 | J68: =MIN(J67,J66*Assumptions!$C$52) -> 0 | ... L68: =MIN(L67,L66*Assumptions!$C$52) -> 0
A69: State tax credits, ending | C69: =C67-C68 -> 2096.0213 | D69: =D67-D68 -> 1982.2086 | E69: =E67-E68 -> 1722.0318 | F69: =F67-F68 -> 1277.2338 | G69: =G67-G68 -> 623.24882 | H69: =H67-H68 -> 0 | I69: =I67-I68 -> 0 | J69: =J67-J68 -> 0 | ... L69: =L67-L68 -> 0
A70: Income tax (2027E onward; 2026E from the bridge) | C70: =Interim_Bridge!D40 -> -189.32101 | D70: =D58-D60+D66-D68 -> 200.34678 | E70: =E58-E60+E66-E68 -> 997.34432 | F70: =F58-F60+F66-F68 -> 6092.2998 | G70: =G58-G60+G66-G68 -> 9373.7842 | H70: =H58-H60+H66-H68 -> 11477.589 | I70: =I58-I60+I66-I68 -> 13642.44 | J70: =J58-J60+J66-J68 -> 16428.573 | K70: =K58-K60+K66-K68 -> 20123.376 | L70: =L58-L60+L66-L68 -> 22524.179 | N70: State loss carryforwards start to expire in 2027 (424B4); expiry is not modelled.
A71: Tax / income before taxes | C71: =IF(Forecast_3Stmt!C21>0,Forecast_3Stmt!C22/Forecast_3Stmt!C21,0) -> -0.071184554 | D71: =IF(Forecast_3Stmt!D21>0,Forecast_3Stmt!D22/Forecast_3Stmt!D21,0) -> 0.018734774 | E71: =IF(Forecast_3Stmt!E21>0,Forecast_3Stmt!E22/Forecast_3Stmt!E21,0) -> 0.0575 | F71: =IF(Forecast_3Stmt!F21>0,Forecast_3Stmt!F22/Forecast_3Stmt!F21,0) -> 0.20545164 | G71: =IF(Forecast_3Stmt!G21>0,Forecast_3Stmt!G22/Forecast_3Stmt!G21,0) -> 0.215 | H71: =IF(Forecast_3Stmt!H21>0,Forecast_3Stmt!H22/Forecast_3Stmt!H21,0) -> 0.21815394 | I71: =IF(Forecast_3Stmt!I21>0,Forecast_3Stmt!I22/Forecast_3Stmt!I21,0) -> 0.23 | J71: =IF(Forecast_3Stmt!J21>0,Forecast_3Stmt!J22/Forecast_3Stmt!J21,0) -> 0.23 | ... L71: =IF(Forecast_3Stmt!L21>0,Forecast_3Stmt!L22/Forecast_3Stmt!L21,0) -> 0.23
A73: G. Working capital
A74: Accounts receivable: % of revenue | C74: =Interim_Bridge!D82/(Interim_Bridge!C25*4) -> 0.081852487 | D74: =$C$74 -> 0.081852487 | E74: =$C$74 -> 0.081852487 | F74: =$C$74 -> 0.081852487 | G74: =$C$74 -> 0.081852487 | H74: =$C$74 -> 0.081852487 | I74: =$C$74 -> 0.081852487 | J74: =$C$74 -> 0.081852487 | K74: =$C$74 -> 0.081852487 | L74: =$C$74 -> 0.081852487 | N74: 2026E: 31 Dec 2026E balance / (Q4 2026E revenue x 4); held.
A75: Inventory: % of revenue | C75: =Interim_Bridge!D83/(Interim_Bridge!C25*4) -> 0.049588336 | D75: =$C$75 -> 0.049588336 | E75: =$C$75 -> 0.049588336 | F75: =$C$75 -> 0.049588336 | G75: =$C$75 -> 0.049588336 | H75: =$C$75 -> 0.049588336 | I75: =$C$75 -> 0.049588336 | J75: =$C$75 -> 0.049588336 | K75: =$C$75 -> 0.049588336 | L75: =$C$75 -> 0.049588336
A76: Prepaid expenses and other current assets: % of revenue | C76: =Interim_Bridge!D84/(Interim_Bridge!C25*4) -> 0.059296741 | D76: =$C$76 -> 0.059296741 | E76: =$C$76 -> 0.059296741 | F76: =$C$76 -> 0.059296741 | G76: =$C$76 -> 0.059296741 | H76: =$C$76 -> 0.059296741 | I76: =$C$76 -> 0.059296741 | J76: =$C$76 -> 0.059296741 | K76: =$C$76 -> 0.059296741 | L76: =$C$76 -> 0.059296741
A77: Accrued expenses and other current liabilities: % of revenue | C77: =Interim_Bridge!D93/(Interim_Bridge!C25*4) -> 0.10286449 | D77: =$C$77 -> 0.10286449 | E77: =$C$77 -> 0.10286449 | F77: =$C$77 -> 0.10286449 | G77: =$C$77 -> 0.10286449 | H77: =$C$77 -> 0.10286449 | I77: =$C$77 -> 0.10286449 | J77: =$C$77 -> 0.10286449 | K77: =$C$77 -> 0.10286449 | L77: =$C$77 -> 0.10286449
A78: Deferred revenue: % of revenue | C78: =Interim_Bridge!D92/(Interim_Bridge!C25*4) -> 0.30051458 | D78: =Assumptions!D154 -> 0.26 | E78: =Assumptions!E154 -> 0.22 | F78: =Assumptions!F154 -> 0.19 | G78: =Assumptions!G154 -> 0.17 | H78: =Assumptions!H154 -> 0.15 | I78: =Assumptions!I154 -> 0.15 | J78: =Assumptions!J154 -> 0.15 | K78: =Assumptions!K154 -> 0.15 | L78: =Assumptions!L154 -> 0.15 | N78: 2027E onward: Assumptions (active).
A79: Accounts payable: % of cash capex plus cash operating costs | C79: =Interim_Bridge!D91/((Interim_Bridge!C59+Interim_Bridge!C25-Interim_Bridge!C31)*4) -> 0.13071296 | D79: =$C$79 -> 0.13071296 | E79: =$C$79 -> 0.13071296 | F79: =$C$79 -> 0.13071296 | G79: =$C$79 -> 0.13071296 | H79: =$C$79 -> 0.13071296 | I79: =$C$79 -> 0.13071296 | J79: =$C$79 -> 0.13071296 | K79: =$C$79 -> 0.13071296 | L79: =$C$79 -> 0.13071296
A80: Accounts receivable | B80: =BS_Hist!C9 -> 1579 | C80: =Interim_Bridge!D82 -> 5612.708 | D80: =Forecast_3Stmt!D10*D74 -> 6734.3874 | E80: =Forecast_3Stmt!E10*E74 -> 9374.0939 | F80: =Forecast_3Stmt!F10*F74 -> 12038.522 | G80: =Forecast_3Stmt!G10*G74 -> 14634.806 | H80: =Forecast_3Stmt!H10*H74 -> 17024.284 | I80: =Forecast_3Stmt!I10*I74 -> 19080.491 | J80: =Forecast_3Stmt!J10*J74 -> 20845.473 | K80: =Forecast_3Stmt!K10*K74 -> 22296.761 | L80: =Forecast_3Stmt!L10*L74 -> 23481.066
A81: Inventory | B81: =BS_Hist!C10 -> 2416 | C81: =Interim_Bridge!D83 -> 3400.3225 | D81: =Forecast_3Stmt!D10*D75 -> 4079.8646 | E81: =Forecast_3Stmt!E10*E75 -> 5679.0665 | F81: =Forecast_3Stmt!F10*F75 -> 7293.2453 | G81: =Forecast_3Stmt!G10*G75 -> 8866.1409 | H81: =Forecast_3Stmt!H10*H75 -> 10313.748 | I81: =Forecast_3Stmt!I10*I75 -> 11559.451 | J81: =Forecast_3Stmt!J10*J75 -> 12628.722 | K81: =Forecast_3Stmt!K10*K75 -> 13507.95 | L81: =Forecast_3Stmt!L10*L75 -> 14225.432
A82: Prepaid expenses and other current assets | B82: =BS_Hist!C11 -> 2210 | C82: =Interim_Bridge!D84 -> 4066.0377 | D82: =Forecast_3Stmt!D10*D76 -> 4878.6205 | E82: =Forecast_3Stmt!E10*E76 -> 6790.9142 | F82: =Forecast_3Stmt!F10*F76 -> 8721.117 | G82: =Forecast_3Stmt!G10*G76 -> 10601.954 | H82: =Forecast_3Stmt!H10*H76 -> 12332.973 | I82: =Forecast_3Stmt!I10*I76 -> 13822.56 | J82: =Forecast_3Stmt!J10*J76 -> 15101.174 | K82: =Forecast_3Stmt!K10*K76 -> 16152.536 | L82: =Forecast_3Stmt!L10*L76 -> 17010.487
A83: Accrued expenses and other current liabilities | B83: =BS_Hist!C26 -> 2569 | C83: =Interim_Bridge!D93 -> 7053.5227 | D83: =Forecast_3Stmt!D10*D77 -> 8463.1435 | E83: =Forecast_3Stmt!E10*E77 -> 11780.478 | F83: =Forecast_3Stmt!F10*F77 -> 15128.88 | G83: =Forecast_3Stmt!G10*G77 -> 18391.645 | H83: =Forecast_3Stmt!H10*H77 -> 21394.516 | I83: =Forecast_3Stmt!I10*I77 -> 23978.563 | J83: =Forecast_3Stmt!J10*J77 -> 26196.627 | K83: =Forecast_3Stmt!K10*K77 -> 28020.469 | L83: =Forecast_3Stmt!L10*L77 -> 29508.791
A84: Deferred revenue | B84: =BS_Hist!C47 -> 12116 | C84: =Interim_Bridge!D92 -> 20606.589 | D84: =Forecast_3Stmt!D10*D78 -> 21391.417 | E84: =Forecast_3Stmt!E10*E78 -> 25195.333 | F84: =Forecast_3Stmt!F10*F78 -> 27944.406 | G84: =Forecast_3Stmt!G10*G78 -> 30395.13 | H84: =Forecast_3Stmt!H10*H78 -> 31198.106 | I84: =Forecast_3Stmt!I10*I78 -> 34966.239 | J84: =Forecast_3Stmt!J10*J78 -> 38200.684 | K84: =Forecast_3Stmt!K10*K78 -> 40860.263 | L84: =Forecast_3Stmt!L10*L78 -> 43030.579
A85: Accounts payable | B85: =BS_Hist!C23 -> 11792 | C85: =Interim_Bridge!D91 -> 15935.777 | D85: =(Segments_Fcst!D49+Forecast_3Stmt!D10-Forecast_3Stmt!D12)*D79 -> 9221.26 | E85: =(Segments_Fcst!E49+Forecast_3Stmt!E10-Forecast_3Stmt!E12)*E79 -> 16367.805 | F85: =(Segments_Fcst!F49+Forecast_3Stmt!F10-Forecast_3Stmt!F12)*F79 -> 17466.294 | G85: =(Segments_Fcst!G49+Forecast_3Stmt!G10-Forecast_3Stmt!G12)*G79 -> 18651.581 | H85: =(Segments_Fcst!H49+Forecast_3Stmt!H10-Forecast_3Stmt!H12)*H79 -> 20130.09 | I85: =(Segments_Fcst!I49+Forecast_3Stmt!I10-Forecast_3Stmt!I12)*I79 -> 21056.074 | J85: =(Segments_Fcst!J49+Forecast_3Stmt!J10-Forecast_3Stmt!J12)*J79 -> 24039.336 | K85: =(Segments_Fcst!K49+Forecast_3Stmt!K10-Forecast_3Stmt!K12)*K79 -> 24663.198 | L85: =(Segments_Fcst!L49+Forecast_3Stmt!L10-Forecast_3Stmt!L12)*L79 -> 25214.434
A86: Net working capital | B86: =B80+B81+B82-B85-B84-B83 -> -20272 | C86: =C80+C81+C82-C85-C84-C83 -> -30516.821 | D86: =D80+D81+D82-D85-D84-D83 -> -23382.948 | E86: =E80+E81+E82-E85-E84-E83 -> -31499.541 | F86: =F80+F81+F82-F85-F84-F83 -> -32486.696 | G86: =G80+G81+G82-G85-G84-G83 -> -33335.456 | H86: =H80+H81+H82-H85-H84-H83 -> -33051.707 | I86: =I80+I81+I82-I85-I84-I83 -> -35538.374 | ... L86: =L80+L81+L82-L85-L84-L83 -> -43036.819
A87: Cash effect of working capital (negative = cash used) | C87: =Interim_Bridge!B67-(C86-Interim_Bridge!B99) -> 5235.8214 | D87: =-(D86-C86) -> -7133.873 | E87: =-(E86-D86) -> 8116.5924 | F87: =-(F86-E86) -> 987.15563 | G87: =-(G86-F86) -> 848.75935 | H87: =-(H86-G86) -> -283.74879 | I87: =-(I86-H86) -> 2486.6674 | J87: =-(J86-I86) -> 4322.9027 | K87: =-(K86-J86) -> 1725.4057 | L87: =-(L86-K86) -> 1450.1364 | N87: 2026E: 9M 2026 cash flow as filed plus the Q4 change from 30 Sep to 31 Dec 2026E.
A89: H. Stock-based compensation (2026E column = Q4 2026E only) | N89: Existing awards: expense stated in the filings, straight line. Their shares are in the diluted count, so the unlevered flows add this expense back; only future grants are a cost there.
A90: Awards outstanding at 31 Dec 2025: unrecognised expense, beginning | C90: =Assumptions!$C$54*MAX(0,1-0.75/Assumptions!$C$55) -> 3707.1562 | D90: =C92 -> 3328.875 | E90: =D92 -> 1815.75 | F90: =E92 -> 302.625 | G90: =F92 -> 0 | H90: =G92 -> 0 | I90: =H92 -> 0 | J90: =I92 -> 0 | K90: =J92 -> 0 | L90: =K92 -> 0 | N90: 30 Sep 2026 balance estimated: US$4,842m less nine months of straight-line expense (the 10-Q does not restate it).
A91: Expense | C91: =MIN(C90,Assumptions!$C$54/Assumptions!$C$55/4) -> 378.28125 | D91: =MIN(D90,Assumptions!$C$54/Assumptions!$C$55) -> 1513.125 | E91: =MIN(E90,Assumptions!$C$54/Assumptions!$C$55) -> 1513.125 | F91: =MIN(F90,Assumptions!$C$54/Assumptions!$C$55) -> 302.625 | G91: =MIN(G90,Assumptions!$C$54/Assumptions!$C$55) -> 0 | H91: =MIN(H90,Assumptions!$C$54/Assumptions!$C$55) -> 0 | I91: =MIN(I90,Assumptions!$C$54/Assumptions!$C$55) -> 0 | J91: =MIN(J90,Assumptions!$C$54/Assumptions!$C$55) -> 0 | K91: =MIN(K90,Assumptions!$C$54/Assumptions!$C$55) -> 0 | L91: =MIN(L90,Assumptions!$C$54/Assumptions!$C$55) -> 0
A92: Ending | C92: =C90-C91 -> 3328.875 | D92: =D90-D91 -> 1815.75 | E92: =E90-E91 -> 302.625 | F92: =F90-F91 -> 0 | G92: =G90-G91 -> 0 | H92: =H90-H91 -> 0 | I92: =I90-I91 -> 0 | J92: =J90-J91 -> 0 | ... L92: =L90-L91 -> 0
A93: Cursor and Mesh awards: unrecognised expense, beginning | C93: =Assumptions!$C$56-Assumptions!$C$57 -> 22159 | D93: =C95 -> 20180.518 | E93: =D95 -> 12266.589 | F93: =E95 -> 4352.6607 | G93: =F95 -> 0 | H93: =G95 -> 0 | I93: =H95 -> 0 | J93: =I95 -> 0 | K93: =J95 -> 0 | L93: =K95 -> 0 | N93: US$23,376m at the 14 Aug close less US$1,217m recognised in Q3 2026 (10-Q).
A94: Expense | C94: =MIN(C93,$C$93/Assumptions!$C$58/4) -> 1978.4821 | D94: =MIN(D93,$C$93/Assumptions!$C$58) -> 7913.9286 | E94: =MIN(E93,$C$93/Assumptions!$C$58) -> 7913.9286 | F94: =MIN(F93,$C$93/Assumptions!$C$58) -> 4352.6607 | G94: =MIN(G93,$C$93/Assumptions!$C$58) -> 0 | H94: =MIN(H93,$C$93/Assumptions!$C$58) -> 0 | I94: =MIN(I93,$C$93/Assumptions!$C$58) -> 0 | J94: =MIN(J93,$C$93/Assumptions!$C$58) -> 0 | K94: =MIN(K93,$C$93/Assumptions!$C$58) -> 0 | L94: =MIN(L93,$C$93/Assumptions!$C$58) -> 0
A95: Ending | C95: =C93-C94 -> 20180.518 | D95: =D93-D94 -> 12266.589 | E95: =E93-E94 -> 4352.6607 | F95: =F93-F94 -> 0 | G95: =G93-G94 -> 0 | H95: =H93-H94 -> 0 | I95: =I93-I94 -> 0 | J95: =J93-J94 -> 0 | ... L95: =L93-L94 -> 0
A96: Expense of existing awards (non-cash; shares already in the diluted count) | C96: =C91+C94 -> 2356.7634 | D96: =D91+D94 -> 9427.0536 | E96: =E91+E94 -> 9427.0536 | F96: =F91+F94 -> 4655.2857 | G96: =G91+G94 -> 0 | H96: =H91+H94 -> 0 | I96: =I91+I94 -> 0 | J96: =J91+J94 -> 0 | ... L96: =L91+L94 -> 0
A97: Future grants: % of revenue x revenue | C97: =Interim_Bridge!C25*Assumptions!$C$64 -> 599.99637 | D97: =Forecast_3Stmt!D10*Assumptions!$C$64 -> 2879.6139 | E97: =Forecast_3Stmt!E10*Assumptions!$C$64 -> 4008.3484 | F97: =Forecast_3Stmt!F10*Assumptions!$C$64 -> 5147.6538 | G97: =Forecast_3Stmt!G10*Assumptions!$C$64 -> 6257.821 | H97: =Forecast_3Stmt!H10*Assumptions!$C$64 -> 7279.5581 | I97: =Forecast_3Stmt!I10*Assumptions!$C$64 -> 8158.7892 | J97: =Forecast_3Stmt!J10*Assumptions!$C$64 -> 8913.4929 | K97: =Forecast_3Stmt!K10*Assumptions!$C$64 -> 9534.0614 | L97: =Forecast_3Stmt!L10*Assumptions!$C$64 -> 10040.468
A98: Stock-based compensation in the income statement | C98: =C96+C97 -> 2956.7598 | D98: =D96+D97 -> 12306.667 | E98: =E96+E97 -> 13435.402 | F98: =F96+F97 -> 9802.9395 | G98: =G96+G97 -> 6257.821 | H98: =H96+H97 -> 7279.5581 | I98: =I96+I97 -> 8158.7892 | J98: =J96+J97 -> 8913.4929 | ... L98: =L96+L97 -> 10040.468 | N98: Musk performance awards: none (both conditions improbable; 424B4 p. F-89). Q4 2026E total compares with US$2,363m in Q3 2026.
A100: I. Unlevered free cash flow (2027E onward; Q4 2026E on Interim_Bridge) | N100: Stock compensation for future grants is a cost and is not added back. Capex is gross: leased GPUs count, so lease rent stays out of the flows and the lease is not deducted again as debt.
A101: Income from operations | D101: =Forecast_3Stmt!D16 -> 11759.656 | E101: =Forecast_3Stmt!E16 -> 19326.293 | F101: =Forecast_3Stmt!F16 -> 31599.567 | G101: =Forecast_3Stmt!G16 -> 44990.754 | H101: =Forecast_3Stmt!H16 -> 52618.02 | I101: =Forecast_3Stmt!I16 -> 57551.637 | J101: =Forecast_3Stmt!J16 -> 67041.693 | K101: =Forecast_3Stmt!K16 -> 80445.637 | L101: =Forecast_3Stmt!L16 -> 87829.941
A102: Taxes on operating income | D102: =-IF(AND(D53>0,D101>0),D70*D101/D53,0) -> -220.31451 | E102: =-IF(AND(E53>0,E101>0),E70*E101/E53,0) -> -1111.2619 | F102: =-IF(AND(F53>0,F101>0),F70*F101/F53,0) -> -6492.183 | G102: =-IF(AND(G53>0,G101>0),G70*G101/G53,0) -> -9673.0121 | H102: =-IF(AND(H53>0,H101>0),H70*H101/H53,0) -> -11478.828 | I102: =-IF(AND(I53>0,I101>0),I70*I101/I53,0) -> -13236.876 | J102: =-IF(AND(J53>0,J101>0),J70*J101/J53,0) -> -15419.589 | K102: =-IF(AND(K53>0,K101>0),K70*K101/K53,0) -> -18502.497 | L102: =-IF(AND(L53>0,L101>0),L70*L101/L53,0) -> -20200.886 | N102: Taxes paid, allocated to operating income; loss carryforwards and credits shelter the early years.
A103: Net operating profit after tax | D103: =D101+D102 -> 11539.342 | E103: =E101+E102 -> 18215.032 | F103: =F101+F102 -> 25107.384 | G103: =G101+G102 -> 35317.742 | H103: =H101+H102 -> 41139.192 | I103: =I101+I102 -> 44314.76 | J103: =J101+J102 -> 51622.104 | K103: =K101+K102 -> 61943.141 | L103: =L101+L102 -> 67629.055
A104: Depreciation and amortization | D104: =D23 -> 23870.16 | E104: =E23 -> 35175.607 | F104: =F23 -> 46432.06 | G104: =G23 -> 56577.226 | H104: =H23 -> 65947.091 | I104: =I23 -> 75625.064 | J104: =J23 -> 78607.482 | K104: =K23 -> 75472.032 | L104: =L23 -> 76454.483
A105: Add back: expense of existing awards (shares already in the diluted count) | D105: =D96 -> 9427.0536 | E105: =E96 -> 9427.0536 | F105: =F96 -> 4655.2857 | G105: =G96 -> 0 | H105: =H96 -> 0 | I105: =I96 -> 0 | J105: =J96 -> 0 | K105: =K96 -> 0 | L105: =L96 -> 0
A106: Capex, gross (cash and leased) | D106: =-Segments_Fcst!D48 -> -76207.675 | E106: =-Segments_Fcst!E48 -> -78632.507 | F106: =-Segments_Fcst!F48 -> -74382.021 | G106: =-Segments_Fcst!G48 -> -71722.051 | H106: =-Segments_Fcst!H48 -> -71859.543 | I106: =-Segments_Fcst!I48 -> -69313.576 | J106: =-Segments_Fcst!J48 -> -83800.792 | K106: =-Segments_Fcst!K48 -> -81732.091 | L106: =-Segments_Fcst!L48 -> -80353.633
A107: Spectrum (EchoStar and 800 MHz), cash part | D107: =-D36 -> -17328 | E107: =-E36 -> 0 | F107: =-F36 -> 0 | G107: =-G36 -> 0 | H107: =-H36 -> 0 | I107: =-I36 -> 0 | J107: =-J36 -> 0 | K107: =-K36 -> 0 | L107: =-L36 -> 0
A108: Change in working capital | D108: =D87 -> -7133.873 | E108: =E87 -> 8116.5924 | F108: =F87 -> 987.15563 | G108: =G87 -> 848.75935 | H108: =H87 -> -283.74879 | I108: =I87 -> 2486.6674 | J108: =J87 -> 4322.9027 | K108: =K87 -> 1725.4057 | L108: =L87 -> 1450.1364
A109: Unlevered free cash flow | D109: =D103+D104+D105+D106+D107+D108 -> -55832.992 | E109: =E103+E104+E105+E106+E107+E108 -> -7698.2225 | F109: =F103+F104+F105+F106+F107+F108 -> 2799.8647 | G109: =G103+G104+G105+G106+G107+G108 -> 21021.676 | H109: =H103+H104+H105+H106+H107+H108 -> 34942.99 | I109: =I103+I104+I105+I106+I107+I108 -> 53112.915 | J109: =J103+J104+J105+J106+J107+J108 -> 50751.697 | K109: =K103+K104+K105+K106+K107+K108 -> 57408.488 | L109: =L103+L104+L105+L106+L107+L108 -> 65180.041
...

Sheet Forecast_3Stmt
A1: Space Exploration Technologies Corp. (SpaceX) | Income statement, balance sheet and cash flow, 2025A and 2026E-2035E
A2: 2025A links to the filings; 2026E to Interim_Bridge; 2027E onward from Segments_Fcst and Schedules (active scenario). USD millions.
B3: Actual | C3: Forecast
A4: Fiscal year ends 31 December | B4: 2025A | C4: 2026E | D4: 2027E | E4: 2028E | F4: 2029E | G4: 2030E | H4: 2031E | I4: 2032E | J4: 2033E | K4: 2034E | L4: 2035E | M4: Comentarios FG | N4: Source / derivation
A6: Income statement
A7: Revenue: Space | B7: =Segments_Fcst!B11 -> 4086 | C7: =Interim_Bridge!D11 -> 4929.9655 | D7: =Segments_Fcst!D11 -> 5620.9366 | E7: =Segments_Fcst!E11 -> 6199.3885 | F7: =Segments_Fcst!F11 -> 6812.5566 | G7: =Segments_Fcst!G11 -> 7415.119 | H7: =Segments_Fcst!H11 -> 7965.5647 | I7: =Segments_Fcst!I11 -> 8518.052 | J7: =Segments_Fcst!J11 -> 9008.1831 | K7: =Segments_Fcst!K11 -> 9491.8812 | L7: =Segments_Fcst!L11 -> 9996.7867
A8: Revenue: Connectivity | B8: =Segments_Fcst!B22 -> 11387 | C8: =Interim_Bridge!D18 -> 18604.285 | D8: =Segments_Fcst!D22 -> 27527.41 | E8: =Segments_Fcst!E22 -> 36530.029 | F8: =Segments_Fcst!F22 -> 46281.912 | G8: =Segments_Fcst!G22 -> 56110.255 | H8: =Segments_Fcst!H22 -> 65330.795 | I8: =Segments_Fcst!I22 -> 74197.507 | J8: =Segments_Fcst!J22 -> 81879.947 | K8: =Segments_Fcst!K22 -> 88880.605 | L8: =Segments_Fcst!L22 -> 95024.222
A9: Revenue: SI | B9: =Segments_Fcst!B36 -> 3201 | C9: =Interim_Bridge!D24 -> 20691.503 | D9: =Segments_Fcst!D36 -> 49126.336 | E9: =Segments_Fcst!E36 -> 71794.823 | F9: =Segments_Fcst!F36 -> 93981.354 | G9: =Segments_Fcst!G36 -> 115269.51 | H9: =Segments_Fcst!H36 -> 134691.01 | I9: =Segments_Fcst!I36 -> 150392.7 | J9: =Segments_Fcst!J36 -> 163783.1 | K9: =Segments_Fcst!K36 -> 174029.27 | L9: =Segments_Fcst!L36 -> 181849.52
A10: Revenue | B10: =B7+B8+B9 -> 18674 | C10: =C7+C8+C9 -> 44225.754 | D10: =D7+D8+D9 -> 82274.682 | E10: =E7+E8+E9 -> 114524.24 | F10: =F7+F8+F9 -> 147075.82 | G10: =G7+G8+G9 -> 178794.88 | H10: =H7+H8+H9 -> 207987.37 | I10: =I7+I8+I9 -> 233108.26 | ... L10: =L7+L8+L9 -> 286870.52
A11: Growth | C11: =C10/B10-1 -> 1.3683064 | D11: =D10/C10-1 -> 0.86033421 | E11: =E10/D10-1 -> 0.39197427 | F11: =F10/E10-1 -> 0.28423312 | G11: =G10/F10-1 -> 0.21566469 | H11: =H10/G10-1 -> 0.16327363 | I11: =I10/H10-1 -> 0.12078083 | J11: =J10/I10-1 -> 0.092501927 | ... L11: =L10/K10-1 -> 0.053115551
A12: Segment adjusted EBITDA | B12: =Segments_Fcst!B46 -> 6584 | C12: =Interim_Bridge!D31 -> 23338.182 | D12: =Segments_Fcst!D46 -> 47936.484 | E12: =Segments_Fcst!E46 -> 67937.303 | F12: =Segments_Fcst!F46 -> 87834.566 | G12: =Segments_Fcst!G46 -> 107825.8 | H12: =Segments_Fcst!H46 -> 125844.67 | I12: =Segments_Fcst!I46 -> 141335.49 | J12: =Segments_Fcst!J46 -> 154562.67 | K12: =Segments_Fcst!K46 -> 165451.73 | L12: =Segments_Fcst!L46 -> 174324.89
A13: Depreciation and amortization | B13: =CF_Hist!D8 -> 6701 | C13: =Interim_Bridge!D32 -> 12680.812 | D13: =Schedules!D23 -> 23870.16 | E13: =Schedules!E23 -> 35175.607 | F13: =Schedules!F23 -> 46432.06 | G13: =Schedules!G23 -> 56577.226 | H13: =Schedules!H23 -> 65947.091 | I13: =Schedules!I23 -> 75625.064 | J13: =Schedules!J23 -> 78607.482 | K13: =Schedules!K23 -> 75472.032 | L13: =Schedules!L23 -> 76454.483
A14: Share-based compensation | B14: =CF_Hist!D9 -> 1947 | C14: =Interim_Bridge!D33 -> 6789.7598 | D14: =Schedules!D98 -> 12306.667 | E14: =Schedules!E98 -> 13435.402 | F14: =Schedules!F98 -> 9802.9395 | G14: =Schedules!G98 -> 6257.821 | H14: =Schedules!H98 -> 7279.5581 | I14: =Schedules!I98 -> 8158.7892 | J14: =Schedules!J98 -> 8913.4929 | K14: =Schedules!K98 -> 9534.0614 | L14: =Schedules!L98 -> 10040.468 | N14: Existing awards (filed amounts) plus future grants; Schedules section H.
A15: Restructuring, impairment and acquisition costs | B15: =Interim_Bridge!G34 -> 525 | C15: =Interim_Bridge!D34 -> 2 | D15: =0 -> 0 | E15: =0 -> 0 | F15: =0 -> 0 | G15: =0 -> 0 | H15: =0 -> 0 | I15: =0 -> 0 | J15: =0 -> 0 | K15: =0 -> 0 | L15: =0 -> 0
A16: Income (loss) from operations | B16: =B12-B13-B14-B15 -> -2589 | C16: =C12-C13-C14-C15 -> 3865.6096 | D16: =D12-D13-D14-D15 -> 11759.656 | E16: =E12-E13-E14-E15 -> 19326.293 | F16: =F12-F13-F14-F15 -> 31599.567 | G16: =G12-G13-G14-G15 -> 44990.754 | H16: =H12-H13-H14-H15 -> 52618.02 | I16: =I12-I13-I14-I15 -> 57551.637 | ... L16: =L12-L13-L14-L15 -> 87829.941
A17: Operating margin | B17: =B16/B10 -> -0.13864196 | C17: =C16/C10 -> 0.087406303 | D17: =D16/D10 -> 0.14293165 | E17: =E16/E10 -> 0.16875286 | F17: =F16/F10 -> 0.21485222 | G17: =G16/G10 -> 0.25163334 | H17: =H16/H10 -> 0.25298661 | I17: =I16/I10 -> 0.24688802 | ... L17: =L16/L10 -> 0.30616579
A18: Interest expense | B18: =IS_Hist!D15 -> -1945 | C18: =Interim_Bridge!D36 -> -2643 | D18: =Schedules!D49 -> -4463.8519 | E18: =Schedules!E49 -> -4419.5783 | F18: =Schedules!F49 -> -3678.3318 | G18: =Schedules!G49 -> -2898.5079 | H18: =Schedules!H49 -> -2127.5811 | I18: =Schedules!I49 -> -1802.5811 | J18: =Schedules!J49 -> -1737.5811 | K18: =Schedules!K49 -> -1737.5811 | L18: =Schedules!L49 -> -1737.5811
A19: Interest income | B19: =IS_Hist!D16 -> 492 | C19: =Interim_Bridge!D37 -> 2373.9703 | D19: =Schedules!D50 -> 3398.0408 | E19: =Schedules!E50 -> 2438.4035 | F19: =Schedules!F50 -> 1731.9699 | G19: =Schedules!G50 -> 1506.7502 | H19: =Schedules!H50 -> 2121.8982 | I19: =Schedules!I50 -> 3565.9023 | J19: =Schedules!J50 -> 6124.4656 | K19: =Schedules!K50 -> 8784.884 | L19: =Schedules!L50 -> 11838.855
A20: Other income (expense), net | B20: =IS_Hist!D17 -> -177 | C20: =Interim_Bridge!D38 -> -937 | D20: =0 -> 0 | E20: =0 -> 0 | F20: =0 -> 0 | G20: =0 -> 0 | H20: =0 -> 0 | I20: =0 -> 0 | J20: =0 -> 0 | K20: =0 -> 0 | L20: =0 -> 0
A21: Income (loss) before income taxes | B21: =B16+B18+B19+B20 -> -4219 | C21: =C16+C18+C19+C20 -> 2659.5799 | D21: =D16+D18+D19+D20 -> 10693.845 | E21: =E16+E18+E19+E20 -> 17345.119 | F21: =F16+F18+F19+F20 -> 29653.205 | G21: =G16+G18+G19+G20 -> 43598.996 | H21: =H16+H18+H19+H20 -> 52612.337 | I21: =I16+I18+I19+I20 -> 59314.958 | ... L21: =L16+L18+L19+L20 -> 97931.215
A22: Provision for (benefit from) income taxes | B22: =IS_Hist!D19 -> 718 | C22: =Interim_Bridge!D40 -> -189.32101 | D22: =Schedules!D70 -> 200.34678 | E22: =Schedules!E70 -> 997.34432 | F22: =Schedules!F70 -> 6092.2998 | G22: =Schedules!G70 -> 9373.7842 | H22: =Schedules!H70 -> 11477.589 | I22: =Schedules!I70 -> 13642.44 | J22: =Schedules!J70 -> 16428.573 | K22: =Schedules!K70 -> 20123.376 | L22: =Schedules!L70 -> 22524.179
A23: Net income (loss) | B23: =B21-B22 -> -4937 | C23: =C21-C22 -> 2848.9009 | D23: =D21-D22 -> 10493.499 | E23: =E21-E22 -> 16347.774 | F23: =F21-F22 -> 23560.905 | G23: =G21-G22 -> 34225.212 | H23: =H21-H22 -> 41134.748 | I23: =I21-I22 -> 45672.518 | ... L23: =L21-L22 -> 75407.035
A24: Net margin | B24: =B23/B10 -> -0.26437828 | C24: =C23/C10 -> 0.064417238 | D24: =D23/D10 -> 0.12754226 | E24: =E23/E10 -> 0.1427451 | F24: =F23/F10 -> 0.16019564 | G24: =G23/G10 -> 0.19142165 | H24: =H23/H10 -> 0.19777522 | I24: =I23/I10 -> 0.19592835 | ... L24: =L23/L10 -> 0.26286087
A25: Segment adjusted EBITDA margin | B25: =B12/B10 -> 0.35257577 | C25: =C12/C10 -> 0.52770569 | D25: =D12/D10 -> 0.58263956 | E25: =E12/E10 -> 0.5932133 | F25: =F12/F10 -> 0.59720602 | G25: =G12/G10 -> 0.60306983 | H25: =H12/H10 -> 0.60505917 | I25: =I12/I10 -> 0.60630837 | ... L25: =L12/L10 -> 0.60767795
A27: Balance sheet (31 December)
A28: Cash and marketable securities | B28: =BS_Hist!C46 -> 24747 | C28: =Interim_Bridge!D81 -> 80522.295 | D28: =C28+D68 -> 57782.073 | E28: =D28+E68 -> 41041.942 | F28: =E28+F68 -> 35704.982 | G28: =F28+G68 -> 50281.949 | H28: =G28+H68 -> 84500.054 | I28: =H28+I68 -> 145129.52 | J28: =I28+J68 -> 208172.61 | K28: =J28+K68 -> 280541.58 | L28: =K28+L68 -> 363540.07
A29: Accounts receivable | B29: =BS_Hist!C9 -> 1579 | C29: =Interim_Bridge!D82 -> 5612.708 | D29: =Schedules!D80 -> 6734.3874 | E29: =Schedules!E80 -> 9374.0939 | F29: =Schedules!F80 -> 12038.522 | G29: =Schedules!G80 -> 14634.806 | H29: =Schedules!H80 -> 17024.284 | I29: =Schedules!I80 -> 19080.491 | J29: =Schedules!J80 -> 20845.473 | K29: =Schedules!K80 -> 22296.761 | L29: =Schedules!L80 -> 23481.066
A30: Inventory | B30: =BS_Hist!C10 -> 2416 | C30: =Interim_Bridge!D83 -> 3400.3225 | D30: =Schedules!D81 -> 4079.8646 | E30: =Schedules!E81 -> 5679.0665 | F30: =Schedules!F81 -> 7293.2453 | G30: =Schedules!G81 -> 8866.1409 | H30: =Schedules!H81 -> 10313.748 | I30: =Schedules!I81 -> 11559.451 | J30: =Schedules!J81 -> 12628.722 | K30: =Schedules!K81 -> 13507.95 | L30: =Schedules!L81 -> 14225.432
A31: Prepaid expenses and other current assets | B31: =BS_Hist!C11 -> 2210 | C31: =Interim_Bridge!D84 -> 4066.0377 | D31: =Schedules!D82 -> 4878.6205 | E31: =Schedules!E82 -> 6790.9142 | F31: =Schedules!F82 -> 8721.117 | G31: =Schedules!G82 -> 10601.954 | H31: =Schedules!H82 -> 12332.973 | I31: =Schedules!I82 -> 13822.56 | J31: =Schedules!J82 -> 15101.174 | K31: =Schedules!K82 -> 16152.536 | L31: =Schedules!L82 -> 17010.487
A32: Property, plant, and equipment, net (including leased GPUs) | B32: =BS_Hist!C14 -> 42602 | C32: =Interim_Bridge!D85 -> 109411 | D32: =Schedules!D24 -> 163647.76 | E32: =Schedules!E24 -> 209003.91 | F32: =Schedules!F24 -> 238853.13 | G32: =Schedules!G24 -> 255198.39 | H32: =Schedules!H24 -> 261110.84 | I32: =Schedules!I24 -> 254799.35 | J32: =Schedules!J24 -> 259992.66 | K32: =Schedules!K24 -> 266252.72 | L32: =Schedules!L24 -> 270151.87
A33: Finance lease right-of-use assets (existing) | B33: =BS_Hist!C15 -> 1260 | C33: =Interim_Bridge!D86 -> 961 | D33: =Schedules!D19 -> 645 | E33: =Schedules!E19 -> 329 | F33: =Schedules!F19 -> 13 | G33: =Schedules!G19 -> 0 | H33: =Schedules!H19 -> 0 | I33: =Schedules!I19 -> 0 | J33: =Schedules!J19 -> 0 | K33: =Schedules!K19 -> 0 | L33: =Schedules!L19 -> 0
A34: Intangible assets, net | B34: =BS_Hist!C16 -> 1548 | C34: =Interim_Bridge!D87 -> 5958.1875 | D34: =Schedules!D22 -> 4374.9375 | E34: =Schedules!E22 -> 2791.6875 | F34: =Schedules!F22 -> 1208.4375 | G34: =Schedules!G22 -> 21 | H34: =Schedules!H22 -> 21 | I34: =Schedules!I22 -> 21 | J34: =Schedules!J22 -> 21 | K34: =Schedules!K22 -> 21 | L34: =Schedules!L22 -> 21
A35: EchoStar spectrum | B35: 0 | C35: =Interim_Bridge!D88 -> 385 | D35: =Schedules!D38 -> 28813.32 | E35: =Schedules!E38 -> 28813.32 | F35: =Schedules!F38 -> 28813.32 | G35: =Schedules!G38 -> 28813.32 | H35: =Schedules!H38 -> 28813.32 | I35: =Schedules!I38 -> 28813.32 | J35: =Schedules!J38 -> 28813.32 | K35: =Schedules!K38 -> 28813.32 | L35: =Schedules!L38 -> 28813.32
A36: Goodwill, digital assets, deferred tax and other assets | B36: =BS_Hist!C18+BS_Hist!C17+BS_Hist!C19+BS_Hist!C20 -> 15717 | C36: =Interim_Bridge!D89 -> 56193 | D36: =C36 -> 56193 | E36: =D36 -> 56193 | F36: =E36 -> 56193 | G36: =F36 -> 56193 | H36: =G36 -> 56193 | I36: =H36 -> 56193 | J36: =I36 -> 56193 | K36: =J36 -> 56193 | L36: =K36 -> 56193 | N36: Held flat.
A37: Total assets | B37: =B28+B29+B30+B31+B32+B33+B34+B35+B36 -> 92079 | C37: =C28+C29+C30+C31+C32+C33+C34+C35+C36 -> 266509.55 | D37: =D28+D29+D30+D31+D32+D33+D34+D35+D36 -> 327148.97 | E37: =E28+E29+E30+E31+E32+E33+E34+E35+E36 -> 360016.94 | F37: =F28+F29+F30+F31+F32+F33+F34+F35+F36 -> 388838.75 | G37: =G28+G29+G30+G31+G32+G33+G34+G35+G36 -> 424610.56 | H37: =H28+H29+H30+H31+H32+H33+H34+H35+H36 -> 470309.22 | I37: =I28+I29+I30+I31+I32+I33+I34+I35+I36 -> 529418.69 | ... L37: =L28+L29+L30+L31+L32+L33+L34+L35+L36 -> 773436.25
A38: Accounts payable | B38: =BS_Hist!C23 -> 11792 | C38: =Interim_Bridge!D91 -> 15935.777 | D38: =Schedules!D85 -> 9221.26 | E38: =Schedules!E85 -> 16367.805 | F38: =Schedules!F85 -> 17466.294 | G38: =Schedules!G85 -> 18651.581 | H38: =Schedules!H85 -> 20130.09 | I38: =Schedules!I85 -> 21056.074 | J38: =Schedules!J85 -> 24039.336 | K38: =Schedules!K85 -> 24663.198 | L38: =Schedules!L85 -> 25214.434
A39: Deferred revenue, current and noncurrent | B39: =BS_Hist!C47 -> 12116 | C39: =Interim_Bridge!D92 -> 20606.589 | D39: =Schedules!D84 -> 21391.417 | E39: =Schedules!E84 -> 25195.333 | F39: =Schedules!F84 -> 27944.406 | G39: =Schedules!G84 -> 30395.13 | H39: =Schedules!H84 -> 31198.106 | I39: =Schedules!I84 -> 34966.239 | J39: =Schedules!J84 -> 38200.684 | K39: =Schedules!K84 -> 40860.263 | L39: =Schedules!L84 -> 43030.579
A40: Accrued expenses and other current liabilities | B40: =BS_Hist!C26 -> 2569 | C40: =Interim_Bridge!D93 -> 7053.5227 | D40: =Schedules!D83 -> 8463.1435 | E40: =Schedules!E83 -> 11780.478 | F40: =Schedules!F83 -> 15128.88 | G40: =Schedules!G83 -> 18391.645 | H40: =Schedules!H83 -> 21394.516 | I40: =Schedules!I83 -> 23978.563 | J40: =Schedules!J83 -> 26196.627 | K40: =Schedules!K83 -> 28020.469 | L40: =Schedules!L83 -> 29508.791
A41: Debt and finance leases, existing (carrying) | B41: =BS_Hist!C48 -> 22896 | C41: =Interim_Bridge!D94 -> 38270 | D41: =Schedules!D43 -> 35529 | E41: =Schedules!E43 -> 32346 | F41: =Schedules!F43 -> 28608 | G41: =Schedules!G43 -> 24998 | H41: =Schedules!H43 -> 24998 | I41: =Schedules!I43 -> 24998 | J41: =Schedules!J43 -> 24998 | K41: =Schedules!K43 -> 24998 | L41: =Schedules!L43 -> 24998
A42: Apollo GPU lease liability | B42: 0 | C42: 0 | D42: =Schedules!D30 -> 34000 | E42: =Schedules!E30 -> 26000 | F42: =Schedules!F30 -> 18000 | G42: =Schedules!G30 -> 10000 | H42: =Schedules!H30 -> 2000 | I42: =Schedules!I30 -> 0 | J42: =Schedules!J30 -> 0 | K42: =Schedules!K30 -> 0 | L42: =Schedules!L30 -> 0
A43: New borrowing (when cash falls below the floor) | B43: 0 | C43: 0 | D43: =C43+D66+D67 -> 0 | E43: =D43+E66+E67 -> 0 | F43: =E43+F66+F67 -> 0 | G43: =F43+G66+G67 -> 0 | H43: =G43+H66+H67 -> 0 | I43: =H43+I66+I67 -> 0 | J43: =I43+J66+J67 -> 0 | K43: =J43+K66+K67 -> 0 | L43: =K43+L66+L67 -> 0
A44: Other liabilities | B44: =BS_Hist!C31 -> 1381 | C44: =Interim_Bridge!D95 -> 1657 | D44: =C44 -> 1657 | E44: =D44 -> 1657 | F44: =E44 -> 1657 | G44: =F44 -> 1657 | H44: =G44 -> 1657 | I44: =H44 -> 1657 | J44: =I44 -> 1657 | K44: =J44 -> 1657 | L44: =K44 -> 1657 | N44: Held flat.
A45: Total liabilities | B45: =B38+B39+B40+B41+B42+B43+B44 -> 50754 | C45: =C38+C39+C40+C41+C42+C43+C44 -> 83522.89 | D45: =D38+D39+D40+D41+D42+D43+D44 -> 110261.82 | E45: =E38+E39+E40+E41+E42+E43+E44 -> 113346.62 | F45: =F38+F39+F40+F41+F42+F43+F44 -> 108804.58 | G45: =G38+G39+G40+G41+G42+G43+G44 -> 104093.36 | H45: =H38+H39+H40+H41+H42+H43+H44 -> 101377.71 | I45: =I38+I39+I40+I41+I42+I43+I44 -> 106655.88 | ... L45: =L38+L39+L40+L41+L42+L43+L44 -> 124408.8
A46: Redeemable convertible preferred stock | B46: =BS_Hist!C34 -> 38752 | C46: 0 | D46: =0 -> 0 | E46: =0 -> 0 | F46: =0 -> 0 | G46: =0 -> 0 | H46: =0 -> 0 | I46: =0 -> 0 | J46: =0 -> 0 | K46: =0 -> 0 | L46: =0 -> 0 | N46: Converted into common stock in 2026 (10-Q).
A47: Shareholders' equity | B47: =BS_Hist!C42 -> 2573 | C47: =Interim_Bridge!D97 -> 182986.66 | D47: =C47+D23+D14+Schedules!D37 -> 216887.15 | E47: =D47+E23+E14+Schedules!E37 -> 246670.32 | F47: =E47+F23+F14+Schedules!F37 -> 280034.17 | G47: =F47+G23+G14+Schedules!G37 -> 320517.2 | H47: =G47+H23+H14+Schedules!H37 -> 368931.51 | I47: =H47+I23+I14+Schedules!I37 -> 422762.81 | J47: =I47+J23+J14+Schedules!J37 -> 486676.31 | K47: =J47+K23+K14+Schedules!K37 -> 563579.94 | L47: =K47+L23+L14+Schedules!L37 -> 649027.44 | N47: Adds net income, stock compensation (non-cash) and the EchoStar shares at closing. No dividends or buybacks.
A48: Total liabilities, preferred stock and equity | B48: =B45+B46+B47 -> 92079 | C48: =C45+C46+C47 -> 266509.55 | D48: =D45+D46+D47 -> 327148.97 | E48: =E45+E46+E47 -> 360016.94 | F48: =F45+F46+F47 -> 388838.75 | G48: =G45+G46+G47 -> 424610.56 | H48: =H45+H46+H47 -> 470309.22 | I48: =I45+I46+I47 -> 529418.69 | ... L48: =L45+L46+L47 -> 773436.25
A50: Cash flow
A51: Net income (loss) | B51: =CF_Hist!D7 -> -4937 | C51: =Interim_Bridge!D63 -> 2848.9009 | D51: =D23 -> 10493.499 | E51: =E23 -> 16347.774 | F51: =F23 -> 23560.905 | G51: =G23 -> 34225.212 | H51: =H23 -> 41134.748 | I51: =I23 -> 45672.518 | J51: =J23 -> 55000.005 | K51: =K23 -> 67369.564 | L51: =L23 -> 75407.035
A52: Depreciation and amortization | B52: =CF_Hist!D8 -> 6701 | C52: =Interim_Bridge!D64 -> 12680.812 | D52: =D13 -> 23870.16 | E52: =E13 -> 35175.607 | F52: =F13 -> 46432.06 | G52: =G13 -> 56577.226 | H52: =H13 -> 65947.091 | I52: =I13 -> 75625.064 | J52: =J13 -> 78607.482 | K52: =K13 -> 75472.032 | L52: =L13 -> 76454.483
A53: Share-based compensation | B53: =CF_Hist!D9 -> 1947 | C53: =Interim_Bridge!D65 -> 6789.7598 | D53: =D14 -> 12306.667 | E53: =E14 -> 13435.402 | F53: =F14 -> 9802.9395 | G53: =G14 -> 6257.821 | H53: =H14 -> 7279.5581 | I53: =I14 -> 8158.7892 | J53: =J14 -> 8913.4929 | K53: =K14 -> 9534.0614 | L53: =L14 -> 10040.468
A54: Other non-cash items | B54: =CF_Hist!D10+CF_Hist!D11+CF_Hist!D12+CF_Hist!D14+CF_Hist!D15+CF_Hist!D17 -> 985 | C54: =Interim_Bridge!D66 -> 368 | D54: =0 -> 0 | E54: =0 -> 0 | F54: =0 -> 0 | G54: =0 -> 0 | H54: =0 -> 0 | I54: =0 -> 0 | J54: =0 -> 0 | K54: =0 -> 0 | L54: =0 -> 0
A55: Changes in operating assets and liabilities | B55: =CF_Hist!D20+CF_Hist!D21+CF_Hist!D22+CF_Hist!D23+CF_Hist!D24+CF_Hist!D25+CF_Hist!D26 -> 2089 | C55: =Interim_Bridge!D67 -> 5235.8214 | D55: =Schedules!D87 -> -7133.873 | E55: =Schedules!E87 -> 8116.5924 | F55: =Schedules!F87 -> 987.15563 | G55: =Schedules!G87 -> 848.75935 | H55: =Schedules!H87 -> -283.74879 | I55: =Schedules!I87 -> 2486.6674 | J55: =Schedules!J87 -> 4322.9027 | K55: =Schedules!K87 -> 1725.4057 | L55: =Schedules!L87 -> 1450.1364
A56: Net cash provided by operating activities | B56: =B51+B52+B53+B54+B55 -> 6785 | C56: =C51+C52+C53+C54+C55 -> 27923.295 | D56: =D51+D52+D53+D54+D55 -> 39536.453 | E56: =E51+E52+E53+E54+E55 -> 73075.376 | F56: =F51+F52+F53+F54+F55 -> 80783.06 | G56: =G51+G52+G53+G54+G55 -> 97909.018 | H56: =H51+H52+H53+H54+H55 -> 114077.65 | I56: =I51+I52+I53+I54+I55 -> 131943.04 | ... L56: =L51+L52+L53+L54+L55 -> 163352.12
A57: Capex paid in cash | B57: =CF_Hist!D30 -> -20737 | C57: =Interim_Bridge!D69 -> -71269 | D57: =-Segments_Fcst!D49 -> -36207.675 | E57: =-Segments_Fcst!E49 -> -78632.507 | F57: =-Segments_Fcst!F49 -> -74382.021 | G57: =-Segments_Fcst!G49 -> -71722.051 | H57: =-Segments_Fcst!H49 -> -71859.543 | I57: =-Segments_Fcst!I49 -> -69313.576 | J57: =-Segments_Fcst!J49 -> -83800.792 | K57: =-Segments_Fcst!K49 -> -81732.091 | L57: =-Segments_Fcst!L49 -> -80353.633
A58: EchoStar spectrum payments | B58: 0 | C58: =Interim_Bridge!D70 -> -385 | D58: =-Schedules!D36 -> -17328 | E58: =-Schedules!E36 -> 0 | F58: =-Schedules!F36 -> 0 | G58: =-Schedules!G36 -> 0 | H58: =-Schedules!H36 -> 0 | I58: =-Schedules!I36 -> 0 | J58: =-Schedules!J36 -> 0 | K58: =-Schedules!K36 -> 0 | L58: =-Schedules!L36 -> 0
A59: Other investing | B59: =CF_Hist!D31+CF_Hist!D32+CF_Hist!D38+CF_Hist!D39 -> -232 | C59: =Interim_Bridge!D71 -> 1057 | D59: =0 -> 0 | E59: =0 -> 0 | F59: =0 -> 0 | G59: =0 -> 0 | H59: =0 -> 0 | I59: =0 -> 0 | J59: =0 -> 0 | K59: =0 -> 0 | L59: =0 -> 0
A60: Add back: marketable securities flows (inside the model's cash) | B60: =-(CF_Hist!D33+CF_Hist!D34+CF_Hist!D35) -> -1394 | C60: =Interim_Bridge!D72 -> 37599 | D60: =0 -> 0 | E60: =0 -> 0 | F60: =0 -> 0 | G60: =0 -> 0 | H60: =0 -> 0 | I60: =0 -> 0 | J60: =0 -> 0 | K60: =0 -> 0 | L60: =0 -> 0
A61: Existing debt and finance leases, net | B61: =CF_Hist!D43+CF_Hist!D44+CF_Hist!D45+CF_Hist!D46 -> 8836 | C61: =Interim_Bridge!D73 -> 9868 | D61: =-Schedules!D42 -> -2741 | E61: =-Schedules!E42 -> -3183 | F61: =-Schedules!F42 -> -3738 | G61: =-Schedules!G42 -> -3610 | H61: =-Schedules!H42 -> 0 | I61: =-Schedules!I42 -> 0 | J61: =-Schedules!J42 -> 0 | K61: =-Schedules!K42 -> 0 | L61: =-Schedules!L42 -> 0
A62: Apollo lease principal | B62: 0 | C62: 0 | D62: =-Schedules!D29 -> -6000 | E62: =-Schedules!E29 -> -8000 | F62: =-Schedules!F29 -> -8000 | G62: =-Schedules!G29 -> -8000 | H62: =-Schedules!H29 -> -8000 | I62: =-Schedules!I29 -> -2000 | J62: =-Schedules!J29 -> 0 | K62: =-Schedules!K29 -> 0 | L62: =-Schedules!L29 -> 0
A63: Equity issued and repurchased | B63: =CF_Hist!D48+CF_Hist!D49+CF_Hist!D50+CF_Hist!D51 -> 17514 | C63: =Interim_Bridge!D74 -> 89377 | D63: =0 -> 0 | E63: =0 -> 0 | F63: =0 -> 0 | G63: =0 -> 0 | H63: =0 -> 0 | I63: =0 -> 0 | J63: =0 -> 0 | K63: =0 -> 0 | L63: =0 -> 0
A64: Restricted cash, exchange rates and security marks (balancing item, actuals) | B64: =B28-BS_Hist!B46-(B56+B57+B58+B59+B60+B61+B63) -> 1790 | C64: =Interim_Bridge!D75 -> -38395 | D64: =0 -> 0 | E64: =0 -> 0 | F64: =0 -> 0 | G64: =0 -> 0 | H64: =0 -> 0 | I64: =0 -> 0 | J64: =0 -> 0 | K64: =0 -> 0 | L64: =0 -> 0
A65: Cash before new borrowing (memo) | D65: =C28+D56+D57+D58+D59+D60+D61+D62+D63+D64 -> 57782.073 | E65: =D28+E56+E57+E58+E59+E60+E61+E62+E63+E64 -> 41041.942 | F65: =E28+F56+F57+F58+F59+F60+F61+F62+F63+F64 -> 35704.982 | G65: =F28+G56+G57+G58+G59+G60+G61+G62+G63+G64 -> 50281.949 | H65: =G28+H56+H57+H58+H59+H60+H61+H62+H63+H64 -> 84500.054 | I65: =H28+I56+I57+I58+I59+I60+I61+I62+I63+I64 -> 145129.52 | J65: =I28+J56+J57+J58+J59+J60+J61+J62+J63+J64 -> 208172.61 | K65: =J28+K56+K57+K58+K59+K60+K61+K62+K63+K64 -> 280541.58 | L65: =K28+L56+L57+L58+L59+L60+L61+L62+L63+L64 -> 363540.07
A66: New borrowing drawn | D66: =MAX(0,Assumptions!$C$59-D65) -> 0 | E66: =MAX(0,Assumptions!$C$59-E65) -> 0 | F66: =MAX(0,Assumptions!$C$59-F65) -> 0 | G66: =MAX(0,Assumptions!$C$59-G65) -> 0 | H66: =MAX(0,Assumptions!$C$59-H65) -> 0 | I66: =MAX(0,Assumptions!$C$59-I65) -> 0 | J66: =MAX(0,Assumptions!$C$59-J65) -> 0 | K66: =MAX(0,Assumptions!$C$59-K65) -> 0 | L66: =MAX(0,Assumptions!$C$59-L65) -> 0
A67: New borrowing repaid | D67: =-MIN(C43,MAX(0,D65-Assumptions!$C$59)) -> 0 | E67: =-MIN(D43,MAX(0,E65-Assumptions!$C$59)) -> 0 | F67: =-MIN(E43,MAX(0,F65-Assumptions!$C$59)) -> 0 | G67: =-MIN(F43,MAX(0,G65-Assumptions!$C$59)) -> 0 | H67: =-MIN(G43,MAX(0,H65-Assumptions!$C$59)) -> 0 | I67: =-MIN(H43,MAX(0,I65-Assumptions!$C$59)) -> 0 | J67: =-MIN(I43,MAX(0,J65-Assumptions!$C$59)) -> 0 | K67: =-MIN(J43,MAX(0,K65-Assumptions!$C$59)) -> 0 | L67: =-MIN(K43,MAX(0,L65-Assumptions!$C$59)) -> 0
A68: Net change in cash and marketable securities | B68: =B56+B57+B58+B59+B60+B61+B62+B63+B64 -> 12562 | C68: =C56+C57+C58+C59+C60+C61+C62+C63+C64 -> 55775.295 | D68: =D65-C28+D66+D67 -> -22740.221 | E68: =E65-D28+E66+E67 -> -16740.131 | F68: =F65-E28+F66+F67 -> -5336.9601 | G68: =G65-F28+G66+G67 -> 14576.967 | H68: =H65-G28+H66+H67 -> 34218.105 | I68: =I65-H28+I66+I67 -> 60629.462 | J68: =J65-I28+J66+J67 -> 63043.091 | K68: =K65-J28+K66+K67 -> 72368.973 | L68: =L65-K28+L66+L67 -> 82998.49
A69: Free cash flow (operating cash flow less cash capex) | B69: =B56+B57 -> -13952 | C69: =C56+C57 -> -43345.705 | D69: =D56+D57 -> 3328.7786 | E69: =E56+E57 -> -5557.1314 | F69: =F56+F57 -> 6401.0399 | G69: =G56+G57 -> 26186.967 | H69: =H56+H57 -> 42218.105 | I69: =I56+I57 -> 62629.462 | ... L69: =L56+L57 -> 82998.49
A70: Free cash flow after lease principal | B70: =B69+B62 -> -13952 | C70: =C69+C62 -> -43345.705 | D70: =D69+D62 -> -2671.2214 | E70: =E69+E62 -> -13557.131 | F70: =F69+F62 -> -1598.9601 | G70: =G69+G62 -> 18186.967 | H70: =H69+H62 -> 34218.105 | I70: =I69+I62 -> 60629.462 | ... L70: =L69+L62 -> 82998.49
A72: Checks (zero passes)
A73: Balance sheet balances | B73: =B37-B48 -> 0 | C73: =C37-C48 -> 0 | D73: =D37-D48 -> 0 | E73: =E37-E48 -> 0 | F73: =F37-F48 -> 0 | G73: =G37-G48 -> 0 | H73: =H37-H48 -> 0 | I73: =I37-I48 -> 0 | ... L73: =L37-L48 -> 0
A74: Cash roll-forward | C74: =B28+C68-C28 -> 0 | D74: =C28+D68-D28 -> 0 | E74: =D28+E68-E28 -> 0 | F74: =E28+F68-F28 -> 0 | G74: =F28+G68-G28 -> 0 | H74: =G28+H68-H28 -> 0 | I74: =H28+I68-I28 -> 0 | J74: =I28+J68-J28 -> 0 | ... L74: =K28+L68-L28 -> 0
A75: Cash never below the floor (2027E onward) | D75: =MIN(0,D28-Assumptions!$C$59+0.001) -> 0 | E75: =MIN(0,E28-Assumptions!$C$59+0.001) -> 0 | F75: =MIN(0,F28-Assumptions!$C$59+0.001) -> 0 | G75: =MIN(0,G28-Assumptions!$C$59+0.001) -> 0 | H75: =MIN(0,H28-Assumptions!$C$59+0.001) -> 0 | I75: =MIN(0,I28-Assumptions!$C$59+0.001) -> 0 | J75: =MIN(0,J28-Assumptions!$C$59+0.001) -> 0 | K75: =MIN(0,K28-Assumptions!$C$59+0.001) -> 0 | L75: =MIN(0,L28-Assumptions!$C$59+0.001) -> 0
A76: 2025A operating result equals the 424B4 | B76: =B16-IS_Hist!D14 -> 0
A77: 2025A net income equals the 424B4 | B77: =B23-IS_Hist!D20 -> 0
A78: 2025A operating cash flow equals the 424B4 | B78: =B56-CF_Hist!D27 -> 0
A79: 2025A total assets equal the 424B4 | B79: =B37-BS_Hist!C21 -> 0
A80: 2026E net income equals the bridge | C80: =C23-Interim_Bridge!D41 -> 0

Sheet Debt_Credit
A1: Space Exploration Technologies Corp. (SpaceX) | Liquidity, debt, obligations and credit metrics
A2: Latest period for every balance: 30 Sep 2026 (10-Q Q3). Commitments signed after that date are shown separately with their own date. USD millions.
A4: Item | B4: 30 Sep 2026A | C4: Comentarios FG | D4: Source / derivation
A6: A. Liquidity
A7: Cash and cash equivalents | B7: =BS_Hist!D7 -> 51294
A8: Marketable securities | B8: =BS_Hist!D8 -> 38561
A9: Undrawn: SpaceX Credit Facility | B9: 5000 | D9: 10-Q Q3 2026 p. 52
A10: Undrawn: xAI revolving line of credit | B10: 250 | D10: 10-Q Q3 2026 p. 52
A11: Liquidity | B11: =B7+B8+B9+B10 -> 95105
A13: B. Debt and debt-like items (all in the EV bridge)
A14: SpaceX Notes (five tranches, 2031-2056), principal | B14: 25000 | D14: 10-Q Q3 2026 p. 17; 10-Q Q3 2026 p. 18
A15: X 2027 and X 2030 Notes, principal | B15: 27 | D15: 10-Q Q3 2026 p. 17
A16: Other financings (mostly Valor AI hardware, failed sale-leasebacks), principal | B16: 12979 | D16: 10-Q Q3 2026 p. 17; 10-Q Q3 2026 p. 21
A17: Total debt, principal | B17: =B14+B15+B16 -> 38006
A18: Finance lease liability | B18: 983 | D18: 10-Q Q3 2026 p. 17
A19: Debt and finance leases, principal | B19: =B17+B18 -> 38989
A20: Less: unamortised financing costs | B20: =-145 -> -145 | D20: 10-Q Q3 2026 p. 17
A21: Debt and finance leases, carrying (balance sheet) | B21: =B19+B20 -> 38844
A22: Litigation accrual (debt-like) | B22: 350 | D22: 10-Q Q3 2026 p. 31
A23: Restructuring liabilities (debt-like) | B23: 249 | D23: 10-Q Q3 2026 p. 22
A24: Debt and debt-like items for the EV bridge | B24: =B19+B22+B23 -> 39588 | D24: Operating lease liabilities (US$374m current) are left out: their cost stays in operating expenses, so deducting them would count them twice.
A25: Digital assets (non-operating, added in the EV bridge) | B25: =BS_Hist!D17 -> 1573
A26: Net debt (debt and debt-like - cash - securities - digital assets) | B26: =B24-B7-B8-B25 -> -51840
A27: Covenant: consolidated leverage ratio, maximum (x) | B27: 3.75 | D27: 10-Q Q3 Note 9 (SpaceX Credit Facility).
A29: C. Scheduled debt principal maturities at 30 Sep 2026
A30: 2026 (remaining three months) | B30: 495 | D30: 10-Q Q3 2026 p. 21
A31: 2027 | B31: 2425 | D31: 10-Q Q3 2026 p. 21
A32: 2028 | B32: 2867 | D32: 10-Q Q3 2026 p. 21
A33: 2029 | B33: 3422 | D33: 10-Q Q3 2026 p. 21
A34: 2030 | B34: 3597 | D34: 10-Q Q3 2026 p. 21
A35: Thereafter | B35: 25200 | D35: 10-Q Q3 2026 p. 21
A36: Total | B36: =SUM(B30:B35) -> 38006
