Workbook

Sheet 00_Cover
A1: ASML Holding N.V. — Regated institutional model
A2: Native-currency, source-ledgered semiconductor model | 2026-07-16 | owner-ready, independent certification pending
A4: Model identifier | B4: ASML_9of10_Regated
A5: Ticker / CIK | B5: ASML / 0000937966
A6: Reporting currency / scale | B6: EUR / EUR millions
A7: Latest historical period | B7: FY2025A
A8: Forecast horizon | B8: Five fiscal years
A9: Valuation method | B9: Unlevered DCF to USD traded-security value
A10: Scenario control | B10: Assumptions!B3 — 1 Base / 2 Bull / 3 Bear
A11: Source gate | B11: Formula-driven exact claim ledger
A12: Native recalculation | B12: LibreOffice 26.2.4.2; two isolated-profile passes + reopen
A13: Architecture | B13: Prior ten-sheet order preserved; Gate_9of10 appended last
A14: Decision status | B14: READY FOR INDEPENDENT 9/10 REVIEW — not self-certified
A16: Use sequence: Sources → Historical → Assumptions → Forecast → Valuation → Sensitivity → Checks → Gate_9of10. Forecasts are estimates. Historical values remain in native currency; only the final security bridge uses dated FX and ADR ratio.

Sheet Sources
A1: Claim-level source and provenance ledger
A2: Every historical hardcode and external valuation input carries exact identity, period, value, locator, accession/URL, target, transform and review status.
A4: Source ID | B4: Legal entity / identifier | C4: Metric / line item | D4: Value | E4: Unit | F4: Period / as-of | G4: Source / class | H4: Taxonomy / claim locator | I4: Form | J4: Filed | K4: Accession | L4: Target cell | M4: Scale / FX / sign transform | N4: Exact official URL | O4: Retrieved | P4: Preparer | Q4: Verification | R4: Limitation / disposition
A5: ASML-S001 | B5: ASML Holding N.V. | ASML | CIK 0000937966 | C5: Revenue | D5: 18611 | E5: EURm | F5: 2021-12-31 | G5: 20-F / Official regulator filing / XBRL | H5: us-gaap:RevenueFromContractWithCustomerExcludingAssessedTax | I5: 20-F | J5: 2024-02-14 | K5: 0000937966-24-000008 | L5: Historical!B5 | M5: EUR / 1e6; sign preserved | N5: https://www.sec.gov/Archives/edgar/data/937966/000093796624000008/0000937966-24-000008-index.html | O5: 2026-07-16 | P5: Codex / semiconductor cluster | Q5: VERIFIED | R5: None
A6: ASML-S002 | B6: ASML Holding N.V. | ASML | CIK 0000937966 | C6: Revenue | D6: 21173.4 | E6: EURm | F6: 2022-12-31 | G6: 20-F / Official regulator filing / XBRL | H6: us-gaap:RevenueFromContractWithCustomerExcludingAssessedTax | I6: 20-F | J6: 2025-03-05 | K6: 0000937966-25-000009 | L6: Historical!C5 | M6: EUR / 1e6; sign preserved | N6: https://www.sec.gov/Archives/edgar/data/937966/000093796625000009/0000937966-25-000009-index.html | O6: 2026-07-16 | P6: Codex / semiconductor cluster | Q6: VERIFIED | R6: None
A7: ASML-S003 | B7: ASML Holding N.V. | ASML | CIK 0000937966 | C7: Revenue | D7: 27558.5 | E7: EURm | F7: 2023-12-31 | G7: 20-F / Official regulator filing / XBRL | H7: us-gaap:RevenueFromContractWithCustomerExcludingAssessedTax | I7: 20-F | J7: 2026-02-25 | K7: 0001628280-26-011378 | L7: Historical!D5 | M7: EUR / 1e6; sign preserved | N7: https://www.sec.gov/Archives/edgar/data/937966/000162828026011378/0001628280-26-011378-index.html | O7: 2026-07-16 | P7: Codex / semiconductor cluster | Q7: VERIFIED | R7: None
A8: ASML-S004 | B8: ASML Holding N.V. | ASML | CIK 0000937966 | C8: Revenue | D8: 28262.9 | E8: EURm | F8: 2024-12-31 | G8: 20-F / Official regulator filing / XBRL | H8: us-gaap:RevenueFromContractWithCustomerExcludingAssessedTax | I8: 20-F | J8: 2026-02-25 | K8: 0001628280-26-011378 | L8: Historical!E5 | M8: EUR / 1e6; sign preserved | N8: https://www.sec.gov/Archives/edgar/data/937966/000162828026011378/0001628280-26-011378-index.html | O8: 2026-07-16 | P8: Codex / semiconductor cluster | Q8: VERIFIED | R8: None
A9: ASML-S005 | B9: ASML Holding N.V. | ASML | CIK 0000937966 | C9: Revenue | D9: 32667.3 | E9: EURm | F9: 2025-12-31 | G9: 20-F / Official regulator filing / XBRL | H9: us-gaap:RevenueFromContractWithCustomerExcludingAssessedTax | I9: 20-F | J9: 2026-02-25 | K9: 0001628280-26-011378 | L9: Historical!F5 | M9: EUR / 1e6; sign preserved | N9: https://www.sec.gov/Archives/edgar/data/937966/000162828026011378/0001628280-26-011378-index.html | O9: 2026-07-16 | P9: Codex / semiconductor cluster | Q9: VERIFIED | R9: None
A10: ASML-S006 | B10: ASML Holding N.V. | ASML | CIK 0000937966 | C10: Gross profit | D10: 9809 | E10: EURm | F10: 2021-12-31 | G10: 20-F / Official regulator filing / XBRL | H10: us-gaap:GrossProfit | I10: 20-F | J10: 2024-02-14 | K10: 0000937966-24-000008 | L10: Historical!B7 | M10: EUR / 1e6; sign preserved | N10: https://www.sec.gov/Archives/edgar/data/937966/000093796624000008/0000937966-24-000008-index.html | O10: 2026-07-16 | P10: Codex / semiconductor cluster | Q10: VERIFIED | R10: None
A11: ASML-S007 | B11: ASML Holding N.V. | ASML | CIK 0000937966 | C11: Gross profit | D11: 10700.1 | E11: EURm | F11: 2022-12-31 | G11: 20-F / Official regulator filing / XBRL | H11: us-gaap:GrossProfit | I11: 20-F | J11: 2025-03-05 | K11: 0000937966-25-000009 | L11: Historical!C7 | M11: EUR / 1e6; sign preserved | N11: https://www.sec.gov/Archives/edgar/data/937966/000093796625000009/0000937966-25-000009-index.html | O11: 2026-07-16 | P11: Codex / semiconductor cluster | Q11: VERIFIED | R11: None
A12: ASML-S008 | B12: ASML Holding N.V. | ASML | CIK 0000937966 | C12: Gross profit | D12: 14136.1 | E12: EURm | F12: 2023-12-31 | G12: 20-F / Official regulator filing / XBRL | H12: us-gaap:GrossProfit | I12: 20-F | J12: 2026-02-25 | K12: 0001628280-26-011378 | L12: Historical!D7 | M12: EUR / 1e6; sign preserved | N12: https://www.sec.gov/Archives/edgar/data/937966/000162828026011378/0001628280-26-011378-index.html | O12: 2026-07-16 | P12: Codex / semiconductor cluster | Q12: VERIFIED | R12: None
A13: ASML-S009 | B13: ASML Holding N.V. | ASML | CIK 0000937966 | C13: Gross profit | D13: 14492 | E13: EURm | F13: 2024-12-31 | G13: 20-F / Official regulator filing / XBRL | H13: us-gaap:GrossProfit | I13: 20-F | J13: 2026-02-25 | K13: 0001628280-26-011378 | L13: Historical!E7 | M13: EUR / 1e6; sign preserved | N13: https://www.sec.gov/Archives/edgar/data/937966/000162828026011378/0001628280-26-011378-index.html | O13: 2026-07-16 | P13: Codex / semiconductor cluster | Q13: VERIFIED | R13: None
A14: ASML-S010 | B14: ASML Holding N.V. | ASML | CIK 0000937966 | C14: Gross profit | D14: 17258 | E14: EURm | F14: 2025-12-31 | G14: 20-F / Official regulator filing / XBRL | H14: us-gaap:GrossProfit | I14: 20-F | J14: 2026-02-25 | K14: 0001628280-26-011378 | L14: Historical!F7 | M14: EUR / 1e6; sign preserved | N14: https://www.sec.gov/Archives/edgar/data/937966/000162828026011378/0001628280-26-011378-index.html | O14: 2026-07-16 | P14: Codex / semiconductor cluster | Q14: VERIFIED | R14: None
A15: ASML-S011 | B15: ASML Holding N.V. | ASML | CIK 0000937966 | C15: Operating income | D15: 6750.1 | E15: EURm | F15: 2021-12-31 | G15: 20-F / Official regulator filing / XBRL | H15: us-gaap:OperatingIncomeLoss | I15: 20-F | J15: 2024-02-14 | K15: 0000937966-24-000008 | L15: Historical!B9 | M15: EUR / 1e6; sign preserved | N15: https://www.sec.gov/Archives/edgar/data/937966/000093796624000008/0000937966-24-000008-index.html | O15: 2026-07-16 | P15: Codex / semiconductor cluster | Q15: VERIFIED | R15: None
A16: ASML-S012 | B16: ASML Holding N.V. | ASML | CIK 0000937966 | C16: Operating income | D16: 6500.7 | E16: EURm | F16: 2022-12-31 | G16: 20-F / Official regulator filing / XBRL | H16: us-gaap:OperatingIncomeLoss | I16: 20-F | J16: 2025-03-05 | K16: 0000937966-25-000009 | L16: Historical!C9 | M16: EUR / 1e6; sign preserved | N16: https://www.sec.gov/Archives/edgar/data/937966/000093796625000009/0000937966-25-000009-index.html | O16: 2026-07-16 | P16: Codex / semiconductor cluster | Q16: VERIFIED | R16: None
... A97: ASML-S093 | B97: ASML Holding N.V. | ASML | CIK 0000937966 | C97: Terminal growth | D97: 0.03 | E97: model input | F97: Forecast horizon | G97: Model input / Forecast assumption / model input | H97: Base/Bull/Bear estimate | I97: Model input | J97: 2026-07-16 | K97: n/a | L97: Assumptions!B21:D21 | M97: blue model input | N97: https://www.sec.gov/Archives/edgar/data/937966/000162828026011378/asml-20251231.htm | O97: 2026-07-16 | P97: Codex / semiconductor cluster | Q97: VERIFIED | R97: Not a reported fact

Sheet Historical
A1: Historical financials
A2: EUR millions; native reported history. Percent rows are formula-derived.
A4: Metric | B4: FY2021A | C4: FY2022A | D4: FY2023A | E4: FY2024A | F4: FY2025A | G4: Unit | H4: Source coverage
A5: Revenue | B5: 18611 | C5: 21173.4 | D5: 27558.5 | E5: 28262.9 | F5: 32667.3 | G5: EUR millions | H5: =IF(COUNTIF(Sources!$C$5:$C$97,"Revenue")>=1,"VERIFIED","CHECK") -> VERIFIED
A6: Growth | C6: =IF(B5<>0,C5/B5-1,0) -> 0.13768202 | D6: =IF(C5<>0,D5/C5-1,0) -> 0.30156234 | E6: =IF(D5<>0,E5/D5-1,0) -> 0.025560172 | F6: =IF(E5<>0,F5/E5-1,0) -> 0.1558368 | G6: % | H6: Formula-derived
A7: Gross profit | B7: 9809 | C7: 10700.1 | D7: 14136.1 | E7: 14492 | F7: 17258 | G7: EUR millions | H7: =IF(COUNTIF(Sources!$C$5:$C$97,"Gross profit")>=1,"VERIFIED","CHECK") -> VERIFIED
A8: Gross margin | B8: =IF(B5<>0,B7/B5,0) -> 0.52705389 | C8: =IF(C5<>0,C7/C5,0) -> 0.50535578 | D8: =IF(D5<>0,D7/D5,0) -> 0.51294882 | E8: =IF(E5<>0,E7/E5,0) -> 0.51275701 | F8: =IF(F5<>0,F7/F5,0) -> 0.52829588 | G8: % | H8: Formula-derived
A9: Operating income | B9: 6750.1 | C9: 6500.7 | D9: 9042.3 | E9: 9022.6 | F9: 11301.4 | G9: EUR millions | H9: =IF(COUNTIF(Sources!$C$5:$C$97,"Operating income")>=1,"VERIFIED","CHECK") -> VERIFIED
A10: Operating margin | B10: =IF(B5<>0,B9/B5,0) -> 0.36269411 | C10: =IF(C5<>0,C9/C5,0) -> 0.30702202 | D10: =IF(D5<>0,D9/D5,0) -> 0.32811292 | E10: =IF(E5<>0,E9/E5,0) -> 0.31923829 | F10: =IF(F5<>0,F9/F5,0) -> 0.34595452 | G10: % | H10: Formula-derived
A11: Net income attributable / consolidated | B11: 5883.2 | C11: 5624.2 | D11: 7839 | E11: 7571.6 | F11: 9609.4 | G11: EUR millions | H11: =IF(COUNTIF(Sources!$C$5:$C$97,"Net income attributable / consolidated")>=1,"VERIFIED","CHECK") -> VERIFIED
A12: Cash flow from operations | B12: 10845.8 | C12: 8486.8 | D12: 5443.4 | E12: 11166.2 | F12: 12658.5 | G12: EUR millions | H12: =IF(COUNTIF(Sources!$C$5:$C$97,"Cash flow from operations")>=1,"VERIFIED","CHECK") -> VERIFIED
A13: Capital expenditure | B13: 900.7 | C13: 1281.8 | D13: 2155.6 | E13: 2067.2 | F13: 1573.6 | G13: EUR millions | H13: =IF(COUNTIF(Sources!$C$5:$C$97,"Capital expenditure")>=1,"VERIFIED","CHECK") -> VERIFIED
A14: Research and development | B14: 2547 | C14: 3253.5 | D14: 3980.6 | E14: 4303.7 | F14: 4698.8 | G14: EUR millions | H14: =IF(COUNTIF(Sources!$C$5:$C$97,"Research and development")>=1,"VERIFIED","CHECK") -> VERIFIED
A15: Total assets | B15: 30231 | C15: 36300.4 | D15: 39957.5 | E15: 48589.6 | F15: 50566.6 | G15: EUR millions | H15: =IF(COUNTIF(Sources!$C$5:$C$97,"Total assets")>=1,"VERIFIED","CHECK") -> VERIFIED
A16: Total liabilities | B16: 20090.4 | C16: 27489.6 | D16: 26505.1 | E16: 30112.8 | F16: 30954.4 | G16: EUR millions | H16: =IF(COUNTIF(Sources!$C$5:$C$97,"Total liabilities")>=1,"VERIFIED","CHECK") -> VERIFIED
A17: Equity attributable / stockholders' equity | B17: 10140.6 | C17: 8810.8 | D17: 13452.4 | E17: 18476.8 | F17: 19612.2 | G17: EUR millions | H17: =IF(COUNTIF(Sources!$C$5:$C$97,"Equity attributable / stockholders' equity")>=1,"VERIFIED","CHECK") -> VERIFIED
A18: Cash and cash equivalents | B18: 6951.8 | C18: 7268.3 | D18: 7004.7 | E18: 12735.9 | F18: 12916 | G18: EUR millions | H18: =IF(COUNTIF(Sources!$C$5:$C$97,"Cash and cash equivalents")>=1,"VERIFIED","CHECK") -> VERIFIED
A19: Interest-bearing debt | B19: 4075 | C19: 3514.2 | D19: 4631.5 | E19: 3677.3 | F19: 2709 | G19: EUR millions | H19: =IF(COUNTIF(Sources!$C$5:$C$97,"Interest-bearing debt")>=1,"VERIFIED","CHECK") -> VERIFIED
A20: Diluted weighted-average shares | B20: 410.4 | C20: 398 | D20: 394.1 | E20: 393.6 | F20: 388.9 | G20: millions of shares | H20: =IF(COUNTIF(Sources!$C$5:$C$97,"Diluted weighted-average shares")>=1,"VERIFIED","CHECK") -> VERIFIED

Sheet Assumptions
A1: Scenario assumptions
A2: Blue = input; green = selected formula. Selector 1 Base / 2 Bull / 3 Bear. EUR stays native through DCF.
A3: Scenario selector | B3: 1
A4: Driver | B4: Base | C4: Bull | D4: Bear | E4: Active | F4: Classification / rationale
A5: System units growth — Y1 | B5: 0.05 | C5: 0.09 | D5: -0.03 | E5: =CHOOSE($B$3,B5,C5,D5) -> 0.05 | F5: Company-specific revenue driver estimate
A6: System units growth — Y5 | B6: 0.04 | C6: 0.07 | D6: 0.01 | E6: =CHOOSE($B$3,B6,C6,D6) -> 0.04 | F6: Company-specific revenue driver estimate
A7: Average system revenue growth — Y1 | B7: 0.05 | C7: 0.08 | D7: 0.02 | E7: =CHOOSE($B$3,B7,C7,D7) -> 0.05 | F7: Company-specific revenue driver estimate
A8: Average system revenue growth — Y5 | B8: 0.03 | C8: 0.06 | D8: 0.01 | E8: =CHOOSE($B$3,B8,C8,D8) -> 0.03 | F8: Company-specific revenue driver estimate
A9: Installed-base revenue growth — Y1 | B9: 0.1 | C9: 0.13 | D9: 0.06 | E9: =CHOOSE($B$3,B9,C9,D9) -> 0.1 | F9: Company-specific revenue driver estimate
A10: Installed-base revenue growth — Y5 | B10: 0.07 | C10: 0.1 | D10: 0.04 | E10: =CHOOSE($B$3,B10,C10,D10) -> 0.07 | F10: Company-specific revenue driver estimate
A11: Gross margin — Y1 | B11: 0.525 | C11: 0.54 | D11: 0.5 | E11: =CHOOSE($B$3,B11,C11,D11) -> 0.525 | F11: Operating / FCFF estimate
A12: Gross margin — Y5 | B12: 0.545 | C12: 0.57 | D12: 0.515 | E12: =CHOOSE($B$3,B12,C12,D12) -> 0.545 | F12: Operating / FCFF estimate
A13: R&D / revenue | B13: 0.143 | C13: 0.14 | D13: 0.15 | E13: =CHOOSE($B$3,B13,C13,D13) -> 0.143 | F13: Operating / FCFF estimate
A14: Other operating expense / revenue | B14: 0.039 | C14: 0.036 | D14: 0.043 | E14: =CHOOSE($B$3,B14,C14,D14) -> 0.039 | F14: Operating / FCFF estimate
A15: Cash tax rate | B15: 0.15 | C15: 0.14 | D15: 0.17 | E15: =CHOOSE($B$3,B15,C15,D15) -> 0.15 | F15: Operating / FCFF estimate
A16: D&A / revenue | B16: 0.05 | C16: 0.052 | D16: 0.048 | E16: =CHOOSE($B$3,B16,C16,D16) -> 0.05 | F16: Operating / FCFF estimate
... A26: Shareholder distributions / FCFF (dividends + buybacks payout ratio) | B26: 0.62 | C26: 0.55 | D26: 0.7 | E26: =CHOOSE($B$3,B26,C26,D26) -> 0.62 | F26: Cash roll-forward driver — FY2022-25A avg payout (dividend+buyback)/FCFF ≈0.62; Bull lower buyback intensity, Bear higher (defensive capital return). Fixes Forecast!C26:G26 frozen-cash defect.
A27: Debt policy | B27: Static — no financing driver modeled (documented simplifying assumption, not a hidden freeze)

Sheet Forecast
A1: Company-specific operating forecast
A2: EUR millions; sector operating drivers build revenue bottom-up.
A4: Metric | B4: FY2025A | C4: FY2026E | D4: FY2027E | E4: FY2028E | F4: FY2029E | G4: FY2030E
A5: Systems sold | B5: 535 | C5: =B5*(1+Assumptions!$E$5) -> 561.75 | D5: =C5*(1+Assumptions!$E$5+(Assumptions!$E$6-Assumptions!$E$5)*1/4) -> 588.43313 | E5: =D5*(1+Assumptions!$E$5+(Assumptions!$E$6-Assumptions!$E$5)*2/4) -> 614.91262 | F5: =E5*(1+Assumptions!$E$5+(Assumptions!$E$6-Assumptions!$E$5)*3/4) -> 641.0464 | G5: =F5*(1+Assumptions!$E$5+(Assumptions!$E$6-Assumptions!$E$5)*4/4) -> 666.68826
A6: Average system revenue | B6: 45.746355 | C6: =B6*(1+Assumptions!$E$7) -> 48.033673 | D6: =C6*(1+Assumptions!$E$7+(Assumptions!$E$8-Assumptions!$E$7)*1/4) -> 50.195188 | E6: =D6*(1+Assumptions!$E$7+(Assumptions!$E$8-Assumptions!$E$7)*2/4) -> 52.202996 | F6: =E6*(1+Assumptions!$E$7+(Assumptions!$E$8-Assumptions!$E$7)*3/4) -> 54.030101 | G6: =F6*(1+Assumptions!$E$7+(Assumptions!$E$8-Assumptions!$E$7)*4/4) -> 55.651004
A7: Installed Base Management revenue | B7: 8193 | C7: =B7*(1+Assumptions!$E$9) -> 9012.3 | D7: =C7*(1+Assumptions!$E$9+(Assumptions!$E$10-Assumptions!$E$9)*1/4) -> 9845.9378 | E7: =D7*(1+Assumptions!$E$9+(Assumptions!$E$10-Assumptions!$E$9)*2/4) -> 10682.842 | F7: =E7*(1+Assumptions!$E$9+(Assumptions!$E$10-Assumptions!$E$9)*3/4) -> 11510.763 | G7: =F7*(1+Assumptions!$E$9+(Assumptions!$E$10-Assumptions!$E$9)*4/4) -> 12316.516
A8: Total revenue | B8: =B5*B6+B7 -> 32667.3 | C8: =C5*C6+C7 -> 35995.216 | D8: =D5*D6+D7 -> 39382.449 | E8: =E5*E6+E7 -> 42783.123 | F8: =F5*F6+F7 -> 46146.564 | G8: =G5*G6+G7 -> 49418.387
A9: Revenue growth | B9: =Historical!F6 -> 0.1558368 | C9: =IF(B8<>0,C8/B8-1,0) -> 0.101873 | D9: =IF(C8<>0,D8/C8-1,0) -> 0.094102324 | E9: =IF(D8<>0,E8/D8-1,0) -> 0.086349985 | F9: =IF(E8<>0,F8/E8-1,0) -> 0.078616075 | G9: =IF(F8<>0,G8/F8-1,0) -> 0.070900673
A10: Gross margin | B10: =Historical!F8 -> 0.52829588 | C10: =Assumptions!$E$11 -> 0.525 | D10: =Assumptions!$E$11+(Assumptions!$E$12-Assumptions!$E$11)*1/4 -> 0.53 | E10: =Assumptions!$E$11+(Assumptions!$E$12-Assumptions!$E$11)*2/4 -> 0.535 | F10: =Assumptions!$E$11+(Assumptions!$E$12-Assumptions!$E$11)*3/4 -> 0.54 | G10: =Assumptions!$E$11+(Assumptions!$E$12-Assumptions!$E$11)*4/4 -> 0.545
A11: Gross profit | B11: =B8*B10 -> 17258 | C11: =C8*C10 -> 18897.488 | D11: =D8*D10 -> 20872.698 | E11: =E8*E10 -> 22888.971 | F11: =F8*F10 -> 24919.145 | G11: =G8*G10 -> 26933.021
A12: R&D / revenue | B12: =IF(B8<>0,Historical!F14/B8,0) -> 0.14383803 | C12: =Assumptions!$E$13 -> 0.143 | D12: =Assumptions!$E$13 -> 0.143 | E12: =Assumptions!$E$13 -> 0.143 | F12: =Assumptions!$E$13 -> 0.143 | G12: =Assumptions!$E$13 -> 0.143
A13: R&D | B13: =Historical!F14 -> 4698.8 | C13: =C8*C12 -> 5147.3159 | D13: =D8*D12 -> 5631.6902 | E13: =E8*E12 -> 6117.9866 | F13: =F8*F12 -> 6598.9587 | G13: =G8*G12 -> 7066.8293
A14: Other operating expense / revenue | B14: =IF(B8<>0,(B11-Historical!F9-B13)/B8,0) -> 0.038503335 | C14: =Assumptions!$E$14 -> 0.039 | D14: =Assumptions!$E$14 -> 0.039 | E14: =Assumptions!$E$14 -> 0.039 | F14: =Assumptions!$E$14 -> 0.039 | G14: =Assumptions!$E$14 -> 0.039
A15: Other operating expense | B15: =B8*B14 -> 1257.8 | C15: =C8*C14 -> 1403.8134 | D15: =D8*D14 -> 1535.9155 | E15: =E8*E14 -> 1668.5418 | F15: =F8*F14 -> 1799.716 | G15: =G8*G14 -> 1927.3171
A16: Operating income | B16: =B11-B13-B15 -> 11301.4 | C16: =C11-C13-C15 -> 12346.359 | D16: =D11-D13-D15 -> 13705.092 | E16: =E11-E13-E15 -> 15102.442 | F16: =F11-F13-F15 -> 16520.47 | G16: =G11-G13-G15 -> 17938.874
A17: Operating margin | B17: =IF(B8<>0,B16/B8,0) -> 0.34595452 | C17: =IF(C8<>0,C16/C8,0) -> 0.343 | D17: =IF(D8<>0,D16/D8,0) -> 0.348 | E17: =IF(E8<>0,E16/E8,0) -> 0.353 | F17: =IF(F8<>0,F16/F8,0) -> 0.358 | G17: =IF(G8<>0,G16/G8,0) -> 0.363
A18: Cash tax rate | B18: =Assumptions!E15 -> 0.15 | C18: =Assumptions!$E$15 -> 0.15 | D18: =Assumptions!$E$15 -> 0.15 | E18: =Assumptions!$E$15 -> 0.15 | F18: =Assumptions!$E$15 -> 0.15 | G18: =Assumptions!$E$15 -> 0.15
A19: NOPAT | B19: =B16*(1-B18) -> 9606.19 | C19: =C16*(1-C18) -> 10494.405 | D19: =D16*(1-D18) -> 11649.328 | E19: =E16*(1-E18) -> 12837.076 | F19: =F16*(1-F18) -> 14042.4 | G19: =G16*(1-G18) -> 15248.043
A20: D&A / revenue | B20: =Assumptions!E16 -> 0.05 | C20: =Assumptions!$E$16 -> 0.05 | D20: =Assumptions!$E$16 -> 0.05 | E20: =Assumptions!$E$16 -> 0.05 | F20: =Assumptions!$E$16 -> 0.05 | G20: =Assumptions!$E$16 -> 0.05
A21: D&A | B21: =B8*B20 -> 1633.365 | C21: =C8*C20 -> 1799.7608 | D21: =D8*D20 -> 1969.1225 | E21: =E8*E20 -> 2139.1562 | F21: =F8*F20 -> 2307.3282 | G21: =G8*G20 -> 2470.9193
A22: Capex / revenue | B22: =IF(B8<>0,Historical!F13/B8,0) -> 0.048170495 | C22: =Assumptions!$E$17 -> 0.05 | D22: =Assumptions!$E$17+(Assumptions!$E$18-Assumptions!$E$17)*1/4 -> 0.04875 | E22: =Assumptions!$E$17+(Assumptions!$E$18-Assumptions!$E$17)*2/4 -> 0.0475 | F22: =Assumptions!$E$17+(Assumptions!$E$18-Assumptions!$E$17)*3/4 -> 0.04625 | G22: =Assumptions!$E$17+(Assumptions!$E$18-Assumptions!$E$17)*4/4 -> 0.045
A23: Capital expenditure | B23: =Historical!F13 -> 1573.6 | C23: =C8*C22 -> 1799.7608 | D23: =D8*D22 -> 1919.8944 | E23: =E8*E22 -> 2032.1983 | F23: =F8*F22 -> 2134.2786 | G23: =G8*G22 -> 2223.8274
A24: Change in NWC | B24: 0 | C24: =MAX(0,(C8-B8)*Assumptions!$E$19) -> 99.837473 | D24: =MAX(0,(D8-C8)*Assumptions!$E$19) -> 101.617 | E24: =MAX(0,(E8-D8)*Assumptions!$E$19) -> 102.02022 | F24: =MAX(0,(F8-E8)*Assumptions!$E$19) -> 100.90324 | G24: =MAX(0,(G8-F8)*Assumptions!$E$19) -> 98.154674
A25: FCFF | B25: =B19+B21-B23-B24 -> 9665.955 | C25: =C19+C21-C23-C24 -> 10394.568 | D25: =D19+D21-D23-D24 -> 11596.94 | E25: =E19+E21-E23-E24 -> 12842.014 | F25: =F19+F21-F23-F24 -> 14114.546 | G25: =G19+G21-G23-G24 -> 15396.98
A26: Cash / liquidity | B26: 12916 | C26: =B26+Forecast!C25*(1-Assumptions!$E$26) -> 16865.936 | D26: =C26+Forecast!D25*(1-Assumptions!$E$26) -> 21272.773 | E26: =D26+Forecast!E25*(1-Assumptions!$E$26) -> 26152.738 | F26: =E26+Forecast!F25*(1-Assumptions!$E$26) -> 31516.265 | G26: =F26+Forecast!G25*(1-Assumptions!$E$26) -> 37367.118
A27: Interest-bearing debt | B27: 2709 | C27: =B$27 -> 2709 | D27: =B$27 -> 2709 | E27: =B$27 -> 2709 | F27: =B$27 -> 2709 | G27: =B$27 -> 2709
A28: Diluted shares | B28: 388.9 | C28: =$B$28 -> 388.9 | D28: =$B$28 -> 388.9 | E28: =$B$28 -> 388.9 | F28: =$B$28 -> 388.9 | G28: =$B$28 -> 388.9

Sheet Valuation
A1: Discounted cash flow valuation
A2: EUR millions; DCF stays native through equity value. Final line converts to the USD traded security.
A4: Metric | B4: Year 1 | C4: Year 2 | D4: Year 3 | E4: Year 4 | F4: Year 5 | G4: Output
A5: FCFF | B5: =Forecast!C25 -> 10394.568 | C5: =Forecast!D25 -> 11596.94 | D5: =Forecast!E25 -> 12842.014 | E5: =Forecast!F25 -> 14114.546 | F5: =Forecast!G25 -> 15396.98
A6: Discount factor | B6: =1/(1+Assumptions!$E$20)^1 -> 0.92165899 | C6: =1/(1+Assumptions!$E$20)^2 -> 0.84945529 | D6: =1/(1+Assumptions!$E$20)^3 -> 0.7829081 | E6: =1/(1+Assumptions!$E$20)^4 -> 0.72157428 | F6: =1/(1+Assumptions!$E$20)^5 -> 0.66504542
A7: PV of FCFF | B7: =B5*B6 -> 9580.2467 | C7: =C5*C6 -> 9851.0816 | D7: =D5*D6 -> 10054.117 | E7: =E5*E6 -> 10184.693 | F7: =F5*F6 -> 10239.691
A9: Output | B9: Value
A10: PV explicit FCFF | B10: =SUM(B7:F7) -> 49909.83
A11: Terminal value | B11: =IF(Assumptions!$E$20>Assumptions!$E$21,F5*(1+Assumptions!$E$21)/(Assumptions!$E$20-Assumptions!$E$21),0) -> 288343.45
A12: PV terminal value | B12: =B11*F6 -> 191761.49
A13: Enterprise value | B13: =B10+B12 -> 241671.32
A14: Cash / liquidity | B14: =Forecast!B26 -> 12916
A15: Interest-bearing debt | B15: =Forecast!B27 -> 2709
A16: Equity value | B16: =B13+B14-B15 -> 251878.32
A17: Diluted shares (mm) | B17: =Forecast!B28 -> 388.9
A18: Implied EUR / ordinary share | B18: =IF(B17>0,B16/B17,0) -> 647.66861
A19: FX conversion input | B19: =Assumptions!E22 -> 1.1474
A20: Ordinary shares per traded security | B20: =Assumptions!E23 -> 1
A21: Implied USD / traded security | B21: =B18*Assumptions!$E$22*Assumptions!$E$23 -> 743.13497
A22: Current traded-security price (USD) | B22: =Assumptions!E24 -> 1815.27
A23: Upside / (downside) | B23: =IF(B22>0,B21/B22-1,0) -> -0.59062015

Sheet Sensitivity
A1: DCF sensitivity — implied USD / traded security
A2: Dynamic per-share matrix; center is active WACC / terminal growth.
A4: Terminal growth / WACC | B4: =Assumptions!$E$20+-0.02 -> 0.065 | C4: =Assumptions!$E$20+-0.01 -> 0.075 | D4: =Assumptions!$E$20+0 -> 0.085 | E4: =Assumptions!$E$20+0.01 -> 0.095 | F4: =Assumptions!$E$20+0.02 -> 0.105
A5: =Assumptions!$E$21+-0.01 -> 0.02 | B5: =((Valuation!$B$5/(1+B$4)^1+Valuation!$C$5/(1+B$4)^2+Valuation!$D$5/(1+B$4)^3+Valuation!$E$5/(1+B$4)^4+Valuation!$F$5/(1+B$4)^5+IF(B$4>$A5,Valuation!$F$5*(1+$A5)/(B$4-$A5)/(1+B$4)^5,0)+Valuation!$B$14-Valuation!$B$15)/Valuation!$B$17)*Assumptions!$E$22*Assumptions!$E$23 -> 937.50928 | C5: =((Valuation!$B$5/(1+C$4)^1+Valuation!$C$5/(1+C$4)^2+Valuation!$D$5/(1+C$4)^3+Valuation!$E$5/(1+C$4)^4+Valuation!$F$5/(1+C$4)^5+IF(C$4>$A5,Valuation!$F$5*(1+$A5)/(C$4-$A5)/(1+C$4)^5,0)+Valuation!$B$14-Valuation!$B$15)/Valuation!$B$17)*Assumptions!$E$22*Assumptions!$E$23 -> 768.39778 | D5: =((Valuation!$B$5/(1+D$4)^1+Valuation!$C$5/(1+D$4)^2+Valuation!$D$5/(1+D$4)^3+Valuation!$E$5/(1+D$4)^4+Valuation!$F$5/(1+D$4)^5+IF(D$4>$A5,Valuation!$F$5*(1+$A5)/(D$4-$A5)/(1+D$4)^5,0)+Valuation!$B$14-Valuation!$B$15)/Valuation!$B$17)*Assumptions!$E$22*Assumptions!$E$23 -> 651.44592 | E5: =((Valuation!$B$5/(1+E$4)^1+Valuation!$C$5/(1+E$4)^2+Valuation!$D$5/(1+E$4)^3+Valuation!$E$5/(1+E$4)^4+Valuation!$F$5/(1+E$4)^5+IF(E$4>$A5,Valuation!$F$5*(1+$A5)/(E$4-$A5)/(1+E$4)^5,0)+Valuation!$B$14-Valuation!$B$15)/Valuation!$B$17)*Assumptions!$E$22*Assumptions!$E$23 -> 565.78474 | F5: =((Valuation!$B$5/(1+F$4)^1+Valuation!$C$5/(1+F$4)^2+Valuation!$D$5/(1+F$4)^3+Valuation!$E$5/(1+F$4)^4+Valuation!$F$5/(1+F$4)^5+IF(F$4>$A5,Valuation!$F$5*(1+$A5)/(F$4-$A5)/(1+F$4)^5,0)+Valuation!$B$14-Valuation!$B$15)/Valuation!$B$17)*Assumptions!$E$22*Assumptions!$E$23 -> 500.36624
A6: =Assumptions!$E$21+-0.005 -> 0.025 | B6: =((Valuation!$B$5/(1+B$4)^1+Valuation!$C$5/(1+B$4)^2+Valuation!$D$5/(1+B$4)^3+Valuation!$E$5/(1+B$4)^4+Valuation!$F$5/(1+B$4)^5+IF(B$4>$A6,Valuation!$F$5*(1+$A6)/(B$4-$A6)/(1+B$4)^5,0)+Valuation!$B$14-Valuation!$B$15)/Valuation!$B$17)*Assumptions!$E$22*Assumptions!$E$23 -> 1035.5963 | C6: =((Valuation!$B$5/(1+C$4)^1+Valuation!$C$5/(1+C$4)^2+Valuation!$D$5/(1+C$4)^3+Valuation!$E$5/(1+C$4)^4+Valuation!$F$5/(1+C$4)^5+IF(C$4>$A6,Valuation!$F$5*(1+$A6)/(C$4-$A6)/(1+C$4)^5,0)+Valuation!$B$14-Valuation!$B$15)/Valuation!$B$17)*Assumptions!$E$22*Assumptions!$E$23 -> 830.2444 | D6: =((Valuation!$B$5/(1+D$4)^1+Valuation!$C$5/(1+D$4)^2+Valuation!$D$5/(1+D$4)^3+Valuation!$E$5/(1+D$4)^4+Valuation!$F$5/(1+D$4)^5+IF(D$4>$A6,Valuation!$F$5*(1+$A6)/(D$4-$A6)/(1+D$4)^5,0)+Valuation!$B$14-Valuation!$B$15)/Valuation!$B$17)*Assumptions!$E$22*Assumptions!$E$23 -> 693.47006 | E6: =((Valuation!$B$5/(1+E$4)^1+Valuation!$C$5/(1+E$4)^2+Valuation!$D$5/(1+E$4)^3+Valuation!$E$5/(1+E$4)^4+Valuation!$F$5/(1+E$4)^5+IF(E$4>$A6,Valuation!$F$5*(1+$A6)/(E$4-$A6)/(1+E$4)^5,0)+Valuation!$B$14-Valuation!$B$15)/Valuation!$B$17)*Assumptions!$E$22*Assumptions!$E$23 -> 595.87782 | F6: =((Valuation!$B$5/(1+F$4)^1+Valuation!$C$5/(1+F$4)^2+Valuation!$D$5/(1+F$4)^3+Valuation!$E$5/(1+F$4)^4+Valuation!$F$5/(1+F$4)^5+IF(F$4>$A6,Valuation!$F$5*(1+$A6)/(F$4-$A6)/(1+F$4)^5,0)+Valuation!$B$14-Valuation!$B$15)/Valuation!$B$17)*Assumptions!$E$22*Assumptions!$E$23 -> 522.77018
A7: =Assumptions!$E$21+0 -> 0.03 | B7: =((Valuation!$B$5/(1+B$4)^1+Valuation!$C$5/(1+B$4)^2+Valuation!$D$5/(1+B$4)^3+Valuation!$E$5/(1+B$4)^4+Valuation!$F$5/(1+B$4)^5+IF(B$4>$A7,Valuation!$F$5*(1+$A7)/(B$4-$A7)/(1+B$4)^5,0)+Valuation!$B$14-Valuation!$B$15)/Valuation!$B$17)*Assumptions!$E$22*Assumptions!$E$23 -> 1161.7082 | C7: =((Valuation!$B$5/(1+C$4)^1+Valuation!$C$5/(1+C$4)^2+Valuation!$D$5/(1+C$4)^3+Valuation!$E$5/(1+C$4)^4+Valuation!$F$5/(1+C$4)^5+IF(C$4>$A7,Valuation!$F$5*(1+$A7)/(C$4-$A7)/(1+C$4)^5,0)+Valuation!$B$14-Valuation!$B$15)/Valuation!$B$17)*Assumptions!$E$22*Assumptions!$E$23 -> 905.8347 | D7: =((Valuation!$B$5/(1+D$4)^1+Valuation!$C$5/(1+D$4)^2+Valuation!$D$5/(1+D$4)^3+Valuation!$E$5/(1+D$4)^4+Valuation!$F$5/(1+D$4)^5+IF(D$4>$A7,Valuation!$F$5*(1+$A7)/(D$4-$A7)/(1+D$4)^5,0)+Valuation!$B$14-Valuation!$B$15)/Valuation!$B$17)*Assumptions!$E$22*Assumptions!$E$23 -> 743.13497 | E7: =((Valuation!$B$5/(1+E$4)^1+Valuation!$C$5/(1+E$4)^2+Valuation!$D$5/(1+E$4)^3+Valuation!$E$5/(1+E$4)^4+Valuation!$F$5/(1+E$4)^5+IF(E$4>$A7,Valuation!$F$5*(1+$A7)/(E$4-$A7)/(1+E$4)^5,0)+Valuation!$B$14-Valuation!$B$15)/Valuation!$B$17)*Assumptions!$E$22*Assumptions!$E$23 -> 630.60061 | F7: =((Valuation!$B$5/(1+F$4)^1+Valuation!$C$5/(1+F$4)^2+Valuation!$D$5/(1+F$4)^3+Valuation!$E$5/(1+F$4)^4+Valuation!$F$5/(1+F$4)^5+IF(F$4>$A7,Valuation!$F$5*(1+$A7)/(F$4-$A7)/(1+F$4)^5,0)+Valuation!$B$14-Valuation!$B$15)/Valuation!$B$17)*Assumptions!$E$22*Assumptions!$E$23 -> 548.16131
A8: =Assumptions!$E$21+0.005 -> 0.035 | B8: =((Valuation!$B$5/(1+B$4)^1+Valuation!$C$5/(1+B$4)^2+Valuation!$D$5/(1+B$4)^3+Valuation!$E$5/(1+B$4)^4+Valuation!$F$5/(1+B$4)^5+IF(B$4>$A8,Valuation!$F$5*(1+$A8)/(B$4-$A8)/(1+B$4)^5,0)+Valuation!$B$14-Valuation!$B$15)/Valuation!$B$17)*Assumptions!$E$22*Assumptions!$E$23 -> 1329.8574 | C8: =((Valuation!$B$5/(1+C$4)^1+Valuation!$C$5/(1+C$4)^2+Valuation!$D$5/(1+C$4)^3+Valuation!$E$5/(1+C$4)^4+Valuation!$F$5/(1+C$4)^5+IF(C$4>$A8,Valuation!$F$5*(1+$A8)/(C$4-$A8)/(1+C$4)^5,0)+Valuation!$B$14-Valuation!$B$15)/Valuation!$B$17)*Assumptions!$E$22*Assumptions!$E$23 -> 1000.3226 | D8: =((Valuation!$B$5/(1+D$4)^1+Valuation!$C$5/(1+D$4)^2+Valuation!$D$5/(1+D$4)^3+Valuation!$E$5/(1+D$4)^4+Valuation!$F$5/(1+D$4)^5+IF(D$4>$A8,Valuation!$F$5*(1+$A8)/(D$4-$A8)/(1+D$4)^5,0)+Valuation!$B$14-Valuation!$B$15)/Valuation!$B$17)*Assumptions!$E$22*Assumptions!$E$23 -> 802.73285 | E8: =((Valuation!$B$5/(1+E$4)^1+Valuation!$C$5/(1+E$4)^2+Valuation!$D$5/(1+E$4)^3+Valuation!$E$5/(1+E$4)^4+Valuation!$F$5/(1+E$4)^5+IF(E$4>$A8,Valuation!$F$5*(1+$A8)/(E$4-$A8)/(1+E$4)^5,0)+Valuation!$B$14-Valuation!$B$15)/Valuation!$B$17)*Assumptions!$E$22*Assumptions!$E$23 -> 671.11053 | F8: =((Valuation!$B$5/(1+F$4)^1+Valuation!$C$5/(1+F$4)^2+Valuation!$D$5/(1+F$4)^3+Valuation!$E$5/(1+F$4)^4+Valuation!$F$5/(1+F$4)^5+IF(F$4>$A8,Valuation!$F$5*(1+$A8)/(F$4-$A8)/(1+F$4)^5,0)+Valuation!$B$14-Valuation!$B$15)/Valuation!$B$17)*Assumptions!$E$22*Assumptions!$E$23 -> 577.17975
A9: =Assumptions!$E$21+0.01 -> 0.04 | B9: =((Valuation!$B$5/(1+B$4)^1+Valuation!$C$5/(1+B$4)^2+Valuation!$D$5/(1+B$4)^3+Valuation!$E$5/(1+B$4)^4+Valuation!$F$5/(1+B$4)^5+IF(B$4>$A9,Valuation!$F$5*(1+$A9)/(B$4-$A9)/(1+B$4)^5,0)+Valuation!$B$14-Valuation!$B$15)/Valuation!$B$17)*Assumptions!$E$22*Assumptions!$E$23 -> 1565.2662 | C9: =((Valuation!$B$5/(1+C$4)^1+Valuation!$C$5/(1+C$4)^2+Valuation!$D$5/(1+C$4)^3+Valuation!$E$5/(1+C$4)^4+Valuation!$F$5/(1+C$4)^5+IF(C$4>$A9,Valuation!$F$5*(1+$A9)/(C$4-$A9)/(1+C$4)^5,0)+Valuation!$B$14-Valuation!$B$15)/Valuation!$B$17)*Assumptions!$E$22*Assumptions!$E$23 -> 1121.807 | D9: =((Valuation!$B$5/(1+D$4)^1+Valuation!$C$5/(1+D$4)^2+Valuation!$D$5/(1+D$4)^3+Valuation!$E$5/(1+D$4)^4+Valuation!$F$5/(1+D$4)^5+IF(D$4>$A9,Valuation!$F$5*(1+$A9)/(D$4-$A9)/(1+D$4)^5,0)+Valuation!$B$14-Valuation!$B$15)/Valuation!$B$17)*Assumptions!$E$22*Assumptions!$E$23 -> 875.5747 | E9: =((Valuation!$B$5/(1+E$4)^1+Valuation!$C$5/(1+E$4)^2+Valuation!$D$5/(1+E$4)^3+Valuation!$E$5/(1+E$4)^4+Valuation!$F$5/(1+E$4)^5+IF(E$4>$A9,Valuation!$F$5*(1+$A9)/(E$4-$A9)/(1+E$4)^5,0)+Valuation!$B$14-Valuation!$B$15)/Valuation!$B$17)*Assumptions!$E$22*Assumptions!$E$23 -> 718.98589 | F9: =((Valuation!$B$5/(1+F$4)^1+Valuation!$C$5/(1+F$4)^2+Valuation!$D$5/(1+F$4)^3+Valuation!$E$5/(1+F$4)^4+Valuation!$F$5/(1+F$4)^5+IF(F$4>$A9,Valuation!$F$5*(1+$A9)/(F$4-$A9)/(1+F$4)^5,0)+Valuation!$B$14-Valuation!$B$15)/Valuation!$B$17)*Assumptions!$E$22*Assumptions!$E$23 -> 610.66257

Sheet Checks
A1: Formula-driven model checks
A2: Critical checks must pass after native recalculation/reopen; source coverage is computed, never hardcoded.
A4: Assertion | B4: Actual | C4: Expected | D4: Difference | E4: Tolerance | F4: Status | G4: Severity | H4: Fix hint
A5: Source records verified | B5: =COUNTIF(Sources!$Q$5:$Q$97,"VERIFIED") -> 93 | C5: =COUNTA(Sources!$A$5:$A$97) -> 93 | D5: =B5-C5 -> 0 | E5: 0 | F5: =IF(AND(D5=0,C5>0),"PASS","FAIL") -> PASS | G5: Critical | H5: Complete missing ledger rows
A6: Historical source coverage | B6: =COUNTIF(Historical!$H$5:$H$20,"CHECK") -> 0 | C6: 0 | D6: =B6-C6 -> 0 | E6: 0 | F6: =IF(ABS(D6)<=E6,"PASS","FAIL") -> PASS | G6: Critical | H6: Resolve metric-to-source mapping
A7: Revenue driver tie | B7: =Forecast!G8 -> 49418.387 | C7: =Forecast!G5*Forecast!G6+Forecast!G7 -> 49418.387 | D7: =B7-C7 -> 0 | E7: 0.1 | F7: =IF(ABS(D7)<=E7,"PASS","FAIL") -> PASS | G7: Critical | H7: Repair bottom-up formula
A8: Operating income tie | B8: =Forecast!G16 -> 17938.874 | C8: =Forecast!G11-Forecast!G13-Forecast!G15 -> 17938.874 | D8: =B8-C8 -> 0 | E8: 0.1 | F8: =IF(ABS(D8)<=E8,"PASS","FAIL") -> PASS | G8: Critical | H8: Repair operating formula
A9: FCFF tie | B9: =Forecast!G25 -> 15396.98 | C9: =Forecast!G19+Forecast!G21-Forecast!G23-Forecast!G24 -> 15396.98 | D9: =B9-C9 -> 0 | E9: 0.1 | F9: =IF(ABS(D9)<=E9,"PASS","FAIL") -> PASS | G9: Critical | H9: Repair FCFF formula
A10: WACC exceeds terminal growth | B10: =Assumptions!E20 -> 0.085 | C10: =Assumptions!E21 -> 0.03 | D10: =B10-C10 -> 0.055 | E10: 0 | F10: =IF(D10>E10,"PASS","FAIL") -> PASS | G10: Critical | H10: Adjust WACC / g
A11: Valuation bridge | B11: =Valuation!B16 -> 251878.32 | C11: =Valuation!B13+Valuation!B14-Valuation!B15 -> 251878.32 | D11: =B11-C11 -> 0 | E11: 0.1 | F11: =IF(ABS(D11)<=E11,"PASS","FAIL") -> PASS | G11: Critical | H11: Repair bridge
A12: Sensitivity center tie | B12: =Sensitivity!D7 -> 743.13497 | C12: =Valuation!B21 -> 743.13497 | D12: =B12-C12 -> 0 | E12: 0.1 | F12: =IF(ABS(D12)<=E12,"PASS","FAIL") -> PASS | G12: Critical | H12: Repair matrix
A13: Scenario selector valid | B13: =Assumptions!B3 -> 1 | C13: 1 | D13: =IF(OR(B13=1,B13=2,B13=3),0,1) -> 0 | E13: 0 | F13: =IF(D13=0,"PASS","FAIL") -> PASS | G13: Critical | H13: Reset 1/2/3
A14: Forecast revenue non-negative | B14: =MIN(Forecast!C8:G8) -> 35995.216 | C14: 0 | D14: =B14-C14 -> 35995.216 | E14: 0 | F14: =IF(D14>=0,"PASS","FAIL") -> PASS | G14: Critical | H14: Review drivers
A15: Cash and debt non-negative | B15: =MIN(Forecast!B26:G27) -> 2709 | C15: 0 | D15: =B15-C15 -> 2709 | E15: 0 | F15: =IF(D15>=0,"PASS","FAIL") -> PASS | G15: Critical | H15: Review balances
A16: Traded-security price positive | B16: =Valuation!B21 -> 743.13497 | C16: 0 | D16: =B16-C16 -> 743.13497 | E16: 0 | F16: =IF(D16>0,"PASS","FAIL") -> PASS | G16: Critical | H16: Review FX / ADR bridge
A17: Semantic KPI links | B17: 8 | C17: 8 | D17: =B17-C17 -> 0 | E17: 0 | F17: =IF(AND(ABS(Sector_KPIs!D5-Forecast!G5*Forecast!G6)<0.1,ABS(Sector_KPIs!D6-Forecast!G7)<0.1,ABS(Sector_KPIs!D7-Forecast!G5)<0.1,ABS(Sector_KPIs!D8-Forecast!G6)<0.1,ISTEXT(Sector_KPIs!D9),ABS(Sector_KPIs!D10-Forecast!G10)<0.000001,ABS(Sector_KPIs!D11-Forecast!C8)<0.1,ABS(Sector_KPIs!D12-Forecast!C8)<0.1),"PASS","FAIL") -> PASS | G17: Critical | H17: Repair company-specific KPI links
A18: KPI unit / range sanity | B18: =1 -> 1 | C18: =1 -> 1 | D18: =B18-C18 -> 0 | E18: 0 | F18: =IF(AND(Sector_KPIs!B5>0,Sector_KPIs!B6>0,Sector_KPIs!B7>0,Sector_KPIs!B8>0,Sector_KPIs!B9>0,Sector_KPIs!B10>=0,Sector_KPIs!B10<=1,Sector_KPIs!B11>0,Sector_KPIs!B12>=Sector_KPIs!B11,Sector_KPIs!D5>0,Sector_KPIs!D6>0,Sector_KPIs!D7>0,Sector_KPIs!D8>0,Sector_KPIs!D10>=0,Sector_KPIs!D10<=1,Sector_KPIs!D11>0,Sector_KPIs!D12>0),"PASS","FAIL") -> PASS | G18: Critical | H18: Repair units or economic ranges
A19: Source target-cell link coverage | B19: =COUNTA(Sources!$L$5:$L$97) -> 93 | C19: =COUNTA(Sources!$A$5:$A$97) -> 93 | D19: =B19-C19 -> 0 | E19: 0 | F19: =IF(ABS(D19)<=E19,"PASS","FAIL") -> PASS | G19: Critical | H19: Add exact sheet-and-cell targets
A20: Source unit completeness | B20: =COUNTBLANK(Sources!$E$5:$E$97) -> 0 | C20: 0 | D20: =B20-C20 -> 0 | E20: 0 | F20: =IF(ABS(D20)<=E20,"PASS","FAIL") -> PASS | G20: Critical | H20: Populate source units
A21: Exact source URL completeness | B21: =COUNTA(Sources!$N$5:$N$97) -> 93 | C21: =COUNTA(Sources!$A$5:$A$97) -> 93 | D21: =B21-C21 -> 0 | E21: 0 | F21: =IF(ABS(D21)<=E21,"PASS","FAIL") -> PASS | G21: Critical | H21: Use exact primary-source URLs
A23: Overall gate | B23: =IF(COUNTIF(F5:F21,"FAIL")=0,"PASS","FAIL") -> PASS
A24: Decision use | B24: Owner-ready only after independent review

Sheet Sector_KPIs
A1: Semiconductor operating KPI framework
A2: Reported sector drivers plus formula-linked active outputs; no generic blanks.
A4: KPI | B4: Reported latest | C4: Unit | D4: Forecast / active output | E4: Source / method | F4: Status
A5: Net system sales | B5: 24474.3 | C5: EURm | D5: =Forecast!G5*Forecast!G6 -> 37101.871 | E5: Official FY2025 annual report | F5: =IF(COUNTIF(Sources!$L$5:$L$97,"Sector_KPIs!B5")>=1,"VERIFIED","CHECK") -> VERIFIED
A6: Installed Base Management sales | B6: 8193 | C6: EURm | D6: =Forecast!G7 -> 12316.516 | E6: Official FY2025 annual report | F6: =IF(COUNTIF(Sources!$L$5:$L$97,"Sector_KPIs!B6")>=1,"VERIFIED","CHECK") -> VERIFIED
A7: Systems sold | B7: 535 | C7: systems | D7: =Forecast!G5 -> 666.68826 | E7: 48 EUV + 279 DUV + 208 metrology/inspection | F7: =IF(COUNTIF(Sources!$L$5:$L$97,"Sector_KPIs!B7")>=1,"VERIFIED","CHECK") -> VERIFIED
A8: Average revenue / system | B8: =IF(B7<>0,B5/B7,0) -> 45.746355 | C8: EURm / system | D8: =Forecast!G6 -> 55.651004 | E8: Formula-derived from net system sales and systems sold | F8: =IF(COUNTIF(Sources!$L$5:$L$97,"Sector_KPIs!B8")>=1,"VERIFIED","CHECK") -> VERIFIED
A9: Year-end backlog | B9: 38797 | C9: EURm | D9: ="Context only / reported backlog" -> Context only / reported backlog | E9: Official FY2025 annual report | F9: =IF(COUNTIF(Sources!$L$5:$L$97,"Sector_KPIs!B9")>=1,"VERIFIED","CHECK") -> VERIFIED
A10: Gross margin | B10: 0.528 | C10: % | D10: =Forecast!G10 -> 0.545 | E10: Official FY2025 annual report | F10: =IF(COUNTIF(Sources!$L$5:$L$97,"Sector_KPIs!B10")>=1,"VERIFIED","CHECK") -> VERIFIED
A11: 2026 revenue guidance low | B11: 34000 | C11: EURm | D11: =Forecast!C8 -> 35995.216 | E11: Official Q4 FY2025 results | F11: =IF(COUNTIF(Sources!$L$5:$L$97,"Sector_KPIs!B11")>=1,"VERIFIED","CHECK") -> VERIFIED
A12: 2026 revenue guidance high | B12: 39000 | C12: EURm | D12: =Forecast!C8 -> 35995.216 | E12: Official Q4 FY2025 results | F12: =IF(COUNTIF(Sources!$L$5:$L$97,"Sector_KPIs!B12")>=1,"VERIFIED","CHECK") -> VERIFIED

Sheet Change_Log
A1: Change log and governance
A2: Controlled rebuild; prior workbook preserved unchanged.
A4: Date | B4: Version | C4: Author | D4: Change | E4: Evidence | F4: Reviewer status | G4: Disposition
A5: 2026-07-16 | B5: 2.0 | C5: Codex | D5: Preserved prior ten sheets; appended Gate_9of10 | E5: Prior SHA-256 20c141773a2c775de7cfa826f5a62e4986727cdbe8baf5a5e6f46e579487e3eb | F5: Builder verified | G5: No overwrite
A6: 2026-07-16 | B6: 2.0 | C6: Codex | D6: Native-currency exact-source history | E6: Sources + Historical | F6: Builder verified | G6: Independent review pending
A7: 2026-07-16 | B7: 2.0 | C7: Codex | D7: Company-specific forecast, DCF, sensitivity and checks | E7: Forecast + Valuation + Checks | F7: Builder verified | G7: Independent review pending
A8: 2026-07-16 | B8: 2.0 | C8: Codex | D8: Native recalc/reopen and full-sheet QA | E8: internal QA evidence (not published) | F8: Post-LO evidence | G8: Independent review pending
A9: 2026-07-16 | B9: 2.1 | C9: Codex | D9: Repaired KPI semantics, exact source targets, unit/range/link gates and TSMC H1/H2/H5 | E9: Sector_KPIs + Sources + Checks + Gate_9of10 | F9: High-effort repair; independent review pending | G9: Frozen only after native recalc and hash-bound QA
A10: 46224 | B10: 2.2 | C10: Claude (run 24e4a1f1) | D10: Ola 2 elevation: added IS_Hist/CF_Hist (FY2022A-25A), BS_Hist/SCE_Hist (FY2023A-25A) full line-item audited statements, Checks_TieOut (cross-statement + dual-filing consistency), Sources_Audited. Fixed Forecast!C26:G26 frozen cash/debt defect — cash now rolls forward via FCFF less a documented payout-ratio driver (Assumptions!E26); debt kept flat under an explicit documented assumption (Assumptions!B27), not a bare self-reference. | E10: Sources: 20-F_2025-12-31 (accn 0001628280-26-011378) R3/R4/R6/R7/R8/R10/R11; 20-F_2024-12-31_Financial_Report.xlsx; companyfacts.json | F10: Builder verified | G10: Independent review pending; FY2021A-22A BS and FY2021A IS/CF full line-item detail remain a documented gap (PARTIAL), not fabricated
A11: 2026-08-14 | B11: 2.3 | C11: Claude (builder de cobertura, Ola 1 flota internacional) | D11: Capa de cobertura aditiva segun plantilla Apple: hojas nuevas Drivers_MDA (drivers del 20-F FY2021A-FY2025A: lineas de negocio, tecnologia/unidades/ASP, end-use, geografia, long-lived assets, backlog/RPO/contract liabilities, clientes, empleados, FX, deuda, retornos, guidance, NOT_AVAILABLE, puente al Forecast) y Market_Package (doble cotizacion EUR/USD fechada, puente a EV, WACC fechado, multiplos, implicitos del DCF, control de procedencia, anclas de extraccion independiente); 26 tie-outs nuevos en Checks_TieOut filas 36-61. UNICA celda preexistente modificada: Checks_TieOut!B2 (rango del COUNTIF ampliado J5:J33 -> J5:J61 — endurece el gate). Forecast intacto (fuera de alcance de la ola). | E11: Respaldo pre-cobertura SHA-256 5e7a68fb8aa65786786f32c5b4de1bbd22d8ae619d2b088df22193c2427751ef; fuentes: 20-F FY2021-FY2025 locales (asml/) + mercado fechado 2026-08-13/14 | F11: Builder verificado; refutacion independiente pendiente | G11: NOTA de gobernanza: Checks_TieOut NO esta cableado a Checks!B23 ni a Gate_9of10 (hallazgo M1 heredado del patron de flota); el MASTER de esta hoja es el gate de la capa. Cablearlo requiere tocar Checks — fuera del alcance de esta capa.

Sheet Gate_9of10
A1: 9-of-10 gate evidence
A2: Owner evidence register aligned exactly to the governing independent rubric; PASS means ready for review, not self-certification.
A4: Gate | B4: Weight | C4: Earned | D4: Status | E4: Exact workbook / external evidence | F4: Blocker class | G4: Notes
A5: H0 Controlled lineage / package | B5: 5 | C5: =IF(D5="PASS",B5,0) -> 5 | D5: PASS | E5: Change_Log!A5:G5; internal QA evidence (not published) | F5: Lineage | G5: Prior file preserved; 10-sheet order + Gate_9of10
A6: H1 Source fidelity | B6: 20 | C6: =IF(D6="PASS",B6,0) -> 20 | D6: =IF(AND(Checks!F5="PASS",Checks!F6="PASS",COUNTIF(Checks!F19:F21,"FAIL")=0),"PASS","FAIL") -> PASS | E6: Sources!A4:R; Checks!A5:F6; Checks!A19:F21 | F6: Source | G6: Claim-level exact-source ledger
A7: H2 Historical / formula / schedule mechanics | B7: 15 | C7: =IF(D7="PASS",B7,0) -> 15 | D7: =IF(AND(COUNTIF(Historical!H5:H20,"CHECK")=0,COUNTIF(Checks!F7:F9,"FAIL")=0,Checks!F17="PASS",Checks!F18="PASS"),"PASS","FAIL") -> PASS | E7: Historical!A4:H20; Forecast!A5:G28; Sector_KPIs!A4:F12; Checks!A7:F9; Checks!A17:F18 | F7: Mechanics | G7: Native history and formula-driven operating schedule
A8: H3 Scenario / sensitivity | B8: 10 | C8: =IF(D8="PASS",B8,0) -> 10 | D8: =IF(AND(Checks!F12="PASS",Checks!F13="PASS"),"PASS","FAIL") -> PASS | E8: Assumptions!B3:E24; Sensitivity!A4:F9; Checks!A12:F13 | F8: Scenario | G8: B/B/B perturb-reset evidence in support JSON
A9: H4 Valuation fit / mechanics | B9: 15 | C9: =IF(D9="PASS",B9,0) -> 15 | D9: =IF(AND(Checks!F10="PASS",Checks!F11="PASS",Checks!F12="PASS",Valuation!B21>0),"PASS","FAIL") -> PASS | E9: Valuation!A4:G23; Checks!A10:F12 | F9: Valuation | G9: Native-currency DCF and dated security bridge
A10: H5 Checks / error state | B10: 8 | C10: =IF(D10="PASS",B10,0) -> 8 | D10: =IF(Checks!B23="PASS","PASS","FAIL") -> PASS | E10: Checks!A4:H23; internal QA evidence (not published) | F10: Checks | G10: All critical checks and post-recalc error scan
A11: H6 Native recalc / reproducibility | B11: 10 | C11: =IF(D11="PASS",B11,0) -> 10 | D11: PASS | E11: internal QA evidence (not published) | native LibreOffice x2 + reopen | F11: Recalc | G11: Two unique LibreOffice profiles; evidence bound to final SHA-256
A12: H7 Post-recalc visual QA | B12: 7 | C12: =IF(D12="PASS",B12,0) -> 7 | D12: PASS | E12: internal QA evidence (not published) | F12: Visual | G12: Every final sheet rendered and reviewed
A13: H8 Economic upgrade | B13: 5 | C13: =IF(D13="PASS",B13,0) -> 5 | D13: =IF(AND(Forecast!G8>0,COUNTIF(Sector_KPIs!F5:F12,"VERIFIED")=8,Checks!F17="PASS",Checks!F18="PASS"),"PASS","FAIL") -> PASS | E13: Forecast!A5:G28; Sector_KPIs!A4:F | F13: Economics | G13: Company-specific semiconductor operating build
A14: H9 Governance / handoff | B14: 5 | C14: =IF(D14="PASS",B14,0) -> 5 | D14: PASS | E14: 00_Cover!A14:B18; Change_Log!A4:G8; Gate_9of10!A16:B18 | F14: Governance | G14: Independent certification remains pending
A16: Owner score | B16: =SUM(C5:C14) -> 100
A17: Decision | B17: =IF(AND(B16>=90,COUNTIF(D5:D14,"FAIL")=0),"READY FOR INDEPENDENT 9/10 REVIEW","OWNER DEMOTION / REMEDIATE") -> READY FOR INDEPENDENT 9/10 REVIEW
A18: Independent certification | B18: PENDING

Sheet IS_Hist
A1: ASML Holding N.V. — Consolidated Statements of Operations (audited, as published)
A2: EUR millions, shares in millions. FY2022A-FY2024A per 20-F_2024-12-31 Financial_Report.xlsx; FY2023A-FY2025A per 20-F_2025-12-31 R3/R4 (FY2023A & FY2024A byte-identical across both filings — verified in Checks_TieOut).
A4: Line item | B4: FY2022A | C4: FY2023A | D4: FY2024A | E4: FY2025A | G4: Note ref
A5: Total net sales | B5: 21173.4 | C5: 27558.5 | D5: 28262.9 | E5: 32667.3
A6: Total cost of sales | B6: -10473.3 | C6: -13422.4 | D6: -13770.9 | E6: -15409.3 | G6: 1
A7: Gross profit | B7: 10700.1 | C7: 14136.1 | D7: 14492 | E7: 17258
A8: Research and development (R&D) costs | B8: -3253.5 | C8: -3980.6 | D8: -4303.7 | E8: -4698.8
A9: Selling, general and administrative (SG&A) costs | B9: -945.9 | C9: -1113.2 | D9: -1165.7 | E9: -1257.8
A10: Income from operations | B10: 6500.7 | C10: 9042.3 | D10: 9022.6 | E10: 11301.4
A11: Interest and other, net | B11: -44.6 | C11: 41.2 | D11: 19.8 | E11: 104.7
A12: Income before income taxes | B12: 6456.1 | C12: 9083.5 | D12: 9042.4 | E12: 11406.1
A13: Income tax expense | B13: -969.9 | C13: -1435.8 | D13: -1680.6 | E13: -2013.4
A14: Income after income taxes | B14: 5486.2 | C14: 7647.7 | D14: 7361.8 | E14: 9392.7
A15: Profit from equity method investments | B15: 138 | C15: 191.3 | D15: 209.8 | E15: 216.7
A16: Net income | B16: 5624.2 | C16: 7839 | D16: 7571.6 | E16: 9609.4
A17: Basic net income per ordinary share (EUR) | B17: 14.14 | C17: 19.91 | D17: 19.25 | E17: 24.73
A18: Diluted net income per ordinary share (EUR) | B18: 14.13 | C18: 19.89 | D18: 19.24 | E18: 24.71
... A20: Diluted weighted-average shares (mm) | B20: 398 | C20: 394.1 | D20: 393.6 | E20: 388.9
A22: Memo — net sales by category
A23: Net system sales | B23: 15430.3 | C23: 21938.6 | D23: 21768.7 | E23: 24474.3
A24: Net system cost of sales | B24: -7582.3 | C24: -10151 | D24: -10406.9 | E24: -11384
A25: Net service and field option sales | B25: 5743.1 | C25: 5619.9 | D25: 6494.2 | E25: 8193
A26: Net service and field option cost of sales | B26: -2891 | C26: -3271.4 | D26: -3364 | E26: -4025.3

Sheet CF_Hist
A1: ASML Holding N.V. — Consolidated Statements of Cash Flows (audited, as published)
A2: EUR millions. Same dual-filing source basis as IS_Hist; signs as published (outflows negative). Blank/0.0 = line not presented that year in the source filing.
A4: Line item | B4: FY2022A | C4: FY2023A | D4: FY2024A | E4: FY2025A | G4: Note ref
A5: Net income | B5: 5624.2 | C5: 7839 | D5: 7571.6 | E5: 9609.4
A6: Adjustments to reconcile net income to operating cash flows:
A7: Depreciation and amortization | B7: 583.6 | C7: 739.8 | D7: 918.6 | E7: 1025.9 | G7: 1
A8: Impairment and loss on disposal | B8: 39.3 | C8: 37.5 | D8: 35.8 | E8: 49.7
A9: Share-based compensation expense | B9: 68.9 | C9: 134.8 | D9: 172.6 | E9: 202.3
A10: Inventory reserves | B10: 278.5 | C10: 485.3 | D10: 554.7 | E10: 469.4
A11: Deferred tax expense (benefit) | B11: -564.2 | C11: -133.6 | D11: -144.8 | E11: 180.7
A12: Equity method investments | B12: 15.3 | C12: 4.2 | D12: 4.4 | E12: 94.6 | G12: 2
A13: Changes in assets and liabilities:
A14: Accounts receivable, net | B14: -2338 | C14: 959.9 | D14: -139.9 | E14: 1415.5
A15: Finance receivables, net | B15: 212.2 | C15: -88.6 | D15: 1038.7 | E15: -227.2
A16: Inventories | B16: -2080.9 | C16: -1646.9 | D16: -1860.9 | E16: -832.5
A17: Other assets | B17: -864.3 | C17: -344.3 | D17: -1299 | E17: -561.9
A18: Accrued and other liabilities | B18: 439.7 | C18: 222 | D18: 625.5 | E18: -237.3
A19: Accounts payable | B19: 406.2 | C19: -261.7 | D19: 1127.6 | E19: 13.4
A20: Current tax assets and liabilities | B20: 33.6 | C20: -939.4 | D20: 689.5 | E20: 334.1
A21: Contract assets and liabilities | B21: 6632.7 | C21: -1564.6 | D21: 1871.8 | E21: 1122.4
A22: Net cash provided by operating activities | B22: 8486.8 | C22: 5443.4 | D22: 11166.2 | E22: 12658.5
A23: Investing activities
A24: Purchase of property, plant and equipment | B24: -1281.8 | C24: -2155.6 | D24: -2067.2 | E24: -1573.6 | G24: 3
A25: Purchase of intangible assets | B25: -37.5 | C25: -40.6 | D25: -15.9 | E25: -57.6
A26: Purchase of short-term investments | B26: -334.3 | C26: -23.6 | D26: -305.2 | E26: -406.2
A27: Maturity of short-term investments | B27: 864.7 | C27: 125.6 | D27: 305.2 | E27: 5.3
A28: Purchase of equity investments | B28: 0 | C28: 0 | D28: 0 | E28: -1302.2
A29: Loans issued and other investments | B29: -240 | C29: -561.5 | D29: -526.2 | E29: -703.7 | G29: 4
A30: Repayment on loans | B30: 0 | C30: 0 | D30: 0 | E30: 260.2
A31: Acquisition of subsidiaries (net of cash acquired) | B31: 0 | C31: -33.6 | D31: 0 | E31: 0
A32: Net cash used in investing activities | B32: -1028.9 | C32: -2689.3 | D32: -2609.3 | E32: -3777.8
A33: Financing activities
A34: Dividend paid | B34: -2559.8 | C34: -2348.3 | D34: -2452.9 | E34: -2550.3
A35: Purchase of treasury shares | B35: -4639.7 | C35: -1000 | D35: -500 | E35: -5950
A36: Net proceeds from issuance of shares | B36: 81.8 | C36: 99.4 | D36: 124 | E36: 142.3
A37: Net proceeds from issuance of notes / borrowings | B37: 495.6 | C37: 997.8 | D37: 22.5 | E37: 754.2
A38: Repayment of debt and finance lease obligations | B38: -516.2 | C38: -752.8 | D38: -25.7 | E38: -1066.7
A39: Net cash used in financing activities | B39: -7138.3 | C39: -3003.9 | D39: -2832.1 | E39: -8670.5
A40: Net cash flows | B40: 319.6 | C40: -249.8 | D40: 5724.8 | E40: 210.2
A41: Effect of foreign exchange rate changes | B41: -3.1 | C41: -13.8 | D41: 6.4 | E41: -30.1
A42: Net increase (decrease) in cash and cash equivalents | B42: 316.5 | C42: -263.6 | D42: 5731.2 | E42: 180.1
A43: Cash and cash equivalents — beginning of the year | B43: 6951.8 | C43: 7268.3 | D43: 7004.7 | E43: 12735.9
A44: Cash and cash equivalents — end of the year | B44: 7268.3 | C44: 7004.7 | D44: 12735.9 | E44: 12916
A46: Supplemental disclosures
A47: Unpaid PP&E in accounts payable (non-cash) | B47: 50.3 | C47: 49.3 | D47: 23.6 | E47: 22.3
A48: Interest received | B48: 42.4 | C48: 190.8 | D48: 169.5 | E48: 201.3
A49: Interest paid | B49: -82.2 | C49: -137.8 | D49: -160 | E49: -114.5
A50: Income taxes paid, net of refunds | B50: -1734.6 | C50: -2568.3 | D50: -1098 | E50: -1621.4

Sheet BS_Hist
A1: ASML Holding N.V. — Consolidated Balance Sheets (audited, as published)
A2: EUR millions, as of December 31. FY2023A-FY2024A per 20-F_2024-12-31 Financial_Report.xlsx; FY2024A-FY2025A per 20-F_2025-12-31 R6/R7 (FY2024A byte-identical across both filings). FY2021A-FY2022A full line-item BS not in this source package — documented gap; Historical!B15:C19 retains the previously verified 5-yr summary aggregates unchanged.
A4: Line item | B4: FY2023A | C4: FY2024A | D4: FY2025A | F4: Note ref
A5: Assets
A6: Cash and cash equivalents | B6: 7004.7 | C6: 12735.9 | D6: 12916
A7: Short-term investments | B7: 5.4 | C7: 5.4 | D7: 405.9
A8: Accounts receivable, net | B8: 4334.1 | C8: 4477.5 | D8: 3023 | F8: 1
A9: Finance receivables, net (current) | B9: 1379.2 | C9: 82.6 | D9: 613.5
A10: Current tax assets | B10: 1001.2 | C10: 283.6 | D10: 88.9
A11: Contract assets | B11: 240.1 | C11: 320.6 | D11: 440.6
A12: Inventories, net | B12: 8850.7 | C12: 10891.5 | D12: 11429.3
A13: Loans receivable (current) | B13: 0 | C13: 0 | D13: 266.1 | F13: 2
A14: Other assets (current) | B14: 1578.5 | C14: 1940.3 | D14: 1432.8 | F14: 3
A15: Total current assets | B15: 24393.9 | C15: 30737.4 | D15: 30616.1
A16: Finance receivables, net (non-current) | B16: 60.6 | C16: 317.2 | D16: 13.3
A17: Deferred tax assets | B17: 1872.3 | C17: 1940.7 | D17: 1719.4
A18: Loans receivable (non-current) | B18: 929.2 | C18: 1456.6 | D18: 1653.9 | F18: 4
A19: Other assets (non-current) | B19: 651.8 | C19: 790.8 | D19: 1057.1 | F19: 5
A20: Equity investments | B20: 0 | C20: 0 | D20: 1320.7
A21: Equity method investments | B21: 919.6 | C21: 903 | D21: 822.6
A22: Goodwill | B22: 4588.6 | C22: 4588.6 | D22: 4588.6
A23: Other intangible assets, net | B23: 741.7 | C23: 621.3 | D23: 540.1
A24: Property, plant and equipment, net | B24: 5493.2 | C24: 6846.8 | D24: 7893.8
A25: Right-of-use assets | B25: 306.6 | C25: 387.2 | D25: 341
A26: Total non-current assets | B26: 15563.6 | C26: 17852.2 | D26: 19950.5
A27: Total assets | B27: 39957.5 | C27: 48589.6 | D27: 50566.6
A28: Liabilities and shareholders’ equity
A29: Accounts payable | B29: 2347.3 | C29: 3500.4 | D29: 3521.8 | F29: 6
A30: Accrued and other liabilities (current) | B30: 2177.4 | C30: 2686.6 | D30: 2567.3 | F30: 7
A31: Current tax liabilities | B31: 308.9 | C31: 283.3 | D31: 486.6
A32: Short-term borrowings / current portion of long-term debt | B32: 0.1 | C32: 1010.3 | D32: 1681.9
A33: Contract liabilities (current) | B33: 11441 | C33: 12570.8 | D33: 16006.3
A34: Total current liabilities | B34: 16274.7 | C34: 20051.4 | D34: 24263.9
A35: Long-term debt | B35: 4631.5 | C35: 3677.3 | D35: 2709
A36: Deferred and other income tax liabilities | B36: 372.2 | C36: 299.2 | D36: 183
A37: Contract liabilities (non-current) | B37: 4825.5 | C37: 5625.4 | D37: 3366.3
A38: Accrued and other liabilities (non-current) | B38: 401.2 | C38: 459.5 | D38: 432.2
A39: Total non-current liabilities | B39: 10230.4 | C39: 10061.4 | D39: 6690.5
A40: Total liabilities | B40: 26505.1 | C40: 30112.8 | D40: 30954.4 | F40: 8
A41: Issued and outstanding shares (par value) | B41: 36 | C41: 35.4 | D41: 34.9
A42: Share premium | B42: 3998.1 | C42: 4049 | D42: 4107.1
A43: Treasury shares at cost | B43: -3306.2 | C43: -476 | D43: -2252.9
A44: Retained earnings | B44: 12379.5 | C44: 14414.3 | D44: 17587.3
A45: Accumulated other comprehensive income | B45: 345 | C45: 454.1 | D45: 135.8
A46: Total shareholders’ equity | B46: 13452.4 | C46: 18476.8 | D46: 19612.2
A47: Total liabilities and shareholders’ equity | B47: 39957.5 | C47: 48589.6 | D47: 50566.6

Sheet SCE_Hist
A1: ASML Holding N.V. — Consolidated Statements of Shareholders’ Equity (audited, as published)
A2: EUR millions. Source: 20-F_2025-12-31 R8, rollforward from beginning balance at Dec 31, 2022 (€8,810.8mm, matches companyfacts.json us-gaap:StockholdersEquity). Each column is that fiscal year’s own movements.
A4: Line item | B4: FY2023A | C4: FY2024A | D4: FY2025A | F4: Note ref
A5: Beginning balance, total equity | B5: 8810.8 | C5: 13452.4 | D5: 18476.8
A6: Net income | B6: 7839 | C6: 7571.6 | D6: 9609.4
A7: Proportionate share of OCI from equity method investments | B7: 0.2 | C7: -12.1 | D7: 14.1
A8: Gain (loss) on foreign currency translation | B8: -68.3 | C8: 91.9 | D8: -257.8
A9: Gain (loss) on financial instruments | B9: -15.2 | C9: 29.3 | D9: -74.6
A10: Total comprehensive income | B10: 7755.7 | C10: 7680.7 | D10: 9291.1
A11: Purchase of treasury shares | B11: -1000 | C11: -500 | D11: -5950
A12: Cancellation of treasury shares (net zero, intra-equity reclass) | B12: 0 | C12: 0 | D12: 0
A13: Share-based payments | B13: 134.8 | C13: 172.6 | D13: 202.3
A14: Issuance of shares | B14: 99.4 | C14: 124 | D14: 142.3
A15: Dividend paid | B15: -2348.3 | C15: -2452.9 | D15: -2550.3
A16: Ending balance, total equity | B16: 13452.4 | C16: 18476.8 | D16: 19612.2

Sheet Checks_TieOut
A1: Tie-out checks — audited historical statements (all deltas must be 0; EUR millions)
A2: MASTER | B2: =IF(COUNTIF(J5:J61,"FAIL")=0,"OK — ALL TIE-OUTS PASS","FAIL") -> FAIL
B3: =COUNTIF(J5:J61,"PASS")&" PASS / "&(COUNTIF(J5:J61,"PASS")+COUNTIF(J5:J61,"FAIL"))&" checks" -> 54 PASS / 55 checks
A4: Check | F4: FY2022A | G4: FY2023A | H4: FY2024A | I4: FY2025A | J4: Status
A5: IS: Gross profit = Net sales − COGS | F5: =IS_Hist!B5+IS_Hist!B6-IS_Hist!B7 -> 0 | G5: =IS_Hist!C5+IS_Hist!C6-IS_Hist!C7 -> 0 | H5: =IS_Hist!D5+IS_Hist!D6-IS_Hist!D7 -> 0 | I5: =IS_Hist!E5+IS_Hist!E6-IS_Hist!E7 -> 0 | J5: =IF(AND(ABS(N(F5))<=0.5,ABS(N(G5))<=0.5,ABS(N(H5))<=0.5,ABS(N(I5))<=0.5),"PASS","FAIL") -> PASS
A6: IS: Income from ops = GP − R&D − SG&A | F6: =IS_Hist!B7+IS_Hist!B8+IS_Hist!B9-IS_Hist!B10 -> 0 | G6: =IS_Hist!C7+IS_Hist!C8+IS_Hist!C9-IS_Hist!C10 -> 0 | H6: =IS_Hist!D7+IS_Hist!D8+IS_Hist!D9-IS_Hist!D10 -> 0 | I6: =IS_Hist!E7+IS_Hist!E8+IS_Hist!E9-IS_Hist!E10 -> 0 | J6: =IF(AND(ABS(N(F6))<=0.5,ABS(N(G6))<=0.5,ABS(N(H6))<=0.5,ABS(N(I6))<=0.5),"PASS","FAIL") -> PASS
A7: IS: PBT = Ops income + interest/other | F7: =IS_Hist!B10+IS_Hist!B11-IS_Hist!B12 -> 0 | G7: =IS_Hist!C10+IS_Hist!C11-IS_Hist!C12 -> 0 | H7: =IS_Hist!D10+IS_Hist!D11-IS_Hist!D12 -> 0 | I7: =IS_Hist!E10+IS_Hist!E11-IS_Hist!E12 -> 0 | J7: =IF(AND(ABS(N(F7))<=0.5,ABS(N(G7))<=0.5,ABS(N(H7))<=0.5,ABS(N(I7))<=0.5),"PASS","FAIL") -> PASS
A8: IS: Income after tax = PBT − tax | F8: =IS_Hist!B12+IS_Hist!B13-IS_Hist!B14 -> 0 | G8: =IS_Hist!C12+IS_Hist!C13-IS_Hist!C14 -> 0 | H8: =IS_Hist!D12+IS_Hist!D13-IS_Hist!D14 -> 0 | I8: =IS_Hist!E12+IS_Hist!E13-IS_Hist!E14 -> 0 | J8: =IF(AND(ABS(N(F8))<=0.5,ABS(N(G8))<=0.5,ABS(N(H8))<=0.5,ABS(N(I8))<=0.5),"PASS","FAIL") -> PASS
A9: IS: Net income = after-tax + equity method | F9: =IS_Hist!B14+IS_Hist!B15-IS_Hist!B16 -> 0 | G9: =IS_Hist!C14+IS_Hist!C15-IS_Hist!C16 -> 0 | H9: =IS_Hist!D14+IS_Hist!D15-IS_Hist!D16 -> 0 | I9: =IS_Hist!E14+IS_Hist!E15-IS_Hist!E16 -> 0 | J9: =IF(AND(ABS(N(F9))<=0.5,ABS(N(G9))<=0.5,ABS(N(H9))<=0.5,ABS(N(I9))<=0.5),"PASS","FAIL") -> PASS
A10: IS: Net sales = system + service memo | F10: =IS_Hist!B23+IS_Hist!B25-IS_Hist!B5 -> 0 | G10: =IS_Hist!C23+IS_Hist!C25-IS_Hist!C5 -> 0 | H10: =IS_Hist!D23+IS_Hist!D25-IS_Hist!D5 -> 0 | I10: =IS_Hist!E23+IS_Hist!E25-IS_Hist!E5 -> 0 | J10: =IF(AND(ABS(N(F10))<=0.5,ABS(N(G10))<=0.5,ABS(N(H10))<=0.5,ABS(N(I10))<=0.5),"PASS","FAIL") -> PASS
A11: CF: CFO build sums to reported CFO | F11: =SUM(CF_Hist!B5:B21)-CF_Hist!B22 -> 0 | G11: =SUM(CF_Hist!C5:C21)-CF_Hist!C22 -> 0 | H11: =SUM(CF_Hist!D5:D21)-CF_Hist!D22 -> 0 | I11: =SUM(CF_Hist!E5:E21)-CF_Hist!E22 -> 0 | J11: =IF(AND(ABS(N(F11))<=0.5,ABS(N(G11))<=0.5,ABS(N(H11))<=0.5,ABS(N(I11))<=0.5),"PASS","FAIL") -> PASS
A12: CF: CFI build sums to reported CFI | F12: =SUM(CF_Hist!B24:B31)-CF_Hist!B32 -> 0 | G12: =SUM(CF_Hist!C24:C31)-CF_Hist!C32 -> 0 | H12: =SUM(CF_Hist!D24:D31)-CF_Hist!D32 -> 0 | I12: =SUM(CF_Hist!E24:E31)-CF_Hist!E32 -> 0 | J12: =IF(AND(ABS(N(F12))<=0.5,ABS(N(G12))<=0.5,ABS(N(H12))<=0.5,ABS(N(I12))<=0.5),"PASS","FAIL") -> PASS
A13: CF: CFF build sums to reported CFF | F13: =SUM(CF_Hist!B34:B38)-CF_Hist!B39 -> 0 | G13: =SUM(CF_Hist!C34:C38)-CF_Hist!C39 -> 0 | H13: =SUM(CF_Hist!D34:D38)-CF_Hist!D39 -> 0 | I13: =SUM(CF_Hist!E34:E38)-CF_Hist!E39 -> 0 | J13: =IF(AND(ABS(N(F13))<=0.5,ABS(N(G13))<=0.5,ABS(N(H13))<=0.5,ABS(N(I13))<=0.5),"PASS","FAIL") -> PASS
A14: CF: Net change = CFO+CFI+CFF | F14: =CF_Hist!B22+CF_Hist!B32+CF_Hist!B39-CF_Hist!B40 -> 0 | G14: =CF_Hist!C22+CF_Hist!C32+CF_Hist!C39-CF_Hist!C40 -> 0 | H14: =CF_Hist!D22+CF_Hist!D32+CF_Hist!D39-CF_Hist!D40 -> 0 | I14: =CF_Hist!E22+CF_Hist!E32+CF_Hist!E39-CF_Hist!E40 -> 0 | J14: =IF(AND(ABS(N(F14))<=0.5,ABS(N(G14))<=0.5,ABS(N(H14))<=0.5,ABS(N(I14))<=0.5),"PASS","FAIL") -> PASS
A15: CF: End cash = begin + change + FX | F15: =CF_Hist!B43+CF_Hist!B40+CF_Hist!B41-CF_Hist!B44 -> 0 | G15: =CF_Hist!C43+CF_Hist!C40+CF_Hist!C41-CF_Hist!C44 -> 0 | H15: =CF_Hist!D43+CF_Hist!D40+CF_Hist!D41-CF_Hist!D44 -> 0 | I15: =CF_Hist!E43+CF_Hist!E40+CF_Hist!E41-CF_Hist!E44 -> 0 | J15: =IF(AND(ABS(N(F15))<=0.5,ABS(N(G15))<=0.5,ABS(N(H15))<=0.5,ABS(N(I15))<=0.5),"PASS","FAIL") -> PASS
A16: X: CF net income = IS net income | F16: =CF_Hist!B5-IS_Hist!B16 -> 0 | G16: =CF_Hist!C5-IS_Hist!C16 -> 0 | H16: =CF_Hist!D5-IS_Hist!D16 -> 0 | I16: =CF_Hist!E5-IS_Hist!E16 -> 0 | J16: =IF(AND(ABS(N(F16))<=0.5,ABS(N(G16))<=0.5,ABS(N(H16))<=0.5,ABS(N(I16))<=0.5),"PASS","FAIL") -> PASS
A17: BS: Total current assets sum | G17: =SUM(BS_Hist!B6:B14)-BS_Hist!B15 -> 0 | H17: =SUM(BS_Hist!C6:C14)-BS_Hist!C15 -> 0 | I17: =SUM(BS_Hist!D6:D14)-BS_Hist!D15 -> 0 | J17: =IF(AND(ABS(N(G17))<=0.5,ABS(N(H17))<=0.5,ABS(N(I17))<=0.5),"PASS","FAIL") -> PASS
A18: BS: Total non-current assets sum | G18: =SUM(BS_Hist!B16:B25)-BS_Hist!B26 -> 0 | H18: =SUM(BS_Hist!C16:C25)-BS_Hist!C26 -> 0 | I18: =SUM(BS_Hist!D16:D25)-BS_Hist!D26 -> 0 | J18: =IF(AND(ABS(N(G18))<=0.5,ABS(N(H18))<=0.5,ABS(N(I18))<=0.5),"PASS","FAIL") -> PASS
A19: BS: Total assets = CA + NCA | G19: =BS_Hist!B15+BS_Hist!B26-BS_Hist!B27 -> 0 | H19: =BS_Hist!C15+BS_Hist!C26-BS_Hist!C27 -> 0 | I19: =BS_Hist!D15+BS_Hist!D26-BS_Hist!D27 -> 0 | J19: =IF(AND(ABS(N(G19))<=0.5,ABS(N(H19))<=0.5,ABS(N(I19))<=0.5),"PASS","FAIL") -> PASS
A20: BS: Total current liabilities sum | G20: =SUM(BS_Hist!B29:B33)-BS_Hist!B34 -> 0 | H20: =SUM(BS_Hist!C29:C33)-BS_Hist!C34 -> 0 | I20: =SUM(BS_Hist!D29:D33)-BS_Hist!D34 -> 0 | J20: =IF(AND(ABS(N(G20))<=0.5,ABS(N(H20))<=0.5,ABS(N(I20))<=0.5),"PASS","FAIL") -> PASS
A21: BS: Total non-current liabilities sum | G21: =SUM(BS_Hist!B35:B38)-BS_Hist!B39 -> 0 | H21: =SUM(BS_Hist!C35:C38)-BS_Hist!C39 -> 0 | I21: =SUM(BS_Hist!D35:D38)-BS_Hist!D39 -> 0 | J21: =IF(AND(ABS(N(G21))<=0.5,ABS(N(H21))<=0.5,ABS(N(I21))<=0.5),"PASS","FAIL") -> PASS
A22: BS: Total liabilities = CL + NCL | G22: =BS_Hist!B34+BS_Hist!B39-BS_Hist!B40 -> 0 | H22: =BS_Hist!C34+BS_Hist!C39-BS_Hist!C40 -> 0 | I22: =BS_Hist!D34+BS_Hist!D39-BS_Hist!D40 -> 0 | J22: =IF(AND(ABS(N(G22))<=0.5,ABS(N(H22))<=0.5,ABS(N(I22))<=0.5),"PASS","FAIL") -> PASS
A23: BS: Equity components sum | G23: =SUM(BS_Hist!B41:B45)-BS_Hist!B46 -> 0 | H23: =SUM(BS_Hist!C41:C45)-BS_Hist!C46 -> 0 | I23: =SUM(BS_Hist!D41:D45)-BS_Hist!D46 -> 0 | J23: =IF(AND(ABS(N(G23))<=0.5,ABS(N(H23))<=0.5,ABS(N(I23))<=0.5),"PASS","FAIL") -> PASS
A24: BS: TL&E = TL + TE | G24: =BS_Hist!B40+BS_Hist!B46-BS_Hist!B47 -> 0 | H24: =BS_Hist!C40+BS_Hist!C46-BS_Hist!C47 -> 0 | I24: =BS_Hist!D40+BS_Hist!D46-BS_Hist!D47 -> 0 | J24: =IF(AND(ABS(N(G24))<=0.5,ABS(N(H24))<=0.5,ABS(N(I24))<=0.5),"PASS","FAIL") -> PASS
A25: BS: Balance (TA − TL&E) | G25: =BS_Hist!B27-BS_Hist!B47 -> 0 | H25: =BS_Hist!C27-BS_Hist!C47 -> 0 | I25: =BS_Hist!D27-BS_Hist!D47 -> 0 | J25: =IF(AND(ABS(N(G25))<=0.5,ABS(N(H25))<=0.5,ABS(N(I25))<=0.5),"PASS","FAIL") -> PASS
A26: SCE: Ending = Begin + TCI + capital actions | G26: =SCE_Hist!B5+SCE_Hist!B10+SCE_Hist!B11+SCE_Hist!B12+SCE_Hist!B13+SCE_Hist!B14+SCE_Hist!B15-SCE_Hist!B16 -> 0 | H26: =SCE_Hist!C5+SCE_Hist!C10+SCE_Hist!C11+SCE_Hist!C12+SCE_Hist!C13+SCE_Hist!C14+SCE_Hist!C15-SCE_Hist!C16 -> 0 | I26: =SCE_Hist!D5+SCE_Hist!D10+SCE_Hist!D11+SCE_Hist!D12+SCE_Hist!D13+SCE_Hist!D14+SCE_Hist!D15-SCE_Hist!D16 -> 0 | J26: =IF(AND(ABS(N(G26))<=0.5,ABS(N(H26))<=0.5,ABS(N(I26))<=0.5),"PASS","FAIL") -> PASS
A27: SCE: TCI = NI + OCI components | G27: =SCE_Hist!B6+SCE_Hist!B7+SCE_Hist!B8+SCE_Hist!B9-SCE_Hist!B10 -> 0 | H27: =SCE_Hist!C6+SCE_Hist!C7+SCE_Hist!C8+SCE_Hist!C9-SCE_Hist!C10 -> 0 | I27: =SCE_Hist!D6+SCE_Hist!D7+SCE_Hist!D8+SCE_Hist!D9-SCE_Hist!D10 -> 0 | J27: =IF(AND(ABS(N(G27))<=0.5,ABS(N(H27))<=0.5,ABS(N(I27))<=0.5),"PASS","FAIL") -> PASS
A28: X: SCE ending equity = BS total equity | G28: =SCE_Hist!B16-BS_Hist!B46 -> 0 | H28: =SCE_Hist!C16-BS_Hist!C46 -> 0 | I28: =SCE_Hist!D16-BS_Hist!D46 -> 0 | J28: =IF(AND(ABS(N(G28))<=0.5,ABS(N(H28))<=0.5,ABS(N(I28))<=0.5),"PASS","FAIL") -> PASS
A29: X: CF end cash (FY2023A-25A) = BS cash | G29: =CF_Hist!C44-BS_Hist!B6 -> 0 | H29: =CF_Hist!D44-BS_Hist!C6 -> 0 | I29: =CF_Hist!E44-BS_Hist!D6 -> 0 | J29: =IF(AND(ABS(N(G29))<=0.5,ABS(N(H29))<=0.5,ABS(N(I29))<=0.5),"PASS","FAIL") -> PASS
A30: X: FY2023A/FY2024A net sales identical across both source filings | G30: =IS_Hist!C5-27558.5+IS_Hist!D5-28262.9 -> 0 | J30: =IF(ABS(N(G30))<=0.5,"PASS","FAIL") -> PASS
A31: X: FY2024A total assets identical across both source filings | G31: =BS_Hist!C27-48589.6 -> 0 | J31: =IF(ABS(N(G31))<=0.5,"PASS","FAIL") -> PASS
A32: X: Forecast cash roll-forward ties (C26 = B26 + FCFF*(1-payout)) | G32: =Forecast!C26-(Forecast!B26+Forecast!C25*(1-Assumptions!$E$26)) -> 0 | J32: =IF(ABS(N(G32))<=0.01,"PASS","FAIL") -> PASS
A33: X: Forecast cash no longer frozen (G26 <> B26) | G33: =IF(Forecast!G26<>Forecast!B26,0,1) -> 0 | J33: =IF(N(G33)=0,"PASS","FAIL") -> PASS
A35: COBERTURA 2026-08-14 — Drivers_MDA y Market_Package. Convención de columnas de ESTE bloque (filas 36-61): B=FY2021A, C=FY2022A, D=FY2023A, E=FY2024A, F=FY2025A (alineadas a las columnas de Drivers_MDA; distinto del bloque original que usa F:I), J=status, K=años cubiertos.
A36: DRV: sistemas + Installed Base Management = total de ventas netas (FY21 vs Historical, FY22-25 vs IS_Hist) | B36: =Drivers_MDA!B10 -> 0 | C36: =Drivers_MDA!C10 -> 0 | D36: =Drivers_MDA!D10 -> 0 | E36: =Drivers_MDA!E10 -> 0 | F36: =Drivers_MDA!F10 -> 0 | J36: =IF(AND(ABS(N(B36))<=0.5,ABS(N(C36))<=0.5,ABS(N(D36))<=0.5,ABS(N(E36))<=0.5,ABS(N(F36))<=0.5),"PASS","FAIL") -> PASS | K36: B-F
A37: DRV: sistemas y servicio coinciden con las filas memo de IS_Hist (23/25) | C37: =ABS(Drivers_MDA!C11)+ABS(Drivers_MDA!C12) -> 0 | D37: =ABS(Drivers_MDA!D11)+ABS(Drivers_MDA!D12) -> 0 | E37: =ABS(Drivers_MDA!E11)+ABS(Drivers_MDA!E12) -> 0 | F37: =ABS(Drivers_MDA!F11)+ABS(Drivers_MDA!F12) -> 0 | J37: =IF(AND(ABS(N(C37))<=0.5,ABS(N(D37))<=0.5,ABS(N(E37))<=0.5,ABS(N(F37))<=0.5),"PASS","FAIL") -> PASS | K37: C-F
A38: DRV: costo de sistemas + costo de servicio = costo total del IS (FY21: utilidad bruta implícita vs Historical!B7) | B38: =Drivers_MDA!B17 -> 0 | C38: =Drivers_MDA!C16 -> 0 | D38: =Drivers_MDA!D16 -> 0 | E38: =Drivers_MDA!E16 -> 0 | F38: =Drivers_MDA!F16 -> 0 | J38: =IF(AND(ABS(N(B38))<=0.5,ABS(N(C38))<=0.5,ABS(N(D38))<=0.5,ABS(N(E38))<=0.5,ABS(N(F38))<=0.5),"PASS","FAIL") -> PASS | K38: B-F
A39: DRV: margen bruto REPORTADO vs calculado del modelo (tol 0.001 — el filing redondea a 0.1pp) | B39: =Drivers_MDA!B21 -> -5.3892859e-05 | C39: =Drivers_MDA!C21 -> -0.00035577659 | D39: =Drivers_MDA!D21 -> 5.1182031e-05 | E39: =Drivers_MDA!E21 -> 0.00024299346 | F39: =Drivers_MDA!F21 -> -0.00029587998 | J39: =IF(AND(ABS(N(B39))<=0.001,ABS(N(C39))<=0.001,ABS(N(D39))<=0.001,ABS(N(E39))<=0.001,ABS(N(F39))<=0.001),"PASS","FAIL") -> PASS | K39: B-F
A40: DRV: ingreso por tecnología (Nota 2) suma al net system sales — dos tablas independientes del filing | B40: =Drivers_MDA!B41 -> 0 | C40: =Drivers_MDA!C41 -> 0 | D40: =Drivers_MDA!D41 -> 0 | E40: =Drivers_MDA!E41 -> 0 | F40: =Drivers_MDA!F41 -> 0 | J40: =IF(AND(ABS(N(B40))<=0.5,ABS(N(C40))<=0.5,ABS(N(D40))<=0.5,ABS(N(E40))<=0.5,ABS(N(F40))<=0.5),"PASS","FAIL") -> PASS | K40: B-F
A41: DRV: unidades — total FY2025 = Sector_KPIs!B7 y sistemas litográficos (excl. M&I) = KPI reportado del 20-F (FY2024: 418, FY2025: 327) | E41: =Drivers_MDA!E51-418 -> 0 | F41: =Drivers_MDA!F51-327+Drivers_MDA!F32 -> 0 | J41: =IF(AND(ABS(N(E41))<=0.5,ABS(N(F41))<=0.5),"PASS","FAIL") -> PASS | K41: E-F
A42: DRV: end-use (Logic + Memory) = net system sales, en unidades y en ingreso — tablas independientes | B42: =ABS(Drivers_MDA!B58)+ABS(Drivers_MDA!B59) -> 0 | C42: =ABS(Drivers_MDA!C58)+ABS(Drivers_MDA!C59) -> 0 | D42: =ABS(Drivers_MDA!D58)+ABS(Drivers_MDA!D59) -> 0 | E42: =ABS(Drivers_MDA!E58)+ABS(Drivers_MDA!E59) -> 0 | F42: =ABS(Drivers_MDA!F58)+ABS(Drivers_MDA!F59) -> 0 | J42: =IF(AND(ABS(N(B42))<=0.5,ABS(N(C42))<=0.5,ABS(N(D42))<=0.5,ABS(N(E42))<=0.5,ABS(N(F42))<=0.5),"PASS","FAIL") -> PASS | K42: B-F
A43: DRV: ventas por geografía (Nota 3) suman al total de ventas netas | B43: =Drivers_MDA!B73 -> 0 | C43: =Drivers_MDA!C73 -> 0 | D43: =Drivers_MDA!D73 -> 0 | E43: =Drivers_MDA!E73 -> 0 | F43: =Drivers_MDA!F73 -> 0 | J43: =IF(AND(ABS(N(B43))<=0.5,ABS(N(C43))<=0.5,ABS(N(D43))<=0.5,ABS(N(E43))<=0.5,ABS(N(F43))<=0.5),"PASS","FAIL") -> PASS | K43: B-F
A44: DRV: long-lived assets por región = PP&E neto + right-of-use del balance (FY23-25) | D44: =Drivers_MDA!D80 -> 0 | E44: =Drivers_MDA!E80 -> 0 | F44: =Drivers_MDA!F80 -> 0 | J44: =IF(AND(ABS(N(D44))<=0.5,ABS(N(E44))<=0.5,ABS(N(F44))<=0.5),"PASS","FAIL") -> PASS | K44: D-F
A45: DRV: contract liabilities de la Nota 2 = corrientes + no corrientes del balance (FY23-25) | D45: =Drivers_MDA!D89 -> 0 | E45: =Drivers_MDA!E89 -> 0 | F45: =Drivers_MDA!F89 -> 0 | J45: =IF(AND(ABS(N(D45))<=0.5,ABS(N(E45))<=0.5,ABS(N(F45))<=0.5),"PASS","FAIL") -> PASS | K45: D-F
A46: DRV: sistemas nuevos + usados = net system sales | B46: =Drivers_MDA!B50 -> 0 | C46: =Drivers_MDA!C50 -> 0 | D46: =Drivers_MDA!D50 -> 0 | E46: =Drivers_MDA!E50 -> 0 | F46: =Drivers_MDA!F50 -> 0 | J46: =IF(AND(ABS(N(B46))<=0.5,ABS(N(C46))<=0.5,ABS(N(D46))<=0.5,ABS(N(E46))<=0.5,ABS(N(F46))<=0.5),"PASS","FAIL") -> PASS | K46: B-F
A47: DRV: concentración de clientes — % reportado vs monto/ventas (tol 0.005, el filing publica €bn con un decimal) | B47: =Drivers_MDA!B96 -> 0.00035419913 | C47: =Drivers_MDA!C96 -> 0.00069696884 | D47: =Drivers_MDA!D96 -> -0.0016680335 | E47: =Drivers_MDA!E96 -> 0.00019248556 | F47: =Drivers_MDA!F96 -> -0.00023302814 | J47: =IF(AND(ABS(N(B47))<=0.005,ABS(N(C47))<=0.005,ABS(N(D47))<=0.005,ABS(N(E47))<=0.005,ABS(N(F47))<=0.005),"PASS","FAIL") -> PASS | K47: B-F
A48: DRV: deuda del filing (ECP + porción corriente | no corriente, Nota 16) = BS_Hist filas 32 y 35 (FY24-25) | E48: =ABS(Drivers_MDA!E123)+ABS(Drivers_MDA!E124) -> 0 | F48: =ABS(Drivers_MDA!F123)+ABS(Drivers_MDA!F124) -> 0 | J48: =IF(AND(ABS(N(E48))<=0.5,ABS(N(F48))<=0.5),"PASS","FAIL") -> PASS | K48: E-F
A49: DRV: recompras del filing = purchase of treasury shares del CF_Hist (FY24-25) | E49: =ABS(Drivers_MDA!E129) -> 0 | F49: =ABS(Drivers_MDA!F129) -> 0 | J49: =IF(AND(ABS(N(E49))<=0.5,ABS(N(F49))<=0.5),"PASS","FAIL") -> PASS | K49: E-F
A50: DRV: backlog FY2025 = Sector_KPIs!B9 y guidance FY2026 = Sector_KPIs!B11/B12 | F50: =ABS(Drivers_MDA!F87)+Drivers_MDA!F137 -> 0 | J50: =IF(ABS(N(F50))<=0.5,"PASS","FAIL") -> PASS | K50: F
A51: FCST: anclas FY2025A del motor (Forecast!B5:B8) = filing (unidades, ASP, IBM, ingreso total; tol 0.01) | F51: =ABS(Drivers_MDA!F150)+ABS(Drivers_MDA!F151)+ABS(Drivers_MDA!F152)+ABS(Drivers_MDA!F153) -> 0 | J51: =IF(ABS(N(F51))<=0.01,"PASS","FAIL") -> PASS | K51: F
A52: KPI: Sector_KPIs (net system sales, IBM, gross margin) = Drivers_MDA FY2025A | F52: =ABS(Drivers_MDA!F154)+ABS(Drivers_MDA!F155)+ABS(Drivers_MDA!F156) -> 0 | J52: =IF(ABS(N(F52))<=0.5,"PASS","FAIL") -> PASS | K52: F
A53: MKT: procedencia de los inputs de mercado — fuente presente, fecha con serial válido, sin desfases internos ni paquete obsoleto (tol 0) | F53: =Market_Package!B80+Market_Package!B81+Market_Package!B82 -> 1 | J53: =IF(N(F53)=0,"PASS","FAIL") -> FAIL | K53: F
A54: MKT: paridad de doble cotización (|EUR×FX/USD − 1| ≤ 2%), precio USD dentro de ±25% del ancla del modelo (Assumptions!E24) y FX dentro de ±10% del FX del modelo (Assumptions!E22) | F54: =IF(ABS(Market_Package!B10)>0.02,1,0)+IF(ABS(Market_Package!B8/Assumptions!E24-1)>0.25,1,0)+IF(ABS(Market_Package!B9/Assumptions!E22-1)>0.1,1,0) -> 0 | J54: =IF(N(F54)=0,"PASS","FAIL") -> PASS | K54: F
A55: MKT: capitalización = precio × acciones (cableado) y acciones de la portada del 20-F dentro de ±3% de las diluidas del DCF (Forecast!B28) | F55: =IF(ABS(Market_Package!B13-Market_Package!B7*Market_Package!B11)>0.5,1,0)+IF(ABS(Market_Package!B11/Forecast!B28-1)>0.03,1,0) -> 0 | J55: =IF(N(F55)=0,"PASS","FAIL") -> PASS | K55: F
A56: MKT: efectivo e inversiones del paquete = anclas tecleadas de la Nota 4 (extracción PDF, independiente de los R-files), FY2025 y vintage FY2024 | F56: =IF(ABS(Market_Package!B17-Market_Package!B99)>0.5,1,0)+IF(ABS(Market_Package!B18-Market_Package!B100)>0.5,1,0)+IF(ABS(BS_Hist!C6-Market_Package!B104)>0.5,1,0) -> 0 | J56: =IF(N(F56)=0,"PASS","FAIL") -> PASS | K56: E-F
A57: MKT: deuda del paquete = anclas de la Nota 16 (corto plazo = ECP + porción corriente; LP = no corriente) y brecha vs la deuda del DCF exactamente = BS_Hist!D32 (H1 mecanizado) | F57: =IF(ABS(Market_Package!B20-(Market_Package!B101+Market_Package!B103))>0.5,1,0)+IF(ABS(Market_Package!B21-Market_Package!B102)>0.5,1,0)+IF(ABS(Market_Package!B22-Market_Package!B25-BS_Hist!D32)>0.5,1,0) -> 0 | J57: =IF(N(F57)=0,"PASS","FAIL") -> PASS | K57: F
A58: MKT: WACC recomputado desde los inputs crudos (B31/B32/B33/B35 y la tasa efectiva del IS) SIN pasar por Ke ni Kd después de impuestos, tol 1e-6; más bandas de sanidad (Rf 0.5-8%, beta 0.3-2.5, Kd 0.5-12%, WACC 4-20%) | F58: =IF(ABS(Market_Package!B45-((Market_Package!B13/(Market_Package!B13+Market_Package!B22))*(Market_Package!B31+Market_Package!B33*Market_Package!B32)+(Market_Package!B22/(Market_Package!B13+Market_Package!B22))*Market_Package!B35*(1+IS_Hist!E13/IS_Hist!E12)))>0.000001,1,0)+IF(OR(Market_Package!B31<0.005,Market_Package!B31>0.08),1,0)+IF(OR(Market_Package!B33<0.3,Market_Package!B33>2.5),1,0)+IF(OR(Market_Package!B35<0.005,Market_Package!B35>0.12),1,0)+IF(OR(Market_Package!B45<0.04,Market_Package!B45>0.2),1,0) -> 0 | J58: =IF(N(F58)=0,"PASS","FAIL") -> PASS | K58: F
A59: MKT: enterprise value = reconstrucción con anclas tecleadas (precio × acciones + deuda de Nota 16 − caja de Nota 4), EV > 0, y EV de mercado entre 1x y 6x el EV del DCF (Valuation!B13) | F59: =IF(ABS(Market_Package!B24-(Market_Package!B7*Market_Package!B11+(Market_Package!B101+Market_Package!B102+Market_Package!B103)-(Market_Package!B99+Market_Package!B100)))>0.5,1,0)+IF(Market_Package!B24<=0,1,0)+IF(OR(Market_Package!B24/Valuation!B13<1,Market_Package!B24/Valuation!B13>6),1,0) -> 0 | J59: =IF(N(F59)=0,"PASS","FAIL") -> PASS | K59: F
A60: MKT: bandas de plausibilidad de múltiplos (NO es tie): EV/EBITDA 5-80x, P/E 5-120x, FCF yield 0.2-15% | F60: =IF(OR(Market_Package!B62<5,Market_Package!B62>80),1,0)+IF(OR(Market_Package!B59<5,Market_Package!B59>120),1,0)+IF(OR(Market_Package!B64<0.002,Market_Package!B64>0.15),1,0) -> 0 | J60: =IF(N(F60)=0,"PASS","FAIL") -> PASS | K60: F
A61: DRV: bandas de plausibilidad (NO es tie) para constantes sin tie mecanizado — FTEs promedio 20k-80k, RPO/ventas 0.8x-2.5x, % clientes >10% entre 30-90%, top-3 AR entre 20-95% | B61: =IF(OR(Drivers_MDA!B100<20000,Drivers_MDA!B100>80000),1,0)+IF(OR(Drivers_MDA!B83/Drivers_MDA!B9<0.8,Drivers_MDA!B83/Drivers_MDA!B9>2.5),1,0)+IF(OR(Drivers_MDA!B95<0.3,Drivers_MDA!B95>0.9),1,0)+IF(OR(Drivers_MDA!B97<0.2,Drivers_MDA!B97>0.95),1,0) -> 0 | C61: =IF(OR(Drivers_MDA!C100<20000,Drivers_MDA!C100>80000),1,0)+IF(OR(Drivers_MDA!C83/Drivers_MDA!C9<0.8,Drivers_MDA!C83/Drivers_MDA!C9>2.5),1,0)+IF(OR(Drivers_MDA!C95<0.3,Drivers_MDA!C95>0.9),1,0)+IF(OR(Drivers_MDA!C97<0.2,Drivers_MDA!C97>0.95),1,0) -> 0 | D61: =IF(OR(Drivers_MDA!D100<20000,Drivers_MDA!D100>80000),1,0)+IF(OR(Drivers_MDA!D83/Drivers_MDA!D9<0.8,Drivers_MDA!D83/Drivers_MDA!D9>2.5),1,0)+IF(OR(Drivers_MDA!D95<0.3,Drivers_MDA!D95>0.9),1,0)+IF(OR(Drivers_MDA!D97<0.2,Drivers_MDA!D97>0.95),1,0) -> 0 | E61: =IF(OR(Drivers_MDA!E100<20000,Drivers_MDA!E100>80000),1,0)+IF(OR(Drivers_MDA!E83/Drivers_MDA!E9<0.8,Drivers_MDA!E83/Drivers_MDA!E9>2.5),1,0)+IF(OR(Drivers_MDA!E95<0.3,Drivers_MDA!E95>0.9),1,0)+IF(OR(Drivers_MDA!E97<0.2,Drivers_MDA!E97>0.95),1,0) -> 0 | F61: =IF(OR(Drivers_MDA!F100<20000,Drivers_MDA!F100>80000),1,0)+IF(OR(Drivers_MDA!F83/Drivers_MDA!F9<0.8,Drivers_MDA!F83/Drivers_MDA!F9>2.5),1,0)+IF(OR(Drivers_MDA!F95<0.3,Drivers_MDA!F95>0.9),1,0)+IF(OR(Drivers_MDA!F97<0.2,Drivers_MDA!F97>0.95),1,0) -> 0 | J61: =IF(AND(N(B61)=0,N(C61)=0,N(D61)=0,N(E61)=0,N(F61)=0),"PASS","FAIL") -> PASS | K61: B-F
A62: SIN TIE MECANIZADO (declarado, FUERA del rango del MASTER): Drivers_MDA filas 84 (% RPO a 12m), 86 D-E (backlog FY23-24; FY24 es 'around €36bn' aproximado), 93-95 y 97 (concentración: solo banda), 100 (FTEs: solo banda), 102 (FTEs cierre), 105-113 (notionals y sensibilidades FX/tasas), 117-119 (Eurobonds principal/carrying/FV), 125 (dividendo declarado), 127 (número de acciones recompradas), 131-132 (componentes de interés) — verificación manual contra el filing; el muestreo es del refutador.

Sheet Sources_Audited
A1: Audited source register — ASML statement-grade blocks (Ola 2 elevation, run 24e4a1f1)
A3: Sheet / block | B3: Years covered | C3: Primary source file(s) | D3: R-file / XBRL tag / accession | E3: Notes
A4: IS_Hist | B4: FY2022A-FY2024A | C4: 20-F_2024-12-31_Financial_Report.xlsx — "Consolidated Statements of Oper[ations]" sheet | D4: Accession 0000937966-25-000009 (20-F filed 2025-03-05, FY2024 annual report) | E4: Read via Mog SDK only, per hard rule.
A5: IS_Hist | B5: FY2023A-FY2025A | C5: 20-F_2025-12-31_Rfiles/R3.htm, R4.htm | D5: Accession 0001628280-26-011378 (20-F filed 2026-02-25, FY2025 annual report) | E5: FY2023A/FY2024A values cross-checked identical to Financial_Report.xlsx — see Checks_TieOut dual-filing rows.
A6: CF_Hist | B6: FY2022A-FY2024A | C6: 20-F_2024-12-31_Financial_Report.xlsx — "Consolidated Statements of Cash" sheet | D6: Accession 0000937966-25-000009
A7: CF_Hist | B7: FY2023A-FY2025A | C7: 20-F_2025-12-31_Rfiles/R10.htm, R11.htm | D7: Accession 0001628280-26-011378
A8: BS_Hist | B8: FY2023A-FY2024A | C8: 20-F_2024-12-31_Financial_Report.xlsx — "Consolidated Balance Sheets" sheet | D8: Accession 0000937966-25-000009
A9: BS_Hist | B9: FY2024A-FY2025A | C9: 20-F_2025-12-31_Rfiles/R6.htm, R7.htm | D9: Accession 0001628280-26-011378 | E9: FY2024A values cross-checked identical across both filings.
A10: SCE_Hist | B10: FY2023A-FY2025A | C10: 20-F_2025-12-31_Rfiles/R8.htm | D10: Accession 0001628280-26-011378 | E10: Beginning balance Dec-31-2022 (€8,810.8mm) cross-checked to companyfacts.json us-gaap:StockholdersEquity, accn 0000937966-23-000014.
A11: Gap (documented, not fabricated) | B11: FY2021A-FY2022A BS; FY2021A IS/CF full line item | C11: Not present in this run's source package (prior 20-F R-files/Financial_Report not pulled) | D11: companyfacts.json confirms only headline tags (Assets, Liabilities, StockholdersEquity, Revenue, GrossProfit, OperatingIncomeLoss, NetIncomeLoss, R&D, PP&E capex, CFO) for these years — matches existing Historical sheet summary, already sourced there. | E11: Historical!B5:B20 (FY2021A column) is untouched and remains the audit trail for these years at summary granularity.
A12: Forecast cash defect fix | B12: n/a | C12: Assumptions!A26:F26 (new payout-ratio driver), Forecast!C26:G26 (rebuilt formulas) | D12: n/a — model mechanics fix, not a sourced claim | E12: Payout ratio 0.62 = (avg dividends+buybacks)/(avg FCFF) FY2022A-FY2025A from CF_Hist, computed off audited actuals; see Checks_TieOut cash-defect rows.
A13: Drivers_MDA (hoja nueva, capa de cobertura) | B13: FY2021A-FY2025A | C13: 20-F FY2021 a FY2025 (PDFs locales asml/asml-20211231.pdf ... asml-20251231.pdf), Notas 2/3/4/16/25, Item 5 y KPIs; leidos con pdftotext -layout | D13: Accessions: 0000937966-22-000013 / 0000937966-23-000014 / 0000937966-24-000008 / 0000937966-25-000009 / 0001628280-26-011378 | E13: Constantes tecleadas con tie mecanizado contra IS_Hist/BS_Hist/CF_Hist/Historical/Sector_KPIs/Forecast (Checks_TieOut filas 36-52). FY2023 verificado dual-filing (20-F FY2023 vs FY2025).
A14: Market_Package (hoja nueva, capa de cobertura) | B14: as-of 2026-08-13 (precios, FX, Rf) / 2026-08-14 (beta) / 2026-01-01 (ERP) / 2025-12-31 (acciones y anclas) | C14: Euronext y Nasdaq via stockanalysis.com (historicos diarios); EUR/USD referencia BCE via api.frankfurter.dev; Bund 10Y via investing.com (secundaria, declarada); ERP Damodaran ene-2026; spread AA USD de FRED BAMLC0A2CAAEY menos UST 10Y (CSVs primarios en scratchpad/audit/ de la corrida de flota); acciones de la portada del 20-F FY2025 | D14: n/a — datos de mercado fechados; control mecanizado en Market_Package!B80:B83 y Checks_TieOut filas 53-60 | E14: Todos los inputs de mercado con fuente y fecha serial. Kd construido (Bund + spread AA USD) declarado como proxy — limitacion L3 de la hoja.
A15: Gap declarado (capa de cobertura) | B15: Backlog FY2021-22; notionals FX FY2021-23; FTEs de cierre FY2024-25; balances intermedios 2026 | C15: No presentes en los 20-F del paquete local o no localizados en la extraccion de texto; ASML no publica economia por nodo (proxy: mezcla por tecnologia y end-use en Drivers_MDA bloques 2-3) | D15: Declarados en Drivers_MDA bloque 12 con razon por fila | E15: Regla de flota: un NOT_AVAILABLE con razon vale mas que un numero sin fuente. Nada se fabrico.

Sheet Drivers_MDA
A1: ASML Holding N.V. — Drivers de negocio del 20-F y disclosures (FY2021A–FY2025A)
A2: EUR millones salvo indicación. CAPA DE COBERTURA ADITIVA: no altera ninguna hoja histórica ni el Forecast. Todo dato 'Reportado' es una constante publicada tecleada del filing; todo 'Calculado' es fórmula viva; los 'Tie' deben ser 0. Los checks mecanizados viven en Checks_TieOut filas 36-61.
A4: Métrica | B4: FY2021A | C4: FY2022A | D4: FY2023A | E4: FY2024A | F4: FY2025A | G4: Unidad | H4: Fuente (documento - sección - accession) | I4: Estado
A6: 1. VENTAS NETAS POR LÍNEA DE NEGOCIO (sistemas vs Installed Base Management)
A7: Net system sales | B7: 13652.8 | C7: 15430.3 | D7: 21938.6 | E7: 21768.7 | F7: 24474.3 | G7: EUR m | H7: FY21-22: 20-F FY2022 (accn 0000937966-23-000014), Consolidated Statements of Operations | FY23-25: 20-F FY2025 (accn 0001628280-26-011378), Consolidated Statements of Operations; FY2023 verificado dual-filing contra 20-F FY2023 (accn 0000937966-24-000008) | I7: Reportado
A8: Net service and field option sales (Installed Base Management) | B8: 4958.2 | C8: 5743.1 | D8: 5619.9 | E8: 6494.2 | F8: 8193 | G8: EUR m | H8: FY21-22: 20-F FY2022 (accn 0000937966-23-000014), Consolidated Statements of Operations | FY23-25: 20-F FY2025 (accn 0001628280-26-011378), Consolidated Statements of Operations; FY2023 verificado dual-filing contra 20-F FY2023 (accn 0000937966-24-000008) | I8: Reportado
A9: Total net sales | B9: =B7+B8 -> 18611 | C9: =C7+C8 -> 21173.4 | D9: =D7+D8 -> 27558.5 | E9: =E7+E8 -> 28262.9 | F9: =F7+F8 -> 32667.3 | G9: EUR m | H9: Calculado | I9: Calculado
A10: Tie: total vs modelo (FY21 vs Historical!B5; FY22-25 vs IS_Hist) | B10: =B9-Historical!B5 -> 0 | C10: =C9-IS_Hist!B5 -> 0 | D10: =D9-IS_Hist!C5 -> 0 | E10: =E9-IS_Hist!D5 -> 0 | F10: =F9-IS_Hist!E5 -> 0 | G10: EUR m | H10: Debe ser 0 los cinco años | I10: Tie
A11: Tie: sistemas vs memo IS_Hist (FY22-25) | C11: =C7-IS_Hist!B23 -> 0 | D11: =D7-IS_Hist!C23 -> 0 | E11: =E7-IS_Hist!D23 -> 0 | F11: =F7-IS_Hist!E23 -> 0 | G11: EUR m | H11: IS_Hist filas memo 23/25; FY2021 no está en IS_Hist (ventana FY22-25) | I11: Tie
A12: Tie: servicio vs memo IS_Hist (FY22-25) | C12: =C8-IS_Hist!B25 -> 0 | D12: =D8-IS_Hist!C25 -> 0 | E12: =E8-IS_Hist!D25 -> 0 | F12: =F8-IS_Hist!E25 -> 0 | G12: EUR m | H12: Debe ser 0 | I12: Tie
A13: Cost of system sales | B13: -6482.9 | C13: -7582.3 | D13: -10151 | E13: -10406.9 | F13: -11384 | G13: EUR m | H13: FY21-22: 20-F FY2022 (accn 0000937966-23-000014), Consolidated Statements of Operations | FY23-25: 20-F FY2025 (accn 0001628280-26-011378), Consolidated Statements of Operations; FY2023 verificado dual-filing contra 20-F FY2023 (accn 0000937966-24-000008) | FY2021 verificado también en 20-F FY2023 (accn 0000937966-24-000008) | I13: Reportado
A14: Cost of service and field option sales | B14: -2319.1 | C14: -2891 | D14: -3271.4 | E14: -3364 | F14: -4025.3 | G14: EUR m | H14: FY21-22: 20-F FY2022 (accn 0000937966-23-000014), Consolidated Statements of Operations | FY23-25: 20-F FY2025 (accn 0001628280-26-011378), Consolidated Statements of Operations; FY2023 verificado dual-filing contra 20-F FY2023 (accn 0000937966-24-000008) | I14: Reportado
A15: Total cost of sales | B15: =B13+B14 -> -8802 | C15: =C13+C14 -> -10473.3 | D15: =D13+D14 -> -13422.4 | E15: =E13+E14 -> -13770.9 | F15: =F13+F14 -> -15409.3 | G15: EUR m | H15: Calculado | I15: Calculado
A16: Tie: costo total vs IS_Hist (FY22-25) | C16: =C15-IS_Hist!B6 -> 0 | D16: =D15-IS_Hist!C6 -> 0 | E16: =E15-IS_Hist!D6 -> 0 | F16: =F15-IS_Hist!E6 -> 0 | G16: EUR m | H16: Debe ser 0 | I16: Tie
A17: Tie FY2021: utilidad bruta implícita vs Historical!B7 | B17: =B9+B15-Historical!B7 -> 0 | G17: EUR m | H17: 18.611,0 - 8.802,0 = 9.809,0; Historical no trae fila de costo FY2021 | I17: Tie
A18: Margen bruto de sistemas | B18: =(B7+B13)/B7 -> 0.52515967 | C18: =(C7+C13)/C7 -> 0.50860968 | D18: =(D7+D13)/D7 -> 0.53729955 | E18: =(E7+E13)/E7 -> 0.52193287 | F18: =(F7+F13)/F7 -> 0.53485902 | G18: % | H18: Calculado | I18: Calculado
A19: Margen bruto de servicio / IBM | B19: =(B8+B14)/B8 -> 0.53226978 | C19: =(C8+C14)/C8 -> 0.49661333 | D19: =(D8+D14)/D8 -> 0.41789 | E19: =(E8+E14)/E8 -> 0.48199932 | F19: =(F8+F14)/F8 -> 0.50869035 | G19: % | H19: Calculado | I19: Calculado
A20: Margen bruto total REPORTADO (%) | B20: 0.527 | C20: 0.505 | D20: 0.513 | E20: 0.513 | F20: 0.528 | G20: % | H20: Item 5 'Operating results' / KPIs de cada 20-F: 52.7 / 50.5 / 51.3 / 51.3 / 52.8. FY2025: accn 0001628280-26-011378 | I20: Reportado
A21: Tie: margen reportado vs calculado del modelo (Historical fila 8; tol 0.001 por redondeo a 0.1pp) | B21: =B20-Historical!B8 -> -5.3892859e-05 | C21: =C20-Historical!C8 -> -0.00035577659 | D21: =D20-Historical!D8 -> 5.1182031e-05 | E21: =E20-Historical!E8 -> 0.00024299346 | F21: =F20-Historical!F8 -> -0.00029587998 | G21: pp | H21: Reportado redondeado a 0.1pp convive con el calculado; no se sobrescriben | I21: Tie
A23: 2. SISTEMAS POR TECNOLOGÍA — unidades e ingreso reconocido (Nota 2)
A24: EUV NXE — unidades | B24: 42 | C24: 40 | D24: 53 | E24: 42 | F24: 44 | G24: sistemas | H24: FY21-22: 20-F FY2022 (accn 0000937966-23-000014), Nota 2 'Revenue from contracts with customers', desagregación por tecnología/end-use | FY23-25: 20-F FY2025 (accn 0001628280-26-011378), Nota 2; FY2023 dual-filing vs 20-F FY2023 (accn 0000937966-24-000008) | I24: Reportado
A25: EUV EXE (High-NA) — unidades | B25: 0 | C25: 0 | D25: 0 | E25: 2 | F25: 4 | G25: sistemas | H25: EXE (High-NA): primer ingreso reconocido en FY2024 (2 unidades). El '—' de la tabla del filing para FY2023 y la ausencia de línea en FY21-22 son cero económico (el producto no había generado ingreso), no dato faltante. FY21-22: 20-F FY2022 (accn 0000937966-23-000014), Nota 2 'Revenue from contracts with customers', desagregación por tecnología/end-use | FY23-25: 20-F FY2025 (accn 0001628280-26-011378), Nota 2; FY2023 dual-filing vs 20-F FY2023 (accn 0000937966-24-000008) | I25: Reportado
A26: ArF immersion — unidades | B26: 81 | C26: 81 | D26: 125 | E26: 129 | F26: 131 | G26: sistemas | H26: FY21-22: 20-F FY2022 (accn 0000937966-23-000014), Nota 2 'Revenue from contracts with customers', desagregación por tecnología/end-use | FY23-25: 20-F FY2025 (accn 0001628280-26-011378), Nota 2; FY2023 dual-filing vs 20-F FY2023 (accn 0000937966-24-000008) | I26: Reportado
A27: ArF dry — unidades | B27: 22 | C27: 28 | D27: 32 | E27: 28 | F27: 16 | G27: sistemas | H27: FY21-22: 20-F FY2022 (accn 0000937966-23-000014), Nota 2 'Revenue from contracts with customers', desagregación por tecnología/end-use | FY23-25: 20-F FY2025 (accn 0001628280-26-011378), Nota 2; FY2023 dual-filing vs 20-F FY2023 (accn 0000937966-24-000008) | I27: Reportado
A28: KrF — unidades | B28: 131 | C28: 151 | D28: 184 | E28: 152 | F28: 78 | G28: sistemas | H28: FY21-22: 20-F FY2022 (accn 0000937966-23-000014), Nota 2 'Revenue from contracts with customers', desagregación por tecnología/end-use | FY23-25: 20-F FY2025 (accn 0001628280-26-011378), Nota 2; FY2023 dual-filing vs 20-F FY2023 (accn 0000937966-24-000008) | I28: Reportado
A29: i-line — unidades | B29: 33 | C29: 45 | D29: 55 | E29: 65 | F29: 54 | G29: sistemas | H29: FY21-22: 20-F FY2022 (accn 0000937966-23-000014), Nota 2 'Revenue from contracts with customers', desagregación por tecnología/end-use | FY23-25: 20-F FY2025 (accn 0001628280-26-011378), Nota 2; FY2023 dual-filing vs 20-F FY2023 (accn 0000937966-24-000008) | I29: Reportado
A30: Metrology & Inspection — unidades | B30: 196 | C30: 216 | D30: 151 | E30: 165 | F30: 208 | G30: sistemas | H30: FY21-22: 20-F FY2022 (accn 0000937966-23-000014), Nota 2 'Revenue from contracts with customers', desagregación por tecnología/end-use | FY23-25: 20-F FY2025 (accn 0001628280-26-011378), Nota 2; FY2023 dual-filing vs 20-F FY2023 (accn 0000937966-24-000008) | I30: Reportado
A31: Total unidades vendidas | B31: =SUM(B24:B30) -> 505 | C31: =SUM(C24:C30) -> 561 | D31: =SUM(D24:D30) -> 600 | E31: =SUM(E24:E30) -> 583 | F31: =SUM(F24:F30) -> 535 | G31: sistemas | H31: Calculado: 505 / 561 / 600 / 583 / 535 | I31: Calculado
A32: Tie: unidades FY2025 vs Sector_KPIs!B7 | F32: =F31-Sector_KPIs!B7 -> 0 | G32: sistemas | H32: Debe ser 0 | I32: Tie
A33: EUV NXE — ingreso | B33: 6284 | C33: 7045.3 | D33: 9124 | E33: 7856.4 | F33: 10445.8 | G33: EUR m | H33: FY21-22: 20-F FY2022 (accn 0000937966-23-000014), Nota 2 'Revenue from contracts with customers', desagregación por tecnología/end-use | FY23-25: 20-F FY2025 (accn 0001628280-26-011378), Nota 2; FY2023 dual-filing vs 20-F FY2023 (accn 0000937966-24-000008) | I33: Reportado
A34: EUV EXE (High-NA) — ingreso | B34: 0 | C34: 0 | D34: 0 | E34: 465 | F34: 1156.9 | G34: EUR m | H34: Mismo tratamiento del cero económico que la fila 25. FY21-22: 20-F FY2022 (accn 0000937966-23-000014), Nota 2 'Revenue from contracts with customers', desagregación por tecnología/end-use | FY23-25: 20-F FY2025 (accn 0001628280-26-011378), Nota 2; FY2023 dual-filing vs 20-F FY2023 (accn 0000937966-24-000008) | I34: Reportado
A35: ArF immersion — ingreso | B35: 4959.6 | C35: 5236.5 | D35: 9017.4 | E35: 9667 | F35: 10311.4 | G35: EUR m | H35: FY21-22: 20-F FY2022 (accn 0000937966-23-000014), Nota 2 'Revenue from contracts with customers', desagregación por tecnología/end-use | FY23-25: 20-F FY2025 (accn 0001628280-26-011378), Nota 2; FY2023 dual-filing vs 20-F FY2023 (accn 0000937966-24-000008) | I35: Reportado
A36: ArF dry — ingreso | B36: 431.9 | C36: 623.7 | D36: 780.2 | E36: 774.4 | F36: 427 | G36: EUR m | H36: FY21-22: 20-F FY2022 (accn 0000937966-23-000014), Nota 2 'Revenue from contracts with customers', desagregación por tecnología/end-use | FY23-25: 20-F FY2025 (accn 0001628280-26-011378), Nota 2; FY2023 dual-filing vs 20-F FY2023 (accn 0000937966-24-000008) | I36: Reportado
A37: KrF — ingreso | B37: 1321.3 | C37: 1653.7 | D37: 2202.5 | E37: 1991.2 | F37: 1001.3 | G37: EUR m | H37: FY21-22: 20-F FY2022 (accn 0000937966-23-000014), Nota 2 'Revenue from contracts with customers', desagregación por tecnología/end-use | FY23-25: 20-F FY2025 (accn 0001628280-26-011378), Nota 2; FY2023 dual-filing vs 20-F FY2023 (accn 0000937966-24-000008) | I37: Reportado
A38: i-line — ingreso | B38: 142.3 | C38: 211.5 | D38: 278.4 | E38: 369.2 | F38: 307.3 | G38: EUR m | H38: FY21-22: 20-F FY2022 (accn 0000937966-23-000014), Nota 2 'Revenue from contracts with customers', desagregación por tecnología/end-use | FY23-25: 20-F FY2025 (accn 0001628280-26-011378), Nota 2; FY2023 dual-filing vs 20-F FY2023 (accn 0000937966-24-000008) | I38: Reportado
A39: Metrology & Inspection — ingreso | B39: 513.7 | C39: 659.6 | D39: 536.1 | E39: 645.5 | F39: 824.6 | G39: EUR m | H39: FY21-22: 20-F FY2022 (accn 0000937966-23-000014), Nota 2 'Revenue from contracts with customers', desagregación por tecnología/end-use | FY23-25: 20-F FY2025 (accn 0001628280-26-011378), Nota 2; FY2023 dual-filing vs 20-F FY2023 (accn 0000937966-24-000008) | I39: Reportado
A40: Total ingreso por tecnología | B40: =SUM(B33:B39) -> 13652.8 | C40: =SUM(C33:C39) -> 15430.3 | D40: =SUM(D33:D39) -> 21938.6 | E40: =SUM(E33:E39) -> 21768.7 | F40: =SUM(F33:F39) -> 24474.3 | G40: EUR m | H40: Calculado | I40: Calculado
A41: Tie: total tecnología vs net system sales (fila 7) | B41: =B40-B7 -> 0 | C41: =C40-C7 -> 0 | D41: =D40-D7 -> 0 | E41: =E40-E7 -> 0 | F41: =F40-F7 -> 0 | G41: EUR m | H41: Dos tablas independientes del filing; debe ser 0 | I41: Tie
A42: ASP promedio por sistema | B42: =B40/B31 -> 27.035248 | C42: =C40/C31 -> 27.504991 | D42: =D40/D31 -> 36.564333 | E42: =E40/E31 -> 37.339108 | F42: =F40/F31 -> 45.746355 | G42: EUR m / sistema | H42: Calculado: 27.0 / 27.5 / 36.6 / 37.3 / 45.7 — la escalera de precio del roadmap | I42: Calculado
A43: Tie: ASP FY2025 vs Sector_KPIs!B8 | F43: =F42-Sector_KPIs!B8 -> 0 | G43: EUR m / sistema | H43: Debe ser 0 | I43: Tie
A44: Ingreso EUV total (NXE + EXE) | B44: =B33+B34 -> 6284 | C44: =C33+C34 -> 7045.3 | D44: =D33+D34 -> 9124 | E44: =E33+E34 -> 8321.4 | F44: =F33+F34 -> 11602.7 | G44: EUR m | H44: Calculado | I44: Calculado
A45: Mix EUV / ingreso de sistemas | B45: =B44/B40 -> 0.46027189 | C45: =C44/C40 -> 0.45658866 | D45: =D44/D40 -> 0.41588798 | E45: =E44/E40 -> 0.38226444 | F45: =F44/F40 -> 0.47407689 | G45: % | H45: Calculado: 46.0% / 45.7% / 41.6% / 38.2% / 47.4% | I45: Calculado
A46: ASP EUV (NXE+EXE) | B46: =B44/(B24+B25) -> 149.61905 | C46: =C44/(C24+C25) -> 176.1325 | D46: =D44/(D24+D25) -> 172.15094 | E46: =E44/(E24+E25) -> 189.12273 | F46: =F44/(F24+F25) -> 241.72292 | G46: EUR m / sistema | H46: Calculado: 149.6 / 176.1 / 172.2 / 189.1 / 241.7 — economía por transición de plataforma (proxy público de la economía por nodo) | I46: Calculado
A47: ASP DUV (ArFi + ArF dry + KrF + i-line) | B47: =(B35+B36+B37+B38)/(B26+B27+B28+B29) -> 25.674532 | C47: =(C35+C36+C37+C38)/(C26+C27+C28+C29) -> 25.32918 | D47: =(D35+D36+D37+D38)/(D26+D27+D28+D29) -> 31.006313 | E47: =(E35+E36+E37+E38)/(E26+E27+E28+E29) -> 34.229412 | F47: =(F35+F36+F37+F38)/(F26+F27+F28+F29) -> 43.179211 | G47: EUR m / sistema | H47: Calculado | I47: Calculado
A48: Sistemas nuevos — ingreso | B48: 13446.1 | C48: 15152.3 | D48: 21622.4 | E48: 21139.7 | F48: 23898.6 | G48: EUR m | H48: FY21-22: 20-F FY2022 (accn 0000937966-23-000014), Nota 3 'Segment disclosure' (geografía, new/used, clientes) | FY23-25: 20-F FY2025 (accn 0001628280-26-011378), Nota 3 | I48: Reportado
A49: Sistemas usados — ingreso | B49: 206.7 | C49: 278 | D49: 316.2 | E49: 629 | F49: 575.7 | G49: EUR m | H49: FY21-22: 20-F FY2022 (accn 0000937966-23-000014), Nota 3 'Segment disclosure' (geografía, new/used, clientes) | FY23-25: 20-F FY2025 (accn 0001628280-26-011378), Nota 3 | En 2025 se vendieron 27 sistemas litográficos refurbished (informe de circularidad del 20-F FY2025) | I49: Reportado
A50: Tie: nuevos + usados vs net system sales | B50: =B48+B49-B7 -> 0 | C50: =C48+C49-C7 -> 0 | D50: =D48+D49-D7 -> 0 | E50: =E48+E49-E7 -> 0 | F50: =F48+F49-F7 -> 0 | G50: EUR m | H50: Debe ser 0 | I50: Tie
A51: Memo: sistemas litográficos vendidos (excl. Metrology & Inspection) | B51: =B31-B30 -> 309 | C51: =C31-C30 -> 345 | D51: =D31-D30 -> 449 | E51: =E31-E30 -> 418 | F51: =F31-F30 -> 327 | G51: sistemas | H51: Calculado: 309 / 345 / 449 / 418 / 327. El KPI del 20-F FY2025 reporta 327 (2024: 418) — amarrado en Checks_TieOut fila 41 | I51: Calculado
A53: 3. SISTEMAS POR END-USE (Logic vs Memory, Nota 2)
A54: Logic — unidades | B54: 327 | C54: 357 | D54: 439 | E54: 399 | F54: 364 | G54: sistemas | H54: FY21-22: 20-F FY2022 (accn 0000937966-23-000014), Nota 2 'Revenue from contracts with customers', desagregación por tecnología/end-use | FY23-25: 20-F FY2025 (accn 0001628280-26-011378), Nota 2; FY2023 dual-filing vs 20-F FY2023 (accn 0000937966-24-000008) | I54: Reportado
A55: Memory — unidades | B55: 178 | C55: 204 | D55: 161 | E55: 184 | F55: 171 | G55: sistemas | H55: FY21-22: 20-F FY2022 (accn 0000937966-23-000014), Nota 2 'Revenue from contracts with customers', desagregación por tecnología/end-use | FY23-25: 20-F FY2025 (accn 0001628280-26-011378), Nota 2; FY2023 dual-filing vs 20-F FY2023 (accn 0000937966-24-000008) | I55: Reportado
A56: Logic — ingreso | B56: 9588.5 | C56: 9977.6 | D56: 15984.7 | E56: 13195.1 | F56: 16054.1 | G56: EUR m | H56: FY21-22: 20-F FY2022 (accn 0000937966-23-000014), Nota 2 'Revenue from contracts with customers', desagregación por tecnología/end-use | FY23-25: 20-F FY2025 (accn 0001628280-26-011378), Nota 2; FY2023 dual-filing vs 20-F FY2023 (accn 0000937966-24-000008) | I56: Reportado
A57: Memory — ingreso | B57: 4064.3 | C57: 5452.7 | D57: 5953.9 | E57: 8573.6 | F57: 8420.2 | G57: EUR m | H57: FY21-22: 20-F FY2022 (accn 0000937966-23-000014), Nota 2 'Revenue from contracts with customers', desagregación por tecnología/end-use | FY23-25: 20-F FY2025 (accn 0001628280-26-011378), Nota 2; FY2023 dual-filing vs 20-F FY2023 (accn 0000937966-24-000008) | I57: Reportado
A58: Tie: unidades Logic + Memory vs total unidades | B58: =B54+B55-B31 -> 0 | C58: =C54+C55-C31 -> 0 | D58: =D54+D55-D31 -> 0 | E58: =E54+E55-E31 -> 0 | F58: =F54+F55-F31 -> 0 | G58: sistemas | H58: Debe ser 0 | I58: Tie
A59: Tie: ingreso Logic + Memory vs net system sales | B59: =B56+B57-B7 -> 0 | C59: =C56+C57-C7 -> 0 | D59: =D56+D57-D7 -> 0 | E59: =E56+E57-E7 -> 0 | F59: =F56+F57-F7 -> 0 | G59: EUR m | H59: Debe ser 0 | I59: Tie
A60: Mix Memory / ingreso de sistemas | B60: =B57/B7 -> 0.29768985 | C60: =C57/C7 -> 0.35337615 | D60: =D57/D7 -> 0.27138924 | E60: =E57/E7 -> 0.39384989 | F60: =F57/F7 -> 0.34404253 | G60: % | H60: Calculado: 29.8% / 35.3% / 27.1% / 39.4% / 34.4% — HBM/DDR5 empujan el ciclo de Memory | I60: Calculado
A62: 4. VENTAS NETAS POR GEOGRAFÍA (ubicación de la fábrica del cliente, Nota 3)
A63: Japón | B63: 459.3 | C63: 1008.6 | D63: 613.6 | E63: 1156 | F63: 1420.9 | G63: EUR m | H63: FY21-22: 20-F FY2022 (accn 0000937966-23-000014), Nota 3 'Segment disclosure' (geografía, new/used, clientes) | FY23-25: 20-F FY2025 (accn 0001628280-26-011378), Nota 3 | I63: Reportado
A64: Corea del Sur | B64: 6223 | C64: 6045.6 | D64: 6949.2 | E64: 6408.8 | F64: 8159.6 | G64: EUR m | H64: FY21-22: 20-F FY2022 (accn 0000937966-23-000014), Nota 3 'Segment disclosure' (geografía, new/used, clientes) | FY23-25: 20-F FY2025 (accn 0001628280-26-011378), Nota 3 | I64: Reportado
A65: Singapur | B65: 126.2 | C65: 475.5 | D65: 282.1 | E65: 285 | F65: 608.4 | G65: EUR m | H65: FY21-22: 20-F FY2022 (accn 0000937966-23-000014), Nota 3 'Segment disclosure' (geografía, new/used, clientes) | FY23-25: 20-F FY2025 (accn 0001628280-26-011378), Nota 3 | I65: Reportado
A66: Taiwán | B66: 7327.9 | C66: 8095.5 | D66: 8074.6 | E66: 4354 | F66: 8337.9 | G66: EUR m | H66: FY21-22: 20-F FY2022 (accn 0000937966-23-000014), Nota 3 'Segment disclosure' (geografía, new/used, clientes) | FY23-25: 20-F FY2025 (accn 0001628280-26-011378), Nota 3 | I66: Reportado
A67: China | B67: 2740.8 | C67: 2916 | D67: 7251.8 | E67: 10195.1 | F67: 9519.7 | G67: EUR m | H67: FY21-22: 20-F FY2022 (accn 0000937966-23-000014), Nota 3 'Segment disclosure' (geografía, new/used, clientes) | FY23-25: 20-F FY2025 (accn 0001628280-26-011378), Nota 3 | I67: Reportado
A68: Resto de Asia | B68: 1.8 | C68: 7.2 | D68: 3.9 | E68: 3.5 | F68: 2.7 | G68: EUR m | H68: FY21-22: 20-F FY2022 (accn 0000937966-23-000014), Nota 3 'Segment disclosure' (geografía, new/used, clientes) | FY23-25: 20-F FY2025 (accn 0001628280-26-011378), Nota 3 | I68: Reportado
A69: Países Bajos | B69: 14.2 | C69: 9.2 | D69: 25.1 | E69: 16.6 | F69: 4.7 | G69: EUR m | H69: FY21-22: 20-F FY2022 (accn 0000937966-23-000014), Nota 3 'Segment disclosure' (geografía, new/used, clientes) | FY23-25: 20-F FY2025 (accn 0001628280-26-011378), Nota 3 | I69: Reportado
A70: EMEA (resto) | B70: 134.6 | C70: 624.5 | D70: 1206.8 | E70: 1322.1 | F70: 524.3 | G70: EUR m | H70: FY21-22: 20-F FY2022 (accn 0000937966-23-000014), Nota 3 'Segment disclosure' (geografía, new/used, clientes) | FY23-25: 20-F FY2025 (accn 0001628280-26-011378), Nota 3 | I70: Reportado
A71: Estados Unidos | B71: 1583.2 | C71: 1991.3 | D71: 3151.4 | E71: 4521.8 | F71: 4089.1 | G71: EUR m | H71: FY21-22: 20-F FY2022 (accn 0000937966-23-000014), Nota 3 'Segment disclosure' (geografía, new/used, clientes) | FY23-25: 20-F FY2025 (accn 0001628280-26-011378), Nota 3 | I71: Reportado
A72: Total por geografía | B72: =SUM(B63:B71) -> 18611 | C72: =SUM(C63:C71) -> 21173.4 | D72: =SUM(D63:D71) -> 27558.5 | E72: =SUM(E63:E71) -> 28262.9 | F72: =SUM(F63:F71) -> 32667.3 | G72: EUR m | H72: Calculado | I72: Calculado
A73: Tie: geografía vs total ventas netas (FY21 vs Historical!B5) | B73: =B72-Historical!B5 -> 0 | C73: =C72-IS_Hist!B5 -> 0 | D73: =D72-IS_Hist!C5 -> 0 | E73: =E72-IS_Hist!D5 -> 0 | F73: =F72-IS_Hist!E5 -> 0 | G73: EUR m | H73: Debe ser 0 los cinco años | I73: Tie
A74: Mix China | B74: =B67/B72 -> 0.14726774 | C74: =C67/C72 -> 0.13771997 | D74: =D67/D72 -> 0.26314204 | E74: =E67/E72 -> 0.36072378 | F74: =F67/F72 -> 0.29141374 | G74: % | H74: Calculado: 14.7% / 13.8% / 26.3% / 36.1% / 29.1% — el driver de riesgo geopolítico más visible de la serie (controles de exportación DUV) | I74: Calculado
A75: Mix Taiwán + Corea del Sur | B75: =(B66+B64)/B72 -> 0.72811241 | C75: =(C66+C64)/C72 -> 0.66787101 | D75: =(D66+D64)/D72 -> 0.5451603 | E75: =(E66+E64)/E72 -> 0.38081018 | F75: =(F66+F64)/F72 -> 0.50501572 | G75: % | H75: Calculado — el eje leading-edge (foundry + HBM) | I75: Calculado
A77: 5. LONG-LIVED ASSETS POR GEOGRAFÍA (PP&E + right-of-use, Nota 3)
A78: Total long-lived assets | B78: 2982.7 | C78: 4136.9 | D78: 5799.8 | E78: 7234 | F78: 8234.8 | G78: EUR m | H78: FY21-22: 20-F FY2022 (accn 0000937966-23-000014), Nota 3 'Segment disclosure' (geografía, new/used, clientes) | FY23-25: 20-F FY2025 (accn 0001628280-26-011378), Nota 3 | I78: Reportado
A79: — de los cuales Países Bajos (Veldhoven) | B79: 2048.1 | C79: 2748.5 | D79: 3783.6 | E79: 4621.4 | F79: 5342.4 | G79: EUR m | H79: FY21-22: 20-F FY2022 (accn 0000937966-23-000014), Nota 3 'Segment disclosure' (geografía, new/used, clientes) | FY23-25: 20-F FY2025 (accn 0001628280-26-011378), Nota 3 | Expansiones de fábrica e investigación en Veldhoven | I79: Reportado
A80: Tie: total vs BS_Hist (PP&E neto + right-of-use; FY23-25 — el BS del modelo empieza en FY2023) | D80: =D78-(BS_Hist!B24+BS_Hist!B25) -> 0 | E80: =E78-(BS_Hist!C24+BS_Hist!C25) -> 0 | F80: =F78-(BS_Hist!D24+BS_Hist!D25) -> 0 | G80: EUR m | H80: Debe ser 0; FY21-22 sin BS de línea completa en el modelo (gap documentado en Sources_Audited!A11) — sin tie | I80: Tie
A82: 6. BACKLOG, RPO Y CONTRACT LIABILITIES (el motor de demanda)
A83: Remaining performance obligations (RPO, auditado) | B83: 28900 | C83: 45400 | D83: 45000 | E83: 43300 | F83: 46500 | G83: EUR m | H83: Nota 2 de cada 20-F: €28.9bn / €45.4bn / €45.0bn / €43.3bn / €46.5bn. FY21-22: accn 0000937966-23-000014; FY23: accn 0000937966-24-000008; FY24-25: accn 0001628280-26-011378 | I83: Reportado
A84: % del RPO a reconocer en los próximos 12 meses | B84: 0.61 | C84: 0.56 | D84: 0.57 | E84: 0.59 | F84: 0.65 | G84: % | H84: Misma nota; FY2023: 57% per 20-F FY2023 | I84: Reportado
A85: RPO / ventas netas del año | B85: =B83/B9 -> 1.5528451 | C85: =C83/C9 -> 2.1441998 | D85: =D83/D9 -> 1.63289 | E85: =E83/E9 -> 1.5320438 | F85: =F83/F9 -> 1.4234418 | G85: x | H85: Calculado: 1.55x / 2.14x / 1.63x / 1.53x / 1.42x | I85: Calculado
A86: Backlog (valor de pedidos según definición ASML, no auditado) | D86: 39000 | E86: 36000 | F86: 38797 | G86: EUR m | H86: FY2023: 'backlog of €39.0 billion' (20-F FY2023, accn 0000937966-24-000008, carta del presidente). FY2024: 'around a healthy €36 billion' (20-F FY2024, accn 0000937966-25-000009) — APROXIMADO. FY2025: €38,797m exacto (annual report IFRS, asml.com/investors — misma fuente de Sector_KPIs!B9; el 20-F dice €38.8bn). FY2021-22: no está en los 20-F del paquete — ver bloque 12 | I86: Reportado
A87: Tie: backlog FY2025 vs Sector_KPIs!B9 | F87: =F86-Sector_KPIs!B9 -> 0 | G87: EUR m | H87: Debe ser 0 | I87: Tie
A88: Contract liabilities totales (corrientes + no corrientes) | B88: 11160.9 | C88: 17750.9 | D88: 16266.5 | E88: 18196.2 | F88: 19372.6 | G88: EUR m | H88: Nota 2 (tabla de contract assets/liabilities). FY21-22: accn 0000937966-23-000014; FY23-25: accn 0001628280-26-011378 | I88: Reportado
A89: Tie: contract liabilities vs BS_Hist (corriente + no corriente; FY23-25) | D89: =D88-(BS_Hist!B33+BS_Hist!B37) -> 0 | E89: =E88-(BS_Hist!C33+BS_Hist!C37) -> 0 | F89: =F88-(BS_Hist!D33+BS_Hist!D37) -> 0 | G89: EUR m | H89: Debe ser 0 — los down payments son el colchón de caja del modelo | I89: Tie
A90: Cobertura: contract liabilities / RPO | B90: =B88/B83 -> 0.38619031 | C90: =C88/C83 -> 0.39098899 | D90: =D88/D83 -> 0.36147778 | E90: =E88/E83 -> 0.42023557 | F90: =F88/F83 -> 0.41661505 | G90: % | H90: Calculado — cuánto del backlog auditado ya está prepagado | I90: Calculado
A92: 7. CLIENTES Y CONCENTRACIÓN (Nota 3)
A93: Clientes que superan 10% de ventas netas (número) | B93: 2 | C93: 2 | D93: 2 | E93: 4 | F93: 4 | G93: clientes | H93: FY21-22: 20-F FY2022 (accn 0000937966-23-000014), Nota 3 'Segment disclosure' (geografía, new/used, clientes) | FY23-25: 20-F FY2025 (accn 0001628280-26-011378), Nota 3 | I93: Reportado
A94: Ventas netas de esos clientes (redondeado en el filing) | B94: 12500 | C94: 11800 | D94: 14900 | E94: 15200 | F94: 20000 | G94: EUR m | H94: FY21-22: 20-F FY2022 (accn 0000937966-23-000014), Nota 3 'Segment disclosure' (geografía, new/used, clientes) | FY23-25: 20-F FY2025 (accn 0001628280-26-011378), Nota 3 | El filing publica €bn con un decimal | I94: Reportado
A95: % de ventas netas reportado | B95: 0.672 | C95: 0.558 | D95: 0.539 | E95: 0.538 | F95: 0.612 | G95: % | H95: FY21-22: 20-F FY2022 (accn 0000937966-23-000014), Nota 3 'Segment disclosure' (geografía, new/used, clientes) | FY23-25: 20-F FY2025 (accn 0001628280-26-011378), Nota 3 | I95: Reportado
A96: Tie: % reportado vs monto/ventas (tol 0.005 por redondeo de €bn) | B96: =B95-B94/B9 -> 0.00035419913 | C96: =C95-C94/C9 -> 0.00069696884 | D96: =D95-D94/D9 -> -0.0016680335 | E96: =E95-E94/E9 -> 0.00019248556 | F96: =F95-F94/F9 -> -0.00023302814 | G96: pp | H96: Cruce interno de dos disclosures del mismo filing | I96: Tie
A97: Top-3 clientes: % de accounts receivable + finance receivables | B97: 0.837 | C97: 0.786 | D97: 0.644 | E97: 0.541 | F97: 0.354 | G97: % | H97: FY21-22: 20-F FY2022 (accn 0000937966-23-000014), Nota 3 'Segment disclosure' (geografía, new/used, clientes) | FY23-25: 20-F FY2025 (accn 0001628280-26-011378), Nota 3 | I97: Reportado
A99: 8. EMPLEADOS Y PRODUCTIVIDAD
A100: Promedio de empleados de nómina (FTEs) | B100: 28223 | C100: 33071 | D100: 38805 | E100: 41697 | F100: 43267 | G100: FTEs | H100: 20-F FY2025 (accn 0001628280-26-011378), sección de remuneración (razón CEO pay): serie FY2021-FY2025 uniforme | I100: Reportado
A101: Ventas netas por FTE promedio | B101: =B9*1000/B100 -> 659.42671 | C101: =C9*1000/C100 -> 640.24069 | D101: =D9*1000/D100 -> 710.1791 | E101: =E9*1000/E100 -> 677.81615 | F101: =F9*1000/F100 -> 755.01653 | G101: EUR miles / FTE | H101: Calculado: 659 / 640 / 710 / 678 / 755 | I101: Calculado
A102: Memo: FTEs de nómina al cierre del año | B102: 30842 | C102: 37643 | D102: 40747 | G102: FTEs | H102: 20-F FY2021/FY2022/FY2023 (accns 0000937966-22-000013 / 0000937966-23-000014 / 0000937966-24-000008), Item 'Our people'. FY2024-25 no localizados en la extracción del paquete — parcial, ver bloque 12 | I102: Reportado
A104: 9. COBERTURA FX Y TASAS (Nota 25 — ventana FY2024-FY2025 del 20-F FY2025)
A105: Notional forwards FX — USD | E105: 1 | F105: 1.6 | G105: USD bn | H105: 20-F FY2025 (accn 0001628280-26-011378), Nota 25 'Financial risk management' | I105: Reportado
A106: Notional forwards FX — JPY | E106: 1.1 | F106: 39.7 | G106: JPY bn | H106: 20-F FY2025 (accn 0001628280-26-011378), Nota 25 'Financial risk management' | I106: Reportado
A107: Notional forwards FX — TWD | E107: 27.6 | F107: 18 | G107: TWD bn | H107: 20-F FY2025 (accn 0001628280-26-011378), Nota 25 'Financial risk management' | I107: Reportado
A108: Notional forwards FX — KRW | E108: 66.4 | F108: 144.9 | G108: KRW bn | H108: 20-F FY2025 (accn 0001628280-26-011378), Nota 25 'Financial risk management' | I108: Reportado
A109: Notional forwards FX — CNY | E109: 1.1 | F109: 1.1 | G109: CNY bn | H109: 20-F FY2025 (accn 0001628280-26-011378), Nota 25 'Financial risk management' | I109: Reportado
A110: Sensibilidad FX +10% (monedas vs EUR) — impacto en utilidad neta | E110: -38.5 | F110: -1.6 | G110: EUR m | H110: 20-F FY2025 (accn 0001628280-26-011378), Nota 25 'Financial risk management' | I110: Reportado
...

Sheet Market_Package
A1: ASML Holding N.V. — Paquete de mercado fechado y costo de capital (EUR nativo; puente USD por el ADR)
A2: Cada input de mercado lleva fuente y FECHA con serial válido. Los enlaces al balance y a los estados son fórmulas vivas contra las hojas históricas. Los checks mecanizados viven en Checks_TieOut filas 53-60. ASML reporta en EUR; la acción cotiza en EUR (Euronext Amsterdam, listado primario) y en USD (Nasdaq, 1 acción ordinaria = 1 título).
A4: Concepto | B4: Valor | C4: Unidad | D4: Fecha del dato (as-of) | E4: Fuente | F4: Nota / método
A6: 1. PRECIO, ACCIONES Y CAPITALIZACIÓN (doble cotización)
A7: Precio de cierre — Euronext Amsterdam (EUR) | B7: 1609.4 | C7: EUR/acción | D7: 46247 | E7: stockanalysis.com/quote/ams/ASML/history — histórico diario | F7: Recuperado 2026-08-14. Cierre del 2026-08-14: 1,579.60 (memo). Listado primario en EUR.
A8: Precio de cierre — Nasdaq (USD) | B8: 1847.9 | C8: USD/acción | D8: 46247 | E8: stockanalysis.com/stocks/asml/history — histórico diario | F8: Recuperado 2026-08-14. Cierre del 2026-08-14: 1,844.46 (memo). 1 ordinaria = 1 título USD.
A9: EUR/USD (tasa de referencia del BCE) | B9: 1.1534 | C9: USD por EUR | D9: 46247 | E9: BCE — tasa de referencia diaria, vía api.frankfurter.dev/v1/2026-08-13 | F9: 2026-08-14: 1.1567 (memo). El modelo usa 1.1474 en Assumptions!E22 (as-of de la corrida de julio).
A10: Chequeo de paridad de doble cotización | B10: =B7*B9/B8-1 -> 0.0045359381 | C10: % | D10: 46247 | E10: Calculado: precio EUR × FX / precio USD − 1 | F10: +0.45% el 2026-08-13 — diferencia de horario de cierre (17:30 CET vs 16:00 EDT). El check 54 exige |·| ≤ 2%.
A11: Acciones ordinarias en circulación | B11: 385.41766 | C11: millones de acciones | D11: 46022 | E11: SEC Form 20-F FY2025, portada (accn 0001628280-26-011378): '385,417,665 Ordinary Shares' al cierre del período | F11: Conteo primario más reciente del paquete. stockanalysis 2026-08-14: 384.10m (memo — recompras del programa 2026 desde el cierre).
A12: Memo — acciones diluidas promedio FY2025 (las que usa el DCF) | B12: =Forecast!B28 -> 388.9 | C12: millones de acciones | D12: 46022 | E12: Forecast!B28 ← IS_Hist!E20 | F12: Enlace vivo. 388.9m; brecha vs portada −0.9% (check 55, tol 3%).
A13: Capitalización de mercado (EUR) | B13: =B7*B11 -> 620291.19 | C13: EUR m | D13: 46247 | E13: Calculado: precio Euronext × acciones en circulación | F13: 620,291 EUR m
A14: Memo — capitalización de mercado (USD) | B14: =B8*B11 -> 712213.3 | C14: USD m | D14: 46247 | E14: Calculado: precio Nasdaq × acciones
A16: 2. PUENTE A ENTERPRISE VALUE (balance FY2025A del propio modelo, EUR)
A17: Efectivo y equivalentes | B17: =BS_Hist!D6 -> 12916 | C17: EUR m | D17: 46022 | E17: BS_Hist!D6 — 20-F FY2025, balance auditado | F17: Enlace vivo
A18: Inversiones de corto plazo | B18: =BS_Hist!D7 -> 405.9 | C18: EUR m | D18: 46022 | E18: BS_Hist!D7 | F18: Enlace vivo
A19: Total efectivo e inversiones | B19: =B17+B18 -> 13321.9 | C19: EUR m | D19: 46022 | E19: Calculado | F19: 13,321.9
A20: Deuda de corto plazo (ECP + porción corriente de deuda LP) | B20: =BS_Hist!D32 -> 1681.9 | C20: EUR m | D20: 46022 | E20: BS_Hist!D32 | F20: Enlace vivo. Descomposición tecleada del filing en el bloque 8 y en Drivers_MDA filas 120-121.
A21: Deuda de largo plazo (no corriente) | B21: =BS_Hist!D35 -> 2709 | C21: EUR m | D21: 46022 | E21: BS_Hist!D35 | F21: Enlace vivo
A22: Deuda bruta total | B22: =B20+B21 -> 4390.9 | C22: EUR m | D22: 46022 | E22: Calculado | F22: 4,390.9 — incluye papel comercial y porción corriente
A23: Deuda neta / (caja neta) | B23: =B22-B19 -> -8931 | C23: EUR m | D23: 46022 | E23: Calculado | F23: Negativo = caja neta (−8,931.0)
A24: Enterprise value | B24: =B13+B22-B19 -> 611360.19 | C24: EUR m | D24: 46247 | E24: Calculado: cap. de mercado + deuda bruta − efectivo e inversiones | F24: Precio al 2026-08-13 contra balance al 2025-12-31 (L4)
A25: Memo — deuda usada hoy en Valuation!B15 | B25: =Forecast!B27 -> 2709 | C25: EUR m | D25: 46022 | E25: Forecast!B27 ← Historical!F19 | F25: Solo deuda LP no corriente (2,709)
A26: Memo — diferencia vs la deuda bruta de esta hoja | B26: =B22-B25 -> 1681.9 | C26: EUR m | D26: 46022 | E26: Calculado | F26: HALLAZGO H1: 1,681.9 = exactamente BS_Hist!D32 (ECP 691.7 + porción corriente 990.2). El puente del DCF omite la deuda de corto plazo. Mecanizado en el check 57.
A27: Memo — caja usada hoy en Valuation!B14 | B27: =Forecast!B26 -> 12916 | C27: EUR m | D27: 46022 | E27: Forecast!B26 | F27: Solo efectivo y equivalentes (12,916)
A28: Memo — diferencia vs el efectivo e inversiones de esta hoja | B28: =B19-B27 -> 405.9 | C28: EUR m | D28: 46022 | E28: Calculado | F28: HALLAZGO H1b: 405.9 = exactamente BS_Hist!D7 (inversiones de corto plazo omitidas del puente).
A30: 3. COSTO DE CAPITAL (EUR)
A31: Tasa libre de riesgo (Bund alemán 10 años) | B31: 0.03139 | C31: % | D31: 46247 | E31: investing.com — 'Germany 10-Year Bond Yield Historical Data', cierre 2026-08-13 | F31: Fuente secundaria (la serie primaria del Bundesbank no fue descargable en esta corrida — declarado). Cross-check: tradingeconomics ~3.15-3.20% la misma semana.
A32: Prima de riesgo de mercado (ERP implícita, S&P 500) | B32: 0.0423 | C32: % | D32: 46023 | E32: A. Damodaran (NYU Stern), 'Implied Equity Risk Premiums — United States' (histimpl.html), actualización enero 2026 | F32: ERP de mercado maduro; Países Bajos Aaa → prima país 0 (declarado, L2). Misma ERP de la corrida de flota (verificada en la auditoría del piloto Apple 2026-08-14).
A33: Beta (5 años, mensual, título USD vs S&P 500) | B33: 1.37 | C33: x | D33: 46248 | E33: stockanalysis.com/stocks/asml | F33: Proveedor; beta del título USD contra índice USD para un flujo EUR — limitación L1.
A34: Costo de capital propio (CAPM) | B34: =B31+B33*B32 -> 0.089341 | C34: % | D34: 46247 | E34: Calculado: Rf + beta × ERP | F34: 8.934%
A35: Costo de deuda antes de impuestos (construido) | B35: 0.0371 | C35: % | D35: 46247 | E35: Construcción declarada: Bund 10Y 3.139% (B31) + spread AA USD 0.57pp (= FRED BAMLC0A2CAAEY 5.20% − UST 10Y 4.63%, ambos 2026-08-13; series primarias en scratchpad/audit/kd.csv y ust.csv de la corrida de flota) | F35: No existe serie EUR IG efectiva descargable en FRED — proxy de spread entre monedas, limitación L3. Peso de la deuda 0.7%: 25pb de error mueven el WACC menos de 1pb.
A36: Memo — stack de Eurobonds vigente | B36: Cupones 0.250%-2.250%, vencimientos 2026-2032 | C36: texto | D36: 46022 | E36: 20-F FY2025 (accn 0001628280-26-011378), Nota 16 | F36: Fair value 3,590.8 vs principal 3,750.0 (95.8% del par): el mercado exige yields por encima del cupón.
A37: Memo — tasa promedio ponderada del papel comercial (ECP) | B37: 0.0203 | C37: % | D37: 46022 | E37: 20-F FY2025, Nota 16: WAIR 2.03% al 2025-12-31
A38: Tasa efectiva de impuestos (FY2025A del modelo) | B38: =-IS_Hist!E13/IS_Hist!E12 -> 0.17651958 | C38: % | D38: 46022 | E38: IS_Hist!E13 / IS_Hist!E12 | F38: Enlace vivo: 17.65%
A39: Costo de deuda después de impuestos | B39: =B35*(1-B38) -> 0.030551124 | C39: % | D39: 46247 | E39: Calculado: Kd × (1 − t)
A40: Valor de mercado del capital (E) | B40: =B13 -> 620291.19 | C40: EUR m | D40: 46247 | E40: Calculado
A41: Deuda bruta (D) | B41: =B22 -> 4390.9 | C41: EUR m | D41: 46022 | E41: Calculado | F41: Valor en libros como proxy; el fair value de los Eurobonds (3,590.8) está en B36/bloque 8.
A42: Capital total (D+E) | B42: =B40+B41 -> 624682.09 | C42: EUR m | E42: Calculado
A43: Peso del capital propio | B43: =B40/B42 -> 0.99297098 | C43: % | E43: Calculado | F43: 99.30%
A44: Peso de la deuda | B44: =B41/B42 -> 0.0070290154 | C44: % | E44: Calculado | F44: 0.70%
A45: WACC | B45: =B43*B34+B44*B39 -> 0.088927765 | C45: % | D45: 46247 | E45: Calculado: We × Ke + Wd × Kd × (1 − t) | F45: 8.893% — fórmula viva: mover B31, B32, B33 o B35 mueve el WACC
A46: Memo — WACC usado hoy en el DCF | B46: =Assumptions!E20 -> 0.085 | C46: % | D46: 46219 | E46: Assumptions!E20 (escenario activo del selector B3) | F46: 8.5% en Base
A47: Memo — diferencia (este paquete − modelo) | B47: =B45-B46 -> 0.0039277651 | C47: pp | E47: Calculado | F47: +0.393pp (H3)
A49: 4. MÚLTIPLOS IMPLÍCITOS vs FY2025A DEL MODELO (EUR)
A50: Ventas netas FY2025A | B50: =IS_Hist!E5 -> 32667.3 | C50: EUR m | D50: 46022 | E50: IS_Hist!E5 | F50: Enlace vivo
A51: Utilidad operativa FY2025A (EBIT) | B51: =IS_Hist!E10 -> 11301.4 | C51: EUR m | D51: 46022 | E51: IS_Hist!E10 | F51: Enlace vivo
A52: Depreciación y amortización FY2025A | B52: =CF_Hist!E7 -> 1025.9 | C52: EUR m | D52: 46022 | E52: CF_Hist!E7 | F52: Enlace vivo
A53: EBITDA FY2025A (calc) | B53: =B51+B52 -> 12327.3 | C53: EUR m | D53: 46022 | E53: Calculado: EBIT + D&A | F53: ASML no publica EBITDA — construcción del analista (L5)
A54: Utilidad neta FY2025A | B54: =IS_Hist!E16 -> 9609.4 | C54: EUR m | D54: 46022 | E54: IS_Hist!E16 | F54: Enlace vivo
A55: UPA diluida FY2025A (EUR) | B55: =IS_Hist!E18 -> 24.71 | C55: EUR/acción | D55: 46022 | E55: IS_Hist!E18 | F55: Enlace vivo
A56: Flujo de efectivo de operación FY2025A | B56: =CF_Hist!E22 -> 12658.5 | C56: EUR m | D56: 46022 | E56: CF_Hist!E22 | F56: Enlace vivo
A57: Capex PP&E FY2025A | B57: =-CF_Hist!E24 -> 1573.6 | C57: EUR m | D57: 46022 | E57: CF_Hist!E24 (publicado como salida negativa) | F57: Enlace vivo con signo invertido
A58: Flujo de caja libre FY2025A (CFO − capex PP&E) | B58: =B56-B57 -> 11084.9 | C58: EUR m | D58: 46022 | E58: Calculado | F58: 11,084.9 — def. del modelo (Historical). La def. del 20-F resta también intangibles (57.6) → 11,027.3 ('FCF €11.0bn' del KPI).
A59: P/E (cap. de mercado EUR / utilidad neta) | B59: =B13/B54 -> 64.55046 | C59: x | D59: 46247 | E59: Calculado | F59: 64.5x
A60: P/E (precio EUR / UPA diluida) | B60: =B7/B55 -> 65.131526 | C60: x | D60: 46247 | E60: Calculado | F60: 65.1x — difiere del anterior por la base de acciones
A61: EV / Ventas | B61: =B24/B50 -> 18.714745 | C61: x | D61: 46247 | E61: Calculado | F61: 18.7x
A62: EV / EBITDA | B62: =B24/B53 -> 49.594006 | C62: x | D62: 46247 | E62: Calculado | F62: 49.6x
A63: EV / EBIT | B63: =B24/B51 -> 54.09597 | C63: x | D63: 46247 | E63: Calculado | F63: 54.1x
A64: FCF yield (FCF / cap. de mercado) | B64: =B58/B13 -> 0.017870478 | C64: % | D64: 46247 | E64: Calculado | F64: 1.79%
A65: Dividend yield (dividendos pagados FY2025A) | B65: =-CF_Hist!E34/B13 -> 0.0041114561 | C65: % | D65: 46247 | E65: CF_Hist!E34 | F65: 0.41% — sobre lo efectivamente pagado en el año
A66: Buyback yield (recompras FY2025A) | B66: =-CF_Hist!E35/B13 -> 0.0095922691 | C66: % | D66: 46247 | E66: CF_Hist!E35 | F66: 0.96%
A67: Rendimiento total al accionista | B67: =B65+B66 -> 0.013703725 | C67: % | D67: 46247 | E67: Calculado | F67: 1.37%
A68: Memo — dividendo declarado FY2025 (EUR/acción) | B68: 7.5 | C68: EUR/acción | D68: 46022 | E68: 20-F FY2025, 'Dividend policy' | F68: Yield sobre el declarado: 7.50 / 1,609.40 = 0.47%
A70: 5. MEMO — IMPLÍCITOS DEL PROPIO DCF (para dimensionar el −59% de Valuation!B23)
A71: Precio implícito del DCF (EUR/acción) | B71: =Valuation!B18 -> 647.66861 | C71: EUR/acción | D71: 46219 | E71: Valuation!B18 | F71: 647.67 — enlace vivo
A72: Precio implícito del DCF (USD/título) | B72: =Valuation!B21 -> 743.13497 | C72: USD/título | D72: 46219 | E72: Valuation!B21 | F72: 743.13
A73: Precio de mercado que usa el modelo (USD, constante) | B73: =Assumptions!E24 -> 1815.27 | C73: USD/título | D73: 46219 | E73: Assumptions!E24 | F73: 1,815.27 as-of ~2026-07-16 — desfasado ~1 mes vs B8 (H2)
A74: Upside / (downside) del escenario Base | B74: =Valuation!B23 -> -0.59062015 | C74: % | D74: 46219 | E74: Valuation!B23 | F74: HALLAZGO H4: −59.1%. El DCF Base implica menos de la mitad del precio de mercado; visible en Valuation pero sin advertencia en 00_Cover. Esta capa lo declara; corregir drivers/terminal es decisión del dueño, no de la cobertura.
A75: P/E implícito del DCF (equity value / utilidad neta FY2025A) | B75: =Valuation!B16/IS_Hist!E16 -> 26.21166 | C75: x | D75: 46219 | E75: Calculado | F75: 26.2x contra 64.5x de mercado — la brecha es la lectura, no un error aritmético
A76: EV/EBITDA implícito del DCF | B76: =Valuation!B13/B53 -> 19.604562 | C76: x | D76: 46219 | E76: Calculado | F76: 19.6x contra 49.6x de mercado
A78: 6. CONTROL DE PROCEDENCIA (todo input de mercado con fuente y fecha serial)
A79: Inputs de mercado sujetos a control | B79: 8 | C79: conteo | E79: B7 precio EUR, B8 precio USD, B9 FX, B11 acciones, B31 Rf, B32 ERP, B33 beta, B35 Kd | F79: El resto de la hoja son enlaces vivos o cálculos
A80: Inputs sin fuente | B80: =IF(LEN(E7)=0,1,0)+IF(LEN(E8)=0,1,0)+IF(LEN(E9)=0,1,0)+IF(LEN(E11)=0,1,0)+IF(LEN(E31)=0,1,0)+IF(LEN(E32)=0,1,0)+IF(LEN(E33)=0,1,0)+IF(LEN(E35)=0,1,0) -> 0 | C80: conteo | E80: Calculado | F80: Debe ser 0
A81: Inputs sin fecha válida (ausente o texto en vez de serial) | B81: =IF(OR(LEN(D7)=0,NOT(ISNUMBER(D7))),1,0)+IF(OR(LEN(D8)=0,NOT(ISNUMBER(D8))),1,0)+IF(OR(LEN(D9)=0,NOT(ISNUMBER(D9))),1,0)+IF(OR(LEN(D11)=0,NOT(ISNUMBER(D11))),1,0)+IF(OR(LEN(D31)=0,NOT(ISNUMBER(D31))),1,0)+IF(OR(LEN(D32)=0,NOT(ISNUMBER(D32))),1,0)+IF(OR(LEN(D33)=0,NOT(ISNUMBER(D33))),1,0)+IF(OR(LEN(D35)=0,NOT(ISNUMBER(D35))),1,0) -> 0 | C81: conteo | E81: Calculado | F81: Debe ser 0 — una fecha como texto cuenta como inválida
A82: Inputs de cotización desfasados entre sí (>5 días) o paquete obsoleto (>10 días) | B82: =IF(D7<MAX(D7,D8,D9,D31)-5,1,0)+IF(D8<MAX(D7,D8,D9,D31)-5,1,0)+IF(D9<MAX(D7,D8,D9,D31)-5,1,0)+IF(D31<MAX(D7,D8,D9,D31)-5,1,0)+IF(MAX(D7,D8,D9,D31,D33)<TODAY()-10,1,0) -> 1 | C82: conteo | E82: Calculado | F82: Debe ser 0. Cubre precios, FX y Rf entre sí, y la obsolescencia del paquete completo.
A83: Estado de procedencia | B83: =IF(AND(B80=0,B81=0,B82=0),"PASS","FAIL") -> FAIL | C83: estado | E83: Calculado
A85: 7. LIMITACIONES Y HALLAZGOS
A86: H1 — El puente de deuda del DCF (Valuation!B15 ← Forecast!B27 ← Historical!F19) usa solo la deuda LP no corriente (2,709) y omite 1,681.9 de deuda de corto plazo (ECP 691.7 + porción corriente 990.2 = BS_Hist!D32). Cuantificado en B26 y mecanizado en el check 57. No se corrigió: tocar Valuation movería outputs ya gateados.
A87: H1b — El puente de caja del DCF (Valuation!B14 ← Forecast!B26) usa solo efectivo y equivalentes (12,916) y omite las inversiones de corto plazo (405.9 = BS_Hist!D7). Cuantificado en B28.
A88: H2 — Assumptions!E24 tiene el precio en duro (USD 1,815.27, as-of ~2026-07-16), hoy desfasado −1.8% vs el cierre fechado de esta hoja (B8). El check 54 lo vigila con banda de ±25%.
A89: H3 — El WACC del DCF (8.5%, escenario Base) es un juicio de escenario; el de esta hoja (8.893%) es un cálculo fechado. Diferencia +0.393pp (B47). No se cableó al DCF a propósito: rompería el diseño de escenarios Base/Bull/Bear.
A90: H4 — Valuation!B23 muestra −59.1% de downside en el escenario Base sin ninguna advertencia en 00_Cover. Los múltiplos implícitos del DCF (bloque 5: P/E 26.2x, EV/EBITDA 19.6x) contra los de mercado (64.5x / 49.6x) dimensionan la brecha: el mercado paga más del doble por el mismo flujo. Es la clase de hallazgo 'Amazon B5' del audit de flota — declarado aquí porque el gate del libro hoy no lo vigila.
A91: L1 — La beta es de proveedor (stockanalysis.com), del título USD contra el S&P 500, aplicada a un flujo EUR con Rf alemán: inconsistencia de índice declarada. Una beta propia contra el AEX/STOXX es trabajo pendiente.
A92: L2 — La ERP es la implícita de Damodaran para EE.UU./mercado maduro al 2026-01-01; el Rf es alemán al 2026-08-13. Mezcla de fechas y jurisdicciones declarada a propósito (Países Bajos Aaa → prima país 0).
A93: L3 — El Kd es una construcción (Bund + spread AA USD como proxy), no una curva EUR propia. Con Wd = 0.7%, 25pb de error mueven el WACC menos de 1pb.
A94: L4 — El EV mezcla precio del 2026-08-13 con balance del 2025-12-31 (el más reciente auditado del modelo). No hay balance intermedio en el paquete local (ASML publica 6-K trimestrales que no están espejados).
A95: L5 — EBITDA y FCF son construcciones no-GAAP del analista; la definición de FCF del 20-F resta además los intangibles.
A96: L6 — Doble cotización: la paridad Euronext × FX vs Nasdaq cerró en +0.45% el 2026-08-13 (B10); el check 54 tolera hasta 2% por horarios de cierre.
A98: 8. ANCLAS DE EXTRACCIÓN INDEPENDIENTE — constantes tecleadas del PDF del 20-F FY2025 (asml-20251231.pdf, Notas 4 y 16), NO fórmulas contra BS_Hist. Los checks 56-57 amarran el balance del modelo contra estas anclas: camino de extracción distinto (PDF/pdftotext vs R-files del build de Ola 2).
A99: Efectivo y equivalentes al 2025-12-31 (Nota 4) | B99: 12916 | C99: EUR m | D99: 46022 | E99: 20-F FY2025 (accn 0001628280-26-011378), Nota 4: depósitos 5,558.5 + money market funds 6,222.2 + bancos 1,135.3 | F99: Ancla del check 56
A100: Inversiones de corto plazo al 2025-12-31 (Nota 4) | B100: 405.9 | C100: EUR m | D100: 46022 | E100: 20-F FY2025, Nota 4 | F100: Ancla del check 56
A101: Porción corriente de deuda LP al 2025-12-31 (Nota 16) | B101: 990.2 | C101: EUR m | D101: 46022 | E101: 20-F FY2025, Nota 16 | F101: Ancla del check 57
A102: Deuda LP no corriente al 2025-12-31 (Nota 16) | B102: 2709 | C102: EUR m | D102: 46022 | E102: 20-F FY2025, Nota 16 | F102: Ancla del check 57
A103: Papel comercial (ECP) carrying al 2025-12-31 (Nota 16) | B103: 691.7 | C103: EUR m | D103: 46022 | E103: 20-F FY2025, Nota 16 | F103: Ancla del check 57
A104: Memo vintage dual — efectivo al 2024-12-31 (Nota 4) | B104: 12735.9 | C104: EUR m | D104: 45657 | E104: 20-F FY2025, Nota 4, columna 2024 | F104: Ancla FY2024 del check 56 contra BS_Hist!C6
A105: Estas anclas replican cifras del mismo 20-F por un camino de extracción distinto: cazan corrupciones de BS_Hist (clase de defecto probada en el audit de flota), no re-verifican el filing en sí. La verificación contra el filing es el muestreo del refutador.

Sheet Claude Code Log
A1: Turn # | B1: Date | C1: User Request | D1: Action Taken | E1: Details | F1: Outcome
A2: 1 | B2: 46324.359 | C2: Prepare a public model copy | D2: Remove local paths and private build references; preserve financial formulas and inputs | E2: Agent run with MOG as the tool, checked by guard v1. The guard measured every sheet before and after the run. Changed: Change_Log: 1 cell written, at E8; Gate_9of10: 4 cells written, at E5, E10, E11, E12. Agent: OpenFinmods export | F2: Compare against source and review public copy
