Workbook

Sheet EEFF
A1: Empresas Melo, S.A. y Subsidiarias
A2: Estados Financieros Auditados FY21-FY25
A3: en B/. sin escala
A5: Años | B5: FY21A | C5: FY22A | D5: FY23A | E5: FY24A | F5: FY25A | G5: FY26E | H5: FY27E | I5: FY28E | J5: FY29E | K5: FY30E
A6: Estado de Resultados
A7: Ingresos de actividades ordinarias | B7: 438114952 | C7: 467074668 | D7: 451706230 | E7: 460719410 | F7: 470347932
A8: Otros ingresos | B8: 3966219 | C8: 4392200 | D8: 11003710 | E8: 3762535 | F8: 3613091
A9: Cambios en el inventario de mercancía, productos terminados, en proceso y otros | B9: -150244827 | C9: -187077140 | D9: -173249606 | E9: -174005656 | F9: -188175458
A10: Consumo de materia prima y materiales usados | B10: -101025169 | C10: -90597120 | D10: -84145281 | E10: -83918521 | F10: -75807001
A11: Gastos de personal | B11: -74974041 | C11: -79103480 | D11: -80903627 | E11: -86329033 | F11: -88885187
A12: Depreciación y amortización | B12: -13985672 | C12: -13342976 | D12: -14036279 | E12: -14828901 | F12: -15329288
A13: Depreciación activos por derecho de uso | B13: -4161694 | C13: -3991659 | D13: -3696447 | E13: -4684964 | F13: -5404896
A14: Pérdida crediticia esperada | B14: -967420 | C14: -425576 | D14: -1225588 | E14: -1314799 | F14: -467105
A15: Otros gastos | B15: -65024491 | C15: -70360443 | D15: -80568534 | E15: -77373935 | F15: -75884685
A16: Ganancia operativa | B16: 31697857 | C16: 26568474 | D16: 24884578 | E16: 22026136 | F16: 24007403
A17: Costos financieros, netos
A18: Intereses y dividendos ganados | B18: 881939 | C18: 783585 | D18: 885958 | E18: 1130662 | F18: 1414749
A19: Intereses por arrendamiento - derecho de uso | B19: -968434 | C19: -882753 | D19: -792291 | E19: -956053 | F19: -1156672
A20: Intereses financieros | B20: -5019054 | C20: -3558962 | D20: -4663883 | E20: -4939562 | F20: -4478120
A21: Costos financieros, neto | B21: -5105549 | C21: -3658130 | D21: -4570216 | E21: -4764953 | F21: -4220043
A22: Participación en resultados integrales de asociadas | B22: 539906 | C22: 930830 | D22: 1210952 | E22: 869552 | F22: 766156
A23: Utilidad antes del impuesto sobre la renta | B23: 27132214 | C23: 23841174 | D23: 21525314 | E23: 18130735 | F23: 20553516
A24: Impuesto sobre la renta | B24: -6945729 | C24: -6379563 | D24: -3925237 | E24: -4602653 | F24: -5123047
A25: Utilidad neta | B25: 20186485 | C25: 17461611 | D25: 17600077 | E25: 13528082 | F25: 15430469
A26: Otros resultados integrales:
A27: Partidas que no se reclasificarán posteriormente
A28: Reserva para conversión de moneda extranjera | B28: -84705 | C28: 107709 | D28: 321093 | E28: 79637 | F28: 14817
A29: Total de otros resultados integrales | B29: -84705 | C29: 107709 | D29: 321093 | E29: 79637 | F29: 14817
A30: Total de resultados integrales | B30: 20101780 | C30: 17569320 | D30: 17921170 | E30: 13607719 | F30: 15445286
A32: Años | B32: FY21A | C32: FY22A | D32: FY23A | E32: FY24A | F32: FY25A | G32: FY26E | H32: FY27E | I32: FY28E | J32: FY29E | K32: FY30E
A33: Balance General
A34: Activos corrientes
A35: Efectivo y equivalentes de efectivo | B35: 12172483 | C35: 8201026 | D35: 11881528 | E35: 12820824 | F35: 18492864
A36: Documentos y cuentas por cobrar, neto | B36: 60325155 | C36: 58872294 | D36: 54894249 | E36: 54841331 | F36: 48263595
A37: Inventarios | B37: 88171572 | C37: 105633064 | D37: 106328130 | E37: 98522552 | F37: 86074972
A38: Inventario de materiales, piezas y repuestos | B38: 4258589 | C38: 5430871 | D38: 5515664 | E38: 6892253 | F38: 7251432
A39: Activos biológicos | B39: 9533860 | C39: 10662082 | D39: 9971872 | E39: 7465217 | F39: 8437671
A40: Adelantos para compra de inventarios y granos | B40: 6251470 | C40: 4920799 | D40: 11950319 | E40: 15359479 | F40: 20193108
A41: Gastos pagados por adelantado | B41: 3864487 | C41: 9230111 | D41: 2040615 | E41: 1624291 | F41: 1437596
A42: Impuesto sobre la renta pagado por adelantado | B42: 425681 | C42: 2555114 | D42: 3378806 | E42: 618474 | F42: 1553236
A43: Otros activos | B43: 233838 | C43: 214904 | D43: 9308 | E43: 9269 | F43: 10371
A44: Total de activos corrientes | B44: 185237135 | C44: 205720265 | D44: 205970491 | E44: 198153690 | F44: 191714845
A45: Activos no corrientes
A46: Efectivo y equivalentes de efectivo | D46: 0 | E46: 1400000 | F46: 0
A47: Inventario de materiales, piezas y repuestos | B47: 311258 | C47: 365289 | D47: 364529 | E47: 958317 | F47: 936271
A48: Inmuebles, mobiliarios, equipos y mejoras, neto | B48: 118176330 | C48: 118021872 | D48: 118793851 | E48: 107205696 | F48: 116379856
A49: Activo intangible, neto | D49: 0 | E49: 7095327 | F49: 6339823
A50: Equipo para arrendamiento, neto | B50: 2092260 | C50: 2003420 | D50: 3633937 | E50: 3477575 | F50: 2378222
A51: Activos por derecho de uso, neto | B51: 15786574 | C51: 15156793 | D51: 13962183 | E51: 17055964 | F51: 18159806
A52: Propiedades de inversión | B52: 148371 | C52: 261371 | D52: 261371 | E52: 261371 | F52: 148371
A53: Otras inversiones | B53: 31424 | C53: 31424 | D53: 31424 | E53: 31424 | F53: 31424
A54: Inversión en asociadas | B54: 2861083 | C54: 3638487 | D54: 4547604 | E54: 7400838 | F54: 5634822
A55: Activos biológicos | B55: 8125114 | C55: 7741648 | D55: 9201413 | E55: 9128819 | F55: 9133839
A56: Fondo de cesantía | B56: 8635712 | C56: 9721714 | D56: 10105488 | E56: 11118212 | F56: 11778683
A57: Impuesto sobre la renta diferido | B57: 1044908 | C57: 1045572 | D57: 1052947 | E57: 686286 | F57: 687558
A58: Otros activos | B58: 557678 | C58: 579758 | D58: 614722 | E58: 639691 | F58: 654787
A59: Total de activos no corrientes | B59: 157770712 | C59: 158567348 | D59: 162569469 | E59: 166459520 | F59: 172263462
A60: Total de activos | B60: 343007847 | C60: 364287613 | D60: 368539960 | E60: 364613210 | F60: 363978307
A61: Pasivos corrientes
A62: Préstamos por pagar | B62: 12760000 | C62: 14000000 | D62: 13639186 | E62: 8000000 | F62: 6900000
A63: Valores comerciales negociables | B63: 20160000 | C63: 15500000 | D63: 16029000 | E63: 13091000 | F63: 16247000
A64: Pasivos por arrendamiento | B64: 4224303 | C64: 3785984 | D64: 3552010 | E64: 4221359 | F64: 5155019
A65: Cuentas por pagar proveedores | B65: 38125871 | C65: 43123997 | D65: 36713984 | E65: 32750402 | F65: 29473014
A66: Adelantos recibidos de clientes | B66: 4071359 | C66: 1852616 | D66: 3808280 | E66: 4437544 | F66: 4357881
A67: Cuentas por pagar compañías relacionadas | B67: 2899098 | C67: 3275580 | D67: 3137075 | E67: 3230564 | F67: 2401344
A68: Impuesto sobre la renta por pagar | B68: 2908783 | C68: 0
A69: Gastos acumulados y otros pasivos | B69: 6872985 | C69: 6265107 | D69: 5462939 | E69: 6337692 | F69: 5712859
A70: Total de pasivos corrientes | B70: 92022399 | C70: 87803284 | D70: 82342474 | E70: 72068561 | F70: 70247117
A71: Pasivos no corrientes
A72: Préstamos por pagar | D72: 0 | E72: 2124600 | F72: 2124600
A73: Bonos por pagar | B73: 52466986 | C73: 67427589 | D73: 67388899 | E73: 62350209 | F73: 52311519
A74: Pasivos por arrendamiento | B74: 13843602 | C74: 13639753 | D74: 12665832 | E74: 15160872 | F74: 15351662
A75: Provisión para prima de antigüedad | B75: 9043565 | C75: 9664351 | D75: 9909963 | E75: 10236726 | F75: 10533014
A76: Total de pasivos no corrientes | B76: 75354153 | C76: 90731693 | D76: 89964694 | E76: 89872407 | F76: 80320795
A77: Total de pasivos | B77: 167376552 | C77: 178534977 | D77: 172307168 | E77: 161940968 | F77: 150567912
A78: Patrimonio
A79: Capital emitido: acciones comunes, sin valor nominal; y en circulación: 205 | B79: 31292259 | C79: 32592259 | D79: 32456289 | E79: 32456289 | F79: 33179964
A80: Utilidades no distribuidas | B80: 144629043 | C80: 153342675 | D80: 163637708 | E80: 169997522 | F80: 179997183
A81: Reserva de conversión | B81: -290007 | C81: -182298 | D81: 138795 | E81: 218431 | F81: 233248
A82: Total de patrimonio | B82: 175631295 | C82: 185752636 | D82: 196232792 | E82: 202672242 | F82: 213410395
A83: Total de pasivos y patrimonio | B83: 343007847 | C83: 364287613 | D83: 368539960 | E83: 364613210 | F83: 363978307
A85: Años | B85: FY21A | C85: FY22A | D85: FY23A | E85: FY24A | F85: FY25A | G85: FY26E | H85: FY27E | I85: FY28E | J85: FY29E | K85: FY30E
A86: Estado de Flujos de Efectivo
A87: Flujos de efectivo por las actividades de operación:
A88: Utilidad neta | B88: 20186485 | C88: 17461611 | D88: 17600077 | E88: 13528082 | F88: 15430469
A89: Ajustes por:
A90: Participación en resultados de asociadas | B90: -539906 | C90: -930830 | D90: -1210952 | E90: -869552 | F90: -766156
A91: Depreciación y amortización de inmuebles, mobiliarios, equipo y mejoras | B91: 12893750 | C91: 12462508 | D91: 13066774 | E91: 13312735 | F91: 13402269
A92: Amortización activo intangible | E92: 182380 | F92: 763104
A93: Depreciación de equipo para arrendamiento | B93: 1091922 | C93: 880468 | D93: 973473 | E93: 1264783 | F93: 1163915
A94: Depreciación de activos por derecho de uso | B94: 4161694 | C94: 3991659 | D94: 3696447 | E94: 4684964 | F94: 5404896
A95: Pérdida en venta de activo fijo | B95: 49192 | C95: -44332 | D95: -219350 | E95: 4678 | F95: 66377
A96: Ganancia en venta de valores | D96: -6443146
A97: Ingreso en cancelación y arreglos de derecho de uso | B97: -720417 | C97: -109142 | D97: -42504 | E97: -15072 | F97: 0
A98: Pérdida en venta de propiedad de inversión | E98: 0 | F98: 8000
A99: Provisión para prima de antigüedad | B99: 1664489 | C99: 1965660 | D99: 1148953 | E99: 1202654 | F99: 1226427
A100: Pérdida crediticia esperada | E100: 1314799 | F100: 467105
A101: Costos financieros, neto | B101: 5105549 | C101: 3658130 | D101: 4570216 | E101: 4764953 | F101: 4220043
A102: Impuesto sobre la renta | B102: 6945729 | C102: 6379563 | D102: 3925237 | E102: 4602653 | F102: 5123047
A103: Cambios en:
...

Sheet Notas_EEFF
A1: Empresas Melo, S.A. y Subsidiarias
A2: Notas a los Estados Financieros
A3: Fuente: informes auditados vía OCR Mistral (verbatim).
A5: Año | B5: Documento fuente | C5: Página OCR | D5: Tabla OCR / sección | E5: Nota # | F5: Título original de la nota | G5: Categoría modelable | H5: Line item EEFF | I5: Sub-line item / detalle | J5: Texto original / disclosure | K5: Monto reportado | L5: Moneda | M5: Unidad / escala | N5: Fecha / venc. / tasa / plazo | O5: Contraparte / contrato / instrumento | P5: Impacto en Supuestos | Q5: Impacto en ModeloFinanciero | R5: Link a celda EEFF | S5: Comentario de extracción | T5: Status
A6: 2022 | B6: INA_EMMELO_2022_0.pdf | C6: page-35 | D6: markdown.md | E6: 1 | F6: 1. Información general | G6: Otros | J6: Empresas Melo, S.A., (en adelante, el "Fideicomitente Emisor") y MMG Bank Corporation como Agente Fiduciario (FIDBI-006), constituyeron el Fideicomiso de Garantía mediante Escritura Pública No.19,704 del 17 de diciembre de 2009, de la Notaría Cuarta del Circuito de Panamá. | T6: OK
A7: 2022 | B7: INA_EMMELO_2022_0.pdf | C7: page-35 | D7: markdown.md | E7: 1 | F7: 1. Información general | G7: Otros | J7: El objetivo general del Fideicomiso es garantizar con los bienes que mantienen, el cumplimiento de las obligaciones adquiridas por parte del Fideicomitente. Las obligaciones por parte del Fideicomitente son derivadas de: a) la emisión de bonos corporativos rotativos de hasta B/.50,000.000, cuyo registro y oferta pública fue autorizada por la Superintendencia de Mercado de Valores de Panamá mediante Resolución CNV No.358-09 de 20 de noviembre de 2009, modificada mediante Resolución SMV-552-14 del 13 de noviembre de 2014. | K7: 50000 | L7: B/. | T7: OK
A8: 2022 | B8: INA_EMMELO_2022_0.pdf | C8: page-35 | D8: markdown.md | E8: 1 | F8: 1. Información general | G8: Otros | J8: El Fiduciario es MMG Bank Corporation ("Agente Fiduciario") es una sociedad anónima organizada y de conformidad con las leyes de la República de Panamá, autorizada para ejercer el negocio Fiduciario en o desde la República de Panamá mediante Resolución Fiduciaria No.SBP-FID.0009-2013 de 14 de junio de 2013. | T8: OK
A9: 2022 | B9: INA_EMMELO_2022_0.pdf | C9: page-35 | D9: markdown.md | E9: 1 | F9: 1. Información general | G9: Otros | J9: El negocio de Fideicomiso en Panamá está regulado mediante la ley No.1 del 5 de enero de 1984, y la Ley No.21 del 10 de mayo de 2017, así como resoluciones y acuerdos de la Superintendencia de Bancos de Panamá. | T9: OK
A10: 2022 | B10: INA_EMMELO_2022_0.pdf | C10: page-35 | D10: markdown.md | E10: 1 | F10: 1. Información general | G10: Otros | J10: Los bienes del Fideicomiso de garantía están compuestos por: | T10: OK
A11: 2022 | B11: INA_EMMELO_2022_0.pdf | C11: page-35 | D11: markdown.md | E11: 1 | F11: 1. Información general | G11: Otros | J11: - Los derechos reales derivados de la Primera Hipoteca y Anticresis que se constituye a favor del Fiduciario, sobre ciertos bienes inmuebles propiedad del Fideicomitente y/o el Garante Hipotecario y cuyo valor de mercado, según avalúo por un evaluador aceptable al Fiduciario deberá cubrir al menos un 120% del saldo insoluto a capital de los Bonos emitidos y en circulación (Ver Nota No.4). | T11: OK
A12: 2022 | B12: INA_EMMELO_2022_0.pdf | C12: page-35 | D12: markdown.md | E12: 1 | F12: 1. Información general | G12: Otros | J12: - Cesión de las pólizas de seguro contra incendios de las fincas hipotecadas a favor del Fiduciario. | T12: OK
A13: 2022 | B13: INA_EMMELO_2022_0.pdf | C13: page-35 | D13: markdown.md | E13: 1 | F13: 1. Información general | G13: Otros | J13: El total del Patrimonio del Fideicomiso es de B/.66,200,381 (2021: B/.67,125,350) de los cuales la suma de B/.66,200,381 (2021: B/.67,125,350) están conformados por el derecho real de hipoteca a favor del Fiduciario detallados en la Nota No.4. | K13: 66200381 | L13: B/. | T13: OK
A14: 2022 | B14: INA_EMMELO_2022_0.pdf | C14: page-35 | D14: markdown.md | E14: 1 | F14: 1. Información general | G14: Otros | J14: Al 31 de diciembre de 2022, la Cobertura de Garantía representa el 195%, la cual resulta de dividir el valor de mercado de los bienes inmuebles hipotecados entre el saldo insoluto a capital de los Bonos emitidos y en circulación. | T14: OK
A15: 2022 | B15: INA_EMMELO_2022_0.pdf | C15: page-35 | D15: markdown.md | E15: 1 | F15: 1. Información general | G15: Otros | J15: El Fideicomiso estará vigente hasta la fecha en que todas las obligaciones garantizadas se extingan. | T15: OK
A16: 2022 | B16: INA_EMMELO_2022_0.pdf | C16: page-35 | D16: markdown.md | E16: 1 | F16: 1. Información general | G16: Otros | J16: La oficina principal de la Fiduciaria está localizada en Costa del Este, Avenida Paseo del Mar, Edificio MMG Tower, Piso 22, Ciudad de Panamá República de Panamá. | T16: OK
A17: 2022 | B17: INA_EMMELO_2022_0.pdf | C17: page-36 | D17: markdown.md | E17: 2 | F17: 2. Bases para la preparación de los estados financieros | G17: Otros | J17: ### 2.1. Base de medición | T17: OK
A18: 2022 | B18: INA_EMMELO_2022_0.pdf | C18: page-36 | D18: markdown.md | E18: 2 | F18: 2. Bases para la preparación de los estados financieros | G18: Otros | J18: Los estados financieros del Fideicomiso de Garantía Empresas Melo S.A. (FIDBI-006) (MMG Bank Corporation como Agente Fiduciario al 31 de diciembre de 2022, fueron preparados sobre la base de costo o costo amortizado. | T18: OK
A19: 2022 | B19: INA_EMMELO_2022_0.pdf | C19: page-36 | D19: markdown.md | E19: 2 | F19: 2. Bases para la preparación de los estados financieros | G19: Otros | J19: ### 2.2. Moneda funcional y de presentación | T19: OK
A20: 2022 | B20: INA_EMMELO_2022_0.pdf | C20: page-36 | D20: markdown.md | E20: 2 | F20: 2. Bases para la preparación de los estados financieros | G20: Otros | J20: Los estados financieros están expresados en balboas (B/.), que es la moneda funcional del Fideicomiso y la unidad monetaria de la República de Panamá, la cual está a la par y es de libre cambio con el dólar (US$) de los Estados Unidos de América. La República de Panamá no emite papel moneda propio y en su lugar, el dólar (US$) de los Estados Unidos de América es utilizado como moneda de curso legal. | T20: OK
A21: 2022 | B21: INA_EMMELO_2022_0.pdf | C21: page-36 | D21: markdown.md | E21: 3 | F21: 3. Resumen de las principales políticas contables | G21: Políticas contables | J21: ### 3.1. Estimaciones y juicios realizados | T21: OK
A22: 2022 | B22: INA_EMMELO_2022_0.pdf | C22: page-36 | D22: markdown.md | E22: 3 | F22: 3. Resumen de las principales políticas contables | G22: Políticas contables | J22: La preparación de los estados financieros del Fideicomiso requiere que se realicen estimaciones y juicios contables que son evaluados de manera continua y se basan en experiencia pasadas y ciertos factores aplicables al sector, mismos que son razonables bajo las circunstancias actuales y las expectativas de sucesos futuros. | T22: OK
A23: 2022 | B23: INA_EMMELO_2022_0.pdf | C23: page-36 | D23: markdown.md | E23: 3 | F23: 3. Resumen de las principales políticas contables | G23: Políticas contables | J23: Al 31 de diciembre de 2022, el Fideicomiso no ha requerido estimaciones contables significativas. | T23: OK
A24: 2022 | B24: INA_EMMELO_2022_0.pdf | C24: page-36 | D24: markdown.md | E24: 3 | F24: 3. Resumen de las principales políticas contables | G24: Políticas contables | J24: ### 3.2. Derecho real de hipoteca | T24: OK
A25: 2022 | B25: INA_EMMELO_2022_0.pdf | C25: page-36 | D25: markdown.md | E25: 3 | F25: 3. Resumen de las principales políticas contables | G25: Políticas contables | J25: El derecho real de hipoteca sobre bienes inmuebles se reconoce como activos dentro del estado de situación financiera de acuerdo con las políticas contables de la Fiduciaria, por el monto o valor de mercado de las hipotecas constituidas a favor del Fiduciario según indica en la Escritura Pública donde consta la primera hipoteca y anticresis. | T25: OK
... A30: 2022 | B30: INA_EMMELO_2022_0.pdf | C30: page-37 | D30: markdown.md | E30: 3 | F30: 3. Resumen de las principales políticas contables | G30: Políticas contables | J30: Corresponden a desembolsos o retiros de derecho real de hipoteca que debe efectuar la administradora del Fideicomiso de conformidad y en cumplimiento con el Contrato de Fideicomiso, los cuales se reconocen como retiros al Patrimonio del Fideicomiso. | T30: OK
A31: 2022 | B31: INA_EMMELO_2022_0.pdf | C31: page-37 | D31: markdown.md | E31: 4 | F31: 4. Derecho real de hipoteca | G31: Otros | J31: Los derechos hipotecarios y anticréticos corresponden a la primera hipoteca constituida a favor del Fiduciario MMG Bank Corporation, sobre bienes inmuebles del Fideicomitente y/o del Garante Hipotecario Inmobiliaria los Libertadores, S.A., por un valor de B/.61,077,310. | K31: 61077310 | L31: B/. | T31: OK
A32: 2022 | B32: INA_EMMELO_2022_0.pdf | C32: page-37 | D32: markdown.md | E32: 4 | F32: 4. Derecho real de hipoteca | G32: Otros | J32: Los bienes inmuebles en garantía tienen un valor de mercado de B/.66,200,381 (2021: B/.67,125,350) según informe del Avaluador Panamericana de Avalúos, S.A. de fecha 30 de diciembre 2022, (2021: según informe del Avaluador Panamericana de Avalúos, S.A. de fecha diciembre 2021). | K32: 66200381 | L32: B/. | T32: OK
A33: 2022 | B33: INA_EMMELO_2022_0.pdf | C33: page-37 | D33: tbl-32.html | E33: 4 | F33: 4. Derecho real de hipoteca | G33: Otros | J33: [tbl-32.html](tbl-32.html) | T33: OK
A34: 2022 | B34: INA_EMMELO_2022_0.pdf | C34: page-37 | D34: markdown.md | E34: 5 | F34: 5. Impuesto sobre la renta | G34: Impuestos | J34: - El Decreto Ejecutivo No.170 del 27 de octubre de 1993, establece en el artículo 81 que se consideran contribuyentes el Fideicomiso constituido conforme a la Ley que generan rentas gravables. El Fideicomiso constituido de acuerdo con la Ley No.1 del 5 de enero de 1984, se considera contribuyente al Fiduciario, quien determinará el impuesto de acuerdo con las reglas generales aplicables a las personas jurídicas o naturales según sea su naturaleza. | T34: OK
A35: 2022 | B35: INA_EMMELO_2022_0.pdf | C35: page-37 | D35: markdown.md | E35: 5 | F35: 5. Impuesto sobre la renta | G35: Impuestos | J35: - De acuerdo con la legislación fiscal vigente, la renta proveniente de los intereses ganados sobre depósitos en bancos locales, están exentos del pago del impuesto sobre la renta. | T35: OK
A36: 2022 | B36: INA_EMMELO_2022_0.pdf | C36: page-37 | D36: markdown.md | E36: 5 | F36: 5. Impuesto sobre la renta | G36: Impuestos | J36: - Al 31 de diciembre de 2022, el Fideicomiso no generó renta gravable. | T36: OK
A37: 2022 | B37: INA_EMMELO_2022_0.pdf | C37: page-38 | D37: markdown.md | E37: 5 | F37: 5. Impuesto sobre la renta | G37: Impuestos | J37: Notas a los Estados Financieros Por el año terminado el 31 de diciembre de 2022 (Cifras en balboas) | T37: OK
A38: 2023 | B38: INA_EMMELO_2023_0.pdf | C38: page-34 | D38: markdown.md | E38: 1 | F38: 1. Información general | G38: Otros | J38: Empresas Melo, S.A., (en adelante, el "Fideicomitente Emisor") y MMG Bank Corporation como Agente Fiduciario (FIDBI-006), constituyeron el Fideicomiso de Garantía mediante Escritura Pública No.19,704 del 17 de diciembre de 2009, de la Notaría Cuarta del Circuito de Panamá. | T38: OK
A39: 2023 | B39: INA_EMMELO_2023_0.pdf | C39: page-34 | D39: markdown.md | E39: 1 | F39: 1. Información general | G39: Otros | J39: El objetivo general del Fideicomiso es garantizar con los bienes que mantienen, el cumplimiento de las obligaciones adquiridas por parte del Fideicomitente. Las obligaciones por parte del Fideicomitente son derivadas de: a) la emisión de bonos corporativos rotativos de hasta B/.50,000.000, cuyo registro y oferta pública fue autorizada por la Superintendencia de Mercado de Valores de Panamá mediante Resolución CNV No.358-09 de 20 de noviembre de 2009. | K39: 50000 | L39: B/. | T39: OK
A40: 2023 | B40: INA_EMMELO_2023_0.pdf | C40: page-34 | D40: markdown.md | E40: 1 | F40: 1. Información general | G40: Otros | J40: El Fiduciario es MMG Bank Corporation ("Agente Fiduciario") es una sociedad anónima organizada y de conformidad con las leyes de la República de Panamá, autorizada para ejercer el negocio Fiduciario en o desde la República de Panamá mediante Resolución Fiduciaria No.SBP-FID.0009-2013 de 14 de junio de 2013. | T40: OK
A41: 2023 | B41: INA_EMMELO_2023_0.pdf | C41: page-34 | D41: markdown.md | E41: 1 | F41: 1. Información general | G41: Otros | J41: El negocio de Fideicomiso en Panamá está regulado mediante la ley No.1 del 5 de enero de 1984, y la Ley No.21 del 10 de mayo de 2017, así como resoluciones y acuerdos de la Superintendencia de Bancos de Panamá. | T41: OK
A42: 2023 | B42: INA_EMMELO_2023_0.pdf | C42: page-34 | D42: markdown.md | E42: 1 | F42: 1. Información general | G42: Otros | J42: Los bienes del Fideicomiso de garantía están compuestos por: | T42: OK
A43: 2023 | B43: INA_EMMELO_2023_0.pdf | C43: page-34 | D43: markdown.md | E43: 1 | F43: 1. Información general | G43: Otros | J43: - Los derechos reales derivados de la Primera Hipoteca y Anticresis que se constituye a favor del Fiduciario, sobre ciertos bienes inmuebles propiedad del Fideicomitente y/o el Garante Hipotecario y cuyo valor de mercado, según avalúo por un avaluador aceptable al Fiduciario deberá cubrir al menos un 120% del saldo insoluto a capital de los Bonos emitidos y en circulación (Ver Nota No.4). | T43: OK
A44: 2023 | B44: INA_EMMELO_2023_0.pdf | C44: page-34 | D44: markdown.md | E44: 1 | F44: 1. Información general | G44: Otros | J44: - Cesión de las pólizas de seguro contra incendios de las fincas hipotecadas a favor del Fiduciario. | T44: OK
A45: 2023 | B45: INA_EMMELO_2023_0.pdf | C45: page-34 | D45: markdown.md | E45: 1 | F45: 1. Información general | G45: Otros | J45: El total del Patrimonio del Fideicomiso es de B/.57,200,381 (2022: B/.66,200,381) de los cuales la suma de B/.57,200,381 (2022: B/.66,200,381) están conformados por el derecho real de hipoteca a favor del Fiduciario detallados en la Nota No.4. | K45: 57200381 | L45: B/. | T45: OK
A46: 2023 | B46: INA_EMMELO_2023_0.pdf | C46: page-34 | D46: markdown.md | E46: 1 | F46: 1. Información general | G46: Otros | J46: Al 31 de diciembre de 2023, la Cobertura de Garantía representa el 168% (2022: 195%), la cual resulta de dividir el valor de mercado de los bienes inmuebles hipotecados entre el saldo insoluto a capital de los Bonos emitidos y en circulación. | T46: OK
A47: 2023 | B47: INA_EMMELO_2023_0.pdf | C47: page-34 | D47: markdown.md | E47: 1 | F47: 1. Información general | G47: Otros | J47: El Fideicomiso estará vigente hasta la fecha en que todas las obligaciones garantizadas se extingan. | T47: OK
A48: 2023 | B48: INA_EMMELO_2023_0.pdf | C48: page-34 | D48: markdown.md | E48: 1 | F48: 1. Información general | G48: Otros | J48: La oficina principal de la Fiduciaria está localizada en Costa del Este, Avenida Paseo del Mar, Edificio MMG Tower, Piso 22, Ciudad de Panamá República de Panamá. | T48: OK
A49: 2023 | B49: INA_EMMELO_2023_0.pdf | C49: page-35 | D49: markdown.md | E49: 2 | F49: 2. Bases para la preparación de los estados financieros | G49: Otros | J49: ### 2.1. Base de medición | T49: OK
A50: 2023 | B50: INA_EMMELO_2023_0.pdf | C50: page-35 | D50: markdown.md | E50: 2 | F50: 2. Bases para la preparación de los estados financieros | G50: Otros | J50: Los estados financieros del Fideicomiso de Garantía Empresas Melo S.A. (FIDBI-006) (MMG Bank Corporation como Agente Fiduciario al 31 de diciembre de 2023, fueron preparados sobre la base de costo o costo amortizado. | T50: OK
A51: 2023 | B51: INA_EMMELO_2023_0.pdf | C51: page-35 | D51: markdown.md | E51: 2 | F51: 2. Bases para la preparación de los estados financieros | G51: Otros | J51: ### 2.2. Moneda funcional y de presentación | T51: OK
A52: 2023 | B52: INA_EMMELO_2023_0.pdf | C52: page-35 | D52: markdown.md | E52: 2 | F52: 2. Bases para la preparación de los estados financieros | G52: Otros | J52: Los estados financieros están expresados en balboas (B/.), que es la moneda funcional del Fideicomiso y la unidad monetaria de la República de Panamá, la cual está a la par y es de libre cambio con el dólar (US$) de los Estados Unidos de América. La República de Panamá no emite papel moneda propio y en su lugar, el dólar (US$) de los Estados Unidos de América es utilizado como moneda de curso legal. | T52: OK
A53: 2023 | B53: INA_EMMELO_2023_0.pdf | C53: page-35 | D53: markdown.md | E53: 3 | F53: 3. Resumen de las principales políticas contables | G53: Políticas contables | J53: ### 3.1. Estimaciones y juicios realizados | T53: OK
A54: 2023 | B54: INA_EMMELO_2023_0.pdf | C54: page-35 | D54: markdown.md | E54: 3 | F54: 3. Resumen de las principales políticas contables | G54: Políticas contables | J54: La preparación de los estados financieros del Fideicomiso requiere que se realicen estimaciones y juicios contables que son evaluados de manera continua y se basan en experiencia pasadas y ciertos factores aplicables al sector, mismos que son razonables bajo las circunstancias actuales y las expectativas de sucesos futuros. | T54: OK
A55: 2023 | B55: INA_EMMELO_2023_0.pdf | C55: page-35 | D55: markdown.md | E55: 3 | F55: 3. Resumen de las principales políticas contables | G55: Políticas contables | J55: Al 31 de diciembre de 2023 y 2022, el Fideicomiso no ha requerido estimaciones contables significativas. | T55: OK
A56: 2023 | B56: INA_EMMELO_2023_0.pdf | C56: page-35 | D56: markdown.md | E56: 3 | F56: 3. Resumen de las principales políticas contables | G56: Políticas contables | J56: ### 3.2. Derecho real de hipoteca | T56: OK
A57: 2023 | B57: INA_EMMELO_2023_0.pdf | C57: page-35 | D57: markdown.md | E57: 3 | F57: 3. Resumen de las principales políticas contables | G57: Políticas contables | J57: El derecho real de hipoteca sobre bienes inmuebles se reconoce como activos dentro del estado de situación financiera de acuerdo con las políticas contables de la Fiduciaria, por el monto o valor de mercado de las hipotecas constituidas a favor del Fiduciario según indica en la Escritura Pública donde consta la primera hipoteca y anticresis. | T57: OK
... A62: 2023 | B62: INA_EMMELO_2023_0.pdf | C62: page-36 | D62: markdown.md | E62: 3 | F62: 3. Resumen de las principales políticas contables | G62: Políticas contables | J62: Corresponden a desembolsos o retiros de derecho real de hipoteca que debe efectuar la administradora del Fideicomiso de conformidad y en cumplimiento con el Contrato de Fideicomiso, los cuales se reconocen como retiros al Patrimonio del Fideicomiso. | T62: OK
A63: 2023 | B63: INA_EMMELO_2023_0.pdf | C63: page-36 | D63: markdown.md | E63: 4 | F63: 4. Derecho real de hipoteca | G63: Otros | J63: Los derechos hipotecarios y anticréticos corresponden a la primera hipoteca constituida a favor del Fiduciario MMG Bank Corporation, sobre bienes inmuebles del Fideicomitente y/o del Garante Hipotecario Inmobiliaria los Libertadores, S.A., por un valor de B/.61,077,310. | K63: 61077310 | L63: B/. | T63: OK
A64: 2023 | B64: INA_EMMELO_2023_0.pdf | C64: page-36 | D64: markdown.md | E64: 4 | F64: 4. Derecho real de hipoteca | G64: Otros | J64: Mediante Escritura Pública No.2,620 de 15 de marzo de 2023, el Fiduciario otorga consentimiento para cancelar parcialmente gravámenes hipotecarios y anticréticos que pesaban sobre 8 fincas de propiedad de Empresas Melo. | T64: OK
A65: 2023 | B65: INA_EMMELO_2023_0.pdf | C65: page-36 | D65: markdown.md | E65: 4 | F65: 4. Derecho real de hipoteca | G65: Otros | J65: Los bienes inmuebles en garantía tienen un valor de mercado de B/.57,200,381 (2022: B/.66,200,381) según informe del Avaluador Panamericana de Avalúos, S.A. de fecha 28 de septiembre 2023 (2022: según informe del Avaluador Panamericana de Avalúos, S.A. de fecha 30 de diciembre 2022). | K65: 57200381 | L65: B/. | T65: OK
A66: 2023 | B66: INA_EMMELO_2023_0.pdf | C66: page-36 | D66: tbl-20.html | E66: 4 | F66: 4. Derecho real de hipoteca | G66: Otros | J66: [tbl-20.html](tbl-20.html) | T66: OK
A67: 2023 | B67: INA_EMMELO_2023_0.pdf | C67: page-36 | D67: markdown.md | E67: 5 | F67: 5. Impuesto sobre la renta | G67: Impuestos | J67: - El Decreto Ejecutivo No.170 del 27 de octubre de 1993, establece en el artículo 81 que se consideran contribuyentes el Fideicomiso constituido conforme a la Ley que generan rentas gravables. El Fideicomiso constituido de acuerdo con la Ley No.1 del 5 de enero de 1984, se considera contribuyente al Fiduciario, quien determinará el impuesto de acuerdo con las reglas generales aplicables a las personas jurídicas o naturales según sea su naturaleza. | T67: OK
A68: 2023 | B68: INA_EMMELO_2023_0.pdf | C68: page-36 | D68: markdown.md | E68: 5 | F68: 5. Impuesto sobre la renta | G68: Impuestos | J68: - De acuerdo con la legislación fiscal vigente, la renta proveniente de los intereses ganados sobre depósitos en bancos locales, están exentos del pago del impuesto sobre la renta. | T68: OK
A69: 2023 | B69: INA_EMMELO_2023_0.pdf | C69: page-36 | D69: markdown.md | E69: 5 | F69: 5. Impuesto sobre la renta | G69: Impuestos | J69: - Al 31 de diciembre de 2023 y 2022, el Fideicomiso no generó renta gravable. | T69: OK
A70: 2023 | B70: INA_EMMELO_2023_0.pdf | C70: page-37 | D70: markdown.md | E70: 5 | F70: 5. Impuesto sobre la renta | G70: Impuestos | J70: Notas a los Estados Financieros Por el año terminado el 31 de diciembre de 2023 (Cifras en balboas) | T70: OK
A71: 2024 | B71: INA_EMMELO_2024_0.pdf | C71: page-30 | D71: markdown.md | E71: 1 | F71: 1. Información general | G71: Otros | J71: Empresas Melo, S.A., (en adelante, el "Fideicomitente Emisor") y MMG Bank Corporation como Agente Fiduciario (FIDBI-006), constituyeron el Fideicomiso de Garantía mediante Escritura Pública No.19,704 del 17 de diciembre de 2009, de la Notaría Cuarta del Circuito de Panamá. | T71: OK
A72: 2024 | B72: INA_EMMELO_2024_0.pdf | C72: page-30 | D72: markdown.md | E72: 1 | F72: 1. Información general | G72: Otros | J72: El objetivo general del Fideicomiso es garantizar con los bienes que mantienen, el cumplimiento de las obligaciones adquiridas por parte del Fideicomitente. Las obligaciones por parte del Fideicomitente son derivadas de: a) la emisión de bonos corporativos rotativos de hasta B/.50,000.000, cuyo registro y oferta pública fue autorizada por la Superintendencia de Mercado de Valores de Panamá mediante Resolución CNV No.358-09 de 20 de noviembre de 2009. | K72: 50000 | L72: B/. | T72: OK
A73: 2024 | B73: INA_EMMELO_2024_0.pdf | C73: page-30 | D73: markdown.md | E73: 1 | F73: 1. Información general | G73: Otros | J73: El Fiduciario es MMG Bank Corporation ("Agente Fiduciario") es una sociedad anónima organizada y de conformidad con las leyes de la República de Panamá, autorizada para ejercer el negocio Fiduciario en o desde la República de Panamá mediante Resolución Fiduciaria No.SBP-FID.0009-2013 de 14 de junio de 2013. | T73: OK
A74: 2024 | B74: INA_EMMELO_2024_0.pdf | C74: page-30 | D74: markdown.md | E74: 1 | F74: 1. Información general | G74: Otros | J74: El negocio de Fideicomiso en Panamá está regulado mediante la ley No.1 del 5 de enero de 1984, y la Ley No.21 del 10 de mayo de 2017, así como resoluciones y acuerdos de la Superintendencia de Bancos de Panamá. | T74: OK
A75: 2024 | B75: INA_EMMELO_2024_0.pdf | C75: page-30 | D75: markdown.md | E75: 1 | F75: 1. Información general | G75: Otros | J75: Los bienes del Fideicomiso de garantía están compuestos por: | T75: OK
A76: 2024 | B76: INA_EMMELO_2024_0.pdf | C76: page-30 | D76: markdown.md | E76: 1 | F76: 1. Información general | G76: Otros | J76: - Los derechos reales derivados de la Primera Hipoteca y Anticresis que se constituye a favor del Fiduciario, sobre ciertos bienes inmuebles propiedad del Fideicomitente y/o el Garante Hipotecario y cuyo valor de mercado, según avalúo por un evaluador aceptable al Fiduciario deberá cubrir al menos un 120% del saldo insoluto a capital de los Bonos emitidos y en circulación (Ver Nota No.4). | T76: OK
A77: 2024 | B77: INA_EMMELO_2024_0.pdf | C77: page-30 | D77: markdown.md | E77: 1 | F77: 1. Información general | G77: Otros | J77: - Cesión de las pólizas de seguro contra incendios de las fincas hipotecadas a favor del Fiduciario. | T77: OK
A78: 2024 | B78: INA_EMMELO_2024_0.pdf | C78: page-30 | D78: markdown.md | E78: 1 | F78: 1. Información general | G78: Otros | J78: El total del Patrimonio del Fideicomiso es de B/.66,274,750 (2023: B/.57,200,381) de los cuales la suma de B/.66,274,750 (2023: B/.57,200,381) están conformados por el derecho real de hipoteca a favor del Fiduciario detallados en la Nota No.4. | K78: 66274750 | L78: B/. | T78: OK
A79: 2024 | B79: INA_EMMELO_2024_0.pdf | C79: page-30 | D79: markdown.md | E79: 1 | F79: 1. Información general | G79: Otros | J79: Al 31 de diciembre de 2024, la Cobertura de Garantía representa el 195% (2023: 168%), la cual resulta de dividir el valor de mercado de los bienes inmuebles hipotecados entre el saldo insoluto a capital de los Bonos emitidos y en circulación. | T79: OK
A80: 2024 | B80: INA_EMMELO_2024_0.pdf | C80: page-30 | D80: markdown.md | E80: 1 | F80: 1. Información general | G80: Otros | J80: El Fideicomiso estará vigente hasta la fecha en que todas las obligaciones garantizadas se extingan. | T80: OK
A81: 2024 | B81: INA_EMMELO_2024_0.pdf | C81: page-30 | D81: markdown.md | E81: 1 | F81: 1. Información general | G81: Otros | J81: La oficina principal de la Fiduciaria está localizada en Costa del Este, Avenida Paseo del Mar, Edificio MMG Tower, Piso 22, Ciudad de Panamá República de Panamá. | T81: OK
A82: 2024 | B82: INA_EMMELO_2024_0.pdf | C82: page-31 | D82: markdown.md | E82: 2 | F82: 2. Bases para la preparación de los estados financieros | G82: Otros | J82: ### 2.1. Base de medición | T82: OK
A83: 2024 | B83: INA_EMMELO_2024_0.pdf | C83: page-31 | D83: markdown.md | E83: 2 | F83: 2. Bases para la preparación de los estados financieros | G83: Otros | J83: Los estados financieros del Fideicomiso de Garantía Empresas Melo S.A. (FIDBI-006) (MMG Bank Corporation como Agente Fiduciario al 31 de diciembre de 2024, fueron preparados sobre la base de costo o costo amortizado. | T83: OK
A84: 2024 | B84: INA_EMMELO_2024_0.pdf | C84: page-31 | D84: markdown.md | E84: 2 | F84: 2. Bases para la preparación de los estados financieros | G84: Otros | J84: ### 2.2. Moneda funcional y de presentación | T84: OK
A85: 2024 | B85: INA_EMMELO_2024_0.pdf | C85: page-31 | D85: markdown.md | E85: 2 | F85: 2. Bases para la preparación de los estados financieros | G85: Otros | J85: Los estados financieros están expresados en balboas (B/.), que es la moneda funcional del Fideicomiso y la unidad monetaria de la República de Panamá, la cual está a la par y es de libre cambio con el dólar (US$) de los Estados Unidos de América. La República de Panamá no emite papel moneda propio y en su lugar, el dólar (US$) de los Estados Unidos de América es utilizado como moneda de curso legal. | T85: OK
A86: 2024 | B86: INA_EMMELO_2024_0.pdf | C86: page-31 | D86: markdown.md | E86: 3 | F86: 3. Resumen de las principales políticas contables | G86: Políticas contables | J86: ### 3.1. Estimaciones y juicios realizados | T86: OK
A87: 2024 | B87: INA_EMMELO_2024_0.pdf | C87: page-31 | D87: markdown.md | E87: 3 | F87: 3. Resumen de las principales políticas contables | G87: Políticas contables | J87: La preparación de los estados financieros del Fideicomiso requiere que se realicen estimaciones y juicios contables que son evaluados de manera continua y se basan en experiencia pasadas y ciertos factores aplicables al sector, mismos que son razonables bajo las circunstancias actuales y las expectativas de sucesos futuros. | T87: OK
A88: 2024 | B88: INA_EMMELO_2024_0.pdf | C88: page-31 | D88: markdown.md | E88: 3 | F88: 3. Resumen de las principales políticas contables | G88: Políticas contables | J88: Al 31 de diciembre de 2024 y 2023, el Fideicomiso no ha requerido estimaciones contables significativas. | T88: OK
A89: 2024 | B89: INA_EMMELO_2024_0.pdf | C89: page-31 | D89: markdown.md | E89: 3 | F89: 3. Resumen de las principales políticas contables | G89: Políticas contables | J89: ### 3.2. Derecho real de hipoteca | T89: OK
A90: 2024 | B90: INA_EMMELO_2024_0.pdf | C90: page-31 | D90: markdown.md | E90: 3 | F90: 3. Resumen de las principales políticas contables | G90: Políticas contables | J90: El derecho real de hipoteca sobre bienes inmuebles se reconoce como activos dentro del estado de situación financiera de acuerdo con las políticas contables de la Fiduciaria, por el monto o valor de mercado de las hipotecas constituidas a favor del Fiduciario según indica en la Escritura Pública donde consta la primera hipoteca y anticresis. | T90: OK
... A94: 2024 | B94: INA_EMMELO_2024_0.pdf | C94: page-32 | D94: markdown.md | E94: 3 | F94: 3. Resumen de las principales políticas contables | G94: Políticas contables | J94: Corresponden a desembolsos o retiros de derecho real de hipoteca que debe efectuar la administradora del Fideicomiso de conformidad y en cumplimiento con el Contrato de Fideicomiso, los cuales se reconocen como retiros al Patrimonio del Fideicomiso. | T94: OK
A95: 2024 | B95: INA_EMMELO_2024_0.pdf | C95: page-32 | D95: markdown.md | E95: 4 | F95: 4. Derecho real de hipoteca | G95: Otros | J95: Los derechos hipotecarios y anticréticos corresponden a la primera hipoteca constituida a favor del Fiduciario MMG Bank Corporation, sobre bienes inmuebles del Fideicomitente y/o del Garante Hipotecario Inmobiliaria los Libertadores, S.A., por un valor de B/.61,077,310. | K95: 61077310 | L95: B/. | T95: OK
A96: 2024 | B96: INA_EMMELO_2024_0.pdf | C96: page-32 | D96: markdown.md | E96: 4 | F96: 4. Derecho real de hipoteca | G96: Otros | J96: Mediante Escritura Pública No.2,620 de 15 de marzo de 2023, el Fiduciario otorga consentimiento para cancelar parcialmente gravámenes hipotecarios y anticréticos que pesaban sobre 8 fincas de propiedad de Empresas Melo. | T96: OK
A97: 2024 | B97: INA_EMMELO_2024_0.pdf | C97: page-32 | D97: markdown.md | E97: 4 | F97: 4. Derecho real de hipoteca | G97: Otros | J97: Los bienes inmuebles en garantía tienen un valor de mercado de B/.66,274,750 (2023: B/.57,200,381) según informe del Avaluador Panamericana de Avalúos, S.A., de fecha de diciembre 2024 (2023: según informe del Avaluador Panamericana de Avalúos, S.A. de fecha 28 de septiembre 2023). | K97: 66274750 | L97: B/. | T97: OK
A98: 2024 | B98: INA_EMMELO_2024_0.pdf | C98: page-32 | D98: tbl-23.html | E98: 4 | F98: 4. Derecho real de hipoteca | G98: Otros | J98: [tbl-23.html](tbl-23.html) | T98: OK
A99: 2024 | B99: INA_EMMELO_2024_0.pdf | C99: page-32 | D99: markdown.md | E99: 5 | F99: 5. Impuesto sobre la renta | G99: Impuestos | J99: - El Decreto Ejecutivo No.170 del 27 de octubre de 1993, establece en el artículo 81 que se consideran contribuyentes el Fideicomiso constituido conforme a la Ley que generan rentas gravables. El Fideicomiso constituido de acuerdo con la Ley No.1 del 5 de enero de 1984, se considera contribuyente al Fiduciario, quien determinará el impuesto de acuerdo con las reglas generales aplicables a las personas jurídicas o naturales según sea su naturaleza. | T99: OK
A100: 2024 | B100: INA_EMMELO_2024_0.pdf | C100: page-32 | D100: markdown.md | E100: 5 | F100: 5. Impuesto sobre la renta | G100: Impuestos | J100: - De acuerdo con la legislación fiscal vigente, la renta proveniente de los intereses ganados sobre depósitos en bancos locales, están exentos del pago del impuesto sobre la renta. | T100: OK
A101: 2024 | B101: INA_EMMELO_2024_0.pdf | C101: page-32 | D101: markdown.md | E101: 5 | F101: 5. Impuesto sobre la renta | G101: Impuestos | J101: - Al 31 de diciembre de 2024 y 2023, el Fideicomiso no generó renta gravable. | T101: OK
A102: 2025 | B102: INA_EMMELO_2025_0.pdf | C102: page-40 | D102: markdown.md | E102: 1 | F102: 1. Información general | G102: Otros | J102: Empresas Melo, S.A., (en adelante, el "Fideicomitente Emisor") y MMG Bank Corporation como Agente Fiduciario (FIDBI-006), constituyeron el Fideicomiso de Garantía mediante Escritura Pública No.19,704 del 17 de diciembre de 2009, de la Notaría Cuarta del Circuito de Panamá. | T102: OK
A103: 2025 | B103: INA_EMMELO_2025_0.pdf | C103: page-40 | D103: markdown.md | E103: 1 | F103: 1. Información general | G103: Otros | J103: El objetivo general del Fideicomiso es garantizar con los bienes que mantienen, el cumplimiento de las obligaciones adquiridas por parte del Fideicomitente. Las obligaciones por parte del Fideicomitente son derivadas de la emisión de bonos corporativos rotativos de hasta B/.50,000.000, cuyo registro y oferta pública fue autorizada por la Superintendencia de Mercado de Valores de Panamá mediante Resolución CNV No.358-09 de 20 de noviembre de 2009. | K103: 50000 | L103: B/. | T103: OK
A104: 2025 | B104: INA_EMMELO_2025_0.pdf | C104: page-40 | D104: markdown.md | E104: 1 | F104: 1. Información general | G104: Otros | J104: El Fiduciario es MMG Bank Corporation ("Agente Fiduciario") es una sociedad anónima organizada y de conformidad con las leyes de la República de Panamá, autorizada para ejercer el negocio Fiduciario en o desde la República de Panamá mediante Resolución Fiduciaria No.SBP-FID.0009-2013 de 14 de junio de 2013. | T104: OK
A105: 2025 | B105: INA_EMMELO_2025_0.pdf | C105: page-40 | D105: markdown.md | E105: 1 | F105: 1. Información general | G105: Otros | J105: El negocio de Fideicomiso en Panamá está regulado mediante la ley No.1 del 5 de enero de 1984, y la Ley No.21 del 10 de mayo de 2017, así como resoluciones y acuerdos de la Superintendencia de Bancos de Panamá. | T105: OK
A106: 2025 | B106: INA_EMMELO_2025_0.pdf | C106: page-40 | D106: markdown.md | E106: 1 | F106: 1. Información general | G106: Otros | J106: Los bienes del Fideicomiso de garantía están compuestos por: | T106: OK
A107: 2025 | B107: INA_EMMELO_2025_0.pdf | C107: page-40 | D107: markdown.md | E107: 1 | F107: 1. Información general | G107: Otros | J107: - Los derechos reales derivados de la Primera Hipoteca y Anticresis que se constituye a favor del Fiduciario, sobre ciertos bienes inmuebles propiedad del Fideicomitente y/o el Garante Hipotecario y cuyo valor de mercado, según avalúo por un evaluador aceptable al Fiduciario deberá cubrir al menos un 120% del saldo insoluto a capital de los Bonos emitidos y en circulación (Ver Nota No.4). | T107: OK
A108: 2025 | B108: INA_EMMELO_2025_0.pdf | C108: page-40 | D108: markdown.md | E108: 1 | F108: 1. Información general | G108: Otros | J108: - Cesión de las pólizas de seguro contra incendios de las fincas hipotecadas a favor del Fiduciario. | T108: OK
A109: 2025 | B109: INA_EMMELO_2025_0.pdf | C109: page-40 | D109: markdown.md | E109: 1 | F109: 1. Información general | G109: Otros | J109: El total del Patrimonio del Fideicomiso es de B/.66,274,750 (2024: B/.66,274,750) de los cuales la suma de B/.66,274,750 (2024: B/.66,274,750) están conformados por el derecho real de hipoteca a favor del Fiduciario detallados en la Nota No.4. | K109: 66274750 | L109: B/. | T109: OK
A110: 2025 | B110: INA_EMMELO_2025_0.pdf | C110: page-40 | D110: markdown.md | E110: 1 | F110: 1. Información general | G110: Otros | J110: Al 31 de diciembre de 2025, la Cobertura de Garantía representa el 195% (2024: 195%), la cual resulta de dividir el valor de mercado de los bienes inmuebles hipotecados entre el saldo insoluto a capital de los Bonos emitidos y en circulación. | T110: OK
A111: 2025 | B111: INA_EMMELO_2025_0.pdf | C111: page-40 | D111: markdown.md | E111: 1 | F111: 1. Información general | G111: Otros | J111: El Fideicomiso estará vigente hasta la fecha en que todas las obligaciones garantizadas se extingan. | T111: OK
A112: 2025 | B112: INA_EMMELO_2025_0.pdf | C112: page-40 | D112: markdown.md | E112: 1 | F112: 1. Información general | G112: Otros | J112: La oficina principal de la Fiduciaria está localizada en Costa del Este, Avenida Paseo del Mar, PH MMG Tower, Piso 22, Ciudad de Panamá República de Panamá. | T112: OK
...

Sheet Supuestos
A1: Empresas Melo, S.A. y Subsidiarias
A3: COLOR KEY: Input (azul) · Fórmula (negro) · Link inter-hoja (verde)
A4: Escenario (1=Base, 2=Bull, 3=Bear)
A5: Selector escenario | C5: 1 | M5: caso | N5: NOT_DISCLOSED | Q5: Derivación mecánica declarada por el plan.
A6: Escenario activo | C6: =CHOOSE($C$5,"Base","Bull","Bear") -> Base | M6: moneda del modelo | N6: NOT_DISCLOSED | Q6: Selector de caso activo C5: Base/Bull/Bear.
A8: Años | B8: FY21A | C8: FY22A | D8: FY23A | E8: FY24A | F8: FY25A | G8: FY26E | H8: FY27E | I8: FY28E | J8: FY29E | K8: FY30E | M8: Unidad | N8: Fuente / nota | Q8: Rationale
A10: A. INGRESOS POR SEGMENTO — CRECIMIENTO (% YoY)
A11: Restaurantes — crecimiento activo | G11: =CHOOSE($C$5,G13,G14,G12) -> 0.025 | H11: =CHOOSE($C$5,H13,H14,H12) -> 0.025 | I11: =CHOOSE($C$5,I13,I14,I12) -> 0.025 | J11: =CHOOSE($C$5,J13,J14,J12) -> 0.025 | K11: =CHOOSE($C$5,K13,K14,K12) -> 0.025 | M11: % | N11: NOT_DISCLOSED | Q11: Selector de caso activo C5: Base/Bull/Bear.
A12: Bear — escenario, DRIVER_DETAIL_PENDING ticket/transacciones | G12: 0.005 | H12: 0.005 | I12: 0.005 | J12: 0.005 | K12: 0.005 | M12: moneda del modelo | N12: DRIVER_DETAIL_PENDING | Q12: Input de escenario desde fuente citada o NOT_DISCLOSED.
A13: Base — escenario, DOCUMENT_MAP §8.6 trafico/ticket | G13: 0.025 | H13: 0.025 | I13: 0.025 | J13: 0.025 | K13: 0.025 | M13: moneda del modelo | N13: label:Base — escenario, DOCUMENT_MAP §8.6 trafico/ticket | Q13: Input de escenario desde fuente citada o NOT_DISCLOSED.
A14: Bull — escenario, DRIVER_DETAIL_PENDING ticket/transacciones | G14: 0.045 | H14: 0.045 | I14: 0.045 | J14: 0.045 | K14: 0.045 | M14: moneda del modelo | N14: DRIVER_DETAIL_PENDING | Q14: Input de escenario desde fuente citada o NOT_DISCLOSED.
A15: Restaurantes ingresos hist — Nota 7/28 EMMELO | B15: 25824346 | C15: 32764624 | D15: 39061729 | E15: 45926258 | F15: 47079166 | M15: moneda del modelo | N15: label:Restaurantes ingresos hist — Nota 7/28 EMMELO | Q15: Derivación mecánica declarada por el plan.
A16: Maquinaria — crecimiento activo | G16: =CHOOSE($C$5,G18,G19,G17) -> 0.035 | H16: =CHOOSE($C$5,H18,H19,H17) -> 0.035 | I16: =CHOOSE($C$5,I18,I19,I17) -> 0.035 | J16: =CHOOSE($C$5,J18,J19,J17) -> 0.035 | K16: =CHOOSE($C$5,K18,K19,K17) -> 0.035 | M16: % | N16: NOT_DISCLOSED | Q16: Selector de caso activo C5: Base/Bull/Bear.
A17: Bear — escenario, DRIVER_DETAIL_PENDING unidades/ASP | G17: 0.015 | H17: 0.015 | I17: 0.015 | J17: 0.015 | K17: 0.015 | M17: moneda del modelo | N17: DRIVER_DETAIL_PENDING | Q17: Input de escenario desde fuente citada o NOT_DISCLOSED.
A18: Base — escenario, DOCUMENT_MAP §8.6 mercado autos +10.8% | G18: 0.035 | H18: 0.035 | I18: 0.035 | J18: 0.035 | K18: 0.035 | M18: % | N18: label:Base — escenario, DOCUMENT_MAP §8.6 mercado autos +10.8% | Q18: Input de escenario desde fuente citada o NOT_DISCLOSED.
A19: Bull — escenario, DRIVER_DETAIL_PENDING unidades/ASP | G19: 0.055 | H19: 0.055 | I19: 0.055 | J19: 0.055 | K19: 0.055 | M19: moneda del modelo | N19: DRIVER_DETAIL_PENDING | Q19: Input de escenario desde fuente citada o NOT_DISCLOSED.
A20: Maquinaria ingresos hist — Nota 7/28 EMMELO | B20: 61483016 | C20: 76982373 | D20: 76432292 | E20: 90672130 | F20: 95723653 | M20: moneda del modelo | N20: label:Maquinaria ingresos hist — Nota 7/28 EMMELO | Q20: Derivación mecánica declarada por el plan.
A21: Almacenes — crecimiento activo | G21: =CHOOSE($C$5,G23,G24,G22) -> 0.02 | H21: =CHOOSE($C$5,H23,H24,H22) -> 0.02 | I21: =CHOOSE($C$5,I23,I24,I22) -> 0.02 | J21: =CHOOSE($C$5,J23,J24,J22) -> 0.02 | K21: =CHOOSE($C$5,K23,K24,K22) -> 0.02 | M21: % | N21: NOT_DISCLOSED | Q21: Selector de caso activo C5: Base/Bull/Bear.
A22: Bear — escenario, DRIVER_DETAIL_PENDING same-store/agro index | G22: 0 | H22: 0 | I22: 0 | J22: 0 | K22: 0 | M22: moneda del modelo | N22: DRIVER_DETAIL_PENDING | Q22: Input de escenario desde fuente citada o NOT_DISCLOSED.
A23: Base — escenario, DOCUMENT_MAP §8.6 clima/precios insumos | G23: 0.02 | H23: 0.02 | I23: 0.02 | J23: 0.02 | K23: 0.02 | M23: moneda del modelo | N23: label:Base — escenario, DOCUMENT_MAP §8.6 clima/precios insumos | Q23: Input de escenario desde fuente citada o NOT_DISCLOSED.
A24: Bull — escenario, DRIVER_DETAIL_PENDING same-store/agro index | G24: 0.04 | H24: 0.04 | I24: 0.04 | J24: 0.04 | K24: 0.04 | M24: moneda del modelo | N24: DRIVER_DETAIL_PENDING | Q24: Input de escenario desde fuente citada o NOT_DISCLOSED.
A25: Almacenes ingresos hist — Nota 7/28 EMMELO | B25: 61656121 | C25: 167727756 | D25: 146014874 | E25: 143014423 | F25: 144232867 | M25: moneda del modelo | N25: label:Almacenes ingresos hist — Nota 7/28 EMMELO | Q25: Derivación mecánica declarada por el plan.
A26: Avicola — crecimiento activo | G26: =CHOOSE($C$5,G28,G29,G27) -> 0.01 | H26: =CHOOSE($C$5,H28,H29,H27) -> 0.01 | I26: =CHOOSE($C$5,I28,I29,I27) -> 0.01 | J26: =CHOOSE($C$5,J28,J29,J27) -> 0.01 | K26: =CHOOSE($C$5,K28,K29,K27) -> 0.01 | M26: % | N26: NOT_DISCLOSED | Q26: Selector de caso activo C5: Base/Bull/Bear.
A27: Bear — escenario, DRIVER_DETAIL_PENDING kg/ASP | G27: -0.01 | H27: -0.01 | I27: -0.01 | J27: -0.01 | K27: -0.01 | M27: moneda del modelo | N27: DRIVER_DETAIL_PENDING | Q27: Input de escenario desde fuente citada o NOT_DISCLOSED.
A28: Base — escenario, DOCUMENT_MAP §8.6 produccion pollo +2.9% | G28: 0.01 | H28: 0.01 | I28: 0.01 | J28: 0.01 | K28: 0.01 | M28: % | N28: label:Base — escenario, DOCUMENT_MAP §8.6 produccion pollo +2.9% | Q28: Input de escenario desde fuente citada o NOT_DISCLOSED.
A29: Bull — escenario, DRIVER_DETAIL_PENDING kg/ASP | G29: 0.03 | H29: 0.03 | I29: 0.03 | J29: 0.03 | K29: 0.03 | M29: moneda del modelo | N29: DRIVER_DETAIL_PENDING | Q29: Input de escenario desde fuente citada o NOT_DISCLOSED.
A30: Avicola ingresos hist — Nota 7/28 EMMELO | B30: 173657281 | C30: 186524815 | D30: 186914880 | E30: 179451747 | F30: 178502998 | M30: moneda del modelo | N30: label:Avicola ingresos hist — Nota 7/28 EMMELO | Q30: Derivación mecánica declarada por el plan.
A31: Otros/servicios — crecimiento activo | G31: =CHOOSE($C$5,G33,G34,G32) -> 0.005 | H31: =CHOOSE($C$5,H33,H34,H32) -> 0.005 | I31: =CHOOSE($C$5,I33,I34,I32) -> 0.005 | J31: =CHOOSE($C$5,J33,J34,J32) -> 0.005 | K31: =CHOOSE($C$5,K33,K34,K32) -> 0.005 | M31: % | N31: NOT_DISCLOSED | Q31: Selector de caso activo C5: Base/Bull/Bear.
A32: Bear — escenario residual | G32: -0.005 | H32: -0.005 | I32: -0.005 | J32: -0.005 | K32: -0.005 | M32: moneda del modelo | N32: NOT_DISCLOSED | Q32: Input de escenario desde fuente citada o NOT_DISCLOSED.
A33: Base — escenario residual | G33: 0.005 | H33: 0.005 | I33: 0.005 | J33: 0.005 | K33: 0.005 | M33: moneda del modelo | N33: NOT_DISCLOSED | Q33: Input de escenario desde fuente citada o NOT_DISCLOSED.
A34: Bull — escenario residual | G34: 0.015 | H34: 0.015 | I34: 0.015 | J34: 0.015 | K34: 0.015 | M34: moneda del modelo | N34: NOT_DISCLOSED | Q34: Input de escenario desde fuente citada o NOT_DISCLOSED.
A35: Otros/servicios hist — residual vs ingresos consolidados | B35: 115494188 | C35: 3075100 | D35: 3882455 | E35: 1654852 | F35: 4809248 | M35: moneda del modelo | N35: NOT_DISCLOSED | Q35: Derivación mecánica declarada por el plan.
A36: B. COSTOS, CAPEX Y CAPITAL DE TRABAJO
A37: Consumo materia prima % ingresos — activo | G37: =CHOOSE($C$5,G39,G40,G38) -> -0.161 | H37: =CHOOSE($C$5,H39,H40,H38) -> -0.161 | I37: =CHOOSE($C$5,I39,I40,I38) -> -0.161 | J37: =CHOOSE($C$5,J39,J40,J38) -> -0.161 | K37: =CHOOSE($C$5,K39,K40,K38) -> -0.161 | M37: % | N37: NOT_DISCLOSED | Q37: Selector de caso activo C5: Base/Bull/Bear.
A38: Bear — costo insumos escenario | G38: -0.17 | H38: -0.17 | I38: -0.17 | J38: -0.17 | K38: -0.17 | M38: moneda del modelo | N38: NOT_DISCLOSED | Q38: Input de escenario desde fuente citada o NOT_DISCLOSED.
A39: Base — FY25 EEFF!F10/F7 | G39: -0.161 | H39: -0.161 | I39: -0.161 | J39: -0.161 | K39: -0.161 | M39: moneda del modelo | N39: NOT_DISCLOSED | Q39: Input de escenario desde fuente citada o NOT_DISCLOSED.
A40: Bull — costo insumos escenario | G40: -0.15 | H40: -0.15 | I40: -0.15 | J40: -0.15 | K40: -0.15 | M40: moneda del modelo | N40: NOT_DISCLOSED | Q40: Input de escenario desde fuente citada o NOT_DISCLOSED.
A41: Consumo materia prima % ingresos hist | B41: =EEFF!B10/EEFF!B7 -> -0.23059055 | C41: =EEFF!C10/EEFF!C7 -> -0.1939671 | D41: =EEFF!D10/EEFF!D7 -> -0.1862832 | E41: =EEFF!E10/EEFF!E7 -> -0.1821467 | F41: =EEFF!F10/EEFF!F7 -> -0.16117218 | M41: % | N41: EEFF (citado por fórmula viva) | Q41: Derivación mecánica por fórmula viva.
A42: Gastos personal % ingresos — activo | G42: =CHOOSE($C$5,G44,G45,G43) -> -0.189 | H42: =CHOOSE($C$5,H44,H45,H43) -> -0.189 | I42: =CHOOSE($C$5,I44,I45,I43) -> -0.189 | J42: =CHOOSE($C$5,J44,J45,J43) -> -0.189 | K42: =CHOOSE($C$5,K44,K45,K43) -> -0.189 | M42: % | N42: NOT_DISCLOSED | Q42: Selector de caso activo C5: Base/Bull/Bear.
A43: Bear — gasto personal escenario | G43: -0.195 | H43: -0.195 | I43: -0.195 | J43: -0.195 | K43: -0.195 | M43: moneda del modelo | N43: NOT_DISCLOSED | Q43: Input de escenario desde fuente citada o NOT_DISCLOSED.
A44: Base — FY25 EEFF!F11/F7 | G44: -0.189 | H44: -0.189 | I44: -0.189 | J44: -0.189 | K44: -0.189 | M44: moneda del modelo | N44: NOT_DISCLOSED | Q44: Input de escenario desde fuente citada o NOT_DISCLOSED.
A45: Bull — gasto personal escenario | G45: -0.18 | H45: -0.18 | I45: -0.18 | J45: -0.18 | K45: -0.18 | M45: moneda del modelo | N45: NOT_DISCLOSED | Q45: Input de escenario desde fuente citada o NOT_DISCLOSED.
A46: Gastos personal % ingresos hist | B46: =EEFF!B11/EEFF!B7 -> -0.1711287 | C46: =EEFF!C11/EEFF!C7 -> -0.16935939 | D46: =EEFF!D11/EEFF!D7 -> -0.17910673 | E46: =EEFF!E11/EEFF!E7 -> -0.18737876 | F46: =EEFF!F11/EEFF!F7 -> -0.18897752 | M46: % | N46: EEFF (citado por fórmula viva) | Q46: Derivación mecánica por fórmula viva.
A47: Otros gastos % ingresos — activo | G47: =CHOOSE($C$5,G49,G50,G48) -> -0.161 | H47: =CHOOSE($C$5,H49,H50,H48) -> -0.161 | I47: =CHOOSE($C$5,I49,I50,I48) -> -0.161 | J47: =CHOOSE($C$5,J49,J50,J48) -> -0.161 | K47: =CHOOSE($C$5,K49,K50,K48) -> -0.161 | M47: % | N47: NOT_DISCLOSED | Q47: Selector de caso activo C5: Base/Bull/Bear.
A48: Bear — otros gastos escenario | G48: -0.166 | H48: -0.166 | I48: -0.166 | J48: -0.166 | K48: -0.166 | M48: moneda del modelo | N48: NOT_DISCLOSED | Q48: Input de escenario desde fuente citada o NOT_DISCLOSED.
A49: Base — FY25 EEFF!F15/F7 | G49: -0.161 | H49: -0.161 | I49: -0.161 | J49: -0.161 | K49: -0.161 | M49: moneda del modelo | N49: NOT_DISCLOSED | Q49: Input de escenario desde fuente citada o NOT_DISCLOSED.
A50: Bull — otros gastos escenario | G50: -0.155 | H50: -0.155 | I50: -0.155 | J50: -0.155 | K50: -0.155 | M50: moneda del modelo | N50: NOT_DISCLOSED | Q50: Input de escenario desde fuente citada o NOT_DISCLOSED.
A51: Otros gastos % ingresos hist | B51: =EEFF!B15/EEFF!B7 -> -0.14841879 | C51: =EEFF!C15/EEFF!C7 -> -0.15064067 | D51: =EEFF!D15/EEFF!D7 -> -0.17836489 | E51: =EEFF!E15/EEFF!E7 -> -0.16794156 | F51: =EEFF!F15/EEFF!F7 -> -0.16133734 | M51: % | N51: EEFF (citado por fórmula viva) | Q51: Derivación mecánica por fórmula viva.
A52: Capex PP&E % ingresos — activo | G52: =CHOOSE($C$5,G54,G55,G53) -> 0.033 | H52: =CHOOSE($C$5,H54,H55,H53) -> 0.033 | I52: =CHOOSE($C$5,I54,I55,I53) -> 0.033 | J52: =CHOOSE($C$5,J54,J55,J53) -> 0.033 | K52: =CHOOSE($C$5,K54,K55,K53) -> 0.033 | M52: % | N52: NOT_DISCLOSED | Q52: Selector de caso activo C5: Base/Bull/Bear.
A53: Bear — capex intensidad escenario | G53: 0.04 | H53: 0.04 | I53: 0.04 | J53: 0.04 | K53: 0.04 | M53: moneda del modelo | N53: NOT_DISCLOSED | Q53: Input de escenario desde fuente citada o NOT_DISCLOSED.
A54: Base — Nota 16 FY25 capex/ingresos | G54: 0.033 | H54: 0.033 | I54: 0.033 | J54: 0.033 | K54: 0.033 | M54: moneda del modelo | N54: label:Base — Nota 16 FY25 capex/ingresos | Q54: Input de escenario desde fuente citada o NOT_DISCLOSED.
A55: Bull — capex intensidad escenario | G55: 0.03 | H55: 0.03 | I55: 0.03 | J55: 0.03 | K55: 0.03 | M55: moneda del modelo | N55: NOT_DISCLOSED | Q55: Input de escenario desde fuente citada o NOT_DISCLOSED.
A56: Capex PP&E % ingresos hist — CF/ingresos | B56: =ABS(EEFF!B122)/EEFF!B7 -> 0.019345733 | C56: =ABS(EEFF!C122)/EEFF!C7 -> 0.026589226 | D56: =ABS(EEFF!D122)/EEFF!D7 -> 0.032359582 | E56: =ABS(EEFF!E122)/EEFF!E7 -> 0.03267329 | F56: =ABS(EEFF!F122)/EEFF!F7 -> 0.033093144 | M56: % | N56: EEFF (citado por fórmula viva) | Q56: Derivación mecánica por fórmula viva.
A57: DSO dias — activo | G57: =CHOOSE($C$5,G59,G60,G58) -> 37 | H57: =CHOOSE($C$5,H59,H60,H58) -> 37 | I57: =CHOOSE($C$5,I59,I60,I58) -> 37 | J57: =CHOOSE($C$5,J59,J60,J58) -> 37 | K57: =CHOOSE($C$5,K59,K60,K58) -> 37 | M57: días | N57: NOT_DISCLOSED | Q57: Selector de caso activo C5: Base/Bull/Bear.
A58: Bear — DSO escenario | G58: 42 | H58: 42 | I58: 42 | J58: 42 | K58: 42 | M58: moneda del modelo | N58: NOT_DISCLOSED | Q58: Input de escenario desde fuente citada o NOT_DISCLOSED.
A59: Base — FY25 AR/ingresos*365 | G59: 37 | H59: 37 | I59: 37 | J59: 37 | K59: 37 | M59: moneda del modelo | N59: NOT_DISCLOSED | Q59: Input de escenario desde fuente citada o NOT_DISCLOSED.
A60: Bull — DSO escenario | G60: 34 | H60: 34 | I60: 34 | J60: 34 | K60: 34 | M60: moneda del modelo | N60: NOT_DISCLOSED | Q60: Input de escenario desde fuente citada o NOT_DISCLOSED.
A61: DSO dias hist | B61: =EEFF!B36/EEFF!B7*365 -> 50.257772 | C61: =EEFF!C36/EEFF!C7*365 -> 46.006321 | D61: =EEFF!D36/EEFF!D7*365 -> 44.35715 | E61: =EEFF!E36/EEFF!E7*365 -> 43.447455 | F61: =EEFF!F36/EEFF!F7*365 -> 37.453576 | M61: días | N61: EEFF (citado por fórmula viva) | Q61: Derivación mecánica por fórmula viva.
A62: Inventario dias — activo | G62: =CHOOSE($C$5,G64,G65,G63) -> 415 | H62: =CHOOSE($C$5,H64,H65,H63) -> 415 | I62: =CHOOSE($C$5,I64,I65,I63) -> 415 | J62: =CHOOSE($C$5,J64,J65,J63) -> 415 | K62: =CHOOSE($C$5,K64,K65,K63) -> 415 | M62: días | N62: NOT_DISCLOSED | Q62: Selector de caso activo C5: Base/Bull/Bear.
A63: Bear — inventario dias escenario | G63: 430 | H63: 430 | I63: 430 | J63: 430 | K63: 430 | M63: días | N63: NOT_DISCLOSED | Q63: Input de escenario desde fuente citada o NOT_DISCLOSED.
A64: Base — FY25 inventario/consumo*365 | G64: 415 | H64: 415 | I64: 415 | J64: 415 | K64: 415 | M64: moneda del modelo | N64: NOT_DISCLOSED | Q64: Input de escenario desde fuente citada o NOT_DISCLOSED.
A65: Bull — inventario dias escenario | G65: 390 | H65: 390 | I65: 390 | J65: 390 | K65: 390 | M65: días | N65: NOT_DISCLOSED | Q65: Input de escenario desde fuente citada o NOT_DISCLOSED.
A66: Inventario dias hist | B66: =EEFF!B37/ABS(EEFF!B10)*365 -> 318.56045 | C66: =EEFF!C37/ABS(EEFF!C10)*365 -> 425.5772 | D66: =EEFF!D37/ABS(EEFF!D10)*365 -> 461.22334 | E66: =EEFF!E37/ABS(EEFF!E10)*365 -> 428.51961 | F66: =EEFF!F37/ABS(EEFF!F10)*365 -> 414.43883 | M66: días | N66: EEFF (citado por fórmula viva) | Q66: Derivación mecánica por fórmula viva.
A67: DPO proveedores y relacionadas — activo | G67: =CHOOSE($C$5,G69,G70,G68) -> 154 | H67: =CHOOSE($C$5,H69,H70,H68) -> 154 | I67: =CHOOSE($C$5,I69,I70,I68) -> 154 | J67: =CHOOSE($C$5,J69,J70,J68) -> 154 | K67: =CHOOSE($C$5,K69,K70,K68) -> 154 | M67: moneda del modelo | N67: NOT_DISCLOSED | Q67: Selector de caso activo C5: Base/Bull/Bear.
A68: Bear — DPO escenario | G68: 145 | H68: 145 | I68: 145 | J68: 145 | K68: 145 | M68: moneda del modelo | N68: NOT_DISCLOSED | Q68: Input de escenario desde fuente citada o NOT_DISCLOSED.
A69: Base — FY25 AP+relacionadas/consumo*365 | G69: 154 | H69: 154 | I69: 154 | J69: 154 | K69: 154 | M69: moneda del modelo | N69: NOT_DISCLOSED | Q69: Input de escenario desde fuente citada o NOT_DISCLOSED.
A70: Bull — DPO escenario | G70: 165 | H70: 165 | I70: 165 | J70: 165 | K70: 165 | M70: moneda del modelo | N70: NOT_DISCLOSED | Q70: Input de escenario desde fuente citada o NOT_DISCLOSED.
A71: DPO proveedores y relacionadas hist | B71: =(EEFF!B65+EEFF!B67)/ABS(EEFF!B10)*365 -> 148.22161 | C71: =(EEFF!C65+EEFF!C67)/ABS(EEFF!C10)*365 -> 186.93581 | D71: =(EEFF!D65+EEFF!D67)/ABS(EEFF!D10)*365 -> 172.86337 | E71: =(EEFF!E65+EEFF!E67)/ABS(EEFF!E10)*365 -> 156.49767 | F71: =(EEFF!F65+EEFF!F67)/ABS(EEFF!F10)*365 -> 153.47053 | M71: % | N71: EEFF (citado por fórmula viva) | Q71: Derivación mecánica por fórmula viva.

Sheet ModeloFinanciero
A1: Empresas Melo, S.A. y Subsidiarias
A2: Estados Financieros Auditados FY21-FY25
A3: en B/. sin escala
A5: Años | B5: FY21A | C5: FY22A | D5: FY23A | E5: FY24A | F5: FY25A | G5: FY26E | H5: FY27E | I5: FY28E | J5: FY29E | K5: FY30E
A6: Estado de Resultados
A7: Ingresos de actividades ordinarias | B7: =EEFF!B7 -> 438114952 | C7: =EEFF!C7 -> 467074668 | D7: =EEFF!D7 -> 451706230 | E7: =EEFF!E7 -> 460719410 | F7: =EEFF!F7 -> 470347932 | G7: =F7*(1+(Supuestos!G11*0.100094+Supuestos!G16*0.203517+Supuestos!G21*0.306651+Supuestos!G26*0.379513+Supuestos!G31*0.010225)) -> 4.7956897e+08 | H7: =G7*(1+(Supuestos!H11*0.100094+Supuestos!H16*0.203517+Supuestos!H21*0.306651+Supuestos!H26*0.379513+Supuestos!H31*0.010225)) -> 4.8897079e+08 | I7: =H7*(1+(Supuestos!I11*0.100094+Supuestos!I16*0.203517+Supuestos!I21*0.306651+Supuestos!I26*0.379513+Supuestos!I31*0.010225)) -> 4.9855692e+08 | J7: =I7*(1+(Supuestos!J11*0.100094+Supuestos!J16*0.203517+Supuestos!J21*0.306651+Supuestos!J26*0.379513+Supuestos!J31*0.010225)) -> 5.0833099e+08 | K7: =J7*(1+(Supuestos!K11*0.100094+Supuestos!K16*0.203517+Supuestos!K21*0.306651+Supuestos!K26*0.379513+Supuestos!K31*0.010225)) -> 5.1829668e+08
A8: Otros ingresos | B8: =EEFF!B8 -> 3966219 | C8: =EEFF!C8 -> 4392200 | D8: =EEFF!D8 -> 11003710 | E8: =EEFF!E8 -> 3762535 | F8: =EEFF!F8 -> 3613091 | G8: =F8 -> 3613091 | H8: =G8 -> 3613091 | I8: =H8 -> 3613091 | J8: =I8 -> 3613091 | K8: =J8 -> 3613091
A9: Cambios en el inventario de mercancía, productos terminados, en proceso y otros | B9: =EEFF!B9 -> -150244827 | C9: =EEFF!C9 -> -187077140 | D9: =EEFF!D9 -> -173249606 | E9: =EEFF!E9 -> -174005656 | F9: =EEFF!F9 -> -188175458 | G9: =F9 -> -188175458 | H9: =G9 -> -188175458 | I9: =H9 -> -188175458 | J9: =I9 -> -188175458 | K9: =J9 -> -188175458
A10: Consumo de materia prima y materiales usados | B10: =EEFF!B10 -> -101025169 | C10: =EEFF!C10 -> -90597120 | D10: =EEFF!D10 -> -84145281 | E10: =EEFF!E10 -> -83918521 | F10: =EEFF!F10 -> -75807001 | G10: =G7*Supuestos!G37 -> -77210604 | H10: =H7*Supuestos!H37 -> -78724297 | I10: =I7*Supuestos!I37 -> -80267664 | J10: =J7*Supuestos!J37 -> -81841290 | K10: =K7*Supuestos!K37 -> -83445765
A11: Gastos de personal | B11: =EEFF!B11 -> -74974041 | C11: =EEFF!C11 -> -79103480 | D11: =EEFF!D11 -> -80903627 | E11: =EEFF!E11 -> -86329033 | F11: =EEFF!F11 -> -88885187 | G11: =G7*Supuestos!G42 -> -90638536 | H11: =H7*Supuestos!H42 -> -92415479 | I11: =I7*Supuestos!I42 -> -94227258 | J11: =J7*Supuestos!J42 -> -96074557 | K11: =K7*Supuestos!K42 -> -97958072
A12: Depreciación y amortización | B12: =EEFF!B12 -> -13985672 | C12: =EEFF!C12 -> -13342976 | D12: =EEFF!D12 -> -14036279 | E12: =EEFF!E12 -> -14828901 | F12: =EEFF!F12 -> -15329288 | G12: =F12 -> -15329288 | H12: =G12 -> -15329288 | I12: =H12 -> -15329288 | J12: =I12 -> -15329288 | K12: =J12 -> -15329288
A13: Depreciación activos por derecho de uso | B13: =EEFF!B13 -> -4161694 | C13: =EEFF!C13 -> -3991659 | D13: =EEFF!D13 -> -3696447 | E13: =EEFF!E13 -> -4684964 | F13: =EEFF!F13 -> -5404896 | G13: =F13 -> -5404896 | H13: =G13 -> -5404896 | I13: =H13 -> -5404896 | J13: =I13 -> -5404896 | K13: =J13 -> -5404896
A14: Pérdida crediticia esperada | B14: =EEFF!B14 -> -967420 | C14: =EEFF!C14 -> -425576 | D14: =EEFF!D14 -> -1225588 | E14: =EEFF!E14 -> -1314799 | F14: =EEFF!F14 -> -467105 | G14: =F14 -> -467105 | H14: =G14 -> -467105 | I14: =H14 -> -467105 | J14: =I14 -> -467105 | K14: =J14 -> -467105
A15: Otros gastos | B15: =EEFF!B15 -> -65024491 | C15: =EEFF!C15 -> -70360443 | D15: =EEFF!D15 -> -80568534 | E15: =EEFF!E15 -> -77373935 | F15: =EEFF!F15 -> -75884685 | G15: =G7*Supuestos!G47 -> -77210604 | H15: =H7*Supuestos!H47 -> -78724297 | I15: =I7*Supuestos!I47 -> -80267664 | J15: =J7*Supuestos!J47 -> -81841290 | K15: =K7*Supuestos!K47 -> -83445765
A16: Ganancia operativa | B16: =EEFF!B16 -> 31697857 | C16: =EEFF!C16 -> 26568474 | D16: =EEFF!D16 -> 24884578 | E16: =EEFF!E16 -> 22026136 | F16: =EEFF!F16 -> 24007403 | G16: =G7+G8+G9+G10+G11+G12+G13+G14+G15 -> 28745571 | H16: =H7+H8+H9+H10+H11+H12+H13+H14+H15 -> 33343059 | I16: =I7+I8+I9+I10+I11+I12+I13+I14+I15 -> 38030679 | J16: =J7+J8+J9+J10+J11+J12+J13+J14+J15 -> 42810199 | K16: =K7+K8+K9+K10+K11+K12+K13+K14+K15 -> 47683419
A18: Costos financieros, netos
A19: Intereses y dividendos ganados | B19: =EEFF!B18 -> 881939 | C19: =EEFF!C18 -> 783585 | D19: =EEFF!D18 -> 885958 | E19: =EEFF!E18 -> 1130662 | F19: =EEFF!F18 -> 1414749 | G19: =F19 -> 1414749 | H19: =G19 -> 1414749 | I19: =H19 -> 1414749 | J19: =I19 -> 1414749 | K19: =J19 -> 1414749
A20: Intereses por arrendamiento - derecho de uso | B20: =EEFF!B19 -> -968434 | C20: =EEFF!C19 -> -882753 | D20: =EEFF!D19 -> -792291 | E20: =EEFF!E19 -> -956053 | F20: =EEFF!F19 -> -1156672 | G20: =F20 -> -1156672 | H20: =G20 -> -1156672 | I20: =H20 -> -1156672 | J20: =I20 -> -1156672 | K20: =J20 -> -1156672
A21: Intereses financieros | B21: =EEFF!B20 -> -5019054 | C21: =EEFF!C20 -> -3558962 | D21: =EEFF!D20 -> -4663883 | E21: =EEFF!E20 -> -4939562 | F21: =EEFF!F20 -> -4478120 | G21: =F21 -> -4478120 | H21: =G21 -> -4478120 | I21: =H21 -> -4478120 | J21: =I21 -> -4478120 | K21: =J21 -> -4478120
A22: Costos financieros, neto | B22: =EEFF!B21 -> -5105549 | C22: =EEFF!C21 -> -3658130 | D22: =EEFF!D21 -> -4570216 | E22: =EEFF!E21 -> -4764953 | F22: =EEFF!F21 -> -4220043 | G22: =G19+G20+G21 -> -4220043 | H22: =H19+H20+H21 -> -4220043 | I22: =I19+I20+I21 -> -4220043 | J22: =J19+J20+J21 -> -4220043 | K22: =K19+K20+K21 -> -4220043
A23: Participación en resultados integrales de asociadas | B23: =EEFF!B22 -> 539906 | C23: =EEFF!C22 -> 930830 | D23: =EEFF!D22 -> 1210952 | E23: =EEFF!E22 -> 869552 | F23: =EEFF!F22 -> 766156 | G23: =F23 -> 766156 | H23: =G23 -> 766156 | I23: =H23 -> 766156 | J23: =I23 -> 766156 | K23: =J23 -> 766156
A24: Utilidad antes del impuesto sobre la renta | B24: =EEFF!B23 -> 27132214 | C24: =EEFF!C23 -> 23841174 | D24: =EEFF!D23 -> 21525314 | E24: =EEFF!E23 -> 18130735 | F24: =EEFF!F23 -> 20553516 | G24: =G16+G22+G23 -> 25291684 | H24: =H16+H22+H23 -> 29889172 | I24: =I16+I22+I23 -> 34576792 | J24: =J16+J22+J23 -> 39356312 | K24: =K16+K22+K23 -> 44229532
A25: Impuesto sobre la renta | B25: =EEFF!B24 -> -6945729 | C25: =EEFF!C24 -> -6379563 | D25: =EEFF!D24 -> -3925237 | E25: =EEFF!E24 -> -4602653 | F25: =EEFF!F24 -> -5123047 | G25: =F25 -> -5123047 | H25: =G25 -> -5123047 | I25: =H25 -> -5123047 | J25: =I25 -> -5123047 | K25: =J25 -> -5123047
A26: Utilidad neta | B26: =EEFF!B25 -> 20186485 | C26: =EEFF!C25 -> 17461611 | D26: =EEFF!D25 -> 17600077 | E26: =EEFF!E25 -> 13528082 | F26: =EEFF!F25 -> 15430469 | G26: =G24+G25 -> 20168637 | H26: =H24+H25 -> 24766125 | I26: =I24+I25 -> 29453745 | J26: =J24+J25 -> 34233265 | K26: =K24+K25 -> 39106485
A28: Otros resultados integrales:
A29: Partidas que no se reclasificarán posteriormente
A30: Reserva para conversión de moneda extranjera | B30: =EEFF!B28 -> -84705 | C30: =EEFF!C28 -> 107709 | D30: =EEFF!D28 -> 321093 | E30: =EEFF!E28 -> 79637 | F30: =EEFF!F28 -> 14817 | G30: =F30 -> 14817 | H30: =G30 -> 14817 | I30: =H30 -> 14817 | J30: =I30 -> 14817 | K30: =J30 -> 14817
A31: Total de otros resultados integrales | B31: =EEFF!B29 -> -84705 | C31: =EEFF!C29 -> 107709 | D31: =EEFF!D29 -> 321093 | E31: =EEFF!E29 -> 79637 | F31: =EEFF!F29 -> 14817 | G31: =G30 -> 14817 | H31: =H30 -> 14817 | I31: =I30 -> 14817 | J31: =J30 -> 14817 | K31: =K30 -> 14817
A32: Total de resultados integrales | B32: =EEFF!B30 -> 20101780 | C32: =EEFF!C30 -> 17569320 | D32: =EEFF!D30 -> 17921170 | E32: =EEFF!E30 -> 13607719 | F32: =EEFF!F30 -> 15445286 | G32: =G26+G31 -> 20183454 | H32: =H26+H31 -> 24780942 | I32: =I26+I31 -> 29468562 | J32: =J26+J31 -> 34248082 | K32: =K26+K31 -> 39121302
A34: Años | B34: FY21A | C34: FY22A | D34: FY23A | E34: FY24A | F34: FY25A | G34: FY26E | H34: FY27E | I34: FY28E | J34: FY29E | K34: FY30E
A35: Balance General
A36: Activos corrientes
A37: Efectivo conciliado (puente conciliación: efectivo BS - plazo fijo) | B37: =B39 -> 12172483 | C37: =C39 -> 8201026 | D37: =D39 -> 11881528 | E37: =E39-E38 -> 10820824 | F37: =F39-F38 -> 10492864 | G37: =G39-G38 -> 10492864 | H37: =H39-H38 -> 10492864 | I37: =I39-I38 -> 10492864 | J37: =J39-J38 -> 10492864 | K37: =K39-K38 -> 10492864
A38: Depósitos a plazo fijo incluidos en efectivo BS (saldo corriente; fuente Nota 8: EMMELO_2024 lines 5734-5739; INA_2025_full lines 9918-9942; parsed EEFF BS rows 54/65/81, CF rows 172/229) | E38: =2000000 -> 2000000 | F38: =8000000 -> 8000000 | G38: =F38 -> 8000000 | H38: =G38 -> 8000000 | I38: =H38 -> 8000000 | J38: =I38 -> 8000000 | K38: =J38 -> 8000000
A39: Efectivo y equivalentes de efectivo | B39: =EEFF!B35 -> 12172483 | C39: =EEFF!C35 -> 8201026 | D39: =EEFF!D35 -> 11881528 | E39: =EEFF!E35 -> 12820824 | F39: =EEFF!F35 -> 18492864 | G39: =F39 -> 18492864 | H39: =G39 -> 18492864 | I39: =H39 -> 18492864 | J39: =I39 -> 18492864 | K39: =J39 -> 18492864
A40: Documentos y cuentas por cobrar, neto | B40: =EEFF!B36 -> 60325155 | C40: =EEFF!C36 -> 58872294 | D40: =EEFF!D36 -> 54894249 | E40: =EEFF!E36 -> 54841331 | F40: =EEFF!F36 -> 48263595 | G40: =F40 -> 48263595 | H40: =G40 -> 48263595 | I40: =H40 -> 48263595 | J40: =I40 -> 48263595 | K40: =J40 -> 48263595
A41: Inventarios | B41: =EEFF!B37 -> 88171572 | C41: =EEFF!C37 -> 105633064 | D41: =EEFF!D37 -> 106328130 | E41: =EEFF!E37 -> 98522552 | F41: =EEFF!F37 -> 86074972 | G41: =F41 -> 86074972 | H41: =G41 -> 86074972 | I41: =H41 -> 86074972 | J41: =I41 -> 86074972 | K41: =J41 -> 86074972
A42: Inventario de materiales, piezas y repuestos | B42: =EEFF!B38 -> 4258589 | C42: =EEFF!C38 -> 5430871 | D42: =EEFF!D38 -> 5515664 | E42: =EEFF!E38 -> 6892253 | F42: =EEFF!F38 -> 7251432 | G42: =F42 -> 7251432 | H42: =G42 -> 7251432 | I42: =H42 -> 7251432 | J42: =I42 -> 7251432 | K42: =J42 -> 7251432
A43: Activos biológicos | B43: =EEFF!B39 -> 9533860 | C43: =EEFF!C39 -> 10662082 | D43: =EEFF!D39 -> 9971872 | E43: =EEFF!E39 -> 7465217 | F43: =EEFF!F39 -> 8437671 | G43: =F43 -> 8437671 | H43: =G43 -> 8437671 | I43: =H43 -> 8437671 | J43: =I43 -> 8437671 | K43: =J43 -> 8437671
A44: Adelantos para compra de inventarios y granos | B44: =EEFF!B40 -> 6251470 | C44: =EEFF!C40 -> 4920799 | D44: =EEFF!D40 -> 11950319 | E44: =EEFF!E40 -> 15359479 | F44: =EEFF!F40 -> 20193108 | G44: =F44 -> 20193108 | H44: =G44 -> 20193108 | I44: =H44 -> 20193108 | J44: =I44 -> 20193108 | K44: =J44 -> 20193108
A45: Gastos pagados por adelantado | B45: =EEFF!B41 -> 3864487 | C45: =EEFF!C41 -> 9230111 | D45: =EEFF!D41 -> 2040615 | E45: =EEFF!E41 -> 1624291 | F45: =EEFF!F41 -> 1437596 | G45: =F45 -> 1437596 | H45: =G45 -> 1437596 | I45: =H45 -> 1437596 | J45: =I45 -> 1437596 | K45: =J45 -> 1437596
A46: Impuesto sobre la renta pagado por adelantado | B46: =EEFF!B42 -> 425681 | C46: =EEFF!C42 -> 2555114 | D46: =EEFF!D42 -> 3378806 | E46: =EEFF!E42 -> 618474 | F46: =EEFF!F42 -> 1553236 | G46: =F46 -> 1553236 | H46: =G46 -> 1553236 | I46: =H46 -> 1553236 | J46: =I46 -> 1553236 | K46: =J46 -> 1553236
A47: Otros activos | B47: =EEFF!B43 -> 233838 | C47: =EEFF!C43 -> 214904 | D47: =EEFF!D43 -> 9308 | E47: =EEFF!E43 -> 9269 | F47: =EEFF!F43 -> 10371 | G47: =F47 -> 10371 | H47: =G47 -> 10371 | I47: =H47 -> 10371 | J47: =I47 -> 10371 | K47: =J47 -> 10371
A48: Total de activos corrientes | B48: =EEFF!B44 -> 185237135 | C48: =EEFF!C44 -> 205720265 | D48: =EEFF!D44 -> 205970491 | E48: =EEFF!E44 -> 198153690 | F48: =EEFF!F44 -> 191714845 | G48: =F48 -> 191714845 | H48: =G48 -> 191714845 | I48: =H48 -> 191714845 | J48: =I48 -> 191714845 | K48: =J48 -> 191714845
A50: Activos no corrientes
A51: Efectivo y equivalentes de efectivo | B51: =EEFF!B46 -> 0 | C51: =EEFF!C46 -> 0 | D51: =EEFF!D46 -> 0 | E51: =EEFF!E46 -> 1400000 | F51: =EEFF!F46 -> 0 | G51: =F51 -> 0 | H51: =G51 -> 0 | I51: =H51 -> 0 | J51: =I51 -> 0 | K51: =J51 -> 0
A52: Inventario de materiales, piezas y repuestos | B52: =EEFF!B47 -> 311258 | C52: =EEFF!C47 -> 365289 | D52: =EEFF!D47 -> 364529 | E52: =EEFF!E47 -> 958317 | F52: =EEFF!F47 -> 936271 | G52: =F52 -> 936271 | H52: =G52 -> 936271 | I52: =H52 -> 936271 | J52: =I52 -> 936271 | K52: =J52 -> 936271
A53: Inmuebles, mobiliarios, equipos y mejoras, neto | B53: =EEFF!B48 -> 118176330 | C53: =EEFF!C48 -> 118021872 | D53: =EEFF!D48 -> 118793851 | E53: =EEFF!E48 -> 107205696 | F53: =EEFF!F48 -> 116379856 | G53: =F53 -> 116379856 | H53: =G53 -> 116379856 | I53: =H53 -> 116379856 | J53: =I53 -> 116379856 | K53: =J53 -> 116379856
A54: Activo intangible, neto | B54: =EEFF!B49 -> 0 | C54: =EEFF!C49 -> 0 | D54: =EEFF!D49 -> 0 | E54: =EEFF!E49 -> 7095327 | F54: =EEFF!F49 -> 6339823 | G54: =F54 -> 6339823 | H54: =G54 -> 6339823 | I54: =H54 -> 6339823 | J54: =I54 -> 6339823 | K54: =J54 -> 6339823
A55: Equipo para arrendamiento, neto | B55: =EEFF!B50 -> 2092260 | C55: =EEFF!C50 -> 2003420 | D55: =EEFF!D50 -> 3633937 | E55: =EEFF!E50 -> 3477575 | F55: =EEFF!F50 -> 2378222 | G55: =F55 -> 2378222 | H55: =G55 -> 2378222 | I55: =H55 -> 2378222 | J55: =I55 -> 2378222 | K55: =J55 -> 2378222
A56: Activos por derecho de uso, neto | B56: =EEFF!B51 -> 15786574 | C56: =EEFF!C51 -> 15156793 | D56: =EEFF!D51 -> 13962183 | E56: =EEFF!E51 -> 17055964 | F56: =EEFF!F51 -> 18159806 | G56: =F56 -> 18159806 | H56: =G56 -> 18159806 | I56: =H56 -> 18159806 | J56: =I56 -> 18159806 | K56: =J56 -> 18159806
A57: Propiedades de inversión | B57: =EEFF!B52 -> 148371 | C57: =EEFF!C52 -> 261371 | D57: =EEFF!D52 -> 261371 | E57: =EEFF!E52 -> 261371 | F57: =EEFF!F52 -> 148371 | G57: =F57 -> 148371 | H57: =G57 -> 148371 | I57: =H57 -> 148371 | J57: =I57 -> 148371 | K57: =J57 -> 148371
A58: Otras inversiones | B58: =EEFF!B53 -> 31424 | C58: =EEFF!C53 -> 31424 | D58: =EEFF!D53 -> 31424 | E58: =EEFF!E53 -> 31424 | F58: =EEFF!F53 -> 31424 | G58: =F58 -> 31424 | H58: =G58 -> 31424 | I58: =H58 -> 31424 | J58: =I58 -> 31424 | K58: =J58 -> 31424
A59: Inversión en asociadas | B59: =EEFF!B54 -> 2861083 | C59: =EEFF!C54 -> 3638487 | D59: =EEFF!D54 -> 4547604 | E59: =EEFF!E54 -> 7400838 | F59: =EEFF!F54 -> 5634822 | G59: =F59 -> 5634822 | H59: =G59 -> 5634822 | I59: =H59 -> 5634822 | J59: =I59 -> 5634822 | K59: =J59 -> 5634822
A60: Activos biológicos | B60: =EEFF!B55 -> 8125114 | C60: =EEFF!C55 -> 7741648 | D60: =EEFF!D55 -> 9201413 | E60: =EEFF!E55 -> 9128819 | F60: =EEFF!F55 -> 9133839 | G60: =F60 -> 9133839 | H60: =G60 -> 9133839 | I60: =H60 -> 9133839 | J60: =I60 -> 9133839 | K60: =J60 -> 9133839
A61: Fondo de cesantía | B61: =EEFF!B56 -> 8635712 | C61: =EEFF!C56 -> 9721714 | D61: =EEFF!D56 -> 10105488 | E61: =EEFF!E56 -> 11118212 | F61: =EEFF!F56 -> 11778683 | G61: =F61 -> 11778683 | H61: =G61 -> 11778683 | I61: =H61 -> 11778683 | J61: =I61 -> 11778683 | K61: =J61 -> 11778683
A62: Impuesto sobre la renta diferido | B62: =EEFF!B57 -> 1044908 | C62: =EEFF!C57 -> 1045572 | D62: =EEFF!D57 -> 1052947 | E62: =EEFF!E57 -> 686286 | F62: =EEFF!F57 -> 687558 | G62: =F62 -> 687558 | H62: =G62 -> 687558 | I62: =H62 -> 687558 | J62: =I62 -> 687558 | K62: =J62 -> 687558
... A65: Total de activos | B65: =EEFF!B60 -> 343007847 | C65: =EEFF!C60 -> 364287613 | D65: =EEFF!D60 -> 368539960 | E65: =EEFF!E60 -> 364613210 | F65: =EEFF!F60 -> 363978307 | G65: =F65 -> 363978307 | H65: =G65 -> 363978307 | I65: =H65 -> 363978307 | J65: =I65 -> 363978307 | K65: =J65 -> 363978307
A67: Pasivos corrientes
A68: Préstamos por pagar | B68: =EEFF!B62 -> 12760000 | C68: =EEFF!C62 -> 14000000 | D68: =EEFF!D62 -> 13639186 | E68: =EEFF!E62 -> 8000000 | F68: =EEFF!F62 -> 6900000 | G68: =F68 -> 6900000 | H68: =G68 -> 6900000 | I68: =H68 -> 6900000 | J68: =I68 -> 6900000 | K68: =J68 -> 6900000
A69: Valores comerciales negociables | B69: =EEFF!B63 -> 20160000 | C69: =EEFF!C63 -> 15500000 | D69: =EEFF!D63 -> 16029000 | E69: =EEFF!E63 -> 13091000 | F69: =EEFF!F63 -> 16247000 | G69: =F69 -> 16247000 | H69: =G69 -> 16247000 | I69: =H69 -> 16247000 | J69: =I69 -> 16247000 | K69: =J69 -> 16247000
A70: Pasivos por arrendamiento | B70: =EEFF!B64 -> 4224303 | C70: =EEFF!C64 -> 3785984 | D70: =EEFF!D64 -> 3552010 | E70: =EEFF!E64 -> 4221359 | F70: =EEFF!F64 -> 5155019 | G70: =F70 -> 5155019 | H70: =G70 -> 5155019 | I70: =H70 -> 5155019 | J70: =I70 -> 5155019 | K70: =J70 -> 5155019
A71: Cuentas por pagar proveedores | B71: =EEFF!B65 -> 38125871 | C71: =EEFF!C65 -> 43123997 | D71: =EEFF!D65 -> 36713984 | E71: =EEFF!E65 -> 32750402 | F71: =EEFF!F65 -> 29473014 | G71: =F71 -> 29473014 | H71: =G71 -> 29473014 | I71: =H71 -> 29473014 | J71: =I71 -> 29473014 | K71: =J71 -> 29473014
A72: Adelantos recibidos de clientes | B72: =EEFF!B66 -> 4071359 | C72: =EEFF!C66 -> 1852616 | D72: =EEFF!D66 -> 3808280 | E72: =EEFF!E66 -> 4437544 | F72: =EEFF!F66 -> 4357881 | G72: =F72 -> 4357881 | H72: =G72 -> 4357881 | I72: =H72 -> 4357881 | J72: =I72 -> 4357881 | K72: =J72 -> 4357881
A73: Cuentas por pagar compañías relacionadas | B73: =EEFF!B67 -> 2899098 | C73: =EEFF!C67 -> 3275580 | D73: =EEFF!D67 -> 3137075 | E73: =EEFF!E67 -> 3230564 | F73: =EEFF!F67 -> 2401344 | G73: =F73 -> 2401344 | H73: =G73 -> 2401344 | I73: =H73 -> 2401344 | J73: =I73 -> 2401344 | K73: =J73 -> 2401344
A74: Impuesto sobre la renta por pagar | B74: =EEFF!B68 -> 2908783 | C74: =EEFF!C68 -> 0 | D74: =EEFF!D68 -> 0 | E74: =EEFF!E68 -> 0 | F74: =EEFF!F68 -> 0
A75: Gastos acumulados y otros pasivos | B75: =EEFF!B69 -> 6872985 | C75: =EEFF!C69 -> 6265107 | D75: =EEFF!D69 -> 5462939 | E75: =EEFF!E69 -> 6337692 | F75: =EEFF!F69 -> 5712859 | G75: =F75 -> 5712859 | H75: =G75 -> 5712859 | I75: =H75 -> 5712859 | J75: =I75 -> 5712859 | K75: =J75 -> 5712859
A76: Total de pasivos corrientes | B76: =EEFF!B70 -> 92022399 | C76: =EEFF!C70 -> 87803284 | D76: =EEFF!D70 -> 82342474 | E76: =EEFF!E70 -> 72068561 | F76: =EEFF!F70 -> 70247117 | G76: =F76 -> 70247117 | H76: =G76 -> 70247117 | I76: =H76 -> 70247117 | J76: =I76 -> 70247117 | K76: =J76 -> 70247117
A78: Pasivos no corrientes
A79: Préstamos por pagar | B79: =EEFF!B72 -> 0 | C79: =EEFF!C72 -> 0 | D79: =EEFF!D72 -> 0 | E79: =EEFF!E72 -> 2124600 | F79: =EEFF!F72 -> 2124600 | G79: =F79 -> 2124600 | H79: =G79 -> 2124600 | I79: =H79 -> 2124600 | J79: =I79 -> 2124600 | K79: =J79 -> 2124600
A80: Bonos por pagar | B80: =EEFF!B73 -> 52466986 | C80: =EEFF!C73 -> 67427589 | D80: =EEFF!D73 -> 67388899 | E80: =EEFF!E73 -> 62350209 | F80: =EEFF!F73 -> 52311519 | G80: =F80 -> 52311519 | H80: =G80 -> 52311519 | I80: =H80 -> 52311519 | J80: =I80 -> 52311519 | K80: =J80 -> 52311519
A81: Pasivos por arrendamiento | B81: =EEFF!B74 -> 13843602 | C81: =EEFF!C74 -> 13639753 | D81: =EEFF!D74 -> 12665832 | E81: =EEFF!E74 -> 15160872 | F81: =EEFF!F74 -> 15351662 | G81: =F81 -> 15351662 | H81: =G81 -> 15351662 | I81: =H81 -> 15351662 | J81: =I81 -> 15351662 | K81: =J81 -> 15351662
A82: Provisión para prima de antigüedad | B82: =EEFF!B75 -> 9043565 | C82: =EEFF!C75 -> 9664351 | D82: =EEFF!D75 -> 9909963 | E82: =EEFF!E75 -> 10236726 | F82: =EEFF!F75 -> 10533014 | G82: =F82 -> 10533014 | H82: =G82 -> 10533014 | I82: =H82 -> 10533014 | J82: =I82 -> 10533014 | K82: =J82 -> 10533014
A83: Total de pasivos no corrientes | B83: =EEFF!B76 -> 75354153 | C83: =EEFF!C76 -> 90731693 | D83: =EEFF!D76 -> 89964694 | E83: =EEFF!E76 -> 89872407 | F83: =EEFF!F76 -> 80320795 | G83: =F83 -> 80320795 | H83: =G83 -> 80320795 | I83: =H83 -> 80320795 | J83: =I83 -> 80320795 | K83: =J83 -> 80320795
A84: Total de pasivos | B84: =EEFF!B77 -> 167376552 | C84: =EEFF!C77 -> 178534977 | D84: =EEFF!D77 -> 172307168 | E84: =EEFF!E77 -> 161940968 | F84: =EEFF!F77 -> 150567912 | G84: =F84 -> 150567912 | H84: =G84 -> 150567912 | I84: =H84 -> 150567912 | J84: =I84 -> 150567912 | K84: =J84 -> 150567912
A86: Patrimonio
A87: Capital emitido: acciones comunes, sin valor nominal; y en circulación: 205 | B87: =EEFF!B79 -> 31292259 | C87: =EEFF!C79 -> 32592259 | D87: =EEFF!D79 -> 32456289 | E87: =EEFF!E79 -> 32456289 | F87: =EEFF!F79 -> 33179964 | G87: =F87 -> 33179964 | H87: =G87 -> 33179964 | I87: =H87 -> 33179964 | J87: =I87 -> 33179964 | K87: =J87 -> 33179964
A88: Utilidades no distribuidas | B88: =EEFF!B80 -> 144629043 | C88: =EEFF!C80 -> 153342675 | D88: =EEFF!D80 -> 163637708 | E88: =EEFF!E80 -> 169997522 | F88: =EEFF!F80 -> 179997183 | G88: =F88 -> 179997183 | H88: =G88 -> 179997183 | I88: =H88 -> 179997183 | J88: =I88 -> 179997183 | K88: =J88 -> 179997183
A89: Reserva de conversión | B89: =EEFF!B81 -> -290007 | C89: =EEFF!C81 -> -182298 | D89: =EEFF!D81 -> 138795 | E89: =EEFF!E81 -> 218431 | F89: =EEFF!F81 -> 233248 | G89: =F89 -> 233248 | H89: =G89 -> 233248 | I89: =H89 -> 233248 | J89: =I89 -> 233248 | K89: =J89 -> 233248
A90: Total de patrimonio | B90: =EEFF!B82 -> 175631295 | C90: =EEFF!C82 -> 185752636 | D90: =EEFF!D82 -> 196232792 | E90: =EEFF!E82 -> 202672242 | F90: =EEFF!F82 -> 213410395 | G90: =F90 -> 213410395 | H90: =G90 -> 213410395 | I90: =H90 -> 213410395 | J90: =I90 -> 213410395 | K90: =J90 -> 213410395
A91: Total de pasivos y patrimonio | B91: =EEFF!B83 -> 343007847 | C91: =EEFF!C83 -> 364287613 | D91: =EEFF!D83 -> 368539960 | E91: =EEFF!E83 -> 364613210 | F91: =EEFF!F83 -> 363978307 | G91: =F91 -> 363978307 | H91: =G91 -> 363978307 | I91: =H91 -> 363978307 | J91: =I91 -> 363978307 | K91: =J91 -> 363978307
A93: Años | B93: FY21A | C93: FY22A | D93: FY23A | E93: FY24A | F93: FY25A | G93: FY26E | H93: FY27E | I93: FY28E | J93: FY29E | K93: FY30E
A94: Estado de Flujos de Efectivo
A95: Flujos de efectivo por las actividades de operación:
A96: Utilidad neta | B96: =EEFF!B88 -> 20186485 | C96: =EEFF!C88 -> 17461611 | D96: =EEFF!D88 -> 17600077 | E96: =EEFF!E88 -> 13528082 | F96: =EEFF!F88 -> 15430469 | G96: =F96 -> 15430469 | H96: =G96 -> 15430469 | I96: =H96 -> 15430469 | J96: =I96 -> 15430469 | K96: =J96 -> 15430469
A98: Ajustes por:
A99: Participación en resultados de asociadas | B99: =EEFF!B90 -> -539906 | C99: =EEFF!C90 -> -930830 | D99: =EEFF!D90 -> -1210952 | E99: =EEFF!E90 -> -869552 | F99: =EEFF!F90 -> -766156 | G99: =F99 -> -766156 | H99: =G99 -> -766156 | I99: =H99 -> -766156 | J99: =I99 -> -766156 | K99: =J99 -> -766156
A100: Depreciación y amortización de inmuebles, mobiliarios, equipo y mejoras | B100: =EEFF!B91 -> 12893750 | C100: =EEFF!C91 -> 12462508 | D100: =EEFF!D91 -> 13066774 | E100: =EEFF!E91 -> 13312735 | F100: =EEFF!F91 -> 13402269 | G100: =F100 -> 13402269 | H100: =G100 -> 13402269 | I100: =H100 -> 13402269 | J100: =I100 -> 13402269 | K100: =J100 -> 13402269
A101: Amortización activo intangible | B101: =EEFF!B92 -> 0 | C101: =EEFF!C92 -> 0 | D101: =EEFF!D92 -> 0 | E101: =EEFF!E92 -> 182380 | F101: =EEFF!F92 -> 763104 | G101: =F101 -> 763104 | H101: =G101 -> 763104 | I101: =H101 -> 763104 | J101: =I101 -> 763104 | K101: =J101 -> 763104
A102: Depreciación de equipo para arrendamiento | B102: =EEFF!B93 -> 1091922 | C102: =EEFF!C93 -> 880468 | D102: =EEFF!D93 -> 973473 | E102: =EEFF!E93 -> 1264783 | F102: =EEFF!F93 -> 1163915 | G102: =F102 -> 1163915 | H102: =G102 -> 1163915 | I102: =H102 -> 1163915 | J102: =I102 -> 1163915 | K102: =J102 -> 1163915
A103: Depreciación de activos por derecho de uso | B103: =EEFF!B94 -> 4161694 | C103: =EEFF!C94 -> 3991659 | D103: =EEFF!D94 -> 3696447 | E103: =EEFF!E94 -> 4684964 | F103: =EEFF!F94 -> 5404896 | G103: =F103 -> 5404896 | H103: =G103 -> 5404896 | I103: =H103 -> 5404896 | J103: =I103 -> 5404896 | K103: =J103 -> 5404896
A104: Pérdida en venta de activo fijo | B104: =EEFF!B95 -> 49192 | C104: =EEFF!C95 -> -44332 | D104: =EEFF!D95 -> -219350 | E104: =EEFF!E95 -> 4678 | F104: =EEFF!F95 -> 66377 | G104: =F104 -> 66377 | H104: =G104 -> 66377 | I104: =H104 -> 66377 | J104: =I104 -> 66377 | K104: =J104 -> 66377
A105: Ganancia en venta de valores | B105: =EEFF!B96 -> 0 | C105: =EEFF!C96 -> 0 | D105: =EEFF!D96 -> -6443146 | E105: =EEFF!E96 -> 0 | F105: =EEFF!F96 -> 0
A106: Ingreso en cancelación y arreglos de derecho de uso | B106: =EEFF!B97 -> -720417 | C106: =EEFF!C97 -> -109142 | D106: =EEFF!D97 -> -42504 | E106: =EEFF!E97 -> -15072 | F106: =EEFF!F97 -> 0 | G106: =F106 -> 0 | H106: =G106 -> 0 | I106: =H106 -> 0 | J106: =I106 -> 0 | K106: =J106 -> 0
A107: Pérdida en venta de propiedad de inversión | B107: =EEFF!B98 -> 0 | C107: =EEFF!C98 -> 0 | D107: =EEFF!D98 -> 0 | E107: =EEFF!E98 -> 0 | F107: =EEFF!F98 -> 8000 | G107: =F107 -> 8000 | H107: =G107 -> 8000 | I107: =H107 -> 8000 | J107: =I107 -> 8000 | K107: =J107 -> 8000
A108: Provisión para prima de antigüedad | B108: =EEFF!B99 -> 1664489 | C108: =EEFF!C99 -> 1965660 | D108: =EEFF!D99 -> 1148953 | E108: =EEFF!E99 -> 1202654 | F108: =EEFF!F99 -> 1226427 | G108: =F108 -> 1226427 | H108: =G108 -> 1226427 | I108: =H108 -> 1226427 | J108: =I108 -> 1226427 | K108: =J108 -> 1226427
A109: Pérdida crediticia esperada | B109: =EEFF!B100 -> 0 | C109: =EEFF!C100 -> 0 | D109: =EEFF!D100 -> 0 | E109: =EEFF!E100 -> 1314799 | F109: =EEFF!F100 -> 467105 | G109: =F109 -> 467105 | H109: =G109 -> 467105 | I109: =H109 -> 467105 | J109: =I109 -> 467105 | K109: =J109 -> 467105
A110: Costos financieros, neto | B110: =EEFF!B101 -> 5105549 | C110: =EEFF!C101 -> 3658130 | D110: =EEFF!D101 -> 4570216 | E110: =EEFF!E101 -> 4764953 | F110: =EEFF!F101 -> 4220043 | G110: =F110 -> 4220043 | H110: =G110 -> 4220043 | I110: =H110 -> 4220043 | J110: =I110 -> 4220043 | K110: =J110 -> 4220043
A111: Impuesto sobre la renta | B111: =EEFF!B102 -> 6945729 | C111: =EEFF!C102 -> 6379563 | D111: =EEFF!D102 -> 3925237 | E111: =EEFF!E102 -> 4602653 | F111: =EEFF!F102 -> 5123047 | G111: =F111 -> 5123047 | H111: =G111 -> 5123047 | I111: =H111 -> 5123047 | J111: =I111 -> 5123047 | K111: =J111 -> 5123047
A113: Cambios en:
...

Sheet _CHECKS
A1: Empresas Melo, S.A. y Subsidiarias
A2: _CHECKS panel — operating-EBITDA template, live formulas, known residuals signed visible
A3: Status semantics: PASS = zero undocumented hard failures; KNOWN_RESIDUAL = signed G7 residual; SOURCE_GAP = unresolved semantic anchor/schedule.
A4: MASTER_STATUS | B4: MODEL STATUS | C4: =IF(COUNTIF($C$6:$C$29,"FAIL")=0,"PASS","FAIL") -> PASS | G4: Master PASS counts only FAIL rows; KNOWN_RESIDUAL/SOURCE_GAP remain visible but non-blocking.
A5: check_id | B5: description | C5: status | D5: hardness | E5: tolerance | F5: expected | G5: note | H5: FY21A | I5: FY22A | J5: FY23A | K5: FY24A | L5: FY25A | M5: FY26E | N5: FY27E | O5: FY28E | P5: FY29E | Q5: FY30E
A7: UNIVERSAL CHECKS
A8: BS_BALANCE | B8: UNIVERSAL | expected 0; hard fail if ABS(value) > hard_tie_tolerance. Observed: UEPII critical gate <10 for BS/cash; BG hard reconciliation >=1000 because full USD. | source applies_to: all 16 archetypes | C8: =IF(SUMPRODUCT((ABS(H8:Q8)>1000)*1)=0,"PASS","FAIL") -> PASS | D8: hard | E8: 1000 USD | F8: 0 | G8: expected 0; hard fail if ABS(value) > hard_tie_tolerance. Observed: UEPII critical gate <10 for BS/cash; BG hard reconciliation >=1000 because full USD. Default full-USD hard tie threshold is $1,000 unless the workbook declares a tighter scale-aware tolerance. | H8: =ModeloFinanciero!B65-ModeloFinanciero!B91 -> 0 | I8: =ModeloFinanciero!C65-ModeloFinanciero!C91 -> 0 | J8: =ModeloFinanciero!D65-ModeloFinanciero!D91 -> 0 | K8: =ModeloFinanciero!E65-ModeloFinanciero!E91 -> 0 | L8: =ModeloFinanciero!F65-ModeloFinanciero!F91 -> 0 | M8: =ModeloFinanciero!G65-ModeloFinanciero!G91 -> 0 | N8: =ModeloFinanciero!H65-ModeloFinanciero!H91 -> 0 | O8: =ModeloFinanciero!I65-ModeloFinanciero!I91 -> 0 | ... Q8: =ModeloFinanciero!K65-ModeloFinanciero!K91 -> 0
A9: CASH_TIE | B9: UNIVERSAL | expected 0; use hard_tie_tolerance; if cash includes restricted cash/time deposits, define cash_component role explicitly. | source applies_to: all 16 archetypes | C9: SOURCE_GAP | D9: hard | E9: 1000 USD | F9: 0 | G9: No semantic anchors resolved for CASH_TIE. | H9: =0 -> 0 | I9: =0 -> 0 | J9: =0 -> 0 | K9: =0 -> 0 | L9: =0 -> 0 | M9: =0 -> 0 | N9: =0 -> 0 | O9: =0 -> 0 | ... Q9: =0 -> 0
A10: CF_ROLLFORWARD | B10: UNIVERSAL | expected 0; hard_tie_tolerance; historical rows may be WARN if source CF transcript is incomplete. | source applies_to: all 16 where CF is modeled | C10: SOURCE_GAP | D10: hard | E10: 1000 USD | F10: 0 | G10: No semantic anchors resolved for CF_ROLLFORWARD. | H10: =0 -> 0 | I10: =0 -> 0 | J10: =0 -> 0 | K10: =0 -> 0 | L10: =0 -> 0 | M10: =0 -> 0 | N10: =0 -> 0 | O10: =0 -> 0 | ... Q10: =0 -> 0
A11: NI_TIE_TO_EQUITY | B11: UNIVERSAL | expected 0; hard_tie_tolerance. | source applies_to: all 16 | C11: =IF(SUMPRODUCT((ABS(H11:Q11)>1000)*1)=0,"PASS","FAIL") -> PASS | D11: hard | E11: 1000 USD | F11: 0 | G11: expected 0; hard_tie_tolerance. Default full-USD hard tie threshold is $1,000 unless the workbook declares a tighter scale-aware tolerance. | H11: =ModeloFinanciero!B26-ModeloFinanciero!B96 -> 0 | I11: =ModeloFinanciero!C26-ModeloFinanciero!C96 -> 0 | J11: =ModeloFinanciero!D26-ModeloFinanciero!D96 -> 0 | K11: =ModeloFinanciero!E26-ModeloFinanciero!E96 -> 0 | L11: =ModeloFinanciero!F26-ModeloFinanciero!F96 -> 0
A12: NI_SIGN_SANITY | B12: UNIVERSAL | expected 0; sign convention must be stated in row description. | source applies_to: all 16 | C12: SOURCE_GAP | D12: hard | E12: 1000 USD | F12: 0 | G12: Sign convention diagnostic remains visible; tax-sign taxonomy is not a signed hard-control anchor. | H12: =ModeloFinanciero!B26-(ModeloFinanciero!B24-ABS(ModeloFinanciero!B25)) -> 0 | I12: =ModeloFinanciero!C26-(ModeloFinanciero!C24-ABS(ModeloFinanciero!C25)) -> 0 | J12: =ModeloFinanciero!D26-(ModeloFinanciero!D24-ABS(ModeloFinanciero!D25)) -> 0 | K12: =ModeloFinanciero!E26-(ModeloFinanciero!E24-ABS(ModeloFinanciero!E25)) -> 0 | L12: =ModeloFinanciero!F26-(ModeloFinanciero!F24-ABS(ModeloFinanciero!F25)) -> 0 | M12: =ModeloFinanciero!G26-(ModeloFinanciero!G24-ABS(ModeloFinanciero!G25)) -> 0 | N12: =ModeloFinanciero!H26-(ModeloFinanciero!H24-ABS(ModeloFinanciero!H25)) -> 0 | O12: =ModeloFinanciero!I26-(ModeloFinanciero!I24-ABS(ModeloFinanciero!I25)) -> 0 | ... Q12: =ModeloFinanciero!K26-(ModeloFinanciero!K24-ABS(ModeloFinanciero!K25)) -> 0
A13: RE_ROLLFORWARD | B13: UNIVERSAL | expected 0; hard_tie_tolerance. | source applies_to: all 16 with RE row | C13: KNOWN_RESIDUAL | D13: hard | E13: 1000 USD | F13: 87205 @ FY25A | G13: G7c retained earnings roll: Small rounding/minor movement suspected; signed as visible known residual. | I13: =EEFF!C80-EEFF!B80-(EEFF!C25+EEFF!C144) -> 0 | J13: =EEFF!D80-EEFF!C80-(EEFF!D25+EEFF!D144) -> 50000 | K13: =EEFF!E80-EEFF!D80-(EEFF!E25+EEFF!E144) -> 0 | L13: =EEFF!F80-EEFF!E80-(EEFF!F25+EEFF!F144) -> 87205
A14: EQUITY_TOTAL_TIE | B14: UNIVERSAL | expected 0; hard_tie_tolerance. | source applies_to: all 16 | C14: =IF(SUMPRODUCT((ABS(H14:Q14)>1000)*1)=0,"PASS","FAIL") -> PASS | D14: hard | E14: 1000 USD | F14: 0 | G14: expected 0; hard_tie_tolerance. Default full-USD hard tie threshold is $1,000 unless the workbook declares a tighter scale-aware tolerance. | H14: =SUM(ModeloFinanciero!B87,ModeloFinanciero!B88,ModeloFinanciero!B89)-ModeloFinanciero!B90 -> 0 | I14: =SUM(ModeloFinanciero!C87,ModeloFinanciero!C88,ModeloFinanciero!C89)-ModeloFinanciero!C90 -> 0 | J14: =SUM(ModeloFinanciero!D87,ModeloFinanciero!D88,ModeloFinanciero!D89)-ModeloFinanciero!D90 -> 0 | K14: =SUM(ModeloFinanciero!E87,ModeloFinanciero!E88,ModeloFinanciero!E89)-ModeloFinanciero!E90 -> 0 | L14: =SUM(ModeloFinanciero!F87,ModeloFinanciero!F88,ModeloFinanciero!F89)-ModeloFinanciero!F90 -> 0 | M14: =SUM(ModeloFinanciero!G87,ModeloFinanciero!G88,ModeloFinanciero!G89)-ModeloFinanciero!G90 -> 0 | N14: =SUM(ModeloFinanciero!H87,ModeloFinanciero!H88,ModeloFinanciero!H89)-ModeloFinanciero!H90 -> 0 | O14: =SUM(ModeloFinanciero!I87,ModeloFinanciero!I88,ModeloFinanciero!I89)-ModeloFinanciero!I90 -> 0 | ... Q14: =SUM(ModeloFinanciero!K87,ModeloFinanciero!K88,ModeloFinanciero!K89)-ModeloFinanciero!K90 -> 0
A15: BS_LINEITEM_SUM_ASSETS | B15: UNIVERSAL | expected 0; hard_tie_tolerance. | source applies_to: all 16 | C15: =IF(SUMPRODUCT((ABS(H15:Q15)>1000)*1)=0,"PASS","FAIL") -> PASS | D15: hard | E15: 1000 USD | F15: 0 | G15: expected 0; hard_tie_tolerance. Default full-USD hard tie threshold is $1,000 unless the workbook declares a tighter scale-aware tolerance. | H15: =SUM(ModeloFinanciero!B48,ModeloFinanciero!B64)-ModeloFinanciero!B65 -> 0 | I15: =SUM(ModeloFinanciero!C48,ModeloFinanciero!C64)-ModeloFinanciero!C65 -> 0 | J15: =SUM(ModeloFinanciero!D48,ModeloFinanciero!D64)-ModeloFinanciero!D65 -> 0 | K15: =SUM(ModeloFinanciero!E48,ModeloFinanciero!E64)-ModeloFinanciero!E65 -> 0 | L15: =SUM(ModeloFinanciero!F48,ModeloFinanciero!F64)-ModeloFinanciero!F65 -> 0 | M15: =SUM(ModeloFinanciero!G48,ModeloFinanciero!G64)-ModeloFinanciero!G65 -> 0 | N15: =SUM(ModeloFinanciero!H48,ModeloFinanciero!H64)-ModeloFinanciero!H65 -> 0 | O15: =SUM(ModeloFinanciero!I48,ModeloFinanciero!I64)-ModeloFinanciero!I65 -> 0 | ... Q15: =SUM(ModeloFinanciero!K48,ModeloFinanciero!K64)-ModeloFinanciero!K65 -> 0
A16: BS_LINEITEM_SUM_LIAB_EQUITY | B16: UNIVERSAL | expected 0; hard_tie_tolerance. | source applies_to: all 16 | C16: =IF(SUMPRODUCT((ABS(H16:Q16)>1000)*1)=0,"PASS","FAIL") -> PASS | D16: hard | E16: 1000 USD | F16: 0 | G16: expected 0; hard_tie_tolerance. Default full-USD hard tie threshold is $1,000 unless the workbook declares a tighter scale-aware tolerance. | H16: =ModeloFinanciero!B84+ModeloFinanciero!B90-ModeloFinanciero!B91 -> 0 | I16: =ModeloFinanciero!C84+ModeloFinanciero!C90-ModeloFinanciero!C91 -> 0 | J16: =ModeloFinanciero!D84+ModeloFinanciero!D90-ModeloFinanciero!D91 -> 0 | K16: =ModeloFinanciero!E84+ModeloFinanciero!E90-ModeloFinanciero!E91 -> 0 | L16: =ModeloFinanciero!F84+ModeloFinanciero!F90-ModeloFinanciero!F91 -> 0 | M16: =ModeloFinanciero!G84+ModeloFinanciero!G90-ModeloFinanciero!G91 -> 0 | N16: =ModeloFinanciero!H84+ModeloFinanciero!H90-ModeloFinanciero!H91 -> 0 | O16: =ModeloFinanciero!I84+ModeloFinanciero!I90-ModeloFinanciero!I91 -> 0 | ... Q16: =ModeloFinanciero!K84+ModeloFinanciero!K90-ModeloFinanciero!K91 -> 0
A17: SOURCE_TIE_HISTORICAL | B17: UNIVERSAL | expected 0 for audited rows; SOURCE_GAP/WARN allowed only with explicit source-gap note. | source applies_to: all 16 | C17: =IF(SUMPRODUCT((ABS(H17:Q17)>100000)*1)=0,"PASS","FAIL") -> PASS | D17: hard | E17: 100000 USD | F17: 0 | G17: Audited rows tie to 0; only bank ending-cash-vs-EEFF cash rows may use the observed $100,000 hard threshold; SOURCE_GAP/WARN requires explicit source-gap note. | H17: =ModeloFinanciero!B65-EEFF!B60 -> 0 | I17: =ModeloFinanciero!C65-EEFF!C60 -> 0 | J17: =ModeloFinanciero!D65-EEFF!D60 -> 0 | K17: =ModeloFinanciero!E65-EEFF!E60 -> 0 | L17: =ModeloFinanciero!F65-EEFF!F60 -> 0
A18: NO_FORMULA_ERRORS | B18: UNIVERSAL | expected PASS/0; no masking. | source applies_to: all 16 | C18: =IF(SUMPRODUCT((ABS(H18:Q18)>0)*1)=0,"PASS","FAIL") -> PASS | D18: hard | E18: PASS | F18: PASS | G18: expected PASS/0; no masking. | H18: =0 -> 0 | I18: =0 -> 0 | J18: =0 -> 0 | K18: =0 -> 0 | L18: =0 -> 0 | M18: =0 -> 0 | N18: =0 -> 0 | O18: =0 -> 0 | ... Q18: =0 -> 0
A19: NO_CHECKS_MASTER_FAIL | B19: UNIVERSAL | expected PASS; status row should cite included/excluded rows. | source applies_to: all 16 | C19: =IF(SUMPRODUCT((ABS(H19:Q19)>0)*1)=0,"PASS","FAIL") -> PASS | D19: hard | E19: PASS | F19: PASS | G19: expected PASS; status row should cite included/excluded rows. | H19: =COUNTIF($C$6:$C$18,"FAIL")+COUNTIF($C$20:$C$29,"FAIL") -> 0 | I19: =COUNTIF($C$6:$C$18,"FAIL")+COUNTIF($C$20:$C$29,"FAIL") -> 0 | J19: =COUNTIF($C$6:$C$18,"FAIL")+COUNTIF($C$20:$C$29,"FAIL") -> 0 | K19: =COUNTIF($C$6:$C$18,"FAIL")+COUNTIF($C$20:$C$29,"FAIL") -> 0 | L19: =COUNTIF($C$6:$C$18,"FAIL")+COUNTIF($C$20:$C$29,"FAIL") -> 0 | M19: =COUNTIF($C$6:$C$18,"FAIL")+COUNTIF($C$20:$C$29,"FAIL") -> 0 | N19: =COUNTIF($C$6:$C$18,"FAIL")+COUNTIF($C$20:$C$29,"FAIL") -> 0 | O19: =COUNTIF($C$6:$C$18,"FAIL")+COUNTIF($C$20:$C$29,"FAIL") -> 0 | ... Q19: =COUNTIF($C$6:$C$18,"FAIL")+COUNTIF($C$20:$C$29,"FAIL") -> 0
A21: CONDITIONAL CHECKS
A22: PPE_SCHEDULE_TIE | B22: ARCHETYPE/conditional | expected 0; hard_tie_tolerance. | source applies_to: operating-EBITDA, power, utility, downstream fuel, other non-financials | C22: SOURCE_GAP | D22: hard | E22: 1000 USD | F22: 0 | G22: No semantic anchors resolved for PPE_SCHEDULE_TIE. | H22: =0 -> 0 | I22: =0 -> 0 | J22: =0 -> 0 | K22: =0 -> 0 | L22: =0 -> 0 | M22: =0 -> 0 | N22: =0 -> 0 | O22: =0 -> 0 | ... Q22: =0 -> 0
A23: LEASE_SCHEDULE_TIE | B23: ARCHETYPE/conditional | expected 0; hard_tie_tolerance. | source applies_to: IFRS-16 issuers | C23: SOURCE_GAP | D23: hard | E23: 1000 USD | F23: 0 | G23: No semantic anchors resolved for LEASE_SCHEDULE_TIE. | H23: =0 -> 0 | I23: =0 -> 0 | J23: =0 -> 0 | K23: =0 -> 0 | L23: =0 -> 0 | M23: =0 -> 0 | N23: =0 -> 0 | O23: =0 -> 0 | ... Q23: =0 -> 0
A24: DEBT_SCHEDULE_TIE | B24: ARCHETYPE/conditional | expected 0; hard_tie_tolerance; project-finance debt can include accrued interest/unamortized cost roles. | source applies_to: non-bank-lender, power, utility, operating-EBITDA with debt | C24: SOURCE_GAP | D24: hard | E24: 1000 USD | F24: 0 | G24: No semantic anchors resolved for DEBT_SCHEDULE_TIE. | H24: =0 -> 0 | I24: =0 -> 0 | J24: =0 -> 0 | K24: =0 -> 0 | L24: =0 -> 0 | M24: =0 -> 0 | N24: =0 -> 0 | O24: =0 -> 0 | ... Q24: =0 -> 0
A26: OPERATING-EBITDA CHECKS
A27: OPERATING_GP_OR_EBITDA_TIE | B27: ARCHETYPE | expected 0; hard_tie_tolerance. | source applies_to: operating-EBITDA, downstream fuel, power when EBITDA is used | C27: SOURCE_GAP | D27: hard | E27: 1000 USD | F27: 0 | G27: No semantic anchors resolved for OPERATING_GP_OR_EBITDA_TIE. | H27: =0 -> 0 | I27: =0 -> 0 | J27: =0 -> 0 | K27: =0 -> 0 | L27: =0 -> 0 | M27: =0 -> 0 | N27: =0 -> 0 | O27: =0 -> 0 | ... Q27: =0 -> 0
A28: OPERATING_WC_DRIVER_TIE | B28: ARCHETYPE | expected 0; hard_tie_tolerance. | source applies_to: operating-EBITDA/downstream fuel | C28: SOURCE_GAP | D28: hard | E28: 1000 USD | F28: 0 | G28: No semantic anchors resolved for OPERATING_WC_DRIVER_TIE. | H28: =0 -> 0 | I28: =0 -> 0 | J28: =0 -> 0 | K28: =0 -> 0 | L28: =0 -> 0 | M28: =0 -> 0 | N28: =0 -> 0 | O28: =0 -> 0 | ... Q28: =0 -> 0
A29: DOWNSTREAM_VOL_MARGIN_TIE | B29: ARCHETYPE | expected 0; observed PDelta hard check #13. | source applies_to: downstream fuel | C29: SOURCE_GAP | D29: hard | E29: 1000 USD | F29: 0 | G29: No semantic anchors resolved for DOWNSTREAM_VOL_MARGIN_TIE. | H29: =0 -> 0 | I29: =0 -> 0 | J29: =0 -> 0 | K29: =0 -> 0 | L29: =0 -> 0 | M29: =0 -> 0 | N29: =0 -> 0 | O29: =0 -> 0 | ... Q29: =0 -> 0

Sheet Source_Register
A1: Empresas Melo, S.A. y Subsidiarias
A2: Source_Register — operating-EBITDA archetype. Every row traces to a published filing (OCR text) or to a working file kept by the maintainer.
A3: Status semantics: OK = citation resolved to an existing artifact. SOURCE_GAP = traceability missing (visible, not hidden). NOT_DISCLOSED = no registration/manifest found for this issuer.
A4: source_id | B4: kind | C4: ticker | D4: filing | E4: year | F4: nota | G4: tabla_ocr | H4: feeds_sheet | I4: feeds_anchor | J4: date | K4: status | L4: evidence_count | M4: note
A5: OCR_ROOT:empresas-melo | B5: OCR_ROOT | C5: EMMELO | H5: EEFF; Notas_EEFF | I5: OCR of the published filings | J5: NOT_DISCLOSED | K5: OK | L5: 1 | M5: Annual reports (INA) of empresas-melo
A6: EEFF_FILING:ina_emmelo_2022_0 | B6: EEFF_FILING | C6: EMMELO | D6: INA_EMMELO_2022_0.pdf | E6: 2022 | G6: markdown.md | H6: EEFF; Notas_EEFF; MD&A | I6: 00-index.md; 01-eeff.md; 02-notas.md; 03-mda.md; 09-otros.md | J6: FY22 (A) | K6: OK | L6: 136 | M6: markdown.md sha256=6ab96734f8a56f37...
A7: EEFF_FILING:ina_emmelo_2023_0 | B7: EEFF_FILING | C7: EMMELO | D7: INA_EMMELO_2023_0.pdf | E7: 2023 | G7: markdown.md | H7: EEFF; Notas_EEFF; MD&A | I7: 00-index.md; 01-eeff.md; 02-notas.md; 03-mda.md; 09-otros.md | J7: FY23 (A) | K7: OK | L7: 131 | M7: markdown.md sha256=3c3b2b7fcd1cded0...
A8: EEFF_FILING:ina_emmelo_2024_0 | B8: EEFF_FILING | C8: EMMELO | D8: INA_EMMELO_2024_0.pdf | E8: 2024 | G8: markdown.md | H8: EEFF; Notas_EEFF; MD&A | I8: 00-index.md; 01-eeff.md; 02-notas.md; 03-mda.md; 09-otros.md | J8: FY24 (A) | K8: OK | L8: 131 | M8: markdown.md sha256=0453cb35a1efd158...
A9: EEFF_FILING:ina_emmelo_2025_0 | B9: EEFF_FILING | C9: EMMELO | D9: INA_EMMELO_2025_0.pdf | E9: 2025 | G9: markdown.md | H9: EEFF; Notas_EEFF; MD&A | I9: 00-index.md; 01-eeff.md; 02-notas.md; 03-mda.md; 09-otros.md | J9: FY25 (A) | K9: OK | L9: 131 | M9: markdown.md sha256=1947f4ae922e5ae1...
A10: NOTA:INA_EMMELO_2022_0.pdf#1 | B10: NOTA | C10: EMMELO | D10: INA_EMMELO_2022_0.pdf | E10: 2022 | F10: 1 | G10: markdown.md | H10: Notas_EEFF | I10: 1. Información general | J10: FY22 (A) | K10: OK | L10: 20
A11: NOTA:INA_EMMELO_2022_0.pdf#10 | B11: NOTA | C11: EMMELO | D11: INA_EMMELO_2022_0.pdf | E11: 2022 | F11: 10 | G11: markdown.md; tbl-63.html; tbl-64.html | H11: Notas_EEFF | I11: 10. Propiedades de inversión | J11: FY22 (A) | K11: OK | L11: 10
A12: NOTA:INA_EMMELO_2022_0.pdf#11 | B12: NOTA | C12: EMMELO | D12: INA_EMMELO_2022_0.pdf | E12: 2022 | F12: 11 | G12: markdown.md; tbl-65.html | H12: Notas_EEFF | I12: 11. Otras inversiones | J12: FY22 (A) | K12: OK | L12: 3
A13: NOTA:INA_EMMELO_2022_0.pdf#12 | B13: NOTA | C13: EMMELO | D13: INA_EMMELO_2022_0.pdf | E13: 2022 | F13: 12 | G13: markdown.md; tbl-66.html; tbl-67.html; +3 more | H13: Notas_EEFF | I13: 12. Activos biológicos (continuación) | J13: FY22 (A) | K13: OK | L13: 15
A14: NOTA:INA_EMMELO_2022_0.pdf#13 | B14: NOTA | C14: EMMELO | D14: INA_EMMELO_2022_0.pdf | E14: 2022 | F14: 13 | G14: markdown.md; tbl-71.html | H14: Notas_EEFF | I14: 13. Adelantos para compras | J14: FY22 (A) | K14: OK | L14: 4
A15: NOTA:INA_EMMELO_2022_0.pdf#14 | B15: NOTA | C15: EMMELO | D15: INA_EMMELO_2022_0.pdf | E15: 2022 | F15: 14 | G15: markdown.md; tbl-72.html | H15: Notas_EEFF | I15: 14. Inmuebles, mobiliarios, equipos y mejoras, neto | J15: FY22 (A) | K15: OK | L15: 5
A16: NOTA:INA_EMMELO_2022_0.pdf#15 | B16: NOTA | C16: EMMELO | D16: INA_EMMELO_2022_0.pdf | E16: 2022 | F16: 15 | G16: markdown.md; tbl-73.html | H16: Notas_EEFF | I16: 15. Equipo para arrendamiento, neto | J16: FY22 (A) | K16: OK | L16: 3
A17: NOTA:INA_EMMELO_2022_0.pdf#16 | B17: NOTA | C17: EMMELO | D17: INA_EMMELO_2022_0.pdf | E17: 2022 | F17: 16 | G17: markdown.md; tbl-74.html | H17: Notas_EEFF | I17: 16. Activos por Derecho de Uso | J17: FY22 (A) | K17: OK | L17: 3
A18: NOTA:INA_EMMELO_2022_0.pdf#17 | B18: NOTA | C18: EMMELO | D18: INA_EMMELO_2022_0.pdf | E18: 2022 | F18: 17 | G18: markdown.md; tbl-75.html; tbl-76.html; +2 more | H18: Notas_EEFF | I18: 17. Pasivos por arrendamientos | J18: FY22 (A) | K18: OK | L18: 9
A19: NOTA:INA_EMMELO_2022_0.pdf#18 | B19: NOTA | C19: EMMELO | D19: INA_EMMELO_2022_0.pdf | E19: 2022 | F19: 18 | G19: markdown.md; tbl-79.html; tbl-80.html; +2 more | H19: Notas_EEFF | I19: 18. Inversiones en asociadas | J19: FY22 (A) | K19: OK | L19: 10
A20: NOTA:INA_EMMELO_2022_0.pdf#19 | B20: NOTA | C20: EMMELO | D20: INA_EMMELO_2022_0.pdf | E20: 2022 | F20: 19 | G20: markdown.md; tbl-83.html | H20: Notas_EEFF | I20: 19. Préstamos por pagar | J20: FY22 (A) | K20: OK | L20: 7
A21: NOTA:INA_EMMELO_2022_0.pdf#2 | B21: NOTA | C21: EMMELO | D21: INA_EMMELO_2022_0.pdf | E21: 2022 | F21: 2 | G21: markdown.md | H21: Notas_EEFF | I21: 2. Declaración de cumplimiento | J21: FY22 (A) | K21: OK | L21: 3
... A122: NOTA:INA_EMMELO_2025_0.pdf#9 | B122: NOTA | C122: EMMELO | D122: INA_EMMELO_2025_0.pdf | E122: 2025 | F122: 9 | G122: markdown.md; tbl-48.html; tbl-49.html; +1 more | H122: Notas_EEFF | I122: 9. Saldos y transacciones con partes relacionadas (continuación) | J122: FY25 (A) | K122: OK | L122: 11
A123: DRIVER:DRIVER_DETAIL_PENDING | B123: DRIVER_OTHER | C123: EMMELO | H123: Supuestos | I123: Restaurantes — crecimiento activo | J123: NOT_DISCLOSED | K123: SOURCE_GAP | L123: 8 | M123: Unclassified _source citation shape: DRIVER_DETAIL_PENDING
A124: DRIVER:EEFF (citado por fórmula viva) | B124: DRIVER_OTHER | C124: EMMELO | H124: Supuestos | I124: Consumo materia prima % ingresos hist | J124: NOT_DISCLOSED | K124: SOURCE_GAP | L124: 7 | M124: Unclassified _source citation shape: EEFF (citado por fórmula viva)
A125: DRIVER:NOT_DISCLOSED | B125: DRIVER_OTHER | C125: EMMELO | H125: Supuestos | I125: Selector escenario | J125: NOT_DISCLOSED | K125: SOURCE_GAP | L125: 38 | M125: Unclassified _source citation shape: NOT_DISCLOSED
A126: DRIVER:label:Almacenes ingresos hist — Nota 7/28 EMMELO | B126: DRIVER_OTHER | C126: EMMELO | H126: Supuestos | I126: Almacenes ingresos hist — Nota 7/28 EMMELO | J126: NOT_DISCLOSED | K126: SOURCE_GAP | L126: 1 | M126: Unclassified _source citation shape: label:Almacenes ingresos hist — Nota 7/28 EMMELO
A127: DRIVER:label:Avicola ingresos hist — Nota 7/28 EMMELO | B127: DRIVER_OTHER | C127: EMMELO | H127: Supuestos | I127: Avicola ingresos hist — Nota 7/28 EMMELO | J127: NOT_DISCLOSED | K127: SOURCE_GAP | L127: 1 | M127: Unclassified _source citation shape: label:Avicola ingresos hist — Nota 7/28 EMMELO
A128: DRIVER:label:Base — Nota 16 FY25 capex/ingresos | B128: DRIVER_OTHER | C128: EMMELO | H128: Supuestos | I128: Capex PP&E % ingresos — activo | J128: NOT_DISCLOSED | K128: SOURCE_GAP | L128: 1 | M128: Unclassified _source citation shape: label:Base — Nota 16 FY25 capex/ingresos
A129: DRIVER:label:Base — escenario, DOCUMENT_MAP §8.6 clima/precios insumos | B129: DRIVER_OTHER | C129: EMMELO | H129: Supuestos | I129: Almacenes — crecimiento activo | J129: NOT_DISCLOSED | K129: SOURCE_GAP | L129: 1 | M129: Unclassified _source citation shape: label:Base — escenario, DOCUMENT_MAP §8.6 clima/precios insumos
A130: DRIVER:label:Base — escenario, DOCUMENT_MAP §8.6 mercado autos +10.8% | B130: DRIVER_OTHER | C130: EMMELO | H130: Supuestos | I130: Maquinaria — crecimiento activo | J130: NOT_DISCLOSED | K130: SOURCE_GAP | L130: 1 | M130: Unclassified _source citation shape: label:Base — escenario, DOCUMENT_MAP §8.6 mercado autos +10.8%
A131: DRIVER:label:Base — escenario, DOCUMENT_MAP §8.6 produccion pollo +2.9% | B131: DRIVER_OTHER | C131: EMMELO | H131: Supuestos | I131: Avicola — crecimiento activo | J131: NOT_DISCLOSED | K131: SOURCE_GAP | L131: 1 | M131: Unclassified _source citation shape: label:Base — escenario, DOCUMENT_MAP §8.6 produccion pollo +2.9%
A132: DRIVER:label:Base — escenario, DOCUMENT_MAP §8.6 trafico/ticket | B132: DRIVER_OTHER | C132: EMMELO | H132: Supuestos | I132: Restaurantes — crecimiento activo | J132: NOT_DISCLOSED | K132: SOURCE_GAP | L132: 1 | M132: Unclassified _source citation shape: label:Base — escenario, DOCUMENT_MAP §8.6 trafico/ticket
A133: DRIVER:label:Maquinaria ingresos hist — Nota 7/28 EMMELO | B133: DRIVER_OTHER | C133: EMMELO | H133: Supuestos | I133: Maquinaria ingresos hist — Nota 7/28 EMMELO | J133: NOT_DISCLOSED | K133: SOURCE_GAP | L133: 1 | M133: Unclassified _source citation shape: label:Maquinaria ingresos hist — Nota 7/28 EMMELO
A134: DRIVER:label:Restaurantes ingresos hist — Nota 7/28 EMMELO | B134: DRIVER_OTHER | C134: EMMELO | H134: Supuestos | I134: Restaurantes ingresos hist — Nota 7/28 EMMELO | J134: NOT_DISCLOSED | K134: SOURCE_GAP | L134: 1 | M134: Unclassified _source citation shape: label:Restaurantes ingresos hist — Nota 7/28 EMMELO

Sheet _CHANGELOG
A1: Empresas Melo, S.A. y Subsidiarias
A2: _CHANGELOG — generation record for empresas-melo.
A3: Internal build history omitted from the public export. Record public changes below.

Sheet MD&A
A1: Empresas Melo, S.A. y Subsidiarias
A2: MD&A — Informe de Actualización INA_EMMELO_2025_0 (índice verbatim del mirror OCR; la narrativa completa vive en el mirror)
A3: Fuente: mirror OCR INA_EMMELO_2025_0, sección MD&A · sha256=788b7267ddcaee2c… · linaje completo en Source_Register.
A5: A. ÍNDICE DE SECCIONES DEL MD&A (verbatim, con página del filing)
A6: · REPUBLICA DE PANAMA (pág. 1)
A7: · SUPERINTENDENCIA DEL MERCADO DE VALORES (pág. 1)
A8: · FORMULARIO IN-A (pág. 1)
A9: · INFORME DE ACTUALIZACION ANUAL* (pág. 1)
A10: · I PARTE (pág. 1)
A11: · I. INFORMACION DE LA COMPAÑÍA (pág. 1)
A12: · A. Historia y Desarrollo de Empresas Melo, S.A. (pág. 1)
A13: · B. Pacto Social y Estatutos del Solicitante (pág. 2)
... A67: Doctrina: hoja índice/verbatim — sin narrativa inventada; cifras solo del filing (NOT_DISCLOSED donde no hay dato).

Sheet Claude Code Log
A1: Turn # | B1: Date | C1: User Request | D1: Action Taken | E1: Details | F1: Outcome
A2: 1 | B2: 46324.359 | C2: Prepare a public model copy | D2: Remove local paths and private build references; preserve financial formulas and inputs | E2: Agent run with MOG as the tool, checked by guard v1. The guard measured every sheet before and after the run. Changed: Notas_EEFF: 1 cell written, at A3; _CHECKS: 1 cell written, at G12; Source_Register: 3 cells written, at A2, I5, M5; _CHANGELOG: data A1:H33 -> A1:A3 (rows 33 -> 3, columns 8 -> 1), 205 cells written, at A2, A3, B3, C3, D3, E3, F3, G3, H3, A4, B4, C4, D4, E4, F4 and 190 more. Other actions: clear x1. Agent: OpenFinmods export | F2: Compare against source and review public copy
