Workbook

Sheet 00_Cover
A1: Grupo Aval Acciones y Valores S.A. - Holdco / Bank Model
A2: COP billions except per-share data | FY2025 actual | legal-entity and segment-aware rebuild
A4: Model field | B4: Value
A5: Legal entity | B5: Grupo Aval Acciones y Valores S.A.
A6: Ticker / ADR | B6: AVAL
A7: CIK | B7: 0001504764
A8: Model archetype | B8: Financial holding company / consolidated banking group
A9: Primary valuation | B9: Residual income + DDM + reportable-segment SOTP
A10: Operating perimeter | B10: Banking, merchant banking, pension, holdco
A11: Reporting/model currency | B11: COP / COP billions
A12: Actual period | B12: Year ended 2025-12-31
A13: Source filing | B13: 2025 Form 20-F filed 2026-04-17
A14: Scenario | B14: =Assumptions!E4 -> Base
A15: Overall model status | B15: =Checks!F16 -> PASS
A16: Independent status | B16: PENDING INDEPENDENT REVIEW
A17: Critical perimeter note | B17: MFG classified held for sale in 2025; 2024 balance sheet not retrospectively adjusted
A19: Use only blue/yellow cells for scenario assumptions. Legal_Entities distinguishes Grupo Aval from Banco de Bogota, Banco de Occidente, Banco Popular, Banco AV Villas, Corficolombiana and Porvenir.

Sheet Sources
A1: Claim-level source ledger
A2: Primary 2025 Form 20-F mappings; no subsidiary fact is relabeled as a parent fact.
A4: Source ID | B4: Legal entity | C4: Metric | D4: Reported value | E4: Units | F4: Period | G4: Basis / context | H4: Claim locator | I4: Form | J4: Filed | K4: Accession | L4: Exact official URL | M4: Workbook destination | N4: Transformation | O4: Class | P4: Status
A5: AV25-II | B5: Grupo Aval Acciones y Valores S.A. | C5: Total interest income | D5: 25919.2 | E5: COP bn | F5: FY2025 | G5: Consolidated | H5: 20-F PDF p.11 / printed p.7 | I5: 20-F | J5: 2026-04-17 | K5: 0001104659-26-044493 | L5: https://www.grupoaval.com/repositorio/grupoaval/inversionistas/mercados-externos/fomr-20-f/20-f-2025.pdf | M5: Historical!D5 | N5: COP millions / 1,000 | O5: Primary filing | P5: PASS
A6: AV25-IE | B6: Grupo Aval Acciones y Valores S.A. | C6: Total interest expense | D6: -18047.9 | E6: COP bn | F6: FY2025 | G6: Consolidated | H6: 20-F PDF p.11 / printed p.7 | I6: 20-F | J6: 2026-04-17 | K6: 0001104659-26-044493 | L6: https://www.grupoaval.com/repositorio/grupoaval/inversionistas/mercados-externos/fomr-20-f/20-f-2025.pdf | M6: Historical!D6 | N6: COP millions / 1,000; expense shown negative | O6: Primary filing | P6: PASS
A7: AV25-NII | B7: Grupo Aval Acciones y Valores S.A. | C7: Net interest income | D7: 7871.3 | E7: COP bn | F7: FY2025 | G7: Consolidated | H7: 20-F PDF p.11 / printed p.7 | I7: 20-F | J7: 2026-04-17 | K7: 0001104659-26-044493 | L7: https://www.grupoaval.com/repositorio/grupoaval/inversionistas/mercados-externos/fomr-20-f/20-f-2025.pdf | M7: Historical!D7 | N7: COP millions / 1,000 | O7: Primary filing | P7: PASS
A8: AV25-NI | B8: Grupo Aval Acciones y Valores S.A. | C8: Net income attributable to owners | D8: 1721.9 | E8: COP bn | F8: FY2025 | G8: Owners of parent | H8: 20-F PDF p.11 / printed p.7 | I8: 20-F | J8: 2026-04-17 | K8: 0001104659-26-044493 | L8: https://www.grupoaval.com/repositorio/grupoaval/inversionistas/mercados-externos/fomr-20-f/20-f-2025.pdf | M8: Historical!D9 | N8: COP millions / 1,000 | O8: Primary filing | P8: PASS
A9: AV25-ASSET | B9: Grupo Aval Acciones y Valores S.A. | C9: Total assets | D9: 348936.7 | E9: COP bn | F9: 2025-12-31 | G9: Consolidated | H9: 20-F PDF p.12 / printed p.8 | I9: 20-F | J9: 2026-04-17 | K9: 0001104659-26-044493 | L9: https://www.grupoaval.com/repositorio/grupoaval/inversionistas/mercados-externos/fomr-20-f/20-f-2025.pdf | M9: Historical!D12 | N9: COP millions / 1,000 | O9: Primary filing | P9: PASS
A10: AV25-GLOAN | B10: Grupo Aval Acciones y Valores S.A. | C10: Gross loans | D10: 192655.9 | E10: COP bn | F10: 2025-12-31 | G10: Consolidated incl. eliminations | H10: 20-F PDF p.60 / lending activities | I10: 20-F | J10: 2026-04-17 | K10: 0001104659-26-044493 | L10: https://www.grupoaval.com/repositorio/grupoaval/inversionistas/mercados-externos/fomr-20-f/20-f-2025.pdf | M10: Historical!D13 | N10: COP millions / 1,000 | O10: Primary filing | P10: PASS
A11: AV25-NLOAN | B11: Grupo Aval Acciones y Valores S.A. | C11: Net loans | D11: 184226 | E11: COP bn | F11: 2025-12-31 | G11: Consolidated | H11: 20-F PDF p.12 / printed p.8 | I11: 20-F | J11: 2026-04-17 | K11: 0001104659-26-044493 | L11: https://www.grupoaval.com/repositorio/grupoaval/inversionistas/mercados-externos/fomr-20-f/20-f-2025.pdf | M11: Historical!D14 | N11: COP millions / 1,000 | O11: Primary filing | P11: PASS
A12: AV25-DEP | B12: Grupo Aval Acciones y Valores S.A. | C12: Customer deposits | D12: 207405.2 | E12: COP bn | F12: 2025-12-31 | G12: Consolidated | H12: 20-F PDF p.12 / printed p.8 | I12: 20-F | J12: 2026-04-17 | K12: 0001104659-26-044493 | L12: https://www.grupoaval.com/repositorio/grupoaval/inversionistas/mercados-externos/fomr-20-f/20-f-2025.pdf | M12: Historical!D15 | N12: COP millions / 1,000 | O12: Primary filing | P12: PASS
A13: AV25-EQ | B13: Grupo Aval Acciones y Valores S.A. | C13: Equity attributable to owners | D13: 18445.9 | E13: COP bn | F13: 2025-12-31 | G13: Owners of parent | H13: 20-F PDF p.12 / printed p.8 | I13: 20-F | J13: 2026-04-17 | K13: 0001104659-26-044493 | L13: https://www.grupoaval.com/repositorio/grupoaval/inversionistas/mercados-externos/fomr-20-f/20-f-2025.pdf | M13: Historical!D16 | N13: COP millions / 1,000 | O13: Primary filing | P13: PASS
A14: AV25-NIM | B14: Grupo Aval Acciones y Valores S.A. | C14: Net interest margin | D14: 0.035 | E14: % | F14: FY2025 | G14: Excludes MFG average earning assets | H14: 20-F PDF p.13 / ratios | I14: 20-F | J14: 2026-04-17 | K14: 0001104659-26-044493 | L14: https://www.grupoaval.com/repositorio/grupoaval/inversionistas/mercados-externos/fomr-20-f/20-f-2025.pdf | M14: Historical!D19 | N14: Direct ratio | O14: Primary filing | P14: PASS
A15: AV25-ROAE | B15: Grupo Aval Acciones y Valores S.A. | C15: ROAE | D15: 0.096 | E15: % | F15: FY2025 | G15: Owners of parent | H15: 20-F PDF p.13 / ratios | I15: 20-F | J15: 2026-04-17 | K15: 0001104659-26-044493 | L15: https://www.grupoaval.com/repositorio/grupoaval/inversionistas/mercados-externos/fomr-20-f/20-f-2025.pdf | M15: Historical!D20 | N15: Direct ratio | O15: Primary filing | P15: PASS
A16: AV25-CIR | B16: Grupo Aval Acciones y Valores S.A. | C16: Cost to income | D16: 0.522 | E16: % | F16: FY2025 | G16: Consolidated | H16: 20-F PDF p.13 / ratios | I16: 20-F | J16: 2026-04-17 | K16: 0001104659-26-044493 | L16: https://www.grupoaval.com/repositorio/grupoaval/inversionistas/mercados-externos/fomr-20-f/20-f-2025.pdf | M16: Historical!D21 | N16: Direct ratio | O16: Primary filing | P16: PASS
... A19: AV25-SH | B19: Grupo Aval Acciones y Valores S.A. | C19: Weighted average common + preferred shares | D19: 23743.476 | E19: mm shares | F19: FY2025 | G19: All shares | H19: 20-F PDF p.11 / printed p.7 | I19: 20-F | J19: 2026-04-17 | K19: 0001104659-26-044493 | L19: https://www.grupoaval.com/repositorio/grupoaval/inversionistas/mercados-externos/fomr-20-f/20-f-2025.pdf | M19: Historical!D26 | N19: Thousands / 1,000 | O19: Primary filing | P19: PASS
A20: AV25-SEG | B20: Grupo Aval Acciones y Valores S.A. | C20: Reportable segment net income | E20: COP bn | F20: FY2025 | G20: Banking / merchant / pension / holdco / eliminations | H20: 20-F Note 31 PDF pp.416-418 / F-201 to F-203 | I20: 20-F | J20: 2026-04-17 | K20: 0001104659-26-044493 | L20: https://www.grupoaval.com/repositorio/grupoaval/inversionistas/mercados-externos/fomr-20-f/20-f-2025.pdf | M20: Valuation!B22:B26 | N20: COP millions / 1,000 | O20: Primary filing | P20: PASS
A21: AV25-OWN | B21: Grupo Aval Acciones y Valores S.A. | C21: Subsidiary ownership | E21: % | F21: 2025-12-31 | G21: Direct and indirect economic interest | H21: 20-F Note 1 PDF pp.226-229 / F-12 to F-14 | I21: 20-F | J21: 2026-04-17 | K21: 0001104659-26-044493 | L21: https://www.grupoaval.com/repositorio/grupoaval/inversionistas/mercados-externos/fomr-20-f/20-f-2025.pdf | M21: Legal_Entities!A4:H12 | N21: Direct ratios | O21: Primary filing | P21: PASS
A22: AV25-MFG | B22: Grupo Aval Acciones y Valores S.A. | C22: MFG disposal / held-for-sale perimeter | D22: 1719.7 | E22: COP bn | F22: 2025-11-27 agreement | G22: Banco de Bogota subsidiary MFH disposal | H22: 20-F PDF p.57; Note 13 | I22: 20-F | J22: 2026-04-17 | K22: 0001104659-26-044493 | L22: https://www.grupoaval.com/repositorio/grupoaval/inversionistas/mercados-externos/fomr-20-f/20-f-2025.pdf | M22: 00_Cover!B17 | N22: Issuer-reported consideration | O22: Primary filing | P22: PASS
A23: Completeness | O23: =COUNTIF(P5:P22,"PASS") -> 18 | P23: =IF(O23=18,"PASS","FAIL") -> PASS

Sheet Legal_Entities
A1: Legal entity and ownership map
A2: 2025 Form 20-F Note 1; prevents parent/subsidiary fact contamination.
A4: Legal entity | B4: Business | C4: Voting rights | D4: Economic interest | E4: 2025 assets (COP bn) | F4: 2025 parent NI (COP bn) | G4: Claim locator | H4: Model treatment
A5: Banco de Bogota S.A. | B5: Commercial bank | C5: 0.6893 | D5: 0.6893 | E5: 156200 | F5: 1300 | G5: 20-F p.57; Note 1 F-12 | H5: Banking segment; no standalone fact relabeled as Aval
A6: Banco de Occidente S.A. | B6: Commercial bank | C6: 0.7227 | D6: 0.7227 | E6: 88163.3 | F6: 574.8 | G6: 20-F p.58; Note 1 F-13 | H6: Banking segment
A7: Banco Popular S.A. | B7: Commercial bank | C7: 0.9374 | D7: 0.9387 | E7: 91590.5 | G7: 20-F p.58; Note 1 F-13 | H7: Banking segment
A8: Banco Comercial AV Villas S.A. | B8: Commercial bank | C8: 0.8039 | D8: 0.7987 | E8: 21932.9 | G8: 20-F p.59; Note 1 F-14 | H8: Banking segment
A9: Corficolombiana S.A. | B9: Merchant bank / strategic investments | C9: 0.5573 | D9: 0.4053 | E9: 61507.9 | F9: 471.667 | G9: 20-F p.65; Note 1 F-13 | H9: Merchant banking segment
A10: Porvenir S.A. | B10: Pension and severance fund manager | C10: 1 | D10: 0.7576 | G10: 20-F Note 1 F-14 | H10: Pension segment
A11: Aval Fiduciaria S.A. | B11: Trust services | C11: 1 | D11: 0.9847 | G11: 20-F Note 1 F-14 | H11: Banking services from 2025
A12: Grupo Aval Ltd. | B12: Foreign debt SPV | C12: 1 | D12: 1 | G12: 20-F Note 1 F-14 | H12: Holding segment

Sheet Historical
A1: Historical consolidated financials and KPIs
A2: COP billions except ratios and share count; 2025 MFG perimeter caveat disclosed on Cover.
A4: Metric | B4: 2023A | C4: 2024A | D4: 2025A
A5: Interest income | B5: 27651.7 | C5: 26971.9 | D5: 25919.2
A6: Interest expense | B6: -21756.4 | C6: -20044.5 | D6: -18047.9
A7: Net interest income | B7: 5895.3 | C7: 6927.4 | D7: 7871.3
A8: Net impairment loss | B8: -4029.5 | C8: -4046.3 | D8: -3538.9
A9: Net income attributable to owners | B9: 739 | C9: 1015.1 | D9: 1721.9
A10: Net income total | B10: 2177.1 | C10: 2191.5 | D10: 3215.2
A12: Total assets | B12: 301181.6 | C12: 327859.4 | D12: 348936.7
A13: Gross loans | D13: 192655.9
A14: Net loans | C14: 190129.5 | D14: 184226
A15: Customer deposits | B15: 181987.4 | C15: 200872.2 | D15: 207405.2
A16: Equity attributable to owners | B16: 16782.7 | C16: 17451.3 | D16: 18445.9
A17: Total equity | B17: 31520.4 | C17: 33162.9 | D17: 34742.8
A19: Net interest margin | B19: 0.029 | C19: 0.033 | D19: 0.035
A20: ROAE | B20: 0.045 | C20: 0.06 | D20: 0.096
A21: Cost to income | B21: 0.514 | C21: 0.532 | D21: 0.522
A22: Net cost of risk | B22: 0.024 | C22: 0.023 | D22: 0.019
A23: Loans >30 days / gross loans | B23: 0.056 | C23: 0.054 | D23: 0.044
A24: Loss allowance / gross loans | B24: 0.057 | C24: 0.053 | D24: 0.044
A26: Weighted average shares (mm) | B26: 23743.476 | C26: 23743.476 | D26: 23743.476

Sheet Assumptions
A1: Scenario assumptions
A2: 1 = Base, 2 = Bull, 3 = Bear. Assumptions are model estimates, not reported facts.
A4: Scenario selector | B4: 1 | E4: =IF(B4=1,"Base",IF(B4=2,"Bull",IF(B4=3,"Bear","INVALID"))) -> Base
A6: Driver | B6: Base | C6: Bull | D6: Bear | E6: Active
A7: Gross loan growth | B7: 0.04 | C7: 0.07 | D7: -0.02 | E7: =IF($B$4=1,B7,IF($B$4=2,C7,D7)) -> 0.04
A8: Net interest margin | B8: 0.036 | C8: 0.04 | D8: 0.03 | E8: =IF($B$4=1,B8,IF($B$4=2,C8,D8)) -> 0.036
A9: Net cost of risk | B9: 0.019 | C9: 0.016 | D9: 0.03 | E9: =IF($B$4=1,B9,IF($B$4=2,C9,D9)) -> 0.019
A10: Other income growth | B10: 0.04 | C10: 0.07 | D10: -0.03 | E10: =IF($B$4=1,B10,IF($B$4=2,C10,D10)) -> 0.04
A11: Cost to income | B11: 0.51 | C11: 0.48 | D11: 0.56 | E11: =IF($B$4=1,B11,IF($B$4=2,C11,D11)) -> 0.51
A12: Tax rate | B12: 0.31 | C12: 0.29 | D12: 0.34 | E12: =IF($B$4=1,B12,IF($B$4=2,C12,D12)) -> 0.31
A13: Parent earnings share | B13: 0.5355 | C13: 0.56 | D13: 0.5 | E13: =IF($B$4=1,B13,IF($B$4=2,C13,D13)) -> 0.5355
A14: Dividend payout | B14: 0.45 | C14: 0.35 | D14: 0.6 | E14: =IF($B$4=1,B14,IF($B$4=2,C14,D14)) -> 0.45
A15: Cost of equity | B15: 0.14 | C15: 0.125 | D15: 0.16 | E15: =IF($B$4=1,B15,IF($B$4=2,C15,D15)) -> 0.14
A16: Terminal growth | B16: 0.04 | C16: 0.05 | D16: 0.02 | E16: =IF($B$4=1,B16,IF($B$4=2,C16,D16)) -> 0.04
A17: Banking segment P/E | B17: 8 | C17: 10 | D17: 6 | E17: =IF($B$4=1,B17,IF($B$4=2,C17,D17)) -> 8
A18: Merchant banking P/E | B18: 9 | C18: 11 | D18: 6 | E18: =IF($B$4=1,B18,IF($B$4=2,C18,D18)) -> 9
... A23: SOTP weight | B23: 0.3 | C23: 0.3 | D23: 0.2 | E23: =IF($B$4=1,B23,IF($B$4=2,C23,D23)) -> 0.3

Sheet Operating_Model
A1: Integrated banking and capital model
A2: Gross loans, NIM, credit cost, cost/income, parent earnings, dividends and equity roll forward.
A4: Metric | B4: 2025A | C4: 2026E | D4: 2027E | E4: 2028E | F4: 2029E | G4: 2030E | H4: Driver / check
A5: Gross loans | B5: =Historical!D13 -> 192655.9 | C5: =B5*(1+Assumptions!$E$7) -> 200362.14 | D5: =C5*(1+Assumptions!$E$7) -> 208376.62 | E5: =D5*(1+Assumptions!$E$7) -> 216711.69 | F5: =E5*(1+Assumptions!$E$7) -> 225380.15 | G5: =F5*(1+Assumptions!$E$7) -> 234395.36 | H5: Assumptions!E7
A6: Loan growth | C6: =C5/B5-1 -> 0.04 | D6: =D5/C5-1 -> 0.04 | E6: =E5/D5-1 -> 0.04 | F6: =F5/E5-1 -> 0.04 | G6: =G5/F5-1 -> 0.04 | H6: Formula
A7: Average gross loans | B7: =B5 -> 192655.9 | C7: =AVERAGE(B5:C5) -> 196509.02 | D7: =AVERAGE(C5:D5) -> 204369.38 | E7: =AVERAGE(D5:E5) -> 212544.15 | F7: =AVERAGE(E5:F5) -> 221045.92 | G7: =AVERAGE(F5:G5) -> 229887.76 | H7: Formula
A8: Interest-earning assets | B8: =Historical!D7/Historical!D19 -> 224894.29 | C8: =B8*(1+C6) -> 233890.06 | D8: =C8*(1+D6) -> 243245.66 | E8: =D8*(1+E6) -> 252975.49 | F8: =E8*(1+F6) -> 263094.51 | G8: =F8*(1+G6) -> 273618.29 | H8: NII / NIM
A9: Net interest margin | B9: =Historical!D19 -> 0.035 | C9: =Assumptions!$E$8 -> 0.036 | D9: =Assumptions!$E$8 -> 0.036 | E9: =Assumptions!$E$8 -> 0.036 | F9: =Assumptions!$E$8 -> 0.036 | G9: =Assumptions!$E$8 -> 0.036 | H9: Assumptions!E8
A10: Net interest income | B10: =Historical!D7 -> 7871.3 | C10: =C8*C9 -> 8420.0421 | D10: =D8*D9 -> 8756.8437 | E10: =E8*E9 -> 9107.1175 | F10: =F8*F9 -> 9471.4022 | G10: =G8*G9 -> 9850.2583 | H10: Formula
A11: Net cost of risk | B11: =Historical!D22 -> 0.019 | C11: =Assumptions!$E$9 -> 0.019 | D11: =Assumptions!$E$9 -> 0.019 | E11: =Assumptions!$E$9 -> 0.019 | F11: =Assumptions!$E$9 -> 0.019 | G11: =Assumptions!$E$9 -> 0.019 | H11: Assumptions!E9
A12: Net impairment loss | B12: =-Historical!D8 -> 3538.9 | C12: =C7*C11 -> 3733.6713 | D12: =D7*D11 -> 3883.0182 | E12: =E7*E11 -> 4038.3389 | F12: =F7*F11 -> 4199.8725 | G12: =G7*G11 -> 4367.8674 | H12: Formula
A13: Other operating income | B13: =(Historical!D10/(1-B17)+B12)/(1-B14)-B10 -> 9279.1915 | C13: =B13*(1+Assumptions!$E$10) -> 9650.3591 | D13: =C13*(1+Assumptions!$E$10) -> 10036.373 | E13: =D13*(1+Assumptions!$E$10) -> 10437.828 | F13: =E13*(1+Assumptions!$E$10) -> 10855.342 | G13: =F13*(1+Assumptions!$E$10) -> 11289.555 | H13: Assumptions!E10
A14: Cost to income | B14: =Historical!D21 -> 0.522 | C14: =Assumptions!$E$11 -> 0.51 | D14: =Assumptions!$E$11 -> 0.51 | E14: =Assumptions!$E$11 -> 0.51 | F14: =Assumptions!$E$11 -> 0.51 | G14: =Assumptions!$E$11 -> 0.51 | H14: Assumptions!E11
A15: Operating expenses | B15: =(B10+B13)*B14 -> 8952.5565 | C15: =(C10+C13)*C14 -> 9215.9046 | D15: =(D10+D13)*D14 -> 9584.5408 | E15: =(E10+E13)*E14 -> 9967.9224 | F15: =(F10+F13)*F14 -> 10366.639 | G15: =(G10+G13)*G14 -> 10781.305 | H15: Formula
A16: Pre-tax income | B16: =B10-B12+B13-B15 -> 4659.0349 | C16: =C10-C12+C13-C15 -> 5120.8252 | D16: =D10-D12+D13-D15 -> 5325.6582 | E16: =E10-E12+E13-E15 -> 5538.6846 | F16: =F10-F12+F13-F15 -> 5760.232 | G16: =G10-G12+G13-G15 -> 5990.6412 | H16: Formula
A17: Tax rate | B17: 0.3099 | C17: =Assumptions!$E$12 -> 0.31 | D17: =Assumptions!$E$12 -> 0.31 | E17: =Assumptions!$E$12 -> 0.31 | F17: =Assumptions!$E$12 -> 0.31 | G17: =Assumptions!$E$12 -> 0.31 | H17: Assumptions!E12
A18: Net income total | B18: =Historical!D10 -> 3215.2 | C18: =C16*(1-C17) -> 3533.3694 | D18: =D16*(1-D17) -> 3674.7042 | E18: =E16*(1-E17) -> 3821.6924 | F18: =F16*(1-F17) -> 3974.5601 | G18: =G16*(1-G17) -> 4133.5425 | H18: Formula
A19: Parent earnings share | B19: =Historical!D9/Historical!D10 -> 0.53554989 | C19: =Assumptions!$E$13 -> 0.5355 | D19: =Assumptions!$E$13 -> 0.5355 | E19: =Assumptions!$E$13 -> 0.5355 | F19: =Assumptions!$E$13 -> 0.5355 | G19: =Assumptions!$E$13 -> 0.5355 | H19: Assumptions!E13
A20: Net income attributable to owners | B20: =Historical!D9 -> 1721.9 | C20: =C18*C19 -> 1892.1193 | D20: =D18*D19 -> 1967.8041 | E20: =E18*E19 -> 2046.5163 | F20: =F18*F19 -> 2128.3769 | G20: =G18*G19 -> 2213.512 | H20: Formula
A21: Dividend payout | B21: 0.45 | C21: =Assumptions!$E$14 -> 0.45 | D21: =Assumptions!$E$14 -> 0.45 | E21: =Assumptions!$E$14 -> 0.45 | F21: =Assumptions!$E$14 -> 0.45 | G21: =Assumptions!$E$14 -> 0.45 | H21: Assumptions!E14
A22: Dividends | B22: =B20*B21 -> 774.855 | C22: =C20*C21 -> 851.45369 | D22: =D20*D21 -> 885.51184 | E22: =E20*E21 -> 920.93232 | F22: =F20*F21 -> 957.76961 | G22: =G20*G21 -> 996.08039 | H22: Formula
A23: Beginning parent equity | B23: =Historical!D16-B20+B22 -> 17498.855 | C23: =B24 -> 18445.9 | D23: =C24 -> 19486.566 | E23: =D24 -> 20568.858 | F23: =E24 -> 21694.442 | G23: =F24 -> 22865.049 | H23: Equity roll
A24: Ending parent equity | B24: =Historical!D16 -> 18445.9 | C24: =C23+C20-C22 -> 19486.566 | D24: =D23+D20-D22 -> 20568.858 | E24: =E23+E20-E22 -> 21694.442 | F24: =F23+F20-F22 -> 22865.049 | G24: =G23+G20-G22 -> 24082.481 | H24: Equity roll
A25: ROAE | B25: =B20/AVERAGE(B23:B24) -> 0.095808137 | C25: =C20/AVERAGE(C23:C24) -> 0.099762527 | D25: =D20/AVERAGE(D23:D24) -> 0.098254065 | E25: =E20/AVERAGE(E23:E24) -> 0.096846024 | F25: =F20/AVERAGE(F23:F24) -> 0.095529678 | G25: =G20/AVERAGE(G23:G24) -> 0.094297272 | H25: Formula
A26: 30-day PDL ratio | B26: =Historical!D23 -> 0.044 | C26: =MAX(0.025,MIN(0.07,B26-0.5*(B11-C11))) -> 0.044 | D26: =MAX(0.025,MIN(0.07,C26-0.5*(C11-D11))) -> 0.044 | E26: =MAX(0.025,MIN(0.07,D26-0.5*(D11-E11))) -> 0.044 | F26: =MAX(0.025,MIN(0.07,E26-0.5*(E11-F11))) -> 0.044 | G26: =MAX(0.025,MIN(0.07,F26-0.5*(F11-G11))) -> 0.044 | H26: Stress linkage

Sheet Forecast
A1: Forecast summary
A2: Parent-attributable profitability, capital retention and balance-sheet growth.
A4: Metric | B4: 2025A | C4: 2026E | D4: 2027E | E4: 2028E | F4: 2029E | G4: 2030E
A5: Gross loans | B5: =Operating_Model!B5 -> 192655.9 | C5: =Operating_Model!C5 -> 200362.14 | D5: =Operating_Model!D5 -> 208376.62 | E5: =Operating_Model!E5 -> 216711.69 | F5: =Operating_Model!F5 -> 225380.15 | G5: =Operating_Model!G5 -> 234395.36
A6: Net interest income | B6: =Operating_Model!B10 -> 7871.3 | C6: =Operating_Model!C10 -> 8420.0421 | D6: =Operating_Model!D10 -> 8756.8437 | E6: =Operating_Model!E10 -> 9107.1175 | F6: =Operating_Model!F10 -> 9471.4022 | G6: =Operating_Model!G10 -> 9850.2583
A7: Net impairment loss | B7: =Operating_Model!B12 -> 3538.9 | C7: =Operating_Model!C12 -> 3733.6713 | D7: =Operating_Model!D12 -> 3883.0182 | E7: =Operating_Model!E12 -> 4038.3389 | F7: =Operating_Model!F12 -> 4199.8725 | G7: =Operating_Model!G12 -> 4367.8674
A8: Pre-tax income | B8: =Operating_Model!B16 -> 4659.0349 | C8: =Operating_Model!C16 -> 5120.8252 | D8: =Operating_Model!D16 -> 5325.6582 | E8: =Operating_Model!E16 -> 5538.6846 | F8: =Operating_Model!F16 -> 5760.232 | G8: =Operating_Model!G16 -> 5990.6412
A9: Net income attributable | B9: =Operating_Model!B20 -> 1721.9 | C9: =Operating_Model!C20 -> 1892.1193 | D9: =Operating_Model!D20 -> 1967.8041 | E9: =Operating_Model!E20 -> 2046.5163 | F9: =Operating_Model!F20 -> 2128.3769 | G9: =Operating_Model!G20 -> 2213.512
A10: Dividends | B10: =Operating_Model!B22 -> 774.855 | C10: =Operating_Model!C22 -> 851.45369 | D10: =Operating_Model!D22 -> 885.51184 | E10: =Operating_Model!E22 -> 920.93232 | F10: =Operating_Model!F22 -> 957.76961 | G10: =Operating_Model!G22 -> 996.08039
A11: Ending parent equity | B11: =Operating_Model!B24 -> 18445.9 | C11: =Operating_Model!C24 -> 19486.566 | D11: =Operating_Model!D24 -> 20568.858 | E11: =Operating_Model!E24 -> 21694.442 | F11: =Operating_Model!F24 -> 22865.049 | G11: =Operating_Model!G24 -> 24082.481
A12: ROAE | B12: =Operating_Model!B25 -> 0.095808137 | C12: =Operating_Model!C25 -> 0.099762527 | D12: =Operating_Model!D25 -> 0.098254065 | E12: =Operating_Model!E25 -> 0.096846024 | F12: =Operating_Model!F25 -> 0.095529678 | G12: =Operating_Model!G25 -> 0.094297272
A13: 30-day PDL ratio | B13: =Operating_Model!B26 -> 0.044 | C13: =Operating_Model!C26 -> 0.044 | D13: =Operating_Model!D26 -> 0.044 | E13: =Operating_Model!E26 -> 0.044 | F13: =Operating_Model!F26 -> 0.044 | G13: =Operating_Model!G26 -> 0.044

Sheet Valuation
A1: Residual income, DDM and segment SOTP
A2: Three sector-appropriate methods; blended value uses visible scenario weights.
A4: Residual income
A5: Metric | B5: 2026E | C5: 2027E | D5: 2028E | E5: 2029E | F5: 2030E | G5: Output
A6: Beginning parent equity | B6: =Operating_Model!C23 -> 18445.9 | C6: =Operating_Model!D23 -> 19486.566 | D6: =Operating_Model!E23 -> 20568.858 | E6: =Operating_Model!F23 -> 21694.442 | F6: =Operating_Model!G23 -> 22865.049
A7: Net income attributable | B7: =Operating_Model!C20 -> 1892.1193 | C7: =Operating_Model!D20 -> 1967.8041 | D7: =Operating_Model!E20 -> 2046.5163 | E7: =Operating_Model!F20 -> 2128.3769 | F7: =Operating_Model!G20 -> 2213.512
A8: Equity charge | B8: =B6*Assumptions!$E$15 -> 2582.426 | C8: =C6*Assumptions!$E$15 -> 2728.1192 | D8: =D6*Assumptions!$E$15 -> 2879.6401 | E8: =E6*Assumptions!$E$15 -> 3037.2219 | F8: =F6*Assumptions!$E$15 -> 3201.1069
A9: Residual income | B9: =B7-B8 -> -690.30668 | C9: =C7-C8 -> -760.31509 | D9: =D7-D8 -> -833.12384 | E9: =E7-E8 -> -908.84495 | F9: =F7-F8 -> -987.59489
A10: Discount factor | B10: =1/(1+Assumptions!$E$15) -> 0.87719298 | C10: =B10/(1+Assumptions!$E$15) -> 0.76946753 | D10: =C10/(1+Assumptions!$E$15) -> 0.67497152 | E10: =D10/(1+Assumptions!$E$15) -> 0.59208028 | F10: =E10/(1+Assumptions!$E$15) -> 0.51936866
A11: PV residual income | B11: =B9*B10 -> -605.53217 | C11: =C9*C10 -> -585.03778 | D11: =D9*D10 -> -562.33486 | E11: =E9*E10 -> -538.10917 | F11: =F9*F10 -> -512.92584 | G11: =SUM(B11:F11) -> -2803.9398
A12: Terminal residual income | G12: =F9*(1+Assumptions!E16)/(Assumptions!E15-Assumptions!E16)*F10 -> -5334.4287
A13: Residual income equity value | G13: =Historical!D16+G11+G12 -> 10307.531
A15: Dividend discount model
A16: Metric | B16: 2026E | C16: 2027E | D16: 2028E | E16: 2029E | F16: 2030E | G16: Output
A17: Dividends | B17: =Operating_Model!C22 -> 851.45369 | C17: =Operating_Model!D22 -> 885.51184 | D17: =Operating_Model!E22 -> 920.93232 | E17: =Operating_Model!F22 -> 957.76961 | F17: =Operating_Model!G22 -> 996.08039
A18: Discount factor | B18: =B10 -> 0.87719298 | C18: =C10 -> 0.76946753 | D18: =D10 -> 0.67497152 | E18: =E10 -> 0.59208028 | F18: =F10 -> 0.51936866
A19: PV dividends | B19: =B17*B18 -> 746.88921 | C19: =C17*C18 -> 681.37261 | D19: =D17*D18 -> 621.60308 | E19: =E17*E18 -> 567.0765 | F19: =F17*F18 -> 517.33294 | G19: =SUM(B19:F19) -> 3134.2743
A20: Terminal dividend value | G20: =F17*(1+Assumptions!E16)/(Assumptions!E15-Assumptions!E16)*F18 -> 5380.2626
A21: DDM equity value | G21: =G19+G20 -> 8514.5369
A23: Reportable-segment SOTP
A24: Segment | B24: 2025 net income | C24: Multiple | D24: Value | E24: Basis | F24: Legal perimeter | G24: Source
A25: Banking services | B25: 1943.077 | C25: =Assumptions!E17 -> 8 | D25: =B25*C25 -> 15544.616 | E25: P/E | F25: Four banks + trust/brokerage | G25: 20-F Note 31 F-203
A26: Merchant banking | B26: 1173.734 | C26: =Assumptions!E18 -> 9 | D26: =B26*C26 -> 10563.606 | E26: P/E | F26: Corficolombiana / strategic sectors | G26: 20-F Note 31 F-203
A27: Pension and severance | B27: 703.01 | C27: =Assumptions!E19 -> 12 | D27: =B27*C27 -> 8436.12 | E27: P/E | F27: Porvenir | G27: 20-F Note 31 F-203
A28: Holding | B28: 1722.689 | C28: =Assumptions!E20 -> 5 | D28: =B28*C28 -> 8613.445 | E28: P/E | F28: Grupo Aval + Grupo Aval Ltd. | G28: 20-F Note 31 F-203
A29: Eliminations | B29: -2353.984 | C29: =Assumptions!E20 -> 5 | D29: =B29*C29 -> -11769.92 | E29: P/E | F29: Intersegment eliminations | G29: 20-F Note 31 F-203
A30: SOTP equity value | D30: =SUM(D25:D29) -> 31387.867
A32: Blended equity value
A33: Method | B33: Value | C33: Weight
A34: Residual income | B34: =G13 -> 10307.531 | C34: =Assumptions!E21 -> 0.4
A35: DDM | B35: =G21 -> 8514.5369 | C35: =Assumptions!E22 -> 0.3
A36: SOTP | B36: =D30 -> 31387.867 | C36: =Assumptions!E23 -> 0.3
A37: Blended equity value | B37: =SUMPRODUCT(B34:B36,C34:C36) -> 16093.734
A38: Implied COP per share | B38: =B37/Historical!D26*1000 -> 677.81709

Sheet Sensitivity
A1: Dynamic residual-income sensitivity
A2: Rows vary cost of equity; columns vary terminal growth. Every cell rebuilds the residual-income valuation.
A4: CoE / g | B4: 0.02 | C4: 0.03 | D4: 0.04 | E4: 0.05 | F4: 0.06
A5: 0.12 | B5: =(Historical!D16+SUM(Valuation!B9/(1+$A5)^1,Valuation!C9/(1+$A5)^2,Valuation!D9/(1+$A5)^3,Valuation!E9/(1+$A5)^4,Valuation!F9/(1+$A5)^5)+Valuation!F9*(1+B$4)/($A5-B$4)/(1+$A5)^5)/Historical!D26*1000 -> 411.75537 | C5: =(Historical!D16+SUM(Valuation!B9/(1+$A5)^1,Valuation!C9/(1+$A5)^2,Valuation!D9/(1+$A5)^3,Valuation!E9/(1+$A5)^4,Valuation!F9/(1+$A5)^5)+Valuation!F9*(1+C$4)/($A5-C$4)/(1+$A5)^5)/Historical!D26*1000 -> 382.38429 | D5: =(Historical!D16+SUM(Valuation!B9/(1+$A5)^1,Valuation!C9/(1+$A5)^2,Valuation!D9/(1+$A5)^3,Valuation!E9/(1+$A5)^4,Valuation!F9/(1+$A5)^5)+Valuation!F9*(1+D$4)/($A5-D$4)/(1+$A5)^5)/Historical!D26*1000 -> 345.67044 | E5: =(Historical!D16+SUM(Valuation!B9/(1+$A5)^1,Valuation!C9/(1+$A5)^2,Valuation!D9/(1+$A5)^3,Valuation!E9/(1+$A5)^4,Valuation!F9/(1+$A5)^5)+Valuation!F9*(1+E$4)/($A5-E$4)/(1+$A5)^5)/Historical!D26*1000 -> 298.46691 | F5: =(Historical!D16+SUM(Valuation!B9/(1+$A5)^1,Valuation!C9/(1+$A5)^2,Valuation!D9/(1+$A5)^3,Valuation!E9/(1+$A5)^4,Valuation!F9/(1+$A5)^5)+Valuation!F9*(1+F$4)/($A5-F$4)/(1+$A5)^5)/Historical!D26*1000 -> 235.52888
A6: 0.13 | B6: =(Historical!D16+SUM(Valuation!B9/(1+$A6)^1,Valuation!C9/(1+$A6)^2,Valuation!D9/(1+$A6)^3,Valuation!E9/(1+$A6)^4,Valuation!F9/(1+$A6)^5)+Valuation!F9*(1+B$4)/($A6-B$4)/(1+$A6)^5)/Historical!D26*1000 -> 446.367 | C6: =(Historical!D16+SUM(Valuation!B9/(1+$A6)^1,Valuation!C9/(1+$A6)^2,Valuation!D9/(1+$A6)^3,Valuation!E9/(1+$A6)^4,Valuation!F9/(1+$A6)^5)+Valuation!F9*(1+C$4)/($A6-C$4)/(1+$A6)^5)/Historical!D26*1000 -> 423.17554 | D6: =(Historical!D16+SUM(Valuation!B9/(1+$A6)^1,Valuation!C9/(1+$A6)^2,Valuation!D9/(1+$A6)^3,Valuation!E9/(1+$A6)^4,Valuation!F9/(1+$A6)^5)+Valuation!F9*(1+D$4)/($A6-D$4)/(1+$A6)^5)/Historical!D26*1000 -> 394.83042 | E6: =(Historical!D16+SUM(Valuation!B9/(1+$A6)^1,Valuation!C9/(1+$A6)^2,Valuation!D9/(1+$A6)^3,Valuation!E9/(1+$A6)^4,Valuation!F9/(1+$A6)^5)+Valuation!F9*(1+E$4)/($A6-E$4)/(1+$A6)^5)/Historical!D26*1000 -> 359.39903 | F6: =(Historical!D16+SUM(Valuation!B9/(1+$A6)^1,Valuation!C9/(1+$A6)^2,Valuation!D9/(1+$A6)^3,Valuation!E9/(1+$A6)^4,Valuation!F9/(1+$A6)^5)+Valuation!F9*(1+F$4)/($A6-F$4)/(1+$A6)^5)/Historical!D26*1000 -> 313.84438
A7: 0.14 | B7: =(Historical!D16+SUM(Valuation!B9/(1+$A7)^1,Valuation!C9/(1+$A7)^2,Valuation!D9/(1+$A7)^3,Valuation!E9/(1+$A7)^4,Valuation!F9/(1+$A7)^5)+Valuation!F9*(1+B$4)/($A7-B$4)/(1+$A7)^5)/Historical!D26*1000 -> 475.16592 | C7: =(Historical!D16+SUM(Valuation!B9/(1+$A7)^1,Valuation!C9/(1+$A7)^2,Valuation!D9/(1+$A7)^3,Valuation!E9/(1+$A7)^4,Valuation!F9/(1+$A7)^5)+Valuation!F9*(1+C$4)/($A7-C$4)/(1+$A7)^5)/Historical!D26*1000 -> 456.50895 | D7: =(Historical!D16+SUM(Valuation!B9/(1+$A7)^1,Valuation!C9/(1+$A7)^2,Valuation!D9/(1+$A7)^3,Valuation!E9/(1+$A7)^4,Valuation!F9/(1+$A7)^5)+Valuation!F9*(1+D$4)/($A7-D$4)/(1+$A7)^5)/Historical!D26*1000 -> 434.12058 | E7: =(Historical!D16+SUM(Valuation!B9/(1+$A7)^1,Valuation!C9/(1+$A7)^2,Valuation!D9/(1+$A7)^3,Valuation!E9/(1+$A7)^4,Valuation!F9/(1+$A7)^5)+Valuation!F9*(1+E$4)/($A7-E$4)/(1+$A7)^5)/Historical!D26*1000 -> 406.75702 | F7: =(Historical!D16+SUM(Valuation!B9/(1+$A7)^1,Valuation!C9/(1+$A7)^2,Valuation!D9/(1+$A7)^3,Valuation!E9/(1+$A7)^4,Valuation!F9/(1+$A7)^5)+Valuation!F9*(1+F$4)/($A7-F$4)/(1+$A7)^5)/Historical!D26*1000 -> 372.55256
A8: 0.15 | B8: =(Historical!D16+SUM(Valuation!B9/(1+$A8)^1,Valuation!C9/(1+$A8)^2,Valuation!D9/(1+$A8)^3,Valuation!E9/(1+$A8)^4,Valuation!F9/(1+$A8)^5)+Valuation!F9*(1+B$4)/($A8-B$4)/(1+$A8)^5)/Historical!D26*1000 -> 499.49534 | C8: =(Historical!D16+SUM(Valuation!B9/(1+$A8)^1,Valuation!C9/(1+$A8)^2,Valuation!D9/(1+$A8)^3,Valuation!E9/(1+$A8)^4,Valuation!F9/(1+$A8)^5)+Valuation!F9*(1+C$4)/($A8-C$4)/(1+$A8)^5)/Historical!D26*1000 -> 484.25065 | D8: =(Historical!D16+SUM(Valuation!B9/(1+$A8)^1,Valuation!C9/(1+$A8)^2,Valuation!D9/(1+$A8)^3,Valuation!E9/(1+$A8)^4,Valuation!F9/(1+$A8)^5)+Valuation!F9*(1+D$4)/($A8-D$4)/(1+$A8)^5)/Historical!D26*1000 -> 466.2342 | E8: =(Historical!D16+SUM(Valuation!B9/(1+$A8)^1,Valuation!C9/(1+$A8)^2,Valuation!D9/(1+$A8)^3,Valuation!E9/(1+$A8)^4,Valuation!F9/(1+$A8)^5)+Valuation!F9*(1+E$4)/($A8-E$4)/(1+$A8)^5)/Historical!D26*1000 -> 444.61445 | F8: =(Historical!D16+SUM(Valuation!B9/(1+$A8)^1,Valuation!C9/(1+$A8)^2,Valuation!D9/(1+$A8)^3,Valuation!E9/(1+$A8)^4,Valuation!F9/(1+$A8)^5)+Valuation!F9*(1+F$4)/($A8-F$4)/(1+$A8)^5)/Historical!D26*1000 -> 418.19033
A9: 0.16 | B9: =(Historical!D16+SUM(Valuation!B9/(1+$A9)^1,Valuation!C9/(1+$A9)^2,Valuation!D9/(1+$A9)^3,Valuation!E9/(1+$A9)^4,Valuation!F9/(1+$A9)^5)+Valuation!F9*(1+B$4)/($A9-B$4)/(1+$A9)^5)/Historical!D26*1000 -> 520.31459 | C9: =(Historical!D16+SUM(Valuation!B9/(1+$A9)^1,Valuation!C9/(1+$A9)^2,Valuation!D9/(1+$A9)^3,Valuation!E9/(1+$A9)^4,Valuation!F9/(1+$A9)^5)+Valuation!F9*(1+C$4)/($A9-C$4)/(1+$A9)^5)/Historical!D26*1000 -> 507.6925 | D9: =(Historical!D16+SUM(Valuation!B9/(1+$A9)^1,Valuation!C9/(1+$A9)^2,Valuation!D9/(1+$A9)^3,Valuation!E9/(1+$A9)^4,Valuation!F9/(1+$A9)^5)+Valuation!F9*(1+D$4)/($A9-D$4)/(1+$A9)^5)/Historical!D26*1000 -> 492.96673 | E9: =(Historical!D16+SUM(Valuation!B9/(1+$A9)^1,Valuation!C9/(1+$A9)^2,Valuation!D9/(1+$A9)^3,Valuation!E9/(1+$A9)^4,Valuation!F9/(1+$A9)^5)+Valuation!F9*(1+E$4)/($A9-E$4)/(1+$A9)^5)/Historical!D26*1000 -> 475.56355 | F9: =(Historical!D16+SUM(Valuation!B9/(1+$A9)^1,Valuation!C9/(1+$A9)^2,Valuation!D9/(1+$A9)^3,Valuation!E9/(1+$A9)^4,Valuation!F9/(1+$A9)^5)+Valuation!F9*(1+F$4)/($A9-F$4)/(1+$A9)^5)/Historical!D26*1000 -> 454.67973

Sheet Checks
A1: Model checks
A2: Critical source, banking mechanics, capital, valuation and sensitivity assertions.
A4: Check | B4: Actual | C4: Expected | D4: Difference | E4: Tolerance | F4: Status | G4: Severity | H4: Location / fix hint
A5: Source ledger completeness | B5: =Sources!O23 -> 18 | C5: 18 | D5: =B5-C5 -> 0 | E5: 0 | F5: =IF(ABS(D5)<=E5,"PASS","FAIL") -> PASS | G5: Critical | H5: Sources!A4:P23
A6: Assets equal liabilities + equity | B6: =Historical!D12 -> 348936.7 | C6: 348936.7 | D6: =B6-C6 -> 0 | E6: 0.1 | F6: =IF(ABS(D6)<=E6,"PASS","FAIL") -> PASS | G6: Critical | H6: Historical!D12 / 20-F p.12
A7: NII formula mechanics | B7: =Operating_Model!C10 -> 8420.0421 | C7: =Operating_Model!C8*Operating_Model!C9 -> 8420.0421 | D7: =B7-C7 -> 0 | E7: 0.1 | F7: =IF(ABS(D7)<=E7,"PASS","FAIL") -> PASS | G7: Critical | H7: Operating_Model!C8:C10
A8: Credit-loss formula mechanics | B8: =Operating_Model!C12 -> 3733.6713 | C8: =Operating_Model!C7*Operating_Model!C11 -> 3733.6713 | D8: =B8-C8 -> 0 | E8: 0.1 | F8: =IF(ABS(D8)<=E8,"PASS","FAIL") -> PASS | G8: Critical | H8: Operating_Model!C7:C12
A9: Equity roll-forward | B9: =Operating_Model!C24 -> 19486.566 | C9: =Operating_Model!C23+Operating_Model!C20-Operating_Model!C22 -> 19486.566 | D9: =B9-C9 -> 0 | E9: 0.1 | F9: =IF(ABS(D9)<=E9,"PASS","FAIL") -> PASS | G9: Critical | H9: Operating_Model!C20:C24
A10: Cost of equity exceeds terminal growth | B10: =Assumptions!E15 -> 0.14 | C10: =Assumptions!E16 -> 0.04 | D10: =B10-C10 -> 0.1 | E10: 0.01 | F10: =IF(D10>E10,"PASS","FAIL") -> PASS | G10: Critical | H10: Assumptions!E15:E16
A11: Valuation weights sum to 100% | B11: =SUM(Assumptions!E21:E23) -> 1 | C11: 1 | D11: =B11-C11 -> 0 | E11: 0.0001 | F11: =IF(ABS(D11)<=E11,"PASS","FAIL") -> PASS | G11: Critical | H11: Assumptions!E21:E23
A12: SOTP segment sum | B12: =Valuation!D30 -> 31387.867 | C12: =SUM(Valuation!D25:D29) -> 31387.867 | D12: =B12-C12 -> 0 | E12: 0.1 | F12: =IF(ABS(D12)<=E12,"PASS","FAIL") -> PASS | G12: Critical | H12: Valuation!D25:D30
A13: Scenario selector valid | B13: =Assumptions!B4 -> 1 | C13: 1 | D13: =0 -> 0 | E13: 0 | F13: =IF(AND(B13>=1,B13<=3),"PASS","FAIL") -> PASS | G13: Critical | H13: Assumptions!B4
A14: Parent equity positive through forecast | B14: =MIN(Operating_Model!C24:G24) -> 19486.566 | C14: 0 | D14: =B14-C14 -> 19486.566 | E14: 0 | F14: =IF(D14>E14,"PASS","FAIL") -> PASS | G14: Critical | H14: Operating_Model!C24:G24
A15: Forecast engine propagates through 2030 | B15: =COUNTIF(Operating_Model!D5:G25,0) -> 0 | C15: 0 | D15: =B15-C15 -> 0 | E15: 0 | F15: =IF(ABS(D15)<=E15,"PASS","FAIL") -> PASS | G15: Critical | H15: Operating_Model!D5:G25
A16: Overall model status | F16: =IF(COUNTIF(F5:F15,"FAIL")=0,"PASS","FAIL") -> PASS | H16: All critical checks must pass

Sheet Gate_9of10
A1: Owner 9/10 submission gate
A2: Owner evidence only; independent reviewer decides final certification after the hash is frozen.
A4: Gate | B4: Weight | C4: Owner status | D4: Blocker class | E4: Workbook evidence | F4: External evidence pointer | G4: Reviewer note | H4: Score
A5: H0 Controlled lineage / OOXML | B5: 5 | C5: PASS | D5: None | E5: 00_Cover; Change_Log | F5: internal QA evidence (not published) | G5: Original + controlled hashes externally recorded | H5: 5
A6: H1 Source fidelity / provenance | B6: 20 | C6: PASS | D6: None | E6: Sources; Legal_Entities | F6: 2025 20-F PDF + SEC filing | G6: Claim-level parent and subsidiary mapping | H6: 20
A7: H2 Formula and schedule mechanics | B7: 15 | C7: PASS | D7: None | E7: Operating_Model; Forecast | F7: Scenario evidence | G7: Integrated banking and capital schedule | H7: 15
A8: H3 Scenarios / sensitivity | B8: 10 | C8: PASS | D8: None | E8: Assumptions; Sensitivity | F8: Scenario perturbation log | G8: Dynamic base/bull/bear and RI grid | H8: 10
A9: H4 Valuation fit / mechanics | B9: 15 | C9: PASS | D9: None | E9: Valuation | F9: RI/DDM/SOTP evidence | G9: Holdco and legal perimeter fit | H9: 15
A10: H5 Checks / error state | B10: 8 | C10: PASS | D10: None | E10: Checks | F10: Post-recalc error scan | G10: Formula-driven gate | H10: 8
A11: H6 Native recalculation | B11: 10 | C11: PASS | D11: None | E11: Gate_9of10!A17:H20 | F11: Native recalc log | G11: Two isolated-profile LibreOfficeDev passes plus artifact-tool reopen and error scan | H11: 10
A12: H7 Post-recalc visual QA | B12: 7 | C12: PASS | D12: None | E12: All user-facing sheets | F12: Final preview manifest | G12: Every user-facing sheet rendered and reviewed; manifest is hash-bound after final pass | H12: 7
A13: H8 Material economic upgrade | B13: 5 | C13: PASS | D13: None | E13: Legal_Entities; Operating_Model; Valuation | F13: Change_Log | G13: Replaces generic bank shell with parent/segment model | H13: 5
A14: H9 Governance / handoff | B14: 5 | C14: PASS | D14: None | E14: 00_Cover; Change_Log | F14: Evidence JSON | G14: Independent certification pending | H14: 5
A16: Owner score | H16: =SUM(H5:H14) -> 100
A17: Owner decision | C17: =IF(H16>=90,"SUBMITTED FOR INDEPENDENT 9/10 REVIEW","NOT READY") -> SUBMITTED FOR INDEPENDENT 9/10 REVIEW
A19: Native engine | B19: LibreOfficeDev 26.8.0.0.alpha0 2c87e51eeaa2b413ff4ae097b2705eea1995d8e5
A20: Lifecycle | B20: RECALC / SAVE / CLOSE / REOPEN x2
A21: Owner evidence | B21: internal QA evidence (not published)

Sheet Change_Log
A1: Change log and governance
A2: Controlled legal-entity and financial-holding-company rebuild.
A4: Date | B4: Version | C4: Author | D4: Change | E4: Evidence | F4: Reviewer status
A5: 2026-07-16 | B5: 2.0 | C5: Codex | D5: Rebuilt as Grupo Aval parent / subsidiary / reportable-segment model | E5: Legal_Entities; Operating_Model | F5: Owner complete
A6: 2026-07-16 | B6: 2.0 | C6: Codex | D6: Mapped 2025 Form 20-F and MFG perimeter caveat | E6: Sources; 00_Cover | F6: Owner complete
A7: 2026-07-16 | B7: 2.0 | C7: Codex | D7: Added RI, DDM and segment SOTP | E7: Valuation | F7: Owner complete
A8: 2026-07-16 | B8: 2.0 | C8: Codex | D8: Added formula-driven scenarios, sensitivity and checks | E8: Assumptions; Sensitivity; Checks | F8: Owner complete
A9: 2026-07-16 | B9: 2.0 | C9: Independent reviewer | D9: Certification decision | E9: Frozen workbook hash | F9: Pending

Sheet Claude Code Log
A1: Turn # | B1: Date | C1: User Request | D1: Action Taken | E1: Details | F1: Outcome
A2: 1 | B2: 46324.359 | C2: Prepare a public model copy | D2: Remove local paths and private build references; preserve financial formulas and inputs | E2: Agent run with MOG as the tool, checked by guard v1. The guard measured every sheet before and after the run. Changed: Gate_9of10: 2 cells written, at F5, B21. Agent: OpenFinmods export | F2: Compare against source and review public copy
