Workbook

Sheet EEFF
A1: Panama Power Holdings, Inc. y Subsidiarias
A2: Estados Financieros Auditados FY21-FY25
A3: en B/. sin escala
A5: Años | B5: FY21A | C5: FY22A | D5: FY23A | E5: FY24A | F5: FY25A | G5: FY26E | H5: FY27E | I5: FY28E | J5: FY29E | K5: FY30E
A6: Estado de Resultados
A7: Venta de energía | B7: 42793727 | C7: 57204243 | D7: 53187368 | E7: 55356497 | F7: 48358044
A8: Compras de energía y costos asociados | B8: 4427043 | C8: 8559953 | D8: 12013335 | E8: 9960198 | F8: 4986124
A9: Cargo de transmisión | B9: 1368202 | C9: 1850469 | D9: 2243773 | E9: 2503761 | F9: 1761951
A10: Total de costo de energía | B10: 5795245 | C10: 10410422 | D10: 14257108 | E10: 12463959 | F10: 6748075
A11: Ingresos por crédito fiscal y otros | B11: 869881 | C11: 1974498 | D11: 2169724 | E11: 642966 | F11: 1922207
A12: Depreciación y amortización | B12: 11878451 | C12: 11881633 | D12: 11997283 | E12: 12446869 | F12: 12521408
A13: Operación y mantenimiento | B13: 2400538 | C13: 2548375 | D13: 2841019 | E13: 2549512 | F13: 3004212
A14: Generales y administrativos | B14: 4588379 | C14: 5332929 | D14: 5554329 | E14: 5511351 | F14: 5684677
A15: Otras pérdidas netas | C15: 0 | D15: 127418
A16: Pérdida en activos no financieros | B16: 20000
A17: Pérdida en activos financieros | B17: 139398
A18: Total de gastos operativos | B18: 19026766 | C18: 19762937 | D18: 20520049 | E18: 20507732 | F18: 21210297
A19: Utilidad operativa | B19: 18841597 | C19: 29005382 | D19: 20579935 | E19: 23027772 | F19: 22321879
A20: Costos financieros | B20: 10739963 | C20: 10140045 | D20: 9645428 | E20: 9291709 | F20: 8681196
A21: Ingresos financieros | B21: -129032 | C21: -140572 | D21: -242921 | E21: -362555 | F21: -547419
A22: Costos financieros, neto | B22: 10610931 | C22: 9999473 | D22: 9402507 | E22: 8929154 | F22: 8133777
A23: Utilidad antes de impuesto sobre la renta | B23: 8230666 | C23: 19005909 | D23: 11177428 | E23: 14098618 | F23: 14188102
A24: Impuesto sobre la renta | B24: -3095130 | C24: -5342988 | D24: -3950425 | E24: -4617385 | F24: -4887298
A25: Utilidad neta integral | B25: 5135536 | C25: 13662921 | D25: 7227003 | E25: 9481233 | F25: 9300804
A27: Años | B27: FY21A | C27: FY22A | D27: FY23A | E27: FY24A | F27: FY25A | G27: FY26E | H27: FY27E | I27: FY28E | J27: FY29E | K27: FY30E
A28: Balance General
A29: Efectivo | B29: 9167597 | C29: 10955792 | D29: 10299859 | E29: 9494389 | F29: 11057503
A30: Depósito a plazo fijo mayor a 90 días | F30: 8000000
A31: Cuentas por cobrar | B31: 9794078 | C31: 10480520 | D31: 10514874 | E31: 10018368 | F31: 8602706
A32: Inventario de repuestos y suministros | B32: 1954889 | C32: 2283806 | D32: 2176373 | E32: 2315599 | F32: 2666409
A33: Gastos pagados por adelantado | B33: 189074 | C33: 171942 | D33: 1400465 | E33: 475685 | F33: 836786
A34: Crédito fiscal por inversión | B34: 1825438 | C34: 2648365 | D34: 1541175 | E34: 1829780 | F34: 0
A35: Otros activos | B35: 654057 | C35: 1115702 | D35: 510364 | E35: 551482 | F35: 497274
A36: Total de activos circulantes | B36: 23585133 | C36: 27656127 | D36: 26443110 | E36: 24685303 | F36: 31660678
A37: Activo financiero restringido | B37: 4206485 | C37: 4234822 | D37: 4033700 | E37: 4197349 | F37: 4260349
A38: Cuentas por cobrar, no circulante | B38: 213118
A39: Propiedad, planta y equipo, neto | B39: 289872297 | C39: 280225020 | D39: 278143135 | E39: 266144886 | F39: 254111593
A40: Plusvalía | B40: 7033750 | C40: 7033750 | D40: 7033750 | E40: 7033750 | F40: 7033750
A41: Costos de exploración y evaluación | B41: 173084 | C41: 174084
A42: Activos intangibles, neto | B42: 538918 | C42: 525826 | D42: 512733 | E42: 499640 | F42: 509989
A43: Activos por derechos de uso | B43: 142658 | C43: 101898 | D43: 69290 | E43: 36682 | F43: 4074
A44: Impuesto sobre la renta diferido | B44: 193382 | C44: 140101 | D44: 86820
A45: Crédito fiscal por inversión, no circulante | B45: 1863452 | C45: 1321139 | D45: 238792
A46: Otros activos, no circulante | B46: 209800 | C46: 227497 | D46: 242970 | E46: 276061 | F46: 284646
A47: Total de activos no circulantes | B47: 304446944 | C47: 293984137 | D47: 290361190 | E47: 278188368 | F47: 266204401
A48: Total de activos | B48: 328032077 | C48: 321640264 | D48: 316804300 | E48: 302873671 | F48: 297865079
A49: Cuentas por pagar | B49: 3817823 | C49: 1649350 | D49: 1515059 | E49: 614193 | F49: 1148554
A50: Bonos por pagar | B50: 8791215 | C50: 8791215 | D50: 12541215 | E50: 8791215 | F50: 8791215
A51: Intereses de bonos por pagar | C51: 26611 | D51: 2297125 | E51: 22920 | F51: 21419
A52: Préstamos por pagar | B52: 0 | C52: 758413 | D52: 418472 | E52: 67845 | F52: 215241
A53: Ingreso diferido por crédito fiscal por inversión | B53: 1825438 | C53: 2648365 | D53: 1541175 | E53: 1829780 | F53: 0
A54: Impuesto sobre la renta por pagar | B54: 1255449 | C54: 2384922 | D54: 30637 | E54: 1883666 | F54: 181645
A55: Pasivos por arrendamientos | B55: 32604 | C55: 32604 | D55: 32604 | E55: 32604 | F55: 4074
A56: Otros pasivos | B56: 1522447 | C56: 1534472 | D56: 1223799 | E56: 1101389 | F56: 1330438
A57: Total de pasivos circulantes | B57: 17244976 | C57: 17825952 | D57: 19600086 | E57: 14343612 | F57: 11692586
A58: Bonos por pagar, neto | B58: 156615714 | C58: 147824500 | D58: 139033286 | E58: 130242072 | F58: 121450858
A59: Préstamos por pagar, no circulante | C59: 0 | D59: 3503256 | E59: 2679481 | F59: 2275211
A60: Ingreso diferido por crédito fiscal en inversión | B60: 1863452 | C60: 1321139 | D60: 238792
A61: Pasivos por arrendamientos, no circulante | B61: 110054 | C61: 69294 | D61: 36686 | E61: 4078 | F61: 0
A62: Otros pasivos, no circulante | B62: 204886 | C62: 218261 | D62: 242828 | E62: 261536 | F62: 289022
A63: Total de pasivos no circulantes | B63: 158794106 | C63: 149433194 | D63: 143054848 | E63: 133187167 | F63: 124015091
A64: Total de pasivos | B64: 176039082 | C64: 167259146 | D64: 162654934 | E64: 147530779 | F64: 135707677
A65: Acciones comunes | B65: 16575011 | C65: 16575011 | D65: 16575011 | E65: 16575011 | F65: 16575011
A66: Acciones preferidas | B66: 5000 | C66: 5000 | D66: 5000 | E66: 5000 | F66: 5000
A67: Excedente en valor de suscripción de acciones comunes | B67: 144564461 | C67: 133624953 | D67: 126166198 | E67: 117878693 | F67: 115392441
A68: Impuesto complementario | B68: -1349935 | C68: -1685225 | D68: -1685225 | E68: -1685427 | F68: -1685469
A69: Utilidades no distribuidas | B69: -7801542 | C69: 5861379 | D69: 13088382 | E69: 22569615 | F69: 31870419
A70: Total de patrimonio | B70: 151992995 | C70: 154381118 | D70: 154149366 | E70: 155342892 | F70: 162157402
A71: Total de pasivos y patrimonio | B71: 328032077 | C71: 321640264 | D71: 316804300 | E71: 302873671 | F71: 297865079
A73: Años | B73: FY21A | C73: FY22A | D73: FY23A | E73: FY24A | F73: FY25A | G73: FY26E | H73: FY27E | I73: FY28E | J73: FY29E | K73: FY30E
A74: Estado de Flujos de Efectivo
A75: Utilidad antes de impuesto sobre la renta | B75: 8230666 | C75: 19005909 | D75: 11177428 | E75: 14098618 | F75: 14188102
A76: Depreciación | B76: 11837322 | C76: 11835933 | D76: 11948074 | E76: 12401168 | F76: 12475149
A77: Retiro de activo fijo | B77: 0 | C77: 105000
A78: Amortización de intangibles | B78: 13719 | C78: 13092 | D78: 13093 | E78: 13093 | F78: 13651
A79: Depreciación de derechos de uso | B79: 27410 | C79: 32608 | D79: 36116 | E79: 32608 | F79: 32608
A80: Amortización de costos de financiamiento diferidos | B80: 210785 | C80: 208786 | D80: 208786 | E80: 208786 | F80: 208786
A81: Gastos de intereses | B81: 10348312 | C81: 9766628 | D81: 9267884 | E81: 8906765 | F81: 8323100
A82: Pérdida en activos no financieros | B82: 20000
A83: Ingresos por crédito fiscal | B83: -757608 | C83: -1930197 | D83: -1653193 | E83: -600000 | F83: -1829780
A84: Cuentas por cobrar | B84: -616516 | C84: -473324 | D84: -34354 | E84: 496506 | F84: 1415662
A85: Inventario de repuestos y suministros | B85: -6659 | C85: -328917 | D85: 107433 | E85: -139226 | F85: -350810
A86: Gastos pagados por adelantado | B86: 468120 | C86: 4885169 | D86: 2721902 | E86: 1730438 | F86: 4196213
A87: Otros activos | B87: 88309 | C87: -479342 | D87: 589865 | E87: -159744 | F87: 46908
A88: Cuentas por pagar | B88: 1281734 | C88: -7113790 | D88: -3693608 | E88: -2897310 | F88: -4225876
A89: Otros pasivos | B89: 46812 | C89: 25400 | D89: -286106 | E89: -103702 | F89: 256535
A90: Intereses pagados | B90: -10341713 | C90: -9775991 | D90: -6997370 | E90: -11176527 | F90: -8325188
A91: Impuesto sobre la renta pagado | B91: -891774 | C91: -2116783 | D91: -4992852 | E91: -805658 | F91: -4557314
A92: Efectivo neto provisto por las actividades de operación | B92: 19958919 | C92: 23660181 | D92: 18413098 | E92: 22005815 | F92: 21867746
A93: Depósito a plazo con vencimiento original mayor a tres meses | E93: 0 | F93: -8000000
A94: Costo de evaluación y exploración | B94: 0 | C94: -1000 | D94: 174084
A95: Adquisición de activos intangibles | E95: 0 | F95: -24000
A96: Adiciones de propiedad, planta y equipo | B96: -140606 | C96: -2293656 | D96: -9866189 | E96: -402919 | F96: -441856
A97: Adquisición de activos por derecho de uso | B97: -77042
A98: Efectivo neto utilizado en las actividades de inversión | B98: -217648 | C98: -2294656 | D98: -9692105 | E98: -402919 | F98: -8465856
A99: Producto de préstamos | B99: 0 | C99: 758413 | D99: 3163315
A100: Pagos de préstamos | D100: 0 | E100: -1174402 | F100: -256874
A101: Pagos de bonos | B101: -9000000 | C101: -9000000 | D101: -5250000 | E101: -12750000 | F101: -9000000
A102: Activo financiero restringido | B102: 130811 | C102: -28337 | D102: 201122 | E102: -163649 | F102: -63000
A103: Costo de financiamiento diferido | B103: -14910
...

Sheet Supuestos
A1: Panama Power Holdings, Inc. y Subsidiarias
A3: COLOR KEY: Input (azul) · Fórmula (negro) · Link inter-hoja (verde)
A4: Escenario (1=Base, 2=Bull, 3=Bear)
A5: Selector escenario | C5: 1 | M5: caso | N5: NOT_DISCLOSED | Q5: Input de escenario desde fuente citada o NOT_DISCLOSED.
A6: Escenario activo | C6: =CHOOSE($C$5,"Base","Bull","Bear") -> Base | M6: moneda del modelo | N6: NOT_DISCLOSED | Q6: Selector de caso activo C5: Base/Bull/Bear.
A8: Años | B8: FY21A | C8: FY22A | D8: FY23A | E8: FY24A | F8: FY25A | G8: FY26E | H8: FY27E | I8: FY28E | J8: FY29E | K8: FY30E | M8: Unidad | N8: Fuente / nota | Q8: Rationale
A10: A. PRODUCCIÓN POR PLANTA (MWh neto = MW × 8.760 h × CF; CF derivado de generación real, blended hidro+solar)
A11: Factor de planta NETO (CF) — activo | G11: =CHOOSE($C$5,G13,G14,G12) -> 0.41 | H11: =CHOOSE($C$5,H13,H14,H12) -> 0.41 | I11: =CHOOSE($C$5,I13,I14,I12) -> 0.41 | J11: =CHOOSE($C$5,J13,J14,J12) -> 0.41 | K11: =CHOOSE($C$5,K13,K14,K12) -> 0.41 | M11: % | N11: a working file kept by the maintainer | Q11: Selector de caso activo C5: Base/Bull/Bear.
A12: Bear | G12: 0.35 | H12: 0.35 | I12: 0.35 | J12: 0.35 | K12: 0.35 | M12: % | N12: a working file kept by the maintainer | Q12: Escenario driver citado; NOT_DISCLOSED si no hay fuente explícita.
A13: Base | G13: 0.41 | H13: 0.41 | I13: 0.41 | J13: 0.41 | K13: 0.41 | M13: % | N13: a working file kept by the maintainer | Q13: Escenario driver citado; NOT_DISCLOSED si no hay fuente explícita.
A14: Bull | G14: 0.46 | H14: 0.46 | I14: 0.46 | J14: 0.46 | K14: 0.46 | M14: % | N14: a working file kept by the maintainer | Q14: Escenario driver citado; NOT_DISCLOSED si no hay fuente explícita.
A15: Horas / año | B15: 8760 | C15: 8760 | D15: 8760 | E15: 8760 | F15: 8760 | G15: 8760 | H15: 8760 | I15: 8760 | J15: 8760 | K15: 8760 | M15: horas/año | N15: a working file kept by the maintainer | Q15: Input de escenario desde fuente citada o NOT_DISCLOSED.
A16: El Alto — 73.18 MW | G16: =73.18*G15*G11 -> 262833.29 | H16: =73.18*H15*H11 -> 262833.29 | I16: =73.18*I15*I11 -> 262833.29 | J16: =73.18*J15*J11 -> 262833.29 | K16: =73.18*K15*K11 -> 262833.29 | M16: MW | N16: a working file kept by the maintainer | Q16: Derivación mecánica por fórmula viva.
A17: Pedregalito 1 — 20.1 MW | G17: =20.1*G15*G11 -> 72191.16 | H17: =20.1*H15*H11 -> 72191.16 | I17: =20.1*I15*I11 -> 72191.16 | J17: =20.1*J15*J11 -> 72191.16 | K17: =20.1*K15*K11 -> 72191.16 | M17: MW | N17: a working file kept by the maintainer | Q17: Derivación mecánica por fórmula viva.
A18: Pedregalito 2 — 12.5 MW | G18: =12.5*G15*G11 -> 44895 | H18: =12.5*H15*H11 -> 44895 | I18: =12.5*I15*I11 -> 44895 | J18: =12.5*J15*J11 -> 44895 | K18: =12.5*K15*K11 -> 44895 | M18: MW | N18: a working file kept by the maintainer | Q18: Derivación mecánica por fórmula viva.
A19: Cochea — 15.5 MW | G19: =15.5*G15*G11 -> 55669.8 | H19: =15.5*H15*H11 -> 55669.8 | I19: =15.5*I15*I11 -> 55669.8 | J19: =15.5*J15*J11 -> 55669.8 | K19: =15.5*K15*K11 -> 55669.8 | M19: MW | N19: a working file kept by the maintainer | Q19: Derivación mecánica por fórmula viva.
A20: Mini Central El Alto — 0.98 MW | G20: =0.98*G15*G11 -> 3519.768 | H20: =0.98*H15*H11 -> 3519.768 | I20: =0.98*I15*I11 -> 3519.768 | J20: =0.98*J15*J11 -> 3519.768 | K20: =0.98*K15*K11 -> 3519.768 | M20: MW | N20: a working file kept by the maintainer | Q20: Derivación mecánica por fórmula viva.
A21: Pedregalito Solar — 9.9 MW | G21: =9.9*G15*G11 -> 35556.84 | H21: =9.9*H15*H11 -> 35556.84 | I21: =9.9*I15*I11 -> 35556.84 | J21: =9.9*J15*J11 -> 35556.84 | K21: =9.9*K15*K11 -> 35556.84 | M21: MW | N21: a working file kept by the maintainer | Q21: Derivación mecánica por fórmula viva.
A22: Generación neta total (MWh) | B22: 426569 | C22: 549284 | D22: 374482 | E22: 497784 | F22: 470665 | G22: =G76 -> 476626.99 | H22: =H76 -> 476626.99 | I22: =I76 -> 476626.99 | J22: =J76 -> 476626.99 | K22: =K76 -> 476626.99 | M22: MWh | N22: F1 fila 76: suma generacion por planta (CF ENSO Bear/Base/Bull por planta, CND A2). Filas 16-21 = memo legacy CF-flota (ya no suman al total forecast). | Q22: Suma mecánica del bloque.
A24: B. PRECIOS POR FUENTE ($/MWh)
A25: PPA contratado ($/MWh, blended realizado FY25 potencia+energía) | B25: 106.01 | C25: 105.52 | D25: 112.15 | E25: 111.21 | F25: 108.46 | G25: =(G85+G92+G94+G96)/G32 -> 80.102546 | H25: =(H85+H92+H94+H96)/H32 -> 71.627493 | I25: =(I85+I92+I94+I96)/I32 -> 79.754891 | J25: =(J85+J92+J94+J96)/J32 -> 79.754891 | K25: =(K85+0.5*K65*91.649)/K32 -> 51.19908 | M25: MWh | N25: F2/F3: forecast = blended Seccion F (ingresos contratados: award GC-02-2026 fila 85 + PPAs vigentes filas 92/94/96) / MWh contratados fila 32; K = award + 0.5xCochea a 91.649 $/MWh (A4a). Solo energia (capacidad va como termino propio en fila 39). Label pinned por contrato ACTIVE pph_pilot_energy_pxq_v0 (node ppa_blended_price) — hist B-F sigue siendo blended realizado. | Q25: Derivación mecánica por fórmula viva.
A26: Spot / merchant ($/MWh) — activo | B26: 58.4 | C26: 77.76 | D26: 113.08 | E26: 72.56 | F26: 62.75 | G26: =CHOOSE($C$5,G28,G29,G27) -> 60 | H26: =CHOOSE($C$5,H28,H29,H27) -> 58 | I26: =CHOOSE($C$5,I28,I29,I27) -> 57 | J26: =CHOOSE($C$5,J28,J29,J27) -> 56 | K26: =CHOOSE($C$5,K28,K29,K27) -> 55 | M26: MWh | N26: a working file kept by the maintainer | Q26: Selector de caso activo C5: Base/Bull/Bear.
A27: Bear | G27: 45 | H27: 44 | I27: 43 | J27: 42 | K27: 41 | M27: moneda del modelo | N27: a working file kept by the maintainer | Q27: Escenario driver citado; NOT_DISCLOSED si no hay fuente explícita.
A28: Base | G28: 60 | H28: 58 | I28: 57 | J28: 56 | K28: 55 | M28: moneda del modelo | N28: a working file kept by the maintainer | Q28: Escenario driver citado; NOT_DISCLOSED si no hay fuente explícita.
A29: Bull | G29: 75 | H29: 73 | I29: 72 | J29: 71 | K29: 70 | M29: moneda del modelo | N29: a working file kept by the maintainer | Q29: Escenario driver citado; NOT_DISCLOSED si no hay fuente explícita.
A31: C. VOLUMEN POR CANAL (MWh, con cliffs PPA por parque)
A32: MWh contratado (potencia+energía y solo-energía) | B32: 300655 | C32: 306746 | D32: 276777 | E32: 282678 | F32: 305119 | G32: =G83+G55+G60+G65 -> 284701.22 | H32: =H83+H55+H60+H65 -> 364081.22 | I32: =I83+I55+I60+I65 -> 272938.22 | J32: =J83+J55+J60+J65 -> 272938.22 | K32: =K83+0.5*K65 -> 117889.08 | M32: MWh | N32: F2 fila 83 (award GC-02-2026 SED+SEO, MWh/ano activo) + F1 generacion Ped1(55)/Ped2(60)/Cochea(65) mientras PPA vigente (expiries dic-29/jun-30; sin re-contratacion asumida — ausentes de GC-02-2026). | Q32: Derivación mecánica por fórmula viva.
A33: MWh spot / merchant (residual) | B33: 157317 | C33: 246692 | D33: 129626 | E33: 219421 | F33: 215832 | G33: =MAX(0,G22-G32) -> 191925.77 | H33: =MAX(0,H22-H32) -> 112545.77 | I33: =MAX(0,I22-I32) -> 203688.77 | J33: =MAX(0,J22-J32) -> 203688.77 | K33: =MAX(0,K22-K32) -> 358737.91 | M33: MWh | N33: Fila 22 (= F1 fila 76, generacion total ENSO) - fila 32 (contratado). Referencia via fila 22 para mantener el nodo de contrato total_generation_mwh vivo (no decorativo). | Q33: Derivación mecánica por fórmula viva.
A35: D. INGRESO POR FUENTE ($ = MWh × precio)
A36: Ingreso energía FY25A (auditado, ref EEFF) | B36: =EEFF!B7 -> 42793727 | C36: =EEFF!C7 -> 57204243 | D36: =EEFF!D7 -> 53187368 | E36: =EEFF!E7 -> 55356497 | F36: =EEFF!F7 -> 48358044 | M36: MWh | N36: EEFF:Venta de energía | Q36: Mirror histórico desde fuente citada.
A37: Ingreso PPA | B37: =B32*B25 -> 31872437 | C37: =C32*C25 -> 32367838 | D37: =D32*D25 -> 31040541 | E37: =E32*E25 -> 31436620 | F37: =F32*F25 -> 33093207 | G37: =G32*G25 -> 22805293 | H37: =H32*H25 -> 26078226 | I37: =I32*I25 -> 21768158 | ... K37: =K32*K25 -> 6035812.4 | M37: moneda del modelo | N37: a working file kept by the maintainer | Q37: Derivación mecánica por fórmula viva.
A38: Ingreso spot / merchant | B38: =B33*B26 -> 9187312.8 | C38: =C33*C26 -> 19182770 | D38: =D33*D26 -> 14658108 | E38: =E33*E26 -> 15921188 | F38: =F33*F26 -> 13543458 | G38: =G33*G26 -> 11515546 | H38: =H33*H26 -> 6527654.5 | I38: =I33*I26 -> 11610260 | ... K38: =K33*K26 -> 19730585 | M38: moneda del modelo | N38: a working file kept by the maintainer | Q38: Derivación mecánica por fórmula viva.
A39: TOTAL INGRESO ENERGÍA | B39: =B37+B38 -> 41059749 | C39: =C37+C38 -> 51550608 | D39: =D37+D38 -> 45698649 | E39: =E37+E38 -> 47357808 | F39: =F37+F38 -> 46636665 | G39: =G37+G38+G82 -> 38521429 | H39: =H37+H38+H82 -> 32605880 | I39: =I37+I38+I82 -> 33463954 | J39: =J37+J38+J82 -> 33345801 | K39: =K37+K38+K82 -> 25937470 | M39: MWh | N39: Ingreso PPA (37) + spot/merchant (38) + capacidad El Alto (F2 fila 82: valle FY27 = 0 explicito, award 4.4MW@3.24 desde jul-2028). EEFF Venta de energia incluye canales de capacidad (Nota 20). | Q39: Suma mecánica del bloque.
A41: E. O&M Y COSTOS OPERATIVOS ($)
A42: Compras de energía y costos asociados (firming spot, hidrología) | B42: =EEFF!B8 -> 4427043 | C42: =EEFF!C8 -> 8559953 | D42: =EEFF!D8 -> 12013335 | E42: =EEFF!E8 -> 9960198 | F42: =EEFF!F8 -> 4986124 | G42: =G102 -> 5053166.2 | H42: =H102 -> 9162668.8 | I42: =I102 -> 4444195.7 | J42: =J102 -> 4444195.7 | K42: =K102 -> 4444195.7 | M42: MWh | N42: F4 fila 102: $/MWh firming (mediana FY22-24 auditada A6g, HCAISAN 84-91% de compras) x MWh comprometido El Alto (fila 83). | Q42: Derivación mecánica por fórmula viva.
A43: TOTAL COSTO DE ENERGÍA (COGS) | B43: =B42 -> 4427043 | C43: =C42 -> 8559953 | D43: =D42 -> 12013335 | E43: =E42 -> 9960198 | F43: =F42 -> 4986124 | G43: =G42 -> 5053166.2 | H43: =H42 -> 9162668.8 | I43: =I42 -> 4444195.7 | ... K43: =K42 -> 4444195.7 | M43: MWh | N43: a working file kept by the maintainer | Q43: Suma mecánica del bloque.
A44: Honorarios administración (RP InterEnergy) | B44: 959176 | C44: 1278900 | D44: 1278900 | E44: 1278900 | F44: 1278900 | G44: 1278900 | H44: 1278900 | I44: 1278900 | J44: 1278900 | K44: 1278900 | M44: moneda del modelo | N44: a working file kept by the maintainer | Q44: Input de escenario desde fuente citada o NOT_DISCLOSED.
A45: Resto G&A (= G&A total F4 auditado A6g − honorarios) | B45: =EEFF!B14-B44 -> 3629203 | C45: =EEFF!C14-C44 -> 4054029 | D45: =EEFF!D14-D44 -> 4275429 | E45: =EEFF!E14-E44 -> 4232451 | F45: =EEFF!F14-F44 -> 4405777 | G45: =G116-G44 -> 4232451 | H45: =H116-H44 -> 4232451 | I45: =I116-I44 -> 4232451 | J45: =J116-J44 -> 4232451 | K45: =K116-K44 -> 4232451 | M45: moneda del modelo | N45: F4 fila 116 (G&A total auditado A6g FY24, por subsidiaria) - fila 44 honorarios. Fila 46 = 44+45 = 5,511,351 = G&A emisor FY24. | Q45: Derivación mecánica por fórmula viva.
A46: TOTAL GASTOS ADMIN (G&A) | B46: =B44+B45 -> 4588379 | C46: =C44+C45 -> 5332929 | D46: =D44+D45 -> 5554329 | E46: =E44+E45 -> 5511351 | F46: =F44+F45 -> 5684677 | G46: =G44+G45 -> 5511351 | H46: =H44+H45 -> 5511351 | I46: =I44+I45 -> 5511351 | ... K46: =K44+K45 -> 5511351 | M46: moneda del modelo | N46: a working file kept by the maintainer | Q46: Suma mecánica del bloque.
A48: F. PROFORMA POR PLANTA — DRIVERS DE VOLUMEN, PRECIO Y COSTO (FY26E-FY30E)
A49: Bloque de drivers granulares — CABLEADO al forecast (fix pass 2026-07-12): filas 22/25/32/33/39/42/45 (G-K) consumen F1-F4. Filas 1-46 en posicion: MF referencia 39/43/46 y el trace PxQ 37/38/39 se preserva. O&M total (fila 108) = memo NO cableado: ModeloFinanciero!13 lleva O&M flat FY25A; cablearlo via fila 46 duplicaria O&M.
A50: F1. Volumen por planta (CF ENSO x MW x 8.760 h; Bear=FY23 seco / Base=mediana FY21-25 / Bull=FY22 humedo)
A51: Pedregalito 1 (GENPED) — CF Bear (FY23 seco) | G51: 0.358 | H51: 0.358 | I51: 0.358 | J51: 0.358 | K51: 0.358 | M51: % | N51: Generation_PPA!A2 (CND generacion_YYYY.xlsx, CF por planta FY21-25) + sector research note (Bear=FY23 seco, Bull=FY22 humedo, Base=mediana) | Q51: Input de escenario desde fuente citada o NOT_DISCLOSED.
A52: Pedregalito 1 (GENPED) — CF Base (mediana FY21-25) | G52: 0.426 | H52: 0.426 | I52: 0.426 | J52: 0.426 | K52: 0.426 | M52: % | N52: Generation_PPA!A2 (CND generacion_YYYY.xlsx, CF por planta FY21-25) + sector research note (Bear=FY23 seco, Bull=FY22 humedo, Base=mediana) | Q52: Input de escenario desde fuente citada o NOT_DISCLOSED.
A53: Pedregalito 1 (GENPED) — CF Bull (FY22 humedo) | G53: 0.535 | H53: 0.535 | I53: 0.535 | J53: 0.535 | K53: 0.535 | M53: % | N53: Generation_PPA!A2 (CND generacion_YYYY.xlsx, CF por planta FY21-25) + sector research note (Bear=FY23 seco, Bull=FY22 humedo, Base=mediana) | Q53: Input de escenario desde fuente citada o NOT_DISCLOSED.
A54: Pedregalito 1 (GENPED) — CF activo (escenario) | G54: =CHOOSE($C$5,G52,G53,G51) -> 0.426 | H54: =CHOOSE($C$5,H52,H53,H51) -> 0.426 | I54: =CHOOSE($C$5,I52,I53,I51) -> 0.426 | J54: =CHOOSE($C$5,J52,J53,J51) -> 0.426 | K54: =CHOOSE($C$5,K52,K53,K51) -> 0.426 | M54: % | N54: NOT_DISCLOSED | Q54: Selector de caso activo C5: Base/Bull/Bear.
A55: Pedregalito 1 (GENPED) — Generacion (MWh) = 20.089 MW x 8.760 x CF | G55: =20.089*8760*G54 -> 74967.327 | H55: =20.089*8760*H54 -> 74967.327 | I55: =20.089*8760*I54 -> 74967.327 | J55: =20.089*8760*J54 -> 74967.327 | K55: =20.089*8760*K54 -> 74967.327 | M55: MWh | N55: Generation_PPA!A2 (CND generacion_YYYY.xlsx, CF por planta FY21-25) + sector research note (Bear=FY23 seco, Bull=FY22 humedo, Base=mediana) | Q55: Derivación mecánica por fórmula viva.
A56: Pedregalito 2 (RCHICO) — CF Bear (FY23 seco) | G56: 0.363 | H56: 0.363 | I56: 0.363 | J56: 0.363 | K56: 0.363 | M56: % | N56: Generation_PPA!A2 (CND generacion_YYYY.xlsx, CF por planta FY21-25) + sector research note (Bear=FY23 seco, Bull=FY22 humedo, Base=mediana) | Q56: Input de escenario desde fuente citada o NOT_DISCLOSED.
A57: Pedregalito 2 (RCHICO) — CF Base (mediana FY21-25) | G57: 0.438 | H57: 0.438 | I57: 0.438 | J57: 0.438 | K57: 0.438 | M57: % | N57: Generation_PPA!A2 (CND generacion_YYYY.xlsx, CF por planta FY21-25) + sector research note (Bear=FY23 seco, Bull=FY22 humedo, Base=mediana) | Q57: Input de escenario desde fuente citada o NOT_DISCLOSED.
A58: Pedregalito 2 (RCHICO) — CF Bull (FY22 humedo) | G58: 0.546 | H58: 0.546 | I58: 0.546 | J58: 0.546 | K58: 0.546 | M58: % | N58: Generation_PPA!A2 (CND generacion_YYYY.xlsx, CF por planta FY21-25) + sector research note (Bear=FY23 seco, Bull=FY22 humedo, Base=mediana) | Q58: Input de escenario desde fuente citada o NOT_DISCLOSED.
A59: Pedregalito 2 (RCHICO) — CF activo (escenario) | G59: =CHOOSE($C$5,G57,G58,G56) -> 0.438 | H59: =CHOOSE($C$5,H57,H58,H56) -> 0.438 | I59: =CHOOSE($C$5,I57,I58,I56) -> 0.438 | J59: =CHOOSE($C$5,J57,J58,J56) -> 0.438 | K59: =CHOOSE($C$5,K57,K58,K56) -> 0.438 | M59: % | N59: NOT_DISCLOSED | Q59: Selector de caso activo C5: Base/Bull/Bear.
A60: Pedregalito 2 (RCHICO) — Generacion (MWh) = 12.52 MW x 8.760 x CF | G60: =12.52*8760*G59 -> 48037.738 | H60: =12.52*8760*H59 -> 48037.738 | I60: =12.52*8760*I59 -> 48037.738 | J60: =12.52*8760*J59 -> 48037.738 | K60: =12.52*8760*K59 -> 48037.738 | M60: MWh | N60: Generation_PPA!A2 (CND generacion_YYYY.xlsx, CF por planta FY21-25) + sector research note (Bear=FY23 seco, Bull=FY22 humedo, Base=mediana) | Q60: Derivación mecánica por fórmula viva.
A61: Cochea (ALTOVALLE) — CF Bear (FY23 seco) | G61: 0.399 | H61: 0.399 | I61: 0.399 | J61: 0.399 | K61: 0.399 | M61: % | N61: Generation_PPA!A2 (CND generacion_YYYY.xlsx, CF por planta FY21-25) + sector research note (Bear=FY23 seco, Bull=FY22 humedo, Base=mediana) | Q61: Input de escenario desde fuente citada o NOT_DISCLOSED.
A62: Cochea (ALTOVALLE) — CF Base (mediana FY21-25) | G62: 0.472 | H62: 0.472 | I62: 0.472 | J62: 0.472 | K62: 0.472 | M62: % | N62: Generation_PPA!A2 (CND generacion_YYYY.xlsx, CF por planta FY21-25) + sector research note (Bear=FY23 seco, Bull=FY22 humedo, Base=mediana) | Q62: Input de escenario desde fuente citada o NOT_DISCLOSED.
A63: Cochea (ALTOVALLE) — CF Bull (FY22 humedo) | G63: 0.575 | H63: 0.575 | I63: 0.575 | J63: 0.575 | K63: 0.575 | M63: % | N63: Generation_PPA!A2 (CND generacion_YYYY.xlsx, CF por planta FY21-25) + sector research note (Bear=FY23 seco, Bull=FY22 humedo, Base=mediana) | Q63: Input de escenario desde fuente citada o NOT_DISCLOSED.
A64: Cochea (ALTOVALLE) — CF activo (escenario) | G64: =CHOOSE($C$5,G62,G63,G61) -> 0.472 | H64: =CHOOSE($C$5,H62,H63,H61) -> 0.472 | I64: =CHOOSE($C$5,I62,I63,I61) -> 0.472 | J64: =CHOOSE($C$5,J62,J63,J61) -> 0.472 | K64: =CHOOSE($C$5,K62,K63,K61) -> 0.472 | M64: % | N64: NOT_DISCLOSED | Q64: Selector de caso activo C5: Base/Bull/Bear.
A65: Cochea (ALTOVALLE) — Generacion (MWh) = 15.5 MW x 8.760 x CF | G65: =15.5*8760*G64 -> 64088.16 | H65: =15.5*8760*H64 -> 64088.16 | I65: =15.5*8760*I64 -> 64088.16 | J65: =15.5*8760*J64 -> 64088.16 | K65: =15.5*8760*K64 -> 64088.16 | M65: MWh | N65: Generation_PPA!A2 (CND generacion_YYYY.xlsx, CF por planta FY21-25) + sector research note (Bear=FY23 seco, Bull=FY22 humedo, Base=mediana) | Q65: Derivación mecánica por fórmula viva.
A66: El Alto + Mini (HCAISAN) — CF Bear (FY23 seco) | G66: 0.35 | H66: 0.35 | I66: 0.35 | J66: 0.35 | K66: 0.35 | M66: % | N66: Generation_PPA!A2 (CND generacion_YYYY.xlsx, CF por planta FY21-25) + sector research note (Bear=FY23 seco, Bull=FY22 humedo, Base=mediana) | Q66: Input de escenario desde fuente citada o NOT_DISCLOSED.
A67: El Alto + Mini (HCAISAN) — CF Base (mediana FY21-25) | G67: 0.425 | H67: 0.425 | I67: 0.425 | J67: 0.425 | K67: 0.425 | M67: % | N67: Generation_PPA!A2 (CND generacion_YYYY.xlsx, CF por planta FY21-25) + sector research note (Bear=FY23 seco, Bull=FY22 humedo, Base=mediana) | Q67: Input de escenario desde fuente citada o NOT_DISCLOSED.
A68: El Alto + Mini (HCAISAN) — CF Bull (FY22 humedo) | G68: 0.516 | H68: 0.516 | I68: 0.516 | J68: 0.516 | K68: 0.516 | M68: % | N68: Generation_PPA!A2 (CND generacion_YYYY.xlsx, CF por planta FY21-25) + sector research note (Bear=FY23 seco, Bull=FY22 humedo, Base=mediana) | Q68: Input de escenario desde fuente citada o NOT_DISCLOSED.
A69: El Alto + Mini (HCAISAN) — CF activo (escenario) | G69: =CHOOSE($C$5,G67,G68,G66) -> 0.425 | H69: =CHOOSE($C$5,H67,H68,H66) -> 0.425 | I69: =CHOOSE($C$5,I67,I68,I66) -> 0.425 | J69: =CHOOSE($C$5,J67,J68,J66) -> 0.425 | K69: =CHOOSE($C$5,K67,K68,K66) -> 0.425 | M69: % | N69: NOT_DISCLOSED | Q69: Selector de caso activo C5: Base/Bull/Bear.
A70: El Alto + Mini (HCAISAN) — Generacion (MWh) = 73.18 MW x 8.760 x CF | G70: =73.18*8760*G69 -> 272449.14 | H70: =73.18*8760*H69 -> 272449.14 | I70: =73.18*8760*I69 -> 272449.14 | J70: =73.18*8760*J69 -> 272449.14 | K70: =73.18*8760*K69 -> 272449.14 | M70: MWh | N70: Generation_PPA!A2 (CND generacion_YYYY.xlsx, CF por planta FY21-25) + sector research note (Bear=FY23 seco, Bull=FY22 humedo, Base=mediana) | Q70: Derivación mecánica por fórmula viva.
A71: Pedregalito Solar — CF Bear (FY23 seco) | G71: 0.197 | H71: 0.197 | I71: 0.197 | J71: 0.197 | K71: 0.197 | M71: % | N71: Generation_PPA!A2 (CND generacion_YYYY.xlsx, CF por planta FY21-25) + sector research note (Bear=FY23 seco, Bull=FY22 humedo, Base=mediana) | Q71: Input de escenario desde fuente citada o NOT_DISCLOSED.
A72: Pedregalito Solar — CF Base (mediana FY21-25) (irradiancia; FY23/24 pre-COD excluidos, solo FY25 limpio; sin spread ENSO) | G72: 0.197 | H72: 0.197 | I72: 0.197 | J72: 0.197 | K72: 0.197 | M72: % | N72: Generation_PPA!A2 (CND generacion_YYYY.xlsx, CF por planta FY21-25) + sector research note (Bear=FY23 seco, Bull=FY22 humedo, Base=mediana) | Q72: Input de escenario desde fuente citada o NOT_DISCLOSED.
A73: Pedregalito Solar — CF Bull (FY22 humedo) | G73: 0.197 | H73: 0.197 | I73: 0.197 | J73: 0.197 | K73: 0.197 | M73: % | N73: Generation_PPA!A2 (CND generacion_YYYY.xlsx, CF por planta FY21-25) + sector research note (Bear=FY23 seco, Bull=FY22 humedo, Base=mediana) | Q73: Input de escenario desde fuente citada o NOT_DISCLOSED.
A74: Pedregalito Solar — CF activo (escenario) | G74: =CHOOSE($C$5,G72,G73,G71) -> 0.197 | H74: =CHOOSE($C$5,H72,H73,H71) -> 0.197 | I74: =CHOOSE($C$5,I72,I73,I71) -> 0.197 | J74: =CHOOSE($C$5,J72,J73,J71) -> 0.197 | K74: =CHOOSE($C$5,K72,K73,K71) -> 0.197 | M74: % | N74: NOT_DISCLOSED | Q74: Selector de caso activo C5: Base/Bull/Bear.
A75: Pedregalito Solar — Generacion (MWh) = 9.9 MW x 8.760 x CF | G75: =9.9*8760*G74 -> 17084.628 | H75: =9.9*8760*H74 -> 17084.628 | I75: =9.9*8760*I74 -> 17084.628 | J75: =9.9*8760*J74 -> 17084.628 | K75: =9.9*8760*K74 -> 17084.628 | M75: MWh | N75: Generation_PPA!A2 (CND generacion_YYYY.xlsx, CF por planta FY21-25) + sector research note (Bear=FY23 seco, Bull=FY22 humedo, Base=mediana) | Q75: Derivación mecánica por fórmula viva.
A76: Generacion total proforma (MWh) | G76: =G55+G60+G65+G70+G75 -> 476626.99 | H76: =H55+H60+H65+H70+H75 -> 476626.99 | I76: =I55+I60+I65+I70+I75 -> 476626.99 | J76: =J55+J60+J65+J70+J75 -> 476626.99 | K76: =K55+K60+K65+K70+K75 -> 476626.99 | M76: MWh | N76: NOT_DISCLOSED | Q76: Suma mecánica del bloque.
A78: F2. El Alto (HCAISAN) — cliff PPA: capacidad + energia (adjudicacion GC-02-2026); VALLE de capacidad explicito FY27
A79: El Alto — Capacidad contratada activa (MW): FY26 ENSA half -> valle -> award 4.4 MW | G79: 11.0705 | H79: 0 | I79: 4.4 | J79: 4.4 | K79: 4.4 | M79: MW | N79: Generation_PPA!A3b Group 2 (adjudicacion verificada GC-02-2026/LPI 01-26) + maintainer research note | Q79: Derivación mecánica declarada por el plan.
A80: El Alto — Precio potencia ($/kW-mes): $31.62 DCD viejo -> $3.24 award | G80: 31.62 | H80: 0 | I80: 3.24 | J80: 3.24 | K80: 3.24 | M80: moneda del modelo | N80: Generation_PPA!A3b Group 2 (adjudicacion verificada GC-02-2026/LPI 01-26) + maintainer research note | Q80: Derivación mecánica declarada por el plan.
A81: El Alto — Meses de capacidad activos (award inicia 1-jul-2028 = 6m en FY28) | G81: 12 | H81: 0 | I81: 6 | J81: 12 | K81: 12 | M81: moneda del modelo | N81: Generation_PPA!A3b Group 2 (adjudicacion verificada GC-02-2026/LPI 01-26) + maintainer research note | Q81: Derivación mecánica declarada por el plan.
A82: El Alto — Ingreso capacidad (potencia) $ = MW x 1000 x $/kW-mes x meses [VALLE FY27] | G82: =G79*1000*G80*G81 -> 4200590.5 | H82: =H79*1000*H80*H81 -> 0 | I82: =I79*1000*I80*I81 -> 85536 | J82: =J79*1000*J80*J81 -> 171072 | K82: =K79*1000*K80*K81 -> 171072 | M82: MW | N82: NOT_DISCLOSED | Q82: Derivación mecánica por fórmula viva.
A83: El Alto — Energia contratada award (SED+SEO, MWh/ano activo) | G83: 97608 | H83: 176988 | I83: 85845 | J83: 85845 | K83: 85845 | M83: MWh | N83: Generation_PPA!A3b Group 2 (adjudicacion verificada GC-02-2026/LPI 01-26) + maintainer research note | Q83: Derivación mecánica declarada por el plan.
A84: El Alto — Precio energia contratada ($/MWh, blended SED $47.3 / SEO $36.1) | G84: 42.375 | H84: 41.862 | I84: 36.1 | J84: 36.1 | K84: 36.1 | M84: MWh | N84: Generation_PPA!A3b Group 2 (adjudicacion verificada GC-02-2026/LPI 01-26) + maintainer research note | Q84: Derivación mecánica declarada por el plan.
A85: El Alto — Ingreso energia contratada $ = MWh x $/MWh | G85: =G83*G84 -> 4136139 | H85: =H83*H84 -> 7409071.7 | I85: =I83*I84 -> 3099004.5 | J85: =J83*J84 -> 3099004.5 | K85: =K83*K84 -> 3099004.5 | M85: MWh | N85: NOT_DISCLOSED | Q85: Derivación mecánica por fórmula viva.
A86: El Alto — MWh merchant (residual) = Generacion - contratada | G86: =MAX(0,G70-G83) -> 174841.14 | H86: =MAX(0,H70-H83) -> 95461.14 | I86: =MAX(0,I70-I83) -> 186604.14 | J86: =MAX(0,J70-J83) -> 186604.14 | K86: =MAX(0,K70-K83) -> 186604.14 | M86: MWh | N86: Supuestos!26 Spot/merchant activo (Task 3, CND) — driver merchant post-expiry | Q86: Derivación mecánica por fórmula viva.
A87: El Alto — Ingreso merchant $ = MWh merchant x spot (fila 26) | G87: =G86*G26 -> 10490468 | H87: =H86*H26 -> 5536746.1 | I87: =I86*I26 -> 10636436 | J87: =J86*J26 -> 10449832 | K87: =K86*K26 -> 10263228 | M87: MWh | N87: Supuestos!26 Spot/merchant activo (Task 3, CND) — driver merchant post-expiry | Q87: Derivación mecánica por fórmula viva.
A88: El Alto — Ingreso total $ (capacidad + energia + merchant) | G88: =G82+G85+G87 -> 18827198 | H88: =H82+H85+H87 -> 12945818 | I88: =I82+I85+I87 -> 13820976 | J88: =J82+J85+J87 -> 13719908 | K88: =K82+K85+K87 -> 13533304 | M88: MWh | N88: NOT_DISCLOSED | Q88: Suma mecánica del bloque.
A90: F3. Plantas PPA (Pedregalito 1/2, Cochea): precio contratado hasta expiry -> merchant(spot); Solar 100% merchant (sin PPA propio)
A91: Pedregalito 1 (GENPED) — Precio ($/MWh): PPA blended hasta expiry, luego merchant(spot) | G91: 103.541 | H91: 103.541 | I91: 103.541 | J91: 103.541 | K91: =K26 -> 55 | M91: MWh | N91: Generation_PPA!A4a (blended PPA $/MWh, MW-weighted) + sector research note; post-expiry: Supuestos!26 Spot/merchant activo (Task 3, CND) — driver merchant post-expiry | Q91: Derivación mecánica por fórmula viva.
A92: Pedregalito 1 (GENPED) — Ingreso energia $ = Generacion x precio | G92: =G55*G91 -> 7762192 | H92: =H55*H91 -> 7762192 | I92: =I55*I91 -> 7762192 | J92: =J55*J91 -> 7762192 | K92: =K55*K91 -> 4123203 | M92: MWh | N92: NOT_DISCLOSED | Q92: Derivación mecánica por fórmula viva.
A93: Pedregalito 2 (RCHICO) — Precio ($/MWh): PPA blended hasta expiry, luego merchant(spot) | G93: 104.779 | H93: 104.779 | I93: 104.779 | J93: 104.779 | K93: =K26 -> 55 | M93: MWh | N93: Generation_PPA!A4a (blended PPA $/MWh, MW-weighted) + sector research note; post-expiry: Supuestos!26 Spot/merchant activo (Task 3, CND) — driver merchant post-expiry | Q93: Derivación mecánica por fórmula viva.
A94: Pedregalito 2 (RCHICO) — Ingreso energia $ = Generacion x precio | G94: =G60*G93 -> 5033346.1 | H94: =H60*H93 -> 5033346.1 | I94: =I60*I93 -> 5033346.1 | J94: =J60*J93 -> 5033346.1 | K94: =K60*K93 -> 2642075.6 | M94: MWh | N94: NOT_DISCLOSED | Q94: Derivación mecánica por fórmula viva.
A95: Cochea (ALTOVALLE) — Precio ($/MWh): PPA blended hasta expiry, luego merchant(spot) | G95: 91.649 | H95: 91.649 | I95: 91.649 | J95: 91.649 | K95: =0.5*91.649+0.5*K26 -> 73.3245 | M95: MWh | N95: Generation_PPA!A4a (blended PPA $/MWh, MW-weighted) + sector research note; post-expiry: Supuestos!26 Spot/merchant activo (Task 3, CND) — driver merchant post-expiry | Q95: Derivación mecánica por fórmula viva.
A96: Cochea (ALTOVALLE) — Ingreso energia $ = Generacion x precio | G96: =G65*G95 -> 5873615.8 | H96: =H65*H95 -> 5873615.8 | I96: =I65*I95 -> 5873615.8 | J96: =J65*J95 -> 5873615.8 | K96: =K65*K95 -> 4699232.3 | M96: MWh | N96: NOT_DISCLOSED | Q96: Derivación mecánica por fórmula viva.
A97: Pedregalito Solar — Ingreso energia $ = Generacion x spot (fila 26; sin PPA propio, NOT_DISCLOSED contrato) | G97: =G75*G26 -> 1025077.7 | H97: =H75*H26 -> 990908.42 | I97: =I75*I26 -> 973823.8 | J97: =J75*J26 -> 956739.17 | K97: =K75*K26 -> 939654.54 | M97: MWh | N97: NOT_DISCLOSED | Q97: Derivación mecánica por fórmula viva.
A98: Ingreso energia total proforma $ (5 plantas: El Alto + 3 PPA + Solar) | G98: =G88+G92+G94+G96+G97 -> 38521429 | H98: =H88+H92+H94+H96+H97 -> 32605880 | I98: =I88+I92+I94+I96+I97 -> 33463954 | J98: =J88+J92+J94+J96+J97 -> 33345801 | K98: =K88+K92+K94+K96+K97 -> 25937470 | M98: MWh | N98: NOT_DISCLOSED | Q98: Suma mecánica del bloque.
A100: F4. Costos — compras firming ($/MWh sobre volumen comprometido HCAISAN, A6g) + O&M y G&A por planta (auditado A6g FY24, held flat)
A101: Compras — $/MWh sobre volumen comprometido HCAISAN (mediana FY22-24 auditada, A6g) | G101: 51.77 | H101: 51.77 | I101: 51.77 | J101: 51.77 | K101: 51.77 | M101: MWh | N101: Generation_PPA!A6g (compras HCAISAN auditada FY22-24) + row397 (HCAISAN=84-91% de compras totales) | Q101: Derivación mecánica declarada por el plan.
A102: Compras de energia (firming) $ = $/MWh x MWh comprometido El Alto (fila energia award) | G102: =G101*G83 -> 5053166.2 | H102: =H101*H83 -> 9162668.8 | I102: =I101*I83 -> 4444195.7 | J102: =J101*J83 -> 4444195.7 | K102: =K101*K83 -> 4444195.7 | M102: MWh | N102: NOT_DISCLOSED | Q102: Derivación mecánica por fórmula viva.
A103: O&M — Cochea (ALTOVALLE) (A6g FY24 auditado, held flat) | G103: 535798 | H103: 535798 | I103: 535798 | J103: 535798 | K103: 535798 | M103: moneda del modelo | N103: Generation_PPA!A6g (Consolidacion IS por subsidiaria, auditada FY24; suma amarra a Nota 22/21 emisor) | Q103: Derivación mecánica declarada por el plan.
A104: O&M — Pedregalito Solar (A6g FY24 auditado, held flat) | G104: 18268 | H104: 18268 | I104: 18268 | J104: 18268 | K104: 18268 | M104: moneda del modelo | N104: Generation_PPA!A6g (Consolidacion IS por subsidiaria, auditada FY24; suma amarra a Nota 22/21 emisor) | Q104: Derivación mecánica declarada por el plan.
A105: O&M — El Alto (HCAISAN) (A6g FY24 auditado, held flat) | G105: 1054490 | H105: 1054490 | I105: 1054490 | J105: 1054490 | K105: 1054490 | M105: moneda del modelo | N105: Generation_PPA!A6g (Consolidacion IS por subsidiaria, auditada FY24; suma amarra a Nota 22/21 emisor) | Q105: Derivación mecánica declarada por el plan.
A106: O&M — Pedregalito 1 (GENPED) (A6g FY24 auditado, held flat) | G106: 721775 | H106: 721775 | I106: 721775 | J106: 721775 | K106: 721775 | M106: moneda del modelo | N106: Generation_PPA!A6g (Consolidacion IS por subsidiaria, auditada FY24; suma amarra a Nota 22/21 emisor) | Q106: Derivación mecánica declarada por el plan.
A107: O&M — Pedregalito 2 (RCHICO) (A6g FY24 auditado, held flat) | G107: 219181 | H107: 219181 | I107: 219181 | J107: 219181 | K107: 219181 | M107: moneda del modelo | N107: Generation_PPA!A6g (Consolidacion IS por subsidiaria, auditada FY24; suma amarra a Nota 22/21 emisor) | Q107: Derivación mecánica declarada por el plan.
A108: O&M total proforma $ (amarra a Nota 22 emisor FY24 = 2,549,512) | G108: =G103+G104+G105+G106+G107 -> 2549512 | H108: =H103+H104+H105+H106+H107 -> 2549512 | I108: =I103+I104+I105+I106+I107 -> 2549512 | J108: =J103+J104+J105+J106+J107 -> 2549512 | K108: =K103+K104+K105+K106+K107 -> 2549512 | M108: moneda del modelo | N108: | MEMO fix pass 2026-07-12: NO cableado a MF — MF!13 (Operacion y mantenimiento) va flat FY25A (3,004,212); routearlo via fila 46 (G&A -> MF!14) duplicaria O&M. Driver auditado disponible para Task 8+ si se recablea MF!13. | Q108: Suma mecánica del bloque.
A109: G&A — PPH holdco (A6g FY24 auditado, held flat) | G109: 1625984 | H109: 1625984 | I109: 1625984 | J109: 1625984 | K109: 1625984 | M109: moneda del modelo | N109: Generation_PPA!A6g (Consolidacion IS por subsidiaria, auditada FY24; suma amarra a Nota 22/21 emisor) | Q109: Derivación mecánica declarada por el plan.
A110: G&A — Cochea (ALTOVALLE) (A6g FY24 auditado, held flat) | G110: 652232 | H110: 652232 | I110: 652232 | J110: 652232 | K110: 652232 | M110: moneda del modelo | N110: Generation_PPA!A6g (Consolidacion IS por subsidiaria, auditada FY24; suma amarra a Nota 22/21 emisor) | Q110: Derivación mecánica declarada por el plan.
A111: G&A — Pedregalito Solar (A6g FY24 auditado, held flat) | G111: 55704 | H111: 55704 | I111: 55704 | J111: 55704 | K111: 55704 | M111: moneda del modelo | N111: Generation_PPA!A6g (Consolidacion IS por subsidiaria, auditada FY24; suma amarra a Nota 22/21 emisor) | Q111: Derivación mecánica declarada por el plan.
...

Sheet Notas_EEFF
A1: Panama Power Holdings, Inc. y Subsidiarias
A2: Notas a los Estados Financieros
A3: Fuente: informes auditados vía OCR Mistral (verbatim).
A5: Año | B5: Documento fuente | C5: Página OCR | D5: Tabla OCR / sección | E5: Nota # | F5: Título original de la nota | G5: Categoría modelable | H5: Line item EEFF | I5: Sub-line item / detalle | J5: Texto original / disclosure | K5: Monto reportado | L5: Moneda | M5: Unidad / escala | N5: Fecha / venc. / tasa / plazo | O5: Contraparte / contrato / instrumento | P5: Impacto en Supuestos | Q5: Impacto en ModeloFinanciero | R5: Link a celda EEFF | S5: Comentario de extracción | T5: Status
A6: 2022 | B6: INA_PPHO_2022_0.pdf | C6: page-44 | D6: markdown.md | E6: 1 | F6: 1. Información General | G6: Otros | J6: Panama Power Holdings, Inc. (la "Compañía" o "PPH") fue constituida el 4 de abril de 2007 mediante Escritura Pública No.8298 de acuerdo con las leyes de la República de Panamá y continuada según Ley de Sociedades Mercantiles de las Islas Vírgenes Británicas el 3 de marzo de 2011 bajo el No.1575385, según consta en Escritura Pública No.6,697 del 19 de marzo de 2010. | T6: OK
A7: 2022 | B7: INA_PPHO_2022_0.pdf | C7: page-44 | D7: markdown.md | E7: 1 | F7: 1. Información General | G7: Otros | J7: La principal actividad de la Compañía y sus subsidiarias (en adelante el "Grupo") es llevar a cabo el negocio de generación de energía eléctrica, ya sea en forma directa o indirecta mediante la inversión o participación en sociedades que se dediquen a este giro de negocio. Todas las subsidiarias del Grupo se encuentran incorporadas en la República de Panamá. | T7: OK
A8: 2022 | B8: INA_PPHO_2022_0.pdf | C8: page-44 | D8: markdown.md | E8: 1 | F8: 1. Información General | G8: Otros | J8: La oficina principal del Grupo se encuentra ubicada en Paseo Roberto Motta, Costa del Este, Capital Plaza, Piso 12 en la Ciudad de Panamá, República de Panamá. | T8: OK
A9: 2022 | B9: INA_PPHO_2022_0.pdf | C9: page-44 | D9: markdown.md | E9: 1 | F9: 1. Información General | G9: Otros | J9: La siguiente tabla muestra las subsidiarias del Grupo, la fecha de adquisición y el porcentaje de participación: | T9: OK
A10: 2022 | B10: INA_PPHO_2022_0.pdf | C10: page-44 | D10: markdown.md | E10: 1 | F10: 1. Información General | G10: Otros | J10: | Compañías Subsidiarias | Porcentaje de Participación | Fecha de Adquisición | | --- | --- | --- | | Generadora Alto Valle, S. A. | 100% | 27/12/2007 | | Generadora Pedregalito, S. A. | 100% | 28/12/2007 | | Generadora Río Chico, S. A. | 100% | 28/12/2007 | | Hydro Caisán, S. A. | 100% | 30/06/2010 | | Panama Power Management Services, S. A. | 100% | 02/03/2012 | | Pedregalito Solar Power, S. A. | 100% | 07/07/2014 | | Río Chico Solar Power, S. A. | 100% | 07/07/2014 | | PPH Financing Services, S. A. | 100% | 17/03/2016 | | T10: OK
A11: 2022 | B11: INA_PPHO_2022_0.pdf | C11: page-44 | D11: markdown.md | E11: 1 | F11: 1. Información General | G11: Otros | J11: Las subsidiarias Generadora Pedregalito, S. A. (central "Pedregalito 1") y Generadora Río Chico, S. A. (central "Pedregalito 2") iniciaron la generación de energía en abril y octubre de 2011, respectivamente, la subsidiaria Generadora Alto Valle, S. A. (central "Cochea") inició la generación de energía en octubre de 2012 y la subsidiaria Hydro Caisán, S. A. (central "El Alto") en agosto de 2014. La principal actividad de las otras subsidiarias es brindar soporte a las operaciones del Grupo Panama Power Holdings, Inc. | T11: OK
A12: 2022 | B12: INA_PPHO_2022_0.pdf | C12: page-44 | D12: markdown.md | E12: 1 | F12: 1. Información General | G12: Otros | J12: Mediante Escritura Pública No. 2,797 del 28 de julio de 2021, inscrita en el Registro Público de Panamá el 25 de agosto de 2021, se protocolizó Acta de la Asamblea de Accionistas de la sociedad Generadora Río Piedra, S. A., para autorizar la disolución de la sociedad. | T12: OK
A13: 2022 | B13: INA_PPHO_2022_0.pdf | C13: page-44 | D13: markdown.md | E13: 1 | F13: 1. Información General | G13: Otros | J13: Mediante Escritura Pública No.2,798 del 28 de julio de 2021, inscrita en el Registro Público de Panamá el 16 de agosto de 2021, se protocolizó Acta de la Asamblea de Accionistas de la sociedad Multi Magnetic, Inc., para autorizar la disolución de la sociedad. | T13: OK
A14: 2022 | B14: INA_PPHO_2022_0.pdf | C14: page-45 | D14: markdown.md | E14: 1 | F14: 1. Información General (Continuación) | G14: Otros | J14: Mediante Escritura Pública No.2,799 del 28 de julio de 2021, inscrita en el Registro Público de Panamá el 16 de agosto de 2021, se protocolizó Acta de la Asamblea de Accionistas de la sociedad Caldera Power, Inc., para autorizar la disolución de la sociedad. | T14: OK
A15: 2022 | B15: INA_PPHO_2022_0.pdf | C15: page-45 | D15: markdown.md | E15: 1 | F15: 1. Información General (Continuación) | G15: Otros | J15: Mediante Escritura Pública No. 3465 de 8 de septiembre de 2021 se protocolizó el acuerdo de fusión entre las subsidiarias Hydro Caisán, S. A. y G.R.K. Energy Corp., mediante el cual Hydro Caisán, S. A. se mantiene como la entidad absorbente. Esta fusión se da para consolidar las sociedades que forman parte de un mismo proyecto. Derivado de esta fusión, las partes acordaron convertir la totalidad de las acciones de G.R.K. Energy Corp. en 100 acciones comunes sin valor nominal de Hydro Caisán, S. A., emitidas al accionista de la subsidiaria. La fusión por absorción no representó flujo de efectivo y se realizó a su valor en libros. | T15: OK
A16: 2022 | B16: INA_PPHO_2022_0.pdf | C16: page-45 | D16: markdown.md | E16: 1 | F16: 1. Información General (Continuación) | G16: Otros | J16: Mediante Escritura Pública No. 3464 de 8 de septiembre de 2021 se protocolizó el acuerdo de fusión entre las subsidiarias Hydro Caisán, S. A. y Goodsea Inc., mediante el cual Hydro Caisán, S. A. se mantiene como la entidad absorbente. Esta fusión se da para consolidar las sociedades que forman parte de un mismo proyecto. Derivado de esta fusión, las partes acordaron convertir la totalidad de las acciones de Goodsea, Inc. en 100 acciones comunes sin valor nominal de Hydro Caisán, S. A., emitidas al accionista de la subsidiaria. La fusión por absorción no representó flujo de efectivo y se realizó a su valor en libros. | T16: OK
A17: 2022 | B17: INA_PPHO_2022_0.pdf | C17: page-45 | D17: markdown.md | E17: 1 | F17: 1. Información General (Continuación) | G17: Otros | J17: Los estados financieros consolidados de Panama Power Holdings, Inc. y Subsidiarias fueron aprobados para su emisión por el Presidente del Grupo el 31 de marzo de 2023. El Presidente del Grupo tiene la autoridad de modificación y remisión de los estados financieros consolidados después de aprobados. | T17: OK
... A138: 2022 | B138: INA_PPHO_2022_0.pdf | C138: page-60 | D138: markdown.md | E138: 4 | F138: 4. Administración del Riesgo de Instrumentos Financieros (Continuación) | G138: Riesgo financiero | J138: A continuación se presentan los vencimientos de los pasivos no descontados, incluyendo los intereses calculados a la fecha de vencimiento: | T138: OK
A139: 2022 | B139: INA_PPHO_2022_0.pdf | C139: page-60 | D139: markdown.md | E139: 4 | F139: 4. Administración del Riesgo de Instrumentos Financieros (Continuación) | G139: Riesgo financiero | J139: | | Menos de un Año | Entre 1 y 5 Años | Más de 5 Años | | --- | --- | --- | --- | | 2022 | | | | | Préstamo por pagar | 758,413 | - | - | | Bonos por pagar | 18,269,526 | 83,349,063 | 114,556,708 | | Cuentas por pagar | 1,675,961 | - | - | | Impuesto sobre la renta por pagar | 2,384,922 | - | - | | Otros pasivos | 1,534,472 | 218,261 | - | | 2021 | | | | | Bonos por pagar | 18,776,204 | 88,662,102 | 130,164,2479 | | Cuentas por pagar | 3,817,823 | - | - | | Impuesto sobre la renta por pagar | 1,255,449 | - | - | | Otros pasivos | 1,522,447 | 204,886 | - | | K139: 83349063 | L139: B/. | T139: OK
A140: 2022 | B140: INA_PPHO_2022_0.pdf | C140: page-60 | D140: markdown.md | E140: 4 | F140: 4. Administración del Riesgo de Instrumentos Financieros (Continuación) | G140: Riesgo financiero | J140: Durante el período 2022, el Grupo estuvo monitoreando su posición financiera y operativa por los efectos que pudiese generar el COVID-19 (ver Nota 6). | T140: OK
A141: 2022 | B141: INA_PPHO_2022_0.pdf | C141: page-60 | D141: markdown.md | E141: 4 | F141: 4. Administración del Riesgo de Instrumentos Financieros (Continuación) | G141: Riesgo financiero | J141: ### Objetivos y Políticas de Gestión de Capital | T141: OK
A142: 2022 | B142: INA_PPHO_2022_0.pdf | C142: page-60 | D142: markdown.md | E142: 4 | F142: 4. Administración del Riesgo de Instrumentos Financieros (Continuación) | G142: Riesgo financiero | J142: El objetivo del Grupo en el manejo del capital es el de salvaguardar la habilidad del Grupo para continuar como negocio en marcha, con el objetivo de proveer retornos a sus accionistas y beneficios a otros acreedores y para mantener una estructura óptima de capital que reduzca el costo de capital. | T142: OK
A143: 2022 | B143: INA_PPHO_2022_0.pdf | C143: page-60 | D143: markdown.md | E143: 4 | F143: 4. Administración del Riesgo de Instrumentos Financieros (Continuación) | G143: Riesgo financiero | J143: El Grupo monitorea su capital sobre la base de razón de apalancamiento. El apalancamiento es el resultado de dividir la deuda neta entre el total del capital. La deuda neta se calcula como el total de préstamos que se muestran en el estado consolidado de situación financiera menos el efectivo. El total del capital está determinado como el total del patrimonio, más la deuda neta. | T143: OK
A144: 2022 | B144: INA_PPHO_2022_0.pdf | C144: page-61 | D144: markdown.md | E144: 4 | F144: 4. Administración del Riesgo de Instrumentos Financieros (Continuación) | G144: Riesgo financiero | J144: **Objetivos y Políticas de Gestión de Capital (continuación)** | T144: OK
A145: 2022 | B145: INA_PPHO_2022_0.pdf | C145: page-61 | D145: markdown.md | E145: 4 | F145: 4. Administración del Riesgo de Instrumentos Financieros (Continuación) | G145: Riesgo financiero | J145: A continuación se muestra la razón de apalancamiento del Grupo: | T145: OK
A146: 2022 | B146: INA_PPHO_2022_0.pdf | C146: page-61 | D146: markdown.md | E146: 4 | F146: 4. Administración del Riesgo de Instrumentos Financieros (Continuación) | G146: Riesgo financiero | J146: | | 2022 | 2021 | | --- | --- | --- | | Total de préstamos y bonos por pagar | 159,008,413 | 167,250,000 | | Menos: Efectivo y equivalentes de efectivo | (10,955,792) | (9,167,597) | | Efectivo restringido | (4,234,822) | (4,206,485) | | Deuda neta | 143,817,799 | 153,875,918 | | Total de patrimonio | 154,381,118 | 151,992,995 | | Total de capital | 298,198,917 | 305,868,913 | | Razón de apalancamiento | 48% | 50% | | K146: 167250000 | L146: B/. | T146: OK
A147: 2022 | B147: INA_PPHO_2022_0.pdf | C147: page-61 | D147: markdown.md | E147: 4 | F147: 4. Administración del Riesgo de Instrumentos Financieros (Continuación) | G147: Riesgo financiero | J147: Para propósitos de divulgación, las Normas Internacionales de Información Financiera especifican una jerarquía del valor razonable que clasifica en tres niveles, en base a las variables utilizadas en las técnicas de valorización para medir el valor razonable: La jerarquía se basa en la transparencia de las variables que se utilizan en la valorización de un activo a la fecha de su valorización. Estos tres niveles son los siguientes: | T147: OK
A148: 2022 | B148: INA_PPHO_2022_0.pdf | C148: page-61 | D148: markdown.md | E148: 4 | F148: 4. Administración del Riesgo de Instrumentos Financieros (Continuación) | G148: Riesgo financiero | J148: - Nivel 1: Precios cotizados (no ajustados) en mercados activos para activos y pasivos idénticos a la fecha de medición. - Nivel 2: Variables distintas a los precios cotizados incluidos en el Nivel 1 que son observables para el activo o pasivo, ya sea directamente (es decir, como precios) o indirectamente (es decir, derivados de los precios). - Nivel 3: Variables no observables para el activo y pasivo. | T148: OK
A149: 2022 | B149: INA_PPHO_2022_0.pdf | C149: page-61 | D149: markdown.md | E149: 4 | F149: 4. Administración del Riesgo de Instrumentos Financieros (Continuación) | G149: Riesgo financiero | J149: El Grupo no mantiene activos y pasivos registrados a valor razonable en el estado consolidado de situación financiera. Para los instrumentos financieros que no están registrados a su valor razonable en el estado consolidado de situación financiera, su valor en libros se aproxima a su valor razonable, debido a su naturaleza de corto plazo y bajo riesgo de créditos (en los casos de activos). Estos instrumentos financieros incluyen: el efectivo en banco, cuentas por cobrar, cuentas por pagar proveedores, obligaciones financieras de corto y cuentas con compañías relacionadas. Para los instrumentos financieros a largo plazo, el valor razonable se divulga en la Nota 16. | T149: OK
A150: 2022 | B150: INA_PPHO_2022_0.pdf | C150: page-62 | D150: markdown.md | E150: 5 | F150: 5. Efectivo | G150: Working capital | J150: El desglose del efectivo se presenta a continuación: | T150: OK
A151: 2022 | B151: INA_PPHO_2022_0.pdf | C151: page-62 | D151: markdown.md | E151: 5 | F151: 5. Efectivo | G151: Working capital | J151: | | 2022 | 2021 | | --- | --- | --- | | Caja menuda | 1,104 | 1,056 | | Banco General, S. A. | 10,178,021 | 8,512,233 | | MMG Bank, S. A. | 776,667 | 654,308 | | | 10,955,792 | 9,167,597 | | K151: 1104 | L151: B/. | T151: OK
A152: 2022 | B152: INA_PPHO_2022_0.pdf | C152: page-62 | D152: markdown.md | E152: 6 | F152: 6. Cuentas por Cobrar | G152: Cuentas por cobrar | J152: Las cuentas por cobrar se detallan de la siguiente manera: | T152: OK
A153: 2022 | B153: INA_PPHO_2022_0.pdf | C153: page-62 | D153: markdown.md | E153: 6 | F153: 6. Cuentas por Cobrar | G153: Cuentas por cobrar | J153: | | 2022 | 2021 | | --- | --- | --- | | Edemet-Edechi | 5,462,185 | 5,459,155 | | Elektra Noreste, S. A. | 2,501,926 | 2,497,992 | | Otros | 2,516,409 | 2,050,049 | | | 10,480,520 | 10,007,196 | | Menos: Porción circulante | 10,480,520 | 9,794,078 | | Porción no circulante | - | 213,118 | | K153: 5462185 | L153: B/. | T153: OK
A154: 2022 | B154: INA_PPHO_2022_0.pdf | C154: page-62 | D154: markdown.md | E154: 6 | F154: 6. Cuentas por Cobrar | G154: Cuentas por cobrar | J154: # Devolución de Ajuste Tarifario | T154: OK
A155: 2022 | B155: INA_PPHO_2022_0.pdf | C155: page-62 | D155: markdown.md | E155: 6 | F155: 6. Cuentas por Cobrar | G155: Cuentas por cobrar | J155: El 27 de septiembre de 2017, la Autoridad Nacional de los Servicios Públicos, emitió la Resolución AN No. 11667 - Elec, por la cual se autoriza a la Empresa de Transmisión Eléctrica, S. A. (ETESA), para diferir la devolución tarifaria de los años 2, 3 y 4 a los Agentes del Mercado del período tarifario de julio 2013 a junio 2017, como consecuencia de la revisión de los Cargos por Uso del Sistema Principal de Transmisión (CUSPT) y del Servicio de Operación Integrada (SOI), para que se haga efectiva a partir del mes de julio de 2021, por un período de 8 años. | T155: OK
A156: 2022 | B156: INA_PPHO_2022_0.pdf | C156: page-62 | D156: markdown.md | E156: 6 | F156: 6. Cuentas por Cobrar | G156: Cuentas por cobrar | J156: La Resolución AN No. 11667 - Elec, fue modificada mediante Resolución No. AN No. 11872-Elec del 4 de diciembre de 2017, para cambiar el período de devolución de 8 a 5 años para los ajustes a CUSPT y de 8 a 2 años para los ajustes SOI. | T156: OK
A157: 2022 | B157: INA_PPHO_2022_0.pdf | C157: page-62 | D157: markdown.md | E157: 6 | F157: 6. Cuentas por Cobrar | G157: Cuentas por cobrar | J157: Mediante Resolución No. AN. 13350 - Elec del 10 de mayo de 2019, se adiciona el requerimiento de publicación del ajuste final del año tarifario 4 (período tarifario de julio 2013 a junio 2017), y se ordena a ETESA establecer y notificar el Plan de Devolución mensual para cada Agente del Mercado confirmando los montos y los intereses sobre saldo hasta completar la devolución. En noviembre de 2021, las subsidiarias Generadora Alto Valle, S. A., Generadora Río Chico, S. A., Hydro Caisán, S. A., Generadora Alto Valle, S. A. y ETESA, suscribieron un Acuerdo para el pago anticipado de la devolución tarifaria correspondiente a los años 2, 3 y 4 del período tarifario 2013-2017, el cual establece la programación de dicho pago. | T157: OK
A158: 2022 | B158: INA_PPHO_2022_0.pdf | C158: page-63 | D158: markdown.md | E158: 6 | F158: 6. Cuentas por Cobrar (Continuación) | G158: Cuentas por cobrar | J158: Devolución de Ajuste Tarifario (continuación) | T158: OK
A159: 2022 | B159: INA_PPHO_2022_0.pdf | C159: page-63 | D159: markdown.md | E159: 6 | F159: 6. Cuentas por Cobrar (Continuación) | G159: Cuentas por cobrar | J159: El monto a devolver para las subsidiarias Hydro Caisán, S. A., Generadora Pedregalito, S. A., Generadora Alto Valle, S. A. y Generadora Río Chico, S. A. totalizaba B/.807,747 más intereses por B/.201,306, los cuales se encontraban registrados en las cuentas por cobrar clientes en porción circulante. Durante los meses de marzo, abril y mayo, se recibió la cancelación de esta cuenta por cobrar. | K159: 807747 | L159: B/. | T159: OK
A160: 2022 | B160: INA_PPHO_2022_0.pdf | C160: page-63 | D160: markdown.md | E160: 6 | F160: 6. Cuentas por Cobrar (Continuación) | G160: Cuentas por cobrar | J160: Mediante Ley 152 de 4 de mayo de 2020, se adoptaron una serie de medidas especiales en atención a la emergencia sanitaria nacional. Estas medidas incluyeron, entre otras, la suspensión, por el término de cuatro meses a partir del 1 de marzo de 2020, del pago de los servicios públicos de energía eléctrica, telefonía fija, móvil e internet a las personas afectadas según lo aprobado en dicha Ley. El pago de los servicios públicos antes mencionados, por parte de las personas afectadas que se acogieron a estas medidas, se prorrateó a un término de tres años a partir del 1 de julio de 2020. | T160: OK
A161: 2022 | B161: INA_PPHO_2022_0.pdf | C161: page-63 | D161: markdown.md | E161: 6 | F161: 6. Cuentas por Cobrar (Continuación) | G161: Cuentas por cobrar | J161: Mediante Resolución AN No. 16095-Elec del 21 de mayo de 2020, la Autoridad Nacional de los Servicios Públicos aprobó una serie de medidas transitorias que rigieron hasta el 30 de junio de 2020. Estas medidas incluyeron, entre otras, la posibilidad de una reducción en el pago tanto en el mercado de contratos como en el mercado ocasional, proporcional al déficit en la recaudación de los ingresos contemplados en dicha resolución. La resolución estableció que cualquier saldo adeudado a los Participantes del Mercado Mayorista de Electricidad generado dentro del período del 1 de marzo al 30 de junio de 2020, debía ser prorrateado en cuotas iguales en un plazo no mayor de treinta y seis meses, contados a partir de 1 de julio de 2020. Así mismo, los Participantes del Mercado Mayorista de electricidad, podrían llegar a Acuerdos de Pago distinto al establecido en el numeral 5 de dicha Resolución y debían remitir una copia de dicho Acuerdo a la Autoridad Nacional de los Servicios Públicos. | T161: OK
A162: 2022 | B162: INA_PPHO_2022_0.pdf | C162: page-63 | D162: markdown.md | E162: 6 | F162: 6. Cuentas por Cobrar (Continuación) | G162: Cuentas por cobrar | J162: Con excepción de las cuentas por cobrar amparadas bajo la Ley de Moratoria antes descrita, al 31 de diciembre de 2022, no había cuentas por cobrar vencidas y deterioradas, por lo cual no se ha registrado ninguna provisión para cuentas incobrables. | T162: OK
A163: 2022 | B163: INA_PPHO_2022_0.pdf | C163: page-63 | D163: markdown.md | E163: 7 | F163: 7. Gastos Pagados por Adelantado | G163: Costos / gastos | J163: Los gastos pagados por adelantado se detallan de la siguiente manera: | T163: OK
A164: 2022 | B164: INA_PPHO_2022_0.pdf | C164: page-63 | D164: markdown.md | E164: 7 | F164: 7. Gastos Pagados por Adelantado | G164: Costos / gastos | J164: | | 2022 | 2021 | | --- | --- | --- | | Seguros | 124,848 | 170,002 | | Otros | 47,094 | 19,072 | | | 171,942 | 189,074 | | K164: 124848 | L164: B/. | T164: OK
A165: 2022 | B165: INA_PPHO_2022_0.pdf | C165: page-64 | D165: markdown.md | E165: 8 | F165: 8. Propiedad, Planta y Equipo, Neto | G165: PP&E / capex / depreciación | J165: La propiedad, planta y equipo se presenta a continuación: | T165: OK
A166: 2022 | B166: INA_PPHO_2022_0.pdf | C166: page-64 | D166: markdown.md | E166: 8 | F166: 8. Propiedad, Planta y Equipo, Neto | G166: PP&E / capex / depreciación | J166: | | Terreno | Mobiliario y Equipo | Vehículos | Planta y equipo | Construcción en Proceso | Edificio | Mejoras | Total | | --- | --- | --- | --- | --- | --- | --- | --- | --- | | Saldo neto al 31 de diciembre de 2020 | 13,195,714 | 123,361 | 45,628 | 288,073,834 | - | 78,053 | 52,423 | 301,569,013 | | Adiciones | - | 42,074 | 98,532 | - | - | - | - | 140,606 | | Depreciación | - | (33,644) | (23,966) | (11,760,304) | - | (2,481) | (16,927) | (11,837,322) | | Saldo neto al 31 de diciembre de 2021 | 13,195,714 | 131,791 | 120,194 | 276,313,530 | - | 75,572 | 35,496 | 289,872,297 | | Adiciones | 75,500 | 27,792 | - | 246,613 | 1,943,750 | - | - | 2,293,655 | | Retiros | - | - | - | (105,000) | | | | (105,000) | | Depreciación | - | (38,987) | (38,591) | (11,740,507) | - | (2,481) | (15,366) | (11,835,932) | | Saldo neto al 31 de diciembre de 2022 | 13,271,214 | 120,596 | 81,603 | 264,714,636 | 1,943,750 | 73,091 | 20,130 | 280,225,020 | | 2022 | | | | | | | | | | Costo | 13,271,214 | 605,615 | 535,042 | 376,258,067 | 1,943,750 | 99,240 | 141,102 | 392,854,030 | | Depreciación acumulada | - | (485,019) | (453,439) | (111,543,431) | - | (26,149) | (120,972) | (112,629,010) | | Saldo neto al 31 de diciembre de 2022 | 13,271,214 | 120,596 | 81,603 | 264,714,636 | 1,943,750 | 73,091 | 20,130 | 280,225,020 | | 2021 | | | | | | | | | | Costo | 13,195,714 | 1,088,094 | 593,912 | 376,116,454 | - | 99,240 | 160,028 | 391,253,442 | | Depreciación acumulada | - | (956,303) | (473,716) | (99 | K166: 13195714 | L166: B/. | T166: OK
A167: 2022 | B167: INA_PPHO_2022_0.pdf | C167: page-64 | D167: markdown.md | E167: 8 | F167: 8. Propiedad, Planta y Equipo, Neto | G167: PP&E / capex / depreciación | J167: Al 31 de diciembre de 2022 y 2021, la propiedad, planta y equipo se encuentra en garantía de los bonos por pagar (Véase Nota 15) y no presenta deterioro. | T167: OK
A168: 2022 | B168: INA_PPHO_2022_0.pdf | C168: page-65 | D168: markdown.md | E168: 9 | F168: 9. Otros Activos | G168: Otros | J168: Los otros activos se detallan de la siguiente manera: | T168: OK
A169: 2022 | B169: INA_PPHO_2022_0.pdf | C169: page-65 | D169: markdown.md | E169: 9 | F169: 9. Otros Activos | G169: Otros | J169: | | 2022 | 2021 | | --- | --- | --- | | Adelanto en compras de terreno | 224,028 | 224,028 | | Fondo de cesantía | 235,805 | 220,540 | | Adelanto a proveedor | 768,837 | 200,047 | | Servidumbres de acceso | - | 75,500 | | Intereses por cobrar plazo fijo | 68,107 | 107,430 | | Depósito de garantía | 6,638 | 6,638 | | Otros | 39,784 | 29,674 | | | 1,343,199 | 863,857 | | Menos: Porción circulante | 1,115,702 | 654,057 | | Porción no circulante | 227,497 | 209,800 | | K169: 235805 | L169: B/. | T169: OK
A170: 2022 | B170: INA_PPHO_2022_0.pdf | C170: page-65 | D170: markdown.md | E170: 9 | F170: 9. Otros Activos | G170: Otros | J170: Al 31 de diciembre de 2022, la subsidiaria Pedregalito Sola Power, S.A. realizó adelantos a proveedores por la suma de B/.258,312 para el desarrollo de la planta solar Pedregalito Solar Power (ver notas 24 y 26). | K170: 258312 | L170: B/. | T170: OK
A171: 2022 | B171: INA_PPHO_2022_0.pdf | C171: page-65 | D171: markdown.md | E171: 9 | F171: 9. Otros Activos | G171: Otros | J171: A partir del 4 de noviembre de 2020, el huracán ETA tuvo un impacto significativo en el occidente de Panamá, principalmente en Chiriquí, donde operan las centrales de generación eléctrica propiedad de Panama Power Holdings, Inc. Cabe destacar, que la cuenca más afectada fue la del río Chiriquí Viejo donde opera la central El Alto, propiedad de Hydro Caisán, S. A. La gran cantidad de sedimento traído por el río resultó en indisponibilidad de la central durante ciertos períodos mientras el trabajo de limpieza fue llevado a cabo por el equipo de operaciones y contratistas. | T171: OK
A172: 2022 | B172: INA_PPHO_2022_0.pdf | C172: page-65 | D172: markdown.md | E172: 9 | F172: 9. Otros Activos | G172: Otros | J172: Adicionalmente, El Alto tuvo afectaciones principalmente en caminos de acceso, escollera y cuenco disipador aguas abajo de la presa, y pérdida de fibra óptica y línea eléctrica interna en diferentes puntos de la central. Dichas afectaciones no han tenido un impacto en la producción de la central. | T172: OK
A173: 2022 | B173: INA_PPHO_2022_0.pdf | C173: page-65 | D173: markdown.md | E173: 9 | F173: 9. Otros Activos | G173: Otros | J173: El monto estimado a reclamar excedió la suma de B/.500,000, razón por la cual, de conformidad con lo establecido en la referida sección II. A. 9.1. del prospecto de bonos corporativos, Hydro Caisán, S. A. procedió con comunicado formal de notificación al Agente de Pago, al Fiduciario y a los Tenedores de los bonos corporativos de la ocurrencia de este evento. | K173: 500000 | L173: B/. | T173: OK
A174: 2022 | B174: INA_PPHO_2022_0.pdf | C174: page-65 | D174: markdown.md | E174: 9 | F174: 9. Otros Activos | G174: Otros | J174: En el caso de las centrales Pedregalito 1 y Pedregalito 2, hubo restricciones temporales en el despacho de energía debido a afectaciones en torres de la red de transmisión de ETESA. | T174: OK
A175: 2022 | B175: INA_PPHO_2022_0.pdf | C175: page-66 | D175: markdown.md | E175: 9 | F175: 9. Otros Activos (Continuación) | G175: Otros | J175: Al 31 de diciembre de 2022, la subsidiaria Hydro Caisán, S. A. ha incurrido en gastos por la suma de B/.1,844,310 correspondientes a reparaciones asociadas a este siniestro, de los cuales le han sido reembolsados por parte de las aseguradoras la suma de B/.1,717,626. La diferencia corresponde al monto del deducible por la suma de B/.100,000, el cual fue reconocido como gasto durante el año 2020, y a cuentas por cobrar en concepto de reclamo asociado a este siniestro, incluida como Otros, asciende a la suma de B/.26,684. | K175: 1844310 | L175: B/. | T175: OK
A176: 2022 | B176: INA_PPHO_2022_0.pdf | C176: page-66 | D176: markdown.md | E176: 10 | F176: 10. Efectivo Restringido | G176: Working capital | J176: El efectivo restringido corresponde a la siguiente subsidiaria: | T176: OK
A177: 2022 | B177: INA_PPHO_2022_0.pdf | C177: page-66 | D177: markdown.md | E177: 10 | F177: 10. Efectivo Restringido | G177: Working capital | J177: | | 2022 | 2021 | | --- | --- | --- | | Hydro Caisán, S. A. | 4,324,822 | 4,206,485 | | K177: 4324822 | L177: B/. | T177: OK
A178: 2022 | B178: INA_PPHO_2022_0.pdf | C178: page-66 | D178: markdown.md | E178: 10 | F178: 10. Efectivo Restringido | G178: Working capital | J178: Al 31 de diciembre de 2022, el saldo de los bonos corporativos emitidos por el Grupo totalizaba B/.158,250,000 (2021: B/.167,250,000) (véase Nota 16). | K178: 158250000 | L178: B/. | T178: OK
A179: 2022 | B179: INA_PPHO_2022_0.pdf | C179: page-66 | D179: markdown.md | E179: 10 | F179: 10. Efectivo Restringido | G179: Working capital | J179: Como parte de los acuerdos establecidos en el prospecto de la emisión de los Bonos 2020, se incluye la creación de un fondo de fideicomiso con la cuenta denominada Cuenta de Reserva de la Deuda. Este fondo ha sido constituido por Hydro Caisán, S. A. como fideicomitente y BG Trust, Inc. como fiduciario, y tiene como propósito general mantener un fondo de efectivo para cumplir con las obligaciones de pago de intereses y capital (exceptuando el barrido de caja) equivalente a tres meses. | T179: OK
A180: 2022 | B180: INA_PPHO_2022_0.pdf | C180: page-66 | D180: markdown.md | E180: 11 | F180: 11. Plusvalía | G180: Intangibles | J180: El Grupo asigna la plusvalía a las unidades operativas, en este caso las plantas hidroeléctricas. | T180: OK
A181: 2022 | B181: INA_PPHO_2022_0.pdf | C181: page-66 | D181: markdown.md | E181: 11 | F181: 11. Plusvalía | G181: Intangibles | J181: La segregación de la plusvalía se detalla a continuación: | T181: OK
A182: 2022 | B182: INA_PPHO_2022_0.pdf | C182: page-66 | D182: markdown.md | E182: 11 | F182: 11. Plusvalía | G182: Intangibles | J182: | | 2022 | 2021 | | --- | --- | --- | | Pedregalito 1 y 2 | 723,071 | 723,071 | | Cochea | 739,506 | 739,506 | | El Alto | 5,571,173 | 5,571,173 | | | 7,033,750 | 7,033,750 | | K182: 723071 | L182: B/. | T182: OK
A183: 2022 | B183: INA_PPHO_2022_0.pdf | C183: page-66 | D183: markdown.md | E183: 11 | F183: 11. Plusvalía | G183: Intangibles | J183: El Grupo lleva a cabo anualmente una prueba de deterioro de la plusvalía con el fin de comprobar un posible deterioro. | T183: OK
A184: 2022 | B184: INA_PPHO_2022_0.pdf | C184: page-67 | D184: markdown.md | E184: 11 | F184: 11. Plusvalía (Continuación) | G184: Intangibles | J184: Los importes recuperables de las unidades de efectivo se han calculado en función de su valor de uso. El valor de uso se determina descontando los flujos futuros de efectivo esperados de la utilización continua de cada unidad. El cálculo del valor de uso se basa en los supuestos básicos siguientes: | T184: OK
A185: 2022 | B185: INA_PPHO_2022_0.pdf | C185: page-67 | D185: markdown.md | E185: 11 | F185: 11. Plusvalía (Continuación) | G185: Intangibles | J185: - Se utilizaron los resultados reales de funcionamiento del 2022 y el plan de negocio para el año 2023 para proyectar los flujos futuros de efectivo. Los flujos futuros de efectivo fueron proyectados utilizando tasas de crecimiento promedio basadas en los supuestos a largo plazo de las tasas de crecimiento, proyección de hidrología anual, precio de potencia y energía contratados y precio proyectados de mercado ocasional. El período de pronóstico se basa en la perspectiva a largo plazo del Grupo que se determinó en 10 años. | T185: OK
A186: 2022 | B186: INA_PPHO_2022_0.pdf | C186: page-67 | D186: markdown.md | E186: 11 | F186: 11. Plusvalía (Continuación) | G186: Intangibles | J186: - La tasa de descuento del 9.44% (2021: 5.80%) se calculó sobre la base del costo promedio ponderado del capital (WACC, por sus siglas en inglés) para el Grupo. | T186: OK
A187: 2022 | B187: INA_PPHO_2022_0.pdf | C187: page-67 | D187: markdown.md | E187: 11 | F187: 11. Plusvalía (Continuación) | G187: Intangibles | J187: La plusvalía es monitoreada internamente por la Administración para efectos de gestión; y el monto no es superior a los flujos futuros de efectivo descontados. Los principales supuestos antes descritos pueden cambiar a medida que las condiciones económicas y del mercado cambien. El Grupo estima que los cambios razonablemente posibles en estos supuestos no afecten el importe recuperable de las plantas hidroeléctricas o que disminuya por debajo del valor del importe en libros. | T187: OK
A188: 2022 | B188: INA_PPHO_2022_0.pdf | C188: page-67 | D188: markdown.md | E188: 12 | F188: 12. Costos de Exploración y Evaluación | G188: Costos / gastos | J188: El Grupo mantenía costo de exploración y evaluación como se desglosa a continuación: | T188: OK
A189: 2022 | B189: INA_PPHO_2022_0.pdf | C189: page-67 | D189: markdown.md | E189: 12 | F189: 12. Costos de Exploración y Evaluación | G189: Costos / gastos | J189: | | 2022 | 2021 | | --- | --- | --- | | Pedregalito Solar Power, S. A. | 20,824 | 19,824 | | Río Chico Solar Power, S. A. | 153,260 | 153,260 | | | 174,084 | 173,084 | | K189: 20824 | L189: B/. | T189: OK
A190: 2022 | B190: INA_PPHO_2022_0.pdf | C190: page-68 | D190: markdown.md | E190: 13 | F190: 13. Activos Intangibles, Neto | G190: Intangibles | J190: El detalle de los activos intangibles representado por servidumbres se presenta a continuación: | T190: OK
A191: 2022 | B191: INA_PPHO_2022_0.pdf | C191: page-68 | D191: markdown.md | E191: 13 | F191: 13. Activos Intangibles, Neto | G191: Intangibles | J191: | | 2022 | 2021 | | --- | --- | --- | | Saldo neto al inicio del año | 538,918 | 612,637 | | Ajuste del año | - | (60,000) | | Amortización del año | (13,092) | (13,719) | | Saldo neto al final del año | 525,826 | 538,918 | | Valor neto en libros | | | | Costo | 717,616 | 717,616 | | Amortización acumulada | (191,790) | (178,698) | | Saldo neto | 525,826 | 538,918 | | K191: 538918 | L191: B/. | T191: OK
A192: 2022 | B192: INA_PPHO_2022_0.pdf | C192: page-68 | D192: markdown.md | E192: 14 | F192: 14. Activos por Derecho de Uso | G192: Otros | J192: El Grupo mantiene arrendada la oficina principal donde se encuentra su domicilio administrativo. El arrendamiento se contabiliza en el estado consolidado de situación financiera como un activo por derecho de uso y un pasivo por arrendamiento. El arrendamiento de propiedades generalmente tiene un plazo de arrendamiento que varía de 1 a 5 años, el cual puede tener condiciones que sean prorrogables. El pago del arrendamiento se realiza por montos fijos mensuales. El Grupo ha reconocido los registros contables sobre los contratos vigentes a la fecha de adopción. | T192: OK
A193: 2022 | B193: INA_PPHO_2022_0.pdf | C193: page-68 | D193: markdown.md | E193: 14 | F193: 14. Activos por Derecho de Uso | G193: Otros | J193: Generalmente, cada arrendamiento establece una restricción que, a menos que exista un derecho contractual para que el Grupo subarriende el activo a un tercero, el activo por derecho de uso sólo se puede utilizar por el Grupo. El arrendamiento es cancelable por mutuo acuerdo, por decisión unilateral del arrendatario con o sin penalidad según sea el período de terminación o sólo pueden ser cancelados si se incurre en una penalización significativa por terminación, por incumplimiento de pagos o por incumplimiento por alguna de las partes. El Grupo debe conservar en buen estado la propiedad y devolverla en su estado original al finalizar el arrendamiento. Además, el Grupo debe contratar seguros para los activos de propiedad, planta y equipo e incurrir en gastos de mantenimiento por dichos elementos de acuerdo con el contrato de arrendamiento. | T193: OK
A194: 2022 | B194: INA_PPHO_2022_0.pdf | C194: page-69 | D194: markdown.md | E194: 14 | F194: 14. Activos por Derecho de Uso (Continuación) | G194: Otros | J194: El movimiento de los activos por derecho de uso se presenta a continuación: | T194: OK
A195: 2022 | B195: INA_PPHO_2022_0.pdf | C195: page-69 | D195: markdown.md | E195: 14 | F195: 14. Activos por Derecho de Uso (Continuación) | G195: Otros | J195: | | 2022 | 2021 | | --- | --- | --- | | Saldo neto al inicio del año | 142,658 | 93,026 | | Adiciones | - | 141,572 | | Adenda al contrato | - | (64,530) | | Amortización del año | (40,760) | (27,410) | | Saldo neto al final del año | 101,898 | 142,658 | | K195: 142658 | L195: B/. | T195: OK
A196: 2022 | B196: INA_PPHO_2022_0.pdf | C196: page-69 | D196: markdown.md | E196: 14 | F196: 14. Activos por Derecho de Uso (Continuación) | G196: Otros | J196: Al 31 de diciembre de 2022, El Grupo mantiene activos por derecho de uso que se presentan a continuación: | T196: OK
A197: 2022 | B197: INA_PPHO_2022_0.pdf | C197: page-69 | D197: markdown.md | E197: 14 | F197: 14. Activos por Derecho de Uso (Continuación) | G197: Otros | J197: | | 2022 | 2021 | | --- | --- | --- | | Activos por derecho de uso | | | | Costo | 314,345 | 314,345 | | Adenda al contrato | (64,530) | (64,530) | | Amortización acumulada | (147,917) | (107,157) | | Valor neto | 101,898 | 142,658 | | Pasivo por arrendamiento | | | | Circulante | 32,604 | 32,604 | | No circulante | 69,294 | 110,054 | | | 101,898 | 142,658 | | K197: 314345 | L197: B/. | T197: OK
A198: 2022 | B198: INA_PPHO_2022_0.pdf | C198: page-69 | D198: markdown.md | E198: 14 | F198: 14. Activos por Derecho de Uso (Continuación) | G198: Otros | J198: Los pagos mínimos futuros bajo los arrendamientos financieros y el valor presente de dichos pagos se presentan a continuación: | T198: OK
A199: 2022 | B199: INA_PPHO_2022_0.pdf | C199: page-69 | D199: markdown.md | E199: 14 | F199: 14. Activos por Derecho de Uso (Continuación) | G199: Otros | J199: | | 2022 | 2021 | | --- | --- | --- | | Menos de un año | 36,000 | 36,000 | | Más de 1 año y menos de 5 años | 104,024 | 112,176 | | Total de pagos mínimos bajo arrendamiento | 140,024 | 148,176 | | Menos: Tasa de descuento | (38,126) | (5,518) | | Valor presente de los pagos mínimos | 101,898 | 142,658 | | Menos porción circulante | 32,604 | (32,604) | | Obligación por arrendamiento financiero | | | | largo plazo | 69,294 | 110,054 | | K199: 36000 | L199: B/. | T199: OK
A200: 2022 | B200: INA_PPHO_2022_0.pdf | C200: page-70 | D200: markdown.md | E200: 15 | F200: 15. Cuentas por Pagar | G200: Cuentas por pagar | J200: Las cuentas por pagar se presentan a continuación: | T200: OK
A201: 2022 | B201: INA_PPHO_2022_0.pdf | C201: page-70 | D201: markdown.md | E201: 15 | F201: 15. Cuentas por Pagar | G201: Cuentas por pagar | J201: | | 2022 | 2021 | | --- | --- | --- | | Agentes del mercado y otros proveedores | 1,636,617 | 2,131,468 | | Contratistas | - | 1,605,000 | | Otros | 11,000 | 45,381 | | Intereses de préstamos | 1,733 | - | | Intereses de bonos por pagar | 26,611 | 35,974 | | | 1,675,961 | 3,817,823 | | K201: 1636617 | L201: B/. | T201: OK
A202: 2022 | B202: INA_PPHO_2022_0.pdf | C202: page-70 | D202: markdown.md | E202: 15 | F202: 15. Cuentas por Pagar | G202: Cuentas por pagar | J202: Con fecha 2 de febrero de 2022, dando cumplimiento a lo ordenado mediante Auto emitido por el Juzgado Segundo de Circuito de Coclé, Ramo Civil, la subsidiaria Hydro Caisán, S. A. realizó pago de cuenta por pagar a contratista que mantenía por la suma de $1,500,000 mediante la emisión de un Certificado de Depósito Judicial emitido por el Banco Nacional de Panamá a favor de dicho Juzgado. | K202: 1500000 | L202: B/. | T202: OK
A203: 2022 | B203: INA_PPHO_2022_0.pdf | C203: page-70 | D203: markdown.md | E203: 16 | F203: 16. Bonos por Pagar | G203: Deuda / bonos / préstamos / leases | J203: Los bonos por pagar se presentan a continuación: | T203: OK
A204: 2022 | B204: INA_PPHO_2022_0.pdf | C204: page-70 | D204: markdown.md | E204: 16 | F204: 16. Bonos por Pagar | G204: Deuda / bonos / préstamos / leases | J204: | | 2022 | 2021 | | --- | --- | --- | | Hydro Caisán, S. A. | | | | Bonos Corporativos 2020 con vencimiento el 5 de octubre de 2030 | 158,250,000 | 167,250,000 | | Costos de financiamiento diferidos, neto | (1,634,285) | (1,843,071) | | | 156,615,715 | 165,406,929 | | K204: 158250000 | L204: B/. | T204: OK
A205: 2022 | B205: INA_PPHO_2022_0.pdf | C205: page-70 | D205: markdown.md | E205: 16 | F205: 16. Bonos por Pagar | G205: Deuda / bonos / préstamos / leases | J205: El detalle de los costos de financiamiento diferido se presenta a continuación: | T205: OK
A206: 2022 | B206: INA_PPHO_2022_0.pdf | C206: page-70 | D206: markdown.md | E206: 16 | F206: 16. Bonos por Pagar | G206: Deuda / bonos / préstamos / leases | J206: | | 2022 | 2021 | | --- | --- | --- | | Saldo neto al inicio del año | 1,843,071 | 2,038,946 | | Adiciones | - | 14,910 | | Amortización del año | (208,786) | (210,785) | | Saldo neto al final del año | 1,634,285 | 1,843,071 | | K206: 1843071 | L206: B/. | T206: OK
A207: 2022 | B207: INA_PPHO_2022_0.pdf | C207: page-71 | D207: markdown.md | E207: 16 | F207: 16. Bonos por Pagar (Continuación) | G207: Deuda / bonos / préstamos / leases | J207: La estructura de vencimiento de los bonos por pagar se detalla a continuación: | T207: OK
A208: 2022 | B208: INA_PPHO_2022_0.pdf | C208: page-71 | D208: markdown.md | E208: 16 | F208: 16. Bonos por Pagar (Continuación) | G208: Deuda / bonos / préstamos / leases | J208: | | 2022 | 2021 | | --- | --- | --- | | A un año | 9,000,000 | 9,000,000 | | Entre 1 y 5 años | 36,000,000 | 36,000,000 | | Más de 5 años | 113,250,000 | 122,250,000 | | | 158,250,000 | 167,250,000 | | K208: 9000000 | L208: B/. | T208: OK
A209: 2022 | B209: INA_PPHO_2022_0.pdf | C209: page-71 | D209: markdown.md | E209: 16 | F209: 16. Bonos por Pagar (Continuación) | G209: Deuda / bonos / préstamos / leases | J209: Los Bonos corporativos, emitidos con fecha efectiva 5 de octubre 2020, están respaldados por fianza solidaria de Panama Power Holdings, Inc., Generadora Pedregalito, S. A., Generadora Río Chico, S. A., Generadora Alto Valle, S. A. y PPH Financing Services, S. A. y por un fideicomiso de garantía. | T209: OK
A210: 2022 | B210: INA_PPHO_2022_0.pdf | C210: page-71 | D210: markdown.md | E210: 16 | F210: 16. Bonos por Pagar (Continuación) | G210: Deuda / bonos / préstamos / leases | J210: Dicha emisión fue aprobada mediante Resolución No. SMV-421-20 de 21 de septiembre de 2020 por la Superintendencia de Mercado de Valores. | T210: OK
A211: 2022 | B211: INA_PPHO_2022_0.pdf | C211: page-71 | D211: markdown.md | E211: 16 | F211: 16. Bonos por Pagar (Continuación) | G211: Deuda / bonos / préstamos / leases | J211: La emisión está respaldada por un fideicomiso de garantía cuyo fiduciario es BG Trust, Inc., al cual han sido y serán cedidos, según aplique, la totalidad de los activos correspondientes a bienes muebles e inmuebles, hipoteca sobre la concesión, todos los contratos, cesión de flujos, cuentas por cobrar, depósitos bancarios, cartas de crédito de garantía, y seguros de operación de las Subsidiarias Hydro Caisán, S. A., Generadora Pedregalito, S. A., Generadora Río Chico, S. A. y Generadora Alto Valle, S. A. (las Compañías de los Proyectos). | T211: OK
A212: 2022 | B212: INA_PPHO_2022_0.pdf | C212: page-71 | D212: markdown.md | E212: 16 | F212: 16. Bonos por Pagar (Continuación) | G212: Deuda / bonos / préstamos / leases | J212: La Compañía y sus garantes se obligan a cumplir con todos los aspectos ambientales, técnicos y comerciales requeridos para la operación de las centrales hidroeléctricas, a restricciones sobre la venta y endeudamiento no permitido sobre sus activos, y al cumplimiento de ciertas razones financieras de acuerdo a lo establecido en el prospecto. | T212: OK
A213: 2022 | B213: INA_PPHO_2022_0.pdf | C213: page-71 | D213: markdown.md | E213: 16 | F213: 16. Bonos por Pagar (Continuación) | G213: Deuda / bonos / préstamos / leases | J213: Dentro de los principales términos y condiciones de los Bonos se encuentran: a) plazo de diez años; b) amortizaciones trimestrales fijas a capital por B/.1,750,000 e intereses a una tasa fija de 5.875%; c) barrido de caja anual obligatorio por B/.2,000,000, pagadero parcial o totalmente en cualquier fecha de pago de interés, acumulable en caso de no contar con el flujo suficiente para el pago del mismo, y opcional en caso de suscribir nuevos contratos de energía que resulten en una Razón de Cobertura de Servicio de Deuda mayor a 1.50x; d) Cuenta de Reserva de Servicio de Deuda de tres meses de pago de capital (exceptuando el barrido de caja) e intereses. | K213: 1750000 | L213: B/. | T213: OK
A214: 2022 | B214: INA_PPHO_2022_0.pdf | C214: page-72 | D214: markdown.md | E214: 16 | F214: 16. Bonos por Pagar (Continuación) | G214: Deuda / bonos / préstamos / leases | J214: ### Bonos Corporativos (continuación) | T214: OK
A215: 2022 | B215: INA_PPHO_2022_0.pdf | C215: page-72 | D215: markdown.md | E215: 16 | F215: 16. Bonos por Pagar (Continuación) | G215: Deuda / bonos / préstamos / leases | J215: Adicionalmente, Hydro Caisán, S. A. se comprometió a causar que PPH y las demás Compañías de los Proyectos mantengan y cumplan de manera consolidada con una Razón de Cobertura de Servicio de Deuda mayor a 1.25x para los últimos doce (12) meses como requisito financiero y como condición para pagos restringidos. | T215: OK
A216: 2022 | B216: INA_PPHO_2022_0.pdf | C216: page-72 | D216: markdown.md | E216: 16 | F216: 16. Bonos por Pagar (Continuación) | G216: Deuda / bonos / préstamos / leases | J216: Los bonos fueron emitidos en su totalidad a través de la Bolsa Latinoamericana de Valores y 100% suscritos por un sindicato de bancos liderado por Banco General, S. A., quien también actúa como agente de pago, registro y transferencia de la emisión. | T216: OK
A217: 2022 | B217: INA_PPHO_2022_0.pdf | C217: page-72 | D217: markdown.md | E217: 16 | F217: 16. Bonos por Pagar (Continuación) | G217: Deuda / bonos / préstamos / leases | J217: La totalidad de los términos y condiciones de los Bonos se encuentran en la página web de la Superintendencia del Mercado de Valores, Bolsa Latinoamericana de Valores y página web de la Compañía (www.panamapower.net). | T217: OK
A218: 2022 | B218: INA_PPHO_2022_0.pdf | C218: page-72 | D218: markdown.md | E218: 16 | F218: 16. Bonos por Pagar (Continuación) | G218: Deuda / bonos / préstamos / leases | J218: El valor razonable de la deuda al 31 de diciembre de 2022 es de B/.128,676,793 (2021: B/.160,740,371) determinado en base de flujos descontados de caja utilizando una tasa del 9.240% (2021: 6.422%) y está incluido en el Nivel 2 de la jerarquía del valor razonable. | K218: 128676793 | L218: B/. | T218: OK
A219: 2022 | B219: INA_PPHO_2022_0.pdf | C219: page-72 | D219: markdown.md | E219: 17 | F219: 17. Préstamos por pagar | G219: Deuda / bonos / préstamos / leases | J219: Los préstamos por pagar al 31 de diciembre 2022, se detallan a continuación: | T219: OK
A220: 2022 | B220: INA_PPHO_2022_0.pdf | C220: page-72 | D220: markdown.md | E220: 17 | F220: 17. Préstamos por pagar | G220: Deuda / bonos / préstamos / leases | J220: | | 2022 | 2021 | | --- | --- | --- | | Banco General, S. A. | | | | Línea de crédito No Rotativa | 758,413 | - | | T220: OK
A221: 2022 | B221: INA_PPHO_2022_0.pdf | C221: page-72 | D221: markdown.md | E221: 17 | F221: 17. Préstamos por pagar | G221: Deuda / bonos / préstamos / leases | J221: Con fecha 17 de mayo de 2022, PPH Financing Services, S. A. celebró Contrato de Línea de Adelantos No Rotativa con Banco General, S. A. para financiar la construcción de una mini central de 1.0MW de capacidad firme ubicada en la central hidroeléctrica El Alto. La facilidad cuenta con fianza solidaria de Panama Power Holdings, Inc. | T221: OK
...

Sheet MDA
A1: Panama Power Holdings, Inc. y Subsidiarias
A2: MD&A — IN-A FY2025 (Panama Power Holdings, Inc.), Sección "Análisis de Resultados Financieros y Operativos" (transcripción verbatim del filing público; linaje archivo-línea en Source_Register).
A3: II. ANALISIS DE RESULTADOS FINANCIEROS Y OPERATIVOS
A4: Liquidez
A5: Al 31 de diciembre de 2025, PPH tiene un total de activos circulantes de $31,660,678 ($24,685,303 al 31
A6: de diciembre de 2024 y $26,443,110 al 31 de diciembre de 2023), compuesto por $19,057,503 en
A7: efectivo y equivalentes de efectivo ($9,494,389 al 31 de diciembre de 2024 y $10,299,859 al 31 de
A8: diciembre de 2023), $8,602,706 en cuentas por cobrar ($10,018,368 al 31 de diciembre de 2024 y
A9: $10,514,874 al 31 de diciembre de 2023), $2,666,409 en inventario de repuestos y consumibles
A10: ($2,315,599 al 31 de diciembre de 2024 y $2,176,373 al 31 de diciembre de 2023), $836,786 en gastos
A11: pagados por anticipado ($475,685 al 31 de diciembre de 2024 y $1,400,465 al 31 de diciembre de 2023),
A12: $0 en crédito fiscal por inversión ($1,829,780 al 31 de diciembre de 2024 y $1,541,175 al 31 de diciembre
... A47: planta Pedregalito Solar Power.
A48: 11
A49: ```
A50: ## PDF Page 15
A51: ```text
A52: Venta de Energía
A53: A continuación se presenta un resumen de la composición de la utilidad en venta de energía reflejada en
A54: el estado financiero.
A55: 31-dic-25 vs
A56: PPH Consolidado 31-dic-2025 31-dic-2024 31-dic-2023
A57: 31-dic-24
A58: ING
A59: Producción total 470,665 497,784 374,482 (27,119)
A60: Suplidor de pérdidas de transmisión (19,250) (22,248) (12,211) 2,998
... A100: 44,419MWh.
A101: 12
A102: ```
A103: ## PDF Page 16
A104: ```text
A105: El precio promedio de compras en el mercado ocasional disminuyó de $145/MWh al 31 de diciembre de
A106: 2024 a $70/MWh al 31 de diciembre de 2025. ($129/MWh al 31 de diciembre de 2023).
A107: Las ventas en el mercado ocasional disminuyeron en un 2% de 219,421MWh a 215,832MWh, aunado a
A108: una disminución en el precio promedio de ventas en el mercado ocasional de $73/MWh al 31 de
A109: diciembre de 2024 a $63/MWh al 31 de diciembre de 2025 resultó en una disminución en los ingresos por
A110: ventas en el mercado ocasional de $2,377,920. El precio promedio de ventas en el mercado ocasional
A111: disminuyó de $73/MWh al 31 de diciembre de 2024 a $63/MWh al 31 de diciembre de 2025. ($113/MWh
A112: al 31 de diciembre de 2023).
A113: Para los 12 meses terminados el 31 de diciembre de 2025, PPH generó una utilidad en venta de energía
... A149: comparación a los $302,873,671 registrados al cierre del 31 de diciembre de 2024, producto
A150: 13
A151: ```
A152: ## PDF Page 17
A153: ```text
A154: principalmente a depreciación acumulada. Al 31 de diciembre de 2023 los activos totales cerraron en
A155: 316804300
A156: Los principales componentes del activo no circulante son:
A157: - Activo financiero restringido por $4,260,349 ($4,197,349 al 31 de diciembre de 2024 y $4,033,700
A158: al 31 de diciembre de 2023), correspondiente a los fondos aportados a la Cuenta de Reserva de
A159: Servicio de la Deuda, en respaldo del fideicomiso de garantía de los bonos emitidos por la
A160: subsidiaria Hydro Caisán.
A161: - Propiedad, planta y equipo, neto de depreciación acumulada, por $254,111,593 ($266,144,886 al
A162: 31 de diciembre de 2024 y $278,143,135 al 31 de diciembre de 2023) compuesto por:
A163: o Planta y equipo, neto de depreciación acumulada, por $240,478,473;
A164: o Terrenos por $13,271,214, adquiridos por las subsidiarias de los proyectos;
A165: o Edificio y mejoras (almacén y oficinas) y otros activos, neto de depreciación
A166: acumulada, por $361,906.
A167: - Plusvalía, generada por la adquisición de las compañías dueñas de los proyectos hidroeléctricos
... A196: $1,223,799 al 31 de diciembre de 2023).
A197: 14
A198: ```
A199: ## PDF Page 18
A200: ```text
A201: El grupo suscribió contratos para el desarrollo de una planta solar con una capacidad de 9.90MW
A202: nominal, ubicada en el distrito de Alanje, provincia de Chiriquí. El costo total del proyecto ascendió a
A203: 7957657
A204: Con fecha 2 de febrero de 2022, dando cumplimiento a lo ordenado mediante Auto emitido por el
A205: Juzgado Segundo de Circuito de Coclé, Ramo Civil, Hydro Caisán, S.A. realizó el pago de la cuenta por
A206: pagar a contratista que mantenía por la suma de $1,500,000 mediante la emisión de un Certificado de
A207: Depósito Judicial emitido por el Banco Nacional de Panamá a favor de dicho Juzgado (Ver nota 24 de los
A208: estados financieros auditados que acompañan a este informe anual).
A209: El Pasivo no circulante el cual cerró el periodo en $124,015,091 ($133,187,167 al 31 de diciembre de
A210: 2024 y $143,054,848 al 31 de diciembre de 2023), está compuesto de bonos por pagar emitidos por la
A211: subsidiaria Hydro Caisán por $121,450,858, neto de costos de financiamiento diferidos ($130,242,072 al
A212: 31 de diciembre de 2024 y $139,033,286 al 31 de diciembre de 2023), préstamos por pagar por
A213: $2,275,211 ($2,679,481 al 31 de diciembre de 2024 y $3,503,256 al 31 de diciembre de 2023), ingreso
A214: diferido por crédito fiscal en inversión por $0 ($0 al 31 de diciembre de 2024 y $238,792 al 31 de
A215: diciembre de 2023), obligación por arrendamiento por $0 ($4,078 al 31 de diciembre de 2024 y $36,686
... A245: doce (12) meses como requisito financiero y como condición para pagos restringidos.
A246: 15
A247: ```
A248: ## PDF Page 19
A249: ```text
A250: Los bonos fueron emitidos en su totalidad a través de la Bolsa de Valores de Panamá y 100% suscritos
A251: por un sindicado de bancos liderado por Banco General, S. A. Banco General, S. A. actúa como agente
A252: de pago, registro y transferencia de la emisión.
A253: La totalidad de los términos y condiciones de los Bonos 2020 se encuentran en la página web de la
A254: Superintendencia del Mercado de Valores, Bolsa Latinoamericana de Valores y página web de la
A255: Compañía (www.panamapower.net).
A256: Al 31 de diciembre de 2025, el saldo bruto a capital de los bonos totalizó $131,250,000. La subsidiaria
A257: Hydro Caisán, S.A. realizó, en adición a la amortización a capital trimestral por $1,750,000, la
A258: amortización correspondiente al barrido de caja anual por $2,000,000 correspondiente al periodo en
... A289: precios del gas natural, petróleo, y carbón, el comportamiento y manejo de los embalses de las
A290: 16
A291: ```
A292: ## PDF Page 20
A293: ```text
A294: principales hidroeléctricas del país, la producción de plantas de generación existentes, la entrada en los
A295: últimos años de nuevas fuentes de generación como el gas, fotovoltaicos y eólicos, limitaciones con
...

Sheet ModeloFinanciero
A1: Panama Power Holdings, Inc. y Subsidiarias
A2: Estados Financieros Auditados FY21-FY25
A3: en B/. sin escala
A5: Años | B5: FY21A | C5: FY22A | D5: FY23A | E5: FY24A | F5: FY25A | G5: FY26E | H5: FY27E | I5: FY28E | J5: FY29E | K5: FY30E
A6: Estado de Resultados
A7: Venta de energía | B7: =EEFF!B7 -> 42793727 | C7: =EEFF!C7 -> 57204243 | D7: =EEFF!D7 -> 53187368 | E7: =EEFF!E7 -> 55356497 | F7: =EEFF!F7 -> 48358044 | G7: =Supuestos!G39 -> 38521429 | H7: =Supuestos!H39 -> 32605880 | I7: =Supuestos!I39 -> 33463954 | J7: =Supuestos!J39 -> 33345801 | K7: =Supuestos!K39 -> 25937470
A8: Compras de energía y costos asociados | B8: =EEFF!B8 -> 4427043 | C8: =EEFF!C8 -> 8559953 | D8: =EEFF!D8 -> 12013335 | E8: =EEFF!E8 -> 9960198 | F8: =EEFF!F8 -> 4986124 | G8: =Supuestos!G43 -> 5053166.2 | H8: =Supuestos!H43 -> 9162668.8 | I8: =Supuestos!I43 -> 4444195.7 | J8: =Supuestos!J43 -> 4444195.7 | K8: =Supuestos!K43 -> 4444195.7
A9: Cargo de transmisión | B9: =EEFF!B9 -> 1368202 | C9: =EEFF!C9 -> 1850469 | D9: =EEFF!D9 -> 2243773 | E9: =EEFF!E9 -> 2503761 | F9: =EEFF!F9 -> 1761951 | G9: =F9 -> 1761951 | H9: =G9 -> 1761951 | I9: =H9 -> 1761951 | J9: =I9 -> 1761951 | K9: =J9 -> 1761951
A10: Total de costo de energía | B10: =EEFF!B10 -> 5795245 | C10: =EEFF!C10 -> 10410422 | D10: =EEFF!D10 -> 14257108 | E10: =EEFF!E10 -> 12463959 | F10: =EEFF!F10 -> 6748075 | G10: =G8+G9 -> 6815117.2 | H10: =H8+H9 -> 10924620 | I10: =I8+I9 -> 6206146.7 | J10: =J8+J9 -> 6206146.7 | K10: =K8+K9 -> 6206146.7
A11: Ingresos por crédito fiscal y otros | B11: =EEFF!B11 -> 869881 | C11: =EEFF!C11 -> 1974498 | D11: =EEFF!D11 -> 2169724 | E11: =EEFF!E11 -> 642966 | F11: =EEFF!F11 -> 1922207 | G11: =F11 -> 1922207 | H11: =G11 -> 1922207 | I11: =H11 -> 1922207 | J11: =I11 -> 1922207 | K11: =J11 -> 1922207
A12: Depreciación y amortización | B12: =EEFF!B12 -> 11878451 | C12: =EEFF!C12 -> 11881633 | D12: =EEFF!D12 -> 11997283 | E12: =EEFF!E12 -> 12446869 | F12: =EEFF!F12 -> 12521408 | G12: =F12 -> 12521408 | H12: =G12 -> 12521408 | I12: =H12 -> 12521408 | J12: =I12 -> 12521408 | K12: =J12 -> 12521408
A13: Operación y mantenimiento | B13: =EEFF!B13 -> 2400538 | C13: =EEFF!C13 -> 2548375 | D13: =EEFF!D13 -> 2841019 | E13: =EEFF!E13 -> 2549512 | F13: =EEFF!F13 -> 3004212 | G13: =F13 -> 3004212 | H13: =G13 -> 3004212 | I13: =H13 -> 3004212 | J13: =I13 -> 3004212 | K13: =J13 -> 3004212
A14: Generales y administrativos | B14: =EEFF!B14 -> 4588379 | C14: =EEFF!C14 -> 5332929 | D14: =EEFF!D14 -> 5554329 | E14: =EEFF!E14 -> 5511351 | F14: =EEFF!F14 -> 5684677 | G14: =Supuestos!G46 -> 5511351 | H14: =Supuestos!H46 -> 5511351 | I14: =Supuestos!I46 -> 5511351 | J14: =Supuestos!J46 -> 5511351 | K14: =Supuestos!K46 -> 5511351
A15: Otras pérdidas netas | B15: =EEFF!B15 -> 0 | C15: =EEFF!C15 -> 0 | D15: =EEFF!D15 -> 127418 | E15: =EEFF!E15 -> 0 | F15: =EEFF!F15 -> 0
A16: Pérdida en activos no financieros | B16: =EEFF!B16 -> 20000 | C16: =EEFF!C16 -> 0 | D16: =EEFF!D16 -> 0 | E16: =EEFF!E16 -> 0 | F16: =EEFF!F16 -> 0
A17: Pérdida en activos financieros | B17: =EEFF!B17 -> 139398 | C17: =EEFF!C17 -> 0 | D17: =EEFF!D17 -> 0 | E17: =EEFF!E17 -> 0 | F17: =EEFF!F17 -> 0
A18: Total de gastos operativos | B18: =EEFF!B18 -> 19026766 | C18: =EEFF!C18 -> 19762937 | D18: =EEFF!D18 -> 20520049 | E18: =EEFF!E18 -> 20507732 | F18: =EEFF!F18 -> 21210297 | G18: =G12+G13+G14+G15+G16+G17 -> 21036971 | H18: =H12+H13+H14+H15+H16+H17 -> 21036971 | I18: =I12+I13+I14+I15+I16+I17 -> 21036971 | J18: =J12+J13+J14+J15+J16+J17 -> 21036971 | K18: =K12+K13+K14+K15+K16+K17 -> 21036971
A19: Utilidad operativa | B19: =EEFF!B19 -> 18841597 | C19: =EEFF!C19 -> 29005382 | D19: =EEFF!D19 -> 20579935 | E19: =EEFF!E19 -> 23027772 | F19: =EEFF!F19 -> 22321879 | G19: =G7-G10+G11-G18 -> 12591548 | H19: =H7-H10+H11-H18 -> 2566496.3 | I19: =I7-I10+I11-I18 -> 8143043.5 | J19: =J7-J10+J11-J18 -> 8024890.7 | K19: =K7-K10+K11-K18 -> 616558.91
A20: Costos financieros | B20: =EEFF!B20 -> 10739963 | C20: =EEFF!C20 -> 10140045 | D20: =EEFF!D20 -> 9645428 | E20: =EEFF!E20 -> 9291709 | F20: =EEFF!F20 -> 8681196 | G20: =Debt_Schedule!G18 -> 8152445.5 | H20: =Debt_Schedule!H18 -> 7623695.5 | I20: =Debt_Schedule!I18 -> 7094945.5 | J20: =Debt_Schedule!J18 -> 6566195.5 | K20: =Debt_Schedule!K18 -> 6001442.5
A21: Ingresos financieros | B21: =EEFF!B21 -> -129032 | C21: =EEFF!C21 -> -140572 | D21: =EEFF!D21 -> -242921 | E21: =EEFF!E21 -> -362555 | F21: =EEFF!F21 -> -547419 | G21: =F21 -> -547419 | H21: =G21 -> -547419 | I21: =H21 -> -547419 | J21: =I21 -> -547419 | K21: =J21 -> -547419
A22: Costos financieros, neto | B22: =EEFF!B22 -> 10610931 | C22: =EEFF!C22 -> 9999473 | D22: =EEFF!D22 -> 9402507 | E22: =EEFF!E22 -> 8929154 | F22: =EEFF!F22 -> 8133777 | G22: =G20+G21 -> 7605026.5 | H22: =H20+H21 -> 7076276.5 | I22: =I20+I21 -> 6547526.5 | J22: =J20+J21 -> 6018776.5 | K22: =K20+K21 -> 5454023.5
A23: Utilidad antes de impuesto sobre la renta | B23: =EEFF!B23 -> 8230666 | C23: =EEFF!C23 -> 19005909 | D23: =EEFF!D23 -> 11177428 | E23: =EEFF!E23 -> 14098618 | F23: =EEFF!F23 -> 14188102 | G23: =G19-G22 -> 4986521.8 | H23: =H19-H22 -> -4509780.2 | I23: =I19-I22 -> 1595517 | J23: =J19-J22 -> 2006114.2 | K23: =K19-K22 -> -4837464.6
A24: Impuesto sobre la renta | B24: =EEFF!B24 -> -3095130 | C24: =EEFF!C24 -> -5342988 | D24: =EEFF!D24 -> -3950425 | E24: =EEFF!E24 -> -4617385 | F24: =EEFF!F24 -> -4887298 | G24: =-ROUND(G23*0.3445,0) -> -1717857 | H24: =-ROUND(H23*0.3445,0) -> 1553619 | I24: =-ROUND(I23*0.3445,0) -> -549656 | J24: =-ROUND(J23*0.3445,0) -> -691106 | K24: =-ROUND(K23*0.3445,0) -> 1666507
A25: Utilidad neta integral | B25: =EEFF!B25 -> 5135536 | C25: =EEFF!C25 -> 13662921 | D25: =EEFF!D25 -> 7227003 | E25: =EEFF!E25 -> 9481233 | F25: =EEFF!F25 -> 9300804 | G25: =G23+G24 -> 3268664.8 | H25: =H23+H24 -> -2956161.2 | I25: =I23+I24 -> 1045861 | J25: =J23+J24 -> 1315008.2 | K25: =K23+K24 -> -3170957.6
A27: Años | B27: FY21A | C27: FY22A | D27: FY23A | E27: FY24A | F27: FY25A | G27: FY26E | H27: FY27E | I27: FY28E | J27: FY29E | K27: FY30E
A28: Balance General
A29: Efectivo | B29: =EEFF!B29 -> 9167597 | C29: =EEFF!C29 -> 10955792 | D29: =EEFF!D29 -> 10299859 | E29: =EEFF!E29 -> 9494389 | F29: =EEFF!F29 -> 11057503 | G29: =G110 -> 17614506 | H29: =H110 -> 17946683 | I29: =I110 -> 22280882 | J29: =J110 -> 26884228 | K29: =K110 -> 26965605
A30: Depósito a plazo fijo mayor a 90 días | B30: =EEFF!B30 -> 0 | C30: =EEFF!C30 -> 0 | D30: =EEFF!D30 -> 0 | E30: =EEFF!E30 -> 0 | F30: =EEFF!F30 -> 8000000 | G30: =F30 -> 8000000 | H30: =G30 -> 8000000 | I30: =H30 -> 8000000 | J30: =I30 -> 8000000 | K30: =J30 -> 8000000
A31: Cuentas por cobrar | B31: =EEFF!B31 -> 9794078 | C31: =EEFF!C31 -> 10480520 | D31: =EEFF!D31 -> 10514874 | E31: =EEFF!E31 -> 10018368 | F31: =EEFF!F31 -> 8602706 | G31: =F31 -> 8602706 | H31: =G31 -> 8602706 | I31: =H31 -> 8602706 | J31: =I31 -> 8602706 | K31: =J31 -> 8602706
A32: Inventario de repuestos y suministros | B32: =EEFF!B32 -> 1954889 | C32: =EEFF!C32 -> 2283806 | D32: =EEFF!D32 -> 2176373 | E32: =EEFF!E32 -> 2315599 | F32: =EEFF!F32 -> 2666409 | G32: =F32 -> 2666409 | H32: =G32 -> 2666409 | I32: =H32 -> 2666409 | J32: =I32 -> 2666409 | K32: =J32 -> 2666409
A33: Gastos pagados por adelantado | B33: =EEFF!B33 -> 189074 | C33: =EEFF!C33 -> 171942 | D33: =EEFF!D33 -> 1400465 | E33: =EEFF!E33 -> 475685 | F33: =EEFF!F33 -> 836786 | G33: =F33 -> 836786 | H33: =G33 -> 836786 | I33: =H33 -> 836786 | J33: =I33 -> 836786 | K33: =J33 -> 836786
A34: Crédito fiscal por inversión | B34: =EEFF!B34 -> 1825438 | C34: =EEFF!C34 -> 2648365 | D34: =EEFF!D34 -> 1541175 | E34: =EEFF!E34 -> 1829780 | F34: =EEFF!F34 -> 0 | G34: =F34 -> 0 | H34: =G34 -> 0 | I34: =H34 -> 0 | J34: =I34 -> 0 | K34: =J34 -> 0
A35: Otros activos | B35: =EEFF!B35 -> 654057 | C35: =EEFF!C35 -> 1115702 | D35: =EEFF!D35 -> 510364 | E35: =EEFF!E35 -> 551482 | F35: =EEFF!F35 -> 497274 | G35: =F35 -> 497274 | H35: =G35 -> 497274 | I35: =H35 -> 497274 | J35: =I35 -> 497274 | K35: =J35 -> 497274
A36: Total de activos circulantes | B36: =EEFF!B36 -> 23585133 | C36: =EEFF!C36 -> 27656127 | D36: =EEFF!D36 -> 26443110 | E36: =EEFF!E36 -> 24685303 | F36: =EEFF!F36 -> 31660678 | G36: =SUM(G29:G35) -> 38217681 | H36: =SUM(H29:H35) -> 38549858 | I36: =SUM(I29:I35) -> 42884057 | J36: =SUM(J29:J35) -> 47487403 | K36: =SUM(K29:K35) -> 47568780
A37: Activo financiero restringido | B37: =EEFF!B37 -> 4206485 | C37: =EEFF!C37 -> 4234822 | D37: =EEFF!D37 -> 4033700 | E37: =EEFF!E37 -> 4197349 | F37: =EEFF!F37 -> 4260349 | G37: =F37 -> 4260349 | H37: =G37 -> 4260349 | I37: =H37 -> 4260349 | J37: =I37 -> 4260349 | K37: =J37 -> 4260349
A38: Cuentas por cobrar, no circulante | B38: =EEFF!B38 -> 213118 | C38: =EEFF!C38 -> 0 | D38: =EEFF!D38 -> 0 | E38: =EEFF!E38 -> 0 | F38: =EEFF!F38 -> 0
A39: Propiedad, planta y equipo, neto | B39: =EEFF!B39 -> 289872297 | C39: =EEFF!C39 -> 280225020 | D39: =EEFF!D39 -> 278143135 | E39: =EEFF!E39 -> 266144886 | F39: =EEFF!F39 -> 254111593 | G39: =F39-G96-G12 -> 242032041 | H39: =G39-H96-H12 -> 229952489 | I39: =H39-I96-I12 -> 217872937 | J39: =I39-J96-J12 -> 205793385 | K39: =J39-K96-K12 -> 193713833
A40: Plusvalía | B40: =EEFF!B40 -> 7033750 | C40: =EEFF!C40 -> 7033750 | D40: =EEFF!D40 -> 7033750 | E40: =EEFF!E40 -> 7033750 | F40: =EEFF!F40 -> 7033750 | G40: =F40 -> 7033750 | H40: =G40 -> 7033750 | I40: =H40 -> 7033750 | J40: =I40 -> 7033750 | K40: =J40 -> 7033750
A41: Costos de exploración y evaluación | B41: =EEFF!B41 -> 173084 | C41: =EEFF!C41 -> 174084 | D41: =EEFF!D41 -> 0 | E41: =EEFF!E41 -> 0 | F41: =EEFF!F41 -> 0
A42: Activos intangibles, neto | B42: =EEFF!B42 -> 538918 | C42: =EEFF!C42 -> 525826 | D42: =EEFF!D42 -> 512733 | E42: =EEFF!E42 -> 499640 | F42: =EEFF!F42 -> 509989 | G42: =F42 -> 509989 | H42: =G42 -> 509989 | I42: =H42 -> 509989 | J42: =I42 -> 509989 | K42: =J42 -> 509989
A43: Activos por derechos de uso | B43: =EEFF!B43 -> 142658 | C43: =EEFF!C43 -> 101898 | D43: =EEFF!D43 -> 69290 | E43: =EEFF!E43 -> 36682 | F43: =EEFF!F43 -> 4074 | G43: =F43 -> 4074 | H43: =G43 -> 4074 | I43: =H43 -> 4074 | J43: =I43 -> 4074 | K43: =J43 -> 4074
A44: Impuesto sobre la renta diferido | B44: =EEFF!B44 -> 193382 | C44: =EEFF!C44 -> 140101 | D44: =EEFF!D44 -> 86820 | E44: =EEFF!E44 -> 0 | F44: =EEFF!F44 -> 0
A45: Crédito fiscal por inversión, no circulante | B45: =EEFF!B45 -> 1863452 | C45: =EEFF!C45 -> 1321139 | D45: =EEFF!D45 -> 238792 | E45: =EEFF!E45 -> 0 | F45: =EEFF!F45 -> 0
A46: Otros activos, no circulante | B46: =EEFF!B46 -> 209800 | C46: =EEFF!C46 -> 227497 | D46: =EEFF!D46 -> 242970 | E46: =EEFF!E46 -> 276061 | F46: =EEFF!F46 -> 284646 | G46: =F46 -> 284646 | H46: =G46 -> 284646 | I46: =H46 -> 284646 | J46: =I46 -> 284646 | K46: =J46 -> 284646
A47: Total de activos no circulantes | B47: =EEFF!B47 -> 304446944 | C47: =EEFF!C47 -> 293984137 | D47: =EEFF!D47 -> 290361190 | E47: =EEFF!E47 -> 278188368 | F47: =EEFF!F47 -> 266204401 | G47: =SUM(G37:G46) -> 254124849 | H47: =SUM(H37:H46) -> 242045297 | I47: =SUM(I37:I46) -> 229965745 | J47: =SUM(J37:J46) -> 217886193 | K47: =SUM(K37:K46) -> 205806641
A48: Total de activos | B48: =EEFF!B48 -> 328032077 | C48: =EEFF!C48 -> 321640264 | D48: =EEFF!D48 -> 316804300 | E48: =EEFF!E48 -> 302873671 | F48: =EEFF!F48 -> 297865079 | G48: =G36+G47 -> 2.9234253e+08 | H48: =H36+H47 -> 2.8059515e+08 | I48: =I36+I47 -> 2.728498e+08 | J48: =J36+J47 -> 2.653736e+08 | K48: =K36+K47 -> 2.5337542e+08
A49: Cuentas por pagar | B49: =EEFF!B49 -> 3817823 | C49: =EEFF!C49 -> 1649350 | D49: =EEFF!D49 -> 1515059 | E49: =EEFF!E49 -> 614193 | F49: =EEFF!F49 -> 1148554 | G49: =F49 -> 1148554 | H49: =G49 -> 1148554 | I49: =H49 -> 1148554 | J49: =I49 -> 1148554 | K49: =J49 -> 1148554
A50: Bonos por pagar | B50: =EEFF!B50 -> 8791215 | C50: =EEFF!C50 -> 8791215 | D50: =EEFF!D50 -> 12541215 | E50: =EEFF!E50 -> 8791215 | F50: =EEFF!F50 -> 8791215 | G50: =F50 -> 8791215 | H50: =G50 -> 8791215 | I50: =H50 -> 8791215 | J50: =I50 -> 8791215 | K50: =J50 -> 8791215
A51: Intereses de bonos por pagar | B51: =EEFF!B51 -> 0 | C51: =EEFF!C51 -> 26611 | D51: =EEFF!D51 -> 2297125 | E51: =EEFF!E51 -> 22920 | F51: =EEFF!F51 -> 21419 | G51: =F51 -> 21419 | H51: =G51 -> 21419 | I51: =H51 -> 21419 | J51: =I51 -> 21419 | K51: =J51 -> 21419
A52: Préstamos por pagar | B52: =EEFF!B52 -> 0 | C52: =EEFF!C52 -> 758413 | D52: =EEFF!D52 -> 418472 | E52: =EEFF!E52 -> 67845 | F52: =EEFF!F52 -> 215241 | G52: =F52 -> 215241 | H52: =G52 -> 215241 | I52: =H52 -> 215241 | J52: =I52 -> 215241 | K52: =J52 -> 215241
A53: Ingreso diferido por crédito fiscal por inversión | B53: =EEFF!B53 -> 1825438 | C53: =EEFF!C53 -> 2648365 | D53: =EEFF!D53 -> 1541175 | E53: =EEFF!E53 -> 1829780 | F53: =EEFF!F53 -> 0 | G53: =F53 -> 0 | H53: =G53 -> 0 | I53: =H53 -> 0 | J53: =I53 -> 0 | K53: =J53 -> 0
A54: Impuesto sobre la renta por pagar | B54: =EEFF!B54 -> 1255449 | C54: =EEFF!C54 -> 2384922 | D54: =EEFF!D54 -> 30637 | E54: =EEFF!E54 -> 1883666 | F54: =EEFF!F54 -> 181645 | G54: =F54 -> 181645 | H54: =G54 -> 181645 | I54: =H54 -> 181645 | J54: =I54 -> 181645 | K54: =J54 -> 181645
A55: Pasivos por arrendamientos | B55: =EEFF!B55 -> 32604 | C55: =EEFF!C55 -> 32604 | D55: =EEFF!D55 -> 32604 | E55: =EEFF!E55 -> 32604 | F55: =EEFF!F55 -> 4074 | G55: =F55 -> 4074 | H55: =G55 -> 4074 | I55: =H55 -> 4074 | J55: =I55 -> 4074 | K55: =J55 -> 4074
A56: Otros pasivos | B56: =EEFF!B56 -> 1522447 | C56: =EEFF!C56 -> 1534472 | D56: =EEFF!D56 -> 1223799 | E56: =EEFF!E56 -> 1101389 | F56: =EEFF!F56 -> 1330438 | G56: =F56 -> 1330438 | H56: =G56 -> 1330438 | I56: =H56 -> 1330438 | J56: =I56 -> 1330438 | K56: =J56 -> 1330438
A57: Total de pasivos circulantes | B57: =EEFF!B57 -> 17244976 | C57: =EEFF!C57 -> 17825952 | D57: =EEFF!D57 -> 19600086 | E57: =EEFF!E57 -> 14343612 | F57: =EEFF!F57 -> 11692586 | G57: =SUM(G49:G56) -> 11692586 | H57: =SUM(H49:H56) -> 11692586 | I57: =SUM(I49:I56) -> 11692586 | J57: =SUM(J49:J56) -> 11692586 | K57: =SUM(K49:K56) -> 11692586
A58: Bonos por pagar, neto | B58: =EEFF!B58 -> 156615714 | C58: =EEFF!C58 -> 147824500 | D58: =EEFF!D58 -> 139033286 | E58: =EEFF!E58 -> 130242072 | F58: =EEFF!F58 -> 121450858 | G58: =F58-(9000000-Debt_Schedule!G16) -> 112659644 | H58: =G58-(9000000-Debt_Schedule!H16) -> 103868430 | I58: =H58-(9000000-Debt_Schedule!I16) -> 95077216 | J58: =I58-(9000000-Debt_Schedule!J16) -> 86286002 | K58: =J58-(9000000-Debt_Schedule!K16) -> 77458785
A59: Préstamos por pagar, no circulante | B59: =EEFF!B59 -> 0 | C59: =EEFF!C59 -> 0 | D59: =EEFF!D59 -> 3503256 | E59: =EEFF!E59 -> 2679481 | F59: =EEFF!F59 -> 2275211 | G59: =F59 -> 2275211 | H59: =G59 -> 2275211 | I59: =H59 -> 2275211 | J59: =I59 -> 2275211 | K59: =J59 -> 2275211
A60: Ingreso diferido por crédito fiscal en inversión | B60: =EEFF!B60 -> 1863452 | C60: =EEFF!C60 -> 1321139 | D60: =EEFF!D60 -> 238792 | E60: =EEFF!E60 -> 0 | F60: =EEFF!F60 -> 0
A61: Pasivos por arrendamientos, no circulante | B61: =EEFF!B61 -> 110054 | C61: =EEFF!C61 -> 69294 | D61: =EEFF!D61 -> 36686 | E61: =EEFF!E61 -> 4078 | F61: =EEFF!F61 -> 0 | G61: =F61 -> 0 | H61: =G61 -> 0 | I61: =H61 -> 0 | J61: =I61 -> 0 | K61: =J61 -> 0
A62: Otros pasivos, no circulante | B62: =EEFF!B62 -> 204886 | C62: =EEFF!C62 -> 218261 | D62: =EEFF!D62 -> 242828 | E62: =EEFF!E62 -> 261536 | F62: =EEFF!F62 -> 289022 | G62: =F62 -> 289022 | H62: =G62 -> 289022 | I62: =H62 -> 289022 | J62: =I62 -> 289022 | K62: =J62 -> 289022
A63: Total de pasivos no circulantes | B63: =EEFF!B63 -> 158794106 | C63: =EEFF!C63 -> 149433194 | D63: =EEFF!D63 -> 143054848 | E63: =EEFF!E63 -> 133187167 | F63: =EEFF!F63 -> 124015091 | G63: =SUM(G58:G62) -> 115223877 | H63: =SUM(H58:H62) -> 106432663 | I63: =SUM(I58:I62) -> 97641449 | J63: =SUM(J58:J62) -> 88850235 | K63: =SUM(K58:K62) -> 80023018
A64: Total de pasivos | B64: =EEFF!B64 -> 176039082 | C64: =EEFF!C64 -> 167259146 | D64: =EEFF!D64 -> 162654934 | E64: =EEFF!E64 -> 147530779 | F64: =EEFF!F64 -> 135707677 | G64: =G57+G63 -> 126916463 | H64: =H57+H63 -> 118125249 | I64: =I57+I63 -> 109334035 | J64: =J57+J63 -> 100542821 | K64: =K57+K63 -> 91715604
A65: Acciones comunes | B65: =EEFF!B65 -> 16575011 | C65: =EEFF!C65 -> 16575011 | D65: =EEFF!D65 -> 16575011 | E65: =EEFF!E65 -> 16575011 | F65: =EEFF!F65 -> 16575011 | G65: =F65 -> 16575011 | H65: =G65 -> 16575011 | I65: =H65 -> 16575011 | J65: =I65 -> 16575011 | K65: =J65 -> 16575011
A66: Acciones preferidas | B66: =EEFF!B66 -> 5000 | C66: =EEFF!C66 -> 5000 | D66: =EEFF!D66 -> 5000 | E66: =EEFF!E66 -> 5000 | F66: =EEFF!F66 -> 5000 | G66: =F66 -> 5000 | H66: =G66 -> 5000 | I66: =H66 -> 5000 | J66: =I66 -> 5000 | K66: =J66 -> 5000
A67: Excedente en valor de suscripción de acciones comunes | B67: =EEFF!B67 -> 144564461 | C67: =EEFF!C67 -> 133624953 | D67: =EEFF!D67 -> 126166198 | E67: =EEFF!E67 -> 117878693 | F67: =EEFF!F67 -> 115392441 | G67: =F67 -> 115392441 | H67: =G67 -> 115392441 | I67: =H67 -> 115392441 | J67: =I67 -> 115392441 | K67: =J67 -> 115392441
A68: Impuesto complementario | B68: =EEFF!B68 -> -1349935 | C68: =EEFF!C68 -> -1685225 | D68: =EEFF!D68 -> -1685225 | E68: =EEFF!E68 -> -1685427 | F68: =EEFF!F68 -> -1685469 | G68: =F68 -> -1685469 | H68: =G68 -> -1685469 | I68: =H68 -> -1685469 | J68: =I68 -> -1685469 | K68: =J68 -> -1685469
A69: Utilidades no distribuidas | B69: =EEFF!B69 -> -7801542 | C69: =EEFF!C69 -> 5861379 | D69: =EEFF!D69 -> 13088382 | E69: =EEFF!E69 -> 22569615 | F69: =EEFF!F69 -> 31870419 | G69: =F69+G25 -> 35139084 | H69: =G69+H25 -> 32182923 | I69: =H69+I25 -> 33228784 | J69: =I69+J25 -> 34543792 | K69: =J69+K25 -> 31372834
A70: Total de patrimonio | B70: =EEFF!B70 -> 151992995 | C70: =EEFF!C70 -> 154381118 | D70: =EEFF!D70 -> 154149366 | E70: =EEFF!E70 -> 155342892 | F70: =EEFF!F70 -> 162157402 | G70: =SUM(G65:G69) -> 1.6542607e+08 | H70: =SUM(H65:H69) -> 1.6246991e+08 | I70: =SUM(I65:I69) -> 1.6351577e+08 | J70: =SUM(J65:J69) -> 1.6483077e+08 | K70: =SUM(K65:K69) -> 1.6165982e+08
A71: Total de pasivos y patrimonio | B71: =EEFF!B71 -> 328032077 | C71: =EEFF!C71 -> 321640264 | D71: =EEFF!D71 -> 316804300 | E71: =EEFF!E71 -> 302873671 | F71: =EEFF!F71 -> 297865079 | G71: =G64+G70 -> 2.9234253e+08 | H71: =H64+H70 -> 2.8059515e+08 | I71: =I64+I70 -> 2.728498e+08 | J71: =J64+J70 -> 2.653736e+08 | K71: =K64+K70 -> 2.5337542e+08
A73: Años | B73: FY21A | C73: FY22A | D73: FY23A | E73: FY24A | F73: FY25A | G73: FY26E | H73: FY27E | I73: FY28E | J73: FY29E | K73: FY30E
A74: Estado de Flujos de Efectivo
A75: Utilidad antes de impuesto sobre la renta | B75: =EEFF!B75 -> 8230666 | C75: =EEFF!C75 -> 19005909 | D75: =EEFF!D75 -> 11177428 | E75: =EEFF!E75 -> 14098618 | F75: =EEFF!F75 -> 14188102 | G75: =G23 -> 4986521.8 | H75: =H23 -> -4509780.2 | I75: =I23 -> 1595517 | J75: =J23 -> 2006114.2 | K75: =K23 -> -4837464.6
A76: Depreciación | B76: =EEFF!B76 -> 11837322 | C76: =EEFF!C76 -> 11835933 | D76: =EEFF!D76 -> 11948074 | E76: =EEFF!E76 -> 12401168 | F76: =EEFF!F76 -> 12475149 | G76: =G12 -> 12521408 | H76: =H12 -> 12521408 | I76: =I12 -> 12521408 | J76: =J12 -> 12521408 | K76: =K12 -> 12521408
A77: Retiro de activo fijo | B77: =EEFF!B77 -> 0 | C77: =EEFF!C77 -> 105000 | D77: =EEFF!D77 -> 0 | E77: =EEFF!E77 -> 0 | F77: =EEFF!F77 -> 0
A78: Amortización de intangibles | B78: =EEFF!B78 -> 13719 | C78: =EEFF!C78 -> 13092 | D78: =EEFF!D78 -> 13093 | E78: =EEFF!E78 -> 13093 | F78: =EEFF!F78 -> 13651
A79: Depreciación de derechos de uso | B79: =EEFF!B79 -> 27410 | C79: =EEFF!C79 -> 32608 | D79: =EEFF!D79 -> 36116 | E79: =EEFF!E79 -> 32608 | F79: =EEFF!F79 -> 32608
A80: Amortización de costos de financiamiento diferidos | B80: =EEFF!B80 -> 210785 | C80: =EEFF!C80 -> 208786 | D80: =EEFF!D80 -> 208786 | E80: =EEFF!E80 -> 208786 | F80: =EEFF!F80 -> 208786 | G80: =Debt_Schedule!G16 -> 208786 | H80: =Debt_Schedule!H16 -> 208786 | I80: =Debt_Schedule!I16 -> 208786 | J80: =Debt_Schedule!J16 -> 208786 | K80: =Debt_Schedule!K16 -> 172783
A81: Gastos de intereses | B81: =EEFF!B81 -> 10348312 | C81: =EEFF!C81 -> 9766628 | D81: =EEFF!D81 -> 9267884 | E81: =EEFF!E81 -> 8906765 | F81: =EEFF!F81 -> 8323100
A82: Pérdida en activos no financieros | B82: =EEFF!B82 -> 20000 | C82: =EEFF!C82 -> 0 | D82: =EEFF!D82 -> 0 | E82: =EEFF!E82 -> 0 | F82: =EEFF!F82 -> 0
A83: Ingresos por crédito fiscal | B83: =EEFF!B83 -> -757608 | C83: =EEFF!C83 -> -1930197 | D83: =EEFF!D83 -> -1653193 | E83: =EEFF!E83 -> -600000 | F83: =EEFF!F83 -> -1829780
A84: Cuentas por cobrar | B84: =EEFF!B84 -> -616516 | C84: =EEFF!C84 -> -473324 | D84: =EEFF!D84 -> -34354 | E84: =EEFF!E84 -> 496506 | F84: =EEFF!F84 -> 1415662
A85: Inventario de repuestos y suministros | B85: =EEFF!B85 -> -6659 | C85: =EEFF!C85 -> -328917 | D85: =EEFF!D85 -> 107433 | E85: =EEFF!E85 -> -139226 | F85: =EEFF!F85 -> -350810
A86: Gastos pagados por adelantado | B86: =EEFF!B86 -> 468120 | C86: =EEFF!C86 -> 4885169 | D86: =EEFF!D86 -> 2721902 | E86: =EEFF!E86 -> 1730438 | F86: =EEFF!F86 -> 4196213
A87: Otros activos | B87: =EEFF!B87 -> 88309 | C87: =EEFF!C87 -> -479342 | D87: =EEFF!D87 -> 589865 | E87: =EEFF!E87 -> -159744 | F87: =EEFF!F87 -> 46908
A88: Cuentas por pagar | B88: =EEFF!B88 -> 1281734 | C88: =EEFF!C88 -> -7113790 | D88: =EEFF!D88 -> -3693608 | E88: =EEFF!E88 -> -2897310 | F88: =EEFF!F88 -> -4225876
A89: Otros pasivos | B89: =EEFF!B89 -> 46812 | C89: =EEFF!C89 -> 25400 | D89: =EEFF!D89 -> -286106 | E89: =EEFF!E89 -> -103702 | F89: =EEFF!F89 -> 256535
A90: Intereses pagados | B90: =EEFF!B90 -> -10341713 | C90: =EEFF!C90 -> -9775991 | D90: =EEFF!D90 -> -6997370 | E90: =EEFF!E90 -> -11176527 | F90: =EEFF!F90 -> -8325188
A91: Impuesto sobre la renta pagado | B91: =EEFF!B91 -> -891774 | C91: =EEFF!C91 -> -2116783 | D91: =EEFF!D91 -> -4992852 | E91: =EEFF!E91 -> -805658 | F91: =EEFF!F91 -> -4557314 | G91: =G24 -> -1717857 | H91: =H24 -> 1553619 | I91: =I24 -> -549656 | J91: =J24 -> -691106 | K91: =K24 -> 1666507
A92: Efectivo neto provisto por las actividades de operación | B92: =EEFF!B92 -> 19958919 | C92: =EEFF!C92 -> 23660181 | D92: =EEFF!D92 -> 18413098 | E92: =EEFF!E92 -> 22005815 | F92: =EEFF!F92 -> 21867746 | G92: =SUM(G75:G91) -> 15998859 | H92: =SUM(H75:H91) -> 9774032.8 | I92: =SUM(I75:I91) -> 13776055 | J92: =SUM(J75:J91) -> 14045202 | K92: =SUM(K75:K91) -> 9523233.4
A93: Depósito a plazo con vencimiento original mayor a tres meses | B93: =EEFF!B93 -> 0 | C93: =EEFF!C93 -> 0 | D93: =EEFF!D93 -> 0 | E93: =EEFF!E93 -> 0 | F93: =EEFF!F93 -> -8000000
A94: Costo de evaluación y exploración | B94: =EEFF!B94 -> 0 | C94: =EEFF!C94 -> -1000 | D94: =EEFF!D94 -> 174084 | E94: =EEFF!E94 -> 0 | F94: =EEFF!F94 -> 0
A95: Adquisición de activos intangibles | B95: =EEFF!B95 -> 0 | C95: =EEFF!C95 -> 0 | D95: =EEFF!D95 -> 0 | E95: =EEFF!E95 -> 0 | F95: =EEFF!F95 -> -24000
A96: Adiciones de propiedad, planta y equipo | B96: =EEFF!B96 -> -140606 | C96: =EEFF!C96 -> -2293656 | D96: =EEFF!D96 -> -9866189 | E96: =EEFF!E96 -> -402919 | F96: =EEFF!F96 -> -441856 | G96: =F96 -> -441856 | H96: =G96 -> -441856 | I96: =H96 -> -441856 | J96: =I96 -> -441856 | K96: =J96 -> -441856
A97: Adquisición de activos por derecho de uso | B97: =EEFF!B97 -> -77042 | C97: =EEFF!C97 -> 0 | D97: =EEFF!D97 -> 0 | E97: =EEFF!E97 -> 0 | F97: =EEFF!F97 -> 0
A98: Efectivo neto utilizado en las actividades de inversión | B98: =EEFF!B98 -> -217648 | C98: =EEFF!C98 -> -2294656 | D98: =EEFF!D98 -> -9692105 | E98: =EEFF!E98 -> -402919 | F98: =EEFF!F98 -> -8465856 | G98: =SUM(G93:G97) -> -441856 | H98: =SUM(H93:H97) -> -441856 | I98: =SUM(I93:I97) -> -441856 | J98: =SUM(J93:J97) -> -441856 | K98: =SUM(K93:K97) -> -441856
A99: Producto de préstamos | B99: =EEFF!B99 -> 0 | C99: =EEFF!C99 -> 758413 | D99: =EEFF!D99 -> 3163315 | E99: =EEFF!E99 -> 0 | F99: =EEFF!F99 -> 0
A100: Pagos de préstamos | B100: =EEFF!B100 -> 0 | C100: =EEFF!C100 -> 0 | D100: =EEFF!D100 -> 0 | E100: =EEFF!E100 -> -1174402 | F100: =EEFF!F100 -> -256874
A101: Pagos de bonos | B101: =EEFF!B101 -> -9000000 | C101: =EEFF!C101 -> -9000000 | D101: =EEFF!D101 -> -5250000 | E101: =EEFF!E101 -> -12750000 | F101: =EEFF!F101 -> -9000000 | G101: =-(Debt_Schedule!G9+Debt_Schedule!G10) -> -9000000 | H101: =-(Debt_Schedule!H9+Debt_Schedule!H10) -> -9000000 | I101: =-(Debt_Schedule!I9+Debt_Schedule!I10) -> -9000000 | J101: =-(Debt_Schedule!J9+Debt_Schedule!J10) -> -9000000 | K101: =-(Debt_Schedule!K9+Debt_Schedule!K10) -> -9000000
A102: Activo financiero restringido | B102: =EEFF!B102 -> 130811 | C102: =EEFF!C102 -> -28337 | D102: =EEFF!D102 -> 201122 | E102: =EEFF!E102 -> -163649 | F102: =EEFF!F102 -> -63000
A103: Costo de financiamiento diferido | B103: =EEFF!B103 -> -14910 | C103: =EEFF!C103 -> 0 | D103: =EEFF!D103 -> 0 | E103: =EEFF!E103 -> 0 | F103: =EEFF!F103 -> 0
...

Sheet Generation_PPA
A1: Panama Power Holdings, Inc. y Subsidiarias
A2: Generation_PPA - source-visible MW/MWh, price, and revenue bridge
A3: en B/. sin escala
A4: Filing facts only; use NOT_DISCLOSED where notes/MD&A are silent
A5: Anios | B5: FY21A | C5: FY22A | D5: FY23A | E5: FY24A | F5: FY25A | G5: FY26E | H5: FY27E | I5: FY28E | J5: FY29E | K5: FY30E
A7: A. Capacity and generation (MW -> MWh)
A8: Capacity MW - El Alto | F8: 73.18 | G8: 73.18 | H8: 73.18 | I8: 73.18 | J8: 73.18 | K8: 73.18
A9: Capacity MW - Pedregalito 1 | F9: 20.1 | G9: 20.1 | H9: 20.1 | I9: 20.1 | J9: 20.1 | K9: 20.1
A10: Capacity MW - Pedregalito 2 | F10: 12.5 | G10: 12.5 | H10: 12.5 | I10: 12.5 | J10: 12.5 | K10: 12.5
A11: Capacity MW - Cochea | F11: 15.5 | G11: 15.5 | H11: 15.5 | I11: 15.5 | J11: 15.5 | K11: 15.5
A12: Capacity MW - Mini Central El Alto | F12: 0.98 | G12: 0.98 | H12: 0.98 | I12: 0.98 | J12: 0.98 | K12: 0.98
A13: Capacity MW - Pedregalito Solar | F13: 9.9 | G13: 9.9 | H13: 9.9 | I13: 9.9 | J13: 9.9 | K13: 9.9
A14: Total visible capacity (MW) | F14: =F8+F9+F10+F11+F12+F13 -> 132.16 | G14: =G8+G9+G10+G11+G12+G13 -> 132.16 | H14: =H8+H9+H10+H11+H12+H13 -> 132.16 | I14: =I8+I9+I10+I11+I12+I13 -> 132.16 | J14: =J8+J9+J10+J11+J12+J13 -> 132.16 | K14: =K8+K9+K10+K11+K12+K13 -> 132.16
A17: NOT_DISCLOSED: disponibilidad (AVF) no divulgada en el filing — el CF neto ya la embebe.
A18: Plant factor / net CF - active | B18: NOT_DISCLOSED | C18: NOT_DISCLOSED | D18: 0.35 | E18: 0.465 | F18: 0.407 | G18: =G20 -> 0.41 | H18: =H20 -> 0.41 | I18: =I20 -> 0.41 | J18: =J20 -> 0.41 | K18: =K20 -> 0.41
A19: Bear | G19: 0.35 | H19: 0.35 | I19: 0.35 | J19: 0.35 | K19: 0.35
A20: Base | G20: 0.41 | H20: 0.41 | I20: 0.41 | J20: 0.41 | K20: 0.41
A21: Bull | G21: 0.46 | H21: 0.46 | I21: 0.46 | J21: 0.46 | K21: 0.46
A22: Hours per year | G22: 8760 | H22: 8760 | I22: 8760 | J22: 8760 | K22: 8760
A23: Generation MWh - El Alto | B23: NOT_DISCLOSED | C23: NOT_DISCLOSED | D23: NOT_DISCLOSED | E23: NOT_DISCLOSED | F23: NOT_DISCLOSED | G23: =G8*G22*G18 -> 262833.29 | H23: =H8*H22*H18 -> 262833.29 | I23: =I8*I22*I18 -> 262833.29 | J23: =J8*J22*J18 -> 262833.29 | K23: =K8*K22*K18 -> 262833.29
A24: Generation MWh - Pedregalito 1 | B24: NOT_DISCLOSED | C24: NOT_DISCLOSED | D24: NOT_DISCLOSED | E24: NOT_DISCLOSED | F24: NOT_DISCLOSED | G24: =G9*G22*G18 -> 72191.16 | H24: =H9*H22*H18 -> 72191.16 | I24: =I9*I22*I18 -> 72191.16 | J24: =J9*J22*J18 -> 72191.16 | K24: =K9*K22*K18 -> 72191.16
A25: Generation MWh - Pedregalito 2 | B25: NOT_DISCLOSED | C25: NOT_DISCLOSED | D25: NOT_DISCLOSED | E25: NOT_DISCLOSED | F25: NOT_DISCLOSED | G25: =G10*G22*G18 -> 44895 | H25: =H10*H22*H18 -> 44895 | I25: =I10*I22*I18 -> 44895 | J25: =J10*J22*J18 -> 44895 | K25: =K10*K22*K18 -> 44895
A26: Generation MWh - Cochea | B26: NOT_DISCLOSED | C26: NOT_DISCLOSED | D26: NOT_DISCLOSED | E26: NOT_DISCLOSED | F26: NOT_DISCLOSED | G26: =G11*G22*G18 -> 55669.8 | H26: =H11*H22*H18 -> 55669.8 | I26: =I11*I22*I18 -> 55669.8 | J26: =J11*J22*J18 -> 55669.8 | K26: =K11*K22*K18 -> 55669.8
A27: Generation MWh - Mini Central El Alto | B27: NOT_DISCLOSED | C27: NOT_DISCLOSED | D27: NOT_DISCLOSED | E27: NOT_DISCLOSED | F27: NOT_DISCLOSED | G27: =G12*G22*G18 -> 3519.768 | H27: =H12*H22*H18 -> 3519.768 | I27: =I12*I22*I18 -> 3519.768 | J27: =J12*J22*J18 -> 3519.768 | K27: =K12*K22*K18 -> 3519.768
A28: Generation MWh - Pedregalito Solar | B28: NOT_DISCLOSED | C28: NOT_DISCLOSED | D28: NOT_DISCLOSED | E28: NOT_DISCLOSED | F28: NOT_DISCLOSED | G28: =G13*G22*G18 -> 35556.84 | H28: =H13*H22*H18 -> 35556.84 | I28: =I13*I22*I18 -> 35556.84 | J28: =J13*J22*J18 -> 35556.84 | K28: =K13*K22*K18 -> 35556.84
A29: Historical generation MWh from filing | B29: NOT_DISCLOSED | C29: NOT_DISCLOSED | D29: 374482 | E29: 497784 | F29: 470665 | G29: NOT_DISCLOSED | H29: NOT_DISCLOSED | I29: NOT_DISCLOSED | J29: NOT_DISCLOSED | K29: NOT_DISCLOSED
A30: Total generation MWh | B30: NOT_DISCLOSED | C30: NOT_DISCLOSED | D30: 374482 | E30: 497784 | F30: 470665 | G30: =G23+G24+G25+G26+G27+G28 -> 474665.86 | H30: =H23+H24+H25+H26+H27+H28 -> 474665.86 | I30: =I23+I24+I25+I26+I27+I28 -> 474665.86 | J30: =J23+J24+J25+J26+J27+J28 -> 474665.86 | K30: =K23+K24+K25+K26+K27+K28 -> 474665.86
A32: A2. CND per-plant physical layer (MW x CF x 8.760 -> GWh, tied to CND)
A33: Source: CND generacion_YYYY.xlsx (hoja Generacion, fila 19 TOTAL, col GENPED/RCHICO/ALTOVALLE/HCAISAN/PEDREGALITO SOLAR POWER) + sector research note + maintainer research note
A34: Historical FY21-25 only (blue literals, cited); forecast columns explicit NOT_DISCLOSED — per-plant CND forecast wiring is Tasks 2-4.
A35: Pedregalito 1 (GENPED) - MW (CND/ASEP) | B35: 20.089 | C35: 20.089 | D35: 20.089 | E35: 20.089 | F35: 20.089 | G35: 20.089 | H35: 20.089 | I35: 20.089 | J35: 20.089 | K35: 20.089
A36: Pedregalito 1 (GENPED) - GWh (CND actual) | B36: 74.031 | C36: 94.227 | D36: 63.029 | E36: 80.932 | F36: 74.984 | G36: NOT_DISCLOSED | H36: NOT_DISCLOSED | I36: NOT_DISCLOSED | J36: NOT_DISCLOSED | K36: NOT_DISCLOSED
A37: Pedregalito 1 (GENPED) - CF literal (GWh/(MW*8.76)) | B37: =IF(AND(ISNUMBER(B36),ISNUMBER(B35)),B36/(B35*8.76),"") -> 0.42067935 | C37: =IF(AND(ISNUMBER(C36),ISNUMBER(C35)),C36/(C35*8.76),"") -> 0.53544262 | D37: =IF(AND(ISNUMBER(D36),ISNUMBER(D35)),D36/(D35*8.76),"") -> 0.35816075 | E37: =IF(AND(ISNUMBER(E36),ISNUMBER(E35)),E36/(E35*8.76),"") -> 0.45989411 | F37: =IF(AND(ISNUMBER(F36),ISNUMBER(F35)),F36/(F35*8.76),"") -> 0.42609475 | G37: =IF(AND(ISNUMBER(G36),ISNUMBER(G35)),G36/(G35*8.76),"") | H37: =IF(AND(ISNUMBER(H36),ISNUMBER(H35)),H36/(H35*8.76),"") | I37: =IF(AND(ISNUMBER(I36),ISNUMBER(I35)),I36/(I35*8.76),"") | ... K37: =IF(AND(ISNUMBER(K36),ISNUMBER(K35)),K36/(K35*8.76),"")
A38: Note: Discrepancia §7.1 (data-foundation, NO resuelta): MW=20.089 ASEP (adoptado) vs 19.9 MW en el registro de concesiones .csv; una versión previa usaba 20.1.
A39: Pedregalito 2 (RCHICO) - MW (CND/ASEP) | B39: 12.52 | C39: 12.52 | D39: 12.52 | E39: 12.52 | F39: 12.52 | G39: 12.52 | H39: 12.52 | I39: 12.52 | J39: 12.52 | K39: 12.52
A40: Pedregalito 2 (RCHICO) - GWh (CND actual) | B40: 47.312 | C40: 59.896 | D40: 39.863 | E40: 51.05 | F40: 48.083 | G40: NOT_DISCLOSED | H40: NOT_DISCLOSED | I40: NOT_DISCLOSED | J40: NOT_DISCLOSED | K40: NOT_DISCLOSED
A41: Pedregalito 2 (RCHICO) - CF literal (GWh/(MW*8.76)) | B41: =IF(AND(ISNUMBER(B40),ISNUMBER(B39)),B40/(B39*8.76),"") -> 0.43138285 | C41: =IF(AND(ISNUMBER(C40),ISNUMBER(C39)),C40/(C39*8.76),"") -> 0.54612164 | D41: =IF(AND(ISNUMBER(D40),ISNUMBER(D39)),D40/(D39*8.76),"") -> 0.36346412 | E41: =IF(AND(ISNUMBER(E40),ISNUMBER(E39)),E40/(E39*8.76),"") -> 0.4654653 | F41: =IF(AND(ISNUMBER(F40),ISNUMBER(F39)),F40/(F39*8.76),"") -> 0.43841269 | G41: =IF(AND(ISNUMBER(G40),ISNUMBER(G39)),G40/(G39*8.76),"") | H41: =IF(AND(ISNUMBER(H40),ISNUMBER(H39)),H40/(H39*8.76),"") | I41: =IF(AND(ISNUMBER(I40),ISNUMBER(I39)),I40/(I39*8.76),"") | ... K41: =IF(AND(ISNUMBER(K40),ISNUMBER(K39)),K40/(K39*8.76),"")
A42: Cochea (ALTOVALLE) - MW (CND/ASEP) | B42: 15.5 | C42: 15.5 | D42: 15.5 | E42: 15.5 | F42: 15.5 | G42: 15.5 | H42: 15.5 | I42: 15.5 | J42: 15.5 | K42: 15.5
A43: Cochea (ALTOVALLE) - GWh (CND actual) | B43: 54.274 | C43: 78.092 | D43: 54.207 | E43: 69.298 | F43: 64.129 | G43: NOT_DISCLOSED | H43: NOT_DISCLOSED | I43: NOT_DISCLOSED | J43: NOT_DISCLOSED | K43: NOT_DISCLOSED
A44: Cochea (ALTOVALLE) - CF literal (GWh/(MW*8.76)) | B44: =IF(AND(ISNUMBER(B43),ISNUMBER(B42)),B43/(B42*8.76),"") -> 0.39972014 | C44: =IF(AND(ISNUMBER(C43),ISNUMBER(C42)),C43/(C42*8.76),"") -> 0.57513625 | D44: =IF(AND(ISNUMBER(D43),ISNUMBER(D42)),D43/(D42*8.76),"") -> 0.39922669 | E44: =IF(AND(ISNUMBER(E43),ISNUMBER(E42)),E43/(E42*8.76),"") -> 0.51036972 | F44: =IF(AND(ISNUMBER(F43),ISNUMBER(F42)),F43/(F42*8.76),"") -> 0.47230078 | G44: =IF(AND(ISNUMBER(G43),ISNUMBER(G42)),G43/(G42*8.76),"") | H44: =IF(AND(ISNUMBER(H43),ISNUMBER(H42)),H43/(H42*8.76),"") | I44: =IF(AND(ISNUMBER(I43),ISNUMBER(I42)),I43/(I42*8.76),"") | ... K44: =IF(AND(ISNUMBER(K43),ISNUMBER(K42)),K43/(K42*8.76),"")
A45: El Alto + Mini El Alto (HCAISAN) - MW (CND/ASEP) | B45: 72.2 | C45: 72.2 | D45: 72.2 | E45: 73.18 | F45: 73.18 | G45: 73.18 | H45: 73.18 | I45: 73.18 | J45: 73.18 | K45: 73.18
A46: El Alto + Mini El Alto (HCAISAN) - GWh (CND actual) | B46: 256.762 | C46: 326.563 | D46: 221.333 | E46: 286.349 | F46: 272.331 | G46: NOT_DISCLOSED | H46: NOT_DISCLOSED | I46: NOT_DISCLOSED | J46: NOT_DISCLOSED | K46: NOT_DISCLOSED
A47: El Alto + Mini El Alto (HCAISAN) - CF literal (GWh/(MW*8.76)) | B47: =IF(AND(ISNUMBER(B46),ISNUMBER(B45)),B46/(B45*8.76),"") -> 0.4059658 | C47: =IF(AND(ISNUMBER(C46),ISNUMBER(C45)),C46/(C45*8.76),"") -> 0.516328 | D47: =IF(AND(ISNUMBER(D46),ISNUMBER(D45)),D46/(D45*8.76),"") -> 0.34994909 | E47: =IF(AND(ISNUMBER(E46),ISNUMBER(E45)),E46/(E45*8.76),"") -> 0.44668273 | F47: =IF(AND(ISNUMBER(F46),ISNUMBER(F45)),F46/(F45*8.76),"") -> 0.42481571 | G47: =IF(AND(ISNUMBER(G46),ISNUMBER(G45)),G46/(G45*8.76),"") | H47: =IF(AND(ISNUMBER(H46),ISNUMBER(H45)),H46/(H45*8.76),"") | I47: =IF(AND(ISNUMBER(I46),ISNUMBER(I45)),I46/(I45*8.76),"") | ... K47: =IF(AND(ISNUMBER(K46),ISNUMBER(K45)),K46/(K45*8.76),"")
A48: Note: Discrepancia §7.2 (data-foundation, NO resuelta): Mini El Alto (0.98 MW) COD mar-2024 sube el denominador de 72.2 (FY21-23, El Alto solo) a 73.18 (FY24-25); denominador CF de flota corregido a vintage ASEP (120.309/121.289 MW 2023/24) — la pagina curada usaba 121.28/122.26, que ya contaba Mini El Alto en 2023 pre-COD. NUEVO hallazgo (Task 1, verificado en CND_ESTADISTICAS_Capacidad_Instalada.pdf, columnas por posicion calibradas contra GENPED/RCHICO): la tabla ASEP registra el salto de El Alto standalone 60->72.2 ya en 2021 (OK, consistente con FY21-23=72.2), pero el 0.98 MW de Mini El Alto solo aparece en la columna 2025 de la tabla ASEP (no en 2024) pese al COD mar-2024. Este build usa la convencion 'ano de COD' (73.18 desde FY24) para reproducir el CF §2 ya vetteado; la lectura estricta columna-por-columna de ASEP pondria FY24 en 72.2 y solo FY25 en 73.18. NO resuelto — bandera para Source_Register/Task 11.
A49: Pedregalito Solar (9.9 MWac) - MW (CND/ASEP) | B49: 9.9 | C49: 9.9 | D49: 9.9 | E49: 9.9 | F49: 9.9 | G49: 9.9 | H49: 9.9 | I49: 9.9 | J49: 9.9 | K49: 9.9
A50: Pedregalito Solar (9.9 MWac) - GWh (CND actual) | B50: NOT_DISCLOSED | C50: NOT_DISCLOSED | D50: 2.612 | E50: 17.743 | F50: 17.114 | G50: NOT_DISCLOSED | H50: NOT_DISCLOSED | I50: NOT_DISCLOSED | J50: NOT_DISCLOSED | K50: NOT_DISCLOSED
A51: Pedregalito Solar (9.9 MWac) - CF literal (GWh/(MW*8.76)) | B51: =IF(AND(ISNUMBER(B50),ISNUMBER(B49)),B50/(B49*8.76),"") | C51: =IF(AND(ISNUMBER(C50),ISNUMBER(C49)),C50/(C49*8.76),"") | D51: =IF(AND(ISNUMBER(D50),ISNUMBER(D49)),D50/(D49*8.76),"") -> 0.030118537 | E51: =IF(AND(ISNUMBER(E50),ISNUMBER(E49)),E50/(E49*8.76),"") -> 0.20459158 | F51: =IF(AND(ISNUMBER(F50),ISNUMBER(F49)),F50/(F49*8.76),"") -> 0.19733868 | G51: =IF(AND(ISNUMBER(G50),ISNUMBER(G49)),G50/(G49*8.76),"") | H51: =IF(AND(ISNUMBER(H50),ISNUMBER(H49)),H50/(H49*8.76),"") | I51: =IF(AND(ISNUMBER(I50),ISNUMBER(I49)),I50/(I49*8.76),"") | ... K51: =IF(AND(ISNUMBER(K50),ISNUMBER(K49)),K50/(K49*8.76),"")
A52: Pedregalito Solar (9.9 MWac) - CF COD-adjusted (~8mo since COD) | B52: NOT_DISCLOSED | C52: NOT_DISCLOSED | D52: NOT_DISCLOSED | E52: NOT_DISCLOSED | F52: =IF(AND(ISNUMBER(F50),ISNUMBER(F49)),F50/(F49*8.76*8/12),"") -> 0.29600803 | G52: NOT_DISCLOSED | H52: NOT_DISCLOSED | I52: NOT_DISCLOSED | J52: NOT_DISCLOSED | K52: NOT_DISCLOSED
A53: Note: COD may-2025. FY23 (2.612 GWh) y FY24 (17.743 GWh) son inyecciones de prueba pre-COD, no generacion comercial (flag, no silently fijado). ASEP solo registra esta capacidad desde FY2025; el MW aplicado a FY21-24 es el nameplate de diseno (9.9 MWac), no una cifra ASEP FY-especifica. Se reporta CF literal (8.76 kh completas) y CF COD-ajustado (~8 meses may-dic), ambos rotulados.
A54: Total PPH GWh (CND, sum of plants) | B54: =SUM(B36,B40,B43,B46,B50) -> 432.379 | C54: =SUM(C36,C40,C43,C46,C50) -> 558.778 | D54: =SUM(D36,D40,D43,D46,D50) -> 381.044 | E54: =SUM(E36,E40,E43,E46,E50) -> 505.372 | F54: =SUM(F36,F40,F43,F46,F50) -> 476.641 | G54: =SUM(G36,G40,G43,G46,G50) -> 0 | H54: =SUM(H36,H40,H43,H46,H50) -> 0 | I54: =SUM(I36,I40,I43,I46,I50) -> 0 | ... K54: =SUM(K36,K40,K43,K46,K50) -> 0
A55: Tie: FY21-25 total must equal 432.4 / 558.8 / 381.0 / 505.4 / 476.6 GWh (Step-1, generation-actuals-cnd.md).
A57: A3. PPA contract ladder (26 contracts, dual-source: market CSV + Nota 1 OCR)
A58: Sources: a working file kept by the maintainer (grupo economico "PANA POWER HOLDING"; 26 distinct contract IDs; extracted via python csv module, raw-XML/csv, 2026-07-12)
A59: Sources: OCR: a working file kept by the maintainer:312-412 (Nota 1, tabla PPA)
A60: Classification: DCD = capacidad + energia (12); SED = solo energia (12); BRIDGE = puente corto sep-24->nov-25 (2). 12+12+2=26, dual-source cross-validated.
A61: DRIVER_DETAIL_PENDING: la sigla "SED" no esta definida en la documentación de dominio para este CSV legado (Tipo de contrato). Nota de investigacion (pasada 4, F2): en las licitaciones NUEVAS (01-26/02-24) "SED/SEO" = codigo de contrato Solo Energia Diaria/Ocasional -- no confirmado que sea la MISMA definicion que el Tipo=SED de este CSV historico 2013-2015; no se asume, solo se cita como candidato.
A62: NOT_DISCLOSED: Pedregalito Solar Power no tiene contrato propio en el CSV (26 contratos son todos Tecnologia=Hidro). El Nota 1 OCR le atribuye Licit.02-24 @ $0.06942/kWh (2025-2030), pero investigacion (licitaciones deep-research, correccion #2) NO encuentra ese precio en la adjudicacion primaria de la 02-24 (que da Pedregalito Solar adjudicada a 54.421 USD/MWh = $0.054421/kWh) -- resolucion 100% spot-vs-CSV diferida a Task 4, no se construye aqui una fila PPA para Solar.
A63: -- El Alto (Hydro Caisan) --
A64: 05-08 E5 | El Alto (Hydro Caisan) x EDEMET (DCD, 01-ene-15->31-dic-25) - Potencia (MW, CSV) | B64: 17.048 | C64: 17.048 | D64: 17.048 | E64: 17.048 | F64: 17.048
A65: Precio potencia ($/kW-mes, CSV) | B65: 31.62 | C65: 31.62 | D65: 31.62 | E65: 31.62 | F65: 31.62
A66: Precio energia ($/kWh, CSV) | B66: 0.0306 | C66: 0.0306 | D66: 0.0306 | E66: 0.0306 | F66: 0.0306
A67: Note: Licit. 01-08 (mitad EDEMET) -- STEP-1 TIE-OUT. Precio potencia paso $31.00->$31.62/kW-mes y energia $0.0300->$0.0306/kWh dentro de la vigencia del CSV; se usa la tasa terminal FY25 (empata con OCR Nota1 linea 334-341 y audit_report). Vence 31-dic-2025.
A68: DME-010-08 E4 | El Alto (Hydro Caisan) x ENSA (DCD, 01-ene-16->31-dic-26) - Potencia (MW, CSV) | B68: 5.093 | C68: 5.093 | D68: 5.093 | E68: 5.093 | F68: 5.093 | G68: 5.093
A69: Precio potencia ($/kW-mes, CSV) | B69: 31.62 | C69: 31.62 | D69: 31.62 | E69: 31.62 | F69: 31.62 | G69: 31.62
A70: Precio energia ($/kWh, CSV) | B70: 0.0306 | C70: 0.0306 | D70: 0.0306 | E70: 0.0306 | F70: 0.0306 | G70: 0.0306
A71: Note: Licit. 01-08 (mitad ENSA) -- STEP-1 TIE-OUT. Misma escalada de precio que la pierna EDEMET. Vence 31-dic-2026 -- UN ANO DESPUES que la pierna EDEMET (31-dic-2025): el cliff de El Alto tiene DOS fechas, no una.
A72: 31-13. | El Alto (Hydro Caisan) x EDEMET (SED, 01-dic-15->31-dic-27) - Potencia (MW, CSV) | B72: 12.4265 | C72: 12.4265 | D72: 12.4265 | E72: 12.4265 | F72: 12.4265 | G72: 12.4265 | H72: 12.4265
A73: Precio energia ($/kWh, CSV) | B73: 0.1325 | C73: 0.1325 | D73: 0.1325 | E73: 0.1325 | F73: 0.1325 | G73: 0.1325 | H73: 0.1325
A74: 40-13. | El Alto (Hydro Caisan) x EDECHI (SED, 01-dic-15->31-dic-27) - Potencia (MW, CSV) | B74: 4.21238 | C74: 4.21238 | D74: 4.21238 | E74: 4.21238 | F74: 4.21238 | G74: 4.21238 | H74: 4.21238
A75: Precio energia ($/kWh, CSV) | B75: 0.1325 | C75: 0.1325 | D75: 0.1325 | E75: 0.1325 | F75: 0.1325 | G75: 0.1325 | H75: 0.1325
A76: DME-016-13 | El Alto (Hydro Caisan) x ENSA (SED, 01-dic-15->31-dic-27) - Potencia (MW, CSV) | B76: 4.7108 | C76: 4.7108 | D76: 4.7108 | E76: 4.7108 | F76: 4.7108 | G76: 4.7108 | H76: 4.7108
A77: Precio energia ($/kWh, CSV) | B77: 0.1325 | C77: 0.1325 | D77: 0.1325 | E77: 0.1325 | F77: 0.1325 | G77: 0.1325 | H77: 0.1325
A78: 60-23 | El Alto (Hydro Caisan) x EDECHI (BRIDGE, 01-sep-24->30-sep-24) - Potencia (MW, CSV) | E78: 0.4554
A79: Precio energia ($/kWh, CSV) | E79: 0.09765
A80: Note: Puente de 1 mes (sep-24).
A81: DME-029-23 | El Alto (Hydro Caisan) x ENSA (BRIDGE, 01-sep-24->30-nov-25) - Potencia (MW, CSV) | E81: 40.98 | F81: 40.98
A82: Precio energia ($/kWh, CSV) | E82: 0.1 | F82: 0.1
A83: Note: Puente sep-24->nov-25; precio de energia observado en el CSV oscila $0.08-$0.10/kWh segun mes (varios meses sin despacho, precio y MW en 0); se usa el techo $0.10/kWh como representativo (coincide con el rango $0.08-$0.10/kWh del brief).
A84: -- Pedregalito --
A85: 28-11 E1 | Pedregalito x EDEMET (DCD, 01-ene-15->31-dic-29) - Potencia (MW, CSV) | B85: 2.62546 | C85: 2.62546 | D85: 2.62546 | E85: 2.62546 | F85: 2.62546 | G85: 2.62546 | H85: 2.62546 | I85: 2.62546 | J85: 2.62546
A86: Precio potencia ($/kW-mes, CSV) | B86: 30 | C86: 30 | D86: 30 | E86: 30 | F86: 30 | G86: 30 | H86: 30 | I86: 30 | J86: 30
A87: Precio energia ($/kWh, CSV) | B87: 0.0542 | C87: 0.0542 | D87: 0.0542 | E87: 0.0542 | F87: 0.0542 | G87: 0.0542 | H87: 0.0542 | I87: 0.0542 | J87: 0.0542
A88: 40-11 E1 | Pedregalito x EDECHI (DCD, 01-ene-15->31-dic-29) - Potencia (MW, CSV) | B88: 0.26227 | C88: 0.26227 | D88: 0.26227 | E88: 0.26227 | F88: 0.26227 | G88: 0.26227 | H88: 0.26227 | I88: 0.26227 | J88: 0.26227
A89: Precio potencia ($/kW-mes, CSV) | B89: 30 | C89: 30 | D89: 30 | E89: 30 | F89: 30 | G89: 30 | H89: 30 | I89: 30 | J89: 30
A90: Precio energia ($/kWh, CSV) | B90: 0.0542 | C90: 0.0542 | D90: 0.0542 | E90: 0.0542 | F90: 0.0542 | G90: 0.0542 | H90: 0.0542 | I90: 0.0542 | J90: 0.0542
A91: Note: El CSV trae DOS filas con este mismo ID literal, una sin espacio final y otra con espacio final ("40-11 E1 "), con series mensuales de Potencia ligeramente distintas (una estacional 0.1206-0.26227, la otra plana 0.26227) -- posible duplicado/variante de captura en la fuente; se listan ambas filas tal como aparecen en el CSV (ver fila siguiente), sin fusionar ni silenciosamente descartar ninguna.
A92: 40-11 E1 [variante CSV: ID con espacio final] | Pedregalito x EDECHI (DCD, 01-ene-15->31-dic-29) - Potencia (MW, CSV) | B92: 0.26227 | C92: 0.26227 | D92: 0.26227 | E92: 0.26227 | F92: 0.26227 | G92: 0.26227 | H92: 0.26227 | I92: 0.26227 | J92: 0.26227
A93: Precio potencia ($/kW-mes, CSV) | B93: 30 | C93: 30 | D93: 30 | E93: 30 | F93: 30 | G93: 30 | H93: 30 | I93: 30 | J93: 30
A94: Precio energia ($/kWh, CSV) | B94: 0.0542 | C94: 0.0542 | D94: 0.0542 | E94: 0.0542 | F94: 0.0542 | G94: 0.0542 | H94: 0.0542 | I94: 0.0542 | J94: 0.0542
A95: DME-021-11 | Pedregalito x ENSA (DCD, 01-ene-15->31-dic-29) - Potencia (MW, CSV) | B95: 1.05026 | C95: 1.05026 | D95: 1.05026 | E95: 1.05026 | F95: 1.05026 | G95: 1.05026 | H95: 1.05026 | I95: 1.05026 | J95: 1.05026
A96: Precio potencia ($/kW-mes, CSV) | B96: 30 | C96: 30 | D96: 30 | E96: 30 | F96: 30 | G96: 30 | H96: 30 | I96: 30 | J96: 30
A97: Precio energia ($/kWh, CSV) | B97: 0.0542 | C97: 0.0542 | D97: 0.0542 | E97: 0.0542 | F97: 0.0542 | G97: 0.0542 | H97: 0.0542 | I97: 0.0542 | J97: 0.0542
A98: 28-13 | Pedregalito x EDEMET (SED, 01-dic-15->31-dic-27) - Potencia (MW, CSV) | B98: 4.14622 | C98: 4.14622 | D98: 4.14622 | E98: 4.14622 | F98: 4.14622 | G98: 4.14622 | H98: 4.14622
A99: Precio energia ($/kWh, CSV) | B99: 0.132 | C99: 0.132 | D99: 0.132 | E99: 0.132 | F99: 0.132 | G99: 0.132 | H99: 0.132
A100: 37-13. | Pedregalito x EDECHI (SED, 01-dic-15->31-dic-27) - Potencia (MW, CSV) | B100: 1.40551 | C100: 1.40551 | D100: 1.40551 | E100: 1.40551 | F100: 1.40551 | G100: 1.40551 | H100: 1.40551
A101: Precio energia ($/kWh, CSV) | B101: 0.132 | C101: 0.132 | D101: 0.132 | E101: 0.132 | F101: 0.132 | G101: 0.132 | H101: 0.132
A102: DME-018-13 | Pedregalito x ENSA (SED, 01-dic-15->31-dic-27) - Potencia (MW, CSV) | B102: 1.73064 | C102: 1.73064 | D102: 1.73064 | E102: 1.73064 | F102: 1.73064 | G102: 1.73064 | H102: 1.73064
A103: Precio energia ($/kWh, CSV) | B103: 0.132 | C103: 0.132 | D103: 0.132 | E103: 0.132 | F103: 0.132 | G103: 0.132 | H103: 0.132
A104: -- Rio Chico --
A105: 29-11 E1 | Rio Chico x EDEMET (DCD, 01-ene-15->31-dic-29) - Potencia (MW, CSV) | B105: 1.61008 | C105: 1.61008 | D105: 1.61008 | E105: 1.61008 | F105: 1.61008 | G105: 1.61008 | H105: 1.61008 | I105: 1.61008 | J105: 1.61008
...

Sheet Debt_Schedule
A1: Panama Power Holdings, Inc. y Subsidiarias
A2: Debt_Schedule — Bonos 2020 (Hydro Caisán) · DSCR / LLCR / PLCR · covenant ≥ 1.25x (Nota 16)
A3: Saldo bruto y covenant: Nota 16 + MD&A EE.FF. FY2025 (5.875% fijo, amort. trim. $1.75M, barrido $2.0M/año)
A5: Años | B5: FY21A | C5: FY22A | D5: FY23A | E5: FY24A | F5: FY25A | G5: FY26E | H5: FY27E | I5: FY28E | J5: FY29E | K5: FY30E
A7: A. ROLL DE DEUDA — Bonos 2020 (saldo bruto a capital, Nota 16)
A8: Saldo bruto inicial | F8: =E11 -> 140250000 | G8: =F11 -> 131250000 | H8: =G11 -> 122250000 | I8: =H11 -> 113250000 | J8: =I11 -> 104250000 | K8: =J11 -> 95250000
A9: (−) Amortización programada (4 × $1.75M/trim., Nota 16) | F9: 7000000 | G9: 7000000 | H9: 7000000 | I9: 7000000 | J9: 7000000 | K9: 7000000
A10: (−) Barrido de caja anual ($2.0M, Nota 16) | F10: 2000000 | G10: 2000000 | H10: 2000000 | I10: 2000000 | J10: 2000000 | K10: 2000000
A11: Saldo bruto final | C11: 158250000 | D11: 153000000 | E11: 140250000 | F11: =F8-F9-F10 -> 131250000 | G11: =G8-G9-G10 -> 122250000 | H11: =H8-H9-H10 -> 113250000 | I11: =I8-I9-I10 -> 104250000 | J11: =J8-J9-J10 -> 95250000 | K11: =K8-K9-K10 -> 86250000
A13: B. INTERESES Y COSTOS FINANCIEROS (→ ModeloFinanciero!20)
A14: Tasa de interés fija Bonos 2020 (Nota 16) | F14: 0.05875 | G14: 0.05875 | H14: 0.05875 | I14: 0.05875 | J14: 0.05875 | K14: 0.05875
A15: Gasto de interés bonos (tasa × saldo bruto promedio) | F15: =0.05875*(F8+F11)/2 -> 7975312.5 | G15: =0.05875*(G8+G11)/2 -> 7446562.5 | H15: =0.05875*(H8+H11)/2 -> 6917812.5 | I15: =0.05875*(I8+I11)/2 -> 6389062.5 | J15: =0.05875*(J8+J11)/2 -> 5860312.5 | K15: =0.05875*(K8+K11)/2 -> 5331562.5
A16: (+) Amortización costos financiamiento diferidos (Nota 16) | F16: 208786 | G16: 208786 | H16: 208786 | I16: 208786 | J16: 208786 | K16: 172783
A17: (+) Otros costos financieros (préstamos/otros, plano FY25A) | F17: 497097 | G17: 497097 | H17: 497097 | I17: 497097 | J17: 497097 | K17: 497097
A18: Costos financieros totales (→ MF!20) | F18: =F15+F16+F17 -> 8681195.5 | G18: =G15+G16+G17 -> 8152445.5 | H18: =H15+H16+H17 -> 7623695.5 | I18: =I15+I16+I17 -> 7094945.5 | J18: =J15+J16+J17 -> 6566195.5 | K18: =K15+K16+K17 -> 6001442.5
A20: C. COBERTURA DE SERVICIO DE DEUDA (DSCR) — covenant Nota 16 (≥ 1.25x)
A21: EBITDA (MF: util. operativa + D&A − ingreso crédito fiscal) | B21: =ModeloFinanciero!B19+ModeloFinanciero!B12-ModeloFinanciero!B11 -> 29850167 | C21: =ModeloFinanciero!C19+ModeloFinanciero!C12-ModeloFinanciero!C11 -> 38912517 | D21: =ModeloFinanciero!D19+ModeloFinanciero!D12-ModeloFinanciero!D11 -> 30407494 | E21: =ModeloFinanciero!E19+ModeloFinanciero!E12-ModeloFinanciero!E11 -> 34831675 | F21: =ModeloFinanciero!F19+ModeloFinanciero!F12-ModeloFinanciero!F11 -> 32921080 | G21: =ModeloFinanciero!G19+ModeloFinanciero!G12-ModeloFinanciero!G11 -> 23190749 | H21: =ModeloFinanciero!H19+ModeloFinanciero!H12-ModeloFinanciero!H11 -> 13165697 | I21: =ModeloFinanciero!I19+ModeloFinanciero!I12-ModeloFinanciero!I11 -> 18742244 | ... K21: =ModeloFinanciero!K19+ModeloFinanciero!K12-ModeloFinanciero!K11 -> 11215760
A22: Servicio de deuda (interés + amort. programada + barrido) | F22: =F15+F9+F10 -> 16975312 | G22: =G15+G9+G10 -> 16446562 | H22: =H15+H9+H10 -> 15917812 | I22: =I15+I9+I10 -> 15389062 | J22: =J15+J9+J10 -> 14860312 | K22: =K15+K9+K10 -> 14331562
A23: DSCR covenant (EBITDA / servicio de deuda) | F23: =IFERROR(F21/F22,"") -> 1.9393505 | G23: =IFERROR(G21/G22,"") -> 1.4100667 | H23: =IFERROR(H21/H22,"") -> 0.82710468 | I23: =IFERROR(I21/I22,"") -> 1.2178938 | J23: =IFERROR(J21/J22,"") -> 1.2532773 | K23: =IFERROR(K21/K22,"") -> 0.78259156
A24: Covenant mínimo (Nota 16) | F24: 1.25 | G24: 1.25 | H24: 1.25 | I24: 1.25 | J24: 1.25 | K24: 1.25
A25: ESTADO covenant | G25: =IFERROR(IF(G23>=1.25,"CUMPLE","INCUMPLE <1.25x"),"") -> CUMPLE | H25: =IFERROR(IF(H23>=1.25,"CUMPLE","INCUMPLE <1.25x"),"") -> INCUMPLE <1.25x | I25: =IFERROR(IF(I23>=1.25,"CUMPLE","INCUMPLE <1.25x"),"") -> INCUMPLE <1.25x | J25: =IFERROR(IF(J23>=1.25,"CUMPLE","INCUMPLE <1.25x"),"") -> CUMPLE | K25: =IFERROR(IF(K23>=1.25,"CUMPLE","INCUMPLE <1.25x"),"") -> INCUMPLE <1.25x
A26: NOTA FY25A: modelo DSCR 1.94x vs Nota 16 divulgado 1.84x — diferencia metodológica: interés avg-balance bond-only $7,975,313 vs Gasto por intereses Nota 16 $8,323,100 (−$347,788) + servicio de deuda anualizado $9.0M vs suma trimestral real MD&A $9,652,587; columnas forecast no afectadas.
A28: D. DSCR ANALÍTICO (CFADS) — lente crédito
A29: CFADS (EBITDA − impuesto pagado − capex mantenimiento) | F29: =F21+ModeloFinanciero!F24-ABS(ModeloFinanciero!F96) -> 27591926 | G29: =G21+ModeloFinanciero!G24-ABS(ModeloFinanciero!G96) -> 21031036 | H29: =H21+ModeloFinanciero!H24-ABS(ModeloFinanciero!H96) -> 14277460 | I29: =I21+ModeloFinanciero!I24-ABS(ModeloFinanciero!I96) -> 17750732 | J29: =J21+ModeloFinanciero!J24-ABS(ModeloFinanciero!J96) -> 17491130 | K29: =K21+ModeloFinanciero!K24-ABS(ModeloFinanciero!K96) -> 12440411
A30: DSCR analítico (CFADS / servicio de deuda) | F30: =IFERROR(F29/F22,"") -> 1.6254149 | G30: =IFERROR(G29/G22,"") -> 1.2787497 | H30: =IFERROR(H29/H22,"") -> 0.89694864 | I30: =IFERROR(I29/I22,"") -> 1.1534642 | J30: =IFERROR(J29/J22,"") -> 1.1770365 | K30: =IFERROR(K29/K22,"") -> 0.86804289
A32: E. LLCR / PLCR — cobertura vida-préstamo / vida-proyecto (nuevas; @Kd 5.875%, no WACC)
A33: Tasa de descuento Kd (costo de deuda, Nota 16) | G33: 0.05875 | H33: 0.05875 | I33: 0.05875 | J33: 0.05875 | K33: 0.05875
A34: VP(CFADS vida remanente del préstamo @Kd) | G34: =G29/1.05875+H29/1.05875^2+I29/1.05875^3+J29/1.05875^4+K29/1.05875^5 -> 70829007 | H34: =H29/1.05875+I29/1.05875^2+J29/1.05875^3+K29/1.05875^4 -> 53959175 | I34: =I29/1.05875+J29/1.05875^2+K29/1.05875^3 -> 42851817 | J34: =J29/1.05875+K29/1.05875^2 -> 27618628 | K34: =K29/1.05875 -> 11750093
A35: Deuda vigente (saldo bruto inicial del período) | G35: =G8 -> 131250000 | H35: =H8 -> 122250000 | I35: =I8 -> 113250000 | J35: =J8 -> 104250000 | K35: =K8 -> 95250000
A36: LLCR (VP CFADS vida-préstamo / deuda vigente) | G36: =IFERROR(G34/G35,"") -> 0.53964958 | H36: =IFERROR(H34/H35,"") -> 0.44138385 | I36: =IFERROR(I34/I35,"") -> 0.37838249 | J36: =IFERROR(J34/J35,"") -> 0.26492689 | K36: =IFERROR(K34/K35,"") -> 0.12336056
A37: Reserva de servicio de deuda (DSRA, Nota 11 — activo restringido) | G37: =ModeloFinanciero!G37 -> 4260349 | H37: =ModeloFinanciero!H37 -> 4260349 | I37: =ModeloFinanciero!I37 -> 4260349 | J37: =ModeloFinanciero!J37 -> 4260349 | K37: =ModeloFinanciero!K37 -> 4260349
A38: PLCR ((VP CFADS + DSRA) / deuda vigente) | G38: =IFERROR((G34+G37)/G35,"") -> 0.57210938 | H38: =IFERROR((H34+H37)/H35,"") -> 0.47623333 | I38: =IFERROR((I34+I37)/I35,"") -> 0.41600146 | J38: =IFERROR((J34+J37)/J35,"") -> 0.30579355 | K38: =IFERROR((K34+K37)/K35,"") -> 0.16808863
A40: F. NOTAS / FLAGS
A41: Vencimiento Oct-2030 (plazo 10 años): repago terminal/balloon y refinanciación NOT_DISCLOSED en Nota 16 (prospecto no OCR). El schedule modela solo la amortización divulgada de $9M/año; el saldo bruto FY30E ($86.25M) queda vigente al vencimiento.
A42: Barrido de caja $2.0M: obligatorio salvo DSCR>1.50x por nuevos contratos (entonces opcional) — Nota 16. Modelado como obligatorio (conservador).
A43: Préstamos por pagar (Nota 17, ~$2.5M) e intereses de préstamo mantenidos planos — DRIVER_DETAIL_PENDING (Nota 17 no divulga cronograma forward claro).
A44: LLCR/PLCR<1.0x reflejan la dependencia de refinanciación del balloon terminal + el cliff PPA; NO son un breach de DSCR periódico (el covenant es DSCR). PLCR trunca la vida-proyecto a FY30E (concesión hidro post-2030 fuera del horizonte de 5 años) → cota inferior.
A45: DSCR<1.25x en FY27E/FY28E/FY30E por el cliff PPA (expiración El Alto + valle de capacidad FY27) — EXPUESTO, no ocultado. Histórico divulgado FY22-25: 1.47x–2.15x (todos >1.25x).

Sheet Valuation
A1: Panama Power Holdings, Inc. y Subsidiarias
A2: Valuation — DCF por activo (vida finita) + sensibilidad hidrología × spot
A3: en B/. sin escala salvo indicado (%, x, $/acción)
A4: Archetype proyecto-finance : DCF vida-finita a fin de concesión + terminal salvage; Gordon = lane renovación/cota-superior, NO base. EBITDA por activo = A6g auditada; WACC consolidado (per-activo no divulgado).
A5: Años | B5: FY21A | C5: FY22A | D5: FY23A | E5: FY24A | F5: FY25A | G5: FY26E | H5: FY27E | I5: FY28E | J5: FY29E | K5: FY30E
A7: A. WACC (CAPM + CRP; Hamada visible) — consolidado; per-activo NO soportado (D/E por planta no divulgado)
A8: Tasa libre de riesgo Rf (UST 30Y, FRED may-2026) | C8: 0.0455
A9: Prima de riesgo de mercado ERP (Damodaran implícita) | C9: 0.055
A10: Prima de riesgo país Panamá CRP (Damodaran) | C10: 0.018
A11: Beta desapalancada β_u (Damodaran utility/power) | C11: 0.38
A12: D/V objetivo — JUICIO sobre book (target no divulgado): deuda fin. total FY24 $141.84M / (141.84 + patrimonio 155.34M) = 47.7% book (MF!E{50,51,52,55,58,59,61}/E70), redondeado a 45% | C12: 0.45
A13: E/V = 1 − D/V | C13: =1-C12 -> 0.55
A14: D/E = D/V ÷ E/V | C14: =C12/C13 -> 0.81818182
A15: Tasa impositiva estatutaria ISR Panamá (DCF normalizado) | C15: 0.25
A16: Beta reapalancada Hamada β_l = β_u×(1+(1−t)×D/E) | C16: =C11*(1+(1-C15)*C14) -> 0.61318182
A17: Ke = Rf + β_l×ERP + CRP | C17: =C8+C16*C9+C10 -> 0.097225
A18: Kd (cupón Bonos 2020, Nota 16) | C18: 0.05875
A19: Kd después de impuestos = Kd×(1−t) | C19: =C18*(1-C15) -> 0.0440625
A20: WACC = E/V×Ke + D/V×Kd×(1−t) | C20: =C13*C17+C12*C19 -> 0.073301875
A21: g terminal (house 2.0%; v71 usó 2.5%) | C21: 0.02
A23: B. Factor de descuento (@WACC, convención fin de año t=1..5)
A24: Factor de descuento 1/(1+WACC)^t | G24: =1/(1+$C$20)^1 -> 0.93170433 | H24: =1/(1+$C$20)^2 -> 0.86807295 | I24: =1/(1+$C$20)^3 -> 0.80878732 | J24: =1/(1+$C$20)^4 -> 0.75355065 | K24: =1/(1+$C$20)^5 -> 0.7020864
A26: C. Horizonte por activo — concesiones ASEP 50 años (Nota 24); +50 renovable ⇒ lane Gordon, NO base
A27: El Alto (HCAISAN): refrendo 13-abr-2007 → fin 2057 (N=27 años desde FY30)
A28: Pedregalito 1 (GENPED): refrendo 27-jul-2009 → fin 2059 (N=29)
A29: Pedregalito 2 (RCHICO): refrendo 29-abr-2011 → fin 2061 (N=31)
A30: Cochea (ALTOVALLE): refrendo 27-jul-2009 → fin 2059 (N=29)
A31: Pedregalito Solar: Licencia Definitiva 14-jun-2023 (Res. AN 18482-Elec, INA_2024) — término NO divulgado → vida-panel ~2055 (N=25) DRIVER_DETAIL_PENDING; inmaterial (<4% EBITDA)
A33: D. DCF por activo — EBITDA (A6g auditada FY22-24 → Supuestos F forecast) → UFCF → PV @ WACC; VT vida-finita a fin de concesión
A34: El Alto + Mini (HCAISAN)
A35: EBITDA planta (rev − compras − O&M − G&A; Supuestos F) | G35: =Supuestos!G88-Supuestos!G102-Supuestos!G105-Supuestos!G112 -> 11042861 | H35: =Supuestos!H88-Supuestos!H102-Supuestos!H105-Supuestos!H112 -> 1051978 | I35: =Supuestos!I88-Supuestos!I102-Supuestos!I105-Supuestos!I112 -> 6645609.8 | J35: =Supuestos!J88-Supuestos!J102-Supuestos!J105-Supuestos!J112 -> 6544541.7 | K35: =Supuestos!K88-Supuestos!K102-Supuestos!K105-Supuestos!K112 -> 6357937.6
A36: D&A planta (A6g FY24 auditada, held flat) | G36: =Generation_PPA!E369 -> 6954278 | H36: =Generation_PPA!E369 -> 6954278 | I36: =Generation_PPA!E369 -> 6954278 | J36: =Generation_PPA!E369 -> 6954278 | K36: =Generation_PPA!E369 -> 6954278
A37: UFCF planta = EBITDA − MAX(0,EBIT)×t (EBIT=EBITDA−D&A) | G37: =G35-MAX(0,G35-G36)*$C$15 -> 10020715 | H37: =H35-MAX(0,H35-H36)*$C$15 -> 1051978 | I37: =I35-MAX(0,I35-I36)*$C$15 -> 6645609.8 | J37: =J35-MAX(0,J35-J36)*$C$15 -> 6544541.7 | K37: =K35-MAX(0,K35-K36)*$C$15 -> 6357937.6
A38: PV(UFCF explícito) = UFCF × factor descuento | G38: =G37*G$24 -> 9336343.6 | H38: =H37*H$24 -> 913193.66 | I38: =I37*I$24 -> 5374885 | J38: =J37*J$24 -> 4931643.6 | K38: =K37*K$24 -> 4463821.5
A39: VP explícito (Σ FY26-30) | C39: =SUM(G38:K38) -> 25019887
A40: UFCF normalizado terminal = EBITDA_FY30×(1−t) [capex sostenim.≈escudo D&A] | C40: =K35*(1-$C$15) -> 4768453.2
A41: Factor annuity finito (g,WACC,N=27) a fin de concesión | C41: =(1+$C$21)/($C$20-$C$21)*(1-((1+$C$21)/(1+$C$20))^27) -> 14.29934
A42: VT @FY30 (finito) = UFCF norm × factor | C42: =C40*C41 -> 68185734
A43: PV(VT) = VT ÷ (1+WACC)^5 | C43: =C42/(1+$C$20)^5 -> 47872277
A44: EV activo = VP explícito + PV(VT) | C44: =C39+C43 -> 72892164
A45: Pedregalito 1 (GENPED)
A46: EBITDA planta (rev − compras − O&M − G&A; Supuestos F) | G46: =Supuestos!G92-Supuestos!G106-Supuestos!G113 -> 6341906 | H46: =Supuestos!H92-Supuestos!H106-Supuestos!H113 -> 6341906 | I46: =Supuestos!I92-Supuestos!I106-Supuestos!I113 -> 6341906 | J46: =Supuestos!J92-Supuestos!J106-Supuestos!J113 -> 6341906 | K46: =Supuestos!K92-Supuestos!K106-Supuestos!K113 -> 2702917
A47: D&A planta (A6g FY24 auditada, held flat) | G47: =Generation_PPA!E370 -> 2230118 | H47: =Generation_PPA!E370 -> 2230118 | I47: =Generation_PPA!E370 -> 2230118 | J47: =Generation_PPA!E370 -> 2230118 | K47: =Generation_PPA!E370 -> 2230118
A48: UFCF planta = EBITDA − MAX(0,EBIT)×t (EBIT=EBITDA−D&A) | G48: =G46-MAX(0,G46-G47)*$C$15 -> 5313959 | H48: =H46-MAX(0,H46-H47)*$C$15 -> 5313959 | I48: =I46-MAX(0,I46-I47)*$C$15 -> 5313959 | J48: =J46-MAX(0,J46-J47)*$C$15 -> 5313959 | K48: =K46-MAX(0,K46-K47)*$C$15 -> 2584717.2
A49: PV(UFCF explícito) = UFCF × factor descuento | G49: =G48*G$24 -> 4951038.6 | H49: =H48*H$24 -> 4612904 | I49: =I48*I$24 -> 4297862.7 | J49: =J48*J$24 -> 4004337.2 | K49: =K48*K$24 -> 1814694.8
A50: VP explícito (Σ FY26-30) | C50: =SUM(G49:K49) -> 19680837
A51: UFCF normalizado terminal = EBITDA_FY30×(1−t) [capex sostenim.≈escudo D&A] | C51: =K46*(1-$C$15) -> 2027187.7
A52: Factor annuity finito (g,WACC,N=29) a fin de concesión | C52: =(1+$C$21)/($C$20-$C$21)*(1-((1+$C$21)/(1+$C$20))^29) -> 14.767832
A53: VT @FY30 (finito) = UFCF norm × factor | C53: =C51*C52 -> 29937168
A54: PV(VT) = VT ÷ (1+WACC)^5 | C54: =C53/(1+$C$20)^5 -> 21018478
A55: EV activo = VP explícito + PV(VT) | C55: =C50+C54 -> 40699316
A56: Pedregalito 2 (RCHICO)
A57: EBITDA planta (rev − compras − O&M − G&A; Supuestos F) | G57: =Supuestos!G94-Supuestos!G107-Supuestos!G114 -> 4038824.1 | H57: =Supuestos!H94-Supuestos!H107-Supuestos!H114 -> 4038824.1 | I57: =Supuestos!I94-Supuestos!I107-Supuestos!I114 -> 4038824.1 | J57: =Supuestos!J94-Supuestos!J107-Supuestos!J114 -> 4038824.1 | K57: =Supuestos!K94-Supuestos!K107-Supuestos!K114 -> 1647553.6
A58: D&A planta (A6g FY24 auditada, held flat) | G58: =Generation_PPA!E371 -> 1169305 | H58: =Generation_PPA!E371 -> 1169305 | I58: =Generation_PPA!E371 -> 1169305 | J58: =Generation_PPA!E371 -> 1169305 | K58: =Generation_PPA!E371 -> 1169305
A59: UFCF planta = EBITDA − MAX(0,EBIT)×t (EBIT=EBITDA−D&A) | G59: =G57-MAX(0,G57-G58)*$C$15 -> 3321444.3 | H59: =H57-MAX(0,H57-H58)*$C$15 -> 3321444.3 | I59: =I57-MAX(0,I57-I58)*$C$15 -> 3321444.3 | J59: =J57-MAX(0,J57-J58)*$C$15 -> 3321444.3 | K59: =K57-MAX(0,K57-K58)*$C$15 -> 1527991.4
A60: PV(UFCF explícito) = UFCF × factor descuento | G60: =G59*G$24 -> 3094604.1 | H60: =H59*H$24 -> 2883256 | I60: =I59*I$24 -> 2686342.1 | J60: =J59*J$24 -> 2502876.5 | K60: =K59*K$24 -> 1072782
A61: VP explícito (Σ FY26-30) | C61: =SUM(G60:K60) -> 12239861
A62: UFCF normalizado terminal = EBITDA_FY30×(1−t) [capex sostenim.≈escudo D&A] | C62: =K57*(1-$C$15) -> 1235665.2
A63: Factor annuity finito (g,WACC,N=31) a fin de concesión | C63: =(1+$C$21)/($C$20-$C$21)*(1-((1+$C$21)/(1+$C$20))^31) -> 15.190947
A64: VT @FY30 (finito) = UFCF norm × factor | C64: =C62*C63 -> 18770924
A65: PV(VT) = VT ÷ (1+WACC)^5 | C65: =C64/(1+$C$20)^5 -> 13178811
A66: EV activo = VP explícito + PV(VT) | C66: =C61+C65 -> 25418671
A67: Cochea (ALTOVALLE)
A68: EBITDA planta (rev − compras − O&M − G&A; Supuestos F) | G68: =Supuestos!G96-Supuestos!G103-Supuestos!G110 -> 4685585.8 | H68: =Supuestos!H96-Supuestos!H103-Supuestos!H110 -> 4685585.8 | I68: =Supuestos!I96-Supuestos!I103-Supuestos!I110 -> 4685585.8 | J68: =Supuestos!J96-Supuestos!J103-Supuestos!J110 -> 4685585.8 | K68: =Supuestos!K96-Supuestos!K103-Supuestos!K110 -> 3511202.3
A69: D&A planta (A6g FY24 auditada, held flat) | G69: =Generation_PPA!E367 -> 1686175 | H69: =Generation_PPA!E367 -> 1686175 | I69: =Generation_PPA!E367 -> 1686175 | J69: =Generation_PPA!E367 -> 1686175 | K69: =Generation_PPA!E367 -> 1686175
A70: UFCF planta = EBITDA − MAX(0,EBIT)×t (EBIT=EBITDA−D&A) | G70: =G68-MAX(0,G68-G69)*$C$15 -> 3935733.1 | H70: =H68-MAX(0,H68-H69)*$C$15 -> 3935733.1 | I70: =I68-MAX(0,I68-I69)*$C$15 -> 3935733.1 | J70: =J68-MAX(0,J68-J69)*$C$15 -> 3935733.1 | K70: =K68-MAX(0,K68-K69)*$C$15 -> 3054945.5
A71: PV(UFCF explícito) = UFCF × factor descuento | G71: =G70*G$24 -> 3666939.5 | H71: =H70*H$24 -> 3416503.4 | I71: =I70*I$24 -> 3183171 | J71: =J70*J$24 -> 2965774.2 | K71: =K70*K$24 -> 2144835.7
A72: VP explícito (Σ FY26-30) | C72: =SUM(G71:K71) -> 15377224
A73: UFCF normalizado terminal = EBITDA_FY30×(1−t) [capex sostenim.≈escudo D&A] | C73: =K68*(1-$C$15) -> 2633401.7
A74: Factor annuity finito (g,WACC,N=29) a fin de concesión | C74: =(1+$C$21)/($C$20-$C$21)*(1-((1+$C$21)/(1+$C$20))^29) -> 14.767832
A75: VT @FY30 (finito) = UFCF norm × factor | C75: =C73*C74 -> 38889634
A76: PV(VT) = VT ÷ (1+WACC)^5 | C76: =C75/(1+$C$20)^5 -> 27303883
A77: EV activo = VP explícito + PV(VT) | C77: =C72+C76 -> 42681107
A78: Pedregalito Solar (SOLAR)
A79: EBITDA planta (rev − compras − O&M − G&A; Supuestos F) | G79: =Supuestos!G97-Supuestos!G104-Supuestos!G111 -> 951105.68 | H79: =Supuestos!H97-Supuestos!H104-Supuestos!H111 -> 916936.42 | I79: =Supuestos!I97-Supuestos!I104-Supuestos!I111 -> 899851.8 | J79: =Supuestos!J97-Supuestos!J104-Supuestos!J111 -> 882767.17 | K79: =Supuestos!K97-Supuestos!K104-Supuestos!K111 -> 865682.54
A80: D&A planta (A6g FY24 auditada, held flat) | G80: =Generation_PPA!E368 -> 406993 | H80: =Generation_PPA!E368 -> 406993 | I80: =Generation_PPA!E368 -> 406993 | J80: =Generation_PPA!E368 -> 406993 | K80: =Generation_PPA!E368 -> 406993
A81: UFCF planta = EBITDA − MAX(0,EBIT)×t (EBIT=EBITDA−D&A) | G81: =G79-MAX(0,G79-G80)*$C$15 -> 815077.51 | H81: =H79-MAX(0,H79-H80)*$C$15 -> 789450.57 | I81: =I79-MAX(0,I79-I80)*$C$15 -> 776637.1 | J81: =J79-MAX(0,J79-J80)*$C$15 -> 763823.63 | K81: =K79-MAX(0,K79-K80)*$C$15 -> 751010.16
A82: PV(UFCF explícito) = UFCF × factor descuento | G82: =G81*G$24 -> 759411.24 | H82: =H81*H$24 -> 685300.68 | I82: =I81*I$24 -> 628134.24 | J82: =J81*J$24 -> 575579.79 | K82: =K81*K$24 -> 527274.02
A83: VP explícito (Σ FY26-30) | C83: =SUM(G82:K82) -> 3175700
A84: UFCF normalizado terminal = EBITDA_FY30×(1−t) [capex sostenim.≈escudo D&A] | C84: =K79*(1-$C$15) -> 649261.91
A85: Factor annuity finito (g,WACC,N=25) a fin de concesión | C85: =(1+$C$21)/($C$20-$C$21)*(1-((1+$C$21)/(1+$C$20))^25) -> 13.780605
A86: VT @FY30 (finito) = UFCF norm × factor | C86: =C84*C85 -> 8947222.2
A87: PV(VT) = VT ÷ (1+WACC)^5 | C87: =C86/(1+$C$20)^5 -> 6281723
A88: EV activo = VP explícito + PV(VT) | C88: =C83+C87 -> 9457423
A89: Corporativo y no-asignado (transmisión emisor + G&A holdco/otros + true-up O&M − capex; sin escudo fiscal, EBIT<0)
A90: EBITDA corporativo (−transmisión − G&A holdco/otros − true-up O&M) | G90: =-ModeloFinanciero!G9-Supuestos!G109-Supuestos!G115-(ModeloFinanciero!G13-Supuestos!G108) -> -3869533 | H90: =-ModeloFinanciero!H9-Supuestos!H109-Supuestos!H115-(ModeloFinanciero!H13-Supuestos!H108) -> -3869533 | I90: =-ModeloFinanciero!I9-Supuestos!I109-Supuestos!I115-(ModeloFinanciero!I13-Supuestos!I108) -> -3869533 | J90: =-ModeloFinanciero!J9-Supuestos!J109-Supuestos!J115-(ModeloFinanciero!J13-Supuestos!J108) -> -3869533 | K90: =-ModeloFinanciero!K9-Supuestos!K109-Supuestos!K115-(ModeloFinanciero!K13-Supuestos!K108) -> -3869533
A91: Capex mantenimiento (MF adiciones PP&E, emisor) | G91: =ModeloFinanciero!G96 -> -441856 | H91: =ModeloFinanciero!H96 -> -441856 | I91: =ModeloFinanciero!I96 -> -441856 | J91: =ModeloFinanciero!J96 -> -441856 | K91: =ModeloFinanciero!K96 -> -441856
A92: UFCF corporativo = EBITDA corp + capex (conservador, sin escudo) | G92: =G90+G91 -> -4311389 | H92: =H90+H91 -> -4311389 | I92: =I90+I91 -> -4311389 | J92: =J90+J91 -> -4311389 | K92: =K90+K91 -> -4311389
A93: PV(UFCF corp explícito) | G93: =G92*G$24 -> -4016939.8 | H93: =H92*H$24 -> -3742600.2 | I93: =I92*I$24 -> -3486996.8 | J93: =J92*J$24 -> -3248850 | K93: =K92*K$24 -> -3026967.6
A94: VP explícito corp (Σ) | C94: =SUM(G93:K93) -> -17522354
A95: UFCF norm terminal corp = UFCF corp FY30 | C95: =K92 -> -4311389
A96: Factor annuity finito corp (N=27, concesión más corta) | C96: =(1+$C$21)/($C$20-$C$21)*(1-((1+$C$21)/(1+$C$20))^27) -> 14.29934
A97: VT corp @FY30 (finito) | C97: =C95*C96 -> -61650018
A98: PV(VT corp) | C98: =C97/(1+$C$20)^5 -> -43283639
A99: EV corp = VP explícito + PV(VT) | C99: =C94+C98 -> -60805994
A101: Tie EBITDA: Σ activos + corp − Debt_Schedule!21 (=0; solo columnas forecast G:K — el histórico B:F no tiene buildup por activo aquí, A6g cubre FY22-24) | G101: =G35+G46+G57+G68+G79+G90-Debt_Schedule!G21 -> 0 | H101: =H35+H46+H57+H68+H79+H90-Debt_Schedule!H21 -> 0 | I101: =I35+I46+I57+I68+I79+I90-Debt_Schedule!I21 -> 0 | J101: =J35+J46+J57+J68+J79+J90-Debt_Schedule!J21 -> 0 | K101: =K35+K46+K57+K68+K79+K90-Debt_Schedule!K21 -> 0
A102: UFCF consolidado (Σ activos + corp) | G102: =G37+G48+G59+G70+G81+G92 -> 19095540 | H102: =H37+H48+H59+H70+H81+H92 -> 10101176 | I102: =I37+I48+I59+I70+I81+I92 -> 15681994 | J102: =J37+J48+J59+J70+J81+J92 -> 15568113 | K102: =K37+K48+K59+K70+K81+K92 -> 9965212.8
A104: E. Enterprise Value y puente EV→Equity (net debt = Debt_Schedule + EEFF, sin refi inventado)
A105: Enterprise Value consolidado (vida-finita) = Σ EV activos + corp | C105: =C44+C55+C66+C77+C88+C99 -> 1.3034269e+08
A106: (memo) VP explícito consolidado (Σ activos + corp) | C106: =C39+C50+C61+C72+C83+C94 -> 57971155
...

Sheet Source_Register
A1: Panama Power Holdings, Inc. y Subsidiarias
A2: Source_Register — power archetype. Every row traces to a published filing (OCR text) or to a working file kept by the maintainer.
A3: Status semantics: OK = citation resolved to an existing artifact. SOURCE_GAP = traceability missing (visible, not hidden). NOT_DISCLOSED = no registration/manifest found for this issuer.
A4: source_id | B4: kind | C4: ticker | D4: filing | E4: year | F4: nota | G4: tabla_ocr | H4: feeds_sheet | I4: feeds_anchor | J4: date | K4: status | L4: evidence_count | M4: note
A5: OCR_ROOT:pph | B5: OCR_ROOT | C5: PPHO | H5: EEFF; Notas_EEFF | I5: OCR of the published filings | J5: NOT_DISCLOSED | K5: OK | L5: 1 | M5: Annual reports (INA) of pph
A6: EEFF_FILING:ina_ppho_2022_0 | B6: EEFF_FILING | C6: PPHO | D6: INA_PPHO_2022_0.pdf | E6: 2022 | G6: markdown.md | H6: EEFF; Notas_EEFF; MD&A | I6: 00-index.md; 01-eeff.md; 02-notas.md; 03-mda.md; 09-otros.md | J6: FY22 (A) | K6: OK | L6: 111 | M6: markdown.md sha256=663558049dc00503...
A7: EEFF_FILING:ina_ppho_2023_0 | B7: EEFF_FILING | C7: PPHO | D7: INA_PPHO_2023_0.pdf | E7: 2023 | G7: markdown.md | H7: EEFF; Notas_EEFF; MD&A | I7: 00-index.md; 01-eeff.md; 02-notas.md; 03-mda.md; 09-otros.md | J7: FY23 (A) | K7: OK | L7: 108 | M7: markdown.md sha256=f49ff90f6adca2a7...
A8: EEFF_FILING:ina_ppho_2024_0 | B8: EEFF_FILING | C8: PPHO | D8: INA_PPHO_2024_0.pdf | E8: 2024 | G8: markdown.md | H8: EEFF; Notas_EEFF; MD&A | I8: 00-index.md; 01-eeff.md; 02-notas.md; 03-mda.md; 09-otros.md | J8: FY24 (A) | K8: OK | L8: 107 | M8: markdown.md sha256=f5ac8f7095d3cc1b...
A9: EEFF_FILING:ina_ppho_2025_0 | B9: EEFF_FILING | C9: PPHO | D9: INA_PPHO_2025_0.pdf | E9: 2025 | G9: markdown.md | H9: EEFF; Notas_EEFF; MD&A | I9: 00-index.md; 01-eeff.md; 02-notas.md; 03-mda.md; 09-otros.md | J9: FY25 (A) | K9: OK | L9: 104 | M9: markdown.md sha256=78bd6c38fb48d3ba...
A10: NOTA:INA_PPHO_2022_0.pdf#1 | B10: NOTA | C10: PPHO | D10: INA_PPHO_2022_0.pdf | E10: 2022 | F10: 1 | G10: markdown.md | H10: Notas_EEFF | I10: 1. Información General | J10: FY22 (A) | K10: OK | L10: 12
A11: NOTA:INA_PPHO_2022_0.pdf#10 | B11: NOTA | C11: PPHO | D11: INA_PPHO_2022_0.pdf | E11: 2022 | F11: 10 | G11: markdown.md | H11: Notas_EEFF | I11: 10. Efectivo Restringido | J11: FY22 (A) | K11: OK | L11: 4
A12: NOTA:INA_PPHO_2022_0.pdf#11 | B12: NOTA | C12: PPHO | D12: INA_PPHO_2022_0.pdf | E12: 2022 | F12: 11 | G12: markdown.md | H12: Notas_EEFF | I12: 11. Plusvalía | J12: FY22 (A) | K12: OK | L12: 8
A13: NOTA:INA_PPHO_2022_0.pdf#12 | B13: NOTA | C13: PPHO | D13: INA_PPHO_2022_0.pdf | E13: 2022 | F13: 12 | G13: markdown.md | H13: Notas_EEFF | I13: 12. Costos de Exploración y Evaluación | J13: FY22 (A) | K13: OK | L13: 2
A14: NOTA:INA_PPHO_2022_0.pdf#13 | B14: NOTA | C14: PPHO | D14: INA_PPHO_2022_0.pdf | E14: 2022 | F14: 13 | G14: markdown.md | H14: Notas_EEFF | I14: 13. Activos Intangibles, Neto | J14: FY22 (A) | K14: OK | L14: 2
A15: NOTA:INA_PPHO_2022_0.pdf#14 | B15: NOTA | C15: PPHO | D15: INA_PPHO_2022_0.pdf | E15: 2022 | F15: 14 | G15: markdown.md | H15: Notas_EEFF | I15: 14. Activos por Derecho de Uso (Continuación) | J15: FY22 (A) | K15: OK | L15: 8
A16: NOTA:INA_PPHO_2022_0.pdf#15 | B16: NOTA | C16: PPHO | D16: INA_PPHO_2022_0.pdf | E16: 2022 | F16: 15 | G16: markdown.md | H16: Notas_EEFF | I16: 15. Cuentas por Pagar | J16: FY22 (A) | K16: OK | L16: 3
A17: NOTA:INA_PPHO_2022_0.pdf#16 | B17: NOTA | C17: PPHO | D17: INA_PPHO_2022_0.pdf | E17: 2022 | F17: 16 | G17: markdown.md | H17: Notas_EEFF | I17: 16. Bonos por Pagar (Continuación) | J17: FY22 (A) | K17: OK | L17: 16
A18: NOTA:INA_PPHO_2022_0.pdf#17 | B18: NOTA | C18: PPHO | D18: INA_PPHO_2022_0.pdf | E18: 2022 | F18: 17 | G18: markdown.md | H18: Notas_EEFF | I18: 17. Préstamos por pagar | J18: FY22 (A) | K18: OK | L18: 4
A19: NOTA:INA_PPHO_2022_0.pdf#18 | B19: NOTA | C19: PPHO | D19: INA_PPHO_2022_0.pdf | E19: 2022 | F19: 18 | G19: markdown.md | H19: Notas_EEFF | I19: 18. Otros Pasivos | J19: FY22 (A) | K19: OK | L19: 2
A20: NOTA:INA_PPHO_2022_0.pdf#19 | B20: NOTA | C20: PPHO | D20: INA_PPHO_2022_0.pdf | E20: 2022 | F20: 19 | G20: markdown.md | H20: Notas_EEFF | I20: 19. Acciones de Capital (Continuación) | J20: FY22 (A) | K20: OK | L20: 19
A21: NOTA:INA_PPHO_2022_0.pdf#2 | B21: NOTA | C21: PPHO | D21: INA_PPHO_2022_0.pdf | E21: 2022 | F21: 2 | G21: markdown.md | H21: Notas_EEFF | I21: 2. Resumen de las Políticas de Contabilidad Significativas (Continuación) | J21: FY22 (A) | K21: OK | L21: 96
... A111: NOTA:INA_PPHO_2025_0.pdf#9 | B111: NOTA | C111: PPHO | D111: INA_PPHO_2025_0.pdf | E111: 2025 | F111: 9 | G111: markdown.md | H111: Notas_EEFF | I111: 9. Propiedad, Planta y Equipo, Neto (Continuación) | J111: FY25 (A) | K111: OK | L111: 1
A112: DRIVER: | MEMO fix pass 2026-07-12: NO cableado a MF — MF!13 (Operacion y mantenimiento) va flat FY25 (A) (3,004,212); routearlo via fila 46 (G&A -> MF!14) duplicaria O&M. Driver auditado disponible para | B112: DRIVER_OTHER | C112: PPHO | H112: Supuestos | I112: O&M total proforma $ (amarra a Nota 22 emisor FY24 = 2,549,512) | J112: NOT_DISCLOSED | K112: SOURCE_GAP | L112: 1 | M112: Unclassified _source citation shape: | MEMO fix pass 2026-07-12: NO cableado a MF — MF!13 (Operacion y mantenimiento) va flat FY25 (A) (3,004,212); routearlo via fila 46 (G&A -> MF!14) duplicaria O&M. Driver auditado disponible para Task 8+ si se recablea MF!13.
A113: DRIVER:EEFF:Venta de energía | B113: DRIVER_EEFF | C113: PPHO | H113: Supuestos | I113: Ingreso energía FY25 (A) (auditado, ref EEFF) | J113: NOT_DISCLOSED | K113: OK | L113: 1 | M113: Venta de energía
A114: DRIVER:F1 fila 76: suma generacion por planta (CF ENSO Bear/Base/Bull por planta, CND A2). Filas 16-21 = memo legacy CF-flota (ya no suman al total forecast). | B114: DRIVER_OTHER | C114: PPHO | H114: Supuestos | I114: Generación neta total (MWh) | J114: NOT_DISCLOSED | K114: SOURCE_GAP | L114: 1 | M114: Unclassified _source citation shape: F1 fila 76: suma generacion por planta (CF ENSO Bear/Base/Bull por planta, CND A2). Filas 16-21 = memo legacy CF-flota (ya no suman al total forecast).
A115: DRIVER:F2 fila 83 (award GC-02-2026 SED+SEO, MWh/ano activo) + F1 generacion Ped1(55)/Ped2(60)/Cochea(65) mientras PPA vigente (expiries dic-29/jun-30; sin re-contratacion asumida — ausentes de GC-02- | B115: DRIVER_OTHER | C115: PPHO | H115: Supuestos | I115: MWh contratado (potencia+energía y solo-energía) | J115: NOT_DISCLOSED | K115: SOURCE_GAP | L115: 1 | M115: Unclassified _source citation shape: F2 fila 83 (award GC-02-2026 SED+SEO, MWh/ano activo) + F1 generacion Ped1(55)/Ped2(60)/Cochea(65) mientras PPA vigente (expiries dic-29/jun-30; sin re-contratacion asumida — ausentes de GC-02-2026).
A116: DRIVER:F2/F3: forecast = blended Seccion F (ingresos contratados: award GC-02-2026 fila 85 + PPAs vigentes filas 92/94/96) / MWh contratados fila 32; K = award + 0.5xCochea a 91.649 $/MWh (A4a). Solo | B116: DRIVER_OTHER | C116: PPHO | H116: Supuestos | I116: PPA contratado ($/MWh, blended realizado FY25 potencia+energía) | J116: NOT_DISCLOSED | K116: SOURCE_GAP | L116: 1 | M116: Unclassified _source citation shape: F2/F3: forecast = blended Seccion F (ingresos contratados: award GC-02-2026 fila 85 + PPAs vigentes filas 92/94/96) / MWh contratados fila 32; K = award + 0.5xCochea a 91.649 $/MWh (A4a). Solo energia (capacidad va como termino propio en fila 39). Label pinned por contrato ACTIVE pph_pilot_energy_pxq_v0 (node ppa_blended_price) — hist B-F sigue siendo blended realizado.
A117: DRIVER:F4 fila 102: $/MWh firming (mediana FY22-24 auditada A6g, HCAISAN 84-91% de compras) x MWh comprometido El Alto (fila 83). | B117: DRIVER_OTHER | C117: PPHO | H117: Supuestos | I117: Compras de energía y costos asociados (firming spot, hidrología) | J117: NOT_DISCLOSED | K117: SOURCE_GAP | L117: 1 | M117: Unclassified _source citation shape: F4 fila 102: $/MWh firming (mediana FY22-24 auditada A6g, HCAISAN 84-91% de compras) x MWh comprometido El Alto (fila 83).
A118: DRIVER:F4 fila 116 (G&A total auditado A6g FY24, por subsidiaria) - fila 44 honorarios. Fila 46 = 44+45 = 5,511,351 = G&A emisor FY24. | B118: DRIVER_OTHER | C118: PPHO | H118: Supuestos | I118: Resto G&A (= G&A total F4 auditado A6g − honorarios) | J118: NOT_DISCLOSED | K118: SOURCE_GAP | L118: 1 | M118: Unclassified _source citation shape: F4 fila 116 (G&A total auditado A6g FY24, por subsidiaria) - fila 44 honorarios. Fila 46 = 44+45 = 5,511,351 = G&A emisor FY24.
A119: DRIVER:Fila 22 (= F1 fila 76, generacion total ENSO) - fila 32 (contratado). Referencia via fila 22 para mantener el nodo de contrato total_generation_mwh vivo (no decorativo). | B119: DRIVER_OTHER | C119: PPHO | H119: Supuestos | I119: MWh spot / merchant (residual) | J119: NOT_DISCLOSED | K119: SOURCE_GAP | L119: 1 | M119: Unclassified _source citation shape: Fila 22 (= F1 fila 76, generacion total ENSO) - fila 32 (contratado). Referencia via fila 22 para mantener el nodo de contrato total_generation_mwh vivo (no decorativo).
A120: DRIVER:Generation_PPA!A2 (CND generacion_YYYY.xlsx, CF por planta FY21-25) + sector research note (Bear=FY23 seco, Bull=FY22 humedo, Base=mediana) | B120: DRIVER_OTHER | C120: PPHO | H120: Supuestos | I120: Pedregalito 1 (GENPED) — CF Bear (FY23 seco) | J120: NOT_DISCLOSED | K120: SOURCE_GAP | L120: 20 | M120: Unclassified _source citation shape: Generation_PPA!A2 (CND generacion_YYYY.xlsx, CF por planta FY21-25) + sector research note (Bear=FY23 seco, Bull=FY22 humedo, Base=mediana)
A121: DRIVER:Generation_PPA!A3b Group 2 (adjudicacion verificada GC-02-2026/LPI 01-26) + maintainer research note | B121: DRIVER_OTHER | C121: PPHO | H121: Supuestos | I121: El Alto — Capacidad contratada activa (MW): FY26 ENSA half -> valle -> award 4.4 MW | J121: NOT_DISCLOSED | K121: SOURCE_GAP | L121: 5 | M121: Unclassified _source citation shape: Generation_PPA!A3b Group 2 (adjudicacion verificada GC-02-2026/LPI 01-26) + maintainer research note
A122: DRIVER:Generation_PPA!A4a (blended PPA $/MWh, MW-weighted) + sector research note; post-expiry: Supuestos!26 Spot/merchant activo (Task 3, CND) — driver merchant post-expir | B122: DRIVER_OTHER | C122: PPHO | H122: Supuestos | I122: Pedregalito 1 (GENPED) — Precio ($/MWh): PPA blended hasta expiry, luego merchant(spot) | J122: NOT_DISCLOSED | K122: SOURCE_GAP | L122: 3 | M122: Unclassified _source citation shape: Generation_PPA!A4a (blended PPA $/MWh, MW-weighted) + sector research note; post-expiry: Supuestos!26 Spot/merchant activo (Task 3, CND) — driver merchant post-expiry
A123: DRIVER:Generation_PPA!A6g (Consolidacion IS por subsidiaria, auditada FY24; suma amarra a Nota 22/21 emisor) | B123: DRIVER_OTHER | C123: PPHO | H123: Supuestos | I123: O&M — Cochea (ALTOVALLE) (A6g FY24 auditado, held flat) | J123: NOT_DISCLOSED | K123: SOURCE_GAP | L123: 12 | M123: Unclassified _source citation shape: Generation_PPA!A6g (Consolidacion IS por subsidiaria, auditada FY24; suma amarra a Nota 22/21 emisor)
... A190: DISCREPANCY:EL_ALTO_CONCESSIONS_HORIZON | B190: DISCREPANCY | C190: PPHO | H190: Valuation | I190: maintainer research note | J190: 46214 | K190: OK | L190: 1 | M190: Concesiones ASEP (refrendo + 50 años, Nota 24): El Alto → 2057, Pedregalito 1 → 2059, Cochea → 2059, Pedregalito 2 → 2061 — all three vintages verified (progress.md:102); all OUTLAST both the 2030 bond maturity and the FY30 forecast horizon, which is why the DCF finite-life terminal uses per-concession expiry, not a fixed corporate horizon.

Sheet _CHANGELOG
A1: Panama Power Holdings, Inc. y Subsidiarias
A2: _CHANGELOG — generation record for pph.
A3: Internal build history omitted from the public export. Record public changes below.

Sheet _CHECKS
A1: Panama Power Holdings, Inc. y Subsidiarias
A2: _CHECKS panel — power template, live formulas, known residuals signed visible
A3: Status semantics: PASS = zero undocumented hard failures; KNOWN_RESIDUAL = signed G7 residual; SOURCE_GAP = unresolved semantic anchor/schedule.
A4: MASTER_STATUS | B4: MODEL STATUS | C4: =IF(COUNTIF($C$6:$C$33,"FAIL")=0,"PASS","FAIL") -> PASS | G4: Master PASS counts only FAIL rows; KNOWN_RESIDUAL/SOURCE_GAP remain visible but non-blocking.
A5: check_id | B5: description | C5: status | D5: hardness | E5: tolerance | F5: expected | G5: note | H5: FY21A | I5: FY22A | J5: FY23A | K5: FY24A | L5: FY25A | M5: FY26E | N5: FY27E | O5: FY28E | P5: FY29E | Q5: FY30E
A7: UNIVERSAL CHECKS
A8: BS_BALANCE | B8: UNIVERSAL | expected 0; hard fail if ABS(value) > hard_tie_tolerance. Observed: UEPII critical gate <10 for BS/cash; BG hard reconciliation >=1000 because full USD. | source applies_to: all 16 archetypes | C8: =IF(SUMPRODUCT((ABS(H8:Q8)>1000)*1)=0,"PASS","FAIL") -> PASS | D8: hard | E8: 1000 USD | F8: 0 | G8: expected 0; hard fail if ABS(value) > hard_tie_tolerance. Observed: UEPII critical gate <10 for BS/cash; BG hard reconciliation >=1000 because full USD. Default full-USD hard tie threshold is $1,000 unless the workbook declares a tighter scale-aware tolerance. | H8: =ModeloFinanciero!B48-ModeloFinanciero!B71 -> 0 | I8: =ModeloFinanciero!C48-ModeloFinanciero!C71 -> 0 | J8: =ModeloFinanciero!D48-ModeloFinanciero!D71 -> 0 | K8: =ModeloFinanciero!E48-ModeloFinanciero!E71 -> 0 | L8: =ModeloFinanciero!F48-ModeloFinanciero!F71 -> 0 | M8: =ModeloFinanciero!G48-ModeloFinanciero!G71 -> 0 | N8: =ModeloFinanciero!H48-ModeloFinanciero!H71 -> 0 | O8: =ModeloFinanciero!I48-ModeloFinanciero!I71 -> 0 | ... Q8: =ModeloFinanciero!K48-ModeloFinanciero!K71 -> 0
A9: CASH_TIE | B9: UNIVERSAL | expected 0; use hard_tie_tolerance; if cash includes restricted cash/time deposits, define cash_component role explicitly. | source applies_to: all 16 archetypes | C9: =IF(SUMPRODUCT((ABS(H9:Q9)>1000)*1)=0,"PASS","FAIL") -> PASS | D9: hard | E9: 1000 USD | F9: 0 | G9: Observed hard tie threshold for model-to-model cash residuals; define cash-component role when restricted cash/time deposits exist. | H9: =ModeloFinanciero!B110-ModeloFinanciero!B29 -> 0 | I9: =ModeloFinanciero!C110-ModeloFinanciero!C29 -> 0 | J9: =ModeloFinanciero!D110-ModeloFinanciero!D29 -> 0 | K9: =ModeloFinanciero!E110-ModeloFinanciero!E29 -> 0 | L9: =ModeloFinanciero!F110-ModeloFinanciero!F29 -> 0
A10: CF_ROLLFORWARD | B10: UNIVERSAL | expected 0; hard_tie_tolerance; historical rows may be WARN if source CF transcript is incomplete. | source applies_to: all 16 where CF is modeled | C10: =IF(SUMPRODUCT((ABS(H10:Q10)>1000)*1)=0,"PASS","FAIL") -> PASS | D10: hard | E10: 1000 USD | F10: 0 | G10: expected 0; hard_tie_tolerance; historical rows may be WARN if source CF transcript is incomplete. Default full-USD hard tie threshold is $1,000 unless the workbook declares a tighter scale-aware tolerance. | H10: =ModeloFinanciero!B92+ModeloFinanciero!B98+ModeloFinanciero!B107-ModeloFinanciero!B108 -> 0 | I10: =ModeloFinanciero!C92+ModeloFinanciero!C98+ModeloFinanciero!C107-ModeloFinanciero!C108 -> 0 | J10: =ModeloFinanciero!D92+ModeloFinanciero!D98+ModeloFinanciero!D107-ModeloFinanciero!D108 -> 0 | K10: =ModeloFinanciero!E92+ModeloFinanciero!E98+ModeloFinanciero!E107-ModeloFinanciero!E108 -> 0 | L10: =ModeloFinanciero!F92+ModeloFinanciero!F98+ModeloFinanciero!F107-ModeloFinanciero!F108 -> 0 | M10: =ModeloFinanciero!G92+ModeloFinanciero!G98+ModeloFinanciero!G107-ModeloFinanciero!G108 -> 0 | N10: =ModeloFinanciero!H92+ModeloFinanciero!H98+ModeloFinanciero!H107-ModeloFinanciero!H108 -> 0 | O10: =ModeloFinanciero!I92+ModeloFinanciero!I98+ModeloFinanciero!I107-ModeloFinanciero!I108 -> 0 | ... Q10: =ModeloFinanciero!K92+ModeloFinanciero!K98+ModeloFinanciero!K107-ModeloFinanciero!K108 -> 0
A11: NI_TIE_TO_EQUITY | B11: UNIVERSAL | expected 0; hard_tie_tolerance. | source applies_to: all 16 | C11: SOURCE_GAP | D11: hard | E11: 1000 USD | F11: 0 | G11: No semantic anchors resolved for NI_TIE_TO_EQUITY. | H11: =0 -> 0 | I11: =0 -> 0 | J11: =0 -> 0 | K11: =0 -> 0 | L11: =0 -> 0 | M11: =0 -> 0 | N11: =0 -> 0 | O11: =0 -> 0 | ... Q11: =0 -> 0
A12: NI_SIGN_SANITY | B12: UNIVERSAL | expected 0; sign convention must be stated in row description. | source applies_to: all 16 | C12: =IF(SUMPRODUCT((ABS(H12:Q12)>1000)*1)=0,"PASS","FAIL") -> PASS | D12: hard | E12: 1000 USD | F12: 0 | G12: expected 0; sign convention must be stated in row description. Default full-USD hard tie threshold is $1,000 unless the workbook declares a tighter scale-aware tolerance. | H12: =ModeloFinanciero!B25-(ModeloFinanciero!B23+ModeloFinanciero!B24) -> 0 | I12: =ModeloFinanciero!C25-(ModeloFinanciero!C23+ModeloFinanciero!C24) -> 0 | J12: =ModeloFinanciero!D25-(ModeloFinanciero!D23+ModeloFinanciero!D24) -> 0 | K12: =ModeloFinanciero!E25-(ModeloFinanciero!E23+ModeloFinanciero!E24) -> 0 | L12: =ModeloFinanciero!F25-(ModeloFinanciero!F23+ModeloFinanciero!F24) -> 0 | M12: =ModeloFinanciero!G25-(ModeloFinanciero!G23+ModeloFinanciero!G24) -> 0 | N12: =ModeloFinanciero!H25-(ModeloFinanciero!H23+ModeloFinanciero!H24) -> 0 | O12: =ModeloFinanciero!I25-(ModeloFinanciero!I23+ModeloFinanciero!I24) -> 0 | ... Q12: =ModeloFinanciero!K25-(ModeloFinanciero!K23+ModeloFinanciero!K24) -> 0
A13: RE_ROLLFORWARD | B13: UNIVERSAL | expected 0; hard_tie_tolerance. | source applies_to: all 16 with RE row | C13: =IF(SUMPRODUCT((ABS(H13:Q13)>1000)*1)=0,"PASS","FAIL") -> PASS | D13: hard | E13: 1000 USD | F13: 0 | G13: expected 0; hard_tie_tolerance. Default full-USD hard tie threshold is $1,000 unless the workbook declares a tighter scale-aware tolerance. | I13: =ModeloFinanciero!C69-ModeloFinanciero!B69-(ModeloFinanciero!C25) -> 0 | J13: =ModeloFinanciero!D69-ModeloFinanciero!C69-(ModeloFinanciero!D25) -> 0 | K13: =ModeloFinanciero!E69-ModeloFinanciero!D69-(ModeloFinanciero!E25) -> 0 | L13: =ModeloFinanciero!F69-ModeloFinanciero!E69-(ModeloFinanciero!F25) -> 0
A14: EQUITY_TOTAL_TIE | B14: UNIVERSAL | expected 0; hard_tie_tolerance. | source applies_to: all 16 | C14: =IF(SUMPRODUCT((ABS(H14:Q14)>1000)*1)=0,"PASS","FAIL") -> PASS | D14: hard | E14: 1000 USD | F14: 0 | G14: expected 0; hard_tie_tolerance. Default full-USD hard tie threshold is $1,000 unless the workbook declares a tighter scale-aware tolerance. | H14: =SUM(ModeloFinanciero!B65,ModeloFinanciero!B66,ModeloFinanciero!B67,ModeloFinanciero!B68,ModeloFinanciero!B69)-ModeloFinanciero!B70 -> 0 | I14: =SUM(ModeloFinanciero!C65,ModeloFinanciero!C66,ModeloFinanciero!C67,ModeloFinanciero!C68,ModeloFinanciero!C69)-ModeloFinanciero!C70 -> 0 | J14: =SUM(ModeloFinanciero!D65,ModeloFinanciero!D66,ModeloFinanciero!D67,ModeloFinanciero!D68,ModeloFinanciero!D69)-ModeloFinanciero!D70 -> 0 | K14: =SUM(ModeloFinanciero!E65,ModeloFinanciero!E66,ModeloFinanciero!E67,ModeloFinanciero!E68,ModeloFinanciero!E69)-ModeloFinanciero!E70 -> 0 | L14: =SUM(ModeloFinanciero!F65,ModeloFinanciero!F66,ModeloFinanciero!F67,ModeloFinanciero!F68,ModeloFinanciero!F69)-ModeloFinanciero!F70 -> 0 | M14: =SUM(ModeloFinanciero!G65,ModeloFinanciero!G66,ModeloFinanciero!G67,ModeloFinanciero!G68,ModeloFinanciero!G69)-ModeloFinanciero!G70 -> 0 | N14: =SUM(ModeloFinanciero!H65,ModeloFinanciero!H66,ModeloFinanciero!H67,ModeloFinanciero!H68,ModeloFinanciero!H69)-ModeloFinanciero!H70 -> 0 | O14: =SUM(ModeloFinanciero!I65,ModeloFinanciero!I66,ModeloFinanciero!I67,ModeloFinanciero!I68,ModeloFinanciero!I69)-ModeloFinanciero!I70 -> 0 | ... Q14: =SUM(ModeloFinanciero!K65,ModeloFinanciero!K66,ModeloFinanciero!K67,ModeloFinanciero!K68,ModeloFinanciero!K69)-ModeloFinanciero!K70 -> 0
A15: BS_LINEITEM_SUM_ASSETS | B15: UNIVERSAL | expected 0; hard_tie_tolerance. | source applies_to: all 16 | C15: =IF(SUMPRODUCT((ABS(H15:Q15)>1000)*1)=0,"PASS","FAIL") -> PASS | D15: hard | E15: 1000 USD | F15: 0 | G15: expected 0; hard_tie_tolerance. Default full-USD hard tie threshold is $1,000 unless the workbook declares a tighter scale-aware tolerance. | H15: =SUM(ModeloFinanciero!B36,ModeloFinanciero!B47)-ModeloFinanciero!B48 -> 0 | I15: =SUM(ModeloFinanciero!C36,ModeloFinanciero!C47)-ModeloFinanciero!C48 -> 0 | J15: =SUM(ModeloFinanciero!D36,ModeloFinanciero!D47)-ModeloFinanciero!D48 -> 0 | K15: =SUM(ModeloFinanciero!E36,ModeloFinanciero!E47)-ModeloFinanciero!E48 -> 0 | L15: =SUM(ModeloFinanciero!F36,ModeloFinanciero!F47)-ModeloFinanciero!F48 -> 0 | M15: =SUM(ModeloFinanciero!G36,ModeloFinanciero!G47)-ModeloFinanciero!G48 -> 0 | N15: =SUM(ModeloFinanciero!H36,ModeloFinanciero!H47)-ModeloFinanciero!H48 -> 0 | O15: =SUM(ModeloFinanciero!I36,ModeloFinanciero!I47)-ModeloFinanciero!I48 -> 0 | ... Q15: =SUM(ModeloFinanciero!K36,ModeloFinanciero!K47)-ModeloFinanciero!K48 -> 0
A16: BS_LINEITEM_SUM_LIAB_EQUITY | B16: UNIVERSAL | expected 0; hard_tie_tolerance. | source applies_to: all 16 | C16: =IF(SUMPRODUCT((ABS(H16:Q16)>1000)*1)=0,"PASS","FAIL") -> PASS | D16: hard | E16: 1000 USD | F16: 0 | G16: expected 0; hard_tie_tolerance. Default full-USD hard tie threshold is $1,000 unless the workbook declares a tighter scale-aware tolerance. | H16: =ModeloFinanciero!B64+ModeloFinanciero!B70-ModeloFinanciero!B71 -> 0 | I16: =ModeloFinanciero!C64+ModeloFinanciero!C70-ModeloFinanciero!C71 -> 0 | J16: =ModeloFinanciero!D64+ModeloFinanciero!D70-ModeloFinanciero!D71 -> 0 | K16: =ModeloFinanciero!E64+ModeloFinanciero!E70-ModeloFinanciero!E71 -> 0 | L16: =ModeloFinanciero!F64+ModeloFinanciero!F70-ModeloFinanciero!F71 -> 0 | M16: =ModeloFinanciero!G64+ModeloFinanciero!G70-ModeloFinanciero!G71 -> 0 | N16: =ModeloFinanciero!H64+ModeloFinanciero!H70-ModeloFinanciero!H71 -> 0 | O16: =ModeloFinanciero!I64+ModeloFinanciero!I70-ModeloFinanciero!I71 -> 0 | ... Q16: =ModeloFinanciero!K64+ModeloFinanciero!K70-ModeloFinanciero!K71 -> 0
A17: SOURCE_TIE_HISTORICAL | B17: UNIVERSAL | expected 0 for audited rows; SOURCE_GAP/WARN allowed only with explicit source-gap note. | source applies_to: all 16 | C17: =IF(SUMPRODUCT((ABS(H17:Q17)>100000)*1)=0,"PASS","FAIL") -> PASS | D17: hard | E17: 100000 USD | F17: 0 | G17: Audited rows tie to 0; only bank ending-cash-vs-EEFF cash rows may use the observed $100,000 hard threshold; SOURCE_GAP/WARN requires explicit source-gap note. | H17: =ModeloFinanciero!B48-EEFF!B48 -> 0 | I17: =ModeloFinanciero!C48-EEFF!C48 -> 0 | J17: =ModeloFinanciero!D48-EEFF!D48 -> 0 | K17: =ModeloFinanciero!E48-EEFF!E48 -> 0 | L17: =ModeloFinanciero!F48-EEFF!F48 -> 0
A18: NO_FORMULA_ERRORS | B18: UNIVERSAL | expected PASS/0; no masking. | source applies_to: all 16 | C18: =IF(SUMPRODUCT((ABS(H18:Q18)>0)*1)=0,"PASS","FAIL") -> PASS | D18: hard | E18: PASS | F18: PASS | G18: expected PASS/0; no masking. | H18: =0 -> 0 | I18: =0 -> 0 | J18: =0 -> 0 | K18: =0 -> 0 | L18: =0 -> 0 | M18: =0 -> 0 | N18: =0 -> 0 | O18: =0 -> 0 | ... Q18: =0 -> 0
A19: NO_CHECKS_MASTER_FAIL | B19: UNIVERSAL | expected PASS; status row should cite included/excluded rows. | source applies_to: all 16 | C19: =IF(SUMPRODUCT((ABS(H19:Q19)>0)*1)=0,"PASS","FAIL") -> PASS | D19: hard | E19: PASS | F19: PASS | G19: expected PASS; status row should cite included/excluded rows. | H19: =COUNTIF($C$6:$C$18,"FAIL")+COUNTIF($C$20:$C$33,"FAIL") -> 0 | I19: =COUNTIF($C$6:$C$18,"FAIL")+COUNTIF($C$20:$C$33,"FAIL") -> 0 | J19: =COUNTIF($C$6:$C$18,"FAIL")+COUNTIF($C$20:$C$33,"FAIL") -> 0 | K19: =COUNTIF($C$6:$C$18,"FAIL")+COUNTIF($C$20:$C$33,"FAIL") -> 0 | L19: =COUNTIF($C$6:$C$18,"FAIL")+COUNTIF($C$20:$C$33,"FAIL") -> 0 | M19: =COUNTIF($C$6:$C$18,"FAIL")+COUNTIF($C$20:$C$33,"FAIL") -> 0 | N19: =COUNTIF($C$6:$C$18,"FAIL")+COUNTIF($C$20:$C$33,"FAIL") -> 0 | O19: =COUNTIF($C$6:$C$18,"FAIL")+COUNTIF($C$20:$C$33,"FAIL") -> 0 | ... Q19: =COUNTIF($C$6:$C$18,"FAIL")+COUNTIF($C$20:$C$33,"FAIL") -> 0
A21: CONDITIONAL CHECKS
A22: PPE_SCHEDULE_TIE | B22: ARCHETYPE/conditional | expected 0; hard_tie_tolerance. | source applies_to: operating-EBITDA, power, utility, downstream fuel, other non-financials | C22: SOURCE_GAP | D22: hard | E22: 1000 USD | F22: 0 | G22: No semantic anchors resolved for PPE_SCHEDULE_TIE. | H22: =0 -> 0 | I22: =0 -> 0 | J22: =0 -> 0 | K22: =0 -> 0 | L22: =0 -> 0 | M22: =0 -> 0 | N22: =0 -> 0 | O22: =0 -> 0 | ... Q22: =0 -> 0
A23: LEASE_SCHEDULE_TIE | B23: ARCHETYPE/conditional | expected 0; hard_tie_tolerance. | source applies_to: IFRS-16 issuers | C23: SOURCE_GAP | D23: hard | E23: 1000 USD | F23: 0 | G23: No semantic anchors resolved for LEASE_SCHEDULE_TIE. | H23: =0 -> 0 | I23: =0 -> 0 | J23: =0 -> 0 | K23: =0 -> 0 | L23: =0 -> 0 | M23: =0 -> 0 | N23: =0 -> 0 | O23: =0 -> 0 | ... Q23: =0 -> 0
A24: DEBT_SCHEDULE_TIE | B24: ARCHETYPE/conditional | expected 0; hard_tie_tolerance; project-finance debt can include accrued interest/unamortized cost roles. | source applies_to: non-bank-lender, power, utility, operating-EBITDA with debt | C24: SOURCE_GAP | D24: hard | E24: 1000 USD | F24: 0 | G24: No semantic anchors resolved for DEBT_SCHEDULE_TIE. | H24: =0 -> 0 | I24: =0 -> 0 | J24: =0 -> 0 | K24: =0 -> 0 | L24: =0 -> 0 | M24: =0 -> 0 | N24: =0 -> 0 | O24: =0 -> 0 | ... Q24: =0 -> 0
A26: POWER CHECKS
A27: POWER_REVENUE_BUILD_TIE | B27: ARCHETYPE | expected 0; hard_tie_tolerance. | source applies_to: power, utility | C27: =IF(SUMPRODUCT((ABS(H27:Q27)>1000)*1)=0,"PASS","FAIL") -> PASS | D27: hard | E27: 1000 USD | F27: 0 | G27: expected 0; hard_tie_tolerance. Default full-USD hard tie threshold is $1,000 unless the workbook declares a tighter scale-aware tolerance. | M27: =Supuestos!G39-ModeloFinanciero!G7 -> 0 | N27: =Supuestos!H39-ModeloFinanciero!H7 -> 0 | O27: =Supuestos!I39-ModeloFinanciero!I7 -> 0 | P27: =Supuestos!J39-ModeloFinanciero!J7 -> 0 | Q27: =Supuestos!K39-ModeloFinanciero!K7 -> 0
A28: POWER_CHANNEL_VOLUME_TIE | B28: ARCHETYPE | expected 0; observed UEPII uses N/A for years without channel split. | source applies_to: power, utility | C28: =IF(SUMPRODUCT((ABS(H28:Q28)>0)*1)=0,"PASS","FAIL") -> PASS | D28: hard | E28: volume_tolerance | F28: 0 | G28: expected 0; observed UEPII uses N/A for years without channel split. | M28: =Supuestos!G22-Supuestos!G32-Supuestos!G33 -> 0 | N28: =Supuestos!H22-Supuestos!H32-Supuestos!H33 -> 0 | O28: =Supuestos!I22-Supuestos!I32-Supuestos!I33 -> 0 | P28: =Supuestos!J22-Supuestos!J32-Supuestos!J33 -> 0 | Q28: =Supuestos!K22-Supuestos!K32-Supuestos!K33 -> 0
A29: POWER_CAPACITY_CEILING | B29: ARCHETYPE | PASS/FAIL or 0/1; threshold from hours-per-year parameter. | source applies_to: power, utility | C29: =IF(SUMPRODUCT((ABS(H29:Q29)>0)*1)=0,"PASS","FAIL") -> PASS | D29: hard | E29: PASS | F29: PASS | G29: Per-plant ceiling GWh<=MW*8.76 over Generation_PPA A2 physical rows (Pedregalito 1 (GENPED); Pedregalito 2 (RCHICO); Cochea (ALTOVALLE); El Alto + Mini El Alto (HCAISAN); Pedregalito Solar (9.9 MWac)). Residual = count of plant-years exceeding the ceiling that period. Tested only where GWh is CND-disclosed numeric (FY21-25); FY26-30 GWh is NOT_DISCLOSED in A2 (forecast physical layer not modeled, Generation_PPA row 34) so those columns are blank, not a verified pass. | H29: =IF(ISNUMBER(Generation_PPA!B36),IF(Generation_PPA!B36>Generation_PPA!B35*8.76,1,0),0)+IF(ISNUMBER(Generation_PPA!B40),IF(Generation_PPA!B40>Generation_PPA!B39*8.76,1,0),0)+IF(ISNUMBER(Generation_PPA!B43),IF(Generation_PPA!B43>Generation_PPA!B42*8.76,1,0),0)+IF(ISNUMBER(Generation_PPA!B46),IF(Generation_PPA!B46>Generation_PPA!B45*8.76,1,0),0)+IF(ISNUMBER(Generation_PPA!B50),IF(Generation_PPA!B50>Generation_PPA!B49*8.76,1,0),0) -> 0 | I29: =IF(ISNUMBER(Generation_PPA!C36),IF(Generation_PPA!C36>Generation_PPA!C35*8.76,1,0),0)+IF(ISNUMBER(Generation_PPA!C40),IF(Generation_PPA!C40>Generation_PPA!C39*8.76,1,0),0)+IF(ISNUMBER(Generation_PPA!C43),IF(Generation_PPA!C43>Generation_PPA!C42*8.76,1,0),0)+IF(ISNUMBER(Generation_PPA!C46),IF(Generation_PPA!C46>Generation_PPA!C45*8.76,1,0),0)+IF(ISNUMBER(Generation_PPA!C50),IF(Generation_PPA!C50>Generation_PPA!C49*8.76,1,0),0) -> 0 | J29: =IF(ISNUMBER(Generation_PPA!D36),IF(Generation_PPA!D36>Generation_PPA!D35*8.76,1,0),0)+IF(ISNUMBER(Generation_PPA!D40),IF(Generation_PPA!D40>Generation_PPA!D39*8.76,1,0),0)+IF(ISNUMBER(Generation_PPA!D43),IF(Generation_PPA!D43>Generation_PPA!D42*8.76,1,0),0)+IF(ISNUMBER(Generation_PPA!D46),IF(Generation_PPA!D46>Generation_PPA!D45*8.76,1,0),0)+IF(ISNUMBER(Generation_PPA!D50),IF(Generation_PPA!D50>Generation_PPA!D49*8.76,1,0),0) -> 0 | K29: =IF(ISNUMBER(Generation_PPA!E36),IF(Generation_PPA!E36>Generation_PPA!E35*8.76,1,0),0)+IF(ISNUMBER(Generation_PPA!E40),IF(Generation_PPA!E40>Generation_PPA!E39*8.76,1,0),0)+IF(ISNUMBER(Generation_PPA!E43),IF(Generation_PPA!E43>Generation_PPA!E42*8.76,1,0),0)+IF(ISNUMBER(Generation_PPA!E46),IF(Generation_PPA!E46>Generation_PPA!E45*8.76,1,0),0)+IF(ISNUMBER(Generation_PPA!E50),IF(Generation_PPA!E50>Generation_PPA!E49*8.76,1,0),0) -> 0 | L29: =IF(ISNUMBER(Generation_PPA!F36),IF(Generation_PPA!F36>Generation_PPA!F35*8.76,1,0),0)+IF(ISNUMBER(Generation_PPA!F40),IF(Generation_PPA!F40>Generation_PPA!F39*8.76,1,0),0)+IF(ISNUMBER(Generation_PPA!F43),IF(Generation_PPA!F43>Generation_PPA!F42*8.76,1,0),0)+IF(ISNUMBER(Generation_PPA!F46),IF(Generation_PPA!F46>Generation_PPA!F45*8.76,1,0),0)+IF(ISNUMBER(Generation_PPA!F50),IF(Generation_PPA!F50>Generation_PPA!F49*8.76,1,0),0) -> 0
A30: POWER_DSRA_COVERAGE | B30: ARCHETYPE | expected 0; UEPII tail uses <=1 tolerance in U2 rows. | source applies_to: project-finance power/utility | C30: =IF(SUMPRODUCT((ABS(H30:Q30)>1)*1)=0,"PASS","FAIL") -> PASS | D30: hard | E30: 1 model currency or ratio residual | F30: 0 | G30: DSRA required = 0.25x(amortizacion programada ex-barrido + gasto de interes bonos), per Nota 16's disclosed DSRA definition ('Cuenta de Reserva de Servicio de Deuda de tres meses de pago de capital (exceptuando el barrido de caja) e intereses'; INA_2025_full.md L3661-3662, 'Bonos por Pagar (Continuacion)', PDF p.69). Tested where Debt_Schedule provides a DSRA balance (FY26E-FY30E). Residual = MAX(0, shortfall); 0 = fully funded. | M30: =MAX(0,0.25*(Debt_Schedule!G9+Debt_Schedule!G15)-Debt_Schedule!G37) -> 0 | N30: =MAX(0,0.25*(Debt_Schedule!H9+Debt_Schedule!H15)-Debt_Schedule!H37) -> 0 | O30: =MAX(0,0.25*(Debt_Schedule!I9+Debt_Schedule!I15)-Debt_Schedule!I37) -> 0 | P30: =MAX(0,0.25*(Debt_Schedule!J9+Debt_Schedule!J15)-Debt_Schedule!J37) -> 0 | Q30: =MAX(0,0.25*(Debt_Schedule!K9+Debt_Schedule!K15)-Debt_Schedule!K37) -> 0
A31: POWER_DSCR_COVENANT | B31: ARCHETYPE | must be >=0 or explicit business-warning text; not always a mechanical blocker. | source applies_to: project-finance power/utility | C31: =IF(SUMPRODUCT((Debt_Schedule!G23:K23<Debt_Schedule!G24:K24)*1)=0,"PASS","WARN: DSCR<"&Debt_Schedule!G24&"x "&_xlfn.TEXTJOIN("/",TRUE,IF(Debt_Schedule!G23<Debt_Schedule!G24,"FY26",""),IF(Debt_Schedule!H23<Debt_Schedule!H24,"FY27",""),IF(Debt_Schedule!I23<Debt_Schedule!I24,"FY28",""),IF(Debt_Schedule!J23<Debt_Schedule!J24,"FY29",""),IF(Debt_Schedule!K23<Debt_Schedule!K24,"FY30",""))) -> WARN: DSCR<1.25x FY27/FY28/FY30 | D31: soft | E31: 0 cushion | F31: >=0 | G31: Soft covenant-visibility row (controller decision 2026-07-13): a breach emits a named WARN, never FAIL, so MASTER_STATUS stays governed by hard checks only. The DSCR<1.25x cliff-driven breach (PPA/capacity cliff; covenant 'mayor a 1.25x' consolidado, Nota 16, INA_2025_full.md L3666-3669, floor row Debt_Schedule!24) remains visible in-sheet -- Category D business/covenant risk per checks-and-tie-out-discipline.md, documented not recolored. | M31: =Debt_Schedule!G23-Debt_Schedule!G24 -> 0.16006665 | N31: =Debt_Schedule!H23-Debt_Schedule!H24 -> -0.42289532 | O31: =Debt_Schedule!I23-Debt_Schedule!I24 -> -0.032106156 | P31: =Debt_Schedule!J23-Debt_Schedule!J24 -> 0.0032772584 | Q31: =Debt_Schedule!K23-Debt_Schedule!K24 -> -0.46740844
A32: POWER_DEBT_FACE_ZERO | B32: ARCHETYPE | PASS/FAIL; tail-life projects. | source applies_to: finite-life project finance | C32: =IF(SUMPRODUCT((ABS(H32:Q32)>0)*1)=0,"PASS","FAIL") -> PASS | D32: hard | E32: PASS | F32: PASS | G32: Debt_Schedule!F11 (Saldo bruto final, formula-derived: opening - amort.programada - barrido, not itself a hardcode) tied to Nota 16 tabla de vencimientos, bonos con vencimiento 5-oct-2030 (INA_2025_full.md L3564, repetido L3620; PDF pp.67-68; MD&A secundaria L1094) = $131,250,000. | L32: =Debt_Schedule!F11-131250000 -> 0
A33: OPERATING_GP_OR_EBITDA_TIE | B33: ARCHETYPE | expected 0; hard_tie_tolerance. | source applies_to: operating-EBITDA, downstream fuel, power when EBITDA is used | C33: =IF(SUMPRODUCT((ABS(H33:Q33)>1000)*1)=0,"PASS","FAIL") -> PASS | D33: hard | E33: 1000 USD | F33: 0 | G33: EBITDA = Utilidad operativa + Depreciación y amortización − Ingresos por crédito fiscal y otros (same combination Debt_Schedule!21 uses for the DSCR/LLCR/PLCR EBITDA input; definition matches the issuer's own MD&A EBITDA build, INA_2025_full.md L1108-1114). FY21-25 tie ModeloFinanciero vs EEFF: since MF historicals are a direct EEFF passthrough, this verifies the MF-EEFF passthrough of the EBITDA block is unbroken and the covenant-EBITDA definition is wired consistently -- it is NOT an independent external-source tie. | H33: =(ModeloFinanciero!B19+ModeloFinanciero!B12-ModeloFinanciero!B11)-(EEFF!B19+EEFF!B12-EEFF!B11) -> 0 | I33: =(ModeloFinanciero!C19+ModeloFinanciero!C12-ModeloFinanciero!C11)-(EEFF!C19+EEFF!C12-EEFF!C11) -> 0 | J33: =(ModeloFinanciero!D19+ModeloFinanciero!D12-ModeloFinanciero!D11)-(EEFF!D19+EEFF!D12-EEFF!D11) -> 0 | K33: =(ModeloFinanciero!E19+ModeloFinanciero!E12-ModeloFinanciero!E11)-(EEFF!E19+EEFF!E12-EEFF!E11) -> 0 | L33: =(ModeloFinanciero!F19+ModeloFinanciero!F12-ModeloFinanciero!F11)-(EEFF!F19+EEFF!F12-EEFF!F11) -> 0

Sheet Claude Code Log
A1: Turn # | B1: Date | C1: User Request | D1: Action Taken | E1: Details | F1: Outcome
A2: 1 | B2: 46324.359 | C2: Prepare a public model copy | D2: Remove local paths and private build references; preserve financial formulas and inputs | E2: Agent run with MOG as the tool, checked by guard v1. The guard measured every sheet before and after the run. Changed: Supuestos: 48 cells written, at N11, N12, N13, N14, N15, N16, N17, N18, N19, N20, N21, N26, N27, N28, N29 and 33 more; Notas_EEFF: 1 cell written, at A3; Generation_PPA: 11 cells written, at A33, A38, A58, A59, A61, A143, A148, A156, A168, A174, A281; Debt_Schedule: 1 cell written, at A32; Valuation: 2 cells written, at A4, A129; Source_Register: 113 cells written, at A2, I5, M5, A120, M120, A121, M121, A122, M122, A126, M126, A128, M128, A129, M129 and 98 more; _CHANGELOG: data A1:H45 -> A1:A3 (rows 45 -> 3, columns 8 -> 1), 277 cells written, at A2, A3, B3, C3, D3, E3, F3, G3, H3, A4, B4, C4, D4, E4, F4 and 262 more. Other actions: clear x1. Agent: OpenFinmods export | F2: Compare against source and review public copy
