Workbook

Sheet Cover
A1: Tyson Foods Institutional Financial Model
A2: TSN | USD millions | Historical FY2021-FY2025 | Interim Q2 FY2026 | Forecast FY2026-FY2030
A4: Model status | B4: =Checks!B3 -> OK
A5: Active scenario | B5: =Assumptions!B5 -> Base
A6: Valuation date / latest actual | B6: 46109
A7: DCF value / share | B7: =DCF!B30 -> 108.90302
A8: Exit multiple value / share | B8: =DCF!B34 -> 91.735803
A9: FY2026E reported sales | B9: =Forecast_3Stmt!C7 -> 57202.244
A10: FY2026E operating income | B10: =Forecast_3Stmt!C12 -> 2440.7169
A11: FY2026E free cash flow | B11: =Forecast_3Stmt!C64 -> 1820.7999
A12: Claim mappings | B12: =COUNTA(Sources!A5:A718) -> 714
A13: Model version | B13: 2.0.0
A14: Governance status | B14: OWNER-GATED; INDEPENDENT CERTIFICATION PENDING
A15: Model Architecture
A16: Flow | B16: Sources -> historical statements -> protein drivers -> assumptions -> integrated forecast -> debt/credit -> DCF/sensitivity -> checks
A17: Scenario control | B17: Assumptions!B4: 1 Base / 2 Bull / 3 Bear
A18: Governance boundary | B18: Tyson facts and one-offs are source-mapped; unsourced market/comps inputs are not forced. This model is a donor-company mechanism, not a Panama forecast.
A21: Series | B21: 2021A | C21: 2022A | D21: 2023A | E21: 2024A | F21: 2025A | G21: 2026E | H21: 2027E | I21: 2028E | J21: 2029E | K21: 2030E
A22: Sales | B22: =Historical_IS!B7 -> 47049 | C22: =Historical_IS!C7 -> 53282 | D22: =Historical_IS!D7 -> 52881 | E22: =Historical_IS!E7 -> 53309 | F22: =Historical_IS!F7 -> 54441 | G22: =Forecast_3Stmt!C7 -> 57202.244 | H22: =Forecast_3Stmt!D7 -> 59200.932 | I22: =Forecast_3Stmt!E7 -> 61279.299 | J22: =Forecast_3Stmt!F7 -> 63440.813 | K22: =Forecast_3Stmt!G7 -> 65689.103
A36: Segment | B36: FY2025A | C36: FY2030E
A37: Beef | B37: =Segment_Build!F7 -> 21623 | C37: =Segment_Build!K7 -> 24079.777
A38: Pork | B38: =Segment_Build!F8 -> 5781 | C38: =Segment_Build!K8 -> 6972.6694
A39: Chicken | B39: =Segment_Build!F9 -> 16837 | C39: =Segment_Build!K9 -> 21964.647
A40: Prepared Foods | B40: =Segment_Build!F10 -> 9930 | C40: =Segment_Build!K10 -> 12270.421
A41: International | B41: =Segment_Build!F11 -> 2291 | C41: =Segment_Build!K11 -> 2789.5374

Sheet Historical_IS
A1: Historical Income Statement
A2: USD millions except per-share data; audited GAAP actuals
A4: Metric | B4: 2021A | C4: 2022A | D4: 2023A | E4: 2024A | F4: 2025A
A6: Consolidated Income Statement
A7: Sales | B7: 47049 | C7: 53282 | D7: 52881 | E7: 53309 | F7: 54441
A8: Cost of sales | B8: 40523 | C8: 46614 | D8: 50250 | E8: 49682 | F8: 50879
A9: Gross profit | B9: 6526 | C9: 6668 | D9: 2631 | E9: 3627 | F9: 3562
A10: SG&A | B10: 2130 | C10: 2258 | D10: 2245 | E10: 2218 | F10: 2121
A11: Goodwill impairment | B11: 0 | C11: 0 | D11: 781 | E11: 0 | F11: 343
A12: Operating income | B12: 4396 | C12: 4410 | D12: -395 | E12: 1409 | F12: 1098
A13: Interest income | B13: 8 | C13: 17 | D13: 30 | E13: 89 | F13: 73
A14: Interest expense | B14: 428 | C14: 365 | D14: 355 | E14: 481 | F14: 449
A15: Other income, net | B15: 65 | C15: 87 | D15: 42 | E15: 75 | F15: 47
A16: Income before taxes | B16: 4041 | C16: 4149 | D16: -678 | E16: 1092 | F16: 769
A17: Income tax expense | B17: 981 | C17: 900 | D17: -29 | E17: 270 | F17: 262
A18: Net income including NCI | B18: 3060 | C18: 3249 | D18: -649 | E18: 822 | F18: 507
... A22: Diluted weighted-average shares | B22: 365 | C22: 363 | D22: 284 | E22: 356 | F22: 357

Sheet Historical_BS
A1: Historical Balance Sheet
A2: USD millions except per-share data; audited GAAP actuals
A4: Metric | B4: 2021A | C4: 2022A | D4: 2023A | E4: 2024A | F4: 2025A
A6: Assets
A7: Cash and cash equivalents | B7: 2507 | C7: 1031 | D7: 573 | E7: 1717 | F7: 1229
A8: Accounts receivable | B8: 2400 | C8: 2577 | D8: 2476 | E8: 2406 | F8: 2524
A9: Inventories | B9: 4382 | C9: 5514 | D9: 5328 | E9: 5195 | F9: 5681
A10: Other current assets | B10: 533 | C10: 508 | D10: 345 | E10: 433 | F10: 482
A11: Total current assets | B11: 9822 | C11: 9630 | D11: 8722 | E11: 9751 | F11: 9916
A12: Net PP&E | B12: 7837 | C12: 8685 | D12: 9634 | E12: 9442 | F12: 9204
A13: Goodwill | B13: 10549 | C13: 10513 | D13: 9878 | E13: 9819 | F13: 9469
A14: Intangible assets | B14: 6519 | C14: 6252 | D14: 6098 | E14: 5875 | F14: 5624
A15: Other assets | B15: 1582 | C15: 1741 | D15: 1919 | E15: 2213 | F15: 2445
A16: Total assets | B16: 36309 | C16: 36821 | D16: 36251 | E16: 37100 | F16: 36658
A18: Liabilities and Equity
A19: Current debt | B19: 1067 | C19: 459 | D19: 1895 | E19: 74 | F19: 909
A20: Accounts payable | B20: 2225 | C20: 2483 | D20: 2594 | E20: 2402 | F20: 2601
A21: Other current liabilities | B21: 3033 | C21: 2371 | D21: 2010 | E21: 2311 | F21: 2879
A22: Total current liabilities | B22: 6325 | C22: 5313 | D22: 6499 | E22: 4787 | F22: 6389
A23: Long-term debt | B23: 8281 | C23: 7862 | D23: 7611 | E23: 9713 | F23: 7921
A24: Deferred income taxes | B24: 2195 | C24: 2458 | D24: 2308 | E24: 2285 | F24: 2195
A25: Other liabilities | B25: 1654 | C25: 1377 | D25: 1578 | E25: 1801 | F25: 1926
A26: Total liabilities | B26: 18455 | C26: 17010 | D26: 17996 | E26: 18586 | F26: 18431
A27: Equity attributable to Tyson | B27: 17723 | C27: 19702 | D27: 18133 | E27: 18390 | F27: 18085
A28: Equity attributable to NCI | B28: 131 | C28: 109 | D28: 122 | E28: 124 | F28: 142
A29: Total shareholders' equity | B29: 17854 | C29: 19811 | D29: 18255 | E29: 18514 | F29: 18227
A30: Total liabilities and equity | B30: =B26+B29 -> 36309 | C30: =C26+C29 -> 36821 | D30: =D26+D29 -> 36251 | E30: =E26+E29 -> 37100 | F30: =F26+F29 -> 36658

Sheet Historical_CF
A1: Historical Cash Flow Statement
A2: USD millions except per-share data; audited GAAP actuals
A4: Metric | B4: 2021A | C4: 2022A | D4: 2023A | E4: 2024A | F4: 2025A
A6: Cash Flow Statement
A7: Net income | B7: 3060 | C7: 3249 | D7: -649 | E7: 822 | F7: 507
A8: Depreciation | B8: 934 | C8: 945 | D8: 1100 | E8: 1159 | F8: 1093
A9: Amortization | B9: 280 | C9: 257 | D9: 239 | E9: 241 | F9: 268
A10: Deferred income taxes | B10: -125 | C10: 264 | D10: -183 | E10: -45 | F10: -76
A11: Impairments and disposals | B11: 60 | C11: 34 | D11: 882 | E11: 131 | F11: 469
A12: Stock-based compensation | B12: 91 | C12: 93 | D12: 61 | E12: 101 | F12: 100
A13: Working capital and other operating changes | B13: =B14-SUM(B7:B12) -> -460 | C13: =C14-SUM(C7:C12) -> -2155 | D13: =D14-SUM(D7:D12) -> 302 | E13: =E14-SUM(E7:E12) -> 181 | F13: =F14-SUM(F7:F12) -> -206
A14: Cash provided by operating activities | B14: 3840 | C14: 2687 | D14: 1752 | E14: 2590 | F14: 2155
A15: Capital expenditures | B15: -1209 | C15: -1887 | D15: -1939 | E15: -1132 | F15: -978
A16: Cash used for investing activities | B16: 58 | C16: -1935 | D16: -2299 | E16: -888 | F16: -665
A17: Debt issuance | B17: 585 | C17: 103 | D17: 1130 | E17: 2415 | F17: 175
A18: Debt payments | B18: -2632 | C18: -1191 | D18: -603 | E18: -1641 | F18: -1262
A19: Share repurchases | B19: -67 | C19: -702 | D19: -354 | E19: -49 | F19: -196
A20: Dividends | B20: -636 | C20: -653 | D20: -670 | E20: -684 | F20: -697
A21: Cash from financing activities | B21: -2731 | C21: -2323 | D21: 88 | E21: -581 | F21: -1977
A22: FX and other cash movement | B22: =B23-B14-B16-B21 -> 4 | C22: =C23-C14-C16-C21 -> -35 | D22: =D23-D14-D16-D21 -> 1 | E22: =E23-E14-E16-E21 -> 23 | F22: =F23-F14-F16-F21 -> -1
A23: Change in cash | B23: 1171 | C23: -1606 | D23: -458 | E23: 1144 | F23: -488
A24: Ending cash | B24: 2507 | C24: 1031 | D24: 573 | E24: 1717 | F24: 1229
A25: Free cash flow | B25: =B14+B15 -> 2631 | C25: =C14+C15 -> 800 | D25: =D14+D15 -> -187 | E25: =E14+E15 -> 1458 | F25: =F14+F15 -> 1177

Sheet Segment_Build
A1: Segment Build
A2: FY21-FY22 use legacy allocation; FY23-FY25 use June 2026 five-segment recast
A4: Metric | B4: 2021A | C4: 2022A | D4: 2023A | E4: 2024A | F4: 2025A | G4: 2026E | H4: 2027E | I4: 2028E | J4: 2029E | K4: 2030E
A6: Sales by Segment
A7: Beef | B7: 17999 | C7: 19854 | D7: 19325 | E7: 20479 | F7: 21623 | G7: =F7*(1+Protein_Drivers!B66)*(1+Protein_Drivers!G66)*(1+Assumptions!$B$97) -> 22245.992 | H7: =G7*(1+Protein_Drivers!C66)*(1+Protein_Drivers!H66) -> 22690.912 | I7: =H7*(1+Protein_Drivers!D66)*(1+Protein_Drivers!I66) -> 23144.73 | J7: =I7*(1+Protein_Drivers!E66)*(1+Protein_Drivers!J66) -> 23607.625 | K7: =J7*(1+Protein_Drivers!F66)*(1+Protein_Drivers!K66) -> 24079.777
A8: Pork | B8: 6277 | C8: 6414 | D8: 5768 | E8: 5903 | F8: 5781 | G8: =F8*(1+Protein_Drivers!B67)*(1+Protein_Drivers!G67)*(1+Assumptions!$B$97) -> 6190.317 | H8: =G8*(1+Protein_Drivers!C67)*(1+Protein_Drivers!H67) -> 6377.2646 | I8: =H8*(1+Protein_Drivers!D67)*(1+Protein_Drivers!I67) -> 6569.858 | J8: =I8*(1+Protein_Drivers!E67)*(1+Protein_Drivers!J67) -> 6768.2677 | K8: =J8*(1+Protein_Drivers!F67)*(1+Protein_Drivers!K67) -> 6972.6694
A9: Chicken | B9: 13733 | C9: 16961 | D9: 17060 | E9: 16425 | F9: 16837 | G9: =F9*(1+Protein_Drivers!B68)*(1+Protein_Drivers!G68)*(1+Assumptions!$B$97) -> 18029.124 | H9: =G9*(1+Protein_Drivers!C68)*(1+Protein_Drivers!H68) -> 18941.398 | I9: =H9*(1+Protein_Drivers!D68)*(1+Protein_Drivers!I68) -> 19899.833 | J9: =I9*(1+Protein_Drivers!E68)*(1+Protein_Drivers!J68) -> 20906.764 | K9: =J9*(1+Protein_Drivers!F68)*(1+Protein_Drivers!K68) -> 21964.647
A10: Prepared Foods | B10: 8853 | C10: 9689 | D10: 9845 | E10: 9851 | F10: 9930 | G10: =F10*(1+Protein_Drivers!B69)*(1+Protein_Drivers!G69)*(1+Assumptions!$B$97) -> 10476.713 | H10: =G10*(1+Protein_Drivers!C69)*(1+Protein_Drivers!H69) -> 10898.925 | I10: =H10*(1+Protein_Drivers!D69)*(1+Protein_Drivers!I69) -> 11338.152 | J10: =I10*(1+Protein_Drivers!E69)*(1+Protein_Drivers!J69) -> 11795.079 | K10: =J10*(1+Protein_Drivers!F69)*(1+Protein_Drivers!K69) -> 12270.421
A11: International | B11: 1990 | C11: 2355 | D11: 2515 | E11: 2353 | F11: 2291 | G11: =F11*(1+Protein_Drivers!B70)*(1+Protein_Drivers!G70)*(1+Assumptions!$B$97) -> 2381.7588 | H11: =G11*(1+Protein_Drivers!C70)*(1+Protein_Drivers!H70) -> 2477.7437 | I11: =H11*(1+Protein_Drivers!D70)*(1+Protein_Drivers!I70) -> 2577.5968 | J11: =I11*(1+Protein_Drivers!E70)*(1+Protein_Drivers!J70) -> 2681.474 | K11: =J11*(1+Protein_Drivers!F70)*(1+Protein_Drivers!K70) -> 2789.5374
A12: Intersegment eliminations | B12: -1803 | C12: -1991 | D12: -1632 | E12: -1702 | F12: -2021 | G12: =F12*(1+Protein_Drivers!B71)*(1+Protein_Drivers!G71)*(1+Assumptions!$B$97) -> -2121.6613 | H12: =G12*(1+Protein_Drivers!C71)*(1+Protein_Drivers!H71) -> -2185.3112 | I12: =H12*(1+Protein_Drivers!D71)*(1+Protein_Drivers!I71) -> -2250.8705 | J12: =I12*(1+Protein_Drivers!E71)*(1+Protein_Drivers!J71) -> -2318.3966 | K12: =J12*(1+Protein_Drivers!F71)*(1+Protein_Drivers!K71) -> -2387.9485
A13: Total sales | B13: =SUM(B7:B12) -> 47049 | C13: =SUM(C7:C12) -> 53282 | D13: =SUM(D7:D12) -> 52881 | E13: =SUM(E7:E12) -> 53309 | F13: =SUM(F7:F12) -> 54441 | G13: =SUM(G7:G12) -> 57202.244 | H13: =SUM(H7:H12) -> 59200.932 | I13: =SUM(I7:I12) -> 61279.299 | ... K13: =SUM(K7:K12) -> 65689.103
A15: Segment Operating Income
A16: Beef operating income | B16: 3240 | C16: 2502 | D16: 38 | E16: -246 | F16: -984 | G16: =G7*(Assumptions!B71+Protein_Drivers!B76) -> -424.89845 | H16: =H7*(Assumptions!C71+Protein_Drivers!C76) -> -113.45456 | I16: =I7*(Assumptions!D71+Protein_Drivers!D76) -> 0 | J16: =J7*(Assumptions!E71+Protein_Drivers!E76) -> 118.03812 | K16: =K7*(Assumptions!F71+Protein_Drivers!F76) -> 240.79777
A17: Pork operating income | B17: 328 | C17: 193 | D17: -75 | E17: 26 | F17: -141 | G17: =G8*(Assumptions!B72+Protein_Drivers!B77) -> 285.99265 | H17: =H8*(Assumptions!C72+Protein_Drivers!C77) -> 299.73144 | I17: =I8*(Assumptions!D72+Protein_Drivers!D77) -> 315.35318 | J17: =J8*(Assumptions!E72+Protein_Drivers!E77) -> 331.64512 | K17: =K8*(Assumptions!F72+Protein_Drivers!F77) -> 348.63347
A18: Chicken operating income | B18: -625 | C18: 955 | D18: -378 | E18: 1397 | F18: 1860 | G18: =G9*(Assumptions!B73+Protein_Drivers!B78) -> 2053.5173 | H18: =H9*(Assumptions!C73+Protein_Drivers!C78) -> 2121.4366 | I18: =I9*(Assumptions!D73+Protein_Drivers!D78) -> 2188.9816 | J18: =J9*(Assumptions!E73+Protein_Drivers!E78) -> 2257.9305 | K18: =K9*(Assumptions!F73+Protein_Drivers!F78) -> 2328.2525
A19: Prepared Foods operating income | B19: 1456 | C19: 746 | D19: 1157 | E19: 1224 | F19: 1248 | G19: =G10*(Assumptions!B74+Protein_Drivers!B79) -> 1331.5903 | H19: =H10*(Assumptions!C74+Protein_Drivers!C79) -> 1395.0624 | I19: =I10*(Assumptions!D74+Protein_Drivers!D79) -> 1462.6216 | J19: =J10*(Assumptions!E74+Protein_Drivers!E79) -> 1533.3603 | K19: =K10*(Assumptions!F74+Protein_Drivers!F79) -> 1595.1547
A20: International operating income | B20: -3 | C20: 14 | D20: -158 | E20: 28 | F20: 155 | G20: =G11*(Assumptions!B75+Protein_Drivers!B80) -> 178.39374 | H20: =H11*(Assumptions!C75+Protein_Drivers!C80) -> 188.30852 | I20: =I11*(Assumptions!D75+Protein_Drivers!D80) -> 201.05255 | J20: =J11*(Assumptions!E75+Protein_Drivers!E80) -> 211.83644 | K20: =K11*(Assumptions!F75+Protein_Drivers!F80) -> 223.16299
A21: Total segment operating income | B21: =SUM(B16:B20) -> 4396 | C21: =SUM(C16:C20) -> 4410 | D21: =SUM(D16:D20) -> 584 | E21: =SUM(E16:E20) -> 2429 | F21: =SUM(F16:F20) -> 2138 | G21: =SUM(G16:G20) -> 3424.5955 | H21: =SUM(H16:H20) -> 3891.0844 | I21: =SUM(I16:I20) -> 4168.0089 | ... K21: =SUM(K16:K20) -> 4736.0015
A22: Corporate expenses | B22: 0 | C22: 0 | D22: -750 | E22: -791 | F22: -783 | G22: =-G13*(Assumptions!$B$79-Assumptions!$B$85) -> -697.86738 | H22: =-H13*(Assumptions!$B$79-Assumptions!$B$85) -> -722.25137 | I22: =-I13*(Assumptions!$B$79-Assumptions!$B$85) -> -747.60744 | J22: =-J13*(Assumptions!$B$79-Assumptions!$B$85) -> -773.97792 | K22: =-K13*(Assumptions!$B$79-Assumptions!$B$85) -> -801.40705
A23: Amortization | B23: 0 | C23: 0 | D23: -229 | E23: -229 | F23: -257 | G23: =-G13*Assumptions!$B$85 -> -286.01122 | H23: =-H13*Assumptions!$B$85 -> -296.00466 | I23: =-I13*Assumptions!$B$85 -> -306.39649 | J23: =-J13*Assumptions!$B$85 -> -317.20406 | K23: =-K13*Assumptions!$B$85 -> -328.44551
A24: Consolidated operating income | B24: =SUM(B21:B23) -> 4396 | C24: =SUM(C21:C23) -> 4410 | D24: =SUM(D21:D23) -> -395 | E24: =SUM(E21:E23) -> 1409 | F24: =SUM(F21:F23) -> 1098 | G24: =SUM(G21:G23) -> 2440.7169 | H24: =SUM(H21:H23) -> 2872.8283 | I24: =SUM(I21:I23) -> 3114.005 | ... K24: =SUM(K21:K23) -> 3606.1489

Sheet Assumptions
A1: Assumptions & Scenarios
A2: Blue/yellow cells are editable analyst inputs. FY2026 guidance is on a comparable 52-week basis.
A4: Scenario selector (1 Base / 2 Bull / 3 Bear) | B4: 1
A5: Active scenario | B5: =IF(B4=1,"Base",IF(B4=2,"Bull","Bear")) -> Base
A8: Base Price / Mix Growth
A9: Segment | B9: 2026E | C9: 2027E | D9: 2028E | E9: 2029E | F9: 2030E
A10: Beef | B10: 0.03 | C10: 0.02 | D10: 0.02 | E10: 0.02 | F10: 0.02
A11: Pork | B11: 0.03 | C11: 0.02 | D11: 0.02 | E11: 0.02 | F11: 0.02
A12: Chicken | B12: 0.03 | C12: 0.03 | D12: 0.03 | E12: 0.03 | F12: 0.03
A13: Prepared Foods | B13: 0.03 | C13: 0.03 | D13: 0.03 | E13: 0.03 | F13: 0.03
A14: International | B14: 0.02 | C14: 0.03 | D14: 0.03 | E14: 0.03 | F14: 0.03
A15: Intersegment eliminations | B15: 0.03 | C15: 0.03 | D15: 0.03 | E15: 0.03 | F15: 0.03
A17: Bull Price / Mix Growth
A18: Segment | B18: 2026E | C18: 2027E | D18: 2028E | E18: 2029E | F18: 2030E
A19: Beef | B19: 0.05 | C19: 0.04 | D19: 0.04 | E19: 0.04 | F19: 0.04
A20: Pork | B20: 0.05 | C20: 0.04 | D20: 0.04 | E20: 0.04 | F20: 0.04
A21: Chicken | B21: 0.05 | C21: 0.05 | D21: 0.05 | E21: 0.05 | F21: 0.05
A22: Prepared Foods | B22: 0.05 | C22: 0.05 | D22: 0.05 | E22: 0.05 | F22: 0.05
A23: International | B23: 0.04 | C23: 0.05 | D23: 0.05 | E23: 0.05 | F23: 0.05
A24: Intersegment eliminations | B24: 0.05 | C24: 0.05 | D24: 0.05 | E24: 0.05 | F24: 0.05
A26: Bear Price / Mix Growth
A27: Segment | B27: 2026E | C27: 2027E | D27: 2028E | E27: 2029E | F27: 2030E
A28: Beef | B28: 0 | C28: -0.01 | D28: -0.01 | E28: -0.01 | F28: -0.01
A29: Pork | B29: 0 | C29: -0.01 | D29: -0.01 | E29: -0.01 | F29: -0.01
A30: Chicken | B30: 0 | C30: 0 | D30: 0 | E30: 0 | F30: 0
A31: Prepared Foods | B31: 0 | C31: 0 | D31: 0 | E31: 0 | F31: 0
A32: International | B32: -0.01 | C32: 0 | D32: 0 | E32: 0 | F32: 0
A33: Intersegment eliminations | B33: 0 | C33: 0 | D33: 0 | E33: 0 | F33: 0
A35: Active Price / Mix Growth
A36: Segment | B36: 2026E | C36: 2027E | D36: 2028E | E36: 2029E | F36: 2030E
A37: Beef | B37: =IF($B$4=1,B10,IF($B$4=2,B19,B28)) -> 0.03 | C37: =IF($B$4=1,C10,IF($B$4=2,C19,C28)) -> 0.02 | D37: =IF($B$4=1,D10,IF($B$4=2,D19,D28)) -> 0.02 | E37: =IF($B$4=1,E10,IF($B$4=2,E19,E28)) -> 0.02 | F37: =IF($B$4=1,F10,IF($B$4=2,F19,F28)) -> 0.02
A38: Pork | B38: =IF($B$4=1,B11,IF($B$4=2,B20,B29)) -> 0.03 | C38: =IF($B$4=1,C11,IF($B$4=2,C20,C29)) -> 0.02 | D38: =IF($B$4=1,D11,IF($B$4=2,D20,D29)) -> 0.02 | E38: =IF($B$4=1,E11,IF($B$4=2,E20,E29)) -> 0.02 | F38: =IF($B$4=1,F11,IF($B$4=2,F20,F29)) -> 0.02
A39: Chicken | B39: =IF($B$4=1,B12,IF($B$4=2,B21,B30)) -> 0.03 | C39: =IF($B$4=1,C12,IF($B$4=2,C21,C30)) -> 0.03 | D39: =IF($B$4=1,D12,IF($B$4=2,D21,D30)) -> 0.03 | E39: =IF($B$4=1,E12,IF($B$4=2,E21,E30)) -> 0.03 | F39: =IF($B$4=1,F12,IF($B$4=2,F21,F30)) -> 0.03
A40: Prepared Foods | B40: =IF($B$4=1,B13,IF($B$4=2,B22,B31)) -> 0.03 | C40: =IF($B$4=1,C13,IF($B$4=2,C22,C31)) -> 0.03 | D40: =IF($B$4=1,D13,IF($B$4=2,D22,D31)) -> 0.03 | E40: =IF($B$4=1,E13,IF($B$4=2,E22,E31)) -> 0.03 | F40: =IF($B$4=1,F13,IF($B$4=2,F22,F31)) -> 0.03
A41: International | B41: =IF($B$4=1,B14,IF($B$4=2,B23,B32)) -> 0.02 | C41: =IF($B$4=1,C14,IF($B$4=2,C23,C32)) -> 0.03 | D41: =IF($B$4=1,D14,IF($B$4=2,D23,D32)) -> 0.03 | E41: =IF($B$4=1,E14,IF($B$4=2,E23,E32)) -> 0.03 | F41: =IF($B$4=1,F14,IF($B$4=2,F23,F32)) -> 0.03
A42: Intersegment eliminations | B42: =IF($B$4=1,B15,IF($B$4=2,B24,B33)) -> 0.03 | C42: =IF($B$4=1,C15,IF($B$4=2,C24,C33)) -> 0.03 | D42: =IF($B$4=1,D15,IF($B$4=2,D24,D33)) -> 0.03 | E42: =IF($B$4=1,E15,IF($B$4=2,E24,E33)) -> 0.03 | F42: =IF($B$4=1,F15,IF($B$4=2,F24,F33)) -> 0.03
A45: Base Segment Operating Margin
A46: Segment | B46: 2026E | C46: 2027E | D46: 2028E | E46: 2029E | F46: 2030E
A47: Beef | B47: -0.0191 | C47: -0.005 | D47: 0 | E47: 0.005 | F47: 0.01
A48: Pork | B48: 0.0462 | C48: 0.047 | D48: 0.048 | E48: 0.049 | F48: 0.05
A49: Chicken | B49: 0.1139 | C49: 0.112 | D49: 0.11 | E49: 0.108 | F49: 0.106
A50: Prepared Foods | B50: 0.1271 | C50: 0.128 | D50: 0.129 | E50: 0.13 | F50: 0.13
A51: International | B51: 0.0749 | C51: 0.076 | D51: 0.078 | E51: 0.079 | F51: 0.08
A53: Bull Segment Operating Margin
A54: Segment | B54: 2026E | C54: 2027E | D54: 2028E | E54: 2029E | F54: 2030E
A55: Beef | B55: -0.0041 | C55: 0.01 | D55: 0.015 | E55: 0.02 | F55: 0.025
A56: Pork | B56: 0.0612 | C56: 0.062 | D56: 0.063 | E56: 0.064 | F56: 0.065
A57: Chicken | B57: 0.1289 | C57: 0.127 | D57: 0.125 | E57: 0.123 | F57: 0.121
A58: Prepared Foods | B58: 0.1421 | C58: 0.143 | D58: 0.144 | E58: 0.145 | F58: 0.145
A59: International | B59: 0.0899 | C59: 0.091 | D59: 0.093 | E59: 0.094 | F59: 0.095
A61: Bear Segment Operating Margin
A62: Segment | B62: 2026E | C62: 2027E | D62: 2028E | E62: 2029E | F62: 2030E
A63: Beef | B63: -0.0391 | C63: -0.025 | D63: -0.02 | E63: -0.015 | F63: -0.01
A64: Pork | B64: 0.0262 | C64: 0.027 | D64: 0.028 | E64: 0.029 | F64: 0.03
A65: Chicken | B65: 0.0939 | C65: 0.092 | D65: 0.09 | E65: 0.088 | F65: 0.086
A66: Prepared Foods | B66: 0.1071 | C66: 0.108 | D66: 0.109 | E66: 0.11 | F66: 0.11
A67: International | B67: 0.0549 | C67: 0.056 | D67: 0.058 | E67: 0.059 | F67: 0.06
A69: Active Segment Operating Margin
A70: Segment | B70: 2026E | C70: 2027E | D70: 2028E | E70: 2029E | F70: 2030E
A71: Beef | B71: =IF($B$4=1,B47,IF($B$4=2,B55,B63)) -> -0.0191 | C71: =IF($B$4=1,C47,IF($B$4=2,C55,C63)) -> -0.005 | D71: =IF($B$4=1,D47,IF($B$4=2,D55,D63)) -> 0 | E71: =IF($B$4=1,E47,IF($B$4=2,E55,E63)) -> 0.005 | F71: =IF($B$4=1,F47,IF($B$4=2,F55,F63)) -> 0.01
A72: Pork | B72: =IF($B$4=1,B48,IF($B$4=2,B56,B64)) -> 0.0462 | C72: =IF($B$4=1,C48,IF($B$4=2,C56,C64)) -> 0.047 | D72: =IF($B$4=1,D48,IF($B$4=2,D56,D64)) -> 0.048 | E72: =IF($B$4=1,E48,IF($B$4=2,E56,E64)) -> 0.049 | F72: =IF($B$4=1,F48,IF($B$4=2,F56,F64)) -> 0.05
A73: Chicken | B73: =IF($B$4=1,B49,IF($B$4=2,B57,B65)) -> 0.1139 | C73: =IF($B$4=1,C49,IF($B$4=2,C57,C65)) -> 0.112 | D73: =IF($B$4=1,D49,IF($B$4=2,D57,D65)) -> 0.11 | E73: =IF($B$4=1,E49,IF($B$4=2,E57,E65)) -> 0.108 | F73: =IF($B$4=1,F49,IF($B$4=2,F57,F65)) -> 0.106
A74: Prepared Foods | B74: =IF($B$4=1,B50,IF($B$4=2,B58,B66)) -> 0.1271 | C74: =IF($B$4=1,C50,IF($B$4=2,C58,C66)) -> 0.128 | D74: =IF($B$4=1,D50,IF($B$4=2,D58,D66)) -> 0.129 | E74: =IF($B$4=1,E50,IF($B$4=2,E58,E66)) -> 0.13 | F74: =IF($B$4=1,F50,IF($B$4=2,F58,F66)) -> 0.13
A75: International | B75: =IF($B$4=1,B51,IF($B$4=2,B59,B67)) -> 0.0749 | C75: =IF($B$4=1,C51,IF($B$4=2,C59,C67)) -> 0.076 | D75: =IF($B$4=1,D51,IF($B$4=2,D59,D67)) -> 0.078 | E75: =IF($B$4=1,E51,IF($B$4=2,E59,E67)) -> 0.079 | F75: =IF($B$4=1,F51,IF($B$4=2,F59,F67)) -> 0.08
A78: Corporate, Financial & Valuation Inputs
A79: Corporate expense + amortization / sales | B79: 0.0172 | C79: FY26 midpoint informed by official guidance
A80: SG&A / sales | B80: 0.04 | C80: Analyst input anchored to recent history
A81: Tax rate | B81: 0.25 | C81: FY2026 official outlook
A82: FY2026 net interest expense | B82: 365 | C82: FY2026 official outlook
A83: Interest rate on average debt | B83: 0.045 | C83: Analyst input
A84: Depreciation / sales | B84: 0.02 | C84: Analyst input anchored to history
A85: Amortization / sales | B85: 0.005 | C85: Analyst input anchored to history
A86: Capex / sales | B86: 0.015 | C86: FY26 midpoint and normalized analyst input
A87: AR days | B87: 17 | C87: Analyst input anchored to FY25
A88: Inventory days | B88: 40 | C88: Analyst input anchored to FY25
A89: AP days | B89: 18.5 | C89: Analyst input anchored to FY25
A90: Other current assets / sales | B90: 0.009 | C90: Analyst input
... A107: FY2026 GAAP-to-adjusted items | B107: 0 | C107: Analyst assumption: no additional full-year comparability items modeled

Sheet Protein_Drivers
A1: Protein Economics & Volume-Price-Mix
A2: Tyson donor-company facts drive independent volume, price/mix and protein-input margin mechanics; they are not Panama assumptions
A6: Reported Sales Change Bridge
A7: Metric | B7: FY2024 vs FY2023 | C7: FY2025 vs FY2024 | D7: 6M FY2026 vs 6M FY2025
A8: Prior-period sales | B8: 52881 | C8: 53309 | D8: 26697
A9: Volume effect | B9: 19 | C9: -10 | D9: -354
A10: Average price effect | B10: 298 | C10: 1795 | D10: 1430
A11: Legal-contingency effect | B11: 111 | C11: -653 | D11: 193
A12: Calculated current sales | B12: =SUM(B8:B11) -> 53309 | C12: =SUM(C8:C11) -> 54441 | D12: =SUM(D8:D11) -> 27966
A13: Reported current sales | B13: 53309 | C13: 54441 | D13: 27966
A14: Bridge check | B14: =B12-B13 -> 0 | C14: =C12-C13 -> 0 | D14: =D12-D13 -> 0
A17: Segment Volume / Average Price
A18: Segment | B18: FY25 volume | C18: FY25 price | D18: 6M FY26 volume | E18: 6M FY26 price
A19: Beef | B19: -0.019 | C19: 0.09 | D19: -0.101 | E19: 0.143
A20: Pork | B20: -0.017 | C20: 0.053 | D20: 0.03 | E20: 0.014
A21: Chicken | B21: 0.026 | C21: -0.001 | D21: 0.027 | E21: 0.009
A22: Prepared Foods | B22: -0.025 | C22: 0.033 | D22: 0.003 | E22: 0.062
A23: International | D23: -0.009 | E23: 0.017
A26: Reported Cost-of-Sales Change Bridge
A27: Metric | B27: FY2024 vs FY2023 | C27: FY2025 vs FY2024 | D27: 6M FY2026 vs 6M FY2025
A28: Prior-period cost of sales | B28: 50250 | C28: 49682 | D28: 25002
A29: Volume effect | B29: 18 | C29: -10 | D29: -328
A30: Input cost / pound effect | B30: -586 | C30: 1207 | D30: 1522
A31: Calculated current cost of sales | B31: =SUM(B28:B30) -> 49682 | C31: =SUM(C28:C30) -> 50879 | D31: =SUM(D28:D30) -> 26196
A32: Reported current cost of sales | B32: 49682 | C32: 50879 | D32: 26196
A33: Bridge check | B33: =B31-B32 -> 0 | C33: =C31-C32 -> 0 | D33: =D31-D32 -> 0
A36: Input-Cost Decomposition
A37: Driver | B37: FY2025 vs FY2024 | C37: 6M FY2026 vs 6M FY2025
A38: Live cattle / Beef | B38: 1840 | C38: 1450
A39: Prepared Foods raw materials | B39: 345 | C39: 160
A40: Live hogs / Pork | B40: 295 | C40: 55
A41: Chicken feed ingredients | B41: -340 | C41: -60
A42: Freight and transportation | B42: -110 | C42: 45
A43: Restructuring charges | B43: 43 | C43: 33
A44: Legal contingency accruals | B44: -89 | C44: 21
A45: Plant closures and disposals | B45: -165 | C45: -23
A46: Commodity derivatives | C46: -57
A47: Facility fire / insurance | B47: -34
A48: Other mix, operating costs and productivity (derived residual) | B48: =B50-SUM(B38:B47) -> -578 | C48: =C50-SUM(C38:C47) -> -102
A49: Decomposed total | B49: =SUM(B38:B48) -> 1207 | C49: =SUM(C38:C48) -> 1522
A50: Reported input cost / pound effect | B50: 1207 | C50: 1522
A51: Reconciliation check | B51: =B49-B50 -> 0 | C51: =C49-C50 -> 0
A54: Forecast Base Volume Inputs
A55: Segment | B55: 2026E | C55: 2027E | D55: 2028E | E55: 2029E | F55: 2030E
A56: Beef | B56: -0.02 | C56: 0 | D56: 0 | E56: 0 | F56: 0
A57: Pork | B57: 0.02 | C57: 0.01 | D57: 0.01 | E57: 0.01 | F57: 0.01
A58: Chicken | B58: 0.02 | C58: 0.02 | D58: 0.02 | E58: 0.02 | F58: 0.02
A59: Prepared Foods | B59: 0.005 | C59: 0.01 | D59: 0.01 | E59: 0.01 | F59: 0.01
A60: International | B60: 0 | C60: 0.01 | D60: 0.01 | E60: 0.01 | F60: 0.01
A61: Intersegment eliminations | B61: 0 | C61: 0 | D61: 0 | E61: 0 | F61: 0
A64: Active Volume + Independent Price / Mix + Derived Total Growth
A65: Segment | B65: 2026E Vol. | C65: 2027E Vol. | D65: 2028E Vol. | E65: 2029E Vol. | F65: 2030E Vol. | G65: 2026E Price/Mix | H65: 2027E Price/Mix | I65: 2028E Price/Mix | J65: 2029E Price/Mix | K65: 2030E Price/Mix | L65: 2026E Total Growth | M65: 2027E Total Growth | N65: 2028E Total Growth | O65: 2029E Total Growth | P65: 2030E Total Growth
A66: Beef | B66: =B56+IF(Assumptions!$B$4=2,1%,IF(Assumptions!$B$4=3,-1%,0)) -> -0.02 | C66: =C56+IF(Assumptions!$B$4=2,1%,IF(Assumptions!$B$4=3,-1%,0)) -> 0 | D66: =D56+IF(Assumptions!$B$4=2,1%,IF(Assumptions!$B$4=3,-1%,0)) -> 0 | E66: =E56+IF(Assumptions!$B$4=2,1%,IF(Assumptions!$B$4=3,-1%,0)) -> 0 | F66: =F56+IF(Assumptions!$B$4=2,1%,IF(Assumptions!$B$4=3,-1%,0)) -> 0 | G66: =Assumptions!B37 -> 0.03 | H66: =Assumptions!C37 -> 0.02 | I66: =Assumptions!D37 -> 0.02 | J66: =Assumptions!E37 -> 0.02 | K66: =Assumptions!F37 -> 0.02 | L66: =(1+B66)*(1+G66)-1 -> 0.0094 | M66: =(1+C66)*(1+H66)-1 -> 0.02 | N66: =(1+D66)*(1+I66)-1 -> 0.02 | O66: =(1+E66)*(1+J66)-1 -> 0.02 | P66: =(1+F66)*(1+K66)-1 -> 0.02
A67: Pork | B67: =B57+IF(Assumptions!$B$4=2,1%,IF(Assumptions!$B$4=3,-1%,0)) -> 0.02 | C67: =C57+IF(Assumptions!$B$4=2,1%,IF(Assumptions!$B$4=3,-1%,0)) -> 0.01 | D67: =D57+IF(Assumptions!$B$4=2,1%,IF(Assumptions!$B$4=3,-1%,0)) -> 0.01 | E67: =E57+IF(Assumptions!$B$4=2,1%,IF(Assumptions!$B$4=3,-1%,0)) -> 0.01 | F67: =F57+IF(Assumptions!$B$4=2,1%,IF(Assumptions!$B$4=3,-1%,0)) -> 0.01 | G67: =Assumptions!B38 -> 0.03 | H67: =Assumptions!C38 -> 0.02 | I67: =Assumptions!D38 -> 0.02 | J67: =Assumptions!E38 -> 0.02 | K67: =Assumptions!F38 -> 0.02 | L67: =(1+B67)*(1+G67)-1 -> 0.0506 | M67: =(1+C67)*(1+H67)-1 -> 0.0302 | N67: =(1+D67)*(1+I67)-1 -> 0.0302 | O67: =(1+E67)*(1+J67)-1 -> 0.0302 | P67: =(1+F67)*(1+K67)-1 -> 0.0302
A68: Chicken | B68: =B58+IF(Assumptions!$B$4=2,1%,IF(Assumptions!$B$4=3,-1%,0)) -> 0.02 | C68: =C58+IF(Assumptions!$B$4=2,1%,IF(Assumptions!$B$4=3,-1%,0)) -> 0.02 | D68: =D58+IF(Assumptions!$B$4=2,1%,IF(Assumptions!$B$4=3,-1%,0)) -> 0.02 | E68: =E58+IF(Assumptions!$B$4=2,1%,IF(Assumptions!$B$4=3,-1%,0)) -> 0.02 | F68: =F58+IF(Assumptions!$B$4=2,1%,IF(Assumptions!$B$4=3,-1%,0)) -> 0.02 | G68: =Assumptions!B39 -> 0.03 | H68: =Assumptions!C39 -> 0.03 | I68: =Assumptions!D39 -> 0.03 | J68: =Assumptions!E39 -> 0.03 | K68: =Assumptions!F39 -> 0.03 | L68: =(1+B68)*(1+G68)-1 -> 0.0506 | M68: =(1+C68)*(1+H68)-1 -> 0.0506 | N68: =(1+D68)*(1+I68)-1 -> 0.0506 | O68: =(1+E68)*(1+J68)-1 -> 0.0506 | P68: =(1+F68)*(1+K68)-1 -> 0.0506
A69: Prepared Foods | B69: =B59+IF(Assumptions!$B$4=2,1%,IF(Assumptions!$B$4=3,-1%,0)) -> 0.005 | C69: =C59+IF(Assumptions!$B$4=2,1%,IF(Assumptions!$B$4=3,-1%,0)) -> 0.01 | D69: =D59+IF(Assumptions!$B$4=2,1%,IF(Assumptions!$B$4=3,-1%,0)) -> 0.01 | E69: =E59+IF(Assumptions!$B$4=2,1%,IF(Assumptions!$B$4=3,-1%,0)) -> 0.01 | F69: =F59+IF(Assumptions!$B$4=2,1%,IF(Assumptions!$B$4=3,-1%,0)) -> 0.01 | G69: =Assumptions!B40 -> 0.03 | H69: =Assumptions!C40 -> 0.03 | I69: =Assumptions!D40 -> 0.03 | J69: =Assumptions!E40 -> 0.03 | K69: =Assumptions!F40 -> 0.03 | L69: =(1+B69)*(1+G69)-1 -> 0.03515 | M69: =(1+C69)*(1+H69)-1 -> 0.0403 | N69: =(1+D69)*(1+I69)-1 -> 0.0403 | O69: =(1+E69)*(1+J69)-1 -> 0.0403 | P69: =(1+F69)*(1+K69)-1 -> 0.0403
A70: International | B70: =B60+IF(Assumptions!$B$4=2,1%,IF(Assumptions!$B$4=3,-1%,0)) -> 0 | C70: =C60+IF(Assumptions!$B$4=2,1%,IF(Assumptions!$B$4=3,-1%,0)) -> 0.01 | D70: =D60+IF(Assumptions!$B$4=2,1%,IF(Assumptions!$B$4=3,-1%,0)) -> 0.01 | E70: =E60+IF(Assumptions!$B$4=2,1%,IF(Assumptions!$B$4=3,-1%,0)) -> 0.01 | F70: =F60+IF(Assumptions!$B$4=2,1%,IF(Assumptions!$B$4=3,-1%,0)) -> 0.01 | G70: =Assumptions!B41 -> 0.02 | H70: =Assumptions!C41 -> 0.03 | I70: =Assumptions!D41 -> 0.03 | J70: =Assumptions!E41 -> 0.03 | K70: =Assumptions!F41 -> 0.03 | L70: =(1+B70)*(1+G70)-1 -> 0.02 | M70: =(1+C70)*(1+H70)-1 -> 0.0403 | N70: =(1+D70)*(1+I70)-1 -> 0.0403 | O70: =(1+E70)*(1+J70)-1 -> 0.0403 | P70: =(1+F70)*(1+K70)-1 -> 0.0403
A71: Intersegment eliminations | B71: =B61+0 -> 0 | C71: =C61+0 -> 0 | D71: =D61+0 -> 0 | E71: =E61+0 -> 0 | F71: =F61+0 -> 0 | G71: =Assumptions!B42 -> 0.03 | H71: =Assumptions!C42 -> 0.03 | I71: =Assumptions!D42 -> 0.03 | J71: =Assumptions!E42 -> 0.03 | K71: =Assumptions!F42 -> 0.03 | L71: =(1+B71)*(1+G71)-1 -> 0.03 | M71: =(1+C71)*(1+H71)-1 -> 0.03 | N71: =(1+D71)*(1+I71)-1 -> 0.03 | O71: =(1+E71)*(1+J71)-1 -> 0.03 | P71: =(1+F71)*(1+K71)-1 -> 0.03
A74: Active Protein Input-Cost / Productivity Margin Overlay
A75: Segment | B75: 2026E | C75: 2027E | D75: 2028E | E75: 2029E | F75: 2030E
A76: Beef | B76: =IF(Assumptions!$B$4=1,0,IF(Assumptions!$B$4=2,B85,-B85)) -> 0 | C76: =IF(Assumptions!$B$4=1,0,IF(Assumptions!$B$4=2,C85,-C85)) -> 0 | D76: =IF(Assumptions!$B$4=1,0,IF(Assumptions!$B$4=2,D85,-D85)) -> 0 | E76: =IF(Assumptions!$B$4=1,0,IF(Assumptions!$B$4=2,E85,-E85)) -> 0 | F76: =IF(Assumptions!$B$4=1,0,IF(Assumptions!$B$4=2,F85,-F85)) -> 0
A77: Pork | B77: =IF(Assumptions!$B$4=1,0,IF(Assumptions!$B$4=2,B86,-B86)) -> 0 | C77: =IF(Assumptions!$B$4=1,0,IF(Assumptions!$B$4=2,C86,-C86)) -> 0 | D77: =IF(Assumptions!$B$4=1,0,IF(Assumptions!$B$4=2,D86,-D86)) -> 0 | E77: =IF(Assumptions!$B$4=1,0,IF(Assumptions!$B$4=2,E86,-E86)) -> 0 | F77: =IF(Assumptions!$B$4=1,0,IF(Assumptions!$B$4=2,F86,-F86)) -> 0
A78: Chicken | B78: =IF(Assumptions!$B$4=1,0,IF(Assumptions!$B$4=2,B87,-B87)) -> 0 | C78: =IF(Assumptions!$B$4=1,0,IF(Assumptions!$B$4=2,C87,-C87)) -> 0 | D78: =IF(Assumptions!$B$4=1,0,IF(Assumptions!$B$4=2,D87,-D87)) -> 0 | E78: =IF(Assumptions!$B$4=1,0,IF(Assumptions!$B$4=2,E87,-E87)) -> 0 | F78: =IF(Assumptions!$B$4=1,0,IF(Assumptions!$B$4=2,F87,-F87)) -> 0
A79: Prepared Foods | B79: =IF(Assumptions!$B$4=1,0,IF(Assumptions!$B$4=2,B88,-B88)) -> 0 | C79: =IF(Assumptions!$B$4=1,0,IF(Assumptions!$B$4=2,C88,-C88)) -> 0 | D79: =IF(Assumptions!$B$4=1,0,IF(Assumptions!$B$4=2,D88,-D88)) -> 0 | E79: =IF(Assumptions!$B$4=1,0,IF(Assumptions!$B$4=2,E88,-E88)) -> 0 | F79: =IF(Assumptions!$B$4=1,0,IF(Assumptions!$B$4=2,F88,-F88)) -> 0
A80: International | B80: =IF(Assumptions!$B$4=1,0,IF(Assumptions!$B$4=2,B89,-B89)) -> 0 | C80: =IF(Assumptions!$B$4=1,0,IF(Assumptions!$B$4=2,C89,-C89)) -> 0 | D80: =IF(Assumptions!$B$4=1,0,IF(Assumptions!$B$4=2,D89,-D89)) -> 0 | E80: =IF(Assumptions!$B$4=1,0,IF(Assumptions!$B$4=2,E89,-E89)) -> 0 | F80: =IF(Assumptions!$B$4=1,0,IF(Assumptions!$B$4=2,F89,-F89)) -> 0
A83: Bull / Bear Margin-Overlay Magnitudes
A84: Segment / economic mechanism | B84: 2026E | C84: 2027E | D84: 2028E | E84: 2029E | F84: 2030E
A85: Beef - cattle availability / cost | B85: 0.015 | C85: 0.01 | D85: 0.0075 | E85: 0.005 | F85: 0.005
A86: Pork - hog cost / live operations | B86: 0.01 | C86: 0.0075 | D86: 0.005 | E86: 0.005 | F86: 0.005
A87: Chicken - feed / live performance | B87: 0.01 | C87: 0.0075 | D87: 0.005 | E87: 0.005 | F87: 0.005
A88: Prepared Foods - raw materials / pass-through | B88: 0.0075 | C88: 0.005 | D88: 0.005 | E88: 0.005 | F88: 0.005
A89: International - raw materials / execution | B89: 0.005 | C89: 0.005 | D89: 0.005 | E89: 0.005 | F89: 0.005

Sheet Forecast_3Stmt
A1: Integrated Three-Statement Forecast
A2: FY2026E-FY2030E; 53rd week bridged explicitly; USD millions except per-share data
A4: Metric | B4: 2025A | C4: 2026E | D4: 2027E | E4: 2028E | F4: 2029E | G4: 2030E
A6: Income Statement
A7: Sales | B7: 54441 | C7: =Segment_Build!G13 -> 57202.244 | D7: =Segment_Build!H13 -> 59200.932 | E7: =Segment_Build!I13 -> 61279.299 | F7: =Segment_Build!J13 -> 63440.813 | G7: =Segment_Build!K13 -> 65689.103
A8: Growth | C8: =C7/B7-1 -> 0.050719938 | D8: =D7/C7-1 -> 0.034940722 | E8: =E7/D7-1 -> 0.035106994 | F8: =F7/E7-1 -> 0.035273158 | G8: =G7/F7-1 -> 0.035439168
A9: Cost of sales | B9: 50879 | C9: =C7-C10 -> 52473.437 | D9: =D7-D10 -> 53960.066 | E9: =E7-E10 -> 55714.122 | F9: =F7-F10 -> 57541.552 | G9: =G7-G10 -> 59455.39
A10: Gross profit | B10: 3562 | C10: =SUM(C11:C12) -> 4728.8066 | D10: =SUM(D11:D12) -> 5240.8656 | E10: =SUM(E11:E12) -> 5565.1769 | F10: =SUM(F11:F12) -> 5899.261 | G10: =SUM(G11:G12) -> 6233.713
A11: SG&A | B11: 2121 | C11: =C7*Assumptions!$B$80 -> 2288.0898 | D11: =D7*Assumptions!$B$80 -> 2368.0373 | E11: =E7*Assumptions!$B$80 -> 2451.1719 | F11: =F7*Assumptions!$B$80 -> 2537.6325 | G11: =G7*Assumptions!$B$80 -> 2627.5641
A12: Operating income | B12: 1098 | C12: =Segment_Build!G24 -> 2440.7169 | D12: =Segment_Build!H24 -> 2872.8283 | E12: =Segment_Build!I24 -> 3114.005 | F12: =Segment_Build!J24 -> 3361.6285 | G12: =Segment_Build!K24 -> 3606.1489
A13: Operating margin | B13: 0.0202 | C13: =C12/C7 -> 0.042668201 | D13: =D12/D7 -> 0.048526742 | E13: =E12/E7 -> 0.050816589 | F13: =F12/F7 -> 0.052988421 | G13: =G12/G7 -> 0.054897217
A14: Interest income | B14: 73 | C14: =Schedules!B36*Assumptions!$B$98 -> 12.29 | D14: =Schedules!C36*Assumptions!$B$98 -> 11.440449 | E14: =Schedules!D36*Assumptions!$B$98 -> 11.840186 | F14: =Schedules!E36*Assumptions!$B$98 -> 12.25586 | G14: =Schedules!F36*Assumptions!$B$98 -> 12.688163
A15: Interest expense | B15: 449 | C15: =Schedules!C33 -> 365 | D15: =Schedules!D33 -> 346.12144 | E15: =Schedules!E33 -> 282.21389 | F15: =Schedules!F33 -> 212.92068 | G15: =Schedules!G33 -> 137.49037
A16: Income before taxes | B16: 769 | C16: =SUM(C12,C14)-C15 -> 2088.0069 | D16: =SUM(D12,D14)-D15 -> 2538.1474 | E16: =SUM(E12,E14)-E15 -> 2843.6312 | F16: =SUM(F12,F14)-F15 -> 3160.9637 | G16: =SUM(G12,G14)-G15 -> 3481.3467
A17: Income tax expense | B17: 262 | C17: =C16*Assumptions!$B$81 -> 522.00172 | D17: =D16*Assumptions!$B$81 -> 634.53684 | E17: =E16*Assumptions!$B$81 -> 710.90781 | F17: =F16*Assumptions!$B$81 -> 790.24093 | G17: =G16*Assumptions!$B$81 -> 870.33667
A18: Net income including NCI | B18: 507 | C18: =C16-C17 -> 1566.0052 | D18: =D16-D17 -> 1903.6105 | E18: =E16-E17 -> 2132.7234 | F18: =F16-F17 -> 2370.7228 | G18: =G16-G17 -> 2611.01
A19: Net income attributable to NCI | B19: 33 | C19: =C18*Assumptions!$B$99 -> 31.320103 | D19: =D18*Assumptions!$B$99 -> 38.07221 | E19: =E18*Assumptions!$B$99 -> 42.654469 | F19: =F18*Assumptions!$B$99 -> 47.414456 | G19: =G18*Assumptions!$B$99 -> 52.2202
A20: Net income attributable to Tyson | B20: 474 | C20: =C18-C19 -> 1534.685 | D20: =D18-D19 -> 1865.5383 | E20: =E18-E19 -> 2090.069 | F20: =F18-F19 -> 2323.3083 | G20: =G18-G19 -> 2558.7898
A21: Diluted shares | B21: 357 | C21: =Schedules!C43 -> 354 | D21: =Schedules!D43 -> 354 | E21: =Schedules!E43 -> 354 | F21: =Schedules!F43 -> 354 | G21: =Schedules!G43 -> 354
A22: Diluted EPS | B22: 1.33 | C22: =C20/C21 -> 4.3352685 | D22: =D20/D21 -> 5.2698822 | E22: =E20/E21 -> 5.9041496 | F22: =F20/F21 -> 6.5630179 | G22: =G20/G21 -> 7.2282198
A25: Balance Sheet
A26: Cash | B26: 1229 | C26: =Schedules!C36 -> 1144.0449 | D26: =Schedules!D36 -> 1184.0186 | E26: =Schedules!E36 -> 1225.586 | F26: =Schedules!F36 -> 1268.8163 | G26: =Schedules!G36 -> 1313.7821
A27: Accounts receivable | B27: 2524 | C27: =Schedules!C8 -> 2664.2141 | D27: =Schedules!D8 -> 2757.3037 | E27: =Schedules!E8 -> 2854.1043 | F27: =Schedules!F8 -> 2954.7776 | G27: =Schedules!G8 -> 3059.4925
A28: Inventories | B28: 5681 | C28: =Schedules!C10 -> 5750.5137 | D28: =Schedules!D10 -> 5913.4319 | E28: =Schedules!E10 -> 6105.6572 | F28: =Schedules!F10 -> 6305.9235 | G28: =Schedules!G10 -> 6515.6591
A29: Other current assets | B29: 482 | C29: =Schedules!C14 -> 514.8202 | D29: =Schedules!D14 -> 532.80839 | E29: =Schedules!E14 -> 551.51369 | F29: =Schedules!F14 -> 570.96732 | G29: =Schedules!G14 -> 591.20192
A30: Total current assets | B30: 9916 | C30: =SUM(C26:C29) -> 10073.593 | D30: =SUM(D26:D29) -> 10387.563 | E30: =SUM(E26:E29) -> 10736.861 | F30: =SUM(F26:F29) -> 11100.485 | G30: =SUM(G26:G29) -> 11480.136
A31: Net PP&E | B31: 9204 | C31: =Schedules!C23 -> 8917.9888 | D31: =Schedules!D23 -> 8621.9841 | E31: =Schedules!E23 -> 8315.5876 | F31: =Schedules!F23 -> 7998.3836 | G31: =Schedules!G23 -> 7669.938
A32: Goodwill | B32: 9469 | C32: =B32*(1+Assumptions!$B$103) -> 9469 | D32: =C32*(1+Assumptions!$B$103) -> 9469 | E32: =D32*(1+Assumptions!$B$103) -> 9469 | F32: =E32*(1+Assumptions!$B$103) -> 9469 | G32: =F32*(1+Assumptions!$B$103) -> 9469
A33: Intangible assets | B33: 5624 | C33: =Schedules!C25 -> 5337.9888 | D33: =Schedules!D25 -> 5041.9841 | E33: =Schedules!E25 -> 4735.5876 | F33: =Schedules!F25 -> 4418.3836 | G33: =Schedules!G25 -> 4089.938
A34: Other assets | B34: 2445 | C34: =B34*(1+Assumptions!$B$104) -> 2445 | D34: =C34*(1+Assumptions!$B$104) -> 2445 | E34: =D34*(1+Assumptions!$B$104) -> 2445 | F34: =E34*(1+Assumptions!$B$104) -> 2445 | G34: =F34*(1+Assumptions!$B$104) -> 2445
A35: Total assets | B35: 36658 | C35: =SUM(C30:C34) -> 36243.57 | D35: =SUM(D30:D34) -> 35965.531 | E35: =SUM(E30:E34) -> 35702.036 | F35: =SUM(F30:F34) -> 35431.252 | G35: =SUM(G30:G34) -> 35154.012
A36: Current debt | B36: 909 | C36: =Schedules!C31 -> 769.15875 | D36: =Schedules!D31 -> 627.14199 | E36: =Schedules!E31 -> 473.15707 | F36: =Schedules!F31 -> 305.53416 | G36: =Schedules!G31 -> 124.15657
A37: Accounts payable | B37: 2601 | C37: =Schedules!C12 -> 2659.6126 | D37: =Schedules!D12 -> 2734.9623 | E37: =Schedules!E12 -> 2823.8664 | F37: =Schedules!F12 -> 2916.4896 | G37: =Schedules!G12 -> 3013.4924
A38: Other current liabilities | B38: 2879 | C38: =Schedules!C16 -> 2745.7077 | D38: =Schedules!D16 -> 2841.6447 | E38: =Schedules!E16 -> 2941.4063 | F38: =Schedules!F16 -> 3045.159 | G38: =Schedules!G16 -> 3153.0769
A39: Total current liabilities | B39: 6389 | C39: =SUM(C36:C38) -> 6174.4791 | D39: =SUM(D36:D38) -> 6203.749 | E39: =SUM(E36:E38) -> 6238.4298 | F39: =SUM(F36:F38) -> 6267.1828 | G39: =SUM(G36:G38) -> 6290.7258
A40: Long-term debt | B40: 7921 | C40: =Schedules!C32 -> 6922.4288 | D40: =Schedules!D32 -> 5644.2779 | E40: =Schedules!E32 -> 4258.4136 | F40: =Schedules!F32 -> 2749.8074 | G40: =Schedules!G32 -> 1117.4091
A41: Deferred income taxes | B41: 2195 | C41: =B41*(1+Assumptions!$B$105) -> 2195 | D41: =C41*(1+Assumptions!$B$105) -> 2195 | E41: =D41*(1+Assumptions!$B$105) -> 2195 | F41: =E41*(1+Assumptions!$B$105) -> 2195 | G41: =F41*(1+Assumptions!$B$105) -> 2195
A42: Other liabilities | B42: 1926 | C42: =B42*(1+Assumptions!$B$106) -> 1926 | D42: =C42*(1+Assumptions!$B$106) -> 1926 | E42: =D42*(1+Assumptions!$B$106) -> 1926 | F42: =E42*(1+Assumptions!$B$106) -> 1926 | G42: =F42*(1+Assumptions!$B$106) -> 1926
A43: Total liabilities | B43: 18431 | C43: =SUM(C39:C42) -> 17217.908 | D43: =SUM(D39:D42) -> 15969.027 | E43: =SUM(E39:E42) -> 14617.843 | F43: =SUM(F39:F42) -> 13137.99 | G43: =SUM(G39:G42) -> 11529.135
A44: Equity attributable to Tyson | B44: 18085 | C44: =Schedules!C41 -> 18852.343 | D44: =Schedules!D41 -> 19785.112 | E44: =Schedules!E41 -> 20830.146 | F44: =Schedules!F41 -> 21991.8 | G44: =Schedules!G41 -> 23271.195
A45: Equity attributable to NCI | B45: 142 | C45: =Schedules!C42 -> 173.3201 | D45: =Schedules!D42 -> 211.39231 | E45: =Schedules!E42 -> 254.04678 | F45: =Schedules!F42 -> 301.46124 | G45: =Schedules!G42 -> 353.68144
A46: Total equity | B46: 18227 | C46: =SUM(C44:C45) -> 19025.663 | D46: =SUM(D44:D45) -> 19996.504 | E46: =SUM(E44:E45) -> 21084.193 | F46: =SUM(F44:F45) -> 22293.262 | G46: =SUM(G44:G45) -> 23624.877
A47: Total liabilities and equity | B47: 36658 | C47: =SUM(C43,C46) -> 36243.57 | D47: =SUM(D43,D46) -> 35965.531 | E47: =SUM(E43,E46) -> 35702.036 | F47: =SUM(F43,F46) -> 35431.252 | G47: =SUM(G43,G46) -> 35154.012
A48: Balance sheet check | B48: 0 | C48: =C35-C47 -> 0 | D48: =D35-D47 -> 0 | E48: =E35-E47 -> 0 | F48: =F35-F47 -> 0 | G48: =G35-G47 -> 0
A51: Cash Flow Statement
A52: Net income including NCI | B52: 507 | C52: =C18 -> 1566.0052 | D52: =D18 -> 1903.6105 | E52: =E18 -> 2132.7234 | F52: =F18 -> 2370.7228 | G52: =G18 -> 2611.01
A53: Depreciation | B53: 1093 | C53: =Schedules!C22 -> 1144.0449 | D53: =Schedules!D22 -> 1184.0186 | E53: =Schedules!E22 -> 1225.586 | F53: =Schedules!F22 -> 1268.8163 | G53: =Schedules!G22 -> 1313.7821
A54: Amortization | B54: 268 | C54: =Schedules!C24 -> 286.01122 | D54: =Schedules!D24 -> 296.00466 | E54: =Schedules!E24 -> 306.39649 | F54: =Schedules!F24 -> 317.20406 | G54: =Schedules!G24 -> 328.44551
A55: Change in operating NWC | B55: -352 | C55: =-Schedules!C18 -> -317.2277 | D55: =-Schedules!D18 -> -102.70928 | E55: =-Schedules!E18 -> -119.06542 | F55: =-Schedules!F18 -> -124.01736 | G55: =-Schedules!G18 -> -129.76447
A56: Cash from operating activities | B56: 2155 | C56: =SUM(C52:C55) -> 2678.8336 | D56: =SUM(D52:D55) -> 3280.9245 | E56: =SUM(E52:E55) -> 3545.6405 | F56: =SUM(F52:F55) -> 3832.7257 | G56: =SUM(G52:G55) -> 4123.4731
A57: Capital expenditures | B57: -978 | C57: =-Schedules!C21 -> -858.03366 | D57: =-Schedules!D21 -> -888.01398 | E57: =-Schedules!E21 -> -919.18948 | F57: =-Schedules!F21 -> -951.61219 | G57: =-Schedules!G21 -> -985.33654
A58: Cash used for investing activities | B58: -665 | C58: =C57 -> -858.03366 | D58: =D57 -> -888.01398 | E58: =E57 -> -919.18948 | F58: =F57 -> -951.61219 | G58: =G57 -> -985.33654
A59: Debt issuance / (repayment) | B59: -957 | C59: =Schedules!C29 -> -1138.4125 | D59: =Schedules!D29 -> -1420.1676 | E59: =Schedules!E29 -> -1539.8492 | F59: =Schedules!F29 -> -1676.2291 | G59: =Schedules!G29 -> -1813.7759
A60: Dividends | B60: -697 | C60: =Schedules!C40 -> -767.34252 | D60: =Schedules!D40 -> -932.76915 | E60: =Schedules!E40 -> -1045.0345 | F60: =Schedules!F40 -> -1161.6542 | G60: =Schedules!G40 -> -1279.3949
A61: Cash from financing activities | B61: -1977 | C61: =SUM(C59:C60) -> -1905.755 | D61: =SUM(D59:D60) -> -2352.9368 | E61: =SUM(E59:E60) -> -2584.8837 | F61: =SUM(F59:F60) -> -2837.8833 | G61: =SUM(G59:G60) -> -3093.1708
A62: Change in cash | B62: -488 | C62: =SUM(C56,C58,C61) -> -84.955117 | D62: =SUM(D56,D58,D61) -> 39.973754 | E62: =SUM(E56,E58,E61) -> 41.567336 | F62: =SUM(F56,F58,F61) -> 43.230288 | G62: =SUM(G56,G58,G61) -> 44.965793
A63: Ending cash | B63: 1229 | C63: =B63+C62 -> 1144.0449 | D63: =C63+D62 -> 1184.0186 | E63: =D63+E62 -> 1225.586 | F63: =E63+F62 -> 1268.8163 | G63: =F63+G62 -> 1313.7821
A64: Free cash flow | B64: 1177 | C64: =SUM(C56,C57) -> 1820.7999 | D64: =SUM(D56,D57) -> 2392.9105 | E64: =SUM(E56,E57) -> 2626.451 | F64: =SUM(F56,F57) -> 2881.1135 | G64: =SUM(G56,G57) -> 3138.1366

Sheet Schedules
A1: Operating, Debt & Share Schedules
A2: Debt repayment is capped at beginning debt; excess cash accumulates above the minimum cash floor
A4: Metric | B4: 2025A | C4: 2026E | D4: 2027E | E4: 2028E | F4: 2029E | G4: 2030E
A6: Working Capital
A7: AR days | B7: 16.9 | C7: =Assumptions!$B$87 -> 17 | D7: =Assumptions!$B$87 -> 17 | E7: =Assumptions!$B$87 -> 17 | F7: =Assumptions!$B$87 -> 17 | G7: =Assumptions!$B$87 -> 17
A8: Accounts receivable | B8: 2524 | C8: =Forecast_3Stmt!C7*C7/365 -> 2664.2141 | D8: =Forecast_3Stmt!D7*D7/365 -> 2757.3037 | E8: =Forecast_3Stmt!E7*E7/365 -> 2854.1043 | F8: =Forecast_3Stmt!F7*F7/365 -> 2954.7776 | G8: =Forecast_3Stmt!G7*G7/365 -> 3059.4925
A9: Inventory days | B9: 40.8 | C9: =Assumptions!$B$88 -> 40 | D9: =Assumptions!$B$88 -> 40 | E9: =Assumptions!$B$88 -> 40 | F9: =Assumptions!$B$88 -> 40 | G9: =Assumptions!$B$88 -> 40
A10: Inventory | B10: 5681 | C10: =Forecast_3Stmt!C9*C9/365 -> 5750.5137 | D10: =Forecast_3Stmt!D9*D9/365 -> 5913.4319 | E10: =Forecast_3Stmt!E9*E9/365 -> 6105.6572 | F10: =Forecast_3Stmt!F9*F9/365 -> 6305.9235 | G10: =Forecast_3Stmt!G9*G9/365 -> 6515.6591
A11: AP days | B11: 18.7 | C11: =Assumptions!$B$89 -> 18.5 | D11: =Assumptions!$B$89 -> 18.5 | E11: =Assumptions!$B$89 -> 18.5 | F11: =Assumptions!$B$89 -> 18.5 | G11: =Assumptions!$B$89 -> 18.5
A12: Accounts payable | B12: 2601 | C12: =Forecast_3Stmt!C9*C11/365 -> 2659.6126 | D12: =Forecast_3Stmt!D9*D11/365 -> 2734.9623 | E12: =Forecast_3Stmt!E9*E11/365 -> 2823.8664 | F12: =Forecast_3Stmt!F9*F11/365 -> 2916.4896 | G12: =Forecast_3Stmt!G9*G11/365 -> 3013.4924
A13: Other current assets / sales | B13: 0.0089 | C13: =Assumptions!$B$90 -> 0.009 | D13: =Assumptions!$B$90 -> 0.009 | E13: =Assumptions!$B$90 -> 0.009 | F13: =Assumptions!$B$90 -> 0.009 | G13: =Assumptions!$B$90 -> 0.009
A14: Other current assets | B14: 482 | C14: =Forecast_3Stmt!C7*C13 -> 514.8202 | D14: =Forecast_3Stmt!D7*D13 -> 532.80839 | E14: =Forecast_3Stmt!E7*E13 -> 551.51369 | F14: =Forecast_3Stmt!F7*F13 -> 570.96732 | G14: =Forecast_3Stmt!G7*G13 -> 591.20192
A15: Other current liabilities / sales | B15: 0.0529 | C15: =Assumptions!$B$91 -> 0.048 | D15: =Assumptions!$B$91 -> 0.048 | E15: =Assumptions!$B$91 -> 0.048 | F15: =Assumptions!$B$91 -> 0.048 | G15: =Assumptions!$B$91 -> 0.048
A16: Other current liabilities | B16: 2879 | C16: =Forecast_3Stmt!C7*C15 -> 2745.7077 | D16: =Forecast_3Stmt!D7*D15 -> 2841.6447 | E16: =Forecast_3Stmt!E7*E15 -> 2941.4063 | F16: =Forecast_3Stmt!F7*F15 -> 3045.159 | G16: =Forecast_3Stmt!G7*G15 -> 3153.0769
A17: Operating NWC | B17: 3207 | C17: =SUM(C8,C10,C14)-SUM(C12,C16) -> 3524.2277 | D17: =SUM(D8,D10,D14)-SUM(D12,D16) -> 3626.937 | E17: =SUM(E8,E10,E14)-SUM(E12,E16) -> 3746.0024 | F17: =SUM(F8,F10,F14)-SUM(F12,F16) -> 3870.0198 | G17: =SUM(G8,G10,G14)-SUM(G12,G16) -> 3999.7842
A18: Change in operating NWC | C18: =C17-B17 -> 317.2277 | D18: =D17-C17 -> 102.70928 | E18: =E17-D17 -> 119.06542 | F18: =F17-E17 -> 124.01736 | G18: =G17-F17 -> 129.76447
A20: PP&E and Intangibles
A21: Capital expenditures | B21: 978 | C21: =Forecast_3Stmt!C7*Assumptions!$B$86 -> 858.03366 | D21: =Forecast_3Stmt!D7*Assumptions!$B$86 -> 888.01398 | E21: =Forecast_3Stmt!E7*Assumptions!$B$86 -> 919.18948 | F21: =Forecast_3Stmt!F7*Assumptions!$B$86 -> 951.61219 | G21: =Forecast_3Stmt!G7*Assumptions!$B$86 -> 985.33654
A22: Depreciation | B22: 1093 | C22: =Forecast_3Stmt!C7*Assumptions!$B$84 -> 1144.0449 | D22: =Forecast_3Stmt!D7*Assumptions!$B$84 -> 1184.0186 | E22: =Forecast_3Stmt!E7*Assumptions!$B$84 -> 1225.586 | F22: =Forecast_3Stmt!F7*Assumptions!$B$84 -> 1268.8163 | G22: =Forecast_3Stmt!G7*Assumptions!$B$84 -> 1313.7821
A23: Net PP&E | B23: 9204 | C23: =B23+C21-C22 -> 8917.9888 | D23: =C23+D21-D22 -> 8621.9841 | E23: =D23+E21-E22 -> 8315.5876 | F23: =E23+F21-F22 -> 7998.3836 | G23: =F23+G21-G22 -> 7669.938
A24: Amortization | B24: 268 | C24: =Forecast_3Stmt!C7*Assumptions!$B$85 -> 286.01122 | D24: =Forecast_3Stmt!D7*Assumptions!$B$85 -> 296.00466 | E24: =Forecast_3Stmt!E7*Assumptions!$B$85 -> 306.39649 | F24: =Forecast_3Stmt!F7*Assumptions!$B$85 -> 317.20406 | G24: =Forecast_3Stmt!G7*Assumptions!$B$85 -> 328.44551
A25: Intangible assets | B25: 5624 | C25: =B25-C24 -> 5337.9888 | D25: =C25-D24 -> 5041.9841 | E25: =D25-E24 -> 4735.5876 | F25: =E25-F24 -> 4418.3836 | G25: =F25-G24 -> 4089.938
A27: Cash, Debt & Equity
A28: Beginning gross debt | B28: 8830 | C28: =B30 -> 8830 | D28: =C30 -> 7691.5875 | E28: =D30 -> 6271.4199 | F28: =E30 -> 4731.5707 | G28: =F30 -> 3055.3416
A29: Financing requirement / (repayment) | C29: =MAX(-C28,C35-B36-Forecast_3Stmt!C56-Forecast_3Stmt!C57-C40) -> -1138.4125 | D29: =MAX(-D28,D35-C36-Forecast_3Stmt!D56-Forecast_3Stmt!D57-D40) -> -1420.1676 | E29: =MAX(-E28,E35-D36-Forecast_3Stmt!E56-Forecast_3Stmt!E57-E40) -> -1539.8492 | F29: =MAX(-F28,F35-E36-Forecast_3Stmt!F56-Forecast_3Stmt!F57-F40) -> -1676.2291 | G29: =MAX(-G28,G35-F36-Forecast_3Stmt!G56-Forecast_3Stmt!G57-G40) -> -1813.7759
A30: Ending gross debt | B30: 8830 | C30: =C28+C29 -> 7691.5875 | D30: =D28+D29 -> 6271.4199 | E30: =E28+E29 -> 4731.5707 | F30: =F28+F29 -> 3055.3416 | G30: =G28+G29 -> 1241.5657
A31: Current debt | B31: 909 | C31: =C30*Assumptions!$B$100 -> 769.15875 | D31: =D30*Assumptions!$B$100 -> 627.14199 | E31: =E30*Assumptions!$B$100 -> 473.15707 | F31: =F30*Assumptions!$B$100 -> 305.53416 | G31: =G30*Assumptions!$B$100 -> 124.15657
A32: Long-term debt | B32: 7921 | C32: =C30-C31 -> 6922.4288 | D32: =D30-D31 -> 5644.2779 | E32: =E30-E31 -> 4258.4136 | F32: =F30-F31 -> 2749.8074 | G32: =G30-G31 -> 1117.4091
A33: Interest expense | B33: 449 | C33: =Assumptions!$B$82 -> 365 | D33: =D28*Assumptions!$B$83 -> 346.12144 | E33: =E28*Assumptions!$B$83 -> 282.21389 | F33: =F28*Assumptions!$B$83 -> 212.92068 | G33: =G28*Assumptions!$B$83 -> 137.49037
A34: Minimum cash / sales | B34: 0.0226 | C34: =Assumptions!$B$93 -> 0.02 | D34: =Assumptions!$B$93 -> 0.02 | E34: =Assumptions!$B$93 -> 0.02 | F34: =Assumptions!$B$93 -> 0.02 | G34: =Assumptions!$B$93 -> 0.02
A35: Minimum ending cash | B35: 1229 | C35: =Forecast_3Stmt!C7*C34 -> 1144.0449 | D35: =Forecast_3Stmt!D7*D34 -> 1184.0186 | E35: =Forecast_3Stmt!E7*E34 -> 1225.586 | F35: =Forecast_3Stmt!F7*F34 -> 1268.8163 | G35: =Forecast_3Stmt!G7*G34 -> 1313.7821
A36: CFS ending cash | B36: 1229 | C36: =B36+Forecast_3Stmt!C56+Forecast_3Stmt!C57+C29+C40 -> 1144.0449 | D36: =C36+Forecast_3Stmt!D56+Forecast_3Stmt!D57+D29+D40 -> 1184.0186 | E36: =D36+Forecast_3Stmt!E56+Forecast_3Stmt!E57+E29+E40 -> 1225.586 | F36: =E36+Forecast_3Stmt!F56+Forecast_3Stmt!F57+F29+F40 -> 1268.8163 | G36: =F36+Forecast_3Stmt!G56+Forecast_3Stmt!G57+G29+G40 -> 1313.7821
A37: Cash floor surplus / (shortfall) | B37: 0 | C37: =C36-C35 -> 0 | D37: =D36-D35 -> 0 | E37: =E36-E35 -> 0 | F37: =F36-F35 -> 0 | G37: =G36-G35 -> 0
A38: Beginning Tyson equity | B38: 18085 | C38: =B41 -> 18085 | D38: =C41 -> 18852.343 | E38: =D41 -> 19785.112 | F38: =E41 -> 20830.146 | G38: =F41 -> 21991.8
A39: Tyson net income | B39: 474 | C39: =Forecast_3Stmt!C20 -> 1534.685 | D39: =Forecast_3Stmt!D20 -> 1865.5383 | E39: =Forecast_3Stmt!E20 -> 2090.069 | F39: =Forecast_3Stmt!F20 -> 2323.3083 | G39: =Forecast_3Stmt!G20 -> 2558.7898
A40: Dividends | B40: -697 | C40: =-Forecast_3Stmt!C20*Assumptions!$B$92 -> -767.34252 | D40: =-Forecast_3Stmt!D20*Assumptions!$B$92 -> -932.76915 | E40: =-Forecast_3Stmt!E20*Assumptions!$B$92 -> -1045.0345 | F40: =-Forecast_3Stmt!F20*Assumptions!$B$92 -> -1161.6542 | G40: =-Forecast_3Stmt!G20*Assumptions!$B$92 -> -1279.3949
A41: Ending Tyson equity | B41: 18085 | C41: =SUM(C38:C40) -> 18852.343 | D41: =SUM(D38:D40) -> 19785.112 | E41: =SUM(E38:E40) -> 20830.146 | F41: =SUM(F38:F40) -> 21991.8 | G41: =SUM(G38:G40) -> 23271.195
A42: NCI equity | B42: 142 | C42: =B42+Forecast_3Stmt!C19 -> 173.3201 | D42: =C42+Forecast_3Stmt!D19 -> 211.39231 | E42: =D42+Forecast_3Stmt!E19 -> 254.04678 | F42: =E42+Forecast_3Stmt!F19 -> 301.46124 | G42: =F42+Forecast_3Stmt!G19 -> 353.68144
A43: Diluted shares | B43: 357 | C43: =Assumptions!$B$101 -> 354 | D43: =Assumptions!$B$101 -> 354 | E43: =Assumptions!$B$101 -> 354 | F43: =Assumptions!$B$101 -> 354 | G43: =Assumptions!$B$101 -> 354

Sheet Interim_Bridge
A1: FY2026 Interim Bridge
A2: 6M actual + H2 estimate = comparable 52-week FY2026; week 53 shown separately
A4: Metric | B4: 6M Actual | C4: H2E (52w) | D4: FY26E (52w) | E4: Week 53 | F4: FY26E Reported
A6: Consolidated Bridge
A7: Sales | B7: 27966 | C7: =D7-B7 -> 28156.957 | D7: =F7/(1+Assumptions!$B$97) -> 56122.957 | E7: =F7-D7 -> 1079.2876 | F7: =Segment_Build!G13 -> 57202.244
A8: Operating income | B8: 737 | C8: =D8-B8 -> 1657.6656 | D8: =F8/(1+Assumptions!$B$97) -> 2394.6656 | E8: =F8-D8 -> 46.051262 | F8: =Segment_Build!G24 -> 2440.7169
A9: Cash from operating activities | B9: 829 | C9: =D9-B9 -> 1799.2895 | D9: =F9/(1+Assumptions!$B$97) -> 2628.2895 | E9: =F9-D9 -> 50.544029 | F9: =Forecast_3Stmt!C56 -> 2678.8336
A10: Capital expenditures | B10: 397 | C10: =D10-B10 -> 444.84435 | D10: =F10/(1+Assumptions!$B$97) -> 841.84435 | E10: =F10-D10 -> 16.189314 | F10: =Schedules!C21 -> 858.03366
A11: FY2026 GAAP-to-adjusted items | D11: =Assumptions!B107 -> 0 | F11: =Assumptions!B107 -> 0
A12: Adjusted / normalized operating income | B12: =B8 -> 737 | C12: =C8 -> 1657.6656 | D12: =D8+D11 -> 2394.6656 | E12: =E8 -> 46.051262 | F12: =F8+F11 -> 2440.7169
A13: Segment Sales Bridge
A14: Beef | B14: 10976 | C14: =D14-B14 -> 10850.256 | D14: =F14/(1+Assumptions!$B$97) -> 21826.256 | E14: =F14-D14 -> 419.7357 | F14: =Segment_Build!G7 -> 22245.992
A15: Pork | B15: 3188 | C15: =D15-B15 -> 2885.5186 | D15: =F15/(1+Assumptions!$B$97) -> 6073.5186 | E15: =F15-D15 -> 116.79843 | F15: =Segment_Build!G8 -> 6190.317
A16: Chicken | B16: 8498 | C16: =D16-B16 -> 9190.9522 | D16: =F16/(1+Assumptions!$B$97) -> 17688.952 | E16: =F16-D16 -> 340.17216 | F16: =Segment_Build!G9 -> 18029.124
A17: Prepared Foods | B17: 5184 | C17: =D17-B17 -> 5095.0395 | D17: =F17/(1+Assumptions!$B$97) -> 10279.04 | E17: =F17-D17 -> 197.67384 | F17: =Segment_Build!G10 -> 10476.713
A18: International | B18: 1159 | C18: =D18-B18 -> 1177.82 | D18: =F18/(1+Assumptions!$B$97) -> 2336.82 | E18: =F18-D18 -> 44.938846 | F18: =Segment_Build!G11 -> 2381.7588
A19: Intersegment eliminations | B19: -1039 | C19: =D19-B19 -> -1042.63 | D19: =F19/(1+Assumptions!$B$97) -> -2081.63 | E19: =F19-D19 -> -40.031346 | F19: =Segment_Build!G12 -> -2121.6613
A20: Total sales | B20: =SUM(B14:B19) -> 27966 | C20: =SUM(C14:C19) -> 28156.957 | D20: =SUM(D14:D19) -> 56122.957 | E20: =SUM(E14:E19) -> 1079.2876 | F20: =SUM(F14:F19) -> 57202.244
A22: Segment Operating Income Bridge
A23: Beef | B23: -559 | C23: =D23-B23 -> 142.11851 | D23: =F23/(1+Assumptions!$B$97) -> -416.88149 | E23: =F23-D23 -> -8.0169518 | F23: =Segment_Build!G16 -> -424.89845
A24: Pork | B24: 91 | C24: =D24-B24 -> 189.59656 | D24: =F24/(1+Assumptions!$B$97) -> 280.59656 | E24: =F24-D24 -> 5.3960877 | F24: =Segment_Build!G17 -> 285.99265
A25: Chicken | B25: 955 | C25: =D25-B25 -> 1059.7717 | D25: =F25/(1+Assumptions!$B$97) -> 2014.7717 | E25: =F25-D25 -> 38.745609 | F25: =Segment_Build!G18 -> 2053.5173
A26: Prepared Foods | B26: 670 | C26: =D26-B26 -> 636.46592 | D26: =F26/(1+Assumptions!$B$97) -> 1306.4659 | E26: =F26-D26 -> 25.124345 | F26: =Segment_Build!G19 -> 1331.5903
A27: International | B27: 79 | C27: =D27-B27 -> 96.027818 | D27: =F27/(1+Assumptions!$B$97) -> 175.02782 | E27: =F27-D27 -> 3.3659196 | F27: =Segment_Build!G20 -> 178.39374
A28: Corporate expenses | B28: -391 | C28: =D28-B28 -> -293.70007 | D28: =F28/(1+Assumptions!$B$97) -> -684.70007 | E28: =F28-D28 -> -13.167309 | F28: =Segment_Build!G22 -> -697.86738
A29: Amortization | B29: -108 | C29: =D29-B29 -> -172.61478 | D29: =F29/(1+Assumptions!$B$97) -> -280.61478 | E29: =F29-D29 -> -5.3964381 | F29: =Segment_Build!G23 -> -286.01122
A30: Consolidated operating income | B30: =SUM(B23:B29) -> 737 | C30: =SUM(C23:C29) -> 1657.6656 | D30: =SUM(D23:D29) -> 2394.6656 | E30: =SUM(E23:E29) -> 46.051262 | F30: =SUM(F23:F29) -> 2440.7169

Sheet Debt_Credit
A1: Debt, Liquidity & Covenant Analysis
A2: Q2 FY2026 filed debt stack; no undisclosed covenant threshold is invented
A4: Debt Stack at March 28, 2026
A5: Instrument | B5: Carrying amount | C5: Coupon | D5: Maturity | E5: Source / note
A6: Commercial paper | B6: 30 | C6: 0.04 | D6: <5 days | E6: S05 | Note 6 Debt
A7: 3.55% senior notes | B7: 1350 | C7: 0.0355 | D7: Jun-2027 | E7: S05 | Note 6 Debt
A8: 7.00% senior notes | B8: 18 | C8: 0.07 | D8: Jan-2028 | E8: S05 | Note 6 Debt
A9: 4.35% senior notes | B9: 1000 | C9: 0.0435 | D9: Mar-2029 | E9: S05 | Note 6 Debt
A10: 5.40% senior notes | B10: 600 | C10: 0.054 | D10: Mar-2029 | E10: S05 | Note 6 Debt
A11: 6.13% senior notes | B11: 157 | C11: 0.0613 | D11: Nov-2032 | E11: S05 | Note 6 Debt
A12: 5.70% senior notes | B12: 900 | C12: 0.057 | D12: Mar-2034 | E12: S05 | Note 6 Debt
A13: 4.88% senior notes | B13: 500 | C13: 0.0488 | D13: Aug-2034 | E13: S05 | Note 6 Debt
A14: 4.95% senior notes | B14: 500 | C14: 0.0495 | D14: Feb-2036 | E14: S05 | Note 6 Debt
A15: 5.15% senior notes | B15: 497 | C15: 0.0515 | D15: Aug-2044 | E15: S05 | Note 6 Debt
A16: 4.55% senior notes | B16: 713 | C16: 0.0455 | D16: Jun-2047 | E16: S05 | Note 6 Debt
A17: 5.10% senior notes | B17: 1485 | C17: 0.051 | D17: Sep-2048 | E17: S05 | Note 6 Debt
A18: Senior note discounts | B18: -34 | D18: N/A | E18: S05 | Note 6 Debt
A19: Finance leases | B19: 173 | D19: Various | E19: S05 | Note 6 Debt
A20: Other debt | B20: 235 | D20: Various | E20: S05 | Note 6 Debt
A21: Unamortized issuance costs | B21: -41 | D21: N/A | E21: S05 | Note 6 Debt
A22: Total debt | B22: =SUM(B6:B21) -> 8083
A23: Current debt | B23: 141
A24: Long-term debt | B24: 7942
A25: Classification check | B25: =B22-B23-B24 -> 0
A28: Credit & Liquidity Snapshot
A29: Metric | B29: Value | C29: Source / treatment
A30: Debt fair value | B30: 7823 | C30: S05 | Note 11 fair value
A31: Fixed-rate debt | B31: 8016 | C31: S05 | market-risk disclosure
A32: Weighted average fixed rate | B32: 0.049 | C32: S05 | market-risk disclosure
A33: Cash | B33: 500 | C33: S05 | balance sheet
A34: Net debt | B34: =B22-B33 -> 7583 | C34: Derived
A35: Total liquidity | B35: 3700 | C35: S06 | company-reported
A36: Minimum liquidity target | B36: 1000 | C36: S06 | management target
A37: Revolver commitment | B37: 2500 | C37: S05 | Note 6
A38: Revolver borrowed | B38: 0 | C38: S05 | Note 6
A39: Revolving term commitment | B39: 750 | C39: S05 | Note 6
A40: Revolving term borrowed | B40: 0 | C40: S05 | Note 6
A41: Liquidity headroom vs target | B41: =B35-B36 -> 2700 | C41: Derived
A44: Covenant & Refinancing Register
A45: Topic | B45: Requirement / fact | C45: Threshold | D45: Status | E45: Credit implication | F45: Source
A46: Interest coverage | B46: Minimum interest expense coverage ratio | C46: Not disclosed in filing | D46: Required | E46: Monitor EBITDA and interest headroom | F46: S05 Note 6
A47: Negative covenants | B47: Liens, debt, M&A, asset sales, affiliates and hedging restricted | C47: Subject to exceptions | D47: In force | E47: Constrains financial flexibility | F47: S05 Note 6
A48: Compliance | B48: Tyson reported compliance with all debt covenants | C48: As of 2026-03-28 | D48: COMPLIANT | E48: No filed breach | F48: S05 Note 6
A49: Near-term maturity | B49: $1.35bn notes due June 2027 | C49: 3.55% coupon | D49: OPEN | E49: Principal refinancing concentration | F49: S05 Note 6

Sheet DCF
A1: Discounted Cash Flow Valuation
A2: Valuation date 2026-03-28; H2 FY26 stub then FY27-FY30 mid-year convention; WACC/TGR/exit multiple are analyst inputs
A4: Metric | B4: As of / Input | C4: Remaining FY26E (incl. week 53) | D4: 2027E | E4: 2028E | F4: 2029E | G4: 2030E
A6: Unlevered Free Cash Flow
A7: Sales | C7: =Interim_Bridge!F7-Interim_Bridge!B7 -> 29236.244 | D7: =Forecast_3Stmt!D7 -> 59200.932 | E7: =Forecast_3Stmt!E7 -> 61279.299 | F7: =Forecast_3Stmt!F7 -> 63440.813 | G7: =Forecast_3Stmt!G7 -> 65689.103
A8: Growth | D8: =Forecast_3Stmt!D8 -> 0.034940722 | E8: =Forecast_3Stmt!E8 -> 0.035106994 | F8: =Forecast_3Stmt!F8 -> 0.035273158 | G8: =Forecast_3Stmt!G8 -> 0.035439168
A9: EBIT | C9: =Interim_Bridge!F8-Interim_Bridge!B8 -> 1703.7169 | D9: =Forecast_3Stmt!D12 -> 2872.8283 | E9: =Forecast_3Stmt!E12 -> 3114.005 | F9: =Forecast_3Stmt!F12 -> 3361.6285 | G9: =Forecast_3Stmt!G12 -> 3606.1489
A10: Cash tax on EBIT | C10: =C9*Assumptions!$B$81 -> 425.92922 | D10: =D9*Assumptions!$B$81 -> 718.20709 | E10: =E9*Assumptions!$B$81 -> 778.50124 | F10: =F9*Assumptions!$B$81 -> 840.40713 | G10: =G9*Assumptions!$B$81 -> 901.53723
A11: NOPAT | C11: =C9-C10 -> 1277.7877 | D11: =D9-D10 -> 2154.6213 | E11: =E9-E10 -> 2335.5037 | F11: =F9-F10 -> 2521.2214 | G11: =G9-G10 -> 2704.6117
A12: D&A | C12: =SUM(Forecast_3Stmt!C53:C54)*C7/Forecast_3Stmt!C7 -> 730.9061 | D12: =SUM(Forecast_3Stmt!D53:Forecast_3Stmt!D54) -> 1480.0233 | E12: =SUM(Forecast_3Stmt!E53:Forecast_3Stmt!E54) -> 1531.9825 | F12: =SUM(Forecast_3Stmt!F53:Forecast_3Stmt!F54) -> 1586.0203 | G12: =SUM(Forecast_3Stmt!G53:Forecast_3Stmt!G54) -> 1642.2276
A13: Capital expenditures | C13: =Interim_Bridge!F10-Interim_Bridge!B10 -> 461.03366 | D13: =-Forecast_3Stmt!D57 -> 888.01398 | E13: =-Forecast_3Stmt!E57 -> 919.18948 | F13: =-Forecast_3Stmt!F57 -> 951.61219 | G13: =-Forecast_3Stmt!G57 -> 985.33654
A14: Change in operating NWC | C14: =Schedules!C18*C7/Forecast_3Stmt!C7 -> 162.13606 | D14: =Schedules!D18 -> 102.70928 | E14: =Schedules!E18 -> 119.06542 | F14: =Schedules!F18 -> 124.01736 | G14: =Schedules!G18 -> 129.76447
A15: Unlevered FCF | C15: =SUM(C11:C12)-SUM(C13:C14) -> 1385.524 | D15: =SUM(D11:D12)-SUM(D13:D14) -> 2643.9213 | E15: =SUM(E11:E12)-SUM(E13:E14) -> 2829.2313 | F15: =SUM(F11:F12)-SUM(F13:F14) -> 3031.6122 | G15: =SUM(G11:G12)-SUM(G13:G14) -> 3231.7382
A16: Discount factor | C16: =1/(1+Assumptions!$B$94)^0.25 -> 0.97981157 | D16: =1/(1+Assumptions!$B$94)^1 -> 0.92165899 | E16: =1/(1+Assumptions!$B$94)^2 -> 0.84945529 | F16: =1/(1+Assumptions!$B$94)^3 -> 0.7829081 | G16: =1/(1+Assumptions!$B$94)^4 -> 0.72157428
A17: PV of FCF | C17: =C15*C16 -> 1357.5525 | D17: =D15*D16 -> 2436.7938 | E17: =E15*E16 -> 2403.3055 | F17: =F15*F16 -> 2373.4737 | G17: =G15*G16 -> 2331.9392
A19: Enterprise-to-Equity Bridge
A20: Terminal value - Gordon growth | B20: =G15*(1+Assumptions!$B$95)/(Assumptions!$B$94-Assumptions!$B$95) -> 50713.431
A21: Terminal discount period (years) | B21: 4.5
A22: PV of terminal value | B22: =B20/(1+Assumptions!$B$94)^B21 -> 35130.891
A23: Enterprise value - Gordon growth | B23: =SUM(C17:G17)+B22 -> 46033.956
A24: Cash | B24: 500
A25: Gross debt | B25: 8083
A26: Net debt | B26: 7583
A27: Noncontrolling interest | B27: 103
A28: Equity value - Gordon growth | B28: =B23+B24-B25-B27 -> 38347.956
A29: If-converted shares | B29: =Assumptions!$B$102 -> 352.1294
A30: Value per share - Gordon growth | B30: =B28/B29 -> 108.90302
A31: 2030E EBITDA | B31: =G9+G12 -> 5248.3765
A32: Terminal EV at exit multiple | B32: =B31*Assumptions!$B$96 -> 41987.012
A33: Enterprise value - exit multiple | B33: =SUM(C17:G17)+B32/(1+Assumptions!$B$94)^B21 -> 39988.873
A34: Value per share - exit multiple | B34: =(B33+B24-B25-B27)/B29 -> 91.735803
A35: Share Bridge
A36: Class A shares outstanding | B36: 282.1204
A37: Class B shares outstanding | B37: 70.009005
A38: If-converted shares | B38: =SUM(B36:B37) -> 352.1294
A39: Bridge check | B39: =B38-B29 -> 0

Sheet Sensitivity
A1: DCF Sensitivity
A2: Gordon-growth value per share across WACC and terminal-growth assumptions
A5: WACC / Terminal Growth Sensitivity
A7: WACC / TGR | B7: 0.01 | C7: 0.015 | D7: 0.02 | E7: 0.025 | F7: 0.03
A8: 0.075 | B8: =(DCF!C$15/(1+$A8)^0.25+DCF!D$15/(1+$A8)^1+DCF!E$15/(1+$A8)^2+DCF!F$15/(1+$A8)^3+DCF!G$15/(1+$A8)^4+(DCF!$G$15*(1+B$7)/($A8-B$7))/(1+$A8)^4.5+DCF!$B$24-DCF!$B$25-DCF!$B$27)/DCF!$B$29 -> 112.76872 | C8: =(DCF!C$15/(1+$A8)^0.25+DCF!D$15/(1+$A8)^1+DCF!E$15/(1+$A8)^2+DCF!F$15/(1+$A8)^3+DCF!G$15/(1+$A8)^4+(DCF!$G$15*(1+C$7)/($A8-C$7))/(1+$A8)^4.5+DCF!$B$24-DCF!$B$25-DCF!$B$27)/DCF!$B$29 -> 121.90374 | D8: =(DCF!C$15/(1+$A8)^0.25+DCF!D$15/(1+$A8)^1+DCF!E$15/(1+$A8)^2+DCF!F$15/(1+$A8)^3+DCF!G$15/(1+$A8)^4+(DCF!$G$15*(1+D$7)/($A8-D$7))/(1+$A8)^4.5+DCF!$B$24-DCF!$B$25-DCF!$B$27)/DCF!$B$29 -> 132.69968 | E8: =(DCF!C$15/(1+$A8)^0.25+DCF!D$15/(1+$A8)^1+DCF!E$15/(1+$A8)^2+DCF!F$15/(1+$A8)^3+DCF!G$15/(1+$A8)^4+(DCF!$G$15*(1+E$7)/($A8-E$7))/(1+$A8)^4.5+DCF!$B$24-DCF!$B$25-DCF!$B$27)/DCF!$B$29 -> 145.6548 | F8: =(DCF!C$15/(1+$A8)^0.25+DCF!D$15/(1+$A8)^1+DCF!E$15/(1+$A8)^2+DCF!F$15/(1+$A8)^3+DCF!G$15/(1+$A8)^4+(DCF!$G$15*(1+F$7)/($A8-F$7))/(1+$A8)^4.5+DCF!$B$24-DCF!$B$25-DCF!$B$27)/DCF!$B$29 -> 161.48884
A9: 0.08 | B9: =(DCF!C$15/(1+$A9)^0.25+DCF!D$15/(1+$A9)^1+DCF!E$15/(1+$A9)^2+DCF!F$15/(1+$A9)^3+DCF!G$15/(1+$A9)^4+(DCF!$G$15*(1+B$7)/($A9-B$7))/(1+$A9)^4.5+DCF!$B$24-DCF!$B$25-DCF!$B$27)/DCF!$B$29 -> 103.11258 | C9: =(DCF!C$15/(1+$A9)^0.25+DCF!D$15/(1+$A9)^1+DCF!E$15/(1+$A9)^2+DCF!F$15/(1+$A9)^3+DCF!G$15/(1+$A9)^4+(DCF!$G$15*(1+C$7)/($A9-C$7))/(1+$A9)^4.5+DCF!$B$24-DCF!$B$25-DCF!$B$27)/DCF!$B$29 -> 110.81646 | D9: =(DCF!C$15/(1+$A9)^0.25+DCF!D$15/(1+$A9)^1+DCF!E$15/(1+$A9)^2+DCF!F$15/(1+$A9)^3+DCF!G$15/(1+$A9)^4+(DCF!$G$15*(1+D$7)/($A9-D$7))/(1+$A9)^4.5+DCF!$B$24-DCF!$B$25-DCF!$B$27)/DCF!$B$29 -> 119.80431 | E9: =(DCF!C$15/(1+$A9)^0.25+DCF!D$15/(1+$A9)^1+DCF!E$15/(1+$A9)^2+DCF!F$15/(1+$A9)^3+DCF!G$15/(1+$A9)^4+(DCF!$G$15*(1+E$7)/($A9-E$7))/(1+$A9)^4.5+DCF!$B$24-DCF!$B$25-DCF!$B$27)/DCF!$B$29 -> 130.42632 | F9: =(DCF!C$15/(1+$A9)^0.25+DCF!D$15/(1+$A9)^1+DCF!E$15/(1+$A9)^2+DCF!F$15/(1+$A9)^3+DCF!G$15/(1+$A9)^4+(DCF!$G$15*(1+F$7)/($A9-F$7))/(1+$A9)^4.5+DCF!$B$24-DCF!$B$25-DCF!$B$27)/DCF!$B$29 -> 143.17274
A10: 0.085 | B10: =(DCF!C$15/(1+$A10)^0.25+DCF!D$15/(1+$A10)^1+DCF!E$15/(1+$A10)^2+DCF!F$15/(1+$A10)^3+DCF!G$15/(1+$A10)^4+(DCF!$G$15*(1+B$7)/($A10-B$7))/(1+$A10)^4.5+DCF!$B$24-DCF!$B$25-DCF!$B$27)/DCF!$B$29 -> 94.753063 | C10: =(DCF!C$15/(1+$A10)^0.25+DCF!D$15/(1+$A10)^1+DCF!E$15/(1+$A10)^2+DCF!F$15/(1+$A10)^3+DCF!G$15/(1+$A10)^4+(DCF!$G$15*(1+C$7)/($A10-C$7))/(1+$A10)^4.5+DCF!$B$24-DCF!$B$25-DCF!$B$27)/DCF!$B$29 -> 101.32269 | D10: =(DCF!C$15/(1+$A10)^0.25+DCF!D$15/(1+$A10)^1+DCF!E$15/(1+$A10)^2+DCF!F$15/(1+$A10)^3+DCF!G$15/(1+$A10)^4+(DCF!$G$15*(1+D$7)/($A10-D$7))/(1+$A10)^4.5+DCF!$B$24-DCF!$B$25-DCF!$B$27)/DCF!$B$29 -> 108.90302 | E10: =(DCF!C$15/(1+$A10)^0.25+DCF!D$15/(1+$A10)^1+DCF!E$15/(1+$A10)^2+DCF!F$15/(1+$A10)^3+DCF!G$15/(1+$A10)^4+(DCF!$G$15*(1+E$7)/($A10-E$7))/(1+$A10)^4.5+DCF!$B$24-DCF!$B$25-DCF!$B$27)/DCF!$B$29 -> 117.74675 | F10: =(DCF!C$15/(1+$A10)^0.25+DCF!D$15/(1+$A10)^1+DCF!E$15/(1+$A10)^2+DCF!F$15/(1+$A10)^3+DCF!G$15/(1+$A10)^4+(DCF!$G$15*(1+F$7)/($A10-F$7))/(1+$A10)^4.5+DCF!$B$24-DCF!$B$25-DCF!$B$27)/DCF!$B$29 -> 128.19842
A11: 0.09 | B11: =(DCF!C$15/(1+$A11)^0.25+DCF!D$15/(1+$A11)^1+DCF!E$15/(1+$A11)^2+DCF!F$15/(1+$A11)^3+DCF!G$15/(1+$A11)^4+(DCF!$G$15*(1+B$7)/($A11-B$7))/(1+$A11)^4.5+DCF!$B$24-DCF!$B$25-DCF!$B$27)/DCF!$B$29 -> 87.446727 | C11: =(DCF!C$15/(1+$A11)^0.25+DCF!D$15/(1+$A11)^1+DCF!E$15/(1+$A11)^2+DCF!F$15/(1+$A11)^3+DCF!G$15/(1+$A11)^4+(DCF!$G$15*(1+C$7)/($A11-C$7))/(1+$A11)^4.5+DCF!$B$24-DCF!$B$25-DCF!$B$27)/DCF!$B$29 -> 93.103385 | D11: =(DCF!C$15/(1+$A11)^0.25+DCF!D$15/(1+$A11)^1+DCF!E$15/(1+$A11)^2+DCF!F$15/(1+$A11)^3+DCF!G$15/(1+$A11)^4+(DCF!$G$15*(1+D$7)/($A11-D$7))/(1+$A11)^4.5+DCF!$B$24-DCF!$B$25-DCF!$B$27)/DCF!$B$29 -> 99.568137 | E11: =(DCF!C$15/(1+$A11)^0.25+DCF!D$15/(1+$A11)^1+DCF!E$15/(1+$A11)^2+DCF!F$15/(1+$A11)^3+DCF!G$15/(1+$A11)^4+(DCF!$G$15*(1+E$7)/($A11-E$7))/(1+$A11)^4.5+DCF!$B$24-DCF!$B$25-DCF!$B$27)/DCF!$B$29 -> 107.02747 | F11: =(DCF!C$15/(1+$A11)^0.25+DCF!D$15/(1+$A11)^1+DCF!E$15/(1+$A11)^2+DCF!F$15/(1+$A11)^3+DCF!G$15/(1+$A11)^4+(DCF!$G$15*(1+F$7)/($A11-F$7))/(1+$A11)^4.5+DCF!$B$24-DCF!$B$25-DCF!$B$27)/DCF!$B$29 -> 115.73002
A12: 0.095 | B12: =(DCF!C$15/(1+$A12)^0.25+DCF!D$15/(1+$A12)^1+DCF!E$15/(1+$A12)^2+DCF!F$15/(1+$A12)^3+DCF!G$15/(1+$A12)^4+(DCF!$G$15*(1+B$7)/($A12-B$7))/(1+$A12)^4.5+DCF!$B$24-DCF!$B$25-DCF!$B$27)/DCF!$B$29 -> 81.00742 | C12: =(DCF!C$15/(1+$A12)^0.25+DCF!D$15/(1+$A12)^1+DCF!E$15/(1+$A12)^2+DCF!F$15/(1+$A12)^3+DCF!G$15/(1+$A12)^4+(DCF!$G$15*(1+C$7)/($A12-C$7))/(1+$A12)^4.5+DCF!$B$24-DCF!$B$25-DCF!$B$27)/DCF!$B$29 -> 85.919275 | D12: =(DCF!C$15/(1+$A12)^0.25+DCF!D$15/(1+$A12)^1+DCF!E$15/(1+$A12)^2+DCF!F$15/(1+$A12)^3+DCF!G$15/(1+$A12)^4+(DCF!$G$15*(1+D$7)/($A12-D$7))/(1+$A12)^4.5+DCF!$B$24-DCF!$B$25-DCF!$B$27)/DCF!$B$29 -> 91.486044 | E12: =(DCF!C$15/(1+$A12)^0.25+DCF!D$15/(1+$A12)^1+DCF!E$15/(1+$A12)^2+DCF!F$15/(1+$A12)^3+DCF!G$15/(1+$A12)^4+(DCF!$G$15*(1+E$7)/($A12-E$7))/(1+$A12)^4.5+DCF!$B$24-DCF!$B$25-DCF!$B$27)/DCF!$B$29 -> 97.848066 | F12: =(DCF!C$15/(1+$A12)^0.25+DCF!D$15/(1+$A12)^1+DCF!E$15/(1+$A12)^2+DCF!F$15/(1+$A12)^3+DCF!G$15/(1+$A12)^4+(DCF!$G$15*(1+F$7)/($A12-F$7))/(1+$A12)^4.5+DCF!$B$24-DCF!$B$25-DCF!$B$27)/DCF!$B$29 -> 105.18886
A15: Key Inputs
A16: Base WACC | B16: =Assumptions!B94 -> 0.085
A17: Base terminal growth | B17: =Assumptions!B95 -> 0.02
A18: Base DCF value per share | B18: =DCF!B30 -> 108.90302

Sheet Sources
A1: Claim-Level Source Ledger
A2: Every material source input maps to a destination cell; valuation assumptions are explicitly unsourced
A4: Claim ID | B4: Metric | C4: Period / Date | D4: Source ID | E4: Source title | F4: Accession / identity | G4: Retrieved | H4: URL | I4: Exact locator | J4: Source value | K4: Unit / currency | L4: Destination | M4: Transformation | N4: Class / assumption status | O4: Status
A5: CLM-0001 | B5: Sales | C5: FY2021 | D5: S01 | E5: Tyson Foods FY2022 Form 10-K | F5: 0000100493-22-000097 | G5: 46219 | H5: https://www.sec.gov/Archives/edgar/data/100493/000010049322000097/tsn-20221001.htm | I5: FY2022 10-K, Consolidated Statements of Income, lines 1671-1699 | Sales | FY2021 | J5: 47049 | K5: USD mm | L5: Historical_IS!B7 | M5: Direct transcription from audited filing | N5: Audited filing | Primary / audited | O5: MAPPED
A6: CLM-0002 | B6: Sales | C6: FY2022 | D6: S01 | E6: Tyson Foods FY2022 Form 10-K | F6: 0000100493-22-000097 | G6: 46219 | H6: https://www.sec.gov/Archives/edgar/data/100493/000010049322000097/tsn-20221001.htm | I6: FY2022 10-K, Consolidated Statements of Income, lines 1671-1699 | Sales | FY2022 | J6: 53282 | K6: USD mm | L6: Historical_IS!C7 | M6: Direct transcription from audited filing | N6: Audited filing | Primary / audited | O6: MAPPED
A7: CLM-0003 | B7: Sales | C7: FY2023 | D7: S03 | E7: Tyson Foods FY2025 Form 10-K | F7: 0000100493-25-000095 | G7: 46219 | H7: https://www.sec.gov/Archives/edgar/data/100493/000010049325000095/tsn-20250927.htm | I7: FY2025 10-K, Consolidated Statements of Income, lines 1640-1654 | Sales | FY2023 | J7: 52881 | K7: USD mm | L7: Historical_IS!D7 | M7: Direct transcription from audited filing | N7: Audited filing | Primary / audited | O7: MAPPED
A8: CLM-0004 | B8: Sales | C8: FY2024 | D8: S03 | E8: Tyson Foods FY2025 Form 10-K | F8: 0000100493-25-000095 | G8: 46219 | H8: https://www.sec.gov/Archives/edgar/data/100493/000010049325000095/tsn-20250927.htm | I8: FY2025 10-K, Consolidated Statements of Income, lines 1640-1654 | Sales | FY2024 | J8: 53309 | K8: USD mm | L8: Historical_IS!E7 | M8: Direct transcription from audited filing | N8: Audited filing | Primary / audited | O8: MAPPED
A9: CLM-0005 | B9: Sales | C9: FY2025 | D9: S03 | E9: Tyson Foods FY2025 Form 10-K | F9: 0000100493-25-000095 | G9: 46219 | H9: https://www.sec.gov/Archives/edgar/data/100493/000010049325000095/tsn-20250927.htm | I9: FY2025 10-K, Consolidated Statements of Income, lines 1640-1654 | Sales | FY2025 | J9: 54441 | K9: USD mm | L9: Historical_IS!F7 | M9: Direct transcription from audited filing | N9: Audited filing | Primary / audited | O9: MAPPED
A10: CLM-0006 | B10: Cost of sales | C10: FY2021 | D10: S01 | E10: Tyson Foods FY2022 Form 10-K | F10: 0000100493-22-000097 | G10: 46219 | H10: https://www.sec.gov/Archives/edgar/data/100493/000010049322000097/tsn-20221001.htm | I10: FY2022 10-K, Consolidated Statements of Income, lines 1671-1699 | Cost of sales | FY2021 | J10: 40523 | K10: USD mm | L10: Historical_IS!B8 | M10: Direct transcription from audited filing | N10: Audited filing | Primary / audited | O10: MAPPED
A11: CLM-0007 | B11: Cost of sales | C11: FY2022 | D11: S01 | E11: Tyson Foods FY2022 Form 10-K | F11: 0000100493-22-000097 | G11: 46219 | H11: https://www.sec.gov/Archives/edgar/data/100493/000010049322000097/tsn-20221001.htm | I11: FY2022 10-K, Consolidated Statements of Income, lines 1671-1699 | Cost of sales | FY2022 | J11: 46614 | K11: USD mm | L11: Historical_IS!C8 | M11: Direct transcription from audited filing | N11: Audited filing | Primary / audited | O11: MAPPED
A12: CLM-0008 | B12: Cost of sales | C12: FY2023 | D12: S03 | E12: Tyson Foods FY2025 Form 10-K | F12: 0000100493-25-000095 | G12: 46219 | H12: https://www.sec.gov/Archives/edgar/data/100493/000010049325000095/tsn-20250927.htm | I12: FY2025 10-K, Consolidated Statements of Income, lines 1640-1654 | Cost of sales | FY2023 | J12: 50250 | K12: USD mm | L12: Historical_IS!D8 | M12: Direct transcription from audited filing | N12: Audited filing | Primary / audited | O12: MAPPED
A13: CLM-0009 | B13: Cost of sales | C13: FY2024 | D13: S03 | E13: Tyson Foods FY2025 Form 10-K | F13: 0000100493-25-000095 | G13: 46219 | H13: https://www.sec.gov/Archives/edgar/data/100493/000010049325000095/tsn-20250927.htm | I13: FY2025 10-K, Consolidated Statements of Income, lines 1640-1654 | Cost of sales | FY2024 | J13: 49682 | K13: USD mm | L13: Historical_IS!E8 | M13: Direct transcription from audited filing | N13: Audited filing | Primary / audited | O13: MAPPED
A14: CLM-0010 | B14: Cost of sales | C14: FY2025 | D14: S03 | E14: Tyson Foods FY2025 Form 10-K | F14: 0000100493-25-000095 | G14: 46219 | H14: https://www.sec.gov/Archives/edgar/data/100493/000010049325000095/tsn-20250927.htm | I14: FY2025 10-K, Consolidated Statements of Income, lines 1640-1654 | Cost of sales | FY2025 | J14: 50879 | K14: USD mm | L14: Historical_IS!F8 | M14: Direct transcription from audited filing | N14: Audited filing | Primary / audited | O14: MAPPED
A15: CLM-0011 | B15: Gross profit | C15: FY2021 | D15: S01 | E15: Tyson Foods FY2022 Form 10-K | F15: 0000100493-22-000097 | G15: 46219 | H15: https://www.sec.gov/Archives/edgar/data/100493/000010049322000097/tsn-20221001.htm | I15: FY2022 10-K, Consolidated Statements of Income, lines 1671-1699 | Gross profit | FY2021 | J15: 6526 | K15: USD mm | L15: Historical_IS!B9 | M15: Direct transcription from audited filing | N15: Audited filing | Primary / audited | O15: MAPPED
A16: CLM-0012 | B16: Gross profit | C16: FY2022 | D16: S01 | E16: Tyson Foods FY2022 Form 10-K | F16: 0000100493-22-000097 | G16: 46219 | H16: https://www.sec.gov/Archives/edgar/data/100493/000010049322000097/tsn-20221001.htm | I16: FY2022 10-K, Consolidated Statements of Income, lines 1671-1699 | Gross profit | FY2022 | J16: 6668 | K16: USD mm | L16: Historical_IS!C9 | M16: Direct transcription from audited filing | N16: Audited filing | Primary / audited | O16: MAPPED
... A189: CLM-0185 | B189: Total shareholders' equity | C189: FY2025 | D189: S03 | E189: Tyson Foods FY2025 Form 10-K | F189: 0000100493-25-000095 | G189: 46219 | H189: https://www.sec.gov/Archives/edgar/data/100493/000010049325000095/tsn-20250927.htm | I189: FY2025 10-K, Consolidated Balance Sheets, lines 1686-1717 | Total shareholders' equity | FY2025 | J189: 18227 | K189: USD mm | L189: Historical_BS!F29 | M189: Direct transcription from audited filing | N189: Audited filing | Primary / audited | O189: MAPPED
A190: CLM-0186 | B190: Total liabilities and equity | C190: FY2021 | D190: DERIVED | E190: Workbook formula | F190: N/A | G190: 46219 | H190: N/A - workbook formula | I190: Derived from adjacent sourced statement rows | J190: Formula: =B26+B29 | K190: USD mm | L190: Historical_BS!B30 | M190: Formula: =B26+B29 | N190: Derived | Derived formula | O190: FORMULA
A191: CLM-0187 | B191: Total liabilities and equity | C191: FY2022 | D191: DERIVED | E191: Workbook formula | F191: N/A | G191: 46219 | H191: N/A - workbook formula | I191: Derived from adjacent sourced statement rows | J191: Formula: =C26+C29 | K191: USD mm | L191: Historical_BS!C30 | M191: Formula: =C26+C29 | N191: Derived | Derived formula | O191: FORMULA
A192: CLM-0188 | B192: Total liabilities and equity | C192: FY2023 | D192: DERIVED | E192: Workbook formula | F192: N/A | G192: 46219 | H192: N/A - workbook formula | I192: Derived from adjacent sourced statement rows | J192: Formula: =D26+D29 | K192: USD mm | L192: Historical_BS!D30 | M192: Formula: =D26+D29 | N192: Derived | Derived formula | O192: FORMULA
A193: CLM-0189 | B193: Total liabilities and equity | C193: FY2024 | D193: DERIVED | E193: Workbook formula | F193: N/A | G193: 46219 | H193: N/A - workbook formula | I193: Derived from adjacent sourced statement rows | J193: Formula: =E26+E29 | K193: USD mm | L193: Historical_BS!E30 | M193: Formula: =E26+E29 | N193: Derived | Derived formula | O193: FORMULA
A194: CLM-0190 | B194: Total liabilities and equity | C194: FY2025 | D194: DERIVED | E194: Workbook formula | F194: N/A | G194: 46219 | H194: N/A - workbook formula | I194: Derived from adjacent sourced statement rows | J194: Formula: =F26+F29 | K194: USD mm | L194: Historical_BS!F30 | M194: Formula: =F26+F29 | N194: Derived | Derived formula | O194: FORMULA
A195: CLM-0191 | B195: Net income | C195: FY2021 | D195: S01 | E195: Tyson Foods FY2022 Form 10-K | F195: 0000100493-22-000097 | G195: 46219 | H195: https://www.sec.gov/Archives/edgar/data/100493/000010049322000097/tsn-20221001.htm | I195: FY2022 10-K, Consolidated Statements of Cash Flows, lines 1835-1878 | Net income | FY2021 | J195: 3060 | K195: USD mm | L195: Historical_CF!B7 | M195: Direct transcription from audited filing | N195: Audited filing | Primary / audited | O195: MAPPED
A196: CLM-0192 | B196: Net income | C196: FY2022 | D196: S01 | E196: Tyson Foods FY2022 Form 10-K | F196: 0000100493-22-000097 | G196: 46219 | H196: https://www.sec.gov/Archives/edgar/data/100493/000010049322000097/tsn-20221001.htm | I196: FY2022 10-K, Consolidated Statements of Cash Flows, lines 1835-1878 | Net income | FY2022 | J196: 3249 | K196: USD mm | L196: Historical_CF!C7 | M196: Direct transcription from audited filing | N196: Audited filing | Primary / audited | O196: MAPPED
A197: CLM-0193 | B197: Net income | C197: FY2023 | D197: S03 | E197: Tyson Foods FY2025 Form 10-K | F197: 0000100493-25-000095 | G197: 46219 | H197: https://www.sec.gov/Archives/edgar/data/100493/000010049325000095/tsn-20250927.htm | I197: FY2025 10-K, Consolidated Statements of Cash Flows, lines 1773-1817 | Net income | FY2023 | J197: -649 | K197: USD mm | L197: Historical_CF!D7 | M197: Direct transcription from audited filing | N197: Audited filing | Primary / audited | O197: MAPPED
A198: CLM-0194 | B198: Net income | C198: FY2024 | D198: S03 | E198: Tyson Foods FY2025 Form 10-K | F198: 0000100493-25-000095 | G198: 46219 | H198: https://www.sec.gov/Archives/edgar/data/100493/000010049325000095/tsn-20250927.htm | I198: FY2025 10-K, Consolidated Statements of Cash Flows, lines 1773-1817 | Net income | FY2024 | J198: 822 | K198: USD mm | L198: Historical_CF!E7 | M198: Direct transcription from audited filing | N198: Audited filing | Primary / audited | O198: MAPPED
A199: CLM-0195 | B199: Net income | C199: FY2025 | D199: S03 | E199: Tyson Foods FY2025 Form 10-K | F199: 0000100493-25-000095 | G199: 46219 | H199: https://www.sec.gov/Archives/edgar/data/100493/000010049325000095/tsn-20250927.htm | I199: FY2025 10-K, Consolidated Statements of Cash Flows, lines 1773-1817 | Net income | FY2025 | J199: 507 | K199: USD mm | L199: Historical_CF!F7 | M199: Direct transcription from audited filing | N199: Audited filing | Primary / audited | O199: MAPPED
A200: CLM-0196 | B200: Depreciation | C200: FY2021 | D200: S01 | E200: Tyson Foods FY2022 Form 10-K | F200: 0000100493-22-000097 | G200: 46219 | H200: https://www.sec.gov/Archives/edgar/data/100493/000010049322000097/tsn-20221001.htm | I200: FY2022 10-K, Consolidated Statements of Cash Flows, lines 1835-1878 | Depreciation | FY2021 | J200: 934 | K200: USD mm | L200: Historical_CF!B8 | M200: Direct transcription from audited filing | N200: Audited filing | Primary / audited | O200: MAPPED
A201: CLM-0197 | B201: Depreciation | C201: FY2022 | D201: S01 | E201: Tyson Foods FY2022 Form 10-K | F201: 0000100493-22-000097 | G201: 46219 | H201: https://www.sec.gov/Archives/edgar/data/100493/000010049322000097/tsn-20221001.htm | I201: FY2022 10-K, Consolidated Statements of Cash Flows, lines 1835-1878 | Depreciation | FY2022 | J201: 945 | K201: USD mm | L201: Historical_CF!C8 | M201: Direct transcription from audited filing | N201: Audited filing | Primary / audited | O201: MAPPED
A202: CLM-0198 | B202: Depreciation | C202: FY2023 | D202: S03 | E202: Tyson Foods FY2025 Form 10-K | F202: 0000100493-25-000095 | G202: 46219 | H202: https://www.sec.gov/Archives/edgar/data/100493/000010049325000095/tsn-20250927.htm | I202: FY2025 10-K, Consolidated Statements of Cash Flows, lines 1773-1817 | Depreciation | FY2023 | J202: 1100 | K202: USD mm | L202: Historical_CF!D8 | M202: Direct transcription from audited filing | N202: Audited filing | Primary / audited | O202: MAPPED
A203: CLM-0199 | B203: Depreciation | C203: FY2024 | D203: S03 | E203: Tyson Foods FY2025 Form 10-K | F203: 0000100493-25-000095 | G203: 46219 | H203: https://www.sec.gov/Archives/edgar/data/100493/000010049325000095/tsn-20250927.htm | I203: FY2025 10-K, Consolidated Statements of Cash Flows, lines 1773-1817 | Depreciation | FY2024 | J203: 1159 | K203: USD mm | L203: Historical_CF!E8 | M203: Direct transcription from audited filing | N203: Audited filing | Primary / audited | O203: MAPPED
A204: CLM-0200 | B204: Depreciation | C204: FY2025 | D204: S03 | E204: Tyson Foods FY2025 Form 10-K | F204: 0000100493-25-000095 | G204: 46219 | H204: https://www.sec.gov/Archives/edgar/data/100493/000010049325000095/tsn-20250927.htm | I204: FY2025 10-K, Consolidated Statements of Cash Flows, lines 1773-1817 | Depreciation | FY2025 | J204: 1093 | K204: USD mm | L204: Historical_CF!F8 | M204: Direct transcription from audited filing | N204: Audited filing | Primary / audited | O204: MAPPED
A205: CLM-0201 | B205: Amortization | C205: FY2021 | D205: S01 | E205: Tyson Foods FY2022 Form 10-K | F205: 0000100493-22-000097 | G205: 46219 | H205: https://www.sec.gov/Archives/edgar/data/100493/000010049322000097/tsn-20221001.htm | I205: FY2022 10-K, Consolidated Statements of Cash Flows, lines 1835-1878 | Amortization | FY2021 | J205: 280 | K205: USD mm | L205: Historical_CF!B9 | M205: Direct transcription from audited filing | N205: Audited filing | Primary / audited | O205: MAPPED
A206: CLM-0202 | B206: Amortization | C206: FY2022 | D206: S01 | E206: Tyson Foods FY2022 Form 10-K | F206: 0000100493-22-000097 | G206: 46219 | H206: https://www.sec.gov/Archives/edgar/data/100493/000010049322000097/tsn-20221001.htm | I206: FY2022 10-K, Consolidated Statements of Cash Flows, lines 1835-1878 | Amortization | FY2022 | J206: 257 | K206: USD mm | L206: Historical_CF!C9 | M206: Direct transcription from audited filing | N206: Audited filing | Primary / audited | O206: MAPPED
... A224: CLM-0220 | B224: Stock-based compensation | C224: FY2025 | D224: S03 | E224: Tyson Foods FY2025 Form 10-K | F224: 0000100493-25-000095 | G224: 46219 | H224: https://www.sec.gov/Archives/edgar/data/100493/000010049325000095/tsn-20250927.htm | I224: FY2025 10-K, Consolidated Statements of Cash Flows, lines 1773-1817 | Stock-based compensation | FY2025 | J224: 100 | K224: USD mm | L224: Historical_CF!F12 | M224: Direct transcription from audited filing | N224: Audited filing | Primary / audited | O224: MAPPED
A225: CLM-0221 | B225: Working capital and other operating changes | C225: FY2021 | D225: DERIVED | E225: Workbook formula | F225: N/A | G225: 46219 | H225: N/A - workbook formula | I225: Derived from adjacent sourced statement rows | J225: Formula: =B14-SUM(B7:B12) | K225: USD mm | L225: Historical_CF!B13 | M225: Formula: =B14-SUM(B7:B12) | N225: Derived | Derived formula | O225: FORMULA
A226: CLM-0222 | B226: Working capital and other operating changes | C226: FY2022 | D226: DERIVED | E226: Workbook formula | F226: N/A | G226: 46219 | H226: N/A - workbook formula | I226: Derived from adjacent sourced statement rows | J226: Formula: =C14-SUM(C7:C12) | K226: USD mm | L226: Historical_CF!C13 | M226: Formula: =C14-SUM(C7:C12) | N226: Derived | Derived formula | O226: FORMULA
A227: CLM-0223 | B227: Working capital and other operating changes | C227: FY2023 | D227: DERIVED | E227: Workbook formula | F227: N/A | G227: 46219 | H227: N/A - workbook formula | I227: Derived from adjacent sourced statement rows | J227: Formula: =D14-SUM(D7:D12) | K227: USD mm | L227: Historical_CF!D13 | M227: Formula: =D14-SUM(D7:D12) | N227: Derived | Derived formula | O227: FORMULA
A228: CLM-0224 | B228: Working capital and other operating changes | C228: FY2024 | D228: DERIVED | E228: Workbook formula | F228: N/A | G228: 46219 | H228: N/A - workbook formula | I228: Derived from adjacent sourced statement rows | J228: Formula: =E14-SUM(E7:E12) | K228: USD mm | L228: Historical_CF!E13 | M228: Formula: =E14-SUM(E7:E12) | N228: Derived | Derived formula | O228: FORMULA
A229: CLM-0225 | B229: Working capital and other operating changes | C229: FY2025 | D229: DERIVED | E229: Workbook formula | F229: N/A | G229: 46219 | H229: N/A - workbook formula | I229: Derived from adjacent sourced statement rows | J229: Formula: =F14-SUM(F7:F12) | K229: USD mm | L229: Historical_CF!F13 | M229: Formula: =F14-SUM(F7:F12) | N229: Derived | Derived formula | O229: FORMULA
A230: CLM-0226 | B230: Cash provided by operating activities | C230: FY2021 | D230: S01 | E230: Tyson Foods FY2022 Form 10-K | F230: 0000100493-22-000097 | G230: 46219 | H230: https://www.sec.gov/Archives/edgar/data/100493/000010049322000097/tsn-20221001.htm | I230: FY2022 10-K, Consolidated Statements of Cash Flows, lines 1835-1878 | Cash provided by operating activities | FY2021 | J230: 3840 | K230: USD mm | L230: Historical_CF!B14 | M230: Direct transcription from audited filing | N230: Audited filing | Primary / audited | O230: MAPPED
A231: CLM-0227 | B231: Cash provided by operating activities | C231: FY2022 | D231: S01 | E231: Tyson Foods FY2022 Form 10-K | F231: 0000100493-22-000097 | G231: 46219 | H231: https://www.sec.gov/Archives/edgar/data/100493/000010049322000097/tsn-20221001.htm | I231: FY2022 10-K, Consolidated Statements of Cash Flows, lines 1835-1878 | Cash provided by operating activities | FY2022 | J231: 2687 | K231: USD mm | L231: Historical_CF!C14 | M231: Direct transcription from audited filing | N231: Audited filing | Primary / audited | O231: MAPPED
A232: CLM-0228 | B232: Cash provided by operating activities | C232: FY2023 | D232: S03 | E232: Tyson Foods FY2025 Form 10-K | F232: 0000100493-25-000095 | G232: 46219 | H232: https://www.sec.gov/Archives/edgar/data/100493/000010049325000095/tsn-20250927.htm | I232: FY2025 10-K, Consolidated Statements of Cash Flows, lines 1773-1817 | Cash provided by operating activities | FY2023 | J232: 1752 | K232: USD mm | L232: Historical_CF!D14 | M232: Direct transcription from audited filing | N232: Audited filing | Primary / audited | O232: MAPPED
A233: CLM-0229 | B233: Cash provided by operating activities | C233: FY2024 | D233: S03 | E233: Tyson Foods FY2025 Form 10-K | F233: 0000100493-25-000095 | G233: 46219 | H233: https://www.sec.gov/Archives/edgar/data/100493/000010049325000095/tsn-20250927.htm | I233: FY2025 10-K, Consolidated Statements of Cash Flows, lines 1773-1817 | Cash provided by operating activities | FY2024 | J233: 2590 | K233: USD mm | L233: Historical_CF!E14 | M233: Direct transcription from audited filing | N233: Audited filing | Primary / audited | O233: MAPPED
A234: CLM-0230 | B234: Cash provided by operating activities | C234: FY2025 | D234: S03 | E234: Tyson Foods FY2025 Form 10-K | F234: 0000100493-25-000095 | G234: 46219 | H234: https://www.sec.gov/Archives/edgar/data/100493/000010049325000095/tsn-20250927.htm | I234: FY2025 10-K, Consolidated Statements of Cash Flows, lines 1773-1817 | Cash provided by operating activities | FY2025 | J234: 2155 | K234: USD mm | L234: Historical_CF!F14 | M234: Direct transcription from audited filing | N234: Audited filing | Primary / audited | O234: MAPPED
A235: CLM-0231 | B235: Capital expenditures | C235: FY2021 | D235: S01 | E235: Tyson Foods FY2022 Form 10-K | F235: 0000100493-22-000097 | G235: 46219 | H235: https://www.sec.gov/Archives/edgar/data/100493/000010049322000097/tsn-20221001.htm | I235: FY2022 10-K, Consolidated Statements of Cash Flows, lines 1835-1878 | Capital expenditures | FY2021 | J235: -1209 | K235: USD mm | L235: Historical_CF!B15 | M235: Direct transcription from audited filing | N235: Audited filing | Primary / audited | O235: MAPPED
A236: CLM-0232 | B236: Capital expenditures | C236: FY2022 | D236: S01 | E236: Tyson Foods FY2022 Form 10-K | F236: 0000100493-22-000097 | G236: 46219 | H236: https://www.sec.gov/Archives/edgar/data/100493/000010049322000097/tsn-20221001.htm | I236: FY2022 10-K, Consolidated Statements of Cash Flows, lines 1835-1878 | Capital expenditures | FY2022 | J236: -1887 | K236: USD mm | L236: Historical_CF!C15 | M236: Direct transcription from audited filing | N236: Audited filing | Primary / audited | O236: MAPPED
A237: CLM-0233 | B237: Capital expenditures | C237: FY2023 | D237: S03 | E237: Tyson Foods FY2025 Form 10-K | F237: 0000100493-25-000095 | G237: 46219 | H237: https://www.sec.gov/Archives/edgar/data/100493/000010049325000095/tsn-20250927.htm | I237: FY2025 10-K, Consolidated Statements of Cash Flows, lines 1773-1817 | Capital expenditures | FY2023 | J237: -1939 | K237: USD mm | L237: Historical_CF!D15 | M237: Direct transcription from audited filing | N237: Audited filing | Primary / audited | O237: MAPPED
A238: CLM-0234 | B238: Capital expenditures | C238: FY2024 | D238: S03 | E238: Tyson Foods FY2025 Form 10-K | F238: 0000100493-25-000095 | G238: 46219 | H238: https://www.sec.gov/Archives/edgar/data/100493/000010049325000095/tsn-20250927.htm | I238: FY2025 10-K, Consolidated Statements of Cash Flows, lines 1773-1817 | Capital expenditures | FY2024 | J238: -1132 | K238: USD mm | L238: Historical_CF!E15 | M238: Direct transcription from audited filing | N238: Audited filing | Primary / audited | O238: MAPPED
A239: CLM-0235 | B239: Capital expenditures | C239: FY2025 | D239: S03 | E239: Tyson Foods FY2025 Form 10-K | F239: 0000100493-25-000095 | G239: 46219 | H239: https://www.sec.gov/Archives/edgar/data/100493/000010049325000095/tsn-20250927.htm | I239: FY2025 10-K, Consolidated Statements of Cash Flows, lines 1773-1817 | Capital expenditures | FY2025 | J239: -978 | K239: USD mm | L239: Historical_CF!F15 | M239: Direct transcription from audited filing | N239: Audited filing | Primary / audited | O239: MAPPED
A240: CLM-0236 | B240: Cash used for investing activities | C240: FY2021 | D240: S01 | E240: Tyson Foods FY2022 Form 10-K | F240: 0000100493-22-000097 | G240: 46219 | H240: https://www.sec.gov/Archives/edgar/data/100493/000010049322000097/tsn-20221001.htm | I240: FY2022 10-K, Consolidated Statements of Cash Flows, lines 1835-1878 | Cash used for investing activities | FY2021 | J240: 58 | K240: USD mm | L240: Historical_CF!B16 | M240: Direct transcription from audited filing | N240: Audited filing | Primary / audited | O240: MAPPED
A241: CLM-0237 | B241: Cash used for investing activities | C241: FY2022 | D241: S01 | E241: Tyson Foods FY2022 Form 10-K | F241: 0000100493-22-000097 | G241: 46219 | H241: https://www.sec.gov/Archives/edgar/data/100493/000010049322000097/tsn-20221001.htm | I241: FY2022 10-K, Consolidated Statements of Cash Flows, lines 1835-1878 | Cash used for investing activities | FY2022 | J241: -1935 | K241: USD mm | L241: Historical_CF!C16 | M241: Direct transcription from audited filing | N241: Audited filing | Primary / audited | O241: MAPPED
... A269: CLM-0265 | B269: Cash from financing activities | C269: FY2025 | D269: S03 | E269: Tyson Foods FY2025 Form 10-K | F269: 0000100493-25-000095 | G269: 46219 | H269: https://www.sec.gov/Archives/edgar/data/100493/000010049325000095/tsn-20250927.htm | I269: FY2025 10-K, Consolidated Statements of Cash Flows, lines 1773-1817 | Cash from financing activities | FY2025 | J269: -1977 | K269: USD mm | L269: Historical_CF!F21 | M269: Direct transcription from audited filing | N269: Audited filing | Primary / audited | O269: MAPPED
A270: CLM-0266 | B270: FX and other cash movement | C270: FY2021 | D270: DERIVED | E270: Workbook formula | F270: N/A | G270: 46219 | H270: N/A - workbook formula | I270: Derived from adjacent sourced statement rows | J270: Formula: =B23-B14-B16-B21 | K270: USD mm | L270: Historical_CF!B22 | M270: Formula: =B23-B14-B16-B21 | N270: Derived | Derived formula | O270: FORMULA
A271: CLM-0267 | B271: FX and other cash movement | C271: FY2022 | D271: DERIVED | E271: Workbook formula | F271: N/A | G271: 46219 | H271: N/A - workbook formula | I271: Derived from adjacent sourced statement rows | J271: Formula: =C23-C14-C16-C21 | K271: USD mm | L271: Historical_CF!C22 | M271: Formula: =C23-C14-C16-C21 | N271: Derived | Derived formula | O271: FORMULA
A272: CLM-0268 | B272: FX and other cash movement | C272: FY2023 | D272: DERIVED | E272: Workbook formula | F272: N/A | G272: 46219 | H272: N/A - workbook formula | I272: Derived from adjacent sourced statement rows | J272: Formula: =D23-D14-D16-D21 | K272: USD mm | L272: Historical_CF!D22 | M272: Formula: =D23-D14-D16-D21 | N272: Derived | Derived formula | O272: FORMULA
A273: CLM-0269 | B273: FX and other cash movement | C273: FY2024 | D273: DERIVED | E273: Workbook formula | F273: N/A | G273: 46219 | H273: N/A - workbook formula | I273: Derived from adjacent sourced statement rows | J273: Formula: =E23-E14-E16-E21 | K273: USD mm | L273: Historical_CF!E22 | M273: Formula: =E23-E14-E16-E21 | N273: Derived | Derived formula | O273: FORMULA
A274: CLM-0270 | B274: FX and other cash movement | C274: FY2025 | D274: DERIVED | E274: Workbook formula | F274: N/A | G274: 46219 | H274: N/A - workbook formula | I274: Derived from adjacent sourced statement rows | J274: Formula: =F23-F14-F16-F21 | K274: USD mm | L274: Historical_CF!F22 | M274: Formula: =F23-F14-F16-F21 | N274: Derived | Derived formula | O274: FORMULA
A275: CLM-0271 | B275: Change in cash | C275: FY2021 | D275: S01 | E275: Tyson Foods FY2022 Form 10-K | F275: 0000100493-22-000097 | G275: 46219 | H275: https://www.sec.gov/Archives/edgar/data/100493/000010049322000097/tsn-20221001.htm | I275: FY2022 10-K, Consolidated Statements of Cash Flows, lines 1835-1878 | Change in cash | FY2021 | J275: 1171 | K275: USD mm | L275: Historical_CF!B23 | M275: Direct transcription from audited filing | N275: Audited filing | Primary / audited | O275: MAPPED
A276: CLM-0272 | B276: Change in cash | C276: FY2022 | D276: S01 | E276: Tyson Foods FY2022 Form 10-K | F276: 0000100493-22-000097 | G276: 46219 | H276: https://www.sec.gov/Archives/edgar/data/100493/000010049322000097/tsn-20221001.htm | I276: FY2022 10-K, Consolidated Statements of Cash Flows, lines 1835-1878 | Change in cash | FY2022 | J276: -1606 | K276: USD mm | L276: Historical_CF!C23 | M276: Direct transcription from audited filing | N276: Audited filing | Primary / audited | O276: MAPPED
A277: CLM-0273 | B277: Change in cash | C277: FY2023 | D277: S03 | E277: Tyson Foods FY2025 Form 10-K | F277: 0000100493-25-000095 | G277: 46219 | H277: https://www.sec.gov/Archives/edgar/data/100493/000010049325000095/tsn-20250927.htm | I277: FY2025 10-K, Consolidated Statements of Cash Flows, lines 1773-1817 | Change in cash | FY2023 | J277: -458 | K277: USD mm | L277: Historical_CF!D23 | M277: Direct transcription from audited filing | N277: Audited filing | Primary / audited | O277: MAPPED
A278: CLM-0274 | B278: Change in cash | C278: FY2024 | D278: S03 | E278: Tyson Foods FY2025 Form 10-K | F278: 0000100493-25-000095 | G278: 46219 | H278: https://www.sec.gov/Archives/edgar/data/100493/000010049325000095/tsn-20250927.htm | I278: FY2025 10-K, Consolidated Statements of Cash Flows, lines 1773-1817 | Change in cash | FY2024 | J278: 1144 | K278: USD mm | L278: Historical_CF!E23 | M278: Direct transcription from audited filing | N278: Audited filing | Primary / audited | O278: MAPPED
A279: CLM-0275 | B279: Change in cash | C279: FY2025 | D279: S03 | E279: Tyson Foods FY2025 Form 10-K | F279: 0000100493-25-000095 | G279: 46219 | H279: https://www.sec.gov/Archives/edgar/data/100493/000010049325000095/tsn-20250927.htm | I279: FY2025 10-K, Consolidated Statements of Cash Flows, lines 1773-1817 | Change in cash | FY2025 | J279: -488 | K279: USD mm | L279: Historical_CF!F23 | M279: Direct transcription from audited filing | N279: Audited filing | Primary / audited | O279: MAPPED
A280: CLM-0276 | B280: Ending cash | C280: FY2021 | D280: S01 | E280: Tyson Foods FY2022 Form 10-K | F280: 0000100493-22-000097 | G280: 46219 | H280: https://www.sec.gov/Archives/edgar/data/100493/000010049322000097/tsn-20221001.htm | I280: FY2022 10-K, Consolidated Statements of Cash Flows, lines 1835-1878 | Ending cash | FY2021 | J280: 2507 | K280: USD mm | L280: Historical_CF!B24 | M280: Direct transcription from audited filing | N280: Audited filing | Primary / audited | O280: MAPPED
A281: CLM-0277 | B281: Ending cash | C281: FY2022 | D281: S01 | E281: Tyson Foods FY2022 Form 10-K | F281: 0000100493-22-000097 | G281: 46219 | H281: https://www.sec.gov/Archives/edgar/data/100493/000010049322000097/tsn-20221001.htm | I281: FY2022 10-K, Consolidated Statements of Cash Flows, lines 1835-1878 | Ending cash | FY2022 | J281: 1031 | K281: USD mm | L281: Historical_CF!C24 | M281: Direct transcription from audited filing | N281: Audited filing | Primary / audited | O281: MAPPED
A282: CLM-0278 | B282: Ending cash | C282: FY2023 | D282: S03 | E282: Tyson Foods FY2025 Form 10-K | F282: 0000100493-25-000095 | G282: 46219 | H282: https://www.sec.gov/Archives/edgar/data/100493/000010049325000095/tsn-20250927.htm | I282: FY2025 10-K, Consolidated Statements of Cash Flows, lines 1773-1817 | Ending cash | FY2023 | J282: 573 | K282: USD mm | L282: Historical_CF!D24 | M282: Direct transcription from audited filing | N282: Audited filing | Primary / audited | O282: MAPPED
A283: CLM-0279 | B283: Ending cash | C283: FY2024 | D283: S03 | E283: Tyson Foods FY2025 Form 10-K | F283: 0000100493-25-000095 | G283: 46219 | H283: https://www.sec.gov/Archives/edgar/data/100493/000010049325000095/tsn-20250927.htm | I283: FY2025 10-K, Consolidated Statements of Cash Flows, lines 1773-1817 | Ending cash | FY2024 | J283: 1717 | K283: USD mm | L283: Historical_CF!E24 | M283: Direct transcription from audited filing | N283: Audited filing | Primary / audited | O283: MAPPED
A284: CLM-0280 | B284: Ending cash | C284: FY2025 | D284: S03 | E284: Tyson Foods FY2025 Form 10-K | F284: 0000100493-25-000095 | G284: 46219 | H284: https://www.sec.gov/Archives/edgar/data/100493/000010049325000095/tsn-20250927.htm | I284: FY2025 10-K, Consolidated Statements of Cash Flows, lines 1773-1817 | Ending cash | FY2025 | J284: 1229 | K284: USD mm | L284: Historical_CF!F24 | M284: Direct transcription from audited filing | N284: Audited filing | Primary / audited | O284: MAPPED
A285: CLM-0281 | B285: Free cash flow | C285: FY2021 | D285: DERIVED | E285: Workbook formula | F285: N/A | G285: 46219 | H285: N/A - workbook formula | I285: Derived from adjacent sourced statement rows | J285: Formula: =B14+B15 | K285: USD mm | L285: Historical_CF!B25 | M285: Formula: =B14+B15 | N285: Derived | Derived formula | O285: FORMULA
A286: CLM-0282 | B286: Free cash flow | C286: FY2022 | D286: DERIVED | E286: Workbook formula | F286: N/A | G286: 46219 | H286: N/A - workbook formula | I286: Derived from adjacent sourced statement rows | J286: Formula: =C14+C15 | K286: USD mm | L286: Historical_CF!C25 | M286: Formula: =C14+C15 | N286: Derived | Derived formula | O286: FORMULA
A287: CLM-0283 | B287: Free cash flow | C287: FY2023 | D287: DERIVED | E287: Workbook formula | F287: N/A | G287: 46219 | H287: N/A - workbook formula | I287: Derived from adjacent sourced statement rows | J287: Formula: =D14+D15 | K287: USD mm | L287: Historical_CF!D25 | M287: Formula: =D14+D15 | N287: Derived | Derived formula | O287: FORMULA
A288: CLM-0284 | B288: Free cash flow | C288: FY2024 | D288: DERIVED | E288: Workbook formula | F288: N/A | G288: 46219 | H288: N/A - workbook formula | I288: Derived from adjacent sourced statement rows | J288: Formula: =E14+E15 | K288: USD mm | L288: Historical_CF!E25 | M288: Formula: =E14+E15 | N288: Derived | Derived formula | O288: FORMULA
A289: CLM-0285 | B289: Free cash flow | C289: FY2025 | D289: DERIVED | E289: Workbook formula | F289: N/A | G289: 46219 | H289: N/A - workbook formula | I289: Derived from adjacent sourced statement rows | J289: Formula: =F14+F15 | K289: USD mm | L289: Historical_CF!F25 | M289: Formula: =F14+F15 | N289: Derived | Derived formula | O289: FORMULA
A290: CLM-0286 | B290: Beef sales | C290: FY2021 | D290: S01 | E290: Tyson Foods FY2022 Form 10-K | F290: 0000100493-22-000097 | G290: 46219 | H290: https://www.sec.gov/Archives/edgar/data/100493/000010049322000097/tsn-20221001.htm | I290: FY2022 10-K segment table, legacy allocation | J290: 17999 | K290: USD mm | L290: Segment_Build!B7 | M290: Direct transcription | N290: Audited filing | Primary / legacy basis | O290: MAPPED
A291: CLM-0287 | B291: Beef sales | C291: FY2022 | D291: S01 | E291: Tyson Foods FY2022 Form 10-K | F291: 0000100493-22-000097 | G291: 46219 | H291: https://www.sec.gov/Archives/edgar/data/100493/000010049322000097/tsn-20221001.htm | I291: FY2022 10-K segment table, legacy allocation | J291: 19854 | K291: USD mm | L291: Segment_Build!C7 | M291: Direct transcription | N291: Audited filing | Primary / legacy basis | O291: MAPPED
A292: CLM-0288 | B292: Beef sales | C292: FY2023 | D292: S04 | E292: Tyson Foods segment recast 8-K Exhibit 99.1 | F292: 0000100493-26-000032 | G292: 46219 | H292: https://www.sec.gov/Archives/edgar/data/100493/000010049326000032/tsn20268-kexhibit991060926.htm | I292: June 2026 recast exhibit segment table | J292: 19325 | K292: USD mm | L292: Segment_Build!D7 | M292: Direct transcription | N292: Filed recast | Primary / recast | O292: MAPPED
A293: CLM-0289 | B293: Beef sales | C293: FY2024 | D293: S04 | E293: Tyson Foods segment recast 8-K Exhibit 99.1 | F293: 0000100493-26-000032 | G293: 46219 | H293: https://www.sec.gov/Archives/edgar/data/100493/000010049326000032/tsn20268-kexhibit991060926.htm | I293: June 2026 recast exhibit segment table | J293: 20479 | K293: USD mm | L293: Segment_Build!E7 | M293: Direct transcription | N293: Filed recast | Primary / recast | O293: MAPPED
A294: CLM-0290 | B294: Beef sales | C294: FY2025 | D294: S04 | E294: Tyson Foods segment recast 8-K Exhibit 99.1 | F294: 0000100493-26-000032 | G294: 46219 | H294: https://www.sec.gov/Archives/edgar/data/100493/000010049326000032/tsn20268-kexhibit991060926.htm | I294: June 2026 recast exhibit segment table | J294: 21623 | K294: USD mm | L294: Segment_Build!F7 | M294: Direct transcription | N294: Filed recast | Primary / recast | O294: MAPPED
A295: CLM-0291 | B295: Pork sales | C295: FY2021 | D295: S01 | E295: Tyson Foods FY2022 Form 10-K | F295: 0000100493-22-000097 | G295: 46219 | H295: https://www.sec.gov/Archives/edgar/data/100493/000010049322000097/tsn-20221001.htm | I295: FY2022 10-K segment table, legacy allocation | J295: 6277 | K295: USD mm | L295: Segment_Build!B8 | M295: Direct transcription | N295: Audited filing | Primary / legacy basis | O295: MAPPED
A296: CLM-0292 | B296: Pork sales | C296: FY2022 | D296: S01 | E296: Tyson Foods FY2022 Form 10-K | F296: 0000100493-22-000097 | G296: 46219 | H296: https://www.sec.gov/Archives/edgar/data/100493/000010049322000097/tsn-20221001.htm | I296: FY2022 10-K segment table, legacy allocation | J296: 6414 | K296: USD mm | L296: Segment_Build!C8 | M296: Direct transcription | N296: Audited filing | Primary / legacy basis | O296: MAPPED
A297: CLM-0293 | B297: Pork sales | C297: FY2023 | D297: S04 | E297: Tyson Foods segment recast 8-K Exhibit 99.1 | F297: 0000100493-26-000032 | G297: 46219 | H297: https://www.sec.gov/Archives/edgar/data/100493/000010049326000032/tsn20268-kexhibit991060926.htm | I297: June 2026 recast exhibit segment table | J297: 5768 | K297: USD mm | L297: Segment_Build!D8 | M297: Direct transcription | N297: Filed recast | Primary / recast | O297: MAPPED
A298: CLM-0294 | B298: Pork sales | C298: FY2024 | D298: S04 | E298: Tyson Foods segment recast 8-K Exhibit 99.1 | F298: 0000100493-26-000032 | G298: 46219 | H298: https://www.sec.gov/Archives/edgar/data/100493/000010049326000032/tsn20268-kexhibit991060926.htm | I298: June 2026 recast exhibit segment table | J298: 5903 | K298: USD mm | L298: Segment_Build!E8 | M298: Direct transcription | N298: Filed recast | Primary / recast | O298: MAPPED
A299: CLM-0295 | B299: Pork sales | C299: FY2025 | D299: S04 | E299: Tyson Foods segment recast 8-K Exhibit 99.1 | F299: 0000100493-26-000032 | G299: 46219 | H299: https://www.sec.gov/Archives/edgar/data/100493/000010049326000032/tsn20268-kexhibit991060926.htm | I299: June 2026 recast exhibit segment table | J299: 5781 | K299: USD mm | L299: Segment_Build!F8 | M299: Direct transcription | N299: Filed recast | Primary / recast | O299: MAPPED
A300: CLM-0296 | B300: Chicken sales | C300: FY2021 | D300: S01 | E300: Tyson Foods FY2022 Form 10-K | F300: 0000100493-22-000097 | G300: 46219 | H300: https://www.sec.gov/Archives/edgar/data/100493/000010049322000097/tsn-20221001.htm | I300: FY2022 10-K segment table, legacy allocation | J300: 13733 | K300: USD mm | L300: Segment_Build!B9 | M300: Direct transcription | N300: Audited filing | Primary / legacy basis | O300: MAPPED
A301: CLM-0297 | B301: Chicken sales | C301: FY2022 | D301: S01 | E301: Tyson Foods FY2022 Form 10-K | F301: 0000100493-22-000097 | G301: 46219 | H301: https://www.sec.gov/Archives/edgar/data/100493/000010049322000097/tsn-20221001.htm | I301: FY2022 10-K segment table, legacy allocation | J301: 16961 | K301: USD mm | L301: Segment_Build!C9 | M301: Direct transcription | N301: Audited filing | Primary / legacy basis | O301: MAPPED
... A684: CLM-0680 | B684: 6M FY2026 Amortization | C684: 6M FY2026 ended 2026-03-28 | D684: S05 | E684: Tyson Foods Q2 FY2026 Form 10-Q | F684: 0000100493-26-000020 | G684: 46219 | H684: https://www.sec.gov/Archives/edgar/data/100493/000010049326000020/tsn-20260328.htm | I684: Q2 FY2026 recast segment table | J684: -108 | K684: USD mm | L684: Interim_Bridge!B29 | M684: Direct transcription from filed 10-Q | N684: Filed interim | Primary / filed | O684: MAPPED
A685: CLM-0681 | B685: Commercial paper | C685: 46109 | D685: S05 | E685: Tyson Foods Q2 FY2026 Form 10-Q | F685: 0000100493-26-000020 | G685: 46219 | H685: https://www.sec.gov/Archives/edgar/data/100493/000010049326000020/tsn-20260328.htm | I685: Note 6 Debt, major components of debt | J685: 30 | K685: USD mm | L685: Debt_Credit!B6 | M685: Direct transcription or disclosed arithmetic | N685: Filed interim | Primary / filed | O685: MAPPED
A686: CLM-0682 | B686: 3.55% senior notes | C686: 46109 | D686: S05 | E686: Tyson Foods Q2 FY2026 Form 10-Q | F686: 0000100493-26-000020 | G686: 46219 | H686: https://www.sec.gov/Archives/edgar/data/100493/000010049326000020/tsn-20260328.htm | I686: Note 6 Debt, major components of debt | J686: 1350 | K686: USD mm | L686: Debt_Credit!B7 | M686: Direct transcription or disclosed arithmetic | N686: Filed interim | Primary / filed | O686: MAPPED
A687: CLM-0683 | B687: 7.00% senior notes | C687: 46109 | D687: S05 | E687: Tyson Foods Q2 FY2026 Form 10-Q | F687: 0000100493-26-000020 | G687: 46219 | H687: https://www.sec.gov/Archives/edgar/data/100493/000010049326000020/tsn-20260328.htm | I687: Note 6 Debt, major components of debt | J687: 18 | K687: USD mm | L687: Debt_Credit!B8 | M687: Direct transcription or disclosed arithmetic | N687: Filed interim | Primary / filed | O687: MAPPED
A688: CLM-0684 | B688: 4.35% senior notes | C688: 46109 | D688: S05 | E688: Tyson Foods Q2 FY2026 Form 10-Q | F688: 0000100493-26-000020 | G688: 46219 | H688: https://www.sec.gov/Archives/edgar/data/100493/000010049326000020/tsn-20260328.htm | I688: Note 6 Debt, major components of debt | J688: 1000 | K688: USD mm | L688: Debt_Credit!B9 | M688: Direct transcription or disclosed arithmetic | N688: Filed interim | Primary / filed | O688: MAPPED
A689: CLM-0685 | B689: 5.40% senior notes | C689: 46109 | D689: S05 | E689: Tyson Foods Q2 FY2026 Form 10-Q | F689: 0000100493-26-000020 | G689: 46219 | H689: https://www.sec.gov/Archives/edgar/data/100493/000010049326000020/tsn-20260328.htm | I689: Note 6 Debt, major components of debt | J689: 600 | K689: USD mm | L689: Debt_Credit!B10 | M689: Direct transcription or disclosed arithmetic | N689: Filed interim | Primary / filed | O689: MAPPED
A690: CLM-0686 | B690: 6.13% senior notes | C690: 46109 | D690: S05 | E690: Tyson Foods Q2 FY2026 Form 10-Q | F690: 0000100493-26-000020 | G690: 46219 | H690: https://www.sec.gov/Archives/edgar/data/100493/000010049326000020/tsn-20260328.htm | I690: Note 6 Debt, major components of debt | J690: 157 | K690: USD mm | L690: Debt_Credit!B11 | M690: Direct transcription or disclosed arithmetic | N690: Filed interim | Primary / filed | O690: MAPPED
A691: CLM-0687 | B691: 5.70% senior notes | C691: 46109 | D691: S05 | E691: Tyson Foods Q2 FY2026 Form 10-Q | F691: 0000100493-26-000020 | G691: 46219 | H691: https://www.sec.gov/Archives/edgar/data/100493/000010049326000020/tsn-20260328.htm | I691: Note 6 Debt, major components of debt | J691: 900 | K691: USD mm | L691: Debt_Credit!B12 | M691: Direct transcription or disclosed arithmetic | N691: Filed interim | Primary / filed | O691: MAPPED
A692: CLM-0688 | B692: 4.88% senior notes | C692: 46109 | D692: S05 | E692: Tyson Foods Q2 FY2026 Form 10-Q | F692: 0000100493-26-000020 | G692: 46219 | H692: https://www.sec.gov/Archives/edgar/data/100493/000010049326000020/tsn-20260328.htm | I692: Note 6 Debt, major components of debt | J692: 500 | K692: USD mm | L692: Debt_Credit!B13 | M692: Direct transcription or disclosed arithmetic | N692: Filed interim | Primary / filed | O692: MAPPED
A693: CLM-0689 | B693: 4.95% senior notes | C693: 46109 | D693: S05 | E693: Tyson Foods Q2 FY2026 Form 10-Q | F693: 0000100493-26-000020 | G693: 46219 | H693: https://www.sec.gov/Archives/edgar/data/100493/000010049326000020/tsn-20260328.htm | I693: Note 6 Debt, major components of debt | J693: 500 | K693: USD mm | L693: Debt_Credit!B14 | M693: Direct transcription or disclosed arithmetic | N693: Filed interim | Primary / filed | O693: MAPPED
A694: CLM-0690 | B694: 5.15% senior notes | C694: 46109 | D694: S05 | E694: Tyson Foods Q2 FY2026 Form 10-Q | F694: 0000100493-26-000020 | G694: 46219 | H694: https://www.sec.gov/Archives/edgar/data/100493/000010049326000020/tsn-20260328.htm | I694: Note 6 Debt, major components of debt | J694: 497 | K694: USD mm | L694: Debt_Credit!B15 | M694: Direct transcription or disclosed arithmetic | N694: Filed interim | Primary / filed | O694: MAPPED
A695: CLM-0691 | B695: 4.55% senior notes | C695: 46109 | D695: S05 | E695: Tyson Foods Q2 FY2026 Form 10-Q | F695: 0000100493-26-000020 | G695: 46219 | H695: https://www.sec.gov/Archives/edgar/data/100493/000010049326000020/tsn-20260328.htm | I695: Note 6 Debt, major components of debt | J695: 713 | K695: USD mm | L695: Debt_Credit!B16 | M695: Direct transcription or disclosed arithmetic | N695: Filed interim | Primary / filed | O695: MAPPED
A696: CLM-0692 | B696: 5.10% senior notes | C696: 46109 | D696: S05 | E696: Tyson Foods Q2 FY2026 Form 10-Q | F696: 0000100493-26-000020 | G696: 46219 | H696: https://www.sec.gov/Archives/edgar/data/100493/000010049326000020/tsn-20260328.htm | I696: Note 6 Debt, major components of debt | J696: 1485 | K696: USD mm | L696: Debt_Credit!B17 | M696: Direct transcription or disclosed arithmetic | N696: Filed interim | Primary / filed | O696: MAPPED
... A718: CLM-0714 | B718: Class B shares | C718: 46109 | D718: S05 | E718: Tyson Foods Q2 FY2026 Form 10-Q | F718: 0000100493-26-000020 | G718: 46219 | H718: https://www.sec.gov/Archives/edgar/data/100493/000010049326000020/tsn-20260328.htm | I718: Q2 FY2026 cover / shares outstanding | J718: 70.009005 | K718: mm shares | L718: DCF!B37 | M718: Direct transcription | N718: Filed interim | Primary / filed | O718: MAPPED

Sheet Checks
A1: Model Checks
A2: One assertion per row; overall status aggregates all formula-driven controls
A3: OVERALL MODEL STATUS | B3: =IF(COUNTIF(F6:F81,"OK")=COUNTA(A6:A81),"OK","FAIL") -> OK
A4: Check | B4: Actual | C4: Expected | D4: Difference | E4: Tolerance | F4: Status | G4: Notes / fix hint
A6: FY2021 gross profit | B6: =Historical_IS!B9 -> 6526 | C6: =Historical_IS!B7-Historical_IS!B8 -> 6526 | D6: =B6-C6 -> 0 | E6: 0.5 | F6: =IF(ABS(D6)<=E6,"OK","FAIL") -> OK
A7: FY2021 balance sheet | B7: =Historical_BS!B16 -> 36309 | C7: =Historical_BS!B30 -> 36309 | D7: =B7-C7 -> 0 | E7: 0.5 | F7: =IF(ABS(D7)<=E7,"OK","FAIL") -> OK
A8: FY2021 segment sales | B8: =Segment_Build!B13 -> 47049 | C8: =Historical_IS!B7 -> 47049 | D8: =B8-C8 -> 0 | E8: 0.5 | F8: =IF(ABS(D8)<=E8,"OK","FAIL") -> OK
A9: FY2021 segment OI | B9: =Segment_Build!B24 -> 4396 | C9: =Historical_IS!B12 -> 4396 | D9: =B9-C9 -> 0 | E9: 0.5 | F9: =IF(ABS(D9)<=E9,"OK","FAIL") -> OK
A10: FY2022 gross profit | B10: =Historical_IS!C9 -> 6668 | C10: =Historical_IS!C7-Historical_IS!C8 -> 6668 | D10: =B10-C10 -> 0 | E10: 0.5 | F10: =IF(ABS(D10)<=E10,"OK","FAIL") -> OK
A11: FY2022 balance sheet | B11: =Historical_BS!C16 -> 36821 | C11: =Historical_BS!C30 -> 36821 | D11: =B11-C11 -> 0 | E11: 0.5 | F11: =IF(ABS(D11)<=E11,"OK","FAIL") -> OK
A12: FY2022 segment sales | B12: =Segment_Build!C13 -> 53282 | C12: =Historical_IS!C7 -> 53282 | D12: =B12-C12 -> 0 | E12: 0.5 | F12: =IF(ABS(D12)<=E12,"OK","FAIL") -> OK
A13: FY2022 segment OI | B13: =Segment_Build!C24 -> 4410 | C13: =Historical_IS!C12 -> 4410 | D13: =B13-C13 -> 0 | E13: 0.5 | F13: =IF(ABS(D13)<=E13,"OK","FAIL") -> OK
A14: FY2023 gross profit | B14: =Historical_IS!D9 -> 2631 | C14: =Historical_IS!D7-Historical_IS!D8 -> 2631 | D14: =B14-C14 -> 0 | E14: 0.5 | F14: =IF(ABS(D14)<=E14,"OK","FAIL") -> OK
A15: FY2023 balance sheet | B15: =Historical_BS!D16 -> 36251 | C15: =Historical_BS!D30 -> 36251 | D15: =B15-C15 -> 0 | E15: 0.5 | F15: =IF(ABS(D15)<=E15,"OK","FAIL") -> OK
A16: FY2023 segment sales | B16: =Segment_Build!D13 -> 52881 | C16: =Historical_IS!D7 -> 52881 | D16: =B16-C16 -> 0 | E16: 0.5 | F16: =IF(ABS(D16)<=E16,"OK","FAIL") -> OK
A17: FY2023 segment OI | B17: =Segment_Build!D24 -> -395 | C17: =Historical_IS!D12 -> -395 | D17: =B17-C17 -> 0 | E17: 0.5 | F17: =IF(ABS(D17)<=E17,"OK","FAIL") -> OK
A18: FY2024 gross profit | B18: =Historical_IS!E9 -> 3627 | C18: =Historical_IS!E7-Historical_IS!E8 -> 3627 | D18: =B18-C18 -> 0 | E18: 0.5 | F18: =IF(ABS(D18)<=E18,"OK","FAIL") -> OK
A19: FY2024 balance sheet | B19: =Historical_BS!E16 -> 37100 | C19: =Historical_BS!E30 -> 37100 | D19: =B19-C19 -> 0 | E19: 0.5 | F19: =IF(ABS(D19)<=E19,"OK","FAIL") -> OK
A20: FY2024 segment sales | B20: =Segment_Build!E13 -> 53309 | C20: =Historical_IS!E7 -> 53309 | D20: =B20-C20 -> 0 | E20: 0.5 | F20: =IF(ABS(D20)<=E20,"OK","FAIL") -> OK
A21: FY2024 segment OI | B21: =Segment_Build!E24 -> 1409 | C21: =Historical_IS!E12 -> 1409 | D21: =B21-C21 -> 0 | E21: 0.5 | F21: =IF(ABS(D21)<=E21,"OK","FAIL") -> OK
A22: FY2025 gross profit | B22: =Historical_IS!F9 -> 3562 | C22: =Historical_IS!F7-Historical_IS!F8 -> 3562 | D22: =B22-C22 -> 0 | E22: 0.5 | F22: =IF(ABS(D22)<=E22,"OK","FAIL") -> OK
A23: FY2025 balance sheet | B23: =Historical_BS!F16 -> 36658 | C23: =Historical_BS!F30 -> 36658 | D23: =B23-C23 -> 0 | E23: 0.5 | F23: =IF(ABS(D23)<=E23,"OK","FAIL") -> OK
A24: FY2025 segment sales | B24: =Segment_Build!F13 -> 54441 | C24: =Historical_IS!F7 -> 54441 | D24: =B24-C24 -> 0 | E24: 0.5 | F24: =IF(ABS(D24)<=E24,"OK","FAIL") -> OK
A25: FY2025 segment OI | B25: =Segment_Build!F24 -> 1098 | C25: =Historical_IS!F12 -> 1098 | D25: =B25-C25 -> 0 | E25: 0.5 | F25: =IF(ABS(D25)<=E25,"OK","FAIL") -> OK
A26: FY2026 balance sheet | B26: =Forecast_3Stmt!C48 -> 0 | C26: 0 | D26: =B26-C26 -> 0 | E26: 0.5 | F26: =IF(ABS(D26)<=E26,"OK","FAIL") -> OK | G26: Trace Forecast_3Stmt BS schedules
A27: FY2026 minimum cash floor | B27: =MIN(Schedules!C37,0) -> 0 | C27: 0 | D27: =B27-C27 -> 0 | E27: 0.5 | F27: =IF(ABS(D27)<=E27,"OK","FAIL") -> OK | G27: Actual ending cash may exceed the floor once debt reaches zero
A28: FY2026 debt nonnegative | B28: =MIN(Schedules!C30,0) -> 0 | C28: 0 | D28: =B28-C28 -> 0 | E28: 0 | F28: =IF(ABS(D28)<=E28,"OK","FAIL") -> OK | G28: Negative debt indicates excess cash policy needs revision
A29: FY2026 FCF tie | B29: =DCF!C15 -> 1385.524 | C29: =DCF!C11+DCF!C12-DCF!C13-DCF!C14 -> 1385.524 | D29: =B29-C29 -> 0 | E29: 0.5 | F29: =IF(ABS(D29)<=E29,"OK","FAIL") -> OK
A30: FY2026 Tyson equity roll | B30: =Schedules!C41 -> 18852.343 | C30: =Schedules!C38+Schedules!C39+Schedules!C40 -> 18852.343 | D30: =B30-C30 -> 0 | E30: 0.5 | F30: =IF(ABS(D30)<=E30,"OK","FAIL") -> OK
A31: FY2027 balance sheet | B31: =Forecast_3Stmt!D48 -> 0 | C31: 0 | D31: =B31-C31 -> 0 | E31: 0.5 | F31: =IF(ABS(D31)<=E31,"OK","FAIL") -> OK | G31: Trace Forecast_3Stmt BS schedules
A32: FY2027 minimum cash floor | B32: =MIN(Schedules!D37,0) -> 0 | C32: 0 | D32: =B32-C32 -> 0 | E32: 0.5 | F32: =IF(ABS(D32)<=E32,"OK","FAIL") -> OK | G32: Actual ending cash may exceed the floor once debt reaches zero
A33: FY2027 debt nonnegative | B33: =MIN(Schedules!D30,0) -> 0 | C33: 0 | D33: =B33-C33 -> 0 | E33: 0 | F33: =IF(ABS(D33)<=E33,"OK","FAIL") -> OK | G33: Negative debt indicates excess cash policy needs revision
A34: FY2027 FCF tie | B34: =DCF!D15 -> 2643.9213 | C34: =DCF!D11+DCF!D12-DCF!D13-DCF!D14 -> 2643.9213 | D34: =B34-C34 -> 0 | E34: 0.5 | F34: =IF(ABS(D34)<=E34,"OK","FAIL") -> OK
A35: FY2027 Tyson equity roll | B35: =Schedules!D41 -> 19785.112 | C35: =Schedules!D38+Schedules!D39+Schedules!D40 -> 19785.112 | D35: =B35-C35 -> 0 | E35: 0.5 | F35: =IF(ABS(D35)<=E35,"OK","FAIL") -> OK
A36: FY2028 balance sheet | B36: =Forecast_3Stmt!E48 -> 0 | C36: 0 | D36: =B36-C36 -> 0 | E36: 0.5 | F36: =IF(ABS(D36)<=E36,"OK","FAIL") -> OK | G36: Trace Forecast_3Stmt BS schedules
A37: FY2028 minimum cash floor | B37: =MIN(Schedules!E37,0) -> 0 | C37: 0 | D37: =B37-C37 -> 0 | E37: 0.5 | F37: =IF(ABS(D37)<=E37,"OK","FAIL") -> OK | G37: Actual ending cash may exceed the floor once debt reaches zero
A38: FY2028 debt nonnegative | B38: =MIN(Schedules!E30,0) -> 0 | C38: 0 | D38: =B38-C38 -> 0 | E38: 0 | F38: =IF(ABS(D38)<=E38,"OK","FAIL") -> OK | G38: Negative debt indicates excess cash policy needs revision
A39: FY2028 FCF tie | B39: =DCF!E15 -> 2829.2313 | C39: =DCF!E11+DCF!E12-DCF!E13-DCF!E14 -> 2829.2313 | D39: =B39-C39 -> 0 | E39: 0.5 | F39: =IF(ABS(D39)<=E39,"OK","FAIL") -> OK
A40: FY2028 Tyson equity roll | B40: =Schedules!E41 -> 20830.146 | C40: =Schedules!E38+Schedules!E39+Schedules!E40 -> 20830.146 | D40: =B40-C40 -> 0 | E40: 0.5 | F40: =IF(ABS(D40)<=E40,"OK","FAIL") -> OK
A41: FY2029 balance sheet | B41: =Forecast_3Stmt!F48 -> 0 | C41: 0 | D41: =B41-C41 -> 0 | E41: 0.5 | F41: =IF(ABS(D41)<=E41,"OK","FAIL") -> OK | G41: Trace Forecast_3Stmt BS schedules
A42: FY2029 minimum cash floor | B42: =MIN(Schedules!F37,0) -> 0 | C42: 0 | D42: =B42-C42 -> 0 | E42: 0.5 | F42: =IF(ABS(D42)<=E42,"OK","FAIL") -> OK | G42: Actual ending cash may exceed the floor once debt reaches zero
A43: FY2029 debt nonnegative | B43: =MIN(Schedules!F30,0) -> 0 | C43: 0 | D43: =B43-C43 -> 0 | E43: 0 | F43: =IF(ABS(D43)<=E43,"OK","FAIL") -> OK | G43: Negative debt indicates excess cash policy needs revision
A44: FY2029 FCF tie | B44: =DCF!F15 -> 3031.6122 | C44: =DCF!F11+DCF!F12-DCF!F13-DCF!F14 -> 3031.6122 | D44: =B44-C44 -> 0 | E44: 0.5 | F44: =IF(ABS(D44)<=E44,"OK","FAIL") -> OK
A45: FY2029 Tyson equity roll | B45: =Schedules!F41 -> 21991.8 | C45: =Schedules!F38+Schedules!F39+Schedules!F40 -> 21991.8 | D45: =B45-C45 -> 0 | E45: 0.5 | F45: =IF(ABS(D45)<=E45,"OK","FAIL") -> OK
A46: FY2030 balance sheet | B46: =Forecast_3Stmt!G48 -> 0 | C46: 0 | D46: =B46-C46 -> 0 | E46: 0.5 | F46: =IF(ABS(D46)<=E46,"OK","FAIL") -> OK | G46: Trace Forecast_3Stmt BS schedules
A47: FY2030 minimum cash floor | B47: =MIN(Schedules!G37,0) -> 0 | C47: 0 | D47: =B47-C47 -> 0 | E47: 0.5 | F47: =IF(ABS(D47)<=E47,"OK","FAIL") -> OK | G47: Actual ending cash may exceed the floor once debt reaches zero
A48: FY2030 debt nonnegative | B48: =MIN(Schedules!G30,0) -> 0 | C48: 0 | D48: =B48-C48 -> 0 | E48: 0 | F48: =IF(ABS(D48)<=E48,"OK","FAIL") -> OK | G48: Negative debt indicates excess cash policy needs revision
A49: FY2030 FCF tie | B49: =DCF!G15 -> 3231.7382 | C49: =DCF!G11+DCF!G12-DCF!G13-DCF!G14 -> 3231.7382 | D49: =B49-C49 -> 0 | E49: 0.5 | F49: =IF(ABS(D49)<=E49,"OK","FAIL") -> OK
A50: FY2030 Tyson equity roll | B50: =Schedules!G41 -> 23271.195 | C50: =Schedules!G38+Schedules!G39+Schedules!G40 -> 23271.195 | D50: =B50-C50 -> 0 | E50: 0.5 | F50: =IF(ABS(D50)<=E50,"OK","FAIL") -> OK
A51: DCF equity bridge | B51: =DCF!B28 -> 38347.956 | C51: =DCF!B23+DCF!B24-DCF!B25-DCF!B27 -> 38347.956 | D51: =B51-C51 -> 0 | E51: 0.5 | F51: =IF(ABS(D51)<=E51,"OK","FAIL") -> OK
A52: DCF share bridge | B52: =DCF!B39 -> 0 | C52: 0 | D52: =B52-C52 -> 0 | E52: 1e-06 | F52: =IF(ABS(D52)<=E52,"OK","FAIL") -> OK
A53: DCF timing H2 stub | B53: =1/DCF!C16 -> 1.0206044 | C53: =(1+Assumptions!B94)^0.25 -> 1.0206044 | D53: =B53-C53 -> 0 | E53: 1e-06 | F53: =IF(ABS(D53)<=E53,"OK","FAIL") -> OK
A54: DCF terminal timing | B54: =DCF!B21 -> 4.5 | C54: 4.5 | D54: =B54-C54 -> 0 | E54: 0 | F54: =IF(ABS(D54)<=E54,"OK","FAIL") -> OK
A55: Base-only FY26 comparable sales growth | B55: =IF(Assumptions!B4=1,Interim_Bridge!D7/Historical_IS!F7-1,0) -> 0.030895033 | C55: =IF(Assumptions!B4=1,0.03,0) -> 0.03 | D55: =B55-C55 -> 0.00089503316 | E55: 0.01 | F55: =IF(ABS(D55)<=E55,"OK","FAIL") -> OK | G55: Official Base range is 2%-4%; neutral outside Base
A56: Base-only FY26 52-week adjusted operating income | B56: =IF(Assumptions!B4=1,Interim_Bridge!D12,0) -> 2394.6656 | C56: =IF(Assumptions!B4=1,2300,0) -> 2300 | D56: =B56-C56 -> 94.665608 | E56: 100 | F56: =IF(ABS(D56)<=E56,"OK","FAIL") -> OK | G56: Official Base adjusted OI range is $2.2-$2.4bn; neutral outside Base
A57: Claim-level source mappings | B57: =COUNTA(Sources!A5:A718) -> 714 | C57: 714 | D57: =B57-C57 -> 0 | E57: 0 | F57: =IF(ABS(D57)<=E57,"OK","FAIL") -> OK
A58: Source URLs complete | B58: =COUNTBLANK(Sources!H5:H718) -> 0 | C58: 0 | D58: =B58-C58 -> 0 | E58: 0 | F58: =IF(ABS(D58)<=E58,"OK","FAIL") -> OK
A59: Source locators complete | B59: =COUNTBLANK(Sources!I5:I718) -> 0 | C59: 0 | D59: =B59-C59 -> 0 | E59: 0 | F59: =IF(ABS(D59)<=E59,"OK","FAIL") -> OK
A60: Source destinations complete | B60: =COUNTBLANK(Sources!L5:L718) -> 0 | C60: 0 | D60: =B60-C60 -> 0 | E60: 0 | F60: =IF(ABS(D60)<=E60,"OK","FAIL") -> OK
A61: Source statuses complete | B61: =COUNTA(Sources!O5:O718) -> 714 | C61: 714 | D61: =B61-C61 -> 0 | E61: 0 | F61: =IF(ABS(D61)<=E61,"OK","FAIL") -> OK
A62: FY24 sales volume-price bridge | B62: =Protein_Drivers!B14 -> 0 | C62: 0 | D62: =B62-C62 -> 0 | E62: 0 | F62: =IF(ABS(D62)<=E62,"OK","FAIL") -> OK
A63: FY24 cost volume-input bridge | B63: =Protein_Drivers!B33 -> 0 | C63: 0 | D63: =B63-C63 -> 0 | E63: 0 | F63: =IF(ABS(D63)<=E63,"OK","FAIL") -> OK
A64: FY25 sales volume-price bridge | B64: =Protein_Drivers!C14 -> 0 | C64: 0 | D64: =B64-C64 -> 0 | E64: 0 | F64: =IF(ABS(D64)<=E64,"OK","FAIL") -> OK
A65: FY25 cost volume-input bridge | B65: =Protein_Drivers!C33 -> 0 | C65: 0 | D65: =B65-C65 -> 0 | E65: 0 | F65: =IF(ABS(D65)<=E65,"OK","FAIL") -> OK
A66: 6M FY26 sales volume-price bridge | B66: =Protein_Drivers!D14 -> 0 | C66: 0 | D66: =B66-C66 -> 0 | E66: 0 | F66: =IF(ABS(D66)<=E66,"OK","FAIL") -> OK
A67: 6M FY26 cost volume-input bridge | B67: =Protein_Drivers!D33 -> 0 | C67: 0 | D67: =B67-C67 -> 0 | E67: 0 | F67: =IF(ABS(D67)<=E67,"OK","FAIL") -> OK
A68: FY25 input-cost decomposition | B68: =Protein_Drivers!B51 -> 0 | C68: 0 | D68: =B68-C68 -> 0 | E68: 0 | F68: =IF(ABS(D68)<=E68,"OK","FAIL") -> OK
A69: 6M FY26 input-cost decomposition | B69: =Protein_Drivers!C51 -> 0 | C69: 0 | D69: =B69-C69 -> 0 | E69: 0 | F69: =IF(ABS(D69)<=E69,"OK","FAIL") -> OK
A70: Q2 FY26 debt stack total | B70: =Debt_Credit!B22 -> 8083 | C70: 8083 | D70: =B70-C70 -> 0 | E70: 0 | F70: =IF(ABS(D70)<=E70,"OK","FAIL") -> OK
A71: Q2 FY26 debt classification | B71: =Debt_Credit!B25 -> 0 | C71: 0 | D71: =B71-C71 -> 0 | E71: 0 | F71: =IF(ABS(D71)<=E71,"OK","FAIL") -> OK
A72: FY2026 Beef volume-price sales build | B72: =Segment_Build!G7/Segment_Build!F7/(1+Assumptions!$B$97)-1 -> 0.0094 | C72: =Protein_Drivers!L66 -> 0.0094 | D72: =B72-C72 -> 0 | E72: 1e-06 | F72: =IF(ABS(D72)<=E72,"OK","FAIL") -> OK
A73: FY2027 Beef volume-price sales build | B73: =Segment_Build!H7/Segment_Build!G7-1 -> 0.02 | C73: =Protein_Drivers!M66 -> 0.02 | D73: =B73-C73 -> 0 | E73: 1e-06 | F73: =IF(ABS(D73)<=E73,"OK","FAIL") -> OK
A74: FY2028 Beef volume-price sales build | B74: =Segment_Build!I7/Segment_Build!H7-1 -> 0.02 | C74: =Protein_Drivers!N66 -> 0.02 | D74: =B74-C74 -> 0 | E74: 1e-06 | F74: =IF(ABS(D74)<=E74,"OK","FAIL") -> OK
A75: FY2029 Beef volume-price sales build | B75: =Segment_Build!J7/Segment_Build!I7-1 -> 0.02 | C75: =Protein_Drivers!O66 -> 0.02 | D75: =B75-C75 -> 0 | E75: 1e-06 | F75: =IF(ABS(D75)<=E75,"OK","FAIL") -> OK
A76: FY2030 Beef volume-price sales build | B76: =Segment_Build!K7/Segment_Build!J7-1 -> 0.02 | C76: =Protein_Drivers!P66 -> 0.02 | D76: =B76-C76 -> 0 | E76: 1e-06 | F76: =IF(ABS(D76)<=E76,"OK","FAIL") -> OK
A77: FY2026 Beef margin driver | B77: =Segment_Build!G16/Segment_Build!G7 -> -0.0191 | C77: =Assumptions!B71+Protein_Drivers!B76 -> -0.0191 | D77: =B77-C77 -> 0 | E77: 1e-06 | F77: =IF(ABS(D77)<=E77,"OK","FAIL") -> OK
A78: FY2026 Pork margin driver | B78: =Segment_Build!G17/Segment_Build!G8 -> 0.0462 | C78: =Assumptions!B72+Protein_Drivers!B77 -> 0.0462 | D78: =B78-C78 -> 0 | E78: 1e-06 | F78: =IF(ABS(D78)<=E78,"OK","FAIL") -> OK
A79: FY2026 Chicken margin driver | B79: =Segment_Build!G18/Segment_Build!G9 -> 0.1139 | C79: =Assumptions!B73+Protein_Drivers!B78 -> 0.1139 | D79: =B79-C79 -> 0 | E79: 1e-06 | F79: =IF(ABS(D79)<=E79,"OK","FAIL") -> OK
A80: FY2026 Prepared Foods margin driver | B80: =Segment_Build!G19/Segment_Build!G10 -> 0.1271 | C80: =Assumptions!B74+Protein_Drivers!B79 -> 0.1271 | D80: =B80-C80 -> 0 | E80: 1e-06 | F80: =IF(ABS(D80)<=E80,"OK","FAIL") -> OK
A81: FY2026 International margin driver | B81: =Segment_Build!G20/Segment_Build!G11 -> 0.0749 | C81: =Assumptions!B75+Protein_Drivers!B80 -> 0.0749 | D81: =B81-C81 -> 0 | E81: 1e-06 | F81: =IF(ABS(D81)<=E81,"OK","FAIL") -> OK

Sheet Change_Log
A1: Change Log
A2: Controlled Tyson MOG build
A4: Version | B4: Date | C4: Change | D4: Engine | E4: Author | F4: Status
A5: 1 | B5: 46219 | C5: Initial MOG-native institutional model | D5: @mog-sdk/sdk 0.10.5 | E5: OpenAI Codex | F5: Built
A6: 1.1 | B6: 46219 | C6: Added Q2 FY2026 interim bridge and FY23-FY25 segment recast | D6: @mog-sdk/sdk 0.10.5 | E6: OpenAI Codex | F6: Built
A7: 1.2 | B7: 46219 | C7: Added stub-period DCF, dynamic scenarios, checks and claim ledger | D7: @mog-sdk/sdk + CLI 0.10.5 | E7: OpenAI Codex | F7: Verified
A8: 2.0.0 | B8: 46219 | C8: Added protein VPM, input-cost and debt/covenant schedules; freeze governance. | D8: @mog-sdk/sdk + CLI 0.10.5 | E8: OpenAI Codex | F8: Finalized via MOG CLI

Sheet Limitations
A1: Model Limitations & Certification Status
A2: Transparent boundary between sourced facts, analyst judgment and completed validation
A4: ID | B4: Area | C4: Limitation | D4: Model treatment | E4: Impact | F4: Status
A5: L01 | B5: Certification | C5: Version 2.0.0 is owner-gated; independent frozen-artifact review is pending. | D5: Exact hash and receipts are bound in the external freeze manifest. | E5: No self-certification is asserted. | F5: OPEN
A6: L02 | B6: Calculation engine | C6: Validated only in MOG 0.10.5. | D6: SDK build/reopen plus CLI finalization. | E6: No Excel or LibreOffice certification. | F6: DISCLOSED
A7: L03 | B7: Valuation | C7: WACC, TGR and exit multiple are analyst inputs. | D7: Visible inputs plus sensitivity table. | E7: DCF is decision support, not market fact. | F7: DISCLOSED
A8: L04 | B8: Market data | C8: No reliable date-matched price, beta, ERP or comps pack was forced. | D8: DCF inputs remain disclosed analyst judgments. | E8: No market recommendation asserted. | F8: DISCLOSED
A9: L05 | B9: FY2026 bridge | C9: H2 stub and week 53 are proportional. | D9: 6M actual and week 53 shown separately. | E9: Seasonality may differ. | F9: DISCLOSED
A10: L06 | B10: Forecast balance sheet | C10: Shares and selected BS lines are simplified. | D10: All simplifications are visible inputs. | E10: Precision below management guidance. | F10: DISCLOSED
A11: L07 | B11: Segment comparability | C11: FY21-22 legacy; FY23-25 June 2026 recast. | D11: Comparability break is labeled. | E11: Long trends are not fully like-for-like. | F11: DISCLOSED
A12: L08 | B12: Adjusted earnings | C12: FY2026 future adjustment modeled at zero. | D12: Explicit input on bridge and assumptions. | E12: Future items could change guidance bridge. | F12: DISCLOSED
